[
  {
    "numero_procedimento": "N/A",
    "entidade": "Polícia de Segurança Pública",
    "link": "https://diariodarepublica.pt/dr/detalhe/contrato-publico/33621-993078719",
    "detalhes_completos": "1 - IDENTIFICAÇÃO E CONTACTOS DA ENTIDADE ADJUDICANTE\nDesignação da entidade adjudicante: Polícia de Segurança Pública\nNIPC: 600006662\nEndereço: Av. António Augusto de Aguiar, 20 8º\nCódigo postal: 1050-016\nLocalidade: Lisboa\nPaís: Portugal\nNUT III: PT170\nDistrito: Lisboa\nConcelho: Lisboa\nFreguesia: Freguesia de Avenidas Novas\nTelefone: 213588383\nEndereço da Entidade (URL): https://www.psp.pt/\nEndereço Eletrónico: dl@psp.pt\neDelivery Gateway (URL): https://community.vortal.biz/public/\nFunção da Organização: Adquirente\nNorma jurídica da Entidade Adjudicante: Organismo de direito público\nÁrea de atividade da Autoridade Adjudicante: Segurança e ordem pública\n\n2 - JORNAL OFICIAL DA UNIÃO EUROPEIA\nO procedimento a que este anúncio diz respeito também é publicitado no Jornal Oficial da União Europeia? Não\n\n3 - AVISO\nModelo de Anúncio: Concurso público\nData de Envio do Anúncio: 30-12-2025\n\n5 - PROCESSO\nTipo de Procedimento: Concurso público\nPreço base do procedimento: Sim\nValor do preço base do procedimento: 80.000,00 EUR\nProcedimento com lotes? Não\n\n6 - OBJETO DO CONTRATO\nNúmero de referência interna: CP 71/DAC/2025\nDesignação do contrato: Aquisição de produtos veterinários para os canídeos do Grupo Operacional Cinotécnico da PSP, Biénio 2026/2027\nDescrição: Aquisição de produtos veterinários para os canídeos do Grupo Operacional Cinotécnico da PSP, Biénio 2026/2027\nTipo de Contrato Principal: Aquisição de Bens Móveis\nTipo de Contrato: Aquisição de Bens Móveis\nClassificação CPV (Vocabulário Comum para os Contratos Públicos)\nObjeto principal\nVocabulário Principal: 33600000\nPreço base s/IVA: 80.000,00 EUR\n\n7 - INDICAÇÕES ADICIONAIS\nO contrato envolve aquisição conjunta (satisfação de várias entidades)? Não\nO contrato é adjudicado por uma central de compras? Não\n\n8 - TÉCNICAS\nO concurso destina-se à celebração de um acordo-quadro? Inexistência de acordo-quadro\nÉ utilizado um leilão eletrónico? Não\nÉ adotada uma fase de negociação? Não\nSistema de Aquisição Dinâmico: Inexistência de sistema de aquisição dinâmico\n\n9 - LOCAL DA EXECUÇÃO DO CONTRATO\nLOCAL DA EXECUÇÃO DO CONTRATO (PROCEDIMENTO)\nPaís: Portugal\nNUT III: PT170\nLocalidade: Lisboa\nDistrito: Lisboa\nConcelho: Lisboa\nFreguesia: Freguesia de Avenidas Novas\n\n10 - PRAZO DE EXECUÇÃO DO CONTRATO\nPrazo de execução do contrato: 2 ANOS\nPrevisão de renovações: Não\n\n11 - FUNDOS EU\nTêm fundos EU? Não\n\n12 - DOCUMENTOS DE HABILITAÇÃO\nHabilitação para o exercício da atividade profissional: Não\n\n13 - CONDIÇÕES DE APRESENTAÇÃO\nPlataforma eletrónica utilizada pela entidade adjudicante: VORTAL\nURL para Apresentação: https://community.vortal.biz/public/\nAdmissibilidade da apresentação de propostas variantes: Não autorizado\nPrazo para apresentação das propostas: 20-01-2026 17:00\nPrazo durante o qual os concorrentes são obrigados a manter as respetivas propostas: 120 dias a contar do termo do prazo para a apresentação das propostas\nIndicação de Subcontratação na Proposta: Inexistência de indicação de subcontratação\n\n14 - PRESTAÇÃO DE CAUÇÃO\nPrestação de caução: Não\n\n15 - FORNECIMENTO DAS PEÇAS DO CONCURSO, APRESENTAÇÃO DE PEDIDOS DE PARTICIPAÇÃO E APRESENTAÇÃO DAS PROPOSTAS\nLink para acesso às peças do concurso (URL): https://community.vortal.biz/Public/public-tender-documents/Z292bzZJbE03RDZLQXRIREVqM01oVjgxc1NaODRQc1VDaUxwalpySXA0WEJUdVN6d3F4RGIwN05RTXN6YnY1WWYwTW5EMmxnZG1LQjluZFMzOTJvRFE9PVB0dzcr\n\n20 - OUTROS REQUISITOS\nInformação sobre contratos reservados. Aplica-se a contratos reservados (54º-A)? Não\n\n21 - CRITÉRIO DE ADJUDICAÇÃO\nMultifator: Não\nMonofator:\nNome: Preço\n\n24 - CONDIÇÕES DO CONTRATO\nFaturação Eletrónica: Permitido\nObrigação de Subcontratação:\nCódigo da Obrigação de Subcontratação: Não é aplicável nenhuma obrigação de subcontratação.\n\n25 - COMPRA PÚBLICA ESTRATÉGICA\nCompra Pública Estratégica: Inexistência de contratação pública estratégica\n\n26 - INFORMAÇÕES ADICIONAIS\nContrato adequado para PME: Sim\nCobertura ACP (Acordo dos Contratos Públicos da Organização Mundial do Comércio): Não\n\n27 - IDENTIFICAÇÃO E CONTACTOS DO ÓRGÃO DE RECURSOS ADMINISTRATIVOS\nDesignação: Diretor Nacional da PSP\nEndereço: Largo da Penha de França, N.º 1\nCódigo postal: 1199-010\nLocalidade: Lisboa\nTelefone: +351 213588368\nFax: +351 219020019\nEndereço eletrónico: dl@psp.pt\n\n28 - IDENTIFICAÇÃO DO(S) AUTOR(ES) DE ANÚNCIO\nNome: Licínio Cardoso Vaz\nCargo: Chefe de Divisão\n419942885",
    "nipc": "600006662",
    "distrito": "Lisboa",
    "concelho": "Lisboa",
    "freguesia": "Freguesia de Avenidas Novas",
    "site": "https://www.psp.pt/",
    "email": "dl@psp.pt",
    "designacao_contrato": "Aquisição de produtos veterinários para os canídeos do Grupo Operacional Cinotécnico da PSP, Biénio 2026/2027",
    "descricao": "Aquisição de produtos veterinários para os canídeos do Grupo Operacional Cinotécnico da PSP, Biénio 2026/2027",
    "preco_base": "80.000,00 EUR",
    "prazo_execucao": "2 ANOS",
    "prazo_apresentacao_propostas": "20-01-2026 17:00",
    "fundos_eu": "Não",
    "plataforma_eletronica": "VORTAL",
    "url_procedimento": "https://community.vortal.biz/public/",
    "autor_nome": "Licínio Cardoso Vaz",
    "autor_cargo": "Chefe de Divisão"
  },
  {
    "numero_procedimento": "N/A",
    "entidade": "Instituto Português de Oncologia de Lisboa Francisco Gentil, EPE",
    "link": "https://diariodarepublica.pt/dr/detalhe/contrato-publico/33622-993078720",
    "detalhes_completos": "1 - IDENTIFICAÇÃO E CONTACTOS DA ENTIDADE ADJUDICANTE\nDesignação da entidade adjudicante: Instituto Português de Oncologia de Lisboa Francisco Gentil, EPE\nNIPC: 506361616\nEndereço: Rua Profº Lima Basto\nCódigo postal: 1099-023\nLocalidade: Lisboa\nPaís: Portugal\nNUT III: PT170\nDistrito: Lisboa\nConcelho: Lisboa\nFreguesia: Todas\nTelefone: 217229800\nFax: 217229880\nEndereço da Entidade (URL): www.ipolisboa.min-saude.pt/\nEndereço Eletrónico: ipofg@ipolisboa.min-saude.pt\neDelivery Gateway (URL): https://community.vortal.biz/public/\nFunção da Organização: Adquirente\nNorma jurídica da Entidade Adjudicante: Organismo de direito público\nÁrea de atividade da Autoridade Adjudicante: Saúde\n\n2 - JORNAL OFICIAL DA UNIÃO EUROPEIA\nO procedimento a que este anúncio diz respeito também é publicitado no Jornal Oficial da União Europeia? Não\n\n3 - AVISO\nModelo de Anúncio: Concurso público\nData de Envio do Anúncio: 30-12-2025\n\n5 - PROCESSO\nTipo de Procedimento: Concurso público\nPreço base do procedimento: Sim\nValor do preço base do procedimento: 850.000,00 EUR\nProcedimento com lotes? Não\n\n6 - OBJETO DO CONTRATO\nNúmero de referência interna: PN/315/2026\nDesignação do contrato:  EMPREITADA DE AMPLIAÇÃO DO SERVIÇO DE HEMATOLOGIA\nDescrição:  EMPREITADA DE AMPLIAÇÃO DO SERVIÇO DE HEMATOLOGIA\nTipo de Contrato Principal: Empreitada de Obras Públicas\nTipo de Contrato: Empreitada de Obras Públicas\nClassificação CPV (Vocabulário Comum para os Contratos Públicos)\nObjeto principal\nVocabulário Principal: 45215140\nPreço base s/IVA: 850.000,00 EUR\n\n7 - INDICAÇÕES ADICIONAIS\nO contrato envolve aquisição conjunta (satisfação de várias entidades)? Não\nO contrato é adjudicado por uma central de compras? Não\n\n8 - TÉCNICAS\nO concurso destina-se à celebração de um acordo-quadro? Inexistência de acordo-quadro\nÉ utilizado um leilão eletrónico? Não\nÉ adotada uma fase de negociação? Não\nSistema de Aquisição Dinâmico: Inexistência de sistema de aquisição dinâmico\n\n9 - LOCAL DA EXECUÇÃO DO CONTRATO\nLOCAL DA EXECUÇÃO DO CONTRATO (PROCEDIMENTO)\nPaís: Portugal\nNUT III: PT170\nLocalidade: Lisboa\nDistrito: Lisboa\nConcelho: Lisboa\nFreguesia: Freguesia de São Domingos de Benfica\n\n10 - PRAZO DE EXECUÇÃO DO CONTRATO\nPrazo de execução do contrato: 180 DIAS\nPrevisão de renovações: Não\n\n11 - FUNDOS EU\nTêm fundos EU? Não\n\n12 - DOCUMENTOS DE HABILITAÇÃO\nHabilitação para o exercício da atividade profissional: Não\n\n13 - CONDIÇÕES DE APRESENTAÇÃO\nPlataforma eletrónica utilizada pela entidade adjudicante: VORTAL\nURL para Apresentação: https://community.vortal.biz/public/\nAdmissibilidade da apresentação de propostas variantes: Não autorizado\nPrazo para apresentação das propostas: 27-01-2026 17:59\nPrazo durante o qual os concorrentes são obrigados a manter as respetivas propostas: 120 dias a contar do termo do prazo para a apresentação das propostas\nIndicação de Subcontratação na Proposta: Inexistência de indicação de subcontratação\n\n14 - PRESTAÇÃO DE CAUÇÃO\nPrestação de caução: Não\n\n15 - FORNECIMENTO DAS PEÇAS DO CONCURSO, APRESENTAÇÃO DE PEDIDOS DE PARTICIPAÇÃO E APRESENTAÇÃO DAS PROPOSTAS\nLink para acesso às peças do concurso (URL): https://community.vortal.biz/Public/public-tender-documents/QUpIamdNUXlrV25iZTk0a1VyQVFoempuWGJSazBVbC9NdXBSTmpGcWJXVTVkcSsvTmIwb2Nxd1FIS2YrbVlydUwxMHF5M2MrbTN1Z0NBaGdvM0dVWWc9PVojU3VA\n\n20 - OUTROS REQUISITOS\nInformação sobre contratos reservados. Aplica-se a contratos reservados (54º-A)? Não\n\n21 - CRITÉRIO DE ADJUDICAÇÃO\nMultifator: Sim\nFator: \nNome: Preço\nPonderação: 20%\nSubfatores: Não\nFator: \nNome: Preço\nPonderação: 40%\nSubfatores: Não\nFator: \nNome: Qualidade\nPonderação: 40%\nSubfatores: Não\n\n24 - CONDIÇÕES DO CONTRATO\nFaturação Eletrónica: Permitido\nObrigação de Subcontratação:\nCódigo da Obrigação de Subcontratação: Não é aplicável nenhuma obrigação de subcontratação.\n\n25 - COMPRA PÚBLICA ESTRATÉGICA\nCompra Pública Estratégica: Inexistência de contratação pública estratégica\n\n26 - INFORMAÇÕES ADICIONAIS\nContrato adequado para PME: Sim\nCobertura ACP (Acordo dos Contratos Públicos da Organização Mundial do Comércio): Não\n\n27 - IDENTIFICAÇÃO E CONTACTOS DO ÓRGÃO DE RECURSOS ADMINISTRATIVOS\nDesignação: Conselho de Administração\nEndereço: Rua Prof. Lima Basto\nCódigo postal: 1099-023\nLocalidade: Lisboa\nTelefone: +351 217229800\nFax: +351 217229880\nEndereço eletrónico: ipofg@ipolisboa.min-saude.pt\n\n28 - IDENTIFICAÇÃO DO(S) AUTOR(ES) DE ANÚNCIO\nNome: Ricardo Costa\nCargo: Técnico Superior\n419943216",
    "nipc": "506361616",
    "distrito": "Lisboa",
    "concelho": "Lisboa",
    "freguesia": "Todas",
    "site": "www.ipolisboa.min-saude.pt/",
    "email": "ipofg@ipolisboa.min-saude.pt",
    "designacao_contrato": "EMPREITADA DE AMPLIAÇÃO DO SERVIÇO DE HEMATOLOGIA",
    "descricao": "EMPREITADA DE AMPLIAÇÃO DO SERVIÇO DE HEMATOLOGIA",
    "preco_base": "850.000,00 EUR",
    "prazo_execucao": "180 DIAS",
    "prazo_apresentacao_propostas": "27-01-2026 17:59",
    "fundos_eu": "Não",
    "plataforma_eletronica": "VORTAL",
    "url_procedimento": "https://community.vortal.biz/public/",
    "autor_nome": "Ricardo Costa",
    "autor_cargo": "Técnico Superior"
  },
  {
    "numero_procedimento": "N/A",
    "entidade": "Águas do Centro Litoral, SA",
    "link": "https://diariodarepublica.pt/dr/detalhe/contrato-publico/33623-993078721",
    "detalhes_completos": "1 - IDENTIFICAÇÃO E CONTACTOS DA ENTIDADE ADJUDICANTE\nDesignação da entidade adjudicante: Águas do Centro Litoral, SA\nNIPC: 513606181\nServiço/Órgão/Pessoa de contacto: Júri de procedimento\nEndereço: ETA da Boavista - Av. Dr. Luís de Albuquerque\nCódigo postal: 3030-410\nLocalidade: COIMBRA\nPaís: Portugal\nNUT III: PT16E\nDistrito: Coimbra\nConcelho: Coimbra\nFreguesia: Freguesia de Santo António dos Olivais\nTelefone: 239980900\nFax: 239980949\nEndereço da Entidade (URL): http://www.aguasdocentrolitoral.pt/\nEndereço Eletrónico: geral.adcl@adp.pt\neDelivery Gateway (URL): https://www.acingov.pt\nFunção da Organização: Adquirente\nNorma jurídica da Entidade Adjudicante: Organismo de direito público\nÁrea de atividade da Entidade Adjudicante: Atividades relacionadas com a água\n\n2 - JORNAL OFICIAL DA UNIÃO EUROPEIA\nO procedimento a que este anúncio diz respeito também é publicitado no Jornal Oficial da União Europeia? Não\n\n3 - AVISO\nModelo de Anúncio: Concurso público\nData de Envio do Anúncio: 30-12-2025\n\n5 - PROCESSO\nTipo de Procedimento: Concurso público\nPreço base do procedimento: Sim\nValor do preço base do procedimento: 37.381,00 EUR\nProcedimento com lotes? Não\n\n6 - OBJETO DO CONTRATO\nNúmero de referência interna: PRC/2025/197/CL/CP\nDesignação do contrato: PRC/2025/197/CL/CP-Serviço de Recolha Automática de Dados de Gestão de Frota\nDescrição: PRC/2025/197/CL/CP-Serviço de Recolha Automática de Dados de Gestão de Frota\nTipo de Contrato Principal: Aquisição de Serviços\nTipo de Contrato: Aquisição de Serviços\nClassificação CPV (Vocabulário Comum para os Contratos Públicos)\nObjeto principal\nVocabulário Principal: 50111100\nPreço base s/IVA: 37.381,00 EUR\n\n7 - INDICAÇÕES ADICIONAIS\nO contrato envolve aquisição conjunta (satisfação de várias entidades)? Não\nO contrato é adjudicado por uma central de compras? Não\n\n8 - TÉCNICAS\nO concurso destina-se à celebração de um acordo-quadro? Inexistência de acordo-quadro\nÉ utilizado um leilão eletrónico? Não\nÉ adotada uma fase de negociação? Não\nSistema de Aquisição Dinâmico: Inexistência de sistema de aquisição dinâmico\n\n9 - LOCAL DA EXECUÇÃO DO CONTRATO\nLOCAL DA EXECUÇÃO DO CONTRATO (PROCEDIMENTO)\nPaís: Portugal\nNUT III: PT16E\nLocalidade: Freguesia de Santo António dos Olivais\nDistrito: Coimbra\nConcelho: Coimbra\nFreguesia: Freguesia de Santo António dos Olivais\n\n10 - PRAZO DE EXECUÇÃO DO CONTRATO\nPrazo de execução do contrato: 36 MESES\nPrevisão de renovações: Não\n\n11 - FUNDOS EU\nTêm fundos EU? Não\n\n12 - DOCUMENTOS DE HABILITAÇÃO\nHabilitação para o exercício da atividade profissional: Não\n\n13 - CONDIÇÕES DE APRESENTAÇÃO\nPlataforma eletrónica utilizada pela entidade adjudicante: ACIN\nURL para Apresentação: https://www.acingov.pt\nAdmissibilidade da apresentação de propostas variantes: Não autorizado\nPrazo para apresentação das propostas: 09-01-2026 18:00\nPrazo durante o qual os concorrentes são obrigados a manter as respetivas propostas: 90 dias a contar do termo do prazo para a apresentação das propostas\nIndicação de Subcontratação na Proposta: Inexistência de indicação de subcontratação\n\n14 - PRESTAÇÃO DE CAUÇÃO\nPrestação de caução: Não\n\n15 - FORNECIMENTO DAS PEÇAS DO CONCURSO, APRESENTAÇÃO DE PEDIDOS DE PARTICIPAÇÃO E APRESENTAÇÃO DAS PROPOSTAS\nLink para acesso às peças do concurso (URL): https://www.acingov.pt/acingovprod/2/zonaPublica/zona_publica_c/donwloadProcedurePiece/MTAxMjEzNg==\n\n20 - OUTROS REQUISITOS\nInformação sobre contratos reservados. Aplica-se a contratos reservados (54º-A)? Não\n\n21 - CRITÉRIO DE ADJUDICAÇÃO\nMultifator: Não\nMonofator:\nNome: Outros\nOutro nome: Fator Preço\n\n24 - CONDIÇÕES DO CONTRATO\nFaturação Eletrónica: Permitido\nObrigação de Subcontratação:\nCódigo da Obrigação de Subcontratação: Não é aplicável nenhuma obrigação de subcontratação.\n\n25 - COMPRA PÚBLICA ESTRATÉGICA\nCompra Pública Estratégica: Inexistência de contratação pública estratégica\n\n26 - INFORMAÇÕES ADICIONAIS\nContrato adequado para PME: Sim\nCobertura ACP (Acordo dos Contratos Públicos da Organização Mundial do Comércio): Não\n\n27 - IDENTIFICAÇÃO E CONTACTOS DO ÓRGÃO DE RECURSOS ADMINISTRATIVOS\nDesignação: Águas do Centro Litoral, S.A.\nEndereço: ETA da Boavista - Av. Dr. Luís de Albuquerque\nCódigo postal: 3030-410\nLocalidade: COIMBRA\nTelefone: 239980900\nFax: 239980949\nEndereço eletrónico: geral.adcl@adp.pt\n\n28 - IDENTIFICAÇÃO DO(S) AUTOR(ES) DE ANÚNCIO\nNome: Vera Mónica Vieira Moiteiro\nCargo: Direção de Compras e Logística\n419942714",
    "nipc": "513606181",
    "distrito": "Coimbra",
    "concelho": "Coimbra",
    "freguesia": "Freguesia de Santo António dos Olivais",
    "site": "http://www.aguasdocentrolitoral.pt/",
    "email": "geral.adcl@adp.pt",
    "designacao_contrato": "PRC/2025/197/CL/CP-Serviço de Recolha Automática de Dados de Gestão de Frota",
    "descricao": "PRC/2025/197/CL/CP-Serviço de Recolha Automática de Dados de Gestão de Frota",
    "preco_base": "37.381,00 EUR",
    "prazo_execucao": "36 MESES",
    "prazo_apresentacao_propostas": "09-01-2026 18:00",
    "fundos_eu": "Não",
    "plataforma_eletronica": "ACIN",
    "url_procedimento": "https://www.acingov.pt",
    "autor_nome": "Vera Mónica Vieira Moiteiro",
    "autor_cargo": "Direção de Compras e Logística"
  },
  {
    "numero_procedimento": "N/A",
    "entidade": "Construção Pública, EPE",
    "link": "https://diariodarepublica.pt/dr/detalhe/contrato-publico/33627-993078722",
    "detalhes_completos": "1 - IDENTIFICAÇÃO E CONTACTOS DA ENTIDADE ADJUDICANTE\nDesignação da entidade adjudicante: Construção Pública, EPE\nNIPC: 508069645\nEndereço: Avenida Infante Santo n.º 2\nCódigo postal: 1350-178\nLocalidade: Lisboa\nPaís: Portugal\nNUT III: PT170\nDistrito: Lisboa\nConcelho: Lisboa\nFreguesia: Freguesia da Estrela\nTelefone: 213944710\nFax: 213944710\nEndereço da Entidade (URL): https://construcaopublica.gov.pt\nEndereço Eletrónico: geral@construcaopublica.gov.pt\neDelivery Gateway (URL): https://community.vortal.biz/public/\nFunção da Organização: Adquirente\nNorma jurídica da Entidade Adjudicante: Organismo de direito público\nÁrea de atividade da Autoridade Adjudicante: Serviços públicos das administrações públicas\n\n2 - JORNAL OFICIAL DA UNIÃO EUROPEIA\nO procedimento a que este anúncio diz respeito também é publicitado no Jornal Oficial da União Europeia? Não\n\n3 - AVISO\nModelo de Anúncio: Concurso público\nData de Envio do Anúncio: 30-12-2025\n\n5 - PROCESSO\nTipo de Procedimento: Concurso público\nPreço base do procedimento: Sim\nValor do preço base do procedimento: 390.000,00 EUR\nProcedimento com lotes? Não\n\n6 - OBJETO DO CONTRATO\nNúmero de referência interna: PE_25209_CNE\nDesignação do contrato: PE_25209_CNE - CONCURSO PÚBLICO NACIONAL PARA EMPREITADA DE REPARAÇÃO DO PAVILHÃO DESPORTIVO EXISTENTE NA ESCOLA BÁSICA E SECUNDÁRIA DE VALE DE OVIL EM BAIÃO\nDescrição: PE_25209_CNE - CONCURSO PÚBLICO NACIONAL PARA EMPREITADA DE REPARAÇÃO DO PAVILHÃO DESPORTIVO EXISTENTE NA ESCOLA BÁSICA E SECUNDÁRIA DE VALE DE OVIL EM BAIÃO\nTipo de Contrato Principal: Empreitada de Obras Públicas\nTipo de Contrato: Empreitada de Obras Públicas\nClassificação CPV (Vocabulário Comum para os Contratos Públicos)\nObjeto principal\nVocabulário Principal: 45210000\nPreço base s/IVA: 390.000,00 EUR\n\n7 - INDICAÇÕES ADICIONAIS\nO contrato envolve aquisição conjunta (satisfação de várias entidades)? Não\nO contrato é adjudicado por uma central de compras? Não\n\n8 - TÉCNICAS\nO concurso destina-se à celebração de um acordo-quadro? Inexistência de acordo-quadro\nÉ utilizado um leilão eletrónico? Não\nÉ adotada uma fase de negociação? Não\nSistema de Aquisição Dinâmico: Inexistência de sistema de aquisição dinâmico\n\n9 - LOCAL DA EXECUÇÃO DO CONTRATO\nLOCAL DA EXECUÇÃO DO CONTRATO (PROCEDIMENTO)\nPaís: Portugal\nNUT III: PT11C\nLocalidade: Porto\nDistrito: Porto\nConcelho: Baião\nFreguesia: União das Freguesias de Campelo e Ovil\n\n10 - PRAZO DE EXECUÇÃO DO CONTRATO\nPrazo de execução do contrato: 6 MESES\nPrevisão de renovações: Não\n\n11 - FUNDOS EU\nTêm fundos EU? Não\n\n12 - DOCUMENTOS DE HABILITAÇÃO\nHabilitação para o exercício da atividade profissional: Sim\nTipo: Outros\nDescrição - Outros: Os Referidos no Programa de Concurso.\nDescrição: Documentos referidos no Programa de Concurso.\n\n13 - CONDIÇÕES DE APRESENTAÇÃO\nPlataforma eletrónica utilizada pela entidade adjudicante: VORTAL\nURL para Apresentação: https://community.vortal.biz/public/\nAdmissibilidade da apresentação de propostas variantes: Não autorizado\nPrazo para apresentação das propostas: 26-01-2026 17:00\nPrazo durante o qual os concorrentes são obrigados a manter as respetivas propostas: 180 dias a contar do termo do prazo para a apresentação das propostas\nIndicação de Subcontratação na Proposta: Inexistência de indicação de subcontratação\n\n14 - PRESTAÇÃO DE CAUÇÃO\nPrestação de caução: Sim\nPercentagem: 5%\nDescrição da Garantia Exigida: 22.1. O valor da caução é de 5% (cinco por cento) do preço contratual e será prestada pelo Adjudicatário, por depósito em dinheiro, mediante garantia bancária à primeira solicitação ou ainda por seguro-caução, nos termos dos ANEXOS VI, VII e VIII ao Programa de Concurso, respetivamente.\n\n15 - FORNECIMENTO DAS PEÇAS DO CONCURSO, APRESENTAÇÃO DE PEDIDOS DE PARTICIPAÇÃO E APRESENTAÇÃO DAS PROPOSTAS\nLink para acesso às peças do concurso (URL): https://community.vortal.biz/Public/public-tender-documents/ZEk5ZENUN0ptNk1lMzkzbnRpQ3FmL0twT3ZCc29aTjZjRDlJL3dRNkpxYVFaZDdPRENLM0M5UkdtZnlBdHRZOEZrUFQyaDYwWGd3Q3lzTk9rWldmbGc9PUIqVFFG\n\n20 - OUTROS REQUISITOS\nInformação sobre contratos reservados. Aplica-se a contratos reservados (54º-A)? Não\n\n21 - CRITÉRIO DE ADJUDICAÇÃO\nMultifator: Sim\nFator: \nNome: Preço\nPonderação: 90%\nSubfatores: Não\nFator: \nNome: Qualidade\nPonderação: 10%\nSubfatores: Não\n\n24 - CONDIÇÕES DO CONTRATO\nFaturação Eletrónica: Permitido\nObrigação de Subcontratação:\nCódigo da Obrigação de Subcontratação: Não é aplicável nenhuma obrigação de subcontratação.\n\n25 - COMPRA PÚBLICA ESTRATÉGICA\nCompra Pública Estratégica: Redução dos impactos ambientais\nDescrição do Processo de Adjudicação Estratégico: Conforme as peças do procedimento\nCritérios de contratos Públicos Ecológicos: Critérios de contratação pública ecológica nacional\nCategorias da estratégia nacional: Outros\nOutra categoria (Descrição): Aplicação da RCM n.º 132/2023\nDiretiva Veículos Não Poluentes: Não\nCritério de Acessibilidade: Os critérios de acessibilidade para as pessoas com deficiência não estão incluídos porque o contrato não se destina a pessoas singulares\n\n26 - INFORMAÇÕES ADICIONAIS\nContrato adequado para PME: Sim\nCobertura ACP (Acordo dos Contratos Públicos da Organização Mundial do Comércio): Não\n\n27 - IDENTIFICAÇÃO E CONTACTOS DO ÓRGÃO DE RECURSOS ADMINISTRATIVOS\nDesignação: Conselho de Administração da Construção Pública, E.P.E.\nEndereço: Avenida Infante Santo n.º 2\nCódigo postal: 1350-178\nLocalidade: Lisboa\nTelefone: +351 213944710\nFax: +351 213944775\nEndereço eletrónico: concursos@construcaopublica.gov.pt\n\n28 - IDENTIFICAÇÃO DO(S) AUTOR(ES) DE ANÚNCIO\nNome: Nélia Marisa Araújo Lemos\nCargo: Coordenadora da Equipa de Formação de Contratos\n419943646",
    "nipc": "508069645",
    "distrito": "Lisboa",
    "concelho": "Lisboa",
    "freguesia": "Freguesia da Estrela",
    "site": "https://construcaopublica.gov.pt",
    "email": "geral@construcaopublica.gov.pt",
    "designacao_contrato": "PE_25209_CNE - CONCURSO PÚBLICO NACIONAL PARA EMPREITADA DE REPARAÇÃO DO PAVILHÃO DESPORTIVO EXISTENTE NA ESCOLA BÁSICA E SECUNDÁRIA DE VALE DE OVIL EM BAIÃO",
    "descricao": "PE_25209_CNE - CONCURSO PÚBLICO NACIONAL PARA EMPREITADA DE REPARAÇÃO DO PAVILHÃO DESPORTIVO EXISTENTE NA ESCOLA BÁSICA E SECUNDÁRIA DE VALE DE OVIL EM BAIÃO",
    "preco_base": "390.000,00 EUR",
    "prazo_execucao": "6 MESES",
    "prazo_apresentacao_propostas": "26-01-2026 17:00",
    "fundos_eu": "Não",
    "plataforma_eletronica": "VORTAL",
    "url_procedimento": "https://community.vortal.biz/public/",
    "autor_nome": "Nélia Marisa Araújo Lemos",
    "autor_cargo": "Coordenadora da Equipa de Formação de Contratos"
  },
  {
    "numero_procedimento": "N/A",
    "entidade": "Instituto de Informática, IP",
    "link": "https://diariodarepublica.pt/dr/detalhe/contrato-publico/33630-993078723",
    "detalhes_completos": "1 - IDENTIFICAÇÃO E CONTACTOS DA ENTIDADE ADJUDICANTE\nDesignação da entidade adjudicante: Instituto de Informática, IP\nNIPC: 504322915\nServiço/Órgão/Pessoa de contacto: Área de Contratação Pública\nEndereço: Avenida Professor Dr. Cavaco Silva, n.º 17, Edifício Ciência I\nCódigo postal: 2740-120\nLocalidade: Porto Salvo\nPaís: Portugal\nNUT III: PT170\nDistrito: Lisboa\nConcelho: Oeiras\nFreguesia: Freguesia de Porto Salvo\nTelefone: 214230000\nFax: 214230000\nEndereço da Entidade (URL): http://www.seg-social.pt\nEndereço Eletrónico: ii-contratacao@seg-social.pt\neDelivery Gateway (URL): https://www.acingov.pt\nFunção da Organização: Adquirente\nNorma jurídica da Entidade Adjudicante: Organismo de direito público\nÁrea de atividade da Autoridade Adjudicante: Proteção social\n\n2 - JORNAL OFICIAL DA UNIÃO EUROPEIA\nO procedimento a que este anúncio diz respeito também é publicitado no Jornal Oficial da União Europeia? Não\n\n3 - AVISO\nModelo de Anúncio: Concurso público\nData de Envio do Anúncio: 30-12-2025\n\n5 - PROCESSO\nTipo de Procedimento: Concurso público\nPreço base do procedimento: Sim\nValor do preço base do procedimento: 101.568,56 EUR\nProcedimento com lotes? Não\n\n6 - OBJETO DO CONTRATO\nNúmero de referência interna: 2325000350\nDesignação do contrato: 2325000350 - RENOVAÇÃO DO LICENCIAMENTO IBM INFOSPHERE DATASTAGE\nDescrição: 2325000350 - RENOVAÇÃO DO LICENCIAMENTO IBM INFOSPHERE DATASTAGE\nTipo de Contrato Principal: Aquisição de Bens Móveis\nTipo de Contrato: Aquisição de Bens Móveis\nClassificação CPV (Vocabulário Comum para os Contratos Públicos)\nObjeto principal\nVocabulário Principal: 48611000\nPreço base s/IVA: 101.568,56 EUR\n\n7 - INDICAÇÕES ADICIONAIS\nO contrato envolve aquisição conjunta (satisfação de várias entidades)? Não\nO contrato é adjudicado por uma central de compras? Não\n\n8 - TÉCNICAS\nO concurso destina-se à celebração de um acordo-quadro? Inexistência de acordo-quadro\nÉ utilizado um leilão eletrónico? Não\nÉ adotada uma fase de negociação? Não\nSistema de Aquisição Dinâmico: Inexistência de sistema de aquisição dinâmico\n\n9 - LOCAL DA EXECUÇÃO DO CONTRATO\nLOCAL DA EXECUÇÃO DO CONTRATO (PROCEDIMENTO)\nPaís: Portugal\nNUT III: PT170\nLocalidade: Freguesia de Porto Salvo\nDistrito: Lisboa\nConcelho: Oeiras\nFreguesia: Freguesia de Porto Salvo\n\n10 - PRAZO DE EXECUÇÃO DO CONTRATO\nPrazo de execução do contrato: 11 MESES\nPrevisão de renovações: Não\n\n11 - FUNDOS EU\nTêm fundos EU? Não\n\n12 - DOCUMENTOS DE HABILITAÇÃO\nHabilitação para o exercício da atividade profissional: Não\n\n13 - CONDIÇÕES DE APRESENTAÇÃO\nPlataforma eletrónica utilizada pela entidade adjudicante: ACIN\nURL para Apresentação: https://www.acingov.pt\nAdmissibilidade da apresentação de propostas variantes: Não autorizado\nPrazo para apresentação das propostas: 12-01-2026 23:59\nPrazo durante o qual os concorrentes são obrigados a manter as respetivas propostas: 66 dias a contar do termo do prazo para a apresentação das propostas\nIndicação de Subcontratação na Proposta: Inexistência de indicação de subcontratação\n\n14 - PRESTAÇÃO DE CAUÇÃO\nPrestação de caução: Não\n\n15 - FORNECIMENTO DAS PEÇAS DO CONCURSO, APRESENTAÇÃO DE PEDIDOS DE PARTICIPAÇÃO E APRESENTAÇÃO DAS PROPOSTAS\nLink para acesso às peças do concurso (URL): https://www.acingov.pt/acingovprod/2/zonaPublica/zona_publica_c/donwloadProcedurePiece/MTAxMjY4OA==\n\n20 - OUTROS REQUISITOS\nInformação sobre contratos reservados. Aplica-se a contratos reservados (54º-A)? Não\n\n21 - CRITÉRIO DE ADJUDICAÇÃO\nMultifator: Não\nMonofator:\nNome: Preço\n\n24 - CONDIÇÕES DO CONTRATO\nFaturação Eletrónica: Necessário\nObrigação de Subcontratação:\nCódigo da Obrigação de Subcontratação: Não é aplicável nenhuma obrigação de subcontratação.\n\n25 - COMPRA PÚBLICA ESTRATÉGICA\nCompra Pública Estratégica: Inexistência de contratação pública estratégica\n\n26 - INFORMAÇÕES ADICIONAIS\nContrato adequado para PME: Sim\nCobertura ACP (Acordo dos Contratos Públicos da Organização Mundial do Comércio): Não\n\n27 - IDENTIFICAÇÃO E CONTACTOS DO ÓRGÃO DE RECURSOS ADMINISTRATIVOS\nDesignação: Conselho Diretivo\nEndereço: Avenida Professor Dr. Cavaco Silva, n.º 17, Edifício Ciência I\nCódigo postal: 2740-120\nLocalidade: Porto Salvo\nTelefone: 214230000\nFax: 214230000\nEndereço eletrónico: ii-contratacao@seg-social.pt\nPrazo de interposição do recurso: 5 dias\n\n28 - IDENTIFICAÇÃO DO(S) AUTOR(ES) DE ANÚNCIO\nNome: Helga Patricia Fino da Silva Beirão Paulo\nCargo: Diretora do Departamento de Organização e Gestão de Pessoas\n419943451",
    "nipc": "504322915",
    "distrito": "Lisboa",
    "concelho": "Oeiras",
    "freguesia": "Freguesia de Porto Salvo",
    "site": "http://www.seg-social.pt",
    "email": "ii-contratacao@seg-social.pt",
    "designacao_contrato": "2325000350 - RENOVAÇÃO DO LICENCIAMENTO IBM INFOSPHERE DATASTAGE",
    "descricao": "2325000350 - RENOVAÇÃO DO LICENCIAMENTO IBM INFOSPHERE DATASTAGE",
    "preco_base": "101.568,56 EUR",
    "prazo_execucao": "11 MESES",
    "prazo_apresentacao_propostas": "12-01-2026 23:59",
    "fundos_eu": "Não",
    "plataforma_eletronica": "ACIN",
    "url_procedimento": "https://www.acingov.pt",
    "autor_nome": "Helga Patricia Fino da Silva Beirão Paulo",
    "autor_cargo": "Diretora do Departamento de Organização e Gestão de Pessoas"
  },
  {
    "numero_procedimento": "N/A",
    "entidade": "Freguesia da Penha de França",
    "link": "https://diariodarepublica.pt/dr/detalhe/contrato-publico/33631-993078724",
    "detalhes_completos": "1 - IDENTIFICAÇÃO E CONTACTOS DA ENTIDADE ADJUDICANTE\nDesignação da entidade adjudicante: Freguesia da Penha de França\nNIPC: 510833454\nServiço/Órgão/Pessoa de contacto: Marco Teles Fernandes - Junta de Freguesia da Penha de França\nEndereço: Travessa do Calado, nº2\nCódigo postal: 1170-070\nLocalidade: Lisboa\nPaís: Portugal\nNUT III: PTZZZ\nDistrito: Todos\nConcelho: Todos\nFreguesia: Todas\nTelefone: 218160720\nFax: 218160721\nEndereço da Entidade (URL): http://www.jf-penhafranca.pt/\nEndereço Eletrónico: geral@jf-penhafranca.pt\neDelivery Gateway (URL): https://www.acingov.pt\nFunção da Organização: Adquirente\nNorma jurídica da Entidade Adjudicante: Organismo de direito público\nÁrea de atividade da Autoridade Adjudicante: Serviços públicos das administrações públicas\n\n2 - JORNAL OFICIAL DA UNIÃO EUROPEIA\nO procedimento a que este anúncio diz respeito também é publicitado no Jornal Oficial da União Europeia? Não\n\n3 - AVISO\nModelo de Anúncio: Concurso público\nData de Envio do Anúncio: 30-12-2025\n\n5 - PROCESSO\nTipo de Procedimento: Concurso público\nPreço base do procedimento: Sim\nValor do preço base do procedimento: 84.460,00 EUR\nProcedimento com lotes? Não\n\n6 - OBJETO DO CONTRATO\nNúmero de referência interna: CP/2/2025\nDesignação do contrato: AQUISIÇÃO DE SERVIÇOS DE FORNECIMENTO DE ENERGIA ELÉCTRICA PARA A FREGUESIA DA PENHA DE FRANÇA │ 2026\nDescrição: Aquisição de serviços de eletricidade para a Freguesia da Penha de França, para 16 pontos de entrega (CPE) em Baixa Tensão Normal (BTN) e em Baixa Tensão Especial (BTE). \nTipo de Contrato Principal: Aquisição de Bens Móveis\nTipo de Contrato: Aquisição de Bens Móveis\nClassificação CPV (Vocabulário Comum para os Contratos Públicos)\nObjeto principal\nVocabulário Principal: 09310000\nPreço base s/IVA: 84.460,00 EUR\n\n7 - INDICAÇÕES ADICIONAIS\nO contrato envolve aquisição conjunta (satisfação de várias entidades)? Não\nO contrato é adjudicado por uma central de compras? Não\n\n8 - TÉCNICAS\nO concurso destina-se à celebração de um acordo-quadro? Inexistência de acordo-quadro\nÉ utilizado um leilão eletrónico? Não\nÉ adotada uma fase de negociação? Não\nSistema de Aquisição Dinâmico: Inexistência de sistema de aquisição dinâmico\n\n9 - LOCAL DA EXECUÇÃO DO CONTRATO\nLOCAL DA EXECUÇÃO DO CONTRATO (PROCEDIMENTO)\nPaís: Portugal\nNUT III: PT111\nLocalidade: Freguesia de Penha de França\nDistrito: Lisboa\nConcelho: Lisboa\nFreguesia: Freguesia de Penha de França\n\n10 - PRAZO DE EXECUÇÃO DO CONTRATO\nPrazo de execução do contrato: 365 DIAS\nPrevisão de renovações: Não\n\n11 - FUNDOS EU\nTêm fundos EU? Não\n\n12 - DOCUMENTOS DE HABILITAÇÃO\nHabilitação para o exercício da atividade profissional: Não\n\n13 - CONDIÇÕES DE APRESENTAÇÃO\nPlataforma eletrónica utilizada pela entidade adjudicante: ACIN\nURL para Apresentação: https://www.acingov.pt\nAdmissibilidade da apresentação de propostas variantes: Não autorizado\nPrazo para apresentação das propostas: 04-01-2026 23:59\nPrazo durante o qual os concorrentes são obrigados a manter as respetivas propostas: 66 dias a contar do termo do prazo para a apresentação das propostas\nIndicação de Subcontratação na Proposta: Inexistência de indicação de subcontratação\n\n14 - PRESTAÇÃO DE CAUÇÃO\nPrestação de caução: Não\n\n15 - FORNECIMENTO DAS PEÇAS DO CONCURSO, APRESENTAÇÃO DE PEDIDOS DE PARTICIPAÇÃO E APRESENTAÇÃO DAS PROPOSTAS\nLink para acesso às peças do concurso (URL): https://www.acingov.pt/acingovprod/2/zonaPublica/zona_publica_c/donwloadProcedurePiece/MTAxMjMxMA==\n\n20 - OUTROS REQUISITOS\nInformação sobre contratos reservados. Aplica-se a contratos reservados (54º-A)? Não\n\n21 - CRITÉRIO DE ADJUDICAÇÃO\nMultifator: Não\nMonofator:\nNome: Preço\n\n24 - CONDIÇÕES DO CONTRATO\nFaturação Eletrónica: Permitido\nObrigação de Subcontratação:\nCódigo da Obrigação de Subcontratação: Não é aplicável nenhuma obrigação de subcontratação.\n\n25 - COMPRA PÚBLICA ESTRATÉGICA\nCompra Pública Estratégica: Inexistência de contratação pública estratégica\n\n26 - INFORMAÇÕES ADICIONAIS\nContrato adequado para PME: Não\nCobertura ACP (Acordo dos Contratos Públicos da Organização Mundial do Comércio): Não\n\n27 - IDENTIFICAÇÃO E CONTACTOS DO ÓRGÃO DE RECURSOS ADMINISTRATIVOS\nDesignação: Junta de Freguesia da Penha de França\nEndereço: Travessa do Calado, n.º 2\nCódigo postal: 1170-070\nLocalidade: Lisboa\nTelefone: 218160720\nFax: \nEndereço eletrónico: geral@jf-penhafranca.pt\nPrazo de interposição do recurso: 5 dias\n\n28 - IDENTIFICAÇÃO DO(S) AUTOR(ES) DE ANÚNCIO\nNome: Marco Paulo Teles Gonçalves Fernandes\nCargo: Jurista\n419942203",
    "nipc": "510833454",
    "distrito": "Todos",
    "concelho": "Todos",
    "freguesia": "Todas",
    "site": "http://www.jf-penhafranca.pt/",
    "email": "geral@jf-penhafranca.pt",
    "designacao_contrato": "AQUISIÇÃO DE SERVIÇOS DE FORNECIMENTO DE ENERGIA ELÉCTRICA PARA A FREGUESIA DA PENHA DE FRANÇA │ 2026",
    "descricao": "Aquisição de serviços de eletricidade para a Freguesia da Penha de França, para 16 pontos de entrega (CPE) em Baixa Tensão Normal (BTN) e em Baixa Tensão Especial (BTE).",
    "preco_base": "84.460,00 EUR",
    "prazo_execucao": "365 DIAS",
    "prazo_apresentacao_propostas": "04-01-2026 23:59",
    "fundos_eu": "Não",
    "plataforma_eletronica": "ACIN",
    "url_procedimento": "https://www.acingov.pt",
    "autor_nome": "Marco Paulo Teles Gonçalves Fernandes",
    "autor_cargo": "Jurista"
  },
  {
    "numero_procedimento": "N/A",
    "entidade": "Pesqueiramiga - Associação de Solidariedade Social",
    "link": "https://diariodarepublica.pt/dr/detalhe/contrato-publico/33632-993078725",
    "detalhes_completos": "1 - IDENTIFICAÇÃO E CONTACTOS DA ENTIDADE ADJUDICANTE\nDesignação da entidade adjudicante: Pesqueiramiga - Associação de Solidariedade Social\nNIPC: 501734856\nEndereço: Rua Poças de Barro, 30\nCódigo postal: 5130-376\nLocalidade: Viseu\nPaís: Portugal\nNUT III: PT11D\nDistrito: Viseu\nConcelho: São João da Pesqueira\nFreguesia: União das Freguesias de São João da Pesqueira e Várzea de Trevões\nTelefone: 254484478\nFax: 254488263\nEndereço Eletrónico: info@pesqueiramiga.pt\neDelivery Gateway (URL): https://community.vortal.biz/public/\nFunção da Organização: Adquirente\nNorma jurídica da Entidade Adjudicante: Entidade com direitos especiais ou exclusivos\nÁrea de atividade da Autoridade Adjudicante: Proteção social\n\n2 - JORNAL OFICIAL DA UNIÃO EUROPEIA\nO procedimento a que este anúncio diz respeito também é publicitado no Jornal Oficial da União Europeia? Não\n\n3 - AVISO\nModelo de Anúncio: Concurso público\nData de Envio do Anúncio: 30-12-2025\n\n5 - PROCESSO\nTipo de Procedimento: Concurso público\nPreço base do procedimento: Sim\nValor do preço base do procedimento: 377.415,50 EUR\nProcedimento com lotes? Não\n\n6 - OBJETO DO CONTRATO\nNúmero de referência interna: REM_CENTRO DE APOIO A IDOSOS_02.25\nDesignação do contrato: Empreitada para Remodelação do Edifício Centro de Apoio a Idosos\nDescrição: Empreitada para a realização de obras de remodelação do Edifício Centro de Apoio a Idosos, no âmbito de projeto financiado pelo PRR.\nTipo de Contrato Principal: Empreitada de Obras Públicas\nTipo de Contrato: Empreitada de Obras Públicas\nClassificação CPV (Vocabulário Comum para os Contratos Públicos)\nObjeto principal\nVocabulário Principal: 45215212\nPreço base s/IVA: 377.415,50 EUR\n\n7 - INDICAÇÕES ADICIONAIS\nO contrato envolve aquisição conjunta (satisfação de várias entidades)? Não\nO contrato é adjudicado por uma central de compras? Não\n\n8 - TÉCNICAS\nO concurso destina-se à celebração de um acordo-quadro? Inexistência de acordo-quadro\nÉ utilizado um leilão eletrónico? Não\nÉ adotada uma fase de negociação? Não\nSistema de Aquisição Dinâmico: Inexistência de sistema de aquisição dinâmico\n\n9 - LOCAL DA EXECUÇÃO DO CONTRATO\nLOCAL DA EXECUÇÃO DO CONTRATO (PROCEDIMENTO)\nPaís: Portugal\nNUT III: PT11D\nLocalidade: Viseu\nDistrito: Viseu\nConcelho: São João da Pesqueira\nFreguesia: União das Freguesias de São João da Pesqueira e Várzea de Trevões\n\n10 - PRAZO DE EXECUÇÃO DO CONTRATO\nPrazo de execução do contrato: 120 DIAS\nPrevisão de renovações: Não\n\n11 - FUNDOS EU\nTêm fundos EU? Sim\n\n12 - DOCUMENTOS DE HABILITAÇÃO\nHabilitação para o exercício da atividade profissional: Sim\nTipo: Alvará\nDescrição: Os referidos nas peças do procedimento.\n\n13 - CONDIÇÕES DE APRESENTAÇÃO\nPlataforma eletrónica utilizada pela entidade adjudicante: VORTAL\nURL para Apresentação: https://community.vortal.biz/public/\nAdmissibilidade da apresentação de propostas variantes: Não autorizado\nPrazo para apresentação das propostas: 13-01-2026 23:59\nPrazo durante o qual os concorrentes são obrigados a manter as respetivas propostas: 180 dias a contar do termo do prazo para a apresentação das propostas\nIndicação de Subcontratação na Proposta: Inexistência de indicação de subcontratação\n\n14 - PRESTAÇÃO DE CAUÇÃO\nPrestação de caução: Sim\nPercentagem: 5%\nDescrição da Garantia Exigida: Qualquer dos meios admitidos no Código dos contratos Públicos\n\n15 - FORNECIMENTO DAS PEÇAS DO CONCURSO, APRESENTAÇÃO DE PEDIDOS DE PARTICIPAÇÃO E APRESENTAÇÃO DAS PROPOSTAS\nLink para acesso às peças do concurso (URL): https://community.vortal.biz/Public/public-tender-documents/b3RRbEhoZTQxbVU5U0s0SVI5QmQxK3FGd3JSdHhzMlBZQ1huT3ZYVkJWVm1PVWdFcG00Sk56NjhVMHJhb2p4WEZrRThBY29Hd29EdVZJL0FocHNwS0E9PTdAc3Vj\n\n20 - OUTROS REQUISITOS\nInformação sobre contratos reservados. Aplica-se a contratos reservados (54º-A)? Não\n\n21 - CRITÉRIO DE ADJUDICAÇÃO\nMultifator: Não\nMonofator:\nNome: Outros\nOutro nome: Preço\n\n24 - CONDIÇÕES DO CONTRATO\nFaturação Eletrónica: Permitido\nObrigação de Subcontratação:\nCódigo da Obrigação de Subcontratação: Não é aplicável nenhuma obrigação de subcontratação.\n\n25 - COMPRA PÚBLICA ESTRATÉGICA\nCompra Pública Estratégica: Inexistência de contratação pública estratégica\n\n26 - INFORMAÇÕES ADICIONAIS\nContrato adequado para PME: Sim\nCobertura ACP (Acordo dos Contratos Públicos da Organização Mundial do Comércio): Não\n\n27 - IDENTIFICAÇÃO E CONTACTOS DO ÓRGÃO DE RECURSOS ADMINISTRATIVOS\nDesignação: Pesqueiramiga - Associação de Solidariedade Social\nEndereço: Praça de Santa Maria, 4\nCódigo postal: 5130-333\nLocalidade: São João da Pesqueira\nTelefone: +351 254484478\nFax: +351 254484478\nEndereço eletrónico: info@pesqueiramiga.pt\n\n28 - IDENTIFICAÇÃO DO(S) AUTOR(ES) DE ANÚNCIO\nNome: Maria Fernandina Martins Espírito Santo\nCargo: Presidente da Direção\n419943751",
    "nipc": "501734856",
    "distrito": "Viseu",
    "concelho": "São João da Pesqueira",
    "freguesia": "União das Freguesias de São João da Pesqueira e Várzea de Trevões",
    "site": null,
    "email": "info@pesqueiramiga.pt",
    "designacao_contrato": "Empreitada para Remodelação do Edifício Centro de Apoio a Idosos",
    "descricao": "Empreitada para a realização de obras de remodelação do Edifício Centro de Apoio a Idosos, no âmbito de projeto financiado pelo PRR.",
    "preco_base": "377.415,50 EUR",
    "prazo_execucao": "120 DIAS",
    "prazo_apresentacao_propostas": "13-01-2026 23:59",
    "fundos_eu": "Sim",
    "plataforma_eletronica": "VORTAL",
    "url_procedimento": "https://community.vortal.biz/public/",
    "autor_nome": "Maria Fernandina Martins Espírito Santo",
    "autor_cargo": "Presidente da Direção"
  },
  {
    "numero_procedimento": "N/A",
    "entidade": "Estado-Maior-General das Forças Armadas (EMGFA)",
    "link": "https://diariodarepublica.pt/dr/detalhe/contrato-publico/33635-993078726",
    "detalhes_completos": "1 - IDENTIFICAÇÃO E CONTACTOS DA ENTIDADE ADJUDICANTE\nDesignação da entidade adjudicante: Estado-Maior-General das Forças Armadas (EMGFA)\nNIPC: 600010180\nServiço/Órgão/Pessoa de contacto: Secção de Aquisições\nEndereço: Hospital das Forças Armadas  Polo do Porto Avenida da Boavista, s/n\nCódigo postal: 4050-113\nLocalidade: Porto\nPaís: Portugal\nNUT III: PT11A\nDistrito: Porto\nConcelho: Porto\nFreguesia: União das Freguesias de Cedofeita, Santo Ildefonso, Sé, Miragaia, São Nicolau e Vitória\nTelefone: 226087927\nFax: 000000000\nEndereço da Entidade (URL): https://www.hfar.pt/\nEndereço Eletrónico: hfar_pp_logistica@hfar.pt\neDelivery Gateway (URL): https://www.acingov.pt\nFunção da Organização: Adquirente\nNorma jurídica da Entidade Adjudicante: Organismo de direito público\nÁrea de atividade da Autoridade Adjudicante: Serviços públicos das administrações públicas\n\n2 - JORNAL OFICIAL DA UNIÃO EUROPEIA\nO procedimento a que este anúncio diz respeito também é publicitado no Jornal Oficial da União Europeia? Não\n\n3 - AVISO\nModelo de Anúncio: Concurso público\nData de Envio do Anúncio: 30-12-2025\n\n5 - PROCESSO\nTipo de Procedimento: Concurso público\nPreço base do procedimento: Sim\nValor do preço base do procedimento: 120.000,00 EUR\nProcedimento com lotes? Não\n\n6 - OBJETO DO CONTRATO\nNúmero de referência interna: CP PRR HFAR-PP 2025009785\nDesignação do contrato: 2025009785  Aquisição de Ecocardiógrafo com Sonda Matricial e Transesofágica para o serviço de Cardiologia e Urgência do HFAR-PP - Aviso PRR N.º 06/C01 i04/2025\nDescrição: 2025009785  Aquisição de Ecocardiógrafo com Sonda Matricial e Transesofágica para o serviço de Cardiologia e Urgência do HFAR-PP - Aviso PRR N.º 06/C01 i04/2025 \nTipo de Contrato Principal: Aquisição de Bens Móveis\nTipo de Contrato: Aquisição de Bens Móveis\nClassificação CPV (Vocabulário Comum para os Contratos Públicos)\nObjeto principal\nVocabulário Principal: 33112340\nPreço base s/IVA: 120.000,00 EUR\n\n7 - INDICAÇÕES ADICIONAIS\nO contrato envolve aquisição conjunta (satisfação de várias entidades)? Não\nO contrato é adjudicado por uma central de compras? Não\n\n8 - TÉCNICAS\nO concurso destina-se à celebração de um acordo-quadro? Inexistência de acordo-quadro\nÉ utilizado um leilão eletrónico? Não\nÉ adotada uma fase de negociação? Não\nSistema de Aquisição Dinâmico: Inexistência de sistema de aquisição dinâmico\n\n9 - LOCAL DA EXECUÇÃO DO CONTRATO\nLOCAL DA EXECUÇÃO DO CONTRATO (PROCEDIMENTO)\nPaís: Portugal\nNUT III: PT11A\nLocalidade: União das Freguesias de Cedofeita, Santo Ildefonso, Sé, Miragaia, São Nicolau e Vitória\nDistrito: Porto\nConcelho: Porto\nFreguesia: União das Freguesias de Cedofeita, Santo Ildefonso, Sé, Miragaia, São Nicolau e Vitória\n\n10 - PRAZO DE EXECUÇÃO DO CONTRATO\nPrazo de execução do contrato: 45 DIAS\nPrevisão de renovações: Não\n\n11 - FUNDOS EU\nTêm fundos EU? Sim\n\n12 - DOCUMENTOS DE HABILITAÇÃO\nHabilitação para o exercício da atividade profissional: Não\n\n13 - CONDIÇÕES DE APRESENTAÇÃO\nPlataforma eletrónica utilizada pela entidade adjudicante: ACIN\nURL para Apresentação: https://www.acingov.pt\nAdmissibilidade da apresentação de propostas variantes: Não autorizado\nPrazo para apresentação das propostas: 19-01-2026 23:59\nPrazo durante o qual os concorrentes são obrigados a manter as respetivas propostas: 210 dias a contar do termo do prazo para a apresentação das propostas\nIndicação de Subcontratação na Proposta: Inexistência de indicação de subcontratação\n\n14 - PRESTAÇÃO DE CAUÇÃO\nPrestação de caução: Não\n\n15 - FORNECIMENTO DAS PEÇAS DO CONCURSO, APRESENTAÇÃO DE PEDIDOS DE PARTICIPAÇÃO E APRESENTAÇÃO DAS PROPOSTAS\nLink para acesso às peças do concurso (URL): https://www.acingov.pt/acingovprod/2/zonaPublica/zona_publica_c/donwloadProcedurePiece/MTAwOTQ3MA==\n\n20 - OUTROS REQUISITOS\nInformação sobre contratos reservados. Aplica-se a contratos reservados (54º-A)? Não\n\n21 - CRITÉRIO DE ADJUDICAÇÃO\nMultifator: Não\nMonofator:\nNome: Preço\n\n24 - CONDIÇÕES DO CONTRATO\nFaturação Eletrónica: Permitido\nObrigação de Subcontratação:\nCódigo da Obrigação de Subcontratação: Não é aplicável nenhuma obrigação de subcontratação.\n\n25 - COMPRA PÚBLICA ESTRATÉGICA\nCompra Pública Estratégica: Inexistência de contratação pública estratégica\n\n26 - INFORMAÇÕES ADICIONAIS\nContrato adequado para PME: Não\nCobertura ACP (Acordo dos Contratos Públicos da Organização Mundial do Comércio): Não\n\n27 - IDENTIFICAÇÃO E CONTACTOS DO ÓRGÃO DE RECURSOS ADMINISTRATIVOS\nDesignação: Tribunal Administrativo de Círculo de Lisboa\nEndereço: Av D. João II, Bloco G, piso 6-8, nº 1.08.01, 1990-097 Lisboa\nCódigo postal: 1990-097\nLocalidade: Lisboa\nTelefone: 218367100\nFax: 211545188\nEndereço eletrónico: lisboa.tacl@tribunais.org.pt\n\n28 - IDENTIFICAÇÃO DO(S) AUTOR(ES) DE ANÚNCIO\nNome: José Carlos Candeias Pinheiro Monge\nCargo: Diretor do HFAR\n419940681",
    "nipc": "600010180",
    "distrito": "Porto",
    "concelho": "Porto",
    "freguesia": "União das Freguesias de Cedofeita, Santo Ildefonso, Sé, Miragaia, São Nicolau e Vitória",
    "site": "https://www.hfar.pt/",
    "email": "hfar_pp_logistica@hfar.pt",
    "designacao_contrato": "2025009785  Aquisição de Ecocardiógrafo com Sonda Matricial e Transesofágica para o serviço de Cardiologia e Urgência do HFAR-PP - Aviso PRR N.º 06/C01 i04/2025",
    "descricao": "2025009785  Aquisição de Ecocardiógrafo com Sonda Matricial e Transesofágica para o serviço de Cardiologia e Urgência do HFAR-PP - Aviso PRR N.º 06/C01 i04/2025",
    "preco_base": "120.000,00 EUR",
    "prazo_execucao": "45 DIAS",
    "prazo_apresentacao_propostas": "19-01-2026 23:59",
    "fundos_eu": "Sim",
    "plataforma_eletronica": "ACIN",
    "url_procedimento": "https://www.acingov.pt",
    "autor_nome": "José Carlos Candeias Pinheiro Monge",
    "autor_cargo": "Diretor do HFAR"
  },
  {
    "numero_procedimento": "N/A",
    "entidade": "Estado-Maior-General das Forças Armadas (EMGFA)",
    "link": "https://diariodarepublica.pt/dr/detalhe/contrato-publico/33637-993078727",
    "detalhes_completos": "1 - IDENTIFICAÇÃO E CONTACTOS DA ENTIDADE ADJUDICANTE\nDesignação da entidade adjudicante: Estado-Maior-General das Forças Armadas (EMGFA)\nNIPC: 600010180\nServiço/Órgão/Pessoa de contacto: Secção de Aquisições\nEndereço: Hospital das Forças Armadas  Polo do Porto Avenida da Boavista, s/n\nCódigo postal: 4050-113\nLocalidade: Porto\nPaís: Portugal\nNUT III: PT11A\nDistrito: Porto\nConcelho: Porto\nFreguesia: União das Freguesias de Cedofeita, Santo Ildefonso, Sé, Miragaia, São Nicolau e Vitória\nTelefone: 226087927\nFax: 000000000\nEndereço da Entidade (URL): https://www.hfar.pt/\nEndereço Eletrónico: hfar_pp_logistica@hfar.pt\neDelivery Gateway (URL): https://www.acingov.pt\nFunção da Organização: Adquirente\nNorma jurídica da Entidade Adjudicante: Organismo de direito público\nÁrea de atividade da Autoridade Adjudicante: Serviços públicos das administrações públicas\n\n2 - JORNAL OFICIAL DA UNIÃO EUROPEIA\nO procedimento a que este anúncio diz respeito também é publicitado no Jornal Oficial da União Europeia? Não\n\n3 - AVISO\nModelo de Anúncio: Concurso público\nData de Envio do Anúncio: 30-12-2025\n\n5 - PROCESSO\nTipo de Procedimento: Concurso público\nPreço base do procedimento: Sim\nValor do preço base do procedimento: 140.000,00 EUR\nProcedimento com lotes? Não\n\n6 - OBJETO DO CONTRATO\nNúmero de referência interna: CP PRR HFAR-PL 2025009788\nDesignação do contrato: 2025009788  Aquisição de Arco C Móvel para o serviço de Imagiologia do HFAR-PL - Aviso PRR N.º 06/C01 i04/2025\nDescrição: 2025009788  Aquisição de Arco C Móvel para o serviço de Imagiologia do HFAR-PL - Aviso PRR N.º 06/C01 i04/2025 \nTipo de Contrato Principal: Aquisição de Bens Móveis\nTipo de Contrato: Aquisição de Bens Móveis\nClassificação CPV (Vocabulário Comum para os Contratos Públicos)\nObjeto principal\nVocabulário Principal: 33111400\nPreço base s/IVA: 140.000,00 EUR\n\n7 - INDICAÇÕES ADICIONAIS\nO contrato envolve aquisição conjunta (satisfação de várias entidades)? Não\nO contrato é adjudicado por uma central de compras? Não\n\n8 - TÉCNICAS\nO concurso destina-se à celebração de um acordo-quadro? Inexistência de acordo-quadro\nÉ utilizado um leilão eletrónico? Não\nÉ adotada uma fase de negociação? Não\nSistema de Aquisição Dinâmico: Inexistência de sistema de aquisição dinâmico\n\n9 - LOCAL DA EXECUÇÃO DO CONTRATO\nLOCAL DA EXECUÇÃO DO CONTRATO (PROCEDIMENTO)\nPaís: Portugal\nNUT III: PT11A\nLocalidade: União das Freguesias de Cedofeita, Santo Ildefonso, Sé, Miragaia, São Nicolau e Vitória\nDistrito: Porto\nConcelho: Porto\nFreguesia: União das Freguesias de Cedofeita, Santo Ildefonso, Sé, Miragaia, São Nicolau e Vitória\n\n10 - PRAZO DE EXECUÇÃO DO CONTRATO\nPrazo de execução do contrato: 60 DIAS\nPrevisão de renovações: Não\n\n11 - FUNDOS EU\nTêm fundos EU? Sim\n\n12 - DOCUMENTOS DE HABILITAÇÃO\nHabilitação para o exercício da atividade profissional: Não\n\n13 - CONDIÇÕES DE APRESENTAÇÃO\nPlataforma eletrónica utilizada pela entidade adjudicante: ACIN\nURL para Apresentação: https://www.acingov.pt\nAdmissibilidade da apresentação de propostas variantes: Não autorizado\nPrazo para apresentação das propostas: 19-01-2026 23:59\nPrazo durante o qual os concorrentes são obrigados a manter as respetivas propostas: 210 dias a contar do termo do prazo para a apresentação das propostas\nIndicação de Subcontratação na Proposta: Inexistência de indicação de subcontratação\n\n14 - PRESTAÇÃO DE CAUÇÃO\nPrestação de caução: Não\n\n15 - FORNECIMENTO DAS PEÇAS DO CONCURSO, APRESENTAÇÃO DE PEDIDOS DE PARTICIPAÇÃO E APRESENTAÇÃO DAS PROPOSTAS\nLink para acesso às peças do concurso (URL): https://www.acingov.pt/acingovprod/2/zonaPublica/zona_publica_c/donwloadProcedurePiece/MTAwOTUwMA==\n\n20 - OUTROS REQUISITOS\nInformação sobre contratos reservados. Aplica-se a contratos reservados (54º-A)? Não\n\n21 - CRITÉRIO DE ADJUDICAÇÃO\nMultifator: Não\nMonofator:\nNome: Preço\n\n24 - CONDIÇÕES DO CONTRATO\nFaturação Eletrónica: Permitido\nObrigação de Subcontratação:\nCódigo da Obrigação de Subcontratação: Não é aplicável nenhuma obrigação de subcontratação.\n\n25 - COMPRA PÚBLICA ESTRATÉGICA\nCompra Pública Estratégica: Inexistência de contratação pública estratégica\n\n26 - INFORMAÇÕES ADICIONAIS\nContrato adequado para PME: Não\nCobertura ACP (Acordo dos Contratos Públicos da Organização Mundial do Comércio): Não\n\n27 - IDENTIFICAÇÃO E CONTACTOS DO ÓRGÃO DE RECURSOS ADMINISTRATIVOS\nDesignação: Tribunal Administrativo de Círculo de Lisboa\nEndereço: Av D. João II, Bloco G, piso 6-8, nº 1.08.01, 1990-097 Lisboa\nCódigo postal: 1990-097\nLocalidade: Lisboa\nTelefone: 218367100\nFax: 211545188\nEndereço eletrónico: lisboa.tacl@tribunais.org.pt\n\n28 - IDENTIFICAÇÃO DO(S) AUTOR(ES) DE ANÚNCIO\nNome: José Carlos Candeias Pinheiro Monge\nCargo: Diretor do HFAR\n419940876",
    "nipc": "600010180",
    "distrito": "Porto",
    "concelho": "Porto",
    "freguesia": "União das Freguesias de Cedofeita, Santo Ildefonso, Sé, Miragaia, São Nicolau e Vitória",
    "site": "https://www.hfar.pt/",
    "email": "hfar_pp_logistica@hfar.pt",
    "designacao_contrato": "2025009788  Aquisição de Arco C Móvel para o serviço de Imagiologia do HFAR-PL - Aviso PRR N.º 06/C01 i04/2025",
    "descricao": "2025009788  Aquisição de Arco C Móvel para o serviço de Imagiologia do HFAR-PL - Aviso PRR N.º 06/C01 i04/2025",
    "preco_base": "140.000,00 EUR",
    "prazo_execucao": "60 DIAS",
    "prazo_apresentacao_propostas": "19-01-2026 23:59",
    "fundos_eu": "Sim",
    "plataforma_eletronica": "ACIN",
    "url_procedimento": "https://www.acingov.pt",
    "autor_nome": "José Carlos Candeias Pinheiro Monge",
    "autor_cargo": "Diretor do HFAR"
  },
  {
    "numero_procedimento": "N/A",
    "entidade": "AnÃºncio de procedimento  n.Âº 33639/2025  -  DiÃ¡rio da RepÃºblica n.Âº 251/2025, SÃ©rie II de 2025-12-31",
    "link": "https://diariodarepublica.pt/dr/detalhe/contrato-publico/33639-993078728"
  },
  {
    "numero_procedimento": "N/A",
    "entidade": "AnÃºncio de procedimento  n.Âº 33641/2025  -  DiÃ¡rio da RepÃºblica n.Âº 251/2025, SÃ©rie II de 2025-12-31",
    "link": "https://diariodarepublica.pt/dr/detalhe/contrato-publico/33641-993078729"
  },
  {
    "numero_procedimento": "N/A",
    "entidade": "Agrupamento de Escolas São Martinho do Porto, Alcobaça",
    "link": "https://diariodarepublica.pt/dr/detalhe/contrato-publico/33643-993078759",
    "detalhes_completos": "1 - IDENTIFICAÇÃO E CONTACTOS DA ENTIDADE ADJUDICANTE\nDesignação da entidade adjudicante: Agrupamento de Escolas São Martinho do Porto, Alcobaça\nNIPC: 600079805\nEndereço: R. dos Bombeiros Voluntários\nCódigo postal: 2460-654\nLocalidade: Leiria\nPaís: Portugal\nNUT III: PT16F\nDistrito: Leiria\nConcelho: Leiria\nFreguesia: Todas\nTelefone: 262985090\nEndereço Eletrónico: agrupamentosmp@aesmporto.pt\neDelivery Gateway (URL): https://community.vortal.biz/public/\nFunção da Organização: Adquirente\nNorma jurídica da Entidade Adjudicante: Organismo de direito público\nÁrea de atividade da Autoridade Adjudicante: Educação\n\n2 - JORNAL OFICIAL DA UNIÃO EUROPEIA\nO procedimento a que este anúncio diz respeito também é publicitado no Jornal Oficial da União Europeia? Não\n\n3 - AVISO\nModelo de Anúncio: Concurso público\nData de Envio do Anúncio: 30-12-2025\n\n5 - PROCESSO\nTipo de Procedimento: Concurso público\nPreço base do procedimento: Sim\nValor do preço base do procedimento: 20.864,65 EUR\nProcedimento com lotes? Não\n\n6 - OBJETO DO CONTRATO\nNúmero de referência interna: CP3AESMP_2026_CARNES\nDesignação do contrato: CP3AESMP_2026_CARNES\nDescrição: CP3AESMP_2026_CARNES\nTipo de Contrato Principal: Aquisição de Bens Móveis\nTipo de Contrato: Aquisição de Bens Móveis\nClassificação CPV (Vocabulário Comum para os Contratos Públicos)\nObjeto principal\nVocabulário Principal: 03100000\nPreço base s/IVA: 20.864,65 EUR\n\n7 - INDICAÇÕES ADICIONAIS\nO contrato envolve aquisição conjunta (satisfação de várias entidades)? Não\nO contrato é adjudicado por uma central de compras? Não\n\n8 - TÉCNICAS\nO concurso destina-se à celebração de um acordo-quadro? Inexistência de acordo-quadro\nÉ utilizado um leilão eletrónico? Não\nÉ adotada uma fase de negociação? Não\nSistema de Aquisição Dinâmico: Inexistência de sistema de aquisição dinâmico\n\n9 - LOCAL DA EXECUÇÃO DO CONTRATO\nLOCAL DA EXECUÇÃO DO CONTRATO (PROCEDIMENTO)\nPaís: Portugal\nNUT III: PT16B\nLocalidade: Leiria\nDistrito: Leiria\nConcelho: Alcobaça\nFreguesia: Todas\n\n10 - PRAZO DE EXECUÇÃO DO CONTRATO\nPrazo de execução do contrato: 365 DIAS\nPrevisão de renovações: Não\n\n11 - FUNDOS EU\nTêm fundos EU? Não\n\n12 - DOCUMENTOS DE HABILITAÇÃO\nHabilitação para o exercício da atividade profissional: Não\n\n13 - CONDIÇÕES DE APRESENTAÇÃO\nPlataforma eletrónica utilizada pela entidade adjudicante: VORTAL\nURL para Apresentação: https://community.vortal.biz/public/\nAdmissibilidade da apresentação de propostas variantes: Não autorizado\nPrazo para apresentação das propostas: 07-01-2026 23:59\nPrazo durante o qual os concorrentes são obrigados a manter as respetivas propostas: 90 dias a contar do termo do prazo para a apresentação das propostas\nIndicação de Subcontratação na Proposta: Inexistência de indicação de subcontratação\n\n14 - PRESTAÇÃO DE CAUÇÃO\nPrestação de caução: Não\n\n15 - FORNECIMENTO DAS PEÇAS DO CONCURSO, APRESENTAÇÃO DE PEDIDOS DE PARTICIPAÇÃO E APRESENTAÇÃO DAS PROPOSTAS\nLink para acesso às peças do concurso (URL): https://community.vortal.biz/Public/public-tender-documents/K2xtYjVrL2FOWE00aVc0Q0N1NzN2RnFTcm5NOTVkd0RONE1QTkhhYVJwY2lsc2s0UUdteklYanJ2eWN1aVZLODE4aDc1OUVKQVMrU2Y1NG83ZHhhZGc9PXpyJVN0\n\n20 - OUTROS REQUISITOS\nInformação sobre contratos reservados. Aplica-se a contratos reservados (54º-A)? Não\n\n21 - CRITÉRIO DE ADJUDICAÇÃO\nMultifator: Não\nMonofator:\nNome: Preço\n\n24 - CONDIÇÕES DO CONTRATO\nFaturação Eletrónica: Permitido\nObrigação de Subcontratação:\nCódigo da Obrigação de Subcontratação: Não é aplicável nenhuma obrigação de subcontratação.\n\n25 - COMPRA PÚBLICA ESTRATÉGICA\nCompra Pública Estratégica: Inexistência de contratação pública estratégica\n\n26 - INFORMAÇÕES ADICIONAIS\nContrato adequado para PME: Sim\nCobertura ACP (Acordo dos Contratos Públicos da Organização Mundial do Comércio): Não\n\n27 - IDENTIFICAÇÃO E CONTACTOS DO ÓRGÃO DE RECURSOS ADMINISTRATIVOS\nDesignação: Conselho Administrativo\nEndereço: Rua dos Bombeiros Voluntários\nCódigo postal: 2460-654\nLocalidade: Alcobaça\nTelefone: +351 262985090\nFax: +351 262985090\nEndereço eletrónico: diretor@aesmporto.pt\n\n28 - IDENTIFICAÇÃO DO(S) AUTOR(ES) DE ANÚNCIO\nNome: Luís Silva\nCargo: Diretor\n419943962",
    "nipc": "600079805",
    "distrito": "Leiria",
    "concelho": "Leiria",
    "freguesia": "Todas",
    "site": null,
    "email": "agrupamentosmp@aesmporto.pt",
    "designacao_contrato": "CP3AESMP_2026_CARNES",
    "descricao": "CP3AESMP_2026_CARNES",
    "preco_base": "20.864,65 EUR",
    "prazo_execucao": "365 DIAS",
    "prazo_apresentacao_propostas": "07-01-2026 23:59",
    "fundos_eu": "Não",
    "plataforma_eletronica": "VORTAL",
    "url_procedimento": "https://community.vortal.biz/public/",
    "autor_nome": "Luís Silva",
    "autor_cargo": "Diretor"
  },
  {
    "numero_procedimento": "N/A",
    "entidade": "Estado-Maior-General das Forças Armadas (EMGFA)",
    "link": "https://diariodarepublica.pt/dr/detalhe/contrato-publico/33644-993078760",
    "detalhes_completos": "1 - IDENTIFICAÇÃO E CONTACTOS DA ENTIDADE ADJUDICANTE\nDesignação da entidade adjudicante: Estado-Maior-General das Forças Armadas (EMGFA)\nNIPC: 600010180\nServiço/Órgão/Pessoa de contacto: DepComp/DF/HFAR\nEndereço: AVENIDA ILHA DA MADEIRA\nCódigo postal: 1449-004\nLocalidade: Lisboa\nPaís: Portugal\nNUT III: PT170\nDistrito: Lisboa\nConcelho: Lisboa\nFreguesia: Freguesia de Lumiar\nTelefone: 2130100001\nEndereço da Entidade (URL): www.emgfa.pt\nEndereço Eletrónico: DIRFIN_Contratos@emgfa.pt\neDelivery Gateway (URL): https://www.acingov.pt\nFunção da Organização: Adquirente\nNorma jurídica da Entidade Adjudicante: Organismo de direito público\nÁrea de atividade da Entidade Adjudicante: Atividades aeroportuárias\n\n2 - JORNAL OFICIAL DA UNIÃO EUROPEIA\nO procedimento a que este anúncio diz respeito também é publicitado no Jornal Oficial da União Europeia? Não\n\n3 - AVISO\nModelo de Anúncio: Concurso público\nData de Envio do Anúncio: 30-12-2025\n\n5 - PROCESSO\nTipo de Procedimento: Concurso público\nPreço base do procedimento: Sim\nValor do preço base do procedimento: 53.300,00 EUR\nProcedimento com lotes? Sim\nNº Máx. de Lotes Autorizado: 3\nNúmero máximo de lotes que podem ser adjudicados a um concorrente: 3\n\n6 - OBJETO DO CONTRATO\nNúmero de referência interna: HFAR-PL 2025009778\nDesignação do contrato: 2025009778/PRR_6-EQUIPAMENTOS PARA MEDICINA DENTÁRIA\nDescrição: 2025009778/PRR_6-EQUIPAMENTOS PARA MEDICINA DENTÁRIA\nTipo de Contrato Principal: Aquisição de Bens Móveis\nTipo de Contrato: Aquisição de Bens Móveis\nClassificação CPV (Vocabulário Comum para os Contratos Públicos)\nObjeto principal\nVocabulário Principal: 33169000\nPreço base s/IVA: 53.300,00 EUR\nLotes: \nNº: LOT-0001\nDescrição do Lote: Bancada de próteses\nPreço base s/IVA: 9.100,00 EUR\nClassificação CPV (Vocabulário Comum para os Contratos Públicos)\nObjeto principal\nVocabulário Principal: 33169000\nNº: LOT-0002\nDescrição do Lote: Cadeiras Medicina Dentária\nPreço base s/IVA: 20.000,00 EUR\nClassificação CPV (Vocabulário Comum para os Contratos Públicos)\nObjeto principal\nVocabulário Principal: 33169000\nNº: LOT-0003\nDescrição do Lote: Scanner Intra Oral, com computador portátil\nPreço base s/IVA: 24.200,00 EUR\nClassificação CPV (Vocabulário Comum para os Contratos Públicos)\nObjeto principal\nVocabulário Principal: 33169000\n\n7 - INDICAÇÕES ADICIONAIS\nO contrato envolve aquisição conjunta (satisfação de várias entidades)? Não\nO contrato é adjudicado por uma central de compras? Não\n\n8 - TÉCNICAS\nO concurso destina-se à celebração de um acordo-quadro? Inexistência de acordo-quadro\nÉ utilizado um leilão eletrónico? Não\nÉ adotada uma fase de negociação? Não\nSistema de Aquisição Dinâmico: Inexistência de sistema de aquisição dinâmico\n\n9 - LOCAL DA EXECUÇÃO DO CONTRATO\nLOCAL DA EXECUÇÃO DO CONTRATO (PROCEDIMENTO)\nPaís: Portugal\nNUT III: PT170\nLocalidade: Freguesia de Lumiar\nDistrito: Lisboa\nConcelho: Lisboa\nFreguesia: Freguesia de Lumiar\nLOCAL DA EXECUÇÃO DO CONTRATO (LOTE)\nIdentificador do Lote: LOT-0001; LOT-0002; LOT-0003\nPaís: Portugal\nNUT III: PT170\nLocalidade: Lumiar\nDistrito: Lisboa\nConcelho: Lisboa\nFreguesia: Todas\n\n10 - PRAZO DE EXECUÇÃO DO CONTRATO\nIdentificador do Lote: LOT-0001; LOT-0002; LOT-0003\nPrazo de execução do contrato: 90 DIAS\nPrevisão de renovações: Não\n\n11 - FUNDOS EU\nIdentificador do Lote: LOT-0001; LOT-0002; LOT-0003\nTêm fundos EU? Sim\n\n12 - DOCUMENTOS DE HABILITAÇÃO\nHabilitação para o exercício da atividade profissional: Não\n\n13 - CONDIÇÕES DE APRESENTAÇÃO\nPlataforma eletrónica utilizada pela entidade adjudicante: ACIN\nURL para Apresentação: https://www.acingov.pt\nAdmissibilidade da apresentação de propostas variantes: Não autorizado\nPrazo para apresentação das propostas: 12-01-2026 23:59\nPrazo durante o qual os concorrentes são obrigados a manter as respetivas propostas: 66 dias a contar do termo do prazo para a apresentação das propostas\nIndicação de Subcontratação na Proposta: Inexistência de indicação de subcontratação\n\n14 - PRESTAÇÃO DE CAUÇÃO\nPrestação de caução: Não\n\n15 - FORNECIMENTO DAS PEÇAS DO CONCURSO, APRESENTAÇÃO DE PEDIDOS DE PARTICIPAÇÃO E APRESENTAÇÃO DAS PROPOSTAS\nLink para acesso às peças do concurso (URL): https://www.acingov.pt/acingovprod/2/zonaPublica/zona_publica_c/donwloadProcedurePiece/MTAxMDkyMg==\n\n20 - OUTROS REQUISITOS\nIdentificador do Lote: LOT-0001; LOT-0002; LOT-0003\nInformação sobre contratos reservados. Aplica-se a contratos reservados (54º-A)? Não\n\n21 - CRITÉRIO DE ADJUDICAÇÃO\nO Critério de adjudicação é diferenciado por lote? Não\nMultifator: Não\nMonofator:\nNome: Preço\n\n24 - CONDIÇÕES DO CONTRATO\nIdentificador do Lote: LOT-0001; LOT-0002; LOT-0003\nFaturação Eletrónica: Permitido\nObrigação de Subcontratação:\nCódigo da Obrigação de Subcontratação: Não é aplicável nenhuma obrigação de subcontratação.\n\n25 - COMPRA PÚBLICA ESTRATÉGICA\nCompra Pública Estratégica: Inexistência de contratação pública estratégica\n\n26 - INFORMAÇÕES ADICIONAIS\nIdentificador do Lote: LOT-0001; LOT-0002; LOT-0003\nContrato adequado para PME: Sim\nCobertura ACP (Acordo dos Contratos Públicos da Organização Mundial do Comércio): Não\n\n27 - IDENTIFICAÇÃO E CONTACTOS DO ÓRGÃO DE RECURSOS ADMINISTRATIVOS\nDesignação: EMGFA\nEndereço: Av. Ilha da Madeira N.º 1, 1449-004 Lisboa\nCódigo postal: 1449-004\nLocalidade: Lisboa\nTelefone: 213043000\nFax: \nEndereço eletrónico: emgfa@emgfa.pt\n\n28 - IDENTIFICAÇÃO DO(S) AUTOR(ES) DE ANÚNCIO\nNome: JOSÉ CARLOS CANDEIAS PINHEIRO MONGE\nCargo: DIRETOR HFAR\n419942252",
    "nipc": "600010180",
    "distrito": "Lisboa",
    "concelho": "Lisboa",
    "freguesia": "Freguesia de Lumiar",
    "site": "www.emgfa.pt",
    "email": "DIRFIN_Contratos@emgfa.pt",
    "designacao_contrato": "2025009778/PRR_6-EQUIPAMENTOS PARA MEDICINA DENTÁRIA",
    "descricao": "2025009778/PRR_6-EQUIPAMENTOS PARA MEDICINA DENTÁRIA",
    "preco_base": "53.300,00 EUR",
    "prazo_execucao": "90 DIAS",
    "prazo_apresentacao_propostas": "12-01-2026 23:59",
    "fundos_eu": "Sim",
    "plataforma_eletronica": "ACIN",
    "url_procedimento": "https://www.acingov.pt",
    "autor_nome": "JOSÉ CARLOS CANDEIAS PINHEIRO MONGE",
    "autor_cargo": "DIRETOR HFAR"
  },
  {
    "numero_procedimento": "N/A",
    "entidade": "AnÃºncio de procedimento  n.Âº 33645/2025  -  DiÃ¡rio da RepÃºblica n.Âº 251/2025, SÃ©rie II de 2025-12-31",
    "link": "https://diariodarepublica.pt/dr/detalhe/contrato-publico/33645-993078761"
  },
  {
    "numero_procedimento": "N/A",
    "entidade": "Estado-Maior-General das Forças Armadas (EMGFA)",
    "link": "https://diariodarepublica.pt/dr/detalhe/contrato-publico/33646-993078762",
    "detalhes_completos": "1 - IDENTIFICAÇÃO E CONTACTOS DA ENTIDADE ADJUDICANTE\nDesignação da entidade adjudicante: Estado-Maior-General das Forças Armadas (EMGFA)\nNIPC: 600010180\nServiço/Órgão/Pessoa de contacto: DepCompras\nEndereço: Azinhaga Ulmeiros, 1649-020 Lisboa\nCódigo postal: 1649-020\nLocalidade: Lisboa\nPaís: Portugal\nNUT III: PT170\nDistrito: Lisboa\nConcelho: Lisboa\nFreguesia: Freguesia de Lumiar\nTelefone: 21 751 9777\nFax: 21 751 9777\nEndereço da Entidade (URL): www.hfar.pt\nEndereço Eletrónico: hfar_dcomp_chf@hfar.pt\neDelivery Gateway (URL): https://www.acingov.pt\nFunção da Organização: Adquirente\nNorma jurídica da Entidade Adjudicante: Organismo de direito público\nÁrea de atividade da Entidade Adjudicante: Atividades aeroportuárias\n\n2 - JORNAL OFICIAL DA UNIÃO EUROPEIA\nO procedimento a que este anúncio diz respeito também é publicitado no Jornal Oficial da União Europeia? Não\n\n3 - AVISO\nModelo de Anúncio: Concurso público\nData de Envio do Anúncio: 30-12-2025\n\n5 - PROCESSO\nTipo de Procedimento: Concurso público\nPreço base do procedimento: Sim\nValor do preço base do procedimento: 126.700,00 EUR\nProcedimento com lotes? Sim\nNº Máx. de Lotes Autorizado: 4\nNúmero máximo de lotes que podem ser adjudicados a um concorrente: 4\n\n6 - OBJETO DO CONTRATO\nNúmero de referência interna: HFAR-PL 2025009415\nDesignação do contrato: 2025009415/HFAR-PRR_6-EQUIPAMENTOS PARA CENTRO DE MEDICINA SUBAQUÁTICA E HIPERBÁRICA\nDescrição: 2025009415/HFAR-PRR_6-EQUIPAMENTOS PARA CENTRO DE MEDICINA SUBAQUÁTICA E HIPERBÁRICA\nTipo de Contrato Principal: Aquisição de Bens Móveis\nTipo de Contrato: Aquisição de Bens Móveis\nClassificação CPV (Vocabulário Comum para os Contratos Públicos)\nObjeto principal\nVocabulário Principal: 33169000\nPreço base s/IVA: 126.700,00 EUR\nLotes: \nNº: LOT-0001\nDescrição do Lote: Sistema monitorização qualidade do ar hiperbárico\nPreço base s/IVA: 13.500,00 EUR\nClassificação CPV (Vocabulário Comum para os Contratos Públicos)\nObjeto principal\nVocabulário Principal: 33169000\nNº: LOT-0002\nDescrição do Lote: Maca hiperbárica\nPreço base s/IVA: 25.000,00 EUR\nClassificação CPV (Vocabulário Comum para os Contratos Públicos)\nObjeto principal\nVocabulário Principal: 33169000\nNº: LOT-0003\nDescrição do Lote: Monitor transcutâneo de TCPO2\nPreço base s/IVA: 29.000,00 EUR\nClassificação CPV (Vocabulário Comum para os Contratos Públicos)\nObjeto principal\nVocabulário Principal: 33169000\nNº: LOT-0004\nDescrição do Lote: Seringa infusora hiperbárica\nPreço base s/IVA: 59.200,00 EUR\nClassificação CPV (Vocabulário Comum para os Contratos Públicos)\nObjeto principal\nVocabulário Principal: 33169000\n\n7 - INDICAÇÕES ADICIONAIS\nO contrato envolve aquisição conjunta (satisfação de várias entidades)? Não\nO contrato é adjudicado por uma central de compras? Não\n\n8 - TÉCNICAS\nO concurso destina-se à celebração de um acordo-quadro? Inexistência de acordo-quadro\nÉ utilizado um leilão eletrónico? Não\nÉ adotada uma fase de negociação? Não\nSistema de Aquisição Dinâmico: Inexistência de sistema de aquisição dinâmico\n\n9 - LOCAL DA EXECUÇÃO DO CONTRATO\nLOCAL DA EXECUÇÃO DO CONTRATO (PROCEDIMENTO)\nPaís: Portugal\nNUT III: PT170\nLocalidade: Freguesia de Lumiar\nDistrito: Lisboa\nConcelho: Lisboa\nFreguesia: Freguesia de Lumiar\nLOCAL DA EXECUÇÃO DO CONTRATO (LOTE)\nIdentificador do Lote: LOT-0001; LOT-0002; LOT-0003; LOT-0004\nPaís: Portugal\nNUT III: PT170\nLocalidade: Lumiar\nDistrito: Lisboa\nConcelho: Lisboa\nFreguesia: Todas\n\n10 - PRAZO DE EXECUÇÃO DO CONTRATO\nIdentificador do Lote: LOT-0001; LOT-0002; LOT-0003; LOT-0004\nPrazo de execução do contrato: 90 DIAS\nPrevisão de renovações: Não\n\n11 - FUNDOS EU\nIdentificador do Lote: LOT-0001; LOT-0002; LOT-0003; LOT-0004\nTêm fundos EU? Sim\n\n12 - DOCUMENTOS DE HABILITAÇÃO\nHabilitação para o exercício da atividade profissional: Não\n\n13 - CONDIÇÕES DE APRESENTAÇÃO\nPlataforma eletrónica utilizada pela entidade adjudicante: ACIN\nURL para Apresentação: https://www.acingov.pt\nAdmissibilidade da apresentação de propostas variantes: Não autorizado\nPrazo para apresentação das propostas: 11-01-2026 23:59\nPrazo durante o qual os concorrentes são obrigados a manter as respetivas propostas: 66 dias a contar do termo do prazo para a apresentação das propostas\nIndicação de Subcontratação na Proposta: Inexistência de indicação de subcontratação\n\n14 - PRESTAÇÃO DE CAUÇÃO\nPrestação de caução: Não\n\n15 - FORNECIMENTO DAS PEÇAS DO CONCURSO, APRESENTAÇÃO DE PEDIDOS DE PARTICIPAÇÃO E APRESENTAÇÃO DAS PROPOSTAS\nLink para acesso às peças do concurso (URL): https://www.acingov.pt/acingovprod/2/zonaPublica/zona_publica_c/donwloadProcedurePiece/MTAxMjMzNg==\n\n20 - OUTROS REQUISITOS\nIdentificador do Lote: LOT-0001; LOT-0002; LOT-0003; LOT-0004\nInformação sobre contratos reservados. Aplica-se a contratos reservados (54º-A)? Não\n\n21 - CRITÉRIO DE ADJUDICAÇÃO\nO Critério de adjudicação é diferenciado por lote? Não\nMultifator: Não\nMonofator:\nNome: Preço\n\n24 - CONDIÇÕES DO CONTRATO\nIdentificador do Lote: LOT-0001; LOT-0002; LOT-0003; LOT-0004\nFaturação Eletrónica: Permitido\nObrigação de Subcontratação:\nCódigo da Obrigação de Subcontratação: Não é aplicável nenhuma obrigação de subcontratação.\n\n25 - COMPRA PÚBLICA ESTRATÉGICA\nCompra Pública Estratégica: Inexistência de contratação pública estratégica\n\n26 - INFORMAÇÕES ADICIONAIS\nIdentificador do Lote: LOT-0001; LOT-0002; LOT-0003; LOT-0004\nContrato adequado para PME: Não\nCobertura ACP (Acordo dos Contratos Públicos da Organização Mundial do Comércio): Não\n\n27 - IDENTIFICAÇÃO E CONTACTOS DO ÓRGÃO DE RECURSOS ADMINISTRATIVOS\nDesignação: EMGFA\nEndereço: Av. Ilha da Madeira N.º 1, 1449-004 Lisboa\nCódigo postal: 1449-004\nLocalidade: Lisboa\nEndereço eletrónico: emgfa@emgfa.pt\n\n28 - IDENTIFICAÇÃO DO(S) AUTOR(ES) DE ANÚNCIO\nNome: José Carlos Candeias Pinheiro Monge\nCargo: Diretor HFAR\n419942017",
    "nipc": "600010180",
    "distrito": "Lisboa",
    "concelho": "Lisboa",
    "freguesia": "Freguesia de Lumiar",
    "site": "www.hfar.pt",
    "email": "hfar_dcomp_chf@hfar.pt",
    "designacao_contrato": "2025009415/HFAR-PRR_6-EQUIPAMENTOS PARA CENTRO DE MEDICINA SUBAQUÁTICA E HIPERBÁRICA",
    "descricao": "2025009415/HFAR-PRR_6-EQUIPAMENTOS PARA CENTRO DE MEDICINA SUBAQUÁTICA E HIPERBÁRICA",
    "preco_base": "126.700,00 EUR",
    "prazo_execucao": "90 DIAS",
    "prazo_apresentacao_propostas": "11-01-2026 23:59",
    "fundos_eu": "Sim",
    "plataforma_eletronica": "ACIN",
    "url_procedimento": "https://www.acingov.pt",
    "autor_nome": "José Carlos Candeias Pinheiro Monge",
    "autor_cargo": "Diretor HFAR"
  },
  {
    "numero_procedimento": "N/A",
    "entidade": "Agrupamento de Escolas São Martinho do Porto, Alcobaça",
    "link": "https://diariodarepublica.pt/dr/detalhe/contrato-publico/33647-993078763",
    "detalhes_completos": "1 - IDENTIFICAÇÃO E CONTACTOS DA ENTIDADE ADJUDICANTE\nDesignação da entidade adjudicante: Agrupamento de Escolas São Martinho do Porto, Alcobaça\nNIPC: 600079805\nEndereço: R. dos Bombeiros Voluntários\nCódigo postal: 2460-654\nLocalidade: Leiria\nPaís: Portugal\nNUT III: PT16F\nDistrito: Leiria\nConcelho: Leiria\nFreguesia: Todas\nTelefone: 262985090\nEndereço Eletrónico: agrupamentosmp@aesmporto.pt\neDelivery Gateway (URL): https://community.vortal.biz/public/\nFunção da Organização: Adquirente\nNorma jurídica da Entidade Adjudicante: Organismo de direito público\nÁrea de atividade da Autoridade Adjudicante: Educação\n\n2 - JORNAL OFICIAL DA UNIÃO EUROPEIA\nO procedimento a que este anúncio diz respeito também é publicitado no Jornal Oficial da União Europeia? Não\n\n3 - AVISO\nModelo de Anúncio: Concurso público\nData de Envio do Anúncio: 30-12-2025\n\n5 - PROCESSO\nTipo de Procedimento: Concurso público\nPreço base do procedimento: Sim\nValor do preço base do procedimento: 18.814,72 EUR\nProcedimento com lotes? Não\n\n6 - OBJETO DO CONTRATO\nNúmero de referência interna: CP2AESMP_2026_FRUTA E LEGUMES\nDesignação do contrato: CP2AESMP_2026_FRUTA E LEGUMES\nDescrição: CP2AESMP_2026_FRUTA E LEGUMES\nTipo de Contrato Principal: Aquisição de Bens Móveis\nTipo de Contrato: Aquisição de Bens Móveis\nClassificação CPV (Vocabulário Comum para os Contratos Públicos)\nObjeto principal\nVocabulário Principal: 03100000\nPreço base s/IVA: 18.814,72 EUR\n\n7 - INDICAÇÕES ADICIONAIS\nO contrato envolve aquisição conjunta (satisfação de várias entidades)? Não\nO contrato é adjudicado por uma central de compras? Não\n\n8 - TÉCNICAS\nO concurso destina-se à celebração de um acordo-quadro? Inexistência de acordo-quadro\nÉ utilizado um leilão eletrónico? Não\nÉ adotada uma fase de negociação? Não\nSistema de Aquisição Dinâmico: Inexistência de sistema de aquisição dinâmico\n\n9 - LOCAL DA EXECUÇÃO DO CONTRATO\nLOCAL DA EXECUÇÃO DO CONTRATO (PROCEDIMENTO)\nPaís: Portugal\nNUT III: PT16B\nLocalidade: Leiria\nDistrito: Leiria\nConcelho: Alcobaça\nFreguesia: Todas\n\n10 - PRAZO DE EXECUÇÃO DO CONTRATO\nPrazo de execução do contrato: 365 DIAS\nPrevisão de renovações: Não\n\n11 - FUNDOS EU\nTêm fundos EU? Não\n\n12 - DOCUMENTOS DE HABILITAÇÃO\nHabilitação para o exercício da atividade profissional: Não\n\n13 - CONDIÇÕES DE APRESENTAÇÃO\nPlataforma eletrónica utilizada pela entidade adjudicante: VORTAL\nURL para Apresentação: https://community.vortal.biz/public/\nAdmissibilidade da apresentação de propostas variantes: Não autorizado\nPrazo para apresentação das propostas: 07-01-2026 23:59\nPrazo durante o qual os concorrentes são obrigados a manter as respetivas propostas: 90 dias a contar do termo do prazo para a apresentação das propostas\nIndicação de Subcontratação na Proposta: Inexistência de indicação de subcontratação\n\n14 - PRESTAÇÃO DE CAUÇÃO\nPrestação de caução: Não\n\n15 - FORNECIMENTO DAS PEÇAS DO CONCURSO, APRESENTAÇÃO DE PEDIDOS DE PARTICIPAÇÃO E APRESENTAÇÃO DAS PROPOSTAS\nLink para acesso às peças do concurso (URL): https://community.vortal.biz/Public/public-tender-documents/Wnl3V2N5Q045NUd4eEhSdHkzWS9xSGptaVF3elNpOE4yRWdhczdpemMzN0RjT1p6M0pWRWZBRkxoSHZnS0ZTZ3pNZ01KeWNGVUgzRmRLTlh1cFN2L0E9PV9nXkl1\n\n20 - OUTROS REQUISITOS\nInformação sobre contratos reservados. Aplica-se a contratos reservados (54º-A)? Não\n\n21 - CRITÉRIO DE ADJUDICAÇÃO\nMultifator: Não\nMonofator:\nNome: Preço\n\n24 - CONDIÇÕES DO CONTRATO\nFaturação Eletrónica: Permitido\nObrigação de Subcontratação:\nCódigo da Obrigação de Subcontratação: Não é aplicável nenhuma obrigação de subcontratação.\n\n25 - COMPRA PÚBLICA ESTRATÉGICA\nCompra Pública Estratégica: Inexistência de contratação pública estratégica\n\n26 - INFORMAÇÕES ADICIONAIS\nContrato adequado para PME: Sim\nCobertura ACP (Acordo dos Contratos Públicos da Organização Mundial do Comércio): Não\n\n27 - IDENTIFICAÇÃO E CONTACTOS DO ÓRGÃO DE RECURSOS ADMINISTRATIVOS\nDesignação: Conselho Administrativo\nEndereço: Rua dos Bombeiros Voluntários\nCódigo postal: 2460-654\nLocalidade: Alcobaça\nTelefone: +351 262985090\nFax: +351 262985090\nEndereço eletrónico: diretor@aesmporto.pt\n\n28 - IDENTIFICAÇÃO DO(S) AUTOR(ES) DE ANÚNCIO\nNome: Luís Silva\nCargo: Diretor\n419943946",
    "nipc": "600079805",
    "distrito": "Leiria",
    "concelho": "Leiria",
    "freguesia": "Todas",
    "site": null,
    "email": "agrupamentosmp@aesmporto.pt",
    "designacao_contrato": "CP2AESMP_2026_FRUTA E LEGUMES",
    "descricao": "CP2AESMP_2026_FRUTA E LEGUMES",
    "preco_base": "18.814,72 EUR",
    "prazo_execucao": "365 DIAS",
    "prazo_apresentacao_propostas": "07-01-2026 23:59",
    "fundos_eu": "Não",
    "plataforma_eletronica": "VORTAL",
    "url_procedimento": "https://community.vortal.biz/public/",
    "autor_nome": "Luís Silva",
    "autor_cargo": "Diretor"
  },
  {
    "numero_procedimento": "N/A",
    "entidade": "AnÃºncio de procedimento  n.Âº 33648/2025  -  DiÃ¡rio da RepÃºblica n.Âº 251/2025, SÃ©rie II de 2025-12-31",
    "link": "https://diariodarepublica.pt/dr/detalhe/contrato-publico/33648-993078764"
  },
  {
    "numero_procedimento": "N/A",
    "entidade": "Fundação para a Ciência e a Tecnologia, IP",
    "link": "https://diariodarepublica.pt/dr/detalhe/contrato-publico/33651-993078765",
    "detalhes_completos": "1 - IDENTIFICAÇÃO E CONTACTOS DA ENTIDADE ADJUDICANTE\nDesignação da entidade adjudicante: Fundação para a Ciência e a Tecnologia, IP\nNIPC: 503904040\nServiço/Órgão/Pessoa de contacto: Rodrigo Godinho Santos\nEndereço: Avenida D. Carlos I, nº 126 - 1º andar\nCódigo postal: 1249-074\nLocalidade: Lisboa\nPaís: Portugal\nNUT III: PT170\nDistrito: Lisboa\nConcelho: Lisboa\nFreguesia: Todas\nTelefone: 213924333\nFax: 213924333\nEndereço da Entidade (URL): www.fct.pt\nEndereço Eletrónico: compras@fccn.pt\neDelivery Gateway (URL): https://www.acingov.pt\nFunção da Organização: Adquirente\nNorma jurídica da Entidade Adjudicante: Organismo de direito público\nÁrea de atividade da Autoridade Adjudicante: Serviços públicos das administrações públicas\n\n2 - JORNAL OFICIAL DA UNIÃO EUROPEIA\nO procedimento a que este anúncio diz respeito também é publicitado no Jornal Oficial da União Europeia? Não\n\n3 - AVISO\nModelo de Anúncio: Concurso público\nData de Envio do Anúncio: 30-12-2025\n\n5 - PROCESSO\nTipo de Procedimento: Concurso público\nPreço base do procedimento: Sim\nValor do preço base do procedimento: 144.000,00 EUR\nProcedimento com lotes? Não\n\n6 - OBJETO DO CONTRATO\nNúmero de referência interna: CP/17/2025\nDesignação do contrato: CONCURSO PÚBLICO Nº CP.2025.03.AS DE AQUISIÇÃO DE SERVIÇOS DE SEGUROS DE ACIDENTES PESSOAIS PARA OS BOLSEIROS DIRETAMENTE FINANCIADOS PELA FUNDAÇÃO PARA A CIÊNCIA E A TECNOLOGIA, I.P. PARA OS ANOS 2026, 2027 E 2028.\nDescrição: Aquisição de serviços de seguros de acidentes pessoais para os bolseiros diretamente financiados pela Fundação para a Ciência e a Tecnologia, I. P.\nTipo de Contrato Principal: Aquisição de Serviços\nTipo de Contrato: Aquisição de Serviços\nClassificação CPV (Vocabulário Comum para os Contratos Públicos)\nObjeto principal\nVocabulário Principal: 66512100\nPreço base s/IVA: 144.000,00 EUR\n\n7 - INDICAÇÕES ADICIONAIS\nO contrato envolve aquisição conjunta (satisfação de várias entidades)? Não\nO contrato é adjudicado por uma central de compras? Não\n\n8 - TÉCNICAS\nO concurso destina-se à celebração de um acordo-quadro? Inexistência de acordo-quadro\nÉ utilizado um leilão eletrónico? Não\nÉ adotada uma fase de negociação? Não\nSistema de Aquisição Dinâmico: Inexistência de sistema de aquisição dinâmico\n\n9 - LOCAL DA EXECUÇÃO DO CONTRATO\nLOCAL DA EXECUÇÃO DO CONTRATO (PROCEDIMENTO)\nPaís: Portugal\nNUT III: PT170\nLocalidade: Lisboa\nDistrito: Lisboa\nConcelho: Todos\nFreguesia: Todas\n\n10 - PRAZO DE EXECUÇÃO DO CONTRATO\nData de Início: 01-02-2026\nData de Fim: 31-01-2029\nPrevisão de renovações: Não\n\n11 - FUNDOS EU\nTêm fundos EU? Não\n\n12 - DOCUMENTOS DE HABILITAÇÃO\nHabilitação para o exercício da atividade profissional: Sim\nTipo: Outros\nDescrição - Outros: a.\nsejam empresas de seguros legalmente constituídas, de acordo com o Decreto-Lei n.º 94-B/98, de 17 de abril, na redação em vigor;\nb.\nestejam autorizadas a explorar os ramos e modalidades de seguro objeto do presente concurso;\nc.\nEstejam em condições de garantir a execução do contrato com recurso ao mediador de seguros a designar pela entidade adjudicante.\nDescrição: Documentos de Habilitação\n\n13 - CONDIÇÕES DE APRESENTAÇÃO\nPlataforma eletrónica utilizada pela entidade adjudicante: ACIN\nURL para Apresentação: https://www.acingov.pt\nAdmissibilidade da apresentação de propostas variantes: Não autorizado\nPrazo para apresentação das propostas: 06-01-2026 23:59\nPrazo durante o qual os concorrentes são obrigados a manter as respetivas propostas: 66 dias a contar do termo do prazo para a apresentação das propostas\nIndicação de Subcontratação na Proposta: Inexistência de indicação de subcontratação\n\n14 - PRESTAÇÃO DE CAUÇÃO\nPrestação de caução: Não\n\n15 - FORNECIMENTO DAS PEÇAS DO CONCURSO, APRESENTAÇÃO DE PEDIDOS DE PARTICIPAÇÃO E APRESENTAÇÃO DAS PROPOSTAS\nLink para acesso às peças do concurso (URL): https://www.acingov.pt/acingovprod/2/zonaPublica/zona_publica_c/donwloadProcedurePiece/OTk3ODk1\n\n20 - OUTROS REQUISITOS\nInformação sobre contratos reservados. Aplica-se a contratos reservados (54º-A)? Não\n\n21 - CRITÉRIO DE ADJUDICAÇÃO\nMultifator: Não\nMonofator:\nNome: Preço\n\n24 - CONDIÇÕES DO CONTRATO\nFaturação Eletrónica: Permitido\nObrigação de Subcontratação:\nCódigo da Obrigação de Subcontratação: Não é aplicável nenhuma obrigação de subcontratação.\n\n25 - COMPRA PÚBLICA ESTRATÉGICA\nCompra Pública Estratégica: Inexistência de contratação pública estratégica\n\n26 - INFORMAÇÕES ADICIONAIS\nContrato adequado para PME: Não\nCobertura ACP (Acordo dos Contratos Públicos da Organização Mundial do Comércio): Não\n\n27 - IDENTIFICAÇÃO E CONTACTOS DO ÓRGÃO DE RECURSOS ADMINISTRATIVOS\nDesignação: Vogal CD\nEndereço: Avenida D. Carlos I, 126\nCódigo postal: 1249-074\nLocalidade: Lisboa\nTelefone: 351213924300\nFax: \nEndereço eletrónico: ap@fct.pt\n\n28 - IDENTIFICAÇÃO DO(S) AUTOR(ES) DE ANÚNCIO\nNome: Paulo Trindade\nCargo: Tecnico Superior\n419943468",
    "nipc": "503904040",
    "distrito": "Lisboa",
    "concelho": "Lisboa",
    "freguesia": "Todas",
    "site": "www.fct.pt",
    "email": "compras@fccn.pt",
    "designacao_contrato": "CONCURSO PÚBLICO Nº CP.2025.03.AS DE AQUISIÇÃO DE SERVIÇOS DE SEGUROS DE ACIDENTES PESSOAIS PARA OS BOLSEIROS DIRETAMENTE FINANCIADOS PELA FUNDAÇÃO PARA A CIÊNCIA E A TECNOLOGIA, I.P. PARA OS ANOS 2026, 2027 E 2028.",
    "descricao": "Aquisição de serviços de seguros de acidentes pessoais para os bolseiros diretamente financiados pela Fundação para a Ciência e a Tecnologia, I. P.",
    "preco_base": "144.000,00 EUR",
    "prazo_execucao": null,
    "prazo_apresentacao_propostas": "06-01-2026 23:59",
    "fundos_eu": "Não",
    "plataforma_eletronica": "ACIN",
    "url_procedimento": "https://www.acingov.pt",
    "autor_nome": "Paulo Trindade",
    "autor_cargo": "Tecnico Superior"
  },
  {
    "numero_procedimento": "N/A",
    "entidade": "Unidade Local de Saúde de Santa Maria, EPE",
    "link": "https://diariodarepublica.pt/dr/detalhe/contrato-publico/33624-993270143",
    "detalhes_completos": "Alteração do Anúncio de procedimento n.º 33015/2025, de 2025-12-19, com o ID 419913287\n\n1 - IDENTIFICAÇÃO E CONTACTOS DA ENTIDADE ADJUDICANTE\nDesignação da entidade adjudicante: Unidade Local de Saúde de Santa Maria, EPE\nNIPC: 508481287\nEndereço: Avenida Prof. Egas Moniz\nCódigo postal: 1649-035\nLocalidade: Lisboa\nPaís: Portugal\nNUT III: PT170\nDistrito: Lisboa\nConcelho: Lisboa\nFreguesia: Freguesia de Alvalade - Lisboa\nTelefone: 217805330\nFax: 217805605\nEndereço da Entidade (URL): www.ulssm.min-saude.pt\nEndereço Eletrónico: compras@ulssm.min-saude.pt\neDelivery Gateway (URL): https://community.vortal.biz/public/\nFunção da Organização: Adquirente\nNorma jurídica da Entidade Adjudicante: Empresa pública\nÁrea de atividade da Autoridade Adjudicante: Saúde\n\n2 - JORNAL OFICIAL DA UNIÃO EUROPEIA\nO procedimento a que este anúncio diz respeito também é publicitado no Jornal Oficial da União Europeia? Não\n\n3 - AVISO\nModelo de Anúncio: Concurso público\nData de Envio do Anúncio: 30-12-2025\n\n5 - PROCESSO\nTipo de Procedimento: Concurso público\nPreço base do procedimento: Sim\nValor do preço base do procedimento: 47.564,00 EUR\nProcedimento com lotes? Sim\nNº Máx. de Lotes Autorizado: 2\nNúmero máximo de lotes que podem ser adjudicados a um concorrente: 2\n\n6 - OBJETO DO CONTRATO\nNúmero de referência interna: 262A000129\nDesignação do contrato: Aquisição de copos para medicamentos, ano 2026 e 2027\nDescrição: Aquisição de copos para medicamentos, ano 2026 e 2027\nTipo de Contrato Principal: Aquisição de Bens Móveis\nTipo de Contrato: Aquisição de Bens Móveis\nClassificação CPV (Vocabulário Comum para os Contratos Públicos)\nObjeto principal\nVocabulário Principal: 33140000\nPreço base s/IVA: 47.564,00 EUR\nLotes: \nNº: LOT-0001\nDescrição do Lote: Lote 1\nPreço base s/IVA: 44.000,00 EUR\nClassificação CPV (Vocabulário Comum para os Contratos Públicos)\nObjeto principal\nVocabulário Principal: 33140000\nNº: LOT-0002\nDescrição do Lote: Lote 2\nPreço base s/IVA: 3.564,00 EUR\nClassificação CPV (Vocabulário Comum para os Contratos Públicos)\nObjeto principal\nVocabulário Principal: 33140000\n\n7 - INDICAÇÕES ADICIONAIS\nO contrato envolve aquisição conjunta (satisfação de várias entidades)? Não\nO contrato é adjudicado por uma central de compras? Não\n\n8 - TÉCNICAS\nO concurso destina-se à celebração de um acordo-quadro? Inexistência de acordo-quadro\nÉ utilizado um leilão eletrónico? Não\nÉ adotada uma fase de negociação? Não\nSistema de Aquisição Dinâmico: Inexistência de sistema de aquisição dinâmico\n\n9 - LOCAL DA EXECUÇÃO DO CONTRATO\nLOCAL DA EXECUÇÃO DO CONTRATO (PROCEDIMENTO)\nPaís: Portugal\nNUT III: PT170\nLocalidade: Lisboa\nDistrito: Lisboa\nConcelho: Lisboa\nFreguesia: Freguesia de Alvalade - Lisboa\nLOCAL DA EXECUÇÃO DO CONTRATO (LOTE)\nIdentificador do Lote: LOT-0001; LOT-0002\nPaís: Portugal\nNUT III: PT170\nLocalidade: Lisboa\nDistrito: Lisboa\nConcelho: Lisboa\nFreguesia: Freguesia de Alvalade - Lisboa\n\n10 - PRAZO DE EXECUÇÃO DO CONTRATO\nIdentificador do Lote: LOT-0001; LOT-0002\nPrazo de execução do contrato: 24 MESES\nPrevisão de renovações: Não\n\n11 - FUNDOS EU\nIdentificador do Lote: LOT-0001; LOT-0002\nTêm fundos EU? Não\n\n12 - DOCUMENTOS DE HABILITAÇÃO\nHabilitação para o exercício da atividade profissional: Não\n\n13 - CONDIÇÕES DE APRESENTAÇÃO\nPlataforma eletrónica utilizada pela entidade adjudicante: VORTAL\nURL para Apresentação: https://community.vortal.biz/public/\nAdmissibilidade da apresentação de propostas variantes: Não autorizado\nPrazo para apresentação das propostas: 31-12-2025 17:00\nPrazo durante o qual os concorrentes são obrigados a manter as respetivas propostas: 180 dias a contar do termo do prazo para a apresentação das propostas\nApresentação de Catálogo Eletrónico: Permitido\nIndicação de Subcontratação na Proposta: Inexistência de indicação de subcontratação\n\n14 - PRESTAÇÃO DE CAUÇÃO\nPrestação de caução: Não\n\n15 - FORNECIMENTO DAS PEÇAS DO CONCURSO, APRESENTAÇÃO DE PEDIDOS DE PARTICIPAÇÃO E APRESENTAÇÃO DAS PROPOSTAS\nLink para acesso às peças do concurso (URL): https://community.vortal.biz/Public/public-tender-documents/M1JZaHFXWEVkZzZCV29pVmNxWmJLNGlSK1JWT2pzZFVqUU1zZEcxK2FINmR4TDY4dEFOWGNlSXg0OCtzeFZBWU9MVlBPa2s3cFppRTMzSHUzUlFUU0E9PWZMXmQr\n\n20 - OUTROS REQUISITOS\nIdentificador do Lote: LOT-0001; LOT-0002\nInformação sobre contratos reservados. Aplica-se a contratos reservados (54º-A)? Não\n\n21 - CRITÉRIO DE ADJUDICAÇÃO\nO Critério de adjudicação é diferenciado por lote? Não\nMultifator: Não\nMonofator:\nNome: Preço\n\n24 - CONDIÇÕES DO CONTRATO\nIdentificador do Lote: LOT-0001; LOT-0002\nFaturação Eletrónica: Permitido\nObrigação de Subcontratação:\nCódigo da Obrigação de Subcontratação: Não é aplicável nenhuma obrigação de subcontratação.\n\n25 - COMPRA PÚBLICA ESTRATÉGICA\nCompra Pública Estratégica: Inexistência de contratação pública estratégica\n\n26 - INFORMAÇÕES ADICIONAIS\nIdentificador do Lote: LOT-0001; LOT-0002\nContrato adequado para PME: Sim\nCobertura ACP (Acordo dos Contratos Públicos da Organização Mundial do Comércio): Não\n\n27 - IDENTIFICAÇÃO E CONTACTOS DO ÓRGÃO DE RECURSOS ADMINISTRATIVOS\nDesignação: Conselho de Administração\nEndereço: Av Professor Egas Moniz\nCódigo postal: 1649-035\nLocalidade: Lisboa\nTelefone: +351 217805330\nFax: +351 217803209\nEndereço eletrónico: secretariado.ca@ulssm.min-saude.pt\n\n28 - IDENTIFICAÇÃO DO(S) AUTOR(ES) DE ANÚNCIO\nNome: Marta Alves\nCargo: Assistente Tecnica\n\n29 - ALTERAÇÃO\nMotivo da Alteração: Correção pelo adquirente\nIdentificador da Versão do Anúncio a Alterar: b3da482f-0a04-4c46-b4b4-6fa76302c495-01\nIdentificador das Secções Alteradas do Anúncio Anterior: Condições de Apresentação\nAlteração dos Documentos do Concurso: Sim\nData de alteração dos documentos do concurso: 30-12-2025\n419943743",
    "nipc": "508481287",
    "distrito": "Lisboa",
    "concelho": "Lisboa",
    "freguesia": "Freguesia de Alvalade - Lisboa",
    "site": "www.ulssm.min-saude.pt",
    "email": "compras@ulssm.min-saude.pt",
    "designacao_contrato": "Aquisição de copos para medicamentos, ano 2026 e 2027",
    "descricao": "Aquisição de copos para medicamentos, ano 2026 e 2027",
    "preco_base": "47.564,00 EUR",
    "prazo_execucao": "24 MESES",
    "prazo_apresentacao_propostas": "31-12-2025 17:00",
    "fundos_eu": "Não",
    "plataforma_eletronica": "VORTAL",
    "url_procedimento": "https://community.vortal.biz/public/",
    "autor_nome": "Marta Alves",
    "autor_cargo": "Assistente Tecnica"
  },
  {
    "numero_procedimento": "N/A",
    "entidade": "ViniPortugal - Associação Interprofissional do Vinho",
    "link": "https://diariodarepublica.pt/dr/detalhe/contrato-publico/33625-993270144",
    "detalhes_completos": "1 - IDENTIFICAÇÃO E CONTACTOS DA ENTIDADE ADJUDICANTE\nDesignação da entidade adjudicante: ViniPortugal - Associação Interprofissional do Vinho\nNIPC: 503736864\nEndereço: Rua Mouzinho da Silveira, 5 \nCódigo postal: 2560-312\nLocalidade: Lisboa\nPaís: Portugal\nNUT III: PT16B\nDistrito: Lisboa\nConcelho: Torres Vedras\nFreguesia: Todas\nTelefone: 213569890\nFax: 213569895\nEndereço da Entidade (URL): https://viniportugal.pt/pt/\nEndereço Eletrónico: geral@viniportugal.pt\neDelivery Gateway (URL): https://community.vortal.biz/public/\nFunção da Organização: Adquirente\nNorma jurídica da Entidade Adjudicante: Organismo de direito público\nÁrea de atividade da Autoridade Adjudicante: Educação\n\n2 - JORNAL OFICIAL DA UNIÃO EUROPEIA\nO procedimento a que este anúncio diz respeito também é publicitado no Jornal Oficial da União Europeia? Não\n\n3 - AVISO\nModelo de Anúncio: Concurso público\nData de Envio do Anúncio: 30-12-2025\n\n5 - PROCESSO\nTipo de Procedimento: Concurso público\nPreço base do procedimento: Sim\nValor do preço base do procedimento: 23.000,00 EUR\nProcedimento com lotes? Não\n\n6 - OBJETO DO CONTRATO\nNúmero de referência interna: 2025.55\nDesignação do contrato: Prestação de Serviços de Gestão da área reservada da plataforma da ViniPortugal, ano 2026\nDescrição: Prestação de Serviços de Gestão da área reservada da plataforma da ViniPortugal, ano 2026\nTipo de Contrato Principal: Aquisição de Serviços\nTipo de Contrato: Aquisição de Serviços\nClassificação CPV (Vocabulário Comum para os Contratos Públicos)\nObjeto principal\nVocabulário Principal: 79342200\nPreço base s/IVA: 23.000,00 EUR\n\n7 - INDICAÇÕES ADICIONAIS\nO contrato envolve aquisição conjunta (satisfação de várias entidades)? Não\nO contrato é adjudicado por uma central de compras? Não\n\n8 - TÉCNICAS\nO concurso destina-se à celebração de um acordo-quadro? Inexistência de acordo-quadro\nÉ utilizado um leilão eletrónico? Não\nÉ adotada uma fase de negociação? Não\nSistema de Aquisição Dinâmico: Inexistência de sistema de aquisição dinâmico\n\n9 - LOCAL DA EXECUÇÃO DO CONTRATO\nLOCAL DA EXECUÇÃO DO CONTRATO (PROCEDIMENTO)\nPaís: Portugal\nNUT III: PT170\nLocalidade: Lisboa\nDistrito: Lisboa\nConcelho: Lisboa\nFreguesia: Todas\n\n10 - PRAZO DE EXECUÇÃO DO CONTRATO\nPrazo de execução do contrato: 1 ANOS\nPrevisão de renovações: Não\n\n11 - FUNDOS EU\nTêm fundos EU? Não\n\n12 - DOCUMENTOS DE HABILITAÇÃO\nHabilitação para o exercício da atividade profissional: Não\n\n13 - CONDIÇÕES DE APRESENTAÇÃO\nPlataforma eletrónica utilizada pela entidade adjudicante: VORTAL\nURL para Apresentação: https://community.vortal.biz/public/\nAdmissibilidade da apresentação de propostas variantes: Não autorizado\nPrazo para apresentação das propostas: 07-01-2026 17:00\nPrazo durante o qual os concorrentes são obrigados a manter as respetivas propostas: 180 dias a contar do termo do prazo para a apresentação das propostas\nIndicação de Subcontratação na Proposta: Inexistência de indicação de subcontratação\n\n14 - PRESTAÇÃO DE CAUÇÃO\nPrestação de caução: Não\n\n15 - FORNECIMENTO DAS PEÇAS DO CONCURSO, APRESENTAÇÃO DE PEDIDOS DE PARTICIPAÇÃO E APRESENTAÇÃO DAS PROPOSTAS\nLink para acesso às peças do concurso (URL): https://community.vortal.biz/Public/public-tender-documents/UncxQS9KZ01SYkFaZUZGYk5yVUd0WFY3aS9sa1NQV0ZvMEJHNnEvam9ZdnRMYVc5ZGhERXYyWEpjQWNWZ2FDRHVHTll6bktzZVlqTkJXY2hoVTVYSmc9PUdPKm0m\n\n20 - OUTROS REQUISITOS\nInformação sobre contratos reservados. Aplica-se a contratos reservados (54º-A)? Não\n\n21 - CRITÉRIO DE ADJUDICAÇÃO\nMultifator: Sim\nFator: \nNome: Preço\nPonderação: 40%\nSubfatores: Não\nFator: \nNome: Qualidade\nPonderação: 60%\nSubfatores: Sim\nSubfatores: \nNome: Qualidade Técnica\nPonderação : 100%; \n\n24 - CONDIÇÕES DO CONTRATO\nFaturação Eletrónica: Permitido\nObrigação de Subcontratação:\nCódigo da Obrigação de Subcontratação: Não é aplicável nenhuma obrigação de subcontratação.\n\n25 - COMPRA PÚBLICA ESTRATÉGICA\nCompra Pública Estratégica: Inexistência de contratação pública estratégica\n\n26 - INFORMAÇÕES ADICIONAIS\nContrato adequado para PME: Sim\nCobertura ACP (Acordo dos Contratos Públicos da Organização Mundial do Comércio): Não\n\n27 - IDENTIFICAÇÃO E CONTACTOS DO ÓRGÃO DE RECURSOS ADMINISTRATIVOS\nDesignação: Pedro Fernandes\nEndereço: Rua Mouzinho da Silveira, n.º5\nCódigo postal: 1250-165\nLocalidade: Lisboa\nTelefone: +351 213569890\nFax: +351 213569890\nEndereço eletrónico: processo-concursal@viniportugal.pt\n\n28 - IDENTIFICAÇÃO DO(S) AUTOR(ES) DE ANÚNCIO\nNome: Pedro Fernandes\nCargo: Director Financeiro\n419943638",
    "nipc": "503736864",
    "distrito": "Lisboa",
    "concelho": "Torres Vedras",
    "freguesia": "Todas",
    "site": "https://viniportugal.pt/pt/",
    "email": "geral@viniportugal.pt",
    "designacao_contrato": "Prestação de Serviços de Gestão da área reservada da plataforma da ViniPortugal, ano 2026",
    "descricao": "Prestação de Serviços de Gestão da área reservada da plataforma da ViniPortugal, ano 2026",
    "preco_base": "23.000,00 EUR",
    "prazo_execucao": "1 ANOS",
    "prazo_apresentacao_propostas": "07-01-2026 17:00",
    "fundos_eu": "Não",
    "plataforma_eletronica": "VORTAL",
    "url_procedimento": "https://community.vortal.biz/public/",
    "autor_nome": "Pedro Fernandes",
    "autor_cargo": "Director Financeiro"
  },
  {
    "numero_procedimento": "N/A",
    "entidade": "Infraestruturas de Portugal, SA",
    "link": "https://diariodarepublica.pt/dr/detalhe/contrato-publico/33626-993270145",
    "detalhes_completos": "Alteração do Anúncio de procedimento n.º 33269/2025, de 2025-12-23, com o ID 419923096\n\n1 - IDENTIFICAÇÃO E CONTACTOS DA ENTIDADE ADJUDICANTE\nDesignação da entidade adjudicante: Infraestruturas de Portugal, SA\nNIPC: 503933813\nServiço/Órgão/Pessoa de contacto: Direção de Compras e Logística - Departamento de Compras - Edifício 2\nEndereço: Praça da Portagem\nCódigo postal: 2809-013\nLocalidade: Almada\nPaís: Portugal\nNUT III: PT170\nDistrito: Setúbal\nConcelho: Almada\nFreguesia: União das Freguesias de Almada, Cova da Piedade, Pragal e Cacilhas\nTelefone:  212 879 300 \nFax: 21 287 90 00\nEndereço da Entidade (URL): www.infraestruturasdeportugal.pt\nEndereço Eletrónico: dcl@infraestruturasdeportugal.pt\nFunção da Organização: Adquirente\nNorma jurídica da Entidade Adjudicante: Organismo de direito público\nÁrea de atividade da Entidade Adjudicante: Serviços ferroviários\n\n2 - JORNAL OFICIAL DA UNIÃO EUROPEIA\nO procedimento a que este anúncio diz respeito também é publicitado no Jornal Oficial da União Europeia? Não\n\n3 - AVISO\nModelo de Anúncio: Concurso público\nData de Envio do Anúncio: 30-12-2025\n\n5 - PROCESSO\nTipo de Procedimento: Concurso público\nPreço base do procedimento: Sim\nValor do preço base do procedimento: 120.000,00 EUR\nProcedimento com lotes? Não\n\n6 - OBJETO DO CONTRATO\nNúmero de referência interna: 10021763\nDesignação do contrato: Aquisição de serviços - EN230 - PONTE SOBRE A RIBEIRA DE CORTES (KM190+884) - REABILITAÇÃO E ALARGAMENTO\nDescrição: Aquisição de serviços - EN230 - PONTE SOBRE A RIBEIRA DE CORTES (KM190+884) - REABILITAÇÃO E ALARGAMENTO\nTipo de Contrato Principal: Aquisição de Serviços\nTipo de Contrato: Aquisição de Serviços\nClassificação CPV (Vocabulário Comum para os Contratos Públicos)\nObjeto principal\nVocabulário Principal: 71322300\nPreço base s/IVA: 120.000,00 EUR\n\n7 - INDICAÇÕES ADICIONAIS\nO contrato envolve aquisição conjunta (satisfação de várias entidades)? Não\nO contrato é adjudicado por uma central de compras? Não\n\n8 - TÉCNICAS\nO concurso destina-se à celebração de um acordo-quadro? Inexistência de acordo-quadro\nÉ utilizado um leilão eletrónico? Não\nÉ adotada uma fase de negociação? Não\nSistema de Aquisição Dinâmico: Inexistência de sistema de aquisição dinâmico\n\n9 - LOCAL DA EXECUÇÃO DO CONTRATO\nLOCAL DA EXECUÇÃO DO CONTRATO (PROCEDIMENTO)\nPaís: Portugal\nNUT III: PT16J\nLocalidade: Cortes do Meio\nDistrito: Castelo Branco\nConcelho: Covilhã\nFreguesia: Freguesia de Cortes do Meio\n\n10 - PRAZO DE EXECUÇÃO DO CONTRATO\nPrazo de execução do contrato: 481 DIAS\nPrevisão de renovações: Não\n\n11 - FUNDOS EU\nTêm fundos EU? Não\n\n12 - DOCUMENTOS DE HABILITAÇÃO\nHabilitação para o exercício da atividade profissional: Sim\nTipo: Ordem Profissional\nDescrição: Em conformidade com o exigido na Lei n.º 31/2009, de 3 de julho, atualizada pela Lei n.º 40/2015, de 1 de junho,\n\n13 - CONDIÇÕES DE APRESENTAÇÃO\nPlataforma eletrónica utilizada pela entidade adjudicante: ANOGOV\nURL para Apresentação: https://www.anogov.com/infraestruturasdeportugal-ip/faces/\nAdmissibilidade da apresentação de propostas variantes: Não autorizado\nPrazo para apresentação das propostas: 21-01-2026 17:00\nPrazo durante o qual os concorrentes são obrigados a manter as respetivas propostas: 120 dias a contar do termo do prazo para a apresentação das propostas\nApresentação de Catálogo Eletrónico: Não autorizado\nIndicação de Subcontratação na Proposta: Inexistência de indicação de subcontratação\n\n14 - PRESTAÇÃO DE CAUÇÃO\nPrestação de caução: Não\n\n15 - FORNECIMENTO DAS PEÇAS DO CONCURSO, APRESENTAÇÃO DE PEDIDOS DE PARTICIPAÇÃO E APRESENTAÇÃO DAS PROPOSTAS\nLink para acesso às peças do concurso (URL): https://www.anogov.com/infraestruturasdeportugal-ip/faces/app/acessoDocs.jsp?codigoAcesso=iYBsYkkH7t5oQpzQhk8seWBLBXkXeHe3CAC4xXYv7popWPtlsA\n\n20 - OUTROS REQUISITOS\nInformação sobre contratos reservados. Aplica-se a contratos reservados (54º-A)? Não\n\n21 - CRITÉRIO DE ADJUDICAÇÃO\nMultifator: Sim\nFator: \nNome: Qualidade\nPonderação: 25%\nSubfatores: Não\nFator: \nNome: Outros\nOutro Nome: Valorização do Técnico\nPonderação: 25%\nSubfatores: Não\nFator: \nNome: Preço\nPonderação: 50%\nSubfatores: Não\n\n24 - CONDIÇÕES DO CONTRATO\nFaturação Eletrónica: Permitido\nObrigação de Subcontratação:\nCódigo da Obrigação de Subcontratação: Não é aplicável nenhuma obrigação de subcontratação.\n\n25 - COMPRA PÚBLICA ESTRATÉGICA\nCompra Pública Estratégica: Inexistência de contratação pública estratégica\n\n26 - INFORMAÇÕES ADICIONAIS\nContrato adequado para PME: Sim\nCobertura ACP (Acordo dos Contratos Públicos da Organização Mundial do Comércio): Não\n\n27 - IDENTIFICAÇÃO E CONTACTOS DO ÓRGÃO DE RECURSOS ADMINISTRATIVOS\nDesignação: Conselho de Administração da Infraestruturas de Portugal, S.A.\nEndereço: Praça da Portagem\nCódigo postal: 2809-013\nLocalidade: Almada\nEndereço eletrónico: contratos@infraestruturasdeportugal.pt\n\n28 - IDENTIFICAÇÃO DO(S) AUTOR(ES) DE ANÚNCIO\nNome: Margarida Veloso\nCargo: Diretora Adjunta de Compras e Logística (em acumulação Dir. Departamento de Compras)\n\n29 - ALTERAÇÃO\nMotivo da Alteração: Correção pelo adquirente\nIdentificador da Versão do Anúncio a Alterar: 6e1b454a-ebe6-4afa-8d0e-f3da3c4225b2-01\nIdentificador das Secções Alteradas do Anúncio Anterior: Prazo de execução do contrato\nDescrição das Alterações: Prazo de execução do contrato: 240 DIAS\nAlteração dos Documentos do Concurso: Não\n419941297",
    "nipc": "503933813",
    "distrito": "Setúbal",
    "concelho": "Almada",
    "freguesia": "União das Freguesias de Almada, Cova da Piedade, Pragal e Cacilhas",
    "site": "www.infraestruturasdeportugal.pt",
    "email": "dcl@infraestruturasdeportugal.pt",
    "designacao_contrato": "Aquisição de serviços - EN230 - PONTE SOBRE A RIBEIRA DE CORTES (KM190+884) - REABILITAÇÃO E ALARGAMENTO",
    "descricao": "Aquisição de serviços - EN230 - PONTE SOBRE A RIBEIRA DE CORTES (KM190+884) - REABILITAÇÃO E ALARGAMENTO",
    "preco_base": "120.000,00 EUR",
    "prazo_execucao": "481 DIAS",
    "prazo_apresentacao_propostas": "21-01-2026 17:00",
    "fundos_eu": "Não",
    "plataforma_eletronica": "ANOGOV",
    "url_procedimento": "https://www.anogov.com/infraestruturasdeportugal-ip/faces/",
    "autor_nome": "Margarida Veloso",
    "autor_cargo": "Diretora Adjunta de Compras e Logística (em acumulação Dir. Departamento de Compras)"
  },
  {
    "numero_procedimento": "N/A",
    "entidade": "AnÃºncio de procedimento  n.Âº 33628/2025  -  DiÃ¡rio da RepÃºblica n.Âº 251/2025, SÃ©rie II de 2025-12-31",
    "link": "https://diariodarepublica.pt/dr/detalhe/contrato-publico/33628-993270146"
  },
  {
    "numero_procedimento": "N/A",
    "entidade": "Instituto de Informática, IP",
    "link": "https://diariodarepublica.pt/dr/detalhe/contrato-publico/33629-993270147",
    "detalhes_completos": "1 - IDENTIFICAÇÃO E CONTACTOS DA ENTIDADE ADJUDICANTE\nDesignação da entidade adjudicante: Instituto de Informática, IP\nNIPC: 504322915\nServiço/Órgão/Pessoa de contacto: Área de Contratação Pública\nEndereço: Avenida Professor Dr. Cavaco Silva, n.º 17, Edifício Ciência I\nCódigo postal: 2740-120\nLocalidade: Porto Salvo\nPaís: Portugal\nNUT III: PT170\nDistrito: Lisboa\nConcelho: Oeiras\nFreguesia: Freguesia de Porto Salvo\nTelefone: 214230000\nFax: 214230000\nEndereço da Entidade (URL): http://www.seg-social.pt\nEndereço Eletrónico: ii-contratacao@seg-social.pt\neDelivery Gateway (URL): https://www.acingov.pt\nFunção da Organização: Adquirente\nNorma jurídica da Entidade Adjudicante: Organismo de direito público\nÁrea de atividade da Autoridade Adjudicante: Proteção social\n\n2 - JORNAL OFICIAL DA UNIÃO EUROPEIA\nO procedimento a que este anúncio diz respeito também é publicitado no Jornal Oficial da União Europeia? Não\n\n3 - AVISO\nModelo de Anúncio: Concurso público\nData de Envio do Anúncio: 30-12-2025\n\n5 - PROCESSO\nTipo de Procedimento: Concurso público\nPreço base do procedimento: Sim\nValor do preço base do procedimento: 14.000,00 EUR\nProcedimento com lotes? Sim\nNº Máx. de Lotes Autorizado: 2\nNúmero máximo de lotes que podem ser adjudicados a um concorrente: 2\n\n6 - OBJETO DO CONTRATO\nNúmero de referência interna: 2325000264\nDesignação do contrato: 2325000264 - TD-AP-C17-I03, Transição Digital na Segurança Social - Aquisição de servidores para Cluster Tier0\nDescrição: 2325000264 - TD-AP-C17-I03, Transição Digital na Segurança Social - Aquisição de servidores para Cluster Tier0\nTipo de Contrato Principal: Aquisição de Bens Móveis\nTipo de Contrato: Aquisição de Bens Móveis\nClassificação CPV (Vocabulário Comum para os Contratos Públicos)\nObjeto principal\nVocabulário Principal: 48810000\nPreço base s/IVA: 14.000,00 EUR\nLotes: \nNº: LOT-0001\nDescrição do Lote: servidor rackmount para o CPD Principal\nPreço base s/IVA: 7.500,00 EUR\nClassificação CPV (Vocabulário Comum para os Contratos Públicos)\nObjeto principal\nVocabulário Principal: 48810000\nNº: LOT-0002\nDescrição do Lote: servidor rackmount para o CPD Alternativo\nPreço base s/IVA: 6.500,00 EUR\nClassificação CPV (Vocabulário Comum para os Contratos Públicos)\nObjeto principal\nVocabulário Principal: 48810000\n\n7 - INDICAÇÕES ADICIONAIS\nO contrato envolve aquisição conjunta (satisfação de várias entidades)? Não\nO contrato é adjudicado por uma central de compras? Não\n\n8 - TÉCNICAS\nO concurso destina-se à celebração de um acordo-quadro? Inexistência de acordo-quadro\nÉ utilizado um leilão eletrónico? Não\nÉ adotada uma fase de negociação? Não\nSistema de Aquisição Dinâmico: Inexistência de sistema de aquisição dinâmico\n\n9 - LOCAL DA EXECUÇÃO DO CONTRATO\nLOCAL DA EXECUÇÃO DO CONTRATO (PROCEDIMENTO)\nPaís: Portugal\nNUT III: PT170\nLocalidade: Todas\nDistrito: Lisboa\nConcelho: Loures\nFreguesia: Todas\nPaís: Portugal\nNUT III: PT16G\nLocalidade: Todas\nDistrito: Viseu\nConcelho: Viseu\nFreguesia: Todas\nLOCAL DA EXECUÇÃO DO CONTRATO (LOTE)\nIdentificador do Lote: LOT-0001\nPaís: Portugal\nNUT III: PT170\nLocalidade: Todas\nDistrito: Lisboa\nConcelho: Loures\nFreguesia: Todas\nIdentificador do Lote: LOT-0002\nPaís: Portugal\nNUT III: PT16G\nLocalidade: Todas\nDistrito: Viseu\nConcelho: Viseu\nFreguesia: Todas\n\n10 - PRAZO DE EXECUÇÃO DO CONTRATO\nIdentificador do Lote: LOT-0001; LOT-0002\nPrazo de execução do contrato: 45 DIAS\nPrevisão de renovações: Não\n\n11 - FUNDOS EU\nIdentificador do Lote: LOT-0001; LOT-0002\nTêm fundos EU? Sim\n\n12 - DOCUMENTOS DE HABILITAÇÃO\nHabilitação para o exercício da atividade profissional: Não\n\n13 - CONDIÇÕES DE APRESENTAÇÃO\nPlataforma eletrónica utilizada pela entidade adjudicante: ACIN\nURL para Apresentação: https://www.acingov.pt\nAdmissibilidade da apresentação de propostas variantes: Não autorizado\nPrazo para apresentação das propostas: 08-01-2026 23:59\nPrazo durante o qual os concorrentes são obrigados a manter as respetivas propostas: 66 dias a contar do termo do prazo para a apresentação das propostas\nIndicação de Subcontratação na Proposta: Inexistência de indicação de subcontratação\n\n14 - PRESTAÇÃO DE CAUÇÃO\nPrestação de caução: Não\n\n15 - FORNECIMENTO DAS PEÇAS DO CONCURSO, APRESENTAÇÃO DE PEDIDOS DE PARTICIPAÇÃO E APRESENTAÇÃO DAS PROPOSTAS\nLink para acesso às peças do concurso (URL): https://www.acingov.pt/acingovprod/2/zonaPublica/zona_publica_c/donwloadProcedurePiece/MTAxMDE3Mg==\n\n20 - OUTROS REQUISITOS\nIdentificador do Lote: LOT-0001; LOT-0002\nInformação sobre contratos reservados. Aplica-se a contratos reservados (54º-A)? Não\n\n21 - CRITÉRIO DE ADJUDICAÇÃO\nO Critério de adjudicação é diferenciado por lote? Não\nMultifator: Sim\nFator: \nNome: Preço\nPonderação: 60%\nSubfatores: Não\nFator: \nNome: Outros\nOutro Nome: Mérito técnico\nPonderação: 40%\nSubfatores: Não\n\n24 - CONDIÇÕES DO CONTRATO\nIdentificador do Lote: LOT-0001; LOT-0002\nFaturação Eletrónica: Necessário\nObrigação de Subcontratação:\nCódigo da Obrigação de Subcontratação: Não é aplicável nenhuma obrigação de subcontratação.\n\n25 - COMPRA PÚBLICA ESTRATÉGICA\nCompra Pública Estratégica: Inexistência de contratação pública estratégica\n\n26 - INFORMAÇÕES ADICIONAIS\nIdentificador do Lote: LOT-0001; LOT-0002\nContrato adequado para PME: Sim\nCobertura ACP (Acordo dos Contratos Públicos da Organização Mundial do Comércio): Não\n\n27 - IDENTIFICAÇÃO E CONTACTOS DO ÓRGÃO DE RECURSOS ADMINISTRATIVOS\nDesignação: Conselho Diretivo\nEndereço: Avenida Professor Dr. Cavaco Silva, n.º 17, Edifício Ciência I\nCódigo postal: 2740-120\nLocalidade: Porto Salvo\nTelefone: 214230000\nFax: \nEndereço eletrónico: ii-contratacao@seg-social.pt\nPrazo de interposição do recurso: 5 dias\n\n28 - IDENTIFICAÇÃO DO(S) AUTOR(ES) DE ANÚNCIO\nNome: Helga Patricia Fino da Silva Beirão Paulo\nCargo: Diretora do Departamento de Organização e Gestão de Pessoas\n419943232",
    "nipc": "504322915",
    "distrito": "Lisboa",
    "concelho": "Oeiras",
    "freguesia": "Freguesia de Porto Salvo",
    "site": "http://www.seg-social.pt",
    "email": "ii-contratacao@seg-social.pt",
    "designacao_contrato": "2325000264 - TD-AP-C17-I03, Transição Digital na Segurança Social - Aquisição de servidores para Cluster Tier0",
    "descricao": "2325000264 - TD-AP-C17-I03, Transição Digital na Segurança Social - Aquisição de servidores para Cluster Tier0",
    "preco_base": "14.000,00 EUR",
    "prazo_execucao": "45 DIAS",
    "prazo_apresentacao_propostas": "08-01-2026 23:59",
    "fundos_eu": "Sim",
    "plataforma_eletronica": "ACIN",
    "url_procedimento": "https://www.acingov.pt",
    "autor_nome": "Helga Patricia Fino da Silva Beirão Paulo",
    "autor_cargo": "Diretora do Departamento de Organização e Gestão de Pessoas"
  },
  {
    "numero_procedimento": "N/A",
    "entidade": "Estado-Maior-General das Forças Armadas (EMGFA)",
    "link": "https://diariodarepublica.pt/dr/detalhe/contrato-publico/33633-993270148",
    "detalhes_completos": "1 - IDENTIFICAÇÃO E CONTACTOS DA ENTIDADE ADJUDICANTE\nDesignação da entidade adjudicante: Estado-Maior-General das Forças Armadas (EMGFA)\nNIPC: 600010180\nServiço/Órgão/Pessoa de contacto: Secção de Aquisições\nEndereço: Hospital Forças Armadas Pólo do Porto - Avenida da Boavista S/N\nCódigo postal: 4050-113\nLocalidade: Porto\nPaís: Portugal\nNUT III: PT11A\nDistrito: Porto\nConcelho: Porto\nFreguesia: União das Freguesias de Cedofeita, Santo Ildefonso, Sé, Miragaia, São Nicolau e Vitória\nTelefone: 226087927\nFax: 000000\nEndereço da Entidade (URL): https://www.hfar.pt/\nEndereço Eletrónico: hfar_pp_logistica@hfar.pt\neDelivery Gateway (URL): https://www.acingov.pt\nFunção da Organização: Adquirente\nNorma jurídica da Entidade Adjudicante: Organismo de direito público\nÁrea de atividade da Entidade Adjudicante: Atividades aeroportuárias\n\n2 - JORNAL OFICIAL DA UNIÃO EUROPEIA\nO procedimento a que este anúncio diz respeito também é publicitado no Jornal Oficial da União Europeia? Não\n\n3 - AVISO\nModelo de Anúncio: Concurso público\nData de Envio do Anúncio: 30-12-2025\n\n5 - PROCESSO\nTipo de Procedimento: Concurso público\nPreço base do procedimento: Sim\nValor do preço base do procedimento: 23.900,00 EUR\nProcedimento com lotes? Não\n\n6 - OBJETO DO CONTRATO\nNúmero de referência interna: CP PRR HFAR-PP 2025009786\nDesignação do contrato: 2025009786  Aquisição de Central de Monitorização e Monitores de Telemetria Portáteis para Hospital das Forças Armadas  Polo do Porto Aviso PRR N.º 06/C01 i04/2025\nDescrição: 2025009786  Aquisição de Central de Monitorização e Monitores de Telemetria Portáteis para Hospital das Forças Armadas  Polo do Porto Aviso PRR N.º 06/C01 i04/2025 \nTipo de Contrato Principal: Aquisição de Bens Móveis\nTipo de Contrato: Aquisição de Bens Móveis\nClassificação CPV (Vocabulário Comum para os Contratos Públicos)\nObjeto principal\nVocabulário Principal: 33195000\nPreço base s/IVA: 23.900,00 EUR\n\n7 - INDICAÇÕES ADICIONAIS\nO contrato envolve aquisição conjunta (satisfação de várias entidades)? Não\nO contrato é adjudicado por uma central de compras? Não\n\n8 - TÉCNICAS\nO concurso destina-se à celebração de um acordo-quadro? Inexistência de acordo-quadro\nÉ utilizado um leilão eletrónico? Não\nÉ adotada uma fase de negociação? Não\nSistema de Aquisição Dinâmico: Inexistência de sistema de aquisição dinâmico\n\n9 - LOCAL DA EXECUÇÃO DO CONTRATO\nLOCAL DA EXECUÇÃO DO CONTRATO (PROCEDIMENTO)\nPaís: Portugal\nNUT III: PT11A\nLocalidade: União das Freguesias de Cedofeita, Santo Ildefonso, Sé, Miragaia, São Nicolau e Vitória\nDistrito: Porto\nConcelho: Porto\nFreguesia: União das Freguesias de Cedofeita, Santo Ildefonso, Sé, Miragaia, São Nicolau e Vitória\n\n10 - PRAZO DE EXECUÇÃO DO CONTRATO\nPrazo de execução do contrato: 60 DIAS\nPrevisão de renovações: Não\n\n11 - FUNDOS EU\nTêm fundos EU? Não\n\n12 - DOCUMENTOS DE HABILITAÇÃO\nHabilitação para o exercício da atividade profissional: Não\n\n13 - CONDIÇÕES DE APRESENTAÇÃO\nPlataforma eletrónica utilizada pela entidade adjudicante: ACIN\nURL para Apresentação: https://www.acingov.pt\nAdmissibilidade da apresentação de propostas variantes: Não autorizado\nPrazo para apresentação das propostas: 19-01-2026 23:59\nPrazo durante o qual os concorrentes são obrigados a manter as respetivas propostas: 210 dias a contar do termo do prazo para a apresentação das propostas\nIndicação de Subcontratação na Proposta: Inexistência de indicação de subcontratação\n\n14 - PRESTAÇÃO DE CAUÇÃO\nPrestação de caução: Não\n\n15 - FORNECIMENTO DAS PEÇAS DO CONCURSO, APRESENTAÇÃO DE PEDIDOS DE PARTICIPAÇÃO E APRESENTAÇÃO DAS PROPOSTAS\nLink para acesso às peças do concurso (URL): https://www.acingov.pt/acingovprod/2/zonaPublica/zona_publica_c/donwloadProcedurePiece/MTAwOTQwOA==\n\n20 - OUTROS REQUISITOS\nInformação sobre contratos reservados. Aplica-se a contratos reservados (54º-A)? Não\n\n21 - CRITÉRIO DE ADJUDICAÇÃO\nMultifator: Não\nMonofator:\nNome: Preço\n\n24 - CONDIÇÕES DO CONTRATO\nFaturação Eletrónica: Permitido\nObrigação de Subcontratação:\nCódigo da Obrigação de Subcontratação: Não é aplicável nenhuma obrigação de subcontratação.\n\n25 - COMPRA PÚBLICA ESTRATÉGICA\nCompra Pública Estratégica: Inexistência de contratação pública estratégica\n\n26 - INFORMAÇÕES ADICIONAIS\nContrato adequado para PME: Não\nCobertura ACP (Acordo dos Contratos Públicos da Organização Mundial do Comércio): Não\n\n27 - IDENTIFICAÇÃO E CONTACTOS DO ÓRGÃO DE RECURSOS ADMINISTRATIVOS\nDesignação: Tribunal Administrativo de Círculo de Lisboa\nEndereço: Av D. João II, Bloco G, piso 6-8, nº 1.08.01, 1990-097 Lisboa\nCódigo postal: 1990-097\nLocalidade: Lisboa\nTelefone: 218367100\nFax: 999999999\nEndereço eletrónico: lisboa.tacl@tribunais.org.pt\n\n28 - IDENTIFICAÇÃO DO(S) AUTOR(ES) DE ANÚNCIO\nNome: José Carlos Candeias Pinheiro Monge\nCargo: Diretor do HFAR\n419941986",
    "nipc": "600010180",
    "distrito": "Porto",
    "concelho": "Porto",
    "freguesia": "União das Freguesias de Cedofeita, Santo Ildefonso, Sé, Miragaia, São Nicolau e Vitória",
    "site": "https://www.hfar.pt/",
    "email": "hfar_pp_logistica@hfar.pt",
    "designacao_contrato": "2025009786  Aquisição de Central de Monitorização e Monitores de Telemetria Portáteis para Hospital das Forças Armadas  Polo do Porto Aviso PRR N.º 06/C01 i04/2025",
    "descricao": "2025009786  Aquisição de Central de Monitorização e Monitores de Telemetria Portáteis para Hospital das Forças Armadas  Polo do Porto Aviso PRR N.º 06/C01 i04/2025",
    "preco_base": "23.900,00 EUR",
    "prazo_execucao": "60 DIAS",
    "prazo_apresentacao_propostas": "19-01-2026 23:59",
    "fundos_eu": "Não",
    "plataforma_eletronica": "ACIN",
    "url_procedimento": "https://www.acingov.pt",
    "autor_nome": "José Carlos Candeias Pinheiro Monge",
    "autor_cargo": "Diretor do HFAR"
  },
  {
    "numero_procedimento": "N/A",
    "entidade": "Estado-Maior-General das Forças Armadas (EMGFA)",
    "link": "https://diariodarepublica.pt/dr/detalhe/contrato-publico/33634-993270149",
    "detalhes_completos": "1 - IDENTIFICAÇÃO E CONTACTOS DA ENTIDADE ADJUDICANTE\nDesignação da entidade adjudicante: Estado-Maior-General das Forças Armadas (EMGFA)\nNIPC: 600010180\nServiço/Órgão/Pessoa de contacto: Secção de Aquisições\nEndereço: Hospital das Forças Armadas  Polo do Porto Avenida da Boavista, s/n\nCódigo postal: 4050-113\nLocalidade: Porto\nPaís: Portugal\nNUT III: PT11A\nDistrito: Porto\nConcelho: Porto\nFreguesia: União das Freguesias de Cedofeita, Santo Ildefonso, Sé, Miragaia, São Nicolau e Vitória\nTelefone: 226087927\nFax: 000000000\nEndereço da Entidade (URL): https://www.hfar.pt/\nEndereço Eletrónico: hfar_pp_logistica@hfar.pt\neDelivery Gateway (URL): https://www.acingov.pt\nFunção da Organização: Adquirente\nNorma jurídica da Entidade Adjudicante: Organismo de direito público\nÁrea de atividade da Entidade Adjudicante: Atividades aeroportuárias\n\n2 - JORNAL OFICIAL DA UNIÃO EUROPEIA\nO procedimento a que este anúncio diz respeito também é publicitado no Jornal Oficial da União Europeia? Não\n\n3 - AVISO\nModelo de Anúncio: Concurso público\nData de Envio do Anúncio: 30-12-2025\n\n5 - PROCESSO\nTipo de Procedimento: Concurso público\nPreço base do procedimento: Sim\nValor do preço base do procedimento: 15.000,00 EUR\nProcedimento com lotes? Não\n\n6 - OBJETO DO CONTRATO\nNúmero de referência interna: CP PRR HFAR-PL 2025009784\nDesignação do contrato: 2025009784  Aquisição de eletrocardiógrafos para os serviços de Cardiologia e Urgência do HFAR-PL e para o Centro de Medicina Aeronáutica - Aviso PRR N.º 06/C01 i04/2025\nDescrição: 2025009784  Aquisição de eletrocardiógrafos para os serviços de Cardiologia e Urgência do HFAR-PL e para o Centro de Medicina Aeronáutica - Aviso PRR N.º 06/C01 i04/2025 \nTipo de Contrato Principal: Aquisição de Bens Móveis\nTipo de Contrato: Aquisição de Bens Móveis\nClassificação CPV (Vocabulário Comum para os Contratos Públicos)\nObjeto principal\nVocabulário Principal: 33123210\nPreço base s/IVA: 15.000,00 EUR\n\n7 - INDICAÇÕES ADICIONAIS\nO contrato envolve aquisição conjunta (satisfação de várias entidades)? Não\nO contrato é adjudicado por uma central de compras? Não\n\n8 - TÉCNICAS\nO concurso destina-se à celebração de um acordo-quadro? Inexistência de acordo-quadro\nÉ utilizado um leilão eletrónico? Não\nÉ adotada uma fase de negociação? Não\nSistema de Aquisição Dinâmico: Inexistência de sistema de aquisição dinâmico\n\n9 - LOCAL DA EXECUÇÃO DO CONTRATO\nLOCAL DA EXECUÇÃO DO CONTRATO (PROCEDIMENTO)\nPaís: Portugal\nNUT III: PT170\nLocalidade: Freguesia de Lumiar\nDistrito: Lisboa\nConcelho: Lisboa\nFreguesia: Freguesia de Lumiar\n\n10 - PRAZO DE EXECUÇÃO DO CONTRATO\nPrazo de execução do contrato: 30 DIAS\nPrevisão de renovações: Não\n\n11 - FUNDOS EU\nTêm fundos EU? Sim\n\n12 - DOCUMENTOS DE HABILITAÇÃO\nHabilitação para o exercício da atividade profissional: Não\n\n13 - CONDIÇÕES DE APRESENTAÇÃO\nPlataforma eletrónica utilizada pela entidade adjudicante: ACIN\nURL para Apresentação: https://www.acingov.pt\nAdmissibilidade da apresentação de propostas variantes: Não autorizado\nPrazo para apresentação das propostas: 19-01-2026 23:59\nPrazo durante o qual os concorrentes são obrigados a manter as respetivas propostas: 210 dias a contar do termo do prazo para a apresentação das propostas\nIndicação de Subcontratação na Proposta: Inexistência de indicação de subcontratação\n\n14 - PRESTAÇÃO DE CAUÇÃO\nPrestação de caução: Não\n\n15 - FORNECIMENTO DAS PEÇAS DO CONCURSO, APRESENTAÇÃO DE PEDIDOS DE PARTICIPAÇÃO E APRESENTAÇÃO DAS PROPOSTAS\nLink para acesso às peças do concurso (URL): https://www.acingov.pt/acingovprod/2/zonaPublica/zona_publica_c/donwloadProcedurePiece/MTAwOTM4Mw==\n\n20 - OUTROS REQUISITOS\nInformação sobre contratos reservados. Aplica-se a contratos reservados (54º-A)? Não\n\n21 - CRITÉRIO DE ADJUDICAÇÃO\nMultifator: Não\nMonofator:\nNome: Preço\n\n24 - CONDIÇÕES DO CONTRATO\nFaturação Eletrónica: Permitido\nObrigação de Subcontratação:\nCódigo da Obrigação de Subcontratação: Não é aplicável nenhuma obrigação de subcontratação.\n\n25 - COMPRA PÚBLICA ESTRATÉGICA\nCompra Pública Estratégica: Inexistência de contratação pública estratégica\n\n26 - INFORMAÇÕES ADICIONAIS\nContrato adequado para PME: Não\nCobertura ACP (Acordo dos Contratos Públicos da Organização Mundial do Comércio): Não\n\n27 - IDENTIFICAÇÃO E CONTACTOS DO ÓRGÃO DE RECURSOS ADMINISTRATIVOS\nDesignação: Tribunal Administrativo de Círculo de Lisboa\nEndereço: Av D. João II, Bloco G, piso 6-8, nº 1.08.01, 1990-097 Lisboa\nCódigo postal: 1990-097\nLocalidade: Lisboa\nTelefone: 218367100\nFax: 211545188\nEndereço eletrónico: lisboa.tacl@tribunais.org.pt\n\n28 - IDENTIFICAÇÃO DO(S) AUTOR(ES) DE ANÚNCIO\nNome: António José dos Santos Moura\nCargo: Subdiretor do HFAR\n419941612",
    "nipc": "600010180",
    "distrito": "Porto",
    "concelho": "Porto",
    "freguesia": "União das Freguesias de Cedofeita, Santo Ildefonso, Sé, Miragaia, São Nicolau e Vitória",
    "site": "https://www.hfar.pt/",
    "email": "hfar_pp_logistica@hfar.pt",
    "designacao_contrato": "2025009784  Aquisição de eletrocardiógrafos para os serviços de Cardiologia e Urgência do HFAR-PL e para o Centro de Medicina Aeronáutica - Aviso PRR N.º 06/C01 i04/2025",
    "descricao": "2025009784  Aquisição de eletrocardiógrafos para os serviços de Cardiologia e Urgência do HFAR-PL e para o Centro de Medicina Aeronáutica - Aviso PRR N.º 06/C01 i04/2025",
    "preco_base": "15.000,00 EUR",
    "prazo_execucao": "30 DIAS",
    "prazo_apresentacao_propostas": "19-01-2026 23:59",
    "fundos_eu": "Sim",
    "plataforma_eletronica": "ACIN",
    "url_procedimento": "https://www.acingov.pt",
    "autor_nome": "António José dos Santos Moura",
    "autor_cargo": "Subdiretor do HFAR"
  },
  {
    "numero_procedimento": "N/A",
    "entidade": "AnÃºncio de procedimento  n.Âº 33636/2025  -  DiÃ¡rio da RepÃºblica n.Âº 251/2025, SÃ©rie II de 2025-12-31",
    "link": "https://diariodarepublica.pt/dr/detalhe/contrato-publico/33636-993270150"
  },
  {
    "numero_procedimento": "N/A",
    "entidade": "Estado-Maior-General das Forças Armadas (EMGFA)",
    "link": "https://diariodarepublica.pt/dr/detalhe/contrato-publico/33638-993270151",
    "detalhes_completos": "1 - IDENTIFICAÇÃO E CONTACTOS DA ENTIDADE ADJUDICANTE\nDesignação da entidade adjudicante: Estado-Maior-General das Forças Armadas (EMGFA)\nNIPC: 600010180\nServiço/Órgão/Pessoa de contacto: Secção de Aquisições\nEndereço: Hospital das Forças Armadas  Polo do Porto Avenida da Boavista, s/n\nCódigo postal: 4050-113\nLocalidade: Porto\nPaís: Portugal\nNUT III: PT11A\nDistrito: Porto\nConcelho: Porto\nFreguesia: União das Freguesias de Cedofeita, Santo Ildefonso, Sé, Miragaia, São Nicolau e Vitória\nTelefone: 226087927\nFax: 000000000\nEndereço da Entidade (URL): https://www.hfar.pt/\nEndereço Eletrónico: hfar_pp_logistica@hfar.pt\neDelivery Gateway (URL): https://www.acingov.pt\nFunção da Organização: Adquirente\nNorma jurídica da Entidade Adjudicante: Organismo de direito público\nÁrea de atividade da Autoridade Adjudicante: Serviços públicos das administrações públicas\n\n2 - JORNAL OFICIAL DA UNIÃO EUROPEIA\nO procedimento a que este anúncio diz respeito também é publicitado no Jornal Oficial da União Europeia? Não\n\n3 - AVISO\nModelo de Anúncio: Concurso público\nData de Envio do Anúncio: 30-12-2025\n\n5 - PROCESSO\nTipo de Procedimento: Concurso público\nPreço base do procedimento: Sim\nValor do preço base do procedimento: 22.000,00 EUR\nProcedimento com lotes? Não\n\n6 - OBJETO DO CONTRATO\nNúmero de referência interna: CP PRR HFAR-PP 2025009793\nDesignação do contrato: 2025009793  Aquisição de Armário de Pressão Positiva, com Filtro HEPA para o Serviço de Gastrenterologia do HFAR-PP - Aviso PRR N.º 06/C01 i04/2025\nDescrição: 2025009793  Aquisição de Armário de Pressão Positiva, com Filtro HEPA para o Serviço de Gastrenterologia do HFAR-PP - Aviso PRR N.º 06/C01 i04/2025  \nTipo de Contrato Principal: Aquisição de Bens Móveis\nTipo de Contrato: Aquisição de Bens Móveis\nClassificação CPV (Vocabulário Comum para os Contratos Públicos)\nObjeto principal\nVocabulário Principal: 33192000\nPreço base s/IVA: 22.000,00 EUR\n\n7 - INDICAÇÕES ADICIONAIS\nO contrato envolve aquisição conjunta (satisfação de várias entidades)? Não\nO contrato é adjudicado por uma central de compras? Não\n\n8 - TÉCNICAS\nO concurso destina-se à celebração de um acordo-quadro? Inexistência de acordo-quadro\nÉ utilizado um leilão eletrónico? Não\nÉ adotada uma fase de negociação? Não\nSistema de Aquisição Dinâmico: Inexistência de sistema de aquisição dinâmico\n\n9 - LOCAL DA EXECUÇÃO DO CONTRATO\nLOCAL DA EXECUÇÃO DO CONTRATO (PROCEDIMENTO)\nPaís: Portugal\nNUT III: PT11A\nLocalidade: União das Freguesias de Cedofeita, Santo Ildefonso, Sé, Miragaia, São Nicolau e Vitória\nDistrito: Porto\nConcelho: Porto\nFreguesia: União das Freguesias de Cedofeita, Santo Ildefonso, Sé, Miragaia, São Nicolau e Vitória\n\n10 - PRAZO DE EXECUÇÃO DO CONTRATO\nPrazo de execução do contrato: 60 DIAS\nPrevisão de renovações: Não\n\n11 - FUNDOS EU\nTêm fundos EU? Sim\n\n12 - DOCUMENTOS DE HABILITAÇÃO\nHabilitação para o exercício da atividade profissional: Não\n\n13 - CONDIÇÕES DE APRESENTAÇÃO\nPlataforma eletrónica utilizada pela entidade adjudicante: ACIN\nURL para Apresentação: https://www.acingov.pt\nAdmissibilidade da apresentação de propostas variantes: Não autorizado\nPrazo para apresentação das propostas: 19-01-2026 23:59\nPrazo durante o qual os concorrentes são obrigados a manter as respetivas propostas: 210 dias a contar do termo do prazo para a apresentação das propostas\nIndicação de Subcontratação na Proposta: Inexistência de indicação de subcontratação\n\n14 - PRESTAÇÃO DE CAUÇÃO\nPrestação de caução: Não\n\n15 - FORNECIMENTO DAS PEÇAS DO CONCURSO, APRESENTAÇÃO DE PEDIDOS DE PARTICIPAÇÃO E APRESENTAÇÃO DAS PROPOSTAS\nLink para acesso às peças do concurso (URL): https://www.acingov.pt/acingovprod/2/zonaPublica/zona_publica_c/donwloadProcedurePiece/MTAwOTQ5MQ==\n\n20 - OUTROS REQUISITOS\nInformação sobre contratos reservados. Aplica-se a contratos reservados (54º-A)? Não\n\n21 - CRITÉRIO DE ADJUDICAÇÃO\nMultifator: Não\nMonofator:\nNome: Preço\n\n24 - CONDIÇÕES DO CONTRATO\nFaturação Eletrónica: Permitido\nObrigação de Subcontratação:\nCódigo da Obrigação de Subcontratação: Não é aplicável nenhuma obrigação de subcontratação.\n\n25 - COMPRA PÚBLICA ESTRATÉGICA\nCompra Pública Estratégica: Inexistência de contratação pública estratégica\n\n26 - INFORMAÇÕES ADICIONAIS\nContrato adequado para PME: Não\nCobertura ACP (Acordo dos Contratos Públicos da Organização Mundial do Comércio): Não\n\n27 - IDENTIFICAÇÃO E CONTACTOS DO ÓRGÃO DE RECURSOS ADMINISTRATIVOS\nDesignação: Tribunal Administrativo de Círculo de Lisboa\nEndereço: Av D. João II, Bloco G, piso 6-8, nº 1.08.01, 1990-097 Lisboa\nCódigo postal: 1990-097\nLocalidade: Lisboa\nTelefone: 218367100\nFax: 211545188\nEndereço eletrónico: lisboa.tacl@tribunais.org.pt\n\n28 - IDENTIFICAÇÃO DO(S) AUTOR(ES) DE ANÚNCIO\nNome: José Carlos Candeias Pinheiro Monge\nCargo: Diretor do HFAR\n419941053",
    "nipc": "600010180",
    "distrito": "Porto",
    "concelho": "Porto",
    "freguesia": "União das Freguesias de Cedofeita, Santo Ildefonso, Sé, Miragaia, São Nicolau e Vitória",
    "site": "https://www.hfar.pt/",
    "email": "hfar_pp_logistica@hfar.pt",
    "designacao_contrato": "2025009793  Aquisição de Armário de Pressão Positiva, com Filtro HEPA para o Serviço de Gastrenterologia do HFAR-PP - Aviso PRR N.º 06/C01 i04/2025",
    "descricao": "2025009793  Aquisição de Armário de Pressão Positiva, com Filtro HEPA para o Serviço de Gastrenterologia do HFAR-PP - Aviso PRR N.º 06/C01 i04/2025",
    "preco_base": "22.000,00 EUR",
    "prazo_execucao": "60 DIAS",
    "prazo_apresentacao_propostas": "19-01-2026 23:59",
    "fundos_eu": "Sim",
    "plataforma_eletronica": "ACIN",
    "url_procedimento": "https://www.acingov.pt",
    "autor_nome": "José Carlos Candeias Pinheiro Monge",
    "autor_cargo": "Diretor do HFAR"
  },
  {
    "numero_procedimento": "N/A",
    "entidade": "Estado-Maior-General das Forças Armadas (EMGFA)",
    "link": "https://diariodarepublica.pt/dr/detalhe/contrato-publico/33640-993270152",
    "detalhes_completos": "1 - IDENTIFICAÇÃO E CONTACTOS DA ENTIDADE ADJUDICANTE\nDesignação da entidade adjudicante: Estado-Maior-General das Forças Armadas (EMGFA)\nNIPC: 600010180\nServiço/Órgão/Pessoa de contacto: Secção de Aquisições\nEndereço: HOSPITAL DAS FORÇAS ARMADAS  POLO PORTO SECÇÃO DE LOGÍSTICA - APROVISIONAMENTO AVª DA BOAVISTA S/N 4050-113 PORTO\nCódigo postal: 4050-113\nLocalidade: Porto\nPaís: Portugal\nNUT III: PT170\nDistrito: Lisboa\nConcelho: Lisboa\nFreguesia: Freguesia de Lumiar\nTelefone: 226087927\nFax: 000000\nEndereço da Entidade (URL): https://www.hfar.pt/\nEndereço Eletrónico: hfar_pp_logistica@hfar.pt\neDelivery Gateway (URL): https://www.acingov.pt\nFunção da Organização: Adquirente\nNorma jurídica da Entidade Adjudicante: Organismo de direito público\nÁrea de atividade da Entidade Adjudicante: Atividades aeroportuárias\n\n2 - JORNAL OFICIAL DA UNIÃO EUROPEIA\nO procedimento a que este anúncio diz respeito também é publicitado no Jornal Oficial da União Europeia? Não\n\n3 - AVISO\nModelo de Anúncio: Concurso público\nData de Envio do Anúncio: 30-12-2025\n\n5 - PROCESSO\nTipo de Procedimento: Concurso público\nPreço base do procedimento: Sim\nValor do preço base do procedimento: 90.000,00 EUR\nProcedimento com lotes? Não\n\n6 - OBJETO DO CONTRATO\nNúmero de referência interna: CP_PRR_PP_2025009797\nDesignação do contrato: 2025009797  Aquisição de Monitores de Hemodiálise para o serviço de Nefrologia do HFAR-PP Aviso PRR N.º 06/C01 i04/2025\nDescrição: 2025009797  Aquisição de Monitores de Hemodiálise para o serviço de Nefrologia do HFAR-PP Aviso PRR N.º 06/C01 i04/2025 \nTipo de Contrato Principal: Aquisição de Bens Móveis\nTipo de Contrato: Aquisição de Bens Móveis\nClassificação CPV (Vocabulário Comum para os Contratos Públicos)\nObjeto principal\nVocabulário Principal: 33181300\nPreço base s/IVA: 90.000,00 EUR\n\n7 - INDICAÇÕES ADICIONAIS\nO contrato envolve aquisição conjunta (satisfação de várias entidades)? Não\nO contrato é adjudicado por uma central de compras? Não\n\n8 - TÉCNICAS\nO concurso destina-se à celebração de um acordo-quadro? Inexistência de acordo-quadro\nÉ utilizado um leilão eletrónico? Não\nÉ adotada uma fase de negociação? Não\nSistema de Aquisição Dinâmico: Inexistência de sistema de aquisição dinâmico\n\n9 - LOCAL DA EXECUÇÃO DO CONTRATO\nLOCAL DA EXECUÇÃO DO CONTRATO (PROCEDIMENTO)\nPaís: Portugal\nNUT III: PT11A\nLocalidade: União das Freguesias de Cedofeita, Santo Ildefonso, Sé, Miragaia, São Nicolau e Vitória\nDistrito: Porto\nConcelho: Porto\nFreguesia: União das Freguesias de Cedofeita, Santo Ildefonso, Sé, Miragaia, São Nicolau e Vitória\n\n10 - PRAZO DE EXECUÇÃO DO CONTRATO\nPrazo de execução do contrato: 60 DIAS\nPrevisão de renovações: Não\n\n11 - FUNDOS EU\nTêm fundos EU? Sim\n\n12 - DOCUMENTOS DE HABILITAÇÃO\nHabilitação para o exercício da atividade profissional: Não\n\n13 - CONDIÇÕES DE APRESENTAÇÃO\nPlataforma eletrónica utilizada pela entidade adjudicante: ACIN\nURL para Apresentação: https://www.acingov.pt\nAdmissibilidade da apresentação de propostas variantes: Não autorizado\nPrazo para apresentação das propostas: 19-01-2026 23:59\nPrazo durante o qual os concorrentes são obrigados a manter as respetivas propostas: 210 dias a contar do termo do prazo para a apresentação das propostas\nIndicação de Subcontratação na Proposta: Inexistência de indicação de subcontratação\n\n14 - PRESTAÇÃO DE CAUÇÃO\nPrestação de caução: Não\n\n15 - FORNECIMENTO DAS PEÇAS DO CONCURSO, APRESENTAÇÃO DE PEDIDOS DE PARTICIPAÇÃO E APRESENTAÇÃO DAS PROPOSTAS\nLink para acesso às peças do concurso (URL): https://www.acingov.pt/acingovprod/2/zonaPublica/zona_publica_c/donwloadProcedurePiece/MTAwOTI5Ng==\n\n20 - OUTROS REQUISITOS\nInformação sobre contratos reservados. Aplica-se a contratos reservados (54º-A)? Não\n\n21 - CRITÉRIO DE ADJUDICAÇÃO\nMultifator: Não\nMonofator:\nNome: Preço\n\n24 - CONDIÇÕES DO CONTRATO\nFaturação Eletrónica: Permitido\nObrigação de Subcontratação:\nCódigo da Obrigação de Subcontratação: Não é aplicável nenhuma obrigação de subcontratação.\n\n25 - COMPRA PÚBLICA ESTRATÉGICA\nCompra Pública Estratégica: Inexistência de contratação pública estratégica\n\n26 - INFORMAÇÕES ADICIONAIS\nContrato adequado para PME: Não\nCobertura ACP (Acordo dos Contratos Públicos da Organização Mundial do Comércio): Não\n\n27 - IDENTIFICAÇÃO E CONTACTOS DO ÓRGÃO DE RECURSOS ADMINISTRATIVOS\nDesignação: Tribunal Administrativo de Círculo de Lisboa\nEndereço: Edifício G - Campus de Justiça Av D. João II, nº 1.08.01 Edif, G - 6º andar 1900-097 Lisboa\nCódigo postal: 1900-097\nLocalidade: Lisboa\nTelefone: 218367100\nFax: 999999999\nEndereço eletrónico: lisboa.tacl@tribunais.org.pt\n\n28 - IDENTIFICAÇÃO DO(S) AUTOR(ES) DE ANÚNCIO\nNome: Ana Margarida do Couto Fernandes\nCargo: AT\n419941694",
    "nipc": "600010180",
    "distrito": "Lisboa",
    "concelho": "Lisboa",
    "freguesia": "Freguesia de Lumiar",
    "site": "https://www.hfar.pt/",
    "email": "hfar_pp_logistica@hfar.pt",
    "designacao_contrato": "2025009797  Aquisição de Monitores de Hemodiálise para o serviço de Nefrologia do HFAR-PP Aviso PRR N.º 06/C01 i04/2025",
    "descricao": "2025009797  Aquisição de Monitores de Hemodiálise para o serviço de Nefrologia do HFAR-PP Aviso PRR N.º 06/C01 i04/2025",
    "preco_base": "90.000,00 EUR",
    "prazo_execucao": "60 DIAS",
    "prazo_apresentacao_propostas": "19-01-2026 23:59",
    "fundos_eu": "Sim",
    "plataforma_eletronica": "ACIN",
    "url_procedimento": "https://www.acingov.pt",
    "autor_nome": "Ana Margarida do Couto Fernandes",
    "autor_cargo": "AT"
  },
  {
    "numero_procedimento": "N/A",
    "entidade": "Estado-Maior-General das Forças Armadas (EMGFA)",
    "link": "https://diariodarepublica.pt/dr/detalhe/contrato-publico/33642-993270154",
    "detalhes_completos": "1 - IDENTIFICAÇÃO E CONTACTOS DA ENTIDADE ADJUDICANTE\nDesignação da entidade adjudicante: Estado-Maior-General das Forças Armadas (EMGFA)\nNIPC: 600010180\nServiço/Órgão/Pessoa de contacto: Secção de Aquisições\nEndereço: HOSPITAL DAS FORÇAS ARMADAS  POLO PORTO SECÇÃO DE LOGÍSTICA - APROVISIONAMENTO AVª DA BOAVISTA S/N 4050-113 PORTO\nCódigo postal: 4050-113\nLocalidade: Porto\nPaís: Portugal\nNUT III: PT170\nDistrito: Lisboa\nConcelho: Lisboa\nFreguesia: Freguesia de Lumiar\nTelefone: 226087927\nFax: 000000\nEndereço da Entidade (URL): https://www.hfar.pt/\nEndereço Eletrónico: hfar_pp_logistica@hfar.pt\neDelivery Gateway (URL): https://www.acingov.pt\nFunção da Organização: Adquirente\nNorma jurídica da Entidade Adjudicante: Organismo de direito público\nÁrea de atividade da Entidade Adjudicante: Atividades aeroportuárias\n\n2 - JORNAL OFICIAL DA UNIÃO EUROPEIA\nO procedimento a que este anúncio diz respeito também é publicitado no Jornal Oficial da União Europeia? Não\n\n3 - AVISO\nModelo de Anúncio: Concurso público\nData de Envio do Anúncio: 30-12-2025\n\n5 - PROCESSO\nTipo de Procedimento: Concurso público\nPreço base do procedimento: Sim\nValor do preço base do procedimento: 13.500,00 EUR\nProcedimento com lotes? Não\n\n6 - OBJETO DO CONTRATO\nNúmero de referência interna: CP_PRR_PP_2025009799\nDesignação do contrato: 2025009799  Aquisição de Cadeirões Hospitalares Elétricos para o serviço de Nefrologia do HFAR-PP e Centro de Medicina Subaquática e Hiperbárica Aviso PRR N.º 06/C01 i04/2025\nDescrição: 2025009799  Aquisição de Cadeirões Hospitalares Elétricos para o serviço de Nefrologia do HFAR-PP e Centro de Medicina Subaquática e Hiperbárica  Aviso PRR N.º 06/C01 i04/2025 \nTipo de Contrato Principal: Aquisição de Bens Móveis\nTipo de Contrato: Aquisição de Bens Móveis\nClassificação CPV (Vocabulário Comum para os Contratos Públicos)\nObjeto principal\nVocabulário Principal: 39112000\nPreço base s/IVA: 13.500,00 EUR\n\n7 - INDICAÇÕES ADICIONAIS\nO contrato envolve aquisição conjunta (satisfação de várias entidades)? Não\nO contrato é adjudicado por uma central de compras? Não\n\n8 - TÉCNICAS\nO concurso destina-se à celebração de um acordo-quadro? Inexistência de acordo-quadro\nÉ utilizado um leilão eletrónico? Não\nÉ adotada uma fase de negociação? Não\nSistema de Aquisição Dinâmico: Inexistência de sistema de aquisição dinâmico\n\n9 - LOCAL DA EXECUÇÃO DO CONTRATO\nLOCAL DA EXECUÇÃO DO CONTRATO (PROCEDIMENTO)\nPaís: Portugal\nNUT III: PT11A\nLocalidade: União das Freguesias de Cedofeita, Santo Ildefonso, Sé, Miragaia, São Nicolau e Vitória\nDistrito: Porto\nConcelho: Porto\nFreguesia: União das Freguesias de Cedofeita, Santo Ildefonso, Sé, Miragaia, São Nicolau e Vitória\n\n10 - PRAZO DE EXECUÇÃO DO CONTRATO\nPrazo de execução do contrato: 60 DIAS\nPrevisão de renovações: Não\n\n11 - FUNDOS EU\nTêm fundos EU? Sim\n\n12 - DOCUMENTOS DE HABILITAÇÃO\nHabilitação para o exercício da atividade profissional: Não\n\n13 - CONDIÇÕES DE APRESENTAÇÃO\nPlataforma eletrónica utilizada pela entidade adjudicante: ACIN\nURL para Apresentação: https://www.acingov.pt\nAdmissibilidade da apresentação de propostas variantes: Não autorizado\nPrazo para apresentação das propostas: 19-01-2026 23:59\nPrazo durante o qual os concorrentes são obrigados a manter as respetivas propostas: 210 dias a contar do termo do prazo para a apresentação das propostas\nIndicação de Subcontratação na Proposta: Inexistência de indicação de subcontratação\n\n14 - PRESTAÇÃO DE CAUÇÃO\nPrestação de caução: Não\n\n15 - FORNECIMENTO DAS PEÇAS DO CONCURSO, APRESENTAÇÃO DE PEDIDOS DE PARTICIPAÇÃO E APRESENTAÇÃO DAS PROPOSTAS\nLink para acesso às peças do concurso (URL): https://www.acingov.pt/acingovprod/2/zonaPublica/zona_publica_c/donwloadProcedurePiece/MTAwOTMzNQ==\n\n20 - OUTROS REQUISITOS\nInformação sobre contratos reservados. Aplica-se a contratos reservados (54º-A)? Não\n\n21 - CRITÉRIO DE ADJUDICAÇÃO\nMultifator: Não\nMonofator:\nNome: Outros\nOutro nome: Fator Preço\n\n24 - CONDIÇÕES DO CONTRATO\nFaturação Eletrónica: Permitido\nObrigação de Subcontratação:\nCódigo da Obrigação de Subcontratação: Não é aplicável nenhuma obrigação de subcontratação.\n\n25 - COMPRA PÚBLICA ESTRATÉGICA\nCompra Pública Estratégica: Inexistência de contratação pública estratégica\n\n26 - INFORMAÇÕES ADICIONAIS\nContrato adequado para PME: Não\nCobertura ACP (Acordo dos Contratos Públicos da Organização Mundial do Comércio): Não\n\n27 - IDENTIFICAÇÃO E CONTACTOS DO ÓRGÃO DE RECURSOS ADMINISTRATIVOS\nDesignação: Tribunal Administrativo de Círculo de Lisboa\nEndereço: Av D. João II, Bloco G, piso 6-8, nº 1.08.01, 1990-097 Lisboa\nCódigo postal: 1990-097\nLocalidade: Lisboa\nTelefone: 218367100\nFax: 211545188\nEndereço eletrónico: lisboa.tacl@tribunais.org.pt\n\n28 - IDENTIFICAÇÃO DO(S) AUTOR(ES) DE ANÚNCIO\nNome: Ana Margarida do Couto Fernandes\nCargo: AT\n419941629",
    "nipc": "600010180",
    "distrito": "Lisboa",
    "concelho": "Lisboa",
    "freguesia": "Freguesia de Lumiar",
    "site": "https://www.hfar.pt/",
    "email": "hfar_pp_logistica@hfar.pt",
    "designacao_contrato": "2025009799  Aquisição de Cadeirões Hospitalares Elétricos para o serviço de Nefrologia do HFAR-PP e Centro de Medicina Subaquática e Hiperbárica Aviso PRR N.º 06/C01 i04/2025",
    "descricao": "2025009799  Aquisição de Cadeirões Hospitalares Elétricos para o serviço de Nefrologia do HFAR-PP e Centro de Medicina Subaquática e Hiperbárica Aviso PRR N.º 06/C01 i04/2025",
    "preco_base": "13.500,00 EUR",
    "prazo_execucao": "60 DIAS",
    "prazo_apresentacao_propostas": "19-01-2026 23:59",
    "fundos_eu": "Sim",
    "plataforma_eletronica": "ACIN",
    "url_procedimento": "https://www.acingov.pt",
    "autor_nome": "Ana Margarida do Couto Fernandes",
    "autor_cargo": "AT"
  },
  {
    "numero_procedimento": "N/A",
    "entidade": "Estado-Maior-General das Forças Armadas (EMGFA)",
    "link": "https://diariodarepublica.pt/dr/detalhe/contrato-publico/33649-993270156",
    "detalhes_completos": "1 - IDENTIFICAÇÃO E CONTACTOS DA ENTIDADE ADJUDICANTE\nDesignação da entidade adjudicante: Estado-Maior-General das Forças Armadas (EMGFA)\nNIPC: 600010180\nServiço/Órgão/Pessoa de contacto: DepCompras\nEndereço: Azinhaga Ulmeiros, 1649-020 Lisboa\nCódigo postal: 1649-020\nLocalidade: Lisboa\nPaís: Portugal\nNUT III: PT170\nDistrito: Lisboa\nConcelho: Lisboa\nFreguesia: Freguesia de Lumiar\nTelefone: 21 751 9777\nFax: 21 751 9777\nEndereço da Entidade (URL): www.hfar.pt\nEndereço Eletrónico: hfar_dcomp_chf@hfar.pt\neDelivery Gateway (URL): https://www.acingov.pt\nFunção da Organização: Adquirente\nNorma jurídica da Entidade Adjudicante: Organismo de direito público\nÁrea de atividade da Entidade Adjudicante: Atividades aeroportuárias\n\n2 - JORNAL OFICIAL DA UNIÃO EUROPEIA\nO procedimento a que este anúncio diz respeito também é publicitado no Jornal Oficial da União Europeia? Não\n\n3 - AVISO\nModelo de Anúncio: Concurso público\nData de Envio do Anúncio: 30-12-2025\n\n5 - PROCESSO\nTipo de Procedimento: Concurso público\nPreço base do procedimento: Sim\nValor do preço base do procedimento: 12.000,00 EUR\nProcedimento com lotes? Não\n\n6 - OBJETO DO CONTRATO\nNúmero de referência interna: HFAR-PL 2025009779\nDesignação do contrato: 2025009779/HFAR-PRR_6-EQUIPAMENTOS PARA SERVIÇO DE MEDICINA FÍSICA E REABILITAÇÃO\nDescrição: 2025009779/HFAR-PRR_6-EQUIPAMENTOS PARA SERVIÇO DE MEDICINA FÍSICA E REABILITAÇÃO\nTipo de Contrato Principal: Aquisição de Bens Móveis\nTipo de Contrato: Aquisição de Bens Móveis\nClassificação CPV (Vocabulário Comum para os Contratos Públicos)\nObjeto principal\nVocabulário Principal: 33169000\nPreço base s/IVA: 12.000,00 EUR\n\n7 - INDICAÇÕES ADICIONAIS\nO contrato envolve aquisição conjunta (satisfação de várias entidades)? Não\nO contrato é adjudicado por uma central de compras? Não\n\n8 - TÉCNICAS\nO concurso destina-se à celebração de um acordo-quadro? Inexistência de acordo-quadro\nÉ utilizado um leilão eletrónico? Não\nÉ adotada uma fase de negociação? Não\nSistema de Aquisição Dinâmico: Inexistência de sistema de aquisição dinâmico\n\n9 - LOCAL DA EXECUÇÃO DO CONTRATO\nLOCAL DA EXECUÇÃO DO CONTRATO (PROCEDIMENTO)\nPaís: Portugal\nNUT III: PT170\nLocalidade: Freguesia de Lumiar\nDistrito: Lisboa\nConcelho: Lisboa\nFreguesia: Freguesia de Lumiar\n\n10 - PRAZO DE EXECUÇÃO DO CONTRATO\nPrazo de execução do contrato: 90 DIAS\nPrevisão de renovações: Não\n\n11 - FUNDOS EU\nTêm fundos EU? Sim\n\n12 - DOCUMENTOS DE HABILITAÇÃO\nHabilitação para o exercício da atividade profissional: Não\n\n13 - CONDIÇÕES DE APRESENTAÇÃO\nPlataforma eletrónica utilizada pela entidade adjudicante: ACIN\nURL para Apresentação: https://www.acingov.pt\nAdmissibilidade da apresentação de propostas variantes: Não autorizado\nPrazo para apresentação das propostas: 12-01-2026 23:59\nPrazo durante o qual os concorrentes são obrigados a manter as respetivas propostas: 66 dias a contar do termo do prazo para a apresentação das propostas\nIndicação de Subcontratação na Proposta: Inexistência de indicação de subcontratação\n\n14 - PRESTAÇÃO DE CAUÇÃO\nPrestação de caução: Não\n\n15 - FORNECIMENTO DAS PEÇAS DO CONCURSO, APRESENTAÇÃO DE PEDIDOS DE PARTICIPAÇÃO E APRESENTAÇÃO DAS PROPOSTAS\nLink para acesso às peças do concurso (URL): https://www.acingov.pt/acingovprod/2/zonaPublica/zona_publica_c/donwloadProcedurePiece/MTAxMjM0NQ==\n\n20 - OUTROS REQUISITOS\nInformação sobre contratos reservados. Aplica-se a contratos reservados (54º-A)? Não\n\n21 - CRITÉRIO DE ADJUDICAÇÃO\nMultifator: Não\nMonofator:\nNome: Preço\n\n24 - CONDIÇÕES DO CONTRATO\nFaturação Eletrónica: Permitido\nObrigação de Subcontratação:\nCódigo da Obrigação de Subcontratação: Não é aplicável nenhuma obrigação de subcontratação.\n\n25 - COMPRA PÚBLICA ESTRATÉGICA\nCompra Pública Estratégica: Inexistência de contratação pública estratégica\n\n26 - INFORMAÇÕES ADICIONAIS\nContrato adequado para PME: Não\nCobertura ACP (Acordo dos Contratos Públicos da Organização Mundial do Comércio): Não\n\n27 - IDENTIFICAÇÃO E CONTACTOS DO ÓRGÃO DE RECURSOS ADMINISTRATIVOS\nDesignação: EMGFA\nEndereço: Av. Ilha da Madeira N.º 1, 1449-004 Lisboa\nCódigo postal: 1449-004\nLocalidade: Lisboa\nEndereço eletrónico: emgfa@emgfa.pt\n\n28 - IDENTIFICAÇÃO DO(S) AUTOR(ES) DE ANÚNCIO\nNome: José Carlos Candeias Pinheiro Monge\nCargo: Diretor HFAR\n419942196",
    "nipc": "600010180",
    "distrito": "Lisboa",
    "concelho": "Lisboa",
    "freguesia": "Freguesia de Lumiar",
    "site": "www.hfar.pt",
    "email": "hfar_dcomp_chf@hfar.pt",
    "designacao_contrato": "2025009779/HFAR-PRR_6-EQUIPAMENTOS PARA SERVIÇO DE MEDICINA FÍSICA E REABILITAÇÃO",
    "descricao": "2025009779/HFAR-PRR_6-EQUIPAMENTOS PARA SERVIÇO DE MEDICINA FÍSICA E REABILITAÇÃO",
    "preco_base": "12.000,00 EUR",
    "prazo_execucao": "90 DIAS",
    "prazo_apresentacao_propostas": "12-01-2026 23:59",
    "fundos_eu": "Sim",
    "plataforma_eletronica": "ACIN",
    "url_procedimento": "https://www.acingov.pt",
    "autor_nome": "José Carlos Candeias Pinheiro Monge",
    "autor_cargo": "Diretor HFAR"
  },
  {
    "numero_procedimento": "N/A",
    "entidade": "Município de Borba",
    "link": "https://diariodarepublica.pt/dr/detalhe/contrato-publico/33650-993270157",
    "detalhes_completos": "1 - IDENTIFICAÇÃO E CONTACTOS DA ENTIDADE ADJUDICANTE\nDesignação da entidade adjudicante: Município de Borba\nNIPC: 503956546\nServiço/Órgão/Pessoa de contacto: Contratação Pública\nEndereço: PRAÇA DA REPUBLICA\nCódigo postal: 7150-249\nLocalidade: BORBA\nPaís: Portugal\nNUT III: PT187\nDistrito: Évora\nConcelho: Borba\nFreguesia: Freguesia de Borba (Matriz)\nTelefone: 268891630\nFax: 268894680\nEndereço da Entidade (URL): www.cm-borba.pt\nEndereço Eletrónico: contratacaopublica@cm-borba.pt\nFunção da Organização: Prestador de serviços no domínio da contratação pública\nSubfunção da Organização: Organização que fornece informações adicionais sobre o processo de adjudicação\nNorma jurídica da Entidade Adjudicante: Organismo de direito público, controlado por uma autoridade local\nÁrea de atividade da Autoridade Adjudicante: Serviços públicos das administrações públicas\n\n2 - JORNAL OFICIAL DA UNIÃO EUROPEIA\nO procedimento a que este anúncio diz respeito também é publicitado no Jornal Oficial da União Europeia? Não\n\n3 - AVISO\nModelo de Anúncio: Concurso público\nData de Envio do Anúncio: 30-12-2025\n\n5 - PROCESSO\nTipo de Procedimento: Concurso público\nPreço base do procedimento: Sim\nValor do preço base do procedimento: 856.266,07 EUR\nProcedimento com lotes? Não\n\n6 - OBJETO DO CONTRATO\nNúmero de referência interna: 50/2025\nDesignação do contrato:  Melhoria de Eficiência Energética do Centro Escolar de Borba\nDescrição: Empreitada de melhoria de Eficiência Energética do Centro Escolar de Borba\nTipo de Contrato Principal: Empreitada de Obras Públicas\nTipo de Contrato: Empreitada de Obras Públicas\nClassificação CPV (Vocabulário Comum para os Contratos Públicos)\nObjeto principal\nVocabulário Principal: 45321000\nPreço base s/IVA: 856.266,07 EUR\n\n7 - INDICAÇÕES ADICIONAIS\nO contrato envolve aquisição conjunta (satisfação de várias entidades)? Não\nO contrato é adjudicado por uma central de compras? Não\n\n8 - TÉCNICAS\nO concurso destina-se à celebração de um acordo-quadro? Inexistência de acordo-quadro\nÉ utilizado um leilão eletrónico? Não\nÉ adotada uma fase de negociação? Não\nSistema de Aquisição Dinâmico: Inexistência de sistema de aquisição dinâmico\n\n9 - LOCAL DA EXECUÇÃO DO CONTRATO\nLOCAL DA EXECUÇÃO DO CONTRATO (PROCEDIMENTO)\nPaís: Portugal\nNUT III: PT187\nLocalidade: Borba\nDistrito: Évora\nConcelho: Borba\nFreguesia: Freguesia de Borba (Matriz)\n\n10 - PRAZO DE EXECUÇÃO DO CONTRATO\nPrazo de execução do contrato: 210 DIAS\nPrevisão de renovações: Não\n\n11 - FUNDOS EU\nTêm fundos EU? Sim\n\n12 - DOCUMENTOS DE HABILITAÇÃO\nHabilitação para o exercício da atividade profissional: Não\n\n13 - CONDIÇÕES DE APRESENTAÇÃO\nPlataforma eletrónica utilizada pela entidade adjudicante: VORTAL\nURL para Apresentação: www.cm-borba.pt\nAdmissibilidade da apresentação de propostas variantes: Não autorizado\nPrazo para apresentação das propostas: 30-01-2026 23:59\nPrazo durante o qual os concorrentes são obrigados a manter as respetivas propostas: 66 dias a contar do termo do prazo para a apresentação das propostas\nApresentação de Catálogo Eletrónico: Não autorizado\nIndicação de Subcontratação na Proposta: Inexistência de indicação de subcontratação\n\n14 - PRESTAÇÃO DE CAUÇÃO\nPrestação de caução: Sim\nPercentagem: 5%\nDescrição da Garantia Exigida: Garantia Bancária, Seguro Caução, conforme o disposto no artigo 90º do CCP\n\n15 - FORNECIMENTO DAS PEÇAS DO CONCURSO, APRESENTAÇÃO DE PEDIDOS DE PARTICIPAÇÃO E APRESENTAÇÃO DAS PROPOSTAS\nLink para acesso às peças do concurso (URL): https://community.vortal.biz\n\n20 - OUTROS REQUISITOS\nInformação sobre contratos reservados. Aplica-se a contratos reservados (54º-A)? Não\n\n21 - CRITÉRIO DE ADJUDICAÇÃO\nMultifator: Sim\nFator: \nNome: Qualidade\nPonderação: 60%\nSubfatores: Sim\nSubfatores: \nNome: Memoria descritiva e justificativa\nPonderação : 60%; \nNome: Programa trabalhos\nPonderação : 30%; \nNome: Utilização de materiais reciclados\nPonderação : 10%; \nFator: \nNome: Preço\nPonderação: 40%\nSubfatores: Não\n\n24 - CONDIÇÕES DO CONTRATO\nFaturação Eletrónica: Permitido\nObrigação de Subcontratação:\nCódigo da Obrigação de Subcontratação: O contratante tem de indicar qualquer mudança de subcontratantes durante a execução do contrato.\n\n25 - COMPRA PÚBLICA ESTRATÉGICA\nCompra Pública Estratégica: Inexistência de contratação pública estratégica\n\n26 - INFORMAÇÕES ADICIONAIS\nContrato adequado para PME: Sim\nCobertura ACP (Acordo dos Contratos Públicos da Organização Mundial do Comércio): Não\n\n27 - IDENTIFICAÇÃO E CONTACTOS DO ÓRGÃO DE RECURSOS ADMINISTRATIVOS\nDesignação: Municipio de Borba\nEndereço: PRAÇA DA REPUBLICA\nCódigo postal: 7150-249\nLocalidade: BORBA\nTelefone: 268891630\nFax: \nEndereço eletrónico: geral@cm-borba.pt\nPrazo de interposição do recurso: 90 dias\n\n28 - IDENTIFICAÇÃO DO(S) AUTOR(ES) DE ANÚNCIO\nNome: Maria Fátima Santos Cabaço\nCargo: Assistente Técnica\n419939418",
    "nipc": "503956546",
    "distrito": "Évora",
    "concelho": "Borba",
    "freguesia": "Freguesia de Borba (Matriz)",
    "site": "www.cm-borba.pt",
    "email": "contratacaopublica@cm-borba.pt",
    "designacao_contrato": "Melhoria de Eficiência Energética do Centro Escolar de Borba",
    "descricao": "Empreitada de melhoria de Eficiência Energética do Centro Escolar de Borba",
    "preco_base": "856.266,07 EUR",
    "prazo_execucao": "210 DIAS",
    "prazo_apresentacao_propostas": "30-01-2026 23:59",
    "fundos_eu": "Sim",
    "plataforma_eletronica": "VORTAL",
    "url_procedimento": "www.cm-borba.pt",
    "autor_nome": "Maria Fátima Santos Cabaço",
    "autor_cargo": "Assistente Técnica"
  },
  {
    "numero_procedimento": "N/A",
    "entidade": "Município da Maia",
    "link": "https://diariodarepublica.pt/dr/detalhe/contrato-publico/33652-993270159",
    "detalhes_completos": "1 - IDENTIFICAÇÃO E CONTACTOS DA ENTIDADE ADJUDICANTE\nDesignação da entidade adjudicante: Município da Maia\nNIPC: 505387131\nServiço/Órgão/Pessoa de contacto: Presidente da Câmara\nEndereço: Praça Dr. José Vieira de Carvalho\nCódigo postal: 4470-202\nLocalidade: Maia\nPaís: Portugal\nNUT III: PT11A\nDistrito: Porto\nConcelho: Maia\nFreguesia: Todas\nTelefone: 229408600\nFax: 229418411\nEndereço da Entidade (URL): www.cm-maia.pt\nEndereço Eletrónico: geral@cm-maia.pt\neDelivery Gateway (URL): https://www.acingov.pt\nFunção da Organização: Adquirente\nSubfunção da Organização: Organização que recebe as propostas\nNorma jurídica da Entidade Adjudicante: Autoridade local\nÁrea de atividade da Autoridade Adjudicante: Serviços públicos das administrações públicas\n\n2 - JORNAL OFICIAL DA UNIÃO EUROPEIA\nO procedimento a que este anúncio diz respeito também é publicitado no Jornal Oficial da União Europeia? Não\n\n3 - AVISO\nModelo de Anúncio: Concurso público\nData de Envio do Anúncio: 30-12-2025\n\n5 - PROCESSO\nTipo de Procedimento: Concurso público\nPreço base do procedimento: Sim\nValor do preço base do procedimento: 219.917,57 EUR\nProcedimento com lotes? Não\n\n6 - OBJETO DO CONTRATO\nNúmero de referência interna: 1126/2025\nDesignação do contrato: PROCEDIMENTO N.º 1126/2025 - AQUISIÇÃO DE EQUIPAMENTO PARA A CRIAÇÃO DE 8 SALAS DE AMBIENTE MULTISSENSORIAL DESTINADAS A CRIANÇAS COM NECESSIDADES DE SAÚDE ESPECIAIS (CANDIDATURA AO INVESTIMENTO RE-C03-I0603, OPERAÇÕES INTEGRADAS EM COMUNIDADES DESFAVORECIDAS NA AMP, APOIADA PELO PRR\nDescrição: UISIÇÃO DE EQUIPAMENTO PARA A CRIAÇÃO DE 8 SALAS DE AMBIENTE MULTISSENSORIAL DESTINADAS A CRIANÇAS COM NECESSIDADES DE SAÚDE ESPECIAIS (CANDIDATURA AO INVESTIMENTO RE-C03-I0603, OPERAÇÕES INTEGRADAS EM COMUNIDADES DESFAVORECIDAS NA AMP, APOIADA PELO PRR\nTipo de Contrato Principal: Aquisição de Bens Móveis\nTipo de Contrato: Aquisição de Bens Móveis\nClassificação CPV (Vocabulário Comum para os Contratos Públicos)\nObjeto principal\nVocabulário Principal: 39162000\nPreço base s/IVA: 219.917,57 EUR\n\n7 - INDICAÇÕES ADICIONAIS\nO contrato envolve aquisição conjunta (satisfação de várias entidades)? Não\nO contrato é adjudicado por uma central de compras? Não\n\n8 - TÉCNICAS\nO concurso destina-se à celebração de um acordo-quadro? Inexistência de acordo-quadro\nÉ utilizado um leilão eletrónico? Não\nÉ adotada uma fase de negociação? Não\nSistema de Aquisição Dinâmico: Inexistência de sistema de aquisição dinâmico\n\n9 - LOCAL DA EXECUÇÃO DO CONTRATO\nLOCAL DA EXECUÇÃO DO CONTRATO (PROCEDIMENTO)\nPaís: Portugal\nNUT III: PT11A\nLocalidade: Cidade da Maia\nDistrito: Porto\nConcelho: Maia\nFreguesia: Todas\n\n10 - PRAZO DE EXECUÇÃO DO CONTRATO\nPrazo de execução do contrato: 12 MESES\nPrevisão de renovações: Não\n\n11 - FUNDOS EU\nTêm fundos EU? Sim\n\n12 - DOCUMENTOS DE HABILITAÇÃO\nHabilitação para o exercício da atividade profissional: Não\n\n13 - CONDIÇÕES DE APRESENTAÇÃO\nPlataforma eletrónica utilizada pela entidade adjudicante: ACIN\nURL para Apresentação: https://www.acingov.pt\nAdmissibilidade da apresentação de propostas variantes: Não autorizado\nPrazo para apresentação das propostas: 12-01-2026 23:59\nPrazo durante o qual os concorrentes são obrigados a manter as respetivas propostas: 66 dias a contar do termo do prazo para a apresentação das propostas\nIndicação de Subcontratação na Proposta: Inexistência de indicação de subcontratação\n\n14 - PRESTAÇÃO DE CAUÇÃO\nPrestação de caução: Não\n\n15 - FORNECIMENTO DAS PEÇAS DO CONCURSO, APRESENTAÇÃO DE PEDIDOS DE PARTICIPAÇÃO E APRESENTAÇÃO DAS PROPOSTAS\nLink para acesso às peças do concurso (URL): https://www.acingov.pt/acingovprod/2/zonaPublica/zona_publica_c/donwloadProcedurePiece/MTAxMzE4NQ==\n\n20 - OUTROS REQUISITOS\nInformação sobre contratos reservados. Aplica-se a contratos reservados (54º-A)? Não\n\n21 - CRITÉRIO DE ADJUDICAÇÃO\nMultifator: Não\nMonofator:\nNome: Preço\n\n24 - CONDIÇÕES DO CONTRATO\nFaturação Eletrónica: Permitido\nObrigação de Subcontratação:\nCódigo da Obrigação de Subcontratação: Não é aplicável nenhuma obrigação de subcontratação.\n\n25 - COMPRA PÚBLICA ESTRATÉGICA\nCompra Pública Estratégica: Inexistência de contratação pública estratégica\n\n26 - INFORMAÇÕES ADICIONAIS\nContrato adequado para PME: Sim\nCobertura ACP (Acordo dos Contratos Públicos da Organização Mundial do Comércio): Não\n\n27 - IDENTIFICAÇÃO E CONTACTOS DO ÓRGÃO DE RECURSOS ADMINISTRATIVOS\nDesignação: Presidente da Câmara Municipal da Maia\nEndereço: Praça do Dr.José Vieira de Carvalho\nCódigo postal: 4474-006\nLocalidade: Maia\nTelefone: 351229408600\nFax: 351229480901\nEndereço eletrónico: presidencia@cm-maia.pt\nPrazo de interposição do recurso: 5 dias\n\n28 - IDENTIFICAÇÃO DO(S) AUTOR(ES) DE ANÚNCIO\nNome: António Domingos da Silva Tiago\nCargo: Presidente da Câmara Municipal da Maia\n419944107",
    "nipc": "505387131",
    "distrito": "Porto",
    "concelho": "Maia",
    "freguesia": "Todas",
    "site": "www.cm-maia.pt",
    "email": "geral@cm-maia.pt",
    "designacao_contrato": "PROCEDIMENTO N.º 1126/2025 - AQUISIÇÃO DE EQUIPAMENTO PARA A CRIAÇÃO DE 8 SALAS DE AMBIENTE MULTISSENSORIAL DESTINADAS A CRIANÇAS COM NECESSIDADES DE SAÚDE ESPECIAIS (CANDIDATURA AO INVESTIMENTO RE-C03-I0603, OPERAÇÕES INTEGRADAS EM COMUNIDADES DESFAVORECIDAS NA AMP, APOIADA PELO PRR",
    "descricao": "UISIÇÃO DE EQUIPAMENTO PARA A CRIAÇÃO DE 8 SALAS DE AMBIENTE MULTISSENSORIAL DESTINADAS A CRIANÇAS COM NECESSIDADES DE SAÚDE ESPECIAIS (CANDIDATURA AO INVESTIMENTO RE-C03-I0603, OPERAÇÕES INTEGRADAS EM COMUNIDADES DESFAVORECIDAS NA AMP, APOIADA PELO PRR",
    "preco_base": "219.917,57 EUR",
    "prazo_execucao": "12 MESES",
    "prazo_apresentacao_propostas": "12-01-2026 23:59",
    "fundos_eu": "Sim",
    "plataforma_eletronica": "ACIN",
    "url_procedimento": "https://www.acingov.pt",
    "autor_nome": "António Domingos da Silva Tiago",
    "autor_cargo": "Presidente da Câmara Municipal da Maia"
  },
  {
    "numero_procedimento": "N/A",
    "entidade": "Unidade Local de Saúde de Loures-Odivelas, EPE",
    "link": "https://diariodarepublica.pt/dr/detalhe/contrato-publico/33654-993270172",
    "detalhes_completos": "1 - IDENTIFICAÇÃO E CONTACTOS DA ENTIDADE ADJUDICANTE\nDesignação da entidade adjudicante: Unidade Local de Saúde de Loures-Odivelas, EPE\nNIPC: 516726862\nEndereço: Avenida Carlos Teixeira nº 3\nCódigo postal: 2674-514\nLocalidade: Lisboa\nPaís: Portugal\nNUT III: PT170\nDistrito: Lisboa\nConcelho: Loures\nFreguesia: Freguesia de Loures\nTelefone: 939007019\nFax: 219847200\nEndereço da Entidade (URL): https://www.hbeatrizangelo.pt\nEndereço Eletrónico: andreia.teixeira.chaves@ulslod.min-saude.pt\neDelivery Gateway (URL): https://community.vortal.biz/public/\nFunção da Organização: Adquirente\nNorma jurídica da Entidade Adjudicante: Empresa pública\nÁrea de atividade da Autoridade Adjudicante: Saúde\n\n2 - JORNAL OFICIAL DA UNIÃO EUROPEIA\nO procedimento a que este anúncio diz respeito também é publicitado no Jornal Oficial da União Europeia? Não\n\n3 - AVISO\nModelo de Anúncio: Concurso público\nData de Envio do Anúncio: 30-12-2025\n\n5 - PROCESSO\nTipo de Procedimento: Concurso público\nPreço base do procedimento: Sim\nValor do preço base do procedimento: 88.387,07 EUR\nProcedimento com lotes? Sim\nNº Máx. de Lotes Autorizado: 33\nNúmero máximo de lotes que podem ser adjudicados a um concorrente: 33\n\n6 - OBJETO DO CONTRATO\nNúmero de referência interna: 040000004532026\nDesignação do contrato: PENSOS E MATERIAL DE APOIO PARA O ANO DE 2026\nDescrição: PENSOS E MATERIAL DE APOIO PARA O ANO DE 2026\nTipo de Contrato Principal: Aquisição de Bens Móveis\nTipo de Contrato: Aquisição de Bens Móveis\nClassificação CPV (Vocabulário Comum para os Contratos Públicos)\nObjeto principal\nVocabulário Principal: 33141110\nPreço base s/IVA: 88.387,07 EUR\nLotes: \nNº: LOT-0001\nDescrição do Lote: Lote 1\nPreço base s/IVA: 1.428,04 EUR\nClassificação CPV (Vocabulário Comum para os Contratos Públicos)\nObjeto principal\nVocabulário Principal: 33141110\nNº: LOT-0002\nDescrição do Lote: Lote 2\nPreço base s/IVA: 38.471,89 EUR\nClassificação CPV (Vocabulário Comum para os Contratos Públicos)\nObjeto principal\nVocabulário Principal: 33141110\nNº: LOT-0003\nDescrição do Lote: Lote 3\nPreço base s/IVA: 12.051,84 EUR\nClassificação CPV (Vocabulário Comum para os Contratos Públicos)\nObjeto principal\nVocabulário Principal: 33141110\nNº: LOT-0004\nDescrição do Lote: Lote 4\nPreço base s/IVA: 6.701,08 EUR\nClassificação CPV (Vocabulário Comum para os Contratos Públicos)\nObjeto principal\nVocabulário Principal: 33141110\nNº: LOT-0005\nDescrição do Lote: Lote 5\nPreço base s/IVA: 1.784,08 EUR\nClassificação CPV (Vocabulário Comum para os Contratos Públicos)\nObjeto principal\nVocabulário Principal: 33141110\nNº: LOT-0006\nDescrição do Lote: Lote 6\nPreço base s/IVA: 889,44 EUR\nClassificação CPV (Vocabulário Comum para os Contratos Públicos)\nObjeto principal\nVocabulário Principal: 33141110\nNº: LOT-0007\nDescrição do Lote: Lote 7\nPreço base s/IVA: 798,15 EUR\nClassificação CPV (Vocabulário Comum para os Contratos Públicos)\nObjeto principal\nVocabulário Principal: 33141110\nNº: LOT-0008\nDescrição do Lote: Lote 8\nPreço base s/IVA: 36,25 EUR\nClassificação CPV (Vocabulário Comum para os Contratos Públicos)\nObjeto principal\nVocabulário Principal: 33141110\nNº: LOT-0009\nDescrição do Lote: Lote 9\nPreço base s/IVA: 460,85 EUR\nClassificação CPV (Vocabulário Comum para os Contratos Públicos)\nObjeto principal\nVocabulário Principal: 33141110\nNº: LOT-0010\nDescrição do Lote: Lote 10\nPreço base s/IVA: 949,94 EUR\nClassificação CPV (Vocabulário Comum para os Contratos Públicos)\nObjeto principal\nVocabulário Principal: 33141110\nNº: LOT-0011\nDescrição do Lote: Lote 11\nPreço base s/IVA: 2.840,07 EUR\nClassificação CPV (Vocabulário Comum para os Contratos Públicos)\nObjeto principal\nVocabulário Principal: 33141110\nNº: LOT-0012\nDescrição do Lote: Lote 12\nPreço base s/IVA: 193,56 EUR\nClassificação CPV (Vocabulário Comum para os Contratos Públicos)\nObjeto principal\nVocabulário Principal: 33141110\nNº: LOT-0013\nDescrição do Lote: Lote 13\nPreço base s/IVA: 256,87 EUR\nClassificação CPV (Vocabulário Comum para os Contratos Públicos)\nObjeto principal\nVocabulário Principal: 33141110\nNº: LOT-0014\nDescrição do Lote: Lote 14\nPreço base s/IVA: 169,74 EUR\nClassificação CPV (Vocabulário Comum para os Contratos Públicos)\nObjeto principal\nVocabulário Principal: 33141110\nNº: LOT-0015\nDescrição do Lote: Lote 15\nPreço base s/IVA: 1.678,92 EUR\nClassificação CPV (Vocabulário Comum para os Contratos Públicos)\nObjeto principal\nVocabulário Principal: 33141110\nNº: LOT-0016\nDescrição do Lote: Lote 16\nPreço base s/IVA: 1.406,05 EUR\nClassificação CPV (Vocabulário Comum para os Contratos Públicos)\nObjeto principal\nVocabulário Principal: 33141110\nNº: LOT-0017\nDescrição do Lote: Lote 17\nPreço base s/IVA: 1.378,90 EUR\nClassificação CPV (Vocabulário Comum para os Contratos Públicos)\nObjeto principal\nVocabulário Principal: 33141110\nNº: LOT-0018\nDescrição do Lote: Lote 18\nPreço base s/IVA: 1.932,28 EUR\nClassificação CPV (Vocabulário Comum para os Contratos Públicos)\nObjeto principal\nVocabulário Principal: 33141110\nNº: LOT-0019\nDescrição do Lote: Lote 19\nPreço base s/IVA: 115,31 EUR\nClassificação CPV (Vocabulário Comum para os Contratos Públicos)\nObjeto principal\nVocabulário Principal: 33141110\nNº: LOT-0020\nDescrição do Lote: Lote 20\nPreço base s/IVA: 38,95 EUR\nClassificação CPV (Vocabulário Comum para os Contratos Públicos)\nObjeto principal\nVocabulário Principal: 33141110\nNº: LOT-0021\nDescrição do Lote: Lote 21\nPreço base s/IVA: 26,80 EUR\nClassificação CPV (Vocabulário Comum para os Contratos Públicos)\nObjeto principal\nVocabulário Principal: 33141110\nNº: LOT-0022\nDescrição do Lote: Lote 22\nPreço base s/IVA: 612,95 EUR\nClassificação CPV (Vocabulário Comum para os Contratos Públicos)\nObjeto principal\nVocabulário Principal: 33141110\nNº: LOT-0023\nDescrição do Lote: Lote 23\nPreço base s/IVA: 651,62 EUR\nClassificação CPV (Vocabulário Comum para os Contratos Públicos)\nObjeto principal\nVocabulário Principal: 33141110\nNº: LOT-0024\nDescrição do Lote: Lote 24\nPreço base s/IVA: 47,81 EUR\nClassificação CPV (Vocabulário Comum para os Contratos Públicos)\nObjeto principal\nVocabulário Principal: 33141110\nNº: LOT-0025\nDescrição do Lote: Lote 25\nPreço base s/IVA: 369,31 EUR\nClassificação CPV (Vocabulário Comum para os Contratos Públicos)\nObjeto principal\nVocabulário Principal: 33141110\nNº: LOT-0026\nDescrição do Lote: Lote 26\nPreço base s/IVA: 205,00 EUR\nClassificação CPV (Vocabulário Comum para os Contratos Públicos)\nObjeto principal\nVocabulário Principal: 33141110\nNº: LOT-0027\nDescrição do Lote: Lote 27\nPreço base s/IVA: 245,75 EUR\nClassificação CPV (Vocabulário Comum para os Contratos Públicos)\nObjeto principal\nVocabulário Principal: 33141110\nNº: LOT-0028\nDescrição do Lote: Lote 28\nPreço base s/IVA: 2.995,81 EUR\nClassificação CPV (Vocabulário Comum para os Contratos Públicos)\nObjeto principal\nVocabulário Principal: 33141110\nNº: LOT-0029\nDescrição do Lote: Lote 29\nPreço base s/IVA: 5.350,50 EUR\nClassificação CPV (Vocabulário Comum para os Contratos Públicos)\nObjeto principal\nVocabulário Principal: 33141110\nNº: LOT-0030\nDescrição do Lote: Lote 30\nPreço base s/IVA: 2.124,13 EUR\nClassificação CPV (Vocabulário Comum para os Contratos Públicos)\nObjeto principal\nVocabulário Principal: 33141110\nNº: LOT-0031\nDescrição do Lote: Lote 31\nPreço base s/IVA: 832,30 EUR\nClassificação CPV (Vocabulário Comum para os Contratos Públicos)\nObjeto principal\nVocabulário Principal: 33141110\nNº: LOT-0032\nDescrição do Lote: Lote 32\nPreço base s/IVA: 344,40 EUR\nClassificação CPV (Vocabulário Comum para os Contratos Públicos)\nObjeto principal\nVocabulário Principal: 33141110\nNº: LOT-0033\nDescrição do Lote: Lote 33\nPreço base s/IVA: 998,48 EUR\nClassificação CPV (Vocabulário Comum para os Contratos Públicos)\nObjeto principal\nVocabulário Principal: 33141110\n\n7 - INDICAÇÕES ADICIONAIS\nO contrato envolve aquisição conjunta (satisfação de várias entidades)? Não\nO contrato é adjudicado por uma central de compras? Não\n\n8 - TÉCNICAS\nO concurso destina-se à celebração de um acordo-quadro? Inexistência de acordo-quadro\nÉ utilizado um leilão eletrónico? Não\nÉ adotada uma fase de negociação? Não\nSistema de Aquisição Dinâmico: Inexistência de sistema de aquisição dinâmico\n\n9 - LOCAL DA EXECUÇÃO DO CONTRATO\nLOCAL DA EXECUÇÃO DO CONTRATO (PROCEDIMENTO)\nPaís: Portugal\nNUT III: PT170\nLocalidade: Lisboa\nDistrito: Lisboa\nConcelho: Loures\nFreguesia: Freguesia de Loures\nLOCAL DA EXECUÇÃO DO CONTRATO (LOTE)\nIdentificador do Lote: LOT-0001; LOT-0002; LOT-0003; LOT-0004; LOT-0005; LOT-0006; LOT-0007; LOT-0008; LOT-0009; LOT-0010; LOT-0011; LOT-0012; LOT-0013; LOT-0014; LOT-0015; LOT-0016; LOT-0017; LOT-0018; LOT-0019; LOT-0020; LOT-0021; LOT-0022; LOT-0023; LOT-0024; LOT-0025; LOT-0026; LOT-0027; LOT-0028; LOT-0029; LOT-0030; LOT-0031; LOT-0032; LOT-0033\nPaís: Portugal\nNUT III: PT170\nLocalidade: Lisboa\nDistrito: Lisboa\nConcelho: Loures\nFreguesia: Freguesia de Loures\n\n10 - PRAZO DE EXECUÇÃO DO CONTRATO\nIdentificador do Lote: LOT-0001; LOT-0002; LOT-0003; LOT-0004; LOT-0005; LOT-0006; LOT-0007; LOT-0008; LOT-0009; LOT-0010; LOT-0011; LOT-0012; LOT-0013; LOT-0014; LOT-0015; LOT-0016; LOT-0017; LOT-0018; LOT-0019; LOT-0020; LOT-0021; LOT-0022; LOT-0023; LOT-0024; LOT-0025; LOT-0026; LOT-0027; LOT-0028; LOT-0029; LOT-0030; LOT-0031; LOT-0032; LOT-0033\nPrazo de execução do contrato: 12 MESES\nPrevisão de renovações: Não\n\n11 - FUNDOS EU\nIdentificador do Lote: LOT-0001; LOT-0002; LOT-0003; LOT-0004; LOT-0005; LOT-0006; LOT-0007; LOT-0008; LOT-0009; LOT-0010; LOT-0011; LOT-0012; LOT-0013; LOT-0014; LOT-0015; LOT-0016; LOT-0017; LOT-0018; LOT-0019; LOT-0020; LOT-0021; LOT-0022; LOT-0023; LOT-0024; LOT-0025; LOT-0026; LOT-0027; LOT-0028; LOT-0029; LOT-0030; LOT-0031; LOT-0032; LOT-0033\nTêm fundos EU? Não\n\n12 - DOCUMENTOS DE HABILITAÇÃO\nHabilitação para o exercício da atividade profissional: Não\n\n13 - CONDIÇÕES DE APRESENTAÇÃO\nPlataforma eletrónica utilizada pela entidade adjudicante: VORTAL\nURL para Apresentação: https://community.vortal.biz/public/\nAdmissibilidade da apresentação de propostas variantes: Não autorizado\nPrazo para apresentação das propostas: 08-01-2026 17:00\nPrazo durante o qual os concorrentes são obrigados a manter as respetivas propostas: 90 dias a contar do termo do prazo para a apresentação das propostas\nIndicação de Subcontratação na Proposta: Inexistência de indicação de subcontratação\n\n14 - PRESTAÇÃO DE CAUÇÃO\nPrestação de caução: Não\n\n15 - FORNECIMENTO DAS PEÇAS DO CONCURSO, APRESENTAÇÃO DE PEDIDOS DE PARTICIPAÇÃO E APRESENTAÇÃO DAS PROPOSTAS\nLink para acesso às peças do concurso (URL): https://community.vortal.biz/Public/public-tender-documents/M1AwUVYySXoxUWNlV2Y4Uld1Wm9hTndrNnd4RGZYRS8vbHU1Y3NhK2o3V0lGeUcvZTFaaFpwbXNhVXo5S3lBNWx3QjJZVVpmSzVYSHVodlNuVEtIRVE9PUpZKjgq\n\n20 - OUTROS REQUISITOS\nIdentificador do Lote: LOT-0001; LOT-0002; LOT-0003; LOT-0004; LOT-0005; LOT-0006; LOT-0007; LOT-0008; LOT-0009; LOT-0010; LOT-0011; LOT-0012; LOT-0013; LOT-0014; LOT-0015; LOT-0016; LOT-0017; LOT-0018; LOT-0019; LOT-0020; LOT-0021; LOT-0022; LOT-0023; LOT-0024; LOT-0025; LOT-0026; LOT-0027; LOT-0028; LOT-0029; LOT-0030; LOT-0031; LOT-0032; LOT-0033\nInformação sobre contratos reservados. Aplica-se a contratos reservados (54º-A)? Não\n\n21 - CRITÉRIO DE ADJUDICAÇÃO\nO Critério de adjudicação é diferenciado por lote? Sim\nIdentificador do lote: LOT-0001\nMultifator: Não\nMonofator:\nNome: Preço\nO Critério de adjudicação é diferenciado por lote? Sim\nIdentificador do lote: LOT-0002\nMultifator: Não\nMonofator:\nNome: Preço\nO Critério de adjudicação é diferenciado por lote? Sim\nIdentificador do lote: LOT-0003\nMultifator: Não\nMonofator:\nNome: Preço\nO Critério de adjudicação é diferenciado por lote? Sim\nIdentificador do lote: LOT-0004\nMultifator: Não\nMonofator:\nNome: Preço\nO Critério de adjudicação é diferenciado por lote? Sim\nIdentificador do lote: LOT-0005\nMultifator: Não\nMonofator:\nNome: Preço\nO Critério de adjudicação é diferenciado por lote? Sim\nIdentificador do lote: LOT-0006\nMultifator: Não\nMonofator:\nNome: Preço\nO Critério de adjudicação é diferenciado por lote? Sim\nIdentificador do lote: LOT-0007\nMultifator: Não\nMonofator:\nNome: Preço\nO Critério de adjudicação é diferenciado por lote? Sim\nIdentificador do lote: LOT-0008\nMultifator: Não\nMonofator:\nNome: Preço\nO Critério de adjudicação é diferenciado por lote? Sim\nIdentificador do lote: LOT-0009\nMultifator: Não\nMonofator:\nNome: Preço\nO Critério de adjudicação é diferenciado por lote? Sim\nIdentificador do lote: LOT-0010\nMultifator: Não\nMonofator:\nNome: Preço\nO Critério de adjudicação é diferenciado por lote? Sim\nIdentificador do lote: LOT-0011\nMultifator: Não\nMonofator:\nNome: Preço\nO Critério de adjudicação é diferenciado por lote? Sim\nIdentificador do lote: LOT-0012\nMultifator: Não\nMonofator:\nNome: Preço\nO Critério de adjudicação é diferenciado por lote? Sim\nIdentificador do lote: LOT-0013\nMultifator: Não\nMonofator:\nNome: Preço\nO Critério de adjudicação é diferenciado por lote? Sim\nIdentificador do lote: LOT-0014\nMultifator: Não\nMonofator:\nNome: Preço\nO Critério de adjudicação é diferenciado por lote? Sim\nIdentificador do lote: LOT-0015\nMultifator: Não\nMonofator:\nNome: Preço\nO Critério de adjudicação é diferenciado por lote? Sim\nIdentificador do lote: LOT-0016\nMultifator: Não\nMonofator:\nNome: Preço\nO Critério de adjudicação é diferenciado por lote? Sim\nIdentificador do lote: LOT-0017\nMultifator: Não\nMonofator:\nNome: Preço\nO Critério de adjudicação é diferenciado por lote? Sim\nIdentificador do lote: LOT-0018\nMultifator: Não\nMonofator:\nNome: Preço\nO Critério de adjudicação é diferenciado por lote? Sim\nIdentificador do lote: LOT-0019\nMultifator: Não\nMonofator:\nNome: Preço\nO Critério de adjudicação é diferenciado por lote? Sim\nIdentificador do lote: LOT-0020\nMultifator: Não\nMonofator:\nNome: Preço\nO Critério de adjudicação é diferenciado por lote? Sim\nIdentificador do lote: LOT-0021\nMultifator: Não\nMonofator:\nNome: Preço\nO Critério de adjudicação é diferenciado por lote? Sim\nIdentificador do lote: LOT-0022\nMultifator: Não\nMonofator:\nNome: Preço\nO Critério de adjudicação é diferenciado por lote? Sim\nIdentificador do lote: LOT-0023\nMultifator: Não\nMonofator:\nNome: Preço\nO Critério de adjudicação é diferenciado por lote? Sim\nIdentificador do lote: LOT-0024\nMultifator: Não\nMonofator:\nNome: Preço\nO Critério de adjudicação é diferenciado por lote? Sim\nIdentificador do lote: LOT-0025\nMultifator: Não\nMonofator:\nNome: Preço\nO Critério de adjudicação é diferenciado por lote? Sim\nIdentificador do lote: LOT-0026\nMultifator: Não\nMonofator:\nNome: Preço\nO Critério de adjudicação é diferenciado por lote? Sim\nIdentificador do lote: LOT-0027\nMultifator: Não\nMonofator:\nNome: Preço\nO Critério de adjudicação é diferenciado por lote? Sim\nIdentificador do lote: LOT-0028\nMultifator: Não\nMonofator:\nNome: Preço\nO Critério de adjudicação é diferenciado por lote? Sim\nIdentificador do lote: LOT-0029\nMultifator: Não\nMonofator:\nNome: Preço\nO Critério de adjudicação é diferenciado por lote? Sim\nIdentificador do lote: LOT-0030\nMultifator: Sim\nFator: \nNome: Preço\nPonderação: 50%\nSubfatores: Não\nFator: \nNome: Qualidade\nPonderação: 50%\nSubfatores: Não\nO Critério de adjudicação é diferenciado por lote? Sim\nIdentificador do lote: LOT-0031\nMultifator: Não\nMonofator:\nNome: Preço\nO Critério de adjudicação é diferenciado por lote? Sim\nIdentificador do lote: LOT-0032\nMultifator: Não\nMonofator:\nNome: Preço\nO Critério de adjudicação é diferenciado por lote? Sim\nIdentificador do lote: LOT-0033\nMultifator: Não\nMonofator:\nNome: Preço\n\n24 - CONDIÇÕES DO CONTRATO\nIdentificador do Lote: LOT-0001; LOT-0002; LOT-0003; LOT-0004; LOT-0005; LOT-0006; LOT-0007; LOT-0008; LOT-0009; LOT-0010; LOT-0011; LOT-0012; LOT-0013; LOT-0014; LOT-0015; LOT-0016; LOT-0017; LOT-0018; LOT-0019; LOT-0020; LOT-0021; LOT-0022; LOT-0023; LOT-0024; LOT-0025; LOT-0026; LOT-0027; LOT-0028; LOT-0029; LOT-0030; LOT-0031; LOT-0032; LOT-0033\nFaturação Eletrónica: Permitido\nObrigação de Subcontratação:\nCódigo da Obrigação de Subcontratação: Não é aplicável nenhuma obrigação de subcontratação.\n\n25 - COMPRA PÚBLICA ESTRATÉGICA\nCompra Pública Estratégica: Inexistência de contratação pública estratégica\n\n26 - INFORMAÇÕES ADICIONAIS\nIdentificador do Lote: LOT-0001; LOT-0002; LOT-0003; LOT-0004; LOT-0005; LOT-0006; LOT-0007; LOT-0008; LOT-0009; LOT-0010; LOT-0011; LOT-0012; LOT-0013; LOT-0014; LOT-0015; LOT-0016; LOT-0017; LOT-0018; LOT-0019; LOT-0020; LOT-0021; LOT-0022; LOT-0023; LOT-0024; LOT-0025; LOT-0026; LOT-0027; LOT-0028; LOT-0029; LOT-0030; LOT-0031; LOT-0032; LOT-0033\nContrato adequado para PME: Sim\nCobertura ACP (Acordo dos Contratos Públicos da Organização Mundial do Comércio): Não\n\n27 - IDENTIFICAÇÃO E CONTACTOS DO ÓRGÃO DE RECURSOS ADMINISTRATIVOS\nDesignação: Unidade Local de Saúde de Loures-Odivelas, E.P.E\nEndereço: Av. Carlos Teixeira, 3\nCódigo postal: 2674-514\nLocalidade: Loures\nTelefone: +351 219847200\nFax: +351 219847209\nEndereço eletrónico: Compras_hba@ulslod.min-saude.pt\n\n28 - IDENTIFICAÇÃO DO(S) AUTOR(ES) DE ANÚNCIO\nNome: Manuela Santos\nCargo: Técnica Superior\n419933172",
    "nipc": "516726862",
    "distrito": "Lisboa",
    "concelho": "Loures",
    "freguesia": "Freguesia de Loures",
    "site": "https://www.hbeatrizangelo.pt",
    "email": "andreia.teixeira.chaves@ulslod.min-saude.pt",
    "designacao_contrato": "PENSOS E MATERIAL DE APOIO PARA O ANO DE 2026",
    "descricao": "PENSOS E MATERIAL DE APOIO PARA O ANO DE 2026",
    "preco_base": "88.387,07 EUR",
    "prazo_execucao": "12 MESES",
    "prazo_apresentacao_propostas": "08-01-2026 17:00",
    "fundos_eu": "Não",
    "plataforma_eletronica": "VORTAL",
    "url_procedimento": "https://community.vortal.biz/public/",
    "autor_nome": "Manuela Santos",
    "autor_cargo": "Técnica Superior"
  },
  {
    "numero_procedimento": "N/A",
    "entidade": "Unidade Local de Saúde de Loures-Odivelas, EPE",
    "link": "https://diariodarepublica.pt/dr/detalhe/contrato-publico/33655-993270173",
    "detalhes_completos": "1 - IDENTIFICAÇÃO E CONTACTOS DA ENTIDADE ADJUDICANTE\nDesignação da entidade adjudicante: Unidade Local de Saúde de Loures-Odivelas, EPE\nNIPC: 516726862\nEndereço: Avenida Carlos Teixeira nº 3\nCódigo postal: 2674-514\nLocalidade: Lisboa\nPaís: Portugal\nNUT III: PT170\nDistrito: Lisboa\nConcelho: Loures\nFreguesia: Freguesia de Loures\nTelefone: 939007019\nFax: 219847200\nEndereço da Entidade (URL): https://www.hbeatrizangelo.pt\nEndereço Eletrónico: andreia.teixeira.chaves@ulslod.min-saude.pt\neDelivery Gateway (URL): https://community.vortal.biz/public/\nFunção da Organização: Adquirente\nNorma jurídica da Entidade Adjudicante: Empresa pública\nÁrea de atividade da Autoridade Adjudicante: Saúde\n\n2 - JORNAL OFICIAL DA UNIÃO EUROPEIA\nO procedimento a que este anúncio diz respeito também é publicitado no Jornal Oficial da União Europeia? Não\n\n3 - AVISO\nModelo de Anúncio: Concurso público\nData de Envio do Anúncio: 30-12-2025\n\n5 - PROCESSO\nTipo de Procedimento: Concurso público\nPreço base do procedimento: Sim\nValor do preço base do procedimento: 41.240,16 EUR\nProcedimento com lotes? Sim\nNº Máx. de Lotes Autorizado: 18\nNúmero máximo de lotes que podem ser adjudicados a um concorrente: 18\n\n6 - OBJETO DO CONTRATO\nNúmero de referência interna: 04000004522026 \nDesignação do contrato: PROLONGADORES, TUBOS E DM RESPIRATÓRIOS PARA 2026\nDescrição: PROLONGADORES, TUBOS E DM RESPIRATÓRIOS PARA 2026\nTipo de Contrato Principal: Aquisição de Bens Móveis\nTipo de Contrato: Aquisição de Bens Móveis\nClassificação CPV (Vocabulário Comum para os Contratos Públicos)\nObjeto principal\nVocabulário Principal: 33141240\nPreço base s/IVA: 41.240,16 EUR\nLotes: \nNº: LOT-0001\nDescrição do Lote: Lote 1\nPreço base s/IVA: 16.961,49 EUR\nClassificação CPV (Vocabulário Comum para os Contratos Públicos)\nObjeto principal\nVocabulário Principal: 33141240\nNº: LOT-0002\nDescrição do Lote: Lote 2\nPreço base s/IVA: 600,64 EUR\nClassificação CPV (Vocabulário Comum para os Contratos Públicos)\nObjeto principal\nVocabulário Principal: 33141240\nNº: LOT-0003\nDescrição do Lote: Lote 3\nPreço base s/IVA: 33,55 EUR\nClassificação CPV (Vocabulário Comum para os Contratos Públicos)\nObjeto principal\nVocabulário Principal: 33141240\nNº: LOT-0004\nDescrição do Lote: Lote 4\nPreço base s/IVA: 10,81 EUR\nClassificação CPV (Vocabulário Comum para os Contratos Públicos)\nObjeto principal\nVocabulário Principal: 33141240\nNº: LOT-0005\nDescrição do Lote: Lote 5\nPreço base s/IVA: 155,12 EUR\nClassificação CPV (Vocabulário Comum para os Contratos Públicos)\nObjeto principal\nVocabulário Principal: 33141240\nNº: LOT-0006\nDescrição do Lote: Lote 6\nPreço base s/IVA: 81,37 EUR\nClassificação CPV (Vocabulário Comum para os Contratos Públicos)\nObjeto principal\nVocabulário Principal: 33141240\nNº: LOT-0007\nDescrição do Lote: Lote 7\nPreço base s/IVA: 1.579,84 EUR\nClassificação CPV (Vocabulário Comum para os Contratos Públicos)\nObjeto principal\nVocabulário Principal: 33141240\nNº: LOT-0008\nDescrição do Lote: Lote 8\nPreço base s/IVA: 6.359,10 EUR\nClassificação CPV (Vocabulário Comum para os Contratos Públicos)\nObjeto principal\nVocabulário Principal: 33141240\nNº: LOT-0009\nDescrição do Lote: Lote 9\nPreço base s/IVA: 2.414,90 EUR\nClassificação CPV (Vocabulário Comum para os Contratos Públicos)\nObjeto principal\nVocabulário Principal: 33141240\nNº: LOT-0010\nDescrição do Lote: Lote 10\nPreço base s/IVA: 1.918,84 EUR\nClassificação CPV (Vocabulário Comum para os Contratos Públicos)\nObjeto principal\nVocabulário Principal: 33141240\nNº: LOT-0011\nDescrição do Lote: Lote 11\nPreço base s/IVA: 4.535,83 EUR\nClassificação CPV (Vocabulário Comum para os Contratos Públicos)\nObjeto principal\nVocabulário Principal: 33141240\nNº: LOT-0012\nDescrição do Lote: Lote 12\nPreço base s/IVA: 1.209,60 EUR\nClassificação CPV (Vocabulário Comum para os Contratos Públicos)\nObjeto principal\nVocabulário Principal: 33141240\nNº: LOT-0013\nDescrição do Lote: Lote 13\nPreço base s/IVA: 52,79 EUR\nClassificação CPV (Vocabulário Comum para os Contratos Públicos)\nObjeto principal\nVocabulário Principal: 33141240\nNº: LOT-0014\nDescrição do Lote: Lote 14\nPreço base s/IVA: 2.446,47 EUR\nClassificação CPV (Vocabulário Comum para os Contratos Públicos)\nObjeto principal\nVocabulário Principal: 33141240\nNº: LOT-0015\nDescrição do Lote: Lote 15\nPreço base s/IVA: 1.793,75 EUR\nClassificação CPV (Vocabulário Comum para os Contratos Públicos)\nObjeto principal\nVocabulário Principal: 33141240\nNº: LOT-0016\nDescrição do Lote: Lote 16\nPreço base s/IVA: 816,00 EUR\nClassificação CPV (Vocabulário Comum para os Contratos Públicos)\nObjeto principal\nVocabulário Principal: 33141240\nNº: LOT-0017\nDescrição do Lote: Lote 17\nPreço base s/IVA: 120,00 EUR\nClassificação CPV (Vocabulário Comum para os Contratos Públicos)\nObjeto principal\nVocabulário Principal: 33141240\nNº: LOT-0018\nDescrição do Lote: Lote 18\nPreço base s/IVA: 150,06 EUR\nClassificação CPV (Vocabulário Comum para os Contratos Públicos)\nObjeto principal\nVocabulário Principal: 33141240\n\n7 - INDICAÇÕES ADICIONAIS\nO contrato envolve aquisição conjunta (satisfação de várias entidades)? Não\nO contrato é adjudicado por uma central de compras? Não\n\n8 - TÉCNICAS\nO concurso destina-se à celebração de um acordo-quadro? Inexistência de acordo-quadro\nÉ utilizado um leilão eletrónico? Não\nÉ adotada uma fase de negociação? Não\nSistema de Aquisição Dinâmico: Inexistência de sistema de aquisição dinâmico\n\n9 - LOCAL DA EXECUÇÃO DO CONTRATO\nLOCAL DA EXECUÇÃO DO CONTRATO (PROCEDIMENTO)\nPaís: Portugal\nNUT III: PT170\nLocalidade: Lisboa\nDistrito: Lisboa\nConcelho: Loures\nFreguesia: Freguesia de Loures\nLOCAL DA EXECUÇÃO DO CONTRATO (LOTE)\nIdentificador do Lote: LOT-0001; LOT-0002; LOT-0003; LOT-0004; LOT-0005; LOT-0006; LOT-0007; LOT-0008; LOT-0009; LOT-0010; LOT-0011; LOT-0012; LOT-0013; LOT-0014; LOT-0015; LOT-0016; LOT-0017; LOT-0018\nPaís: Portugal\nNUT III: PT170\nLocalidade: Lisboa\nDistrito: Lisboa\nConcelho: Loures\nFreguesia: Freguesia de Loures\n\n10 - PRAZO DE EXECUÇÃO DO CONTRATO\nIdentificador do Lote: LOT-0001; LOT-0002; LOT-0003; LOT-0004; LOT-0005; LOT-0006; LOT-0007; LOT-0008; LOT-0009; LOT-0010; LOT-0011; LOT-0012; LOT-0013; LOT-0014; LOT-0015; LOT-0016; LOT-0017; LOT-0018\nPrazo de execução do contrato: 12 MESES\nPrevisão de renovações: Não\n\n11 - FUNDOS EU\nIdentificador do Lote: LOT-0001; LOT-0002; LOT-0003; LOT-0004; LOT-0005; LOT-0006; LOT-0007; LOT-0008; LOT-0009; LOT-0010; LOT-0011; LOT-0012; LOT-0013; LOT-0014; LOT-0015; LOT-0016; LOT-0017; LOT-0018\nTêm fundos EU? Não\n\n12 - DOCUMENTOS DE HABILITAÇÃO\nHabilitação para o exercício da atividade profissional: Não\n\n13 - CONDIÇÕES DE APRESENTAÇÃO\nPlataforma eletrónica utilizada pela entidade adjudicante: VORTAL\nURL para Apresentação: https://community.vortal.biz/public/\nAdmissibilidade da apresentação de propostas variantes: Não autorizado\nPrazo para apresentação das propostas: 08-01-2026 17:00\nPrazo durante o qual os concorrentes são obrigados a manter as respetivas propostas: 90 dias a contar do termo do prazo para a apresentação das propostas\nIndicação de Subcontratação na Proposta: Inexistência de indicação de subcontratação\n\n14 - PRESTAÇÃO DE CAUÇÃO\nPrestação de caução: Não\n\n15 - FORNECIMENTO DAS PEÇAS DO CONCURSO, APRESENTAÇÃO DE PEDIDOS DE PARTICIPAÇÃO E APRESENTAÇÃO DAS PROPOSTAS\nLink para acesso às peças do concurso (URL): https://community.vortal.biz/Public/public-tender-documents/cnpBR3VRR3o2WXBiVVJDdVhwVGUwbHFSMG9WNVdhQzdqWlBtdzR2aXo2Q3lDVUYwZHhISWhtRU12TGhSbWwxVjlPRTRlbi9uZjJ6clNIaTJrMVdJRFE9PU1RSEkj\n\n20 - OUTROS REQUISITOS\nIdentificador do Lote: LOT-0001; LOT-0002; LOT-0003; LOT-0004; LOT-0005; LOT-0006; LOT-0007; LOT-0008; LOT-0009; LOT-0010; LOT-0011; LOT-0012; LOT-0013; LOT-0014; LOT-0015; LOT-0016; LOT-0017; LOT-0018\nInformação sobre contratos reservados. Aplica-se a contratos reservados (54º-A)? Não\n\n21 - CRITÉRIO DE ADJUDICAÇÃO\nO Critério de adjudicação é diferenciado por lote? Não\nMultifator: Não\nMonofator:\nNome: Outros\nOutro nome: Preço\n\n24 - CONDIÇÕES DO CONTRATO\nIdentificador do Lote: LOT-0001; LOT-0002; LOT-0003; LOT-0004; LOT-0005; LOT-0006; LOT-0007; LOT-0008; LOT-0009; LOT-0010; LOT-0011; LOT-0012; LOT-0013; LOT-0014; LOT-0015; LOT-0016; LOT-0017; LOT-0018\nFaturação Eletrónica: Permitido\nObrigação de Subcontratação:\nCódigo da Obrigação de Subcontratação: Não é aplicável nenhuma obrigação de subcontratação.\n\n25 - COMPRA PÚBLICA ESTRATÉGICA\nCompra Pública Estratégica: Inexistência de contratação pública estratégica\n\n26 - INFORMAÇÕES ADICIONAIS\nIdentificador do Lote: LOT-0001; LOT-0002; LOT-0003; LOT-0004; LOT-0005; LOT-0006; LOT-0007; LOT-0008; LOT-0009; LOT-0010; LOT-0011; LOT-0012; LOT-0013; LOT-0014; LOT-0015; LOT-0016; LOT-0017; LOT-0018\nContrato adequado para PME: Sim\nCobertura ACP (Acordo dos Contratos Públicos da Organização Mundial do Comércio): Não\n\n27 - IDENTIFICAÇÃO E CONTACTOS DO ÓRGÃO DE RECURSOS ADMINISTRATIVOS\nDesignação: Unidade Local de Saúde de Loures-Odivelas, E.P.E\nEndereço: Av. Carlos Teixeira, 3\nCódigo postal: 2674-514\nLocalidade: Loures\nTelefone: +351 219847200\nFax: +351 219847209\nEndereço eletrónico: compras_hba@ulslod.min-saude.pt\n\n28 - IDENTIFICAÇÃO DO(S) AUTOR(ES) DE ANÚNCIO\nNome: Manuela Santos\nCargo: Técnica Superior\n419933131",
    "nipc": "516726862",
    "distrito": "Lisboa",
    "concelho": "Loures",
    "freguesia": "Freguesia de Loures",
    "site": "https://www.hbeatrizangelo.pt",
    "email": "andreia.teixeira.chaves@ulslod.min-saude.pt",
    "designacao_contrato": "PROLONGADORES, TUBOS E DM RESPIRATÓRIOS PARA 2026",
    "descricao": "PROLONGADORES, TUBOS E DM RESPIRATÓRIOS PARA 2026",
    "preco_base": "41.240,16 EUR",
    "prazo_execucao": "12 MESES",
    "prazo_apresentacao_propostas": "08-01-2026 17:00",
    "fundos_eu": "Não",
    "plataforma_eletronica": "VORTAL",
    "url_procedimento": "https://community.vortal.biz/public/",
    "autor_nome": "Manuela Santos",
    "autor_cargo": "Técnica Superior"
  },
  {
    "numero_procedimento": "N/A",
    "entidade": "Autoridade Antidopagem de Portugal",
    "link": "https://diariodarepublica.pt/dr/detalhe/contrato-publico/33653-993315577",
    "detalhes_completos": "1 - IDENTIFICAÇÃO E CONTACTOS DA ENTIDADE ADJUDICANTE\nDesignação da entidade adjudicante: Autoridade Antidopagem de Portugal\nNIPC: 600087301\nServiço/Órgão/Pessoa de contacto: ESPAP / DPCP\nEndereço: Av. Duque De Ávila, 137 5º\nCódigo postal: 1069-016\nLocalidade: Lisboa\nPaís: Portugal\nNUT III: PT170\nDistrito: Lisboa\nConcelho: Lisboa\nFreguesia: Freguesia de Avenidas Novas\nTelefone: 210517200\nFax: 217977529\nEndereço da Entidade (URL): http://www.adop.pt/\nEndereço Eletrónico: antidopagem@adop.pt\neDelivery Gateway (URL): https://www.acingov.pt\nFunção da Organização: Adquirente\nNorma jurídica da Entidade Adjudicante: Organismo de direito público\nÁrea de atividade da Autoridade Adjudicante: Serviços públicos das administrações públicas\n\n2 - JORNAL OFICIAL DA UNIÃO EUROPEIA\nO procedimento a que este anúncio diz respeito também é publicitado no Jornal Oficial da União Europeia? Não\n\n3 - AVISO\nModelo de Anúncio: Concurso público\nData de Envio do Anúncio: 30-12-2025\n\n5 - PROCESSO\nTipo de Procedimento: Concurso público\nPreço base do procedimento: Sim\nValor do preço base do procedimento: 140.000,00 EUR\nProcedimento com lotes? Sim\nNº Máx. de Lotes Autorizado: 25\nNúmero máximo de lotes que podem ser adjudicados a um concorrente: 1\n\n6 - OBJETO DO CONTRATO\nNúmero de referência interna: CP/718/2025\nDesignação do contrato: Prestação de Serviços em Regime de Tarefa para a Realização de Acções de Controlo de Dopagem\nDescrição: Prestação de Serviços em regime de tarefa para a Realização de Acções de Controlo de Dopagem (25 técnicos)\nTipo de Contrato Principal: Aquisição de Serviços\nTipo de Contrato: Aquisição de Serviços\nClassificação CPV (Vocabulário Comum para os Contratos Públicos)\nObjeto principal\nVocabulário Principal: 85100000\nPreço base s/IVA: 140.000,00 EUR\nLotes: \nNº: LOT-0001\nDescrição do Lote: Lote 1: Prestação de Serviços em Regime de Tarefa para a Realização de Acções de Controlo de Dopagem em provas de atletas femininas - Região Norte\nPreço base s/IVA: 5.600,00 EUR\nClassificação CPV (Vocabulário Comum para os Contratos Públicos)\nObjeto principal\nVocabulário Principal: 85100000\nNº: LOT-0002\nDescrição do Lote: Lote 2: Prestação de Serviços em Regime de Tarefa para a Realização de Acções de Controlo de Dopagem em provas de atletas femininas - Região Norte\nPreço base s/IVA: 5.600,00 EUR\nClassificação CPV (Vocabulário Comum para os Contratos Públicos)\nObjeto principal\nVocabulário Principal: 85100000\nNº: LOT-0003\nDescrição do Lote: Lote 3: Prestação de Serviços em Regime de Tarefa para a Realização de Acções de Controlo de Dopagem em provas de atletas masculinos - Região Norte\nPreço base s/IVA: 5.600,00 EUR\nClassificação CPV (Vocabulário Comum para os Contratos Públicos)\nObjeto principal\nVocabulário Principal: 85100000\nNº: LOT-0004\nDescrição do Lote: Lote 4: Prestação de Serviços em Regime de Tarefa para a Realização de Acções de Controlo de Dopagem em provas de atletas masculinos - Região Norte\nPreço base s/IVA: 5.600,00 EUR\nClassificação CPV (Vocabulário Comum para os Contratos Públicos)\nObjeto principal\nVocabulário Principal: 85100000\nNº: LOT-0005\nDescrição do Lote: Lote 5: Prestação de Serviços em Regime de Tarefa para a Realização de Acções de Controlo de Dopagem em provas de atletas masculinos - Região Norte\nPreço base s/IVA: 5.600,00 EUR\nClassificação CPV (Vocabulário Comum para os Contratos Públicos)\nObjeto principal\nVocabulário Principal: 85100000\nNº: LOT-0006\nDescrição do Lote: Lote 6: Prestação de Serviços em Regime de Tarefa para a Realização de Acções de Controlo de Dopagem em provas de atletas masculinos - Região Norte\nPreço base s/IVA: 5.600,00 EUR\nClassificação CPV (Vocabulário Comum para os Contratos Públicos)\nObjeto principal\nVocabulário Principal: 85100000\nNº: LOT-0007\nDescrição do Lote: Lote 7: Prestação de Serviços em Regime de Tarefa para a Realização de Acções de Controlo de Dopagem em provas de atletas masculinos - Região Norte\nPreço base s/IVA: 5.600,00 EUR\nClassificação CPV (Vocabulário Comum para os Contratos Públicos)\nObjeto principal\nVocabulário Principal: 85100000\nNº: LOT-0008\nDescrição do Lote: Lote 8: Prestação de Serviços em Regime de Tarefa para a Realização de Acções de Controlo de Dopagem em provas de atletas femininas - Região Centro\nPreço base s/IVA: 5.600,00 EUR\nClassificação CPV (Vocabulário Comum para os Contratos Públicos)\nObjeto principal\nVocabulário Principal: 85100000\nNº: LOT-0009\nDescrição do Lote: Lote 9: Prestação de Serviços em Regime de Tarefa para a Realização de Acções de Controlo de Dopagem em provas de atletas femininas - Região Centro\nPreço base s/IVA: 5.600,00 EUR\nClassificação CPV (Vocabulário Comum para os Contratos Públicos)\nObjeto principal\nVocabulário Principal: 85100000\nNº: LOT-0010\nDescrição do Lote: Lote 10: Prestação de Serviços em Regime de Tarefa para a Realização de Acções de Controlo de Dopagem em provas de atletas femininas - Região Centro\nPreço base s/IVA: 5.600,00 EUR\nClassificação CPV (Vocabulário Comum para os Contratos Públicos)\nObjeto principal\nVocabulário Principal: 85100000\nNº: LOT-0011\nDescrição do Lote: Lote 11: Prestação de Serviços em Regime de Tarefa para a Realização de Acções de Controlo de Dopagem em provas de atletas masculinos - Região Centro\nPreço base s/IVA: 5.600,00 EUR\nClassificação CPV (Vocabulário Comum para os Contratos Públicos)\nObjeto principal\nVocabulário Principal: 85100000\nNº: LOT-0012\nDescrição do Lote: Lote 12: Prestação de Serviços em Regime de Tarefa para a Realização de Acções de Controlo de Dopagem em provas de atletas masculinos - Região Centro\nPreço base s/IVA: 5.600,00 EUR\nClassificação CPV (Vocabulário Comum para os Contratos Públicos)\nObjeto principal\nVocabulário Principal: 85100000\nNº: LOT-0013\nDescrição do Lote: Lote 13: Prestação de Serviços em Regime de Tarefa para a Realização de Acções de Controlo de Dopagem em provas de atletas masculinos - Região Centro\nPreço base s/IVA: 5.600,00 EUR\nClassificação CPV (Vocabulário Comum para os Contratos Públicos)\nObjeto principal\nVocabulário Principal: 85100000\nNº: LOT-0014\nDescrição do Lote: Lote 14: Prestação de Serviços em Regime de Tarefa para a Realização de Acções de Controlo de Dopagem em provas de atletas femininas - Região Lisboa e Vale do Tejo\nPreço base s/IVA: 5.600,00 EUR\nClassificação CPV (Vocabulário Comum para os Contratos Públicos)\nObjeto principal\nVocabulário Principal: 85100000\nNº: LOT-0015\nDescrição do Lote: Lote 15: Prestação de Serviços em Regime de Tarefa para a Realização de Acções de Controlo de Dopagem em provas de atletas femininas - Região Lisboa e Vale do Tejo\nPreço base s/IVA: 5.600,00 EUR\nClassificação CPV (Vocabulário Comum para os Contratos Públicos)\nObjeto principal\nVocabulário Principal: 85100000\nNº: LOT-0016\nDescrição do Lote: Lote 16: Prestação de Serviços em Regime de Tarefa para a Realização de Acções de Controlo de Dopagem em provas de atletas femininas - Região Lisboa e Vale do Tejo\nPreço base s/IVA: 5.600,00 EUR\nClassificação CPV (Vocabulário Comum para os Contratos Públicos)\nObjeto principal\nVocabulário Principal: 85100000\nNº: LOT-0017\nDescrição do Lote: Lote 17: Prestação de Serviços em Regime de Tarefa para a Realização de Acções de Controlo de Dopagem em provas de atletas femininas - Região Lisboa e Vale do Tejo\nPreço base s/IVA: 5.600,00 EUR\nClassificação CPV (Vocabulário Comum para os Contratos Públicos)\nObjeto principal\nVocabulário Principal: 85100000\nNº: LOT-0018\nDescrição do Lote: Lote 18: Prestação de Serviços em Regime de Tarefa para a Realização de Acções de Controlo de Dopagem em provas de atletas masculinos - Região Lisboa e Vale do Tejo\nPreço base s/IVA: 5.600,00 EUR\nClassificação CPV (Vocabulário Comum para os Contratos Públicos)\nObjeto principal\nVocabulário Principal: 85100000\nNº: LOT-0019\nDescrição do Lote: Lote 19: Prestação de Serviços em Regime de Tarefa para a Realização de Acções de Controlo de Dopagem em provas de atletas masculinos - Região Lisboa e Vale do Tejo\nPreço base s/IVA: 5.600,00 EUR\nClassificação CPV (Vocabulário Comum para os Contratos Públicos)\nObjeto principal\nVocabulário Principal: 85100000\nNº: LOT-0020\nDescrição do Lote: Lote 20: Prestação de Serviços em Regime de Tarefa para a Realização de Acções de Controlo de Dopagem em provas de atletas masculinos - Região Lisboa e Vale do Tejo\nPreço base s/IVA: 5.600,00 EUR\nClassificação CPV (Vocabulário Comum para os Contratos Públicos)\nObjeto principal\nVocabulário Principal: 85100000\nNº: LOT-0021\nDescrição do Lote: Lote 21: Prestação de Serviços em Regime de Tarefa para a Realização de Acções de Controlo de Dopagem em provas de atletas masculinos - Região Lisboa e Vale do Tejo\nPreço base s/IVA: 5.600,00 EUR\nClassificação CPV (Vocabulário Comum para os Contratos Públicos)\nObjeto principal\nVocabulário Principal: 85100000\nNº: LOT-0022\nDescrição do Lote: Lote 22: Prestação de Serviços em Regime de Tarefa para a Realização de Acções de Controlo de Dopagem em provas de atletas femininas - Algarve\nPreço base s/IVA: 5.600,00 EUR\nClassificação CPV (Vocabulário Comum para os Contratos Públicos)\nObjeto principal\nVocabulário Principal: 85100000\nNº: LOT-0023\nDescrição do Lote: Lote 23: Prestação de Serviços em Regime de Tarefa para a Realização de Acções de Controlo de Dopagem em provas de atletas masculinos - Algarve\nPreço base s/IVA: 5.600,00 EUR\nClassificação CPV (Vocabulário Comum para os Contratos Públicos)\nObjeto principal\nVocabulário Principal: 85100000\nNº: LOT-0024\nDescrição do Lote: Lote 24: Prestação de Serviços em Regime de Tarefa para a Realização de Acções de Controlo de Dopagem em provas de atletas femininas - Madeira\nPreço base s/IVA: 5.600,00 EUR\nClassificação CPV (Vocabulário Comum para os Contratos Públicos)\nObjeto principal\nVocabulário Principal: 85100000\nNº: LOT-0025\nDescrição do Lote: Lote 25: Prestação de Serviços em Regime de Tarefa para a Realização de Acções de Controlo de Dopagem em provas de atletas masculinos - Madeira\nPreço base s/IVA: 5.600,00 EUR\nClassificação CPV (Vocabulário Comum para os Contratos Públicos)\nObjeto principal\nVocabulário Principal: 85100000\n\n7 - INDICAÇÕES ADICIONAIS\nO contrato envolve aquisição conjunta (satisfação de várias entidades)? Não\nO contrato é adjudicado por uma central de compras? Não\n\n8 - TÉCNICAS\nO concurso destina-se à celebração de um acordo-quadro? Inexistência de acordo-quadro\nÉ utilizado um leilão eletrónico? Não\nÉ adotada uma fase de negociação? Não\nSistema de Aquisição Dinâmico: Inexistência de sistema de aquisição dinâmico\n\n9 - LOCAL DA EXECUÇÃO DO CONTRATO\nLOCAL DA EXECUÇÃO DO CONTRATO (PROCEDIMENTO)\nPaís: Portugal\nNUT III: PTZZZ\nLocalidade: Todas\nDistrito: Todos\nConcelho: Todos\nFreguesia: Todas\nLOCAL DA EXECUÇÃO DO CONTRATO (LOTE)\nIdentificador do Lote: LOT-0001; LOT-0002; LOT-0003; LOT-0004; LOT-0005; LOT-0006; LOT-0007; LOT-0008; LOT-0009; LOT-0010; LOT-0011; LOT-0012; LOT-0013; LOT-0014; LOT-0015; LOT-0016; LOT-0017; LOT-0018; LOT-0019; LOT-0020; LOT-0021; LOT-0022; LOT-0023; LOT-0024; LOT-0025\nPaís: Portugal\nNUT III: PTZZZ\nLocalidade: Todas\nDistrito: Todos\nConcelho: Todos\nFreguesia: Todas\n\n10 - PRAZO DE EXECUÇÃO DO CONTRATO\nIdentificador do Lote: LOT-0001; LOT-0002; LOT-0003; LOT-0004; LOT-0005; LOT-0006; LOT-0007; LOT-0008; LOT-0009; LOT-0010; LOT-0011; LOT-0012; LOT-0013; LOT-0014; LOT-0015; LOT-0016; LOT-0017; LOT-0018; LOT-0019; LOT-0020; LOT-0021; LOT-0022; LOT-0023; LOT-0024; LOT-0025\nData de Início: 15-01-2026\nData de Fim: 30-06-2026\nPrevisão de renovações: Não\n\n11 - FUNDOS EU\nIdentificador do Lote: LOT-0001; LOT-0002; LOT-0003; LOT-0004; LOT-0005; LOT-0006; LOT-0007; LOT-0008; LOT-0009; LOT-0010; LOT-0011; LOT-0012; LOT-0013; LOT-0014; LOT-0015; LOT-0016; LOT-0017; LOT-0018; LOT-0019; LOT-0020; LOT-0021; LOT-0022; LOT-0023; LOT-0024; LOT-0025\nTêm fundos EU? Não\n\n12 - DOCUMENTOS DE HABILITAÇÃO\nHabilitação para o exercício da atividade profissional: Sim\nTipo: Ordem Profissional\nDescrição: Documentos de Habilitação\n\n13 - CONDIÇÕES DE APRESENTAÇÃO\nPlataforma eletrónica utilizada pela entidade adjudicante: ACIN\nURL para Apresentação: https://www.acingov.pt\nAdmissibilidade da apresentação de propostas variantes: Não autorizado\nPrazo para apresentação das propostas: 05-01-2026 23:59\nPrazo durante o qual os concorrentes são obrigados a manter as respetivas propostas: 66 dias a contar do termo do prazo para a apresentação das propostas\nIndicação de Subcontratação na Proposta: Inexistência de indicação de subcontratação\n\n14 - PRESTAÇÃO DE CAUÇÃO\nPrestação de caução: Não\n\n15 - FORNECIMENTO DAS PEÇAS DO CONCURSO, APRESENTAÇÃO DE PEDIDOS DE PARTICIPAÇÃO E APRESENTAÇÃO DAS PROPOSTAS\nLink para acesso às peças do concurso (URL): https://www.acingov.pt/acingovprod/2/zonaPublica/zona_publica_c/donwloadProcedurePiece/MTAxMzAxNQ==\n\n20 - OUTROS REQUISITOS\nIdentificador do Lote: LOT-0001; LOT-0002; LOT-0003; LOT-0004; LOT-0005; LOT-0006; LOT-0007; LOT-0008; LOT-0009; LOT-0010; LOT-0011; LOT-0012; LOT-0013; LOT-0014; LOT-0015; LOT-0016; LOT-0017; LOT-0018; LOT-0019; LOT-0020; LOT-0021; LOT-0022; LOT-0023; LOT-0024; LOT-0025\nInformação sobre contratos reservados. Aplica-se a contratos reservados (54º-A)? Não\n\n21 - CRITÉRIO DE ADJUDICAÇÃO\nO Critério de adjudicação é diferenciado por lote? Não\nMultifator: Sim\nFator: \nNome: Outros\nOutro Nome: Preço/h proposto\nPonderação: 40%\nSubfatores: Não\nFator: \nNome: Outros\nOutro Nome: Experiência;\nPonderação: 60%\nSubfatores: Não\n\n24 - CONDIÇÕES DO CONTRATO\nIdentificador do Lote: LOT-0001; LOT-0002; LOT-0003; LOT-0004; LOT-0005; LOT-0006; LOT-0007; LOT-0008; LOT-0009; LOT-0010; LOT-0011; LOT-0012; LOT-0013; LOT-0014; LOT-0015; LOT-0016; LOT-0017; LOT-0018; LOT-0019; LOT-0020; LOT-0021; LOT-0022; LOT-0023; LOT-0024; LOT-0025\nFaturação Eletrónica: Permitido\nObrigação de Subcontratação:\nCódigo da Obrigação de Subcontratação: Não é aplicável nenhuma obrigação de subcontratação.\n\n25 - COMPRA PÚBLICA ESTRATÉGICA\nCompra Pública Estratégica: Inexistência de contratação pública estratégica\n\n26 - INFORMAÇÕES ADICIONAIS\nIdentificador do Lote: LOT-0001; LOT-0002; LOT-0003; LOT-0004; LOT-0005; LOT-0006; LOT-0007; LOT-0008; LOT-0009; LOT-0010; LOT-0011; LOT-0012; LOT-0013; LOT-0014; LOT-0015; LOT-0016; LOT-0017; LOT-0018; LOT-0019; LOT-0020; LOT-0021; LOT-0022; LOT-0023; LOT-0024; LOT-0025\nContrato adequado para PME: Sim\nCobertura ACP (Acordo dos Contratos Públicos da Organização Mundial do Comércio): Não\n\n27 - IDENTIFICAÇÃO E CONTACTOS DO ÓRGÃO DE RECURSOS ADMINISTRATIVOS\nDesignação: Presidente\nEndereço: Av. Duque De Ávila, 137 5º\nCódigo postal: 1069-016\nLocalidade: Lisboa\nTelefone: 214723100\nFax: 214723100\nEndereço eletrónico: compras@espap.gov.pt\n\n28 - IDENTIFICAÇÃO DO(S) AUTOR(ES) DE ANÚNCIO\nNome: Ana Vieira\nCargo: Coordenadora NSC / DPCP\n419944059",
    "nipc": "600087301",
    "distrito": "Lisboa",
    "concelho": "Lisboa",
    "freguesia": "Freguesia de Avenidas Novas",
    "site": "http://www.adop.pt/",
    "email": "antidopagem@adop.pt",
    "designacao_contrato": "Prestação de Serviços em Regime de Tarefa para a Realização de Acções de Controlo de Dopagem",
    "descricao": "Prestação de Serviços em regime de tarefa para a Realização de Acções de Controlo de Dopagem (25 técnicos)",
    "preco_base": "140.000,00 EUR",
    "prazo_execucao": null,
    "prazo_apresentacao_propostas": "05-01-2026 23:59",
    "fundos_eu": "Não",
    "plataforma_eletronica": "ACIN",
    "url_procedimento": "https://www.acingov.pt",
    "autor_nome": "Ana Vieira",
    "autor_cargo": "Coordenadora NSC / DPCP"
  },
  {
    "numero_procedimento": "N/A",
    "entidade": "Agência para o Desenvolvimento e Coesão, IP",
    "link": "https://diariodarepublica.pt/dr/detalhe/contrato-publico/33658-993315604",
    "detalhes_completos": "1 - IDENTIFICAÇÃO E CONTACTOS DA ENTIDADE ADJUDICANTE\nDesignação da entidade adjudicante: Agência para o Desenvolvimento e Coesão, IP\nNIPC: 510928374\nServiço/Órgão/Pessoa de contacto: NGCP\nEndereço: Av. 5 de Outubro, 153\nCódigo postal: 1050-053\nLocalidade: Lisboa\nPaís: Portugal\nNUT III: PT170\nDistrito: Lisboa\nConcelho: Lisboa\nFreguesia: Freguesia de Avenidas Novas\nTelefone: 218814000\nFax: 218881111\nEndereço da Entidade (URL): https://www.adcoesao.pt/\nEndereço Eletrónico: contratacao@adcoesao.pt\neDelivery Gateway (URL): https://www.acingov.pt\nFunção da Organização: Adquirente\nNorma jurídica da Entidade Adjudicante: Organismo de direito público\nÁrea de atividade da Autoridade Adjudicante: Serviços públicos das administrações públicas\n\n2 - JORNAL OFICIAL DA UNIÃO EUROPEIA\nO procedimento a que este anúncio diz respeito também é publicitado no Jornal Oficial da União Europeia? Sim\n\n3 - AVISO\nModelo de Anúncio: Concurso público\nData de Envio do Anúncio: 29-12-2025\n\n5 - PROCESSO\nTipo de Procedimento: Concurso público\nPreço base do procedimento: Sim\nValor do preço base do procedimento: 2.695.000,00 EUR\nProcedimento com lotes? Não\n\n6 - OBJETO DO CONTRATO\nNúmero de referência interna: R/187/2025\nDesignação do contrato: Aquisição de subscrição Plataforma de Desenvolvimento Low-Code, em modelo Plataform-as-a-Service (PaaS)\nDescrição: Aquisição de subscrição Plataforma de Desenvolvimento Low-Code, em modelo Plataform-as-a-Service (PaaS)\nOpções: Não\nTipo de Contrato Principal: Aquisição de Bens Móveis\nTipo de Contrato: Aquisição de Bens Móveis\nClassificação CPV (Vocabulário Comum para os Contratos Públicos)\nObjeto principal\nVocabulário Principal: 48000000\nPreço base s/IVA: 2.695.000,00 EUR\n\n7 - INDICAÇÕES ADICIONAIS\nO contrato envolve aquisição conjunta (satisfação de várias entidades)? Não\nO contrato é adjudicado por uma central de compras? Não\n\n8 - TÉCNICAS\nO concurso destina-se à celebração de um acordo-quadro? Inexistência de acordo-quadro\nÉ utilizado um leilão eletrónico? Não\nÉ adotada uma fase de negociação? Não\nSistema de Aquisição Dinâmico: Inexistência de sistema de aquisição dinâmico\n\n9 - LOCAL DA EXECUÇÃO DO CONTRATO\nLOCAL DA EXECUÇÃO DO CONTRATO (PROCEDIMENTO)\nPaís: Portugal\nNUT III: PT170\nLocalidade: Freguesia de Avenidas Novas\nDistrito: Lisboa\nConcelho: Lisboa\nFreguesia: Freguesia de Avenidas Novas\n\n10 - PRAZO DE EXECUÇÃO DO CONTRATO\nPrazo de execução do contrato: 36 MESES\nPrevisão de renovações: Não\n\n11 - FUNDOS EU\nTêm fundos EU? Sim\n\n12 - DOCUMENTOS DE HABILITAÇÃO\nHabilitação para o exercício da atividade profissional: Não\n\n13 - CONDIÇÕES DE APRESENTAÇÃO\nPlataforma eletrónica utilizada pela entidade adjudicante: ACIN\nURL para Apresentação: https://www.acingov.pt\nAdmissibilidade da apresentação de propostas variantes: Não autorizado\nPrazo para apresentação das propostas: 28-01-2026 23:59\nPrazo durante o qual os concorrentes são obrigados a manter as respetivas propostas: 120 dias a contar do termo do prazo para a apresentação das propostas\nApresentação de Catálogo Eletrónico: Permitido\nIndicação de Subcontratação na Proposta: Inexistência de indicação de subcontratação\n\n14 - PRESTAÇÃO DE CAUÇÃO\nPrestação de caução: Sim\nPercentagem: 5%\nDescrição da Garantia Exigida: O valor da caução é de 5.00% do preço contratual.\n\n15 - FORNECIMENTO DAS PEÇAS DO CONCURSO, APRESENTAÇÃO DE PEDIDOS DE PARTICIPAÇÃO E APRESENTAÇÃO DAS PROPOSTAS\nLink para acesso às peças do concurso (URL): https://www.acingov.pt/acingovprod/2/zonaPublica/zona_publica_c/donwloadProcedurePiece/MTAwOTM4OQ==\n\n20 - OUTROS REQUISITOS\nInformação sobre contratos reservados. Aplica-se a contratos reservados (54º-A)? Não\n\n21 - CRITÉRIO DE ADJUDICAÇÃO\nMultifator: Não\nMonofator:\nNome: Preço\n\n24 - CONDIÇÕES DO CONTRATO\nFaturação Eletrónica: Necessário\nObrigação de Subcontratação:\nCódigo da Obrigação de Subcontratação: Não é aplicável nenhuma obrigação de subcontratação.\n\n25 - COMPRA PÚBLICA ESTRATÉGICA\nCompra Pública Estratégica: Inexistência de contratação pública estratégica\n\n26 - INFORMAÇÕES ADICIONAIS\nContrato adequado para PME: Sim\nCobertura ACP (Acordo dos Contratos Públicos da Organização Mundial do Comércio): Não\n\n27 - IDENTIFICAÇÃO E CONTACTOS DO ÓRGÃO DE RECURSOS ADMINISTRATIVOS\nDesignação: Conselho Diretivo da Agência, I.P.\nEndereço: Avenida 5 de Outubro, 153\nCódigo postal: 1050-053\nLocalidade: Lisboa\nTelefone: 218814000\nFax: \nEndereço eletrónico: agencia@adcoesao.pt\n\n28 - IDENTIFICAÇÃO DO(S) AUTOR(ES) DE ANÚNCIO\nNome: Leonor Lei\nCargo: Coordenadora NGCP\n419933278",
    "nipc": "510928374",
    "distrito": "Lisboa",
    "concelho": "Lisboa",
    "freguesia": "Freguesia de Avenidas Novas",
    "site": "https://www.adcoesao.pt/",
    "email": "contratacao@adcoesao.pt",
    "designacao_contrato": "Aquisição de subscrição Plataforma de Desenvolvimento Low-Code, em modelo Plataform-as-a-Service (PaaS)",
    "descricao": "Aquisição de subscrição Plataforma de Desenvolvimento Low-Code, em modelo Plataform-as-a-Service (PaaS)",
    "preco_base": "2.695.000,00 EUR",
    "prazo_execucao": "36 MESES",
    "prazo_apresentacao_propostas": "28-01-2026 23:59",
    "fundos_eu": "Sim",
    "plataforma_eletronica": "ACIN",
    "url_procedimento": "https://www.acingov.pt",
    "autor_nome": "Leonor Lei",
    "autor_cargo": "Coordenadora NGCP"
  },
  {
    "numero_procedimento": "N/A",
    "entidade": "Unidade Local de Saúde de São José, EPE",
    "link": "https://diariodarepublica.pt/dr/detalhe/contrato-publico/33661-993315609",
    "detalhes_completos": "1 - IDENTIFICAÇÃO E CONTACTOS DA ENTIDADE ADJUDICANTE\nDesignação da entidade adjudicante: Unidade Local de Saúde de São José, EPE\nNIPC: 508080142\nEndereço: Rua José António Serrano\nCódigo postal: 1150-199\nLocalidade: Lisboa\nPaís: Portugal\nNUT III: PT170\nDistrito: Lisboa\nConcelho: Lisboa\nFreguesia: Freguesia de Arroios - Lisboa\nTelefone: 218841403\nFax: 218841025\nEndereço da Entidade (URL): www.chlc.min-saude.pt\nEndereço Eletrónico: geral@chlc.min-saude.pt\neDelivery Gateway (URL): https://community.vortal.biz/public/\nFunção da Organização: Adquirente\nNorma jurídica da Entidade Adjudicante: Organismo de direito público\nÁrea de atividade da Autoridade Adjudicante: Saúde\n\n2 - JORNAL OFICIAL DA UNIÃO EUROPEIA\nO procedimento a que este anúncio diz respeito também é publicitado no Jornal Oficial da União Europeia? Sim\n\n3 - AVISO\nModelo de Anúncio: Concurso público\nData de Envio do Anúncio: 29-12-2025\n\n5 - PROCESSO\nTipo de Procedimento: Concurso público\nPreço base do procedimento: Sim\nValor do preço base do procedimento: 549.000,00 EUR\nProcedimento com lotes? Sim\nNº Máx. de Lotes Autorizado: 2\nNúmero máximo de lotes que podem ser adjudicados a um concorrente: 2\n\n6 - OBJETO DO CONTRATO\nNúmero de referência interna: 12006726\nDesignação do contrato: 12006726 - Cavilhas Magnéticas de Alongamento\nDescrição: 12006726 - Cavilhas Magnéticas de Alongamento\nOpções: Não\nTipo de Contrato Principal: Aquisição de Bens Móveis\nTipo de Contrato: Aquisição de Bens Móveis\nClassificação CPV (Vocabulário Comum para os Contratos Públicos)\nObjeto principal\nVocabulário Principal: 33100000\nPreço base s/IVA: 549.000,00 EUR\nLotes: \nNº: LOT-0001\nDescrição do Lote: Lote 1\nPreço base s/IVA: 167.750,00 EUR\nClassificação CPV (Vocabulário Comum para os Contratos Públicos)\nObjeto principal\nVocabulário Principal: 33100000\nNº: LOT-0002\nDescrição do Lote: Lote 2\nPreço base s/IVA: 381.250,00 EUR\nClassificação CPV (Vocabulário Comum para os Contratos Públicos)\nObjeto principal\nVocabulário Principal: 33100000\n\n7 - INDICAÇÕES ADICIONAIS\nO contrato envolve aquisição conjunta (satisfação de várias entidades)? Não\nO contrato é adjudicado por uma central de compras? Não\n\n8 - TÉCNICAS\nO concurso destina-se à celebração de um acordo-quadro? Inexistência de acordo-quadro\nÉ utilizado um leilão eletrónico? Não\nÉ adotada uma fase de negociação? Não\nSistema de Aquisição Dinâmico: Inexistência de sistema de aquisição dinâmico\n\n9 - LOCAL DA EXECUÇÃO DO CONTRATO\nLOCAL DA EXECUÇÃO DO CONTRATO (PROCEDIMENTO)\nPaís: Portugal\nNUT III: PT170\nLocalidade: Lisboa\nDistrito: Lisboa\nConcelho: Lisboa\nFreguesia: Freguesia de Arroios - Lisboa\nLOCAL DA EXECUÇÃO DO CONTRATO (LOTE)\nIdentificador do Lote: LOT-0001; LOT-0002\nPaís: Portugal\nNUT III: PT170\nLocalidade: Lisboa\nDistrito: Lisboa\nConcelho: Lisboa\nFreguesia: Freguesia de Arroios - Lisboa\n\n10 - PRAZO DE EXECUÇÃO DO CONTRATO\nIdentificador do Lote: LOT-0001; LOT-0002\nPrazo de execução do contrato: 1 ANOS\nPrevisão de renovações: Não\n\n11 - FUNDOS EU\nIdentificador do Lote: LOT-0001; LOT-0002\nTêm fundos EU? Não\n\n12 - DOCUMENTOS DE HABILITAÇÃO\nHabilitação para o exercício da atividade profissional: Não\n\n13 - CONDIÇÕES DE APRESENTAÇÃO\nPlataforma eletrónica utilizada pela entidade adjudicante: VORTAL\nURL para Apresentação: https://community.vortal.biz/public/\nAdmissibilidade da apresentação de propostas variantes: Não autorizado\nPrazo para apresentação das propostas: 02-02-2026 23:59\nPrazo durante o qual os concorrentes são obrigados a manter as respetivas propostas: 120 dias a contar do termo do prazo para a apresentação das propostas\nApresentação de Catálogo Eletrónico: Permitido\nIndicação de Subcontratação na Proposta: Inexistência de indicação de subcontratação\n\n14 - PRESTAÇÃO DE CAUÇÃO\nPrestação de caução: Não\n\n15 - FORNECIMENTO DAS PEÇAS DO CONCURSO, APRESENTAÇÃO DE PEDIDOS DE PARTICIPAÇÃO E APRESENTAÇÃO DAS PROPOSTAS\nLink para acesso às peças do concurso (URL): https://community.vortal.biz/Public/public-tender-documents/bVo4N3ZJZ1YwRkdWcjZjMWNLY3JIUUNwNC9TQ2VSY1VmMHdEdW9LMkw4UkVrRjR0TVZqOHpyODA4SXhlZWYydjdmQ0IrMUJyVG9ld2dwVFFVcDh5QXc9PUVZYkFj\n\n20 - OUTROS REQUISITOS\nIdentificador do Lote: LOT-0001; LOT-0002\nInformação sobre contratos reservados. Aplica-se a contratos reservados (54º-A)? Não\n\n21 - CRITÉRIO DE ADJUDICAÇÃO\nO Critério de adjudicação é diferenciado por lote? Não\nMultifator: Não\nMonofator:\nNome: Preço\n\n24 - CONDIÇÕES DO CONTRATO\nIdentificador do Lote: LOT-0001; LOT-0002\nFaturação Eletrónica: Permitido\nObrigação de Subcontratação:\nCódigo da Obrigação de Subcontratação: Não é aplicável nenhuma obrigação de subcontratação.\n\n25 - COMPRA PÚBLICA ESTRATÉGICA\nCompra Pública Estratégica: Inexistência de contratação pública estratégica\n\n26 - INFORMAÇÕES ADICIONAIS\nIdentificador do Lote: LOT-0001; LOT-0002\nContrato adequado para PME: Sim\nCobertura ACP (Acordo dos Contratos Públicos da Organização Mundial do Comércio): Não\n\n27 - IDENTIFICAÇÃO E CONTACTOS DO ÓRGÃO DE RECURSOS ADMINISTRATIVOS\nDesignação: Conselho de Administração\nEndereço: Rua José António Serrano s/n\nCódigo postal: 1150-199\nLocalidade: Lisboa\nTelefone: +351 218841000\nFax: +351 218841023\nEndereço eletrónico: sec.vca@ulssjose.min-saude.pt\n\n28 - IDENTIFICAÇÃO DO(S) AUTOR(ES) DE ANÚNCIO\nNome: Conselho de Administração\nCargo: Conselho de Administração\n419932857",
    "nipc": "508080142",
    "distrito": "Lisboa",
    "concelho": "Lisboa",
    "freguesia": "Freguesia de Arroios - Lisboa",
    "site": "www.chlc.min-saude.pt",
    "email": "geral@chlc.min-saude.pt",
    "designacao_contrato": "12006726 - Cavilhas Magnéticas de Alongamento",
    "descricao": "12006726 - Cavilhas Magnéticas de Alongamento",
    "preco_base": "549.000,00 EUR",
    "prazo_execucao": "1 ANOS",
    "prazo_apresentacao_propostas": "02-02-2026 23:59",
    "fundos_eu": "Não",
    "plataforma_eletronica": "VORTAL",
    "url_procedimento": "https://community.vortal.biz/public/",
    "autor_nome": "Conselho de Administração",
    "autor_cargo": "Conselho de Administração"
  },
  {
    "numero_procedimento": "N/A",
    "entidade": "Unidade Local de Saúde de São José, EPE",
    "link": "https://diariodarepublica.pt/dr/detalhe/contrato-publico/33662-993315610",
    "detalhes_completos": "1 - IDENTIFICAÇÃO E CONTACTOS DA ENTIDADE ADJUDICANTE\nDesignação da entidade adjudicante: Unidade Local de Saúde de São José, EPE\nNIPC: 508080142\nEndereço: Rua José António Serrano\nCódigo postal: 1150-199\nLocalidade: Lisboa\nPaís: Portugal\nNUT III: PT170\nDistrito: Lisboa\nConcelho: Lisboa\nFreguesia: Freguesia de Arroios - Lisboa\nTelefone: 218841403\nFax: 218841025\nEndereço da Entidade (URL): www.chlc.min-saude.pt\nEndereço Eletrónico: geral@chlc.min-saude.pt\neDelivery Gateway (URL): https://community.vortal.biz/public/\nFunção da Organização: Adquirente\nNorma jurídica da Entidade Adjudicante: Organismo de direito público\nÁrea de atividade da Autoridade Adjudicante: Saúde\n\n2 - JORNAL OFICIAL DA UNIÃO EUROPEIA\nO procedimento a que este anúncio diz respeito também é publicitado no Jornal Oficial da União Europeia? Sim\n\n3 - AVISO\nModelo de Anúncio: Concurso público\nData de Envio do Anúncio: 29-12-2025\n\n5 - PROCESSO\nTipo de Procedimento: Concurso público\nPreço base do procedimento: Sim\nValor do preço base do procedimento: 733.380,00 EUR\nProcedimento com lotes? Sim\nNº Máx. de Lotes Autorizado: 25\nNúmero máximo de lotes que podem ser adjudicados a um concorrente: 25\n\n6 - OBJETO DO CONTRATO\nNúmero de referência interna: 12002426\nDesignação do contrato: Próteses Biliares, pancreáticas, cólicas, esofágicas e duodenais\nDescrição: Próteses Biliares, pancreáticas, cólicas, esofágicas e duodenais\nOpções: Não\nTipo de Contrato Principal: Aquisição de Bens Móveis\nTipo de Contrato: Aquisição de Bens Móveis\nClassificação CPV (Vocabulário Comum para os Contratos Públicos)\nObjeto principal\nVocabulário Principal: 33140000\nPreço base s/IVA: 733.380,00 EUR\nLotes: \nNº: LOT-0001\nDescrição do Lote: Protese biliar plastica recta\nPreço base s/IVA: 3.780,00 EUR\nClassificação CPV (Vocabulário Comum para os Contratos Públicos)\nObjeto principal\nVocabulário Principal: 33140000\nNº: LOT-0002\nDescrição do Lote: Protese biliar plastica curva\nPreço base s/IVA: 1.620,00 EUR\nClassificação CPV (Vocabulário Comum para os Contratos Públicos)\nObjeto principal\nVocabulário Principal: 33140000\nNº: LOT-0003\nDescrição do Lote: Protese biliar plastica pré . Montada recta\nPreço base s/IVA: 27.300,00 EUR\nClassificação CPV (Vocabulário Comum para os Contratos Públicos)\nObjeto principal\nVocabulário Principal: 33140000\nNº: LOT-0004\nDescrição do Lote: Protese biliar plastica pré . Montada curva\nPreço base s/IVA: 4.875,00 EUR\nClassificação CPV (Vocabulário Comum para os Contratos Públicos)\nObjeto principal\nVocabulário Principal: 33140000\nNº: LOT-0005\nDescrição do Lote: Protese biliar plastica de duplo pigtail \nPreço base s/IVA: 12.540,00 EUR\nClassificação CPV (Vocabulário Comum para os Contratos Públicos)\nObjeto principal\nVocabulário Principal: 33140000\nNº: LOT-0006\nDescrição do Lote: Protese pancreatica  pigtail  com ponta anti trauma\nPreço base s/IVA: 11.760,00 EUR\nClassificação CPV (Vocabulário Comum para os Contratos Públicos)\nObjeto principal\nVocabulário Principal: 33140000\nNº: LOT-0007\nDescrição do Lote: Protese Biliar Auto-Expansiva Totalmente Coberta em Nitinol\nPreço base s/IVA: 26.325,00 EUR\nClassificação CPV (Vocabulário Comum para os Contratos Públicos)\nObjeto principal\nVocabulário Principal: 33140000\nNº: LOT-0008\nDescrição do Lote: Protese biliar auto-expansiva totalmente coberta  em  platinol rev. A permalume\nPreço base s/IVA: 28.560,00 EUR\nClassificação CPV (Vocabulário Comum para os Contratos Públicos)\nObjeto principal\nVocabulário Principal: 33140000\nNº: LOT-0009\nDescrição do Lote: Protese biliar auto-expansiva totalmente coberta p/transplantados\nPreço base s/IVA: 14.400,00 EUR\nClassificação CPV (Vocabulário Comum para os Contratos Públicos)\nObjeto principal\nVocabulário Principal: 33140000\nNº: LOT-0010\nDescrição do Lote: Protese Biliar Auto-Expansiva Parcialmente Coberta em Nitinol\nPreço base s/IVA: 10.530,00 EUR\nClassificação CPV (Vocabulário Comum para os Contratos Públicos)\nObjeto principal\nVocabulário Principal: 33140000\nNº: LOT-0011\nDescrição do Lote: Protese Biliar Auto-Expansiva Não Coberta em Nitinol\nPreço base s/IVA: 87.750,00 EUR\nClassificação CPV (Vocabulário Comum para os Contratos Públicos)\nObjeto principal\nVocabulário Principal: 33140000\nNº: LOT-0012\nDescrição do Lote: Protese biliar auto-expansiva não coberta em platinol.\nPreço base s/IVA: 35.700,00 EUR\nClassificação CPV (Vocabulário Comum para os Contratos Públicos)\nObjeto principal\nVocabulário Principal: 33140000\nNº: LOT-0013\nDescrição do Lote: Protese biliar metalica nao coberta c/ introdutor ultra - fino\nPreço base s/IVA: 78.000,00 EUR\nClassificação CPV (Vocabulário Comum para os Contratos Públicos)\nObjeto principal\nVocabulário Principal: 33140000\nNº: LOT-0014\nDescrição do Lote: Protese biliar metalica hiliar de malha larga\nPreço base s/IVA: 36.000,00 EUR\nClassificação CPV (Vocabulário Comum para os Contratos Públicos)\nObjeto principal\nVocabulário Principal: 33140000\nNº: LOT-0015\nDescrição do Lote: Protese p/ hepaticogastrostomia\nPreço base s/IVA: 8.340,00 EUR\nClassificação CPV (Vocabulário Comum para os Contratos Públicos)\nObjeto principal\nVocabulário Principal: 33140000\nNº: LOT-0016\nDescrição do Lote: Protese de aposição luminal c/ sistema de libertação com eletrocautério\nPreço base s/IVA: 122.400,00 EUR\nClassificação CPV (Vocabulário Comum para os Contratos Públicos)\nObjeto principal\nVocabulário Principal: 33140000\nNº: LOT-0017\nDescrição do Lote: Protese Colica Nãq Coberta 100% em Nitinol\nPreço base s/IVA: 52.650,00 EUR\nClassificação CPV (Vocabulário Comum para os Contratos Públicos)\nObjeto principal\nVocabulário Principal: 33140000\nNº: LOT-0018\nDescrição do Lote: Protese esofagica coberta de libertacao distal 100% em nitinol\nPreço base s/IVA: 21.060,00 EUR\nClassificação CPV (Vocabulário Comum para os Contratos Públicos)\nObjeto principal\nVocabulário Principal: 33140000\nNº: LOT-0019\nDescrição do Lote: Protese esofagica coberta com revestimento em permalume de libertacao distal c/mri.\nPreço base s/IVA: 7.140,00 EUR\nClassificação CPV (Vocabulário Comum para os Contratos Públicos)\nObjeto principal\nVocabulário Principal: 33140000\nNº: LOT-0020\nDescrição do Lote: Protese esofagica parcialmente coberta de libertacao distal 100% em nitinol\nPreço base s/IVA: 21.060,00 EUR\nClassificação CPV (Vocabulário Comum para os Contratos Públicos)\nObjeto principal\nVocabulário Principal: 33140000\nNº: LOT-0021\nDescrição do Lote: Protese esof. Parc. Coberta distal c/pistola de libert. Cont. Malha fil. Unico\nPreço base s/IVA: 12.240,00 EUR\nClassificação CPV (Vocabulário Comum para os Contratos Públicos)\nObjeto principal\nVocabulário Principal: 33140000\nNº: LOT-0022\nDescrição do Lote: Protese esofagica de vacoterapia\nPreço base s/IVA: 28.800,00 EUR\nClassificação CPV (Vocabulário Comum para os Contratos Públicos)\nObjeto principal\nVocabulário Principal: 33140000\nNº: LOT-0023\nDescrição do Lote: Protese extra-longa p/tratamento de fistulas traqueo-esofagicas\nPreço base s/IVA: 2.250,00 EUR\nClassificação CPV (Vocabulário Comum para os Contratos Públicos)\nObjeto principal\nVocabulário Principal: 33140000\nNº: LOT-0024\nDescrição do Lote: Protese duodenal n/coberta 100% em nitinol com células não fixas\nPreço base s/IVA: 35.100,00 EUR\nClassificação CPV (Vocabulário Comum para os Contratos Públicos)\nObjeto principal\nVocabulário Principal: 33140000\nNº: LOT-0025\nDescrição do Lote: Protese para varizes esofagicas Extrator de proteses p/varizes esofágicas\nPreço base s/IVA: 43.200,00 EUR\nClassificação CPV (Vocabulário Comum para os Contratos Públicos)\nObjeto principal\nVocabulário Principal: 33140000\n\n7 - INDICAÇÕES ADICIONAIS\nO contrato envolve aquisição conjunta (satisfação de várias entidades)? Não\nO contrato é adjudicado por uma central de compras? Não\n\n8 - TÉCNICAS\nO concurso destina-se à celebração de um acordo-quadro? Inexistência de acordo-quadro\nÉ utilizado um leilão eletrónico? Não\nÉ adotada uma fase de negociação? Não\nSistema de Aquisição Dinâmico: Inexistência de sistema de aquisição dinâmico\n\n9 - LOCAL DA EXECUÇÃO DO CONTRATO\nLOCAL DA EXECUÇÃO DO CONTRATO (PROCEDIMENTO)\nPaís: Portugal\nNUT III: PT170\nLocalidade: Lisboa\nDistrito: Lisboa\nConcelho: Lisboa\nFreguesia: Freguesia de Arroios - Lisboa\nLOCAL DA EXECUÇÃO DO CONTRATO (LOTE)\nIdentificador do Lote: LOT-0001; LOT-0002; LOT-0003; LOT-0004; LOT-0005; LOT-0006; LOT-0007; LOT-0008; LOT-0009; LOT-0010; LOT-0011; LOT-0012; LOT-0013; LOT-0014; LOT-0015; LOT-0016; LOT-0017; LOT-0018; LOT-0019; LOT-0020; LOT-0021; LOT-0022; LOT-0023; LOT-0024; LOT-0025\nPaís: Portugal\nNUT III: PT170\nLocalidade: Lisboa\nDistrito: Lisboa\nConcelho: Lisboa\nFreguesia: Freguesia de Arroios - Lisboa\n\n10 - PRAZO DE EXECUÇÃO DO CONTRATO\nIdentificador do Lote: LOT-0001; LOT-0002; LOT-0003; LOT-0004; LOT-0005; LOT-0006; LOT-0007; LOT-0008; LOT-0009; LOT-0010; LOT-0011; LOT-0012; LOT-0013; LOT-0014; LOT-0015; LOT-0016; LOT-0017; LOT-0018; LOT-0019; LOT-0020; LOT-0021; LOT-0022; LOT-0023; LOT-0024; LOT-0025\nPrazo de execução do contrato: 36 MESES\nPrevisão de renovações: Não\n\n11 - FUNDOS EU\nIdentificador do Lote: LOT-0001; LOT-0002; LOT-0003; LOT-0004; LOT-0005; LOT-0006; LOT-0007; LOT-0008; LOT-0009; LOT-0010; LOT-0011; LOT-0012; LOT-0013; LOT-0014; LOT-0015; LOT-0016; LOT-0017; LOT-0018; LOT-0019; LOT-0020; LOT-0021; LOT-0022; LOT-0023; LOT-0024; LOT-0025\nTêm fundos EU? Não\n\n12 - DOCUMENTOS DE HABILITAÇÃO\nHabilitação para o exercício da atividade profissional: Não\n\n13 - CONDIÇÕES DE APRESENTAÇÃO\nPlataforma eletrónica utilizada pela entidade adjudicante: VORTAL\nURL para Apresentação: https://community.vortal.biz/public/\nAdmissibilidade da apresentação de propostas variantes: Não autorizado\nPrazo para apresentação das propostas: 03-02-2026 23:59\nPrazo durante o qual os concorrentes são obrigados a manter as respetivas propostas: 120 dias a contar do termo do prazo para a apresentação das propostas\nApresentação de Catálogo Eletrónico: Permitido\nIndicação de Subcontratação na Proposta: Inexistência de indicação de subcontratação\n\n14 - PRESTAÇÃO DE CAUÇÃO\nPrestação de caução: Não\n\n15 - FORNECIMENTO DAS PEÇAS DO CONCURSO, APRESENTAÇÃO DE PEDIDOS DE PARTICIPAÇÃO E APRESENTAÇÃO DAS PROPOSTAS\nLink para acesso às peças do concurso (URL): https://community.vortal.biz/Public/public-tender-documents/bXU4MFczSExkT1k3cWdVcHRBaWpLQ0ljMW1YUUZPT25panlJdFNhbUJmcXRLZ0h4MHVrNnhwYjc3WldEN1QwSDQ3VDVxcmhjaVYveXBJenZHamR4Z2c9PVAxNlhU\n\n20 - OUTROS REQUISITOS\nIdentificador do Lote: LOT-0001; LOT-0002; LOT-0003; LOT-0004; LOT-0005; LOT-0006; LOT-0007; LOT-0008; LOT-0009; LOT-0010; LOT-0011; LOT-0012; LOT-0013; LOT-0014; LOT-0015; LOT-0016; LOT-0017; LOT-0018; LOT-0019; LOT-0020; LOT-0021; LOT-0022; LOT-0023; LOT-0024; LOT-0025\nInformação sobre contratos reservados. Aplica-se a contratos reservados (54º-A)? Não\n\n21 - CRITÉRIO DE ADJUDICAÇÃO\nO Critério de adjudicação é diferenciado por lote? Não\nMultifator: Não\nMonofator:\nNome: Preço\n\n24 - CONDIÇÕES DO CONTRATO\nIdentificador do Lote: LOT-0001; LOT-0002; LOT-0003; LOT-0004; LOT-0005; LOT-0006; LOT-0007; LOT-0008; LOT-0009; LOT-0010; LOT-0011; LOT-0012; LOT-0013; LOT-0014; LOT-0015; LOT-0016; LOT-0017; LOT-0018; LOT-0019; LOT-0020; LOT-0021; LOT-0022; LOT-0023; LOT-0024; LOT-0025\nFaturação Eletrónica: Permitido\nObrigação de Subcontratação:\nCódigo da Obrigação de Subcontratação: Não é aplicável nenhuma obrigação de subcontratação.\n\n25 - COMPRA PÚBLICA ESTRATÉGICA\nCompra Pública Estratégica: Inexistência de contratação pública estratégica\n\n26 - INFORMAÇÕES ADICIONAIS\nIdentificador do Lote: LOT-0001; LOT-0002; LOT-0003; LOT-0004; LOT-0005; LOT-0006; LOT-0007; LOT-0008; LOT-0009; LOT-0010; LOT-0011; LOT-0012; LOT-0013; LOT-0014; LOT-0015; LOT-0016; LOT-0017; LOT-0018; LOT-0019; LOT-0020; LOT-0021; LOT-0022; LOT-0023; LOT-0024; LOT-0025\nContrato adequado para PME: Sim\nCobertura ACP (Acordo dos Contratos Públicos da Organização Mundial do Comércio): Não\n\n27 - IDENTIFICAÇÃO E CONTACTOS DO ÓRGÃO DE RECURSOS ADMINISTRATIVOS\nDesignação: Conselho de Administração\nEndereço: Rua José António Serrano s/n\nCódigo postal: 1150-199\nLocalidade: Lisboa\nTelefone: +351 2188410000\nFax: +351 000000000\nEndereço eletrónico: sec.vca@ulssjose.min-saude.pt\n\n28 - IDENTIFICAÇÃO DO(S) AUTOR(ES) DE ANÚNCIO\nNome: Conselho de Administração\nCargo: Conselho de Administração\n419932784",
    "nipc": "508080142",
    "distrito": "Lisboa",
    "concelho": "Lisboa",
    "freguesia": "Freguesia de Arroios - Lisboa",
    "site": "www.chlc.min-saude.pt",
    "email": "geral@chlc.min-saude.pt",
    "designacao_contrato": "Próteses Biliares, pancreáticas, cólicas, esofágicas e duodenais",
    "descricao": "Próteses Biliares, pancreáticas, cólicas, esofágicas e duodenais",
    "preco_base": "733.380,00 EUR",
    "prazo_execucao": "36 MESES",
    "prazo_apresentacao_propostas": "03-02-2026 23:59",
    "fundos_eu": "Não",
    "plataforma_eletronica": "VORTAL",
    "url_procedimento": "https://community.vortal.biz/public/",
    "autor_nome": "Conselho de Administração",
    "autor_cargo": "Conselho de Administração"
  },
  {
    "numero_procedimento": "N/A",
    "entidade": "AnÃºncio de procedimento  n.Âº 33664/2025  -  DiÃ¡rio da RepÃºblica n.Âº 251/2025, SÃ©rie II de 2025-12-31",
    "link": "https://diariodarepublica.pt/dr/detalhe/contrato-publico/33664-993315611"
  },
  {
    "numero_procedimento": "N/A",
    "entidade": "Unidade Local de Saúde de Loures-Odivelas, EPE",
    "link": "https://diariodarepublica.pt/dr/detalhe/contrato-publico/33656-993316678",
    "detalhes_completos": "1 - IDENTIFICAÇÃO E CONTACTOS DA ENTIDADE ADJUDICANTE\nDesignação da entidade adjudicante: Unidade Local de Saúde de Loures-Odivelas, EPE\nNIPC: 516726862\nEndereço: Avenida Carlos Teixeira nº 3\nCódigo postal: 2674-514\nLocalidade: Lisboa\nPaís: Portugal\nNUT III: PT170\nDistrito: Lisboa\nConcelho: Loures\nFreguesia: Freguesia de Loures\nTelefone: 939007019\nFax: 219847200\nEndereço da Entidade (URL): https://www.hbeatrizangelo.pt\nEndereço Eletrónico: andreia.teixeira.chaves@ulslod.min-saude.pt\neDelivery Gateway (URL): https://community.vortal.biz/public/\nFunção da Organização: Adquirente\nNorma jurídica da Entidade Adjudicante: Empresa pública\nÁrea de atividade da Autoridade Adjudicante: Saúde\n\n2 - JORNAL OFICIAL DA UNIÃO EUROPEIA\nO procedimento a que este anúncio diz respeito também é publicitado no Jornal Oficial da União Europeia? Não\n\n3 - AVISO\nModelo de Anúncio: Concurso público\nData de Envio do Anúncio: 30-12-2025\n\n5 - PROCESSO\nTipo de Procedimento: Concurso público\nPreço base do procedimento: Sim\nValor do preço base do procedimento: 86.715,00 EUR\nProcedimento com lotes? Não\n\n6 - OBJETO DO CONTRATO\nNúmero de referência interna: 04000002722026\nDesignação do contrato: AQUISIÇÃO DE SERVIÇOS DE MANUTENÇÃO CORRETIVA, PREVENTIVA E EVOLUTIVA DO MOTOR DE INTEGRAÇÃO CENTRAL\nDescrição: AQUISIÇÃO DE SERVIÇOS DE MANUTENÇÃO CORRETIVA, PREVENTIVA E EVOLUTIVA DO MOTOR DE INTEGRAÇÃO CENTRAL\nTipo de Contrato Principal: Aquisição de Serviços\nTipo de Contrato: Aquisição de Serviços\nClassificação CPV (Vocabulário Comum para os Contratos Públicos)\nObjeto principal\nVocabulário Principal: 72227000\nPreço base s/IVA: 86.715,00 EUR\n\n7 - INDICAÇÕES ADICIONAIS\nO contrato envolve aquisição conjunta (satisfação de várias entidades)? Não\nO contrato é adjudicado por uma central de compras? Não\n\n8 - TÉCNICAS\nO concurso destina-se à celebração de um acordo-quadro? Inexistência de acordo-quadro\nÉ utilizado um leilão eletrónico? Não\nÉ adotada uma fase de negociação? Não\nSistema de Aquisição Dinâmico: Inexistência de sistema de aquisição dinâmico\n\n9 - LOCAL DA EXECUÇÃO DO CONTRATO\nLOCAL DA EXECUÇÃO DO CONTRATO (PROCEDIMENTO)\nPaís: Portugal\nNUT III: PT170\nLocalidade: Lisboa\nDistrito: Lisboa\nConcelho: Loures\nFreguesia: Freguesia de Loures\n\n10 - PRAZO DE EXECUÇÃO DO CONTRATO\nPrazo de execução do contrato: 12 DIAS\nPrevisão de renovações: Não\n\n11 - FUNDOS EU\nTêm fundos EU? Não\n\n12 - DOCUMENTOS DE HABILITAÇÃO\nHabilitação para o exercício da atividade profissional: Não\n\n13 - CONDIÇÕES DE APRESENTAÇÃO\nPlataforma eletrónica utilizada pela entidade adjudicante: VORTAL\nURL para Apresentação: https://community.vortal.biz/public/\nAdmissibilidade da apresentação de propostas variantes: Não autorizado\nPrazo para apresentação das propostas: 12-01-2026 17:00\nPrazo durante o qual os concorrentes são obrigados a manter as respetivas propostas: 120 dias a contar do termo do prazo para a apresentação das propostas\nIndicação de Subcontratação na Proposta: Inexistência de indicação de subcontratação\n\n14 - PRESTAÇÃO DE CAUÇÃO\nPrestação de caução: Não\n\n15 - FORNECIMENTO DAS PEÇAS DO CONCURSO, APRESENTAÇÃO DE PEDIDOS DE PARTICIPAÇÃO E APRESENTAÇÃO DAS PROPOSTAS\nLink para acesso às peças do concurso (URL): https://community.vortal.biz/Public/public-tender-documents/QlhXUTNZQ3ZEd1dmR0hFZTVma0FMVFhyazVWcUtWdnB3OG1VVVFBTWdoV3RyWkFZSjJhbkpGaFdoZE9LOXpwMkFVdkRFc3NETzl1eE0rR2x0ZXo1WFE9PUBMWGs0\n\n20 - OUTROS REQUISITOS\nInformação sobre contratos reservados. Aplica-se a contratos reservados (54º-A)? Não\n\n21 - CRITÉRIO DE ADJUDICAÇÃO\nMultifator: Não\nMonofator:\nNome: Preço\n\n24 - CONDIÇÕES DO CONTRATO\nFaturação Eletrónica: Permitido\nObrigação de Subcontratação:\nCódigo da Obrigação de Subcontratação: Não é aplicável nenhuma obrigação de subcontratação.\n\n25 - COMPRA PÚBLICA ESTRATÉGICA\nCompra Pública Estratégica: Inexistência de contratação pública estratégica\n\n26 - INFORMAÇÕES ADICIONAIS\nContrato adequado para PME: Sim\nCobertura ACP (Acordo dos Contratos Públicos da Organização Mundial do Comércio): Não\n\n27 - IDENTIFICAÇÃO E CONTACTOS DO ÓRGÃO DE RECURSOS ADMINISTRATIVOS\nDesignação: ULSLOD\nEndereço: Av. Carlos Teixeira, 3\nCódigo postal: 2674-514\nLocalidade: Loures\nTelefone: +351 219847200\nFax: +351 219847200\nEndereço eletrónico: servicos_imobilizados_hba@ulslod.min-saude.pt\n\n28 - IDENTIFICAÇÃO DO(S) AUTOR(ES) DE ANÚNCIO\nNome: André Martins\nCargo: Técnico Superior\n419933837",
    "nipc": "516726862",
    "distrito": "Lisboa",
    "concelho": "Loures",
    "freguesia": "Freguesia de Loures",
    "site": "https://www.hbeatrizangelo.pt",
    "email": "andreia.teixeira.chaves@ulslod.min-saude.pt",
    "designacao_contrato": "AQUISIÇÃO DE SERVIÇOS DE MANUTENÇÃO CORRETIVA, PREVENTIVA E EVOLUTIVA DO MOTOR DE INTEGRAÇÃO CENTRAL",
    "descricao": "AQUISIÇÃO DE SERVIÇOS DE MANUTENÇÃO CORRETIVA, PREVENTIVA E EVOLUTIVA DO MOTOR DE INTEGRAÇÃO CENTRAL",
    "preco_base": "86.715,00 EUR",
    "prazo_execucao": "12 DIAS",
    "prazo_apresentacao_propostas": "12-01-2026 17:00",
    "fundos_eu": "Não",
    "plataforma_eletronica": "VORTAL",
    "url_procedimento": "https://community.vortal.biz/public/",
    "autor_nome": "André Martins",
    "autor_cargo": "Técnico Superior"
  },
  {
    "numero_procedimento": "N/A",
    "entidade": "Unidade Local de Saúde de Loures-Odivelas, EPE",
    "link": "https://diariodarepublica.pt/dr/detalhe/contrato-publico/33657-993316679",
    "detalhes_completos": "1 - IDENTIFICAÇÃO E CONTACTOS DA ENTIDADE ADJUDICANTE\nDesignação da entidade adjudicante: Unidade Local de Saúde de Loures-Odivelas, EPE\nNIPC: 516726862\nEndereço: Avenida Carlos Teixeira nº 3\nCódigo postal: 2674-514\nLocalidade: Lisboa\nPaís: Portugal\nNUT III: PT170\nDistrito: Lisboa\nConcelho: Loures\nFreguesia: Freguesia de Loures\nTelefone: 939007019\nFax: 219847200\nEndereço da Entidade (URL): https://www.hbeatrizangelo.pt\nEndereço Eletrónico: andreia.teixeira.chaves@ulslod.min-saude.pt\neDelivery Gateway (URL): https://community.vortal.biz/public/\nFunção da Organização: Adquirente\nNorma jurídica da Entidade Adjudicante: Empresa pública\nÁrea de atividade da Autoridade Adjudicante: Saúde\n\n2 - JORNAL OFICIAL DA UNIÃO EUROPEIA\nO procedimento a que este anúncio diz respeito também é publicitado no Jornal Oficial da União Europeia? Não\n\n3 - AVISO\nModelo de Anúncio: Concurso público\nData de Envio do Anúncio: 30-12-2025\n\n5 - PROCESSO\nTipo de Procedimento: Concurso público\nPreço base do procedimento: Sim\nValor do preço base do procedimento: 22.939,40 EUR\nProcedimento com lotes? Sim\nNº Máx. de Lotes Autorizado: 3\nNúmero máximo de lotes que podem ser adjudicados a um concorrente: 3\n\n6 - OBJETO DO CONTRATO\nNúmero de referência interna: 04000002202026\nDesignação do contrato: AQUISIÇÃO DE SERVIÇOS DE COMUNICAÇÕES FIXAS E DE INTERNET\nDescrição: AQUISIÇÃO DE SERVIÇOS DE COMUNICAÇÕES FIXAS E DE INTERNET\nTipo de Contrato Principal: Aquisição de Serviços\nTipo de Contrato: Aquisição de Serviços\nClassificação CPV (Vocabulário Comum para os Contratos Públicos)\nObjeto principal\nVocabulário Principal: 64200000\nPreço base s/IVA: 22.939,40 EUR\nLotes: \nNº: LOT-0001\nDescrição do Lote: Lote 1\nPreço base s/IVA: 17.322,80 EUR\nClassificação CPV (Vocabulário Comum para os Contratos Públicos)\nObjeto principal\nVocabulário Principal: 64200000\nNº: LOT-0002\nDescrição do Lote: Lote 2\nPreço base s/IVA: 1.888,70 EUR\nClassificação CPV (Vocabulário Comum para os Contratos Públicos)\nObjeto principal\nVocabulário Principal: 64200000\nNº: LOT-0003\nDescrição do Lote: Lote 3\nPreço base s/IVA: 3.727,90 EUR\nClassificação CPV (Vocabulário Comum para os Contratos Públicos)\nObjeto principal\nVocabulário Principal: 64200000\n\n7 - INDICAÇÕES ADICIONAIS\nO contrato envolve aquisição conjunta (satisfação de várias entidades)? Não\nO contrato é adjudicado por uma central de compras? Não\n\n8 - TÉCNICAS\nO concurso destina-se à celebração de um acordo-quadro? Inexistência de acordo-quadro\nÉ utilizado um leilão eletrónico? Não\nÉ adotada uma fase de negociação? Não\nSistema de Aquisição Dinâmico: Inexistência de sistema de aquisição dinâmico\n\n9 - LOCAL DA EXECUÇÃO DO CONTRATO\nLOCAL DA EXECUÇÃO DO CONTRATO (PROCEDIMENTO)\nPaís: Portugal\nNUT III: PT170\nLocalidade: Lisboa\nDistrito: Lisboa\nConcelho: Loures\nFreguesia: Freguesia de Loures\nLOCAL DA EXECUÇÃO DO CONTRATO (LOTE)\nIdentificador do Lote: LOT-0001; LOT-0002; LOT-0003\nPaís: Portugal\nNUT III: PT170\nLocalidade: Lisboa\nDistrito: Lisboa\nConcelho: Loures\nFreguesia: Freguesia de Loures\n\n10 - PRAZO DE EXECUÇÃO DO CONTRATO\nIdentificador do Lote: LOT-0001; LOT-0002; LOT-0003\nPrazo de execução do contrato: 12 MESES\nPrevisão de renovações: Não\n\n11 - FUNDOS EU\nIdentificador do Lote: LOT-0001; LOT-0002; LOT-0003\nTêm fundos EU? Não\n\n12 - DOCUMENTOS DE HABILITAÇÃO\nHabilitação para o exercício da atividade profissional: Não\n\n13 - CONDIÇÕES DE APRESENTAÇÃO\nPlataforma eletrónica utilizada pela entidade adjudicante: VORTAL\nURL para Apresentação: https://community.vortal.biz/public/\nAdmissibilidade da apresentação de propostas variantes: Não autorizado\nPrazo para apresentação das propostas: 12-01-2026 17:00\nPrazo durante o qual os concorrentes são obrigados a manter as respetivas propostas: 120 dias a contar do termo do prazo para a apresentação das propostas\nIndicação de Subcontratação na Proposta: Inexistência de indicação de subcontratação\n\n14 - PRESTAÇÃO DE CAUÇÃO\nPrestação de caução: Não\n\n15 - FORNECIMENTO DAS PEÇAS DO CONCURSO, APRESENTAÇÃO DE PEDIDOS DE PARTICIPAÇÃO E APRESENTAÇÃO DAS PROPOSTAS\nLink para acesso às peças do concurso (URL): https://community.vortal.biz/Public/public-tender-documents/d1h3MDlDTE5nZ0svbnFQUTNFcXlvUVpvdlNieXl0ZFdIZkJVSTEyS1ZYTEhldzh5MmZTaEMwVVhReGJYRVdzY0E4Y2wrRnlSbmx2aC91SkZnWlBiUnc9PWpfMzdj\n\n20 - OUTROS REQUISITOS\nIdentificador do Lote: LOT-0001; LOT-0002; LOT-0003\nInformação sobre contratos reservados. Aplica-se a contratos reservados (54º-A)? Não\n\n21 - CRITÉRIO DE ADJUDICAÇÃO\nO Critério de adjudicação é diferenciado por lote? Não\nMultifator: Não\nMonofator:\nNome: Preço\n\n24 - CONDIÇÕES DO CONTRATO\nIdentificador do Lote: LOT-0001; LOT-0002; LOT-0003\nFaturação Eletrónica: Permitido\nObrigação de Subcontratação:\nCódigo da Obrigação de Subcontratação: Não é aplicável nenhuma obrigação de subcontratação.\n\n25 - COMPRA PÚBLICA ESTRATÉGICA\nCompra Pública Estratégica: Inexistência de contratação pública estratégica\n\n26 - INFORMAÇÕES ADICIONAIS\nIdentificador do Lote: LOT-0001; LOT-0002; LOT-0003\nContrato adequado para PME: Sim\nCobertura ACP (Acordo dos Contratos Públicos da Organização Mundial do Comércio): Não\n\n27 - IDENTIFICAÇÃO E CONTACTOS DO ÓRGÃO DE RECURSOS ADMINISTRATIVOS\nDesignação: ULSLOD\nEndereço: Av. Carlos Teixeira, 3\nCódigo postal: 2674-514\nLocalidade: Loures\nTelefone: +351 219847200\nFax: +351 219847200\nEndereço eletrónico: servicos_imobilizados_hba@ulslod.min-saude.pt\n\n28 - IDENTIFICAÇÃO DO(S) AUTOR(ES) DE ANÚNCIO\nNome: André Martins\nCargo: Técnico Superior\n419933594",
    "nipc": "516726862",
    "distrito": "Lisboa",
    "concelho": "Loures",
    "freguesia": "Freguesia de Loures",
    "site": "https://www.hbeatrizangelo.pt",
    "email": "andreia.teixeira.chaves@ulslod.min-saude.pt",
    "designacao_contrato": "AQUISIÇÃO DE SERVIÇOS DE COMUNICAÇÕES FIXAS E DE INTERNET",
    "descricao": "AQUISIÇÃO DE SERVIÇOS DE COMUNICAÇÕES FIXAS E DE INTERNET",
    "preco_base": "22.939,40 EUR",
    "prazo_execucao": "12 MESES",
    "prazo_apresentacao_propostas": "12-01-2026 17:00",
    "fundos_eu": "Não",
    "plataforma_eletronica": "VORTAL",
    "url_procedimento": "https://community.vortal.biz/public/",
    "autor_nome": "André Martins",
    "autor_cargo": "Técnico Superior"
  },
  {
    "numero_procedimento": "N/A",
    "entidade": "Município de Santa Maria da Feira",
    "link": "https://diariodarepublica.pt/dr/detalhe/contrato-publico/33659-993605118",
    "detalhes_completos": "1 - IDENTIFICAÇÃO E CONTACTOS DA ENTIDADE ADJUDICANTE\nDesignação da entidade adjudicante: Município de Santa Maria da Feira\nNIPC: 501157280\nServiço/Órgão/Pessoa de contacto: Câmara Municipal de Santa Maria da Feira\nEndereço: Praça da República, 135\nCódigo postal: 4520-174\nLocalidade: Santa Maria da Feira\nPaís: Portugal\nNUT III: PT11A\nDistrito: Aveiro\nConcelho: Santa Maria da Feira\nFreguesia: União das Freguesias de Santa Maria da Feira, Travanca, Sanfins e Espargo\nTelefone: 256370800\nFax: 256370807\nEndereço da Entidade (URL): www.cm-feira.pt\nEndereço Eletrónico: central.compras@cm-feira.pt\nFunção da Organização: Adquirente\nNorma jurídica da Entidade Adjudicante: Autoridade local\nÁrea de atividade da Autoridade Adjudicante: Serviços públicos das administrações públicas\n\n2 - JORNAL OFICIAL DA UNIÃO EUROPEIA\nO procedimento a que este anúncio diz respeito também é publicitado no Jornal Oficial da União Europeia? Sim\n\n3 - AVISO\nModelo de Anúncio: Concurso público\nData de Envio do Anúncio: 29-12-2025\n\n5 - PROCESSO\nTipo de Procedimento: Concurso público\nPreço base do procedimento: Sim\nValor do preço base do procedimento: 750.000,00 EUR\nProcedimento com lotes? Não\n\n6 - OBJETO DO CONTRATO\nNúmero de referência interna: SMF/0004031/CPI/B/25\nDesignação do contrato: Fornecimento de Mistura Betuminosa Densa a Quente 0/14mm\nDescrição: Fornecimento de Mistura Betuminosa Densa a Quente 0/14mm\nOpções: Não\nTipo de Contrato Principal: Aquisição de Bens Móveis\nTipo de Contrato: Aquisição de Bens Móveis\nClassificação CPV (Vocabulário Comum para os Contratos Públicos)\nObjeto principal\nVocabulário Principal: 09200000\nPreço base s/IVA: 750.000,00 EUR\n\n7 - INDICAÇÕES ADICIONAIS\nO contrato envolve aquisição conjunta (satisfação de várias entidades)? Não\nO contrato é adjudicado por uma central de compras? Não\n\n8 - TÉCNICAS\nO concurso destina-se à celebração de um acordo-quadro? Inexistência de acordo-quadro\nÉ utilizado um leilão eletrónico? Não\nÉ adotada uma fase de negociação? Não\nSistema de Aquisição Dinâmico: Inexistência de sistema de aquisição dinâmico\n\n9 - LOCAL DA EXECUÇÃO DO CONTRATO\nLOCAL DA EXECUÇÃO DO CONTRATO (PROCEDIMENTO)\nPaís: Portugal\nNUT III: PT11A\nLocalidade: Estaleiro Municipal\nDistrito: Aveiro\nConcelho: Santa Maria da Feira\nFreguesia: Freguesia de São João de Ver\n\n10 - PRAZO DE EXECUÇÃO DO CONTRATO\nPrazo de execução do contrato: 12 MESES\nPrevisão de renovações: Não\n\n11 - FUNDOS EU\nTêm fundos EU? Não\n\n12 - DOCUMENTOS DE HABILITAÇÃO\nHabilitação para o exercício da atividade profissional: Não\n\n13 - CONDIÇÕES DE APRESENTAÇÃO\nPlataforma eletrónica utilizada pela entidade adjudicante: ANOGOV\nURL para Apresentação: https://www.anogov.com/cm-smfeira/faces/\nAdmissibilidade da apresentação de propostas variantes: Não autorizado\nPrazo para apresentação das propostas: 03-02-2026 23:59\nPrazo durante o qual os concorrentes são obrigados a manter as respetivas propostas: 66 dias a contar do termo do prazo para a apresentação das propostas\nApresentação de Catálogo Eletrónico: Não autorizado\nIndicação de Subcontratação na Proposta: Inexistência de indicação de subcontratação\n\n14 - PRESTAÇÃO DE CAUÇÃO\nPrestação de caução: Sim\nPercentagem: 5%\nDescrição da Garantia Exigida: 5 %\n\n15 - FORNECIMENTO DAS PEÇAS DO CONCURSO, APRESENTAÇÃO DE PEDIDOS DE PARTICIPAÇÃO E APRESENTAÇÃO DAS PROPOSTAS\nLink para acesso às peças do concurso (URL): https://www.anogov.com/cm-smfeira/faces/app/acessoDocs.jsp?codigoAcesso=FrorTaF7gwpbBiOZCWYvjURdtRkOrf0EChzJXqb4oBz5k5zVsd\n\n20 - OUTROS REQUISITOS\nInformação sobre contratos reservados. Aplica-se a contratos reservados (54º-A)? Não\n\n21 - CRITÉRIO DE ADJUDICAÇÃO\nMultifator: Sim\nFator: \nNome: Preço\nPonderação: 80%\nSubfatores: Não\nFator: \nNome: Outros\nOutro Nome: Distância do Fornecedor ao Estaleiro\nPonderação: 20%\nSubfatores: Não\n\n24 - CONDIÇÕES DO CONTRATO\nFaturação Eletrónica: Permitido\nObrigação de Subcontratação:\nCódigo da Obrigação de Subcontratação: Não é aplicável nenhuma obrigação de subcontratação.\n\n25 - COMPRA PÚBLICA ESTRATÉGICA\nCompra Pública Estratégica: Inexistência de contratação pública estratégica\n\n26 - INFORMAÇÕES ADICIONAIS\nContrato adequado para PME: Não\nCobertura ACP (Acordo dos Contratos Públicos da Organização Mundial do Comércio): Não\n\n27 - IDENTIFICAÇÃO E CONTACTOS DO ÓRGÃO DE RECURSOS ADMINISTRATIVOS\nDesignação: Câmara Municipal de Santa Maria da Feira\nEndereço: Praça da República\nCódigo postal: 4520-174\nLocalidade: Santa Maria da Feira\nEndereço eletrónico: central.compras@cm-feira.pt\nPrazo de interposição do recurso: 5 dias\n\n28 - IDENTIFICAÇÃO DO(S) AUTOR(ES) DE ANÚNCIO\nNome: Amadeu Albergaria\nCargo: O Presidente da Câmara Municipal\n419933415",
    "nipc": "501157280",
    "distrito": "Aveiro",
    "concelho": "Santa Maria da Feira",
    "freguesia": "União das Freguesias de Santa Maria da Feira, Travanca, Sanfins e Espargo",
    "site": "www.cm-feira.pt",
    "email": "central.compras@cm-feira.pt",
    "designacao_contrato": "Fornecimento de Mistura Betuminosa Densa a Quente 0/14mm",
    "descricao": "Fornecimento de Mistura Betuminosa Densa a Quente 0/14mm",
    "preco_base": "750.000,00 EUR",
    "prazo_execucao": "12 MESES",
    "prazo_apresentacao_propostas": "03-02-2026 23:59",
    "fundos_eu": "Não",
    "plataforma_eletronica": "ANOGOV",
    "url_procedimento": "https://www.anogov.com/cm-smfeira/faces/",
    "autor_nome": "Amadeu Albergaria",
    "autor_cargo": "O Presidente da Câmara Municipal"
  },
  {
    "numero_procedimento": "N/A",
    "entidade": "Docapesca - Portos e Lotas, SA",
    "link": "https://diariodarepublica.pt/dr/detalhe/contrato-publico/33660-993605119",
    "detalhes_completos": "1 - IDENTIFICAÇÃO E CONTACTOS DA ENTIDADE ADJUDICANTE\nDesignação da entidade adjudicante: Docapesca - Portos e Lotas, SA\nNIPC: 500086826\nEndereço: Av. Brasilia - Porta ES 7 - Pedrouços\nCódigo postal: 1400-038\nLocalidade: Lisboa\nPaís: Portugal\nNUT III: PT170\nDistrito: Lisboa\nConcelho: Lisboa\nFreguesia: Todas\nTelefone: 213936100\nFax: 213936101\nEndereço da Entidade (URL): www.docapesca.pt\nEndereço Eletrónico: docapesca@docapesca.pt\neDelivery Gateway (URL): https://community.vortal.biz/public/\nFunção da Organização: Adquirente\nNorma jurídica da Entidade Adjudicante: Autoridade da administração central\nÁrea de atividade da Autoridade Adjudicante: Serviços públicos das administrações públicas\n\n2 - JORNAL OFICIAL DA UNIÃO EUROPEIA\nO procedimento a que este anúncio diz respeito também é publicitado no Jornal Oficial da União Europeia? Sim\n\n3 - AVISO\nModelo de Anúncio: Concurso público\nData de Envio do Anúncio: 29-12-2025\n\n5 - PROCESSO\nTipo de Procedimento: Concurso público\nPreço base do procedimento: Sim\nValor do preço base do procedimento: 265.990,00 EUR\nProcedimento com lotes? Não\n\n6 - OBJETO DO CONTRATO\nNúmero de referência interna: DCM-201-CPI-2025 \nDesignação do contrato: Limpeza, higienização e gestão de resíduos do Porto de Pesca da Figueira da Foz\nDescrição: Prestação de serviços limpeza, higienização e gestão de resíduos do Porto de Pesca da Figueira da Foz\nOpções: Não\nTipo de Contrato Principal: Aquisição de Serviços\nTipo de Contrato: Aquisição de Serviços\nClassificação CPV (Vocabulário Comum para os Contratos Públicos)\nObjeto principal\nVocabulário Principal: 90500000\nPreço base s/IVA: 265.990,00 EUR\n\n7 - INDICAÇÕES ADICIONAIS\nO contrato envolve aquisição conjunta (satisfação de várias entidades)? Não\nO contrato é adjudicado por uma central de compras? Não\n\n8 - TÉCNICAS\nO concurso destina-se à celebração de um acordo-quadro? Inexistência de acordo-quadro\nÉ utilizado um leilão eletrónico? Não\nÉ adotada uma fase de negociação? Não\nSistema de Aquisição Dinâmico: Inexistência de sistema de aquisição dinâmico\n\n9 - LOCAL DA EXECUÇÃO DO CONTRATO\nLOCAL DA EXECUÇÃO DO CONTRATO (PROCEDIMENTO)\nPaís: Portugal\nNUT III: PT16D\nLocalidade: Aveiro\nDistrito: Aveiro\nConcelho: Ílhavo\nFreguesia: Freguesia de Gafanha da Nazaré\n\n10 - PRAZO DE EXECUÇÃO DO CONTRATO\nPrazo de execução do contrato: 24 MESES\nPrevisão de renovações: Não\n\n11 - FUNDOS EU\nTêm fundos EU? Não\n\n12 - DOCUMENTOS DE HABILITAÇÃO\nHabilitação para o exercício da atividade profissional: Não\n\n13 - CONDIÇÕES DE APRESENTAÇÃO\nPlataforma eletrónica utilizada pela entidade adjudicante: VORTAL\nURL para Apresentação: https://community.vortal.biz/public/\nAdmissibilidade da apresentação de propostas variantes: Não autorizado\nPrazo para apresentação das propostas: 29-01-2026 23:59\nPrazo durante o qual os concorrentes são obrigados a manter as respetivas propostas: 66 dias a contar do termo do prazo para a apresentação das propostas\nApresentação de Catálogo Eletrónico: Não autorizado\nIndicação de Subcontratação na Proposta: Inexistência de indicação de subcontratação\n\n14 - PRESTAÇÃO DE CAUÇÃO\nPrestação de caução: Sim\nPercentagem: 4%\nDescrição da Garantia Exigida: Mediante depósito, garantia bancária ou seguro-caução \n\n15 - FORNECIMENTO DAS PEÇAS DO CONCURSO, APRESENTAÇÃO DE PEDIDOS DE PARTICIPAÇÃO E APRESENTAÇÃO DAS PROPOSTAS\nLink para acesso às peças do concurso (URL): https://community.vortal.biz/Public/public-tender-documents/YTk3OTBicjlvcUo4NllXWTRLdU9hY0cxdVZCTnRjb3N6VW9NSmtkMlp6MmxsYlZxTzFCL3pFVmJNbk56SzRGMzU3RWk3WG9IMUN1ejhucmdjY2hteEE9PUh1I0xU\n\n20 - OUTROS REQUISITOS\nInformação sobre contratos reservados. Aplica-se a contratos reservados (54º-A)? Não\n\n21 - CRITÉRIO DE ADJUDICAÇÃO\nMultifator: Sim\nFator: \nNome: Preço\nPonderação: 85%\nSubfatores: Não\nFator: \nNome: Qualidade\nPonderação: 15%\nSubfatores: Não\n\n24 - CONDIÇÕES DO CONTRATO\nFaturação Eletrónica: Permitido\nObrigação de Subcontratação:\nCódigo da Obrigação de Subcontratação: Não é aplicável nenhuma obrigação de subcontratação.\n\n25 - COMPRA PÚBLICA ESTRATÉGICA\nCompra Pública Estratégica: Redução dos impactos ambientais\nDescrição do Processo de Adjudicação Estratégico: Conforme as peças do procedimento\nCritérios de contratos Públicos Ecológicos: Critérios de contratação pública ecológica nacional\nCategorias da estratégia nacional: Outros\nOutra categoria (Descrição): Ponto 8, parte B da RCM n.º 132/2023, de 25 de outubro\nDiretiva Veículos Não Poluentes: Não\nCritério de Acessibilidade: Os critérios de acessibilidade para as pessoas com deficiência não estão incluídos porque o contrato não se destina a pessoas singulares\n\n26 - INFORMAÇÕES ADICIONAIS\nContrato adequado para PME: Sim\nCobertura ACP (Acordo dos Contratos Públicos da Organização Mundial do Comércio): Não\n\n27 - IDENTIFICAÇÃO E CONTACTOS DO ÓRGÃO DE RECURSOS ADMINISTRATIVOS\nDesignação: Docapesca - Portos e Lotas, S.A.\nEndereço: Avenida Brasília, ES 7\nCódigo postal: 1400-038\nLocalidade: Lisboa\nTelefone: +351 213936100\nFax: +351 213936100\nEndereço eletrónico: docapesca@docapesca.pt\n\n28 - IDENTIFICAÇÃO DO(S) AUTOR(ES) DE ANÚNCIO\nNome: Afonso Gonçalves da Silva Oliveira\nCargo: Presidente do Conselho de Admnistração\n419934996",
    "nipc": "500086826",
    "distrito": "Lisboa",
    "concelho": "Lisboa",
    "freguesia": "Todas",
    "site": "www.docapesca.pt",
    "email": "docapesca@docapesca.pt",
    "designacao_contrato": "Limpeza, higienização e gestão de resíduos do Porto de Pesca da Figueira da Foz",
    "descricao": "Prestação de serviços limpeza, higienização e gestão de resíduos do Porto de Pesca da Figueira da Foz",
    "preco_base": "265.990,00 EUR",
    "prazo_execucao": "24 MESES",
    "prazo_apresentacao_propostas": "29-01-2026 23:59",
    "fundos_eu": "Não",
    "plataforma_eletronica": "VORTAL",
    "url_procedimento": "https://community.vortal.biz/public/",
    "autor_nome": "Afonso Gonçalves da Silva Oliveira",
    "autor_cargo": "Presidente do Conselho de Admnistração"
  },
  {
    "numero_procedimento": "N/A",
    "entidade": "Unidade Local de Saúde de São José, EPE",
    "link": "https://diariodarepublica.pt/dr/detalhe/contrato-publico/33663-993605120",
    "detalhes_completos": "1 - IDENTIFICAÇÃO E CONTACTOS DA ENTIDADE ADJUDICANTE\nDesignação da entidade adjudicante: Unidade Local de Saúde de São José, EPE\nNIPC: 508080142\nEndereço: Rua José António Serrano\nCódigo postal: 1150-199\nLocalidade: Lisboa\nPaís: Portugal\nNUT III: PT170\nDistrito: Lisboa\nConcelho: Lisboa\nFreguesia: Freguesia de Arroios - Lisboa\nTelefone: 218841403\nFax: 218841025\nEndereço da Entidade (URL): www.chlc.min-saude.pt\nEndereço Eletrónico: geral@chlc.min-saude.pt\neDelivery Gateway (URL): https://community.vortal.biz/public/\nFunção da Organização: Adquirente\nNorma jurídica da Entidade Adjudicante: Organismo de direito público\nÁrea de atividade da Autoridade Adjudicante: Saúde\n\n2 - JORNAL OFICIAL DA UNIÃO EUROPEIA\nO procedimento a que este anúncio diz respeito também é publicitado no Jornal Oficial da União Europeia? Sim\n\n3 - AVISO\nModelo de Anúncio: Concurso público\nData de Envio do Anúncio: 29-12-2025\n\n5 - PROCESSO\nTipo de Procedimento: Concurso público\nPreço base do procedimento: Sim\nValor do preço base do procedimento: 424.000,00 EUR\nProcedimento com lotes? Sim\nNº Máx. de Lotes Autorizado: 2\nNúmero máximo de lotes que podem ser adjudicados a um concorrente: 2\n\n6 - OBJETO DO CONTRATO\nNúmero de referência interna: 12006526\nDesignação do contrato: 12006526 - Material para Endoscopia da Coluna\nDescrição: 12006526 - Material para Endoscopia da Coluna\n\nOpções: Não\nTipo de Contrato Principal: Aquisição de Bens Móveis\nTipo de Contrato: Aquisição de Bens Móveis\nClassificação CPV (Vocabulário Comum para os Contratos Públicos)\nObjeto principal\nVocabulário Principal: 33100000\nPreço base s/IVA: 424.000,00 EUR\nLotes: \nNº: LOT-0001\nDescrição do Lote: Lote 1\nPreço base s/IVA: 176.000,00 EUR\nClassificação CPV (Vocabulário Comum para os Contratos Públicos)\nObjeto principal\nVocabulário Principal: 33100000\nNº: LOT-0002\nDescrição do Lote: Lote 2\nPreço base s/IVA: 248.000,00 EUR\nClassificação CPV (Vocabulário Comum para os Contratos Públicos)\nObjeto principal\nVocabulário Principal: 33100000\n\n7 - INDICAÇÕES ADICIONAIS\nO contrato envolve aquisição conjunta (satisfação de várias entidades)? Não\nO contrato é adjudicado por uma central de compras? Não\n\n8 - TÉCNICAS\nO concurso destina-se à celebração de um acordo-quadro? Inexistência de acordo-quadro\nÉ utilizado um leilão eletrónico? Não\nÉ adotada uma fase de negociação? Não\nSistema de Aquisição Dinâmico: Inexistência de sistema de aquisição dinâmico\n\n9 - LOCAL DA EXECUÇÃO DO CONTRATO\nLOCAL DA EXECUÇÃO DO CONTRATO (PROCEDIMENTO)\nPaís: Portugal\nNUT III: PT170\nLocalidade: Lisboa\nDistrito: Lisboa\nConcelho: Lisboa\nFreguesia: Freguesia de Arroios - Lisboa\nLOCAL DA EXECUÇÃO DO CONTRATO (LOTE)\nIdentificador do Lote: LOT-0001; LOT-0002\nPaís: Portugal\nNUT III: PT170\nLocalidade: Lisboa\nDistrito: Lisboa\nConcelho: Lisboa\nFreguesia: Freguesia de Arroios - Lisboa\n\n10 - PRAZO DE EXECUÇÃO DO CONTRATO\nIdentificador do Lote: LOT-0001; LOT-0002\nPrazo de execução do contrato: 2 ANOS\nPrevisão de renovações: Sim\nIndicar número máximo de renovações: 1\nPrazo de renovações diferente do prazo inicial: Não\n\n11 - FUNDOS EU\nIdentificador do Lote: LOT-0001; LOT-0002\nTêm fundos EU? Não\n\n12 - DOCUMENTOS DE HABILITAÇÃO\nHabilitação para o exercício da atividade profissional: Não\n\n13 - CONDIÇÕES DE APRESENTAÇÃO\nPlataforma eletrónica utilizada pela entidade adjudicante: VORTAL\nURL para Apresentação: https://community.vortal.biz/public/\nAdmissibilidade da apresentação de propostas variantes: Não autorizado\nPrazo para apresentação das propostas: 02-02-2026 23:59\nPrazo durante o qual os concorrentes são obrigados a manter as respetivas propostas: 120 dias a contar do termo do prazo para a apresentação das propostas\nApresentação de Catálogo Eletrónico: Permitido\nIndicação de Subcontratação na Proposta: Inexistência de indicação de subcontratação\n\n14 - PRESTAÇÃO DE CAUÇÃO\nPrestação de caução: Não\n\n15 - FORNECIMENTO DAS PEÇAS DO CONCURSO, APRESENTAÇÃO DE PEDIDOS DE PARTICIPAÇÃO E APRESENTAÇÃO DAS PROPOSTAS\nLink para acesso às peças do concurso (URL): https://community.vortal.biz/Public/public-tender-documents/MkpIVEMyODMxVVJ3a0VRRjhVbzNGT01aMEY3MmlyL0VjUzlpVzhkbW5WRndLbk5CTFAwK3BNNndhR0dDRHN2R0xUbDdMcFh6SUdRVEVpbFBWTTZMVlE9PUNMSjVM\n\n20 - OUTROS REQUISITOS\nIdentificador do Lote: LOT-0001; LOT-0002\nInformação sobre contratos reservados. Aplica-se a contratos reservados (54º-A)? Não\n\n21 - CRITÉRIO DE ADJUDICAÇÃO\nO Critério de adjudicação é diferenciado por lote? Sim\nIdentificador do lote: LOT-0001\nMultifator: Não\nMonofator:\nNome: Preço\nO Critério de adjudicação é diferenciado por lote? Sim\nIdentificador do lote: LOT-0002\nMultifator: Não\nMonofator:\nNome: Outros\nOutro nome: Conforme Anexo V do Programa do Procedimento\n\n24 - CONDIÇÕES DO CONTRATO\nIdentificador do Lote: LOT-0001; LOT-0002\nFaturação Eletrónica: Permitido\nObrigação de Subcontratação:\nCódigo da Obrigação de Subcontratação: Não é aplicável nenhuma obrigação de subcontratação.\n\n25 - COMPRA PÚBLICA ESTRATÉGICA\nCompra Pública Estratégica: Inexistência de contratação pública estratégica\n\n26 - INFORMAÇÕES ADICIONAIS\nIdentificador do Lote: LOT-0001; LOT-0002\nContrato adequado para PME: Sim\nCobertura ACP (Acordo dos Contratos Públicos da Organização Mundial do Comércio): Não\n\n27 - IDENTIFICAÇÃO E CONTACTOS DO ÓRGÃO DE RECURSOS ADMINISTRATIVOS\nDesignação: Conselho de Administração\nEndereço: Rua José António Serrano s/n\nCódigo postal: 1150-199\nLocalidade: Lisboa\nTelefone: +351 218841000\nFax: +351 218841023\nEndereço eletrónico: sec.vca@ulssjose.min-saude.pt\n\n28 - IDENTIFICAÇÃO DO(S) AUTOR(ES) DE ANÚNCIO\nNome: Conselho de Administração\nCargo: Conselho de Administração\n419932832",
    "nipc": "508080142",
    "distrito": "Lisboa",
    "concelho": "Lisboa",
    "freguesia": "Freguesia de Arroios - Lisboa",
    "site": "www.chlc.min-saude.pt",
    "email": "geral@chlc.min-saude.pt",
    "designacao_contrato": "12006526 - Material para Endoscopia da Coluna",
    "descricao": "12006526 - Material para Endoscopia da Coluna",
    "preco_base": "424.000,00 EUR",
    "prazo_execucao": "2 ANOS",
    "prazo_apresentacao_propostas": "02-02-2026 23:59",
    "fundos_eu": "Não",
    "plataforma_eletronica": "VORTAL",
    "url_procedimento": "https://community.vortal.biz/public/",
    "autor_nome": "Conselho de Administração",
    "autor_cargo": "Conselho de Administração"
  },
  {
    "numero_procedimento": "N/A",
    "entidade": "AnÃºncio de procedimento  n.Âº 33667/2025  -  DiÃ¡rio da RepÃºblica n.Âº 251/2025, SÃ©rie II de 2025-12-31",
    "link": "https://diariodarepublica.pt/dr/detalhe/contrato-publico/33667-993605121"
  },
  {
    "numero_procedimento": "N/A",
    "entidade": "Unidade Local de Saúde de Santa Maria, EPE",
    "link": "https://diariodarepublica.pt/dr/detalhe/contrato-publico/33668-993605122",
    "detalhes_completos": "Alteração do Anúncio de procedimento n.º 32403/2025, de 2025-12-15, com o ID 419877583\n\n1 - IDENTIFICAÇÃO E CONTACTOS DA ENTIDADE ADJUDICANTE\nDesignação da entidade adjudicante: Unidade Local de Saúde de Santa Maria, EPE\nNIPC: 508481287\nEndereço: Avenida Prof. Egas Moniz\nCódigo postal: 1649-035\nLocalidade: Lisboa\nPaís: Portugal\nNUT III: PT170\nDistrito: Lisboa\nConcelho: Lisboa\nFreguesia: Freguesia de Alvalade - Lisboa\nTelefone: 217805330\nFax: 217805605\nEndereço da Entidade (URL): www.ulssm.min-saude.pt\nEndereço Eletrónico: compras@ulssm.min-saude.pt\neDelivery Gateway (URL): https://community.vortal.biz/public/\nFunção da Organização: Adquirente\nNorma jurídica da Entidade Adjudicante: Empresa pública\nÁrea de atividade da Autoridade Adjudicante: Saúde\n\n2 - JORNAL OFICIAL DA UNIÃO EUROPEIA\nO procedimento a que este anúncio diz respeito também é publicitado no Jornal Oficial da União Europeia? Sim\n\n3 - AVISO\nModelo de Anúncio: Concurso público\nData de Envio do Anúncio: 29-12-2025\n\n5 - PROCESSO\nTipo de Procedimento: Concurso público\nPreço base do procedimento: Sim\nValor do preço base do procedimento: 17.288.729,11 EUR\nProcedimento com lotes? Não\n\n6 - OBJETO DO CONTRATO\nNúmero de referência interna: 269A000003\nDesignação do contrato: 269A000003\nDescrição: 269A000003 - “Prestação de serviços de higiene e limpeza das instalações das Unidades hospitalares da ULSSM (Hospital de Santa Maria e Parque Saúde Pulido Valente) para os anos 2026 a 2028\nOpções: Não\nTipo de Contrato Principal: Aquisição de Serviços\nTipo de Contrato: Aquisição de Serviços\nClassificação CPV (Vocabulário Comum para os Contratos Públicos)\nObjeto principal\nVocabulário Principal: 90910000\nPreço base s/IVA: 17.288.729,11 EUR\n\n7 - INDICAÇÕES ADICIONAIS\nO contrato envolve aquisição conjunta (satisfação de várias entidades)? Não\nO contrato é adjudicado por uma central de compras? Não\n\n8 - TÉCNICAS\nO concurso destina-se à celebração de um acordo-quadro? Inexistência de acordo-quadro\nÉ utilizado um leilão eletrónico? Não\nÉ adotada uma fase de negociação? Não\nSistema de Aquisição Dinâmico: Inexistência de sistema de aquisição dinâmico\n\n9 - LOCAL DA EXECUÇÃO DO CONTRATO\nLOCAL DA EXECUÇÃO DO CONTRATO (PROCEDIMENTO)\nPaís: Portugal\nNUT III: PT170\nLocalidade: Lisboa\nDistrito: Lisboa\nConcelho: Lisboa\nFreguesia: Freguesia de Alvalade - Lisboa\n\n10 - PRAZO DE EXECUÇÃO DO CONTRATO\nPrazo de execução do contrato: 3 ANOS\nPrevisão de renovações: Não\n\n11 - FUNDOS EU\nTêm fundos EU? Não\n\n12 - DOCUMENTOS DE HABILITAÇÃO\nHabilitação para o exercício da atividade profissional: Não\n\n13 - CONDIÇÕES DE APRESENTAÇÃO\nPlataforma eletrónica utilizada pela entidade adjudicante: VORTAL\nURL para Apresentação: https://community.vortal.biz/public/\nAdmissibilidade da apresentação de propostas variantes: Não autorizado\nPrazo para apresentação das propostas: 28-01-2026 17:00\nPrazo durante o qual os concorrentes são obrigados a manter as respetivas propostas: 120 dias a contar do termo do prazo para a apresentação das propostas\nApresentação de Catálogo Eletrónico: Não autorizado\nIndicação de Subcontratação na Proposta: Inexistência de indicação de subcontratação\n\n14 - PRESTAÇÃO DE CAUÇÃO\nPrestação de caução: Sim\nPercentagem: 5%\nDescrição da Garantia Exigida: cfr. peças do procedimento\n\n15 - FORNECIMENTO DAS PEÇAS DO CONCURSO, APRESENTAÇÃO DE PEDIDOS DE PARTICIPAÇÃO E APRESENTAÇÃO DAS PROPOSTAS\nLink para acesso às peças do concurso (URL): https://community.vortal.biz/Public/public-tender-documents/enpHY2ZXWlVmY1l5ZTYxdThHL2I0R3BtWUlzVzVRd3hDU1Z2Um1zdSs0dlhYTG9uN1NmcFF0RWRYVkFmcWd1Y0RnSjZwdnA5TmRXM2QwTzN2Q0tSV0E9PTRtWHBt\n\n20 - OUTROS REQUISITOS\nInformação sobre contratos reservados. Aplica-se a contratos reservados (54º-A)? Não\n\n21 - CRITÉRIO DE ADJUDICAÇÃO\nMultifator: Sim\nFator: \nNome: Preço\nPonderação: 90%\nSubfatores: Não\nFator: \nNome: Qualidade\nPonderação: 10%\nSubfatores: Não\n\n24 - CONDIÇÕES DO CONTRATO\nFaturação Eletrónica: Permitido\nObrigação de Subcontratação:\nCódigo da Obrigação de Subcontratação: Não é aplicável nenhuma obrigação de subcontratação.\n\n25 - COMPRA PÚBLICA ESTRATÉGICA\nCompra Pública Estratégica: Redução dos impactos ambientais\nDescrição do Processo de Adjudicação Estratégico: Conforme as peças do procedimento\nCritérios de contratos Públicos Ecológicos: Critérios de contratação pública ecológica nacional\nCategorias da estratégia nacional: Outros\nOutra categoria (Descrição): Higiene e Limpeza\nContratos Públicos Ecológicos: Outros\nDiretiva Veículos Não Poluentes: Não\nCritério de Acessibilidade: Os critérios de acessibilidade para as pessoas com deficiência não estão incluídos, com a seguinte justificação\nJustificação relativa à Acessibilidade: N/A \n\n26 - INFORMAÇÕES ADICIONAIS\nContrato adequado para PME: Sim\nCobertura ACP (Acordo dos Contratos Públicos da Organização Mundial do Comércio): Não\n\n27 - IDENTIFICAÇÃO E CONTACTOS DO ÓRGÃO DE RECURSOS ADMINISTRATIVOS\nDesignação: Conselho de Administração da ULSSM, E.P.E.\nEndereço: Av Professor Egas Moniz\nCódigo postal: 1649-035\nLocalidade: Lisboa\nTelefone: +351 217805330\nFax: +351 217805330\nEndereço eletrónico: compras@ulssm.min-saude.pt\n\n28 - IDENTIFICAÇÃO DO(S) AUTOR(ES) DE ANÚNCIO\nNome: Filipe Sousa\nCargo: Técnico Superior\n\n29 - ALTERAÇÃO\nMotivo da Alteração: Informações agora disponíveis\nIdentificador da Versão do Anúncio a Alterar: b7ae9140-0261-4e56-ba25-aa60320e4d2f-01\nIdentificador das Secções Alteradas do Anúncio Anterior: O procedimento a que este anúncio diz respeito também é publicitado no Jornal Oficial da União Europeia?\nDescrição das Alterações: prorrogação prazo \nAlteração dos Documentos do Concurso: Não\n419935368",
    "nipc": "508481287",
    "distrito": "Lisboa",
    "concelho": "Lisboa",
    "freguesia": "Freguesia de Alvalade - Lisboa",
    "site": "www.ulssm.min-saude.pt",
    "email": "compras@ulssm.min-saude.pt",
    "designacao_contrato": "269A000003",
    "descricao": "269A000003 - “Prestação de serviços de higiene e limpeza das instalações das Unidades hospitalares da ULSSM (Hospital de Santa Maria e Parque Saúde Pulido Valente) para os anos 2026 a 2028",
    "preco_base": "17.288.729,11 EUR",
    "prazo_execucao": "3 ANOS",
    "prazo_apresentacao_propostas": "28-01-2026 17:00",
    "fundos_eu": "Não",
    "plataforma_eletronica": "VORTAL",
    "url_procedimento": "https://community.vortal.biz/public/",
    "autor_nome": "Filipe Sousa",
    "autor_cargo": "Técnico Superior"
  },
  {
    "numero_procedimento": "N/A",
    "entidade": "Agência para o Investimento e Comércio Externo de Portugal, EPE",
    "link": "https://diariodarepublica.pt/dr/detalhe/contrato-publico/33670-993605123",
    "detalhes_completos": "1 - IDENTIFICAÇÃO E CONTACTOS DA ENTIDADE ADJUDICANTE\nDesignação da entidade adjudicante: Agência para o Investimento e Comércio Externo de Portugal, EPE\nNIPC: 506320120\nServiço/Órgão/Pessoa de contacto: Direção de Compras\nEndereço: Rua de Entrecampos, 28, Bloco B, 12º\nCódigo postal: 1700-158\nLocalidade: Lisboa\nPaís: Portugal\nNUT III: PT170\nDistrito: Lisboa\nConcelho: Lisboa\nFreguesia: Freguesia de Alvalade - Lisboa\nTelefone: 217909500\nFax: 217909500\nEndereço da Entidade (URL): http://www.portugalglobal.pt/\nEndereço Eletrónico: contratacao@portugalglobal.pt\neDelivery Gateway (URL): https://www.acingov.pt\nFunção da Organização: Adquirente\nNorma jurídica da Entidade Adjudicante: Empresa pública\nÁrea de atividade da Autoridade Adjudicante: Serviços públicos das administrações públicas\n\n2 - JORNAL OFICIAL DA UNIÃO EUROPEIA\nO procedimento a que este anúncio diz respeito também é publicitado no Jornal Oficial da União Europeia? Sim\n\n3 - AVISO\nModelo de Anúncio: Concurso público\nData de Envio do Anúncio: 29-12-2025\n\n5 - PROCESSO\nTipo de Procedimento: Concurso público\nPreço base do procedimento: Sim\nValor do preço base do procedimento: 178.193,00 EUR\nProcedimento com lotes? Sim\nNº Máx. de Lotes Autorizado: 2\nNúmero máximo de lotes que podem ser adjudicados a um concorrente: 2\n\n6 - OBJETO DO CONTRATO\nNúmero de referência interna: 0367.2025.CPI.DI\nDesignação do contrato: Aquisição de computadores portáteis para a AICEP\nDescrição: Aquisição de computadores portáteis para a AICEP\nOpções: Não\nTipo de Contrato Principal: Aquisição de Bens Móveis\nTipo de Contrato: Aquisição de Bens Móveis\nClassificação CPV (Vocabulário Comum para os Contratos Públicos)\nObjeto principal\nVocabulário Principal: 30213100\nPreço base s/IVA: 178.193,00 EUR\nLotes: \nNº: LOT-0001\nDescrição do Lote: Aquisição de 100 computadores Portáteis 16\nPreço base s/IVA: 106.793,00 EUR\nClassificação CPV (Vocabulário Comum para os Contratos Públicos)\nObjeto principal\nVocabulário Principal: 30213100\nNº: LOT-0002\nDescrição do Lote: Aquisição de 60 computadores Portáteis 14\nPreço base s/IVA: 71.400,00 EUR\nClassificação CPV (Vocabulário Comum para os Contratos Públicos)\nObjeto principal\nVocabulário Principal: 30213100\n\n7 - INDICAÇÕES ADICIONAIS\nO contrato envolve aquisição conjunta (satisfação de várias entidades)? Não\nO contrato é adjudicado por uma central de compras? Não\n\n8 - TÉCNICAS\nO concurso destina-se à celebração de um acordo-quadro? Inexistência de acordo-quadro\nÉ utilizado um leilão eletrónico? Não\nÉ adotada uma fase de negociação? Não\nSistema de Aquisição Dinâmico: Inexistência de sistema de aquisição dinâmico\n\n9 - LOCAL DA EXECUÇÃO DO CONTRATO\nLOCAL DA EXECUÇÃO DO CONTRATO (PROCEDIMENTO)\nPaís: Portugal\nNUT III: PT170\nLocalidade: Freguesia de Alvalade - Lisboa\nDistrito: Lisboa\nConcelho: Lisboa\nFreguesia: Freguesia de Alvalade - Lisboa\nLOCAL DA EXECUÇÃO DO CONTRATO (LOTE)\nIdentificador do Lote: LOT-0001; LOT-0002\nPaís: Portugal\nNUT III: PT170\nLocalidade: Freguesia de Alvalade - Lisboa\nDistrito: Lisboa\nConcelho: Lisboa\nFreguesia: Freguesia de Alvalade - Lisboa\n\n10 - PRAZO DE EXECUÇÃO DO CONTRATO\nIdentificador do Lote: LOT-0001; LOT-0002\nPrazo de execução do contrato: 45 DIAS\nPrevisão de renovações: Não\n\n11 - FUNDOS EU\nIdentificador do Lote: LOT-0001; LOT-0002\nTêm fundos EU? Sim\n\n12 - DOCUMENTOS DE HABILITAÇÃO\nHabilitação para o exercício da atividade profissional: Não\n\n13 - CONDIÇÕES DE APRESENTAÇÃO\nPlataforma eletrónica utilizada pela entidade adjudicante: ACIN\nURL para Apresentação: https://www.acingov.pt\nAdmissibilidade da apresentação de propostas variantes: Não autorizado\nPrazo para apresentação das propostas: 13-01-2026 23:59\nPrazo durante o qual os concorrentes são obrigados a manter as respetivas propostas: 90 dias a contar do termo do prazo para a apresentação das propostas\nApresentação de Catálogo Eletrónico: Permitido\nIndicação de Subcontratação na Proposta: Inexistência de indicação de subcontratação\n\n14 - PRESTAÇÃO DE CAUÇÃO\nPrestação de caução: Não\n\n15 - FORNECIMENTO DAS PEÇAS DO CONCURSO, APRESENTAÇÃO DE PEDIDOS DE PARTICIPAÇÃO E APRESENTAÇÃO DAS PROPOSTAS\nLink para acesso às peças do concurso (URL): https://www.acingov.pt/acingovprod/2/zonaPublica/zona_publica_c/donwloadProcedurePiece/MTAxMDgzNQ==\n\n20 - OUTROS REQUISITOS\nIdentificador do Lote: LOT-0001; LOT-0002\nInformação sobre contratos reservados. Aplica-se a contratos reservados (54º-A)? Não\n\n21 - CRITÉRIO DE ADJUDICAÇÃO\nO Critério de adjudicação é diferenciado por lote? Não\nMultifator: Não\nMonofator:\nNome: Preço\n\n24 - CONDIÇÕES DO CONTRATO\nIdentificador do Lote: LOT-0001; LOT-0002\nFaturação Eletrónica: Permitido\nObrigação de Subcontratação:\nCódigo da Obrigação de Subcontratação: Não é aplicável nenhuma obrigação de subcontratação.\n\n25 - COMPRA PÚBLICA ESTRATÉGICA\nCompra Pública Estratégica: Inexistência de contratação pública estratégica\n\n26 - INFORMAÇÕES ADICIONAIS\nIdentificador do Lote: LOT-0001; LOT-0002\nContrato adequado para PME: Sim\nCobertura ACP (Acordo dos Contratos Públicos da Organização Mundial do Comércio): Não\n\n27 - IDENTIFICAÇÃO E CONTACTOS DO ÓRGÃO DE RECURSOS ADMINISTRATIVOS\nDesignação: Conselho de Administração da AICEP, E.P.E.\nEndereço: Rua de Entrecampos, 28, Bloco B, 12º\nCódigo postal: 1700-158\nLocalidade: Lisboa\nTelefone: 217909500\nFax: \nEndereço eletrónico: contratacao@portugalglobal.pt\nPrazo de interposição do recurso: 5 dias\n\n28 - IDENTIFICAÇÃO DO(S) AUTOR(ES) DE ANÚNCIO\nNome: Susana Leal da Silva\nCargo: Técnica\n419935473",
    "nipc": "506320120",
    "distrito": "Lisboa",
    "concelho": "Lisboa",
    "freguesia": "Freguesia de Alvalade - Lisboa",
    "site": "http://www.portugalglobal.pt/",
    "email": "contratacao@portugalglobal.pt",
    "designacao_contrato": "Aquisição de computadores portáteis para a AICEP",
    "descricao": "Aquisição de computadores portáteis para a AICEP",
    "preco_base": "178.193,00 EUR",
    "prazo_execucao": "45 DIAS",
    "prazo_apresentacao_propostas": "13-01-2026 23:59",
    "fundos_eu": "Sim",
    "plataforma_eletronica": "ACIN",
    "url_procedimento": "https://www.acingov.pt",
    "autor_nome": "Susana Leal da Silva",
    "autor_cargo": "Técnica"
  },
  {
    "numero_procedimento": "N/A",
    "entidade": "Universidade do Porto",
    "link": "https://diariodarepublica.pt/dr/detalhe/contrato-publico/33674-993605140",
    "detalhes_completos": "1 - IDENTIFICAÇÃO E CONTACTOS DA ENTIDADE ADJUDICANTE\nDesignação da entidade adjudicante: Universidade do Porto\nNIPC: 501413197\nServiço/Órgão/Pessoa de contacto: Reitoria da Universidade do Porto / Serviços de Compras e Gestão Contratual\nEndereço: Praça Gomes Teixeira s/n\nCódigo postal: 4099-002\nLocalidade: Porto\nPaís: Portugal\nNUT III: PT11A\nDistrito: Porto\nConcelho: Porto\nFreguesia: União das Freguesias de Cedofeita, Santo Ildefonso, Sé, Miragaia, São Nicolau e Vitória\nTelefone: 220408000\nFax: 2204081867\nEndereço da Entidade (URL): www.reit.up.pt\nEndereço Eletrónico: reitoria@reit.up.pt\neDelivery Gateway (URL): https://www.acingov.pt\nFunção da Organização: Adquirente\nNorma jurídica da Entidade Adjudicante: Organismo de direito público\nÁrea de atividade da Autoridade Adjudicante: Educação\n\n2 - JORNAL OFICIAL DA UNIÃO EUROPEIA\nO procedimento a que este anúncio diz respeito também é publicitado no Jornal Oficial da União Europeia? Sim\n\n3 - AVISO\nModelo de Anúncio: Concurso público\nData de Envio do Anúncio: 29-12-2025\n\n5 - PROCESSO\nTipo de Procedimento: Concurso público\nPreço base do procedimento: Sim\nValor do preço base do procedimento: 93.000,00 EUR\nProcedimento com lotes? Não\n\n6 - OBJETO DO CONTRATO\nNúmero de referência interna: SCGC_REIT_CPI_00007_2025\nDesignação do contrato: Serviços de Consultoria Associados a Patentes\nDescrição: Serviços de Consultoria Associados a Patentes\nOpções: Não\nTipo de Contrato Principal: Aquisição de Serviços\nTipo de Contrato: Aquisição de Serviços\nClassificação CPV (Vocabulário Comum para os Contratos Públicos)\nObjeto principal\nVocabulário Principal: 79120000\nPreço base s/IVA: 93.000,00 EUR\n\n7 - INDICAÇÕES ADICIONAIS\nO contrato envolve aquisição conjunta (satisfação de várias entidades)? Não\nO contrato é adjudicado por uma central de compras? Não\n\n8 - TÉCNICAS\nO concurso destina-se à celebração de um acordo-quadro? Inexistência de acordo-quadro\nÉ utilizado um leilão eletrónico? Não\nÉ adotada uma fase de negociação? Não\nSistema de Aquisição Dinâmico: Inexistência de sistema de aquisição dinâmico\n\n9 - LOCAL DA EXECUÇÃO DO CONTRATO\nLOCAL DA EXECUÇÃO DO CONTRATO (PROCEDIMENTO)\nPaís: Portugal\nNUT III: PT11A\nLocalidade: União das Freguesias de Cedofeita, Santo Ildefonso, Sé, Miragaia, São Nicolau e Vitória\nDistrito: Porto\nConcelho: Porto\nFreguesia: União das Freguesias de Cedofeita, Santo Ildefonso, Sé, Miragaia, São Nicolau e Vitória\n\n10 - PRAZO DE EXECUÇÃO DO CONTRATO\nPrazo de execução do contrato: 12 MESES\nPrevisão de renovações: Não\n\n11 - FUNDOS EU\nTêm fundos EU? Não\n\n12 - DOCUMENTOS DE HABILITAÇÃO\nHabilitação para o exercício da atividade profissional: Não\n\n13 - CONDIÇÕES DE APRESENTAÇÃO\nPlataforma eletrónica utilizada pela entidade adjudicante: ACIN\nURL para Apresentação: https://www.acingov.pt\nAdmissibilidade da apresentação de propostas variantes: Não autorizado\nPrazo para apresentação das propostas: 28-01-2026 23:59\nPrazo durante o qual os concorrentes são obrigados a manter as respetivas propostas: 66 dias a contar do termo do prazo para a apresentação das propostas\nApresentação de Catálogo Eletrónico: Não autorizado\nIndicação de Subcontratação na Proposta: Inexistência de indicação de subcontratação\n\n14 - PRESTAÇÃO DE CAUÇÃO\nPrestação de caução: Não\n\n15 - FORNECIMENTO DAS PEÇAS DO CONCURSO, APRESENTAÇÃO DE PEDIDOS DE PARTICIPAÇÃO E APRESENTAÇÃO DAS PROPOSTAS\nLink para acesso às peças do concurso (URL): https://www.acingov.pt/acingovprod/2/zonaPublica/zona_publica_c/donwloadProcedurePiece/MTAxMDk3MQ==\n\n20 - OUTROS REQUISITOS\nInformação sobre contratos reservados. Aplica-se a contratos reservados (54º-A)? Não\n\n21 - CRITÉRIO DE ADJUDICAÇÃO\nMultifator: Sim\nFator: \nNome: Outros\nOutro Nome: ET  Equipa Técnica - Qualificação e experiência dos elementos afetos ao contrato\nPonderação: 50%\nSubfatores: Não\nFator: \nNome: Preço\nPonderação: 50%\nSubfatores: Não\n\n24 - CONDIÇÕES DO CONTRATO\nFaturação Eletrónica: Permitido\nObrigação de Subcontratação:\nCódigo da Obrigação de Subcontratação: Não é aplicável nenhuma obrigação de subcontratação.\n\n25 - COMPRA PÚBLICA ESTRATÉGICA\nCompra Pública Estratégica: Redução dos impactos ambientais\nDescrição do Processo de Adjudicação Estratégico: Atendendo à natureza imaterial e intelectual dos serviços de consultoria a contratar, a presente contratação integra critérios de sustentabilidade ambiental compatíveis com o respetivo objeto, em conformidade com a Estratégia Nacional para as Compras Públicas Ecológicas 2030 (ECO360) e com a Resolução do Conselho de Ministros n.º 132/2023. A prestação destes serviços assenta predominantemente em meios digitais, designadamente na elaboração, submissão e acompanhamento eletrónico de pedidos de patente, comunicações com institutos de propriedade industrial nacionais e internacionais e produção de documentação técnica e jurídica em formato digital, contribuindo para a desmaterialização de processos, a redução do consumo de papel e a diminuição do impacto ambiental associado a deslocações físicas e envio de documentação. Sempre que possível, será promovida a utilização de ferramentas eletrónicas de comunicação e de gestão processual, bem como a adoção de práticas de trabalho remoto, favorecendo a eficiência energética e a redução da pegada carbónica associada à execução do contrato. Desta forma, a contratação destes serviços permite conciliar a prossecução dos objetivos estratégicos da Universidade do Porto no domínio da inovação e da transferência de conhecimento com princípios de sustentabilidade ambiental, promovendo uma utilização eficiente dos recursos e práticas alinhadas com as orientações nacionais de contratação pública ecológica.\nCritérios de contratos Públicos Ecológicos: Outros critérios de contratação pública ecológica\nCategorias da estratégia nacional: Outros\nOutra categoria (Descrição): Sempre que possível, será promovida a utilização de ferramentas eletrónicas de comunicação e de gestão processual, bem como a adoção de práticas de trabalho remoto, favorecendo a eficiência energética e a redução da pegada carbónica associada à execução do contrato. Desta forma, a contratação destes serviços permite conciliar a prossecução dos objetivos estratégicos da Universidade do Porto no domínio da inovação e da transferência de conhecimento com princípios de sust...\nContratos Públicos Ecológicos: Outros\nDiretiva Veículos Não Poluentes: Não\nCritério de Acessibilidade: Os critérios de acessibilidade para as pessoas com deficiência não estão incluídos porque o contrato não se destina a pessoas singulares\n\n26 - INFORMAÇÕES ADICIONAIS\nContrato adequado para PME: Sim\nCobertura ACP (Acordo dos Contratos Públicos da Organização Mundial do Comércio): Não\n\n27 - IDENTIFICAÇÃO E CONTACTOS DO ÓRGÃO DE RECURSOS ADMINISTRATIVOS\nDesignação: Reitor\nEndereço: Universidade do Porto - Praça Gomes Teixeira, 4099-002 Porto, Portugal\nCódigo postal: 4099-002\nLocalidade: Porto\nTelefone: 220408000\nFax: 220408186\nEndereço eletrónico: compras@sp.up.pt\nPrazo de interposição do recurso: 5 dias\n\n28 - IDENTIFICAÇÃO DO(S) AUTOR(ES) DE ANÚNCIO\nNome: Renata Alexandra da Silva Castelo\nCargo: Técnica Superior\n419937052",
    "nipc": "501413197",
    "distrito": "Porto",
    "concelho": "Porto",
    "freguesia": "União das Freguesias de Cedofeita, Santo Ildefonso, Sé, Miragaia, São Nicolau e Vitória",
    "site": "www.reit.up.pt",
    "email": "reitoria@reit.up.pt",
    "designacao_contrato": "Serviços de Consultoria Associados a Patentes",
    "descricao": "Serviços de Consultoria Associados a Patentes",
    "preco_base": "93.000,00 EUR",
    "prazo_execucao": "12 MESES",
    "prazo_apresentacao_propostas": "28-01-2026 23:59",
    "fundos_eu": "Não",
    "plataforma_eletronica": "ACIN",
    "url_procedimento": "https://www.acingov.pt",
    "autor_nome": "Renata Alexandra da Silva Castelo",
    "autor_cargo": "Técnica Superior"
  },
  {
    "numero_procedimento": "N/A",
    "entidade": "EMEL - Empresa Municipal de Mobilidade e Estacionamento de Lisboa, EM, SA",
    "link": "https://diariodarepublica.pt/dr/detalhe/contrato-publico/33676-993605141",
    "detalhes_completos": "1 - IDENTIFICAÇÃO E CONTACTOS DA ENTIDADE ADJUDICANTE\nDesignação da entidade adjudicante: EMEL - Empresa Municipal de Mobilidade e Estacionamento de Lisboa, EM, SA\nNIPC: 503311332\nServiço/Órgão/Pessoa de contacto: Contratação Pública\nEndereço: Alameda das Linhas de Torres, nº 198/200\nCódigo postal: 1750-150\nLocalidade: Lisboa\nPaís: Portugal\nNUT III: PT170\nDistrito: Lisboa\nConcelho: Lisboa\nFreguesia: Freguesia de Lumiar\nTelefone: 211163060\nFax: 217813699\nEndereço da Entidade (URL): www.emel.pt\nEndereço Eletrónico: contratacaopublica@emel.pt\neDelivery Gateway (URL): https://www.acingov.pt\nFunção da Organização: Adquirente\nSubfunção da Organização: Organização cujo orçamento é utilizado para pagar o contrato; Organização que executa o pagamento; Organização que fornece informações adicionais sobre o processo de adjudicação; Organização que fornece mais informações sobre os prazos dos procedimentos de recurso; Organização que fornece acesso fora de linha aos documentos do concurso; Organização responsável pelo tratamento das propostas; Organização que recebe as propostas; Organização que trata os pedidos de participação; Organização que recebe pedidos de participação; Organização que fornece mais informações sobre os procedimentos de recurso; Organização que assina o contrato\nNorma jurídica da Entidade Adjudicante: Organismo de direito público\nÁrea de atividade da Autoridade Adjudicante: Serviços públicos das administrações públicas\n\n2 - JORNAL OFICIAL DA UNIÃO EUROPEIA\nO procedimento a que este anúncio diz respeito também é publicitado no Jornal Oficial da União Europeia? Não\n\n3 - AVISO\nModelo de Anúncio: Concurso público\nData de Envio do Anúncio: 31-12-2025\n\n5 - PROCESSO\nTipo de Procedimento: Concurso público\nPreço base do procedimento: Sim\nValor do preço base do procedimento: 219.750,00 EUR\nProcedimento com lotes? Não\n\n6 - OBJETO DO CONTRATO\nNúmero de referência interna: CP 49/25\nDesignação do contrato: CP 49/25 - Aquisição de serviços para manutenção e reparação de viaturas da frota EMEL\nDescrição: Aquisição de serviços para manutenção e reparação de viaturas da frota EMEL\nTipo de Contrato Principal: Aquisição de Serviços\nTipo de Contrato: Aquisição de Serviços\nClassificação CPV (Vocabulário Comum para os Contratos Públicos)\nObjeto principal\nVocabulário Principal: 50112000\nPreço base s/IVA: 219.750,00 EUR\n\n7 - INDICAÇÕES ADICIONAIS\nO contrato envolve aquisição conjunta (satisfação de várias entidades)? Não\nO contrato é adjudicado por uma central de compras? Não\n\n8 - TÉCNICAS\nO concurso destina-se à celebração de um acordo-quadro? Inexistência de acordo-quadro\nÉ utilizado um leilão eletrónico? Não\nÉ adotada uma fase de negociação? Não\nSistema de Aquisição Dinâmico: Inexistência de sistema de aquisição dinâmico\n\n9 - LOCAL DA EXECUÇÃO DO CONTRATO\nLOCAL DA EXECUÇÃO DO CONTRATO (PROCEDIMENTO)\nPaís: Portugal\nNUT III: PT170\nLocalidade: Todas\nDistrito: Lisboa\nConcelho: Lisboa\nFreguesia: Todas\n\n10 - PRAZO DE EXECUÇÃO DO CONTRATO\nPrazo de execução do contrato: 547 DIAS\nPrevisão de renovações: Não\n\n11 - FUNDOS EU\nTêm fundos EU? Não\n\n12 - DOCUMENTOS DE HABILITAÇÃO\nHabilitação para o exercício da atividade profissional: Não\n\n13 - CONDIÇÕES DE APRESENTAÇÃO\nPlataforma eletrónica utilizada pela entidade adjudicante: ACIN\nURL para Apresentação: https://www.acingov.pt\nAdmissibilidade da apresentação de propostas variantes: Não autorizado\nPrazo para apresentação das propostas: 18-01-2026 23:59\nPrazo durante o qual os concorrentes são obrigados a manter as respetivas propostas: 66 dias a contar do termo do prazo para a apresentação das propostas\nIndicação de Subcontratação na Proposta: A parte do contrato que o proponente tenciona subcontratar\n\n14 - PRESTAÇÃO DE CAUÇÃO\nPrestação de caução: Não\n\n15 - FORNECIMENTO DAS PEÇAS DO CONCURSO, APRESENTAÇÃO DE PEDIDOS DE PARTICIPAÇÃO E APRESENTAÇÃO DAS PROPOSTAS\nLink para acesso às peças do concurso (URL): https://www.acingov.pt/acingovprod/2/zonaPublica/zona_publica_c/donwloadProcedurePiece/MTAyMjkxOQ==\n\n20 - OUTROS REQUISITOS\nInformação sobre contratos reservados. Aplica-se a contratos reservados (54º-A)? Não\n\n21 - CRITÉRIO DE ADJUDICAÇÃO\nMultifator: Não\nMonofator:\nNome: Preço\n\n24 - CONDIÇÕES DO CONTRATO\nFaturação Eletrónica: Permitido\nObrigação de Subcontratação:\nCódigo da Obrigação de Subcontratação: O contratante tem de indicar qualquer mudança de subcontratantes durante a execução do contrato.\n\n25 - COMPRA PÚBLICA ESTRATÉGICA\nCompra Pública Estratégica: Inexistência de contratação pública estratégica\n\n26 - INFORMAÇÕES ADICIONAIS\nContrato adequado para PME: Sim\nCobertura ACP (Acordo dos Contratos Públicos da Organização Mundial do Comércio): Não\n\n27 - IDENTIFICAÇÃO E CONTACTOS DO ÓRGÃO DE RECURSOS ADMINISTRATIVOS\nDesignação: Conselho de Administração da EMEL\nEndereço: Alameda das Linhas de Torres n.º 198/200\nCódigo postal: 1750-150\nLocalidade: Lisboa\nTelefone: 217813600\nFax: 217813699\nEndereço eletrónico: contratacaopublica@emel.pt\n\n28 - IDENTIFICAÇÃO DO(S) AUTOR(ES) DE ANÚNCIO\nNome: Cláudia Afonso\nCargo: Coordenadora Contração Pública\n419944918",
    "nipc": "503311332",
    "distrito": "Lisboa",
    "concelho": "Lisboa",
    "freguesia": "Freguesia de Lumiar",
    "site": "www.emel.pt",
    "email": "contratacaopublica@emel.pt",
    "designacao_contrato": "CP 49/25 - Aquisição de serviços para manutenção e reparação de viaturas da frota EMEL",
    "descricao": "Aquisição de serviços para manutenção e reparação de viaturas da frota EMEL",
    "preco_base": "219.750,00 EUR",
    "prazo_execucao": "547 DIAS",
    "prazo_apresentacao_propostas": "18-01-2026 23:59",
    "fundos_eu": "Não",
    "plataforma_eletronica": "ACIN",
    "url_procedimento": "https://www.acingov.pt",
    "autor_nome": "Cláudia Afonso",
    "autor_cargo": "Coordenadora Contração Pública"
  },
  {
    "numero_procedimento": "N/A",
    "entidade": "Inova - Empresa de Desenvolvimento Económico e Social de Cantanhede, EM - SA",
    "link": "https://diariodarepublica.pt/dr/detalhe/contrato-publico/33677-993605142",
    "detalhes_completos": "1 - IDENTIFICAÇÃO E CONTACTOS DA ENTIDADE ADJUDICANTE\nDesignação da entidade adjudicante: Inova - Empresa de Desenvolvimento Económico e Social de Cantanhede, EM - SA\nNIPC: 506091481\nServiço/Órgão/Pessoa de contacto: Presidente\nEndereço: Zona Industrial de Cantanhede\nCódigo postal: 3060-197\nLocalidade: Cantanhede\nPaís: Portugal\nNUT III: PTZZZ\nDistrito: Todos\nConcelho: Todos\nFreguesia: Todas\nTelefone: 231410830\nFax: 231410839\nEndereço da Entidade (URL): www.inova-em.pt\nEndereço Eletrónico: geral@inova-em.pt\neDelivery Gateway (URL): https://www.acingov.pt\nFunção da Organização: Adquirente\nNorma jurídica da Entidade Adjudicante: Organismo de direito público\nÁrea de atividade da Autoridade Adjudicante: Serviços públicos das administrações públicas\n\n2 - JORNAL OFICIAL DA UNIÃO EUROPEIA\nO procedimento a que este anúncio diz respeito também é publicitado no Jornal Oficial da União Europeia? Não\n\n3 - AVISO\nModelo de Anúncio: Concurso público\nData de Envio do Anúncio: 31-12-2025\n\n5 - PROCESSO\nTipo de Procedimento: Concurso público\nPreço base do procedimento: Sim\nValor do preço base do procedimento: 122.000,00 EUR\nProcedimento com lotes? Não\n\n6 - OBJETO DO CONTRATO\nNúmero de referência interna: CP 95/2025\nDesignação do contrato: CONVERSÃO DE VIATURA, INCLUINDO FORNECIMENTO E INSTALAÇÃO DE CAIXA DE CARGA, GRUA E OUTROS EQUIPAMENTOS\nDescrição: CONVERSÃO DE VIATURA, INCLUINDO FORNECIMENTO E INSTALAÇÃO DE CAIXA DE CARGA, GRUA E OUTROS EQUIPAMENTOS\nTipo de Contrato Principal: Aquisição de Bens Móveis\nTipo de Contrato: Aquisição de Bens Móveis\nClassificação CPV (Vocabulário Comum para os Contratos Públicos)\nObjeto principal\nVocabulário Principal: 42414400\nPreço base s/IVA: 122.000,00 EUR\n\n7 - INDICAÇÕES ADICIONAIS\nO contrato envolve aquisição conjunta (satisfação de várias entidades)? Não\nO contrato é adjudicado por uma central de compras? Não\n\n8 - TÉCNICAS\nO concurso destina-se à celebração de um acordo-quadro? Inexistência de acordo-quadro\nÉ utilizado um leilão eletrónico? Não\nÉ adotada uma fase de negociação? Não\nSistema de Aquisição Dinâmico: Inexistência de sistema de aquisição dinâmico\n\n9 - LOCAL DA EXECUÇÃO DO CONTRATO\nLOCAL DA EXECUÇÃO DO CONTRATO (PROCEDIMENTO)\nPaís: Portugal\nNUT III: PT16E\nLocalidade: Município de Cantanhede\nDistrito: Coimbra\nConcelho: Cantanhede\nFreguesia: União das Freguesias de Cantanhede e Pocariça\n\n10 - PRAZO DE EXECUÇÃO DO CONTRATO\nPrazo de execução do contrato: 150 DIAS\nPrevisão de renovações: Não\n\n11 - FUNDOS EU\nTêm fundos EU? Não\n\n12 - DOCUMENTOS DE HABILITAÇÃO\nHabilitação para o exercício da atividade profissional: Não\n\n13 - CONDIÇÕES DE APRESENTAÇÃO\nPlataforma eletrónica utilizada pela entidade adjudicante: ACIN\nURL para Apresentação: https://www.acingov.pt\nAdmissibilidade da apresentação de propostas variantes: Não autorizado\nPrazo para apresentação das propostas: 30-01-2026 23:59\nPrazo durante o qual os concorrentes são obrigados a manter as respetivas propostas: 66 dias a contar do termo do prazo para a apresentação das propostas\nIndicação de Subcontratação na Proposta: Inexistência de indicação de subcontratação\n\n14 - PRESTAÇÃO DE CAUÇÃO\nPrestação de caução: Não\n\n15 - FORNECIMENTO DAS PEÇAS DO CONCURSO, APRESENTAÇÃO DE PEDIDOS DE PARTICIPAÇÃO E APRESENTAÇÃO DAS PROPOSTAS\nLink para acesso às peças do concurso (URL): https://www.acingov.pt/acingovprod/2/zonaPublica/zona_publica_c/donwloadProcedurePiece/MTAxMzAyMg==\n\n20 - OUTROS REQUISITOS\nInformação sobre contratos reservados. Aplica-se a contratos reservados (54º-A)? Não\n\n21 - CRITÉRIO DE ADJUDICAÇÃO\nMultifator: Sim\nFator: \nNome: Outros\nOutro Nome: Multifator\nPonderação: 100%\nSubfatores: Não\n\n24 - CONDIÇÕES DO CONTRATO\nFaturação Eletrónica: Permitido\nObrigação de Subcontratação:\nCódigo da Obrigação de Subcontratação: Não é aplicável nenhuma obrigação de subcontratação.\n\n25 - COMPRA PÚBLICA ESTRATÉGICA\nCompra Pública Estratégica: Inexistência de contratação pública estratégica\n\n26 - INFORMAÇÕES ADICIONAIS\nContrato adequado para PME: Sim\nCobertura ACP (Acordo dos Contratos Públicos da Organização Mundial do Comércio): Não\n\n27 - IDENTIFICAÇÃO E CONTACTOS DO ÓRGÃO DE RECURSOS ADMINISTRATIVOS\nDesignação: Presidente do Conselho de Administração\nEndereço: Zona Industrial de Cantanhede\nCódigo postal: 3060-197\nLocalidade: Cantanhede\nTelefone: 231410830\nFax: \nEndereço eletrónico: geral@inova-em.pt\n\n28 - IDENTIFICAÇÃO DO(S) AUTOR(ES) DE ANÚNCIO\nNome: Pedro António Vaz Cardoso\nCargo: Presidente do Conselho de Administração\n419944926",
    "nipc": "506091481",
    "distrito": "Todos",
    "concelho": "Todos",
    "freguesia": "Todas",
    "site": "www.inova-em.pt",
    "email": "geral@inova-em.pt",
    "designacao_contrato": "CONVERSÃO DE VIATURA, INCLUINDO FORNECIMENTO E INSTALAÇÃO DE CAIXA DE CARGA, GRUA E OUTROS EQUIPAMENTOS",
    "descricao": "CONVERSÃO DE VIATURA, INCLUINDO FORNECIMENTO E INSTALAÇÃO DE CAIXA DE CARGA, GRUA E OUTROS EQUIPAMENTOS",
    "preco_base": "122.000,00 EUR",
    "prazo_execucao": "150 DIAS",
    "prazo_apresentacao_propostas": "30-01-2026 23:59",
    "fundos_eu": "Não",
    "plataforma_eletronica": "ACIN",
    "url_procedimento": "https://www.acingov.pt",
    "autor_nome": "Pedro António Vaz Cardoso",
    "autor_cargo": "Presidente do Conselho de Administração"
  },
  {
    "numero_procedimento": "N/A",
    "entidade": "Instituto Nacional de Medicina Legal e Ciências Forenses, IP",
    "link": "https://diariodarepublica.pt/dr/detalhe/contrato-publico/33665-993605845",
    "detalhes_completos": "1 - IDENTIFICAÇÃO E CONTACTOS DA ENTIDADE ADJUDICANTE\nDesignação da entidade adjudicante: Instituto Nacional de Medicina Legal e Ciências Forenses, IP\nNIPC: 508203970\nEndereço: Azinhaga de Santa Comba- Pólo das Ciências da Saúde\nCódigo postal: 3000-548\nLocalidade: Coimbra\nPaís: Portugal\nNUT III: PT16E\nDistrito: Coimbra\nConcelho: Coimbra\nFreguesia: Freguesia de Santo António dos Olivais\nTelefone: 239854220\nFax: 239836470\nEndereço da Entidade (URL): www.inml.mj.pt\nEndereço Eletrónico: aprovisionamento.norte@inmlcf.mj.pt\neDelivery Gateway (URL): https://community.vortal.biz/public/\nFunção da Organização: Adquirente\nNorma jurídica da Entidade Adjudicante: Organismo de direito público\nÁrea de atividade da Autoridade Adjudicante: Segurança e ordem pública\n\n2 - JORNAL OFICIAL DA UNIÃO EUROPEIA\nO procedimento a que este anúncio diz respeito também é publicitado no Jornal Oficial da União Europeia? Sim\n\n3 - AVISO\nModelo de Anúncio: Concurso público\nData de Envio do Anúncio: 29-12-2025\n\n5 - PROCESSO\nTipo de Procedimento: Concurso público\nPreço base do procedimento: Sim\nValor do preço base do procedimento: 1.835.155,89 EUR\nProcedimento com lotes? Não\n\n6 - OBJETO DO CONTRATO\nNúmero de referência interna: PI/227/2025_NPD_5262009775 Cópia\nDesignação do contrato: Aquisição de 3 (três) sistemas LC-MS/MS, com espectrometria de massa do tipo QToF e mobilidade iónica (IMS).\nDescrição: Aquisição de 3 (três) sistemas LC-MS/MS, com espectrometria de massa do tipo QToF e mobilidade iónica (IMS), no âmbito do Fundo para a Segurança Interna (FSI).\nOpções: Não\nTipo de Contrato Principal: Aquisição de Bens Móveis\nTipo de Contrato: Aquisição de Bens Móveis\nClassificação CPV (Vocabulário Comum para os Contratos Públicos)\nObjeto principal\nVocabulário Principal: 38433100\nPreço base s/IVA: 1.835.155,89 EUR\n\n7 - INDICAÇÕES ADICIONAIS\nO contrato envolve aquisição conjunta (satisfação de várias entidades)? Não\nO contrato é adjudicado por uma central de compras? Não\n\n8 - TÉCNICAS\nO concurso destina-se à celebração de um acordo-quadro? Inexistência de acordo-quadro\nÉ utilizado um leilão eletrónico? Não\nÉ adotada uma fase de negociação? Não\nSistema de Aquisição Dinâmico: Inexistência de sistema de aquisição dinâmico\n\n9 - LOCAL DA EXECUÇÃO DO CONTRATO\nLOCAL DA EXECUÇÃO DO CONTRATO (PROCEDIMENTO)\nPaís: Portugal\nNUT III: PT16E\nLocalidade: Coimbra\nDistrito: Coimbra\nConcelho: Coimbra\nFreguesia: Freguesia de Santo António dos Olivais\n\n10 - PRAZO DE EXECUÇÃO DO CONTRATO\nPrazo de execução do contrato: 60 DIAS\nPrevisão de renovações: Não\n\n11 - FUNDOS EU\nTêm fundos EU? Sim\n\n12 - DOCUMENTOS DE HABILITAÇÃO\nHabilitação para o exercício da atividade profissional: Não\n\n13 - CONDIÇÕES DE APRESENTAÇÃO\nPlataforma eletrónica utilizada pela entidade adjudicante: VORTAL\nURL para Apresentação: https://community.vortal.biz/public/\nAdmissibilidade da apresentação de propostas variantes: Não autorizado\nPrazo para apresentação das propostas: 30-01-2026 23:59\nPrazo durante o qual os concorrentes são obrigados a manter as respetivas propostas: 66 dias a contar do termo do prazo para a apresentação das propostas\nApresentação de Catálogo Eletrónico: Permitido\nIndicação de Subcontratação na Proposta: Inexistência de indicação de subcontratação\n\n14 - PRESTAÇÃO DE CAUÇÃO\nPrestação de caução: Sim\nPercentagem: 1%\nDescrição da Garantia Exigida: Conforme peças de procedimento\n\n15 - FORNECIMENTO DAS PEÇAS DO CONCURSO, APRESENTAÇÃO DE PEDIDOS DE PARTICIPAÇÃO E APRESENTAÇÃO DAS PROPOSTAS\nLink para acesso às peças do concurso (URL): https://community.vortal.biz/Public/public-tender-documents/bHRkVzhzNXVmQ3JPdDIxMzVYdkVqcWE1a25yMFpwNzVjcjBOK0ppZVlNeVMxeWdKQnB0UkNicExSZkVLRHgyY3FTeTZ3WWQ1L0hXdnp3TnlmN0R5N2c9PSglMTBW\n\n20 - OUTROS REQUISITOS\nInformação sobre contratos reservados. Aplica-se a contratos reservados (54º-A)? Não\n\n21 - CRITÉRIO DE ADJUDICAÇÃO\nMultifator: Sim\nFator: \nNome: Qualidade\nPonderação: 60%\nSubfatores: Não\nFator: \nNome: Qualidade\nPonderação: 25%\nSubfatores: Não\nFator: \nNome: Preço\nPonderação: 15%\nSubfatores: Não\n\n24 - CONDIÇÕES DO CONTRATO\nFaturação Eletrónica: Permitido\nObrigação de Subcontratação:\nCódigo da Obrigação de Subcontratação: Não é aplicável nenhuma obrigação de subcontratação.\n\n25 - COMPRA PÚBLICA ESTRATÉGICA\nCompra Pública Estratégica: Inexistência de contratação pública estratégica\n\n26 - INFORMAÇÕES ADICIONAIS\nContrato adequado para PME: Sim\nCobertura ACP (Acordo dos Contratos Públicos da Organização Mundial do Comércio): Não\n\n27 - IDENTIFICAÇÃO E CONTACTOS DO ÓRGÃO DE RECURSOS ADMINISTRATIVOS\nDesignação: Conselho Diretivo\nEndereço: Azinhaga de Santa Comba - Pólo das Ciências da Saúde (Pólo III)\nCódigo postal: 3000-548\nLocalidade: Coimbra\nTelefone: +351 239854220\nFax: +351 239854220\nEndereço eletrónico: aprovisionamento.sede@inmlcf.mj.pt\n\n28 - IDENTIFICAÇÃO DO(S) AUTOR(ES) DE ANÚNCIO\nNome: Nuno Ferreira de Almeida\nCargo: Diretor do Departamento de Administração Geral\n419935708",
    "nipc": "508203970",
    "distrito": "Coimbra",
    "concelho": "Coimbra",
    "freguesia": "Freguesia de Santo António dos Olivais",
    "site": "www.inml.mj.pt",
    "email": "aprovisionamento.norte@inmlcf.mj.pt",
    "designacao_contrato": "Aquisição de 3 (três) sistemas LC-MS/MS, com espectrometria de massa do tipo QToF e mobilidade iónica (IMS).",
    "descricao": "Aquisição de 3 (três) sistemas LC-MS/MS, com espectrometria de massa do tipo QToF e mobilidade iónica (IMS), no âmbito do Fundo para a Segurança Interna (FSI).",
    "preco_base": "1.835.155,89 EUR",
    "prazo_execucao": "60 DIAS",
    "prazo_apresentacao_propostas": "30-01-2026 23:59",
    "fundos_eu": "Sim",
    "plataforma_eletronica": "VORTAL",
    "url_procedimento": "https://community.vortal.biz/public/",
    "autor_nome": "Nuno Ferreira de Almeida",
    "autor_cargo": "Diretor do Departamento de Administração Geral"
  },
  {
    "numero_procedimento": "N/A",
    "entidade": "Unidade Local de Saúde do Alentejo Central, EPE",
    "link": "https://diariodarepublica.pt/dr/detalhe/contrato-publico/33666-993605849",
    "detalhes_completos": "1 - IDENTIFICAÇÃO E CONTACTOS DA ENTIDADE ADJUDICANTE\nDesignação da entidade adjudicante: Unidade Local de Saúde do Alentejo Central, EPE\nNIPC: 508085888\nEndereço: Largo Sr. da Pobreza\nCódigo postal: 7000-811\nLocalidade: Évora\nPaís: Portugal\nNUT III: PT187\nDistrito: Évora\nConcelho: Évora\nFreguesia: Todas\nTelefone: 266740111\nFax: 266744212\nEndereço da Entidade (URL): www.hevora.min-saude.pt\nEndereço Eletrónico: concursos.aprov@ulsac.min-saude.pt\neDelivery Gateway (URL): https://community.vortal.biz/public/\nFunção da Organização: Adquirente\nNorma jurídica da Entidade Adjudicante: Organismo de direito público\nÁrea de atividade da Autoridade Adjudicante: Saúde\n\n2 - JORNAL OFICIAL DA UNIÃO EUROPEIA\nO procedimento a que este anúncio diz respeito também é publicitado no Jornal Oficial da União Europeia? Sim\n\n3 - AVISO\nModelo de Anúncio: Concurso público\nData de Envio do Anúncio: 29-12-2025\n\n5 - PROCESSO\nTipo de Procedimento: Concurso público\nPreço base do procedimento: Sim\nValor do preço base do procedimento: 561.600,00 EUR\nProcedimento com lotes? Não\n\n6 - OBJETO DO CONTRATO\nNúmero de referência interna: 190069/26\nDesignação do contrato: Prestação de Serviços Médicos de Anestesiologia\nDescrição: 190069/26 -  Prestação de Serviços Médicos de Anestesiologia\nOpções: Não\nTipo de Contrato Principal: Aquisição de Serviços\nTipo de Contrato: Aquisição de Serviços\nClassificação CPV (Vocabulário Comum para os Contratos Públicos)\nObjeto principal\nVocabulário Principal: 85121200\nPreço base s/IVA: 561.600,00 EUR\n\n7 - INDICAÇÕES ADICIONAIS\nO contrato envolve aquisição conjunta (satisfação de várias entidades)? Não\nO contrato é adjudicado por uma central de compras? Não\n\n8 - TÉCNICAS\nO concurso destina-se à celebração de um acordo-quadro? Inexistência de acordo-quadro\nÉ utilizado um leilão eletrónico? Não\nÉ adotada uma fase de negociação? Não\nSistema de Aquisição Dinâmico: Inexistência de sistema de aquisição dinâmico\n\n9 - LOCAL DA EXECUÇÃO DO CONTRATO\nLOCAL DA EXECUÇÃO DO CONTRATO (PROCEDIMENTO)\nPaís: Portugal\nNUT III: PT187\nLocalidade: Évora\nDistrito: Évora\nConcelho: Évora\nFreguesia: União das Freguesias de Évora (São Mamede, Sé, São Pedro e Santo Antão)\n\n10 - PRAZO DE EXECUÇÃO DO CONTRATO\nPrazo de execução do contrato: 365 DIAS\nPrevisão de renovações: Não\n\n11 - FUNDOS EU\nTêm fundos EU? Não\n\n12 - DOCUMENTOS DE HABILITAÇÃO\nHabilitação para o exercício da atividade profissional: Não\n\n13 - CONDIÇÕES DE APRESENTAÇÃO\nPlataforma eletrónica utilizada pela entidade adjudicante: VORTAL\nURL para Apresentação: https://community.vortal.biz/public/\nAdmissibilidade da apresentação de propostas variantes: Não autorizado\nPrazo para apresentação das propostas: 28-01-2026 18:00\nPrazo durante o qual os concorrentes são obrigados a manter as respetivas propostas: 120 dias a contar do termo do prazo para a apresentação das propostas\nApresentação de Catálogo Eletrónico: Não autorizado\nIndicação de Subcontratação na Proposta: Inexistência de indicação de subcontratação\n\n14 - PRESTAÇÃO DE CAUÇÃO\nPrestação de caução: Sim\nPercentagem: 5%\nDescrição da Garantia Exigida: Conforme Peças do Procedimento\n\n15 - FORNECIMENTO DAS PEÇAS DO CONCURSO, APRESENTAÇÃO DE PEDIDOS DE PARTICIPAÇÃO E APRESENTAÇÃO DAS PROPOSTAS\nLink para acesso às peças do concurso (URL): https://community.vortal.biz/Public/public-tender-documents/TGplWmYrRnArVE5SWUlER2RROUNKMHlmeDBFa1FFUmlyU3krRk9ZaUE0RCtaM1RSY1pZZUNKRGNIQzlNMWNhUlcrZCtReHp5NFpMckVBU3A0WFk3TXc9PUBRISM2\n\n20 - OUTROS REQUISITOS\nInformação sobre contratos reservados. Aplica-se a contratos reservados (54º-A)? Não\n\n21 - CRITÉRIO DE ADJUDICAÇÃO\nMultifator: Sim\nFator: \nNome: Preço\nPonderação: 80%\nSubfatores: Não\nFator: \nNome: Qualidade\nPonderação: 20%\nSubfatores: Não\n\n24 - CONDIÇÕES DO CONTRATO\nFaturação Eletrónica: Permitido\nObrigação de Subcontratação:\nCódigo da Obrigação de Subcontratação: Não é aplicável nenhuma obrigação de subcontratação.\n\n25 - COMPRA PÚBLICA ESTRATÉGICA\nCompra Pública Estratégica: Inexistência de contratação pública estratégica\n\n26 - INFORMAÇÕES ADICIONAIS\nContrato adequado para PME: Sim\nCobertura ACP (Acordo dos Contratos Públicos da Organização Mundial do Comércio): Não\n\n27 - IDENTIFICAÇÃO E CONTACTOS DO ÓRGÃO DE RECURSOS ADMINISTRATIVOS\nDesignação: Conselho de administração\nEndereço: Largo Sr. de Pobreza\nCódigo postal: 7000-811\nLocalidade: Évora\nTelefone: +351 266740100\nFax: +351 266740100\nEndereço eletrónico: concursos.aprov@ulsac.min-saude.pt\n\n28 - IDENTIFICAÇÃO DO(S) AUTOR(ES) DE ANÚNCIO\nNome: Carlos Antonio Mateus Gomes\nCargo: Presidente do Conselho de Administração\n419933318",
    "nipc": "508085888",
    "distrito": "Évora",
    "concelho": "Évora",
    "freguesia": "Todas",
    "site": "www.hevora.min-saude.pt",
    "email": "concursos.aprov@ulsac.min-saude.pt",
    "designacao_contrato": "Prestação de Serviços Médicos de Anestesiologia",
    "descricao": "190069/26 - Prestação de Serviços Médicos de Anestesiologia",
    "preco_base": "561.600,00 EUR",
    "prazo_execucao": "365 DIAS",
    "prazo_apresentacao_propostas": "28-01-2026 18:00",
    "fundos_eu": "Não",
    "plataforma_eletronica": "VORTAL",
    "url_procedimento": "https://community.vortal.biz/public/",
    "autor_nome": "Carlos Antonio Mateus Gomes",
    "autor_cargo": "Presidente do Conselho de Administração"
  },
  {
    "numero_procedimento": "N/A",
    "entidade": "Tratolixo - Tratamento de Residuos Sólidos, EIM - Empresa Intermunicipal, SA",
    "link": "https://diariodarepublica.pt/dr/detalhe/contrato-publico/33669-993605850",
    "detalhes_completos": "1 - IDENTIFICAÇÃO E CONTACTOS DA ENTIDADE ADJUDICANTE\nDesignação da entidade adjudicante: Tratolixo - Tratamento de Residuos Sólidos, EIM - Empresa Intermunicipal, SA\nNIPC: 502444010\nEndereço: Estrada 5 de Junho nº 1 - Trajouce\nCódigo postal: 2785-155\nLocalidade: Lisboa\nPaís: Portugal\nNUT III: PT170\nDistrito: Lisboa\nConcelho: Cascais\nFreguesia: Freguesia de São Domingos de Rana\nTelefone: 214459500\nFax: 214444030\nEndereço da Entidade (URL): www.tratolixo.pt\nEndereço Eletrónico: contratacaopublica@tratolixo.pt\neDelivery Gateway (URL): https://community.vortal.biz/public/\nFunção da Organização: Adquirente\nNorma jurídica da Entidade Adjudicante: Empresa pública\nÁrea de atividade da Autoridade Adjudicante: Serviços públicos das administrações públicas\n\n2 - JORNAL OFICIAL DA UNIÃO EUROPEIA\nO procedimento a que este anúncio diz respeito também é publicitado no Jornal Oficial da União Europeia? Sim\n\n3 - AVISO\nModelo de Anúncio: Concurso público\nData de Envio do Anúncio: 29-12-2025\n\n5 - PROCESSO\nTipo de Procedimento: Concurso público\nPreço base do procedimento: Sim\nValor do preço base do procedimento: 126.900,00 EUR\nProcedimento com lotes? Não\n\n6 - OBJETO DO CONTRATO\nNúmero de referência interna: 25.DEX.136\nDesignação do contrato: 25.DEX.136 - Fornecimento e soldadura de Geomembrana PEAD para impermeabilização da célula 1 do Aterro do Ecoparque da Abrunheira Concurso Público Internacional Caderno de Encargos Ref.ª\nDescrição: 25.DEX.136 - Fornecimento e soldadura de Geomembrana PEAD para impermeabilização da célula 1 do Aterro do Ecoparque da Abrunheira Concurso Público Internacional Caderno de Encargos Ref.ª\nOpções: Não\nTipo de Contrato Principal: Aquisição de Bens Móveis\nTipo de Contrato: Aquisição de Bens Móveis\nClassificação CPV (Vocabulário Comum para os Contratos Públicos)\nObjeto principal\nVocabulário Principal: 19260000\nPreço base s/IVA: 126.900,00 EUR\n\n7 - INDICAÇÕES ADICIONAIS\nO contrato envolve aquisição conjunta (satisfação de várias entidades)? Não\nO contrato é adjudicado por uma central de compras? Não\n\n8 - TÉCNICAS\nO concurso destina-se à celebração de um acordo-quadro? Inexistência de acordo-quadro\nÉ utilizado um leilão eletrónico? Não\nÉ adotada uma fase de negociação? Não\nSistema de Aquisição Dinâmico: Inexistência de sistema de aquisição dinâmico\n\n9 - LOCAL DA EXECUÇÃO DO CONTRATO\nLOCAL DA EXECUÇÃO DO CONTRATO (PROCEDIMENTO)\nPaís: Portugal\nNUT III: PT170\nLocalidade: Lisboa\nDistrito: Lisboa\nConcelho: Mafra\nFreguesia: União das Freguesias de Malveira e São Miguel de Alcainça\n\n10 - PRAZO DE EXECUÇÃO DO CONTRATO\nPrazo de execução do contrato: 6 MESES\nPrevisão de renovações: Não\n\n11 - FUNDOS EU\nTêm fundos EU? Não\n\n12 - DOCUMENTOS DE HABILITAÇÃO\nHabilitação para o exercício da atividade profissional: Não\n\n13 - CONDIÇÕES DE APRESENTAÇÃO\nPlataforma eletrónica utilizada pela entidade adjudicante: VORTAL\nURL para Apresentação: https://community.vortal.biz/public/\nAdmissibilidade da apresentação de propostas variantes: Não autorizado\nPrazo para apresentação das propostas: 13-01-2026 17:00\nPrazo durante o qual os concorrentes são obrigados a manter as respetivas propostas: 66 dias a contar do termo do prazo para a apresentação das propostas\nApresentação de Catálogo Eletrónico: Não autorizado\nIndicação de Subcontratação na Proposta: Inexistência de indicação de subcontratação\n\n14 - PRESTAÇÃO DE CAUÇÃO\nPrestação de caução: Não\n\n15 - FORNECIMENTO DAS PEÇAS DO CONCURSO, APRESENTAÇÃO DE PEDIDOS DE PARTICIPAÇÃO E APRESENTAÇÃO DAS PROPOSTAS\nLink para acesso às peças do concurso (URL): https://community.vortal.biz/Public/public-tender-documents/djFtazIzSDk0bkdjVEduVjhLUHZYRHFWcVk0dis2VkRoNHBFSG9LcHRTOGQ2QXVyanFJcnp1UjIwZzRxZTdDNklVN3l5Y1p2eHFkNVpUQm9JZGM1TkE9PUJfXjJr\n\n20 - OUTROS REQUISITOS\nInformação sobre contratos reservados. Aplica-se a contratos reservados (54º-A)? Não\n\n21 - CRITÉRIO DE ADJUDICAÇÃO\nMultifator: Não\nMonofator:\nNome: Preço\n\n24 - CONDIÇÕES DO CONTRATO\nFaturação Eletrónica: Permitido\nObrigação de Subcontratação:\nCódigo da Obrigação de Subcontratação: Não é aplicável nenhuma obrigação de subcontratação.\n\n25 - COMPRA PÚBLICA ESTRATÉGICA\nCompra Pública Estratégica: Inexistência de contratação pública estratégica\n\n26 - INFORMAÇÕES ADICIONAIS\nContrato adequado para PME: Sim\nCobertura ACP (Acordo dos Contratos Públicos da Organização Mundial do Comércio): Não\n\n27 - IDENTIFICAÇÃO E CONTACTOS DO ÓRGÃO DE RECURSOS ADMINISTRATIVOS\nDesignação: Conselho de Administração da Tratolixo - Tratamento de Resíduos Sólidos, E.I.M., S.A.\nEndereço: Estrada 5 de junho, n.º 1\nCódigo postal: 2785-155\nLocalidade: Cascais\nTelefone: +351 214459500\nFax: +351 214444030\nEndereço eletrónico: contratacaopublica@tratolixo.pt\n\n28 - IDENTIFICAÇÃO DO(S) AUTOR(ES) DE ANÚNCIO\nNome: Pedro Almeida\nCargo: Técnico Superior do Departamento de Aprovisionamento e Contratação Pública\n419934988",
    "nipc": "502444010",
    "distrito": "Lisboa",
    "concelho": "Cascais",
    "freguesia": "Freguesia de São Domingos de Rana",
    "site": "www.tratolixo.pt",
    "email": "contratacaopublica@tratolixo.pt",
    "designacao_contrato": "25.DEX.136 - Fornecimento e soldadura de Geomembrana PEAD para impermeabilização da célula 1 do Aterro do Ecoparque da Abrunheira Concurso Público Internacional Caderno de Encargos Ref.ª",
    "descricao": "25.DEX.136 - Fornecimento e soldadura de Geomembrana PEAD para impermeabilização da célula 1 do Aterro do Ecoparque da Abrunheira Concurso Público Internacional Caderno de Encargos Ref.ª",
    "preco_base": "126.900,00 EUR",
    "prazo_execucao": "6 MESES",
    "prazo_apresentacao_propostas": "13-01-2026 17:00",
    "fundos_eu": "Não",
    "plataforma_eletronica": "VORTAL",
    "url_procedimento": "https://community.vortal.biz/public/",
    "autor_nome": "Pedro Almeida",
    "autor_cargo": "Técnico Superior do Departamento de Aprovisionamento e Contratação Pública"
  },
  {
    "numero_procedimento": "N/A",
    "entidade": "Unidade Local de Saúde da Região de Leiria, EPE",
    "link": "https://diariodarepublica.pt/dr/detalhe/contrato-publico/33671-993605851",
    "detalhes_completos": "1 - IDENTIFICAÇÃO E CONTACTOS DA ENTIDADE ADJUDICANTE\nDesignação da entidade adjudicante: Unidade Local de Saúde da Região de Leiria, EPE\nNIPC: 509822932\nEndereço: Rua das Olhalvas, Pousos\nCódigo postal: 2410-197\nLocalidade: Leiria\nPaís: Portugal\nNUT III: PT16F\nDistrito: Leiria\nConcelho: Leiria\nFreguesia: União das Freguesias de Leiria, Pousos, Barreira e Cortes\nTelefone: 244817010\nEndereço da Entidade (URL): https://www.ulsrl.min-saude.pt\nEndereço Eletrónico: aprovisionamento.geral@ulsrl.min-saude.pt\neDelivery Gateway (URL): https://community.vortal.biz/public/\nFunção da Organização: Adquirente\nNorma jurídica da Entidade Adjudicante: Empresa pública, controlada por uma autoridade da administração central\nÁrea de atividade da Autoridade Adjudicante: Saúde\n\n2 - JORNAL OFICIAL DA UNIÃO EUROPEIA\nO procedimento a que este anúncio diz respeito também é publicitado no Jornal Oficial da União Europeia? Sim\n\n3 - AVISO\nModelo de Anúncio: Concurso público\nData de Envio do Anúncio: 29-12-2025\n\n5 - PROCESSO\nTipo de Procedimento: Concurso público\nPreço base do procedimento: Sim\nValor do preço base do procedimento: 572.978,00 EUR\nProcedimento com lotes? Sim\nNº Máx. de Lotes Autorizado: 5\nNúmero máximo de lotes que podem ser adjudicados a um concorrente: 5\n\n6 - OBJETO DO CONTRATO\nNúmero de referência interna: CP A2/23/2026 - Dispos. de Prep. da Placa Cálcica \nDesignação do contrato: CP A2/23/2026 - Dispositivos de Preparação da Placa Cálcica Coronária\nDescrição: CP A2/23/2026 - Dispositivos de Preparação da Placa Cálcica Coronária\nOpções: Não\nTipo de Contrato Principal: Aquisição de Bens Móveis\nTipo de Contrato: Aquisição de Bens Móveis\nClassificação CPV (Vocabulário Comum para os Contratos Públicos)\nObjeto principal\nVocabulário Principal: 33140000\nPreço base s/IVA: 572.978,00 EUR\nLotes: \nNº: LOT-0001\nDescrição do Lote: Lote 1\nPreço base s/IVA: 84.978,00 EUR\nClassificação CPV (Vocabulário Comum para os Contratos Públicos)\nObjeto principal\nVocabulário Principal: 33140000\nNº: LOT-0002\nDescrição do Lote: Lote 2\nPreço base s/IVA: 151.500,00 EUR\nClassificação CPV (Vocabulário Comum para os Contratos Públicos)\nObjeto principal\nVocabulário Principal: 33140000\nNº: LOT-0003\nDescrição do Lote: Lote 3\nPreço base s/IVA: 228.000,00 EUR\nClassificação CPV (Vocabulário Comum para os Contratos Públicos)\nObjeto principal\nVocabulário Principal: 33140000\nNº: LOT-0004\nDescrição do Lote: Lote 4\nPreço base s/IVA: 70.000,00 EUR\nClassificação CPV (Vocabulário Comum para os Contratos Públicos)\nObjeto principal\nVocabulário Principal: 33140000\nNº: LOT-0005\nDescrição do Lote: Lote 5\nPreço base s/IVA: 38.500,00 EUR\nClassificação CPV (Vocabulário Comum para os Contratos Públicos)\nObjeto principal\nVocabulário Principal: 33140000\n\n7 - INDICAÇÕES ADICIONAIS\nO contrato envolve aquisição conjunta (satisfação de várias entidades)? Não\nO contrato é adjudicado por uma central de compras? Não\n\n8 - TÉCNICAS\nO concurso destina-se à celebração de um acordo-quadro? Inexistência de acordo-quadro\nÉ utilizado um leilão eletrónico? Não\nÉ adotada uma fase de negociação? Não\nSistema de Aquisição Dinâmico: Inexistência de sistema de aquisição dinâmico\n\n9 - LOCAL DA EXECUÇÃO DO CONTRATO\nLOCAL DA EXECUÇÃO DO CONTRATO (PROCEDIMENTO)\nPaís: Portugal\nNUT III: PT16F\nLocalidade: Leiria\nDistrito: Leiria\nConcelho: Leiria\nFreguesia: Todas\nLOCAL DA EXECUÇÃO DO CONTRATO (LOTE)\nIdentificador do Lote: LOT-0001; LOT-0002; LOT-0003; LOT-0004; LOT-0005\nPaís: Portugal\nNUT III: PT16F\nLocalidade: Leiria\nDistrito: Leiria\nConcelho: Leiria\nFreguesia: Todas\n\n10 - PRAZO DE EXECUÇÃO DO CONTRATO\nIdentificador do Lote: LOT-0001; LOT-0002; LOT-0003; LOT-0004; LOT-0005\nPrazo de execução do contrato: 24 MESES\nPrevisão de renovações: Não\n\n11 - FUNDOS EU\nIdentificador do Lote: LOT-0001; LOT-0002; LOT-0003; LOT-0004; LOT-0005\nTêm fundos EU? Não\n\n12 - DOCUMENTOS DE HABILITAÇÃO\nHabilitação para o exercício da atividade profissional: Não\n\n13 - CONDIÇÕES DE APRESENTAÇÃO\nPlataforma eletrónica utilizada pela entidade adjudicante: VORTAL\nURL para Apresentação: https://community.vortal.biz/public/\nAdmissibilidade da apresentação de propostas variantes: Não autorizado\nPrazo para apresentação das propostas: 30-01-2026 18:00\nPrazo durante o qual os concorrentes são obrigados a manter as respetivas propostas: 90 dias a contar do termo do prazo para a apresentação das propostas\nApresentação de Catálogo Eletrónico: Permitido\nIndicação de Subcontratação na Proposta: Inexistência de indicação de subcontratação\n\n14 - PRESTAÇÃO DE CAUÇÃO\nPrestação de caução: Não\n\n15 - FORNECIMENTO DAS PEÇAS DO CONCURSO, APRESENTAÇÃO DE PEDIDOS DE PARTICIPAÇÃO E APRESENTAÇÃO DAS PROPOSTAS\nLink para acesso às peças do concurso (URL): https://community.vortal.biz/Public/public-tender-documents/QmZlWmNqdXRwblNDL3EyVkFvUnA3QlVBdVNnV054d2RvV3ZFa3pQd05sQWNDaGFYd1ltcHZhMm1tRElqTVpyditpK0pDb292azhpZldwcFVnZncyTVE9PV5iXlps\n\n20 - OUTROS REQUISITOS\nIdentificador do Lote: LOT-0001; LOT-0002; LOT-0003; LOT-0004; LOT-0005\nInformação sobre contratos reservados. Aplica-se a contratos reservados (54º-A)? Não\n\n21 - CRITÉRIO DE ADJUDICAÇÃO\nO Critério de adjudicação é diferenciado por lote? Não\nMultifator: Sim\nFator: \nNome: Preço\nPonderação: 40%\nSubfatores: Não\nFator: \nNome: Qualidade\nPonderação: 60%\nSubfatores: Não\n\n24 - CONDIÇÕES DO CONTRATO\nIdentificador do Lote: LOT-0001; LOT-0002; LOT-0003; LOT-0004; LOT-0005\nFaturação Eletrónica: Permitido\nObrigação de Subcontratação:\nCódigo da Obrigação de Subcontratação: Não é aplicável nenhuma obrigação de subcontratação.\n\n25 - COMPRA PÚBLICA ESTRATÉGICA\nCompra Pública Estratégica: Inexistência de contratação pública estratégica\n\n26 - INFORMAÇÕES ADICIONAIS\nIdentificador do Lote: LOT-0001; LOT-0002; LOT-0003; LOT-0004; LOT-0005\nContrato adequado para PME: Sim\nCobertura ACP (Acordo dos Contratos Públicos da Organização Mundial do Comércio): Não\n\n27 - IDENTIFICAÇÃO E CONTACTOS DO ÓRGÃO DE RECURSOS ADMINISTRATIVOS\nDesignação: Unidade Local de Saúde da Região de Leiria\nEndereço: Rua das Olhalvas\nCódigo postal: 2425-197\nLocalidade: Leiria\nTelefone: +351 244817010\nFax: +351 244817000\nEndereço eletrónico: secca@ulsrl.min-saude.pt\n\n28 - IDENTIFICAÇÃO DO(S) AUTOR(ES) DE ANÚNCIO\nNome: Manuel José Santos de Carvalho\nCargo: Presidente do Conselho de Administração\n419934841",
    "nipc": "509822932",
    "distrito": "Leiria",
    "concelho": "Leiria",
    "freguesia": "União das Freguesias de Leiria, Pousos, Barreira e Cortes",
    "site": "https://www.ulsrl.min-saude.pt",
    "email": "aprovisionamento.geral@ulsrl.min-saude.pt",
    "designacao_contrato": "CP A2/23/2026 - Dispositivos de Preparação da Placa Cálcica Coronária",
    "descricao": "CP A2/23/2026 - Dispositivos de Preparação da Placa Cálcica Coronária",
    "preco_base": "572.978,00 EUR",
    "prazo_execucao": "24 MESES",
    "prazo_apresentacao_propostas": "30-01-2026 18:00",
    "fundos_eu": "Não",
    "plataforma_eletronica": "VORTAL",
    "url_procedimento": "https://community.vortal.biz/public/",
    "autor_nome": "Manuel José Santos de Carvalho",
    "autor_cargo": "Presidente do Conselho de Administração"
  },
  {
    "numero_procedimento": "N/A",
    "entidade": "Universidade do Porto",
    "link": "https://diariodarepublica.pt/dr/detalhe/contrato-publico/33672-993605852",
    "detalhes_completos": "Alteração do Anúncio de procedimento n.º 33396/2025, de 2025-12-24, com o ID 419921273\n\n1 - IDENTIFICAÇÃO E CONTACTOS DA ENTIDADE ADJUDICANTE\nDesignação da entidade adjudicante: Universidade do Porto\nNIPC: 501413197\nServiço/Órgão/Pessoa de contacto: Serviço de Compras e Gestão Contratual da U. Porto | Bruno Mateus\nEndereço: Praça Gomes Teixeira s/n\nCódigo postal: 4099-002\nLocalidade: Porto\nPaís: Portugal\nNUT III: PT11A\nDistrito: Porto\nConcelho: Porto\nFreguesia: União das Freguesias de Cedofeita, Santo Ildefonso, Sé, Miragaia, São Nicolau e Vitória\nTelefone: 220408000\nFax: 2204081867\nEndereço da Entidade (URL): www.reit.up.pt\nEndereço Eletrónico: reitoria@reit.up.pt\neDelivery Gateway (URL): https://www.acingov.pt\nFunção da Organização: Adquirente\nNorma jurídica da Entidade Adjudicante: Organismo de direito público\nÁrea de atividade da Autoridade Adjudicante: Educação\n\n2 - JORNAL OFICIAL DA UNIÃO EUROPEIA\nO procedimento a que este anúncio diz respeito também é publicitado no Jornal Oficial da União Europeia? Sim\n\n3 - AVISO\nModelo de Anúncio: Concurso público\nData de Envio do Anúncio: 29-12-2025\n\n5 - PROCESSO\nTipo de Procedimento: Concurso público\nPreço base do procedimento: Sim\nValor do preço base do procedimento: 382.705,98 EUR\nProcedimento com lotes? Sim\nNº Máx. de Lotes Autorizado: 9\nNúmero máximo de lotes que podem ser adjudicados a um concorrente: 9\n\n6 - OBJETO DO CONTRATO\nNúmero de referência interna: SCGC_REIT_CPI_00008_2025\nDesignação do contrato: Aquisição de mobiliário para a Residência Jayme Rios de Souza da U. Porto (Lotes) - PRR\nDescrição: Aquisição de mobiliário para a Residência Jayme Rios de Souza da U. Porto (Lotes) - PRR\nOpções: Não\nTipo de Contrato Principal: Aquisição de Bens Móveis\nTipo de Contrato: Aquisição de Bens Móveis\nClassificação CPV (Vocabulário Comum para os Contratos Públicos)\nObjeto principal\nVocabulário Principal: 39143110\nPreço base s/IVA: 382.705,98 EUR\nLotes: \nNº: LOT-0001\nDescrição do Lote: Mesas e armários\nPreço base s/IVA: 28.677,25 EUR\nClassificação CPV (Vocabulário Comum para os Contratos Públicos)\nObjeto principal\nVocabulário Principal: 39121000\nNº: LOT-0002\nDescrição do Lote: Cadeiras\nPreço base s/IVA: 47.931,52 EUR\nClassificação CPV (Vocabulário Comum para os Contratos Públicos)\nObjeto principal\nVocabulário Principal: 39112000\nNº: LOT-0003\nDescrição do Lote: Sofás\nPreço base s/IVA: 10.560,00 EUR\nClassificação CPV (Vocabulário Comum para os Contratos Públicos)\nObjeto principal\nVocabulário Principal: 39113200\nNº: LOT-0004\nDescrição do Lote: Cacifos e estantes\nPreço base s/IVA: 11.492,79 EUR\nClassificação CPV (Vocabulário Comum para os Contratos Públicos)\nObjeto principal\nVocabulário Principal: 39112000\nNº: LOT-0005\nDescrição do Lote: Camas e mobiliário de quartos\nPreço base s/IVA: 117.099,02 EUR\nClassificação CPV (Vocabulário Comum para os Contratos Públicos)\nObjeto principal\nVocabulário Principal: 39143110\nNº: LOT-0006\nDescrição do Lote: Complementos\nPreço base s/IVA: 51.511,80 EUR\nClassificação CPV (Vocabulário Comum para os Contratos Públicos)\nObjeto principal\nVocabulário Principal: 39150000\nNº: LOT-0007\nDescrição do Lote: Acessórios de desporto\nPreço base s/IVA: 2.000,00 EUR\nClassificação CPV (Vocabulário Comum para os Contratos Públicos)\nObjeto principal\nVocabulário Principal: 39150000\nNº: LOT-0008\nDescrição do Lote: Candeeiro de parede\nPreço base s/IVA: 29.702,40 EUR\nClassificação CPV (Vocabulário Comum para os Contratos Públicos)\nObjeto principal\nVocabulário Principal: 39150000\nNº: LOT-0009\nDescrição do Lote: Cortinas e estores\nPreço base s/IVA: 83.731,20 EUR\nClassificação CPV (Vocabulário Comum para os Contratos Públicos)\nObjeto principal\nVocabulário Principal: 39515400\n\n7 - INDICAÇÕES ADICIONAIS\nO contrato envolve aquisição conjunta (satisfação de várias entidades)? Não\nO contrato é adjudicado por uma central de compras? Não\n\n8 - TÉCNICAS\nO concurso destina-se à celebração de um acordo-quadro? Inexistência de acordo-quadro\nÉ utilizado um leilão eletrónico? Não\nÉ adotada uma fase de negociação? Não\nSistema de Aquisição Dinâmico: Inexistência de sistema de aquisição dinâmico\n\n9 - LOCAL DA EXECUÇÃO DO CONTRATO\nLOCAL DA EXECUÇÃO DO CONTRATO (PROCEDIMENTO)\nPaís: Portugal\nNUT III: PT11A\nLocalidade: Porto\nDistrito: Porto\nConcelho: Porto\nFreguesia: Todas\nLOCAL DA EXECUÇÃO DO CONTRATO (LOTE)\nIdentificador do Lote: LOT-0001; LOT-0002; LOT-0003; LOT-0004; LOT-0005; LOT-0006; LOT-0007; LOT-0008; LOT-0009\nPaís: Portugal\nNUT III: PT11A\nLocalidade: Porto\nDistrito: Porto\nConcelho: Porto\nFreguesia: Todas\n\n10 - PRAZO DE EXECUÇÃO DO CONTRATO\nIdentificador do Lote: LOT-0001; LOT-0002; LOT-0003; LOT-0004; LOT-0005; LOT-0006; LOT-0007; LOT-0008; LOT-0009\nData de Início: 16-04-2026\nData de Fim: 31-05-2026\nPrevisão de renovações: Não\n\n11 - FUNDOS EU\nIdentificador do Lote: LOT-0001; LOT-0002; LOT-0003; LOT-0004; LOT-0005; LOT-0006; LOT-0007; LOT-0008; LOT-0009\nTêm fundos EU? Sim\n\n12 - DOCUMENTOS DE HABILITAÇÃO\nHabilitação para o exercício da atividade profissional: Não\n\n13 - CONDIÇÕES DE APRESENTAÇÃO\nPlataforma eletrónica utilizada pela entidade adjudicante: ACIN\nURL para Apresentação: https://www.acingov.pt\nAdmissibilidade da apresentação de propostas variantes: Não autorizado\nPrazo para apresentação das propostas: 21-01-2026 23:59\nPrazo durante o qual os concorrentes são obrigados a manter as respetivas propostas: 66 dias a contar do termo do prazo para a apresentação das propostas\nApresentação de Catálogo Eletrónico: Permitido\nIndicação de Subcontratação na Proposta: Inexistência de indicação de subcontratação\n\n14 - PRESTAÇÃO DE CAUÇÃO\nPrestação de caução: Não\n\n15 - FORNECIMENTO DAS PEÇAS DO CONCURSO, APRESENTAÇÃO DE PEDIDOS DE PARTICIPAÇÃO E APRESENTAÇÃO DAS PROPOSTAS\nLink para acesso às peças do concurso (URL): https://www.acingov.pt/acingovprod/2/zonaPublica/zona_publica_c/donwloadProcedurePiece/MTAwODg1NA==\n\n20 - OUTROS REQUISITOS\nIdentificador do Lote: LOT-0001; LOT-0002; LOT-0003; LOT-0004; LOT-0005; LOT-0006; LOT-0007; LOT-0008; LOT-0009\nInformação sobre contratos reservados. Aplica-se a contratos reservados (54º-A)? Não\n\n21 - CRITÉRIO DE ADJUDICAÇÃO\nO Critério de adjudicação é diferenciado por lote? Não\nMultifator: Não\nMonofator:\nNome: Preço\n\n24 - CONDIÇÕES DO CONTRATO\nIdentificador do Lote: LOT-0001; LOT-0002; LOT-0003; LOT-0004; LOT-0005; LOT-0006; LOT-0007; LOT-0008; LOT-0009\nFaturação Eletrónica: Necessário\nObrigação de Subcontratação:\nCódigo da Obrigação de Subcontratação: Não é aplicável nenhuma obrigação de subcontratação.\n\n25 - COMPRA PÚBLICA ESTRATÉGICA\nCompra Pública Estratégica: Redução dos impactos ambientais\nDescrição do Processo de Adjudicação Estratégico: O cocontratante deve garantir as melhores práticas ambientais por forma a incluir as medidas necessárias a fim de assegurar a proteção do ar, da água, do solo, e de prevenir ou reduzir a poluição sonora, a produção de resíduos e o consumo energético, com o objetivo de alcançar um nível elevado de proteção do ambiente e minimizar os impactes ambientais. O cocontratante deve igualmente garantir o correto encaminhamento dos eventuais resíduos produzidos no decorrer da execução do contrato, respeitando as boas práticas ambientais previstas na legislação em vigor.\nCritérios de contratos Públicos Ecológicos: Outros critérios de contratação pública ecológica\nCategorias da estratégia nacional: Mobiliário\nContratos Públicos Ecológicos: A proteção e o restauro da biodiversidade e dos ecossistemas; A transição para uma economia circular; A adaptação às alterações climáticas; A mitigação das alterações climáticas; A prevenção e o controlo da poluição\nDiretiva Veículos Não Poluentes: Não\nCritério de Acessibilidade: Os critérios de acessibilidade para as pessoas com deficiência não estão incluídos porque o contrato não se destina a pessoas singulares\n\n26 - INFORMAÇÕES ADICIONAIS\nIdentificador do Lote: LOT-0001; LOT-0002; LOT-0003; LOT-0004; LOT-0005; LOT-0006; LOT-0007; LOT-0008; LOT-0009\nContrato adequado para PME: Sim\nCobertura ACP (Acordo dos Contratos Públicos da Organização Mundial do Comércio): Não\n\n27 - IDENTIFICAÇÃO E CONTACTOS DO ÓRGÃO DE RECURSOS ADMINISTRATIVOS\nDesignação: Reitor da Universidade do Porto\nEndereço: Praça Gomes Teixeira s/n\nCódigo postal: 4099-002\nLocalidade: Porto\nTelefone: 220408797\nFax: 220408797\nEndereço eletrónico: compras@sp.up.pt\nPrazo de interposição do recurso: 5 dias\n\n28 - IDENTIFICAÇÃO DO(S) AUTOR(ES) DE ANÚNCIO\nNome: Bruno André Mesquita da Silva Mateus\nCargo: Técnico Superior\n\n29 - ALTERAÇÃO\nMotivo da Alteração: Correção pelo adquirente\nIdentificador da Versão do Anúncio a Alterar: 15f2e951-c17e-4d48-a3c5-f8c5e7adb048-01\nIdentificador das Secções Alteradas do Anúncio Anterior: Objeto do contrato\nDescrição das Alterações: O \"Título\" do procedimento está divergente da \"Descrição\". A informação correta é a que consta na Descrição: Aquisição de mobiliário para a Residência Jayme Rios de Souza da U. Porto (Lotes) - PRR\nAlteração dos Documentos do Concurso: Não\n419932338",
    "nipc": "501413197",
    "distrito": "Porto",
    "concelho": "Porto",
    "freguesia": "União das Freguesias de Cedofeita, Santo Ildefonso, Sé, Miragaia, São Nicolau e Vitória",
    "site": "www.reit.up.pt",
    "email": "reitoria@reit.up.pt",
    "designacao_contrato": "Aquisição de mobiliário para a Residência Jayme Rios de Souza da U. Porto (Lotes) - PRR",
    "descricao": "Aquisição de mobiliário para a Residência Jayme Rios de Souza da U. Porto (Lotes) - PRR",
    "preco_base": "382.705,98 EUR",
    "prazo_execucao": null,
    "prazo_apresentacao_propostas": "21-01-2026 23:59",
    "fundos_eu": "Sim",
    "plataforma_eletronica": "ACIN",
    "url_procedimento": "https://www.acingov.pt",
    "autor_nome": "Bruno André Mesquita da Silva Mateus",
    "autor_cargo": "Técnico Superior"
  },
  {
    "numero_procedimento": "N/A",
    "entidade": "Município da Guarda",
    "link": "https://diariodarepublica.pt/dr/detalhe/contrato-publico/33673-993605853",
    "detalhes_completos": "1 - IDENTIFICAÇÃO E CONTACTOS DA ENTIDADE ADJUDICANTE\nDesignação da entidade adjudicante: Município da Guarda\nNIPC: 501131140\nEndereço: Praça do Município, nº 1\nCódigo postal: 6301-854\nLocalidade: Guarda\nPaís: Portugal\nNUT III: PT16J\nDistrito: Guarda\nConcelho: Guarda\nFreguesia: Freguesia de Guarda\nTelefone: 271220200\nFax: 271220280\nEndereço da Entidade (URL): www.mun-guarda.pt\nEndereço Eletrónico: geral@mun-guarda.pt\neDelivery Gateway (URL): https://community.vortal.biz/public/\nFunção da Organização: Adquirente\nNorma jurídica da Entidade Adjudicante: Autoridade da administração central\nÁrea de atividade da Autoridade Adjudicante: Serviços públicos das administrações públicas\n\n2 - JORNAL OFICIAL DA UNIÃO EUROPEIA\nO procedimento a que este anúncio diz respeito também é publicitado no Jornal Oficial da União Europeia? Não\n\n3 - AVISO\nModelo de Anúncio: Concurso público\nData de Envio do Anúncio: 31-12-2025\n\n5 - PROCESSO\nTipo de Procedimento: Concurso público\nPreço base do procedimento: Sim\nValor do preço base do procedimento: 92.000,00 EUR\nProcedimento com lotes? Não\n\n6 - OBJETO DO CONTRATO\nNúmero de referência interna: Nº 259/2025_\nDesignação do contrato: Aluguer Operacional de Três Viaturas Ligeiras de Passageiros\nDescrição: Aluguer Operacional de Três Viaturas Ligeiras de Passageiros\nTipo de Contrato Principal: Aquisição de Bens Móveis\nTipo de Contrato: Aquisição de Bens Móveis\nClassificação CPV (Vocabulário Comum para os Contratos Públicos)\nObjeto principal\nVocabulário Principal: 34110000\nPreço base s/IVA: 92.000,00 EUR\n\n7 - INDICAÇÕES ADICIONAIS\nO contrato envolve aquisição conjunta (satisfação de várias entidades)? Não\nO contrato é adjudicado por uma central de compras? Não\n\n8 - TÉCNICAS\nO concurso destina-se à celebração de um acordo-quadro? Inexistência de acordo-quadro\nÉ utilizado um leilão eletrónico? Não\nÉ adotada uma fase de negociação? Não\nSistema de Aquisição Dinâmico: Inexistência de sistema de aquisição dinâmico\n\n9 - LOCAL DA EXECUÇÃO DO CONTRATO\nLOCAL DA EXECUÇÃO DO CONTRATO (PROCEDIMENTO)\nPaís: Portugal\nNUT III: PT16J\nLocalidade: Guarda\nDistrito: Guarda\nConcelho: Guarda\nFreguesia: Freguesia de Guarda\n\n10 - PRAZO DE EXECUÇÃO DO CONTRATO\nPrazo de execução do contrato: 60 MESES\nPrevisão de renovações: Não\n\n11 - FUNDOS EU\nTêm fundos EU? Não\n\n12 - DOCUMENTOS DE HABILITAÇÃO\nHabilitação para o exercício da atividade profissional: Não\n\n13 - CONDIÇÕES DE APRESENTAÇÃO\nPlataforma eletrónica utilizada pela entidade adjudicante: VORTAL\nURL para Apresentação: https://community.vortal.biz/public/\nAdmissibilidade da apresentação de propostas variantes: Não autorizado\nPrazo para apresentação das propostas: 15-01-2026 17:00\nPrazo durante o qual os concorrentes são obrigados a manter as respetivas propostas: 66 dias a contar do termo do prazo para a apresentação das propostas\nIndicação de Subcontratação na Proposta: Inexistência de indicação de subcontratação\n\n14 - PRESTAÇÃO DE CAUÇÃO\nPrestação de caução: Não\n\n15 - FORNECIMENTO DAS PEÇAS DO CONCURSO, APRESENTAÇÃO DE PEDIDOS DE PARTICIPAÇÃO E APRESENTAÇÃO DAS PROPOSTAS\nLink para acesso às peças do concurso (URL): https://community.vortal.biz/Public/public-tender-documents/MjBDSWFvRk9TeFdhVXM5STlNbjgvMDBiSkpiT0dnbTdpajg1dEdTZmUwMlIyZmVKZUM3N3MrVU1EN0EzZGovSzNtMnpGN3pkNHNaSzVZVHlnaEJFN1E9PUxFeWNy\n\n20 - OUTROS REQUISITOS\nInformação sobre contratos reservados. Aplica-se a contratos reservados (54º-A)? Não\n\n21 - CRITÉRIO DE ADJUDICAÇÃO\nMultifator: Não\nMonofator:\nNome: Preço\n\n24 - CONDIÇÕES DO CONTRATO\nFaturação Eletrónica: Permitido\nObrigação de Subcontratação:\nCódigo da Obrigação de Subcontratação: Não é aplicável nenhuma obrigação de subcontratação.\n\n25 - COMPRA PÚBLICA ESTRATÉGICA\nCompra Pública Estratégica: Inexistência de contratação pública estratégica\n\n26 - INFORMAÇÕES ADICIONAIS\nContrato adequado para PME: Sim\nCobertura ACP (Acordo dos Contratos Públicos da Organização Mundial do Comércio): Não\n\n27 - IDENTIFICAÇÃO E CONTACTOS DO ÓRGÃO DE RECURSOS ADMINISTRATIVOS\nDesignação: Presidente da Câmara Municipal da Guarda\nEndereço: Praça do Municipio_\nCódigo postal: 6301-854\nLocalidade: Guarda\nTelefone: +351 271220200\nFax: +351 271220280\nEndereço eletrónico: contratacaopublica@mun-guarda.pt\n\n28 - IDENTIFICAÇÃO DO(S) AUTOR(ES) DE ANÚNCIO\nNome: Sérgio Fernando da Silva Costa\nCargo: Presidente da Câmara Municipal da Guarda\n419943557",
    "nipc": "501131140",
    "distrito": "Guarda",
    "concelho": "Guarda",
    "freguesia": "Freguesia de Guarda",
    "site": "www.mun-guarda.pt",
    "email": "geral@mun-guarda.pt",
    "designacao_contrato": "Aluguer Operacional de Três Viaturas Ligeiras de Passageiros",
    "descricao": "Aluguer Operacional de Três Viaturas Ligeiras de Passageiros",
    "preco_base": "92.000,00 EUR",
    "prazo_execucao": "60 MESES",
    "prazo_apresentacao_propostas": "15-01-2026 17:00",
    "fundos_eu": "Não",
    "plataforma_eletronica": "VORTAL",
    "url_procedimento": "https://community.vortal.biz/public/",
    "autor_nome": "Sérgio Fernando da Silva Costa",
    "autor_cargo": "Presidente da Câmara Municipal da Guarda"
  },
  {
    "numero_procedimento": "N/A",
    "entidade": "Município de Vila Pouca de Aguiar",
    "link": "https://diariodarepublica.pt/dr/detalhe/contrato-publico/33675-993605854",
    "detalhes_completos": "1 - IDENTIFICAÇÃO E CONTACTOS DA ENTIDADE ADJUDICANTE\nDesignação da entidade adjudicante: Município de Vila Pouca de Aguiar\nNIPC: 506810267\nEndereço: Rua Henrique Botelho\nCódigo postal: 5450-020\nLocalidade: Vila Pouca de Aguiar\nPaís: Portugal\nNUT III: PT11B\nDistrito: Vila Real\nConcelho: Vila Pouca de Aguiar\nFreguesia: Todas\nTelefone: 259419100\nEndereço da Entidade (URL): http://www.cm-vpaguiar.pt\nEndereço Eletrónico: vortal@cm-vpaguiar.pt\neDelivery Gateway (URL): https://community.vortal.biz/public/\nFunção da Organização: Adquirente\nNorma jurídica da Entidade Adjudicante: Autoridade local\nÁrea de atividade da Autoridade Adjudicante: Serviços públicos das administrações públicas\n\n2 - JORNAL OFICIAL DA UNIÃO EUROPEIA\nO procedimento a que este anúncio diz respeito também é publicitado no Jornal Oficial da União Europeia? Sim\n\n3 - AVISO\nModelo de Anúncio: Concurso público\nData de Envio do Anúncio: 29-12-2025\n\n5 - PROCESSO\nTipo de Procedimento: Concurso público\nPreço base do procedimento: Sim\nValor do preço base do procedimento: 1.443.636,00 EUR\nProcedimento com lotes? Não\n\n6 - OBJETO DO CONTRATO\nNúmero de referência interna: APR.110/2025\nDesignação do contrato: PRESTAÇÃO DE SERVIÇOS DE GESTÃO DE RESÍDUOS SÓLIDOS URBANOS NO CONCELHO DE VILA POUCA DE AGUIAR\nDescrição: PRESTAÇÃO DE SERVIÇOS DE GESTÃO DE RESÍDUOS SÓLIDOS URBANOS NO CONCELHO DE VILA POUCA DE AGUIAR\nOpções: Não\nTipo de Contrato Principal: Aquisição de Serviços\nTipo de Contrato: Aquisição de Serviços\nClassificação CPV (Vocabulário Comum para os Contratos Públicos)\nObjeto principal\nVocabulário Principal: 90500000\nPreço base s/IVA: 1.443.636,00 EUR\n\n7 - INDICAÇÕES ADICIONAIS\nO contrato envolve aquisição conjunta (satisfação de várias entidades)? Não\nO contrato é adjudicado por uma central de compras? Não\n\n8 - TÉCNICAS\nO concurso destina-se à celebração de um acordo-quadro? Inexistência de acordo-quadro\nÉ utilizado um leilão eletrónico? Não\nÉ adotada uma fase de negociação? Não\nSistema de Aquisição Dinâmico: Inexistência de sistema de aquisição dinâmico\n\n9 - LOCAL DA EXECUÇÃO DO CONTRATO\nLOCAL DA EXECUÇÃO DO CONTRATO (PROCEDIMENTO)\nPaís: Portugal\nNUT III: PT11B\nLocalidade: Vila Real\nDistrito: Vila Real\nConcelho: Vila Pouca de Aguiar\nFreguesia: Freguesia de Vila Pouca de Aguiar\n\n10 - PRAZO DE EXECUÇÃO DO CONTRATO\nPrazo de execução do contrato: 24 MESES\nPrevisão de renovações: Sim\nIndicar número máximo de renovações: 1\nPrazo de renovações diferente do prazo inicial: Sim\nIndicar o prazo de execução da renovação do contrato: 12 MESES\n\n11 - FUNDOS EU\nTêm fundos EU? Não\n\n12 - DOCUMENTOS DE HABILITAÇÃO\nHabilitação para o exercício da atividade profissional: Sim\nTipo: Outros\nDescrição - Outros: Habilitação legal para o exercício da atividade de recolha e transporte de RSU`S\nDescrição: Conforme Artigo 31º do Programa de Procedimento\n\n13 - CONDIÇÕES DE APRESENTAÇÃO\nPlataforma eletrónica utilizada pela entidade adjudicante: VORTAL\nURL para Apresentação: https://community.vortal.biz/public/\nAdmissibilidade da apresentação de propostas variantes: Não autorizado\nPrazo para apresentação das propostas: 28-01-2026 17:00\nPrazo durante o qual os concorrentes são obrigados a manter as respetivas propostas: 66 dias a contar do termo do prazo para a apresentação das propostas\nApresentação de Catálogo Eletrónico: Não autorizado\nIndicação de Subcontratação na Proposta: Inexistência de indicação de subcontratação\n\n14 - PRESTAÇÃO DE CAUÇÃO\nPrestação de caução: Sim\nPercentagem: 5%\nDescrição da Garantia Exigida: Conforme Artigo 32º do Programa de Procedimento\n\n15 - FORNECIMENTO DAS PEÇAS DO CONCURSO, APRESENTAÇÃO DE PEDIDOS DE PARTICIPAÇÃO E APRESENTAÇÃO DAS PROPOSTAS\nLink para acesso às peças do concurso (URL): https://community.vortal.biz/Public/public-tender-documents/cXBCcVdid2p0dndiRUR3Q1pway9YUXEyQzFCMUE2WHpTek5nc1JkcWZObGpsQU8wZWJYQUtoWkMyUFJTT00yVUFsbDBxYlhIek9LMFlRdHJ5bTYxVmc9PTA5dihK\n\n20 - OUTROS REQUISITOS\nInformação sobre contratos reservados. Aplica-se a contratos reservados (54º-A)? Não\n\n21 - CRITÉRIO DE ADJUDICAÇÃO\nMultifator: Não\nMonofator:\nNome: Preço\n\n24 - CONDIÇÕES DO CONTRATO\nFaturação Eletrónica: Permitido\nObrigação de Subcontratação:\nCódigo da Obrigação de Subcontratação: Não é aplicável nenhuma obrigação de subcontratação.\n\n25 - COMPRA PÚBLICA ESTRATÉGICA\nCompra Pública Estratégica: Inexistência de contratação pública estratégica\n\n26 - INFORMAÇÕES ADICIONAIS\nContrato adequado para PME: Sim\nCobertura ACP (Acordo dos Contratos Públicos da Organização Mundial do Comércio): Não\n\n27 - IDENTIFICAÇÃO E CONTACTOS DO ÓRGÃO DE RECURSOS ADMINISTRATIVOS\nDesignação: Tribunal Administrativo e Fiscal de Mirandela\nEndereço: Avª da Republica, nº70\nCódigo postal: 5370-408\nLocalidade: Mirandela\nTelefone: +351 278201770\nFax: +351 213506001\nEndereço eletrónico: mirandela.taf@tribunais.org.pt\n\n28 - IDENTIFICAÇÃO DO(S) AUTOR(ES) DE ANÚNCIO\nNome: Ana Rita Ferreira Dias Bastos\nCargo: Presidente da Câmara Municipal\n419935773",
    "nipc": "506810267",
    "distrito": "Vila Real",
    "concelho": "Vila Pouca de Aguiar",
    "freguesia": "Todas",
    "site": "http://www.cm-vpaguiar.pt",
    "email": "vortal@cm-vpaguiar.pt",
    "designacao_contrato": "PRESTAÇÃO DE SERVIÇOS DE GESTÃO DE RESÍDUOS SÓLIDOS URBANOS NO CONCELHO DE VILA POUCA DE AGUIAR",
    "descricao": "PRESTAÇÃO DE SERVIÇOS DE GESTÃO DE RESÍDUOS SÓLIDOS URBANOS NO CONCELHO DE VILA POUCA DE AGUIAR",
    "preco_base": "1.443.636,00 EUR",
    "prazo_execucao": "24 MESES",
    "prazo_apresentacao_propostas": "28-01-2026 17:00",
    "fundos_eu": "Não",
    "plataforma_eletronica": "VORTAL",
    "url_procedimento": "https://community.vortal.biz/public/",
    "autor_nome": "Ana Rita Ferreira Dias Bastos",
    "autor_cargo": "Presidente da Câmara Municipal"
  }
]