[
  {
    "numero_procedimento": "N/A",
    "entidade": "Santa Casa da Misericórdia de Lisboa",
    "link": "https://diariodarepublica.pt/dr/detalhe/contrato-publico/157-995301068",
    "detalhes_completos": "1 - IDENTIFICAÇÃO E CONTACTOS DA ENTIDADE ADJUDICANTE\nDesignação da entidade adjudicante: Santa Casa da Misericórdia de Lisboa\nNIPC: 500745471\nServiço/Órgão/Pessoa de contacto: Exma. Mesa\nEndereço: Largo Trindade Coelho\nCódigo postal: 1200-470\nLocalidade: Lisboa\nPaís: Portugal\nNUT III: PT170\nDistrito: Lisboa\nConcelho: Todos\nFreguesia: Todas\nTelefone: 213235000\nFax: 213235013\nEndereço da Entidade (URL): http://www.scml.pt/\nEndereço Eletrónico: compras@scml.pt\neDelivery Gateway (URL): https://www.acingov.pt\nFunção da Organização: Adquirente\nSubfunção da Organização: Organização cujo orçamento é utilizado para pagar o contrato; Organização que executa o pagamento; Organização que fornece informações adicionais sobre o processo de adjudicação; Organização que fornece mais informações sobre os prazos dos procedimentos de recurso; Organização que fornece acesso fora de linha aos documentos do concurso; Organização responsável pelo tratamento das propostas; Organização que recebe as propostas; Organização que trata os pedidos de participação; Organização que recebe pedidos de participação; Organização que fornece mais informações sobre os procedimentos de recurso; Organização que assina o contrato\nNorma jurídica da Entidade Adjudicante: Organismo de direito público, controlado por uma autoridade da administração central\nÁrea de atividade da Autoridade Adjudicante: Proteção social\n2 - JORNAL OFICIAL DA UNIÃO EUROPEIA\nO procedimento a que este anúncio diz respeito também é publicitado no Jornal Oficial da União Europeia? Não\n3 - AVISO\nModelo de Anúncio: Concurso público\nData de Envio do Anúncio: 05-01-2026\n5 - PROCESSO\nTipo de Procedimento: Concurso público\nPreço base do procedimento: Sim\nValor do preço base do procedimento: 135.210,00 EUR\nProcedimento com lotes? Não\n6 - OBJETO DO CONTRATO\nNúmero de referência interna: 25DC51CP015\nDesignação do contrato: Prestação de Serviços de Suporte das licenças BMC Control-M e respetivos serviços de consultoria\nDescrição: Prestação de Serviços de Suporte das licenças BMC Control-M e respetivos serviços de consultoria\nTipo de Contrato Principal: Aquisição de Serviços\nTipo de Contrato: Aquisição de Serviços\nClassificação CPV (Vocabulário Comum para os Contratos Públicos)\nObjeto principal\nVocabulário Principal: 72610000\nPreço base s/IVA: 135.210,00 EUR\n7 - INDICAÇÕES ADICIONAIS\nO contrato envolve aquisição conjunta (satisfação de várias entidades)? Não\nO contrato é adjudicado por uma central de compras? Não\n8 - TÉCNICAS\nO concurso destina-se à celebração de um acordo-quadro? Inexistência de acordo-quadro\nÉ utilizado um leilão eletrónico? Não\nÉ adotada uma fase de negociação? Não\nSistema de Aquisição Dinâmico: Inexistência de sistema de aquisição dinâmico\n9 - LOCAL DA EXECUÇÃO DO CONTRATO\nLOCAL DA EXECUÇÃO DO CONTRATO (PROCEDIMENTO)\nPaís: Portugal\nNUT III: PT170\nLocalidade: Freguesia de Misericórdia\nDistrito: Lisboa\nConcelho: Lisboa\nFreguesia: Freguesia de Misericórdia\n10 - PRAZO DE EXECUÇÃO DO CONTRATO\nPrazo de execução do contrato: 36 MESES\nPrevisão de renovações: Não\n11 - FUNDOS EU\nTêm fundos EU? Não\n12 - DOCUMENTOS DE HABILITAÇÃO\nHabilitação para o exercício da atividade profissional: Não\n13 - CONDIÇÕES DE APRESENTAÇÃO\nPlataforma eletrónica utilizada pela entidade adjudicante: ACIN\nURL para Apresentação: https://www.acingov.pt\nAdmissibilidade da apresentação de propostas variantes: Não autorizado\nPrazo para apresentação das propostas: 20-01-2026 17:00\nPrazo durante o qual os concorrentes são obrigados a manter as respetivas propostas: 120 dias a contar do termo do prazo para a apresentação das propostas\nIndicação de Subcontratação na Proposta: Inexistência de indicação de subcontratação\n14 - PRESTAÇÃO DE CAUÇÃO\nPrestação de caução: Não\n15 - FORNECIMENTO DAS PEÇAS DO CONCURSO, APRESENTAÇÃO DE PEDIDOS DE PARTICIPAÇÃO E APRESENTAÇÃO DAS PROPOSTAS\nLink para acesso às peças do concurso (URL): https://www.acingov.pt/acingovprod/2/zonaPublica/zona_publica_c/donwloadProcedurePiece/MTAzNTk4NA==\n20 - OUTROS REQUISITOS\nInformação sobre contratos reservados. Aplica-se a contratos reservados (54º-A)? Não\n21 - CRITÉRIO DE ADJUDICAÇÃO\nMultifator: Não\nMonofator:\nNome: Preço\n24 - CONDIÇÕES DO CONTRATO\nFaturação Eletrónica: Necessário\nObrigação de Subcontratação:\nCódigo da Obrigação de Subcontratação: Não é aplicável nenhuma obrigação de subcontratação.\n25 - COMPRA PÚBLICA ESTRATÉGICA\nCompra Pública Estratégica: Inexistência de contratação pública estratégica\n26 - INFORMAÇÕES ADICIONAIS\nContrato adequado para PME: Sim\nCobertura ACP (Acordo dos Contratos Públicos da Organização Mundial do Comércio): Não\n27 - IDENTIFICAÇÃO E CONTACTOS DO ÓRGÃO DE RECURSOS ADMINISTRATIVOS\nDesignação: Exma. Mesa\nEndereço: Largo Trindade Coelho\nCódigo postal: 1200-470\nLocalidade: Lisboa\nTelefone: 213235000\nFax: \nEndereço eletrónico: dicom.nabse@scml.pt\n28 - IDENTIFICAÇÃO DO(S) AUTOR(ES) DE ANÚNCIO\nNome: Vanda Simão\nCargo: Diretora da Direção de Compras\n419947135",
    "nipc": "500745471",
    "distrito": "Lisboa",
    "concelho": "Todos",
    "freguesia": "Todas",
    "site": "http://www.scml.pt/",
    "email": "compras@scml.pt",
    "designacao_contrato": "Prestação de Serviços de Suporte das licenças BMC Control-M e respetivos serviços de consultoria",
    "descricao": "Prestação de Serviços de Suporte das licenças BMC Control-M e respetivos serviços de consultoria",
    "preco_base": "135.210,00 EUR",
    "prazo_execucao": "36 MESES",
    "prazo_apresentacao_propostas": "20-01-2026 17:00",
    "fundos_eu": "Não",
    "plataforma_eletronica": "ACIN",
    "url_procedimento": "https://www.acingov.pt",
    "autor_nome": "Vanda Simão",
    "autor_cargo": "Diretora da Direção de Compras"
  },
  {
    "numero_procedimento": "N/A",
    "entidade": "Município de Vila Nova de Famalicão",
    "link": "https://diariodarepublica.pt/dr/detalhe/contrato-publico/158-995301070",
    "detalhes_completos": "1 - IDENTIFICAÇÃO E CONTACTOS DA ENTIDADE ADJUDICANTE\nDesignação da entidade adjudicante: Município de Vila Nova de Famalicão\nNIPC: 506663264\nServiço/Órgão/Pessoa de contacto: DGM - Contratação Pública\nEndereço: Praça Álvaro Marques\nCódigo postal: 4764-502\nLocalidade: Vila Nova de Famalicão\nPaís: Portugal\nNUT III: PT119\nDistrito: Braga\nConcelho: Vila Nova de Famalicão\nFreguesia: União das Freguesias de Vila Nova de Famalicão e Calendário\nTelefone: 252320900\nFax: 252320906\nEndereço da Entidade (URL): www.famalicao.pt\nEndereço Eletrónico: concursos@famalicao.pt\nFunção da Organização: Adquirente\nNorma jurídica da Entidade Adjudicante: Autoridade local\nÁrea de atividade da Autoridade Adjudicante: Serviços públicos das administrações públicas\n2 - JORNAL OFICIAL DA UNIÃO EUROPEIA\nO procedimento a que este anúncio diz respeito também é publicitado no Jornal Oficial da União Europeia? Não\n3 - AVISO\nModelo de Anúncio: Concurso público\nData de Envio do Anúncio: 05-01-2026\n5 - PROCESSO\nTipo de Procedimento: Concurso público\nPreço base do procedimento: Sim\nValor do preço base do procedimento: 48.000,00 EUR\nProcedimento com lotes? Não\n6 - OBJETO DO CONTRATO\nNúmero de referência interna: 2025DBS0071DASU\nDesignação do contrato: Argamassa para serviços de saneamento e águas pluviais\nDescrição: Argamassa para serviços de saneamento e águas pluviais\nTipo de Contrato Principal: Aquisição de Bens Móveis\nTipo de Contrato: Aquisição de Bens Móveis\nClassificação CPV (Vocabulário Comum para os Contratos Públicos)\nObjeto principal\nVocabulário Principal: 44111800\nPreço base s/IVA: 48.000,00 EUR\n7 - INDICAÇÕES ADICIONAIS\nO contrato envolve aquisição conjunta (satisfação de várias entidades)? Não\nO contrato é adjudicado por uma central de compras? Não\n8 - TÉCNICAS\nO concurso destina-se à celebração de um acordo-quadro? Inexistência de acordo-quadro\nÉ utilizado um leilão eletrónico? Não\nÉ adotada uma fase de negociação? Sim\nSistema de Aquisição Dinâmico: Inexistência de sistema de aquisição dinâmico\n9 - LOCAL DA EXECUÇÃO DO CONTRATO\nLOCAL DA EXECUÇÃO DO CONTRATO (PROCEDIMENTO)\nPaís: Portugal\nNUT III: PT119\nLocalidade: Concelho de Vila Nova de Famalicão\nDistrito: Braga\nConcelho: Vila Nova de Famalicão\nFreguesia: Todas\n10 - PRAZO DE EXECUÇÃO DO CONTRATO\nPrazo de execução do contrato: 730 DIAS\nPrevisão de renovações: Não\n11 - FUNDOS EU\nTêm fundos EU? Não\n12 - DOCUMENTOS DE HABILITAÇÃO\nHabilitação para o exercício da atividade profissional: Não\n13 - CONDIÇÕES DE APRESENTAÇÃO\nPlataforma eletrónica utilizada pela entidade adjudicante: ANOGOV\nURL para Apresentação: https://www.anogov.com/cm-famalicao/faces/\nAdmissibilidade da apresentação de propostas variantes: Não autorizado\nPrazo para apresentação das propostas: 14-01-2026 23:59\nPrazo durante o qual os concorrentes são obrigados a manter as respetivas propostas: 66 dias a contar do termo do prazo para a apresentação das propostas\nApresentação de Catálogo Eletrónico: Necessário\nIndicação de Subcontratação na Proposta: O(s) subcontratante(s) proposto(s) necessário(s) para cumprir a obrigação de subcontratar uma percentagem mínima do contrato\n14 - PRESTAÇÃO DE CAUÇÃO\nPrestação de caução: Não\n15 - FORNECIMENTO DAS PEÇAS DO CONCURSO, APRESENTAÇÃO DE PEDIDOS DE PARTICIPAÇÃO E APRESENTAÇÃO DAS PROPOSTAS\nLink para acesso às peças do concurso (URL): https://www.anogov.com/cm-famalicao/faces/app/acessoDocs.jsp?codigoAcesso=hCNzjfgaf9TtbrLwM5UGicoPUqceIdcbXkFhwXz3Nz3yfvSpwh\n20 - OUTROS REQUISITOS\nInformação sobre contratos reservados. Aplica-se a contratos reservados (54º-A)? Não\n21 - CRITÉRIO DE ADJUDICAÇÃO\nMultifator: Não\nMonofator:\nNome: Preço\n24 - CONDIÇÕES DO CONTRATO\nFaturação Eletrónica: Permitido\nObrigação de Subcontratação:\nCódigo da Obrigação de Subcontratação: Não é aplicável nenhuma obrigação de subcontratação.\n25 - COMPRA PÚBLICA ESTRATÉGICA\nCompra Pública Estratégica: Inexistência de contratação pública estratégica\n26 - INFORMAÇÕES ADICIONAIS\nContrato adequado para PME: Não\nCobertura ACP (Acordo dos Contratos Públicos da Organização Mundial do Comércio): Não\n27 - IDENTIFICAÇÃO E CONTACTOS DO ÓRGÃO DE RECURSOS ADMINISTRATIVOS\nDesignação: Município de Vila Nova de Famalicão\nEndereço: Praça Álvaro Marques\nCódigo postal: 4760-502\nLocalidade: Vila Nova de Famalicão\nEndereço eletrónico: concursos@famalicao.pt\n28 - IDENTIFICAÇÃO DO(S) AUTOR(ES) DE ANÚNCIO\nNome: Mário Passos\nCargo: Presidente da Câmara\n419947175",
    "nipc": "506663264",
    "distrito": "Braga",
    "concelho": "Vila Nova de Famalicão",
    "freguesia": "União das Freguesias de Vila Nova de Famalicão e Calendário",
    "site": "www.famalicao.pt",
    "email": "concursos@famalicao.pt",
    "designacao_contrato": "Argamassa para serviços de saneamento e águas pluviais",
    "descricao": "Argamassa para serviços de saneamento e águas pluviais",
    "preco_base": "48.000,00 EUR",
    "prazo_execucao": "730 DIAS",
    "prazo_apresentacao_propostas": "14-01-2026 23:59",
    "fundos_eu": "Não",
    "plataforma_eletronica": "ANOGOV",
    "url_procedimento": "https://www.anogov.com/cm-famalicao/faces/",
    "autor_nome": "Mário Passos",
    "autor_cargo": "Presidente da Câmara"
  },
  {
    "numero_procedimento": "N/A",
    "entidade": "Unidade Local de Saúde de Braga, EPE",
    "link": "https://diariodarepublica.pt/dr/detalhe/contrato-publico/161-995301071",
    "detalhes_completos": "1 - IDENTIFICAÇÃO E CONTACTOS DA ENTIDADE ADJUDICANTE\nDesignação da entidade adjudicante: Unidade Local de Saúde de Braga, EPE\nNIPC: 515545180\nEndereço: Sete Fontes – São Victor  \nCódigo postal: 4710-243\nLocalidade: Braga\nPaís: Portugal\nNUT III: PT112\nDistrito: Braga\nConcelho: Braga\nFreguesia: Todas\nTelefone: 220411150\nEndereço da Entidade (URL): https://www.hospitaldebraga.pt/\nEndereço Eletrónico: hospitaldebraga@arsnorte.min-saude.pt\neDelivery Gateway (URL): https://community.vortal.biz/public/\nFunção da Organização: Adquirente\nNorma jurídica da Entidade Adjudicante: Empresa pública\nÁrea de atividade da Autoridade Adjudicante: Saúde\n2 - JORNAL OFICIAL DA UNIÃO EUROPEIA\nO procedimento a que este anúncio diz respeito também é publicitado no Jornal Oficial da União Europeia? Não\n3 - AVISO\nModelo de Anúncio: Concurso público\nData de Envio do Anúncio: 05-01-2026\n5 - PROCESSO\nTipo de Procedimento: Concurso público\nPreço base do procedimento: Sim\nValor do preço base do procedimento: 115.421,00 EUR\nProcedimento com lotes? Sim\nNº Máx. de Lotes Autorizado: 16\nNúmero máximo de lotes que podem ser adjudicados a um concorrente: 16\n6 - OBJETO DO CONTRATO\nNúmero de referência interna: 5/00216/26\nDesignação do contrato: Aquisição de material de ORL.\nDescrição: Aquisição de material de ORL.\nTipo de Contrato Principal: Aquisição de Bens Móveis\nTipo de Contrato: Aquisição de Bens Móveis\nClassificação CPV (Vocabulário Comum para os Contratos Públicos)\nObjeto principal\nVocabulário Principal: 33140000\nPreço base s/IVA: 115.421,00 EUR\nLotes: \nNº: LOT-0001\nDescrição do Lote: Lote 1\nPreço base s/IVA: 2.041,20 EUR\nClassificação CPV (Vocabulário Comum para os Contratos Públicos)\nObjeto principal\nVocabulário Principal: 33140000\nNº: LOT-0002\nDescrição do Lote: Lote 2\nPreço base s/IVA: 210,00 EUR\nClassificação CPV (Vocabulário Comum para os Contratos Públicos)\nObjeto principal\nVocabulário Principal: 33140000\nNº: LOT-0003\nDescrição do Lote: Lote 3\nPreço base s/IVA: 5.616,00 EUR\nClassificação CPV (Vocabulário Comum para os Contratos Públicos)\nObjeto principal\nVocabulário Principal: 33140000\nNº: LOT-0004\nDescrição do Lote: Lote 4\nPreço base s/IVA: 16.482,00 EUR\nClassificação CPV (Vocabulário Comum para os Contratos Públicos)\nObjeto principal\nVocabulário Principal: 33140000\nNº: LOT-0005\nDescrição do Lote: Lote 5\nPreço base s/IVA: 19.440,00 EUR\nClassificação CPV (Vocabulário Comum para os Contratos Públicos)\nObjeto principal\nVocabulário Principal: 33140000\nNº: LOT-0006\nDescrição do Lote: Lote 6\nPreço base s/IVA: 6.084,00 EUR\nClassificação CPV (Vocabulário Comum para os Contratos Públicos)\nObjeto principal\nVocabulário Principal: 33140000\nNº: LOT-0007\nDescrição do Lote: Lote 7\nPreço base s/IVA: 41.000,00 EUR\nClassificação CPV (Vocabulário Comum para os Contratos Públicos)\nObjeto principal\nVocabulário Principal: 33140000\nNº: LOT-0008\nDescrição do Lote: Lote 8\nPreço base s/IVA: 3.260,00 EUR\nClassificação CPV (Vocabulário Comum para os Contratos Públicos)\nObjeto principal\nVocabulário Principal: 33140000\nNº: LOT-0009\nDescrição do Lote: Lote 9\nPreço base s/IVA: 1.375,80 EUR\nClassificação CPV (Vocabulário Comum para os Contratos Públicos)\nObjeto principal\nVocabulário Principal: 33140000\nNº: LOT-0010\nDescrição do Lote: Lote 10 \nPreço base s/IVA: 3.940,00 EUR\nClassificação CPV (Vocabulário Comum para os Contratos Públicos)\nObjeto principal\nVocabulário Principal: 33140000\nNº: LOT-0011\nDescrição do Lote: Lote 11\nPreço base s/IVA: 3.095,00 EUR\nClassificação CPV (Vocabulário Comum para os Contratos Públicos)\nObjeto principal\nVocabulário Principal: 33140000\nNº: LOT-0012\nDescrição do Lote: Lote 12\nPreço base s/IVA: 3.100,00 EUR\nClassificação CPV (Vocabulário Comum para os Contratos Públicos)\nObjeto principal\nVocabulário Principal: 33140000\nNº: LOT-0013\nDescrição do Lote: Lote 13\nPreço base s/IVA: 5.280,00 EUR\nClassificação CPV (Vocabulário Comum para os Contratos Públicos)\nObjeto principal\nVocabulário Principal: 33140000\nNº: LOT-0014\nDescrição do Lote: Lote 14\nPreço base s/IVA: 1.857,00 EUR\nClassificação CPV (Vocabulário Comum para os Contratos Públicos)\nObjeto principal\nVocabulário Principal: 33140000\nNº: LOT-0015\nDescrição do Lote: Lote 15\nPreço base s/IVA: 1.240,00 EUR\nClassificação CPV (Vocabulário Comum para os Contratos Públicos)\nObjeto principal\nVocabulário Principal: 33140000\nNº: LOT-0016\nDescrição do Lote: Lote 16\nPreço base s/IVA: 1.400,00 EUR\nClassificação CPV (Vocabulário Comum para os Contratos Públicos)\nObjeto principal\nVocabulário Principal: 33140000\n7 - INDICAÇÕES ADICIONAIS\nO contrato envolve aquisição conjunta (satisfação de várias entidades)? Não\nO contrato é adjudicado por uma central de compras? Não\n8 - TÉCNICAS\nO concurso destina-se à celebração de um acordo-quadro? Inexistência de acordo-quadro\nÉ utilizado um leilão eletrónico? Não\nÉ adotada uma fase de negociação? Não\nSistema de Aquisição Dinâmico: Inexistência de sistema de aquisição dinâmico\n9 - LOCAL DA EXECUÇÃO DO CONTRATO\nLOCAL DA EXECUÇÃO DO CONTRATO (PROCEDIMENTO)\nPaís: Portugal\nNUT III: PT112\nLocalidade: Braga\nDistrito: Braga\nConcelho: Braga\nFreguesia: Todas\nLOCAL DA EXECUÇÃO DO CONTRATO (LOTE)\nIdentificador do Lote: LOT-0001; LOT-0002; LOT-0003; LOT-0004; LOT-0005; LOT-0006; LOT-0007; LOT-0008; LOT-0009; LOT-0010; LOT-0011; LOT-0012; LOT-0013; LOT-0014; LOT-0015; LOT-0016\nPaís: Portugal\nNUT III: PT112\nLocalidade: Braga\nDistrito: Braga\nConcelho: Braga\nFreguesia: Todas\n10 - PRAZO DE EXECUÇÃO DO CONTRATO\nIdentificador do Lote: LOT-0001; LOT-0002; LOT-0003; LOT-0004; LOT-0005; LOT-0006; LOT-0007; LOT-0008; LOT-0009; LOT-0010; LOT-0011; LOT-0012; LOT-0013; LOT-0014; LOT-0015; LOT-0016\nPrazo de execução do contrato: 12 MESES\nPrevisão de renovações: Não\n11 - FUNDOS EU\nIdentificador do Lote: LOT-0001; LOT-0002; LOT-0003; LOT-0004; LOT-0005; LOT-0006; LOT-0007; LOT-0008; LOT-0009; LOT-0010; LOT-0011; LOT-0012; LOT-0013; LOT-0014; LOT-0015; LOT-0016\nTêm fundos EU? Não\n12 - DOCUMENTOS DE HABILITAÇÃO\nHabilitação para o exercício da atividade profissional: Não\n13 - CONDIÇÕES DE APRESENTAÇÃO\nPlataforma eletrónica utilizada pela entidade adjudicante: VORTAL\nURL para Apresentação: https://community.vortal.biz/public/\nAdmissibilidade da apresentação de propostas variantes: Não autorizado\nPrazo para apresentação das propostas: 19-01-2026 17:00\nPrazo durante o qual os concorrentes são obrigados a manter as respetivas propostas: 120 dias a contar do termo do prazo para a apresentação das propostas\nIndicação de Subcontratação na Proposta: Inexistência de indicação de subcontratação\n14 - PRESTAÇÃO DE CAUÇÃO\nPrestação de caução: Não\n15 - FORNECIMENTO DAS PEÇAS DO CONCURSO, APRESENTAÇÃO DE PEDIDOS DE PARTICIPAÇÃO E APRESENTAÇÃO DAS PROPOSTAS\nLink para acesso às peças do concurso (URL): https://community.vortal.biz/Public/public-tender-documents/M3NCc1NkN2Z2bUIzMkl0ekF6dEpqZTl3dUp1aTlhOE4vTTB3VE5VUVJyWWFMeThMSEtxamxPQVpjZ3RXbHloSGpydTUvL1NJdUhxNENFR3NsdHQrN2c9PUkpS3Bq\n20 - OUTROS REQUISITOS\nIdentificador do Lote: LOT-0001; LOT-0002; LOT-0003; LOT-0004; LOT-0005; LOT-0006; LOT-0007; LOT-0008; LOT-0009; LOT-0010; LOT-0011; LOT-0012; LOT-0013; LOT-0014; LOT-0015; LOT-0016\nInformação sobre contratos reservados. Aplica-se a contratos reservados (54º-A)? Não\n21 - CRITÉRIO DE ADJUDICAÇÃO\nO Critério de adjudicação é diferenciado por lote? Sim\nIdentificador do lote: LOT-0001\nMultifator: Não\nMonofator:\nNome: Preço\nO Critério de adjudicação é diferenciado por lote? Sim\nIdentificador do lote: LOT-0002\nMultifator: Não\nMonofator:\nNome: Preço\nO Critério de adjudicação é diferenciado por lote? Sim\nIdentificador do lote: LOT-0003\nMultifator: Não\nMonofator:\nNome: Preço\nO Critério de adjudicação é diferenciado por lote? Sim\nIdentificador do lote: LOT-0004\nMultifator: Não\nMonofator:\nNome: Preço\nO Critério de adjudicação é diferenciado por lote? Sim\nIdentificador do lote: LOT-0005\nMultifator: Não\nMonofator:\nNome: Preço\nO Critério de adjudicação é diferenciado por lote? Sim\nIdentificador do lote: LOT-0006\nMultifator: Não\nMonofator:\nNome: Preço\nO Critério de adjudicação é diferenciado por lote? Sim\nIdentificador do lote: LOT-0007\nMultifator: Sim\nFator: \nNome: Preço\nPonderação: 50%\nSubfatores: Não\nFator: \nNome: Qualidade\nPonderação: 50%\nSubfatores: Não\nO Critério de adjudicação é diferenciado por lote? Sim\nIdentificador do lote: LOT-0008\nMultifator: Sim\nFator: \nNome: Preço\nPonderação: 50%\nSubfatores: Não\nFator: \nNome: Qualidade\nPonderação: 50%\nSubfatores: Não\nO Critério de adjudicação é diferenciado por lote? Sim\nIdentificador do lote: LOT-0009\nMultifator: Não\nMonofator:\nNome: Preço\nO Critério de adjudicação é diferenciado por lote? Sim\nIdentificador do lote: LOT-0010\nMultifator: Sim\nFator: \nNome: Preço\nPonderação: 50%\nSubfatores: Não\nFator: \nNome: Qualidade\nPonderação: 50%\nSubfatores: Não\nO Critério de adjudicação é diferenciado por lote? Sim\nIdentificador do lote: LOT-0011\nMultifator: Sim\nFator: \nNome: Preço\nPonderação: 50%\nSubfatores: Não\nFator: \nNome: Qualidade\nPonderação: 50%\nSubfatores: Não\nO Critério de adjudicação é diferenciado por lote? Sim\nIdentificador do lote: LOT-0012\nMultifator: Sim\nFator: \nNome: Preço\nPonderação: 50%\nSubfatores: Não\nFator: \nNome: Qualidade\nPonderação: 50%\nSubfatores: Não\nO Critério de adjudicação é diferenciado por lote? Sim\nIdentificador do lote: LOT-0013\nMultifator: Sim\nFator: \nNome: Preço\nPonderação: 50%\nSubfatores: Não\nFator: \nNome: Qualidade\nPonderação: 50%\nSubfatores: Não\nO Critério de adjudicação é diferenciado por lote? Sim\nIdentificador do lote: LOT-0014\nMultifator: Sim\nFator: \nNome: Preço\nPonderação: 50%\nSubfatores: Não\nFator: \nNome: Qualidade\nPonderação: 50%\nSubfatores: Não\nO Critério de adjudicação é diferenciado por lote? Sim\nIdentificador do lote: LOT-0015\nMultifator: Sim\nFator: \nNome: Preço\nPonderação: 50%\nSubfatores: Não\nFator: \nNome: Qualidade\nPonderação: 50%\nSubfatores: Não\nO Critério de adjudicação é diferenciado por lote? Sim\nIdentificador do lote: LOT-0016\nMultifator: Não\nMonofator:\nNome: Preço\n24 - CONDIÇÕES DO CONTRATO\nIdentificador do Lote: LOT-0001; LOT-0002; LOT-0003; LOT-0004; LOT-0005; LOT-0006; LOT-0007; LOT-0008; LOT-0009; LOT-0010; LOT-0011; LOT-0012; LOT-0013; LOT-0014; LOT-0015; LOT-0016\nFaturação Eletrónica: Permitido\nObrigação de Subcontratação:\nCódigo da Obrigação de Subcontratação: Não é aplicável nenhuma obrigação de subcontratação.\n25 - COMPRA PÚBLICA ESTRATÉGICA\nCompra Pública Estratégica: Inexistência de contratação pública estratégica\n26 - INFORMAÇÕES ADICIONAIS\nIdentificador do Lote: LOT-0001; LOT-0002; LOT-0003; LOT-0004; LOT-0005; LOT-0006; LOT-0007; LOT-0008; LOT-0009; LOT-0010; LOT-0011; LOT-0012; LOT-0013; LOT-0014; LOT-0015; LOT-0016\nContrato adequado para PME: Sim\nCobertura ACP (Acordo dos Contratos Públicos da Organização Mundial do Comércio): Não\n27 - IDENTIFICAÇÃO E CONTACTOS DO ÓRGÃO DE RECURSOS ADMINISTRATIVOS\nDesignação: Conselho Administração\nEndereço: Sete Fontes- São Victor\nCódigo postal: 4710-243\nLocalidade: Braga\nTelefone: +351 253027000\nFax: +351 253027999\nEndereço eletrónico: hbraga@ulsb.min-saude.pt\n28 - IDENTIFICAÇÃO DO(S) AUTOR(ES) DE ANÚNCIO\nNome: Rafaela Araújo\nCargo: Técnica Superior\n419947147",
    "nipc": "515545180",
    "distrito": "Braga",
    "concelho": "Braga",
    "freguesia": "Todas",
    "site": "https://www.hospitaldebraga.pt/",
    "email": "hospitaldebraga@arsnorte.min-saude.pt",
    "designacao_contrato": "Aquisição de material de ORL.",
    "descricao": "Aquisição de material de ORL.",
    "preco_base": "115.421,00 EUR",
    "prazo_execucao": "12 MESES",
    "prazo_apresentacao_propostas": "19-01-2026 17:00",
    "fundos_eu": "Não",
    "plataforma_eletronica": "VORTAL",
    "url_procedimento": "https://community.vortal.biz/public/",
    "autor_nome": "Rafaela Araújo",
    "autor_cargo": "Técnica Superior"
  },
  {
    "numero_procedimento": "N/A",
    "entidade": "Unidade Local de Saúde de Braga, EPE",
    "link": "https://diariodarepublica.pt/dr/detalhe/contrato-publico/163-995301073",
    "detalhes_completos": "1 - IDENTIFICAÇÃO E CONTACTOS DA ENTIDADE ADJUDICANTE\nDesignação da entidade adjudicante: Unidade Local de Saúde de Braga, EPE\nNIPC: 515545180\nEndereço: Sete Fontes – São Victor  \nCódigo postal: 4710-243\nLocalidade: Braga\nPaís: Portugal\nNUT III: PT112\nDistrito: Braga\nConcelho: Braga\nFreguesia: Todas\nTelefone: 220411150\nEndereço da Entidade (URL): https://www.hospitaldebraga.pt/\nEndereço Eletrónico: hospitaldebraga@arsnorte.min-saude.pt\neDelivery Gateway (URL): https://community.vortal.biz/public/\nFunção da Organização: Adquirente\nNorma jurídica da Entidade Adjudicante: Empresa pública\nÁrea de atividade da Autoridade Adjudicante: Saúde\n2 - JORNAL OFICIAL DA UNIÃO EUROPEIA\nO procedimento a que este anúncio diz respeito também é publicitado no Jornal Oficial da União Europeia? Não\n3 - AVISO\nModelo de Anúncio: Concurso público\nData de Envio do Anúncio: 05-01-2026\n5 - PROCESSO\nTipo de Procedimento: Concurso público\nPreço base do procedimento: Sim\nValor do preço base do procedimento: 90.000,00 EUR\nProcedimento com lotes? Não\n6 - OBJETO DO CONTRATO\nNúmero de referência interna: 5/00220/26\nDesignação do contrato: Aquisição de testes viscoelásticos, com colocação de equipamento em regime de contra-consumo\nDescrição: Aquisição de testes viscoelásticos, com colocação de equipamento em regime de contra-consumo\nTipo de Contrato Principal: Aquisição de Bens Móveis\nTipo de Contrato: Aquisição de Bens Móveis\nClassificação CPV (Vocabulário Comum para os Contratos Públicos)\nObjeto principal\nVocabulário Principal: 33696000\nPreço base s/IVA: 90.000,00 EUR\n7 - INDICAÇÕES ADICIONAIS\nO contrato envolve aquisição conjunta (satisfação de várias entidades)? Não\nO contrato é adjudicado por uma central de compras? Não\n8 - TÉCNICAS\nO concurso destina-se à celebração de um acordo-quadro? Inexistência de acordo-quadro\nÉ utilizado um leilão eletrónico? Não\nÉ adotada uma fase de negociação? Não\nSistema de Aquisição Dinâmico: Inexistência de sistema de aquisição dinâmico\n9 - LOCAL DA EXECUÇÃO DO CONTRATO\nLOCAL DA EXECUÇÃO DO CONTRATO (PROCEDIMENTO)\nPaís: Portugal\nNUT III: PT112\nLocalidade: Braga\nDistrito: Braga\nConcelho: Braga\nFreguesia: Todas\n10 - PRAZO DE EXECUÇÃO DO CONTRATO\nPrazo de execução do contrato: 36 MESES\nPrevisão de renovações: Não\n11 - FUNDOS EU\nTêm fundos EU? Não\n12 - DOCUMENTOS DE HABILITAÇÃO\nHabilitação para o exercício da atividade profissional: Não\n13 - CONDIÇÕES DE APRESENTAÇÃO\nPlataforma eletrónica utilizada pela entidade adjudicante: VORTAL\nURL para Apresentação: https://community.vortal.biz/public/\nAdmissibilidade da apresentação de propostas variantes: Não autorizado\nPrazo para apresentação das propostas: 19-01-2026 17:00\nPrazo durante o qual os concorrentes são obrigados a manter as respetivas propostas: 120 dias a contar do termo do prazo para a apresentação das propostas\nIndicação de Subcontratação na Proposta: Inexistência de indicação de subcontratação\n14 - PRESTAÇÃO DE CAUÇÃO\nPrestação de caução: Não\n15 - FORNECIMENTO DAS PEÇAS DO CONCURSO, APRESENTAÇÃO DE PEDIDOS DE PARTICIPAÇÃO E APRESENTAÇÃO DAS PROPOSTAS\nLink para acesso às peças do concurso (URL): https://community.vortal.biz/Public/public-tender-documents/QXFrKzJOSFVEN1piWTE4d01LRDlxWkNWcjZiWks5dUE0L0JGS3N3TnFXMzRXMmZheCtsdHUrc3VHQ0pYZHRxbmdKdjZ6QWRDdWY2OWhnUExTQ2lpVXc9PVZVJFpl\n20 - OUTROS REQUISITOS\nInformação sobre contratos reservados. Aplica-se a contratos reservados (54º-A)? Não\n21 - CRITÉRIO DE ADJUDICAÇÃO\nMultifator: Sim\nFator: \nNome: Preço\nPonderação: 60%\nSubfatores: Não\nFator: \nNome: Qualidade\nPonderação: 40%\nSubfatores: Não\n24 - CONDIÇÕES DO CONTRATO\nFaturação Eletrónica: Permitido\nObrigação de Subcontratação:\nCódigo da Obrigação de Subcontratação: Não é aplicável nenhuma obrigação de subcontratação.\n25 - COMPRA PÚBLICA ESTRATÉGICA\nCompra Pública Estratégica: Inexistência de contratação pública estratégica\n26 - INFORMAÇÕES ADICIONAIS\nContrato adequado para PME: Sim\nCobertura ACP (Acordo dos Contratos Públicos da Organização Mundial do Comércio): Não\n27 - IDENTIFICAÇÃO E CONTACTOS DO ÓRGÃO DE RECURSOS ADMINISTRATIVOS\nDesignação: Conselho de Administração\nEndereço: Sete Fontes- São Victor\nCódigo postal: 4710-243\nLocalidade: Braga\nTelefone: +351 253027000\nFax: +351 253027999\nEndereço eletrónico: hbraga@ulsb.min-saude.pt\n28 - IDENTIFICAÇÃO DO(S) AUTOR(ES) DE ANÚNCIO\nNome: Cristina Freitas\nCargo: Técnico Superior\n419947145",
    "nipc": "515545180",
    "distrito": "Braga",
    "concelho": "Braga",
    "freguesia": "Todas",
    "site": "https://www.hospitaldebraga.pt/",
    "email": "hospitaldebraga@arsnorte.min-saude.pt",
    "designacao_contrato": "Aquisição de testes viscoelásticos, com colocação de equipamento em regime de contra-consumo",
    "descricao": "Aquisição de testes viscoelásticos, com colocação de equipamento em regime de contra-consumo",
    "preco_base": "90.000,00 EUR",
    "prazo_execucao": "36 MESES",
    "prazo_apresentacao_propostas": "19-01-2026 17:00",
    "fundos_eu": "Não",
    "plataforma_eletronica": "VORTAL",
    "url_procedimento": "https://community.vortal.biz/public/",
    "autor_nome": "Cristina Freitas",
    "autor_cargo": "Técnico Superior"
  },
  {
    "numero_procedimento": "N/A",
    "entidade": "Universidade de Coimbra",
    "link": "https://diariodarepublica.pt/dr/detalhe/contrato-publico/155-996007036",
    "detalhes_completos": "Alteração do Anúncio de procedimento n.º 33305/2025, de 2025-12-23, com o ID 419926555\n1 - IDENTIFICAÇÃO E CONTACTOS DA ENTIDADE ADJUDICANTE\nDesignação da entidade adjudicante: Universidade de Coimbra\nNIPC: 501617582\nServiço/Órgão/Pessoa de contacto: Divisão de Compras\nEndereço: Rua Larga, Edifício FMUC, R/Ch Esquerdo\nCódigo postal: 3004-504\nLocalidade: Coimbra\nPaís: Portugal\nNUT III: PT16E\nDistrito: Coimbra\nConcelho: Coimbra\nFreguesia: Freguesia de Santo António dos Olivais\nTelefone: 239242750\nFax: 239242750\nEndereço da Entidade (URL): www.uc.pt\nEndereço Eletrónico: dca@uc.pt\neDelivery Gateway (URL): https://www.acingov.pt\nFunção da Organização: Adquirente\nNorma jurídica da Entidade Adjudicante: Organismo de direito público\nÁrea de atividade da Autoridade Adjudicante: Serviços públicos das administrações públicas\n2 - JORNAL OFICIAL DA UNIÃO EUROPEIA\nO procedimento a que este anúncio diz respeito também é publicitado no Jornal Oficial da União Europeia? Não\n3 - AVISO\nModelo de Anúncio: Concurso público\nData de Envio do Anúncio: 05-01-2026\n5 - PROCESSO\nTipo de Procedimento: Concurso público\nPreço base do procedimento: Sim\nValor do preço base do procedimento: 745.000,00 EUR\nProcedimento com lotes? Não\n6 - OBJETO DO CONTRATO\nNúmero de referência interna: 25A00058\nDesignação do contrato: 25A00058 - Empreitada para instalação de AVAC nas Torres F e G do Edifício do Departamento de Engenharia Informática da Faculdade de Ciências e Tecnologia da Universidade de Coimbra\nDescrição: 25A00058 - Empreitada para instalação de AVAC nas Torres F e G do Edifício do Departamento de Engenharia Informática da Faculdade de Ciências e Tecnologia da UC.\nTipo de Contrato Principal: Empreitada de Obras Públicas\nTipo de Contrato: Empreitada de Obras Públicas\nClassificação CPV (Vocabulário Comum para os Contratos Públicos)\nObjeto principal\nVocabulário Principal: 45331000\nPreço base s/IVA: 442.808,18 EUR\nObjeto Complementar\nVocabulário Principal: 45453100\nPreço base s/IVA: 302.191,82 EUR\n7 - INDICAÇÕES ADICIONAIS\nO contrato envolve aquisição conjunta (satisfação de várias entidades)? Não\nO contrato é adjudicado por uma central de compras? Não\n8 - TÉCNICAS\nO concurso destina-se à celebração de um acordo-quadro? Inexistência de acordo-quadro\nÉ utilizado um leilão eletrónico? Não\nÉ adotada uma fase de negociação? Não\nSistema de Aquisição Dinâmico: Inexistência de sistema de aquisição dinâmico\n9 - LOCAL DA EXECUÇÃO DO CONTRATO\nLOCAL DA EXECUÇÃO DO CONTRATO (PROCEDIMENTO)\nPaís: Portugal\nNUT III: PT16E\nLocalidade: Freguesia de Santo António dos Olivais\nDistrito: Coimbra\nConcelho: Coimbra\nFreguesia: Freguesia de Santo António dos Olivais\n10 - PRAZO DE EXECUÇÃO DO CONTRATO\nPrazo de execução do contrato: 180 DIAS\nPrevisão de renovações: Não\n11 - FUNDOS EU\nTêm fundos EU? Não\n12 - DOCUMENTOS DE HABILITAÇÃO\nHabilitação para o exercício da atividade profissional: Sim\nTipo: Alvará\nDescrição: 12ª Subcategorias da 4.ª Categoria, na classe correspondente ao valor total da proposta;\n2ª, 5ª e 7.ª Subcategorias da 1.ª Categoria, na classe correspondente ao valor dos trabalhos que lhe respeitam;\n1ª, 4.ª 10ª e 18.º Subcategorias da 4.ª Categoria, na classe correspondente ao valor dos trabalhos que lhe respeitam;\n1.ª e 12.ª subcategoria da 5.º Categoria, na classe correspondente ao valor dos trabalhos que lhe respeitam.\n13 - CONDIÇÕES DE APRESENTAÇÃO\nPlataforma eletrónica utilizada pela entidade adjudicante: ACIN\nURL para Apresentação: https://www.acingov.pt\nAdmissibilidade da apresentação de propostas variantes: Não autorizado\nPrazo para apresentação das propostas: 22-01-2026 23:59\nPrazo durante o qual os concorrentes são obrigados a manter as respetivas propostas: 66 dias a contar do termo do prazo para a apresentação das propostas\nIndicação de Subcontratação na Proposta: Inexistência de indicação de subcontratação\n14 - PRESTAÇÃO DE CAUÇÃO\nPrestação de caução: Sim\nPercentagem: 5%\nDescrição da Garantia Exigida: O valor da caução é de 5.00% do preço contratual.\n15 - FORNECIMENTO DAS PEÇAS DO CONCURSO, APRESENTAÇÃO DE PEDIDOS DE PARTICIPAÇÃO E APRESENTAÇÃO DAS PROPOSTAS\nLink para acesso às peças do concurso (URL): https://www.acingov.pt/acingovprod/2/zonaPublica/zona_publica_c/donwloadProcedurePiece/MTAwNDg4Mg==\n20 - OUTROS REQUISITOS\nInformação sobre contratos reservados. Aplica-se a contratos reservados (54º-A)? Não\n21 - CRITÉRIO DE ADJUDICAÇÃO\nMultifator: Sim\nFator: \nNome: Preço\nPonderação: 55%\nSubfatores: Não\nFator: \nNome: Outros\nOutro Nome: Valia Técnica da Proposta\nPonderação: 40%\nSubfatores: Não\nFator: \nNome: Outros\nOutro Nome: Utilização de materiais reutilizados ou reciclados\nPonderação: 5%\nSubfatores: Não\n24 - CONDIÇÕES DO CONTRATO\nFaturação Eletrónica: Permitido\nObrigação de Subcontratação:\nCódigo da Obrigação de Subcontratação: Não é aplicável nenhuma obrigação de subcontratação.\n25 - COMPRA PÚBLICA ESTRATÉGICA\nCompra Pública Estratégica: Inexistência de contratação pública estratégica\n26 - INFORMAÇÕES ADICIONAIS\nContrato adequado para PME: Sim\nCobertura ACP (Acordo dos Contratos Públicos da Organização Mundial do Comércio): Não\n27 - IDENTIFICAÇÃO E CONTACTOS DO ÓRGÃO DE RECURSOS ADMINISTRATIVOS\nDesignação: Reitor da Universidade de Coimbra\nEndereço: Paço das Escolas\nCódigo postal: 3004-531\nLocalidade: Coimbra\nTelefone: 239859900\nFax: \nEndereço eletrónico: gbreitor@uc.pt\n28 - IDENTIFICAÇÃO DO(S) AUTOR(ES) DE ANÚNCIO\nNome: Professor Doutor Amílcar Celta Falcão Ramos Ferreira\nCargo: Reitor da Universidade de Coimbra\n29 - ALTERAÇÃO\nMotivo da Alteração: Informações atualizadas\nIdentificador da Versão do Anúncio a Alterar: fb421bde-f657-4bba-80ab-c75927c8ccd5-01\nIdentificador das Secções Alteradas do Anúncio Anterior: Condições de Apresentação\nDescrição das Alterações: Modificação do prazo para a apresentação de propostas\nAlteração dos Documentos do Concurso: Não\n419947161",
    "nipc": "501617582",
    "distrito": "Coimbra",
    "concelho": "Coimbra",
    "freguesia": "Freguesia de Santo António dos Olivais",
    "site": "www.uc.pt",
    "email": "dca@uc.pt",
    "designacao_contrato": "25A00058 - Empreitada para instalação de AVAC nas Torres F e G do Edifício do Departamento de Engenharia Informática da Faculdade de Ciências e Tecnologia da Universidade de Coimbra",
    "descricao": "25A00058 - Empreitada para instalação de AVAC nas Torres F e G do Edifício do Departamento de Engenharia Informática da Faculdade de Ciências e Tecnologia da UC.",
    "preco_base": "442.808,18 EUR",
    "prazo_execucao": "180 DIAS",
    "prazo_apresentacao_propostas": "22-01-2026 23:59",
    "fundos_eu": "Não",
    "plataforma_eletronica": "ACIN",
    "url_procedimento": "https://www.acingov.pt",
    "autor_nome": "Professor Doutor Amílcar Celta Falcão Ramos Ferreira",
    "autor_cargo": "Reitor da Universidade de Coimbra"
  },
  {
    "numero_procedimento": "N/A",
    "entidade": "Município de Caminha",
    "link": "https://diariodarepublica.pt/dr/detalhe/contrato-publico/156-996007037",
    "detalhes_completos": "1 - IDENTIFICAÇÃO E CONTACTOS DA ENTIDADE ADJUDICANTE\nDesignação da entidade adjudicante: Município de Caminha\nNIPC: 500843139\nServiço/Órgão/Pessoa de contacto: Gabinete de Candidaturas, Empreitadas e Aprovisionamento\nEndereço: Largo Calouste Gulbenkian\nCódigo postal: 4910-113\nLocalidade: Caminha\nPaís: Portugal\nNUT III: PT111\nDistrito: Viana do Castelo\nConcelho: Caminha\nFreguesia: Todas\nTelefone: 258710300\nFax: 258710319\nEndereço da Entidade (URL): www.cm-caminha.pt\nEndereço Eletrónico: geral@cm-caminha.pt\neDelivery Gateway (URL): https://www.acingov.pt\nFunção da Organização: Adquirente\nNorma jurídica da Entidade Adjudicante: Organismo de direito público\nÁrea de atividade da Autoridade Adjudicante: Serviços públicos das administrações públicas\n\n2 - JORNAL OFICIAL DA UNIÃO EUROPEIA\nO procedimento a que este anúncio diz respeito também é publicitado no Jornal Oficial da União Europeia? Não\n\n3 - AVISO\nModelo de Anúncio: Concurso público\nData de Envio do Anúncio: 05-01-2026\n\n5 - PROCESSO\nTipo de Procedimento: Concurso público\nPreço base do procedimento: Sim\nValor do preço base do procedimento: 143.400,00 EUR\nProcedimento com lotes? Sim\nNº Máx. de Lotes Autorizado: 4\nNúmero máximo de lotes que podem ser adjudicados a um concorrente: 4\n\n6 - OBJETO DO CONTRATO\nNúmero de referência interna: 190/2025\nDesignação do contrato: 190_2025_CP_S_PRESTAÇÃO DE SERVIÇOS DE LIMPEZA\nDescrição: 190_2025_CP_S_PRESTAÇÃO DE SERVIÇOS DE LIMPEZA\nTipo de Contrato Principal: Aquisição de Serviços\nTipo de Contrato: Aquisição de Serviços\nClassificação CPV (Vocabulário Comum para os Contratos Públicos)\nObjeto principal\nVocabulário Principal: 90910000\nPreço base s/IVA: 143.400,00 EUR\nLotes: \nNº: LOT-0001\nDescrição do Lote: Serviço de Limpeza, manutenção e higiene nas Piscinas Municipais - Vila Praia de Âncora\nPreço base s/IVA: 35.000,00 EUR\nClassificação CPV (Vocabulário Comum para os Contratos Públicos)\nObjeto principal\nVocabulário Principal: 90910000\nNº: LOT-0002\nDescrição do Lote: Serviço de limpeza, manutenção e higiene em espaços culturais, nomeadamente Posto de Turismo de Vila Praia de Âncora, Loja de Aprestos - Vila Praia de Âncora, Valadares Teatro Municipal, Cineteatro dos Bombeiros Voluntários de Vila Praia de Âncora, Forte da Lagarteira - Vila Praia de Âncora, Museu Municipal de Caminha, Torre do Relógio, Galeria de Arte Caminhense, e em es...\nPreço base s/IVA: 50.000,00 EUR\nClassificação CPV (Vocabulário Comum para os Contratos Públicos)\nObjeto principal\nVocabulário Principal: 90910000\nNº: LOT-0003\nDescrição do Lote: Serviço de limpeza, manutenção e higiene no edifício administrativo sito no Largo Calouste Gulbenkian, num total de 4 horas diárias e no GAM-Gabinete Apoio ao Munícipe, num total de 1 hora diária.\nPreço base s/IVA: 41.000,00 EUR\nClassificação CPV (Vocabulário Comum para os Contratos Públicos)\nObjeto principal\nVocabulário Principal: 90910000\nNº: LOT-0004\nDescrição do Lote: Serviço de Limpeza do Biblioteca Municipal Caminha\nPreço base s/IVA: 17.400,00 EUR\nClassificação CPV (Vocabulário Comum para os Contratos Públicos)\nObjeto principal\nVocabulário Principal: 90910000\n\n7 - INDICAÇÕES ADICIONAIS\nO contrato envolve aquisição conjunta (satisfação de várias entidades)? Não\nO contrato é adjudicado por uma central de compras? Não\n\n8 - TÉCNICAS\nO concurso destina-se à celebração de um acordo-quadro? Inexistência de acordo-quadro\nÉ utilizado um leilão eletrónico? Não\nÉ adotada uma fase de negociação? Não\nSistema de Aquisição Dinâmico: Inexistência de sistema de aquisição dinâmico\n\n9 - LOCAL DA EXECUÇÃO DO CONTRATO\nLOCAL DA EXECUÇÃO DO CONTRATO (PROCEDIMENTO)\nPaís: Portugal\nNUT III: PT111\nLocalidade: União das Freguesias de Caminha (Matriz) e Vilarelho\nDistrito: Viana do Castelo\nConcelho: Caminha\nFreguesia: União das Freguesias de Caminha (Matriz) e Vilarelho\nPaís: Portugal\nNUT III: PT111\nLocalidade: Freguesia de Vila Praia de Âncora\nDistrito: Viana do Castelo\nConcelho: Caminha\nFreguesia: Freguesia de Vila Praia de Âncora\nLOCAL DA EXECUÇÃO DO CONTRATO (LOTE)\nIdentificador do Lote: LOT-0001; LOT-0002; LOT-0003; LOT-0004\nPaís: Portugal\nNUT III: PT111\nLocalidade: União das Freguesias de Caminha (Matriz) e Vilarelho\nDistrito: Viana do Castelo\nConcelho: Caminha\nFreguesia: União das Freguesias de Caminha (Matriz) e Vilarelho\nIdentificador do Lote: LOT-0001; LOT-0002; LOT-0003; LOT-0004\nPaís: Portugal\nNUT III: PT111\nLocalidade: Freguesia de Vila Praia de Âncora\nDistrito: Viana do Castelo\nConcelho: Caminha\nFreguesia: Freguesia de Vila Praia de Âncora\n\n10 - PRAZO DE EXECUÇÃO DO CONTRATO\nIdentificador do Lote: LOT-0002\nData de Início: 25-02-2026\nData de Fim: 24-02-2028\nPrevisão de renovações: Não\nIdentificador do Lote: LOT-0003\nData de Início: 01-02-2026\nData de Fim: 31-01-2028\nPrevisão de renovações: Não\nIdentificador do Lote: LOT-0001; LOT-0004\nData de Início: 04-04-2026\nData de Fim: 03-04-2028\nPrevisão de renovações: Não\n\n11 - FUNDOS EU\nIdentificador do Lote: LOT-0001; LOT-0002; LOT-0003; LOT-0004\nTêm fundos EU? Não\n\n12 - DOCUMENTOS DE HABILITAÇÃO\nHabilitação para o exercício da atividade profissional: Não\n\n13 - CONDIÇÕES DE APRESENTAÇÃO\nPlataforma eletrónica utilizada pela entidade adjudicante: ACIN\nURL para Apresentação: https://www.acingov.pt\nAdmissibilidade da apresentação de propostas variantes: Não autorizado\nPrazo para apresentação das propostas: 11-01-2026 23:59\nPrazo durante o qual os concorrentes são obrigados a manter as respetivas propostas: 66 dias a contar do termo do prazo para a apresentação das propostas\nIndicação de Subcontratação na Proposta: Inexistência de indicação de subcontratação\n\n14 - PRESTAÇÃO DE CAUÇÃO\nPrestação de caução: Não\n\n15 - FORNECIMENTO DAS PEÇAS DO CONCURSO, APRESENTAÇÃO DE PEDIDOS DE PARTICIPAÇÃO E APRESENTAÇÃO DAS PROPOSTAS\nLink para acesso às peças do concurso (URL): https://www.acingov.pt/acingovprod/2/zonaPublica/zona_publica_c/donwloadProcedurePiece/MTAxMjExMQ==\n\n20 - OUTROS REQUISITOS\nIdentificador do Lote: LOT-0001; LOT-0002; LOT-0003; LOT-0004\nInformação sobre contratos reservados. Aplica-se a contratos reservados (54º-A)? Não\n\n21 - CRITÉRIO DE ADJUDICAÇÃO\nO Critério de adjudicação é diferenciado por lote? Não\nMultifator: Não\nMonofator:\nNome: Preço\n\n24 - CONDIÇÕES DO CONTRATO\nIdentificador do Lote: LOT-0001; LOT-0002; LOT-0003; LOT-0004\nFaturação Eletrónica: Permitido\nObrigação de Subcontratação:\nCódigo da Obrigação de Subcontratação: Não é aplicável nenhuma obrigação de subcontratação.\n\n25 - COMPRA PÚBLICA ESTRATÉGICA\nCompra Pública Estratégica: Inexistência de contratação pública estratégica\n\n26 - INFORMAÇÕES ADICIONAIS\nIdentificador do Lote: LOT-0001; LOT-0002; LOT-0003; LOT-0004\nContrato adequado para PME: Não\nCobertura ACP (Acordo dos Contratos Públicos da Organização Mundial do Comércio): Não\n\n27 - IDENTIFICAÇÃO E CONTACTOS DO ÓRGÃO DE RECURSOS ADMINISTRATIVOS\nDesignação: Tribunal Administrativo e Fiscal de Braga\nEndereço: Rua de Damão, n.º 220\nCódigo postal: 4710-232\nLocalidade: Braga\nTelefone: 253208800\nFax: 213506000\nEndereço eletrónico: braga.taf@tribunais.org.pt\n\n28 - IDENTIFICAÇÃO DO(S) AUTOR(ES) DE ANÚNCIO\nNome: Ana Veloso Dourado Ferreira\nCargo: Chefe da Divisão de Administração e Finanças Municipais\n419945339",
    "nipc": "500843139",
    "distrito": "Viana do Castelo",
    "concelho": "Caminha",
    "freguesia": "Todas",
    "site": "www.cm-caminha.pt",
    "email": "geral@cm-caminha.pt",
    "designacao_contrato": "190_2025_CP_S_PRESTAÇÃO DE SERVIÇOS DE LIMPEZA",
    "descricao": "190_2025_CP_S_PRESTAÇÃO DE SERVIÇOS DE LIMPEZA",
    "preco_base": "143.400,00 EUR",
    "prazo_execucao": null,
    "prazo_apresentacao_propostas": "11-01-2026 23:59",
    "fundos_eu": "Não",
    "plataforma_eletronica": "ACIN",
    "url_procedimento": "https://www.acingov.pt",
    "autor_nome": "Ana Veloso Dourado Ferreira",
    "autor_cargo": "Chefe da Divisão de Administração e Finanças Municipais"
  },
  {
    "numero_procedimento": "N/A",
    "entidade": "Agrupamento de Escolas Pinheiro e Rosa, Faro",
    "link": "https://diariodarepublica.pt/dr/detalhe/contrato-publico/159-996007039",
    "detalhes_completos": "1 - IDENTIFICAÇÃO E CONTACTOS DA ENTIDADE ADJUDICANTE\nDesignação da entidade adjudicante: Agrupamento de Escolas Pinheiro e Rosa, Faro\nNIPC: 600086097\nEndereço: Rua António Gedeão\nCódigo postal: 8005-546\nLocalidade: Faro\nPaís: Portugal\nNUT III: PT150\nDistrito: Faro\nConcelho: Faro\nFreguesia: União das Freguesias de Faro (Sé e São Pedro)\nTelefone: 289894370\nEndereço da Entidade (URL): https://www.aeprosa.pt/\nEndereço Eletrónico: direcao@aeprosa.pt\neDelivery Gateway (URL): https://community.vortal.biz/public/\nFunção da Organização: Adquirente\nNorma jurídica da Entidade Adjudicante: Instituição, órgão ou agência da UE\nÁrea de atividade da Autoridade Adjudicante: Educação\n2 - JORNAL OFICIAL DA UNIÃO EUROPEIA\nO procedimento a que este anúncio diz respeito também é publicitado no Jornal Oficial da União Europeia? Não\n3 - AVISO\nModelo de Anúncio: Concurso público\nData de Envio do Anúncio: 05-01-2026\n5 - PROCESSO\nTipo de Procedimento: Concurso público\nPreço base do procedimento: Sim\nValor do preço base do procedimento: 120.000,00 EUR\nProcedimento com lotes? Não\n6 - OBJETO DO CONTRATO\nNúmero de referência interna: 01/SASE/2026\nDesignação do contrato: Aquisição de Frutas e Legumes\nDescrição: Aquisição de Frutas e Legumes\nTipo de Contrato Principal: Aquisição de Bens Móveis\nTipo de Contrato: Aquisição de Bens Móveis\nClassificação CPV (Vocabulário Comum para os Contratos Públicos)\nObjeto principal\nVocabulário Principal: 15300000\nPreço base s/IVA: 120.000,00 EUR\n7 - INDICAÇÕES ADICIONAIS\nO contrato envolve aquisição conjunta (satisfação de várias entidades)? Não\nO contrato é adjudicado por uma central de compras? Não\n8 - TÉCNICAS\nO concurso destina-se à celebração de um acordo-quadro? Inexistência de acordo-quadro\nÉ utilizado um leilão eletrónico? Não\nÉ adotada uma fase de negociação? Não\nSistema de Aquisição Dinâmico: Inexistência de sistema de aquisição dinâmico\n9 - LOCAL DA EXECUÇÃO DO CONTRATO\nLOCAL DA EXECUÇÃO DO CONTRATO (PROCEDIMENTO)\nPaís: Portugal\nNUT III: PT150\nLocalidade: Faro\nDistrito: Faro\nConcelho: Faro\nFreguesia: Todas\n10 - PRAZO DE EXECUÇÃO DO CONTRATO\nPrazo de execução do contrato: 12 MESES\nPrevisão de renovações: Não\n11 - FUNDOS EU\nTêm fundos EU? Não\n12 - DOCUMENTOS DE HABILITAÇÃO\nHabilitação para o exercício da atividade profissional: Não\n13 - CONDIÇÕES DE APRESENTAÇÃO\nPlataforma eletrónica utilizada pela entidade adjudicante: VORTAL\nURL para Apresentação: https://community.vortal.biz/public/\nAdmissibilidade da apresentação de propostas variantes: Não autorizado\nPrazo para apresentação das propostas: 12-01-2026 17:00\nPrazo durante o qual os concorrentes são obrigados a manter as respetivas propostas: 66 dias a contar do termo do prazo para a apresentação das propostas\nIndicação de Subcontratação na Proposta: Inexistência de indicação de subcontratação\n14 - PRESTAÇÃO DE CAUÇÃO\nPrestação de caução: Não\n15 - FORNECIMENTO DAS PEÇAS DO CONCURSO, APRESENTAÇÃO DE PEDIDOS DE PARTICIPAÇÃO E APRESENTAÇÃO DAS PROPOSTAS\nLink para acesso às peças do concurso (URL): https://community.vortal.biz/Public/public-tender-documents/SEdobnVHRW1xWDRGaVJMMURqNDdPSlN3RXd2L1o2bmZZNlArWWJIZno4MGs1RmNhZFQ1cWVkdDJObHdsUXNRSXRjZHBDOG0zU2YwUFZRZkdoRmdWTHc9PXZMNUsm\n20 - OUTROS REQUISITOS\nInformação sobre contratos reservados. Aplica-se a contratos reservados (54º-A)? Não\n21 - CRITÉRIO DE ADJUDICAÇÃO\nMultifator: Sim\nFator: \nNome: Preço\nPonderação: 90%\nSubfatores: Não\nFator: \nNome: Qualidade\nPonderação: 10%\nSubfatores: Não\n24 - CONDIÇÕES DO CONTRATO\nFaturação Eletrónica: Permitido\nObrigação de Subcontratação:\nCódigo da Obrigação de Subcontratação: Não é aplicável nenhuma obrigação de subcontratação.\n25 - COMPRA PÚBLICA ESTRATÉGICA\nCompra Pública Estratégica: Inexistência de contratação pública estratégica\n26 - INFORMAÇÕES ADICIONAIS\nContrato adequado para PME: Sim\nCobertura ACP (Acordo dos Contratos Públicos da Organização Mundial do Comércio): Não\n27 - IDENTIFICAÇÃO E CONTACTOS DO ÓRGÃO DE RECURSOS ADMINISTRATIVOS\nDesignação: Conselho Administrativo do Agrupamento Pinheiro e Rosa\nEndereço: Rua António Gedeão n.º 1\nCódigo postal: 8005-546\nLocalidade: Faro\nTelefone: +351 289894370\nFax: +351 289894379\nEndereço eletrónico: direcao@aeprosa.pt\n28 - IDENTIFICAÇÃO DO(S) AUTOR(ES) DE ANÚNCIO\nNome: Francisco Manuel Conde Soares\nCargo: Diretor\n419947198",
    "nipc": "600086097",
    "distrito": "Faro",
    "concelho": "Faro",
    "freguesia": "União das Freguesias de Faro (Sé e São Pedro)",
    "site": "https://www.aeprosa.pt/",
    "email": "direcao@aeprosa.pt",
    "designacao_contrato": "Aquisição de Frutas e Legumes",
    "descricao": "Aquisição de Frutas e Legumes",
    "preco_base": "120.000,00 EUR",
    "prazo_execucao": "12 MESES",
    "prazo_apresentacao_propostas": "12-01-2026 17:00",
    "fundos_eu": "Não",
    "plataforma_eletronica": "VORTAL",
    "url_procedimento": "https://community.vortal.biz/public/",
    "autor_nome": "Francisco Manuel Conde Soares",
    "autor_cargo": "Diretor"
  },
  {
    "numero_procedimento": "N/A",
    "entidade": "Penafiel Verde, EM",
    "link": "https://diariodarepublica.pt/dr/detalhe/contrato-publico/160-996007041",
    "detalhes_completos": "1 - IDENTIFICAÇÃO E CONTACTOS DA ENTIDADE ADJUDICANTE\nDesignação da entidade adjudicante: Penafiel Verde, EM\nNIPC: 507700651\nEndereço: Rua Abílio Miranda\nCódigo postal: 4560-501\nLocalidade: Porto\nPaís: Portugal\nNUT III: PT11C\nDistrito: Porto\nConcelho: Penafiel\nFreguesia: Freguesia de Penafiel\nTelefone: 255710130\nFax: 255710130\nEndereço da Entidade (URL): https://www.penafielverde.pt/\nEndereço Eletrónico: contratacaopublica@penafielverde.pt\neDelivery Gateway (URL): https://community.vortal.biz/public/\nFunção da Organização: Adquirente\nNorma jurídica da Entidade Adjudicante: Empresa pública\nÁrea de atividade da Entidade Adjudicante: Atividades relacionadas com a água\n2 - JORNAL OFICIAL DA UNIÃO EUROPEIA\nO procedimento a que este anúncio diz respeito também é publicitado no Jornal Oficial da União Europeia? Não\n3 - AVISO\nModelo de Anúncio: Concurso público\nData de Envio do Anúncio: 05-01-2026\n5 - PROCESSO\nTipo de Procedimento: Concurso público\nPreço base do procedimento: Sim\nValor do preço base do procedimento: 13.238,00 EUR\nProcedimento com lotes? Não\n6 - OBJETO DO CONTRATO\nNúmero de referência interna: 2025-71\nDesignação do contrato: AQUISIÇÃO DE TINAS DE RETENÇÃO E KIT'S DE EMERGÊNCIA PARA DERRAMES DE PRODUTOS QUIMICOS\nDescrição: AQUISIÇÃO DE TINAS DE RETENÇÃO E KIT'S DE EMERGÊNCIA PARA DERRAMES DE PRODUTOS QUIMICOS\nTipo de Contrato Principal: Aquisição de Bens Móveis\nTipo de Contrato: Aquisição de Bens Móveis\nClassificação CPV (Vocabulário Comum para os Contratos Públicos)\nObjeto principal\nVocabulário Principal: 44421722\nPreço base s/IVA: 13.238,00 EUR\n7 - INDICAÇÕES ADICIONAIS\nO contrato envolve aquisição conjunta (satisfação de várias entidades)? Não\nO contrato é adjudicado por uma central de compras? Não\n8 - TÉCNICAS\nO concurso destina-se à celebração de um acordo-quadro? Inexistência de acordo-quadro\nÉ utilizado um leilão eletrónico? Não\nÉ adotada uma fase de negociação? Não\nSistema de Aquisição Dinâmico: Inexistência de sistema de aquisição dinâmico\n9 - LOCAL DA EXECUÇÃO DO CONTRATO\nLOCAL DA EXECUÇÃO DO CONTRATO (PROCEDIMENTO)\nPaís: Portugal\nNUT III: PT11C\nLocalidade: Porto\nDistrito: Porto\nConcelho: Penafiel\nFreguesia: Freguesia de Penafiel\n10 - PRAZO DE EXECUÇÃO DO CONTRATO\nPrazo de execução do contrato: 6 MESES\nPrevisão de renovações: Não\n11 - FUNDOS EU\nTêm fundos EU? Não\n12 - DOCUMENTOS DE HABILITAÇÃO\nHabilitação para o exercício da atividade profissional: Não\n13 - CONDIÇÕES DE APRESENTAÇÃO\nPlataforma eletrónica utilizada pela entidade adjudicante: VORTAL\nURL para Apresentação: https://community.vortal.biz/public/\nAdmissibilidade da apresentação de propostas variantes: Não autorizado\nPrazo para apresentação das propostas: 19-01-2026 23:59\nPrazo durante o qual os concorrentes são obrigados a manter as respetivas propostas: 90 dias a contar do termo do prazo para a apresentação das propostas\nIndicação de Subcontratação na Proposta: Inexistência de indicação de subcontratação\n14 - PRESTAÇÃO DE CAUÇÃO\nPrestação de caução: Não\n15 - FORNECIMENTO DAS PEÇAS DO CONCURSO, APRESENTAÇÃO DE PEDIDOS DE PARTICIPAÇÃO E APRESENTAÇÃO DAS PROPOSTAS\nLink para acesso às peças do concurso (URL): https://community.vortal.biz/Public/public-tender-documents/bmFNeFRSTk1lZnhodWQ0N1dwMEZhSE95Z3hvYURUOEFjeHBOR050UG1kTm4xK3lrUklqUWk2UEJXYWRBSUZKODJ0cGlHeTlEZUNDZFlLcGRKNE55MVE9PShJT1VU\n20 - OUTROS REQUISITOS\nInformação sobre contratos reservados. Aplica-se a contratos reservados (54º-A)? Não\n21 - CRITÉRIO DE ADJUDICAÇÃO\nMultifator: Não\nMonofator:\nNome: Preço\n24 - CONDIÇÕES DO CONTRATO\nFaturação Eletrónica: Permitido\nObrigação de Subcontratação:\nCódigo da Obrigação de Subcontratação: Não é aplicável nenhuma obrigação de subcontratação.\n25 - COMPRA PÚBLICA ESTRATÉGICA\nCompra Pública Estratégica: Inexistência de contratação pública estratégica\n26 - INFORMAÇÕES ADICIONAIS\nContrato adequado para PME: Sim\nCobertura ACP (Acordo dos Contratos Públicos da Organização Mundial do Comércio): Não\n27 - IDENTIFICAÇÃO E CONTACTOS DO ÓRGÃO DE RECURSOS ADMINISTRATIVOS\nDesignação: Conselho de Administração\nEndereço: Rua Abílio Miranda\nCódigo postal: 4560-501\nLocalidade: Penafiel\nTelefone: +351 255710130\nFax: +351 255710130\nEndereço eletrónico: contratacaopublica@penafielverde.pt\n28 - IDENTIFICAÇÃO DO(S) AUTOR(ES) DE ANÚNCIO\nNome: Fátima Sousa\nCargo: Assistente Técnico\n419947148",
    "nipc": "507700651",
    "distrito": "Porto",
    "concelho": "Penafiel",
    "freguesia": "Freguesia de Penafiel",
    "site": "https://www.penafielverde.pt/",
    "email": "contratacaopublica@penafielverde.pt",
    "designacao_contrato": "AQUISIÇÃO DE TINAS DE RETENÇÃO E KIT'S DE EMERGÊNCIA PARA DERRAMES DE PRODUTOS QUIMICOS",
    "descricao": "AQUISIÇÃO DE TINAS DE RETENÇÃO E KIT'S DE EMERGÊNCIA PARA DERRAMES DE PRODUTOS QUIMICOS",
    "preco_base": "13.238,00 EUR",
    "prazo_execucao": "6 MESES",
    "prazo_apresentacao_propostas": "19-01-2026 23:59",
    "fundos_eu": "Não",
    "plataforma_eletronica": "VORTAL",
    "url_procedimento": "https://community.vortal.biz/public/",
    "autor_nome": "Fátima Sousa",
    "autor_cargo": "Assistente Técnico"
  },
  {
    "numero_procedimento": "N/A",
    "entidade": "Unidade Local de Saúde de Braga, EPE",
    "link": "https://diariodarepublica.pt/dr/detalhe/contrato-publico/162-996007043",
    "detalhes_completos": "1 - IDENTIFICAÇÃO E CONTACTOS DA ENTIDADE ADJUDICANTE\nDesignação da entidade adjudicante: Unidade Local de Saúde de Braga, EPE\nNIPC: 515545180\nEndereço: Sete Fontes – São Victor  \nCódigo postal: 4710-243\nLocalidade: Braga\nPaís: Portugal\nNUT III: PT112\nDistrito: Braga\nConcelho: Braga\nFreguesia: Todas\nTelefone: 220411150\nEndereço da Entidade (URL): https://www.hospitaldebraga.pt/\nEndereço Eletrónico: hospitaldebraga@arsnorte.min-saude.pt\neDelivery Gateway (URL): https://community.vortal.biz/public/\nFunção da Organização: Adquirente\nNorma jurídica da Entidade Adjudicante: Empresa pública\nÁrea de atividade da Autoridade Adjudicante: Saúde\n2 - JORNAL OFICIAL DA UNIÃO EUROPEIA\nO procedimento a que este anúncio diz respeito também é publicitado no Jornal Oficial da União Europeia? Não\n3 - AVISO\nModelo de Anúncio: Concurso público\nData de Envio do Anúncio: 05-01-2026\n5 - PROCESSO\nTipo de Procedimento: Concurso público\nPreço base do procedimento: Sim\nValor do preço base do procedimento: 170.387,44 EUR\nProcedimento com lotes? Sim\nNº Máx. de Lotes Autorizado: 5\nNúmero máximo de lotes que podem ser adjudicados a um concorrente: 5\n6 - OBJETO DO CONTRATO\nNúmero de referência interna: 5/00006/26\nDesignação do contrato: Aquisição de Material de Colheita de Amostras Biológicas\nDescrição: Aquisição de Material de Colheita de Amostras Biológicas\nTipo de Contrato Principal: Aquisição de Bens Móveis\nTipo de Contrato: Aquisição de Bens Móveis\nClassificação CPV (Vocabulário Comum para os Contratos Públicos)\nObjeto principal\nVocabulário Principal: 33140000\nPreço base s/IVA: 170.387,44 EUR\nLotes: \nNº: LOT-0001\nDescrição do Lote: Lote 1\nPreço base s/IVA: 121.924,57 EUR\nClassificação CPV (Vocabulário Comum para os Contratos Públicos)\nObjeto principal\nVocabulário Principal: 33140000\nNº: LOT-0002\nDescrição do Lote: Lote 2\nPreço base s/IVA: 1.355,00 EUR\nClassificação CPV (Vocabulário Comum para os Contratos Públicos)\nObjeto principal\nVocabulário Principal: 33140000\nNº: LOT-0003\nDescrição do Lote: Lote 3\nPreço base s/IVA: 32.413,60 EUR\nClassificação CPV (Vocabulário Comum para os Contratos Públicos)\nObjeto principal\nVocabulário Principal: 33140000\nNº: LOT-0004\nDescrição do Lote: Lote 4\nPreço base s/IVA: 865,00 EUR\nClassificação CPV (Vocabulário Comum para os Contratos Públicos)\nObjeto principal\nVocabulário Principal: 33140000\nNº: LOT-0005\nDescrição do Lote: Lote 5\nPreço base s/IVA: 13.829,27 EUR\nClassificação CPV (Vocabulário Comum para os Contratos Públicos)\nObjeto principal\nVocabulário Principal: 33140000\n7 - INDICAÇÕES ADICIONAIS\nO contrato envolve aquisição conjunta (satisfação de várias entidades)? Não\nO contrato é adjudicado por uma central de compras? Não\n8 - TÉCNICAS\nO concurso destina-se à celebração de um acordo-quadro? Inexistência de acordo-quadro\nÉ utilizado um leilão eletrónico? Não\nÉ adotada uma fase de negociação? Não\nSistema de Aquisição Dinâmico: Inexistência de sistema de aquisição dinâmico\n9 - LOCAL DA EXECUÇÃO DO CONTRATO\nLOCAL DA EXECUÇÃO DO CONTRATO (PROCEDIMENTO)\nPaís: Portugal\nNUT III: PT112\nLocalidade: Braga\nDistrito: Braga\nConcelho: Braga\nFreguesia: Todas\nLOCAL DA EXECUÇÃO DO CONTRATO (LOTE)\nIdentificador do Lote: LOT-0001; LOT-0002; LOT-0003; LOT-0004; LOT-0005\nPaís: Portugal\nNUT III: PT112\nLocalidade: Braga\nDistrito: Braga\nConcelho: Braga\nFreguesia: Todas\n10 - PRAZO DE EXECUÇÃO DO CONTRATO\nIdentificador do Lote: LOT-0001; LOT-0002; LOT-0003; LOT-0004; LOT-0005\nPrazo de execução do contrato: 1 ANOS\nPrevisão de renovações: Não\n11 - FUNDOS EU\nIdentificador do Lote: LOT-0001; LOT-0002; LOT-0003; LOT-0004; LOT-0005\nTêm fundos EU? Não\n12 - DOCUMENTOS DE HABILITAÇÃO\nHabilitação para o exercício da atividade profissional: Não\n13 - CONDIÇÕES DE APRESENTAÇÃO\nPlataforma eletrónica utilizada pela entidade adjudicante: VORTAL\nURL para Apresentação: https://community.vortal.biz/public/\nAdmissibilidade da apresentação de propostas variantes: Não autorizado\nPrazo para apresentação das propostas: 19-01-2026 17:00\nPrazo durante o qual os concorrentes são obrigados a manter as respetivas propostas: 120 dias a contar do termo do prazo para a apresentação das propostas\nIndicação de Subcontratação na Proposta: Inexistência de indicação de subcontratação\n14 - PRESTAÇÃO DE CAUÇÃO\nPrestação de caução: Não\n15 - FORNECIMENTO DAS PEÇAS DO CONCURSO, APRESENTAÇÃO DE PEDIDOS DE PARTICIPAÇÃO E APRESENTAÇÃO DAS PROPOSTAS\nLink para acesso às peças do concurso (URL): https://community.vortal.biz/Public/public-tender-documents/RXJrN0dSMjZxU1JNVEhhUk9TVmxRNW9PK29pN2V4WVFUaTRTbUZQN2htcEFqUWRHaUNxeTMzRjFKeWYzbEtSc2RuRW81ZEVkei9jUkNtSDlYOHlpSmc9PUlkZUF2\n20 - OUTROS REQUISITOS\nIdentificador do Lote: LOT-0001; LOT-0002; LOT-0003; LOT-0004; LOT-0005\nInformação sobre contratos reservados. Aplica-se a contratos reservados (54º-A)? Não\n21 - CRITÉRIO DE ADJUDICAÇÃO\nO Critério de adjudicação é diferenciado por lote? Não\nMultifator: Sim\nFator: \nNome: Preço\nPonderação: 60%\nSubfatores: Não\nFator: \nNome: Qualidade\nPonderação: 40%\nSubfatores: Não\n24 - CONDIÇÕES DO CONTRATO\nIdentificador do Lote: LOT-0001; LOT-0002; LOT-0003; LOT-0004; LOT-0005\nFaturação Eletrónica: Permitido\nObrigação de Subcontratação:\nCódigo da Obrigação de Subcontratação: Não é aplicável nenhuma obrigação de subcontratação.\n25 - COMPRA PÚBLICA ESTRATÉGICA\nCompra Pública Estratégica: Inexistência de contratação pública estratégica\n26 - INFORMAÇÕES ADICIONAIS\nIdentificador do Lote: LOT-0001; LOT-0002; LOT-0003; LOT-0004; LOT-0005\nContrato adequado para PME: Sim\nCobertura ACP (Acordo dos Contratos Públicos da Organização Mundial do Comércio): Não\n27 - IDENTIFICAÇÃO E CONTACTOS DO ÓRGÃO DE RECURSOS ADMINISTRATIVOS\nDesignação: Conselho de Administração\nEndereço: Sete Fontes- São Victor\nCódigo postal: 4710-243\nLocalidade: Braga\nTelefone: +351 253027000\nFax: +351 253027999\nEndereço eletrónico: hbraga@ulsb.min-saude.pt\n28 - IDENTIFICAÇÃO DO(S) AUTOR(ES) DE ANÚNCIO\nNome: Cristina Freitas\nCargo: Técnico Superior\n419947157",
    "nipc": "515545180",
    "distrito": "Braga",
    "concelho": "Braga",
    "freguesia": "Todas",
    "site": "https://www.hospitaldebraga.pt/",
    "email": "hospitaldebraga@arsnorte.min-saude.pt",
    "designacao_contrato": "Aquisição de Material de Colheita de Amostras Biológicas",
    "descricao": "Aquisição de Material de Colheita de Amostras Biológicas",
    "preco_base": "170.387,44 EUR",
    "prazo_execucao": "1 ANOS",
    "prazo_apresentacao_propostas": "19-01-2026 17:00",
    "fundos_eu": "Não",
    "plataforma_eletronica": "VORTAL",
    "url_procedimento": "https://community.vortal.biz/public/",
    "autor_nome": "Cristina Freitas",
    "autor_cargo": "Técnico Superior"
  },
  {
    "numero_procedimento": "N/A",
    "entidade": "Unidade Local de Saúde de Santo António, EPE",
    "link": "https://diariodarepublica.pt/dr/detalhe/contrato-publico/167-996007046",
    "detalhes_completos": "1 - IDENTIFICAÇÃO E CONTACTOS DA ENTIDADE ADJUDICANTE\nDesignação da entidade adjudicante: Unidade Local de Saúde de Santo António, EPE\nNIPC: 517392259\nEndereço: Largo Prof. Abel Salazar\nCódigo postal: 4099-001\nLocalidade: Área Metropolitana do Porto\nPaís: Portugal\nNUT III: PT11A\nDistrito: Porto\nConcelho: Porto\nFreguesia: Todas\nTelefone: 222077500\nFax: 223320318\nEndereço da Entidade (URL): www.hgsa.pt\nEndereço Eletrónico: helpdesk.b-on@hgsa.min-saude.pt\neDelivery Gateway (URL): https://community.vortal.biz/public/\nFunção da Organização: Adquirente\nNorma jurídica da Entidade Adjudicante: Organismo de direito público\nÁrea de atividade da Autoridade Adjudicante: Saúde\n2 - JORNAL OFICIAL DA UNIÃO EUROPEIA\nO procedimento a que este anúncio diz respeito também é publicitado no Jornal Oficial da União Europeia? Não\n3 - AVISO\nModelo de Anúncio: Concurso público\nData de Envio do Anúncio: 05-01-2026\n5 - PROCESSO\nTipo de Procedimento: Concurso público\nPreço base do procedimento: Sim\nValor do preço base do procedimento: 38.000,00 EUR\nProcedimento com lotes? Não\n6 - OBJETO DO CONTRATO\nNúmero de referência interna: CP/1220/2025\nDesignação do contrato: Concurso Público nº 1220/2025: Aquisição de 20 (vinte) Seringas TCI para o Bloco Operatório da ULS de Santo António, EPE\nDescrição: Concurso Público nº 1220/2025: Aquisição de 20 (vinte) Seringas TCI para o Bloco Operatório da ULS de Santo António, EPE\nTipo de Contrato Principal: Aquisição de Bens Móveis\nTipo de Contrato: Aquisição de Bens Móveis\nClassificação CPV (Vocabulário Comum para os Contratos Públicos)\nObjeto principal\nVocabulário Principal: 33162100\nPreço base s/IVA: 38.000,00 EUR\n7 - INDICAÇÕES ADICIONAIS\nO contrato envolve aquisição conjunta (satisfação de várias entidades)? Não\nO contrato é adjudicado por uma central de compras? Não\n8 - TÉCNICAS\nO concurso destina-se à celebração de um acordo-quadro? Inexistência de acordo-quadro\nÉ utilizado um leilão eletrónico? Não\nÉ adotada uma fase de negociação? Sim\nSistema de Aquisição Dinâmico: Inexistência de sistema de aquisição dinâmico\n9 - LOCAL DA EXECUÇÃO DO CONTRATO\nLOCAL DA EXECUÇÃO DO CONTRATO (PROCEDIMENTO)\nPaís: Portugal\nNUT III: PT11A\nLocalidade: Área Metropolitana do Porto\nDistrito: Porto\nConcelho: Porto\nFreguesia: Todas\n10 - PRAZO DE EXECUÇÃO DO CONTRATO\nPrazo de execução do contrato: 30 DIAS\nPrevisão de renovações: Não\n11 - FUNDOS EU\nTêm fundos EU? Não\n12 - DOCUMENTOS DE HABILITAÇÃO\nHabilitação para o exercício da atividade profissional: Não\n13 - CONDIÇÕES DE APRESENTAÇÃO\nPlataforma eletrónica utilizada pela entidade adjudicante: VORTAL\nURL para Apresentação: https://community.vortal.biz/public/\nAdmissibilidade da apresentação de propostas variantes: Não autorizado\nPrazo para apresentação das propostas: 19-01-2026 23:59\nPrazo durante o qual os concorrentes são obrigados a manter as respetivas propostas: 120 dias a contar do termo do prazo para a apresentação das propostas\nIndicação de Subcontratação na Proposta: Inexistência de indicação de subcontratação\n14 - PRESTAÇÃO DE CAUÇÃO\nPrestação de caução: Não\n15 - FORNECIMENTO DAS PEÇAS DO CONCURSO, APRESENTAÇÃO DE PEDIDOS DE PARTICIPAÇÃO E APRESENTAÇÃO DAS PROPOSTAS\nLink para acesso às peças do concurso (URL): https://community.vortal.biz/Public/public-tender-documents/YmxQZTI0L0JvZ0pBQWpqY3V4SlcrL1dDVk12WVJveXdNVXE0N2J5cFg1SitLeGd4T00vRzRuRGZLcE9xUnJaRzJFQUhmenR6WlFmMzkrTlJDRVZVbGc9PSUrbzFS\n20 - OUTROS REQUISITOS\nInformação sobre contratos reservados. Aplica-se a contratos reservados (54º-A)? Não\n21 - CRITÉRIO DE ADJUDICAÇÃO\nMultifator: Sim\nFator: \nNome: Preço\nPonderação: 55%\nSubfatores: Não\nFator: \nNome: Qualidade\nPonderação: 35%\nSubfatores: Não\nFator: \nNome: Outros\nOutro Nome: Duração Garantia\nPonderação: 5%\nSubfatores: Não\nFator: \nNome: Outros\nOutro Nome: Prazo de Entrega\nPonderação: 5%\nSubfatores: Não\n24 - CONDIÇÕES DO CONTRATO\nFaturação Eletrónica: Permitido\nObrigação de Subcontratação:\nCódigo da Obrigação de Subcontratação: Não é aplicável nenhuma obrigação de subcontratação.\n25 - COMPRA PÚBLICA ESTRATÉGICA\nCompra Pública Estratégica: Inexistência de contratação pública estratégica\n26 - INFORMAÇÕES ADICIONAIS\nContrato adequado para PME: Sim\nCobertura ACP (Acordo dos Contratos Públicos da Organização Mundial do Comércio): Não\n27 - IDENTIFICAÇÃO E CONTACTOS DO ÓRGÃO DE RECURSOS ADMINISTRATIVOS\nDesignação: Conselho de Administração da ULS Santo Antonio\nEndereço: Largo Professor Abel Salazar\nCódigo postal: 4099-001\nLocalidade: Porto\nTelefone: +351 222077529\nFax: +351 223320318\nEndereço eletrónico: Ricardoribeiro.aprov@ulssa.min-saude.pt\n28 - IDENTIFICAÇÃO DO(S) AUTOR(ES) DE ANÚNCIO\nNome: Ricardo Ribeiro\nCargo: Assistente Técnico\n419947125",
    "nipc": "517392259",
    "distrito": "Porto",
    "concelho": "Porto",
    "freguesia": "Todas",
    "site": "www.hgsa.pt",
    "email": "helpdesk.b-on@hgsa.min-saude.pt",
    "designacao_contrato": "Concurso Público nº 1220/2025: Aquisição de 20 (vinte) Seringas TCI para o Bloco Operatório da ULS de Santo António, EPE",
    "descricao": "Concurso Público nº 1220/2025: Aquisição de 20 (vinte) Seringas TCI para o Bloco Operatório da ULS de Santo António, EPE",
    "preco_base": "38.000,00 EUR",
    "prazo_execucao": "30 DIAS",
    "prazo_apresentacao_propostas": "19-01-2026 23:59",
    "fundos_eu": "Não",
    "plataforma_eletronica": "VORTAL",
    "url_procedimento": "https://community.vortal.biz/public/",
    "autor_nome": "Ricardo Ribeiro",
    "autor_cargo": "Assistente Técnico"
  },
  {
    "numero_procedimento": "N/A",
    "entidade": "Unidade Local de Saúde de Santo António, EPE",
    "link": "https://diariodarepublica.pt/dr/detalhe/contrato-publico/168-996007047",
    "detalhes_completos": "1 - IDENTIFICAÇÃO E CONTACTOS DA ENTIDADE ADJUDICANTE\nDesignação da entidade adjudicante: Unidade Local de Saúde de Santo António, EPE\nNIPC: 517392259\nEndereço: Largo Prof. Abel Salazar\nCódigo postal: 4099-001\nLocalidade: Área Metropolitana do Porto\nPaís: Portugal\nNUT III: PT11A\nDistrito: Porto\nConcelho: Porto\nFreguesia: Todas\nTelefone: 222077500\nFax: 223320318\nEndereço da Entidade (URL): www.hgsa.pt\nEndereço Eletrónico: helpdesk.b-on@hgsa.min-saude.pt\neDelivery Gateway (URL): https://community.vortal.biz/public/\nFunção da Organização: Adquirente\nNorma jurídica da Entidade Adjudicante: Organismo de direito público\nÁrea de atividade da Autoridade Adjudicante: Saúde\n2 - JORNAL OFICIAL DA UNIÃO EUROPEIA\nO procedimento a que este anúncio diz respeito também é publicitado no Jornal Oficial da União Europeia? Não\n3 - AVISO\nModelo de Anúncio: Concurso público\nData de Envio do Anúncio: 05-01-2026\n5 - PROCESSO\nTipo de Procedimento: Concurso público\nPreço base do procedimento: Sim\nValor do preço base do procedimento: 17.886,18 EUR\nProcedimento com lotes? Não\n6 - OBJETO DO CONTRATO\nNúmero de referência interna: CP/1500/2025\nDesignação do contrato: Concurso Público nº 1500/2025: Aquisição de Capacete de EEG de 256 Canais para o Serviço de Neurofisiologia da ULS de Santo António, EPE\nDescrição: Concurso Público nº 1500/2025: Aquisição de Capacete de EEG de 256 Canais para o Serviço de Neurofisiologia da ULS de Santo António, EPE\nTipo de Contrato Principal: Aquisição de Bens Móveis\nTipo de Contrato: Aquisição de Bens Móveis\nClassificação CPV (Vocabulário Comum para os Contratos Públicos)\nObjeto principal\nVocabulário Principal: 33100000\nPreço base s/IVA: 17.886,18 EUR\n7 - INDICAÇÕES ADICIONAIS\nO contrato envolve aquisição conjunta (satisfação de várias entidades)? Não\nO contrato é adjudicado por uma central de compras? Não\n8 - TÉCNICAS\nO concurso destina-se à celebração de um acordo-quadro? Inexistência de acordo-quadro\nÉ utilizado um leilão eletrónico? Não\nÉ adotada uma fase de negociação? Sim\nSistema de Aquisição Dinâmico: Inexistência de sistema de aquisição dinâmico\n9 - LOCAL DA EXECUÇÃO DO CONTRATO\nLOCAL DA EXECUÇÃO DO CONTRATO (PROCEDIMENTO)\nPaís: Portugal\nNUT III: PT11A\nLocalidade: Área Metropolitana do Porto\nDistrito: Porto\nConcelho: Porto\nFreguesia: Todas\n10 - PRAZO DE EXECUÇÃO DO CONTRATO\nPrazo de execução do contrato: 60 DIAS\nPrevisão de renovações: Não\n11 - FUNDOS EU\nTêm fundos EU? Não\n12 - DOCUMENTOS DE HABILITAÇÃO\nHabilitação para o exercício da atividade profissional: Não\n13 - CONDIÇÕES DE APRESENTAÇÃO\nPlataforma eletrónica utilizada pela entidade adjudicante: VORTAL\nURL para Apresentação: https://community.vortal.biz/public/\nAdmissibilidade da apresentação de propostas variantes: Não autorizado\nPrazo para apresentação das propostas: 19-01-2026 23:59\nPrazo durante o qual os concorrentes são obrigados a manter as respetivas propostas: 120 dias a contar do termo do prazo para a apresentação das propostas\nIndicação de Subcontratação na Proposta: Inexistência de indicação de subcontratação\n14 - PRESTAÇÃO DE CAUÇÃO\nPrestação de caução: Não\n15 - FORNECIMENTO DAS PEÇAS DO CONCURSO, APRESENTAÇÃO DE PEDIDOS DE PARTICIPAÇÃO E APRESENTAÇÃO DAS PROPOSTAS\nLink para acesso às peças do concurso (URL): https://community.vortal.biz/Public/public-tender-documents/Wko5eGl3QWZKWkNmbTFsMWZwS3ZneHZWL2svYnd5MUJ0UzRLdWRjb3YzWTVPcnRCbFBuYlc4MVY3VXVDeURkckgwS3RJcy9rTnNZdUVGRlRzOFNWMGc9PWZHZURA\n20 - OUTROS REQUISITOS\nInformação sobre contratos reservados. Aplica-se a contratos reservados (54º-A)? Não\n21 - CRITÉRIO DE ADJUDICAÇÃO\nMultifator: Não\nMonofator:\nNome: Preço\n24 - CONDIÇÕES DO CONTRATO\nFaturação Eletrónica: Permitido\nObrigação de Subcontratação:\nCódigo da Obrigação de Subcontratação: Não é aplicável nenhuma obrigação de subcontratação.\n25 - COMPRA PÚBLICA ESTRATÉGICA\nCompra Pública Estratégica: Inexistência de contratação pública estratégica\n26 - INFORMAÇÕES ADICIONAIS\nContrato adequado para PME: Sim\nCobertura ACP (Acordo dos Contratos Públicos da Organização Mundial do Comércio): Não\n27 - IDENTIFICAÇÃO E CONTACTOS DO ÓRGÃO DE RECURSOS ADMINISTRATIVOS\nDesignação: Conselho de Administração da ULS Santo Antonio\nEndereço: Largo Professor Abel Salazar\nCódigo postal: 4099-001\nLocalidade: Porto\nTelefone: +351 222077529\nFax: +351 223320318\nEndereço eletrónico: Ricardoribeiro.aprov@ulssa.min-saude.pt\n28 - IDENTIFICAÇÃO DO(S) AUTOR(ES) DE ANÚNCIO\nNome: Ricardo Ribeiro\nCargo: Assistente Técnico\n419947134",
    "nipc": "517392259",
    "distrito": "Porto",
    "concelho": "Porto",
    "freguesia": "Todas",
    "site": "www.hgsa.pt",
    "email": "helpdesk.b-on@hgsa.min-saude.pt",
    "designacao_contrato": "Concurso Público nº 1500/2025: Aquisição de Capacete de EEG de 256 Canais para o Serviço de Neurofisiologia da ULS de Santo António, EPE",
    "descricao": "Concurso Público nº 1500/2025: Aquisição de Capacete de EEG de 256 Canais para o Serviço de Neurofisiologia da ULS de Santo António, EPE",
    "preco_base": "17.886,18 EUR",
    "prazo_execucao": "60 DIAS",
    "prazo_apresentacao_propostas": "19-01-2026 23:59",
    "fundos_eu": "Não",
    "plataforma_eletronica": "VORTAL",
    "url_procedimento": "https://community.vortal.biz/public/",
    "autor_nome": "Ricardo Ribeiro",
    "autor_cargo": "Assistente Técnico"
  },
  {
    "numero_procedimento": "N/A",
    "entidade": "Unidade Local de Saúde do Alentejo Central, EPE",
    "link": "https://diariodarepublica.pt/dr/detalhe/contrato-publico/172-996007048",
    "detalhes_completos": "1 - IDENTIFICAÇÃO E CONTACTOS DA ENTIDADE ADJUDICANTE\nDesignação da entidade adjudicante: Unidade Local de Saúde do Alentejo Central, EPE\nNIPC: 508085888\nEndereço: Largo Sr. da Pobreza\nCódigo postal: 7000-811\nLocalidade: Évora\nPaís: Portugal\nNUT III: PT187\nDistrito: Évora\nConcelho: Évora\nFreguesia: Todas\nTelefone: 266740111\nFax: 266744212\nEndereço da Entidade (URL): www.hevora.min-saude.pt\nEndereço Eletrónico: concursos.aprov@ulsac.min-saude.pt\neDelivery Gateway (URL): https://community.vortal.biz/public/\nFunção da Organização: Adquirente\nNorma jurídica da Entidade Adjudicante: Organismo de direito público\nÁrea de atividade da Autoridade Adjudicante: Saúde\n2 - JORNAL OFICIAL DA UNIÃO EUROPEIA\nO procedimento a que este anúncio diz respeito também é publicitado no Jornal Oficial da União Europeia? Não\n3 - AVISO\nModelo de Anúncio: Concurso público\nData de Envio do Anúncio: 05-01-2026\n5 - PROCESSO\nTipo de Procedimento: Concurso público\nPreço base do procedimento: Sim\nValor do preço base do procedimento: 112.320,00 EUR\nProcedimento com lotes? Não\n6 - OBJETO DO CONTRATO\nNúmero de referência interna: 190070/26 \nDesignação do contrato: 190070/26 - Prestação de Serviços Médicos de Cirurgia\nDescrição: 190070/26 - Prestação de Serviços Médicos de Cirurgia\nTipo de Contrato Principal: Aquisição de Serviços\nTipo de Contrato: Aquisição de Serviços\nClassificação CPV (Vocabulário Comum para os Contratos Públicos)\nObjeto principal\nVocabulário Principal: 85121280\nPreço base s/IVA: 112.320,00 EUR\n7 - INDICAÇÕES ADICIONAIS\nO contrato envolve aquisição conjunta (satisfação de várias entidades)? Não\nO contrato é adjudicado por uma central de compras? Não\n8 - TÉCNICAS\nO concurso destina-se à celebração de um acordo-quadro? Inexistência de acordo-quadro\nÉ utilizado um leilão eletrónico? Não\nÉ adotada uma fase de negociação? Não\nSistema de Aquisição Dinâmico: Inexistência de sistema de aquisição dinâmico\n9 - LOCAL DA EXECUÇÃO DO CONTRATO\nLOCAL DA EXECUÇÃO DO CONTRATO (PROCEDIMENTO)\nPaís: Portugal\nNUT III: PT187\nLocalidade: Évora\nDistrito: Évora\nConcelho: Évora\nFreguesia: União das Freguesias de Évora (São Mamede, Sé, São Pedro e Santo Antão)\n10 - PRAZO DE EXECUÇÃO DO CONTRATO\nPrazo de execução do contrato: 365 DIAS\nPrevisão de renovações: Não\n11 - FUNDOS EU\nTêm fundos EU? Não\n12 - DOCUMENTOS DE HABILITAÇÃO\nHabilitação para o exercício da atividade profissional: Não\n13 - CONDIÇÕES DE APRESENTAÇÃO\nPlataforma eletrónica utilizada pela entidade adjudicante: VORTAL\nURL para Apresentação: https://community.vortal.biz/public/\nAdmissibilidade da apresentação de propostas variantes: Não autorizado\nPrazo para apresentação das propostas: 20-01-2026 18:00\nPrazo durante o qual os concorrentes são obrigados a manter as respetivas propostas: 120 dias a contar do termo do prazo para a apresentação das propostas\nIndicação de Subcontratação na Proposta: Inexistência de indicação de subcontratação\n14 - PRESTAÇÃO DE CAUÇÃO\nPrestação de caução: Não\n15 - FORNECIMENTO DAS PEÇAS DO CONCURSO, APRESENTAÇÃO DE PEDIDOS DE PARTICIPAÇÃO E APRESENTAÇÃO DAS PROPOSTAS\nLink para acesso às peças do concurso (URL): https://community.vortal.biz/Public/public-tender-documents/M1BoaTJjbDE5dFd6UHFHN3FzVWhDT1ZzekFKWmp5YThJY3pHeFMyaDhtU0VBN0x1emNRK2RkOTlNNWp4OGtqenBwV280TEp3b2xNSjJNMzg1NHpZM1E9PVcmaEh6\n20 - OUTROS REQUISITOS\nInformação sobre contratos reservados. Aplica-se a contratos reservados (54º-A)? Não\n21 - CRITÉRIO DE ADJUDICAÇÃO\nMultifator: Sim\nFator: \nNome: Preço\nPonderação: 80%\nSubfatores: Não\nFator: \nNome: Qualidade\nPonderação: 20%\nSubfatores: Não\n24 - CONDIÇÕES DO CONTRATO\nFaturação Eletrónica: Permitido\nObrigação de Subcontratação:\nCódigo da Obrigação de Subcontratação: Não é aplicável nenhuma obrigação de subcontratação.\n25 - COMPRA PÚBLICA ESTRATÉGICA\nCompra Pública Estratégica: Inexistência de contratação pública estratégica\n26 - INFORMAÇÕES ADICIONAIS\nContrato adequado para PME: Sim\nCobertura ACP (Acordo dos Contratos Públicos da Organização Mundial do Comércio): Não\n27 - IDENTIFICAÇÃO E CONTACTOS DO ÓRGÃO DE RECURSOS ADMINISTRATIVOS\nDesignação: Conselho de Administração\nEndereço: Largo Sr. de Pobreza\nCódigo postal: 7000-811\nLocalidade: Évora\nTelefone: +351 266740111\nFax: +351 266740111\nEndereço eletrónico: concursos.aprov@ulsac.min-saude.pt\n28 - IDENTIFICAÇÃO DO(S) AUTOR(ES) DE ANÚNCIO\nNome: Carlos Antonio Mateus Gomes\nCargo: Presidente do Conselho de Administração\n419947106",
    "nipc": "508085888",
    "distrito": "Évora",
    "concelho": "Évora",
    "freguesia": "Todas",
    "site": "www.hevora.min-saude.pt",
    "email": "concursos.aprov@ulsac.min-saude.pt",
    "designacao_contrato": "190070/26 - Prestação de Serviços Médicos de Cirurgia",
    "descricao": "190070/26 - Prestação de Serviços Médicos de Cirurgia",
    "preco_base": "112.320,00 EUR",
    "prazo_execucao": "365 DIAS",
    "prazo_apresentacao_propostas": "20-01-2026 18:00",
    "fundos_eu": "Não",
    "plataforma_eletronica": "VORTAL",
    "url_procedimento": "https://community.vortal.biz/public/",
    "autor_nome": "Carlos Antonio Mateus Gomes",
    "autor_cargo": "Presidente do Conselho de Administração"
  },
  {
    "numero_procedimento": "N/A",
    "entidade": "Agrupamento de Escolas Gabriel Pereira, Évora",
    "link": "https://diariodarepublica.pt/dr/detalhe/contrato-publico/174-996007049",
    "detalhes_completos": "1 - IDENTIFICAÇÃO E CONTACTOS DA ENTIDADE ADJUDICANTE\nDesignação da entidade adjudicante: Agrupamento de Escolas Gabriel Pereira, Évora\nNIPC: 600082318\nEndereço: R. Dr. Domingos Rosado\nCódigo postal: 7005-469\nLocalidade: Évora\nPaís: Portugal\nNUT III: PT187\nDistrito: Évora\nConcelho: Évora\nFreguesia: Todas\nTelefone: 266745600\nEndereço Eletrónico: es.gabrielpereira@escolas.min-edu.pt\neDelivery Gateway (URL): https://community.vortal.biz/public/\nFunção da Organização: Adquirente\nNorma jurídica da Entidade Adjudicante: Organismo de direito público\nÁrea de atividade da Autoridade Adjudicante: Educação\n2 - JORNAL OFICIAL DA UNIÃO EUROPEIA\nO procedimento a que este anúncio diz respeito também é publicitado no Jornal Oficial da União Europeia? Não\n3 - AVISO\nModelo de Anúncio: Concurso público\nData de Envio do Anúncio: 05-01-2026\n5 - PROCESSO\nTipo de Procedimento: Concurso público\nPreço base do procedimento: Sim\nValor do preço base do procedimento: 149.999,99 EUR\nProcedimento com lotes? Sim\nNº Máx. de Lotes Autorizado: 4\nNúmero máximo de lotes que podem ser adjudicados a um concorrente: 4\n6 - OBJETO DO CONTRATO\nNúmero de referência interna: CPN_Nº2/2026_Refeitório\nDesignação do contrato: Fornecimento de Bens Alimentares para Refeitório\nDescrição: Fornecimento de Bens Alimentares para Refeitório\nTipo de Contrato Principal: Aquisição de Bens Móveis\nTipo de Contrato: Aquisição de Bens Móveis\nClassificação CPV (Vocabulário Comum para os Contratos Públicos)\nObjeto principal\nVocabulário Principal: 15800000\nPreço base s/IVA: 149.999,99 EUR\nLotes: \nNº: LOT-0001\nDescrição do Lote: Lote 1\nPreço base s/IVA: 48.844,80 EUR\nClassificação CPV (Vocabulário Comum para os Contratos Públicos)\nObjeto principal\nVocabulário Principal: 15800000\nNº: LOT-0002\nDescrição do Lote: Lote 2\nPreço base s/IVA: 40.600,95 EUR\nClassificação CPV (Vocabulário Comum para os Contratos Públicos)\nObjeto principal\nVocabulário Principal: 15800000\nNº: LOT-0003\nDescrição do Lote: Lote 3\nPreço base s/IVA: 24.672,26 EUR\nClassificação CPV (Vocabulário Comum para os Contratos Públicos)\nObjeto principal\nVocabulário Principal: 15800000\nNº: LOT-0004\nDescrição do Lote: Lote 4\nPreço base s/IVA: 35.881,98 EUR\nClassificação CPV (Vocabulário Comum para os Contratos Públicos)\nObjeto principal\nVocabulário Principal: 15800000\n7 - INDICAÇÕES ADICIONAIS\nO contrato envolve aquisição conjunta (satisfação de várias entidades)? Não\nO contrato é adjudicado por uma central de compras? Não\n8 - TÉCNICAS\nO concurso destina-se à celebração de um acordo-quadro? Inexistência de acordo-quadro\nÉ utilizado um leilão eletrónico? Não\nÉ adotada uma fase de negociação? Não\nSistema de Aquisição Dinâmico: Inexistência de sistema de aquisição dinâmico\n9 - LOCAL DA EXECUÇÃO DO CONTRATO\nLOCAL DA EXECUÇÃO DO CONTRATO (PROCEDIMENTO)\nPaís: Portugal\nNUT III: PT187\nLocalidade: Évora\nDistrito: Évora\nConcelho: Évora\nFreguesia: Todas\nLOCAL DA EXECUÇÃO DO CONTRATO (LOTE)\nIdentificador do Lote: LOT-0001; LOT-0002; LOT-0003; LOT-0004\nPaís: Portugal\nNUT III: PT187\nLocalidade: Évora\nDistrito: Évora\nConcelho: Évora\nFreguesia: Todas\n10 - PRAZO DE EXECUÇÃO DO CONTRATO\nIdentificador do Lote: LOT-0001; LOT-0002; LOT-0003; LOT-0004\nPrazo de execução do contrato: 11 MESES\nPrevisão de renovações: Não\n11 - FUNDOS EU\nIdentificador do Lote: LOT-0001; LOT-0002; LOT-0003; LOT-0004\nTêm fundos EU? Não\n12 - DOCUMENTOS DE HABILITAÇÃO\nHabilitação para o exercício da atividade profissional: Não\n13 - CONDIÇÕES DE APRESENTAÇÃO\nPlataforma eletrónica utilizada pela entidade adjudicante: VORTAL\nURL para Apresentação: https://community.vortal.biz/public/\nAdmissibilidade da apresentação de propostas variantes: Não autorizado\nPrazo para apresentação das propostas: 11-01-2026 17:00\nPrazo durante o qual os concorrentes são obrigados a manter as respetivas propostas: 66 dias a contar do termo do prazo para a apresentação das propostas\nIndicação de Subcontratação na Proposta: Inexistência de indicação de subcontratação\n14 - PRESTAÇÃO DE CAUÇÃO\nPrestação de caução: Não\n15 - FORNECIMENTO DAS PEÇAS DO CONCURSO, APRESENTAÇÃO DE PEDIDOS DE PARTICIPAÇÃO E APRESENTAÇÃO DAS PROPOSTAS\nLink para acesso às peças do concurso (URL): https://community.vortal.biz/Public/public-tender-documents/ZUtpcHNaR1pja3U3NnVaSVg4TEF0dzg0ZHJlNzdkUXl5MnhoNndqRms3QUYyakdlN3dqSG9YcUFVVlVPWStFTzExbVR0dXU5SVArdHdjdjBpMi8rakE9PWlrbjdj\n20 - OUTROS REQUISITOS\nIdentificador do Lote: LOT-0001; LOT-0002; LOT-0003; LOT-0004\nInformação sobre contratos reservados. Aplica-se a contratos reservados (54º-A)? Não\n21 - CRITÉRIO DE ADJUDICAÇÃO\nO Critério de adjudicação é diferenciado por lote? Não\nMultifator: Sim\nFator: \nNome: Preço\nPonderação: 40%\nSubfatores: Não\nFator: \nNome: Qualidade\nPonderação: 60%\nSubfatores: Não\n24 - CONDIÇÕES DO CONTRATO\nIdentificador do Lote: LOT-0001; LOT-0002; LOT-0003; LOT-0004\nFaturação Eletrónica: Permitido\nObrigação de Subcontratação:\nCódigo da Obrigação de Subcontratação: Não é aplicável nenhuma obrigação de subcontratação.\n25 - COMPRA PÚBLICA ESTRATÉGICA\nCompra Pública Estratégica: Inexistência de contratação pública estratégica\n26 - INFORMAÇÕES ADICIONAIS\nIdentificador do Lote: LOT-0001; LOT-0002; LOT-0003; LOT-0004\nContrato adequado para PME: Sim\nCobertura ACP (Acordo dos Contratos Públicos da Organização Mundial do Comércio): Não\n27 - IDENTIFICAÇÃO E CONTACTOS DO ÓRGÃO DE RECURSOS ADMINISTRATIVOS\nDesignação: Conselho Administrativo\nEndereço: Rua Dr. Domingos Rosado\nCódigo postal: 7005-469\nLocalidade: Évora\nTelefone: +351 266745600\nFax: +351 266744179\nEndereço eletrónico: direcao@aegp.edu.pt\n28 - IDENTIFICAÇÃO DO(S) AUTOR(ES) DE ANÚNCIO\nNome: Agrupamento de Escolas Gabriel Pereira\nCargo: Diretor\n419947215",
    "nipc": "600082318",
    "distrito": "Évora",
    "concelho": "Évora",
    "freguesia": "Todas",
    "site": null,
    "email": "es.gabrielpereira@escolas.min-edu.pt",
    "designacao_contrato": "Fornecimento de Bens Alimentares para Refeitório",
    "descricao": "Fornecimento de Bens Alimentares para Refeitório",
    "preco_base": "149.999,99 EUR",
    "prazo_execucao": "11 MESES",
    "prazo_apresentacao_propostas": "11-01-2026 17:00",
    "fundos_eu": "Não",
    "plataforma_eletronica": "VORTAL",
    "url_procedimento": "https://community.vortal.biz/public/",
    "autor_nome": "Agrupamento de Escolas Gabriel Pereira",
    "autor_cargo": "Diretor"
  },
  {
    "numero_procedimento": "N/A",
    "entidade": "Cinemateca Portuguesa - Museu do Cinema, IP",
    "link": "https://diariodarepublica.pt/dr/detalhe/contrato-publico/164-996275675",
    "detalhes_completos": "1 - IDENTIFICAÇÃO E CONTACTOS DA ENTIDADE ADJUDICANTE\nDesignação da entidade adjudicante: Cinemateca Portuguesa - Museu do Cinema, IP\nNIPC: 501603409\nServiço/Órgão/Pessoa de contacto: Divisão de Gestão\nEndereço: Rua Barata Salgueiro, n.º 39\nCódigo postal: 1269-059\nLocalidade: Lisboa\nPaís: Portugal\nNUT III: PT170\nDistrito: Lisboa\nConcelho: Lisboa\nFreguesia: Freguesia de Santo António - Lisboa\nTelefone: 213596200\nEndereço da Entidade (URL): www.cinemateca.pt\nEndereço Eletrónico: compras@cinemateca.pt\neDelivery Gateway (URL): https://www.acingov.pt\nFunção da Organização: Adquirente\nNorma jurídica da Entidade Adjudicante: Organismo de direito público\nÁrea de atividade da Autoridade Adjudicante: Serviços públicos das administrações públicas\n2 - JORNAL OFICIAL DA UNIÃO EUROPEIA\nO procedimento a que este anúncio diz respeito também é publicitado no Jornal Oficial da União Europeia? Não\n3 - AVISO\nModelo de Anúncio: Concurso público\nData de Envio do Anúncio: 05-01-2026\n5 - PROCESSO\nTipo de Procedimento: Concurso público\nPreço base do procedimento: Sim\nValor do preço base do procedimento: 257.000,00 EUR\nProcedimento com lotes? Não\n6 - OBJETO DO CONTRATO\nNúmero de referência interna: CP/01/2026\nDesignação do contrato: Atualização e consolidação de dois centros de dados do departamento ANIM da Cinemateca\nDescrição: Atualização e consolidação dos dois centros de dados do departamento do Arquivo Nacional das Imagens em Movimento da Cinemateca, bem como a manutenção dos equipamentos por um período de 36 meses\nTipo de Contrato Principal: Empreitada de Obras Públicas\nTipo de Contrato: Empreitada de Obras Públicas; Aquisição de Serviços\nClassificação CPV (Vocabulário Comum para os Contratos Públicos)\nObjeto principal\nVocabulário Principal: 45300000\nPreço base s/IVA: 230.000,00 EUR\nObjeto Complementar\nVocabulário Principal: 50700000\nPreço base s/IVA: 27.000,00 EUR\n7 - INDICAÇÕES ADICIONAIS\nO contrato envolve aquisição conjunta (satisfação de várias entidades)? Não\nO contrato é adjudicado por uma central de compras? Não\n8 - TÉCNICAS\nO concurso destina-se à celebração de um acordo-quadro? Inexistência de acordo-quadro\nÉ utilizado um leilão eletrónico? Não\nÉ adotada uma fase de negociação? Não\nSistema de Aquisição Dinâmico: Inexistência de sistema de aquisição dinâmico\n9 - LOCAL DA EXECUÇÃO DO CONTRATO\nLOCAL DA EXECUÇÃO DO CONTRATO (PROCEDIMENTO)\nPaís: Portugal\nNUT III: PT170\nLocalidade: Freixial\nDistrito: Lisboa\nConcelho: Loures\nFreguesia: Freguesia de Bucelas\n10 - PRAZO DE EXECUÇÃO DO CONTRATO\nPrazo de execução do contrato: 39 MESES\nPrevisão de renovações: Não\n11 - FUNDOS EU\nTêm fundos EU? Sim\n12 - DOCUMENTOS DE HABILITAÇÃO\nHabilitação para o exercício da atividade profissional: Sim\nTipo: Alvará\nDescrição: 4ª Categoria  Instalações Elétricas e Mecânicas contendo as seguintes subcategorias:\n- 1ª subcategoria - Instalações elétricas de utilização de baixa tensão com potência até 50 kVA;\n- 9ª subcategoria - Infraestruturas de telecomunicações;\n- 10.ª subcategoria - Sistemas de extinção de incêndios, de segurança e de deteção;\n- 12.ª subcategoria - Aquecimento, ventilação, ar condicionado e refrigeração.\n13 - CONDIÇÕES DE APRESENTAÇÃO\nPlataforma eletrónica utilizada pela entidade adjudicante: ACIN\nURL para Apresentação: https://www.acingov.pt\nAdmissibilidade da apresentação de propostas variantes: Não autorizado\nPrazo para apresentação das propostas: 20-01-2026 23:59\nPrazo durante o qual os concorrentes são obrigados a manter as respetivas propostas: 90 dias a contar do termo do prazo para a apresentação das propostas\nIndicação de Subcontratação na Proposta: A parte do contrato que o proponente tenciona subcontratar\n14 - PRESTAÇÃO DE CAUÇÃO\nPrestação de caução: Não\n15 - FORNECIMENTO DAS PEÇAS DO CONCURSO, APRESENTAÇÃO DE PEDIDOS DE PARTICIPAÇÃO E APRESENTAÇÃO DAS PROPOSTAS\nLink para acesso às peças do concurso (URL): https://www.acingov.pt/acingovprod/2/zonaPublica/zona_publica_c/donwloadProcedurePiece/MTAzNjE3Nw==\n20 - OUTROS REQUISITOS\nInformação sobre contratos reservados. Aplica-se a contratos reservados (54º-A)? Não\n21 - CRITÉRIO DE ADJUDICAÇÃO\nMultifator: Sim\nFator: \nNome: Preço\nPonderação: 50%\nSubfatores: Não\nFator: \nNome: Outros\nOutro Nome: Plano de Implementação de Projeto\nPonderação: 50%\nSubfatores: Não\n24 - CONDIÇÕES DO CONTRATO\nFaturação Eletrónica: Permitido\nObrigação de Subcontratação:\nCódigo da Obrigação de Subcontratação: Não é aplicável nenhuma obrigação de subcontratação.\n25 - COMPRA PÚBLICA ESTRATÉGICA\nCompra Pública Estratégica: Inexistência de contratação pública estratégica\n26 - INFORMAÇÕES ADICIONAIS\nContrato adequado para PME: Sim\nCobertura ACP (Acordo dos Contratos Públicos da Organização Mundial do Comércio): Não\n27 - IDENTIFICAÇÃO E CONTACTOS DO ÓRGÃO DE RECURSOS ADMINISTRATIVOS\nDesignação: Diretor\nEndereço: Rua Barata Salgueiro, n.º 39\nCódigo postal: 1269-059\nLocalidade: Lisboa\nTelefone: 213596200\nFax: \nEndereço eletrónico: cinemateca@cinemateca.pt\nPrazo de interposição do recurso: 30 dias\n28 - IDENTIFICAÇÃO DO(S) AUTOR(ES) DE ANÚNCIO\nNome: Isabel Juliana Schedel Arouca\nCargo: Chefe da Divisão de Gestão\n419947210",
    "nipc": "501603409",
    "distrito": "Lisboa",
    "concelho": "Lisboa",
    "freguesia": "Freguesia de Santo António - Lisboa",
    "site": "www.cinemateca.pt",
    "email": "compras@cinemateca.pt",
    "designacao_contrato": "Atualização e consolidação de dois centros de dados do departamento ANIM da Cinemateca",
    "descricao": "Atualização e consolidação dos dois centros de dados do departamento do Arquivo Nacional das Imagens em Movimento da Cinemateca, bem como a manutenção dos equipamentos por um período de 36 meses",
    "preco_base": "230.000,00 EUR",
    "prazo_execucao": "39 MESES",
    "prazo_apresentacao_propostas": "20-01-2026 23:59",
    "fundos_eu": "Sim",
    "plataforma_eletronica": "ACIN",
    "url_procedimento": "https://www.acingov.pt",
    "autor_nome": "Isabel Juliana Schedel Arouca",
    "autor_cargo": "Chefe da Divisão de Gestão"
  },
  {
    "numero_procedimento": "N/A",
    "entidade": "Município de Arcos de Valdevez",
    "link": "https://diariodarepublica.pt/dr/detalhe/contrato-publico/165-996275676",
    "detalhes_completos": "1 - IDENTIFICAÇÃO E CONTACTOS DA ENTIDADE ADJUDICANTE\nDesignação da entidade adjudicante: Município de Arcos de Valdevez\nNIPC: 505211696\nEndereço: Praça  Municipal\nCódigo postal: 4974-003\nLocalidade: Viana do Castelo\nPaís: Portugal\nNUT III: PT111\nDistrito: Viana do Castelo\nConcelho: Arcos de Valdevez\nFreguesia: União das Freguesias de Arcos de Valdevez (São Paio) e Giela\nTelefone: 258520500\nFax: 258520509\nEndereço da Entidade (URL): www.cmav.pt\nEndereço Eletrónico: geral@cmav.pt\neDelivery Gateway (URL): https://community.vortal.biz/public/\nFunção da Organização: Adquirente\nNorma jurídica da Entidade Adjudicante: Autoridade local\nÁrea de atividade da Autoridade Adjudicante: Serviços públicos das administrações públicas\n2 - JORNAL OFICIAL DA UNIÃO EUROPEIA\nO procedimento a que este anúncio diz respeito também é publicitado no Jornal Oficial da União Europeia? Não\n3 - AVISO\nModelo de Anúncio: Concurso público\nData de Envio do Anúncio: 05-01-2026\n5 - PROCESSO\nTipo de Procedimento: Concurso público\nPreço base do procedimento: Sim\nValor do preço base do procedimento: 50.000,00 EUR\nProcedimento com lotes? Não\n6 - OBJETO DO CONTRATO\nNúmero de referência interna: PO 601/2025\nDesignação do contrato: PO 601/2025 - Extensão da rede de saneamento em Oliveira - Troço A1 - A25 e Aguiã - Troço 18\nDescrição: PO 601/2025 - Extensão da rede de saneamento em Oliveira - Troço A1 - A25 e Aguiã - Troço 18\nTipo de Contrato Principal: Empreitada de Obras Públicas\nTipo de Contrato: Empreitada de Obras Públicas\nClassificação CPV (Vocabulário Comum para os Contratos Públicos)\nObjeto principal\nVocabulário Principal: 45231300\nPreço base s/IVA: 50.000,00 EUR\n7 - INDICAÇÕES ADICIONAIS\nO contrato envolve aquisição conjunta (satisfação de várias entidades)? Não\nO contrato é adjudicado por uma central de compras? Não\n8 - TÉCNICAS\nO concurso destina-se à celebração de um acordo-quadro? Inexistência de acordo-quadro\nÉ utilizado um leilão eletrónico? Não\nÉ adotada uma fase de negociação? Não\nSistema de Aquisição Dinâmico: Inexistência de sistema de aquisição dinâmico\n9 - LOCAL DA EXECUÇÃO DO CONTRATO\nLOCAL DA EXECUÇÃO DO CONTRATO (PROCEDIMENTO)\nPaís: Portugal\nNUT III: PT111\nLocalidade: Viana do Castelo\nDistrito: Viana do Castelo\nConcelho: Arcos de Valdevez\nFreguesia: União das Freguesias de Arcos de Valdevez (São Paio) e Giela\n10 - PRAZO DE EXECUÇÃO DO CONTRATO\nPrazo de execução do contrato: 60 DIAS\nPrevisão de renovações: Não\n11 - FUNDOS EU\nTêm fundos EU? Não\n12 - DOCUMENTOS DE HABILITAÇÃO\nHabilitação para o exercício da atividade profissional: Sim\nTipo: Alvará\nDescrição: Conforme indicado no artigo n.º 16.º do Programa de Procedimento\n13 - CONDIÇÕES DE APRESENTAÇÃO\nPlataforma eletrónica utilizada pela entidade adjudicante: VORTAL\nURL para Apresentação: https://community.vortal.biz/public/\nAdmissibilidade da apresentação de propostas variantes: Não autorizado\nPrazo para apresentação das propostas: 02-02-2026 18:00\nPrazo durante o qual os concorrentes são obrigados a manter as respetivas propostas: 120 dias a contar do termo do prazo para a apresentação das propostas\nIndicação de Subcontratação na Proposta: Inexistência de indicação de subcontratação\n14 - PRESTAÇÃO DE CAUÇÃO\nPrestação de caução: Não\n15 - FORNECIMENTO DAS PEÇAS DO CONCURSO, APRESENTAÇÃO DE PEDIDOS DE PARTICIPAÇÃO E APRESENTAÇÃO DAS PROPOSTAS\nLink para acesso às peças do concurso (URL): https://community.vortal.biz/Public/public-tender-documents/MG9kM3R2QkpqNklsQ25uV2M5NU1sR2RiNmZsTitLVGxPakJFam9uZnFnVW1NZnZVMGphZ0pwNDZZTitkYVZQTEd5ZVY4cm5FTFp2OTFITVQ4Y0U2bVE9PSV3JVF6\n20 - OUTROS REQUISITOS\nInformação sobre contratos reservados. Aplica-se a contratos reservados (54º-A)? Não\n21 - CRITÉRIO DE ADJUDICAÇÃO\nMultifator: Sim\nFator: \nNome: Preço\nPonderação: 40%\nSubfatores: Não\nFator: \nNome: Qualidade\nPonderação: 60%\nSubfatores: Sim\nSubfatores: \nNome: Plano de Trabalhos (PT)\nPonderação : 50%; \nNome: Plano de Mão-de-obra (PMO)\nPonderação : 25%; \nNome: Plano de Equipamentos (PE)\nPonderação : 25%; \n24 - CONDIÇÕES DO CONTRATO\nFaturação Eletrónica: Permitido\nObrigação de Subcontratação:\nCódigo da Obrigação de Subcontratação: Não é aplicável nenhuma obrigação de subcontratação.\n25 - COMPRA PÚBLICA ESTRATÉGICA\nCompra Pública Estratégica: Inexistência de contratação pública estratégica\n26 - INFORMAÇÕES ADICIONAIS\nContrato adequado para PME: Sim\nCobertura ACP (Acordo dos Contratos Públicos da Organização Mundial do Comércio): Não\n27 - IDENTIFICAÇÃO E CONTACTOS DO ÓRGÃO DE RECURSOS ADMINISTRATIVOS\nDesignação: Município de Arcos de Valdevez\nEndereço: Praça Municipal\nCódigo postal: 4974-003\nLocalidade: Arcos de Valdevez\nTelefone: +351 258520500\nFax: +351 258520509\nEndereço eletrónico: geral@cmav.pt\n28 - IDENTIFICAÇÃO DO(S) AUTOR(ES) DE ANÚNCIO\nNome: Olegário Gomes Gonçalves\nCargo: Presidente da Câmara\n419947091",
    "nipc": "505211696",
    "distrito": "Viana do Castelo",
    "concelho": "Arcos de Valdevez",
    "freguesia": "União das Freguesias de Arcos de Valdevez (São Paio) e Giela",
    "site": "www.cmav.pt",
    "email": "geral@cmav.pt",
    "designacao_contrato": "PO 601/2025 - Extensão da rede de saneamento em Oliveira - Troço A1 - A25 e Aguiã - Troço 18",
    "descricao": "PO 601/2025 - Extensão da rede de saneamento em Oliveira - Troço A1 - A25 e Aguiã - Troço 18",
    "preco_base": "50.000,00 EUR",
    "prazo_execucao": "60 DIAS",
    "prazo_apresentacao_propostas": "02-02-2026 18:00",
    "fundos_eu": "Não",
    "plataforma_eletronica": "VORTAL",
    "url_procedimento": "https://community.vortal.biz/public/",
    "autor_nome": "Olegário Gomes Gonçalves",
    "autor_cargo": "Presidente da Câmara"
  },
  {
    "numero_procedimento": "N/A",
    "entidade": "Portos dos Açores, SA",
    "link": "https://diariodarepublica.pt/dr/detalhe/contrato-publico/166-996275677",
    "detalhes_completos": "1 - IDENTIFICAÇÃO E CONTACTOS DA ENTIDADE ADJUDICANTE\nDesignação da entidade adjudicante: Portos dos Açores, SA\nNIPC: 512077843\nEndereço: Avenida Gago Coutinho e Sacadura Cabral, 7\nCódigo postal: 9900-062\nLocalidade: HORTA\nPaís: Portugal\nNUT III: PT200\nDistrito: Região Autónoma dos Açores\nConcelho: Todos\nFreguesia: Todas\nTelefone: 292208300\nFax: 292208315\nEndereço da Entidade (URL): www.portosdosacores.pt\nEndereço Eletrónico: geral@portosdosacores.pt\neDelivery Gateway (URL): https://www.acingov.pt\nFunção da Organização: Adquirente\nNorma jurídica da Entidade Adjudicante: Organismo de direito público\nÁrea de atividade da Entidade Adjudicante: Atividades portuárias\n2 - JORNAL OFICIAL DA UNIÃO EUROPEIA\nO procedimento a que este anúncio diz respeito também é publicitado no Jornal Oficial da União Europeia? Não\n3 - AVISO\nModelo de Anúncio: Concurso público\nData de Envio do Anúncio: 05-01-2026\n5 - PROCESSO\nTipo de Procedimento: Concurso público\nPreço base do procedimento: Sim\nValor do preço base do procedimento: 3.000.000,00 EUR\nProcedimento com lotes? Não\n6 - OBJETO DO CONTRATO\nNúmero de referência interna: CP/1/2026/PA, SA\nDesignação do contrato: CONCURSO PÚBLICO PARA A ADJUDICAÇÃO DA EMPREITADA DE CONSTRUÇÃO DO NOVO EDIFÍCIO MULTIUSOS DO PORTO DA HORTA, ILHA DO FAIAL\nDescrição: CONCURSO PÚBLICO PARA A ADJUDICAÇÃO DA EMPREITADA DE CONSTRUÇÃO DO NOVO EDIFÍCIO MULTIUSOS DO PORTO DA HORTA, ILHA DO FAIAL\nTipo de Contrato Principal: Empreitada de Obras Públicas\nTipo de Contrato: Empreitada de Obras Públicas\nClassificação CPV (Vocabulário Comum para os Contratos Públicos)\nObjeto principal\nVocabulário Principal: 45210000\nPreço base s/IVA: 3.000.000,00 EUR\n7 - INDICAÇÕES ADICIONAIS\nO contrato envolve aquisição conjunta (satisfação de várias entidades)? Não\nO contrato é adjudicado por uma central de compras? Não\n8 - TÉCNICAS\nO concurso destina-se à celebração de um acordo-quadro? Inexistência de acordo-quadro\nÉ utilizado um leilão eletrónico? Não\nÉ adotada uma fase de negociação? Não\nSistema de Aquisição Dinâmico: Inexistência de sistema de aquisição dinâmico\n9 - LOCAL DA EXECUÇÃO DO CONTRATO\nLOCAL DA EXECUÇÃO DO CONTRATO (PROCEDIMENTO)\nPaís: Portugal\nNUT III: PT200\nLocalidade: HORTA\nDistrito: Região Autónoma dos Açores\nConcelho: Horta\nFreguesia: Todas\n10 - PRAZO DE EXECUÇÃO DO CONTRATO\nPrazo de execução do contrato: 20 MESES\nPrevisão de renovações: Não\n11 - FUNDOS EU\nTêm fundos EU? Sim\n12 - DOCUMENTOS DE HABILITAÇÃO\nHabilitação para o exercício da atividade profissional: Sim\nTipo: Alvará\nDescrição: Alvará emitido pelo Instituto dos Mercados Públicos do Imobiliário e da Construção, I.P. (IMPIC, I.P.), que comprove as necessárias habilitações para o exercício da atividade profissional nos termos do caderno de encargos.\n13 - CONDIÇÕES DE APRESENTAÇÃO\nPlataforma eletrónica utilizada pela entidade adjudicante: ACIN\nURL para Apresentação: https://www.acingov.pt\nAdmissibilidade da apresentação de propostas variantes: Não autorizado\nPrazo para apresentação das propostas: 19-02-2026 23:59\nPrazo durante o qual os concorrentes são obrigados a manter as respetivas propostas: 66 dias a contar do termo do prazo para a apresentação das propostas\nIndicação de Subcontratação na Proposta: Inexistência de indicação de subcontratação\n14 - PRESTAÇÃO DE CAUÇÃO\nPrestação de caução: Sim\nPercentagem: 2%\nDescrição da Garantia Exigida: O valor da caução é de 2.00% do preço contratual.\n15 - FORNECIMENTO DAS PEÇAS DO CONCURSO, APRESENTAÇÃO DE PEDIDOS DE PARTICIPAÇÃO E APRESENTAÇÃO DAS PROPOSTAS\nLink para acesso às peças do concurso (URL): https://www.acingov.pt/acingovprod/2/zonaPublica/zona_publica_c/donwloadProcedurePiece/MTAzNjE0Mg==\n20 - OUTROS REQUISITOS\nInformação sobre contratos reservados. Aplica-se a contratos reservados (54º-A)? Não\n21 - CRITÉRIO DE ADJUDICAÇÃO\nMultifator: Não\nMonofator:\nNome: Preço\n24 - CONDIÇÕES DO CONTRATO\nFaturação Eletrónica: Permitido\nObrigação de Subcontratação:\nCódigo da Obrigação de Subcontratação: Não é aplicável nenhuma obrigação de subcontratação.\n25 - COMPRA PÚBLICA ESTRATÉGICA\nCompra Pública Estratégica: Inexistência de contratação pública estratégica\n26 - INFORMAÇÕES ADICIONAIS\nContrato adequado para PME: Não\nCobertura ACP (Acordo dos Contratos Públicos da Organização Mundial do Comércio): Não\n27 - IDENTIFICAÇÃO E CONTACTOS DO ÓRGÃO DE RECURSOS ADMINISTRATIVOS\nDesignação: Conselho de Administração\nEndereço: Avenida Gago Coutinho e Sacadura Cabral, 7\nCódigo postal: 9900-062\nLocalidade: HORTA\nTelefone: 292208300\nFax: \nEndereço eletrónico: geral@portosdosacores.pt\n28 - IDENTIFICAÇÃO DO(S) AUTOR(ES) DE ANÚNCIO\nNome: Renata Maria Freitas Lima\nCargo: Técnica Administrativa\n419947205",
    "nipc": "512077843",
    "distrito": "Região Autónoma dos Açores",
    "concelho": "Todos",
    "freguesia": "Todas",
    "site": "www.portosdosacores.pt",
    "email": "geral@portosdosacores.pt",
    "designacao_contrato": "CONCURSO PÚBLICO PARA A ADJUDICAÇÃO DA EMPREITADA DE CONSTRUÇÃO DO NOVO EDIFÍCIO MULTIUSOS DO PORTO DA HORTA, ILHA DO FAIAL",
    "descricao": "CONCURSO PÚBLICO PARA A ADJUDICAÇÃO DA EMPREITADA DE CONSTRUÇÃO DO NOVO EDIFÍCIO MULTIUSOS DO PORTO DA HORTA, ILHA DO FAIAL",
    "preco_base": "3.000.000,00 EUR",
    "prazo_execucao": "20 MESES",
    "prazo_apresentacao_propostas": "19-02-2026 23:59",
    "fundos_eu": "Sim",
    "plataforma_eletronica": "ACIN",
    "url_procedimento": "https://www.acingov.pt",
    "autor_nome": "Renata Maria Freitas Lima",
    "autor_cargo": "Técnica Administrativa"
  },
  {
    "numero_procedimento": "N/A",
    "entidade": "Unidade Local de Saúde de Santo António, EPE",
    "link": "https://diariodarepublica.pt/dr/detalhe/contrato-publico/169-996275678",
    "detalhes_completos": "1 - IDENTIFICAÇÃO E CONTACTOS DA ENTIDADE ADJUDICANTE\nDesignação da entidade adjudicante: Unidade Local de Saúde de Santo António, EPE\nNIPC: 517392259\nEndereço: Largo Prof. Abel Salazar\nCódigo postal: 4099-001\nLocalidade: Área Metropolitana do Porto\nPaís: Portugal\nNUT III: PT11A\nDistrito: Porto\nConcelho: Porto\nFreguesia: Todas\nTelefone: 222077500\nFax: 223320318\nEndereço da Entidade (URL): www.hgsa.pt\nEndereço Eletrónico: helpdesk.b-on@hgsa.min-saude.pt\neDelivery Gateway (URL): https://community.vortal.biz/public/\nFunção da Organização: Adquirente\nNorma jurídica da Entidade Adjudicante: Organismo de direito público\nÁrea de atividade da Autoridade Adjudicante: Saúde\n2 - JORNAL OFICIAL DA UNIÃO EUROPEIA\nO procedimento a que este anúncio diz respeito também é publicitado no Jornal Oficial da União Europeia? Não\n3 - AVISO\nModelo de Anúncio: Concurso público\nData de Envio do Anúncio: 05-01-2026\n5 - PROCESSO\nTipo de Procedimento: Concurso público\nPreço base do procedimento: Sim\nValor do preço base do procedimento: 183.030,00 EUR\nProcedimento com lotes? Não\n6 - OBJETO DO CONTRATO\nNúmero de referência interna: CP/1458/2025\nDesignação do contrato: Concurso Público nº 1548/2025 - Aquisição de sistema de aférese para colheita de multicomponentes sanguíneos, com colocação de equipamento em regime de comodato para um período de 36 meses\nDescrição: Concurso Público nº 1548/2025 - Aquisição de sistema de aférese para colheita de multicomponentes sanguíneos, com colocação de equipamento em regime de comodato para um período de 36 meses\nTipo de Contrato Principal: Aquisição de Bens Móveis\nTipo de Contrato: Aquisição de Bens Móveis\nClassificação CPV (Vocabulário Comum para os Contratos Públicos)\nObjeto principal\nVocabulário Principal: 33696000\nPreço base s/IVA: 183.030,00 EUR\n7 - INDICAÇÕES ADICIONAIS\nO contrato envolve aquisição conjunta (satisfação de várias entidades)? Não\nO contrato é adjudicado por uma central de compras? Não\n8 - TÉCNICAS\nO concurso destina-se à celebração de um acordo-quadro? Inexistência de acordo-quadro\nÉ utilizado um leilão eletrónico? Não\nÉ adotada uma fase de negociação? Sim\nSistema de Aquisição Dinâmico: Inexistência de sistema de aquisição dinâmico\n9 - LOCAL DA EXECUÇÃO DO CONTRATO\nLOCAL DA EXECUÇÃO DO CONTRATO (PROCEDIMENTO)\nPaís: Portugal\nNUT III: PT11A\nLocalidade: Área Metropolitana do Porto\nDistrito: Porto\nConcelho: Porto\nFreguesia: Todas\n10 - PRAZO DE EXECUÇÃO DO CONTRATO\nPrazo de execução do contrato: 36 MESES\nPrevisão de renovações: Não\n11 - FUNDOS EU\nTêm fundos EU? Não\n12 - DOCUMENTOS DE HABILITAÇÃO\nHabilitação para o exercício da atividade profissional: Não\n13 - CONDIÇÕES DE APRESENTAÇÃO\nPlataforma eletrónica utilizada pela entidade adjudicante: VORTAL\nURL para Apresentação: https://community.vortal.biz/public/\nAdmissibilidade da apresentação de propostas variantes: Não autorizado\nPrazo para apresentação das propostas: 26-01-2026 23:59\nPrazo durante o qual os concorrentes são obrigados a manter as respetivas propostas: 120 dias a contar do termo do prazo para a apresentação das propostas\nIndicação de Subcontratação na Proposta: Inexistência de indicação de subcontratação\n14 - PRESTAÇÃO DE CAUÇÃO\nPrestação de caução: Não\n15 - FORNECIMENTO DAS PEÇAS DO CONCURSO, APRESENTAÇÃO DE PEDIDOS DE PARTICIPAÇÃO E APRESENTAÇÃO DAS PROPOSTAS\nLink para acesso às peças do concurso (URL): https://community.vortal.biz/Public/public-tender-documents/dXVxRGIzcHNyNE0yQUMwWGVnRGxEbUQ4OEx3c0krVEZldWs4cnlQRURKbUVjRFF0UUdrb2FBcFI0U0prajJ6VC9YdytKMllEWXBXUGdyOU12YTFBVmc9PSUrbUBY\n20 - OUTROS REQUISITOS\nInformação sobre contratos reservados. Aplica-se a contratos reservados (54º-A)? Não\n21 - CRITÉRIO DE ADJUDICAÇÃO\nMultifator: Sim\nFator: \nNome: Preço\nPonderação: 50%\nSubfatores: Não\nFator: \nNome: Qualidade\nPonderação: 50%\nSubfatores: Não\n24 - CONDIÇÕES DO CONTRATO\nFaturação Eletrónica: Permitido\nObrigação de Subcontratação:\nCódigo da Obrigação de Subcontratação: Não é aplicável nenhuma obrigação de subcontratação.\n25 - COMPRA PÚBLICA ESTRATÉGICA\nCompra Pública Estratégica: Inexistência de contratação pública estratégica\n26 - INFORMAÇÕES ADICIONAIS\nContrato adequado para PME: Sim\nCobertura ACP (Acordo dos Contratos Públicos da Organização Mundial do Comércio): Não\n27 - IDENTIFICAÇÃO E CONTACTOS DO ÓRGÃO DE RECURSOS ADMINISTRATIVOS\nDesignação: Conselho de Administração da ULS Santo Antonio\nEndereço: Largo Professor Abel Salazar\nCódigo postal: 4099-001\nLocalidade: Porto\nTelefone: +351 222077529\nFax: +351 223320318\nEndereço eletrónico: Ricardoribeiro.aprov@ulssa.min-saude.pt\n28 - IDENTIFICAÇÃO DO(S) AUTOR(ES) DE ANÚNCIO\nNome: Ricardo Ribeiro\nCargo: Assistente Técnico\n419947154",
    "nipc": "517392259",
    "distrito": "Porto",
    "concelho": "Porto",
    "freguesia": "Todas",
    "site": "www.hgsa.pt",
    "email": "helpdesk.b-on@hgsa.min-saude.pt",
    "designacao_contrato": "Concurso Público nº 1548/2025 - Aquisição de sistema de aférese para colheita de multicomponentes sanguíneos, com colocação de equipamento em regime de comodato para um período de 36 meses",
    "descricao": "Concurso Público nº 1548/2025 - Aquisição de sistema de aférese para colheita de multicomponentes sanguíneos, com colocação de equipamento em regime de comodato para um período de 36 meses",
    "preco_base": "183.030,00 EUR",
    "prazo_execucao": "36 MESES",
    "prazo_apresentacao_propostas": "26-01-2026 23:59",
    "fundos_eu": "Não",
    "plataforma_eletronica": "VORTAL",
    "url_procedimento": "https://community.vortal.biz/public/",
    "autor_nome": "Ricardo Ribeiro",
    "autor_cargo": "Assistente Técnico"
  },
  {
    "numero_procedimento": "N/A",
    "entidade": "Unidade Local de Saúde de Santo António, EPE",
    "link": "https://diariodarepublica.pt/dr/detalhe/contrato-publico/170-996275679",
    "detalhes_completos": "1 - IDENTIFICAÇÃO E CONTACTOS DA ENTIDADE ADJUDICANTE\nDesignação da entidade adjudicante: Unidade Local de Saúde de Santo António, EPE\nNIPC: 517392259\nEndereço: Largo Prof. Abel Salazar\nCódigo postal: 4099-001\nLocalidade: Área Metropolitana do Porto\nPaís: Portugal\nNUT III: PT11A\nDistrito: Porto\nConcelho: Porto\nFreguesia: Todas\nTelefone: 222077500\nFax: 223320318\nEndereço da Entidade (URL): www.hgsa.pt\nEndereço Eletrónico: helpdesk.b-on@hgsa.min-saude.pt\neDelivery Gateway (URL): https://community.vortal.biz/public/\nFunção da Organização: Adquirente\nNorma jurídica da Entidade Adjudicante: Organismo de direito público\nÁrea de atividade da Autoridade Adjudicante: Saúde\n2 - JORNAL OFICIAL DA UNIÃO EUROPEIA\nO procedimento a que este anúncio diz respeito também é publicitado no Jornal Oficial da União Europeia? Não\n3 - AVISO\nModelo de Anúncio: Concurso público\nData de Envio do Anúncio: 05-01-2026\n5 - PROCESSO\nTipo de Procedimento: Concurso público\nPreço base do procedimento: Sim\nValor do preço base do procedimento: 51.322,50 EUR\nProcedimento com lotes? Sim\nNº Máx. de Lotes Autorizado: 10\nNúmero máximo de lotes que podem ser adjudicados a um concorrente: 10\n6 - OBJETO DO CONTRATO\nNúmero de referência interna: CP/1550/2025\nDesignação do contrato: Concurso Público nº 1550/2025 - Aquisição de material diverso para Gastrenterologia, da ULS de Santo António, EPE\nDescrição: Concurso Público nº 1550/2025 - Aquisição de material diverso para Gastrenterologia, da ULS de Santo António, EPE\nTipo de Contrato Principal: Aquisição de Bens Móveis\nTipo de Contrato: Aquisição de Bens Móveis\nClassificação CPV (Vocabulário Comum para os Contratos Públicos)\nObjeto principal\nVocabulário Principal: 33140000\nPreço base s/IVA: 51.322,50 EUR\nLotes: \nNº: LOT-0001\nDescrição do Lote: Lote1\nPreço base s/IVA: 1.845,00 EUR\nClassificação CPV (Vocabulário Comum para os Contratos Públicos)\nObjeto principal\nVocabulário Principal: 33140000\nNº: LOT-0002\nDescrição do Lote: Lote2\nPreço base s/IVA: 6.457,50 EUR\nClassificação CPV (Vocabulário Comum para os Contratos Públicos)\nObjeto principal\nVocabulário Principal: 33140000\nNº: LOT-0003\nDescrição do Lote: Lote3\nPreço base s/IVA: 3.690,00 EUR\nClassificação CPV (Vocabulário Comum para os Contratos Públicos)\nObjeto principal\nVocabulário Principal: 33140000\nNº: LOT-0004\nDescrição do Lote: Lote4\nPreço base s/IVA: 2.730,00 EUR\nClassificação CPV (Vocabulário Comum para os Contratos Públicos)\nObjeto principal\nVocabulário Principal: 33140000\nNº: LOT-0005\nDescrição do Lote: Lote5\nPreço base s/IVA: 1.800,00 EUR\nClassificação CPV (Vocabulário Comum para os Contratos Públicos)\nObjeto principal\nVocabulário Principal: 33140000\nNº: LOT-0006\nDescrição do Lote: Lote6\nPreço base s/IVA: 1.800,00 EUR\nClassificação CPV (Vocabulário Comum para os Contratos Públicos)\nObjeto principal\nVocabulário Principal: 33140000\nNº: LOT-0007\nDescrição do Lote: Lote7\nPreço base s/IVA: 1.800,00 EUR\nClassificação CPV (Vocabulário Comum para os Contratos Públicos)\nObjeto principal\nVocabulário Principal: 33140000\nNº: LOT-0008\nDescrição do Lote: Lote8\nPreço base s/IVA: 900,00 EUR\nClassificação CPV (Vocabulário Comum para os Contratos Públicos)\nObjeto principal\nVocabulário Principal: 33140000\nNº: LOT-0009\nDescrição do Lote: Lote9\nPreço base s/IVA: 900,00 EUR\nClassificação CPV (Vocabulário Comum para os Contratos Públicos)\nObjeto principal\nVocabulário Principal: 33140000\nNº: LOT-0010\nDescrição do Lote: Lote10\nPreço base s/IVA: 29.400,00 EUR\nClassificação CPV (Vocabulário Comum para os Contratos Públicos)\nObjeto principal\nVocabulário Principal: 33140000\n7 - INDICAÇÕES ADICIONAIS\nO contrato envolve aquisição conjunta (satisfação de várias entidades)? Não\nO contrato é adjudicado por uma central de compras? Não\n8 - TÉCNICAS\nO concurso destina-se à celebração de um acordo-quadro? Inexistência de acordo-quadro\nÉ utilizado um leilão eletrónico? Não\nÉ adotada uma fase de negociação? Sim\nSistema de Aquisição Dinâmico: Inexistência de sistema de aquisição dinâmico\n9 - LOCAL DA EXECUÇÃO DO CONTRATO\nLOCAL DA EXECUÇÃO DO CONTRATO (PROCEDIMENTO)\nPaís: Portugal\nNUT III: PT11A\nLocalidade: Área Metropolitana do Porto\nDistrito: Porto\nConcelho: Porto\nFreguesia: Todas\nLOCAL DA EXECUÇÃO DO CONTRATO (LOTE)\nIdentificador do Lote: LOT-0001; LOT-0002; LOT-0003; LOT-0004; LOT-0005; LOT-0006; LOT-0007; LOT-0008; LOT-0009; LOT-0010\nPaís: Portugal\nNUT III: PT11A\nLocalidade: Área Metropolitana do Porto\nDistrito: Porto\nConcelho: Porto\nFreguesia: Todas\n10 - PRAZO DE EXECUÇÃO DO CONTRATO\nIdentificador do Lote: LOT-0001; LOT-0002; LOT-0003; LOT-0004; LOT-0005; LOT-0006; LOT-0007; LOT-0008; LOT-0009; LOT-0010\nPrazo de execução do contrato: 36 MESES\nPrevisão de renovações: Não\n11 - FUNDOS EU\nIdentificador do Lote: LOT-0001; LOT-0002; LOT-0003; LOT-0004; LOT-0005; LOT-0006; LOT-0007; LOT-0008; LOT-0009; LOT-0010\nTêm fundos EU? Não\n12 - DOCUMENTOS DE HABILITAÇÃO\nHabilitação para o exercício da atividade profissional: Não\n13 - CONDIÇÕES DE APRESENTAÇÃO\nPlataforma eletrónica utilizada pela entidade adjudicante: VORTAL\nURL para Apresentação: https://community.vortal.biz/public/\nAdmissibilidade da apresentação de propostas variantes: Não autorizado\nPrazo para apresentação das propostas: 26-01-2026 23:59\nPrazo durante o qual os concorrentes são obrigados a manter as respetivas propostas: 120 dias a contar do termo do prazo para a apresentação das propostas\nIndicação de Subcontratação na Proposta: Inexistência de indicação de subcontratação\n14 - PRESTAÇÃO DE CAUÇÃO\nPrestação de caução: Não\n15 - FORNECIMENTO DAS PEÇAS DO CONCURSO, APRESENTAÇÃO DE PEDIDOS DE PARTICIPAÇÃO E APRESENTAÇÃO DAS PROPOSTAS\nLink para acesso às peças do concurso (URL): https://community.vortal.biz/Public/public-tender-documents/OFFvTnh5Sy92czBBZCt2Z0x2YnVSeFg4TG5YbUg1RWVvb3F3dWd0WUwrcTE1eVk3ci9JcjVoVUM5RWU2dTZ4Q1dxdlNJM1dPc2xqWTAzbFl2aDUyMHc9PStrdFdr\n20 - OUTROS REQUISITOS\nIdentificador do Lote: LOT-0001; LOT-0002; LOT-0003; LOT-0004; LOT-0005; LOT-0006; LOT-0007; LOT-0008; LOT-0009; LOT-0010\nInformação sobre contratos reservados. Aplica-se a contratos reservados (54º-A)? Não\n21 - CRITÉRIO DE ADJUDICAÇÃO\nO Critério de adjudicação é diferenciado por lote? Não\nMultifator: Não\nMonofator:\nNome: Preço\n24 - CONDIÇÕES DO CONTRATO\nIdentificador do Lote: LOT-0001; LOT-0002; LOT-0003; LOT-0004; LOT-0005; LOT-0006; LOT-0007; LOT-0008; LOT-0009; LOT-0010\nFaturação Eletrónica: Permitido\nObrigação de Subcontratação:\nCódigo da Obrigação de Subcontratação: Não é aplicável nenhuma obrigação de subcontratação.\n25 - COMPRA PÚBLICA ESTRATÉGICA\nCompra Pública Estratégica: Inexistência de contratação pública estratégica\n26 - INFORMAÇÕES ADICIONAIS\nIdentificador do Lote: LOT-0001; LOT-0002; LOT-0003; LOT-0004; LOT-0005; LOT-0006; LOT-0007; LOT-0008; LOT-0009; LOT-0010\nContrato adequado para PME: Sim\nCobertura ACP (Acordo dos Contratos Públicos da Organização Mundial do Comércio): Não\n27 - IDENTIFICAÇÃO E CONTACTOS DO ÓRGÃO DE RECURSOS ADMINISTRATIVOS\nDesignação: Conselho de Administração da ULS Santo Antonio\nEndereço: Largo Professor Abel Salazar\nCódigo postal: 4099-001\nLocalidade: Porto\nTelefone: +351 222077529\nFax: +351 223320318\nEndereço eletrónico: Ricardoribeiro.aprov@ulssa.min-saude.pt\n28 - IDENTIFICAÇÃO DO(S) AUTOR(ES) DE ANÚNCIO\nNome: Ricardo Ribeiro\nCargo: Assistente Técnico\n419947155",
    "nipc": "517392259",
    "distrito": "Porto",
    "concelho": "Porto",
    "freguesia": "Todas",
    "site": "www.hgsa.pt",
    "email": "helpdesk.b-on@hgsa.min-saude.pt",
    "designacao_contrato": "Concurso Público nº 1550/2025 - Aquisição de material diverso para Gastrenterologia, da ULS de Santo António, EPE",
    "descricao": "Concurso Público nº 1550/2025 - Aquisição de material diverso para Gastrenterologia, da ULS de Santo António, EPE",
    "preco_base": "51.322,50 EUR",
    "prazo_execucao": "36 MESES",
    "prazo_apresentacao_propostas": "26-01-2026 23:59",
    "fundos_eu": "Não",
    "plataforma_eletronica": "VORTAL",
    "url_procedimento": "https://community.vortal.biz/public/",
    "autor_nome": "Ricardo Ribeiro",
    "autor_cargo": "Assistente Técnico"
  },
  {
    "numero_procedimento": "N/A",
    "entidade": "Serviço de Utilização Comum dos Hospitais",
    "link": "https://diariodarepublica.pt/dr/detalhe/contrato-publico/171-996275680",
    "detalhes_completos": "1 - IDENTIFICAÇÃO E CONTACTOS DA ENTIDADE ADJUDICANTE\nDesignação da entidade adjudicante: Serviço de Utilização Comum dos Hospitais\nNIPC: 500900469\nEndereço: Av. Do Brasil Nr. 53 Pav. 33 A, Lisboa\nCódigo postal: 1700-063\nLocalidade: Lisboa\nPaís: Portugal\nNUT III: PT170\nDistrito: Lisboa\nConcelho: Lisboa\nFreguesia: Todas\nTelefone: 217923400\nFax: 217958526\nEndereço da Entidade (URL): www.such.pt\nEndereço Eletrónico: somoscomercial@such.pt\neDelivery Gateway (URL): https://community.vortal.biz/public/\nFunção da Organização: Adquirente\nNorma jurídica da Entidade Adjudicante: Organismo de direito público\nÁrea de atividade da Autoridade Adjudicante: Saúde\n2 - JORNAL OFICIAL DA UNIÃO EUROPEIA\nO procedimento a que este anúncio diz respeito também é publicitado no Jornal Oficial da União Europeia? Não\n3 - AVISO\nModelo de Anúncio: Concurso público\nData de Envio do Anúncio: 05-01-2026\n5 - PROCESSO\nTipo de Procedimento: Concurso público\nPreço base do procedimento: Sim\nValor do preço base do procedimento: 36.000,00 EUR\nProcedimento com lotes? Não\n6 - OBJETO DO CONTRATO\nNúmero de referência interna: PR2025/21726\nDesignação do contrato: Prestação de Serviços desmontagem, transporte e revisão de caldeira existente na Central Térmica\nDescrição: Prestação de Serviços desmontagem, transporte e revisão de caldeira existente na Central Térmica\nTipo de Contrato Principal: Aquisição de Serviços\nTipo de Contrato: Aquisição de Serviços\nClassificação CPV (Vocabulário Comum para os Contratos Públicos)\nObjeto principal\nVocabulário Principal: 50700000\nPreço base s/IVA: 36.000,00 EUR\n7 - INDICAÇÕES ADICIONAIS\nO contrato envolve aquisição conjunta (satisfação de várias entidades)? Não\nO contrato é adjudicado por uma central de compras? Não\n8 - TÉCNICAS\nO concurso destina-se à celebração de um acordo-quadro? Inexistência de acordo-quadro\nÉ utilizado um leilão eletrónico? Não\nÉ adotada uma fase de negociação? Não\nSistema de Aquisição Dinâmico: Inexistência de sistema de aquisição dinâmico\n9 - LOCAL DA EXECUÇÃO DO CONTRATO\nLOCAL DA EXECUÇÃO DO CONTRATO (PROCEDIMENTO)\nPaís: Portugal\nNUT III: PT170\nLocalidade: Lisboa\nDistrito: Lisboa\nConcelho: Lisboa\nFreguesia: Freguesia de Alvalade - Lisboa\n10 - PRAZO DE EXECUÇÃO DO CONTRATO\nPrazo de execução do contrato: 2 MESES\nPrevisão de renovações: Não\n11 - FUNDOS EU\nTêm fundos EU? Não\n12 - DOCUMENTOS DE HABILITAÇÃO\nHabilitação para o exercício da atividade profissional: Sim\nTipo: Outros\nDescrição - Outros: Não Aplicável\nDescrição: Não Aplicável\n13 - CONDIÇÕES DE APRESENTAÇÃO\nPlataforma eletrónica utilizada pela entidade adjudicante: VORTAL\nURL para Apresentação: https://community.vortal.biz/public/\nAdmissibilidade da apresentação de propostas variantes: Não autorizado\nPrazo para apresentação das propostas: 20-01-2026 17:00\nPrazo durante o qual os concorrentes são obrigados a manter as respetivas propostas: 66 dias a contar do termo do prazo para a apresentação das propostas\nIndicação de Subcontratação na Proposta: Inexistência de indicação de subcontratação\n14 - PRESTAÇÃO DE CAUÇÃO\nPrestação de caução: Não\n15 - FORNECIMENTO DAS PEÇAS DO CONCURSO, APRESENTAÇÃO DE PEDIDOS DE PARTICIPAÇÃO E APRESENTAÇÃO DAS PROPOSTAS\nLink para acesso às peças do concurso (URL): https://community.vortal.biz/Public/public-tender-documents/Z2pseCtnY2Y4RHNydU40eE9lRldJOXJ6VlJkemF0UGJDRlh2WmhaZkViRnlUb1ZNQWZFdWJlTTlxa1c2NmxuYzVYWGZBYnErbzdKZlAvOUhZYmdraHc9PU1HU1hp\n20 - OUTROS REQUISITOS\nInformação sobre contratos reservados. Aplica-se a contratos reservados (54º-A)? Não\n21 - CRITÉRIO DE ADJUDICAÇÃO\nMultifator: Não\nMonofator:\nNome: Outros\nOutro nome: Preço\n24 - CONDIÇÕES DO CONTRATO\nFaturação Eletrónica: Permitido\nObrigação de Subcontratação:\nCódigo da Obrigação de Subcontratação: Não é aplicável nenhuma obrigação de subcontratação.\n25 - COMPRA PÚBLICA ESTRATÉGICA\nCompra Pública Estratégica: Inexistência de contratação pública estratégica\n26 - INFORMAÇÕES ADICIONAIS\nContrato adequado para PME: Sim\nCobertura ACP (Acordo dos Contratos Públicos da Organização Mundial do Comércio): Não\n27 - IDENTIFICAÇÃO E CONTACTOS DO ÓRGÃO DE RECURSOS ADMINISTRATIVOS\nDesignação: Serviço de Aprovisionamento e Logistica\nEndereço: Parque da Saúde - Pavilhão 33-A, Avª do Brasil, 53\nCódigo postal: 1700-003\nLocalidade: Lisboa\nTelefone: +351 217923400\nFax: +351 217958526\nEndereço eletrónico: contratacaopublica@such.pt\n28 - IDENTIFICAÇÃO DO(S) AUTOR(ES) DE ANÚNCIO\nNome: Paulo Jorge Rendeiro Correia de Sousa\nCargo: Presidente do Conselho de administração\n419947080",
    "nipc": "500900469",
    "distrito": "Lisboa",
    "concelho": "Lisboa",
    "freguesia": "Todas",
    "site": "www.such.pt",
    "email": "somoscomercial@such.pt",
    "designacao_contrato": "Prestação de Serviços desmontagem, transporte e revisão de caldeira existente na Central Térmica",
    "descricao": "Prestação de Serviços desmontagem, transporte e revisão de caldeira existente na Central Térmica",
    "preco_base": "36.000,00 EUR",
    "prazo_execucao": "2 MESES",
    "prazo_apresentacao_propostas": "20-01-2026 17:00",
    "fundos_eu": "Não",
    "plataforma_eletronica": "VORTAL",
    "url_procedimento": "https://community.vortal.biz/public/",
    "autor_nome": "Paulo Jorge Rendeiro Correia de Sousa",
    "autor_cargo": "Presidente do Conselho de administração"
  },
  {
    "numero_procedimento": "N/A",
    "entidade": "Agrupamento de Escolas Gabriel Pereira, Évora",
    "link": "https://diariodarepublica.pt/dr/detalhe/contrato-publico/173-996275682",
    "detalhes_completos": "1 - IDENTIFICAÇÃO E CONTACTOS DA ENTIDADE ADJUDICANTE\nDesignação da entidade adjudicante: Agrupamento de Escolas Gabriel Pereira, Évora\nNIPC: 600082318\nEndereço: R. Dr. Domingos Rosado\nCódigo postal: 7005-469\nLocalidade: Évora\nPaís: Portugal\nNUT III: PT187\nDistrito: Évora\nConcelho: Évora\nFreguesia: Todas\nTelefone: 266745600\nEndereço Eletrónico: es.gabrielpereira@escolas.min-edu.pt\neDelivery Gateway (URL): https://community.vortal.biz/public/\nFunção da Organização: Adquirente\nNorma jurídica da Entidade Adjudicante: Organismo de direito público\nÁrea de atividade da Autoridade Adjudicante: Educação\n2 - JORNAL OFICIAL DA UNIÃO EUROPEIA\nO procedimento a que este anúncio diz respeito também é publicitado no Jornal Oficial da União Europeia? Não\n3 - AVISO\nModelo de Anúncio: Concurso público\nData de Envio do Anúncio: 05-01-2026\n5 - PROCESSO\nTipo de Procedimento: Concurso público\nPreço base do procedimento: Sim\nValor do preço base do procedimento: 97.194,38 EUR\nProcedimento com lotes? Sim\nNº Máx. de Lotes Autorizado: 8\nNúmero máximo de lotes que podem ser adjudicados a um concorrente: 8\n6 - OBJETO DO CONTRATO\nNúmero de referência interna: CPN_01_2026_BUFETE\nDesignação do contrato: Aquisição de Bens Alimentares - BUFETE\nDescrição: Aquisição de Bens Alimentares - BUFETE\nTipo de Contrato Principal: Aquisição de Bens Móveis\nTipo de Contrato: Aquisição de Bens Móveis\nClassificação CPV (Vocabulário Comum para os Contratos Públicos)\nObjeto principal\nVocabulário Principal: 15800000\nPreço base s/IVA: 97.194,38 EUR\nLotes: \nNº: LOT-0001\nDescrição do Lote: Lote 1\nPreço base s/IVA: 5.063,94 EUR\nClassificação CPV (Vocabulário Comum para os Contratos Públicos)\nObjeto principal\nVocabulário Principal: 15800000\nNº: LOT-0002\nDescrição do Lote: Lote 2\nPreço base s/IVA: 9.109,58 EUR\nClassificação CPV (Vocabulário Comum para os Contratos Públicos)\nObjeto principal\nVocabulário Principal: 15800000\nNº: LOT-0003\nDescrição do Lote: Lote 3\nPreço base s/IVA: 9.015,00 EUR\nClassificação CPV (Vocabulário Comum para os Contratos Públicos)\nObjeto principal\nVocabulário Principal: 15800000\nNº: LOT-0004\nDescrição do Lote: Lote 4\nPreço base s/IVA: 25.894,00 EUR\nClassificação CPV (Vocabulário Comum para os Contratos Públicos)\nObjeto principal\nVocabulário Principal: 15800000\nNº: LOT-0005\nDescrição do Lote: Lote 5\nPreço base s/IVA: 6.200,96 EUR\nClassificação CPV (Vocabulário Comum para os Contratos Públicos)\nObjeto principal\nVocabulário Principal: 15800000\nNº: LOT-0006\nDescrição do Lote: Lote 6\nPreço base s/IVA: 8.468,00 EUR\nClassificação CPV (Vocabulário Comum para os Contratos Públicos)\nObjeto principal\nVocabulário Principal: 15800000\nNº: LOT-0007\nDescrição do Lote: Lote 7\nPreço base s/IVA: 25.947,40 EUR\nClassificação CPV (Vocabulário Comum para os Contratos Públicos)\nObjeto principal\nVocabulário Principal: 15800000\nNº: LOT-0008\nDescrição do Lote: Lote 8\nPreço base s/IVA: 7.495,50 EUR\nClassificação CPV (Vocabulário Comum para os Contratos Públicos)\nObjeto principal\nVocabulário Principal: 15800000\n7 - INDICAÇÕES ADICIONAIS\nO contrato envolve aquisição conjunta (satisfação de várias entidades)? Não\nO contrato é adjudicado por uma central de compras? Não\n8 - TÉCNICAS\nO concurso destina-se à celebração de um acordo-quadro? Inexistência de acordo-quadro\nÉ utilizado um leilão eletrónico? Não\nÉ adotada uma fase de negociação? Não\nSistema de Aquisição Dinâmico: Inexistência de sistema de aquisição dinâmico\n9 - LOCAL DA EXECUÇÃO DO CONTRATO\nLOCAL DA EXECUÇÃO DO CONTRATO (PROCEDIMENTO)\nPaís: Portugal\nNUT III: PT187\nLocalidade: Évora\nDistrito: Évora\nConcelho: Évora\nFreguesia: Todas\nLOCAL DA EXECUÇÃO DO CONTRATO (LOTE)\nIdentificador do Lote: LOT-0001; LOT-0002; LOT-0003; LOT-0004; LOT-0005; LOT-0006; LOT-0007; LOT-0008\nPaís: Portugal\nNUT III: PT187\nLocalidade: Évora\nDistrito: Évora\nConcelho: Évora\nFreguesia: Todas\n10 - PRAZO DE EXECUÇÃO DO CONTRATO\nIdentificador do Lote: LOT-0001; LOT-0002; LOT-0003; LOT-0004; LOT-0005; LOT-0006; LOT-0007; LOT-0008\nPrazo de execução do contrato: 11 MESES\nPrevisão de renovações: Não\n11 - FUNDOS EU\nIdentificador do Lote: LOT-0001; LOT-0002; LOT-0003; LOT-0004; LOT-0005; LOT-0006; LOT-0007; LOT-0008\nTêm fundos EU? Não\n12 - DOCUMENTOS DE HABILITAÇÃO\nHabilitação para o exercício da atividade profissional: Não\n13 - CONDIÇÕES DE APRESENTAÇÃO\nPlataforma eletrónica utilizada pela entidade adjudicante: VORTAL\nURL para Apresentação: https://community.vortal.biz/public/\nAdmissibilidade da apresentação de propostas variantes: Não autorizado\nPrazo para apresentação das propostas: 11-01-2026 17:00\nPrazo durante o qual os concorrentes são obrigados a manter as respetivas propostas: 66 dias a contar do termo do prazo para a apresentação das propostas\nIndicação de Subcontratação na Proposta: Inexistência de indicação de subcontratação\n14 - PRESTAÇÃO DE CAUÇÃO\nPrestação de caução: Não\n15 - FORNECIMENTO DAS PEÇAS DO CONCURSO, APRESENTAÇÃO DE PEDIDOS DE PARTICIPAÇÃO E APRESENTAÇÃO DAS PROPOSTAS\nLink para acesso às peças do concurso (URL): https://community.vortal.biz/Public/public-tender-documents/aEM0M3pJWG42TENKWjlUNE92ZFVwQldKNW1OSTJnUXJ0ajlYdVR3Z0JDQ21kWUNZdFhra0tyVFJwMFNydnZsMXhqOFgwRHUxTXJaemFnVHFpRG9NWnc9PWxqeSVW\n20 - OUTROS REQUISITOS\nIdentificador do Lote: LOT-0001; LOT-0002; LOT-0003; LOT-0004; LOT-0005; LOT-0006; LOT-0007; LOT-0008\nInformação sobre contratos reservados. Aplica-se a contratos reservados (54º-A)? Não\n21 - CRITÉRIO DE ADJUDICAÇÃO\nO Critério de adjudicação é diferenciado por lote? Não\nMultifator: Sim\nFator: \nNome: Preço\nPonderação: 40%\nSubfatores: Não\nFator: \nNome: Qualidade\nPonderação: 60%\nSubfatores: Não\n24 - CONDIÇÕES DO CONTRATO\nIdentificador do Lote: LOT-0001; LOT-0002; LOT-0003; LOT-0004; LOT-0005; LOT-0006; LOT-0007; LOT-0008\nFaturação Eletrónica: Permitido\nObrigação de Subcontratação:\nCódigo da Obrigação de Subcontratação: Não é aplicável nenhuma obrigação de subcontratação.\n25 - COMPRA PÚBLICA ESTRATÉGICA\nCompra Pública Estratégica: Inexistência de contratação pública estratégica\n26 - INFORMAÇÕES ADICIONAIS\nIdentificador do Lote: LOT-0001; LOT-0002; LOT-0003; LOT-0004; LOT-0005; LOT-0006; LOT-0007; LOT-0008\nContrato adequado para PME: Sim\nCobertura ACP (Acordo dos Contratos Públicos da Organização Mundial do Comércio): Não\n27 - IDENTIFICAÇÃO E CONTACTOS DO ÓRGÃO DE RECURSOS ADMINISTRATIVOS\nDesignação: Conselho Administrativo\nEndereço: Rua Dr. Domingos Rosado\nCódigo postal: 7005-469\nLocalidade: Évora\nTelefone: +351 266745600\nFax: +351 266709898\nEndereço eletrónico: direcao@aegp.edu.pt\n28 - IDENTIFICAÇÃO DO(S) AUTOR(ES) DE ANÚNCIO\nNome: Agrupamento de Escolas Gabriel Pereira\nCargo: Diretor\n419947190",
    "nipc": "600082318",
    "distrito": "Évora",
    "concelho": "Évora",
    "freguesia": "Todas",
    "site": null,
    "email": "es.gabrielpereira@escolas.min-edu.pt",
    "designacao_contrato": "Aquisição de Bens Alimentares - BUFETE",
    "descricao": "Aquisição de Bens Alimentares - BUFETE",
    "preco_base": "97.194,38 EUR",
    "prazo_execucao": "11 MESES",
    "prazo_apresentacao_propostas": "11-01-2026 17:00",
    "fundos_eu": "Não",
    "plataforma_eletronica": "VORTAL",
    "url_procedimento": "https://community.vortal.biz/public/",
    "autor_nome": "Agrupamento de Escolas Gabriel Pereira",
    "autor_cargo": "Diretor"
  },
  {
    "numero_procedimento": "N/A",
    "entidade": "Águas do Norte, SA",
    "link": "https://diariodarepublica.pt/dr/detalhe/contrato-publico/175-996319462",
    "detalhes_completos": "1 - IDENTIFICAÇÃO E CONTACTOS DA ENTIDADE ADJUDICANTE\nDesignação da entidade adjudicante: Águas do Norte, SA\nNIPC: 513606084\nEndereço: Rua Dom Pedro de Castro, N.º 1A\nCódigo postal: 5000-669\nLocalidade: Vila Real\nPaís: Portugal\nNUT III: PT11D\nDistrito: Vila Real\nConcelho: Vila Real\nFreguesia: Freguesia de Vila Real\nTelefone: 259309370\nFax: 259309371\nEndereço da Entidade (URL): http://www.adnorte.pt/\nEndereço Eletrónico: geral.adnorte@adp.pt\neDelivery Gateway (URL): https://www.acingov.pt\nFunção da Organização: Adquirente\nNorma jurídica da Entidade Adjudicante: Organismo de direito público\nÁrea de atividade da Autoridade Adjudicante: Serviços públicos das administrações públicas\n2 - JORNAL OFICIAL DA UNIÃO EUROPEIA\nO procedimento a que este anúncio diz respeito também é publicitado no Jornal Oficial da União Europeia? Não\n3 - AVISO\nModelo de Anúncio: Concurso público\nData de Envio do Anúncio: 06-01-2026\n5 - PROCESSO\nTipo de Procedimento: Concurso público\nPreço base do procedimento: Sim\nValor do preço base do procedimento: 112.500,00 EUR\nProcedimento com lotes? Sim\nNº Máx. de Lotes Autorizado: 2\nNúmero máximo de lotes que podem ser adjudicados a um concorrente: 2\n6 - OBJETO DO CONTRATO\nNúmero de referência interna: PRC_0263/2025_STE\nDesignação do contrato: PRC_0263/2025_STE - Aquisição de serviços para estudo de delimitação de perímetros de proteção de captações de água da Águas do Norte, S.A.\nDescrição: PRC_0263/2025_STE - Aquisição de serviços para estudo de delimitação de perímetros de proteção de captações de água da Águas do Norte, S.A.\nTipo de Contrato Principal: Aquisição de Serviços\nTipo de Contrato: Aquisição de Serviços\nClassificação CPV (Vocabulário Comum para os Contratos Públicos)\nObjeto principal\nVocabulário Principal: 90713100\nPreço base s/IVA: 112.500,00 EUR\nLotes: \nNº: LOT-0001\nDescrição do Lote: Lote A - Alta\nPreço base s/IVA: 22.500,00 EUR\nClassificação CPV (Vocabulário Comum para os Contratos Públicos)\nObjeto principal\nVocabulário Principal: 90713100\nNº: LOT-0002\nDescrição do Lote: Lote B - Baixa\nPreço base s/IVA: 90.000,00 EUR\nClassificação CPV (Vocabulário Comum para os Contratos Públicos)\nObjeto principal\nVocabulário Principal: 90713100\n7 - INDICAÇÕES ADICIONAIS\nO contrato envolve aquisição conjunta (satisfação de várias entidades)? Não\nO contrato é adjudicado por uma central de compras? Não\n8 - TÉCNICAS\nO concurso destina-se à celebração de um acordo-quadro? Inexistência de acordo-quadro\nÉ utilizado um leilão eletrónico? Não\nÉ adotada uma fase de negociação? Não\nSistema de Aquisição Dinâmico: Inexistência de sistema de aquisição dinâmico\n9 - LOCAL DA EXECUÇÃO DO CONTRATO\nLOCAL DA EXECUÇÃO DO CONTRATO (PROCEDIMENTO)\nPaís: Portugal\nNUT III: PT11A\nLocalidade: Todas\nDistrito: Aveiro\nConcelho: Arouca\nFreguesia: Todas\nPaís: Portugal\nNUT III: PT112\nLocalidade: União das Freguesias de Areias de Vilar e Encourados\nDistrito: Braga\nConcelho: Barcelos\nFreguesia: União das Freguesias de Areias de Vilar e Encourados\nPaís: Portugal\nNUT III: PT11C\nLocalidade: Todas\nDistrito: Braga\nConcelho: Celorico de Basto\nFreguesia: Todas\nPaís: Portugal\nNUT III: PT11D\nLocalidade: Todas\nDistrito: Braganca\nConcelho: Torre de Moncorvo\nFreguesia: Todas\nPaís: Portugal\nNUT III: PT11C\nLocalidade: Todas\nDistrito: Porto\nConcelho: Amarante\nFreguesia: Todas\nPaís: Portugal\nNUT III: PT11A\nLocalidade: Todas\nDistrito: Porto\nConcelho: Santo Tirso\nFreguesia: Todas\nPaís: Portugal\nNUT III: PT11C\nLocalidade: Todas\nDistrito: Porto\nConcelho: Baião\nFreguesia: Todas\nPaís: Portugal\nNUT III: PT111\nLocalidade: União das Freguesias de Viana do Castelo (Santa Maria Maior e Monserrate) e Meadela\nDistrito: Viana do Castelo\nConcelho: Viana do Castelo\nFreguesia: União das Freguesias de Viana do Castelo (Santa Maria Maior e Monserrate) e Meadela\nPaís: Portugal\nNUT III: PT11D\nLocalidade: União das Freguesias de Borbela e Lamas de Olo\nDistrito: Vila Real\nConcelho: Vila Real\nFreguesia: União das Freguesias de Borbela e Lamas de Olo\nPaís: Portugal\nNUT III: PT11C\nLocalidade: Cinfães\nDistrito: Viseu\nConcelho: Cinfães\nFreguesia: Todas\nLOCAL DA EXECUÇÃO DO CONTRATO (LOTE)\nIdentificador do Lote: LOT-0001; LOT-0002\nPaís: Portugal\nNUT III: PT11A\nLocalidade: Todas\nDistrito: Aveiro\nConcelho: Arouca\nFreguesia: Todas\nIdentificador do Lote: LOT-0001; LOT-0002\nPaís: Portugal\nNUT III: PT112\nLocalidade: União das Freguesias de Areias de Vilar e Encourados\nDistrito: Braga\nConcelho: Barcelos\nFreguesia: União das Freguesias de Areias de Vilar e Encourados\nIdentificador do Lote: LOT-0001; LOT-0002\nPaís: Portugal\nNUT III: PT11C\nLocalidade: Todas\nDistrito: Braga\nConcelho: Celorico de Basto\nFreguesia: Todas\nIdentificador do Lote: LOT-0001; LOT-0002\nPaís: Portugal\nNUT III: PT11D\nLocalidade: Todas\nDistrito: Braganca\nConcelho: Torre de Moncorvo\nFreguesia: Todas\nIdentificador do Lote: LOT-0001; LOT-0002\nPaís: Portugal\nNUT III: PT11C\nLocalidade: Todas\nDistrito: Porto\nConcelho: Amarante\nFreguesia: Todas\nIdentificador do Lote: LOT-0001; LOT-0002\nPaís: Portugal\nNUT III: PT11C\nLocalidade: Todas\nDistrito: Porto\nConcelho: Baião\nFreguesia: Todas\nIdentificador do Lote: LOT-0001; LOT-0002\nPaís: Portugal\nNUT III: PT11A\nLocalidade: Todas\nDistrito: Porto\nConcelho: Santo Tirso\nFreguesia: Todas\nIdentificador do Lote: LOT-0001; LOT-0002\nPaís: Portugal\nNUT III: PT111\nLocalidade: União das Freguesias de Viana do Castelo (Santa Maria Maior e Monserrate) e Meadela\nDistrito: Viana do Castelo\nConcelho: Viana do Castelo\nFreguesia: União das Freguesias de Viana do Castelo (Santa Maria Maior e Monserrate) e Meadela\nIdentificador do Lote: LOT-0001; LOT-0002\nPaís: Portugal\nNUT III: PT11D\nLocalidade: União das Freguesias de Borbela e Lamas de Olo\nDistrito: Vila Real\nConcelho: Vila Real\nFreguesia: União das Freguesias de Borbela e Lamas de Olo\nIdentificador do Lote: LOT-0001; LOT-0002\nPaís: Portugal\nNUT III: PT11C\nLocalidade: Cinfães\nDistrito: Viseu\nConcelho: Cinfães\nFreguesia: Todas\n10 - PRAZO DE EXECUÇÃO DO CONTRATO\nIdentificador do Lote: LOT-0001; LOT-0002\nPrazo de execução do contrato: 3 ANOS\nPrevisão de renovações: Não\n11 - FUNDOS EU\nIdentificador do Lote: LOT-0001; LOT-0002\nTêm fundos EU? Não\n12 - DOCUMENTOS DE HABILITAÇÃO\nHabilitação para o exercício da atividade profissional: Não\n13 - CONDIÇÕES DE APRESENTAÇÃO\nPlataforma eletrónica utilizada pela entidade adjudicante: ACIN\nURL para Apresentação: https://www.acingov.pt\nAdmissibilidade da apresentação de propostas variantes: Não autorizado\nPrazo para apresentação das propostas: 19-01-2026 17:00\nPrazo durante o qual os concorrentes são obrigados a manter as respetivas propostas: 90 dias a contar do termo do prazo para a apresentação das propostas\nIndicação de Subcontratação na Proposta: Inexistência de indicação de subcontratação\n14 - PRESTAÇÃO DE CAUÇÃO\nPrestação de caução: Não\n15 - FORNECIMENTO DAS PEÇAS DO CONCURSO, APRESENTAÇÃO DE PEDIDOS DE PARTICIPAÇÃO E APRESENTAÇÃO DAS PROPOSTAS\nLink para acesso às peças do concurso (URL): https://www.acingov.pt/acingovprod/2/zonaPublica/zona_publica_c/donwloadProcedurePiece/MTAwOTE4NQ==\n20 - OUTROS REQUISITOS\nIdentificador do Lote: LOT-0001; LOT-0002\nInformação sobre contratos reservados. Aplica-se a contratos reservados (54º-A)? Não\n21 - CRITÉRIO DE ADJUDICAÇÃO\nO Critério de adjudicação é diferenciado por lote? Não\nMultifator: Não\nMonofator:\nNome: Preço\n24 - CONDIÇÕES DO CONTRATO\nIdentificador do Lote: LOT-0001; LOT-0002\nFaturação Eletrónica: Permitido\nObrigação de Subcontratação:\nCódigo da Obrigação de Subcontratação: Não é aplicável nenhuma obrigação de subcontratação.\n25 - COMPRA PÚBLICA ESTRATÉGICA\nCompra Pública Estratégica: Inexistência de contratação pública estratégica\n26 - INFORMAÇÕES ADICIONAIS\nIdentificador do Lote: LOT-0001; LOT-0002\nContrato adequado para PME: Sim\nCobertura ACP (Acordo dos Contratos Públicos da Organização Mundial do Comércio): Não\n27 - IDENTIFICAÇÃO E CONTACTOS DO ÓRGÃO DE RECURSOS ADMINISTRATIVOS\nDesignação: Águas do Norte S.A.\nEndereço: Rua Dom Pedro de Castro, N.º 1A\nCódigo postal: 5000-669\nLocalidade: Vila Real\nTelefone: 259309370\nFax: 259309371\nEndereço eletrónico: geral.adnorte@adp.pt\n28 - IDENTIFICAÇÃO DO(S) AUTOR(ES) DE ANÚNCIO\nNome: José Miguel Carvalho\nCargo: Técnico de Compras e Logística\n419947090",
    "nipc": "513606084",
    "distrito": "Vila Real",
    "concelho": "Vila Real",
    "freguesia": "Freguesia de Vila Real",
    "site": "http://www.adnorte.pt/",
    "email": "geral.adnorte@adp.pt",
    "designacao_contrato": "PRC_0263/2025_STE - Aquisição de serviços para estudo de delimitação de perímetros de proteção de captações de água da Águas do Norte, S.A.",
    "descricao": "PRC_0263/2025_STE - Aquisição de serviços para estudo de delimitação de perímetros de proteção de captações de água da Águas do Norte, S.A.",
    "preco_base": "112.500,00 EUR",
    "prazo_execucao": "3 ANOS",
    "prazo_apresentacao_propostas": "19-01-2026 17:00",
    "fundos_eu": "Não",
    "plataforma_eletronica": "ACIN",
    "url_procedimento": "https://www.acingov.pt",
    "autor_nome": "José Miguel Carvalho",
    "autor_cargo": "Técnico de Compras e Logística"
  },
  {
    "numero_procedimento": "N/A",
    "entidade": "AgdA - Águas Públicas do Alentejo, SA",
    "link": "https://diariodarepublica.pt/dr/detalhe/contrato-publico/176-996320794",
    "detalhes_completos": "1 - IDENTIFICAÇÃO E CONTACTOS DA ENTIDADE ADJUDICANTE\nDesignação da entidade adjudicante: AgdA - Águas Públicas do Alentejo, SA\nNIPC: 509133843\nServiço/Órgão/Pessoa de contacto: Serviço de Compras e Logística\nEndereço: Rua Dr. Aresta Branco, nº.51\nCódigo postal: 7800-310\nLocalidade: Beja\nPaís: Portugal\nNUT III: PT184\nDistrito: Beja\nConcelho: Beja\nFreguesia: Todas\nTelefone: 284101100\nFax: 284101199\nEndereço da Entidade (URL): https://www.agda.pt\nEndereço Eletrónico: geral.agda@adp.pt\neDelivery Gateway (URL): https://www.acingov.pt\nFunção da Organização: Adquirente\nNorma jurídica da Entidade Adjudicante: Organismo de direito público\nÁrea de atividade da Autoridade Adjudicante: Serviços públicos das administrações públicas\n2 - JORNAL OFICIAL DA UNIÃO EUROPEIA\nO procedimento a que este anúncio diz respeito também é publicitado no Jornal Oficial da União Europeia? Não\n3 - AVISO\nModelo de Anúncio: Concurso público\nData de Envio do Anúncio: 06-01-2026\n5 - PROCESSO\nTipo de Procedimento: Concurso público\nPreço base do procedimento: Sim\nValor do preço base do procedimento: 974.000,00 EUR\nProcedimento com lotes? Não\n6 - OBJETO DO CONTRATO\nNúmero de referência interna: 129_040_25_CP_EO_B\nDesignação do contrato: Empreitada de Execução da Reabilitação dos Reservatórios de Almograve e São Francisco da Serra\nDescrição: Empreitada de Execução da Reabilitação dos Reservatórios de Almograve e São Francisco da Serra\nTipo de Contrato Principal: Empreitada de Obras Públicas\nTipo de Contrato: Empreitada de Obras Públicas\nClassificação CPV (Vocabulário Comum para os Contratos Públicos)\nObjeto principal\nVocabulário Principal: 45453100\nPreço base s/IVA: 974.000,00 EUR\n7 - INDICAÇÕES ADICIONAIS\nO contrato envolve aquisição conjunta (satisfação de várias entidades)? Não\nO contrato é adjudicado por uma central de compras? Não\n8 - TÉCNICAS\nO concurso destina-se à celebração de um acordo-quadro? Inexistência de acordo-quadro\nÉ utilizado um leilão eletrónico? Não\nÉ adotada uma fase de negociação? Não\nSistema de Aquisição Dinâmico: Inexistência de sistema de aquisição dinâmico\n9 - LOCAL DA EXECUÇÃO DO CONTRATO\nLOCAL DA EXECUÇÃO DO CONTRATO (PROCEDIMENTO)\nPaís: Portugal\nNUT III: PT184\nLocalidade: Longueira/Almograve\nDistrito: Beja\nConcelho: Odemira\nFreguesia: Freguesia de Longueira/Almograve\nPaís: Portugal\nNUT III: PT181\nLocalidade: São Francisco da Serra\nDistrito: Setúbal\nConcelho: Santiago do Cacém\nFreguesia: Freguesia de São Francisco da Serra\n10 - PRAZO DE EXECUÇÃO DO CONTRATO\nPrazo de execução do contrato: 210 DIAS\nPrevisão de renovações: Não\n11 - FUNDOS EU\nTêm fundos EU? Não\n12 - DOCUMENTOS DE HABILITAÇÃO\nHabilitação para o exercício da atividade profissional: Sim\nTipo: Alvará\nDescrição: Documento comprovativo da titularidade de alvará ou certificado de empreiteiro de obras públicas, contendo as seguintes habilitações:\ni) 6ª subcategoria da 2ª categoria e da classe correspondente ao valor global da proposta;\nii) 1ª, 2ª, 4ª, 5ª, e 7ªsubcategorias da 1ª categoria, da classe correspondente ao valor dos trabalhos especializados que lhe respeite, consoante a parte que a esses trabalhos cabe na proposta;\niii) 1ª subcategoria da 4ª categoria, da classe correspondente ao valor dos trabalhos especializados que lhe respeite, consoante a parte que a esses trabalhos cabe na proposta.\niv) 2ª, 5ª, 8ª, 9ª, 10ª, 11ª, e 12 ª subcategoria da 5ª categoria, da classe correspondente ao valor dos trabalhos especializados que lhe respeite, consoante a parte que a esses trabalhos cabe na proposta.\n13 - CONDIÇÕES DE APRESENTAÇÃO\nPlataforma eletrónica utilizada pela entidade adjudicante: ACIN\nURL para Apresentação: https://www.acingov.pt\nAdmissibilidade da apresentação de propostas variantes: Não autorizado\nPrazo para apresentação das propostas: 04-02-2026 18:00\nPrazo durante o qual os concorrentes são obrigados a manter as respetivas propostas: 90 dias a contar do termo do prazo para a apresentação das propostas\nIndicação de Subcontratação na Proposta: Inexistência de indicação de subcontratação\n14 - PRESTAÇÃO DE CAUÇÃO\nPrestação de caução: Sim\nPercentagem: 5%\nDescrição da Garantia Exigida: O valor da caução é de 5.00% do preço contratual.\n15 - FORNECIMENTO DAS PEÇAS DO CONCURSO, APRESENTAÇÃO DE PEDIDOS DE PARTICIPAÇÃO E APRESENTAÇÃO DAS PROPOSTAS\nLink para acesso às peças do concurso (URL): https://www.acingov.pt/acingovprod/2/zonaPublica/zona_publica_c/donwloadProcedurePiece/MTAzNjE2NQ==\n20 - OUTROS REQUISITOS\nInformação sobre contratos reservados. Aplica-se a contratos reservados (54º-A)? Não\n21 - CRITÉRIO DE ADJUDICAÇÃO\nMultifator: Sim\nFator: \nNome: Preço\nPonderação: 50%\nSubfatores: Não\nFator: \nNome: Outros\nOutro Nome: Valia Técnica\nPonderação: 50%\nSubfatores: Sim\nSubfatores: \nNome: B.1 Metodologia de execução da obra\nPonderação : 50%; \nNome: B.2 Detalhe e consistência do Plano de Trabalhos B.2.1 Plano de Trabalhos\nPonderação : 20%; \nNome: B.2 Detalhe e consistência do Plano de Trabalhos B.2.2 Plano de Meios\nPonderação : 10%; \nNome: B.3 Caracterização dos equipamentos e materiais\nPonderação : 20%; \n24 - CONDIÇÕES DO CONTRATO\nFaturação Eletrónica: Permitido\nObrigação de Subcontratação:\nCódigo da Obrigação de Subcontratação: Não é aplicável nenhuma obrigação de subcontratação.\n25 - COMPRA PÚBLICA ESTRATÉGICA\nCompra Pública Estratégica: Inexistência de contratação pública estratégica\n26 - INFORMAÇÕES ADICIONAIS\nContrato adequado para PME: Não\nCobertura ACP (Acordo dos Contratos Públicos da Organização Mundial do Comércio): Não\n27 - IDENTIFICAÇÃO E CONTACTOS DO ÓRGÃO DE RECURSOS ADMINISTRATIVOS\nDesignação: AgdA-Águas Públicas do Alentejo, S.A.\nEndereço: Rua Dr. Aresta Branco, nº.51\nCódigo postal: 7800-310\nLocalidade: Beja\nTelefone: 284101100\nFax: \nEndereço eletrónico: geral.agda@adp.pt\nPrazo de interposição do recurso: 10 dias\n28 - IDENTIFICAÇÃO DO(S) AUTOR(ES) DE ANÚNCIO\nNome: Maria de Fátima Costa\nCargo: Técnica Superior de Compras e Logística\n419947216",
    "nipc": "509133843",
    "distrito": "Beja",
    "concelho": "Beja",
    "freguesia": "Todas",
    "site": "https://www.agda.pt",
    "email": "geral.agda@adp.pt",
    "designacao_contrato": "Empreitada de Execução da Reabilitação dos Reservatórios de Almograve e São Francisco da Serra",
    "descricao": "Empreitada de Execução da Reabilitação dos Reservatórios de Almograve e São Francisco da Serra",
    "preco_base": "974.000,00 EUR",
    "prazo_execucao": "210 DIAS",
    "prazo_apresentacao_propostas": "04-02-2026 18:00",
    "fundos_eu": "Não",
    "plataforma_eletronica": "ACIN",
    "url_procedimento": "https://www.acingov.pt",
    "autor_nome": "Maria de Fátima Costa",
    "autor_cargo": "Técnica Superior de Compras e Logística"
  },
  {
    "numero_procedimento": "N/A",
    "entidade": "Município de Miranda do Douro",
    "link": "https://diariodarepublica.pt/dr/detalhe/contrato-publico/178-996320802",
    "detalhes_completos": "1 - IDENTIFICAÇÃO E CONTACTOS DA ENTIDADE ADJUDICANTE\nDesignação da entidade adjudicante: Município de Miranda do Douro\nNIPC: 506806898\nServiço/Órgão/Pessoa de contacto: Divisão Administrativa e Financeira-Serviço de Aprovisionamento\nEndereço: Largo D. João III\nCódigo postal: 5210-190\nLocalidade: Miranda do Douro\nPaís: Portugal\nNUT III: PT11E\nDistrito: Braganca\nConcelho: Miranda do Douro\nFreguesia: Freguesia de Miranda do Douro\nTelefone: 273430020\nFax: 273438005\nEndereço da Entidade (URL): www.cm-mdouro.pt\nEndereço Eletrónico: geral@cm-mdouro.pt\neDelivery Gateway (URL): https://www.acingov.pt\nFunção da Organização: Adquirente\nSubfunção da Organização: Organização que recebe as propostas\nNorma jurídica da Entidade Adjudicante: Organismo de direito público\nÁrea de atividade da Autoridade Adjudicante: Serviços públicos das administrações públicas\n2 - JORNAL OFICIAL DA UNIÃO EUROPEIA\nO procedimento a que este anúncio diz respeito também é publicitado no Jornal Oficial da União Europeia? Não\n3 - AVISO\nModelo de Anúncio: Concurso público\nData de Envio do Anúncio: 06-01-2026\n5 - PROCESSO\nTipo de Procedimento: Concurso público\nPreço base do procedimento: Sim\nValor do preço base do procedimento: 147.020,00 EUR\nProcedimento com lotes? Não\n6 - OBJETO DO CONTRATO\nNúmero de referência interna: CPN 10/DAF/2025\nDesignação do contrato: Aluguer e montagem de tendas, standes e outros equipamentos no Festival de Sabores Mirandeses 2026 e na Festa da Bola Doce e dos Produtos da Terra 2026\nDescrição: Aluguer e montagem de tendas, standes e outros equipamentos no Festival de Sabores Mirandeses 2026 e na Festa da Bola Doce e dos Produtos da Terra 2026\nTipo de Contrato Principal: Locação de Bens Móveis\nTipo de Contrato: Locação de Bens Móveis\nClassificação CPV (Vocabulário Comum para os Contratos Públicos)\nObjeto principal\nVocabulário Principal: 39522530\nPreço base s/IVA: 147.020,00 EUR\n7 - INDICAÇÕES ADICIONAIS\nO contrato envolve aquisição conjunta (satisfação de várias entidades)? Não\nO contrato é adjudicado por uma central de compras? Não\n8 - TÉCNICAS\nO concurso destina-se à celebração de um acordo-quadro? Inexistência de acordo-quadro\nÉ utilizado um leilão eletrónico? Não\nÉ adotada uma fase de negociação? Não\nSistema de Aquisição Dinâmico: Inexistência de sistema de aquisição dinâmico\n9 - LOCAL DA EXECUÇÃO DO CONTRATO\nLOCAL DA EXECUÇÃO DO CONTRATO (PROCEDIMENTO)\nPaís: Portugal\nNUT III: PT11E\nLocalidade: Freguesia de Miranda do Douro\nDistrito: Braganca\nConcelho: Miranda do Douro\nFreguesia: Freguesia de Miranda do Douro\n10 - PRAZO DE EXECUÇÃO DO CONTRATO\nPrazo de execução do contrato: 10 DIAS\nPrevisão de renovações: Não\n11 - FUNDOS EU\nTêm fundos EU? Não\n12 - DOCUMENTOS DE HABILITAÇÃO\nHabilitação para o exercício da atividade profissional: Não\n13 - CONDIÇÕES DE APRESENTAÇÃO\nPlataforma eletrónica utilizada pela entidade adjudicante: ACIN\nURL para Apresentação: https://www.acingov.pt\nAdmissibilidade da apresentação de propostas variantes: Não autorizado\nPrazo para apresentação das propostas: 18-01-2026 20:00\nPrazo durante o qual os concorrentes são obrigados a manter as respetivas propostas: 66 dias a contar do termo do prazo para a apresentação das propostas\nIndicação de Subcontratação na Proposta: Inexistência de indicação de subcontratação\n14 - PRESTAÇÃO DE CAUÇÃO\nPrestação de caução: Não\n15 - FORNECIMENTO DAS PEÇAS DO CONCURSO, APRESENTAÇÃO DE PEDIDOS DE PARTICIPAÇÃO E APRESENTAÇÃO DAS PROPOSTAS\nLink para acesso às peças do concurso (URL): https://www.acingov.pt/acingovprod/2/zonaPublica/zona_publica_c/donwloadProcedurePiece/MTAzNjA3Nw==\n20 - OUTROS REQUISITOS\nInformação sobre contratos reservados. Aplica-se a contratos reservados (54º-A)? Não\n21 - CRITÉRIO DE ADJUDICAÇÃO\nMultifator: Não\nMonofator:\nNome: Preço\n24 - CONDIÇÕES DO CONTRATO\nFaturação Eletrónica: Permitido\nObrigação de Subcontratação:\nCódigo da Obrigação de Subcontratação: Não é aplicável nenhuma obrigação de subcontratação.\n25 - COMPRA PÚBLICA ESTRATÉGICA\nCompra Pública Estratégica: Inexistência de contratação pública estratégica\n26 - INFORMAÇÕES ADICIONAIS\nContrato adequado para PME: Sim\nCobertura ACP (Acordo dos Contratos Públicos da Organização Mundial do Comércio): Não\n27 - IDENTIFICAÇÃO E CONTACTOS DO ÓRGÃO DE RECURSOS ADMINISTRATIVOS\nDesignação: Câmara Municipal de Miranda do Douro\nEndereço: Largo D. João III\nCódigo postal: 5210-190\nLocalidade: Miranda do Douro\nTelefone: 273430020\nFax: 273438005\nEndereço eletrónico: geral@cm-mdouro.pt\nPrazo de interposição do recurso: 5 dias\n28 - IDENTIFICAÇÃO DO(S) AUTOR(ES) DE ANÚNCIO\nNome: Helena Maria da Silva Ventura Barril\nCargo: Presidente da Câmara Municipal\n419947094",
    "nipc": "506806898",
    "distrito": "Braganca",
    "concelho": "Miranda do Douro",
    "freguesia": "Freguesia de Miranda do Douro",
    "site": "www.cm-mdouro.pt",
    "email": "geral@cm-mdouro.pt",
    "designacao_contrato": "Aluguer e montagem de tendas, standes e outros equipamentos no Festival de Sabores Mirandeses 2026 e na Festa da Bola Doce e dos Produtos da Terra 2026",
    "descricao": "Aluguer e montagem de tendas, standes e outros equipamentos no Festival de Sabores Mirandeses 2026 e na Festa da Bola Doce e dos Produtos da Terra 2026",
    "preco_base": "147.020,00 EUR",
    "prazo_execucao": "10 DIAS",
    "prazo_apresentacao_propostas": "18-01-2026 20:00",
    "fundos_eu": "Não",
    "plataforma_eletronica": "ACIN",
    "url_procedimento": "https://www.acingov.pt",
    "autor_nome": "Helena Maria da Silva Ventura Barril",
    "autor_cargo": "Presidente da Câmara Municipal"
  },
  {
    "numero_procedimento": "N/A",
    "entidade": "Unidade Local de Saúde de São José, EPE",
    "link": "https://diariodarepublica.pt/dr/detalhe/contrato-publico/181-996320804",
    "detalhes_completos": "1 - IDENTIFICAÇÃO E CONTACTOS DA ENTIDADE ADJUDICANTE\nDesignação da entidade adjudicante: Unidade Local de Saúde de São José, EPE\nNIPC: 508080142\nEndereço: Rua José António Serrano\nCódigo postal: 1150-199\nLocalidade: Lisboa\nPaís: Portugal\nNUT III: PT170\nDistrito: Lisboa\nConcelho: Lisboa\nFreguesia: Freguesia de Arroios - Lisboa\nTelefone: 218841403\nFax: 218841025\nEndereço da Entidade (URL): www.chlc.min-saude.pt\nEndereço Eletrónico: geral@chlc.min-saude.pt\neDelivery Gateway (URL): https://community.vortal.biz/public/\nFunção da Organização: Adquirente\nNorma jurídica da Entidade Adjudicante: Organismo de direito público\nÁrea de atividade da Autoridade Adjudicante: Saúde\n2 - JORNAL OFICIAL DA UNIÃO EUROPEIA\nO procedimento a que este anúncio diz respeito também é publicitado no Jornal Oficial da União Europeia? Não\n3 - AVISO\nModelo de Anúncio: Concurso público\nData de Envio do Anúncio: 06-01-2026\n5 - PROCESSO\nTipo de Procedimento: Concurso público\nPreço base do procedimento: Não\nProcedimento com lotes? Sim\nNº Máx. de Lotes Autorizado: 40\nNúmero máximo de lotes que podem ser adjudicados a um concorrente: 40\n6 - OBJETO DO CONTRATO\nNúmero de referência interna: 11000626\nDesignação do contrato: 11000626 - Aquisição de Matérias Primas e Desinfetantes\nDescrição: 11000626 - Aquisição de Matérias Primas e Desinfetantes\nTipo de Contrato Principal: Aquisição de Bens Móveis\nTipo de Contrato: Aquisição de Bens Móveis\nClassificação CPV (Vocabulário Comum para os Contratos Públicos)\nObjeto principal\nVocabulário Principal: 33600000\nLotes: \nNº: LOT-0001\nDescrição do Lote: Lote 1\nClassificação CPV (Vocabulário Comum para os Contratos Públicos)\nObjeto principal\nVocabulário Principal: 33600000\nNº: LOT-0002\nDescrição do Lote: Lote 2\nClassificação CPV (Vocabulário Comum para os Contratos Públicos)\nObjeto principal\nVocabulário Principal: 33600000\nNº: LOT-0003\nDescrição do Lote: Lote 3\nClassificação CPV (Vocabulário Comum para os Contratos Públicos)\nObjeto principal\nVocabulário Principal: 33600000\nNº: LOT-0004\nDescrição do Lote: Lote 4\nClassificação CPV (Vocabulário Comum para os Contratos Públicos)\nObjeto principal\nVocabulário Principal: 33600000\nNº: LOT-0005\nDescrição do Lote: Lote 5\nClassificação CPV (Vocabulário Comum para os Contratos Públicos)\nObjeto principal\nVocabulário Principal: 33600000\nNº: LOT-0006\nDescrição do Lote: Lote 6\nClassificação CPV (Vocabulário Comum para os Contratos Públicos)\nObjeto principal\nVocabulário Principal: 33600000\nNº: LOT-0007\nDescrição do Lote: Lote 7\nClassificação CPV (Vocabulário Comum para os Contratos Públicos)\nObjeto principal\nVocabulário Principal: 33600000\nNº: LOT-0008\nDescrição do Lote: Lote 8\nClassificação CPV (Vocabulário Comum para os Contratos Públicos)\nObjeto principal\nVocabulário Principal: 33600000\nNº: LOT-0009\nDescrição do Lote: Lote 9\nClassificação CPV (Vocabulário Comum para os Contratos Públicos)\nObjeto principal\nVocabulário Principal: 33600000\nNº: LOT-0010\nDescrição do Lote: Lote 10\nClassificação CPV (Vocabulário Comum para os Contratos Públicos)\nObjeto principal\nVocabulário Principal: 33600000\nNº: LOT-0011\nDescrição do Lote: Lote 11\nClassificação CPV (Vocabulário Comum para os Contratos Públicos)\nObjeto principal\nVocabulário Principal: 33600000\nNº: LOT-0012\nDescrição do Lote: Lote 12\nClassificação CPV (Vocabulário Comum para os Contratos Públicos)\nObjeto principal\nVocabulário Principal: 33600000\nNº: LOT-0013\nDescrição do Lote: Lote 13\nClassificação CPV (Vocabulário Comum para os Contratos Públicos)\nObjeto principal\nVocabulário Principal: 33600000\nNº: LOT-0014\nDescrição do Lote: Lote 14\nClassificação CPV (Vocabulário Comum para os Contratos Públicos)\nObjeto principal\nVocabulário Principal: 33600000\nNº: LOT-0015\nDescrição do Lote: Lote 15\nClassificação CPV (Vocabulário Comum para os Contratos Públicos)\nObjeto principal\nVocabulário Principal: 33600000\nNº: LOT-0016\nDescrição do Lote: Lote 16\nClassificação CPV (Vocabulário Comum para os Contratos Públicos)\nObjeto principal\nVocabulário Principal: 33600000\nNº: LOT-0017\nDescrição do Lote: Lote 17\nClassificação CPV (Vocabulário Comum para os Contratos Públicos)\nObjeto principal\nVocabulário Principal: 33600000\nNº: LOT-0018\nDescrição do Lote: Lote 18\nClassificação CPV (Vocabulário Comum para os Contratos Públicos)\nObjeto principal\nVocabulário Principal: 33600000\nNº: LOT-0019\nDescrição do Lote: Lote 19\nClassificação CPV (Vocabulário Comum para os Contratos Públicos)\nObjeto principal\nVocabulário Principal: 33600000\nNº: LOT-0020\nDescrição do Lote: Lote 20\nClassificação CPV (Vocabulário Comum para os Contratos Públicos)\nObjeto principal\nVocabulário Principal: 33600000\nNº: LOT-0021\nDescrição do Lote: Lote 21\nClassificação CPV (Vocabulário Comum para os Contratos Públicos)\nObjeto principal\nVocabulário Principal: 33600000\nNº: LOT-0022\nDescrição do Lote: Lote 22\nClassificação CPV (Vocabulário Comum para os Contratos Públicos)\nObjeto principal\nVocabulário Principal: 33600000\nNº: LOT-0023\nDescrição do Lote: Lote 23\nClassificação CPV (Vocabulário Comum para os Contratos Públicos)\nObjeto principal\nVocabulário Principal: 33600000\nNº: LOT-0024\nDescrição do Lote: Lote 24\nClassificação CPV (Vocabulário Comum para os Contratos Públicos)\nObjeto principal\nVocabulário Principal: 33600000\nNº: LOT-0025\nDescrição do Lote: Lote 25\nClassificação CPV (Vocabulário Comum para os Contratos Públicos)\nObjeto principal\nVocabulário Principal: 33600000\nNº: LOT-0026\nDescrição do Lote: Lote 26\nClassificação CPV (Vocabulário Comum para os Contratos Públicos)\nObjeto principal\nVocabulário Principal: 33600000\nNº: LOT-0027\nDescrição do Lote: Lote 27\nClassificação CPV (Vocabulário Comum para os Contratos Públicos)\nObjeto principal\nVocabulário Principal: 33600000\nNº: LOT-0028\nDescrição do Lote: Lote 28\nClassificação CPV (Vocabulário Comum para os Contratos Públicos)\nObjeto principal\nVocabulário Principal: 33600000\nNº: LOT-0029\nDescrição do Lote: Lote 29\nClassificação CPV (Vocabulário Comum para os Contratos Públicos)\nObjeto principal\nVocabulário Principal: 33600000\nNº: LOT-0030\nDescrição do Lote: Lote 30\nClassificação CPV (Vocabulário Comum para os Contratos Públicos)\nObjeto principal\nVocabulário Principal: 33600000\nNº: LOT-0031\nDescrição do Lote: Lote 31\nClassificação CPV (Vocabulário Comum para os Contratos Públicos)\nObjeto principal\nVocabulário Principal: 33600000\nNº: LOT-0032\nDescrição do Lote: Lote 32\nClassificação CPV (Vocabulário Comum para os Contratos Públicos)\nObjeto principal\nVocabulário Principal: 33600000\nNº: LOT-0033\nDescrição do Lote: Lote 33\nClassificação CPV (Vocabulário Comum para os Contratos Públicos)\nObjeto principal\nVocabulário Principal: 33600000\nNº: LOT-0034\nDescrição do Lote: Lote 34\nClassificação CPV (Vocabulário Comum para os Contratos Públicos)\nObjeto principal\nVocabulário Principal: 33600000\nNº: LOT-0035\nDescrição do Lote: Lote 35\nClassificação CPV (Vocabulário Comum para os Contratos Públicos)\nObjeto principal\nVocabulário Principal: 33600000\nNº: LOT-0036\nDescrição do Lote: Lote 36\nClassificação CPV (Vocabulário Comum para os Contratos Públicos)\nObjeto principal\nVocabulário Principal: 33600000\nNº: LOT-0037\nDescrição do Lote: Lote 37\nClassificação CPV (Vocabulário Comum para os Contratos Públicos)\nObjeto principal\nVocabulário Principal: 33600000\nNº: LOT-0038\nDescrição do Lote: Lote 38\nClassificação CPV (Vocabulário Comum para os Contratos Públicos)\nObjeto principal\nVocabulário Principal: 33600000\nNº: LOT-0039\nDescrição do Lote: Lote 39\nClassificação CPV (Vocabulário Comum para os Contratos Públicos)\nObjeto principal\nVocabulário Principal: 33600000\nNº: LOT-0040\nDescrição do Lote: Lote 40\nClassificação CPV (Vocabulário Comum para os Contratos Públicos)\nObjeto principal\nVocabulário Principal: 33600000\n7 - INDICAÇÕES ADICIONAIS\nO contrato envolve aquisição conjunta (satisfação de várias entidades)? Não\nO contrato é adjudicado por uma central de compras? Não\n8 - TÉCNICAS\nO concurso destina-se à celebração de um acordo-quadro? Inexistência de acordo-quadro\nÉ utilizado um leilão eletrónico? Não\nÉ adotada uma fase de negociação? Não\nSistema de Aquisição Dinâmico: Inexistência de sistema de aquisição dinâmico\n9 - LOCAL DA EXECUÇÃO DO CONTRATO\nLOCAL DA EXECUÇÃO DO CONTRATO (PROCEDIMENTO)\nPaís: Portugal\nNUT III: PT170\nLocalidade: Lisboa\nDistrito: Lisboa\nConcelho: Lisboa\nFreguesia: Freguesia de Arroios - Lisboa\nLOCAL DA EXECUÇÃO DO CONTRATO (LOTE)\nIdentificador do Lote: LOT-0001; LOT-0002; LOT-0003; LOT-0004; LOT-0005; LOT-0006; LOT-0007; LOT-0008; LOT-0009; LOT-0010; LOT-0011; LOT-0012; LOT-0013; LOT-0014; LOT-0015; LOT-0016; LOT-0017; LOT-0018; LOT-0019; LOT-0020; LOT-0021; LOT-0022; LOT-0023; LOT-0024; LOT-0025; LOT-0026; LOT-0027; LOT-0028; LOT-0029; LOT-0030; LOT-0031; LOT-0032; LOT-0033; LOT-0034; LOT-0035; LOT-0036; LOT-0037; LOT-0038; LOT-0039; LOT-0040\nPaís: Portugal\nNUT III: PT170\nLocalidade: Lisboa\nDistrito: Lisboa\nConcelho: Lisboa\nFreguesia: Freguesia de Arroios - Lisboa\n10 - PRAZO DE EXECUÇÃO DO CONTRATO\nIdentificador do Lote: LOT-0001; LOT-0002; LOT-0003; LOT-0004; LOT-0005; LOT-0006; LOT-0007; LOT-0008; LOT-0009; LOT-0010; LOT-0011; LOT-0012; LOT-0013; LOT-0014; LOT-0015; LOT-0016; LOT-0017; LOT-0018; LOT-0019; LOT-0020; LOT-0021; LOT-0022; LOT-0023; LOT-0024; LOT-0025; LOT-0026; LOT-0027; LOT-0028; LOT-0029; LOT-0030; LOT-0031; LOT-0032; LOT-0033; LOT-0034; LOT-0035; LOT-0036; LOT-0037; LOT-0038; LOT-0039; LOT-0040\nPrazo de execução do contrato: 3 ANOS\nPrevisão de renovações: Sim\nIndicar número máximo de renovações: 2\nPrazo de renovações diferente do prazo inicial: Não\n11 - FUNDOS EU\nIdentificador do Lote: LOT-0001; LOT-0002; LOT-0003; LOT-0004; LOT-0005; LOT-0006; LOT-0007; LOT-0008; LOT-0009; LOT-0010; LOT-0011; LOT-0012; LOT-0013; LOT-0014; LOT-0015; LOT-0016; LOT-0017; LOT-0018; LOT-0019; LOT-0020; LOT-0021; LOT-0022; LOT-0023; LOT-0024; LOT-0025; LOT-0026; LOT-0027; LOT-0028; LOT-0029; LOT-0030; LOT-0031; LOT-0032; LOT-0033; LOT-0034; LOT-0035; LOT-0036; LOT-0037; LOT-0038; LOT-0039; LOT-0040\nTêm fundos EU? Não\n12 - DOCUMENTOS DE HABILITAÇÃO\nHabilitação para o exercício da atividade profissional: Não\n13 - CONDIÇÕES DE APRESENTAÇÃO\nPlataforma eletrónica utilizada pela entidade adjudicante: VORTAL\nURL para Apresentação: https://community.vortal.biz/public/\nAdmissibilidade da apresentação de propostas variantes: Não autorizado\nPrazo para apresentação das propostas: 13-01-2026 23:59\nPrazo durante o qual os concorrentes são obrigados a manter as respetivas propostas: 120 dias a contar do termo do prazo para a apresentação das propostas\nIndicação de Subcontratação na Proposta: Inexistência de indicação de subcontratação\n14 - PRESTAÇÃO DE CAUÇÃO\nPrestação de caução: Não\n15 - FORNECIMENTO DAS PEÇAS DO CONCURSO, APRESENTAÇÃO DE PEDIDOS DE PARTICIPAÇÃO E APRESENTAÇÃO DAS PROPOSTAS\nLink para acesso às peças do concurso (URL): https://community.vortal.biz/Public/public-tender-documents/KytKYVpPSDhRNjZWNGQxZWhOWTNTcWNBeUo2Yzd4dmJwcmI5dG1EYW1wMTBOQzJjeDd4Y04vUU1oRDJSWlIyUzhFYWt3SUttb3lKSW5wUTk2Z2RES1E9PWhqR2pt\n20 - OUTROS REQUISITOS\nIdentificador do Lote: LOT-0001; LOT-0002; LOT-0003; LOT-0004; LOT-0005; LOT-0006; LOT-0007; LOT-0008; LOT-0009; LOT-0010; LOT-0011; LOT-0012; LOT-0013; LOT-0014; LOT-0015; LOT-0016; LOT-0017; LOT-0018; LOT-0019; LOT-0020; LOT-0021; LOT-0022; LOT-0023; LOT-0024; LOT-0025; LOT-0026; LOT-0027; LOT-0028; LOT-0029; LOT-0030; LOT-0031; LOT-0032; LOT-0033; LOT-0034; LOT-0035; LOT-0036; LOT-0037; LOT-0038; LOT-0039; LOT-0040\nInformação sobre contratos reservados. Aplica-se a contratos reservados (54º-A)? Não\n21 - CRITÉRIO DE ADJUDICAÇÃO\nO Critério de adjudicação é diferenciado por lote? Não\nMultifator: Não\nMonofator:\nNome: Qualidade\n24 - CONDIÇÕES DO CONTRATO\nIdentificador do Lote: LOT-0001; LOT-0002; LOT-0003; LOT-0004; LOT-0005; LOT-0006; LOT-0007; LOT-0008; LOT-0009; LOT-0010; LOT-0011; LOT-0012; LOT-0013; LOT-0014; LOT-0015; LOT-0016; LOT-0017; LOT-0018; LOT-0019; LOT-0020; LOT-0021; LOT-0022; LOT-0023; LOT-0024; LOT-0025; LOT-0026; LOT-0027; LOT-0028; LOT-0029; LOT-0030; LOT-0031; LOT-0032; LOT-0033; LOT-0034; LOT-0035; LOT-0036; LOT-0037; LOT-0038; LOT-0039; LOT-0040\nFaturação Eletrónica: Permitido\nObrigação de Subcontratação:\nCódigo da Obrigação de Subcontratação: Não é aplicável nenhuma obrigação de subcontratação.\n25 - COMPRA PÚBLICA ESTRATÉGICA\nCompra Pública Estratégica: Inexistência de contratação pública estratégica\n26 - INFORMAÇÕES ADICIONAIS\nIdentificador do Lote: LOT-0001; LOT-0002; LOT-0003; LOT-0004; LOT-0005; LOT-0006; LOT-0007; LOT-0008; LOT-0009; LOT-0010; LOT-0011; LOT-0012; LOT-0013; LOT-0014; LOT-0015; LOT-0016; LOT-0017; LOT-0018; LOT-0019; LOT-0020; LOT-0021; LOT-0022; LOT-0023; LOT-0024; LOT-0025; LOT-0026; LOT-0027; LOT-0028; LOT-0029; LOT-0030; LOT-0031; LOT-0032; LOT-0033; LOT-0034; LOT-0035; LOT-0036; LOT-0037; LOT-0038; LOT-0039; LOT-0040\nContrato adequado para PME: Sim\nCobertura ACP (Acordo dos Contratos Públicos da Organização Mundial do Comércio): Não\n27 - IDENTIFICAÇÃO E CONTACTOS DO ÓRGÃO DE RECURSOS ADMINISTRATIVOS\nDesignação: Conselho de Administração da ULS S. José, E.P.E.\nEndereço: RUA JOSÉ ANTÓNIO SERRANO.\nCódigo postal: 1150-199\nLocalidade: Lisboa\nTelefone: +351 218841000\nFax: +351 218841088\nEndereço eletrónico: sec.vca@ulssjose.min-saude.pt\n28 - IDENTIFICAÇÃO DO(S) AUTOR(ES) DE ANÚNCIO\nNome: Conselho de Administração da ULS S. José, E.P.E.\nCargo: Conselho de Administração da ULS S. José, E.P.E.\n419947143",
    "nipc": "508080142",
    "distrito": "Lisboa",
    "concelho": "Lisboa",
    "freguesia": "Freguesia de Arroios - Lisboa",
    "site": "www.chlc.min-saude.pt",
    "email": "geral@chlc.min-saude.pt",
    "designacao_contrato": "11000626 - Aquisição de Matérias Primas e Desinfetantes",
    "descricao": "11000626 - Aquisição de Matérias Primas e Desinfetantes",
    "preco_base": null,
    "prazo_execucao": "3 ANOS",
    "prazo_apresentacao_propostas": "13-01-2026 23:59",
    "fundos_eu": "Não",
    "plataforma_eletronica": "VORTAL",
    "url_procedimento": "https://community.vortal.biz/public/",
    "autor_nome": "Conselho de Administração da ULS S. José, E.P.E.",
    "autor_cargo": "Conselho de Administração da ULS S. José, E.P.E."
  },
  {
    "numero_procedimento": "N/A",
    "entidade": "Unidade Local de Saúde de São João, EPE",
    "link": "https://diariodarepublica.pt/dr/detalhe/contrato-publico/183-996320805",
    "detalhes_completos": "1 - IDENTIFICAÇÃO E CONTACTOS DA ENTIDADE ADJUDICANTE\nDesignação da entidade adjudicante: Unidade Local de Saúde de São João, EPE\nNIPC: 509821197\nServiço/Órgão/Pessoa de contacto: Serviço de Aprovisionamento\nEndereço: Alameda Prof. Hernâni Monteiro\nCódigo postal: 4200-319\nLocalidade: Área Metropolitana do Porto\nPaís: Portugal\nNUT III: PT11A\nDistrito: Porto\nConcelho: Porto\nFreguesia: Freguesia de Paranhos - Porto\nTelefone: 225512100\nFax: 225504463\nEndereço da Entidade (URL): https://portal-chsj.min-saude.pt/\nEndereço Eletrónico: geral@ulssjoao.min-saude.pt\neDelivery Gateway (URL): https://community.vortal.biz/public/\nFunção da Organização: Adquirente\nNorma jurídica da Entidade Adjudicante: Organismo de direito público\nÁrea de atividade da Autoridade Adjudicante: Saúde\n2 - JORNAL OFICIAL DA UNIÃO EUROPEIA\nO procedimento a que este anúncio diz respeito também é publicitado no Jornal Oficial da União Europeia? Não\n3 - AVISO\nModelo de Anúncio: Concurso público\nData de Envio do Anúncio: 06-01-2026\n5 - PROCESSO\nTipo de Procedimento: Concurso público\nPreço base do procedimento: Sim\nValor do preço base do procedimento: 81.000,00 EUR\nProcedimento com lotes? Não\n6 - OBJETO DO CONTRATO\nNúmero de referência interna: 61000126\nDesignação do contrato: Aquisição de Solução de Desinfeção por Peróxido de Hidrogénio com Iões de Prata\nDescrição: Aquisição de Solução de Desinfeção por Peróxido de Hidrogénio com Iões de Prata\nTipo de Contrato Principal: Aquisição de Bens Móveis\nTipo de Contrato: Aquisição de Bens Móveis\nClassificação CPV (Vocabulário Comum para os Contratos Públicos)\nObjeto principal\nVocabulário Principal: 24900000\nPreço base s/IVA: 81.000,00 EUR\n7 - INDICAÇÕES ADICIONAIS\nO contrato envolve aquisição conjunta (satisfação de várias entidades)? Não\nO contrato é adjudicado por uma central de compras? Não\n8 - TÉCNICAS\nO concurso destina-se à celebração de um acordo-quadro? Inexistência de acordo-quadro\nÉ utilizado um leilão eletrónico? Não\nÉ adotada uma fase de negociação? Não\nSistema de Aquisição Dinâmico: Inexistência de sistema de aquisição dinâmico\n9 - LOCAL DA EXECUÇÃO DO CONTRATO\nLOCAL DA EXECUÇÃO DO CONTRATO (PROCEDIMENTO)\nPaís: Portugal\nNUT III: PT11A\nLocalidade: Área Metropolitana do Porto\nDistrito: Porto\nConcelho: Porto\nFreguesia: Freguesia de Paranhos - Porto\n10 - PRAZO DE EXECUÇÃO DO CONTRATO\nPrazo de execução do contrato: 36 MESES\nPrevisão de renovações: Não\n11 - FUNDOS EU\nTêm fundos EU? Não\n12 - DOCUMENTOS DE HABILITAÇÃO\nHabilitação para o exercício da atividade profissional: Não\n13 - CONDIÇÕES DE APRESENTAÇÃO\nPlataforma eletrónica utilizada pela entidade adjudicante: VORTAL\nURL para Apresentação: https://community.vortal.biz/public/\nAdmissibilidade da apresentação de propostas variantes: Não autorizado\nPrazo para apresentação das propostas: 15-01-2026 17:00\nPrazo durante o qual os concorrentes são obrigados a manter as respetivas propostas: 90 dias a contar do termo do prazo para a apresentação das propostas\nIndicação de Subcontratação na Proposta: Inexistência de indicação de subcontratação\n14 - PRESTAÇÃO DE CAUÇÃO\nPrestação de caução: Não\n15 - FORNECIMENTO DAS PEÇAS DO CONCURSO, APRESENTAÇÃO DE PEDIDOS DE PARTICIPAÇÃO E APRESENTAÇÃO DAS PROPOSTAS\nLink para acesso às peças do concurso (URL): https://community.vortal.biz/Public/public-tender-documents/S3h4VEJUZ1RjSUIyTm9NQnV6MnVTTDExWnZTcDMwZ0MxRmtMTTlFRW15SElad2VQQkN0bFZ1TGNuT2QwS21tc1JUbE5NUllRay9wVDhwOWN1Q0YvMHc9PVZIZ0kr\n20 - OUTROS REQUISITOS\nInformação sobre contratos reservados. Aplica-se a contratos reservados (54º-A)? Não\n21 - CRITÉRIO DE ADJUDICAÇÃO\nMultifator: Sim\nFator: \nNome: Preço\nPonderação: 80%\nSubfatores: Não\nFator: \nNome: Qualidade\nPonderação: 20%\nSubfatores: Não\n24 - CONDIÇÕES DO CONTRATO\nFaturação Eletrónica: Permitido\nObrigação de Subcontratação:\nCódigo da Obrigação de Subcontratação: Não é aplicável nenhuma obrigação de subcontratação.\n25 - COMPRA PÚBLICA ESTRATÉGICA\nCompra Pública Estratégica: Inexistência de contratação pública estratégica\n26 - INFORMAÇÕES ADICIONAIS\nContrato adequado para PME: Sim\nCobertura ACP (Acordo dos Contratos Públicos da Organização Mundial do Comércio): Não\n27 - IDENTIFICAÇÃO E CONTACTOS DO ÓRGÃO DE RECURSOS ADMINISTRATIVOS\nDesignação: Conselho de Administração\nEndereço: ULS São João - Alameda Professor Hernani Monteiro\nCódigo postal: 4200-319\nLocalidade: Porto\nTelefone: +351 225512100\nFax: +351 225025766\nEndereço eletrónico: ca@ulssjoao.min-saude.pt\n28 - IDENTIFICAÇÃO DO(S) AUTOR(ES) DE ANÚNCIO\nNome: Tiago Ferreira\nCargo: Diretor do Serviço de Aprovisionamento\n419947226",
    "nipc": "509821197",
    "distrito": "Porto",
    "concelho": "Porto",
    "freguesia": "Freguesia de Paranhos - Porto",
    "site": "https://portal-chsj.min-saude.pt/",
    "email": "geral@ulssjoao.min-saude.pt",
    "designacao_contrato": "Aquisição de Solução de Desinfeção por Peróxido de Hidrogénio com Iões de Prata",
    "descricao": "Aquisição de Solução de Desinfeção por Peróxido de Hidrogénio com Iões de Prata",
    "preco_base": "81.000,00 EUR",
    "prazo_execucao": "36 MESES",
    "prazo_apresentacao_propostas": "15-01-2026 17:00",
    "fundos_eu": "Não",
    "plataforma_eletronica": "VORTAL",
    "url_procedimento": "https://community.vortal.biz/public/",
    "autor_nome": "Tiago Ferreira",
    "autor_cargo": "Diretor do Serviço de Aprovisionamento"
  },
  {
    "numero_procedimento": "N/A",
    "entidade": "Município de Bragança",
    "link": "https://diariodarepublica.pt/dr/detalhe/contrato-publico/185-996320810",
    "detalhes_completos": "1 - IDENTIFICAÇÃO E CONTACTOS DA ENTIDADE ADJUDICANTE\nDesignação da entidade adjudicante: Município de Bragança\nNIPC: 506215547\nServiço/Órgão/Pessoa de contacto: Presidente\nEndereço: Forte São João de Deus 5300-263 Bragança\nCódigo postal: 5300-263\nLocalidade: Bragança\nPaís: Portugal\nNUT III: PT11E\nDistrito: Braganca\nConcelho: Bragança\nFreguesia: União das Freguesias de Sé, Santa Maria e Meixedo\nTelefone: 273304216\nFax: 273304299\nEndereço da Entidade (URL): www.cm-braganca.pt\nEndereço Eletrónico: cmb@cm-braganca.pt\neDelivery Gateway (URL): https://www.acingov.pt\nFunção da Organização: Adquirente\nNorma jurídica da Entidade Adjudicante: Organismo de direito público\nÁrea de atividade da Autoridade Adjudicante: Serviços públicos das administrações públicas\n2 - JORNAL OFICIAL DA UNIÃO EUROPEIA\nO procedimento a que este anúncio diz respeito também é publicitado no Jornal Oficial da União Europeia? Não\n3 - AVISO\nModelo de Anúncio: Concurso público\nData de Envio do Anúncio: 06-01-2026\n5 - PROCESSO\nTipo de Procedimento: Concurso público\nPreço base do procedimento: Sim\nValor do preço base do procedimento: 105.000,00 EUR\nProcedimento com lotes? Não\n6 - OBJETO DO CONTRATO\nNúmero de referência interna: 42/2025-CP-UDJ\nDesignação do contrato: Aquisição de serviços para organização do evento Bragança Gaming Takeover 2026\nDescrição: Aquisição de serviços para organização do evento Bragança Gaming Takeover 2026\nTipo de Contrato Principal: Aquisição de Serviços\nTipo de Contrato: Aquisição de Serviços\nClassificação CPV (Vocabulário Comum para os Contratos Públicos)\nObjeto principal\nVocabulário Principal: 79952000\nPreço base s/IVA: 105.000,00 EUR\n7 - INDICAÇÕES ADICIONAIS\nO contrato envolve aquisição conjunta (satisfação de várias entidades)? Não\nO contrato é adjudicado por uma central de compras? Não\n8 - TÉCNICAS\nO concurso destina-se à celebração de um acordo-quadro? Inexistência de acordo-quadro\nÉ utilizado um leilão eletrónico? Não\nÉ adotada uma fase de negociação? Não\nSistema de Aquisição Dinâmico: Inexistência de sistema de aquisição dinâmico\n9 - LOCAL DA EXECUÇÃO DO CONTRATO\nLOCAL DA EXECUÇÃO DO CONTRATO (PROCEDIMENTO)\nPaís: Portugal\nNUT III: PT11E\nLocalidade: União das Freguesias de Sé, Santa Maria e Meixedo\nDistrito: Braganca\nConcelho: Bragança\nFreguesia: União das Freguesias de Sé, Santa Maria e Meixedo\n10 - PRAZO DE EXECUÇÃO DO CONTRATO\nPrazo de execução do contrato: 6 MESES\nPrevisão de renovações: Não\n11 - FUNDOS EU\nTêm fundos EU? Não\n12 - DOCUMENTOS DE HABILITAÇÃO\nHabilitação para o exercício da atividade profissional: Não\n13 - CONDIÇÕES DE APRESENTAÇÃO\nPlataforma eletrónica utilizada pela entidade adjudicante: ACIN\nURL para Apresentação: https://www.acingov.pt\nAdmissibilidade da apresentação de propostas variantes: Não autorizado\nPrazo para apresentação das propostas: 12-01-2026 23:59\nPrazo durante o qual os concorrentes são obrigados a manter as respetivas propostas: 66 dias a contar do termo do prazo para a apresentação das propostas\nIndicação de Subcontratação na Proposta: Inexistência de indicação de subcontratação\n14 - PRESTAÇÃO DE CAUÇÃO\nPrestação de caução: Não\n15 - FORNECIMENTO DAS PEÇAS DO CONCURSO, APRESENTAÇÃO DE PEDIDOS DE PARTICIPAÇÃO E APRESENTAÇÃO DAS PROPOSTAS\nLink para acesso às peças do concurso (URL): https://www.acingov.pt/acingovprod/2/zonaPublica/zona_publica_c/donwloadProcedurePiece/MTAzNjE0Ng==\n20 - OUTROS REQUISITOS\nInformação sobre contratos reservados. Aplica-se a contratos reservados (54º-A)? Não\n21 - CRITÉRIO DE ADJUDICAÇÃO\nMultifator: Não\nMonofator:\nNome: Preço\n24 - CONDIÇÕES DO CONTRATO\nFaturação Eletrónica: Permitido\nObrigação de Subcontratação:\nCódigo da Obrigação de Subcontratação: Não é aplicável nenhuma obrigação de subcontratação.\n25 - COMPRA PÚBLICA ESTRATÉGICA\nCompra Pública Estratégica: Inexistência de contratação pública estratégica\n26 - INFORMAÇÕES ADICIONAIS\nContrato adequado para PME: Não\nCobertura ACP (Acordo dos Contratos Públicos da Organização Mundial do Comércio): Não\n27 - IDENTIFICAÇÃO E CONTACTOS DO ÓRGÃO DE RECURSOS ADMINISTRATIVOS\nDesignação: Câmara Municipal de Bragança\nEndereço: Forte S. J. Deus\nCódigo postal: 5300-263\nLocalidade: Bragança\nTelefone: 273304200\nFax: \nEndereço eletrónico: cmb@cm-braganca.pt\nPrazo de interposição do recurso: 5 dias\n28 - IDENTIFICAÇÃO DO(S) AUTOR(ES) DE ANÚNCIO\nNome: Isabel Cristina Fernandes Rodrigues Ferreira\nCargo: Presidente da Câmara Municipal\n419947144",
    "nipc": "506215547",
    "distrito": "Braganca",
    "concelho": "Bragança",
    "freguesia": "União das Freguesias de Sé, Santa Maria e Meixedo",
    "site": "www.cm-braganca.pt",
    "email": "cmb@cm-braganca.pt",
    "designacao_contrato": "Aquisição de serviços para organização do evento Bragança Gaming Takeover 2026",
    "descricao": "Aquisição de serviços para organização do evento Bragança Gaming Takeover 2026",
    "preco_base": "105.000,00 EUR",
    "prazo_execucao": "6 MESES",
    "prazo_apresentacao_propostas": "12-01-2026 23:59",
    "fundos_eu": "Não",
    "plataforma_eletronica": "ACIN",
    "url_procedimento": "https://www.acingov.pt",
    "autor_nome": "Isabel Cristina Fernandes Rodrigues Ferreira",
    "autor_cargo": "Presidente da Câmara Municipal"
  },
  {
    "numero_procedimento": "N/A",
    "entidade": "AGERE- Empresa de Águas Efluentes e Resíduos de Braga, EM",
    "link": "https://diariodarepublica.pt/dr/detalhe/contrato-publico/177-998488105",
    "detalhes_completos": "1 - IDENTIFICAÇÃO E CONTACTOS DA ENTIDADE ADJUDICANTE\nDesignação da entidade adjudicante: AGERE- Empresa de Águas Efluentes e Resíduos de Braga, EM\nNIPC: 504807692\nEndereço: Praça Conde de Agrolongo, 115\nCódigo postal: 4700-312\nLocalidade: Braga\nPaís: Portugal\nNUT III: PT112\nDistrito: Braga\nConcelho: Braga\nFreguesia: Todas\nTelefone: 253205000\nFax: 253205075\nEndereço da Entidade (URL): www.agere.pt\nEndereço Eletrónico: agere@agere.pt\neDelivery Gateway (URL): https://community.vortal.biz/public/\nFunção da Organização: Adquirente\nNorma jurídica da Entidade Adjudicante: Empresa pública\nÁrea de atividade da Entidade Adjudicante: Atividades relacionadas com a água\n2 - JORNAL OFICIAL DA UNIÃO EUROPEIA\nO procedimento a que este anúncio diz respeito também é publicitado no Jornal Oficial da União Europeia? Não\n3 - AVISO\nModelo de Anúncio: Concurso público\nData de Envio do Anúncio: 06-01-2026\n5 - PROCESSO\nTipo de Procedimento: Concurso público\nPreço base do procedimento: Sim\nValor do preço base do procedimento: 77.740,00 EUR\nProcedimento com lotes? Não\n6 - OBJETO DO CONTRATO\nNúmero de referência interna: CP DC 45/2025\nDesignação do contrato: SERVIÇOS DE REALIZAÇÃO DE INSPEÇÃO DE RAMAIS DOMICILIÁRIOS COM RECURSO À VIDEOSCOPIA\nDescrição: SERVIÇOS DE REALIZAÇÃO DE INSPEÇÃO DE RAMAIS DOMICILIÁRIOS COM RECURSO À VIDEOSCOPIA\nTipo de Contrato Principal: Aquisição de Serviços\nTipo de Contrato: Aquisição de Serviços\nClassificação CPV (Vocabulário Comum para os Contratos Públicos)\nObjeto principal\nVocabulário Principal: 71631430\nPreço base s/IVA: 77.740,00 EUR\n7 - INDICAÇÕES ADICIONAIS\nO contrato envolve aquisição conjunta (satisfação de várias entidades)? Não\nO contrato é adjudicado por uma central de compras? Não\n8 - TÉCNICAS\nO concurso destina-se à celebração de um acordo-quadro? Inexistência de acordo-quadro\nÉ utilizado um leilão eletrónico? Não\nÉ adotada uma fase de negociação? Não\nSistema de Aquisição Dinâmico: Inexistência de sistema de aquisição dinâmico\n9 - LOCAL DA EXECUÇÃO DO CONTRATO\nLOCAL DA EXECUÇÃO DO CONTRATO (PROCEDIMENTO)\nPaís: Portugal\nNUT III: PT112\nLocalidade: Braga\nDistrito: Braga\nConcelho: Braga\nFreguesia: União das Freguesias de Braga (São José de São Lázaro e São João do Souto)\n10 - PRAZO DE EXECUÇÃO DO CONTRATO\nPrazo de execução do contrato: 3 ANOS\nPrevisão de renovações: Não\n11 - FUNDOS EU\nTêm fundos EU? Não\n12 - DOCUMENTOS DE HABILITAÇÃO\nHabilitação para o exercício da atividade profissional: Não\n13 - CONDIÇÕES DE APRESENTAÇÃO\nPlataforma eletrónica utilizada pela entidade adjudicante: VORTAL\nURL para Apresentação: https://community.vortal.biz/public/\nAdmissibilidade da apresentação de propostas variantes: Não autorizado\nPrazo para apresentação das propostas: 15-01-2026 17:00\nPrazo durante o qual os concorrentes são obrigados a manter as respetivas propostas: 66 dias a contar do termo do prazo para a apresentação das propostas\nIndicação de Subcontratação na Proposta: Inexistência de indicação de subcontratação\n14 - PRESTAÇÃO DE CAUÇÃO\nPrestação de caução: Não\n15 - FORNECIMENTO DAS PEÇAS DO CONCURSO, APRESENTAÇÃO DE PEDIDOS DE PARTICIPAÇÃO E APRESENTAÇÃO DAS PROPOSTAS\nLink para acesso às peças do concurso (URL): https://community.vortal.biz/Public/public-tender-documents/ZWxZMWVxeG10RXBkOVEvR3ZoeFpoWCtQRExpRUZLVlNIVDZVUnRkTUNZYkRQZ1lNQVY0Y2hFWjhMM0NsQlRkRkVlSnhPYlYvbVBtOGg3bEphWG1NWmc9PSpCV3Q3\n20 - OUTROS REQUISITOS\nInformação sobre contratos reservados. Aplica-se a contratos reservados (54º-A)? Não\n21 - CRITÉRIO DE ADJUDICAÇÃO\nMultifator: Não\nMonofator:\nNome: Preço\n24 - CONDIÇÕES DO CONTRATO\nFaturação Eletrónica: Permitido\nObrigação de Subcontratação:\nCódigo da Obrigação de Subcontratação: Não é aplicável nenhuma obrigação de subcontratação.\n25 - COMPRA PÚBLICA ESTRATÉGICA\nCompra Pública Estratégica: Inexistência de contratação pública estratégica\n26 - INFORMAÇÕES ADICIONAIS\nContrato adequado para PME: Sim\nCobertura ACP (Acordo dos Contratos Públicos da Organização Mundial do Comércio): Não\n27 - IDENTIFICAÇÃO E CONTACTOS DO ÓRGÃO DE RECURSOS ADMINISTRATIVOS\nDesignação: Conselho de Administração da AGERE EM\nEndereço: Praça Conde de Agrolongo, 115\nCódigo postal: 4700-312\nLocalidade: Braga\nTelefone: +351 253205001\nFax: +351 253205075\nEndereço eletrónico: administracao@agere.pt\n28 - IDENTIFICAÇÃO DO(S) AUTOR(ES) DE ANÚNCIO\nNome: Engª Paula Campos\nCargo: Administradora Executiva\n419947233",
    "nipc": "504807692",
    "distrito": "Braga",
    "concelho": "Braga",
    "freguesia": "Todas",
    "site": "www.agere.pt",
    "email": "agere@agere.pt",
    "designacao_contrato": "SERVIÇOS DE REALIZAÇÃO DE INSPEÇÃO DE RAMAIS DOMICILIÁRIOS COM RECURSO À VIDEOSCOPIA",
    "descricao": "SERVIÇOS DE REALIZAÇÃO DE INSPEÇÃO DE RAMAIS DOMICILIÁRIOS COM RECURSO À VIDEOSCOPIA",
    "preco_base": "77.740,00 EUR",
    "prazo_execucao": "3 ANOS",
    "prazo_apresentacao_propostas": "15-01-2026 17:00",
    "fundos_eu": "Não",
    "plataforma_eletronica": "VORTAL",
    "url_procedimento": "https://community.vortal.biz/public/",
    "autor_nome": "Engª Paula Campos",
    "autor_cargo": "Administradora Executiva"
  },
  {
    "numero_procedimento": "N/A",
    "entidade": "Unidade Local de Saúde do Oeste, EPE",
    "link": "https://diariodarepublica.pt/dr/detalhe/contrato-publico/179-998488106",
    "detalhes_completos": "1 - IDENTIFICAÇÃO E CONTACTOS DA ENTIDADE ADJUDICANTE\nDesignação da entidade adjudicante: Unidade Local de Saúde do Oeste, EPE\nNIPC: 514993871\nEndereço: Rua Diário de Notícias\nCódigo postal: 2500-176\nLocalidade: Leiria\nPaís: Portugal\nNUT III: PT16B\nDistrito: Leiria\nConcelho: Caldas da Rainha\nFreguesia: União das Freguesias de Caldas da Rainha - Nossa Senhora do Pópulo, Coto e São Gregório\nTelefone: 262830300\nFax: 262830300\nEndereço da Entidade (URL): https://www.choeste.min-saude.pt\nEndereço Eletrónico: aprovisionamento@choeste.min-saude.pt\neDelivery Gateway (URL): https://community.vortal.biz/public/\nFunção da Organização: Adquirente\nNorma jurídica da Entidade Adjudicante: Organismo de direito público\nÁrea de atividade da Autoridade Adjudicante: Saúde\n2 - JORNAL OFICIAL DA UNIÃO EUROPEIA\nO procedimento a que este anúncio diz respeito também é publicitado no Jornal Oficial da União Europeia? Não\n3 - AVISO\nModelo de Anúncio: Concurso público\nData de Envio do Anúncio: 06-01-2026\n5 - PROCESSO\nTipo de Procedimento: Concurso público\nPreço base do procedimento: Sim\nValor do preço base do procedimento: 6.865,30 EUR\nProcedimento com lotes? Sim\nNº Máx. de Lotes Autorizado: 9\nNúmero máximo de lotes que podem ser adjudicados a um concorrente: 9\n6 - OBJETO DO CONTRATO\nNúmero de referência interna: 11000426\nDesignação do contrato: Aquisição de Medicamentos Anti -Infeciosos 2026\nDescrição: Aquisição de Medicamentos Anti -Infeciosos 2026\nTipo de Contrato Principal: Aquisição de Bens Móveis\nTipo de Contrato: Aquisição de Bens Móveis\nClassificação CPV (Vocabulário Comum para os Contratos Públicos)\nObjeto principal\nVocabulário Principal: 33600000\nPreço base s/IVA: 6.865,30 EUR\nLotes: \nNº: LOT-0001\nDescrição do Lote: Lote 1\nPreço base s/IVA: 402,00 EUR\nClassificação CPV (Vocabulário Comum para os Contratos Públicos)\nObjeto principal\nVocabulário Principal: 33600000\nNº: LOT-0002\nDescrição do Lote: Lote 2\nPreço base s/IVA: 100,00 EUR\nClassificação CPV (Vocabulário Comum para os Contratos Públicos)\nObjeto principal\nVocabulário Principal: 33600000\nNº: LOT-0003\nDescrição do Lote: Lote 3\nPreço base s/IVA: 609,36 EUR\nClassificação CPV (Vocabulário Comum para os Contratos Públicos)\nObjeto principal\nVocabulário Principal: 33600000\nNº: LOT-0004\nDescrição do Lote: Lote 4\nPreço base s/IVA: 853,60 EUR\nClassificação CPV (Vocabulário Comum para os Contratos Públicos)\nObjeto principal\nVocabulário Principal: 33600000\nNº: LOT-0005\nDescrição do Lote: Lote 5\nPreço base s/IVA: 1.557,96 EUR\nClassificação CPV (Vocabulário Comum para os Contratos Públicos)\nObjeto principal\nVocabulário Principal: 33600000\nNº: LOT-0006\nDescrição do Lote: Lote 6\nPreço base s/IVA: 152,00 EUR\nClassificação CPV (Vocabulário Comum para os Contratos Públicos)\nObjeto principal\nVocabulário Principal: 33600000\nNº: LOT-0007\nDescrição do Lote: Lote 7\nPreço base s/IVA: 104,40 EUR\nClassificação CPV (Vocabulário Comum para os Contratos Públicos)\nObjeto principal\nVocabulário Principal: 33600000\nNº: LOT-0008\nDescrição do Lote: Lote 8\nPreço base s/IVA: 2.160,00 EUR\nClassificação CPV (Vocabulário Comum para os Contratos Públicos)\nObjeto principal\nVocabulário Principal: 33600000\nNº: LOT-0009\nDescrição do Lote: Lote 9\nPreço base s/IVA: 925,98 EUR\nClassificação CPV (Vocabulário Comum para os Contratos Públicos)\nObjeto principal\nVocabulário Principal: 33600000\n7 - INDICAÇÕES ADICIONAIS\nO contrato envolve aquisição conjunta (satisfação de várias entidades)? Não\nO contrato é adjudicado por uma central de compras? Não\n8 - TÉCNICAS\nO concurso destina-se à celebração de um acordo-quadro? Inexistência de acordo-quadro\nÉ utilizado um leilão eletrónico? Não\nÉ adotada uma fase de negociação? Não\nSistema de Aquisição Dinâmico: Inexistência de sistema de aquisição dinâmico\n9 - LOCAL DA EXECUÇÃO DO CONTRATO\nLOCAL DA EXECUÇÃO DO CONTRATO (PROCEDIMENTO)\nPaís: Portugal\nNUT III: PT16B\nLocalidade: Leiria\nDistrito: Leiria\nConcelho: Caldas da Rainha\nFreguesia: União das Freguesias de Caldas da Rainha - Nossa Senhora do Pópulo, Coto e São Gregório\nLOCAL DA EXECUÇÃO DO CONTRATO (LOTE)\nIdentificador do Lote: LOT-0001; LOT-0002; LOT-0003; LOT-0004; LOT-0005; LOT-0006; LOT-0007; LOT-0008; LOT-0009\nPaís: Portugal\nNUT III: PT16B\nLocalidade: Leiria\nDistrito: Leiria\nConcelho: Caldas da Rainha\nFreguesia: União das Freguesias de Caldas da Rainha - Nossa Senhora do Pópulo, Coto e São Gregório\n10 - PRAZO DE EXECUÇÃO DO CONTRATO\nIdentificador do Lote: LOT-0001; LOT-0002; LOT-0003; LOT-0004; LOT-0005; LOT-0006; LOT-0007; LOT-0008; LOT-0009\nPrazo de execução do contrato: 12 MESES\nPrevisão de renovações: Não\n11 - FUNDOS EU\nIdentificador do Lote: LOT-0001; LOT-0002; LOT-0003; LOT-0004; LOT-0005; LOT-0006; LOT-0007; LOT-0008; LOT-0009\nTêm fundos EU? Não\n12 - DOCUMENTOS DE HABILITAÇÃO\nHabilitação para o exercício da atividade profissional: Não\n13 - CONDIÇÕES DE APRESENTAÇÃO\nPlataforma eletrónica utilizada pela entidade adjudicante: VORTAL\nURL para Apresentação: https://community.vortal.biz/public/\nAdmissibilidade da apresentação de propostas variantes: Não autorizado\nPrazo para apresentação das propostas: 19-01-2026 17:00\nPrazo durante o qual os concorrentes são obrigados a manter as respetivas propostas: 120 dias a contar do termo do prazo para a apresentação das propostas\nIndicação de Subcontratação na Proposta: Inexistência de indicação de subcontratação\n14 - PRESTAÇÃO DE CAUÇÃO\nPrestação de caução: Não\n15 - FORNECIMENTO DAS PEÇAS DO CONCURSO, APRESENTAÇÃO DE PEDIDOS DE PARTICIPAÇÃO E APRESENTAÇÃO DAS PROPOSTAS\nLink para acesso às peças do concurso (URL): https://community.vortal.biz/Public/public-tender-documents/alk5SWZPNCtVb1lVWXpZKzFIZHUyL2lUd2l2UENQdnYzVVNBdStSRFFXVC9qTk5LbVNSWTE2SDF5d3FwVlppelZkODlNRW1CK1J4WWZMZDZJbUE3N1E9PUk3UElm\n20 - OUTROS REQUISITOS\nIdentificador do Lote: LOT-0001; LOT-0002; LOT-0003; LOT-0004; LOT-0005; LOT-0006; LOT-0007; LOT-0008; LOT-0009\nInformação sobre contratos reservados. Aplica-se a contratos reservados (54º-A)? Não\n21 - CRITÉRIO DE ADJUDICAÇÃO\nO Critério de adjudicação é diferenciado por lote? Não\nMultifator: Não\nMonofator:\nNome: Preço\n24 - CONDIÇÕES DO CONTRATO\nIdentificador do Lote: LOT-0001; LOT-0002; LOT-0003; LOT-0004; LOT-0005; LOT-0006; LOT-0007; LOT-0008; LOT-0009\nFaturação Eletrónica: Permitido\nObrigação de Subcontratação:\nCódigo da Obrigação de Subcontratação: Não é aplicável nenhuma obrigação de subcontratação.\n25 - COMPRA PÚBLICA ESTRATÉGICA\nCompra Pública Estratégica: Inexistência de contratação pública estratégica\n26 - INFORMAÇÕES ADICIONAIS\nIdentificador do Lote: LOT-0001; LOT-0002; LOT-0003; LOT-0004; LOT-0005; LOT-0006; LOT-0007; LOT-0008; LOT-0009\nContrato adequado para PME: Sim\nCobertura ACP (Acordo dos Contratos Públicos da Organização Mundial do Comércio): Não\n27 - IDENTIFICAÇÃO E CONTACTOS DO ÓRGÃO DE RECURSOS ADMINISTRATIVOS\nDesignação: Conselho de Administração da Unidade Local de Saúde do Oeste EPE\nEndereço: Rua Diário de Notícias\nCódigo postal: 2500-176\nLocalidade: Caldas da Rainha\nTelefone: +351 262830300\nFax: +351 262830300\nEndereço eletrónico: secretariado.ca@ulso.min-saude.pt\n28 - IDENTIFICAÇÃO DO(S) AUTOR(ES) DE ANÚNCIO\nNome: Elsa Baião\nCargo: Presidente Conselho Administração\n419947191",
    "nipc": "514993871",
    "distrito": "Leiria",
    "concelho": "Caldas da Rainha",
    "freguesia": "União das Freguesias de Caldas da Rainha - Nossa Senhora do Pópulo, Coto e São Gregório",
    "site": "https://www.choeste.min-saude.pt",
    "email": "aprovisionamento@choeste.min-saude.pt",
    "designacao_contrato": "Aquisição de Medicamentos Anti -Infeciosos 2026",
    "descricao": "Aquisição de Medicamentos Anti -Infeciosos 2026",
    "preco_base": "6.865,30 EUR",
    "prazo_execucao": "12 MESES",
    "prazo_apresentacao_propostas": "19-01-2026 17:00",
    "fundos_eu": "Não",
    "plataforma_eletronica": "VORTAL",
    "url_procedimento": "https://community.vortal.biz/public/",
    "autor_nome": "Elsa Baião",
    "autor_cargo": "Presidente Conselho Administração"
  },
  {
    "numero_procedimento": "N/A",
    "entidade": "Serviços Municipalizados da Câmara Municipal do Concelho da Nazaré",
    "link": "https://diariodarepublica.pt/dr/detalhe/contrato-publico/180-998488107",
    "detalhes_completos": "1 - IDENTIFICAÇÃO E CONTACTOS DA ENTIDADE ADJUDICANTE\nDesignação da entidade adjudicante: Serviços Municipalizados da Câmara Municipal do Concelho da Nazaré\nNIPC: 680017399\nServiço/Órgão/Pessoa de contacto: Conselho de Administração dos Serviços Municipalizados da Nazaré (P)\nEndereço: Bairro dos Pescadores - Rua A, 2 - 1° andar\nCódigo postal: 2450-115\nLocalidade: Nazaré\nPaís: Portugal\nNUT III: PT16B\nDistrito: Leiria\nConcelho: Nazaré\nFreguesia: Todas\nTelefone: 262561153\nFax: 262568442\nEndereço da Entidade (URL): www.sm-nazare.pt\nEndereço Eletrónico: geral@sm-nazare.pt\neDelivery Gateway (URL): https://www.acingov.pt\nFunção da Organização: Adquirente\nNorma jurídica da Entidade Adjudicante: Organismo de direito público\nÁrea de atividade da Autoridade Adjudicante: Serviços públicos das administrações públicas\n2 - JORNAL OFICIAL DA UNIÃO EUROPEIA\nO procedimento a que este anúncio diz respeito também é publicitado no Jornal Oficial da União Europeia? Não\n3 - AVISO\nModelo de Anúncio: Concurso público\nData de Envio do Anúncio: 06-01-2026\n5 - PROCESSO\nTipo de Procedimento: Concurso público\nPreço base do procedimento: Sim\nValor do preço base do procedimento: 145.640,00 EUR\nProcedimento com lotes? Não\n6 - OBJETO DO CONTRATO\nNúmero de referência interna: CP/2/2025-PPC/SMNazaré\nDesignação do contrato: Serviços de limpeza e desobstrução da rede de drenagem de águas residuais domésticas durante o ano de 2026\nDescrição: Serviços de limpeza e desobstrução da rede de drenagem de águas residuais domésticas durante o ano de 2026\nTipo de Contrato Principal: Aquisição de Serviços\nTipo de Contrato: Aquisição de Serviços\nClassificação CPV (Vocabulário Comum para os Contratos Públicos)\nObjeto principal\nVocabulário Principal: 90470000\nPreço base s/IVA: 145.640,00 EUR\n7 - INDICAÇÕES ADICIONAIS\nO contrato envolve aquisição conjunta (satisfação de várias entidades)? Não\nO contrato é adjudicado por uma central de compras? Não\n8 - TÉCNICAS\nO concurso destina-se à celebração de um acordo-quadro? Inexistência de acordo-quadro\nÉ utilizado um leilão eletrónico? Não\nÉ adotada uma fase de negociação? Não\nSistema de Aquisição Dinâmico: Inexistência de sistema de aquisição dinâmico\n9 - LOCAL DA EXECUÇÃO DO CONTRATO\nLOCAL DA EXECUÇÃO DO CONTRATO (PROCEDIMENTO)\nPaís: Portugal\nNUT III: PT16B\nLocalidade: Freguesia de Famalicão - Nazaré\nDistrito: Leiria\nConcelho: Nazaré\nFreguesia: Freguesia de Famalicão - Nazaré\nPaís: Portugal\nNUT III: PT16B\nLocalidade: Freguesia de Nazaré\nDistrito: Leiria\nConcelho: Nazaré\nFreguesia: Freguesia de Nazaré\nPaís: Portugal\nNUT III: PT16B\nLocalidade: Freguesia de Valado dos Frades\nDistrito: Leiria\nConcelho: Nazaré\nFreguesia: Freguesia de Valado dos Frades\n10 - PRAZO DE EXECUÇÃO DO CONTRATO\nData de Início: 01-02-2026\nData de Fim: 31-12-2026\nPrevisão de renovações: Não\n11 - FUNDOS EU\nTêm fundos EU? Não\n12 - DOCUMENTOS DE HABILITAÇÃO\nHabilitação para o exercício da atividade profissional: Não\n13 - CONDIÇÕES DE APRESENTAÇÃO\nPlataforma eletrónica utilizada pela entidade adjudicante: ACIN\nURL para Apresentação: https://www.acingov.pt\nAdmissibilidade da apresentação de propostas variantes: Não autorizado\nPrazo para apresentação das propostas: 13-01-2026 23:59\nPrazo durante o qual os concorrentes são obrigados a manter as respetivas propostas: 66 dias a contar do termo do prazo para a apresentação das propostas\nIndicação de Subcontratação na Proposta: Inexistência de indicação de subcontratação\n14 - PRESTAÇÃO DE CAUÇÃO\nPrestação de caução: Não\n15 - FORNECIMENTO DAS PEÇAS DO CONCURSO, APRESENTAÇÃO DE PEDIDOS DE PARTICIPAÇÃO E APRESENTAÇÃO DAS PROPOSTAS\nLink para acesso às peças do concurso (URL): https://www.acingov.pt/acingovprod/2/zonaPublica/zona_publica_c/donwloadProcedurePiece/MTAwNzQ0NQ==\n20 - OUTROS REQUISITOS\nInformação sobre contratos reservados. Aplica-se a contratos reservados (54º-A)? Não\n21 - CRITÉRIO DE ADJUDICAÇÃO\nMultifator: Não\nMonofator:\nNome: Outros\nOutro nome: Fator Preço\n24 - CONDIÇÕES DO CONTRATO\nFaturação Eletrónica: Permitido\nObrigação de Subcontratação:\nCódigo da Obrigação de Subcontratação: Não é aplicável nenhuma obrigação de subcontratação.\n25 - COMPRA PÚBLICA ESTRATÉGICA\nCompra Pública Estratégica: Inexistência de contratação pública estratégica\n26 - INFORMAÇÕES ADICIONAIS\nContrato adequado para PME: Sim\nCobertura ACP (Acordo dos Contratos Públicos da Organização Mundial do Comércio): Não\n27 - IDENTIFICAÇÃO E CONTACTOS DO ÓRGÃO DE RECURSOS ADMINISTRATIVOS\nDesignação: Conselho de Administração dos Serviços Municipalizados da Nazaré\nEndereço: Bairro dos Pescadores, Rua B, n.º 2  A 1º andar\nCódigo postal: 2450-113\nLocalidade: Nazaré\nTelefone: 262562118\nFax: \nEndereço eletrónico: geral@sm-nazare.pt\nPrazo de interposição do recurso: 30 dias\n28 - IDENTIFICAÇÃO DO(S) AUTOR(ES) DE ANÚNCIO\nNome: Luís Miguel Rodrigues Sousinha\nCargo: Presidente do Conselho de Administração dos Serviços Municipalizados da Nazaré\n419947237",
    "nipc": "680017399",
    "distrito": "Leiria",
    "concelho": "Nazaré",
    "freguesia": "Todas",
    "site": "www.sm-nazare.pt",
    "email": "geral@sm-nazare.pt",
    "designacao_contrato": "Serviços de limpeza e desobstrução da rede de drenagem de águas residuais domésticas durante o ano de 2026",
    "descricao": "Serviços de limpeza e desobstrução da rede de drenagem de águas residuais domésticas durante o ano de 2026",
    "preco_base": "145.640,00 EUR",
    "prazo_execucao": null,
    "prazo_apresentacao_propostas": "13-01-2026 23:59",
    "fundos_eu": "Não",
    "plataforma_eletronica": "ACIN",
    "url_procedimento": "https://www.acingov.pt",
    "autor_nome": "Luís Miguel Rodrigues Sousinha",
    "autor_cargo": "Presidente do Conselho de Administração dos Serviços Municipalizados da Nazaré"
  },
  {
    "numero_procedimento": "N/A",
    "entidade": "Unidade Local de Saúde de São José, EPE",
    "link": "https://diariodarepublica.pt/dr/detalhe/contrato-publico/182-998488108",
    "detalhes_completos": "1 - IDENTIFICAÇÃO E CONTACTOS DA ENTIDADE ADJUDICANTE\nDesignação da entidade adjudicante: Unidade Local de Saúde de São José, EPE\nNIPC: 508080142\nEndereço: Rua José António Serrano\nCódigo postal: 1150-199\nLocalidade: Lisboa\nPaís: Portugal\nNUT III: PT170\nDistrito: Lisboa\nConcelho: Lisboa\nFreguesia: Freguesia de Arroios - Lisboa\nTelefone: 218841403\nFax: 218841025\nEndereço da Entidade (URL): www.chlc.min-saude.pt\nEndereço Eletrónico: geral@chlc.min-saude.pt\neDelivery Gateway (URL): https://community.vortal.biz/public/\nFunção da Organização: Adquirente\nNorma jurídica da Entidade Adjudicante: Organismo de direito público\nÁrea de atividade da Autoridade Adjudicante: Saúde\n2 - JORNAL OFICIAL DA UNIÃO EUROPEIA\nO procedimento a que este anúncio diz respeito também é publicitado no Jornal Oficial da União Europeia? Não\n3 - AVISO\nModelo de Anúncio: Concurso público\nData de Envio do Anúncio: 06-01-2026\n5 - PROCESSO\nTipo de Procedimento: Concurso público\nPreço base do procedimento: Sim\nValor do preço base do procedimento: 161.533,04 EUR\nProcedimento com lotes? Sim\nNº Máx. de Lotes Autorizado: 9\nNúmero máximo de lotes que podem ser adjudicados a um concorrente: 9\n6 - OBJETO DO CONTRATO\nNúmero de referência interna: 12010326\nDesignação do contrato: Aquisição de Sistemas de Alimentação, para 2026 e 2027\nDescrição: Aquisição tendente ao fornecimento de Sistemas de Alimentação, para 2026 e 2027\nTipo de Contrato Principal: Aquisição de Bens Móveis\nTipo de Contrato: Aquisição de Bens Móveis\nClassificação CPV (Vocabulário Comum para os Contratos Públicos)\nObjeto principal\nVocabulário Principal: 33140000\nPreço base s/IVA: 161.533,04 EUR\nLotes: \nNº: LOT-0001\nDescrição do Lote: Lote 1\nPreço base s/IVA: 1.969,12 EUR\nClassificação CPV (Vocabulário Comum para os Contratos Públicos)\nObjeto principal\nVocabulário Principal: 33140000\nNº: LOT-0002\nDescrição do Lote: Lote 2\nPreço base s/IVA: 1.061,72 EUR\nClassificação CPV (Vocabulário Comum para os Contratos Públicos)\nObjeto principal\nVocabulário Principal: 33140000\nNº: LOT-0003\nDescrição do Lote: Lote 3\nPreço base s/IVA: 60.011,00 EUR\nClassificação CPV (Vocabulário Comum para os Contratos Públicos)\nObjeto principal\nVocabulário Principal: 33140000\nNº: LOT-0004\nDescrição do Lote: Lote 4\nPreço base s/IVA: 630,00 EUR\nClassificação CPV (Vocabulário Comum para os Contratos Públicos)\nObjeto principal\nVocabulário Principal: 33140000\nNº: LOT-0005\nDescrição do Lote: Lote 5\nPreço base s/IVA: 7.290,00 EUR\nClassificação CPV (Vocabulário Comum para os Contratos Públicos)\nObjeto principal\nVocabulário Principal: 33140000\nNº: LOT-0006\nDescrição do Lote: Lote 6\nPreço base s/IVA: 48.960,00 EUR\nClassificação CPV (Vocabulário Comum para os Contratos Públicos)\nObjeto principal\nVocabulário Principal: 33140000\nNº: LOT-0007\nDescrição do Lote: Lote 7\nPreço base s/IVA: 4.800,00 EUR\nClassificação CPV (Vocabulário Comum para os Contratos Públicos)\nObjeto principal\nVocabulário Principal: 33140000\nNº: LOT-0008\nDescrição do Lote: Lote 8\nPreço base s/IVA: 23.772,90 EUR\nClassificação CPV (Vocabulário Comum para os Contratos Públicos)\nObjeto principal\nVocabulário Principal: 33140000\nNº: LOT-0009\nDescrição do Lote: Lote 9\nPreço base s/IVA: 13.038,30 EUR\nClassificação CPV (Vocabulário Comum para os Contratos Públicos)\nObjeto principal\nVocabulário Principal: 33140000\n7 - INDICAÇÕES ADICIONAIS\nO contrato envolve aquisição conjunta (satisfação de várias entidades)? Não\nO contrato é adjudicado por uma central de compras? Não\n8 - TÉCNICAS\nO concurso destina-se à celebração de um acordo-quadro? Inexistência de acordo-quadro\nÉ utilizado um leilão eletrónico? Não\nÉ adotada uma fase de negociação? Não\nSistema de Aquisição Dinâmico: Inexistência de sistema de aquisição dinâmico\n9 - LOCAL DA EXECUÇÃO DO CONTRATO\nLOCAL DA EXECUÇÃO DO CONTRATO (PROCEDIMENTO)\nPaís: Portugal\nNUT III: PT170\nLocalidade: Lisboa\nDistrito: Lisboa\nConcelho: Lisboa\nFreguesia: Freguesia de Arroios - Lisboa\nLOCAL DA EXECUÇÃO DO CONTRATO (LOTE)\nIdentificador do Lote: LOT-0001; LOT-0002; LOT-0003; LOT-0004; LOT-0005; LOT-0006; LOT-0007; LOT-0008; LOT-0009\nPaís: Portugal\nNUT III: PT170\nLocalidade: Lisboa\nDistrito: Lisboa\nConcelho: Lisboa\nFreguesia: Freguesia de Arroios - Lisboa\n10 - PRAZO DE EXECUÇÃO DO CONTRATO\nIdentificador do Lote: LOT-0001; LOT-0002; LOT-0003; LOT-0004; LOT-0005; LOT-0006; LOT-0007; LOT-0008; LOT-0009\nPrazo de execução do contrato: 12 MESES\nPrevisão de renovações: Sim\nIndicar número máximo de renovações: 1\nPrazo de renovações diferente do prazo inicial: Não\n11 - FUNDOS EU\nIdentificador do Lote: LOT-0001; LOT-0002; LOT-0003; LOT-0004; LOT-0005; LOT-0006; LOT-0007; LOT-0008; LOT-0009\nTêm fundos EU? Não\n12 - DOCUMENTOS DE HABILITAÇÃO\nHabilitação para o exercício da atividade profissional: Não\n13 - CONDIÇÕES DE APRESENTAÇÃO\nPlataforma eletrónica utilizada pela entidade adjudicante: VORTAL\nURL para Apresentação: https://community.vortal.biz/public/\nAdmissibilidade da apresentação de propostas variantes: Não autorizado\nPrazo para apresentação das propostas: 19-01-2026 23:59\nPrazo durante o qual os concorrentes são obrigados a manter as respetivas propostas: 120 dias a contar do termo do prazo para a apresentação das propostas\nIndicação de Subcontratação na Proposta: Inexistência de indicação de subcontratação\n14 - PRESTAÇÃO DE CAUÇÃO\nPrestação de caução: Não\n15 - FORNECIMENTO DAS PEÇAS DO CONCURSO, APRESENTAÇÃO DE PEDIDOS DE PARTICIPAÇÃO E APRESENTAÇÃO DAS PROPOSTAS\nLink para acesso às peças do concurso (URL): https://community.vortal.biz/Public/public-tender-documents/RlR1UE1mMUJiT21jbnJlTnl3bE9wK3pqVkxvTFN0K1RySHNDcERrQnJ4K1FSY0I4eklmZ1FUUkZsbTd5cmJXQjUrNTlLOUcyMkdjb1NYUS9qMGxXYWc9PSt6RHF4\n20 - OUTROS REQUISITOS\nIdentificador do Lote: LOT-0001; LOT-0002; LOT-0003; LOT-0004; LOT-0005; LOT-0006; LOT-0007; LOT-0008; LOT-0009\nInformação sobre contratos reservados. Aplica-se a contratos reservados (54º-A)? Não\n21 - CRITÉRIO DE ADJUDICAÇÃO\nO Critério de adjudicação é diferenciado por lote? Não\nMultifator: Não\nMonofator:\nNome: Preço\n24 - CONDIÇÕES DO CONTRATO\nIdentificador do Lote: LOT-0001; LOT-0002; LOT-0003; LOT-0004; LOT-0005; LOT-0006; LOT-0007; LOT-0008; LOT-0009\nFaturação Eletrónica: Permitido\nObrigação de Subcontratação:\nCódigo da Obrigação de Subcontratação: Não é aplicável nenhuma obrigação de subcontratação.\n25 - COMPRA PÚBLICA ESTRATÉGICA\nCompra Pública Estratégica: Inexistência de contratação pública estratégica\n26 - INFORMAÇÕES ADICIONAIS\nIdentificador do Lote: LOT-0001; LOT-0002; LOT-0003; LOT-0004; LOT-0005; LOT-0006; LOT-0007; LOT-0008; LOT-0009\nContrato adequado para PME: Sim\nCobertura ACP (Acordo dos Contratos Públicos da Organização Mundial do Comércio): Não\n27 - IDENTIFICAÇÃO E CONTACTOS DO ÓRGÃO DE RECURSOS ADMINISTRATIVOS\nDesignação: Conselho de Administração\nEndereço: Rua José António Serrano s/n\nCódigo postal: 1150-199\nLocalidade: Lisboa\nTelefone: +351 218841403\nFax: +351 218841025\nEndereço eletrónico: sec.vca@ulssaojose.min-saude.pt\n28 - IDENTIFICAÇÃO DO(S) AUTOR(ES) DE ANÚNCIO\nNome: Conselho de Administração\nCargo: Conselho de Administração\n419947124",
    "nipc": "508080142",
    "distrito": "Lisboa",
    "concelho": "Lisboa",
    "freguesia": "Freguesia de Arroios - Lisboa",
    "site": "www.chlc.min-saude.pt",
    "email": "geral@chlc.min-saude.pt",
    "designacao_contrato": "Aquisição de Sistemas de Alimentação, para 2026 e 2027",
    "descricao": "Aquisição tendente ao fornecimento de Sistemas de Alimentação, para 2026 e 2027",
    "preco_base": "161.533,04 EUR",
    "prazo_execucao": "12 MESES",
    "prazo_apresentacao_propostas": "19-01-2026 23:59",
    "fundos_eu": "Não",
    "plataforma_eletronica": "VORTAL",
    "url_procedimento": "https://community.vortal.biz/public/",
    "autor_nome": "Conselho de Administração",
    "autor_cargo": "Conselho de Administração"
  },
  {
    "numero_procedimento": "N/A",
    "entidade": "Unidade Local de Saúde de São João, EPE",
    "link": "https://diariodarepublica.pt/dr/detalhe/contrato-publico/184-998488109",
    "detalhes_completos": "1 - IDENTIFICAÇÃO E CONTACTOS DA ENTIDADE ADJUDICANTE\nDesignação da entidade adjudicante: Unidade Local de Saúde de São João, EPE\nNIPC: 509821197\nEndereço: Alameda Prof. Hernâni Monteiro\nCódigo postal: 4200-319\nLocalidade: Área Metropolitana do Porto\nPaís: Portugal\nNUT III: PT11A\nDistrito: Porto\nConcelho: Porto\nFreguesia: Freguesia de Paranhos - Porto\nTelefone: 225512100\nFax: 225504463\nEndereço da Entidade (URL): https://portal-chsj.min-saude.pt/\nEndereço Eletrónico: geral@ulssjoao.min-saude.pt\neDelivery Gateway (URL): https://community.vortal.biz/public/\nFunção da Organização: Adquirente\nNorma jurídica da Entidade Adjudicante: Organismo de direito público\nÁrea de atividade da Autoridade Adjudicante: Saúde\n2 - JORNAL OFICIAL DA UNIÃO EUROPEIA\nO procedimento a que este anúncio diz respeito também é publicitado no Jornal Oficial da União Europeia? Não\n3 - AVISO\nModelo de Anúncio: Concurso público\nData de Envio do Anúncio: 06-01-2026\n5 - PROCESSO\nTipo de Procedimento: Concurso público\nPreço base do procedimento: Sim\nValor do preço base do procedimento: 171.990,00 EUR\nProcedimento com lotes? Não\n6 - OBJETO DO CONTRATO\nNúmero de referência interna: 61000426\nDesignação do contrato: Aquisição de Papel Absorvente para Limpeza II\nDescrição: Aquisição de Papel Absorvente para Limpeza II\nTipo de Contrato Principal: Aquisição de Bens Móveis\nTipo de Contrato: Aquisição de Bens Móveis\nClassificação CPV (Vocabulário Comum para os Contratos Públicos)\nObjeto principal\nVocabulário Principal: 33700000\nPreço base s/IVA: 171.990,00 EUR\n7 - INDICAÇÕES ADICIONAIS\nO contrato envolve aquisição conjunta (satisfação de várias entidades)? Não\nO contrato é adjudicado por uma central de compras? Não\n8 - TÉCNICAS\nO concurso destina-se à celebração de um acordo-quadro? Inexistência de acordo-quadro\nÉ utilizado um leilão eletrónico? Não\nÉ adotada uma fase de negociação? Não\nSistema de Aquisição Dinâmico: Inexistência de sistema de aquisição dinâmico\n9 - LOCAL DA EXECUÇÃO DO CONTRATO\nLOCAL DA EXECUÇÃO DO CONTRATO (PROCEDIMENTO)\nPaís: Portugal\nNUT III: PT11A\nLocalidade: Área Metropolitana do Porto\nDistrito: Porto\nConcelho: Porto\nFreguesia: Freguesia de Paranhos - Porto\n10 - PRAZO DE EXECUÇÃO DO CONTRATO\nPrazo de execução do contrato: 36 MESES\nPrevisão de renovações: Não\n11 - FUNDOS EU\nTêm fundos EU? Não\n12 - DOCUMENTOS DE HABILITAÇÃO\nHabilitação para o exercício da atividade profissional: Não\n13 - CONDIÇÕES DE APRESENTAÇÃO\nPlataforma eletrónica utilizada pela entidade adjudicante: VORTAL\nURL para Apresentação: https://community.vortal.biz/public/\nAdmissibilidade da apresentação de propostas variantes: Não autorizado\nPrazo para apresentação das propostas: 15-01-2026 17:00\nPrazo durante o qual os concorrentes são obrigados a manter as respetivas propostas: 90 dias a contar do termo do prazo para a apresentação das propostas\nIndicação de Subcontratação na Proposta: Inexistência de indicação de subcontratação\n14 - PRESTAÇÃO DE CAUÇÃO\nPrestação de caução: Não\n15 - FORNECIMENTO DAS PEÇAS DO CONCURSO, APRESENTAÇÃO DE PEDIDOS DE PARTICIPAÇÃO E APRESENTAÇÃO DAS PROPOSTAS\nLink para acesso às peças do concurso (URL): https://community.vortal.biz/Public/public-tender-documents/Z1R4VkFsVEZRQUI4Z3hJbk5wNzVod2dndis2NnFwRjNuYWF2YkpMVEdQZGlKWDk2MXg2OE52N2ZMaDZ5eEFsKzU3Q1JVL000aHdkTWxTNG93WHVJUXc9PWRlMDJ6\n20 - OUTROS REQUISITOS\nInformação sobre contratos reservados. Aplica-se a contratos reservados (54º-A)? Não\n21 - CRITÉRIO DE ADJUDICAÇÃO\nMultifator: Não\nMonofator:\nNome: Preço\n24 - CONDIÇÕES DO CONTRATO\nFaturação Eletrónica: Permitido\nObrigação de Subcontratação:\nCódigo da Obrigação de Subcontratação: Não é aplicável nenhuma obrigação de subcontratação.\n25 - COMPRA PÚBLICA ESTRATÉGICA\nCompra Pública Estratégica: Inexistência de contratação pública estratégica\n26 - INFORMAÇÕES ADICIONAIS\nContrato adequado para PME: Sim\nCobertura ACP (Acordo dos Contratos Públicos da Organização Mundial do Comércio): Não\n27 - IDENTIFICAÇÃO E CONTACTOS DO ÓRGÃO DE RECURSOS ADMINISTRATIVOS\nDesignação: Conselho de Administração\nEndereço: ULS São João - Alameda Professor Hernani Monteiro\nCódigo postal: 4200-319\nLocalidade: Porto\nTelefone: +351 225512100\nFax: +351 225025766\nEndereço eletrónico: ca@ulssjoao.min-saude.pt\n28 - IDENTIFICAÇÃO DO(S) AUTOR(ES) DE ANÚNCIO\nNome: Tiago Ferreira\nCargo: Diretor do Serviço de Aprovisionamento\n419947230",
    "nipc": "509821197",
    "distrito": "Porto",
    "concelho": "Porto",
    "freguesia": "Freguesia de Paranhos - Porto",
    "site": "https://portal-chsj.min-saude.pt/",
    "email": "geral@ulssjoao.min-saude.pt",
    "designacao_contrato": "Aquisição de Papel Absorvente para Limpeza II",
    "descricao": "Aquisição de Papel Absorvente para Limpeza II",
    "preco_base": "171.990,00 EUR",
    "prazo_execucao": "36 MESES",
    "prazo_apresentacao_propostas": "15-01-2026 17:00",
    "fundos_eu": "Não",
    "plataforma_eletronica": "VORTAL",
    "url_procedimento": "https://community.vortal.biz/public/",
    "autor_nome": "Tiago Ferreira",
    "autor_cargo": "Diretor do Serviço de Aprovisionamento"
  },
  {
    "numero_procedimento": "N/A",
    "entidade": "Instituto Português de Oncologia de Coimbra Francisco Gentil, EPE",
    "link": "https://diariodarepublica.pt/dr/detalhe/contrato-publico/186-998488134",
    "detalhes_completos": "1 - IDENTIFICAÇÃO E CONTACTOS DA ENTIDADE ADJUDICANTE\nDesignação da entidade adjudicante: Instituto Português de Oncologia de Coimbra Francisco Gentil, EPE\nNIPC: 506361438\nEndereço: Av. Bissaya Barreto, 98\nCódigo postal: 3000-075\nLocalidade: Coimbra\nPaís: Portugal\nNUT III: PT16E\nDistrito: Coimbra\nConcelho: Coimbra\nFreguesia: Freguesia de Santo António dos Olivais\nTelefone: 239400226\nFax: 239400226\nEndereço da Entidade (URL): www.ipocoimbra.min-saude.pt\nEndereço Eletrónico: aprovc@ipocoimbra.min-saude.pt\neDelivery Gateway (URL): https://community.vortal.biz/public/\nFunção da Organização: Adquirente\nNorma jurídica da Entidade Adjudicante: Autoridade da administração central\nÁrea de atividade da Autoridade Adjudicante: Saúde\n2 - JORNAL OFICIAL DA UNIÃO EUROPEIA\nO procedimento a que este anúncio diz respeito também é publicitado no Jornal Oficial da União Europeia? Não\n3 - AVISO\nModelo de Anúncio: Concurso público\nData de Envio do Anúncio: 06-01-2026\n5 - PROCESSO\nTipo de Procedimento: Concurso público\nPreço base do procedimento: Sim\nValor do preço base do procedimento: 73.718,19 EUR\nProcedimento com lotes? Sim\nNº Máx. de Lotes Autorizado: 3\nNúmero máximo de lotes que podem ser adjudicados a um concorrente: 3\n6 - OBJETO DO CONTRATO\nNúmero de referência interna: 7AC26\nDesignação do contrato: Agulhas Transbronquicas Ebus e CrioEbus\nDescrição: Agulhas Transbronquicas Ebus e CrioEbus\nTipo de Contrato Principal: Aquisição de Bens Móveis\nTipo de Contrato: Aquisição de Bens Móveis\nClassificação CPV (Vocabulário Comum para os Contratos Públicos)\nObjeto principal\nVocabulário Principal: 33100000\nPreço base s/IVA: 73.718,19 EUR\nLotes: \nNº: LOT-0001\nDescrição do Lote: AGULHA TRANSBRONQUICA DE PUNÇAO ASPIRATIVA 21G (TÉCNICA \"EBUS\")\nPreço base s/IVA: 42.937,02 EUR\nClassificação CPV (Vocabulário Comum para os Contratos Públicos)\nObjeto principal\nVocabulário Principal: 33100000\nNº: LOT-0002\nDescrição do Lote: AGULHA TRANSBRONQUICA DE PUNÇAO ASPIRATIVA 22G (TÉCNICA CRIO-EBUS)\nPreço base s/IVA: 23.625,00 EUR\nClassificação CPV (Vocabulário Comum para os Contratos Públicos)\nObjeto principal\nVocabulário Principal: 33100000\nNº: LOT-0003\nDescrição do Lote: AGULHA TRANSBRONQUICA DE PUNÇAO ASPIRATIVA 25G (TÉCNICA \"EBUS\")\nPreço base s/IVA: 7.156,17 EUR\nClassificação CPV (Vocabulário Comum para os Contratos Públicos)\nObjeto principal\nVocabulário Principal: 33100000\n7 - INDICAÇÕES ADICIONAIS\nO contrato envolve aquisição conjunta (satisfação de várias entidades)? Não\nO contrato é adjudicado por uma central de compras? Não\n8 - TÉCNICAS\nO concurso destina-se à celebração de um acordo-quadro? Inexistência de acordo-quadro\nÉ utilizado um leilão eletrónico? Não\nÉ adotada uma fase de negociação? Não\nSistema de Aquisição Dinâmico: Inexistência de sistema de aquisição dinâmico\n9 - LOCAL DA EXECUÇÃO DO CONTRATO\nLOCAL DA EXECUÇÃO DO CONTRATO (PROCEDIMENTO)\nPaís: Portugal\nNUT III: PT16E\nLocalidade: Coimbra\nDistrito: Coimbra\nConcelho: Coimbra\nFreguesia: Freguesia de Santo António dos Olivais\nLOCAL DA EXECUÇÃO DO CONTRATO (LOTE)\nIdentificador do Lote: LOT-0001; LOT-0002; LOT-0003\nPaís: Portugal\nNUT III: PT16E\nLocalidade: Coimbra\nDistrito: Coimbra\nConcelho: Coimbra\nFreguesia: Freguesia de Santo António dos Olivais\n10 - PRAZO DE EXECUÇÃO DO CONTRATO\nIdentificador do Lote: LOT-0001; LOT-0002; LOT-0003\nPrazo de execução do contrato: 12 MESES\nPrevisão de renovações: Não\n11 - FUNDOS EU\nIdentificador do Lote: LOT-0001; LOT-0002; LOT-0003\nTêm fundos EU? Não\n12 - DOCUMENTOS DE HABILITAÇÃO\nHabilitação para o exercício da atividade profissional: Não\n13 - CONDIÇÕES DE APRESENTAÇÃO\nPlataforma eletrónica utilizada pela entidade adjudicante: VORTAL\nURL para Apresentação: https://community.vortal.biz/public/\nAdmissibilidade da apresentação de propostas variantes: Não autorizado\nPrazo para apresentação das propostas: 21-01-2026 23:59\nPrazo durante o qual os concorrentes são obrigados a manter as respetivas propostas: 120 dias a contar do termo do prazo para a apresentação das propostas\nIndicação de Subcontratação na Proposta: Inexistência de indicação de subcontratação\n14 - PRESTAÇÃO DE CAUÇÃO\nPrestação de caução: Não\n15 - FORNECIMENTO DAS PEÇAS DO CONCURSO, APRESENTAÇÃO DE PEDIDOS DE PARTICIPAÇÃO E APRESENTAÇÃO DAS PROPOSTAS\nLink para acesso às peças do concurso (URL): https://community.vortal.biz/Public/public-tender-documents/K1ZSQUpTcWR4b2plVTJvVStXV3Nra1FqT3dGeXdNWFdQa3NvcCtVU0RPaExQK1hUaEJpUGZUN2l3dm9NdTE0QVo0d3BTNlgybXhFUWxmL3hMdUJraHc9PWRzNURl\n20 - OUTROS REQUISITOS\nIdentificador do Lote: LOT-0001; LOT-0002; LOT-0003\nInformação sobre contratos reservados. Aplica-se a contratos reservados (54º-A)? Não\n21 - CRITÉRIO DE ADJUDICAÇÃO\nO Critério de adjudicação é diferenciado por lote? Não\nMultifator: Sim\nFator: \nNome: Preço\nPonderação: 30%\nSubfatores: Não\nFator: \nNome: Qualidade\nPonderação: 70%\nSubfatores: Não\n24 - CONDIÇÕES DO CONTRATO\nIdentificador do Lote: LOT-0001; LOT-0002; LOT-0003\nFaturação Eletrónica: Permitido\nObrigação de Subcontratação:\nCódigo da Obrigação de Subcontratação: Não é aplicável nenhuma obrigação de subcontratação.\n25 - COMPRA PÚBLICA ESTRATÉGICA\nCompra Pública Estratégica: Inexistência de contratação pública estratégica\n26 - INFORMAÇÕES ADICIONAIS\nIdentificador do Lote: LOT-0001; LOT-0002; LOT-0003\nContrato adequado para PME: Sim\nCobertura ACP (Acordo dos Contratos Públicos da Organização Mundial do Comércio): Não\n27 - IDENTIFICAÇÃO E CONTACTOS DO ÓRGÃO DE RECURSOS ADMINISTRATIVOS\nDesignação: Conselho de Administração do IPO Coimbra F.G. EPE\nEndereço: Av. Bissaya Barreto, 98\nCódigo postal: 3000-075\nLocalidade: Coimbra\nTelefone: +351 239400200\nFax: +351 000000000\nEndereço eletrónico: secad@ipocoimbra.min-saude.pt\n28 - IDENTIFICAÇÃO DO(S) AUTOR(ES) DE ANÚNCIO\nNome: Teresa Goulão\nCargo: Diretora Serviço Aprovisionamento\n419947204",
    "nipc": "506361438",
    "distrito": "Coimbra",
    "concelho": "Coimbra",
    "freguesia": "Freguesia de Santo António dos Olivais",
    "site": "www.ipocoimbra.min-saude.pt",
    "email": "aprovc@ipocoimbra.min-saude.pt",
    "designacao_contrato": "Agulhas Transbronquicas Ebus e CrioEbus",
    "descricao": "Agulhas Transbronquicas Ebus e CrioEbus",
    "preco_base": "73.718,19 EUR",
    "prazo_execucao": "12 MESES",
    "prazo_apresentacao_propostas": "21-01-2026 23:59",
    "fundos_eu": "Não",
    "plataforma_eletronica": "VORTAL",
    "url_procedimento": "https://community.vortal.biz/public/",
    "autor_nome": "Teresa Goulão",
    "autor_cargo": "Diretora Serviço Aprovisionamento"
  },
  {
    "numero_procedimento": "N/A",
    "entidade": "AnÃºncio de procedimento  n.Âº 187/2026  -  DiÃ¡rio da RepÃºblica n.Âº 3/2026, SÃ©rie II de 2026-01-06",
    "link": "https://diariodarepublica.pt/dr/detalhe/contrato-publico/187-998488136"
  },
  {
    "numero_procedimento": "N/A",
    "entidade": "Metropolitano de Lisboa, EPE",
    "link": "https://diariodarepublica.pt/dr/detalhe/contrato-publico/188-998488138",
    "detalhes_completos": "1 - IDENTIFICAÇÃO E CONTACTOS DA ENTIDADE ADJUDICANTE\nDesignação da entidade adjudicante: Metropolitano de Lisboa, EPE\nNIPC: 500192855\nEndereço: Estrada da Pontinha, s/n\nCódigo postal: 1600-582\nLocalidade: Lisboa\nPaís: Portugal\nNUT III: PT170\nDistrito: Lisboa\nConcelho: Lisboa\nFreguesia: Freguesia de Carnide - Lisboa\nTelefone: 213500115\nFax: 217980605\nEndereço da Entidade (URL): www.metrolisboa.pt\nEndereço Eletrónico: atendimento@metrolisboa.pt\neDelivery Gateway (URL): https://community.vortal.biz/public/\nFunção da Organização: Adquirente\nNorma jurídica da Entidade Adjudicante: Empresa pública\nÁrea de atividade da Entidade Adjudicante: Serviços urbanos de caminho de ferro, de elétricos, de tróleis ou de autocarros\n2 - JORNAL OFICIAL DA UNIÃO EUROPEIA\nO procedimento a que este anúncio diz respeito também é publicitado no Jornal Oficial da União Europeia? Não\n3 - AVISO\nModelo de Anúncio: Concurso público\nData de Envio do Anúncio: 06-01-2026\n5 - PROCESSO\nTipo de Procedimento: Concurso público\nPreço base do procedimento: Sim\nValor do preço base do procedimento: 30.000,00 EUR\nProcedimento com lotes? Não\n6 - OBJETO DO CONTRATO\nNúmero de referência interna: Proc. N.º 064/2025 – DLO/ML\nDesignação do contrato: “Aquisição de equipamentos informáticos para novos postos de trabalho do Metropolitano de Lisboa, E.P.E.” - Proc. N.º 064/2025 – DLO/ML”\nDescrição: “Aquisição de equipamentos informáticos para novos postos de trabalho do Metropolitano de Lisboa, E.P.E.” - Proc. N.º 064/2025 – DLO/ML”\nTipo de Contrato Principal: Aquisição de Bens Móveis\nTipo de Contrato: Aquisição de Bens Móveis; Aquisição de Serviços\nClassificação CPV (Vocabulário Comum para os Contratos Públicos)\nObjeto principal\nVocabulário Principal: 30210000\nPreço base s/IVA: 28.500,00 EUR\nObjeto Complementar\nVocabulário Principal: 50312000\nPreço base s/IVA: 1.500,00 EUR\n7 - INDICAÇÕES ADICIONAIS\nO contrato envolve aquisição conjunta (satisfação de várias entidades)? Não\nO contrato é adjudicado por uma central de compras? Não\n8 - TÉCNICAS\nO concurso destina-se à celebração de um acordo-quadro? Inexistência de acordo-quadro\nÉ utilizado um leilão eletrónico? Não\nÉ adotada uma fase de negociação? Não\nSistema de Aquisição Dinâmico: Inexistência de sistema de aquisição dinâmico\n9 - LOCAL DA EXECUÇÃO DO CONTRATO\nLOCAL DA EXECUÇÃO DO CONTRATO (PROCEDIMENTO)\nPaís: Portugal\nNUT III: PT170\nLocalidade: Lisboa\nDistrito: Lisboa\nConcelho: Lisboa\nFreguesia: Freguesia de Arroios - Lisboa\n10 - PRAZO DE EXECUÇÃO DO CONTRATO\nPrazo de execução do contrato: 60 DIAS\nPrevisão de renovações: Não\n11 - FUNDOS EU\nTêm fundos EU? Não\n12 - DOCUMENTOS DE HABILITAÇÃO\nHabilitação para o exercício da atividade profissional: Não\n13 - CONDIÇÕES DE APRESENTAÇÃO\nPlataforma eletrónica utilizada pela entidade adjudicante: VORTAL\nURL para Apresentação: https://community.vortal.biz/public/\nAdmissibilidade da apresentação de propostas variantes: Não autorizado\nPrazo para apresentação das propostas: 15-01-2026 17:00\nPrazo durante o qual os concorrentes são obrigados a manter as respetivas propostas: 180 dias a contar do termo do prazo para a apresentação das propostas\nIndicação de Subcontratação na Proposta: Inexistência de indicação de subcontratação\n14 - PRESTAÇÃO DE CAUÇÃO\nPrestação de caução: Não\n15 - FORNECIMENTO DAS PEÇAS DO CONCURSO, APRESENTAÇÃO DE PEDIDOS DE PARTICIPAÇÃO E APRESENTAÇÃO DAS PROPOSTAS\nLink para acesso às peças do concurso (URL): https://community.vortal.biz/Public/public-tender-documents/ZE5xakpUZzByQTV3eVpKMzhlQ3NxU2RaYVF6OXBvdXhEQWYzK01CQXI3dGhKZWJNMFBqNXMvTGVZeVN2dk10VDE3bStmMGQzc1gvbU44enRpNWY4ckE9PTNnKEg0\n20 - OUTROS REQUISITOS\nInformação sobre contratos reservados. Aplica-se a contratos reservados (54º-A)? Não\n21 - CRITÉRIO DE ADJUDICAÇÃO\nMultifator: Não\nMonofator:\nNome: Outros\nOutro nome: Preço\n24 - CONDIÇÕES DO CONTRATO\nFaturação Eletrónica: Permitido\nObrigação de Subcontratação:\nCódigo da Obrigação de Subcontratação: Não é aplicável nenhuma obrigação de subcontratação.\n25 - COMPRA PÚBLICA ESTRATÉGICA\nCompra Pública Estratégica: Inexistência de contratação pública estratégica\n26 - INFORMAÇÕES ADICIONAIS\nContrato adequado para PME: Sim\nCobertura ACP (Acordo dos Contratos Públicos da Organização Mundial do Comércio): Não\n27 - IDENTIFICAÇÃO E CONTACTOS DO ÓRGÃO DE RECURSOS ADMINISTRATIVOS\nDesignação: Conselho de Administração\nEndereço: Complexo Carnide, Estrada da Pontinha\nCódigo postal: 1600-582\nLocalidade: Lisboa\nTelefone: +351 217101094\nFax: +351 211570569\nEndereço eletrónico: DLO@metrolisboa.pt\n28 - IDENTIFICAÇÃO DO(S) AUTOR(ES) DE ANÚNCIO\nNome: Cristina Alexandra Rodrigues da Cruz Vaz Tomé\nCargo: Presidente do Conselho de Administração\n419947249",
    "nipc": "500192855",
    "distrito": "Lisboa",
    "concelho": "Lisboa",
    "freguesia": "Freguesia de Carnide - Lisboa",
    "site": "www.metrolisboa.pt",
    "email": "atendimento@metrolisboa.pt",
    "designacao_contrato": "“Aquisição de equipamentos informáticos para novos postos de trabalho do Metropolitano de Lisboa, E.P.E.” - Proc. N.º 064/2025 – DLO/ML”",
    "descricao": "“Aquisição de equipamentos informáticos para novos postos de trabalho do Metropolitano de Lisboa, E.P.E.” - Proc. N.º 064/2025 – DLO/ML”",
    "preco_base": "28.500,00 EUR",
    "prazo_execucao": "60 DIAS",
    "prazo_apresentacao_propostas": "15-01-2026 17:00",
    "fundos_eu": "Não",
    "plataforma_eletronica": "VORTAL",
    "url_procedimento": "https://community.vortal.biz/public/",
    "autor_nome": "Cristina Alexandra Rodrigues da Cruz Vaz Tomé",
    "autor_cargo": "Presidente do Conselho de Administração"
  },
  {
    "numero_procedimento": "N/A",
    "entidade": "Santa Casa da Misericórdia de Vila Nova de Gaia",
    "link": "https://diariodarepublica.pt/dr/detalhe/contrato-publico/189-998488143",
    "detalhes_completos": "1 - IDENTIFICAÇÃO E CONTACTOS DA ENTIDADE ADJUDICANTE\nDesignação da entidade adjudicante: Santa Casa da Misericórdia de Vila Nova de Gaia\nNIPC: 500874751\nEndereço: Rua Teixeira Lopes 33\nCódigo postal: 4400-320\nLocalidade: V.N. Gaia\nPaís: Portugal\nNUT III: PT11A\nDistrito: Porto\nConcelho: Vila Nova de Gaia\nFreguesia: União das Freguesias de Mafamude e Vilar do Paraíso\nTelefone: 223773350\nFax: 223773359\nEndereço da Entidade (URL): www.scmg.pt\nEndereço Eletrónico: dg@scmg.pt\nFunção da Organização: Adquirente\nNorma jurídica da Entidade Adjudicante: Autoridade local\nÁrea de atividade da Autoridade Adjudicante: Proteção social\n2 - JORNAL OFICIAL DA UNIÃO EUROPEIA\nO procedimento a que este anúncio diz respeito também é publicitado no Jornal Oficial da União Europeia? Não\n3 - AVISO\nModelo de Anúncio: Concurso público\nData de Envio do Anúncio: 06-01-2026\n5 - PROCESSO\nTipo de Procedimento: Concurso público\nPreço base do procedimento: Sim\nValor do preço base do procedimento: 175.000,00 EUR\nProcedimento com lotes? Não\n6 - OBJETO DO CONTRATO\nNúmero de referência interna: MG_DGPRT_07_2025\nDesignação do contrato: Empreitada de Substituição de Cobertura na Rua Augusto Rosa 190\nDescrição: Empreitada de Substituição de Cobertura \nTipo de Contrato Principal: Empreitada de Obras Públicas\nTipo de Contrato: Empreitada de Obras Públicas\nClassificação CPV (Vocabulário Comum para os Contratos Públicos)\nObjeto principal\nVocabulário Principal: 45261910\nPreço base s/IVA: 175.000,00 EUR\n7 - INDICAÇÕES ADICIONAIS\nO contrato envolve aquisição conjunta (satisfação de várias entidades)? Não\nO contrato é adjudicado por uma central de compras? Não\n8 - TÉCNICAS\nO concurso destina-se à celebração de um acordo-quadro? Inexistência de acordo-quadro\nÉ utilizado um leilão eletrónico? Não\nÉ adotada uma fase de negociação? Não\nSistema de Aquisição Dinâmico: Inexistência de sistema de aquisição dinâmico\n9 - LOCAL DA EXECUÇÃO DO CONTRATO\nLOCAL DA EXECUÇÃO DO CONTRATO (PROCEDIMENTO)\nPaís: Portugal\nNUT III: PT11A\nLocalidade: Porto\nDistrito: Porto\nConcelho: Porto\nFreguesia: União das Freguesias de Cedofeita, Santo Ildefonso, Sé, Miragaia, São Nicolau e Vitória\n10 - PRAZO DE EXECUÇÃO DO CONTRATO\nPrazo de execução do contrato: 3 MESES\nPrevisão de renovações: Não\n11 - FUNDOS EU\nTêm fundos EU? Não\n12 - DOCUMENTOS DE HABILITAÇÃO\nHabilitação para o exercício da atividade profissional: Não\n13 - CONDIÇÕES DE APRESENTAÇÃO\nPlataforma eletrónica utilizada pela entidade adjudicante: COMPRASPT\nURL para Apresentação: https://www.compraspt.com/cpt-scmvngaia/faces/\nAdmissibilidade da apresentação de propostas variantes: Não autorizado\nPrazo para apresentação das propostas: 16-01-2026 23:59\nPrazo durante o qual os concorrentes são obrigados a manter as respetivas propostas: 66 dias a contar do termo do prazo para a apresentação das propostas\nApresentação de Catálogo Eletrónico: Permitido\nIndicação de Subcontratação na Proposta: Inexistência de indicação de subcontratação\n14 - PRESTAÇÃO DE CAUÇÃO\nPrestação de caução: Sim\nPercentagem: 5%\nDescrição da Garantia Exigida: Garantia Bancária\n15 - FORNECIMENTO DAS PEÇAS DO CONCURSO, APRESENTAÇÃO DE PEDIDOS DE PARTICIPAÇÃO E APRESENTAÇÃO DAS PROPOSTAS\nLink para acesso às peças do concurso (URL): https://www.compraspt.com/cpt-scmvngaia/faces/app/acessoDocs.jsp?codigoAcesso=NjB7nQx0mfiEOBsOPfOGJvv1GJCfoyGHsNFr6XVKPVawxDBWaD\n20 - OUTROS REQUISITOS\nInformação sobre contratos reservados. Aplica-se a contratos reservados (54º-A)? Não\n21 - CRITÉRIO DE ADJUDICAÇÃO\nMultifator: Não\nMonofator:\nNome: Preço\n24 - CONDIÇÕES DO CONTRATO\nFaturação Eletrónica: Permitido\nObrigação de Subcontratação:\nCódigo da Obrigação de Subcontratação: Não é aplicável nenhuma obrigação de subcontratação.\n25 - COMPRA PÚBLICA ESTRATÉGICA\nCompra Pública Estratégica: Inexistência de contratação pública estratégica\n26 - INFORMAÇÕES ADICIONAIS\nContrato adequado para PME: Não\nCobertura ACP (Acordo dos Contratos Públicos da Organização Mundial do Comércio): Não\n27 - IDENTIFICAÇÃO E CONTACTOS DO ÓRGÃO DE RECURSOS ADMINISTRATIVOS\nDesignação: Tribunal Administrativo e Fiscal do Porto\nEndereço: Rua Duque da Terceira 331/339\nCódigo postal: 4000-536\nLocalidade: Porto\nTelefone: 225198400\nFax: \nEndereço eletrónico: porto.taf@tribunais.org.pt\nPrazo de interposição do recurso: 5 dias\n28 - IDENTIFICAÇÃO DO(S) AUTOR(ES) DE ANÚNCIO\nNome: Marlene Carvalho\nCargo: Técnica Procedimental\n419947223",
    "nipc": "500874751",
    "distrito": "Porto",
    "concelho": "Vila Nova de Gaia",
    "freguesia": "União das Freguesias de Mafamude e Vilar do Paraíso",
    "site": "www.scmg.pt",
    "email": "dg@scmg.pt",
    "designacao_contrato": "Empreitada de Substituição de Cobertura na Rua Augusto Rosa 190",
    "descricao": "Empreitada de Substituição de Cobertura",
    "preco_base": "175.000,00 EUR",
    "prazo_execucao": "3 MESES",
    "prazo_apresentacao_propostas": "16-01-2026 23:59",
    "fundos_eu": "Não",
    "plataforma_eletronica": "COMPRASPT",
    "url_procedimento": "https://www.compraspt.com/cpt-scmvngaia/faces/",
    "autor_nome": "Marlene Carvalho",
    "autor_cargo": "Técnica Procedimental"
  },
  {
    "numero_procedimento": "N/A",
    "entidade": "Município de Braga",
    "link": "https://diariodarepublica.pt/dr/detalhe/contrato-publico/190-998488144",
    "detalhes_completos": "1 - IDENTIFICAÇÃO E CONTACTOS DA ENTIDADE ADJUDICANTE\nDesignação da entidade adjudicante: Município de Braga\nNIPC: 506901173\nEndereço: Praça do Municípal\nCódigo postal: 4700-435\nLocalidade: Braga\nPaís: Portugal\nNUT III: PT112\nDistrito: Braga\nConcelho: Braga\nFreguesia: União das Freguesias de Braga (Maximinos, Sé e Cividade)\nTelefone: 253616060\nFax: 253203151\nEndereço da Entidade (URL): www.cm-braga.pt\nEndereço Eletrónico: contratacao.publica@cm-braga.pt\neDelivery Gateway (URL): https://community.vortal.biz/public/\nFunção da Organização: Adquirente\nNorma jurídica da Entidade Adjudicante: Autoridade local\nÁrea de atividade da Autoridade Adjudicante: Serviços públicos das administrações públicas\n\n2 - JORNAL OFICIAL DA UNIÃO EUROPEIA\nO procedimento a que este anúncio diz respeito também é publicitado no Jornal Oficial da União Europeia? Não\n\n3 - AVISO\nModelo de Anúncio: Concurso público\nData de Envio do Anúncio: 06-01-2026\n\n5 - PROCESSO\nTipo de Procedimento: Concurso público\nPreço base do procedimento: Sim\nValor do preço base do procedimento: 219.000,00 EUR\nProcedimento com lotes? Não\n\n6 - OBJETO DO CONTRATO\nNúmero de referência interna: CP/43/25/DCP\nDesignação do contrato: CP/43/25/DCP - Aquisição de serviços de seguros de responsabilidade civil\nDescrição: CP/43/25/DCP - Aquisição de serviços de seguros de responsabilidade civil\nTipo de Contrato Principal: Aquisição de Serviços\nTipo de Contrato: Aquisição de Serviços\nClassificação CPV (Vocabulário Comum para os Contratos Públicos)\nObjeto principal\nVocabulário Principal: 66516400\nPreço base s/IVA: 219.000,00 EUR\n\n7 - INDICAÇÕES ADICIONAIS\nO contrato envolve aquisição conjunta (satisfação de várias entidades)? Não\nO contrato é adjudicado por uma central de compras? Não\n\n8 - TÉCNICAS\nO concurso destina-se à celebração de um acordo-quadro? Inexistência de acordo-quadro\nÉ utilizado um leilão eletrónico? Não\nÉ adotada uma fase de negociação? Não\nSistema de Aquisição Dinâmico: Inexistência de sistema de aquisição dinâmico\n\n9 - LOCAL DA EXECUÇÃO DO CONTRATO\nLOCAL DA EXECUÇÃO DO CONTRATO (PROCEDIMENTO)\nPaís: Portugal\nNUT III: PT112\nLocalidade: Braga\nDistrito: Braga\nConcelho: Braga\nFreguesia: União das Freguesias de Braga (Maximinos, Sé e Cividade)\n\n10 - PRAZO DE EXECUÇÃO DO CONTRATO\nPrazo de execução do contrato: 11 MESES\nPrevisão de renovações: Não\n\n11 - FUNDOS EU\nTêm fundos EU? Não\n\n12 - DOCUMENTOS DE HABILITAÇÃO\nHabilitação para o exercício da atividade profissional: Não\n\n13 - CONDIÇÕES DE APRESENTAÇÃO\nPlataforma eletrónica utilizada pela entidade adjudicante: VORTAL\nURL para Apresentação: https://community.vortal.biz/public/\nAdmissibilidade da apresentação de propostas variantes: Não autorizado\nPrazo para apresentação das propostas: 12-01-2026 23:59\nPrazo durante o qual os concorrentes são obrigados a manter as respetivas propostas: 66 dias a contar do termo do prazo para a apresentação das propostas\nIndicação de Subcontratação na Proposta: Inexistência de indicação de subcontratação\n\n14 - PRESTAÇÃO DE CAUÇÃO\nPrestação de caução: Não\n\n15 - FORNECIMENTO DAS PEÇAS DO CONCURSO, APRESENTAÇÃO DE PEDIDOS DE PARTICIPAÇÃO E APRESENTAÇÃO DAS PROPOSTAS\nLink para acesso às peças do concurso (URL): https://community.vortal.biz/Public/public-tender-documents/Q0wvbVd3UlA2bUhJeC9JNmgwSjNCMFhsUlJrUFhiZ2NLQkRtQW82SWJjeTNUeU9RK0Z3WEp6K2NBZmE4dGl1cnFUdWpwYlBOQzNXaDcwbVlHRThzVGc9PVVIUkJp\n\n20 - OUTROS REQUISITOS\nInformação sobre contratos reservados. Aplica-se a contratos reservados (54º-A)? Não\n\n21 - CRITÉRIO DE ADJUDICAÇÃO\nMultifator: Não\nMonofator:\nNome: Preço\n\n24 - CONDIÇÕES DO CONTRATO\nFaturação Eletrónica: Permitido\nObrigação de Subcontratação:\nCódigo da Obrigação de Subcontratação: Não é aplicável nenhuma obrigação de subcontratação.\n\n25 - COMPRA PÚBLICA ESTRATÉGICA\nCompra Pública Estratégica: Inexistência de contratação pública estratégica\n\n26 - INFORMAÇÕES ADICIONAIS\nContrato adequado para PME: Sim\nCobertura ACP (Acordo dos Contratos Públicos da Organização Mundial do Comércio): Não\n\n27 - IDENTIFICAÇÃO E CONTACTOS DO ÓRGÃO DE RECURSOS ADMINISTRATIVOS\nDesignação: Presidente da Câmara Municipal de Braga\nEndereço: Praça Municipal\nCódigo postal: 4700-435\nLocalidade: Braga\nTelefone: +351 253616060\nFax: +351 253616060\nEndereço eletrónico: contratacao.publica@cm-braga.pt\n\n28 - IDENTIFICAÇÃO DO(S) AUTOR(ES) DE ANÚNCIO\nNome: Ana Isabel Costa\nCargo: Técnica Superior\n419945647",
    "nipc": "506901173",
    "distrito": "Braga",
    "concelho": "Braga",
    "freguesia": "União das Freguesias de Braga (Maximinos, Sé e Cividade)",
    "site": "www.cm-braga.pt",
    "email": "contratacao.publica@cm-braga.pt",
    "designacao_contrato": "CP/43/25/DCP - Aquisição de serviços de seguros de responsabilidade civil",
    "descricao": "CP/43/25/DCP - Aquisição de serviços de seguros de responsabilidade civil",
    "preco_base": "219.000,00 EUR",
    "prazo_execucao": "11 MESES",
    "prazo_apresentacao_propostas": "12-01-2026 23:59",
    "fundos_eu": "Não",
    "plataforma_eletronica": "VORTAL",
    "url_procedimento": "https://community.vortal.biz/public/",
    "autor_nome": "Ana Isabel Costa",
    "autor_cargo": "Técnica Superior"
  },
  {
    "numero_procedimento": "N/A",
    "entidade": "Edia - Empresa de Desenvolvimento e Infra-Estruturas do Alqueva, SA",
    "link": "https://diariodarepublica.pt/dr/detalhe/contrato-publico/191-998488146",
    "detalhes_completos": "1 - IDENTIFICAÇÃO E CONTACTOS DA ENTIDADE ADJUDICANTE\nDesignação da entidade adjudicante: Edia - Empresa de Desenvolvimento e Infra-Estruturas do Alqueva, SA\nNIPC: 503450189\nEndereço: Rua Zeca Afonso, nº  2 Beja\nCódigo postal: 7800-522\nLocalidade: Beja\nPaís: Portugal\nNUT III: PT184\nDistrito: Beja\nConcelho: Beja\nFreguesia: União das Freguesias de Beja (Santiago Maior e São João Baptista)\nTelefone: 284315100\nFax: 284315101\nEndereço da Entidade (URL): www.edia.pt\nEndereço Eletrónico: edia@edia.pt\neDelivery Gateway (URL): https://community.vortal.biz/public/\nFunção da Organização: Adquirente\nNorma jurídica da Entidade Adjudicante: Organismo de direito público, controlado por uma autoridade da administração central\nÁrea de atividade da Autoridade Adjudicante: Serviços públicos das administrações públicas\n2 - JORNAL OFICIAL DA UNIÃO EUROPEIA\nO procedimento a que este anúncio diz respeito também é publicitado no Jornal Oficial da União Europeia? Não\n3 - AVISO\nModelo de Anúncio: Concurso público\nData de Envio do Anúncio: 06-01-2026\n5 - PROCESSO\nTipo de Procedimento: Concurso público\nPreço base do procedimento: Sim\nValor do preço base do procedimento: 215.000,00 EUR\nProcedimento com lotes? Não\n6 - OBJETO DO CONTRATO\nNúmero de referência interna: CP 44/2025\nDesignação do contrato: Prestação de Serviços de Comunicações\nDescrição: A prestação de serviços visa fornecimento de serviços de comunicações de dados, fixas e móveis para toda a EDIA, incluindo o Empreendimento de Fins Múltiplos de Alqueva (EFMA)\nTipo de Contrato Principal: Aquisição de Serviços\nTipo de Contrato: Aquisição de Serviços\nClassificação CPV (Vocabulário Comum para os Contratos Públicos)\nObjeto principal\nVocabulário Principal: 64200000\nPreço base s/IVA: 215.000,00 EUR\n7 - INDICAÇÕES ADICIONAIS\nO contrato envolve aquisição conjunta (satisfação de várias entidades)? Não\nO contrato é adjudicado por uma central de compras? Não\n8 - TÉCNICAS\nO concurso destina-se à celebração de um acordo-quadro? Inexistência de acordo-quadro\nÉ utilizado um leilão eletrónico? Não\nÉ adotada uma fase de negociação? Não\nSistema de Aquisição Dinâmico: Inexistência de sistema de aquisição dinâmico\n9 - LOCAL DA EXECUÇÃO DO CONTRATO\nLOCAL DA EXECUÇÃO DO CONTRATO (PROCEDIMENTO)\nPaís: Portugal\nNUT III: PT184\nLocalidade: Beja\nDistrito: Beja\nConcelho: Beja\nFreguesia: União das Freguesias de Beja (Santiago Maior e São João Baptista)\n10 - PRAZO DE EXECUÇÃO DO CONTRATO\nPrazo de execução do contrato: 1095 DIAS\nPrevisão de renovações: Não\n11 - FUNDOS EU\nTêm fundos EU? Não\n12 - DOCUMENTOS DE HABILITAÇÃO\nHabilitação para o exercício da atividade profissional: Não\n13 - CONDIÇÕES DE APRESENTAÇÃO\nPlataforma eletrónica utilizada pela entidade adjudicante: VORTAL\nURL para Apresentação: https://community.vortal.biz/public/\nAdmissibilidade da apresentação de propostas variantes: Não autorizado\nPrazo para apresentação das propostas: 21-01-2026 18:00\nPrazo durante o qual os concorrentes são obrigados a manter as respetivas propostas: 180 dias a contar do termo do prazo para a apresentação das propostas\nIndicação de Subcontratação na Proposta: Inexistência de indicação de subcontratação\n14 - PRESTAÇÃO DE CAUÇÃO\nPrestação de caução: Sim\nPercentagem: 5%\nDescrição da Garantia Exigida: A caução será prestada por depósito em dinheiro ou títulos, garantia bancária ou por seguro-caução, utilizando-se um dos modelos (V, VI ou VII) anexos ao Programa de Concurso.\n15 - FORNECIMENTO DAS PEÇAS DO CONCURSO, APRESENTAÇÃO DE PEDIDOS DE PARTICIPAÇÃO E APRESENTAÇÃO DAS PROPOSTAS\nLink para acesso às peças do concurso (URL): https://community.vortal.biz/Public/public-tender-documents/SDlRK3crZENLRTdFVWxaRkswUDRUdlZEQ0x4bmE2Kyt2anRLVEFCQUdpaTlmS0VxSXRNc1JtSDhENTNSMzRBaDZ4MWZLV1gzeGR3STQwUVZvWXdQOWc9PWhrWklW\n20 - OUTROS REQUISITOS\nInformação sobre contratos reservados. Aplica-se a contratos reservados (54º-A)? Não\n21 - CRITÉRIO DE ADJUDICAÇÃO\nMultifator: Sim\nFator: \nNome: Outros\nOutro Nome: Preço\nPonderação: 80%\nSubfatores: Não\nFator: \nNome: Qualidade\nPonderação: 20%\nSubfatores: Não\n24 - CONDIÇÕES DO CONTRATO\nFaturação Eletrónica: Permitido\nObrigação de Subcontratação:\nCódigo da Obrigação de Subcontratação: Não é aplicável nenhuma obrigação de subcontratação.\n25 - COMPRA PÚBLICA ESTRATÉGICA\nCompra Pública Estratégica: Inexistência de contratação pública estratégica\n26 - INFORMAÇÕES ADICIONAIS\nContrato adequado para PME: Sim\nCobertura ACP (Acordo dos Contratos Públicos da Organização Mundial do Comércio): Não\n27 - IDENTIFICAÇÃO E CONTACTOS DO ÓRGÃO DE RECURSOS ADMINISTRATIVOS\nDesignação: Conselho de Administração da EDIA, S.A.\nEndereço: Rua Zeca Afonso, 2\nCódigo postal: 7800-522\nLocalidade: Beja\nTelefone: +351 284315100\nFax: +351 284315121\nEndereço eletrónico: edia@edia.pt\nPrazo de interposição do recurso: 5 dias\n28 - IDENTIFICAÇÃO DO(S) AUTOR(ES) DE ANÚNCIO\nNome: Ana Maria Queiroga\nCargo: Técnica Superior do Gabinete de Apoio Jurídico\n419947284",
    "nipc": "503450189",
    "distrito": "Beja",
    "concelho": "Beja",
    "freguesia": "União das Freguesias de Beja (Santiago Maior e São João Baptista)",
    "site": "www.edia.pt",
    "email": "edia@edia.pt",
    "designacao_contrato": "Prestação de Serviços de Comunicações",
    "descricao": "A prestação de serviços visa fornecimento de serviços de comunicações de dados, fixas e móveis para toda a EDIA, incluindo o Empreendimento de Fins Múltiplos de Alqueva (EFMA)",
    "preco_base": "215.000,00 EUR",
    "prazo_execucao": "1095 DIAS",
    "prazo_apresentacao_propostas": "21-01-2026 18:00",
    "fundos_eu": "Não",
    "plataforma_eletronica": "VORTAL",
    "url_procedimento": "https://community.vortal.biz/public/",
    "autor_nome": "Ana Maria Queiroga",
    "autor_cargo": "Técnica Superior do Gabinete de Apoio Jurídico"
  },
  {
    "numero_procedimento": "N/A",
    "entidade": "Secretário-Geral",
    "link": "https://diariodarepublica.pt/dr/detalhe/contrato-publico/192-998488147",
    "detalhes_completos": "1 - IDENTIFICAÇÃO E CONTACTOS DA ENTIDADE ADJUDICANTE\nDesignação da entidade adjudicante: Secretário-Geral\nNIPC: 600054128\nServiço/Órgão/Pessoa de contacto: João Nicolau, Divisão de Contratação\nEndereço: Palácio de São Bento\nCódigo postal: 1249-069\nLocalidade: Lisboa\nPaís: Portugal\nNUT III: PT170\nDistrito: Lisboa\nConcelho: Lisboa\nFreguesia: Freguesia da Estrela\nTelefone: 213919000\nFax: 213917440\nEndereço da Entidade (URL): www.parlamento.pt\nEndereço Eletrónico: Correio.Geral@ar.parlamento.pt\neDelivery Gateway (URL): https://www.acingov.pt\nFunção da Organização: Adquirente\nNorma jurídica da Entidade Adjudicante: Organismo de direito público\nÁrea de atividade da Autoridade Adjudicante: Serviços públicos das administrações públicas\n2 - JORNAL OFICIAL DA UNIÃO EUROPEIA\nO procedimento a que este anúncio diz respeito também é publicitado no Jornal Oficial da União Europeia? Não\n3 - AVISO\nModelo de Anúncio: Concurso público\nData de Envio do Anúncio: 06-01-2026\n5 - PROCESSO\nTipo de Procedimento: Concurso público\nPreço base do procedimento: Sim\nValor do preço base do procedimento: 40.000,00 EUR\nProcedimento com lotes? Não\n6 - OBJETO DO CONTRATO\nNúmero de referência interna: 46/DC/2025\nDesignação do contrato: Aquisição de serviços de Levantamento, Identificação e Documentação da Rede de Fibra Ótica da Assembleia da República\nDescrição: Aquisição de serviços de Levantamento, Identificação e Documentação da Rede de Fibra Ótica da Assembleia da República\nTipo de Contrato Principal: Aquisição de Serviços\nTipo de Contrato: Aquisição de Serviços\nClassificação CPV (Vocabulário Comum para os Contratos Públicos)\nObjeto principal\nVocabulário Principal: 72700000\nPreço base s/IVA: 40.000,00 EUR\n7 - INDICAÇÕES ADICIONAIS\nO contrato envolve aquisição conjunta (satisfação de várias entidades)? Não\nO contrato é adjudicado por uma central de compras? Não\n8 - TÉCNICAS\nO concurso destina-se à celebração de um acordo-quadro? Inexistência de acordo-quadro\nÉ utilizado um leilão eletrónico? Não\nÉ adotada uma fase de negociação? Não\nSistema de Aquisição Dinâmico: Inexistência de sistema de aquisição dinâmico\n9 - LOCAL DA EXECUÇÃO DO CONTRATO\nLOCAL DA EXECUÇÃO DO CONTRATO (PROCEDIMENTO)\nPaís: Portugal\nNUT III: PT170\nLocalidade: Freguesia da Estrela\nDistrito: Lisboa\nConcelho: Lisboa\nFreguesia: Freguesia da Estrela\n10 - PRAZO DE EXECUÇÃO DO CONTRATO\nPrazo de execução do contrato: 3 MESES\nPrevisão de renovações: Não\n11 - FUNDOS EU\nTêm fundos EU? Não\n12 - DOCUMENTOS DE HABILITAÇÃO\nHabilitação para o exercício da atividade profissional: Não\n13 - CONDIÇÕES DE APRESENTAÇÃO\nPlataforma eletrónica utilizada pela entidade adjudicante: ACIN\nURL para Apresentação: https://www.acingov.pt\nAdmissibilidade da apresentação de propostas variantes: Não autorizado\nPrazo para apresentação das propostas: 15-01-2026 23:59\nPrazo durante o qual os concorrentes são obrigados a manter as respetivas propostas: 90 dias a contar do termo do prazo para a apresentação das propostas\nIndicação de Subcontratação na Proposta: Inexistência de indicação de subcontratação\n14 - PRESTAÇÃO DE CAUÇÃO\nPrestação de caução: Não\n15 - FORNECIMENTO DAS PEÇAS DO CONCURSO, APRESENTAÇÃO DE PEDIDOS DE PARTICIPAÇÃO E APRESENTAÇÃO DAS PROPOSTAS\nLink para acesso às peças do concurso (URL): https://www.acingov.pt/acingovprod/2/zonaPublica/zona_publica_c/donwloadProcedurePiece/OTk5OTE1\n20 - OUTROS REQUISITOS\nInformação sobre contratos reservados. Aplica-se a contratos reservados (54º-A)? Não\n21 - CRITÉRIO DE ADJUDICAÇÃO\nMultifator: Não\nMonofator:\nNome: Preço\n24 - CONDIÇÕES DO CONTRATO\nFaturação Eletrónica: Permitido\nObrigação de Subcontratação:\nCódigo da Obrigação de Subcontratação: Não é aplicável nenhuma obrigação de subcontratação.\n25 - COMPRA PÚBLICA ESTRATÉGICA\nCompra Pública Estratégica: Inexistência de contratação pública estratégica\n26 - INFORMAÇÕES ADICIONAIS\nContrato adequado para PME: Não\nCobertura ACP (Acordo dos Contratos Públicos da Organização Mundial do Comércio): Não\n27 - IDENTIFICAÇÃO E CONTACTOS DO ÓRGÃO DE RECURSOS ADMINISTRATIVOS\nDesignação: Presidente da Assembleia da República\nEndereço: Praça da Constituição de 1976\nCódigo postal: 1249-068\nLocalidade: Lisboa\nTelefone: 213910000\nFax: \nEndereço eletrónico: GABPAR.Correio@ar.parlamento.pt\n28 - IDENTIFICAÇÃO DO(S) AUTOR(ES) DE ANÚNCIO\nNome: Anabela Cabral Ferreira\nCargo: Secretária Geral da Assembleia da República\n419947241",
    "nipc": "600054128",
    "distrito": "Lisboa",
    "concelho": "Lisboa",
    "freguesia": "Freguesia da Estrela",
    "site": "www.parlamento.pt",
    "email": "Correio.Geral@ar.parlamento.pt",
    "designacao_contrato": "Aquisição de serviços de Levantamento, Identificação e Documentação da Rede de Fibra Ótica da Assembleia da República",
    "descricao": "Aquisição de serviços de Levantamento, Identificação e Documentação da Rede de Fibra Ótica da Assembleia da República",
    "preco_base": "40.000,00 EUR",
    "prazo_execucao": "3 MESES",
    "prazo_apresentacao_propostas": "15-01-2026 23:59",
    "fundos_eu": "Não",
    "plataforma_eletronica": "ACIN",
    "url_procedimento": "https://www.acingov.pt",
    "autor_nome": "Anabela Cabral Ferreira",
    "autor_cargo": "Secretária Geral da Assembleia da República"
  },
  {
    "numero_procedimento": "N/A",
    "entidade": "Unidade Local de Saúde de Santa Maria, EPE",
    "link": "https://diariodarepublica.pt/dr/detalhe/contrato-publico/194-998488148",
    "detalhes_completos": "1 - IDENTIFICAÇÃO E CONTACTOS DA ENTIDADE ADJUDICANTE\nDesignação da entidade adjudicante: Unidade Local de Saúde de Santa Maria, EPE\nNIPC: 508481287\nEndereço: Avenida Prof. Egas Moniz\nCódigo postal: 1649-035\nLocalidade: Lisboa\nPaís: Portugal\nNUT III: PT170\nDistrito: Lisboa\nConcelho: Lisboa\nFreguesia: Freguesia de Alvalade - Lisboa\nTelefone: 217805330\nFax: 217805605\nEndereço da Entidade (URL): www.ulssm.min-saude.pt\nEndereço Eletrónico: compras@ulssm.min-saude.pt\neDelivery Gateway (URL): https://community.vortal.biz/public/\nFunção da Organização: Adquirente\nNorma jurídica da Entidade Adjudicante: Empresa pública\nÁrea de atividade da Autoridade Adjudicante: Saúde\n2 - JORNAL OFICIAL DA UNIÃO EUROPEIA\nO procedimento a que este anúncio diz respeito também é publicitado no Jornal Oficial da União Europeia? Não\n3 - AVISO\nModelo de Anúncio: Concurso público\nData de Envio do Anúncio: 06-01-2026\n5 - PROCESSO\nTipo de Procedimento: Concurso público\nPreço base do procedimento: Sim\nValor do preço base do procedimento: 101.626,70 EUR\nProcedimento com lotes? Sim\nNº Máx. de Lotes Autorizado: 6\nNúmero máximo de lotes que podem ser adjudicados a um concorrente: 6\n6 - OBJETO DO CONTRATO\nNúmero de referência interna: 261A000026 -  ano 2026\nDesignação do contrato: 261A000026 -  vários bens - SGTF - Urgência e Medicina Intensiva\nDescrição: 261A000026 -  vários bens - SGTF - Urgência e Medicina Intensiva\nTipo de Contrato Principal: Aquisição de Bens Móveis\nTipo de Contrato: Aquisição de Bens Móveis\nClassificação CPV (Vocabulário Comum para os Contratos Públicos)\nObjeto principal\nVocabulário Principal: 33600000\nPreço base s/IVA: 101.626,70 EUR\nLotes: \nNº: LOT-0001\nDescrição do Lote: lote1\nPreço base s/IVA: 11.178,00 EUR\nClassificação CPV (Vocabulário Comum para os Contratos Públicos)\nObjeto principal\nVocabulário Principal: 33600000\nNº: LOT-0002\nDescrição do Lote: lote2\nPreço base s/IVA: 1.508,00 EUR\nClassificação CPV (Vocabulário Comum para os Contratos Públicos)\nObjeto principal\nVocabulário Principal: 33600000\nNº: LOT-0003\nDescrição do Lote: lote3\nPreço base s/IVA: 170,70 EUR\nClassificação CPV (Vocabulário Comum para os Contratos Públicos)\nObjeto principal\nVocabulário Principal: 33600000\nNº: LOT-0004\nDescrição do Lote: lote4\nPreço base s/IVA: 9.000,00 EUR\nClassificação CPV (Vocabulário Comum para os Contratos Públicos)\nObjeto principal\nVocabulário Principal: 33600000\nNº: LOT-0005\nDescrição do Lote: lote5\nPreço base s/IVA: 78.300,00 EUR\nClassificação CPV (Vocabulário Comum para os Contratos Públicos)\nObjeto principal\nVocabulário Principal: 33600000\nNº: LOT-0006\nDescrição do Lote: lote6\nPreço base s/IVA: 1.470,00 EUR\nClassificação CPV (Vocabulário Comum para os Contratos Públicos)\nObjeto principal\nVocabulário Principal: 33600000\n7 - INDICAÇÕES ADICIONAIS\nO contrato envolve aquisição conjunta (satisfação de várias entidades)? Não\nO contrato é adjudicado por uma central de compras? Não\n8 - TÉCNICAS\nO concurso destina-se à celebração de um acordo-quadro? Inexistência de acordo-quadro\nÉ utilizado um leilão eletrónico? Não\nÉ adotada uma fase de negociação? Não\nSistema de Aquisição Dinâmico: Inexistência de sistema de aquisição dinâmico\n9 - LOCAL DA EXECUÇÃO DO CONTRATO\nLOCAL DA EXECUÇÃO DO CONTRATO (PROCEDIMENTO)\nPaís: Portugal\nNUT III: PT170\nLocalidade: Lisboa\nDistrito: Lisboa\nConcelho: Lisboa\nFreguesia: Freguesia de Alvalade - Lisboa\nLOCAL DA EXECUÇÃO DO CONTRATO (LOTE)\nIdentificador do Lote: LOT-0001; LOT-0002; LOT-0003; LOT-0004; LOT-0005; LOT-0006\nPaís: Portugal\nNUT III: PT170\nLocalidade: Lisboa\nDistrito: Lisboa\nConcelho: Lisboa\nFreguesia: Freguesia de Alvalade - Lisboa\n10 - PRAZO DE EXECUÇÃO DO CONTRATO\nIdentificador do Lote: LOT-0001; LOT-0002; LOT-0003; LOT-0004; LOT-0005; LOT-0006\nPrazo de execução do contrato: 12 MESES\nPrevisão de renovações: Não\n11 - FUNDOS EU\nIdentificador do Lote: LOT-0001; LOT-0002; LOT-0003; LOT-0004; LOT-0005; LOT-0006\nTêm fundos EU? Não\n12 - DOCUMENTOS DE HABILITAÇÃO\nHabilitação para o exercício da atividade profissional: Não\n13 - CONDIÇÕES DE APRESENTAÇÃO\nPlataforma eletrónica utilizada pela entidade adjudicante: VORTAL\nURL para Apresentação: https://community.vortal.biz/public/\nAdmissibilidade da apresentação de propostas variantes: Não autorizado\nPrazo para apresentação das propostas: 15-01-2026 17:00\nPrazo durante o qual os concorrentes são obrigados a manter as respetivas propostas: 66 dias a contar do termo do prazo para a apresentação das propostas\nIndicação de Subcontratação na Proposta: Inexistência de indicação de subcontratação\n14 - PRESTAÇÃO DE CAUÇÃO\nPrestação de caução: Não\n15 - FORNECIMENTO DAS PEÇAS DO CONCURSO, APRESENTAÇÃO DE PEDIDOS DE PARTICIPAÇÃO E APRESENTAÇÃO DAS PROPOSTAS\nLink para acesso às peças do concurso (URL): https://community.vortal.biz/Public/public-tender-documents/OEhlT3dYZlBDMElxZGFQNTlPRncreHRTWk1JZ0JPT3haaDhTdTk0eE45cjErNmFqM2hzbkk4SlRub1FXeHI5RnYxc1pKNTdkaVNLWk96NDYrdFM4UVE9PSlZT0xn\n20 - OUTROS REQUISITOS\nIdentificador do Lote: LOT-0001; LOT-0002; LOT-0003; LOT-0004; LOT-0005; LOT-0006\nInformação sobre contratos reservados. Aplica-se a contratos reservados (54º-A)? Não\n21 - CRITÉRIO DE ADJUDICAÇÃO\nO Critério de adjudicação é diferenciado por lote? Não\nMultifator: Não\nMonofator:\nNome: Preço\n24 - CONDIÇÕES DO CONTRATO\nIdentificador do Lote: LOT-0001; LOT-0002; LOT-0003; LOT-0004; LOT-0005; LOT-0006\nFaturação Eletrónica: Permitido\nObrigação de Subcontratação:\nCódigo da Obrigação de Subcontratação: Não é aplicável nenhuma obrigação de subcontratação.\n25 - COMPRA PÚBLICA ESTRATÉGICA\nCompra Pública Estratégica: Inexistência de contratação pública estratégica\n26 - INFORMAÇÕES ADICIONAIS\nIdentificador do Lote: LOT-0001; LOT-0002; LOT-0003; LOT-0004; LOT-0005; LOT-0006\nContrato adequado para PME: Sim\nCobertura ACP (Acordo dos Contratos Públicos da Organização Mundial do Comércio): Não\n27 - IDENTIFICAÇÃO E CONTACTOS DO ÓRGÃO DE RECURSOS ADMINISTRATIVOS\nDesignação: Conselho de Administração\nEndereço: Av Professor Egas Moniz\nCódigo postal: 1649-035\nLocalidade: Lisboa\nTelefone: +351 217805330\nFax: +351 217805605\nEndereço eletrónico: secretariado.ca@ulssm.min-saude.pt\n28 - IDENTIFICAÇÃO DO(S) AUTOR(ES) DE ANÚNCIO\nNome: Helena Ribeiro\nCargo: Assistente técnico\n419947162",
    "nipc": "508481287",
    "distrito": "Lisboa",
    "concelho": "Lisboa",
    "freguesia": "Freguesia de Alvalade - Lisboa",
    "site": "www.ulssm.min-saude.pt",
    "email": "compras@ulssm.min-saude.pt",
    "designacao_contrato": "261A000026 - vários bens - SGTF - Urgência e Medicina Intensiva",
    "descricao": "261A000026 - vários bens - SGTF - Urgência e Medicina Intensiva",
    "preco_base": "101.626,70 EUR",
    "prazo_execucao": "12 MESES",
    "prazo_apresentacao_propostas": "15-01-2026 17:00",
    "fundos_eu": "Não",
    "plataforma_eletronica": "VORTAL",
    "url_procedimento": "https://community.vortal.biz/public/",
    "autor_nome": "Helena Ribeiro",
    "autor_cargo": "Assistente técnico"
  },
  {
    "numero_procedimento": "N/A",
    "entidade": "Serviço de Saúde da Região Autónoma da Madeira, EPE-RAM",
    "link": "https://diariodarepublica.pt/dr/detalhe/contrato-publico/195-998488152",
    "detalhes_completos": "1 - IDENTIFICAÇÃO E CONTACTOS DA ENTIDADE ADJUDICANTE\nDesignação da entidade adjudicante: Serviço de Saúde da Região Autónoma da Madeira, EPE-RAM\nNIPC: 511228848\nServiço/Órgão/Pessoa de contacto: Núcleo de Aprovisionamento\nEndereço: Av Luis de Camões 57\nCódigo postal: 9004-514\nLocalidade: Funchal\nPaís: Portugal\nNUT III: PT300\nDistrito: Região Autónoma da Madeira\nConcelho: Funchal\nFreguesia: Todas\nTelefone: 291705610\nFax: 291742545\nEndereço da Entidade (URL): www.sesaram.pt\nEndereço Eletrónico: aprovisionamento@sesaram.pt\neDelivery Gateway (URL): https://www.acingov.pt\nFunção da Organização: Adquirente\nNorma jurídica da Entidade Adjudicante: Organismo de direito público\nÁrea de atividade da Autoridade Adjudicante: Serviços públicos das administrações públicas\n2 - JORNAL OFICIAL DA UNIÃO EUROPEIA\nO procedimento a que este anúncio diz respeito também é publicitado no Jornal Oficial da União Europeia? Não\n3 - AVISO\nModelo de Anúncio: Concurso público\nData de Envio do Anúncio: 06-01-2026\n5 - PROCESSO\nTipo de Procedimento: Concurso público\nPreço base do procedimento: Sim\nValor do preço base do procedimento: 878.256,91 EUR\nProcedimento com lotes? Não\n6 - OBJETO DO CONTRATO\nNúmero de referência interna: NCP20250143\nDesignação do contrato: NCP20250143 - Empreitada de Beneficiação e Remodelação Profunda do Centro de Saúde do Santo da Serra\nDescrição: NCP20250143 - Empreitada de Beneficiação e Remodelação Profunda do Centro de Saúde do Santo da Serra\nTipo de Contrato Principal: Empreitada de Obras Públicas\nTipo de Contrato: Empreitada de Obras Públicas\nClassificação CPV (Vocabulário Comum para os Contratos Públicos)\nObjeto principal\nVocabulário Principal: 45215100\nPreço base s/IVA: 878.256,91 EUR\n7 - INDICAÇÕES ADICIONAIS\nO contrato envolve aquisição conjunta (satisfação de várias entidades)? Não\nO contrato é adjudicado por uma central de compras? Não\n8 - TÉCNICAS\nO concurso destina-se à celebração de um acordo-quadro? Inexistência de acordo-quadro\nÉ utilizado um leilão eletrónico? Não\nÉ adotada uma fase de negociação? Não\nSistema de Aquisição Dinâmico: Inexistência de sistema de aquisição dinâmico\n9 - LOCAL DA EXECUÇÃO DO CONTRATO\nLOCAL DA EXECUÇÃO DO CONTRATO (PROCEDIMENTO)\nPaís: Portugal\nNUT III: PT300\nLocalidade: Freguesia de São Pedro (Funchal)\nDistrito: Região Autónoma da Madeira\nConcelho: Funchal\nFreguesia: Freguesia de São Pedro (Funchal)\n10 - PRAZO DE EXECUÇÃO DO CONTRATO\nPrazo de execução do contrato: 137 DIAS\nPrevisão de renovações: Não\n11 - FUNDOS EU\nTêm fundos EU? Sim\n12 - DOCUMENTOS DE HABILITAÇÃO\nHabilitação para o exercício da atividade profissional: Não\n13 - CONDIÇÕES DE APRESENTAÇÃO\nPlataforma eletrónica utilizada pela entidade adjudicante: ACIN\nURL para Apresentação: https://www.acingov.pt\nAdmissibilidade da apresentação de propostas variantes: Não autorizado\nPrazo para apresentação das propostas: 21-01-2026 23:59\nPrazo durante o qual os concorrentes são obrigados a manter as respetivas propostas: 90 dias a contar do termo do prazo para a apresentação das propostas\nIndicação de Subcontratação na Proposta: Inexistência de indicação de subcontratação\n14 - PRESTAÇÃO DE CAUÇÃO\nPrestação de caução: Não\n15 - FORNECIMENTO DAS PEÇAS DO CONCURSO, APRESENTAÇÃO DE PEDIDOS DE PARTICIPAÇÃO E APRESENTAÇÃO DAS PROPOSTAS\nLink para acesso às peças do concurso (URL): https://www.acingov.pt/acingovprod/2/zonaPublica/zona_publica_c/donwloadProcedurePiece/MTAzNjA5Mg==\n20 - OUTROS REQUISITOS\nInformação sobre contratos reservados. Aplica-se a contratos reservados (54º-A)? Não\n21 - CRITÉRIO DE ADJUDICAÇÃO\nMultifator: Não\nMonofator:\nNome: Preço\n24 - CONDIÇÕES DO CONTRATO\nFaturação Eletrónica: Permitido\nObrigação de Subcontratação:\nCódigo da Obrigação de Subcontratação: Não é aplicável nenhuma obrigação de subcontratação.\n25 - COMPRA PÚBLICA ESTRATÉGICA\nCompra Pública Estratégica: Inexistência de contratação pública estratégica\n26 - INFORMAÇÕES ADICIONAIS\nContrato adequado para PME: Não\nCobertura ACP (Acordo dos Contratos Públicos da Organização Mundial do Comércio): Não\n27 - IDENTIFICAÇÃO E CONTACTOS DO ÓRGÃO DE RECURSOS ADMINISTRATIVOS\nDesignação: Conselho de Administração do SESARAM, EPERAM\nEndereço: Av Luis de Camões 57\nCódigo postal: 9004-514\nLocalidade: Funchal\nTelefone: 291705610\nFax: \nEndereço eletrónico: aprovisionamento@sesaram.pt\n28 - IDENTIFICAÇÃO DO(S) AUTOR(ES) DE ANÚNCIO\nNome: DEBORA EULALIA PEREIRA SANTOS\nCargo: Assistente Técnica\n419947253",
    "nipc": "511228848",
    "distrito": "Região Autónoma da Madeira",
    "concelho": "Funchal",
    "freguesia": "Todas",
    "site": "www.sesaram.pt",
    "email": "aprovisionamento@sesaram.pt",
    "designacao_contrato": "NCP20250143 - Empreitada de Beneficiação e Remodelação Profunda do Centro de Saúde do Santo da Serra",
    "descricao": "NCP20250143 - Empreitada de Beneficiação e Remodelação Profunda do Centro de Saúde do Santo da Serra",
    "preco_base": "878.256,91 EUR",
    "prazo_execucao": "137 DIAS",
    "prazo_apresentacao_propostas": "21-01-2026 23:59",
    "fundos_eu": "Sim",
    "plataforma_eletronica": "ACIN",
    "url_procedimento": "https://www.acingov.pt",
    "autor_nome": "DEBORA EULALIA PEREIRA SANTOS",
    "autor_cargo": "Assistente Técnica"
  },
  {
    "numero_procedimento": "N/A",
    "entidade": "Serviço de Saúde da Região Autónoma da Madeira, EPE-RAM",
    "link": "https://diariodarepublica.pt/dr/detalhe/contrato-publico/196-998488153",
    "detalhes_completos": "1 - IDENTIFICAÇÃO E CONTACTOS DA ENTIDADE ADJUDICANTE\nDesignação da entidade adjudicante: Serviço de Saúde da Região Autónoma da Madeira, EPE-RAM\nNIPC: 511228848\nServiço/Órgão/Pessoa de contacto: NÚCLEO DE APROVISIONAMENTO\nEndereço: AVENIDA LUÍS DE CAMÕES, 57\nCódigo postal: 9004-514\nLocalidade: FUNCHAL\nPaís: Portugal\nNUT III: PT300\nDistrito: Região Autónoma da Madeira\nConcelho: Todos\nFreguesia: Todas\nTelefone: 291709600\nFax: 291709601\nEndereço da Entidade (URL): www.sesaram.pt\nEndereço Eletrónico: aprovisionamento@sesaram.pt\neDelivery Gateway (URL): https://www.acingov.pt\nFunção da Organização: Adquirente\nNorma jurídica da Entidade Adjudicante: Organismo de direito público\nÁrea de atividade da Autoridade Adjudicante: Serviços públicos das administrações públicas\n2 - JORNAL OFICIAL DA UNIÃO EUROPEIA\nO procedimento a que este anúncio diz respeito também é publicitado no Jornal Oficial da União Europeia? Não\n3 - AVISO\nModelo de Anúncio: Concurso público\nData de Envio do Anúncio: 06-01-2026\n5 - PROCESSO\nTipo de Procedimento: Concurso público\nPreço base do procedimento: Sim\nValor do preço base do procedimento: 159.540,00 EUR\nProcedimento com lotes? Não\n6 - OBJETO DO CONTRATO\nNúmero de referência interna: N CP20250050\nDesignação do contrato: AQUISIÇÃO DE SERVIÇOS PARA REALIZAÇÃO DE ESTUDOS ANÁTOMO-PATOLÓGICOS PARA O SESARAM, EPERAM\nDescrição: AQUISIÇÃO DE SERVIÇOS PARA REALIZAÇÃO DE ESTUDOS ANÁTOMO-PATOLÓGICOS PARA O SESARAM, EPERAM\nTipo de Contrato Principal: Aquisição de Serviços\nTipo de Contrato: Aquisição de Serviços\nClassificação CPV (Vocabulário Comum para os Contratos Públicos)\nObjeto principal\nVocabulário Principal: 71900000\nPreço base s/IVA: 159.540,00 EUR\n7 - INDICAÇÕES ADICIONAIS\nO contrato envolve aquisição conjunta (satisfação de várias entidades)? Não\nO contrato é adjudicado por uma central de compras? Não\n8 - TÉCNICAS\nO concurso destina-se à celebração de um acordo-quadro? Inexistência de acordo-quadro\nÉ utilizado um leilão eletrónico? Não\nÉ adotada uma fase de negociação? Não\nSistema de Aquisição Dinâmico: Inexistência de sistema de aquisição dinâmico\n9 - LOCAL DA EXECUÇÃO DO CONTRATO\nLOCAL DA EXECUÇÃO DO CONTRATO (PROCEDIMENTO)\nPaís: Portugal\nNUT III: PT300\nLocalidade: Funchal\nDistrito: Região Autónoma da Madeira\nConcelho: Todos\nFreguesia: Todas\n10 - PRAZO DE EXECUÇÃO DO CONTRATO\nPrazo de execução do contrato: 1095 DIAS\nPrevisão de renovações: Sim\nIndicar número máximo de renovações: 2\nPrazo de renovações diferente do prazo inicial: Não\n11 - FUNDOS EU\nTêm fundos EU? Não\n12 - DOCUMENTOS DE HABILITAÇÃO\nHabilitação para o exercício da atividade profissional: Não\n13 - CONDIÇÕES DE APRESENTAÇÃO\nPlataforma eletrónica utilizada pela entidade adjudicante: ACIN\nURL para Apresentação: https://www.acingov.pt\nAdmissibilidade da apresentação de propostas variantes: Não autorizado\nPrazo para apresentação das propostas: 18-01-2026 23:59\nPrazo durante o qual os concorrentes são obrigados a manter as respetivas propostas: 66 dias a contar do termo do prazo para a apresentação das propostas\nIndicação de Subcontratação na Proposta: Inexistência de indicação de subcontratação\n14 - PRESTAÇÃO DE CAUÇÃO\nPrestação de caução: Não\n15 - FORNECIMENTO DAS PEÇAS DO CONCURSO, APRESENTAÇÃO DE PEDIDOS DE PARTICIPAÇÃO E APRESENTAÇÃO DAS PROPOSTAS\nLink para acesso às peças do concurso (URL): https://www.acingov.pt/acingovprod/2/zonaPublica/zona_publica_c/donwloadProcedurePiece/MTAwNDI0Mg==\n20 - OUTROS REQUISITOS\nInformação sobre contratos reservados. Aplica-se a contratos reservados (54º-A)? Não\n21 - CRITÉRIO DE ADJUDICAÇÃO\nMultifator: Não\nMonofator:\nNome: Preço\n24 - CONDIÇÕES DO CONTRATO\nFaturação Eletrónica: Permitido\nObrigação de Subcontratação:\nCódigo da Obrigação de Subcontratação: Não é aplicável nenhuma obrigação de subcontratação.\n25 - COMPRA PÚBLICA ESTRATÉGICA\nCompra Pública Estratégica: Inexistência de contratação pública estratégica\n26 - INFORMAÇÕES ADICIONAIS\nContrato adequado para PME: Não\nCobertura ACP (Acordo dos Contratos Públicos da Organização Mundial do Comércio): Não\n27 - IDENTIFICAÇÃO E CONTACTOS DO ÓRGÃO DE RECURSOS ADMINISTRATIVOS\nDesignação: Conselho de Administração\nEndereço: Avenida Luís de Camões, 57\nCódigo postal: 9004-514\nLocalidade: Funchal\nTelefone: 291709600\nFax: 291709601\nEndereço eletrónico: aprovisionamento@sesaram.pt\n28 - IDENTIFICAÇÃO DO(S) AUTOR(ES) DE ANÚNCIO\nNome: Célia Maria Sousa Gonçalves\nCargo: Assistente Técnica\n419947228",
    "nipc": "511228848",
    "distrito": "Região Autónoma da Madeira",
    "concelho": "Todos",
    "freguesia": "Todas",
    "site": "www.sesaram.pt",
    "email": "aprovisionamento@sesaram.pt",
    "designacao_contrato": "AQUISIÇÃO DE SERVIÇOS PARA REALIZAÇÃO DE ESTUDOS ANÁTOMO-PATOLÓGICOS PARA O SESARAM, EPERAM",
    "descricao": "AQUISIÇÃO DE SERVIÇOS PARA REALIZAÇÃO DE ESTUDOS ANÁTOMO-PATOLÓGICOS PARA O SESARAM, EPERAM",
    "preco_base": "159.540,00 EUR",
    "prazo_execucao": "1095 DIAS",
    "prazo_apresentacao_propostas": "18-01-2026 23:59",
    "fundos_eu": "Não",
    "plataforma_eletronica": "ACIN",
    "url_procedimento": "https://www.acingov.pt",
    "autor_nome": "Célia Maria Sousa Gonçalves",
    "autor_cargo": "Assistente Técnica"
  },
  {
    "numero_procedimento": "N/A",
    "entidade": "Instituto do Turismo de Portugal, IP",
    "link": "https://diariodarepublica.pt/dr/detalhe/contrato-publico/199-998488155",
    "detalhes_completos": "1 - IDENTIFICAÇÃO E CONTACTOS DA ENTIDADE ADJUDICANTE\nDesignação da entidade adjudicante: Instituto do Turismo de Portugal, IP\nNIPC: 508666236\nEndereço: Rua Ivone Silva, lote 6\nCódigo postal: 1050-124\nLocalidade: Lisboa\nPaís: Portugal\nNUT III: PT170\nDistrito: Lisboa\nConcelho: Lisboa\nFreguesia: Freguesia de Avenidas Novas\nTelefone: 211140200\nFax: 211140200\nEndereço da Entidade (URL): https://www.turismodeportugal.pt\nEndereço Eletrónico: info@turismodeportugal.pt\neDelivery Gateway (URL): https://community.vortal.biz/public/\nFunção da Organização: Adquirente\nNorma jurídica da Entidade Adjudicante: Instituição, órgão ou agência da UE\nÁrea de atividade da Autoridade Adjudicante: Serviços públicos das administrações públicas\n2 - JORNAL OFICIAL DA UNIÃO EUROPEIA\nO procedimento a que este anúncio diz respeito também é publicitado no Jornal Oficial da União Europeia? Não\n3 - AVISO\nModelo de Anúncio: Concurso público\nData de Envio do Anúncio: 06-01-2026\n5 - PROCESSO\nTipo de Procedimento: Concurso público\nPreço base do procedimento: Sim\nValor do preço base do procedimento: 89.551,00 EUR\nProcedimento com lotes? Não\n6 - OBJETO DO CONTRATO\nNúmero de referência interna: P(87/2025) 01/DPAC/202503023\nDesignação do contrato: Aquisição de serviços de tradução técnica, retroversão, revisão e adaptação, em vários idiomas, para o Turismo de Portugal, I.P.\nDescrição: Aquisição de serviços de tradução técnica, retroversão, revisão e adaptação, em vários idiomas, para o Turismo de Portugal, I.P.\nTipo de Contrato Principal: Aquisição de Serviços\nTipo de Contrato: Aquisição de Serviços\nClassificação CPV (Vocabulário Comum para os Contratos Públicos)\nObjeto principal\nVocabulário Principal: 79530000\nPreço base s/IVA: 89.551,00 EUR\n7 - INDICAÇÕES ADICIONAIS\nO contrato envolve aquisição conjunta (satisfação de várias entidades)? Não\nO contrato é adjudicado por uma central de compras? Não\n8 - TÉCNICAS\nO concurso destina-se à celebração de um acordo-quadro? Inexistência de acordo-quadro\nÉ utilizado um leilão eletrónico? Não\nÉ adotada uma fase de negociação? Não\nSistema de Aquisição Dinâmico: Inexistência de sistema de aquisição dinâmico\n9 - LOCAL DA EXECUÇÃO DO CONTRATO\nLOCAL DA EXECUÇÃO DO CONTRATO (PROCEDIMENTO)\nPaís: Portugal\nNUT III: PT170\nLocalidade: Lisboa\nDistrito: Lisboa\nConcelho: Lisboa\nFreguesia: Freguesia de Avenidas Novas\n10 - PRAZO DE EXECUÇÃO DO CONTRATO\nPrazo de execução do contrato: 24 MESES\nPrevisão de renovações: Não\n11 - FUNDOS EU\nTêm fundos EU? Não\n12 - DOCUMENTOS DE HABILITAÇÃO\nHabilitação para o exercício da atividade profissional: Não\n13 - CONDIÇÕES DE APRESENTAÇÃO\nPlataforma eletrónica utilizada pela entidade adjudicante: VORTAL\nURL para Apresentação: https://community.vortal.biz/public/\nAdmissibilidade da apresentação de propostas variantes: Não autorizado\nPrazo para apresentação das propostas: 15-01-2026 23:59\nPrazo durante o qual os concorrentes são obrigados a manter as respetivas propostas: 90 dias a contar do termo do prazo para a apresentação das propostas\nIndicação de Subcontratação na Proposta: Inexistência de indicação de subcontratação\n14 - PRESTAÇÃO DE CAUÇÃO\nPrestação de caução: Não\n15 - FORNECIMENTO DAS PEÇAS DO CONCURSO, APRESENTAÇÃO DE PEDIDOS DE PARTICIPAÇÃO E APRESENTAÇÃO DAS PROPOSTAS\nLink para acesso às peças do concurso (URL): https://community.vortal.biz/Public/public-tender-documents/REVRZXR6NFRRMk54eXhoYlFkdjAwNnorekNtNDJQY2V3RThtN0hzWW5QeHNrK2N0NE14b2FLYVdJT0xhWk5ncnZraVNtRDIrLzh1MElCM29IZFMydVE9PWwkI1dx\n20 - OUTROS REQUISITOS\nInformação sobre contratos reservados. Aplica-se a contratos reservados (54º-A)? Não\n21 - CRITÉRIO DE ADJUDICAÇÃO\nMultifator: Não\nMonofator:\nNome: Outros\nOutro nome: Preço\n24 - CONDIÇÕES DO CONTRATO\nFaturação Eletrónica: Permitido\nObrigação de Subcontratação:\nCódigo da Obrigação de Subcontratação: Não é aplicável nenhuma obrigação de subcontratação.\n25 - COMPRA PÚBLICA ESTRATÉGICA\nCompra Pública Estratégica: Inexistência de contratação pública estratégica\n26 - INFORMAÇÕES ADICIONAIS\nContrato adequado para PME: Sim\nCobertura ACP (Acordo dos Contratos Públicos da Organização Mundial do Comércio): Não\n27 - IDENTIFICAÇÃO E CONTACTOS DO ÓRGÃO DE RECURSOS ADMINISTRATIVOS\nDesignação: Conselho Diretivo do Instituto do Turismo de Portugal, I.P.\nEndereço: Rua Ivone Silva, Lote 6\nCódigo postal: 1050-124\nLocalidade: Lisboa\nTelefone: +351 211140200\nFax: +351 211140600\nEndereço eletrónico: dcgg-concursos@turismodeportugal.pt\n28 - IDENTIFICAÇÃO DO(S) AUTOR(ES) DE ANÚNCIO\nNome: Graça Carvalho\nCargo: Técnica superior\n419947243",
    "nipc": "508666236",
    "distrito": "Lisboa",
    "concelho": "Lisboa",
    "freguesia": "Freguesia de Avenidas Novas",
    "site": "https://www.turismodeportugal.pt",
    "email": "info@turismodeportugal.pt",
    "designacao_contrato": "Aquisição de serviços de tradução técnica, retroversão, revisão e adaptação, em vários idiomas, para o Turismo de Portugal, I.P.",
    "descricao": "Aquisição de serviços de tradução técnica, retroversão, revisão e adaptação, em vários idiomas, para o Turismo de Portugal, I.P.",
    "preco_base": "89.551,00 EUR",
    "prazo_execucao": "24 MESES",
    "prazo_apresentacao_propostas": "15-01-2026 23:59",
    "fundos_eu": "Não",
    "plataforma_eletronica": "VORTAL",
    "url_procedimento": "https://community.vortal.biz/public/",
    "autor_nome": "Graça Carvalho",
    "autor_cargo": "Técnica superior"
  },
  {
    "numero_procedimento": "N/A",
    "entidade": "Instituto do Turismo de Portugal, IP",
    "link": "https://diariodarepublica.pt/dr/detalhe/contrato-publico/200-998488156",
    "detalhes_completos": "1 - IDENTIFICAÇÃO E CONTACTOS DA ENTIDADE ADJUDICANTE\nDesignação da entidade adjudicante: Instituto do Turismo de Portugal, IP\nNIPC: 508666236\nEndereço: Rua Ivone Silva, lote 6\nCódigo postal: 1050-124\nLocalidade: Lisboa\nPaís: Portugal\nNUT III: PT170\nDistrito: Lisboa\nConcelho: Lisboa\nFreguesia: Freguesia de Avenidas Novas\nTelefone: 211140200\nFax: 211140200\nEndereço da Entidade (URL): https://www.turismodeportugal.pt\nEndereço Eletrónico: info@turismodeportugal.pt\neDelivery Gateway (URL): https://community.vortal.biz/public/\nFunção da Organização: Adquirente\nNorma jurídica da Entidade Adjudicante: Instituição, órgão ou agência da UE\nÁrea de atividade da Autoridade Adjudicante: Serviços públicos das administrações públicas\n2 - JORNAL OFICIAL DA UNIÃO EUROPEIA\nO procedimento a que este anúncio diz respeito também é publicitado no Jornal Oficial da União Europeia? Não\n3 - AVISO\nModelo de Anúncio: Concurso público\nData de Envio do Anúncio: 06-01-2026\n5 - PROCESSO\nTipo de Procedimento: Concurso público\nPreço base do procedimento: Sim\nValor do preço base do procedimento: 1.468.000,00 EUR\nProcedimento com lotes? Sim\nNº Máx. de Lotes Autorizado: 7\nNúmero máximo de lotes que podem ser adjudicados a um concorrente: 7\n6 - OBJETO DO CONTRATO\nNúmero de referência interna: P(179/2025)01/DPAC/202503510-1.\nDesignação do contrato: Empreitada em regime de conceção-construção de empreitadas para a implementação de medidas de melhoria de eficiência energética em edifícios das Escolas de Hotelaria e Turismo\nDescrição: Empreitada em regime de conceção-construção de empreitadas para a implementação de medidas de melhoria de eficiência energética em edifícios das Escolas de Hotelaria e Turismo\nTipo de Contrato Principal: Empreitada de Obras Públicas\nTipo de Contrato: Empreitada de Obras Públicas\nClassificação CPV (Vocabulário Comum para os Contratos Públicos)\nObjeto principal\nVocabulário Principal: 45300000\nPreço base s/IVA: 1.468.000,00 EUR\nLotes: \nNº: LOT-0001\nDescrição do Lote: Lote 1\nPreço base s/IVA: 65.000,00 EUR\nClassificação CPV (Vocabulário Comum para os Contratos Públicos)\nObjeto principal\nVocabulário Principal: 45300000\nNº: LOT-0002\nDescrição do Lote: Lote 2\nPreço base s/IVA: 476.000,00 EUR\nClassificação CPV (Vocabulário Comum para os Contratos Públicos)\nObjeto principal\nVocabulário Principal: 45300000\nNº: LOT-0003\nDescrição do Lote: Lote 3\nPreço base s/IVA: 338.000,00 EUR\nClassificação CPV (Vocabulário Comum para os Contratos Públicos)\nObjeto principal\nVocabulário Principal: 45300000\nNº: LOT-0004\nDescrição do Lote: Lote 4\nPreço base s/IVA: 120.000,00 EUR\nClassificação CPV (Vocabulário Comum para os Contratos Públicos)\nObjeto principal\nVocabulário Principal: 45300000\nNº: LOT-0005\nDescrição do Lote: Lote 5\nPreço base s/IVA: 136.000,00 EUR\nClassificação CPV (Vocabulário Comum para os Contratos Públicos)\nObjeto principal\nVocabulário Principal: 45300000\nNº: LOT-0006\nDescrição do Lote: Lote 6\nPreço base s/IVA: 140.000,00 EUR\nClassificação CPV (Vocabulário Comum para os Contratos Públicos)\nObjeto principal\nVocabulário Principal: 45300000\nNº: LOT-0007\nDescrição do Lote: Lote 7\nPreço base s/IVA: 193.000,00 EUR\nClassificação CPV (Vocabulário Comum para os Contratos Públicos)\nObjeto principal\nVocabulário Principal: 45300000\n7 - INDICAÇÕES ADICIONAIS\nO contrato envolve aquisição conjunta (satisfação de várias entidades)? Não\nO contrato é adjudicado por uma central de compras? Não\n8 - TÉCNICAS\nO concurso destina-se à celebração de um acordo-quadro? Inexistência de acordo-quadro\nÉ utilizado um leilão eletrónico? Não\nÉ adotada uma fase de negociação? Não\nSistema de Aquisição Dinâmico: Inexistência de sistema de aquisição dinâmico\n9 - LOCAL DA EXECUÇÃO DO CONTRATO\nLOCAL DA EXECUÇÃO DO CONTRATO (PROCEDIMENTO)\nPaís: Portugal\nNUT III: PT170\nLocalidade: Lisboa\nDistrito: Lisboa\nConcelho: Lisboa\nFreguesia: Freguesia de Avenidas Novas\nLOCAL DA EXECUÇÃO DO CONTRATO (LOTE)\nIdentificador do Lote: LOT-0001; LOT-0002; LOT-0003; LOT-0004; LOT-0005; LOT-0006; LOT-0007\nPaís: Portugal\nNUT III: PT170\nLocalidade: Lisboa\nDistrito: Lisboa\nConcelho: Lisboa\nFreguesia: Freguesia de Avenidas Novas\n10 - PRAZO DE EXECUÇÃO DO CONTRATO\nIdentificador do Lote: LOT-0001; LOT-0002; LOT-0003; LOT-0004; LOT-0005; LOT-0006; LOT-0007\nPrazo de execução do contrato: 45 DIAS\nPrevisão de renovações: Não\n11 - FUNDOS EU\nIdentificador do Lote: LOT-0001; LOT-0002; LOT-0003; LOT-0004; LOT-0005; LOT-0006; LOT-0007\nTêm fundos EU? Não\n12 - DOCUMENTOS DE HABILITAÇÃO\nHabilitação para o exercício da atividade profissional: Não\n13 - CONDIÇÕES DE APRESENTAÇÃO\nPlataforma eletrónica utilizada pela entidade adjudicante: VORTAL\nURL para Apresentação: https://community.vortal.biz/public/\nAdmissibilidade da apresentação de propostas variantes: Não autorizado\nPrazo para apresentação das propostas: 20-02-2026 23:59\nPrazo durante o qual os concorrentes são obrigados a manter as respetivas propostas: 90 dias a contar do termo do prazo para a apresentação das propostas\nIndicação de Subcontratação na Proposta: Inexistência de indicação de subcontratação\n14 - PRESTAÇÃO DE CAUÇÃO\nPrestação de caução: Não\n15 - FORNECIMENTO DAS PEÇAS DO CONCURSO, APRESENTAÇÃO DE PEDIDOS DE PARTICIPAÇÃO E APRESENTAÇÃO DAS PROPOSTAS\nLink para acesso às peças do concurso (URL): https://community.vortal.biz/Public/public-tender-documents/WHJBVkpodk1LalFLMUNqSWozTEhEeUs1ZXNaYnBvd0ZZc1paTjlZYzN3dlNweFR0L21mcXFpUlc5TGdZbkh3OXMzbk9Da1o3WTJNcGtLQ1ByY1dxU2c9PU15RjBL\n20 - OUTROS REQUISITOS\nIdentificador do Lote: LOT-0001; LOT-0002; LOT-0003; LOT-0004; LOT-0005; LOT-0006; LOT-0007\nInformação sobre contratos reservados. Aplica-se a contratos reservados (54º-A)? Não\n21 - CRITÉRIO DE ADJUDICAÇÃO\nO Critério de adjudicação é diferenciado por lote? Sim\nIdentificador do lote: LOT-0001\nMultifator: Sim\nFator: \nNome: Preço\nPonderação: 20%\nSubfatores: Não\nFator: \nNome: Qualidade\nPonderação: 35%\nSubfatores: Não\nFator: \nNome: Qualidade\nPonderação: 30%\nSubfatores: Não\nFator: \nNome: Qualidade\nPonderação: 15%\nSubfatores: Não\nO Critério de adjudicação é diferenciado por lote? Sim\nIdentificador do lote: LOT-0002\nMultifator: Não\nMonofator:\nNome: Preço\nO Critério de adjudicação é diferenciado por lote? Sim\nIdentificador do lote: LOT-0003\nMultifator: Não\nMonofator:\nNome: Preço\nO Critério de adjudicação é diferenciado por lote? Sim\nIdentificador do lote: LOT-0004\nMultifator: Não\nMonofator:\nNome: Preço\nO Critério de adjudicação é diferenciado por lote? Sim\nIdentificador do lote: LOT-0005\nMultifator: Não\nMonofator:\nNome: Preço\nO Critério de adjudicação é diferenciado por lote? Sim\nIdentificador do lote: LOT-0006\nMultifator: Não\nMonofator:\nNome: Preço\nO Critério de adjudicação é diferenciado por lote? Sim\nIdentificador do lote: LOT-0007\nMultifator: Não\nMonofator:\nNome: Preço\n24 - CONDIÇÕES DO CONTRATO\nIdentificador do Lote: LOT-0001; LOT-0002; LOT-0003; LOT-0004; LOT-0005; LOT-0006; LOT-0007\nFaturação Eletrónica: Permitido\nObrigação de Subcontratação:\nCódigo da Obrigação de Subcontratação: Não é aplicável nenhuma obrigação de subcontratação.\n25 - COMPRA PÚBLICA ESTRATÉGICA\nCompra Pública Estratégica: Inexistência de contratação pública estratégica\n26 - INFORMAÇÕES ADICIONAIS\nIdentificador do Lote: LOT-0001; LOT-0002; LOT-0003; LOT-0004; LOT-0005; LOT-0006; LOT-0007\nContrato adequado para PME: Sim\nCobertura ACP (Acordo dos Contratos Públicos da Organização Mundial do Comércio): Não\n27 - IDENTIFICAÇÃO E CONTACTOS DO ÓRGÃO DE RECURSOS ADMINISTRATIVOS\nDesignação: Instituto do Turismo de Portugal, I.P,\nEndereço: Rua Ivone Silva, Lote 6\nCódigo postal: 1050-124\nLocalidade: Lisboa\nTelefone: +351 211140200\nFax: +351 211140200\nEndereço eletrónico: dcgg-concursos@turismodeportugal.pt\n28 - IDENTIFICAÇÃO DO(S) AUTOR(ES) DE ANÚNCIO\nNome: Graça Carvalho\nCargo: Técnica Superior\n419947285",
    "nipc": "508666236",
    "distrito": "Lisboa",
    "concelho": "Lisboa",
    "freguesia": "Freguesia de Avenidas Novas",
    "site": "https://www.turismodeportugal.pt",
    "email": "info@turismodeportugal.pt",
    "designacao_contrato": "Empreitada em regime de conceção-construção de empreitadas para a implementação de medidas de melhoria de eficiência energética em edifícios das Escolas de Hotelaria e Turismo",
    "descricao": "Empreitada em regime de conceção-construção de empreitadas para a implementação de medidas de melhoria de eficiência energética em edifícios das Escolas de Hotelaria e Turismo",
    "preco_base": "1.468.000,00 EUR",
    "prazo_execucao": "45 DIAS",
    "prazo_apresentacao_propostas": "20-02-2026 23:59",
    "fundos_eu": "Não",
    "plataforma_eletronica": "VORTAL",
    "url_procedimento": "https://community.vortal.biz/public/",
    "autor_nome": "Graça Carvalho",
    "autor_cargo": "Técnica Superior"
  },
  {
    "numero_procedimento": "N/A",
    "entidade": "Município de Mértola",
    "link": "https://diariodarepublica.pt/dr/detalhe/contrato-publico/201-998488157",
    "detalhes_completos": "1 - IDENTIFICAÇÃO E CONTACTOS DA ENTIDADE ADJUDICANTE\nDesignação da entidade adjudicante: Município de Mértola\nNIPC: 503279765\nEndereço: Praça Luís de Camões, 2\nCódigo postal: 7750-319\nLocalidade: Mértola\nPaís: Portugal\nNUT III: PT184\nDistrito: Beja\nConcelho: Mértola\nFreguesia: Todas\nTelefone: 286610100\nFax: 286610100\nEndereço da Entidade (URL): www.cm-mertola.pt\nEndereço Eletrónico: geral@cm-mertola.pt\neDelivery Gateway (URL): https://community.vortal.biz/public/\nFunção da Organização: Adquirente\nNorma jurídica da Entidade Adjudicante: Autoridade local\nÁrea de atividade da Autoridade Adjudicante: Serviços públicos das administrações públicas\n2 - JORNAL OFICIAL DA UNIÃO EUROPEIA\nO procedimento a que este anúncio diz respeito também é publicitado no Jornal Oficial da União Europeia? Não\n3 - AVISO\nModelo de Anúncio: Concurso público\nData de Envio do Anúncio: 06-01-2026\n5 - PROCESSO\nTipo de Procedimento: Concurso público\nPreço base do procedimento: Sim\nValor do preço base do procedimento: 3.336.007,00 EUR\nProcedimento com lotes? Não\n6 - OBJETO DO CONTRATO\nNúmero de referência interna: E-Proc.n.º8/2025\nDesignação do contrato: Concurso Público para a empreitada de Cintura Verde de Mértola\nDescrição: Empreitada de Cintura Verde de Mértola. A empreitada integra a reabilitação do Largo da Feira,  incluindo a valorização de espaço arqueológico existente e também a área envolvente ao pavilhão multiusos.\nTipo de Contrato Principal: Empreitada de Obras Públicas\nTipo de Contrato: Empreitada de Obras Públicas\nClassificação CPV (Vocabulário Comum para os Contratos Públicos)\nObjeto principal\nVocabulário Principal: 45112700\nPreço base s/IVA: 3.336.007,00 EUR\n7 - INDICAÇÕES ADICIONAIS\nO contrato envolve aquisição conjunta (satisfação de várias entidades)? Não\nO contrato é adjudicado por uma central de compras? Não\n8 - TÉCNICAS\nO concurso destina-se à celebração de um acordo-quadro? Inexistência de acordo-quadro\nÉ utilizado um leilão eletrónico? Não\nÉ adotada uma fase de negociação? Não\nSistema de Aquisição Dinâmico: Inexistência de sistema de aquisição dinâmico\n9 - LOCAL DA EXECUÇÃO DO CONTRATO\nLOCAL DA EXECUÇÃO DO CONTRATO (PROCEDIMENTO)\nPaís: Portugal\nNUT III: PT184\nLocalidade: Beja\nDistrito: Beja\nConcelho: Mértola\nFreguesia: Freguesia de Mértola\n10 - PRAZO DE EXECUÇÃO DO CONTRATO\nPrazo de execução do contrato: 540 DIAS\nPrevisão de renovações: Não\n11 - FUNDOS EU\nTêm fundos EU? Não\n12 - DOCUMENTOS DE HABILITAÇÃO\nHabilitação para o exercício da atividade profissional: Sim\nTipo: Alvará\nDescrição: Alvará de empreiteiro de obras públicas contendo as seguintes habilitações: 1.ª subcategoria da 2.ª categoria, de classe que cubra o valor global da proposta;\nA 1.ª, 2.ª, 4.ª e 5ª subcategorias da 1.ª categoria, a 6.ª, 8.ª e 9.ª subcategorias da 2.ª categoria, a 1.ª subcategoria da 4.ª categoria, a 1.ª, 2.ª e 12.ª subcategorias da 5.ª categoria, nas classes correspondentes à parte dos trabalhos a que respeitam\n13 - CONDIÇÕES DE APRESENTAÇÃO\nPlataforma eletrónica utilizada pela entidade adjudicante: VORTAL\nURL para Apresentação: https://community.vortal.biz/public/\nAdmissibilidade da apresentação de propostas variantes: Não autorizado\nPrazo para apresentação das propostas: 27-01-2026 23:59\nPrazo durante o qual os concorrentes são obrigados a manter as respetivas propostas: 66 dias a contar do termo do prazo para a apresentação das propostas\nIndicação de Subcontratação na Proposta: Inexistência de indicação de subcontratação\n14 - PRESTAÇÃO DE CAUÇÃO\nPrestação de caução: Sim\nPercentagem: 5%\nDescrição da Garantia Exigida:   Conforme definido no art.º 90.º do CCP e ponto 20 do Programa do Concurso\n15 - FORNECIMENTO DAS PEÇAS DO CONCURSO, APRESENTAÇÃO DE PEDIDOS DE PARTICIPAÇÃO E APRESENTAÇÃO DAS PROPOSTAS\nLink para acesso às peças do concurso (URL): https://community.vortal.biz/Public/public-tender-documents/WEQrYzRNUGxDM0tPQU54aDA2ek5BeENqN3FOTE81UWd6T3lPbWc5dFcvQzkvajlFcTArMjVvSUpKUlNzajE4L3JmcTBwdkNRQk1jb2ZoTC9zbGdKOGc9PWM4eHRr\n20 - OUTROS REQUISITOS\nInformação sobre contratos reservados. Aplica-se a contratos reservados (54º-A)? Não\n21 - CRITÉRIO DE ADJUDICAÇÃO\nMultifator: Não\nMonofator:\nNome: Preço\n24 - CONDIÇÕES DO CONTRATO\nFaturação Eletrónica: Permitido\nObrigação de Subcontratação:\nCódigo da Obrigação de Subcontratação: Não é aplicável nenhuma obrigação de subcontratação.\n25 - COMPRA PÚBLICA ESTRATÉGICA\nCompra Pública Estratégica: Inexistência de contratação pública estratégica\n26 - INFORMAÇÕES ADICIONAIS\nContrato adequado para PME: Sim\nCobertura ACP (Acordo dos Contratos Públicos da Organização Mundial do Comércio): Não\n27 - IDENTIFICAÇÃO E CONTACTOS DO ÓRGÃO DE RECURSOS ADMINISTRATIVOS\nDesignação: Câmara Municipal de Mértola\nEndereço: Praça Luís de Camões, 2\nCódigo postal: 7750-329\nLocalidade: Mértola\nTelefone: +351 286610100\nFax: +351 286610101\nEndereço eletrónico: geral@cm-mertola.pt\n28 - IDENTIFICAÇÃO DO(S) AUTOR(ES) DE ANÚNCIO\nNome: Mário José Santos Tomé\nCargo: Presidente da Câmara Municipal de Mértola\n419947214",
    "nipc": "503279765",
    "distrito": "Beja",
    "concelho": "Mértola",
    "freguesia": "Todas",
    "site": "www.cm-mertola.pt",
    "email": "geral@cm-mertola.pt",
    "designacao_contrato": "Concurso Público para a empreitada de Cintura Verde de Mértola",
    "descricao": "Empreitada de Cintura Verde de Mértola. A empreitada integra a reabilitação do Largo da Feira, incluindo a valorização de espaço arqueológico existente e também a área envolvente ao pavilhão multiusos.",
    "preco_base": "3.336.007,00 EUR",
    "prazo_execucao": "540 DIAS",
    "prazo_apresentacao_propostas": "27-01-2026 23:59",
    "fundos_eu": "Não",
    "plataforma_eletronica": "VORTAL",
    "url_procedimento": "https://community.vortal.biz/public/",
    "autor_nome": "Mário José Santos Tomé",
    "autor_cargo": "Presidente da Câmara Municipal de Mértola"
  },
  {
    "numero_procedimento": "N/A",
    "entidade": "Unidade Local de Saúde da Lezíria, EPE",
    "link": "https://diariodarepublica.pt/dr/detalhe/contrato-publico/203-998488163",
    "detalhes_completos": "1 - IDENTIFICAÇÃO E CONTACTOS DA ENTIDADE ADJUDICANTE\nDesignação da entidade adjudicante: Unidade Local de Saúde da Lezíria, EPE\nNIPC: 506361462\nEndereço: Av. Bernardo Santareno S/N\nCódigo postal: 2005-177\nLocalidade: Santarém\nPaís: Portugal\nNUT III: PT185\nDistrito: Santarém\nConcelho: Santarém\nFreguesia: União de Freguesias da Cidade de Santarém\nTelefone: 243300200\nFax: 243370220\nEndereço da Entidade (URL): www.hds.min-saude.pt\nEndereço Eletrónico: hdsca@hds.min-saude.pt\neDelivery Gateway (URL): https://community.vortal.biz/public/\nFunção da Organização: Adquirente\nNorma jurídica da Entidade Adjudicante: Organismo de direito público\nÁrea de atividade da Autoridade Adjudicante: Saúde\n2 - JORNAL OFICIAL DA UNIÃO EUROPEIA\nO procedimento a que este anúncio diz respeito também é publicitado no Jornal Oficial da União Europeia? Não\n3 - AVISO\nModelo de Anúncio: Concurso público\nData de Envio do Anúncio: 06-01-2026\n5 - PROCESSO\nTipo de Procedimento: Concurso público\nPreço base do procedimento: Sim\nValor do preço base do procedimento: 160.000,00 EUR\nProcedimento com lotes? Não\n6 - OBJETO DO CONTRATO\nNúmero de referência interna: 120013/2026\nDesignação do contrato: Aquisição de D.M. de Ortopedia – Prótese do Joelho em regime de consignação para o ano de 2026\nDescrição: Aquisição de D.M. de Ortopedia – Prótese do Joelho em regime de consignação para o ano de 2026\nTipo de Contrato Principal: Aquisição de Bens Móveis\nTipo de Contrato: Aquisição de Bens Móveis\nClassificação CPV (Vocabulário Comum para os Contratos Públicos)\nObjeto principal\nVocabulário Principal: 33140000\nPreço base s/IVA: 160.000,00 EUR\n7 - INDICAÇÕES ADICIONAIS\nO contrato envolve aquisição conjunta (satisfação de várias entidades)? Não\nO contrato é adjudicado por uma central de compras? Não\n8 - TÉCNICAS\nO concurso destina-se à celebração de um acordo-quadro? Inexistência de acordo-quadro\nÉ utilizado um leilão eletrónico? Não\nÉ adotada uma fase de negociação? Não\nSistema de Aquisição Dinâmico: Inexistência de sistema de aquisição dinâmico\n9 - LOCAL DA EXECUÇÃO DO CONTRATO\nLOCAL DA EXECUÇÃO DO CONTRATO (PROCEDIMENTO)\nPaís: Portugal\nNUT III: PTZZZ\nLocalidade: PORTUGAL\nDistrito: Todos\nConcelho: Todos\nFreguesia: Todas\n10 - PRAZO DE EXECUÇÃO DO CONTRATO\nPrazo de execução do contrato: 365 DIAS\nPrevisão de renovações: Não\n11 - FUNDOS EU\nTêm fundos EU? Não\n12 - DOCUMENTOS DE HABILITAÇÃO\nHabilitação para o exercício da atividade profissional: Não\n13 - CONDIÇÕES DE APRESENTAÇÃO\nPlataforma eletrónica utilizada pela entidade adjudicante: VORTAL\nURL para Apresentação: https://community.vortal.biz/public/\nAdmissibilidade da apresentação de propostas variantes: Não autorizado\nPrazo para apresentação das propostas: 12-01-2026 23:59\nPrazo durante o qual os concorrentes são obrigados a manter as respetivas propostas: 66 dias a contar do termo do prazo para a apresentação das propostas\nIndicação de Subcontratação na Proposta: Inexistência de indicação de subcontratação\n14 - PRESTAÇÃO DE CAUÇÃO\nPrestação de caução: Não\n15 - FORNECIMENTO DAS PEÇAS DO CONCURSO, APRESENTAÇÃO DE PEDIDOS DE PARTICIPAÇÃO E APRESENTAÇÃO DAS PROPOSTAS\nLink para acesso às peças do concurso (URL): https://community.vortal.biz/Public/public-tender-documents/UHNRYnI0Z1hRTU9sS2hwNDBFNVJuOHFqSm1BNElDVmVBRFN0SnQvMUFldUxIbmdoUVFOZW1rbzIvY0F6WnExcWNkenlsVUw1L2h3aEhvZTJxTFFEWmc9PXhXX2k5\n20 - OUTROS REQUISITOS\nInformação sobre contratos reservados. Aplica-se a contratos reservados (54º-A)? Não\n21 - CRITÉRIO DE ADJUDICAÇÃO\nMultifator: Sim\nFator: \nNome: Preço\nPonderação: 60%\nSubfatores: Não\nFator: \nNome: Qualidade\nPonderação: 40%\nSubfatores: Não\n24 - CONDIÇÕES DO CONTRATO\nFaturação Eletrónica: Permitido\nObrigação de Subcontratação:\nCódigo da Obrigação de Subcontratação: Não é aplicável nenhuma obrigação de subcontratação.\n25 - COMPRA PÚBLICA ESTRATÉGICA\nCompra Pública Estratégica: Inexistência de contratação pública estratégica\n26 - INFORMAÇÕES ADICIONAIS\nContrato adequado para PME: Sim\nCobertura ACP (Acordo dos Contratos Públicos da Organização Mundial do Comércio): Não\n27 - IDENTIFICAÇÃO E CONTACTOS DO ÓRGÃO DE RECURSOS ADMINISTRATIVOS\nDesignação: Conselho de Administração da Unidade Local de Saúde da Lezíria, EPE\nEndereço: Av. Bernardo Santareno\nCódigo postal: 2005-177\nLocalidade: Santarém\nTelefone: +351 243300200\nFax: +351 243370220\nEndereço eletrónico: ca@ulsleziria.min-saude.pt\n28 - IDENTIFICAÇÃO DO(S) AUTOR(ES) DE ANÚNCIO\nNome: Pedro Manuel Dias de Figueiredo Pereira Marques\nCargo: Presidente do Conselho de Administração\n419947279",
    "nipc": "506361462",
    "distrito": "Santarém",
    "concelho": "Santarém",
    "freguesia": "União de Freguesias da Cidade de Santarém",
    "site": "www.hds.min-saude.pt",
    "email": "hdsca@hds.min-saude.pt",
    "designacao_contrato": "Aquisição de D.M. de Ortopedia – Prótese do Joelho em regime de consignação para o ano de 2026",
    "descricao": "Aquisição de D.M. de Ortopedia – Prótese do Joelho em regime de consignação para o ano de 2026",
    "preco_base": "160.000,00 EUR",
    "prazo_execucao": "365 DIAS",
    "prazo_apresentacao_propostas": "12-01-2026 23:59",
    "fundos_eu": "Não",
    "plataforma_eletronica": "VORTAL",
    "url_procedimento": "https://community.vortal.biz/public/",
    "autor_nome": "Pedro Manuel Dias de Figueiredo Pereira Marques",
    "autor_cargo": "Presidente do Conselho de Administração"
  },
  {
    "numero_procedimento": "N/A",
    "entidade": "Unidade Local de Saúde do Alto Minho, EPE",
    "link": "https://diariodarepublica.pt/dr/detalhe/contrato-publico/205-998488171",
    "detalhes_completos": "1 - IDENTIFICAÇÃO E CONTACTOS DA ENTIDADE ADJUDICANTE\nDesignação da entidade adjudicante: Unidade Local de Saúde do Alto Minho, EPE\nNIPC: 508786193\nEndereço: Estrada de Santa Luzia, Viana do Castelo\nCódigo postal: 4904-858\nLocalidade: Viana do Castelo\nPaís: Portugal\nNUT III: PT111\nDistrito: Viana do Castelo\nConcelho: Viana do Castelo\nFreguesia: União das Freguesias de Viana do Castelo (Santa Maria Maior e Monserrate) e Meadela\nTelefone: 258802381\nFax: 258802389\nEndereço da Entidade (URL): https://www.ulsam.min-saude.pt\nEndereço Eletrónico: sourcing@ulsam.min-saude.pt\neDelivery Gateway (URL): https://community.vortal.biz/public/\nFunção da Organização: Adquirente\nNorma jurídica da Entidade Adjudicante: Organismo de direito público\nÁrea de atividade da Autoridade Adjudicante: Saúde\n2 - JORNAL OFICIAL DA UNIÃO EUROPEIA\nO procedimento a que este anúncio diz respeito também é publicitado no Jornal Oficial da União Europeia? Não\n3 - AVISO\nModelo de Anúncio: Concurso público\nData de Envio do Anúncio: 06-01-2026\n5 - PROCESSO\nTipo de Procedimento: Concurso público\nPreço base do procedimento: Sim\nValor do preço base do procedimento: 148.602,90 EUR\nProcedimento com lotes? Sim\nNº Máx. de Lotes Autorizado: 6\nNúmero máximo de lotes que podem ser adjudicados a um concorrente: 6\n6 - OBJETO DO CONTRATO\nNúmero de referência interna: 02/56/2026\nDesignação do contrato: MCC - Luvas Não Cirúrgicas 2026 -  CA-3314-CP-P-251126-A\nDescrição: MCC - Luvas Não Cirúrgicas 2026 -  CA-3314-CP-P-251126-A\nTipo de Contrato Principal: Aquisição de Bens Móveis\nTipo de Contrato: Aquisição de Bens Móveis\nClassificação CPV (Vocabulário Comum para os Contratos Públicos)\nObjeto principal\nVocabulário Principal: 33140000\nPreço base s/IVA: 148.602,90 EUR\nLotes: \nNº: LOT-0001\nDescrição do Lote: Lote 1\nPreço base s/IVA: 112.889,70 EUR\nClassificação CPV (Vocabulário Comum para os Contratos Públicos)\nObjeto principal\nVocabulário Principal: 33140000\nNº: LOT-0002\nDescrição do Lote: Lote 2\nPreço base s/IVA: 23.028,00 EUR\nClassificação CPV (Vocabulário Comum para os Contratos Públicos)\nObjeto principal\nVocabulário Principal: 33140000\nNº: LOT-0003\nDescrição do Lote: Lote 3\nPreço base s/IVA: 4.395,20 EUR\nClassificação CPV (Vocabulário Comum para os Contratos Públicos)\nObjeto principal\nVocabulário Principal: 33140000\nNº: LOT-0004\nDescrição do Lote: Lote 4\nPreço base s/IVA: 6.102,00 EUR\nClassificação CPV (Vocabulário Comum para os Contratos Públicos)\nObjeto principal\nVocabulário Principal: 33140000\nNº: LOT-0005\nDescrição do Lote: Lote 5\nPreço base s/IVA: 969,00 EUR\nClassificação CPV (Vocabulário Comum para os Contratos Públicos)\nObjeto principal\nVocabulário Principal: 33140000\nNº: LOT-0006\nDescrição do Lote: Lote 6\nPreço base s/IVA: 1.219,00 EUR\nClassificação CPV (Vocabulário Comum para os Contratos Públicos)\nObjeto principal\nVocabulário Principal: 33140000\n7 - INDICAÇÕES ADICIONAIS\nO contrato envolve aquisição conjunta (satisfação de várias entidades)? Não\nO contrato é adjudicado por uma central de compras? Não\n8 - TÉCNICAS\nO concurso destina-se à celebração de um acordo-quadro? Inexistência de acordo-quadro\nÉ utilizado um leilão eletrónico? Não\nÉ adotada uma fase de negociação? Não\nSistema de Aquisição Dinâmico: Inexistência de sistema de aquisição dinâmico\n9 - LOCAL DA EXECUÇÃO DO CONTRATO\nLOCAL DA EXECUÇÃO DO CONTRATO (PROCEDIMENTO)\nPaís: Portugal\nNUT III: PT111\nLocalidade: Viana do Castelo\nDistrito: Viana do Castelo\nConcelho: Viana do Castelo\nFreguesia: União das Freguesias de Viana do Castelo (Santa Maria Maior e Monserrate) e Meadela\nLOCAL DA EXECUÇÃO DO CONTRATO (LOTE)\nIdentificador do Lote: LOT-0001; LOT-0002; LOT-0003; LOT-0004; LOT-0005; LOT-0006\nPaís: Portugal\nNUT III: PT111\nLocalidade: Viana do Castelo\nDistrito: Viana do Castelo\nConcelho: Viana do Castelo\nFreguesia: União das Freguesias de Viana do Castelo (Santa Maria Maior e Monserrate) e Meadela\n10 - PRAZO DE EXECUÇÃO DO CONTRATO\nIdentificador do Lote: LOT-0001; LOT-0002; LOT-0003; LOT-0004; LOT-0005; LOT-0006\nPrazo de execução do contrato: 11 MESES\nPrevisão de renovações: Não\n11 - FUNDOS EU\nIdentificador do Lote: LOT-0001; LOT-0002; LOT-0003; LOT-0004; LOT-0005; LOT-0006\nTêm fundos EU? Não\n12 - DOCUMENTOS DE HABILITAÇÃO\nHabilitação para o exercício da atividade profissional: Não\n13 - CONDIÇÕES DE APRESENTAÇÃO\nPlataforma eletrónica utilizada pela entidade adjudicante: VORTAL\nURL para Apresentação: https://community.vortal.biz/public/\nAdmissibilidade da apresentação de propostas variantes: Não autorizado\nPrazo para apresentação das propostas: 15-01-2026 18:00\nPrazo durante o qual os concorrentes são obrigados a manter as respetivas propostas: 120 dias a contar do termo do prazo para a apresentação das propostas\nIndicação de Subcontratação na Proposta: Inexistência de indicação de subcontratação\n14 - PRESTAÇÃO DE CAUÇÃO\nPrestação de caução: Não\n15 - FORNECIMENTO DAS PEÇAS DO CONCURSO, APRESENTAÇÃO DE PEDIDOS DE PARTICIPAÇÃO E APRESENTAÇÃO DAS PROPOSTAS\nLink para acesso às peças do concurso (URL): https://community.vortal.biz/Public/public-tender-documents/VmUxRmNxREwrWDY5Q0pva3NCVUNkS3hod3lDWm1McGVOVVhQdkJMRWtQeTJlMHNpZVBJa25sQ2QyVEdnalB5OXF0YmdvWDFwWGlWRE9jMmVOTEt4dGc9PWh4SCVR\n20 - OUTROS REQUISITOS\nIdentificador do Lote: LOT-0001; LOT-0002; LOT-0003; LOT-0004; LOT-0005; LOT-0006\nInformação sobre contratos reservados. Aplica-se a contratos reservados (54º-A)? Não\n21 - CRITÉRIO DE ADJUDICAÇÃO\nO Critério de adjudicação é diferenciado por lote? Sim\nIdentificador do lote: LOT-0001\nMultifator: Sim\nFator: \nNome: Preço\nPonderação: 40%\nSubfatores: Não\nFator: \nNome: Qualidade\nPonderação: 60%\nSubfatores: Não\nO Critério de adjudicação é diferenciado por lote? Sim\nIdentificador do lote: LOT-0002\nMultifator: Sim\nFator: \nNome: Preço\nPonderação: 40%\nSubfatores: Não\nFator: \nNome: Qualidade\nPonderação: 60%\nSubfatores: Não\nO Critério de adjudicação é diferenciado por lote? Sim\nIdentificador do lote: LOT-0003\nMultifator: Não\nMonofator:\nNome: Preço\nO Critério de adjudicação é diferenciado por lote? Sim\nIdentificador do lote: LOT-0004\nMultifator: Não\nMonofator:\nNome: Preço\nO Critério de adjudicação é diferenciado por lote? Sim\nIdentificador do lote: LOT-0005\nMultifator: Não\nMonofator:\nNome: Preço\nO Critério de adjudicação é diferenciado por lote? Sim\nIdentificador do lote: LOT-0006\nMultifator: Não\nMonofator:\nNome: Preço\n24 - CONDIÇÕES DO CONTRATO\nIdentificador do Lote: LOT-0001; LOT-0002; LOT-0003; LOT-0004; LOT-0005; LOT-0006\nFaturação Eletrónica: Permitido\nObrigação de Subcontratação:\nCódigo da Obrigação de Subcontratação: Não é aplicável nenhuma obrigação de subcontratação.\n25 - COMPRA PÚBLICA ESTRATÉGICA\nCompra Pública Estratégica: Inexistência de contratação pública estratégica\n26 - INFORMAÇÕES ADICIONAIS\nIdentificador do Lote: LOT-0001; LOT-0002; LOT-0003; LOT-0004; LOT-0005; LOT-0006\nContrato adequado para PME: Sim\nCobertura ACP (Acordo dos Contratos Públicos da Organização Mundial do Comércio): Não\n27 - IDENTIFICAÇÃO E CONTACTOS DO ÓRGÃO DE RECURSOS ADMINISTRATIVOS\nDesignação: Conselho de Administração\nEndereço: Estrada de Santa Luzia\nCódigo postal: 4904-858\nLocalidade: Viana do Castelo\nTelefone: +351 258802166\nFax: +351 258802511\nEndereço eletrónico: administracao@ulsam.min-saude.pt\n28 - IDENTIFICAÇÃO DO(S) AUTOR(ES) DE ANÚNCIO\nNome: Jeni Patrícia Fernandes de Araújo Pereira\nCargo: Assistente Técnico do Serviço de Aprovisionamento\n419947247",
    "nipc": "508786193",
    "distrito": "Viana do Castelo",
    "concelho": "Viana do Castelo",
    "freguesia": "União das Freguesias de Viana do Castelo (Santa Maria Maior e Monserrate) e Meadela",
    "site": "https://www.ulsam.min-saude.pt",
    "email": "sourcing@ulsam.min-saude.pt",
    "designacao_contrato": "MCC - Luvas Não Cirúrgicas 2026 - CA-3314-CP-P-251126-A",
    "descricao": "MCC - Luvas Não Cirúrgicas 2026 - CA-3314-CP-P-251126-A",
    "preco_base": "148.602,90 EUR",
    "prazo_execucao": "11 MESES",
    "prazo_apresentacao_propostas": "15-01-2026 18:00",
    "fundos_eu": "Não",
    "plataforma_eletronica": "VORTAL",
    "url_procedimento": "https://community.vortal.biz/public/",
    "autor_nome": "Jeni Patrícia Fernandes de Araújo Pereira",
    "autor_cargo": "Assistente Técnico do Serviço de Aprovisionamento"
  },
  {
    "numero_procedimento": "N/A",
    "entidade": "Unidade Local de Saúde de Santa Maria, EPE",
    "link": "https://diariodarepublica.pt/dr/detalhe/contrato-publico/193-998616951",
    "detalhes_completos": "1 - IDENTIFICAÇÃO E CONTACTOS DA ENTIDADE ADJUDICANTE\nDesignação da entidade adjudicante: Unidade Local de Saúde de Santa Maria, EPE\nNIPC: 508481287\nEndereço: Avenida Prof. Egas Moniz\nCódigo postal: 1649-035\nLocalidade: Lisboa\nPaís: Portugal\nNUT III: PT170\nDistrito: Lisboa\nConcelho: Lisboa\nFreguesia: Freguesia de Alvalade - Lisboa\nTelefone: 217805330\nFax: 217805605\nEndereço da Entidade (URL): www.ulssm.min-saude.pt\nEndereço Eletrónico: compras@ulssm.min-saude.pt\neDelivery Gateway (URL): https://community.vortal.biz/public/\nFunção da Organização: Adquirente\nNorma jurídica da Entidade Adjudicante: Empresa pública\nÁrea de atividade da Autoridade Adjudicante: Saúde\n2 - JORNAL OFICIAL DA UNIÃO EUROPEIA\nO procedimento a que este anúncio diz respeito também é publicitado no Jornal Oficial da União Europeia? Não\n3 - AVISO\nModelo de Anúncio: Concurso público\nData de Envio do Anúncio: 06-01-2026\n5 - PROCESSO\nTipo de Procedimento: Concurso público\nPreço base do procedimento: Sim\nValor do preço base do procedimento: 68.304,40 EUR\nProcedimento com lotes? Sim\nNº Máx. de Lotes Autorizado: 13\nNúmero máximo de lotes que podem ser adjudicados a um concorrente: 13\n6 - OBJETO DO CONTRATO\nNúmero de referência interna: 261A000025 -  ano 2026\nDesignação do contrato: 261A000025 -  vários bens - SGTF - Tórax\nDescrição: 261A000025 -  vários bens - SGTF - Tórax\nTipo de Contrato Principal: Aquisição de Bens Móveis\nTipo de Contrato: Aquisição de Bens Móveis\nClassificação CPV (Vocabulário Comum para os Contratos Públicos)\nObjeto principal\nVocabulário Principal: 33600000\nPreço base s/IVA: 68.304,40 EUR\nLotes: \nNº: LOT-0001\nDescrição do Lote: lote1\nPreço base s/IVA: 225,00 EUR\nClassificação CPV (Vocabulário Comum para os Contratos Públicos)\nObjeto principal\nVocabulário Principal: 33600000\nNº: LOT-0002\nDescrição do Lote: lote2\nPreço base s/IVA: 287,00 EUR\nClassificação CPV (Vocabulário Comum para os Contratos Públicos)\nObjeto principal\nVocabulário Principal: 33600000\nNº: LOT-0003\nDescrição do Lote: lote3\nPreço base s/IVA: 820,00 EUR\nClassificação CPV (Vocabulário Comum para os Contratos Públicos)\nObjeto principal\nVocabulário Principal: 33600000\nNº: LOT-0004\nDescrição do Lote: lote4\nPreço base s/IVA: 2.970,00 EUR\nClassificação CPV (Vocabulário Comum para os Contratos Públicos)\nObjeto principal\nVocabulário Principal: 33600000\nNº: LOT-0005\nDescrição do Lote: lote5\nPreço base s/IVA: 663,00 EUR\nClassificação CPV (Vocabulário Comum para os Contratos Públicos)\nObjeto principal\nVocabulário Principal: 33600000\nNº: LOT-0006\nDescrição do Lote: lote6\nPreço base s/IVA: 31.725,00 EUR\nClassificação CPV (Vocabulário Comum para os Contratos Públicos)\nObjeto principal\nVocabulário Principal: 33600000\nNº: LOT-0007\nDescrição do Lote: lote7\nPreço base s/IVA: 3.285,60 EUR\nClassificação CPV (Vocabulário Comum para os Contratos Públicos)\nObjeto principal\nVocabulário Principal: 33600000\nNº: LOT-0008\nDescrição do Lote: lote8\nPreço base s/IVA: 1.440,00 EUR\nClassificação CPV (Vocabulário Comum para os Contratos Públicos)\nObjeto principal\nVocabulário Principal: 33600000\nNº: LOT-0009\nDescrição do Lote: lote9\nPreço base s/IVA: 1.750,00 EUR\nClassificação CPV (Vocabulário Comum para os Contratos Públicos)\nObjeto principal\nVocabulário Principal: 33600000\nNº: LOT-0010\nDescrição do Lote: lote10\nPreço base s/IVA: 18.879,36 EUR\nClassificação CPV (Vocabulário Comum para os Contratos Públicos)\nObjeto principal\nVocabulário Principal: 33600000\nNº: LOT-0011\nDescrição do Lote: lote11\nPreço base s/IVA: 295,20 EUR\nClassificação CPV (Vocabulário Comum para os Contratos Públicos)\nObjeto principal\nVocabulário Principal: 33600000\nNº: LOT-0012\nDescrição do Lote: lote12\nPreço base s/IVA: 309,24 EUR\nClassificação CPV (Vocabulário Comum para os Contratos Públicos)\nObjeto principal\nVocabulário Principal: 33600000\nNº: LOT-0013\nDescrição do Lote: lote13\nPreço base s/IVA: 5.655,00 EUR\nClassificação CPV (Vocabulário Comum para os Contratos Públicos)\nObjeto principal\nVocabulário Principal: 33600000\n7 - INDICAÇÕES ADICIONAIS\nO contrato envolve aquisição conjunta (satisfação de várias entidades)? Não\nO contrato é adjudicado por uma central de compras? Não\n8 - TÉCNICAS\nO concurso destina-se à celebração de um acordo-quadro? Inexistência de acordo-quadro\nÉ utilizado um leilão eletrónico? Não\nÉ adotada uma fase de negociação? Não\nSistema de Aquisição Dinâmico: Inexistência de sistema de aquisição dinâmico\n9 - LOCAL DA EXECUÇÃO DO CONTRATO\nLOCAL DA EXECUÇÃO DO CONTRATO (PROCEDIMENTO)\nPaís: Portugal\nNUT III: PT170\nLocalidade: Lisboa\nDistrito: Lisboa\nConcelho: Lisboa\nFreguesia: Freguesia de Alvalade - Lisboa\nLOCAL DA EXECUÇÃO DO CONTRATO (LOTE)\nIdentificador do Lote: LOT-0001; LOT-0002; LOT-0003; LOT-0004; LOT-0005; LOT-0006; LOT-0007; LOT-0008; LOT-0009; LOT-0010; LOT-0011; LOT-0012; LOT-0013\nPaís: Portugal\nNUT III: PT170\nLocalidade: Lisboa\nDistrito: Lisboa\nConcelho: Lisboa\nFreguesia: Freguesia de Alvalade - Lisboa\n10 - PRAZO DE EXECUÇÃO DO CONTRATO\nIdentificador do Lote: LOT-0001; LOT-0002; LOT-0003; LOT-0004; LOT-0005; LOT-0006; LOT-0007; LOT-0008; LOT-0009; LOT-0010; LOT-0011; LOT-0012; LOT-0013\nPrazo de execução do contrato: 12 MESES\nPrevisão de renovações: Não\n11 - FUNDOS EU\nIdentificador do Lote: LOT-0001; LOT-0002; LOT-0003; LOT-0004; LOT-0005; LOT-0006; LOT-0007; LOT-0008; LOT-0009; LOT-0010; LOT-0011; LOT-0012; LOT-0013\nTêm fundos EU? Não\n12 - DOCUMENTOS DE HABILITAÇÃO\nHabilitação para o exercício da atividade profissional: Não\n13 - CONDIÇÕES DE APRESENTAÇÃO\nPlataforma eletrónica utilizada pela entidade adjudicante: VORTAL\nURL para Apresentação: https://community.vortal.biz/public/\nAdmissibilidade da apresentação de propostas variantes: Não autorizado\nPrazo para apresentação das propostas: 15-01-2026 17:00\nPrazo durante o qual os concorrentes são obrigados a manter as respetivas propostas: 66 dias a contar do termo do prazo para a apresentação das propostas\nIndicação de Subcontratação na Proposta: Inexistência de indicação de subcontratação\n14 - PRESTAÇÃO DE CAUÇÃO\nPrestação de caução: Não\n15 - FORNECIMENTO DAS PEÇAS DO CONCURSO, APRESENTAÇÃO DE PEDIDOS DE PARTICIPAÇÃO E APRESENTAÇÃO DAS PROPOSTAS\nLink para acesso às peças do concurso (URL): https://community.vortal.biz/Public/public-tender-documents/RlhRWE1nRHo3QzQ2d2ZLaThKZ2ZYUjRrOFRuYnZJSUZVeVhPZWprYU5kZGVpMXZJMEIwSXorc1hkTEJ4Y0diRHJyVkU4dUc4cmJmRXZKUkgvQWk0S0E9PTc1RERZ\n20 - OUTROS REQUISITOS\nIdentificador do Lote: LOT-0001; LOT-0002; LOT-0003; LOT-0004; LOT-0005; LOT-0006; LOT-0007; LOT-0008; LOT-0009; LOT-0010; LOT-0011; LOT-0012; LOT-0013\nInformação sobre contratos reservados. Aplica-se a contratos reservados (54º-A)? Não\n21 - CRITÉRIO DE ADJUDICAÇÃO\nO Critério de adjudicação é diferenciado por lote? Não\nMultifator: Não\nMonofator:\nNome: Preço\n24 - CONDIÇÕES DO CONTRATO\nIdentificador do Lote: LOT-0001; LOT-0002; LOT-0003; LOT-0004; LOT-0005; LOT-0006; LOT-0007; LOT-0008; LOT-0009; LOT-0010; LOT-0011; LOT-0012; LOT-0013\nFaturação Eletrónica: Permitido\nObrigação de Subcontratação:\nCódigo da Obrigação de Subcontratação: Não é aplicável nenhuma obrigação de subcontratação.\n25 - COMPRA PÚBLICA ESTRATÉGICA\nCompra Pública Estratégica: Inexistência de contratação pública estratégica\n26 - INFORMAÇÕES ADICIONAIS\nIdentificador do Lote: LOT-0001; LOT-0002; LOT-0003; LOT-0004; LOT-0005; LOT-0006; LOT-0007; LOT-0008; LOT-0009; LOT-0010; LOT-0011; LOT-0012; LOT-0013\nContrato adequado para PME: Sim\nCobertura ACP (Acordo dos Contratos Públicos da Organização Mundial do Comércio): Não\n27 - IDENTIFICAÇÃO E CONTACTOS DO ÓRGÃO DE RECURSOS ADMINISTRATIVOS\nDesignação: Conselho de Administração\nEndereço: Av Professor Egas Moniz\nCódigo postal: 1649-035\nLocalidade: Lisboa\nTelefone: +351 217805330\nFax: +351 217805605\nEndereço eletrónico: secretariado.ca@ulssm.min-saude.pt\n28 - IDENTIFICAÇÃO DO(S) AUTOR(ES) DE ANÚNCIO\nNome: Helena Ribeiro\nCargo: Assistente técnico\n419947163",
    "nipc": "508481287",
    "distrito": "Lisboa",
    "concelho": "Lisboa",
    "freguesia": "Freguesia de Alvalade - Lisboa",
    "site": "www.ulssm.min-saude.pt",
    "email": "compras@ulssm.min-saude.pt",
    "designacao_contrato": "261A000025 - vários bens - SGTF - Tórax",
    "descricao": "261A000025 - vários bens - SGTF - Tórax",
    "preco_base": "68.304,40 EUR",
    "prazo_execucao": "12 MESES",
    "prazo_apresentacao_propostas": "15-01-2026 17:00",
    "fundos_eu": "Não",
    "plataforma_eletronica": "VORTAL",
    "url_procedimento": "https://community.vortal.biz/public/",
    "autor_nome": "Helena Ribeiro",
    "autor_cargo": "Assistente técnico"
  },
  {
    "numero_procedimento": "N/A",
    "entidade": "AnÃºncio de procedimento  n.Âº 197/2026  -  DiÃ¡rio da RepÃºblica n.Âº 3/2026, SÃ©rie II de 2026-01-06",
    "link": "https://diariodarepublica.pt/dr/detalhe/contrato-publico/197-998616952"
  },
  {
    "numero_procedimento": "N/A",
    "entidade": "Instituto do Turismo de Portugal, IP",
    "link": "https://diariodarepublica.pt/dr/detalhe/contrato-publico/198-998616958",
    "detalhes_completos": "1 - IDENTIFICAÇÃO E CONTACTOS DA ENTIDADE ADJUDICANTE\nDesignação da entidade adjudicante: Instituto do Turismo de Portugal, IP\nNIPC: 508666236\nEndereço: Rua Ivone Silva, lote 6\nCódigo postal: 1050-124\nLocalidade: Lisboa\nPaís: Portugal\nNUT III: PT170\nDistrito: Lisboa\nConcelho: Lisboa\nFreguesia: Freguesia de Avenidas Novas\nTelefone: 211140200\nFax: 211140200\nEndereço da Entidade (URL): https://www.turismodeportugal.pt\nEndereço Eletrónico: info@turismodeportugal.pt\neDelivery Gateway (URL): https://community.vortal.biz/public/\nFunção da Organização: Adquirente\nNorma jurídica da Entidade Adjudicante: Instituição, órgão ou agência da UE\nÁrea de atividade da Autoridade Adjudicante: Serviços públicos das administrações públicas\n2 - JORNAL OFICIAL DA UNIÃO EUROPEIA\nO procedimento a que este anúncio diz respeito também é publicitado no Jornal Oficial da União Europeia? Não\n3 - AVISO\nModelo de Anúncio: Concurso público\nData de Envio do Anúncio: 06-01-2026\n5 - PROCESSO\nTipo de Procedimento: Concurso público\nPreço base do procedimento: Sim\nValor do preço base do procedimento: 14.350,00 EUR\nProcedimento com lotes? Não\n6 - OBJETO DO CONTRATO\nNúmero de referência interna: P(175/2025) 01/DPAC/202503694\nDesignação do contrato: Aquisição e montagem de unidade de alimentação ininterrupta (UPS) e de transformador de isolamento para o circuito de segurança da Escola de Hotelaria e Turismo de Portimão\nDescrição: Aquisição e montagem de unidade de alimentação ininterrupta (UPS) e de transformador de isolamento para o circuito de segurança da Escola de Hotelaria e Turismo de Portimão.\nTipo de Contrato Principal: Aquisição de Bens Móveis\nTipo de Contrato: Aquisição de Bens Móveis\nClassificação CPV (Vocabulário Comum para os Contratos Públicos)\nObjeto principal\nVocabulário Principal: 31682500\nPreço base s/IVA: 14.350,00 EUR\n7 - INDICAÇÕES ADICIONAIS\nO contrato envolve aquisição conjunta (satisfação de várias entidades)? Não\nO contrato é adjudicado por uma central de compras? Não\n8 - TÉCNICAS\nO concurso destina-se à celebração de um acordo-quadro? Inexistência de acordo-quadro\nÉ utilizado um leilão eletrónico? Não\nÉ adotada uma fase de negociação? Não\nSistema de Aquisição Dinâmico: Inexistência de sistema de aquisição dinâmico\n9 - LOCAL DA EXECUÇÃO DO CONTRATO\nLOCAL DA EXECUÇÃO DO CONTRATO (PROCEDIMENTO)\nPaís: Portugal\nNUT III: PT170\nLocalidade: Lisboa\nDistrito: Lisboa\nConcelho: Lisboa\nFreguesia: Freguesia de Avenidas Novas\n10 - PRAZO DE EXECUÇÃO DO CONTRATO\nPrazo de execução do contrato: 45 DIAS\nPrevisão de renovações: Não\n11 - FUNDOS EU\nTêm fundos EU? Não\n12 - DOCUMENTOS DE HABILITAÇÃO\nHabilitação para o exercício da atividade profissional: Não\n13 - CONDIÇÕES DE APRESENTAÇÃO\nPlataforma eletrónica utilizada pela entidade adjudicante: VORTAL\nURL para Apresentação: https://community.vortal.biz/public/\nAdmissibilidade da apresentação de propostas variantes: Não autorizado\nPrazo para apresentação das propostas: 21-01-2026 23:59\nPrazo durante o qual os concorrentes são obrigados a manter as respetivas propostas: 120 dias a contar do termo do prazo para a apresentação das propostas\nIndicação de Subcontratação na Proposta: Inexistência de indicação de subcontratação\n14 - PRESTAÇÃO DE CAUÇÃO\nPrestação de caução: Não\n15 - FORNECIMENTO DAS PEÇAS DO CONCURSO, APRESENTAÇÃO DE PEDIDOS DE PARTICIPAÇÃO E APRESENTAÇÃO DAS PROPOSTAS\nLink para acesso às peças do concurso (URL): https://community.vortal.biz/Public/public-tender-documents/QzU5TXErVzBLMDI2OFhRK0tCTlNEdERxNFYyZ3FPb3Rrek5FT1ZSaTVvRU1DWDVBUC9QUHR1NnpYUWZzeDZlYUpqL0tGSzFvYVhEczYzOWt5Sk5VWUE9PUtQZVV2\n20 - OUTROS REQUISITOS\nInformação sobre contratos reservados. Aplica-se a contratos reservados (54º-A)? Não\n21 - CRITÉRIO DE ADJUDICAÇÃO\nMultifator: Não\nMonofator:\nNome: Outros\nOutro nome: Preço\n24 - CONDIÇÕES DO CONTRATO\nFaturação Eletrónica: Permitido\nObrigação de Subcontratação:\nCódigo da Obrigação de Subcontratação: Não é aplicável nenhuma obrigação de subcontratação.\n25 - COMPRA PÚBLICA ESTRATÉGICA\nCompra Pública Estratégica: Inexistência de contratação pública estratégica\n26 - INFORMAÇÕES ADICIONAIS\nContrato adequado para PME: Sim\nCobertura ACP (Acordo dos Contratos Públicos da Organização Mundial do Comércio): Não\n27 - IDENTIFICAÇÃO E CONTACTOS DO ÓRGÃO DE RECURSOS ADMINISTRATIVOS\nDesignação: Conselho Diretivo do Instituto do Turismo de Portugal, I.P.\nEndereço: Rua Ivone Silva, Lote 6\nCódigo postal: 1050-124\nLocalidade: Lisboa\nTelefone: +351 211140200\nFax: +351 211140600\nEndereço eletrónico: dcgg-concursos@turismodeportugal.pt\n28 - IDENTIFICAÇÃO DO(S) AUTOR(ES) DE ANÚNCIO\nNome: Graça Carvalho\nCargo: Técnica superior\n419947222",
    "nipc": "508666236",
    "distrito": "Lisboa",
    "concelho": "Lisboa",
    "freguesia": "Freguesia de Avenidas Novas",
    "site": "https://www.turismodeportugal.pt",
    "email": "info@turismodeportugal.pt",
    "designacao_contrato": "Aquisição e montagem de unidade de alimentação ininterrupta (UPS) e de transformador de isolamento para o circuito de segurança da Escola de Hotelaria e Turismo de Portimão",
    "descricao": "Aquisição e montagem de unidade de alimentação ininterrupta (UPS) e de transformador de isolamento para o circuito de segurança da Escola de Hotelaria e Turismo de Portimão.",
    "preco_base": "14.350,00 EUR",
    "prazo_execucao": "45 DIAS",
    "prazo_apresentacao_propostas": "21-01-2026 23:59",
    "fundos_eu": "Não",
    "plataforma_eletronica": "VORTAL",
    "url_procedimento": "https://community.vortal.biz/public/",
    "autor_nome": "Graça Carvalho",
    "autor_cargo": "Técnica superior"
  },
  {
    "numero_procedimento": "N/A",
    "entidade": "Agência para a Reforma Tecnológica do Estado, IP",
    "link": "https://diariodarepublica.pt/dr/detalhe/contrato-publico/202-998616959",
    "detalhes_completos": "1 - IDENTIFICAÇÃO E CONTACTOS DA ENTIDADE ADJUDICANTE\nDesignação da entidade adjudicante: Agência para a Reforma Tecnológica do Estado, IP\nNIPC: 508184509\nServiço/Órgão/Pessoa de contacto: Divisão de Contratação Publica\nEndereço: Rua de Santa Marta n.º 55, 3º\nCódigo postal: 1150-294\nLocalidade: Lisboa\nPaís: Portugal\nNUT III: PT170\nDistrito: Lisboa\nConcelho: Lisboa\nFreguesia: Freguesia de Santo António - Lisboa\nTelefone: 217231200\nFax: 217231220\nEndereço da Entidade (URL): https://www.arte.gov.pt/\nEndereço Eletrónico: contratacao@ama.gov.pt\neDelivery Gateway (URL): https://www.acingov.pt\nFunção da Organização: Adquirente\nSubfunção da Organização: Organização que executa o pagamento; Organização que recebe as propostas; Organização que assina o contrato\nNorma jurídica da Entidade Adjudicante: Organismo de direito público\nÁrea de atividade da Autoridade Adjudicante: Serviços públicos das administrações públicas\n2 - JORNAL OFICIAL DA UNIÃO EUROPEIA\nO procedimento a que este anúncio diz respeito também é publicitado no Jornal Oficial da União Europeia? Não\n3 - AVISO\nModelo de Anúncio: Concurso público\nData de Envio do Anúncio: 06-01-2026\n5 - PROCESSO\nTipo de Procedimento: Concurso público\nPreço base do procedimento: Não\nProcedimento com lotes? Sim\nNº Máx. de Lotes Autorizado: 3\nNúmero máximo de lotes que podem ser adjudicados a um concorrente: 3\n6 - OBJETO DO CONTRATO\nNúmero de referência interna: CP/223/2025/ARTE\nDesignação do contrato: CONCURSO PÚBLICO N.º 223/2025/DCP/EAP/INSTALAÇÃO E EXPLORAÇÃO DE MÁQUINAS DE VENDA AUTOMÁTICA (DE BEBIDAS E SNACKS) NAS LOJAS DE CIDADÃO E SERVIÇOS CENTRAIS DA ARTE, I.P., DIVIDIDO EM 3 LOTES\nDescrição: instalação e exploração de máquinas de venda automática de bebidas (quentes e frias) e\nsnacks em Lojas do Cidadão e outras instalações da ARTE, cuja localização e volume de procura\njustificam a prestação de serviço que visa melhorar as condições dos funcionários e de espera dos\nutentes, nos termos e condições constantes no Caderno de Encargos (cláusula primeira do Caderno de\nEncargos, em anexo).\nTipo de Contrato Principal: Aquisição de Serviços\nTipo de Contrato: Aquisição de Serviços\nClassificação CPV (Vocabulário Comum para os Contratos Públicos)\nObjeto principal\nVocabulário Principal: 55000000\nLotes: \nNº: LOT-0001\nDescrição do Lote: De acordo com as peças do procedimento\nClassificação CPV (Vocabulário Comum para os Contratos Públicos)\nObjeto principal\nVocabulário Principal: 55000000\nNº: LOT-0002\nDescrição do Lote: De acordo com as peças do procedimento\nClassificação CPV (Vocabulário Comum para os Contratos Públicos)\nObjeto principal\nVocabulário Principal: 55000000\nNº: LOT-0003\nDescrição do Lote: De acordo com as peças do procedimento\nClassificação CPV (Vocabulário Comum para os Contratos Públicos)\nObjeto principal\nVocabulário Principal: 55000000\n7 - INDICAÇÕES ADICIONAIS\nO contrato envolve aquisição conjunta (satisfação de várias entidades)? Não\nO contrato é adjudicado por uma central de compras? Não\n8 - TÉCNICAS\nO concurso destina-se à celebração de um acordo-quadro? Inexistência de acordo-quadro\nÉ utilizado um leilão eletrónico? Não\nÉ adotada uma fase de negociação? Não\nSistema de Aquisição Dinâmico: Inexistência de sistema de aquisição dinâmico\n9 - LOCAL DA EXECUÇÃO DO CONTRATO\nLOCAL DA EXECUÇÃO DO CONTRATO (PROCEDIMENTO)\nPaís: Portugal\nNUT III: PT111\nLocalidade: TODAS\nDistrito: Todos\nConcelho: Todos\nFreguesia: Todas\nLOCAL DA EXECUÇÃO DO CONTRATO (LOTE)\nIdentificador do Lote: LOT-0001; LOT-0002; LOT-0003\nPaís: Portugal\nNUT III: PT111\nLocalidade: TODAS\nDistrito: Todos\nConcelho: Todos\nFreguesia: Todas\n10 - PRAZO DE EXECUÇÃO DO CONTRATO\nIdentificador do Lote: LOT-0001; LOT-0002; LOT-0003\nPrazo de execução do contrato: 12 MESES\nPrevisão de renovações: Sim\nIndicar número máximo de renovações: 1\nPrazo de renovações diferente do prazo inicial: Não\n11 - FUNDOS EU\nIdentificador do Lote: LOT-0001; LOT-0002; LOT-0003\nTêm fundos EU? Não\n12 - DOCUMENTOS DE HABILITAÇÃO\nHabilitação para o exercício da atividade profissional: Não\n13 - CONDIÇÕES DE APRESENTAÇÃO\nPlataforma eletrónica utilizada pela entidade adjudicante: ACIN\nURL para Apresentação: https://www.acingov.pt\nAdmissibilidade da apresentação de propostas variantes: Não autorizado\nPrazo para apresentação das propostas: 19-01-2026 23:59\nPrazo durante o qual os concorrentes são obrigados a manter as respetivas propostas: 120 dias a contar do termo do prazo para a apresentação das propostas\nIndicação de Subcontratação na Proposta: Inexistência de indicação de subcontratação\n14 - PRESTAÇÃO DE CAUÇÃO\nPrestação de caução: Sim\nPercentagem: 5%\nDescrição da Garantia Exigida: O adjudicatário deverá prestar uma caução destinada a garantir a celebração do contrato, bem como o exato e pontual cumprimento de todas as obrigações legais e contratuais que assume com essa celebração, no valor de 2 000,00 (dois mil euros) por lote, conforme artigo 33.º do Programa de Procedimento.\n15 - FORNECIMENTO DAS PEÇAS DO CONCURSO, APRESENTAÇÃO DE PEDIDOS DE PARTICIPAÇÃO E APRESENTAÇÃO DAS PROPOSTAS\nLink para acesso às peças do concurso (URL): https://www.acingov.pt/acingovprod/2/zonaPublica/zona_publica_c/donwloadProcedurePiece/MTAxMjE0Mg==\n20 - OUTROS REQUISITOS\nIdentificador do Lote: LOT-0001; LOT-0002; LOT-0003\nInformação sobre contratos reservados. Aplica-se a contratos reservados (54º-A)? Não\n21 - CRITÉRIO DE ADJUDICAÇÃO\nO Critério de adjudicação é diferenciado por lote? Não\nMultifator: Não\nMonofator:\nNome: Preço\n24 - CONDIÇÕES DO CONTRATO\nIdentificador do Lote: LOT-0001; LOT-0002; LOT-0003\nFaturação Eletrónica: Permitido\nObrigação de Subcontratação:\nCódigo da Obrigação de Subcontratação: Não é aplicável nenhuma obrigação de subcontratação.\n25 - COMPRA PÚBLICA ESTRATÉGICA\nCompra Pública Estratégica: Inexistência de contratação pública estratégica\n26 - INFORMAÇÕES ADICIONAIS\nIdentificador do Lote: LOT-0001; LOT-0002; LOT-0003\nContrato adequado para PME: Sim\nCobertura ACP (Acordo dos Contratos Públicos da Organização Mundial do Comércio): Não\n27 - IDENTIFICAÇÃO E CONTACTOS DO ÓRGÃO DE RECURSOS ADMINISTRATIVOS\nDesignação: Conselho Diretivo da ARTE, IP.\nEndereço: Rua de Santa Marta n.º 55, 3º\nCódigo postal: 1150-294\nLocalidade: Lisboa\nTelefone: 217231200\nFax: \nEndereço eletrónico: contratacao@ama.gov.pt\nPrazo de interposição do recurso: 10 dias\n28 - IDENTIFICAÇÃO DO(S) AUTOR(ES) DE ANÚNCIO\nNome: Miguel João Fernandes Garcia\nCargo: Técnico Superior\n419947283",
    "nipc": "508184509",
    "distrito": "Lisboa",
    "concelho": "Lisboa",
    "freguesia": "Freguesia de Santo António - Lisboa",
    "site": "https://www.arte.gov.pt/",
    "email": "contratacao@ama.gov.pt",
    "designacao_contrato": "CONCURSO PÚBLICO N.º 223/2025/DCP/EAP/INSTALAÇÃO E EXPLORAÇÃO DE MÁQUINAS DE VENDA AUTOMÁTICA (DE BEBIDAS E SNACKS) NAS LOJAS DE CIDADÃO E SERVIÇOS CENTRAIS DA ARTE, I.P., DIVIDIDO EM 3 LOTES",
    "descricao": "instalação e exploração de máquinas de venda automática de bebidas (quentes e frias) e",
    "preco_base": null,
    "prazo_execucao": "12 MESES",
    "prazo_apresentacao_propostas": "19-01-2026 23:59",
    "fundos_eu": "Não",
    "plataforma_eletronica": "ACIN",
    "url_procedimento": "https://www.acingov.pt",
    "autor_nome": "Miguel João Fernandes Garcia",
    "autor_cargo": "Técnico Superior"
  },
  {
    "numero_procedimento": "N/A",
    "entidade": "Unidade Local de Saúde do Alto Minho, EPE",
    "link": "https://diariodarepublica.pt/dr/detalhe/contrato-publico/204-998616961",
    "detalhes_completos": "1 - IDENTIFICAÇÃO E CONTACTOS DA ENTIDADE ADJUDICANTE\nDesignação da entidade adjudicante: Unidade Local de Saúde do Alto Minho, EPE\nNIPC: 508786193\nEndereço: Estrada de Santa Luzia, Viana do Castelo\nCódigo postal: 4904-858\nLocalidade: Viana do Castelo\nPaís: Portugal\nNUT III: PT111\nDistrito: Viana do Castelo\nConcelho: Viana do Castelo\nFreguesia: União das Freguesias de Viana do Castelo (Santa Maria Maior e Monserrate) e Meadela\nTelefone: 258802381\nFax: 258802389\nEndereço da Entidade (URL): https://www.ulsam.min-saude.pt\nEndereço Eletrónico: sourcing@ulsam.min-saude.pt\neDelivery Gateway (URL): https://community.vortal.biz/public/\nFunção da Organização: Adquirente\nNorma jurídica da Entidade Adjudicante: Organismo de direito público\nÁrea de atividade da Autoridade Adjudicante: Saúde\n2 - JORNAL OFICIAL DA UNIÃO EUROPEIA\nO procedimento a que este anúncio diz respeito também é publicitado no Jornal Oficial da União Europeia? Não\n3 - AVISO\nModelo de Anúncio: Concurso público\nData de Envio do Anúncio: 06-01-2026\n5 - PROCESSO\nTipo de Procedimento: Concurso público\nPreço base do procedimento: Sim\nValor do preço base do procedimento: 120.340,80 EUR\nProcedimento com lotes? Não\n6 - OBJETO DO CONTRATO\nNúmero de referência interna: 02/46/2026\nDesignação do contrato: ULTRACISION 2026 - CA-3314-CP-CR-251117-A \nDescrição: ULTRACISION 2026 - CA-3314-CP-CR-251117-A \nTipo de Contrato Principal: Aquisição de Bens Móveis\nTipo de Contrato: Aquisição de Bens Móveis\nClassificação CPV (Vocabulário Comum para os Contratos Públicos)\nObjeto principal\nVocabulário Principal: 33140000\nPreço base s/IVA: 120.340,80 EUR\n7 - INDICAÇÕES ADICIONAIS\nO contrato envolve aquisição conjunta (satisfação de várias entidades)? Não\nO contrato é adjudicado por uma central de compras? Não\n8 - TÉCNICAS\nO concurso destina-se à celebração de um acordo-quadro? Inexistência de acordo-quadro\nÉ utilizado um leilão eletrónico? Não\nÉ adotada uma fase de negociação? Não\nSistema de Aquisição Dinâmico: Inexistência de sistema de aquisição dinâmico\n9 - LOCAL DA EXECUÇÃO DO CONTRATO\nLOCAL DA EXECUÇÃO DO CONTRATO (PROCEDIMENTO)\nPaís: Portugal\nNUT III: PT111\nLocalidade: Viana do Castelo\nDistrito: Viana do Castelo\nConcelho: Viana do Castelo\nFreguesia: União das Freguesias de Viana do Castelo (Santa Maria Maior e Monserrate) e Meadela\n10 - PRAZO DE EXECUÇÃO DO CONTRATO\nPrazo de execução do contrato: 11 MESES\nPrevisão de renovações: Não\n11 - FUNDOS EU\nTêm fundos EU? Não\n12 - DOCUMENTOS DE HABILITAÇÃO\nHabilitação para o exercício da atividade profissional: Não\n13 - CONDIÇÕES DE APRESENTAÇÃO\nPlataforma eletrónica utilizada pela entidade adjudicante: VORTAL\nURL para Apresentação: https://community.vortal.biz/public/\nAdmissibilidade da apresentação de propostas variantes: Não autorizado\nPrazo para apresentação das propostas: 15-01-2026 18:00\nPrazo durante o qual os concorrentes são obrigados a manter as respetivas propostas: 120 dias a contar do termo do prazo para a apresentação das propostas\nIndicação de Subcontratação na Proposta: Inexistência de indicação de subcontratação\n14 - PRESTAÇÃO DE CAUÇÃO\nPrestação de caução: Não\n15 - FORNECIMENTO DAS PEÇAS DO CONCURSO, APRESENTAÇÃO DE PEDIDOS DE PARTICIPAÇÃO E APRESENTAÇÃO DAS PROPOSTAS\nLink para acesso às peças do concurso (URL): https://community.vortal.biz/Public/public-tender-documents/YVRCbzlSdHVaUEJucDJQcFdmZlU2VkViTjQvTm5aWThrK0pSMWpPMSt1S2ZQY1VPa1AvQ1VleTlyMG9NUFd4bDd2MTRkYnhiTmNQQnhaUkhlT2RnTUE9PShmR3Nj\n20 - OUTROS REQUISITOS\nInformação sobre contratos reservados. Aplica-se a contratos reservados (54º-A)? Não\n21 - CRITÉRIO DE ADJUDICAÇÃO\nMultifator: Não\nMonofator:\nNome: Preço\n24 - CONDIÇÕES DO CONTRATO\nFaturação Eletrónica: Permitido\nObrigação de Subcontratação:\nCódigo da Obrigação de Subcontratação: Não é aplicável nenhuma obrigação de subcontratação.\n25 - COMPRA PÚBLICA ESTRATÉGICA\nCompra Pública Estratégica: Inexistência de contratação pública estratégica\n26 - INFORMAÇÕES ADICIONAIS\nContrato adequado para PME: Sim\nCobertura ACP (Acordo dos Contratos Públicos da Organização Mundial do Comércio): Não\n27 - IDENTIFICAÇÃO E CONTACTOS DO ÓRGÃO DE RECURSOS ADMINISTRATIVOS\nDesignação: Conselho de Administração\nEndereço: Estrada de Santa Luzia\nCódigo postal: 4904-858\nLocalidade: Viana do Castelo\nTelefone: +351 258802166\nFax: +351 258802511\nEndereço eletrónico: administracao@ulsam.min-saude.pt\n28 - IDENTIFICAÇÃO DO(S) AUTOR(ES) DE ANÚNCIO\nNome: Cristina Videira Lopes Rodrigues\nCargo: Assistente Técnico do Serviço de Aprovisionamento\n419947246",
    "nipc": "508786193",
    "distrito": "Viana do Castelo",
    "concelho": "Viana do Castelo",
    "freguesia": "União das Freguesias de Viana do Castelo (Santa Maria Maior e Monserrate) e Meadela",
    "site": "https://www.ulsam.min-saude.pt",
    "email": "sourcing@ulsam.min-saude.pt",
    "designacao_contrato": "ULTRACISION 2026 - CA-3314-CP-CR-251117-A",
    "descricao": "ULTRACISION 2026 - CA-3314-CP-CR-251117-A",
    "preco_base": "120.340,80 EUR",
    "prazo_execucao": "11 MESES",
    "prazo_apresentacao_propostas": "15-01-2026 18:00",
    "fundos_eu": "Não",
    "plataforma_eletronica": "VORTAL",
    "url_procedimento": "https://community.vortal.biz/public/",
    "autor_nome": "Cristina Videira Lopes Rodrigues",
    "autor_cargo": "Assistente Técnico do Serviço de Aprovisionamento"
  },
  {
    "numero_procedimento": "N/A",
    "entidade": "ViniPortugal - Associação Interprofissional do Vinho",
    "link": "https://diariodarepublica.pt/dr/detalhe/contrato-publico/208-998616963",
    "detalhes_completos": "1 - IDENTIFICAÇÃO E CONTACTOS DA ENTIDADE ADJUDICANTE\nDesignação da entidade adjudicante: ViniPortugal - Associação Interprofissional do Vinho\nNIPC: 503736864\nEndereço: Rua Mouzinho da Silveira, 5 \nCódigo postal: 2560-312\nLocalidade: Lisboa\nPaís: Portugal\nNUT III: PT16B\nDistrito: Lisboa\nConcelho: Torres Vedras\nFreguesia: Todas\nTelefone: 213569890\nFax: 213569895\nEndereço da Entidade (URL): https://viniportugal.pt/pt/\nEndereço Eletrónico: geral@viniportugal.pt\neDelivery Gateway (URL): https://community.vortal.biz/public/\nFunção da Organização: Adquirente\nNorma jurídica da Entidade Adjudicante: Organismo de direito público\nÁrea de atividade da Autoridade Adjudicante: Educação\n2 - JORNAL OFICIAL DA UNIÃO EUROPEIA\nO procedimento a que este anúncio diz respeito também é publicitado no Jornal Oficial da União Europeia? Não\n3 - AVISO\nModelo de Anúncio: Concurso limitado por prévia qualificação\nData de Envio do Anúncio: 06-01-2026\n5 - PROCESSO\nTipo de Procedimento: Concurso limitado por prévia qualificação\nPreço base do procedimento: Sim\nValor do preço base do procedimento: 90.000,00 EUR\nProcedimento com lotes? Não\n6 - OBJETO DO CONTRATO\nNúmero de referência interna: 2025.56\nDesignação do contrato: Prestação de Serviços de Execução do Plano de Marketing Anual da Marca Wines of Portugal, para o mercado de Angola, ano 2026\nDescrição: Prestação de Serviços de Execução do Plano de Marketing Anual da Marca Wines of Portugal, para o mercado de Angola, ano 2026\nTipo de Contrato Principal: Aquisição de Serviços\nTipo de Contrato: Aquisição de Serviços\nClassificação CPV (Vocabulário Comum para os Contratos Públicos)\nObjeto principal\nVocabulário Principal: 79342200\nPreço base s/IVA: 90.000,00 EUR\n7 - INDICAÇÕES ADICIONAIS\nO contrato envolve aquisição conjunta (satisfação de várias entidades)? Não\nO contrato é adjudicado por uma central de compras? Não\n8 - TÉCNICAS\nO concurso destina-se à celebração de um acordo-quadro? Inexistência de acordo-quadro\nÉ utilizado um leilão eletrónico? Não\nSistema de Aquisição Dinâmico: Inexistência de sistema de aquisição dinâmico\n9 - LOCAL DA EXECUÇÃO DO CONTRATO\nLOCAL DA EXECUÇÃO DO CONTRATO (PROCEDIMENTO)\nPaís: Portugal\nNUT III: PT170\nLocalidade: Lisboa\nDistrito: Lisboa\nConcelho: Lisboa\nFreguesia: Todas\n10 - PRAZO DE EXECUÇÃO DO CONTRATO\nPrazo de execução do contrato: 1 ANOS\nPrevisão de renovações: Não\n11 - FUNDOS EU\nTêm fundos EU? Não\n12 - DOCUMENTOS DE HABILITAÇÃO\nHabilitação para o exercício da atividade profissional: Não\n13 - CONDIÇÕES DE APRESENTAÇÃO\nPlataforma eletrónica utilizada pela entidade adjudicante: VORTAL\nURL para Apresentação: https://community.vortal.biz/public/\nAdmissibilidade da apresentação de propostas variantes: Não autorizado\nPrazo para apresentação das candidaturas: 16-01-2026 17:00\nRequisitos mínimos \nRequisitos mínimos de capacidade técnica: Conforme as peças do procedimento\nRequisitos mínimos de capacidade financeira: Conforme as peças do procedimento\nPrazo durante o qual os concorrentes são obrigados a manter as respetivas propostas: 180 dias a contar do termo do prazo para a apresentação das propostas\nIndicação de Subcontratação na Proposta: Inexistência de indicação de subcontratação\n14 - PRESTAÇÃO DE CAUÇÃO\nPrestação de caução: Não\n15 - FORNECIMENTO DAS PEÇAS DO CONCURSO, APRESENTAÇÃO DE PEDIDOS DE PARTICIPAÇÃO E APRESENTAÇÃO DAS PROPOSTAS\nLink para acesso às peças do concurso (URL): https://community.vortal.biz/Public/public-tender-documents/VFJVKy9DK0NHY24weWNiTHhHRkFxSVVFRGY4Nkt3N2xjWGNnWnRINGp5bi83cENYaUQvbjBTNGNWVUFxckEyQUZDZnkyK1BFREd0UmhHc3dLb2RyaEE9PWx4a255\n20 - OUTROS REQUISITOS\nInformação sobre contratos reservados. Aplica-se a contratos reservados (54º-A)? Não\n21 - CRITÉRIO DE ADJUDICAÇÃO\nMultifator: Sim\nFator: \nNome: Preço\nPonderação: 30%\nSubfatores: Não\nFator: \nNome: Qualidade\nPonderação: 70%\nSubfatores: Sim\nSubfatores: \nNome: Qualidade Total\nPonderação : 60%; \nNome: Actividades Extras ou Benefícios Adicionais\nPonderação : 40%; \n24 - CONDIÇÕES DO CONTRATO\nFaturação Eletrónica: Permitido\nObrigação de Subcontratação:\nCódigo da Obrigação de Subcontratação: Não é aplicável nenhuma obrigação de subcontratação.\n25 - COMPRA PÚBLICA ESTRATÉGICA\nCompra Pública Estratégica: Inexistência de contratação pública estratégica\n26 - INFORMAÇÕES ADICIONAIS\nContrato adequado para PME: Sim\nCobertura ACP (Acordo dos Contratos Públicos da Organização Mundial do Comércio): Não\n27 - IDENTIFICAÇÃO E CONTACTOS DO ÓRGÃO DE RECURSOS ADMINISTRATIVOS\nDesignação: Pedro Fernandes\nEndereço: Rua Mouzinho da Silveira, n.º5\nCódigo postal: 1250-165\nLocalidade: Lisboa\nTelefone: +351 213569890\nFax: +351 213569890\nEndereço eletrónico: processo-concursal@viniportugal.pt\n28 - IDENTIFICAÇÃO DO(S) AUTOR(ES) DE ANÚNCIO\nNome: Pedro Fernandes\nCargo: Director Financeiro\n419947308",
    "nipc": "503736864",
    "distrito": "Lisboa",
    "concelho": "Torres Vedras",
    "freguesia": "Todas",
    "site": "https://viniportugal.pt/pt/",
    "email": "geral@viniportugal.pt",
    "designacao_contrato": "Prestação de Serviços de Execução do Plano de Marketing Anual da Marca Wines of Portugal, para o mercado de Angola, ano 2026",
    "descricao": "Prestação de Serviços de Execução do Plano de Marketing Anual da Marca Wines of Portugal, para o mercado de Angola, ano 2026",
    "preco_base": "90.000,00 EUR",
    "prazo_execucao": "1 ANOS",
    "prazo_apresentacao_propostas": null,
    "fundos_eu": "Não",
    "plataforma_eletronica": "VORTAL",
    "url_procedimento": "https://community.vortal.biz/public/",
    "autor_nome": "Pedro Fernandes",
    "autor_cargo": "Director Financeiro"
  },
  {
    "numero_procedimento": "N/A",
    "entidade": "IHM - Investimentos Habitacionais da Madeira, EPERAM",
    "link": "https://diariodarepublica.pt/dr/detalhe/contrato-publico/206-998665102",
    "detalhes_completos": "1 - IDENTIFICAÇÃO E CONTACTOS DA ENTIDADE ADJUDICANTE\nDesignação da entidade adjudicante: IHM - Investimentos Habitacionais da Madeira, EPERAM\nNIPC: 511035365\nServiço/Órgão/Pessoa de contacto: Conselho de Administração da IHM, EPERAM\nEndereço: Rua Dr. Pestana Júnior, n.º6\nCódigo postal: 9064-506\nLocalidade: Funchal\nPaís: Portugal\nNUT III: PT300\nDistrito: Região Autónoma da Madeira\nConcelho: Funchal\nFreguesia: Freguesia de Santa Maria Maior (Funchal)\nTelefone: 291145240\nFax: 291225161\nEndereço da Entidade (URL): www.ihm.pt\nEndereço Eletrónico: conselhoadministracao@ihm.pt\neDelivery Gateway (URL): https://www.acingov.pt\nFunção da Organização: Adquirente\nSubfunção da Organização: Organização que recebe as propostas\nNorma jurídica da Entidade Adjudicante: Organismo de direito público\nÁrea de atividade da Autoridade Adjudicante: Serviços públicos das administrações públicas\n2 - JORNAL OFICIAL DA UNIÃO EUROPEIA\nO procedimento a que este anúncio diz respeito também é publicitado no Jornal Oficial da União Europeia? Não\n3 - AVISO\nModelo de Anúncio: Concurso público\nData de Envio do Anúncio: 06-01-2026\n5 - PROCESSO\nTipo de Procedimento: Concurso público\nPreço base do procedimento: Sim\nValor do preço base do procedimento: 400.000,00 EUR\nProcedimento com lotes? Sim\nNº Máx. de Lotes Autorizado: 2\nNúmero máximo de lotes que podem ser adjudicados a um concorrente: 1\n6 - OBJETO DO CONTRATO\nNúmero de referência interna: EMP-M/3/2025\nDesignação do contrato: Empreitada de Pequenas Reparações nos Fogos, Zonas Comuns e Exteriores dos Conjuntos Habitacionais sob Gestão da IHM EPERAM no Concelho do Funchal\nDescrição: Empreitada de Pequenas Reparações nos Fogos, Zonas Comuns e Exteriores dos Conjuntos Habitacionais sob Gestão da IHM EPERAM no Concelho do Funchal\nTipo de Contrato Principal: Empreitada de Obras Públicas\nTipo de Contrato: Empreitada de Obras Públicas\nClassificação CPV (Vocabulário Comum para os Contratos Públicos)\nObjeto principal\nVocabulário Principal: 45453100\nPreço base s/IVA: 400.000,00 EUR\nLotes: \nNº: LOT-0001\nDescrição do Lote: Execução de trabalhos de manutenção de fogos zonas comuns e exteriores dos conjuntos habitacionais sob gestão da IHM no concelho do Funchal, nas freguesias de São Martinho, Santa Maria Maior e São Gonçalo\nPreço base s/IVA: 200.000,00 EUR\nClassificação CPV (Vocabulário Comum para os Contratos Públicos)\nObjeto principal\nVocabulário Principal: 45453100\nNº: LOT-0002\nDescrição do Lote: Execução de trabalhos de manutenção de fogos zonas comuns e exteriores dos conjuntos habitacionais sob gestão da IHM no concelho do Funchal, nas freguesias de Santo António, São Roque, Imaculado coração de Maria, Santa Luzia e São Pedro\nPreço base s/IVA: 200.000,00 EUR\nClassificação CPV (Vocabulário Comum para os Contratos Públicos)\nObjeto principal\nVocabulário Principal: 45453100\n7 - INDICAÇÕES ADICIONAIS\nO contrato envolve aquisição conjunta (satisfação de várias entidades)? Não\nO contrato é adjudicado por uma central de compras? Não\n8 - TÉCNICAS\nO concurso destina-se à celebração de um acordo-quadro? Inexistência de acordo-quadro\nÉ utilizado um leilão eletrónico? Não\nÉ adotada uma fase de negociação? Não\nSistema de Aquisição Dinâmico: Inexistência de sistema de aquisição dinâmico\n9 - LOCAL DA EXECUÇÃO DO CONTRATO\nLOCAL DA EXECUÇÃO DO CONTRATO (PROCEDIMENTO)\nPaís: Portugal\nNUT III: PT300\nLocalidade: Conjuntos Habitacionais sob Gestão da IHM EPERAM no Concelho do Funchal\nDistrito: Região Autónoma da Madeira\nConcelho: Funchal\nFreguesia: Todas\nLOCAL DA EXECUÇÃO DO CONTRATO (LOTE)\nIdentificador do Lote: LOT-0001; LOT-0002\nPaís: Portugal\nNUT III: PT300\nLocalidade: Conjuntos Habitacionais sob Gestão da IHM EPERAM no Concelho do Funchal\nDistrito: Região Autónoma da Madeira\nConcelho: Funchal\nFreguesia: Todas\n10 - PRAZO DE EXECUÇÃO DO CONTRATO\nIdentificador do Lote: LOT-0001; LOT-0002\nPrazo de execução do contrato: 240 DIAS\nPrevisão de renovações: Não\n11 - FUNDOS EU\nIdentificador do Lote: LOT-0001; LOT-0002\nTêm fundos EU? Não\n12 - DOCUMENTOS DE HABILITAÇÃO\nHabilitação para o exercício da atividade profissional: Sim\nTipo: Alvará\nDescrição: Identificação das habilitações que deverão constar do alvará de construção do adjudicatário:\na) A 1.ª Subcategoria da 1.ª Categoria, na classe correspondente ao valor global da proposta;\nb) As 4.ª, 5.ª, 6.ª, 7.ª e 8.ª Subcategorias da 1.ª Categoria, na classe correspondente à parte dos trabalhos a que respeitem, caso o concorrente não recorra à faculdade conferida no Programa do Procedimento.\n13 - CONDIÇÕES DE APRESENTAÇÃO\nPlataforma eletrónica utilizada pela entidade adjudicante: ACIN\nURL para Apresentação: https://www.acingov.pt\nAdmissibilidade da apresentação de propostas variantes: Não autorizado\nPrazo para apresentação das propostas: 21-01-2026 23:59\nPrazo durante o qual os concorrentes são obrigados a manter as respetivas propostas: 66 dias a contar do termo do prazo para a apresentação das propostas\nIndicação de Subcontratação na Proposta: Inexistência de indicação de subcontratação\n14 - PRESTAÇÃO DE CAUÇÃO\nPrestação de caução: Não\n15 - FORNECIMENTO DAS PEÇAS DO CONCURSO, APRESENTAÇÃO DE PEDIDOS DE PARTICIPAÇÃO E APRESENTAÇÃO DAS PROPOSTAS\nLink para acesso às peças do concurso (URL): https://www.acingov.pt/acingovprod/2/zonaPublica/zona_publica_c/donwloadProcedurePiece/OTcxMTgx\n20 - OUTROS REQUISITOS\nIdentificador do Lote: LOT-0001; LOT-0002\nInformação sobre contratos reservados. Aplica-se a contratos reservados (54º-A)? Não\n21 - CRITÉRIO DE ADJUDICAÇÃO\nO Critério de adjudicação é diferenciado por lote? Não\nMultifator: Não\nMonofator:\nNome: Preço\n24 - CONDIÇÕES DO CONTRATO\nIdentificador do Lote: LOT-0001; LOT-0002\nFaturação Eletrónica: Permitido\nObrigação de Subcontratação:\nCódigo da Obrigação de Subcontratação: Não é aplicável nenhuma obrigação de subcontratação.\n25 - COMPRA PÚBLICA ESTRATÉGICA\nCompra Pública Estratégica: Realização dos objetivos sociais\nCategorias da estratégia nacional: Outros\nOutra categoria (Descrição): N/A\nContratos Públicos Sociais: Outros\nCritério de Acessibilidade: Os critérios de acessibilidade para as pessoas com deficiência não estão incluídos porque o contrato não se destina a pessoas singulares\n26 - INFORMAÇÕES ADICIONAIS\nIdentificador do Lote: LOT-0001; LOT-0002\nContrato adequado para PME: Sim\nCobertura ACP (Acordo dos Contratos Públicos da Organização Mundial do Comércio): Não\n27 - IDENTIFICAÇÃO E CONTACTOS DO ÓRGÃO DE RECURSOS ADMINISTRATIVOS\nDesignação: Conselho de Administração da IHM\nEndereço: Rua Dr. Pestana Júnior, n.º6\nCódigo postal: 9064-506\nLocalidade: Funchal\nTelefone: 291145240\nFax: \nEndereço eletrónico: conselhoadministracao@ihm.pt\n28 - IDENTIFICAÇÃO DO(S) AUTOR(ES) DE ANÚNCIO\nNome: Leonel Correia da Silva\nCargo: Presidente do Conselho de Administração\n419947271",
    "nipc": "511035365",
    "distrito": "Região Autónoma da Madeira",
    "concelho": "Funchal",
    "freguesia": "Freguesia de Santa Maria Maior (Funchal)",
    "site": "www.ihm.pt",
    "email": "conselhoadministracao@ihm.pt",
    "designacao_contrato": "Empreitada de Pequenas Reparações nos Fogos, Zonas Comuns e Exteriores dos Conjuntos Habitacionais sob Gestão da IHM EPERAM no Concelho do Funchal",
    "descricao": "Empreitada de Pequenas Reparações nos Fogos, Zonas Comuns e Exteriores dos Conjuntos Habitacionais sob Gestão da IHM EPERAM no Concelho do Funchal",
    "preco_base": "400.000,00 EUR",
    "prazo_execucao": "240 DIAS",
    "prazo_apresentacao_propostas": "21-01-2026 23:59",
    "fundos_eu": "Não",
    "plataforma_eletronica": "ACIN",
    "url_procedimento": "https://www.acingov.pt",
    "autor_nome": "Leonel Correia da Silva",
    "autor_cargo": "Presidente do Conselho de Administração"
  },
  {
    "numero_procedimento": "N/A",
    "entidade": "Agrupamento de Escolas de Souselo, Cinfães",
    "link": "https://diariodarepublica.pt/dr/detalhe/contrato-publico/207-998665103",
    "detalhes_completos": "1 - IDENTIFICAÇÃO E CONTACTOS DA ENTIDADE ADJUDICANTE\nDesignação da entidade adjudicante: Agrupamento de Escolas de Souselo, Cinfães\nNIPC: 600076075\nEndereço: Rua Santo André, nº 4636\nCódigo postal: 4690-616\nLocalidade: Viseu\nPaís: Portugal\nNUT III: PT11C\nDistrito: Viseu\nConcelho: Cinfães\nFreguesia: Todas\nTelefone: 255690370\nFax: 255690379\nEndereço Eletrónico: geral@escolasdesouselo.pt\neDelivery Gateway (URL): https://community.vortal.biz/public/\nFunção da Organização: Adquirente\nNorma jurídica da Entidade Adjudicante: Instituição, órgão ou agência da UE\nÁrea de atividade da Autoridade Adjudicante: Educação\n2 - JORNAL OFICIAL DA UNIÃO EUROPEIA\nO procedimento a que este anúncio diz respeito também é publicitado no Jornal Oficial da União Europeia? Não\n3 - AVISO\nModelo de Anúncio: Concurso público\nData de Envio do Anúncio: 06-01-2026\n5 - PROCESSO\nTipo de Procedimento: Concurso público\nPreço base do procedimento: Sim\nValor do preço base do procedimento: 100.219,68 EUR\nProcedimento com lotes? Sim\nNº Máx. de Lotes Autorizado: 8\nNúmero máximo de lotes que podem ser adjudicados a um concorrente: 8\n6 - OBJETO DO CONTRATO\nNúmero de referência interna: CPN 01/2026 Refeitório e Bufete\nDesignação do contrato: CPN 01/2026 Refeitório e Bufete\nDescrição: CPN 01/2026 Refeitório e Bufete\nTipo de Contrato Principal: Aquisição de Bens Móveis\nTipo de Contrato: Aquisição de Bens Móveis\nClassificação CPV (Vocabulário Comum para os Contratos Públicos)\nObjeto principal\nVocabulário Principal: 15800000\nPreço base s/IVA: 50.738,25 EUR\nObjeto Complementar\nVocabulário Principal: 15100000\nPreço base s/IVA: 21.640,25 EUR\nObjeto Complementar\nVocabulário Principal: 15300000\nPreço base s/IVA: 20.782,10 EUR\nObjeto Complementar\nVocabulário Principal: 15500000\nPreço base s/IVA: 7.059,08 EUR\nLotes: \nNº: LOT-0001\nDescrição do Lote: Lote1\nPreço base s/IVA: 21.640,25 EUR\nClassificação CPV (Vocabulário Comum para os Contratos Públicos)\nObjeto principal\nVocabulário Principal: 15800000\nObjeto Complementar\nVocabulário Principal: 15100000\nObjeto Complementar\nVocabulário Principal: 15300000\nObjeto Complementar\nVocabulário Principal: 15500000\nNº: LOT-0002\nDescrição do Lote: Lote2\nPreço base s/IVA: 20.782,10 EUR\nClassificação CPV (Vocabulário Comum para os Contratos Públicos)\nObjeto principal\nVocabulário Principal: 15800000\nObjeto Complementar\nVocabulário Principal: 15100000\nObjeto Complementar\nVocabulário Principal: 15300000\nObjeto Complementar\nVocabulário Principal: 15500000\nNº: LOT-0003\nDescrição do Lote: Lote3\nPreço base s/IVA: 14.034,00 EUR\nClassificação CPV (Vocabulário Comum para os Contratos Públicos)\nObjeto principal\nVocabulário Principal: 15800000\nObjeto Complementar\nVocabulário Principal: 15100000\nObjeto Complementar\nVocabulário Principal: 15300000\nObjeto Complementar\nVocabulário Principal: 15500000\nNº: LOT-0004\nDescrição do Lote: Lote4\nPreço base s/IVA: 7.059,08 EUR\nClassificação CPV (Vocabulário Comum para os Contratos Públicos)\nObjeto principal\nVocabulário Principal: 15800000\nObjeto Complementar\nVocabulário Principal: 15100000\nObjeto Complementar\nVocabulário Principal: 15300000\nObjeto Complementar\nVocabulário Principal: 15500000\nNº: LOT-0005\nDescrição do Lote: Lote5\nPreço base s/IVA: 14.968,65 EUR\nClassificação CPV (Vocabulário Comum para os Contratos Públicos)\nObjeto principal\nVocabulário Principal: 15800000\nObjeto Complementar\nVocabulário Principal: 15100000\nObjeto Complementar\nVocabulário Principal: 15300000\nObjeto Complementar\nVocabulário Principal: 15500000\nNº: LOT-0006\nDescrição do Lote: Lote6\nPreço base s/IVA: 17.342,60 EUR\nClassificação CPV (Vocabulário Comum para os Contratos Públicos)\nObjeto principal\nVocabulário Principal: 15800000\nObjeto Complementar\nVocabulário Principal: 15100000\nObjeto Complementar\nVocabulário Principal: 15300000\nObjeto Complementar\nVocabulário Principal: 15500000\nNº: LOT-0007\nDescrição do Lote: Lote7\nPreço base s/IVA: 348,00 EUR\nClassificação CPV (Vocabulário Comum para os Contratos Públicos)\nObjeto principal\nVocabulário Principal: 15800000\nObjeto Complementar\nVocabulário Principal: 15100000\nObjeto Complementar\nVocabulário Principal: 15300000\nObjeto Complementar\nVocabulário Principal: 15500000\nNº: LOT-0008\nDescrição do Lote: Lote8\nPreço base s/IVA: 4.045,00 EUR\nClassificação CPV (Vocabulário Comum para os Contratos Públicos)\nObjeto principal\nVocabulário Principal: 15800000\nObjeto Complementar\nVocabulário Principal: 15100000\nObjeto Complementar\nVocabulário Principal: 15300000\nObjeto Complementar\nVocabulário Principal: 15500000\n7 - INDICAÇÕES ADICIONAIS\nO contrato envolve aquisição conjunta (satisfação de várias entidades)? Não\nO contrato é adjudicado por uma central de compras? Não\n8 - TÉCNICAS\nO concurso destina-se à celebração de um acordo-quadro? Inexistência de acordo-quadro\nÉ utilizado um leilão eletrónico? Não\nÉ adotada uma fase de negociação? Não\nSistema de Aquisição Dinâmico: Inexistência de sistema de aquisição dinâmico\n9 - LOCAL DA EXECUÇÃO DO CONTRATO\nLOCAL DA EXECUÇÃO DO CONTRATO (PROCEDIMENTO)\nPaís: Portugal\nNUT III: PT11C\nLocalidade: Viseu\nDistrito: Viseu\nConcelho: Cinfães\nFreguesia: Todas\nLOCAL DA EXECUÇÃO DO CONTRATO (LOTE)\nIdentificador do Lote: LOT-0001; LOT-0002; LOT-0003; LOT-0004; LOT-0005; LOT-0006; LOT-0007; LOT-0008\nPaís: Portugal\nNUT III: PT11C\nLocalidade: Viseu\nDistrito: Viseu\nConcelho: Cinfães\nFreguesia: Todas\n10 - PRAZO DE EXECUÇÃO DO CONTRATO\nIdentificador do Lote: LOT-0001; LOT-0002; LOT-0003; LOT-0004; LOT-0005; LOT-0006; LOT-0007; LOT-0008\nPrazo de execução do contrato: 365 DIAS\nPrevisão de renovações: Não\n11 - FUNDOS EU\nIdentificador do Lote: LOT-0001; LOT-0002; LOT-0003; LOT-0004; LOT-0005; LOT-0006; LOT-0007; LOT-0008\nTêm fundos EU? Não\n12 - DOCUMENTOS DE HABILITAÇÃO\nHabilitação para o exercício da atividade profissional: Não\n13 - CONDIÇÕES DE APRESENTAÇÃO\nPlataforma eletrónica utilizada pela entidade adjudicante: VORTAL\nURL para Apresentação: https://community.vortal.biz/public/\nAdmissibilidade da apresentação de propostas variantes: Não autorizado\nPrazo para apresentação das propostas: 15-01-2026 23:59\nPrazo durante o qual os concorrentes são obrigados a manter as respetivas propostas: 66 dias a contar do termo do prazo para a apresentação das propostas\nIndicação de Subcontratação na Proposta: Inexistência de indicação de subcontratação\n14 - PRESTAÇÃO DE CAUÇÃO\nPrestação de caução: Não\n15 - FORNECIMENTO DAS PEÇAS DO CONCURSO, APRESENTAÇÃO DE PEDIDOS DE PARTICIPAÇÃO E APRESENTAÇÃO DAS PROPOSTAS\nLink para acesso às peças do concurso (URL): https://community.vortal.biz/Public/public-tender-documents/WFlaZ1IybFpsSi9CbWpuZmMrNGRpU3BTM1FFdEZNVGpKeHAvLzdyZUJGeDRWQW9OcXU4M1R4cWlsQmdsa2lPRHdJeGg2ODY2eUJ2UVNueXdpTkhDTXc9PShSYzVn\n20 - OUTROS REQUISITOS\nIdentificador do Lote: LOT-0001; LOT-0002; LOT-0003; LOT-0004; LOT-0005; LOT-0006; LOT-0007; LOT-0008\nInformação sobre contratos reservados. Aplica-se a contratos reservados (54º-A)? Não\n21 - CRITÉRIO DE ADJUDICAÇÃO\nO Critério de adjudicação é diferenciado por lote? Não\nMultifator: Não\nMonofator:\nNome: Preço\n24 - CONDIÇÕES DO CONTRATO\nIdentificador do Lote: LOT-0001; LOT-0002; LOT-0003; LOT-0004; LOT-0005; LOT-0006; LOT-0007; LOT-0008\nFaturação Eletrónica: Permitido\nObrigação de Subcontratação:\nCódigo da Obrigação de Subcontratação: Não é aplicável nenhuma obrigação de subcontratação.\n25 - COMPRA PÚBLICA ESTRATÉGICA\nCompra Pública Estratégica: Inexistência de contratação pública estratégica\n26 - INFORMAÇÕES ADICIONAIS\nIdentificador do Lote: LOT-0001; LOT-0002; LOT-0003; LOT-0004; LOT-0005; LOT-0006; LOT-0007; LOT-0008\nContrato adequado para PME: Sim\nCobertura ACP (Acordo dos Contratos Públicos da Organização Mundial do Comércio): Não\n27 - IDENTIFICAÇÃO E CONTACTOS DO ÓRGÃO DE RECURSOS ADMINISTRATIVOS\nDesignação: Conselho Administrativo\nEndereço: Rua Santo André, n.º 4636\nCódigo postal: 4690-616\nLocalidade: Cinfães\nTelefone: +351 255690370\nFax: +351 255690370\nEndereço eletrónico: gestao@agrupamentosouselo.com\n28 - IDENTIFICAÇÃO DO(S) AUTOR(ES) DE ANÚNCIO\nNome: Carlos Manuel Santos da Silveira\nCargo: Diretor\n419947305",
    "nipc": "600076075",
    "distrito": "Viseu",
    "concelho": "Cinfães",
    "freguesia": "Todas",
    "site": null,
    "email": "geral@escolasdesouselo.pt",
    "designacao_contrato": "CPN 01/2026 Refeitório e Bufete",
    "descricao": "CPN 01/2026 Refeitório e Bufete",
    "preco_base": "50.738,25 EUR",
    "prazo_execucao": "365 DIAS",
    "prazo_apresentacao_propostas": "15-01-2026 23:59",
    "fundos_eu": "Não",
    "plataforma_eletronica": "VORTAL",
    "url_procedimento": "https://community.vortal.biz/public/",
    "autor_nome": "Carlos Manuel Santos da Silveira",
    "autor_cargo": "Diretor"
  }
]