[
  {
    "numero_procedimento": "N/A",
    "entidade": "AnÃºncio de procedimento  n.Âº 380/2026  -  DiÃ¡rio da RepÃºblica n.Âº 6/2026, SÃ©rie II de 2026-01-09",
    "link": "https://diariodarepublica.pt/dr/detalhe/contrato-publico/380-1002139957"
  },
  {
    "numero_procedimento": "N/A",
    "entidade": "CI-AMAL - Comunidade Intermunicipal do Algarve",
    "link": "https://diariodarepublica.pt/dr/detalhe/contrato-publico/381-1002139960",
    "detalhes_completos": "1 - IDENTIFICAÇÃO E CONTACTOS DA ENTIDADE ADJUDICANTE\nDesignação da entidade adjudicante: CI-AMAL - Comunidade Intermunicipal do Algarve\nNIPC: 502971096\nServiço/Órgão/Pessoa de contacto: DASP / Contratação Pública\nEndereço: Rua General Humberto Delgado N.º 20\nCódigo postal: 8000-355\nLocalidade: Faro\nPaís: Portugal\nNUT III: PT150\nDistrito: Faro\nConcelho: Faro\nFreguesia: União das Freguesias de Faro (Sé e São Pedro)\nTelefone: 289880800\nFax: 000000000\nEndereço da Entidade (URL): www.amal.pt\nEndereço Eletrónico: geral@amal.pt\neDelivery Gateway (URL): https://www.acingov.pt\nFunção da Organização: Adquirente\nNorma jurídica da Entidade Adjudicante: Organismo de direito público\nÁrea de atividade da Autoridade Adjudicante: Serviços públicos das administrações públicas\n2 - JORNAL OFICIAL DA UNIÃO EUROPEIA\nO procedimento a que este anúncio diz respeito também é publicitado no Jornal Oficial da União Europeia? Não\n3 - AVISO\nModelo de Anúncio: Concurso público\nData de Envio do Anúncio: 08-01-2026\n5 - PROCESSO\nTipo de Procedimento: Concurso público\nPreço base do procedimento: Sim\nValor do preço base do procedimento: 135.000,00 EUR\nProcedimento com lotes? Não\n6 - OBJETO DO CONTRATO\nNúmero de referência interna: CP/10/2025\nDesignação do contrato: CP n.º 10/2025 - Contratação de Prestação de Serviços: Adaptação do PMUS do Algarve, Geração 2.0\nDescrição: Contratação de Prestação de Serviços: Adaptação do PMUS do Algarve, Geração 2.0\nTipo de Contrato Principal: Aquisição de Serviços\nTipo de Contrato: Aquisição de Serviços\nClassificação CPV (Vocabulário Comum para os Contratos Públicos)\nObjeto principal\nVocabulário Principal: 71311200\nPreço base s/IVA: 135.000,00 EUR\n7 - INDICAÇÕES ADICIONAIS\nO contrato envolve aquisição conjunta (satisfação de várias entidades)? Não\nO contrato é adjudicado por uma central de compras? Não\n8 - TÉCNICAS\nO concurso destina-se à celebração de um acordo-quadro? Inexistência de acordo-quadro\nÉ utilizado um leilão eletrónico? Não\nÉ adotada uma fase de negociação? Não\nSistema de Aquisição Dinâmico: Inexistência de sistema de aquisição dinâmico\n9 - LOCAL DA EXECUÇÃO DO CONTRATO\nLOCAL DA EXECUÇÃO DO CONTRATO (PROCEDIMENTO)\nPaís: Portugal\nNUT III: PT150\nLocalidade: Todas\nDistrito: Faro\nConcelho: Todos\nFreguesia: Todas\n10 - PRAZO DE EXECUÇÃO DO CONTRATO\nPrazo de execução do contrato: 10 MESES\nPrevisão de renovações: Não\n11 - FUNDOS EU\nTêm fundos EU? Sim\n12 - DOCUMENTOS DE HABILITAÇÃO\nHabilitação para o exercício da atividade profissional: Não\n13 - CONDIÇÕES DE APRESENTAÇÃO\nPlataforma eletrónica utilizada pela entidade adjudicante: ACIN\nURL para Apresentação: https://www.acingov.pt\nAdmissibilidade da apresentação de propostas variantes: Não autorizado\nPrazo para apresentação das propostas: 29-01-2026 23:59\nPrazo durante o qual os concorrentes são obrigados a manter as respetivas propostas: 120 dias a contar do termo do prazo para a apresentação das propostas\nIndicação de Subcontratação na Proposta: Inexistência de indicação de subcontratação\n14 - PRESTAÇÃO DE CAUÇÃO\nPrestação de caução: Não\n15 - FORNECIMENTO DAS PEÇAS DO CONCURSO, APRESENTAÇÃO DE PEDIDOS DE PARTICIPAÇÃO E APRESENTAÇÃO DAS PROPOSTAS\nLink para acesso às peças do concurso (URL): https://www.acingov.pt/acingovprod/2/zonaPublica/zona_publica_c/donwloadProcedurePiece/MTAzNjE3MA==\n20 - OUTROS REQUISITOS\nInformação sobre contratos reservados. Aplica-se a contratos reservados (54º-A)? Não\n21 - CRITÉRIO DE ADJUDICAÇÃO\nMultifator: Sim\nFator: \nNome: Outros\nOutro Nome: Qualidade do Planeamento e Execução da Prestação de Serviços\nPonderação: 30%\nSubfatores: Não\nFator: \nNome: Outros\nOutro Nome: Adequação do Coordenador geral da Equipa de Trabalho\nPonderação: 10%\nSubfatores: Não\nFator: \nNome: Outros\nOutro Nome: Adequação do Coordenador Técnico na Vertente da Mobilidade\nPonderação: 10%\nSubfatores: Não\nFator: \nNome: Outros\nOutro Nome: Adequação do Especialista em Logística Urbana\nPonderação: 5%\nSubfatores: Não\nFator: \nNome: Outros\nOutro Nome: Adequação do Especialista em Participação Pública\nPonderação: 5%\nSubfatores: Não\nFator: \nNome: Preço\nPonderação: 40%\nSubfatores: Não\n24 - CONDIÇÕES DO CONTRATO\nFaturação Eletrónica: Permitido\nObrigação de Subcontratação:\nCódigo da Obrigação de Subcontratação: Não é aplicável nenhuma obrigação de subcontratação.\n25 - COMPRA PÚBLICA ESTRATÉGICA\nCompra Pública Estratégica: Inexistência de contratação pública estratégica\n26 - INFORMAÇÕES ADICIONAIS\nContrato adequado para PME: Não\nCobertura ACP (Acordo dos Contratos Públicos da Organização Mundial do Comércio): Não\n27 - IDENTIFICAÇÃO E CONTACTOS DO ÓRGÃO DE RECURSOS ADMINISTRATIVOS\nDesignação: Tribunal Administrativo e Fiscal de Loulé\nEndereço: Rua Dr.ª Laura Aires\nCódigo postal: 8100-851\nLocalidade: Loulé\nTelefone: 289400390\nFax: 000000000\nEndereço eletrónico: loule.taf@tribunais.org.pt\n28 - IDENTIFICAÇÃO DO(S) AUTOR(ES) DE ANÚNCIO\nNome: João Vinhas Reis\nCargo: Técnico Superior\n419947460",
    "nipc": "502971096",
    "distrito": "Faro",
    "concelho": "Faro",
    "freguesia": "União das Freguesias de Faro (Sé e São Pedro)",
    "site": "www.amal.pt",
    "email": "geral@amal.pt",
    "designacao_contrato": "CP n.º 10/2025 - Contratação de Prestação de Serviços: Adaptação do PMUS do Algarve, Geração 2.0",
    "descricao": "Contratação de Prestação de Serviços: Adaptação do PMUS do Algarve, Geração 2.0",
    "preco_base": "135.000,00 EUR",
    "prazo_execucao": "10 MESES",
    "prazo_apresentacao_propostas": "29-01-2026 23:59",
    "fundos_eu": "Sim",
    "plataforma_eletronica": "ACIN",
    "url_procedimento": "https://www.acingov.pt",
    "autor_nome": "João Vinhas Reis",
    "autor_cargo": "Técnico Superior"
  },
  {
    "numero_procedimento": "N/A",
    "entidade": "AnÃºncio de procedimento  n.Âº 382/2026  -  DiÃ¡rio da RepÃºblica n.Âº 6/2026, SÃ©rie II de 2026-01-09",
    "link": "https://diariodarepublica.pt/dr/detalhe/contrato-publico/382-1002139963"
  },
  {
    "numero_procedimento": "N/A",
    "entidade": "Infraestruturas de Portugal, SA",
    "link": "https://diariodarepublica.pt/dr/detalhe/contrato-publico/389-1002139968",
    "detalhes_completos": "1 - IDENTIFICAÇÃO E CONTACTOS DA ENTIDADE ADJUDICANTE\nDesignação da entidade adjudicante: Infraestruturas de Portugal, SA\nNIPC: 503933813\nServiço/Órgão/Pessoa de contacto: Direção de Compras e Logística - Departamento de Compras - Edifício 2\nEndereço: Praça da Portagem\nCódigo postal: 2809-013\nLocalidade: Almada\nPaís: Portugal\nNUT III: PT170\nDistrito: Setúbal\nConcelho: Almada\nFreguesia: União das Freguesias de Almada, Cova da Piedade, Pragal e Cacilhas\nTelefone:  212 879 300 \nFax: 21 287 90 00\nEndereço da Entidade (URL): www.infraestruturasdeportugal.pt\nEndereço Eletrónico: dcl@infraestruturasdeportugal.pt\nFunção da Organização: Adquirente\nNorma jurídica da Entidade Adjudicante: Organismo de direito público\nÁrea de atividade da Entidade Adjudicante: Serviços ferroviários\n2 - JORNAL OFICIAL DA UNIÃO EUROPEIA\nO procedimento a que este anúncio diz respeito também é publicitado no Jornal Oficial da União Europeia? Não\n3 - AVISO\nModelo de Anúncio: Concurso público\nData de Envio do Anúncio: 08-01-2026\n5 - PROCESSO\nTipo de Procedimento: Concurso público\nPreço base do procedimento: Sim\nValor do preço base do procedimento: 39.940,00 EUR\nProcedimento com lotes? Não\n6 - OBJETO DO CONTRATO\nNúmero de referência interna: 10021854\nDesignação do contrato: Aquisição de comando manual \nDescrição: Aquisição de comando manual \nTipo de Contrato Principal: Aquisição de Bens Móveis\nTipo de Contrato: Aquisição de Bens Móveis\nClassificação CPV (Vocabulário Comum para os Contratos Públicos)\nObjeto principal\nVocabulário Principal: 34946120\nPreço base s/IVA: 39.940,00 EUR\n7 - INDICAÇÕES ADICIONAIS\nO contrato envolve aquisição conjunta (satisfação de várias entidades)? Não\nO contrato é adjudicado por uma central de compras? Não\n8 - TÉCNICAS\nO concurso destina-se à celebração de um acordo-quadro? Inexistência de acordo-quadro\nÉ utilizado um leilão eletrónico? Não\nÉ adotada uma fase de negociação? Não\nSistema de Aquisição Dinâmico: Inexistência de sistema de aquisição dinâmico\n9 - LOCAL DA EXECUÇÃO DO CONTRATO\nLOCAL DA EXECUÇÃO DO CONTRATO (PROCEDIMENTO)\nPaís: Portugal\nNUT III: PT16I\nLocalidade: Entroncamento\nDistrito: Santarém\nConcelho: Entroncamento\nFreguesia: Freguesia de Nossa Senhora de Fátima - Entroncamento\n10 - PRAZO DE EXECUÇÃO DO CONTRATO\nPrazo de execução do contrato: 150 DIAS\nPrevisão de renovações: Não\n11 - FUNDOS EU\nTêm fundos EU? Não\n12 - DOCUMENTOS DE HABILITAÇÃO\nHabilitação para o exercício da atividade profissional: Não\n13 - CONDIÇÕES DE APRESENTAÇÃO\nPlataforma eletrónica utilizada pela entidade adjudicante: ANOGOV\nURL para Apresentação: https://www.anogov.com/infraestruturasdeportugal-ip/faces/\nAdmissibilidade da apresentação de propostas variantes: Não autorizado\nPrazo para apresentação das propostas: 12-02-2026 17:00\nPrazo durante o qual os concorrentes são obrigados a manter as respetivas propostas: 120 dias a contar do termo do prazo para a apresentação das propostas\nApresentação de Catálogo Eletrónico: Não autorizado\nIndicação de Subcontratação na Proposta: Inexistência de indicação de subcontratação\n14 - PRESTAÇÃO DE CAUÇÃO\nPrestação de caução: Não\n15 - FORNECIMENTO DAS PEÇAS DO CONCURSO, APRESENTAÇÃO DE PEDIDOS DE PARTICIPAÇÃO E APRESENTAÇÃO DAS PROPOSTAS\nLink para acesso às peças do concurso (URL): https://www.anogov.com/infraestruturasdeportugal-ip/faces/app/acessoDocs.jsp?codigoAcesso=zRttRGYPskoajpzNu3Y24n6P3IulM5V6yJz3dyvEWO2fxrJ7Bn\n20 - OUTROS REQUISITOS\nInformação sobre contratos reservados. Aplica-se a contratos reservados (54º-A)? Não\n21 - CRITÉRIO DE ADJUDICAÇÃO\nMultifator: Não\nMonofator:\nNome: Preço\n24 - CONDIÇÕES DO CONTRATO\nFaturação Eletrónica: Permitido\nObrigação de Subcontratação:\nCódigo da Obrigação de Subcontratação: Não é aplicável nenhuma obrigação de subcontratação.\n25 - COMPRA PÚBLICA ESTRATÉGICA\nCompra Pública Estratégica: Inexistência de contratação pública estratégica\n26 - INFORMAÇÕES ADICIONAIS\nContrato adequado para PME: Sim\nCobertura ACP (Acordo dos Contratos Públicos da Organização Mundial do Comércio): Não\n27 - IDENTIFICAÇÃO E CONTACTOS DO ÓRGÃO DE RECURSOS ADMINISTRATIVOS\nDesignação: Conselho de Administração Executivo da Infraestruturas de Portugal, S.A.\nEndereço: Praça da Portagem\nCódigo postal: 2809-013\nLocalidade: Almada\nTelefone: 212879000\nFax: \nEndereço eletrónico: contratos@infraestruturasdeportugal.pt\n28 - IDENTIFICAÇÃO DO(S) AUTOR(ES) DE ANÚNCIO\nNome: Margarida Veloso\nCargo: Diretora Adjunta da Direção de Compras e Logística\n419947488",
    "nipc": "503933813",
    "distrito": "Setúbal",
    "concelho": "Almada",
    "freguesia": "União das Freguesias de Almada, Cova da Piedade, Pragal e Cacilhas",
    "site": "www.infraestruturasdeportugal.pt",
    "email": "dcl@infraestruturasdeportugal.pt",
    "designacao_contrato": "Aquisição de comando manual",
    "descricao": "Aquisição de comando manual",
    "preco_base": "39.940,00 EUR",
    "prazo_execucao": "150 DIAS",
    "prazo_apresentacao_propostas": "12-02-2026 17:00",
    "fundos_eu": "Não",
    "plataforma_eletronica": "ANOGOV",
    "url_procedimento": "https://www.anogov.com/infraestruturasdeportugal-ip/faces/",
    "autor_nome": "Margarida Veloso",
    "autor_cargo": "Diretora Adjunta da Direção de Compras e Logística"
  },
  {
    "numero_procedimento": "N/A",
    "entidade": "Centro Formação Profissional Indústria de Cortiça",
    "link": "https://diariodarepublica.pt/dr/detalhe/contrato-publico/393-1002139970",
    "detalhes_completos": "1 - IDENTIFICAÇÃO E CONTACTOS DA ENTIDADE ADJUDICANTE\nDesignação da entidade adjudicante: Centro Formação Profissional Indústria de Cortiça\nNIPC: 900220538\nEndereço: Rua Alto do Picão n.º 415\nCódigo postal: 4535-393\nLocalidade: Santa Maria de Lamas\nPaís: Portugal\nNUT III: PT11A\nDistrito: Aveiro\nConcelho: Santa Maria da Feira\nFreguesia: Freguesia de Santa Maria de Lamas\nTelefone: 227471200\nFax: 227471209\nEndereço da Entidade (URL): http://www.cincork.com\nEndereço Eletrónico: geral@cincork.com\nFunção da Organização: Adquirente\nNorma jurídica da Entidade Adjudicante: Organismo de direito público\nÁrea de atividade da Autoridade Adjudicante: Educação\n2 - JORNAL OFICIAL DA UNIÃO EUROPEIA\nO procedimento a que este anúncio diz respeito também é publicitado no Jornal Oficial da União Europeia? Não\n3 - AVISO\nModelo de Anúncio: Concurso público\nData de Envio do Anúncio: 08-01-2026\n5 - PROCESSO\nTipo de Procedimento: Concurso público\nPreço base do procedimento: Sim\nValor do preço base do procedimento: 275.090,00 EUR\nProcedimento com lotes? Sim\nNº Máx. de Lotes Autorizado: 4\nNúmero máximo de lotes que podem ser adjudicados a um concorrente: 4\n6 - OBJETO DO CONTRATO\nNúmero de referência interna: CPBL2601\nDesignação do contrato: CPBL2601 - SISTEMA DE PRODUÇÃO DE BLOCOS E ROLHAS AGLOMERADAS DE CORTIÇA\nDescrição: CPBL2601 - SISTEMA DE PRODUÇÃO DE BLOCOS E ROLHAS AGLOMERADAS DE CORTIÇA\nTipo de Contrato Principal: Aquisição de Bens Móveis\nTipo de Contrato: Aquisição de Bens Móveis\nClassificação CPV (Vocabulário Comum para os Contratos Públicos)\nObjeto principal\nVocabulário Principal: 42642300\nPreço base s/IVA: 275.090,00 EUR\nLotes: \nNº: LOT-0001\nDescrição do Lote: Lote 1- Conjunto de aglomeração para rolhas e peças de cortiça e materiais aglomerados incluindo respetivos equipamentos de suporte\nPreço base s/IVA: 184.590,00 EUR\nClassificação CPV (Vocabulário Comum para os Contratos Públicos)\nObjeto principal\nVocabulário Principal: 42642300\nNº: LOT-0002\nDescrição do Lote: Lote 2 - Máquina Serra de Fita \nPreço base s/IVA: 11.000,00 EUR\nClassificação CPV (Vocabulário Comum para os Contratos Públicos)\nObjeto principal\nVocabulário Principal: 42642300\nNº: LOT-0003\nDescrição do Lote: Lote 3 - Máquina Laminadora de Cortiça \nPreço base s/IVA: 21.500,00 EUR\nClassificação CPV (Vocabulário Comum para os Contratos Públicos)\nObjeto principal\nVocabulário Principal: 42642300\nNº: LOT-0004\nDescrição do Lote: Lote 4 - Máquina Lixadora para Cortiça \nPreço base s/IVA: 58.000,00 EUR\nClassificação CPV (Vocabulário Comum para os Contratos Públicos)\nObjeto principal\nVocabulário Principal: 42642300\n7 - INDICAÇÕES ADICIONAIS\nO contrato envolve aquisição conjunta (satisfação de várias entidades)? Não\nO contrato é adjudicado por uma central de compras? Não\n8 - TÉCNICAS\nO concurso destina-se à celebração de um acordo-quadro? Inexistência de acordo-quadro\nÉ utilizado um leilão eletrónico? Não\nÉ adotada uma fase de negociação? Não\nSistema de Aquisição Dinâmico: Inexistência de sistema de aquisição dinâmico\n9 - LOCAL DA EXECUÇÃO DO CONTRATO\nLOCAL DA EXECUÇÃO DO CONTRATO (PROCEDIMENTO)\nLOCAL DA EXECUÇÃO DO CONTRATO (LOTE)\nIdentificador do Lote: LOT-0001\nPaís: Portugal\nNUT III: PT11A\nLocalidade: Santa Maria de Lamas\nDistrito: Aveiro\nConcelho: Santa Maria da Feira\nFreguesia: Freguesia de Santa Maria de Lamas\nIdentificador do Lote: LOT-0002\nPaís: Portugal\nNUT III: PT11A\nLocalidade: Santa Maria de Lamas\nDistrito: Aveiro\nConcelho: Santa Maria da Feira\nFreguesia: Freguesia de Santa Maria de Lamas\nIdentificador do Lote: LOT-0003\nPaís: Portugal\nNUT III: PT11A\nLocalidade: Santa Maria de Lamas\nDistrito: Aveiro\nConcelho: Santa Maria da Feira\nFreguesia: Freguesia de Santa Maria de Lamas\nIdentificador do Lote: LOT-0004\nPaís: Portugal\nNUT III: PT11A\nLocalidade: Santa Maria de Lamas\nDistrito: Aveiro\nConcelho: Santa Maria da Feira\nFreguesia: Freguesia de Santa Maria de Lamas\n10 - PRAZO DE EXECUÇÃO DO CONTRATO\nIdentificador do Lote: LOT-0001\nPrazo de execução do contrato: 50 DIAS\nPrevisão de renovações: Não\nIdentificador do Lote: LOT-0002\nPrazo de execução do contrato: 50 DIAS\nPrevisão de renovações: Não\nIdentificador do Lote: LOT-0003\nPrazo de execução do contrato: 50 DIAS\nPrevisão de renovações: Não\nIdentificador do Lote: LOT-0004\nPrazo de execução do contrato: 50 DIAS\nPrevisão de renovações: Não\n11 - FUNDOS EU\nIdentificador do Lote: LOT-0001; LOT-0002; LOT-0003; LOT-0004\nTêm fundos EU? Não\n12 - DOCUMENTOS DE HABILITAÇÃO\nHabilitação para o exercício da atividade profissional: Não\n13 - CONDIÇÕES DE APRESENTAÇÃO\nPlataforma eletrónica utilizada pela entidade adjudicante: COMPRASPT\nURL para Apresentação: https://www.compraspt.com/cpt-cincork/faces/\nAdmissibilidade da apresentação de propostas variantes: Não autorizado\nPrazo para apresentação das propostas: 20-01-2026 23:30\nPrazo durante o qual os concorrentes são obrigados a manter as respetivas propostas: 66 dias a contar do termo do prazo para a apresentação das propostas\nApresentação de Catálogo Eletrónico: Permitido\nIndicação de Subcontratação na Proposta: A parte do contrato que o proponente tenciona subcontratar\n14 - PRESTAÇÃO DE CAUÇÃO\nPrestação de caução: Não\n15 - FORNECIMENTO DAS PEÇAS DO CONCURSO, APRESENTAÇÃO DE PEDIDOS DE PARTICIPAÇÃO E APRESENTAÇÃO DAS PROPOSTAS\nLink para acesso às peças do concurso (URL): https://www.compraspt.com/cpt-cincork/faces/app/acessoDocs.jsp?codigoAcesso=6GzEhBi9JX1UvydDJ6itkdAs7Ld2lynTYSQAv95uG2mz6zEMDK\n20 - OUTROS REQUISITOS\nIdentificador do Lote: LOT-0001; LOT-0002; LOT-0003; LOT-0004\nInformação sobre contratos reservados. Aplica-se a contratos reservados (54º-A)? Não\n21 - CRITÉRIO DE ADJUDICAÇÃO\nO Critério de adjudicação é diferenciado por lote? Não\nMultifator: Sim\nFator: \nNome: Preço\nPonderação: 80%\nSubfatores: Não\nFator: \nNome: Outros\nOutro Nome: Prazo de entrega e instalação\nPonderação: 20%\nSubfatores: Não\n24 - CONDIÇÕES DO CONTRATO\nIdentificador do Lote: LOT-0001; LOT-0002; LOT-0003; LOT-0004\nFaturação Eletrónica: Permitido\nObrigação de Subcontratação:\nCódigo da Obrigação de Subcontratação: Não é aplicável nenhuma obrigação de subcontratação.\n25 - COMPRA PÚBLICA ESTRATÉGICA\nCompra Pública Estratégica: Inexistência de contratação pública estratégica\n26 - INFORMAÇÕES ADICIONAIS\nIdentificador do Lote: LOT-0001\nContrato adequado para PME: Sim\nCobertura ACP (Acordo dos Contratos Públicos da Organização Mundial do Comércio): Não\nIdentificador do Lote: LOT-0002\nContrato adequado para PME: Sim\nCobertura ACP (Acordo dos Contratos Públicos da Organização Mundial do Comércio): Não\nIdentificador do Lote: LOT-0003\nContrato adequado para PME: Sim\nCobertura ACP (Acordo dos Contratos Públicos da Organização Mundial do Comércio): Não\nIdentificador do Lote: LOT-0004\nContrato adequado para PME: Sim\nCobertura ACP (Acordo dos Contratos Públicos da Organização Mundial do Comércio): Não\n27 - IDENTIFICAÇÃO E CONTACTOS DO ÓRGÃO DE RECURSOS ADMINISTRATIVOS\nDesignação: Conselho de Administração\nEndereço: Rua Alto do Picão n.º 415\nCódigo postal: 4535-393\nLocalidade: Santa Maria de Lamas\nTelefone: 227471200\nFax: \nEndereço eletrónico: ca@cincork.com\nPrazo de interposição do recurso: 5 dias\n28 - IDENTIFICAÇÃO DO(S) AUTOR(ES) DE ANÚNCIO\nNome: Cristina Rodrigues\nCargo: Presidente do Conselho de Administração\n419947526",
    "nipc": "900220538",
    "distrito": "Aveiro",
    "concelho": "Santa Maria da Feira",
    "freguesia": "Freguesia de Santa Maria de Lamas",
    "site": "http://www.cincork.com",
    "email": "geral@cincork.com",
    "designacao_contrato": "CPBL2601 - SISTEMA DE PRODUÇÃO DE BLOCOS E ROLHAS AGLOMERADAS DE CORTIÇA",
    "descricao": "CPBL2601 - SISTEMA DE PRODUÇÃO DE BLOCOS E ROLHAS AGLOMERADAS DE CORTIÇA",
    "preco_base": "275.090,00 EUR",
    "prazo_execucao": "50 DIAS",
    "prazo_apresentacao_propostas": "20-01-2026 23:30",
    "fundos_eu": "Não",
    "plataforma_eletronica": "COMPRASPT",
    "url_procedimento": "https://www.compraspt.com/cpt-cincork/faces/",
    "autor_nome": "Cristina Rodrigues",
    "autor_cargo": "Presidente do Conselho de Administração"
  },
  {
    "numero_procedimento": "N/A",
    "entidade": "Cooptécnica - Gustave Eiffel, Cooperativa de Ensino e Formação Técnico Profissional, CRL",
    "link": "https://diariodarepublica.pt/dr/detalhe/contrato-publico/395-1002139971",
    "detalhes_completos": "1 - IDENTIFICAÇÃO E CONTACTOS DA ENTIDADE ADJUDICANTE\nDesignação da entidade adjudicante: Cooptécnica - Gustave Eiffel, Cooperativa de Ensino e Formação Técnico Profissional, CRL\nNIPC: 502327669\nEndereço: Rua Elias Garcia, nº 29, Amadora\nCódigo postal: 2700-312\nLocalidade: Lisboa\nPaís: Portugal\nNUT III: PT170\nDistrito: Lisboa\nConcelho: Amadora\nFreguesia: Freguesia de Falagueira-Venda Nova\nTelefone: 214996440\nFax: 214966449\nEndereço da Entidade (URL): www.cooptecnica.pt\nEndereço Eletrónico: contratacao.publica@gustaveeiffel.pt\neDelivery Gateway (URL): https://community.vortal.biz/public/\nFunção da Organização: Adquirente\nNorma jurídica da Entidade Adjudicante: Organismo de direito público\nÁrea de atividade da Autoridade Adjudicante: Educação\n2 - JORNAL OFICIAL DA UNIÃO EUROPEIA\nO procedimento a que este anúncio diz respeito também é publicitado no Jornal Oficial da União Europeia? Sim\n3 - AVISO\nModelo de Anúncio: Concurso público\nData de Envio do Anúncio: 07-01-2026\n5 - PROCESSO\nTipo de Procedimento: Concurso público\nPreço base do procedimento: Sim\nValor do preço base do procedimento: 219.884,59 EUR\nProcedimento com lotes? Sim\nNº Máx. de Lotes Autorizado: 8\nNúmero máximo de lotes que podem ser adjudicados a um concorrente: 8\n6 - OBJETO DO CONTRATO\nNúmero de referência interna: CPI 001 CCP 2026\nDesignação do contrato: Aquisição de Serviço de Implementação de Infraestrutura de Cablagem de Fibra Ótica e Cobre\nDescrição: Aquisição de Serviço de Implementação de Infraestrutura de Cablagem de Fibra Ótica e Cobre\nOpções: Não\nTipo de Contrato Principal: Aquisição de Bens Móveis\nTipo de Contrato: Aquisição de Bens Móveis; Locação de Bens Móveis\nClassificação CPV (Vocabulário Comum para os Contratos Públicos)\nObjeto principal\nVocabulário Principal: 32424000\nPreço base s/IVA: 219.884,59 EUR\nLotes: \nNº: LOT-0001\nDescrição do Lote: Lote 1 – Escola da Amadora Centro – Informática\nPreço base s/IVA: 28.747,74 EUR\nClassificação CPV (Vocabulário Comum para os Contratos Públicos)\nObjeto principal\nVocabulário Principal: 32424000\nNº: LOT-0002\nDescrição do Lote: Lote 2 – Escola da Amadora Sede – Digital\nPreço base s/IVA: 40.226,93 EUR\nClassificação CPV (Vocabulário Comum para os Contratos Públicos)\nObjeto principal\nVocabulário Principal: 32424000\nNº: LOT-0003\nDescrição do Lote: Lote 3 - Escola da Amadora Sede – Industrial\nPreço base s/IVA: 39.504,81 EUR\nClassificação CPV (Vocabulário Comum para os Contratos Públicos)\nObjeto principal\nVocabulário Principal: 32424000\nNº: LOT-0004\nDescrição do Lote: Lote 4 - Escola da Amadora Sede – Informática\nPreço base s/IVA: 17.066,18 EUR\nClassificação CPV (Vocabulário Comum para os Contratos Públicos)\nObjeto principal\nVocabulário Principal: 32424000\nNº: LOT-0005\nDescrição do Lote: Lote 5 - Escola do Entroncamento – Industrial\nPreço base s/IVA: 31.509,15 EUR\nClassificação CPV (Vocabulário Comum para os Contratos Públicos)\nObjeto principal\nVocabulário Principal: 32424000\nNº: LOT-0006\nDescrição do Lote: Lote 6 - Escola do Entroncamento – Energias Renováveis\nPreço base s/IVA: 17.328,48 EUR\nClassificação CPV (Vocabulário Comum para os Contratos Públicos)\nObjeto principal\nVocabulário Principal: 32424000\nNº: LOT-0007\nDescrição do Lote: Lote 7 - Escola do Lumiar – Industrial\nPreço base s/IVA: 26.173,38 EUR\nClassificação CPV (Vocabulário Comum para os Contratos Públicos)\nObjeto principal\nVocabulário Principal: 32424000\nNº: LOT-0008\nDescrição do Lote: Lote 8 - Escola do Lumiar – Energias Renováveis\nPreço base s/IVA: 19.327,92 EUR\nClassificação CPV (Vocabulário Comum para os Contratos Públicos)\nObjeto principal\nVocabulário Principal: 32424000\n7 - INDICAÇÕES ADICIONAIS\nO contrato envolve aquisição conjunta (satisfação de várias entidades)? Não\nO contrato é adjudicado por uma central de compras? Não\n8 - TÉCNICAS\nO concurso destina-se à celebração de um acordo-quadro? Inexistência de acordo-quadro\nÉ utilizado um leilão eletrónico? Não\nÉ adotada uma fase de negociação? Não\nSistema de Aquisição Dinâmico: Inexistência de sistema de aquisição dinâmico\n9 - LOCAL DA EXECUÇÃO DO CONTRATO\nLOCAL DA EXECUÇÃO DO CONTRATO (PROCEDIMENTO)\nPaís: Portugal\nNUT III: PT170\nLocalidade: Lisboa\nDistrito: Lisboa\nConcelho: Amadora\nFreguesia: Todas\nLOCAL DA EXECUÇÃO DO CONTRATO (LOTE)\nIdentificador do Lote: LOT-0001; LOT-0002; LOT-0003; LOT-0004; LOT-0005; LOT-0006; LOT-0007; LOT-0008\nPaís: Portugal\nNUT III: PT170\nLocalidade: Lisboa\nDistrito: Lisboa\nConcelho: Amadora\nFreguesia: Todas\nIdentificador do Lote: LOT-0001; LOT-0002; LOT-0003; LOT-0004; LOT-0005; LOT-0006; LOT-0007; LOT-0008\nPaís: Portugal\nNUT III: PT170\nLocalidade: Lisboa\nDistrito: Lisboa\nConcelho: Lisboa\nFreguesia: Freguesia de Lumiar\nIdentificador do Lote: LOT-0001; LOT-0002; LOT-0003; LOT-0004; LOT-0005; LOT-0006; LOT-0007; LOT-0008\nPaís: Portugal\nNUT III: PT16I\nLocalidade: Santarém\nDistrito: Santarém\nConcelho: Entroncamento\nFreguesia: Todas\nIdentificador do Lote: LOT-0001; LOT-0002; LOT-0003; LOT-0004; LOT-0005; LOT-0006; LOT-0007; LOT-0008\nPaís: Portugal\nNUT III: PT170\nLocalidade: Lisboa\nDistrito: Lisboa\nConcelho: Amadora\nFreguesia: Todas\n10 - PRAZO DE EXECUÇÃO DO CONTRATO\nIdentificador do Lote: LOT-0001; LOT-0002; LOT-0003; LOT-0004; LOT-0005; LOT-0006; LOT-0007; LOT-0008\nPrazo de execução do contrato: 15 DIAS\nPrevisão de renovações: Não\n11 - FUNDOS EU\nIdentificador do Lote: LOT-0001; LOT-0002; LOT-0003; LOT-0004; LOT-0005; LOT-0006; LOT-0007; LOT-0008\nTêm fundos EU? Sim\n12 - DOCUMENTOS DE HABILITAÇÃO\nHabilitação para o exercício da atividade profissional: Não\n13 - CONDIÇÕES DE APRESENTAÇÃO\nPlataforma eletrónica utilizada pela entidade adjudicante: VORTAL\nURL para Apresentação: https://community.vortal.biz/public/\nAdmissibilidade da apresentação de propostas variantes: Não autorizado\nPrazo para apresentação das propostas: 20-01-2026 23:59\nPrazo durante o qual os concorrentes são obrigados a manter as respetivas propostas: 10 dias a contar do termo do prazo para a apresentação das propostas\nApresentação de Catálogo Eletrónico: Não autorizado\nIndicação de Subcontratação na Proposta: Inexistência de indicação de subcontratação\n14 - PRESTAÇÃO DE CAUÇÃO\nPrestação de caução: Sim\nPercentagem: 5%\nDescrição da Garantia Exigida: O adjudicatário deve prestar a caução devida no prazo de 10 (dez) dias úteis a contar da notificação da decisão de adjudicação, no valor de 5% do preço contratual, em benefício da Cooptécnica Gustave Eiffel, devendo comprovar essa prestação no dia imediatamente subsequente.\n15 - FORNECIMENTO DAS PEÇAS DO CONCURSO, APRESENTAÇÃO DE PEDIDOS DE PARTICIPAÇÃO E APRESENTAÇÃO DAS PROPOSTAS\nLink para acesso às peças do concurso (URL): https://community.vortal.biz/Public/public-tender-documents/U2xyRTNnM01SdkNsaGlFWHRPVXhXTnJNZWNLUGVhK0FpR0J5WDlvMlRTdkJmS2VJOTNmVlVhOU5wd1JXRGpmZTg3eGZybHdxUWw0OGYxM2hEUlc1dHc9PXZLTlpz\n20 - OUTROS REQUISITOS\nIdentificador do Lote: LOT-0001; LOT-0002; LOT-0003; LOT-0004; LOT-0005; LOT-0006; LOT-0007; LOT-0008\nInformação sobre contratos reservados. Aplica-se a contratos reservados (54º-A)? Não\n21 - CRITÉRIO DE ADJUDICAÇÃO\nO Critério de adjudicação é diferenciado por lote? Não\nMultifator: Não\nMonofator:\nNome: Outros\nOutro nome: Preço\n24 - CONDIÇÕES DO CONTRATO\nIdentificador do Lote: LOT-0001; LOT-0002; LOT-0003; LOT-0004; LOT-0005; LOT-0006; LOT-0007; LOT-0008\nFaturação Eletrónica: Permitido\nObrigação de Subcontratação:\nCódigo da Obrigação de Subcontratação: Não é aplicável nenhuma obrigação de subcontratação.\n25 - COMPRA PÚBLICA ESTRATÉGICA\nCompra Pública Estratégica: Inexistência de contratação pública estratégica\n26 - INFORMAÇÕES ADICIONAIS\nIdentificador do Lote: LOT-0001; LOT-0002; LOT-0003; LOT-0004; LOT-0005; LOT-0006; LOT-0007; LOT-0008\nContrato adequado para PME: Sim\nCobertura ACP (Acordo dos Contratos Públicos da Organização Mundial do Comércio): Não\n27 - IDENTIFICAÇÃO E CONTACTOS DO ÓRGÃO DE RECURSOS ADMINISTRATIVOS\nDesignação: Susana Fernandes\nEndereço: RUA ELIAS GARCIA Nº 29 - VENDA NOVA\nCódigo postal: 2700-312\nLocalidade: Amadora\nTelefone: +351 912355271\nFax: +351 214996449\nEndereço eletrónico: contratacaopublica@gustaveeiffel.pt\n28 - IDENTIFICAÇÃO DO(S) AUTOR(ES) DE ANÚNCIO\nNome: Susana Fernandes\nCargo: Técnico \n419947073",
    "nipc": "502327669",
    "distrito": "Lisboa",
    "concelho": "Amadora",
    "freguesia": "Freguesia de Falagueira-Venda Nova",
    "site": "www.cooptecnica.pt",
    "email": "contratacao.publica@gustaveeiffel.pt",
    "designacao_contrato": "Aquisição de Serviço de Implementação de Infraestrutura de Cablagem de Fibra Ótica e Cobre",
    "descricao": "Aquisição de Serviço de Implementação de Infraestrutura de Cablagem de Fibra Ótica e Cobre",
    "preco_base": "219.884,59 EUR",
    "prazo_execucao": "15 DIAS",
    "prazo_apresentacao_propostas": "20-01-2026 23:59",
    "fundos_eu": "Sim",
    "plataforma_eletronica": "VORTAL",
    "url_procedimento": "https://community.vortal.biz/public/",
    "autor_nome": "Susana Fernandes",
    "autor_cargo": "Técnico"
  },
  {
    "numero_procedimento": "N/A",
    "entidade": "Unidade Local de Saúde do Alto Ave, EPE",
    "link": "https://diariodarepublica.pt/dr/detalhe/contrato-publico/397-1002139972",
    "detalhes_completos": "1 - IDENTIFICAÇÃO E CONTACTOS DA ENTIDADE ADJUDICANTE\nDesignação da entidade adjudicante: Unidade Local de Saúde do Alto Ave, EPE\nNIPC: 508080827\nEndereço: Rua dos Cutileiros, Creixomil\nCódigo postal: 4835-044\nLocalidade: Guimarães\nPaís: Portugal\nNUT III: PT119\nDistrito: Braga\nConcelho: Guimarães\nFreguesia: Todas\nTelefone: 253540330\nFax: 253513592\nEndereço da Entidade (URL): http://www.hospitaldeguimaraes.min-saude.pt/\nEndereço Eletrónico: aprovisionamento@hospitaldeguimaraes.min-saude.pt\neDelivery Gateway (URL): https://community.vortal.biz/public/\nFunção da Organização: Adquirente\nNorma jurídica da Entidade Adjudicante: Organismo de direito público\nÁrea de atividade da Autoridade Adjudicante: Saúde\n2 - JORNAL OFICIAL DA UNIÃO EUROPEIA\nO procedimento a que este anúncio diz respeito também é publicitado no Jornal Oficial da União Europeia? Sim\n3 - AVISO\nModelo de Anúncio: Concurso público\nData de Envio do Anúncio: 07-01-2026\n5 - PROCESSO\nTipo de Procedimento: Concurso público\nPreço base do procedimento: Sim\nValor do preço base do procedimento: 714.100,00 EUR\nProcedimento com lotes? Sim\nNº Máx. de Lotes Autorizado: 17\nNúmero máximo de lotes que podem ser adjudicados a um concorrente: 17\n6 - OBJETO DO CONTRATO\nNúmero de referência interna: CP/0014/2026 \nDesignação do contrato: Material de eletrofisiologia de Ablação para taquicardia ventricular e supra-ventricular\nDescrição: \"Material de eletrofisiologia de Ablação para taquicardia ventricular e supra-ventricular\nOpções: Não\nTipo de Contrato Principal: Aquisição de Bens Móveis\nTipo de Contrato: Aquisição de Bens Móveis\nClassificação CPV (Vocabulário Comum para os Contratos Públicos)\nObjeto principal\nVocabulário Principal: 33182000\nPreço base s/IVA: 714.100,00 EUR\nLotes: \nNº: LOT-0001\nDescrição do Lote: 1\nPreço base s/IVA: 74.000,00 EUR\nClassificação CPV (Vocabulário Comum para os Contratos Públicos)\nObjeto principal\nVocabulário Principal: 33182000\nNº: LOT-0002\nDescrição do Lote: 2\nPreço base s/IVA: 14.400,00 EUR\nClassificação CPV (Vocabulário Comum para os Contratos Públicos)\nObjeto principal\nVocabulário Principal: 33182000\nNº: LOT-0003\nDescrição do Lote: 3\nPreço base s/IVA: 31.250,00 EUR\nClassificação CPV (Vocabulário Comum para os Contratos Públicos)\nObjeto principal\nVocabulário Principal: 33182000\nNº: LOT-0004\nDescrição do Lote: 4\nPreço base s/IVA: 21.250,00 EUR\nClassificação CPV (Vocabulário Comum para os Contratos Públicos)\nObjeto principal\nVocabulário Principal: 33182000\nNº: LOT-0005\nDescrição do Lote: 5\nPreço base s/IVA: 117.750,00 EUR\nClassificação CPV (Vocabulário Comum para os Contratos Públicos)\nObjeto principal\nVocabulário Principal: 33182000\nNº: LOT-0006\nDescrição do Lote: 6\nPreço base s/IVA: 41.250,00 EUR\nClassificação CPV (Vocabulário Comum para os Contratos Públicos)\nObjeto principal\nVocabulário Principal: 33182000\nNº: LOT-0007\nDescrição do Lote: 7\nPreço base s/IVA: 59.000,00 EUR\nClassificação CPV (Vocabulário Comum para os Contratos Públicos)\nObjeto principal\nVocabulário Principal: 33182000\nNº: LOT-0008\nDescrição do Lote: 8\nPreço base s/IVA: 26.250,00 EUR\nClassificação CPV (Vocabulário Comum para os Contratos Públicos)\nObjeto principal\nVocabulário Principal: 33182000\nNº: LOT-0009\nDescrição do Lote: 9\nPreço base s/IVA: 59.000,00 EUR\nClassificação CPV (Vocabulário Comum para os Contratos Públicos)\nObjeto principal\nVocabulário Principal: 33182000\nNº: LOT-0010\nDescrição do Lote: 10\nPreço base s/IVA: 25.650,00 EUR\nClassificação CPV (Vocabulário Comum para os Contratos Públicos)\nObjeto principal\nVocabulário Principal: 33182000\nNº: LOT-0011\nDescrição do Lote: 11\nPreço base s/IVA: 60.250,00 EUR\nClassificação CPV (Vocabulário Comum para os Contratos Públicos)\nObjeto principal\nVocabulário Principal: 33182000\nNº: LOT-0012\nDescrição do Lote: 12\nPreço base s/IVA: 26.050,00 EUR\nClassificação CPV (Vocabulário Comum para os Contratos Públicos)\nObjeto principal\nVocabulário Principal: 33182000\nNº: LOT-0013\nDescrição do Lote: 13\nPreço base s/IVA: 78.600,00 EUR\nClassificação CPV (Vocabulário Comum para os Contratos Públicos)\nObjeto principal\nVocabulário Principal: 33182000\nNº: LOT-0014\nDescrição do Lote: 14\nPreço base s/IVA: 23.450,00 EUR\nClassificação CPV (Vocabulário Comum para os Contratos Públicos)\nObjeto principal\nVocabulário Principal: 33182000\nNº: LOT-0015\nDescrição do Lote: 15\nPreço base s/IVA: 9.250,00 EUR\nClassificação CPV (Vocabulário Comum para os Contratos Públicos)\nObjeto principal\nVocabulário Principal: 33182000\nNº: LOT-0016\nDescrição do Lote: 16\nPreço base s/IVA: 16.950,00 EUR\nClassificação CPV (Vocabulário Comum para os Contratos Públicos)\nObjeto principal\nVocabulário Principal: 33182000\nNº: LOT-0017\nDescrição do Lote: 17\nPreço base s/IVA: 29.750,00 EUR\nClassificação CPV (Vocabulário Comum para os Contratos Públicos)\nObjeto principal\nVocabulário Principal: 33182000\n7 - INDICAÇÕES ADICIONAIS\nO contrato envolve aquisição conjunta (satisfação de várias entidades)? Não\nO contrato é adjudicado por uma central de compras? Não\n8 - TÉCNICAS\nO concurso destina-se à celebração de um acordo-quadro? Inexistência de acordo-quadro\nÉ utilizado um leilão eletrónico? Não\nÉ adotada uma fase de negociação? Não\nSistema de Aquisição Dinâmico: Inexistência de sistema de aquisição dinâmico\n9 - LOCAL DA EXECUÇÃO DO CONTRATO\nLOCAL DA EXECUÇÃO DO CONTRATO (PROCEDIMENTO)\nPaís: Portugal\nNUT III: PT119\nLocalidade: Braga\nDistrito: Braga\nConcelho: Guimarães\nFreguesia: Freguesia de Creixomil - Guimarães\nLOCAL DA EXECUÇÃO DO CONTRATO (LOTE)\nIdentificador do Lote: LOT-0001; LOT-0002; LOT-0003; LOT-0004; LOT-0005; LOT-0006; LOT-0007; LOT-0008; LOT-0009; LOT-0010; LOT-0011; LOT-0012; LOT-0013; LOT-0014; LOT-0015; LOT-0016; LOT-0017\nPaís: Portugal\nNUT III: PT119\nLocalidade: Braga\nDistrito: Braga\nConcelho: Guimarães\nFreguesia: Freguesia de Creixomil - Guimarães\n10 - PRAZO DE EXECUÇÃO DO CONTRATO\nIdentificador do Lote: LOT-0001; LOT-0002; LOT-0003; LOT-0004; LOT-0005; LOT-0006; LOT-0007; LOT-0008; LOT-0009; LOT-0010; LOT-0011; LOT-0012; LOT-0013; LOT-0014; LOT-0015; LOT-0016; LOT-0017\nPrazo de execução do contrato: 12 MESES\nPrevisão de renovações: Não\n11 - FUNDOS EU\nIdentificador do Lote: LOT-0001; LOT-0002; LOT-0003; LOT-0004; LOT-0005; LOT-0006; LOT-0007; LOT-0008; LOT-0009; LOT-0010; LOT-0011; LOT-0012; LOT-0013; LOT-0014; LOT-0015; LOT-0016; LOT-0017\nTêm fundos EU? Não\n12 - DOCUMENTOS DE HABILITAÇÃO\nHabilitação para o exercício da atividade profissional: Não\n13 - CONDIÇÕES DE APRESENTAÇÃO\nPlataforma eletrónica utilizada pela entidade adjudicante: VORTAL\nURL para Apresentação: https://community.vortal.biz/public/\nAdmissibilidade da apresentação de propostas variantes: Não autorizado\nPrazo para apresentação das propostas: 05-02-2026 17:00\nPrazo durante o qual os concorrentes são obrigados a manter as respetivas propostas: 180 dias a contar do termo do prazo para a apresentação das propostas\nApresentação de Catálogo Eletrónico: Permitido\nIndicação de Subcontratação na Proposta: Inexistência de indicação de subcontratação\n14 - PRESTAÇÃO DE CAUÇÃO\nPrestação de caução: Não\n15 - FORNECIMENTO DAS PEÇAS DO CONCURSO, APRESENTAÇÃO DE PEDIDOS DE PARTICIPAÇÃO E APRESENTAÇÃO DAS PROPOSTAS\nLink para acesso às peças do concurso (URL): https://community.vortal.biz/Public/public-tender-documents/RENFcG5Ra0hrTm1sNTRFUEp4T3FRQXNnLytXdWVYT0YyU3Z5WmJIV09iUVVPZENRSWZlN0RuVmkvTWZOL3BoT1pFdEk4dmZvUG9xeXZlNUJEcW5xU0E9PWE3ekkj\n20 - OUTROS REQUISITOS\nIdentificador do Lote: LOT-0001; LOT-0002; LOT-0003; LOT-0004; LOT-0005; LOT-0006; LOT-0007; LOT-0008; LOT-0009; LOT-0010; LOT-0011; LOT-0012; LOT-0013; LOT-0014; LOT-0015; LOT-0016; LOT-0017\nInformação sobre contratos reservados. Aplica-se a contratos reservados (54º-A)? Não\n21 - CRITÉRIO DE ADJUDICAÇÃO\nO Critério de adjudicação é diferenciado por lote? Não\nMultifator: Sim\nFator: \nNome: Preço\nPonderação: 50%\nSubfatores: Não\nFator: \nNome: Qualidade\nPonderação: 50%\nSubfatores: Não\n24 - CONDIÇÕES DO CONTRATO\nIdentificador do Lote: LOT-0001; LOT-0002; LOT-0003; LOT-0004; LOT-0005; LOT-0006; LOT-0007; LOT-0008; LOT-0009; LOT-0010; LOT-0011; LOT-0012; LOT-0013; LOT-0014; LOT-0015; LOT-0016; LOT-0017\nFaturação Eletrónica: Permitido\nObrigação de Subcontratação:\nCódigo da Obrigação de Subcontratação: Não é aplicável nenhuma obrigação de subcontratação.\n25 - COMPRA PÚBLICA ESTRATÉGICA\nCompra Pública Estratégica: Inexistência de contratação pública estratégica\n26 - INFORMAÇÕES ADICIONAIS\nIdentificador do Lote: LOT-0001; LOT-0002; LOT-0003; LOT-0004; LOT-0005; LOT-0006; LOT-0007; LOT-0008; LOT-0009; LOT-0010; LOT-0011; LOT-0012; LOT-0013; LOT-0014; LOT-0015; LOT-0016; LOT-0017\nContrato adequado para PME: Sim\nCobertura ACP (Acordo dos Contratos Públicos da Organização Mundial do Comércio): Não\n27 - IDENTIFICAÇÃO E CONTACTOS DO ÓRGÃO DE RECURSOS ADMINISTRATIVOS\nDesignação: ULSAAVE\nEndereço: Rua dos Cutileiros,\nCódigo postal: 4835-044\nLocalidade: Guimarães\nTelefone: +351 253540330\nFax: +351 253540330\nEndereço eletrónico: compras@ulsaave.min-saude.pt\n28 - IDENTIFICAÇÃO DO(S) AUTOR(ES) DE ANÚNCIO\nNome: Arlindo Soares\nCargo: Diretor do SCL\n419947188",
    "nipc": "508080827",
    "distrito": "Braga",
    "concelho": "Guimarães",
    "freguesia": "Todas",
    "site": "http://www.hospitaldeguimaraes.min-saude.pt/",
    "email": "aprovisionamento@hospitaldeguimaraes.min-saude.pt",
    "designacao_contrato": "Material de eletrofisiologia de Ablação para taquicardia ventricular e supra-ventricular",
    "descricao": "\"Material de eletrofisiologia de Ablação para taquicardia ventricular e supra-ventricular",
    "preco_base": "714.100,00 EUR",
    "prazo_execucao": "12 MESES",
    "prazo_apresentacao_propostas": "05-02-2026 17:00",
    "fundos_eu": "Não",
    "plataforma_eletronica": "VORTAL",
    "url_procedimento": "https://community.vortal.biz/public/",
    "autor_nome": "Arlindo Soares",
    "autor_cargo": "Diretor do SCL"
  },
  {
    "numero_procedimento": "N/A",
    "entidade": "EPAL - Empresa Portuguesa das Águas Livres, SA",
    "link": "https://diariodarepublica.pt/dr/detalhe/contrato-publico/399-1002139973",
    "detalhes_completos": "1 - IDENTIFICAÇÃO E CONTACTOS DA ENTIDADE ADJUDICANTE\nDesignação da entidade adjudicante: EPAL - Empresa Portuguesa das Águas Livres, SA\nNIPC: 500906840\nServiço/Órgão/Pessoa de contacto: Direção de Compras e Logística\nEndereço: Avenida da Liberdade, 24\nCódigo postal: 1250-144\nLocalidade: Lisboa\nPaís: Portugal\nNUT III: PT170\nDistrito: Lisboa\nConcelho: Lisboa\nFreguesia: Freguesia de Santo António - Lisboa\nTelefone: 213251000\nFax: 213251397\nEndereço da Entidade (URL): https://www.epal.pt/EPAL/\nEndereço Eletrónico: logistica.epal@adp.pt\neDelivery Gateway (URL): https://www.acingov.pt\nFunção da Organização: Adquirente\nNorma jurídica da Entidade Adjudicante: Empresa pública\nÁrea de atividade da Autoridade Adjudicante: Proteção ambiental\n2 - JORNAL OFICIAL DA UNIÃO EUROPEIA\nO procedimento a que este anúncio diz respeito também é publicitado no Jornal Oficial da União Europeia? Sim\n3 - AVISO\nModelo de Anúncio: Concurso público\nData de Envio do Anúncio: 07-01-2026\n5 - PROCESSO\nTipo de Procedimento: Concurso público\nPreço base do procedimento: Sim\nValor do preço base do procedimento: 360.000,00 EUR\nProcedimento com lotes? Não\n6 - OBJETO DO CONTRATO\nNúmero de referência interna: MA/4326/2025\nDesignação do contrato: Aquisição de serviços Cloud\nDescrição: Aquisição de serviços Cloud\nOpções: Não\nTipo de Contrato Principal: Aquisição de Serviços\nTipo de Contrato: Aquisição de Serviços\nClassificação CPV (Vocabulário Comum para os Contratos Públicos)\nObjeto principal\nVocabulário Principal: 72310000\nPreço base s/IVA: 360.000,00 EUR\n7 - INDICAÇÕES ADICIONAIS\nO contrato envolve aquisição conjunta (satisfação de várias entidades)? Não\nO contrato é adjudicado por uma central de compras? Não\n8 - TÉCNICAS\nO concurso destina-se à celebração de um acordo-quadro? Inexistência de acordo-quadro\nÉ utilizado um leilão eletrónico? Não\nÉ adotada uma fase de negociação? Não\nSistema de Aquisição Dinâmico: Inexistência de sistema de aquisição dinâmico\n9 - LOCAL DA EXECUÇÃO DO CONTRATO\nLOCAL DA EXECUÇÃO DO CONTRATO (PROCEDIMENTO)\nPaís: Portugal\nNUT III: PT170\nLocalidade: Freguesia de Santo António - Lisboa\nDistrito: Lisboa\nConcelho: Lisboa\nFreguesia: Freguesia de Santo António - Lisboa\n10 - PRAZO DE EXECUÇÃO DO CONTRATO\nPrazo de execução do contrato: 30 MESES\nPrevisão de renovações: Não\n11 - FUNDOS EU\nTêm fundos EU? Não\n12 - DOCUMENTOS DE HABILITAÇÃO\nHabilitação para o exercício da atividade profissional: Não\n13 - CONDIÇÕES DE APRESENTAÇÃO\nPlataforma eletrónica utilizada pela entidade adjudicante: ACIN\nURL para Apresentação: https://www.acingov.pt\nAdmissibilidade da apresentação de propostas variantes: Não autorizado\nPrazo para apresentação das propostas: 09-02-2026 19:00\nPrazo durante o qual os concorrentes são obrigados a manter as respetivas propostas: 150 dias a contar do termo do prazo para a apresentação das propostas\nApresentação de Catálogo Eletrónico: Permitido\nIndicação de Subcontratação na Proposta: A parte do contrato que o proponente tenciona subcontratar\n14 - PRESTAÇÃO DE CAUÇÃO\nPrestação de caução: Não\n15 - FORNECIMENTO DAS PEÇAS DO CONCURSO, APRESENTAÇÃO DE PEDIDOS DE PARTICIPAÇÃO E APRESENTAÇÃO DAS PROPOSTAS\nLink para acesso às peças do concurso (URL): https://www.acingov.pt/acingovprod/2/zonaPublica/zona_publica_c/donwloadProcedurePiece/MTAzNjE1Ng==\n20 - OUTROS REQUISITOS\nInformação sobre contratos reservados. Aplica-se a contratos reservados (54º-A)? Não\n21 - CRITÉRIO DE ADJUDICAÇÃO\nMultifator: Não\nMonofator:\nNome: Preço\n24 - CONDIÇÕES DO CONTRATO\nFaturação Eletrónica: Necessário\nObrigação de Subcontratação:\nCódigo da Obrigação de Subcontratação: Não é aplicável nenhuma obrigação de subcontratação.\n25 - COMPRA PÚBLICA ESTRATÉGICA\nCompra Pública Estratégica: Inexistência de contratação pública estratégica\n26 - INFORMAÇÕES ADICIONAIS\nContrato adequado para PME: Não\nCobertura ACP (Acordo dos Contratos Públicos da Organização Mundial do Comércio): Não\n27 - IDENTIFICAÇÃO E CONTACTOS DO ÓRGÃO DE RECURSOS ADMINISTRATIVOS\nDesignação: Conselho de Administração da EPAL\nEndereço: Avenida da Liberdade, 24\nCódigo postal: 1250-144\nLocalidade: Lisboa\nTelefone: 213251000\nFax: \nEndereço eletrónico: geral.epal@adp.pt\nPrazo de interposição do recurso: 5 dias\n28 - IDENTIFICAÇÃO DO(S) AUTOR(ES) DE ANÚNCIO\nNome: José Manuel Sardinha\nCargo: Presidente do Conselho de Administração\n419947257",
    "nipc": "500906840",
    "distrito": "Lisboa",
    "concelho": "Lisboa",
    "freguesia": "Freguesia de Santo António - Lisboa",
    "site": "https://www.epal.pt/EPAL/",
    "email": "logistica.epal@adp.pt",
    "designacao_contrato": "Aquisição de serviços Cloud",
    "descricao": "Aquisição de serviços Cloud",
    "preco_base": "360.000,00 EUR",
    "prazo_execucao": "30 MESES",
    "prazo_apresentacao_propostas": "09-02-2026 19:00",
    "fundos_eu": "Não",
    "plataforma_eletronica": "ACIN",
    "url_procedimento": "https://www.acingov.pt",
    "autor_nome": "José Manuel Sardinha",
    "autor_cargo": "Presidente do Conselho de Administração"
  },
  {
    "numero_procedimento": "N/A",
    "entidade": "Município de Évora",
    "link": "https://diariodarepublica.pt/dr/detalhe/contrato-publico/401-1002139974",
    "detalhes_completos": "1 - IDENTIFICAÇÃO E CONTACTOS DA ENTIDADE ADJUDICANTE\nDesignação da entidade adjudicante: Município de Évora\nNIPC: 504828576\nEndereço: Pç.  Sertório, Nr. 1\nCódigo postal: 7004-506\nLocalidade: Évora\nPaís: Portugal\nNUT III: PT187\nDistrito: Évora\nConcelho: Évora\nFreguesia: Todas\nTelefone: 266777000\nFax: 266702950\nEndereço da Entidade (URL): https://www.cm-evora.pt/\nEndereço Eletrónico: cmevora@cm-evora.pt\neDelivery Gateway (URL): https://community.vortal.biz/public/\nFunção da Organização: Adquirente\nNorma jurídica da Entidade Adjudicante: Organismo de direito público\nÁrea de atividade da Autoridade Adjudicante: Serviços públicos das administrações públicas\n2 - JORNAL OFICIAL DA UNIÃO EUROPEIA\nO procedimento a que este anúncio diz respeito também é publicitado no Jornal Oficial da União Europeia? Sim\n3 - AVISO\nModelo de Anúncio: Concurso público\nData de Envio do Anúncio: 07-01-2026\n5 - PROCESSO\nTipo de Procedimento: Concurso público\nPreço base do procedimento: Sim\nValor do preço base do procedimento: 303.135,00 EUR\nProcedimento com lotes? Não\n6 - OBJETO DO CONTRATO\nNúmero de referência interna: 218/2025_CPI_BAIRRO_COMERCIAL_DIGITAL_PRR_PRO_5375\nDesignação do contrato: CONTRATAÇÃO DE SERVIÇOS E FORNECIMENTO DA COMPONENTE DE COMUNICAÇÃO DO \"BAIRRO COMERCIAL DIGITAL DE ÉVORA\" PRR – PROJETO BAIRROS COMERCIAIS DIGITAIS - PROJETO Nº 5375.\nDescrição: CONCURSO PÚBLICO INTERNACIONAL NOS TERMOS DA ALÍNEA A) DO N°1 DO ART'.20º DO CCP PARA CONTRATAÇÃO DE SERVIÇOS E FORNECIMENTO DA COMPONENTE DE COMUNICAÇÃO DO \"BAIRRO COMERCIAL DIGITAL DE ÉVORA\" PRR – PROJETO BAIRROS COMERCIAIS DIGITAIS - PROJETO Nº 5375.\nOpções: Não\nTipo de Contrato Principal: Aquisição de Serviços\nTipo de Contrato: Aquisição de Serviços\nClassificação CPV (Vocabulário Comum para os Contratos Públicos)\nObjeto principal\nVocabulário Principal: 72400000\nPreço base s/IVA: 303.135,00 EUR\n7 - INDICAÇÕES ADICIONAIS\nO contrato envolve aquisição conjunta (satisfação de várias entidades)? Não\nO contrato é adjudicado por uma central de compras? Não\n8 - TÉCNICAS\nO concurso destina-se à celebração de um acordo-quadro? Inexistência de acordo-quadro\nÉ utilizado um leilão eletrónico? Não\nÉ adotada uma fase de negociação? Não\nSistema de Aquisição Dinâmico: Inexistência de sistema de aquisição dinâmico\n9 - LOCAL DA EXECUÇÃO DO CONTRATO\nLOCAL DA EXECUÇÃO DO CONTRATO (PROCEDIMENTO)\nPaís: Portugal\nNUT III: PT187\nLocalidade: Évora\nDistrito: Évora\nConcelho: Évora\nFreguesia: União das Freguesias de Évora (São Mamede, Sé, São Pedro e Santo Antão)\n10 - PRAZO DE EXECUÇÃO DO CONTRATO\nPrazo de execução do contrato: 80 DIAS\nPrevisão de renovações: Não\n11 - FUNDOS EU\nTêm fundos EU? Sim\n12 - DOCUMENTOS DE HABILITAÇÃO\nHabilitação para o exercício da atividade profissional: Não\n13 - CONDIÇÕES DE APRESENTAÇÃO\nPlataforma eletrónica utilizada pela entidade adjudicante: VORTAL\nURL para Apresentação: https://community.vortal.biz/public/\nAdmissibilidade da apresentação de propostas variantes: Não autorizado\nPrazo para apresentação das propostas: 22-01-2026 23:59\nPrazo durante o qual os concorrentes são obrigados a manter as respetivas propostas: 66 dias a contar do termo do prazo para a apresentação das propostas\nApresentação de Catálogo Eletrónico: Permitido\nIndicação de Subcontratação na Proposta: Inexistência de indicação de subcontratação\n14 - PRESTAÇÃO DE CAUÇÃO\nPrestação de caução: Não\n15 - FORNECIMENTO DAS PEÇAS DO CONCURSO, APRESENTAÇÃO DE PEDIDOS DE PARTICIPAÇÃO E APRESENTAÇÃO DAS PROPOSTAS\nLink para acesso às peças do concurso (URL): https://community.vortal.biz/Public/public-tender-documents/N0tsWmZBbmhOaTk4YkpLeGlYSW5Yc3VrWTQrL204SFVHaXZEK2paNTc5dkFKNzNmYWY0dllqME05VG1vNy9zbVhpY1BvTDJpcThQSDZ1Ulc1MDJuK2c9PWlZJnd0\n20 - OUTROS REQUISITOS\nInformação sobre contratos reservados. Aplica-se a contratos reservados (54º-A)? Não\n21 - CRITÉRIO DE ADJUDICAÇÃO\nMultifator: Sim\nFator: \nNome: Preço\nPonderação: 30%\nSubfatores: Não\nFator: \nNome: Qualidade\nPonderação: 70%\nSubfatores: Não\n24 - CONDIÇÕES DO CONTRATO\nFaturação Eletrónica: Permitido\nObrigação de Subcontratação:\nCódigo da Obrigação de Subcontratação: Não é aplicável nenhuma obrigação de subcontratação.\n25 - COMPRA PÚBLICA ESTRATÉGICA\nCompra Pública Estratégica: Redução dos impactos ambientais\nDescrição do Processo de Adjudicação Estratégico: Conforme as peças do procedimento\nCritérios de contratos Públicos Ecológicos: Critérios de contratação pública ecológica nacional\nCategorias da estratégia nacional: Centros de dados, salas de servidores e serviços em nuvem\nContratos Públicos Ecológicos: Outros\nDiretiva Veículos Não Poluentes: Não\nCritério de Acessibilidade: Os critérios de acessibilidade para as pessoas com deficiência não estão incluídos porque o contrato não se destina a pessoas singulares\n26 - INFORMAÇÕES ADICIONAIS\nContrato adequado para PME: Sim\nCobertura ACP (Acordo dos Contratos Públicos da Organização Mundial do Comércio): Não\n27 - IDENTIFICAÇÃO E CONTACTOS DO ÓRGÃO DE RECURSOS ADMINISTRATIVOS\nDesignação: CÂMARA MUNICIPAL DE ÉVORA\nEndereço: Praça Sertório, nº1\nCódigo postal: 7004-506\nLocalidade: Évora\nTelefone: +351 266777000\nFax: +351 266777161\nEndereço eletrónico: cme.dagf.aprovisionamento@cm-evora.pt\n28 - IDENTIFICAÇÃO DO(S) AUTOR(ES) DE ANÚNCIO\nNome: Carlos Zorrinho\nCargo: Presidente da Câmara\n419947265",
    "nipc": "504828576",
    "distrito": "Évora",
    "concelho": "Évora",
    "freguesia": "Todas",
    "site": "https://www.cm-evora.pt/",
    "email": "cmevora@cm-evora.pt",
    "designacao_contrato": "CONTRATAÇÃO DE SERVIÇOS E FORNECIMENTO DA COMPONENTE DE COMUNICAÇÃO DO \"BAIRRO COMERCIAL DIGITAL DE ÉVORA\" PRR – PROJETO BAIRROS COMERCIAIS DIGITAIS - PROJETO Nº 5375.",
    "descricao": "CONCURSO PÚBLICO INTERNACIONAL NOS TERMOS DA ALÍNEA A) DO N°1 DO ART'.20º DO CCP PARA CONTRATAÇÃO DE SERVIÇOS E FORNECIMENTO DA COMPONENTE DE COMUNICAÇÃO DO \"BAIRRO COMERCIAL DIGITAL DE ÉVORA\" PRR – PROJETO BAIRROS COMERCIAIS DIGITAIS - PROJETO Nº 5375.",
    "preco_base": "303.135,00 EUR",
    "prazo_execucao": "80 DIAS",
    "prazo_apresentacao_propostas": "22-01-2026 23:59",
    "fundos_eu": "Sim",
    "plataforma_eletronica": "VORTAL",
    "url_procedimento": "https://community.vortal.biz/public/",
    "autor_nome": "Carlos Zorrinho",
    "autor_cargo": "Presidente da Câmara"
  },
  {
    "numero_procedimento": "N/A",
    "entidade": "Associação de Promoção Social Cultural e Desportiva de Fornos de Algodres",
    "link": "https://diariodarepublica.pt/dr/detalhe/contrato-publico/383-1003170655",
    "detalhes_completos": "1 - IDENTIFICAÇÃO E CONTACTOS DA ENTIDADE ADJUDICANTE\nDesignação da entidade adjudicante: Associação de Promoção Social Cultural e Desportiva de Fornos de Algodres\nNIPC: 501799290\nServiço/Órgão/Pessoa de contacto: Susana Carrola - gestora de procedimento\nEndereço: Avenida 25 de abril\nCódigo postal: 6370-174\nLocalidade: Fornos de Algodres\nPaís: Portugal\nNUT III: PT16J\nDistrito: Guarda\nConcelho: Fornos de Algodres\nFreguesia: Freguesia de Fornos de Algodres\nTelefone: 271701335\nFax: 271701337\nEndereço da Entidade (URL): http://www.apscdfa.pt\nEndereço Eletrónico: contratacaopublica@apscdfa.pt\neDelivery Gateway (URL): https://www.acingov.pt\nFunção da Organização: Adquirente\nNorma jurídica da Entidade Adjudicante: Organismo de direito público\nÁrea de atividade da Autoridade Adjudicante: Serviços públicos das administrações públicas\n2 - JORNAL OFICIAL DA UNIÃO EUROPEIA\nO procedimento a que este anúncio diz respeito também é publicitado no Jornal Oficial da União Europeia? Não\n3 - AVISO\nModelo de Anúncio: Concurso público\nData de Envio do Anúncio: 08-01-2026\n5 - PROCESSO\nTipo de Procedimento: Concurso público\nPreço base do procedimento: Sim\nValor do preço base do procedimento: 25.284,20 EUR\nProcedimento com lotes? Não\n6 - OBJETO DO CONTRATO\nNúmero de referência interna: CP/1/2026\nDesignação do contrato: CP 01/2026 - AQUISIÇÃO DE VIATURA ELÉTRICA  5 LUGARES\nDescrição: Aquisição de viatura elétrica  5 lugares\nTipo de Contrato Principal: Aquisição de Bens Móveis\nTipo de Contrato: Aquisição de Bens Móveis\nClassificação CPV (Vocabulário Comum para os Contratos Públicos)\nObjeto principal\nVocabulário Principal: 34110000\nPreço base s/IVA: 25.284,20 EUR\n7 - INDICAÇÕES ADICIONAIS\nO contrato envolve aquisição conjunta (satisfação de várias entidades)? Não\nO contrato é adjudicado por uma central de compras? Não\n8 - TÉCNICAS\nO concurso destina-se à celebração de um acordo-quadro? Inexistência de acordo-quadro\nÉ utilizado um leilão eletrónico? Não\nÉ adotada uma fase de negociação? Não\nSistema de Aquisição Dinâmico: Inexistência de sistema de aquisição dinâmico\n9 - LOCAL DA EXECUÇÃO DO CONTRATO\nLOCAL DA EXECUÇÃO DO CONTRATO (PROCEDIMENTO)\nPaís: Portugal\nNUT III: PT16J\nLocalidade: Freguesia de Fornos de Algodres\nDistrito: Guarda\nConcelho: Fornos de Algodres\nFreguesia: Freguesia de Fornos de Algodres\n10 - PRAZO DE EXECUÇÃO DO CONTRATO\nPrazo de execução do contrato: 30 DIAS\nPrevisão de renovações: Não\n11 - FUNDOS EU\nTêm fundos EU? Não\n12 - DOCUMENTOS DE HABILITAÇÃO\nHabilitação para o exercício da atividade profissional: Não\n13 - CONDIÇÕES DE APRESENTAÇÃO\nPlataforma eletrónica utilizada pela entidade adjudicante: ACIN\nURL para Apresentação: https://www.acingov.pt\nAdmissibilidade da apresentação de propostas variantes: Não autorizado\nPrazo para apresentação das propostas: 13-01-2026 17:00\nPrazo durante o qual os concorrentes são obrigados a manter as respetivas propostas: 66 dias a contar do termo do prazo para a apresentação das propostas\nIndicação de Subcontratação na Proposta: Inexistência de indicação de subcontratação\n14 - PRESTAÇÃO DE CAUÇÃO\nPrestação de caução: Não\n15 - FORNECIMENTO DAS PEÇAS DO CONCURSO, APRESENTAÇÃO DE PEDIDOS DE PARTICIPAÇÃO E APRESENTAÇÃO DAS PROPOSTAS\nLink para acesso às peças do concurso (URL): https://www.acingov.pt/acingovprod/2/zonaPublica/zona_publica_c/donwloadProcedurePiece/MTA0MDgyMw==\n20 - OUTROS REQUISITOS\nInformação sobre contratos reservados. Aplica-se a contratos reservados (54º-A)? Não\n21 - CRITÉRIO DE ADJUDICAÇÃO\nMultifator: Não\nMonofator:\nNome: Preço\n24 - CONDIÇÕES DO CONTRATO\nFaturação Eletrónica: Permitido\nObrigação de Subcontratação:\nCódigo da Obrigação de Subcontratação: Não é aplicável nenhuma obrigação de subcontratação.\n25 - COMPRA PÚBLICA ESTRATÉGICA\nCompra Pública Estratégica: Inexistência de contratação pública estratégica\n26 - INFORMAÇÕES ADICIONAIS\nContrato adequado para PME: Não\nCobertura ACP (Acordo dos Contratos Públicos da Organização Mundial do Comércio): Não\n27 - IDENTIFICAÇÃO E CONTACTOS DO ÓRGÃO DE RECURSOS ADMINISTRATIVOS\nDesignação: Direção da Associação Promoção Social C. D. Fornos Algodres.\nEndereço: Avenida 25 de abril, 10\nCódigo postal: 6370-174\nLocalidade: Fornos de Algodres\nTelefone: 271701335\nFax: 271701337\nEndereço eletrónico: geral@apsocial.pt\nPrazo de interposição do recurso: 2 dias\n28 - IDENTIFICAÇÃO DO(S) AUTOR(ES) DE ANÚNCIO\nNome: Fátima Susana Ramos Carrola\nCargo: Gestor de procedimento\n419947495",
    "nipc": "501799290",
    "distrito": "Guarda",
    "concelho": "Fornos de Algodres",
    "freguesia": "Freguesia de Fornos de Algodres",
    "site": "http://www.apscdfa.pt",
    "email": "contratacaopublica@apscdfa.pt",
    "designacao_contrato": "CP 01/2026 - AQUISIÇÃO DE VIATURA ELÉTRICA  5 LUGARES",
    "descricao": "Aquisição de viatura elétrica  5 lugares",
    "preco_base": "25.284,20 EUR",
    "prazo_execucao": "30 DIAS",
    "prazo_apresentacao_propostas": "13-01-2026 17:00",
    "fundos_eu": "Não",
    "plataforma_eletronica": "ACIN",
    "url_procedimento": "https://www.acingov.pt",
    "autor_nome": "Fátima Susana Ramos Carrola",
    "autor_cargo": "Gestor de procedimento"
  },
  {
    "numero_procedimento": "N/A",
    "entidade": "TUB - Transportes Urbanos de Braga, EM",
    "link": "https://diariodarepublica.pt/dr/detalhe/contrato-publico/384-1003170656",
    "detalhes_completos": "1 - IDENTIFICAÇÃO E CONTACTOS DA ENTIDADE ADJUDICANTE\nDesignação da entidade adjudicante: TUB - Transportes Urbanos de Braga, EM\nNIPC: 504807684\nServiço/Órgão/Pessoa de contacto: Administração Executiva\nEndereço: Rua Quinta de Santa Maria - Maximinos\nCódigo postal: 4700-244\nLocalidade: Braga\nPaís: Portugal\nNUT III: PT112\nDistrito: Braga\nConcelho: Braga\nFreguesia: União das Freguesias de Braga (Maximinos, Sé e Cividade)\nTelefone: 253606890\nFax: 253606899\nEndereço da Entidade (URL): www.tub.pt\nEndereço Eletrónico: geral@tub.pt\neDelivery Gateway (URL): https://www.acingov.pt\nFunção da Organização: Adquirente\nNorma jurídica da Entidade Adjudicante: Organismo de direito público\nÁrea de atividade da Entidade Adjudicante: Serviços urbanos de caminho de ferro, de elétricos, de tróleis ou de autocarros\n2 - JORNAL OFICIAL DA UNIÃO EUROPEIA\nO procedimento a que este anúncio diz respeito também é publicitado no Jornal Oficial da União Europeia? Não\n3 - AVISO\nModelo de Anúncio: Concurso público\nData de Envio do Anúncio: 08-01-2026\n5 - PROCESSO\nTipo de Procedimento: Concurso público\nPreço base do procedimento: Sim\nValor do preço base do procedimento: 450.000,00 EUR\nProcedimento com lotes? Não\n6 - OBJETO DO CONTRATO\nNúmero de referência interna: 2/2026\nDesignação do contrato: Execução da Empreitada de Construção da 1.ª Fase do Parque de Material e Oficinas (PMO) dos TUB - Transportes Urbanos de Braga, E.M.\nDescrição: Execução da Empreitada de Construção da 1.ª Fase do Parque de Material e Oficinas (PMO) dos TUB - Transportes Urbanos de Braga, E.M.\nTipo de Contrato Principal: Empreitada de Obras Públicas\nTipo de Contrato: Empreitada de Obras Públicas\nClassificação CPV (Vocabulário Comum para os Contratos Públicos)\nObjeto principal\nVocabulário Principal: 45213350\nPreço base s/IVA: 450.000,00 EUR\n7 - INDICAÇÕES ADICIONAIS\nO contrato envolve aquisição conjunta (satisfação de várias entidades)? Não\nO contrato é adjudicado por uma central de compras? Não\n8 - TÉCNICAS\nO concurso destina-se à celebração de um acordo-quadro? Inexistência de acordo-quadro\nÉ utilizado um leilão eletrónico? Não\nÉ adotada uma fase de negociação? Não\nSistema de Aquisição Dinâmico: Inexistência de sistema de aquisição dinâmico\n9 - LOCAL DA EXECUÇÃO DO CONTRATO\nLOCAL DA EXECUÇÃO DO CONTRATO (PROCEDIMENTO)\nPaís: Portugal\nNUT III: PT112\nLocalidade: Braga\nDistrito: Braga\nConcelho: Braga\nFreguesia: Todas\n10 - PRAZO DE EXECUÇÃO DO CONTRATO\nPrazo de execução do contrato: 1 MESES\nPrevisão de renovações: Não\n11 - FUNDOS EU\nTêm fundos EU? Sim\n12 - DOCUMENTOS DE HABILITAÇÃO\nHabilitação para o exercício da atividade profissional: Não\n13 - CONDIÇÕES DE APRESENTAÇÃO\nPlataforma eletrónica utilizada pela entidade adjudicante: ACIN\nURL para Apresentação: https://www.acingov.pt\nAdmissibilidade da apresentação de propostas variantes: Não autorizado\nPrazo para apresentação das propostas: 14-01-2026 23:59\nPrazo durante o qual os concorrentes são obrigados a manter as respetivas propostas: 66 dias a contar do termo do prazo para a apresentação das propostas\nIndicação de Subcontratação na Proposta: Inexistência de indicação de subcontratação\n14 - PRESTAÇÃO DE CAUÇÃO\nPrestação de caução: Sim\nPercentagem: 5%\nDescrição da Garantia Exigida: O valor da caução é de 5.00% do preço contratual.\n15 - FORNECIMENTO DAS PEÇAS DO CONCURSO, APRESENTAÇÃO DE PEDIDOS DE PARTICIPAÇÃO E APRESENTAÇÃO DAS PROPOSTAS\nLink para acesso às peças do concurso (URL): https://www.acingov.pt/acingovprod/2/zonaPublica/zona_publica_c/donwloadProcedurePiece/MTAzNzA2NA==\n20 - OUTROS REQUISITOS\nInformação sobre contratos reservados. Aplica-se a contratos reservados (54º-A)? Não\n21 - CRITÉRIO DE ADJUDICAÇÃO\nMultifator: Não\nMonofator:\nNome: Preço\n24 - CONDIÇÕES DO CONTRATO\nFaturação Eletrónica: Permitido\nObrigação de Subcontratação:\nCódigo da Obrigação de Subcontratação: Não é aplicável nenhuma obrigação de subcontratação.\n25 - COMPRA PÚBLICA ESTRATÉGICA\nCompra Pública Estratégica: Inexistência de contratação pública estratégica\n26 - INFORMAÇÕES ADICIONAIS\nContrato adequado para PME: Não\nCobertura ACP (Acordo dos Contratos Públicos da Organização Mundial do Comércio): Não\n27 - IDENTIFICAÇÃO E CONTACTOS DO ÓRGÃO DE RECURSOS ADMINISTRATIVOS\nDesignação: Conselho de Administração\nEndereço: Rua Quinta de Santa Maria, Apartado 2383\nCódigo postal: 4700-244\nLocalidade: Braga\nTelefone: 253606890\nFax: \nEndereço eletrónico: geral@tub.pt\n28 - IDENTIFICAÇÃO DO(S) AUTOR(ES) DE ANÚNCIO\nNome: Bruno Filipe Sequeira de Oliveira\nCargo: Jurista\n419947518",
    "nipc": "504807684",
    "distrito": "Braga",
    "concelho": "Braga",
    "freguesia": "União das Freguesias de Braga (Maximinos, Sé e Cividade)",
    "site": "www.tub.pt",
    "email": "geral@tub.pt",
    "designacao_contrato": "Execução da Empreitada de Construção da 1.ª Fase do Parque de Material e Oficinas (PMO) dos TUB - Transportes Urbanos de Braga, E.M.",
    "descricao": "Execução da Empreitada de Construção da 1.ª Fase do Parque de Material e Oficinas (PMO) dos TUB - Transportes Urbanos de Braga, E.M.",
    "preco_base": "450.000,00 EUR",
    "prazo_execucao": "1 MESES",
    "prazo_apresentacao_propostas": "14-01-2026 23:59",
    "fundos_eu": "Sim",
    "plataforma_eletronica": "ACIN",
    "url_procedimento": "https://www.acingov.pt",
    "autor_nome": "Bruno Filipe Sequeira de Oliveira",
    "autor_cargo": "Jurista"
  },
  {
    "numero_procedimento": "N/A",
    "entidade": "AnÃºncio de procedimento  n.Âº 385/2026  -  DiÃ¡rio da RepÃºblica n.Âº 6/2026, SÃ©rie II de 2026-01-09",
    "link": "https://diariodarepublica.pt/dr/detalhe/contrato-publico/385-1003170658"
  },
  {
    "numero_procedimento": "N/A",
    "entidade": "Município das Lajes do Pico",
    "link": "https://diariodarepublica.pt/dr/detalhe/contrato-publico/386-1003170659",
    "detalhes_completos": "1 - IDENTIFICAÇÃO E CONTACTOS DA ENTIDADE ADJUDICANTE\nDesignação da entidade adjudicante: Município das Lajes do Pico\nNIPC: 512074143\nServiço/Órgão/Pessoa de contacto: Setor do Aprovisionamento\nEndereço: Rua de São Francisco\nCódigo postal: 9930-135\nLocalidade: Lajes do Pico\nPaís: Portugal\nNUT III: PT200\nDistrito: Região Autónoma dos Açores\nConcelho: Lajes do Pico\nFreguesia: Freguesia de Lajes do Pico\nTelefone: 292679700\nEndereço da Entidade (URL): http://cm-lajesdopico.pt/\nEndereço Eletrónico: aprovisionamento.cmlp@gmail.com\neDelivery Gateway (URL): https://www.acingov.pt\nFunção da Organização: Adquirente\nNorma jurídica da Entidade Adjudicante: Organismo de direito público\nÁrea de atividade da Autoridade Adjudicante: Serviços públicos das administrações públicas\n2 - JORNAL OFICIAL DA UNIÃO EUROPEIA\nO procedimento a que este anúncio diz respeito também é publicitado no Jornal Oficial da União Europeia? Não\n3 - AVISO\nModelo de Anúncio: Concurso público\nData de Envio do Anúncio: 08-01-2026\n5 - PROCESSO\nTipo de Procedimento: Concurso público\nPreço base do procedimento: Sim\nValor do preço base do procedimento: 81.650,00 EUR\nProcedimento com lotes? Não\n6 - OBJETO DO CONTRATO\nNúmero de referência interna: CP/3/CMLP/2026\nDesignação do contrato: Empreitada de Reabilitação de Moradia  Rua da Lucinda n.º 32, Ribeirinha  Lajes (U152), no âmbito do Plano de Recuperação e Resiliência, Investimento RE-C02-I01  Programa de Apoio ao Acesso à Habitação\nDescrição: Empreitada de Reabilitação de Moradia  Rua da Lucinda n.º 32, Ribeirinha  Lajes (U152), no âmbito do Plano de Recuperação e Resiliência, Investimento RE-C02-I01  Programa de Apoio ao Acesso à Habitação\nTipo de Contrato Principal: Empreitada de Obras Públicas\nTipo de Contrato: Empreitada de Obras Públicas\nClassificação CPV (Vocabulário Comum para os Contratos Públicos)\nObjeto principal\nVocabulário Principal: 45000000\nPreço base s/IVA: 81.650,00 EUR\n7 - INDICAÇÕES ADICIONAIS\nO contrato envolve aquisição conjunta (satisfação de várias entidades)? Não\nO contrato é adjudicado por uma central de compras? Não\n8 - TÉCNICAS\nO concurso destina-se à celebração de um acordo-quadro? Inexistência de acordo-quadro\nÉ utilizado um leilão eletrónico? Não\nÉ adotada uma fase de negociação? Não\nSistema de Aquisição Dinâmico: Inexistência de sistema de aquisição dinâmico\n9 - LOCAL DA EXECUÇÃO DO CONTRATO\nLOCAL DA EXECUÇÃO DO CONTRATO (PROCEDIMENTO)\nPaís: Portugal\nNUT III: PT200\nLocalidade: Freguesia de Ribeirinha - Lajes do Pico\nDistrito: Região Autónoma dos Açores\nConcelho: Lajes do Pico\nFreguesia: Freguesia de Ribeirinha - Lajes do Pico\n10 - PRAZO DE EXECUÇÃO DO CONTRATO\nPrazo de execução do contrato: 150 DIAS\nPrevisão de renovações: Não\n11 - FUNDOS EU\nTêm fundos EU? Não\n12 - DOCUMENTOS DE HABILITAÇÃO\nHabilitação para o exercício da atividade profissional: Não\n13 - CONDIÇÕES DE APRESENTAÇÃO\nPlataforma eletrónica utilizada pela entidade adjudicante: ACIN\nURL para Apresentação: https://www.acingov.pt\nAdmissibilidade da apresentação de propostas variantes: Não autorizado\nPrazo para apresentação das propostas: 23-01-2026 23:59\nPrazo durante o qual os concorrentes são obrigados a manter as respetivas propostas: 66 dias a contar do termo do prazo para a apresentação das propostas\nIndicação de Subcontratação na Proposta: Inexistência de indicação de subcontratação\n14 - PRESTAÇÃO DE CAUÇÃO\nPrestação de caução: Não\n15 - FORNECIMENTO DAS PEÇAS DO CONCURSO, APRESENTAÇÃO DE PEDIDOS DE PARTICIPAÇÃO E APRESENTAÇÃO DAS PROPOSTAS\nLink para acesso às peças do concurso (URL): https://www.acingov.pt/acingovprod/2/zonaPublica/zona_publica_c/donwloadProcedurePiece/MTA0MTMxMQ==\n20 - OUTROS REQUISITOS\nInformação sobre contratos reservados. Aplica-se a contratos reservados (54º-A)? Não\n21 - CRITÉRIO DE ADJUDICAÇÃO\nMultifator: Não\nMonofator:\nNome: Preço\n24 - CONDIÇÕES DO CONTRATO\nFaturação Eletrónica: Permitido\nObrigação de Subcontratação:\nCódigo da Obrigação de Subcontratação: Não é aplicável nenhuma obrigação de subcontratação.\n25 - COMPRA PÚBLICA ESTRATÉGICA\nCompra Pública Estratégica: Inexistência de contratação pública estratégica\n26 - INFORMAÇÕES ADICIONAIS\nContrato adequado para PME: Sim\nCobertura ACP (Acordo dos Contratos Públicos da Organização Mundial do Comércio): Não\n27 - IDENTIFICAÇÃO E CONTACTOS DO ÓRGÃO DE RECURSOS ADMINISTRATIVOS\nDesignação: Câmara Municipal das Lajes do Pico\nEndereço: Rua de São Francisco Convento de São Francisco\nCódigo postal: 9930-135\nLocalidade: Lajes do Pico\nTelefone: 292679700\nFax: \nEndereço eletrónico: geral@cm-lajesdopico.pt\nPrazo de interposição do recurso: 5 dias\n28 - IDENTIFICAÇÃO DO(S) AUTOR(ES) DE ANÚNCIO\nNome: Manuel dos Santos Pimentel\nCargo: Vice-Presidente da Câmara Municipal das Lajes do Pico\n419947491",
    "nipc": "512074143",
    "distrito": "Região Autónoma dos Açores",
    "concelho": "Lajes do Pico",
    "freguesia": "Freguesia de Lajes do Pico",
    "site": "http://cm-lajesdopico.pt/",
    "email": "aprovisionamento.cmlp@gmail.com",
    "designacao_contrato": "Empreitada de Reabilitação de Moradia  Rua da Lucinda n.º 32, Ribeirinha  Lajes (U152), no âmbito do Plano de Recuperação e Resiliência, Investimento RE-C02-I01  Programa de Apoio ao Acesso à Habitação",
    "descricao": "Empreitada de Reabilitação de Moradia  Rua da Lucinda n.º 32, Ribeirinha  Lajes (U152), no âmbito do Plano de Recuperação e Resiliência, Investimento RE-C02-I01  Programa de Apoio ao Acesso à Habitação",
    "preco_base": "81.650,00 EUR",
    "prazo_execucao": "150 DIAS",
    "prazo_apresentacao_propostas": "23-01-2026 23:59",
    "fundos_eu": "Não",
    "plataforma_eletronica": "ACIN",
    "url_procedimento": "https://www.acingov.pt",
    "autor_nome": "Manuel dos Santos Pimentel",
    "autor_cargo": "Vice-Presidente da Câmara Municipal das Lajes do Pico"
  },
  {
    "numero_procedimento": "N/A",
    "entidade": "Município das Lajes do Pico",
    "link": "https://diariodarepublica.pt/dr/detalhe/contrato-publico/387-1003170660",
    "detalhes_completos": "1 - IDENTIFICAÇÃO E CONTACTOS DA ENTIDADE ADJUDICANTE\nDesignação da entidade adjudicante: Município das Lajes do Pico\nNIPC: 512074143\nServiço/Órgão/Pessoa de contacto: Serviço de Aprovisionamento\nEndereço: Rua de São Francisco\nCódigo postal: 9930-135\nLocalidade: Lajes do Pico\nPaís: Portugal\nNUT III: PT200\nDistrito: Região Autónoma dos Açores\nConcelho: Lajes do Pico\nFreguesia: Freguesia de Lajes do Pico\nTelefone: 292679700\nEndereço da Entidade (URL): http://cm-lajesdopico.pt/\nEndereço Eletrónico: aprovisionamento.cmlp@gmail.com\neDelivery Gateway (URL): https://www.acingov.pt\nFunção da Organização: Adquirente\nNorma jurídica da Entidade Adjudicante: Organismo de direito público\nÁrea de atividade da Autoridade Adjudicante: Serviços públicos das administrações públicas\n2 - JORNAL OFICIAL DA UNIÃO EUROPEIA\nO procedimento a que este anúncio diz respeito também é publicitado no Jornal Oficial da União Europeia? Não\n3 - AVISO\nModelo de Anúncio: Concurso público\nData de Envio do Anúncio: 08-01-2026\n5 - PROCESSO\nTipo de Procedimento: Concurso público\nPreço base do procedimento: Sim\nValor do preço base do procedimento: 99.100,00 EUR\nProcedimento com lotes? Não\n6 - OBJETO DO CONTRATO\nNúmero de referência interna: CP/2/CMLP/2026\nDesignação do contrato: Empreitada de Reabilitação de Moradia  Fetais n.º 57, Piedade  Lajes (U554), no âmbito do Plano de Recuperação e Resiliência, Investimento RE-C02-I01  Programa de Apoio ao Acesso à Habitação\nDescrição: Empreitada de Reabilitação de Moradia  Fetais n.º 57, Piedade  Lajes (U554), no âmbito do Plano de Recuperação e Resiliência, Investimento RE-C02-I01  Programa de Apoio ao Acesso à Habitação\nTipo de Contrato Principal: Empreitada de Obras Públicas\nTipo de Contrato: Empreitada de Obras Públicas\nClassificação CPV (Vocabulário Comum para os Contratos Públicos)\nObjeto principal\nVocabulário Principal: 45453100\nPreço base s/IVA: 99.100,00 EUR\n7 - INDICAÇÕES ADICIONAIS\nO contrato envolve aquisição conjunta (satisfação de várias entidades)? Não\nO contrato é adjudicado por uma central de compras? Não\n8 - TÉCNICAS\nO concurso destina-se à celebração de um acordo-quadro? Inexistência de acordo-quadro\nÉ utilizado um leilão eletrónico? Não\nÉ adotada uma fase de negociação? Não\nSistema de Aquisição Dinâmico: Inexistência de sistema de aquisição dinâmico\n9 - LOCAL DA EXECUÇÃO DO CONTRATO\nLOCAL DA EXECUÇÃO DO CONTRATO (PROCEDIMENTO)\nPaís: Portugal\nNUT III: PT200\nLocalidade: Freguesia de Piedade\nDistrito: Região Autónoma dos Açores\nConcelho: Lajes do Pico\nFreguesia: Freguesia de Piedade\n10 - PRAZO DE EXECUÇÃO DO CONTRATO\nPrazo de execução do contrato: 150 DIAS\nPrevisão de renovações: Não\n11 - FUNDOS EU\nTêm fundos EU? Não\n12 - DOCUMENTOS DE HABILITAÇÃO\nHabilitação para o exercício da atividade profissional: Não\n13 - CONDIÇÕES DE APRESENTAÇÃO\nPlataforma eletrónica utilizada pela entidade adjudicante: ACIN\nURL para Apresentação: https://www.acingov.pt\nAdmissibilidade da apresentação de propostas variantes: Não autorizado\nPrazo para apresentação das propostas: 23-01-2026 23:59\nPrazo durante o qual os concorrentes são obrigados a manter as respetivas propostas: 66 dias a contar do termo do prazo para a apresentação das propostas\nIndicação de Subcontratação na Proposta: Inexistência de indicação de subcontratação\n14 - PRESTAÇÃO DE CAUÇÃO\nPrestação de caução: Não\n15 - FORNECIMENTO DAS PEÇAS DO CONCURSO, APRESENTAÇÃO DE PEDIDOS DE PARTICIPAÇÃO E APRESENTAÇÃO DAS PROPOSTAS\nLink para acesso às peças do concurso (URL): https://www.acingov.pt/acingovprod/2/zonaPublica/zona_publica_c/donwloadProcedurePiece/MTA0MTMwNg==\n20 - OUTROS REQUISITOS\nInformação sobre contratos reservados. Aplica-se a contratos reservados (54º-A)? Não\n21 - CRITÉRIO DE ADJUDICAÇÃO\nMultifator: Não\nMonofator:\nNome: Preço\n24 - CONDIÇÕES DO CONTRATO\nFaturação Eletrónica: Permitido\nObrigação de Subcontratação:\nCódigo da Obrigação de Subcontratação: Não é aplicável nenhuma obrigação de subcontratação.\n25 - COMPRA PÚBLICA ESTRATÉGICA\nCompra Pública Estratégica: Inexistência de contratação pública estratégica\n26 - INFORMAÇÕES ADICIONAIS\nContrato adequado para PME: Sim\nCobertura ACP (Acordo dos Contratos Públicos da Organização Mundial do Comércio): Não\n27 - IDENTIFICAÇÃO E CONTACTOS DO ÓRGÃO DE RECURSOS ADMINISTRATIVOS\nDesignação: Câmara Municipal das Lajes do Pico\nEndereço: Rua de São Francisco Convento de São Francisco\nCódigo postal: 9930-135\nLocalidade: Lajes do Pico\nTelefone: 292679700\nFax: \nEndereço eletrónico: geral@cm-lajesdopico.pt\n28 - IDENTIFICAÇÃO DO(S) AUTOR(ES) DE ANÚNCIO\nNome: Manuel dos Santos Pimentel\nCargo: Vice-Presidente da Câmara Municipal das Lajes do Pico\n419947490",
    "nipc": "512074143",
    "distrito": "Região Autónoma dos Açores",
    "concelho": "Lajes do Pico",
    "freguesia": "Freguesia de Lajes do Pico",
    "site": "http://cm-lajesdopico.pt/",
    "email": "aprovisionamento.cmlp@gmail.com",
    "designacao_contrato": "Empreitada de Reabilitação de Moradia  Fetais n.º 57, Piedade  Lajes (U554), no âmbito do Plano de Recuperação e Resiliência, Investimento RE-C02-I01  Programa de Apoio ao Acesso à Habitação",
    "descricao": "Empreitada de Reabilitação de Moradia  Fetais n.º 57, Piedade  Lajes (U554), no âmbito do Plano de Recuperação e Resiliência, Investimento RE-C02-I01  Programa de Apoio ao Acesso à Habitação",
    "preco_base": "99.100,00 EUR",
    "prazo_execucao": "150 DIAS",
    "prazo_apresentacao_propostas": "23-01-2026 23:59",
    "fundos_eu": "Não",
    "plataforma_eletronica": "ACIN",
    "url_procedimento": "https://www.acingov.pt",
    "autor_nome": "Manuel dos Santos Pimentel",
    "autor_cargo": "Vice-Presidente da Câmara Municipal das Lajes do Pico"
  },
  {
    "numero_procedimento": "N/A",
    "entidade": "Unidade Local de Saúde de Amadora/Sintra, EPE",
    "link": "https://diariodarepublica.pt/dr/detalhe/contrato-publico/388-1003170665",
    "detalhes_completos": "1 - IDENTIFICAÇÃO E CONTACTOS DA ENTIDADE ADJUDICANTE\nDesignação da entidade adjudicante: Unidade Local de Saúde de Amadora/Sintra, EPE\nNIPC: 503035416\nEndereço: VIA RÁPIDA LISBOA-SINTRA IC19\nCódigo postal: 2720-276\nLocalidade: Lisboa\nPaís: Portugal\nNUT III: PT170\nDistrito: Lisboa\nConcelho: Amadora\nFreguesia: Freguesia de Venteira\nTelefone: 214348200\nFax: 214345566\nEndereço da Entidade (URL): https://hff.min-saude.pt/\nEndereço Eletrónico: logistica@ulsasi.min-saude.pt\neDelivery Gateway (URL): https://community.vortal.biz/public/\nFunção da Organização: Adquirente\nNorma jurídica da Entidade Adjudicante: Organismo de direito público\nÁrea de atividade da Autoridade Adjudicante: Saúde\n2 - JORNAL OFICIAL DA UNIÃO EUROPEIA\nO procedimento a que este anúncio diz respeito também é publicitado no Jornal Oficial da União Europeia? Não\n3 - AVISO\nModelo de Anúncio: Concurso público\nData de Envio do Anúncio: 08-01-2026\n5 - PROCESSO\nTipo de Procedimento: Concurso público\nPreço base do procedimento: Sim\nValor do preço base do procedimento: 125.000,00 EUR\nProcedimento com lotes? Não\n6 - OBJETO DO CONTRATO\nNúmero de referência interna: 19F0014626\nDesignação do contrato: Prestação de Serviços para Fiscalização da empreitada de conceção-construção de intervenção na Farmácia Hospitalar, para o HFF, integrado na ULSASI, E.P.E.\nDescrição: Prestação de Serviços para Fiscalização da empreitada de conceção-construção de intervenção na Farmácia Hospitalar, para o HFF, integrado na ULSASI, E.P.E.\nTipo de Contrato Principal: Aquisição de Serviços\nTipo de Contrato: Aquisição de Serviços\nClassificação CPV (Vocabulário Comum para os Contratos Públicos)\nObjeto principal\nVocabulário Principal: 71247000\nPreço base s/IVA: 125.000,00 EUR\n7 - INDICAÇÕES ADICIONAIS\nO contrato envolve aquisição conjunta (satisfação de várias entidades)? Não\nO contrato é adjudicado por uma central de compras? Não\n8 - TÉCNICAS\nO concurso destina-se à celebração de um acordo-quadro? Inexistência de acordo-quadro\nÉ utilizado um leilão eletrónico? Não\nÉ adotada uma fase de negociação? Não\nSistema de Aquisição Dinâmico: Inexistência de sistema de aquisição dinâmico\n9 - LOCAL DA EXECUÇÃO DO CONTRATO\nLOCAL DA EXECUÇÃO DO CONTRATO (PROCEDIMENTO)\nPaís: Portugal\nNUT III: PT170\nLocalidade: Lisboa\nDistrito: Lisboa\nConcelho: Amadora\nFreguesia: Freguesia de Venteira\n10 - PRAZO DE EXECUÇÃO DO CONTRATO\nPrazo de execução do contrato: 195 DIAS\nPrevisão de renovações: Não\n11 - FUNDOS EU\nTêm fundos EU? Sim\n12 - DOCUMENTOS DE HABILITAÇÃO\nHabilitação para o exercício da atividade profissional: Não\n13 - CONDIÇÕES DE APRESENTAÇÃO\nPlataforma eletrónica utilizada pela entidade adjudicante: VORTAL\nURL para Apresentação: https://community.vortal.biz/public/\nAdmissibilidade da apresentação de propostas variantes: Não autorizado\nPrazo para apresentação das propostas: 23-01-2026 17:00\nPrazo durante o qual os concorrentes são obrigados a manter as respetivas propostas: 120 dias a contar do termo do prazo para a apresentação das propostas\nIndicação de Subcontratação na Proposta: Inexistência de indicação de subcontratação\n14 - PRESTAÇÃO DE CAUÇÃO\nPrestação de caução: Não\n15 - FORNECIMENTO DAS PEÇAS DO CONCURSO, APRESENTAÇÃO DE PEDIDOS DE PARTICIPAÇÃO E APRESENTAÇÃO DAS PROPOSTAS\nLink para acesso às peças do concurso (URL): https://community.vortal.biz/Public/public-tender-documents/VzFxc3JXY0Y3TlBxSjhEZCtFRUFOWHlWbDd0OEt4U3RZWGMwV3VwbE1LTVdLemp0eWI5WFpJZEVHTGZUVjgzTTAwYWtqdXJkQjZQZ0tkTCtKcSs5ZGc9PU9RTHdG\n20 - OUTROS REQUISITOS\nInformação sobre contratos reservados. Aplica-se a contratos reservados (54º-A)? Não\n21 - CRITÉRIO DE ADJUDICAÇÃO\nMultifator: Não\nMonofator:\nNome: Outros\nOutro nome: Preço\n24 - CONDIÇÕES DO CONTRATO\nFaturação Eletrónica: Permitido\nObrigação de Subcontratação:\nCódigo da Obrigação de Subcontratação: Não é aplicável nenhuma obrigação de subcontratação.\n25 - COMPRA PÚBLICA ESTRATÉGICA\nCompra Pública Estratégica: Inexistência de contratação pública estratégica\n26 - INFORMAÇÕES ADICIONAIS\nContrato adequado para PME: Sim\nCobertura ACP (Acordo dos Contratos Públicos da Organização Mundial do Comércio): Não\n27 - IDENTIFICAÇÃO E CONTACTOS DO ÓRGÃO DE RECURSOS ADMINISTRATIVOS\nDesignação: Unidade Local de Saúde de Amadora Sintra\nEndereço: IC 19  Venteira\nCódigo postal: 2720-276\nLocalidade: Amadora\nTelefone: +351 214348200\nFax: +351 214345566\nEndereço eletrónico: logistica@ulsasi.min-saude.pt\n28 - IDENTIFICAÇÃO DO(S) AUTOR(ES) DE ANÚNCIO\nNome: Rui Mendes\nCargo: Assistente Técnico\n419947481",
    "nipc": "503035416",
    "distrito": "Lisboa",
    "concelho": "Amadora",
    "freguesia": "Freguesia de Venteira",
    "site": "https://hff.min-saude.pt/",
    "email": "logistica@ulsasi.min-saude.pt",
    "designacao_contrato": "Prestação de Serviços para Fiscalização da empreitada de conceção-construção de intervenção na Farmácia Hospitalar, para o HFF, integrado na ULSASI, E.P.E.",
    "descricao": "Prestação de Serviços para Fiscalização da empreitada de conceção-construção de intervenção na Farmácia Hospitalar, para o HFF, integrado na ULSASI, E.P.E.",
    "preco_base": "125.000,00 EUR",
    "prazo_execucao": "195 DIAS",
    "prazo_apresentacao_propostas": "23-01-2026 17:00",
    "fundos_eu": "Sim",
    "plataforma_eletronica": "VORTAL",
    "url_procedimento": "https://community.vortal.biz/public/",
    "autor_nome": "Rui Mendes",
    "autor_cargo": "Assistente Técnico"
  },
  {
    "numero_procedimento": "N/A",
    "entidade": "Município de Santo Tirso",
    "link": "https://diariodarepublica.pt/dr/detalhe/contrato-publico/390-1003371829",
    "detalhes_completos": "1 - IDENTIFICAÇÃO E CONTACTOS DA ENTIDADE ADJUDICANTE\nDesignação da entidade adjudicante: Município de Santo Tirso\nNIPC: 501306870\nEndereço: Praça 25 de Abril\nCódigo postal: 4780-373\nLocalidade: Área Metropolitana do Porto\nPaís: Portugal\nNUT III: PT11A\nDistrito: Porto\nConcelho: Santo Tirso\nFreguesia: União das Freguesias de Santo Tirso, Couto (Santa Cristina e São Miguel) e Burgães\nTelefone: 252830400\nFax: 252856534\nEndereço da Entidade (URL): www.cm-stirso.pt\nEndereço Eletrónico: santotirso@cm-stirso.pt\neDelivery Gateway (URL): https://community.vortal.biz/public/\nFunção da Organização: Adquirente\nNorma jurídica da Entidade Adjudicante: Autoridade local\nÁrea de atividade da Autoridade Adjudicante: Serviços públicos das administrações públicas\n2 - JORNAL OFICIAL DA UNIÃO EUROPEIA\nO procedimento a que este anúncio diz respeito também é publicitado no Jornal Oficial da União Europeia? Não\n3 - AVISO\nModelo de Anúncio: Concurso público\nData de Envio do Anúncio: 08-01-2026\n5 - PROCESSO\nTipo de Procedimento: Concurso público\nPreço base do procedimento: Sim\nValor do preço base do procedimento: 83.000,00 EUR\nProcedimento com lotes? Não\n6 - OBJETO DO CONTRATO\nNúmero de referência interna: 1003/CPN/S/2025\nDesignação do contrato: CONTRATO DE AQUISIÇÃO DE SERVIÇOS PARA A ORGANIZAÇÃO E IMPLEMENTAÇÃO DE UM PROGRAMA DE APOIO À PROMOÇÃO DAS APRENDIZAGENS DOS ALUNOS DO 2.º E DO 3.º CICLO DO ENSINO BÁSICO\nDescrição: CONTRATO DE AQUISIÇÃO DE SERVIÇOS PARA A ORGANIZAÇÃO E IMPLEMENTAÇÃO DE UM PROGRAMA DE APOIO À PROMOÇÃO DAS APRENDIZAGENS DOS ALUNOS DO 2.º E DO 3.º CICLO\nDO ENSINO BÁSICO\nTipo de Contrato Principal: Aquisição de Serviços\nTipo de Contrato: Aquisição de Serviços\nClassificação CPV (Vocabulário Comum para os Contratos Públicos)\nObjeto principal\nVocabulário Principal: 98133000\nPreço base s/IVA: 83.000,00 EUR\n7 - INDICAÇÕES ADICIONAIS\nO contrato envolve aquisição conjunta (satisfação de várias entidades)? Não\nO contrato é adjudicado por uma central de compras? Não\n8 - TÉCNICAS\nO concurso destina-se à celebração de um acordo-quadro? Inexistência de acordo-quadro\nÉ utilizado um leilão eletrónico? Não\nÉ adotada uma fase de negociação? Não\nSistema de Aquisição Dinâmico: Inexistência de sistema de aquisição dinâmico\n9 - LOCAL DA EXECUÇÃO DO CONTRATO\nLOCAL DA EXECUÇÃO DO CONTRATO (PROCEDIMENTO)\nPaís: Portugal\nNUT III: PT11A\nLocalidade: Área Metropolitana do Porto\nDistrito: Porto\nConcelho: Santo Tirso\nFreguesia: União das Freguesias de Santo Tirso, Couto (Santa Cristina e São Miguel) e Burgães\n10 - PRAZO DE EXECUÇÃO DO CONTRATO\nPrazo de execução do contrato: 24 MESES\nPrevisão de renovações: Não\n11 - FUNDOS EU\nTêm fundos EU? Não\n12 - DOCUMENTOS DE HABILITAÇÃO\nHabilitação para o exercício da atividade profissional: Não\n13 - CONDIÇÕES DE APRESENTAÇÃO\nPlataforma eletrónica utilizada pela entidade adjudicante: VORTAL\nURL para Apresentação: https://community.vortal.biz/public/\nAdmissibilidade da apresentação de propostas variantes: Não autorizado\nPrazo para apresentação das propostas: 26-01-2026 17:30\nPrazo durante o qual os concorrentes são obrigados a manter as respetivas propostas: 66 dias a contar do termo do prazo para a apresentação das propostas\nIndicação de Subcontratação na Proposta: Inexistência de indicação de subcontratação\n14 - PRESTAÇÃO DE CAUÇÃO\nPrestação de caução: Não\n15 - FORNECIMENTO DAS PEÇAS DO CONCURSO, APRESENTAÇÃO DE PEDIDOS DE PARTICIPAÇÃO E APRESENTAÇÃO DAS PROPOSTAS\nLink para acesso às peças do concurso (URL): https://community.vortal.biz/Public/public-tender-documents/UHkxZy9MbVRLR1Y5S3RFUXJnMHdDTCt4WmowVDdlbllFT2Z1WWp3M1U0VzlmKzFQUVd6MmQyYzY2TlBpZ0VzYXduTEZSNjB3V0kvUWZBM01jdkk4SUE9PXAkeUpt\n20 - OUTROS REQUISITOS\nInformação sobre contratos reservados. Aplica-se a contratos reservados (54º-A)? Não\n21 - CRITÉRIO DE ADJUDICAÇÃO\nMultifator: Sim\nFator: \nNome: Preço\nPonderação: 50%\nSubfatores: Não\nFator: \nNome: Qualidade\nPonderação: 50%\nSubfatores: Não\n24 - CONDIÇÕES DO CONTRATO\nFaturação Eletrónica: Permitido\nObrigação de Subcontratação:\nCódigo da Obrigação de Subcontratação: Não é aplicável nenhuma obrigação de subcontratação.\n25 - COMPRA PÚBLICA ESTRATÉGICA\nCompra Pública Estratégica: Inexistência de contratação pública estratégica\n26 - INFORMAÇÕES ADICIONAIS\nContrato adequado para PME: Sim\nCobertura ACP (Acordo dos Contratos Públicos da Organização Mundial do Comércio): Não\n27 - IDENTIFICAÇÃO E CONTACTOS DO ÓRGÃO DE RECURSOS ADMINISTRATIVOS\nDesignação: Município de Santo Tirso\nEndereço: Praça 25 de Abril\nCódigo postal: 4780-373\nLocalidade: Santo Tirso\nTelefone: +351 252830400\nFax: +351 252856534\nEndereço eletrónico: santotirso@cm-stirso.pt\n28 - IDENTIFICAÇÃO DO(S) AUTOR(ES) DE ANÚNCIO\nNome: Alberto Costa\nCargo: Presidente da Câmara Municipal\n419947506",
    "nipc": "501306870",
    "distrito": "Porto",
    "concelho": "Santo Tirso",
    "freguesia": "União das Freguesias de Santo Tirso, Couto (Santa Cristina e São Miguel) e Burgães",
    "site": "www.cm-stirso.pt",
    "email": "santotirso@cm-stirso.pt",
    "designacao_contrato": "CONTRATO DE AQUISIÇÃO DE SERVIÇOS PARA A ORGANIZAÇÃO E IMPLEMENTAÇÃO DE UM PROGRAMA DE APOIO À PROMOÇÃO DAS APRENDIZAGENS DOS ALUNOS DO 2.º E DO 3.º CICLO DO ENSINO BÁSICO",
    "descricao": "CONTRATO DE AQUISIÇÃO DE SERVIÇOS PARA A ORGANIZAÇÃO E IMPLEMENTAÇÃO DE UM PROGRAMA DE APOIO À PROMOÇÃO DAS APRENDIZAGENS DOS ALUNOS DO 2.º E DO 3.º CICLO",
    "preco_base": "83.000,00 EUR",
    "prazo_execucao": "24 MESES",
    "prazo_apresentacao_propostas": "26-01-2026 17:30",
    "fundos_eu": "Não",
    "plataforma_eletronica": "VORTAL",
    "url_procedimento": "https://community.vortal.biz/public/",
    "autor_nome": "Alberto Costa",
    "autor_cargo": "Presidente da Câmara Municipal"
  },
  {
    "numero_procedimento": "N/A",
    "entidade": "Banco de Portugal",
    "link": "https://diariodarepublica.pt/dr/detalhe/contrato-publico/391-1003371830",
    "detalhes_completos": "1 - IDENTIFICAÇÃO E CONTACTOS DA ENTIDADE ADJUDICANTE\nDesignação da entidade adjudicante: Banco de Portugal\nNIPC: 500792771\nEndereço: Rua Francisco Ribeiro, 2\nCódigo postal: 1150-165\nLocalidade: Lisboa\nPaís: Portugal\nNUT III: PT170\nDistrito: Lisboa\nConcelho: Lisboa\nFreguesia: Todas\nTelefone: 213130000\nFax: 213128124\nEndereço da Entidade (URL): www.bportugal.pt\nEndereço Eletrónico: bdp.compras@bportugal.pt\neDelivery Gateway (URL): https://community.vortal.biz/public/\nFunção da Organização: Adquirente\nNorma jurídica da Entidade Adjudicante: Organismo de direito público\nÁrea de atividade da Autoridade Adjudicante: Assuntos económicos\n2 - JORNAL OFICIAL DA UNIÃO EUROPEIA\nO procedimento a que este anúncio diz respeito também é publicitado no Jornal Oficial da União Europeia? Não\n3 - AVISO\nModelo de Anúncio: Concurso público\nData de Envio do Anúncio: 08-01-2026\n5 - PROCESSO\nTipo de Procedimento: Concurso público\nPreço base do procedimento: Sim\nValor do preço base do procedimento: 179.886,00 EUR\nProcedimento com lotes? Não\n6 - OBJETO DO CONTRATO\nNúmero de referência interna: OA044625\nDesignação do contrato: Serviços de manutenção do licenciamento SAS\nDescrição: Serviços de manutenção do licenciamento SAS\nTipo de Contrato Principal: Aquisição de Serviços\nTipo de Contrato: Aquisição de Serviços\nClassificação CPV (Vocabulário Comum para os Contratos Públicos)\nObjeto principal\nVocabulário Principal: 72267000\nPreço base s/IVA: 179.886,00 EUR\n7 - INDICAÇÕES ADICIONAIS\nO contrato envolve aquisição conjunta (satisfação de várias entidades)? Não\nO contrato é adjudicado por uma central de compras? Não\n8 - TÉCNICAS\nO concurso destina-se à celebração de um acordo-quadro? Inexistência de acordo-quadro\nÉ utilizado um leilão eletrónico? Não\nÉ adotada uma fase de negociação? Não\nSistema de Aquisição Dinâmico: Inexistência de sistema de aquisição dinâmico\n9 - LOCAL DA EXECUÇÃO DO CONTRATO\nLOCAL DA EXECUÇÃO DO CONTRATO (PROCEDIMENTO)\nPaís: Portugal\nNUT III: PT170\nLocalidade: Lisboa\nDistrito: Lisboa\nConcelho: Lisboa\nFreguesia: Freguesia de Arroios - Lisboa\n10 - PRAZO DE EXECUÇÃO DO CONTRATO\nPrazo de execução do contrato: 12 MESES\nPrevisão de renovações: Não\n11 - FUNDOS EU\nTêm fundos EU? Não\n12 - DOCUMENTOS DE HABILITAÇÃO\nHabilitação para o exercício da atividade profissional: Não\n13 - CONDIÇÕES DE APRESENTAÇÃO\nPlataforma eletrónica utilizada pela entidade adjudicante: VORTAL\nURL para Apresentação: https://community.vortal.biz/public/\nAdmissibilidade da apresentação de propostas variantes: Não autorizado\nPrazo para apresentação das propostas: 19-01-2026 17:00\nPrazo durante o qual os concorrentes são obrigados a manter as respetivas propostas: 120 dias a contar do termo do prazo para a apresentação das propostas\nIndicação de Subcontratação na Proposta: Inexistência de indicação de subcontratação\n14 - PRESTAÇÃO DE CAUÇÃO\nPrestação de caução: Não\n15 - FORNECIMENTO DAS PEÇAS DO CONCURSO, APRESENTAÇÃO DE PEDIDOS DE PARTICIPAÇÃO E APRESENTAÇÃO DAS PROPOSTAS\nLink para acesso às peças do concurso (URL): https://community.vortal.biz/Public/public-tender-documents/cHBKaUtUdG0yT0E1NUVuKzkzU3R4clF5Rm9ibG1haHkrY2tnRWs1aFd5YUtqUExQK2NMeHFnK1U1MHZoVk5EY2dCaUVBaTRSS0lFTVpyWGY3NmxFSnc9PThORDNu\n20 - OUTROS REQUISITOS\nInformação sobre contratos reservados. Aplica-se a contratos reservados (54º-A)? Não\n21 - CRITÉRIO DE ADJUDICAÇÃO\nMultifator: Não\nMonofator:\nNome: Outros\nOutro nome: Preço\n24 - CONDIÇÕES DO CONTRATO\nFaturação Eletrónica: Permitido\nObrigação de Subcontratação:\nCódigo da Obrigação de Subcontratação: Não é aplicável nenhuma obrigação de subcontratação.\n25 - COMPRA PÚBLICA ESTRATÉGICA\nCompra Pública Estratégica: Inexistência de contratação pública estratégica\n26 - INFORMAÇÕES ADICIONAIS\nContrato adequado para PME: Sim\nCobertura ACP (Acordo dos Contratos Públicos da Organização Mundial do Comércio): Não\n27 - IDENTIFICAÇÃO E CONTACTOS DO ÓRGÃO DE RECURSOS ADMINISTRATIVOS\nDesignação: Conselho de Administração do Banco de Portugal\nEndereço: Avenida Álvaro Pais, 2\nCódigo postal: 1600-007\nLocalidade: Lisboa\nTelefone: +351 213130000\nFax: +351 213128124\nEndereço eletrónico: bdp.compras@bportugal.pt\n28 - IDENTIFICAÇÃO DO(S) AUTOR(ES) DE ANÚNCIO\nNome: DLIAC-UFC\nCargo: DLIAC-UFC\n419947521",
    "nipc": "500792771",
    "distrito": "Lisboa",
    "concelho": "Lisboa",
    "freguesia": "Todas",
    "site": "www.bportugal.pt",
    "email": "bdp.compras@bportugal.pt",
    "designacao_contrato": "Serviços de manutenção do licenciamento SAS",
    "descricao": "Serviços de manutenção do licenciamento SAS",
    "preco_base": "179.886,00 EUR",
    "prazo_execucao": "12 MESES",
    "prazo_apresentacao_propostas": "19-01-2026 17:00",
    "fundos_eu": "Não",
    "plataforma_eletronica": "VORTAL",
    "url_procedimento": "https://community.vortal.biz/public/",
    "autor_nome": "DLIAC-UFC",
    "autor_cargo": "DLIAC-UFC"
  },
  {
    "numero_procedimento": "N/A",
    "entidade": "Teatro Nacional de São João, EPE",
    "link": "https://diariodarepublica.pt/dr/detalhe/contrato-publico/392-1003371831",
    "detalhes_completos": "1 - IDENTIFICAÇÃO E CONTACTOS DA ENTIDADE ADJUDICANTE\nDesignação da entidade adjudicante: Teatro Nacional de São João, EPE\nNIPC: 503966908\nServiço/Órgão/Pessoa de contacto: Departamento de Contratação Pública\nEndereço: Praça da Batalha\nCódigo postal: 4000-102\nLocalidade: Porto\nPaís: Portugal\nNUT III: PT11A\nDistrito: Porto\nConcelho: Porto\nFreguesia: União das Freguesias de Cedofeita, Santo Ildefonso, Sé, Miragaia, São Nicolau e Vitória\nTelefone: 223401900\nFax: 222003449\nEndereço da Entidade (URL): https://www.acingov.pt\nEndereço Eletrónico: geral@tnsj.pt\neDelivery Gateway (URL): https://www.acingov.pt\nFunção da Organização: Adquirente\nNorma jurídica da Entidade Adjudicante: Empresa pública, controlada por uma autoridade da administração central\nÁrea de atividade da Autoridade Adjudicante: Atividades recreativas, culturais e religiosas\n2 - JORNAL OFICIAL DA UNIÃO EUROPEIA\nO procedimento a que este anúncio diz respeito também é publicitado no Jornal Oficial da União Europeia? Não\n3 - AVISO\nModelo de Anúncio: Concurso público\nData de Envio do Anúncio: 08-01-2026\n5 - PROCESSO\nTipo de Procedimento: Concurso público\nPreço base do procedimento: Sim\nValor do preço base do procedimento: 61.955,00 EUR\nProcedimento com lotes? Não\n6 - OBJETO DO CONTRATO\nNúmero de referência interna: 02/CPN/2026\nDesignação do contrato: Prestação de Serviços de Impressão dos Cadernos de Programação e Brochuras de Programação (Versão em Inglês)\nDescrição: Prestação de Serviços de Impressão dos Cadernos de Programação e Brochuras de Programação (Versão em Inglês)\nTipo de Contrato Principal: Aquisição de Serviços\nTipo de Contrato: Aquisição de Serviços\nClassificação CPV (Vocabulário Comum para os Contratos Públicos)\nObjeto principal\nVocabulário Principal: 79810000\nPreço base s/IVA: 61.955,00 EUR\n7 - INDICAÇÕES ADICIONAIS\nO contrato envolve aquisição conjunta (satisfação de várias entidades)? Não\nO contrato é adjudicado por uma central de compras? Não\n8 - TÉCNICAS\nO concurso destina-se à celebração de um acordo-quadro? Inexistência de acordo-quadro\nÉ utilizado um leilão eletrónico? Não\nÉ adotada uma fase de negociação? Não\nSistema de Aquisição Dinâmico: Inexistência de sistema de aquisição dinâmico\n9 - LOCAL DA EXECUÇÃO DO CONTRATO\nLOCAL DA EXECUÇÃO DO CONTRATO (PROCEDIMENTO)\nPaís: Portugal\nNUT III: PT111\nLocalidade: União das Freguesias de Cedofeita, Santo Ildefonso, Sé, Miragaia, São Nicolau e Vitória\nDistrito: Porto\nConcelho: Porto\nFreguesia: União das Freguesias de Cedofeita, Santo Ildefonso, Sé, Miragaia, São Nicolau e Vitória\n10 - PRAZO DE EXECUÇÃO DO CONTRATO\nPrazo de execução do contrato: 240 DIAS\nPrevisão de renovações: Não\n11 - FUNDOS EU\nTêm fundos EU? Não\n12 - DOCUMENTOS DE HABILITAÇÃO\nHabilitação para o exercício da atividade profissional: Não\n13 - CONDIÇÕES DE APRESENTAÇÃO\nPlataforma eletrónica utilizada pela entidade adjudicante: ACIN\nURL para Apresentação: https://www.acingov.pt\nAdmissibilidade da apresentação de propostas variantes: Não autorizado\nPrazo para apresentação das propostas: 14-01-2026 23:59\nPrazo durante o qual os concorrentes são obrigados a manter as respetivas propostas: 66 dias a contar do termo do prazo para a apresentação das propostas\nIndicação de Subcontratação na Proposta: A parte do contrato que o proponente tenciona subcontratar\n14 - PRESTAÇÃO DE CAUÇÃO\nPrestação de caução: Não\n15 - FORNECIMENTO DAS PEÇAS DO CONCURSO, APRESENTAÇÃO DE PEDIDOS DE PARTICIPAÇÃO E APRESENTAÇÃO DAS PROPOSTAS\nLink para acesso às peças do concurso (URL): https://www.acingov.pt/acingovprod/2/zonaPublica/zona_publica_c/donwloadProcedurePiece/MTA0MTM1OQ==\n20 - OUTROS REQUISITOS\nInformação sobre contratos reservados. Aplica-se a contratos reservados (54º-A)? Não\n21 - CRITÉRIO DE ADJUDICAÇÃO\nMultifator: Não\nMonofator:\nNome: Preço\n24 - CONDIÇÕES DO CONTRATO\nFaturação Eletrónica: Permitido\nObrigação de Subcontratação:\nCódigo da Obrigação de Subcontratação: Não é aplicável nenhuma obrigação de subcontratação.\n25 - COMPRA PÚBLICA ESTRATÉGICA\nCompra Pública Estratégica: Inexistência de contratação pública estratégica\n26 - INFORMAÇÕES ADICIONAIS\nContrato adequado para PME: Sim\nCobertura ACP (Acordo dos Contratos Públicos da Organização Mundial do Comércio): Não\n27 - IDENTIFICAÇÃO E CONTACTOS DO ÓRGÃO DE RECURSOS ADMINISTRATIVOS\nDesignação: Conselho de Administração do TNSJ\nEndereço: Praça da Batalha\nCódigo postal: 4000-102\nLocalidade: Porto\nTelefone: 223401966\nFax: 222003449\nEndereço eletrónico: contratacaopublica@tnsj.pt\n28 - IDENTIFICAÇÃO DO(S) AUTOR(ES) DE ANÚNCIO\nNome: Cláudia Leite\nCargo: Vogal do Conselho de Administração do TNSJ\n419947527",
    "nipc": "503966908",
    "distrito": "Porto",
    "concelho": "Porto",
    "freguesia": "União das Freguesias de Cedofeita, Santo Ildefonso, Sé, Miragaia, São Nicolau e Vitória",
    "site": "https://www.acingov.pt",
    "email": "geral@tnsj.pt",
    "designacao_contrato": "Prestação de Serviços de Impressão dos Cadernos de Programação e Brochuras de Programação (Versão em Inglês)",
    "descricao": "Prestação de Serviços de Impressão dos Cadernos de Programação e Brochuras de Programação (Versão em Inglês)",
    "preco_base": "61.955,00 EUR",
    "prazo_execucao": "240 DIAS",
    "prazo_apresentacao_propostas": "14-01-2026 23:59",
    "fundos_eu": "Não",
    "plataforma_eletronica": "ACIN",
    "url_procedimento": "https://www.acingov.pt",
    "autor_nome": "Cláudia Leite",
    "autor_cargo": "Vogal do Conselho de Administração do TNSJ"
  },
  {
    "numero_procedimento": "N/A",
    "entidade": "Município de Serpa",
    "link": "https://diariodarepublica.pt/dr/detalhe/contrato-publico/394-1003372800",
    "detalhes_completos": "1 - IDENTIFICAÇÃO E CONTACTOS DA ENTIDADE ADJUDICANTE\nDesignação da entidade adjudicante: Município de Serpa\nNIPC: 501112049\nServiço/Órgão/Pessoa de contacto: Divisão Financeira\nEndereço: Praça da Republica\nCódigo postal: 7830-320\nLocalidade: serpa\nPaís: Portugal\nNUT III: PT184\nDistrito: Beja\nConcelho: Serpa\nFreguesia: União das Freguesias de Vila Nova de São Bento e Vale de Vargo\nTelefone: 284540100\nEndereço da Entidade (URL): https://www.cm-serpa.pt\nEndereço Eletrónico: geral@cm-serpa.pt\nFunção da Organização: Adquirente\nNorma jurídica da Entidade Adjudicante: Autoridade local\nÁrea de atividade da Autoridade Adjudicante: Serviços públicos das administrações públicas\n2 - JORNAL OFICIAL DA UNIÃO EUROPEIA\nO procedimento a que este anúncio diz respeito também é publicitado no Jornal Oficial da União Europeia? Não\n3 - AVISO\nModelo de Anúncio: Concurso público\nData de Envio do Anúncio: 08-01-2026\n5 - PROCESSO\nTipo de Procedimento: Concurso público\nPreço base do procedimento: Sim\nValor do preço base do procedimento: 698.797,13 EUR\nProcedimento com lotes? Não\n6 - OBJETO DO CONTRATO\nNúmero de referência interna: CP 23/2025\nDesignação do contrato: Empreitada de Alteração e Ampliação do Edifício do Centro de Saúde de Vila Nova de S. Bento.\nDescrição: Empreitada de Alteração e Ampliação do Edifício do Centro de Saúde de Vila Nova de S. Bento.\nTipo de Contrato Principal: Empreitada de Obras Públicas\nTipo de Contrato: Empreitada de Obras Públicas\nClassificação CPV (Vocabulário Comum para os Contratos Públicos)\nObjeto principal\nVocabulário Principal: 45215100\nPreço base s/IVA: 698.797,13 EUR\n7 - INDICAÇÕES ADICIONAIS\nO contrato envolve aquisição conjunta (satisfação de várias entidades)? Não\nO contrato é adjudicado por uma central de compras? Não\n8 - TÉCNICAS\nO concurso destina-se à celebração de um acordo-quadro? Inexistência de acordo-quadro\nÉ utilizado um leilão eletrónico? Não\nÉ adotada uma fase de negociação? Não\nSistema de Aquisição Dinâmico: Inexistência de sistema de aquisição dinâmico\n9 - LOCAL DA EXECUÇÃO DO CONTRATO\nLOCAL DA EXECUÇÃO DO CONTRATO (PROCEDIMENTO)\nPaís: Portugal\nNUT III: PT184\nLocalidade: Vila Nova de São bento\nDistrito: Beja\nConcelho: Serpa\nFreguesia: União das Freguesias de Vila Nova de São Bento e Vale de Vargo\n10 - PRAZO DE EXECUÇÃO DO CONTRATO\nPrazo de execução do contrato: 5 MESES\nPrevisão de renovações: Não\n11 - FUNDOS EU\nTêm fundos EU? Não\n12 - DOCUMENTOS DE HABILITAÇÃO\nHabilitação para o exercício da atividade profissional: Sim\nTipo: Alvará\nDescrição: Alvará de Empreiteiro de Obras Públicas\n13 - CONDIÇÕES DE APRESENTAÇÃO\nPlataforma eletrónica utilizada pela entidade adjudicante: VORTAL\nURL para Apresentação: https://community.vortal.biz/\nAdmissibilidade da apresentação de propostas variantes: Não autorizado\nPrazo para apresentação das propostas: 26-01-2026 17:00\nPrazo durante o qual os concorrentes são obrigados a manter as respetivas propostas: 66 dias a contar do termo do prazo para a apresentação das propostas\nIndicação de Subcontratação na Proposta: A parte do contrato que o proponente tenciona subcontratar\n14 - PRESTAÇÃO DE CAUÇÃO\nPrestação de caução: Sim\nPercentagem: 5%\nDescrição da Garantia Exigida: Garantia Bancária/Seguro caução\n15 - FORNECIMENTO DAS PEÇAS DO CONCURSO, APRESENTAÇÃO DE PEDIDOS DE PARTICIPAÇÃO E APRESENTAÇÃO DAS PROPOSTAS\nLink para acesso às peças do concurso (URL): https://community.vortal.biz/\n20 - OUTROS REQUISITOS\nInformação sobre contratos reservados. Aplica-se a contratos reservados (54º-A)? Não\n21 - CRITÉRIO DE ADJUDICAÇÃO\nMultifator: Sim\nFator: \nNome: Preço\nPonderação: 70%\nSubfatores: Não\nFator: \nNome: Outros\nOutro Nome: Valia Técnica\nPonderação: 30%\nSubfatores: Não\n24 - CONDIÇÕES DO CONTRATO\nFaturação Eletrónica: Permitido\n25 - COMPRA PÚBLICA ESTRATÉGICA\nCompra Pública Estratégica: Inexistência de contratação pública estratégica\n26 - INFORMAÇÕES ADICIONAIS\nContrato adequado para PME: Sim\nCobertura ACP (Acordo dos Contratos Públicos da Organização Mundial do Comércio): Não\n27 - IDENTIFICAÇÃO E CONTACTOS DO ÓRGÃO DE RECURSOS ADMINISTRATIVOS\nDesignação: Municipio de Serpa\nEndereço: Praça da República\nCódigo postal: 7830-320\nLocalidade: serpa\nEndereço eletrónico: geral@cm-serpa.pt\n28 - IDENTIFICAÇÃO DO(S) AUTOR(ES) DE ANÚNCIO\nNome: Francisco Picareta\nCargo: Presidente de Câmara\n419930986",
    "nipc": "501112049",
    "distrito": "Beja",
    "concelho": "Serpa",
    "freguesia": "União das Freguesias de Vila Nova de São Bento e Vale de Vargo",
    "site": "https://www.cm-serpa.pt",
    "email": "geral@cm-serpa.pt",
    "designacao_contrato": "Empreitada de Alteração e Ampliação do Edifício do Centro de Saúde de Vila Nova de S. Bento.",
    "descricao": "Empreitada de Alteração e Ampliação do Edifício do Centro de Saúde de Vila Nova de S. Bento.",
    "preco_base": "698.797,13 EUR",
    "prazo_execucao": "5 MESES",
    "prazo_apresentacao_propostas": "26-01-2026 17:00",
    "fundos_eu": "Não",
    "plataforma_eletronica": "VORTAL",
    "url_procedimento": "https://community.vortal.biz/",
    "autor_nome": "Francisco Picareta",
    "autor_cargo": "Presidente de Câmara"
  },
  {
    "numero_procedimento": "N/A",
    "entidade": "AnÃºncio de procedimento  n.Âº 396/2026  -  DiÃ¡rio da RepÃºblica n.Âº 6/2026, SÃ©rie II de 2026-01-09",
    "link": "https://diariodarepublica.pt/dr/detalhe/contrato-publico/396-1003372801"
  },
  {
    "numero_procedimento": "N/A",
    "entidade": "Unidade Local de Saúde de Lisboa Ocidental, EPE",
    "link": "https://diariodarepublica.pt/dr/detalhe/contrato-publico/398-1003372802",
    "detalhes_completos": "1 - IDENTIFICAÇÃO E CONTACTOS DA ENTIDADE ADJUDICANTE\nDesignação da entidade adjudicante: Unidade Local de Saúde de Lisboa Ocidental, EPE\nNIPC: 507618319\nEndereço: Santa Maria de Belém  Estrada do Forte do Alto do Duque\nCódigo postal: 1449-005\nLocalidade: Lisboa\nPaís: Portugal\nNUT III: PT170\nDistrito: Lisboa\nConcelho: Lisboa\nFreguesia: Todas\nTelefone: 210431000\nFax: 210431642\nEndereço da Entidade (URL): www.chlo.min-saude.pt/\nEndereço Eletrónico: comprasgeral@ulslo.min-saude.pt\neDelivery Gateway (URL): https://community.vortal.biz/public/\nFunção da Organização: Adquirente\nNorma jurídica da Entidade Adjudicante: Organismo de direito público\nÁrea de atividade da Autoridade Adjudicante: Saúde\n2 - JORNAL OFICIAL DA UNIÃO EUROPEIA\nO procedimento a que este anúncio diz respeito também é publicitado no Jornal Oficial da União Europeia? Sim\n3 - AVISO\nModelo de Anúncio: Concurso público\nData de Envio do Anúncio: 07-01-2026\n5 - PROCESSO\nTipo de Procedimento: Concurso público\nPreço base do procedimento: Sim\nValor do preço base do procedimento: 248.166,00 EUR\nProcedimento com lotes? Não\n6 - OBJETO DO CONTRATO\nNúmero de referência interna: 147001026\nDesignação do contrato: Prestação de serviços de interrupção voluntária da gravidez na ULSLO, E.P.E. em 2026\nDescrição: Prestação de serviços de interrupção voluntária da gravidez na ULSLO, E.P.E. em 2026\nOpções: Não\nTipo de Contrato Principal: Aquisição de Serviços\nTipo de Contrato: Aquisição de Serviços\nClassificação CPV (Vocabulário Comum para os Contratos Públicos)\nObjeto principal\nVocabulário Principal: 85111320\nPreço base s/IVA: 248.166,00 EUR\n7 - INDICAÇÕES ADICIONAIS\nO contrato envolve aquisição conjunta (satisfação de várias entidades)? Não\nO contrato é adjudicado por uma central de compras? Não\n8 - TÉCNICAS\nO concurso destina-se à celebração de um acordo-quadro? Inexistência de acordo-quadro\nÉ utilizado um leilão eletrónico? Não\nÉ adotada uma fase de negociação? Não\nSistema de Aquisição Dinâmico: Inexistência de sistema de aquisição dinâmico\n9 - LOCAL DA EXECUÇÃO DO CONTRATO\nLOCAL DA EXECUÇÃO DO CONTRATO (PROCEDIMENTO)\nPaís: Portugal\nNUT III: PT170\nLocalidade: Lisboa\nDistrito: Lisboa\nConcelho: Lisboa\nFreguesia: Todas\n10 - PRAZO DE EXECUÇÃO DO CONTRATO\nPrazo de execução do contrato: 12 MESES\nPrevisão de renovações: Não\n11 - FUNDOS EU\nTêm fundos EU? Não\n12 - DOCUMENTOS DE HABILITAÇÃO\nHabilitação para o exercício da atividade profissional: Não\n13 - CONDIÇÕES DE APRESENTAÇÃO\nPlataforma eletrónica utilizada pela entidade adjudicante: VORTAL\nURL para Apresentação: https://community.vortal.biz/public/\nAdmissibilidade da apresentação de propostas variantes: Não autorizado\nPrazo para apresentação das propostas: 12-02-2026 17:00\nPrazo durante o qual os concorrentes são obrigados a manter as respetivas propostas: 66 dias a contar do termo do prazo para a apresentação das propostas\nApresentação de Catálogo Eletrónico: Não autorizado\nIndicação de Subcontratação na Proposta: Inexistência de indicação de subcontratação\n14 - PRESTAÇÃO DE CAUÇÃO\nPrestação de caução: Não\n15 - FORNECIMENTO DAS PEÇAS DO CONCURSO, APRESENTAÇÃO DE PEDIDOS DE PARTICIPAÇÃO E APRESENTAÇÃO DAS PROPOSTAS\nLink para acesso às peças do concurso (URL): https://community.vortal.biz/Public/public-tender-documents/Rnp2MGNtZzVKbXdjVDdvdmFWY3Y5Y1JuTlVHbi9WQXE2NVppTkZzdStWY1ZqL0ZwVlRjbjRhbGk4S1QybFVRamNhV0R5S3JpTEJNNFc5SGJQMm9zblE9PXF0RWFQ\n20 - OUTROS REQUISITOS\nInformação sobre contratos reservados. Aplica-se a contratos reservados (54º-A)? Não\n21 - CRITÉRIO DE ADJUDICAÇÃO\nMultifator: Não\nMonofator:\nNome: Preço\n24 - CONDIÇÕES DO CONTRATO\nFaturação Eletrónica: Permitido\nObrigação de Subcontratação:\nCódigo da Obrigação de Subcontratação: Não é aplicável nenhuma obrigação de subcontratação.\n25 - COMPRA PÚBLICA ESTRATÉGICA\nCompra Pública Estratégica: Inexistência de contratação pública estratégica\n26 - INFORMAÇÕES ADICIONAIS\nContrato adequado para PME: Sim\nCobertura ACP (Acordo dos Contratos Públicos da Organização Mundial do Comércio): Não\n27 - IDENTIFICAÇÃO E CONTACTOS DO ÓRGÃO DE RECURSOS ADMINISTRATIVOS\nDesignação: Serviço de Gestão de Compras\nEndereço: Estrada do Forte do Alto  do Duque\nCódigo postal: 1449-005\nLocalidade: Lisboa\nTelefone: +351 210431000\nFax: +351 210431639\nEndereço eletrónico: compras.adm.hot.ps.inv@ulslo.min-saude.pt\n28 - IDENTIFICAÇÃO DO(S) AUTOR(ES) DE ANÚNCIO\nNome: Salomé Pedro\nCargo: Técnica Superior\n419947178",
    "nipc": "507618319",
    "distrito": "Lisboa",
    "concelho": "Lisboa",
    "freguesia": "Todas",
    "site": "www.chlo.min-saude.pt/",
    "email": "comprasgeral@ulslo.min-saude.pt",
    "designacao_contrato": "Prestação de serviços de interrupção voluntária da gravidez na ULSLO, E.P.E. em 2026",
    "descricao": "Prestação de serviços de interrupção voluntária da gravidez na ULSLO, E.P.E. em 2026",
    "preco_base": "248.166,00 EUR",
    "prazo_execucao": "12 MESES",
    "prazo_apresentacao_propostas": "12-02-2026 17:00",
    "fundos_eu": "Não",
    "plataforma_eletronica": "VORTAL",
    "url_procedimento": "https://community.vortal.biz/public/",
    "autor_nome": "Salomé Pedro",
    "autor_cargo": "Técnica Superior"
  },
  {
    "numero_procedimento": "N/A",
    "entidade": "AnÃºncio de procedimento  n.Âº 400/2026  -  DiÃ¡rio da RepÃºblica n.Âº 6/2026, SÃ©rie II de 2026-01-09",
    "link": "https://diariodarepublica.pt/dr/detalhe/contrato-publico/400-1003372803"
  },
  {
    "numero_procedimento": "N/A",
    "entidade": "Unidade Local de Saúde da Lezíria, EPE",
    "link": "https://diariodarepublica.pt/dr/detalhe/contrato-publico/402-1003372804",
    "detalhes_completos": "1 - IDENTIFICAÇÃO E CONTACTOS DA ENTIDADE ADJUDICANTE\nDesignação da entidade adjudicante: Unidade Local de Saúde da Lezíria, EPE\nNIPC: 506361462\nEndereço: Av. Bernardo Santareno S/N\nCódigo postal: 2005-177\nLocalidade: Santarém\nPaís: Portugal\nNUT III: PT185\nDistrito: Santarém\nConcelho: Santarém\nFreguesia: União de Freguesias da Cidade de Santarém\nTelefone: 243300200\nFax: 243370220\nEndereço da Entidade (URL): www.hds.min-saude.pt\nEndereço Eletrónico: hdsca@hds.min-saude.pt\neDelivery Gateway (URL): https://community.vortal.biz/public/\nFunção da Organização: Adquirente\nNorma jurídica da Entidade Adjudicante: Organismo de direito público\nÁrea de atividade da Autoridade Adjudicante: Saúde\n2 - JORNAL OFICIAL DA UNIÃO EUROPEIA\nO procedimento a que este anúncio diz respeito também é publicitado no Jornal Oficial da União Europeia? Sim\n3 - AVISO\nModelo de Anúncio: Concurso público\nData de Envio do Anúncio: 07-01-2026\n5 - PROCESSO\nTipo de Procedimento: Concurso público\nPreço base do procedimento: Sim\nValor do preço base do procedimento: 400.000,00 EUR\nProcedimento com lotes? Não\n6 - OBJETO DO CONTRATO\nNúmero de referência interna: 170024/2025\nDesignação do contrato: Aquisição e Instalação de Sistema de Mamografia Digital\nDescrição: 170024/2025 - Aquisição e Instalação de Sistema de Mamografia Digital\nOpções: Não\nTipo de Contrato Principal: Aquisição de Bens Móveis\nTipo de Contrato: Aquisição de Bens Móveis\nClassificação CPV (Vocabulário Comum para os Contratos Públicos)\nObjeto principal\nVocabulário Principal: 33111650\nPreço base s/IVA: 400.000,00 EUR\n7 - INDICAÇÕES ADICIONAIS\nO contrato envolve aquisição conjunta (satisfação de várias entidades)? Não\nO contrato é adjudicado por uma central de compras? Não\n8 - TÉCNICAS\nO concurso destina-se à celebração de um acordo-quadro? Inexistência de acordo-quadro\nÉ utilizado um leilão eletrónico? Não\nÉ adotada uma fase de negociação? Não\nSistema de Aquisição Dinâmico: Inexistência de sistema de aquisição dinâmico\n9 - LOCAL DA EXECUÇÃO DO CONTRATO\nLOCAL DA EXECUÇÃO DO CONTRATO (PROCEDIMENTO)\nPaís: Portugal\nNUT III: PT185\nLocalidade: Santarém\nDistrito: Santarém\nConcelho: Santarém\nFreguesia: União de Freguesias da Cidade de Santarém\n10 - PRAZO DE EXECUÇÃO DO CONTRATO\nPrazo de execução do contrato: 12 MESES\nPrevisão de renovações: Não\n11 - FUNDOS EU\nTêm fundos EU? Não\n12 - DOCUMENTOS DE HABILITAÇÃO\nHabilitação para o exercício da atividade profissional: Não\n13 - CONDIÇÕES DE APRESENTAÇÃO\nPlataforma eletrónica utilizada pela entidade adjudicante: VORTAL\nURL para Apresentação: https://community.vortal.biz/public/\nAdmissibilidade da apresentação de propostas variantes: Não autorizado\nPrazo para apresentação das propostas: 07-02-2026 23:59\nPrazo durante o qual os concorrentes são obrigados a manter as respetivas propostas: 66 dias a contar do termo do prazo para a apresentação das propostas\nApresentação de Catálogo Eletrónico: Permitido\nIndicação de Subcontratação na Proposta: Inexistência de indicação de subcontratação\n14 - PRESTAÇÃO DE CAUÇÃO\nPrestação de caução: Não\n15 - FORNECIMENTO DAS PEÇAS DO CONCURSO, APRESENTAÇÃO DE PEDIDOS DE PARTICIPAÇÃO E APRESENTAÇÃO DAS PROPOSTAS\nLink para acesso às peças do concurso (URL): https://community.vortal.biz/Public/public-tender-documents/RWlwc211MytsS2FxOG5JbHR0b3h1c0lEWVJNaTQxODZMUlZnSVhvbFlQTGdaamlwZTJrNVppQm5meUordUp1ZkJkVjdCR0hQa0dJVXhrZEpMRW96M0E9PXNIVSZs\n20 - OUTROS REQUISITOS\nInformação sobre contratos reservados. Aplica-se a contratos reservados (54º-A)? Não\n21 - CRITÉRIO DE ADJUDICAÇÃO\nMultifator: Sim\nFator: \nNome: Preço\nPonderação: 50%\nSubfatores: Não\nFator: \nNome: Qualidade\nPonderação: 45%\nSubfatores: Não\nFator: \nNome: Qualidade\nPonderação: 5%\nSubfatores: Não\n24 - CONDIÇÕES DO CONTRATO\nFaturação Eletrónica: Permitido\nObrigação de Subcontratação:\nCódigo da Obrigação de Subcontratação: Não é aplicável nenhuma obrigação de subcontratação.\n25 - COMPRA PÚBLICA ESTRATÉGICA\nCompra Pública Estratégica: Inexistência de contratação pública estratégica\n26 - INFORMAÇÕES ADICIONAIS\nContrato adequado para PME: Sim\nCobertura ACP (Acordo dos Contratos Públicos da Organização Mundial do Comércio): Não\n27 - IDENTIFICAÇÃO E CONTACTOS DO ÓRGÃO DE RECURSOS ADMINISTRATIVOS\nDesignação: Conselho de Administração da ULSL\nEndereço: Avenida Bernardo santareno S/N\nCódigo postal: 2005-177\nLocalidade: Santarém\nTelefone: +351 243300200\nFax: +351 243300224\nEndereço eletrónico: ca@ulsleziria.min-saide.pt\n28 - IDENTIFICAÇÃO DO(S) AUTOR(ES) DE ANÚNCIO\nNome: Pedro Manuel Dias de Figueiredo Pereira Marques\nCargo: Presidente do Conselho de Administração da  ULSL\n419947291",
    "nipc": "506361462",
    "distrito": "Santarém",
    "concelho": "Santarém",
    "freguesia": "União de Freguesias da Cidade de Santarém",
    "site": "www.hds.min-saude.pt",
    "email": "hdsca@hds.min-saude.pt",
    "designacao_contrato": "Aquisição e Instalação de Sistema de Mamografia Digital",
    "descricao": "170024/2025 - Aquisição e Instalação de Sistema de Mamografia Digital",
    "preco_base": "400.000,00 EUR",
    "prazo_execucao": "12 MESES",
    "prazo_apresentacao_propostas": "07-02-2026 23:59",
    "fundos_eu": "Não",
    "plataforma_eletronica": "VORTAL",
    "url_procedimento": "https://community.vortal.biz/public/",
    "autor_nome": "Pedro Manuel Dias de Figueiredo Pereira Marques",
    "autor_cargo": "Presidente do Conselho de Administração da ULSL"
  },
  {
    "numero_procedimento": "N/A",
    "entidade": "AnÃºncio de procedimento  n.Âº 404/2026  -  DiÃ¡rio da RepÃºblica n.Âº 6/2026, SÃ©rie II de 2026-01-09",
    "link": "https://diariodarepublica.pt/dr/detalhe/contrato-publico/404-1003372805"
  },
  {
    "numero_procedimento": "N/A",
    "entidade": "VALORLIS - Valorização e Tratamento de Resíduos Sólidos, SA",
    "link": "https://diariodarepublica.pt/dr/detalhe/contrato-publico/406-1003372806",
    "detalhes_completos": "1 - IDENTIFICAÇÃO E CONTACTOS DA ENTIDADE ADJUDICANTE\nDesignação da entidade adjudicante: VALORLIS - Valorização e Tratamento de Resíduos Sólidos, SA\nNIPC: 503811866\nEndereço: Aterro Sanitário de Leiria - Quinta do Banco\nCódigo postal: 2416-902\nLocalidade: Leiria\nPaís: Portugal\nNUT III: PT16F\nDistrito: Leiria\nConcelho: Leiria\nFreguesia: União das Freguesias de Parceiros e Azoia\nTelefone: 244575540\nFax: 244575544\nEndereço da Entidade (URL): www.valorlis.pt\nEndereço Eletrónico: valorlis@valorlis.pt\neDelivery Gateway (URL): https://community.vortal.biz/public/\nFunção da Organização: Adquirente\nNorma jurídica da Entidade Adjudicante: Organização que adjudica um contrato subvencionado por uma autoridade local\nÁrea de atividade da Autoridade Adjudicante: Proteção ambiental\n2 - JORNAL OFICIAL DA UNIÃO EUROPEIA\nO procedimento a que este anúncio diz respeito também é publicitado no Jornal Oficial da União Europeia? Sim\n3 - AVISO\nModelo de Anúncio: Concurso público\nData de Envio do Anúncio: 07-01-2026\n5 - PROCESSO\nTipo de Procedimento: Concurso público\nPreço base do procedimento: Sim\nValor do preço base do procedimento: 446.194,00 EUR\nProcedimento com lotes? Sim\nNº Máx. de Lotes Autorizado: 2\nNúmero máximo de lotes que podem ser adjudicados a um concorrente: 2\n6 - OBJETO DO CONTRATO\nNúmero de referência interna: 1/2026\nDesignação do contrato: Fornecimento de 2 Pás Carregadoras de Rodas\nDescrição: Fornecimento de 2 pás carregadoras de rodas nos termos, condições e especificações estabelecidas nas peças de concurso\nOpções: Não\nTipo de Contrato Principal: Aquisição de Bens Móveis\nTipo de Contrato: Aquisição de Bens Móveis\nClassificação CPV (Vocabulário Comum para os Contratos Públicos)\nObjeto principal\nVocabulário Principal: 43252000\nPreço base s/IVA: 446.194,00 EUR\nLotes: \nNº: LOT-0002\nDescrição do Lote: Lote 2\nPreço base s/IVA: 223.097,00 EUR\nClassificação CPV (Vocabulário Comum para os Contratos Públicos)\nObjeto principal\nVocabulário Principal: 43252000\nNº: LOT-0001\nDescrição do Lote: Lote 1\nPreço base s/IVA: 223.097,00 EUR\nClassificação CPV (Vocabulário Comum para os Contratos Públicos)\nObjeto principal\nVocabulário Principal: 43252000\n7 - INDICAÇÕES ADICIONAIS\nO contrato envolve aquisição conjunta (satisfação de várias entidades)? Não\nO contrato é adjudicado por uma central de compras? Não\n8 - TÉCNICAS\nO concurso destina-se à celebração de um acordo-quadro? Inexistência de acordo-quadro\nÉ utilizado um leilão eletrónico? Não\nÉ adotada uma fase de negociação? Não\nSistema de Aquisição Dinâmico: Inexistência de sistema de aquisição dinâmico\n9 - LOCAL DA EXECUÇÃO DO CONTRATO\nLOCAL DA EXECUÇÃO DO CONTRATO (PROCEDIMENTO)\nPaís: Portugal\nNUT III: PTZZZ\nLocalidade: PORTUGAL\nDistrito: Leiria\nConcelho: Leiria\nFreguesia: União das Freguesias de Parceiros e Azoia\nLOCAL DA EXECUÇÃO DO CONTRATO (LOTE)\nIdentificador do Lote: LOT-0001; LOT-0002\nPaís: Portugal\nNUT III: PT16F\nLocalidade: PORTUGAL\nDistrito: Leiria\nConcelho: Leiria\nFreguesia: União das Freguesias de Parceiros e Azoia\n10 - PRAZO DE EXECUÇÃO DO CONTRATO\nIdentificador do Lote: LOT-0001; LOT-0002\nPrazo de execução do contrato: 90 DIAS\nPrevisão de renovações: Não\n11 - FUNDOS EU\nIdentificador do Lote: LOT-0001; LOT-0002\nTêm fundos EU? Não\n12 - DOCUMENTOS DE HABILITAÇÃO\nHabilitação para o exercício da atividade profissional: Sim\nTipo: Outros\nDescrição - Outros: Conforme peças do procedimento\nDescrição: Conforme Peças do Procedimento\n13 - CONDIÇÕES DE APRESENTAÇÃO\nPlataforma eletrónica utilizada pela entidade adjudicante: VORTAL\nURL para Apresentação: https://community.vortal.biz/public/\nAdmissibilidade da apresentação de propostas variantes: Não autorizado\nPrazo para apresentação das propostas: 06-02-2026 17:00\nPrazo durante o qual os concorrentes são obrigados a manter as respetivas propostas: 66 dias a contar do termo do prazo para a apresentação das propostas\nApresentação de Catálogo Eletrónico: Necessário\nIndicação de Subcontratação na Proposta: Inexistência de indicação de subcontratação\n14 - PRESTAÇÃO DE CAUÇÃO\nPrestação de caução: Sim\nPercentagem: 5%\nDescrição da Garantia Exigida: Conforme Peças do Procedimento\n15 - FORNECIMENTO DAS PEÇAS DO CONCURSO, APRESENTAÇÃO DE PEDIDOS DE PARTICIPAÇÃO E APRESENTAÇÃO DAS PROPOSTAS\nLink para acesso às peças do concurso (URL): https://community.vortal.biz/Public/public-tender-documents/ZWpxRXBxUVBFWmhTN0kxTHF2THFlU2Zsdzl3MnFNdE95aVlXSFU4U0Y2aGprUmF3NVgxRU82d0lSc3RBRFV0Nm1ldURZa0RqcWptd05rbmZrNUg4ZUE9PV82IVAy\n20 - OUTROS REQUISITOS\nIdentificador do Lote: LOT-0001; LOT-0002\nInformação sobre contratos reservados. Aplica-se a contratos reservados (54º-A)? Não\n21 - CRITÉRIO DE ADJUDICAÇÃO\nO Critério de adjudicação é diferenciado por lote? Não\nMultifator: Não\nMonofator:\nNome: Preço\n24 - CONDIÇÕES DO CONTRATO\nIdentificador do Lote: LOT-0001; LOT-0002\nFaturação Eletrónica: Permitido\nObrigação de Subcontratação:\nCódigo da Obrigação de Subcontratação: Não é aplicável nenhuma obrigação de subcontratação.\n25 - COMPRA PÚBLICA ESTRATÉGICA\nCompra Pública Estratégica: Inexistência de contratação pública estratégica\n26 - INFORMAÇÕES ADICIONAIS\nIdentificador do Lote: LOT-0001; LOT-0002\nContrato adequado para PME: Sim\nCobertura ACP (Acordo dos Contratos Públicos da Organização Mundial do Comércio): Não\n27 - IDENTIFICAÇÃO E CONTACTOS DO ÓRGÃO DE RECURSOS ADMINISTRATIVOS\nDesignação: Conselho de Administração da Valorlis\nEndereço: Aterro Sanitário de Leiria - Quinta do Banco - Parceiros - Apartado 157\nCódigo postal: 2416-902\nLocalidade: Leiria\nTelefone: +351 244575540\nFax: +351 244575540\nEndereço eletrónico: geral@valorlis.pt\n28 - IDENTIFICAÇÃO DO(S) AUTOR(ES) DE ANÚNCIO\nNome: Marta Loia Guerreiro\nCargo: Administradora-Delegada\n419947327",
    "nipc": "503811866",
    "distrito": "Leiria",
    "concelho": "Leiria",
    "freguesia": "União das Freguesias de Parceiros e Azoia",
    "site": "www.valorlis.pt",
    "email": "valorlis@valorlis.pt",
    "designacao_contrato": "Fornecimento de 2 Pás Carregadoras de Rodas",
    "descricao": "Fornecimento de 2 pás carregadoras de rodas nos termos, condições e especificações estabelecidas nas peças de concurso",
    "preco_base": "446.194,00 EUR",
    "prazo_execucao": "90 DIAS",
    "prazo_apresentacao_propostas": "06-02-2026 17:00",
    "fundos_eu": "Não",
    "plataforma_eletronica": "VORTAL",
    "url_procedimento": "https://community.vortal.biz/public/",
    "autor_nome": "Marta Loia Guerreiro",
    "autor_cargo": "Administradora-Delegada"
  },
  {
    "numero_procedimento": "N/A",
    "entidade": "BIKINNOV - Bike Value Innovation Center - Association",
    "link": "https://diariodarepublica.pt/dr/detalhe/contrato-publico/408-1003372807",
    "detalhes_completos": "1 - IDENTIFICAÇÃO E CONTACTOS DA ENTIDADE ADJUDICANTE\nDesignação da entidade adjudicante: BIKINNOV - Bike Value Innovation Center - Association\nNIPC: 516839268\nServiço/Órgão/Pessoa de contacto: BIKiNNOV\nEndereço: Rua da Indústria, 369, Covão, 3750-792 Águeda\nCódigo postal: 3750-792\nLocalidade: Águeda\nPaís: Portugal\nNUT III: PT16D\nDistrito: Aveiro\nConcelho: Águeda\nFreguesia: Freguesia de Valongo do Vouga\nTelefone: 234248960\nEndereço da Entidade (URL): www.bikinnov.pt\nEndereço Eletrónico: geral@bikinnov.pt\neDelivery Gateway (URL): https://www.acingov.pt\nFunção da Organização: Adquirente\nNorma jurídica da Entidade Adjudicante: Organismo de direito público\nÁrea de atividade da Autoridade Adjudicante: Serviços públicos das administrações públicas\n2 - JORNAL OFICIAL DA UNIÃO EUROPEIA\nO procedimento a que este anúncio diz respeito também é publicitado no Jornal Oficial da União Europeia? Sim\n3 - AVISO\nModelo de Anúncio: Concurso público\nData de Envio do Anúncio: 07-01-2026\n5 - PROCESSO\nTipo de Procedimento: Concurso público\nPreço base do procedimento: Sim\nValor do preço base do procedimento: 480.000,00 EUR\nProcedimento com lotes? Não\n6 - OBJETO DO CONTRATO\nNúmero de referência interna: 107-111-CTI-25\nDesignação do contrato: Eixo Desenvolvimento de Produto - Equipamentos para Avaliação de Rigidez\nDescrição: Eixo Desenvolvimento de Produto - Equipamentos para Avaliação de Rigidez\nOpções: Não\nTipo de Contrato Principal: Aquisição de Bens Móveis\nTipo de Contrato: Aquisição de Bens Móveis\nClassificação CPV (Vocabulário Comum para os Contratos Públicos)\nObjeto principal\nVocabulário Principal: 38900000\nPreço base s/IVA: 480.000,00 EUR\n7 - INDICAÇÕES ADICIONAIS\nO contrato envolve aquisição conjunta (satisfação de várias entidades)? Não\nO contrato é adjudicado por uma central de compras? Não\n8 - TÉCNICAS\nO concurso destina-se à celebração de um acordo-quadro? Inexistência de acordo-quadro\nÉ utilizado um leilão eletrónico? Não\nÉ adotada uma fase de negociação? Não\nSistema de Aquisição Dinâmico: Inexistência de sistema de aquisição dinâmico\n9 - LOCAL DA EXECUÇÃO DO CONTRATO\nLOCAL DA EXECUÇÃO DO CONTRATO (PROCEDIMENTO)\nPaís: Portugal\nNUT III: PT16D\nLocalidade: Freguesia de Valongo do Vouga\nDistrito: Aveiro\nConcelho: Águeda\nFreguesia: Freguesia de Valongo do Vouga\n10 - PRAZO DE EXECUÇÃO DO CONTRATO\nPrazo de execução do contrato: 6 MESES\nPrevisão de renovações: Não\n11 - FUNDOS EU\nTêm fundos EU? Sim\n12 - DOCUMENTOS DE HABILITAÇÃO\nHabilitação para o exercício da atividade profissional: Não\n13 - CONDIÇÕES DE APRESENTAÇÃO\nPlataforma eletrónica utilizada pela entidade adjudicante: ACIN\nURL para Apresentação: https://www.acingov.pt\nAdmissibilidade da apresentação de propostas variantes: Não autorizado\nPrazo para apresentação das propostas: 06-02-2026 17:00\nPrazo durante o qual os concorrentes são obrigados a manter as respetivas propostas: 90 dias a contar do termo do prazo para a apresentação das propostas\nApresentação de Catálogo Eletrónico: Permitido\nIndicação de Subcontratação na Proposta: Inexistência de indicação de subcontratação\n14 - PRESTAÇÃO DE CAUÇÃO\nPrestação de caução: Não\n15 - FORNECIMENTO DAS PEÇAS DO CONCURSO, APRESENTAÇÃO DE PEDIDOS DE PARTICIPAÇÃO E APRESENTAÇÃO DAS PROPOSTAS\nLink para acesso às peças do concurso (URL): https://www.acingov.pt/acingovprod/2/zonaPublica/zona_publica_c/donwloadProcedurePiece/OTk4MTcw\n20 - OUTROS REQUISITOS\nInformação sobre contratos reservados. Aplica-se a contratos reservados (54º-A)? Não\n21 - CRITÉRIO DE ADJUDICAÇÃO\nMultifator: Sim\nFator: \nNome: Preço\nPonderação: 35%\nSubfatores: Não\nFator: \nNome: Outros\nOutro Nome: Qualidade da proposta\nPonderação: 30%\nSubfatores: Sim\nSubfatores: \nNome: Flexibilidade do equipamento de caracterização de rigidez\nPonderação : 40%; \nNome: Adequabilidade do sistema de caracterização de rigidez face aos objetivos do BIKiNNOV\nPonderação : 25%; \nNome: Base de dados com valores padrão\nPonderação : 35%; \nFator: \nNome: Outros\nOutro Nome: Relevância no setor\nPonderação: 25%\nSubfatores: Não\nFator: \nNome: Outros\nOutro Nome: Prazo de Entrega\nPonderação: 10%\nSubfatores: Não\n24 - CONDIÇÕES DO CONTRATO\nFaturação Eletrónica: Permitido\nObrigação de Subcontratação:\nCódigo da Obrigação de Subcontratação: Não é aplicável nenhuma obrigação de subcontratação.\n25 - COMPRA PÚBLICA ESTRATÉGICA\nCompra Pública Estratégica: Inexistência de contratação pública estratégica\n26 - INFORMAÇÕES ADICIONAIS\nContrato adequado para PME: Sim\nCobertura ACP (Acordo dos Contratos Públicos da Organização Mundial do Comércio): Não\n27 - IDENTIFICAÇÃO E CONTACTOS DO ÓRGÃO DE RECURSOS ADMINISTRATIVOS\nDesignação: BIKiNNOV\nEndereço: Rua da Indústria, 369, Covão, 3750-792 Águeda\nCódigo postal: 3750-792\nLocalidade: Águeda\nTelefone: 234248960\nFax: \nEndereço eletrónico: geral@bikinnov.pt\nPrazo de interposição do recurso: 10 dias\n28 - IDENTIFICAÇÃO DO(S) AUTOR(ES) DE ANÚNCIO\nNome: Inês Tavares\nCargo: Gestora Financeira de Projetos\n419947348",
    "nipc": "516839268",
    "distrito": "Aveiro",
    "concelho": "Águeda",
    "freguesia": "Freguesia de Valongo do Vouga",
    "site": "www.bikinnov.pt",
    "email": "geral@bikinnov.pt",
    "designacao_contrato": "Eixo Desenvolvimento de Produto - Equipamentos para Avaliação de Rigidez",
    "descricao": "Eixo Desenvolvimento de Produto - Equipamentos para Avaliação de Rigidez",
    "preco_base": "480.000,00 EUR",
    "prazo_execucao": "6 MESES",
    "prazo_apresentacao_propostas": "06-02-2026 17:00",
    "fundos_eu": "Sim",
    "plataforma_eletronica": "ACIN",
    "url_procedimento": "https://www.acingov.pt",
    "autor_nome": "Inês Tavares",
    "autor_cargo": "Gestora Financeira de Projetos"
  },
  {
    "numero_procedimento": "N/A",
    "entidade": "AnÃºncio de procedimento  n.Âº 410/2026  -  DiÃ¡rio da RepÃºblica n.Âº 6/2026, SÃ©rie II de 2026-01-09",
    "link": "https://diariodarepublica.pt/dr/detalhe/contrato-publico/410-1003372808"
  },
  {
    "numero_procedimento": "N/A",
    "entidade": "Unidade Local de Saúde do Alto Minho, EPE",
    "link": "https://diariodarepublica.pt/dr/detalhe/contrato-publico/412-1003372809",
    "detalhes_completos": "1 - IDENTIFICAÇÃO E CONTACTOS DA ENTIDADE ADJUDICANTE\nDesignação da entidade adjudicante: Unidade Local de Saúde do Alto Minho, EPE\nNIPC: 508786193\nEndereço: Estrada de Santa Luzia, Viana do Castelo\nCódigo postal: 4904-858\nLocalidade: Viana do Castelo\nPaís: Portugal\nNUT III: PT111\nDistrito: Viana do Castelo\nConcelho: Viana do Castelo\nFreguesia: União das Freguesias de Viana do Castelo (Santa Maria Maior e Monserrate) e Meadela\nTelefone: 258802381\nFax: 258802389\nEndereço da Entidade (URL): https://www.ulsam.min-saude.pt\nEndereço Eletrónico: sourcing@ulsam.min-saude.pt\neDelivery Gateway (URL): https://community.vortal.biz/public/\nFunção da Organização: Adquirente\nNorma jurídica da Entidade Adjudicante: Organismo de direito público\nÁrea de atividade da Autoridade Adjudicante: Saúde\n2 - JORNAL OFICIAL DA UNIÃO EUROPEIA\nO procedimento a que este anúncio diz respeito também é publicitado no Jornal Oficial da União Europeia? Sim\n3 - AVISO\nModelo de Anúncio: Concurso público\nData de Envio do Anúncio: 07-01-2026\n5 - PROCESSO\nTipo de Procedimento: Concurso público\nPreço base do procedimento: Sim\nValor do preço base do procedimento: 249.750,00 EUR\nProcedimento com lotes? Não\n6 - OBJETO DO CONTRATO\nNúmero de referência interna: 01/85/2026\nDesignação do contrato: Lote de Sessões de Cirurgia Plástica e Reconstrutiva na ULSAM, EPE\nDescrição: Lote de Sessões de Cirurgia Plástica e Reconstrutiva na ULSAM, EPE\nOpções: Não\nTipo de Contrato Principal: Aquisição de Serviços\nTipo de Contrato: Aquisição de Serviços\nClassificação CPV (Vocabulário Comum para os Contratos Públicos)\nObjeto principal\nVocabulário Principal: 85120000\nPreço base s/IVA: 249.750,00 EUR\n7 - INDICAÇÕES ADICIONAIS\nO contrato envolve aquisição conjunta (satisfação de várias entidades)? Não\nO contrato é adjudicado por uma central de compras? Não\n8 - TÉCNICAS\nO concurso destina-se à celebração de um acordo-quadro? Inexistência de acordo-quadro\nÉ utilizado um leilão eletrónico? Não\nÉ adotada uma fase de negociação? Não\nSistema de Aquisição Dinâmico: Inexistência de sistema de aquisição dinâmico\n9 - LOCAL DA EXECUÇÃO DO CONTRATO\nLOCAL DA EXECUÇÃO DO CONTRATO (PROCEDIMENTO)\nPaís: Portugal\nNUT III: PT111\nLocalidade: Viana do Castelo\nDistrito: Viana do Castelo\nConcelho: Viana do Castelo\nFreguesia: União das Freguesias de Viana do Castelo (Santa Maria Maior e Monserrate) e Meadela\n10 - PRAZO DE EXECUÇÃO DO CONTRATO\nPrazo de execução do contrato: 3 ANOS\nPrevisão de renovações: Não\n11 - FUNDOS EU\nTêm fundos EU? Não\n12 - DOCUMENTOS DE HABILITAÇÃO\nHabilitação para o exercício da atividade profissional: Não\n13 - CONDIÇÕES DE APRESENTAÇÃO\nPlataforma eletrónica utilizada pela entidade adjudicante: VORTAL\nURL para Apresentação: https://community.vortal.biz/public/\nAdmissibilidade da apresentação de propostas variantes: Não autorizado\nPrazo para apresentação das propostas: 05-02-2026 18:00\nPrazo durante o qual os concorrentes são obrigados a manter as respetivas propostas: 120 dias a contar do termo do prazo para a apresentação das propostas\nApresentação de Catálogo Eletrónico: Permitido\nIndicação de Subcontratação na Proposta: Inexistência de indicação de subcontratação\n14 - PRESTAÇÃO DE CAUÇÃO\nPrestação de caução: Não\n15 - FORNECIMENTO DAS PEÇAS DO CONCURSO, APRESENTAÇÃO DE PEDIDOS DE PARTICIPAÇÃO E APRESENTAÇÃO DAS PROPOSTAS\nLink para acesso às peças do concurso (URL): https://community.vortal.biz/Public/public-tender-documents/ZE5sQnM1VEdnNC9FOGkreUYzNzlOZVQvVFp5UmVualdWb0VmMDFVdHgvK3BMcmgzdHdCM09COXRmNnR6eFBZQXZPaXk0VWdLVjdZNWpVK2pBb2RYVGc9PWhPYUcx\n20 - OUTROS REQUISITOS\nInformação sobre contratos reservados. Aplica-se a contratos reservados (54º-A)? Não\n21 - CRITÉRIO DE ADJUDICAÇÃO\nMultifator: Sim\nFator: \nNome: Preço\nPonderação: 10%\nSubfatores: Não\nFator: \nNome: Qualidade\nPonderação: 90%\nSubfatores: Não\n24 - CONDIÇÕES DO CONTRATO\nFaturação Eletrónica: Permitido\nObrigação de Subcontratação:\nCódigo da Obrigação de Subcontratação: Não é aplicável nenhuma obrigação de subcontratação.\n25 - COMPRA PÚBLICA ESTRATÉGICA\nCompra Pública Estratégica: Inexistência de contratação pública estratégica\n26 - INFORMAÇÕES ADICIONAIS\nContrato adequado para PME: Sim\nCobertura ACP (Acordo dos Contratos Públicos da Organização Mundial do Comércio): Não\n27 - IDENTIFICAÇÃO E CONTACTOS DO ÓRGÃO DE RECURSOS ADMINISTRATIVOS\nDesignação: Conselho de Administração da ULSAM, EPE\nEndereço: Estrada de Santa Luzia\nCódigo postal: 4904-858\nLocalidade: Viana do Castelo\nTelefone: +351 258802166\nFax: +351 258802511\nEndereço eletrónico: administracao@ulsam.min-saude.pt\n28 - IDENTIFICAÇÃO DO(S) AUTOR(ES) DE ANÚNCIO\nNome: Ana Filipa Monteiro\nCargo: As. Técnica - Gestão de Compras\n419947370",
    "nipc": "508786193",
    "distrito": "Viana do Castelo",
    "concelho": "Viana do Castelo",
    "freguesia": "União das Freguesias de Viana do Castelo (Santa Maria Maior e Monserrate) e Meadela",
    "site": "https://www.ulsam.min-saude.pt",
    "email": "sourcing@ulsam.min-saude.pt",
    "designacao_contrato": "Lote de Sessões de Cirurgia Plástica e Reconstrutiva na ULSAM, EPE",
    "descricao": "Lote de Sessões de Cirurgia Plástica e Reconstrutiva na ULSAM, EPE",
    "preco_base": "249.750,00 EUR",
    "prazo_execucao": "3 ANOS",
    "prazo_apresentacao_propostas": "05-02-2026 18:00",
    "fundos_eu": "Não",
    "plataforma_eletronica": "VORTAL",
    "url_procedimento": "https://community.vortal.biz/public/",
    "autor_nome": "Ana Filipa Monteiro",
    "autor_cargo": "As. Técnica - Gestão de Compras"
  },
  {
    "numero_procedimento": "N/A",
    "entidade": "Secretaria-Geral do Ministério da Administração Interna",
    "link": "https://diariodarepublica.pt/dr/detalhe/contrato-publico/414-1003372810",
    "detalhes_completos": "Alteração do Anúncio de procedimento n.º 31784/2025, de 2025-12-09, com o ID 419847312\n1 - IDENTIFICAÇÃO E CONTACTOS DA ENTIDADE ADJUDICANTE\nDesignação da entidade adjudicante: Secretaria-Geral do Ministério da Administração Interna\nNIPC: 600014665\nEndereço: Rua São Mamede, 23\nCódigo postal: 1100-523\nLocalidade: Lisboa\nPaís: Portugal\nNUT III: PT170\nDistrito: Lisboa\nConcelho: Lisboa\nFreguesia: Freguesia de Santa Maria Maior - Lisboa\nTelefone: 213409000\nFax: 213409010\nEndereço da Entidade (URL): www.sg.mai.gov.pt/\nEndereço Eletrónico: gab.sec.geral@sg.mai.gov.pt\neDelivery Gateway (URL): https://community.vortal.biz/public/\nFunção da Organização: Adquirente\nNorma jurídica da Entidade Adjudicante: Autoridade da administração central\nÁrea de atividade da Autoridade Adjudicante: Serviços públicos das administrações públicas\n2 - JORNAL OFICIAL DA UNIÃO EUROPEIA\nO procedimento a que este anúncio diz respeito também é publicitado no Jornal Oficial da União Europeia? Sim\n3 - AVISO\nModelo de Anúncio: Concurso público\nData de Envio do Anúncio: 07-01-2026\n5 - PROCESSO\nTipo de Procedimento: Concurso público\nPreço base do procedimento: Sim\nValor do preço base do procedimento: 7.759.250,00 EUR\nProcedimento com lotes? Sim\nNº Máx. de Lotes Autorizado: 9\nNúmero máximo de lotes que podem ser adjudicados a um concorrente: 9\n6 - OBJETO DO CONTRATO\nNúmero de referência interna: Proc.12/DPIE/2025\nDesignação do contrato: Aquisição de computadores de secretária, computadores de elevado desempenho, portáteis e periféricos, para a GNR e PSP, para os anos de 2025 e 2026, no âmbito do DLPIEFSS\nDescrição: Aquisição de computadores de secretária, computadores de elevado desempenho, portáteis e periféricos, para a GNR e PSP, para os anos de 2025 e 2026, no âmbito do DLPIEFSS\nOpções: Não\nTipo de Contrato Principal: Aquisição de Bens Móveis\nTipo de Contrato: Aquisição de Bens Móveis\nClassificação CPV (Vocabulário Comum para os Contratos Públicos)\nObjeto principal\nVocabulário Principal: 30200000\nPreço base s/IVA: 7.759.250,00 EUR\nLotes: \nNº: LOT-0001\nDescrição do Lote: Lote 1 - Computadores de Secretária (completos) para a GNR e para a PSP\nPreço base s/IVA: 4.267.500,00 EUR\nClassificação CPV (Vocabulário Comum para os Contratos Públicos)\nObjeto principal\nVocabulário Principal: 30200000\nNº: LOT-0002\nDescrição do Lote: Lote 2 - Computadores de elevado desempenho c/ 2 monitores de 24” para a GNR e para a PSP\nPreço base s/IVA: 507.500,00 EUR\nClassificação CPV (Vocabulário Comum para os Contratos Públicos)\nObjeto principal\nVocabulário Principal: 30200000\nNº: LOT-0003\nDescrição do Lote: Lote 3 - Computadores Portáteis leves com monitor Hub/Dock e mala de transporte, para a GNR e para a PSP e Computadores Portáteis leves com rato ótico USB e mala de transporte, para a PSP;\nPreço base s/IVA: 2.020.000,00 EUR\nClassificação CPV (Vocabulário Comum para os Contratos Públicos)\nObjeto principal\nVocabulário Principal: 30200000\nNº: LOT-0004\nDescrição do Lote: Lote 4 - Diversos Monitores para a GNR e para a PSP\nPreço base s/IVA: 514.100,00 EUR\nClassificação CPV (Vocabulário Comum para os Contratos Públicos)\nObjeto principal\nVocabulário Principal: 30200000\nNº: LOT-0005\nDescrição do Lote: Lote 5 - Aquisição de Periféricos de Armazenamento para a PSP\nPreço base s/IVA: 55.700,00 EUR\nClassificação CPV (Vocabulário Comum para os Contratos Públicos)\nObjeto principal\nVocabulário Principal: 30200000\nNº: LOT-0006\nDescrição do Lote: Lote 6 - Aquisição de Periféricos diversos para a GNR e para a PSP\nPreço base s/IVA: 144.350,00 EUR\nClassificação CPV (Vocabulário Comum para os Contratos Públicos)\nObjeto principal\nVocabulário Principal: 30200000\nNº: LOT-0007\nDescrição do Lote: Lote 7 - Aquisição de Digitalizadores de mesa para a PSP\nPreço base s/IVA: 48.100,00 EUR\nClassificação CPV (Vocabulário Comum para os Contratos Públicos)\nObjeto principal\nVocabulário Principal: 30200000\nNº: LOT-0008\nDescrição do Lote: Lote 8 - Aquisição de Digitalizadores de alto desempenho para a PSP\nPreço base s/IVA: 56.000,00 EUR\nClassificação CPV (Vocabulário Comum para os Contratos Públicos)\nObjeto principal\nVocabulário Principal: 30200000\nNº: LOT-0009\nDescrição do Lote: Lote 9 - Aquisição de Impressoras portáteis para a PSP\nPreço base s/IVA: 146.000,00 EUR\nClassificação CPV (Vocabulário Comum para os Contratos Públicos)\nObjeto principal\nVocabulário Principal: 30200000\n7 - INDICAÇÕES ADICIONAIS\nO contrato envolve aquisição conjunta (satisfação de várias entidades)? Não\nO contrato é adjudicado por uma central de compras? Não\n8 - TÉCNICAS\nO concurso destina-se à celebração de um acordo-quadro? Inexistência de acordo-quadro\nÉ utilizado um leilão eletrónico? Não\nÉ adotada uma fase de negociação? Não\nSistema de Aquisição Dinâmico: Inexistência de sistema de aquisição dinâmico\n9 - LOCAL DA EXECUÇÃO DO CONTRATO\nLOCAL DA EXECUÇÃO DO CONTRATO (PROCEDIMENTO)\nPaís: Portugal\nNUT III: PT170\nLocalidade: Lisboa\nDistrito: Lisboa\nConcelho: Lisboa\nFreguesia: Todas\nLOCAL DA EXECUÇÃO DO CONTRATO (LOTE)\nIdentificador do Lote: LOT-0001; LOT-0002; LOT-0003; LOT-0004; LOT-0005; LOT-0006; LOT-0007; LOT-0008; LOT-0009\nPaís: Portugal\nNUT III: PT170\nLocalidade: Lisboa\nDistrito: Lisboa\nConcelho: Lisboa\nFreguesia: Todas\n10 - PRAZO DE EXECUÇÃO DO CONTRATO\nIdentificador do Lote: LOT-0001; LOT-0002; LOT-0003; LOT-0004; LOT-0005; LOT-0006; LOT-0007; LOT-0008; LOT-0009\nPrazo de execução do contrato: 95 DIAS\nPrevisão de renovações: Não\n11 - FUNDOS EU\nIdentificador do Lote: LOT-0001; LOT-0002; LOT-0003; LOT-0004; LOT-0005; LOT-0006; LOT-0007; LOT-0008; LOT-0009\nTêm fundos EU? Não\n12 - DOCUMENTOS DE HABILITAÇÃO\nHabilitação para o exercício da atividade profissional: Não\n13 - CONDIÇÕES DE APRESENTAÇÃO\nPlataforma eletrónica utilizada pela entidade adjudicante: VORTAL\nURL para Apresentação: https://community.vortal.biz/public/\nAdmissibilidade da apresentação de propostas variantes: Não autorizado\nPrazo para apresentação das propostas: 23-02-2026 23:59\nPrazo durante o qual os concorrentes são obrigados a manter as respetivas propostas: 66 dias a contar do termo do prazo para a apresentação das propostas\nApresentação de Catálogo Eletrónico: Não autorizado\nIndicação de Subcontratação na Proposta: Inexistência de indicação de subcontratação\n14 - PRESTAÇÃO DE CAUÇÃO\nPrestação de caução: Sim\nPercentagem: 5%\nDescrição da Garantia Exigida: Prestação de caução para os Lotes 1, 2, 3 e 4\n15 - FORNECIMENTO DAS PEÇAS DO CONCURSO, APRESENTAÇÃO DE PEDIDOS DE PARTICIPAÇÃO E APRESENTAÇÃO DAS PROPOSTAS\nLink para acesso às peças do concurso (URL): https://community.vortal.biz/Public/public-tender-documents/M0hzNTMxaVVpK25BMVBZV1RMSXFXM2d1ODREd3o2QmExK3Q5SlAxbkdTTWhacUR3eWFNZnM1dGROVVRTbHBsaGhRTlZnOWZTNENteWFIdmhCT1E5MXc9PUM2U2ha\n20 - OUTROS REQUISITOS\nIdentificador do Lote: LOT-0001; LOT-0002; LOT-0003; LOT-0004; LOT-0005; LOT-0006; LOT-0007; LOT-0008; LOT-0009\nInformação sobre contratos reservados. Aplica-se a contratos reservados (54º-A)? Não\n21 - CRITÉRIO DE ADJUDICAÇÃO\nO Critério de adjudicação é diferenciado por lote? Sim\nIdentificador do lote: LOT-0001\nMultifator: Sim\nFator: \nNome: Qualidade\nPonderação: 70%\nSubfatores: Não\nFator: \nNome: Preço\nPonderação: 5%\nSubfatores: Não\nFator: \nNome: Qualidade\nPonderação: 25%\nSubfatores: Não\nO Critério de adjudicação é diferenciado por lote? Sim\nIdentificador do lote: LOT-0002\nMultifator: Sim\nFator: \nNome: Qualidade\nPonderação: 70%\nSubfatores: Não\nFator: \nNome: Preço\nPonderação: 5%\nSubfatores: Não\nFator: \nNome: Qualidade\nPonderação: 25%\nSubfatores: Não\nO Critério de adjudicação é diferenciado por lote? Sim\nIdentificador do lote: LOT-0003\nMultifator: Sim\nFator: \nNome: Qualidade\nPonderação: 70%\nSubfatores: Não\nFator: \nNome: Preço\nPonderação: 5%\nSubfatores: Não\nFator: \nNome: Qualidade\nPonderação: 25%\nSubfatores: Não\nO Critério de adjudicação é diferenciado por lote? Sim\nIdentificador do lote: LOT-0004\nMultifator: Sim\nFator: \nNome: Qualidade\nPonderação: 70%\nSubfatores: Não\nFator: \nNome: Preço\nPonderação: 5%\nSubfatores: Não\nFator: \nNome: Qualidade\nPonderação: 25%\nSubfatores: Não\nO Critério de adjudicação é diferenciado por lote? Sim\nIdentificador do lote: LOT-0005\nMultifator: Sim\nFator: \nNome: Qualidade\nPonderação: 70%\nSubfatores: Não\nFator: \nNome: Preço\nPonderação: 30%\nSubfatores: Não\nO Critério de adjudicação é diferenciado por lote? Sim\nIdentificador do lote: LOT-0006\nMultifator: Sim\nFator: \nNome: Qualidade\nPonderação: 70%\nSubfatores: Não\nFator: \nNome: Preço\nPonderação: 30%\nSubfatores: Não\nO Critério de adjudicação é diferenciado por lote? Sim\nIdentificador do lote: LOT-0007\nMultifator: Sim\nFator: \nNome: Qualidade\nPonderação: 70%\nSubfatores: Não\nFator: \nNome: Preço\nPonderação: 30%\nSubfatores: Não\nO Critério de adjudicação é diferenciado por lote? Sim\nIdentificador do lote: LOT-0008\nMultifator: Sim\nFator: \nNome: Qualidade\nPonderação: 70%\nSubfatores: Não\nFator: \nNome: Preço\nPonderação: 30%\nSubfatores: Não\nO Critério de adjudicação é diferenciado por lote? Sim\nIdentificador do lote: LOT-0009\nMultifator: Sim\nFator: \nNome: Qualidade\nPonderação: 70%\nSubfatores: Não\nFator: \nNome: Preço\nPonderação: 30%\nSubfatores: Não\n24 - CONDIÇÕES DO CONTRATO\nIdentificador do Lote: LOT-0001; LOT-0002; LOT-0003; LOT-0004; LOT-0005; LOT-0006; LOT-0007; LOT-0008; LOT-0009\nFaturação Eletrónica: Permitido\nObrigação de Subcontratação:\nCódigo da Obrigação de Subcontratação: Não é aplicável nenhuma obrigação de subcontratação.\n25 - COMPRA PÚBLICA ESTRATÉGICA\nCompra Pública Estratégica: Inexistência de contratação pública estratégica\n26 - INFORMAÇÕES ADICIONAIS\nIdentificador do Lote: LOT-0001; LOT-0002; LOT-0003; LOT-0004; LOT-0005; LOT-0006; LOT-0007; LOT-0008; LOT-0009\nContrato adequado para PME: Sim\nCobertura ACP (Acordo dos Contratos Públicos da Organização Mundial do Comércio): Não\n27 - IDENTIFICAÇÃO E CONTACTOS DO ÓRGÃO DE RECURSOS ADMINISTRATIVOS\nDesignação: Ministério da Administração Interna\nEndereço: Praça do Comércio - Ala Oriental\nCódigo postal: 1149-015\nLocalidade: Lisboa\nTelefone: +351 213409000\nFax: +351 213409000\nEndereço eletrónico: dpie@sg.mai.gov.pt\nPrazo de interposição do recurso: 10 dias\n28 - IDENTIFICAÇÃO DO(S) AUTOR(ES) DE ANÚNCIO\nNome: Ricardo Alberto Carrilho\nCargo: Secretário-Geral do Ministério da Administração Interna\n29 - ALTERAÇÃO\nMotivo da Alteração: Correção pelo adquirente\nIdentificador da Versão do Anúncio a Alterar: bac74588-65a9-4155-8090-6ff29a1a0c7f-01\nIdentificador das Secções Alteradas do Anúncio Anterior: Critério de adjudicação\nDescrição das Alterações: No Lote de 1 ao Lote 4:\nFator quantidade - 70%, Fator Preço - 5%, Fator Ecológico - 25%.\nAlteração dos Documentos do Concurso: Sim\nData de alteração dos documentos do concurso: 07-01-2026\n419947373",
    "nipc": "600014665",
    "distrito": "Lisboa",
    "concelho": "Lisboa",
    "freguesia": "Freguesia de Santa Maria Maior - Lisboa",
    "site": "www.sg.mai.gov.pt/",
    "email": "gab.sec.geral@sg.mai.gov.pt",
    "designacao_contrato": "Aquisição de computadores de secretária, computadores de elevado desempenho, portáteis e periféricos, para a GNR e PSP, para os anos de 2025 e 2026, no âmbito do DLPIEFSS",
    "descricao": "Aquisição de computadores de secretária, computadores de elevado desempenho, portáteis e periféricos, para a GNR e PSP, para os anos de 2025 e 2026, no âmbito do DLPIEFSS",
    "preco_base": "7.759.250,00 EUR",
    "prazo_execucao": "95 DIAS",
    "prazo_apresentacao_propostas": "23-02-2026 23:59",
    "fundos_eu": "Não",
    "plataforma_eletronica": "VORTAL",
    "url_procedimento": "https://community.vortal.biz/public/",
    "autor_nome": "Ricardo Alberto Carrilho",
    "autor_cargo": "Secretário-Geral do Ministério da Administração Interna"
  },
  {
    "numero_procedimento": "N/A",
    "entidade": "APS - Administração dos Portos de Sines e do Algarve, SA",
    "link": "https://diariodarepublica.pt/dr/detalhe/contrato-publico/416-1003372811",
    "detalhes_completos": "1 - IDENTIFICAÇÃO E CONTACTOS DA ENTIDADE ADJUDICANTE\nDesignação da entidade adjudicante: APS - Administração dos Portos de Sines e do Algarve, SA\nNIPC: 501208950\nServiço/Órgão/Pessoa de contacto: ISI - Inovação e Sistemas de Informação\nEndereço: Rua do Porto Industrial, Apartado 16, EC Sines\nCódigo postal: 7521-953\nLocalidade: Setúbal\nPaís: Portugal\nNUT III: PT181\nDistrito: Setúbal\nConcelho: Sines\nFreguesia: Freguesia de Sines\nTelefone: 269860600\nFax: 269860690\nEndereço da Entidade (URL): www.portodesines.pt\nEndereço Eletrónico: geral@apsinesalgarve.pt\neDelivery Gateway (URL): https://community.vortal.biz/public/\nFunção da Organização: Adquirente\nNorma jurídica da Entidade Adjudicante: Empresa pública\nÁrea de atividade da Entidade Adjudicante: Atividades portuárias\n2 - JORNAL OFICIAL DA UNIÃO EUROPEIA\nO procedimento a que este anúncio diz respeito também é publicitado no Jornal Oficial da União Europeia? Sim\n3 - AVISO\nModelo de Anúncio: Concurso público\nData de Envio do Anúncio: 07-01-2026\n5 - PROCESSO\nTipo de Procedimento: Concurso público\nPreço base do procedimento: Sim\nValor do preço base do procedimento: 850.000,00 EUR\nProcedimento com lotes? Não\n6 - OBJETO DO CONTRATO\nNúmero de referência interna: ISI.PR.25.020\nDesignação do contrato: ISI.PR.25.020 – NEXUS - Fornecimento e instalação de Storages\nDescrição: ISI.PR.25.020 – NEXUS - Fornecimento de duas unidades de armazenamento (Storages) com capacidade adequada para alocar todos os sistemas de ficheiros e dados da infraestrutura da empresa, de forma a dar resposta às diversas necessidades da APS, recorrendo a tecnologia atualizada que permita acompanhar a evolução dos serviços e sistemas disponibilizados pela APS.\nOpções: Não\nTipo de Contrato Principal: Aquisição de Bens Móveis\nTipo de Contrato: Aquisição de Bens Móveis\nClassificação CPV (Vocabulário Comum para os Contratos Públicos)\nObjeto principal\nVocabulário Principal: 30233100\nPreço base s/IVA: 850.000,00 EUR\n7 - INDICAÇÕES ADICIONAIS\nO contrato envolve aquisição conjunta (satisfação de várias entidades)? Não\nO contrato é adjudicado por uma central de compras? Não\n8 - TÉCNICAS\nO concurso destina-se à celebração de um acordo-quadro? Inexistência de acordo-quadro\nÉ utilizado um leilão eletrónico? Não\nÉ adotada uma fase de negociação? Não\nSistema de Aquisição Dinâmico: Inexistência de sistema de aquisição dinâmico\n9 - LOCAL DA EXECUÇÃO DO CONTRATO\nLOCAL DA EXECUÇÃO DO CONTRATO (PROCEDIMENTO)\nPaís: Portugal\nNUT III: PT181\nLocalidade: Setúbal\nDistrito: Setúbal\nConcelho: Sines\nFreguesia: Freguesia de Sines\n10 - PRAZO DE EXECUÇÃO DO CONTRATO\nPrazo de execução do contrato: 60 DIAS\nPrevisão de renovações: Não\n11 - FUNDOS EU\nTêm fundos EU? Sim\n12 - DOCUMENTOS DE HABILITAÇÃO\nHabilitação para o exercício da atividade profissional: Sim\nTipo: Outros\nDescrição - Outros: Nos termos da legislação aplicável.\nDescrição: Nos termos das peças do procedimento\n13 - CONDIÇÕES DE APRESENTAÇÃO\nPlataforma eletrónica utilizada pela entidade adjudicante: VORTAL\nURL para Apresentação: https://community.vortal.biz/public/\nAdmissibilidade da apresentação de propostas variantes: Não autorizado\nPrazo para apresentação das propostas: 05-02-2026 23:59\nPrazo durante o qual os concorrentes são obrigados a manter as respetivas propostas: 66 dias a contar do termo do prazo para a apresentação das propostas\nApresentação de Catálogo Eletrónico: Permitido\nIndicação de Subcontratação na Proposta: Inexistência de indicação de subcontratação\n14 - PRESTAÇÃO DE CAUÇÃO\nPrestação de caução: Sim\nPercentagem: 5%\nDescrição da Garantia Exigida: Nos termos das peças do procedimento\n15 - FORNECIMENTO DAS PEÇAS DO CONCURSO, APRESENTAÇÃO DE PEDIDOS DE PARTICIPAÇÃO E APRESENTAÇÃO DAS PROPOSTAS\nLink para acesso às peças do concurso (URL): https://community.vortal.biz/Public/public-tender-documents/b3RsMXc1WlBUNVVNVDArQno2Q0RYUnM2V2dhRis0Ly9QNjlBTWx2dUZOT09IakhkQnBKMTF2OWVMaEp3V2tnaVVoQ0hNQ2h3VVhrMWZRZVhrWCs4dXc9PXhHbk83\n20 - OUTROS REQUISITOS\nInformação sobre contratos reservados. Aplica-se a contratos reservados (54º-A)? Não\n21 - CRITÉRIO DE ADJUDICAÇÃO\nMultifator: Não\nMonofator:\nNome: Outros\nOutro nome: Preço\n24 - CONDIÇÕES DO CONTRATO\nFaturação Eletrónica: Permitido\nObrigação de Subcontratação:\nCódigo da Obrigação de Subcontratação: Não é aplicável nenhuma obrigação de subcontratação.\n25 - COMPRA PÚBLICA ESTRATÉGICA\nCompra Pública Estratégica: Inexistência de contratação pública estratégica\n26 - INFORMAÇÕES ADICIONAIS\nContrato adequado para PME: Sim\nCobertura ACP (Acordo dos Contratos Públicos da Organização Mundial do Comércio): Não\n27 - IDENTIFICAÇÃO E CONTACTOS DO ÓRGÃO DE RECURSOS ADMINISTRATIVOS\nDesignação: APS - Administração dos Portos de Sines e do Algarve, SA\nEndereço: Rua do Porto Industrial - Apartado 16 E.C. Sines\nCódigo postal: 7520-953\nLocalidade: Sines\nTelefone: +351 269860600\nFax: +351 269860690\nEndereço eletrónico: geral@apsinesalgarve.pt\n28 - IDENTIFICAÇÃO DO(S) AUTOR(ES) DE ANÚNCIO\nNome: Pedro do Ó Barradas de Oliveira Ramos\nCargo: Presidente do Conselho de Administração da APS\n419947394",
    "nipc": "501208950",
    "distrito": "Setúbal",
    "concelho": "Sines",
    "freguesia": "Freguesia de Sines",
    "site": "www.portodesines.pt",
    "email": "geral@apsinesalgarve.pt",
    "designacao_contrato": "ISI.PR.25.020 – NEXUS - Fornecimento e instalação de Storages",
    "descricao": "ISI.PR.25.020 – NEXUS - Fornecimento de duas unidades de armazenamento (Storages) com capacidade adequada para alocar todos os sistemas de ficheiros e dados da infraestrutura da empresa, de forma a dar resposta às diversas necessidades da APS, recorrendo a tecnologia atualizada que permita acompanhar a evolução dos serviços e sistemas disponibilizados pela APS.",
    "preco_base": "850.000,00 EUR",
    "prazo_execucao": "60 DIAS",
    "prazo_apresentacao_propostas": "05-02-2026 23:59",
    "fundos_eu": "Sim",
    "plataforma_eletronica": "VORTAL",
    "url_procedimento": "https://community.vortal.biz/public/",
    "autor_nome": "Pedro do Ó Barradas de Oliveira Ramos",
    "autor_cargo": "Presidente do Conselho de Administração da APS"
  },
  {
    "numero_procedimento": "N/A",
    "entidade": "Autoridade Tributária e Aduaneira",
    "link": "https://diariodarepublica.pt/dr/detalhe/contrato-publico/418-1003372812",
    "detalhes_completos": "1 - IDENTIFICAÇÃO E CONTACTOS DA ENTIDADE ADJUDICANTE\nDesignação da entidade adjudicante: Autoridade Tributária e Aduaneira\nNIPC: 600084779\nServiço/Órgão/Pessoa de contacto: Direção de Serviços de Contratação Pública e Logística\nEndereço: Rua da Prata, n.ºs 20-22\nCódigo postal: 1149-027\nLocalidade: Lisboa\nPaís: Portugal\nNUT III: PT170\nDistrito: Lisboa\nConcelho: Lisboa\nFreguesia: Freguesia de Santa Maria Maior - Lisboa\nTelefone: 218812600\nFax: 218812935\nEndereço da Entidade (URL): https://www.portaldasfinancas.gov.pt/\nEndereço Eletrónico: at@at.gov.pt\neDelivery Gateway (URL): https://www.acingov.pt\nFunção da Organização: Adquirente\nSubfunção da Organização: Organização cujo orçamento é utilizado para pagar o contrato; Organização que executa o pagamento; Organização que fornece informações adicionais sobre o processo de adjudicação; Organização que fornece mais informações sobre os prazos dos procedimentos de recurso; Organização que fornece acesso fora de linha aos documentos do concurso; Organização responsável pelo tratamento das propostas; Organização que recebe as propostas; Organização que trata os pedidos de participação; Organização que recebe pedidos de participação; Organização que fornece mais informações sobre os procedimentos de recurso; Organização que assina o contrato\nNorma jurídica da Entidade Adjudicante: Organismo de direito público\nÁrea de atividade da Autoridade Adjudicante: Serviços públicos das administrações públicas\n2 - JORNAL OFICIAL DA UNIÃO EUROPEIA\nO procedimento a que este anúncio diz respeito também é publicitado no Jornal Oficial da União Europeia? Sim\n3 - AVISO\nModelo de Anúncio: Concurso público\nData de Envio do Anúncio: 07-01-2026\n5 - PROCESSO\nTipo de Procedimento: Concurso público\nPreço base do procedimento: Sim\nValor do preço base do procedimento: 498.420,00 EUR\nProcedimento com lotes? Não\n6 - OBJETO DO CONTRATO\nNúmero de referência interna: 107/CP/AT/2025\nDesignação do contrato: Renovação do licenciamento do software PowerCenter e PowerExchange\nDescrição: Renovação do licenciamento do software PowerCenter e PowerExchange\nOpções: Não\nTipo de Contrato Principal: Locação de Bens Móveis\nTipo de Contrato: Locação de Bens Móveis\nClassificação CPV (Vocabulário Comum para os Contratos Públicos)\nObjeto principal\nVocabulário Principal: 48000000\nPreço base s/IVA: 498.420,00 EUR\n7 - INDICAÇÕES ADICIONAIS\nO contrato envolve aquisição conjunta (satisfação de várias entidades)? Não\nO contrato é adjudicado por uma central de compras? Não\n8 - TÉCNICAS\nO concurso destina-se à celebração de um acordo-quadro? Inexistência de acordo-quadro\nÉ utilizado um leilão eletrónico? Não\nÉ adotada uma fase de negociação? Não\nSistema de Aquisição Dinâmico: Inexistência de sistema de aquisição dinâmico\n9 - LOCAL DA EXECUÇÃO DO CONTRATO\nLOCAL DA EXECUÇÃO DO CONTRATO (PROCEDIMENTO)\nPaís: Portugal\nNUT III: PT170\nLocalidade: Freguesia de Campolide\nDistrito: Lisboa\nConcelho: Lisboa\nFreguesia: Freguesia de Campolide\n10 - PRAZO DE EXECUÇÃO DO CONTRATO\nPrazo de execução do contrato: 333 DIAS\nPrevisão de renovações: Não\n11 - FUNDOS EU\nTêm fundos EU? Não\n12 - DOCUMENTOS DE HABILITAÇÃO\nHabilitação para o exercício da atividade profissional: Não\n13 - CONDIÇÕES DE APRESENTAÇÃO\nPlataforma eletrónica utilizada pela entidade adjudicante: ACIN\nURL para Apresentação: https://www.acingov.pt\nAdmissibilidade da apresentação de propostas variantes: Não autorizado\nPrazo para apresentação das propostas: 22-01-2026 23:59\nPrazo durante o qual os concorrentes são obrigados a manter as respetivas propostas: 66 dias a contar do termo do prazo para a apresentação das propostas\nApresentação de Catálogo Eletrónico: Permitido\nIndicação de Subcontratação na Proposta: Inexistência de indicação de subcontratação\n14 - PRESTAÇÃO DE CAUÇÃO\nPrestação de caução: Não\n15 - FORNECIMENTO DAS PEÇAS DO CONCURSO, APRESENTAÇÃO DE PEDIDOS DE PARTICIPAÇÃO E APRESENTAÇÃO DAS PROPOSTAS\nLink para acesso às peças do concurso (URL): https://www.acingov.pt/acingovprod/2/zonaPublica/zona_publica_c/donwloadProcedurePiece/MTAzNjA2OQ==\n20 - OUTROS REQUISITOS\nInformação sobre contratos reservados. Aplica-se a contratos reservados (54º-A)? Não\n21 - CRITÉRIO DE ADJUDICAÇÃO\nMultifator: Não\nMonofator:\nNome: Preço\n24 - CONDIÇÕES DO CONTRATO\nFaturação Eletrónica: Permitido\nObrigação de Subcontratação:\nCódigo da Obrigação de Subcontratação: Não é aplicável nenhuma obrigação de subcontratação.\n25 - COMPRA PÚBLICA ESTRATÉGICA\nCompra Pública Estratégica: Inexistência de contratação pública estratégica\n26 - INFORMAÇÕES ADICIONAIS\nContrato adequado para PME: Sim\nCobertura ACP (Acordo dos Contratos Públicos da Organização Mundial do Comércio): Não\n27 - IDENTIFICAÇÃO E CONTACTOS DO ÓRGÃO DE RECURSOS ADMINISTRATIVOS\nDesignação: Secretária de Estado dos Assuntos Fiscais\nEndereço: Avenida do Infante D Henrique 1\nCódigo postal: 1149-009\nLocalidade: Lisboa\nTelefone: 218816800\nFax: \nEndereço eletrónico: seaf@mf.gov.pt\nPrazo de interposição do recurso: 5 dias\n28 - IDENTIFICAÇÃO DO(S) AUTOR(ES) DE ANÚNCIO\nNome: Helena Alves Borges\nCargo: Diretora Geral da AT\n419947401",
    "nipc": "600084779",
    "distrito": "Lisboa",
    "concelho": "Lisboa",
    "freguesia": "Freguesia de Santa Maria Maior - Lisboa",
    "site": "https://www.portaldasfinancas.gov.pt/",
    "email": "at@at.gov.pt",
    "designacao_contrato": "Renovação do licenciamento do software PowerCenter e PowerExchange",
    "descricao": "Renovação do licenciamento do software PowerCenter e PowerExchange",
    "preco_base": "498.420,00 EUR",
    "prazo_execucao": "333 DIAS",
    "prazo_apresentacao_propostas": "22-01-2026 23:59",
    "fundos_eu": "Não",
    "plataforma_eletronica": "ACIN",
    "url_procedimento": "https://www.acingov.pt",
    "autor_nome": "Helena Alves Borges",
    "autor_cargo": "Diretora Geral da AT"
  },
  {
    "numero_procedimento": "N/A",
    "entidade": "Imprensa Nacional-Casa da Moeda, SA",
    "link": "https://diariodarepublica.pt/dr/detalhe/contrato-publico/420-1003372813",
    "detalhes_completos": "1 - IDENTIFICAÇÃO E CONTACTOS DA ENTIDADE ADJUDICANTE\nDesignação da entidade adjudicante: Imprensa Nacional-Casa da Moeda, SA\nNIPC: 500792887\nServiço/Órgão/Pessoa de contacto: DCS/GCO\nEndereço: Av. António José de Almeida\nCódigo postal: 1000-042\nLocalidade: Lisboa\nPaís: Portugal\nNUT III: PT170\nDistrito: Lisboa\nConcelho: Lisboa\nFreguesia: Freguesia de Avenidas Novas\nTelefone: 217810700\nFax: 217810700\nEndereço da Entidade (URL): www.incm.pt\nEndereço Eletrónico: compras@incm.pt\neDelivery Gateway (URL): https://www.acingov.pt\nFunção da Organização: Adquirente\nNorma jurídica da Entidade Adjudicante: Organismo de direito público\nÁrea de atividade da Autoridade Adjudicante: Serviços públicos das administrações públicas\n2 - JORNAL OFICIAL DA UNIÃO EUROPEIA\nO procedimento a que este anúncio diz respeito também é publicitado no Jornal Oficial da União Europeia? Sim\n3 - AVISO\nModelo de Anúncio: Concurso público\nData de Envio do Anúncio: 07-01-2026\n5 - PROCESSO\nTipo de Procedimento: Concurso público\nPreço base do procedimento: Sim\nValor do preço base do procedimento: 274.000,00 EUR\nProcedimento com lotes? Não\n6 - OBJETO DO CONTRATO\nNúmero de referência interna: 006/2026\nDesignação do contrato: Aquisição de Papel Laser com Marca de Água\nDescrição: Aquisição de Papel Laser com Marca de Água\nOpções: Não\nTipo de Contrato Principal: Aquisição de Bens Móveis\nTipo de Contrato: Aquisição de Bens Móveis\nClassificação CPV (Vocabulário Comum para os Contratos Públicos)\nObjeto principal\nVocabulário Principal: 30197630\nPreço base s/IVA: 274.000,00 EUR\n7 - INDICAÇÕES ADICIONAIS\nO contrato envolve aquisição conjunta (satisfação de várias entidades)? Não\nO contrato é adjudicado por uma central de compras? Não\n8 - TÉCNICAS\nO concurso destina-se à celebração de um acordo-quadro? Inexistência de acordo-quadro\nÉ utilizado um leilão eletrónico? Não\nÉ adotada uma fase de negociação? Não\nSistema de Aquisição Dinâmico: Inexistência de sistema de aquisição dinâmico\n9 - LOCAL DA EXECUÇÃO DO CONTRATO\nLOCAL DA EXECUÇÃO DO CONTRATO (PROCEDIMENTO)\nPaís: Portugal\nNUT III: PT170\nLocalidade: Freguesia de Vialonga\nDistrito: Lisboa\nConcelho: Vila Franca de Xira\nFreguesia: Freguesia de Vialonga\n10 - PRAZO DE EXECUÇÃO DO CONTRATO\nPrazo de execução do contrato: 12 MESES\nPrevisão de renovações: Não\n11 - FUNDOS EU\nTêm fundos EU? Não\n12 - DOCUMENTOS DE HABILITAÇÃO\nHabilitação para o exercício da atividade profissional: Não\n13 - CONDIÇÕES DE APRESENTAÇÃO\nPlataforma eletrónica utilizada pela entidade adjudicante: ACIN\nURL para Apresentação: https://www.acingov.pt\nAdmissibilidade da apresentação de propostas variantes: Não autorizado\nPrazo para apresentação das propostas: 06-02-2026 17:00\nPrazo durante o qual os concorrentes são obrigados a manter as respetivas propostas: 66 dias a contar do termo do prazo para a apresentação das propostas\nApresentação de Catálogo Eletrónico: Permitido\nIndicação de Subcontratação na Proposta: Inexistência de indicação de subcontratação\n14 - PRESTAÇÃO DE CAUÇÃO\nPrestação de caução: Não\n15 - FORNECIMENTO DAS PEÇAS DO CONCURSO, APRESENTAÇÃO DE PEDIDOS DE PARTICIPAÇÃO E APRESENTAÇÃO DAS PROPOSTAS\nLink para acesso às peças do concurso (URL): https://www.acingov.pt/acingovprod/2/zonaPublica/zona_publica_c/donwloadProcedurePiece/MTAzNjk3MA==\n20 - OUTROS REQUISITOS\nInformação sobre contratos reservados. Aplica-se a contratos reservados (54º-A)? Não\n21 - CRITÉRIO DE ADJUDICAÇÃO\nMultifator: Sim\nFator: \nNome: Preço\nPonderação: 85%\nSubfatores: Não\nFator: \nNome: Outros\nOutro Nome: Critérios de Sustentabilidade\nPonderação: 15%\nSubfatores: Não\n24 - CONDIÇÕES DO CONTRATO\nFaturação Eletrónica: Permitido\nObrigação de Subcontratação:\nCódigo da Obrigação de Subcontratação: Não é aplicável nenhuma obrigação de subcontratação.\n25 - COMPRA PÚBLICA ESTRATÉGICA\nCompra Pública Estratégica: Inexistência de contratação pública estratégica\n26 - INFORMAÇÕES ADICIONAIS\nContrato adequado para PME: Não\nCobertura ACP (Acordo dos Contratos Públicos da Organização Mundial do Comércio): Não\n27 - IDENTIFICAÇÃO E CONTACTOS DO ÓRGÃO DE RECURSOS ADMINISTRATIVOS\nDesignação: Imprensa Nacional - Casa da Moeda, S.A.\nEndereço: Av. António José de Almeida 1000-042 Lisboa\nCódigo postal: 1000-042\nLocalidade: Lisboa\nTelefone: 217810870\nFax: \nEndereço eletrónico: compras@incm.pt\n28 - IDENTIFICAÇÃO DO(S) AUTOR(ES) DE ANÚNCIO\nNome: Dora Moita\nCargo: Presidente do Conselho de Administração\n419947390",
    "nipc": "500792887",
    "distrito": "Lisboa",
    "concelho": "Lisboa",
    "freguesia": "Freguesia de Avenidas Novas",
    "site": "www.incm.pt",
    "email": "compras@incm.pt",
    "designacao_contrato": "Aquisição de Papel Laser com Marca de Água",
    "descricao": "Aquisição de Papel Laser com Marca de Água",
    "preco_base": "274.000,00 EUR",
    "prazo_execucao": "12 MESES",
    "prazo_apresentacao_propostas": "06-02-2026 17:00",
    "fundos_eu": "Não",
    "plataforma_eletronica": "ACIN",
    "url_procedimento": "https://www.acingov.pt",
    "autor_nome": "Dora Moita",
    "autor_cargo": "Presidente do Conselho de Administração"
  },
  {
    "numero_procedimento": "N/A",
    "entidade": "Coopetape - Cooperativa de Ensino, CRL",
    "link": "https://diariodarepublica.pt/dr/detalhe/contrato-publico/422-1003372814",
    "detalhes_completos": "1 - IDENTIFICAÇÃO E CONTACTOS DA ENTIDADE ADJUDICANTE\nDesignação da entidade adjudicante: Coopetape - Cooperativa de Ensino, CRL\nNIPC: 504443127\nEndereço: Rua Benemerito Joaquim Rosas S/N\nCódigo postal: 4910-130\nLocalidade: Viana do Castelo\nPaís: Portugal\nNUT III: PT111\nDistrito: Viana do Castelo\nConcelho: Caminha\nFreguesia: União das Freguesias de Caminha (Matriz) e Vilarelho\nTelefone: 258719240\nFax: 258719241\nEndereço da Entidade (URL): www.etap.pt\nEndereço Eletrónico: pauloalves@etap.pt\neDelivery Gateway (URL): https://community.vortal.biz/public/\nFunção da Organização: Adquirente\nNorma jurídica da Entidade Adjudicante: Empresa pública\nÁrea de atividade da Autoridade Adjudicante: Educação\n2 - JORNAL OFICIAL DA UNIÃO EUROPEIA\nO procedimento a que este anúncio diz respeito também é publicitado no Jornal Oficial da União Europeia? Sim\n3 - AVISO\nModelo de Anúncio: Concurso público\nData de Envio do Anúncio: 07-01-2026\n5 - PROCESSO\nTipo de Procedimento: Concurso público\nPreço base do procedimento: Sim\nValor do preço base do procedimento: 1.416.011,75 EUR\nProcedimento com lotes? Sim\nNº Máx. de Lotes Autorizado: 4\nNúmero máximo de lotes que podem ser adjudicados a um concorrente: 4\n6 - OBJETO DO CONTRATO\nNúmero de referência interna: 03-25ETAPCPIMAIA\nDesignação do contrato: 03-25ETAPCPIMAIA\nDescrição: Aquisição de equipamento no âmbito no centro tecnológico especializado de indústria\nOpções: Não\nTipo de Contrato Principal: Aquisição de Bens Móveis\nTipo de Contrato: Aquisição de Bens Móveis\nClassificação CPV (Vocabulário Comum para os Contratos Públicos)\nObjeto principal\nVocabulário Principal: 39150000\nPreço base s/IVA: 1.416.011,75 EUR\nLotes: \nNº: LOT-0001\nDescrição do Lote: Lote 1 - Informática\nPreço base s/IVA: 273.230,00 EUR\nClassificação CPV (Vocabulário Comum para os Contratos Públicos)\nObjeto principal\nVocabulário Principal: 39150000\nNº: LOT-0002\nDescrição do Lote: Lote 2 - Mobiliário Sala de Aula\nPreço base s/IVA: 50.975,05 EUR\nClassificação CPV (Vocabulário Comum para os Contratos Públicos)\nObjeto principal\nVocabulário Principal: 39150000\nNº: LOT-0003\nDescrição do Lote: Lote 3 - Equipamento Mecatrónica e Aeronaves\nPreço base s/IVA: 694.749,00 EUR\nClassificação CPV (Vocabulário Comum para os Contratos Públicos)\nObjeto principal\nVocabulário Principal: 39150000\nNº: LOT-0004\nDescrição do Lote: Lote 4 - Equipamento oficinas\nPreço base s/IVA: 397.057,70 EUR\nClassificação CPV (Vocabulário Comum para os Contratos Públicos)\nObjeto principal\nVocabulário Principal: 39150000\n7 - INDICAÇÕES ADICIONAIS\nO contrato envolve aquisição conjunta (satisfação de várias entidades)? Não\nO contrato é adjudicado por uma central de compras? Não\n8 - TÉCNICAS\nO concurso destina-se à celebração de um acordo-quadro? Inexistência de acordo-quadro\nÉ utilizado um leilão eletrónico? Não\nÉ adotada uma fase de negociação? Não\nSistema de Aquisição Dinâmico: Inexistência de sistema de aquisição dinâmico\n9 - LOCAL DA EXECUÇÃO DO CONTRATO\nLOCAL DA EXECUÇÃO DO CONTRATO (PROCEDIMENTO)\nPaís: Portugal\nNUT III: PT111\nLocalidade: Viana do Castelo\nDistrito: Viana do Castelo\nConcelho: Caminha\nFreguesia: União das Freguesias de Caminha (Matriz) e Vilarelho\nLOCAL DA EXECUÇÃO DO CONTRATO (LOTE)\nIdentificador do Lote: LOT-0001; LOT-0002; LOT-0003; LOT-0004\nPaís: Portugal\nNUT III: PT111\nLocalidade: Viana do Castelo\nDistrito: Viana do Castelo\nConcelho: Caminha\nFreguesia: União das Freguesias de Caminha (Matriz) e Vilarelho\n10 - PRAZO DE EXECUÇÃO DO CONTRATO\nIdentificador do Lote: LOT-0001; LOT-0002; LOT-0003; LOT-0004\nPrazo de execução do contrato: 2 MESES\nPrevisão de renovações: Não\n11 - FUNDOS EU\nIdentificador do Lote: LOT-0001; LOT-0002; LOT-0003; LOT-0004\nTêm fundos EU? Sim\n12 - DOCUMENTOS DE HABILITAÇÃO\nHabilitação para o exercício da atividade profissional: Não\n13 - CONDIÇÕES DE APRESENTAÇÃO\nPlataforma eletrónica utilizada pela entidade adjudicante: VORTAL\nURL para Apresentação: https://community.vortal.biz/public/\nAdmissibilidade da apresentação de propostas variantes: Não autorizado\nPrazo para apresentação das propostas: 08-02-2026 23:59\nPrazo durante o qual os concorrentes são obrigados a manter as respetivas propostas: 90 dias a contar do termo do prazo para a apresentação das propostas\nApresentação de Catálogo Eletrónico: Permitido\nIndicação de Subcontratação na Proposta: Inexistência de indicação de subcontratação\n14 - PRESTAÇÃO DE CAUÇÃO\nPrestação de caução: Não\n15 - FORNECIMENTO DAS PEÇAS DO CONCURSO, APRESENTAÇÃO DE PEDIDOS DE PARTICIPAÇÃO E APRESENTAÇÃO DAS PROPOSTAS\nLink para acesso às peças do concurso (URL): https://community.vortal.biz/Public/public-tender-documents/QURINzUzT2tXK29NNzQ1UE1oQXlySTdZdm4wRG5DNFlvSitPUEFhUkozUHBZQkdXT2MydjBEcWpzRXk2dHgvUW93QXZaOVdkOXVsWnNRSk1UTTJPYVE9PXBWKmh4\n20 - OUTROS REQUISITOS\nIdentificador do Lote: LOT-0001; LOT-0002; LOT-0003; LOT-0004\nInformação sobre contratos reservados. Aplica-se a contratos reservados (54º-A)? Não\n21 - CRITÉRIO DE ADJUDICAÇÃO\nO Critério de adjudicação é diferenciado por lote? Não\nMultifator: Sim\nFator: \nNome: Preço\nPonderação: 50%\nSubfatores: Não\nFator: \nNome: Qualidade\nPonderação: 50%\nSubfatores: Não\n24 - CONDIÇÕES DO CONTRATO\nIdentificador do Lote: LOT-0001; LOT-0002; LOT-0003; LOT-0004\nFaturação Eletrónica: Permitido\nObrigação de Subcontratação:\nCódigo da Obrigação de Subcontratação: Não é aplicável nenhuma obrigação de subcontratação.\n25 - COMPRA PÚBLICA ESTRATÉGICA\nCompra Pública Estratégica: Inexistência de contratação pública estratégica\n26 - INFORMAÇÕES ADICIONAIS\nIdentificador do Lote: LOT-0001; LOT-0002; LOT-0003; LOT-0004\nContrato adequado para PME: Sim\nCobertura ACP (Acordo dos Contratos Públicos da Organização Mundial do Comércio): Não\n27 - IDENTIFICAÇÃO E CONTACTOS DO ÓRGÃO DE RECURSOS ADMINISTRATIVOS\nDesignação: Direção\nEndereço: Rua Benemérito Joaquim Rosas\nCódigo postal: 4910-130\nLocalidade: Caminha\nTelefone: +351 258719240\nFax: +351 258719240\nEndereço eletrónico: caminha@etap.pt\n28 - IDENTIFICAÇÃO DO(S) AUTOR(ES) DE ANÚNCIO\nNome: José Luís Diogo de Azevedo Presa\nCargo: Presidente da direção\n419947417",
    "nipc": "504443127",
    "distrito": "Viana do Castelo",
    "concelho": "Caminha",
    "freguesia": "União das Freguesias de Caminha (Matriz) e Vilarelho",
    "site": "www.etap.pt",
    "email": "pauloalves@etap.pt",
    "designacao_contrato": "03-25ETAPCPIMAIA",
    "descricao": "Aquisição de equipamento no âmbito no centro tecnológico especializado de indústria",
    "preco_base": "1.416.011,75 EUR",
    "prazo_execucao": "2 MESES",
    "prazo_apresentacao_propostas": "08-02-2026 23:59",
    "fundos_eu": "Sim",
    "plataforma_eletronica": "VORTAL",
    "url_procedimento": "https://community.vortal.biz/public/",
    "autor_nome": "José Luís Diogo de Azevedo Presa",
    "autor_cargo": "Presidente da direção"
  },
  {
    "numero_procedimento": "N/A",
    "entidade": "Serviços Municipalizados de Castelo Branco",
    "link": "https://diariodarepublica.pt/dr/detalhe/contrato-publico/423-1003372815",
    "detalhes_completos": "1 - IDENTIFICAÇÃO E CONTACTOS DA ENTIDADE ADJUDICANTE\nDesignação da entidade adjudicante: Serviços Municipalizados de Castelo Branco\nNIPC: 680017640\nServiço/Órgão/Pessoa de contacto: Conselho de Administração\nEndereço: Av. Nuno Álvares Nº 32 r/c\nCódigo postal: 6000-083\nLocalidade: Castelo Branco\nPaís: Portugal\nNUT III: PT16H\nDistrito: Castelo Branco\nConcelho: Castelo Branco\nFreguesia: Freguesia de Castelo Branco - Castelo Branco\nTelefone: 272340500\nFax: 272340501\nEndereço da Entidade (URL): www.sm-castelobranco.pt\nEndereço Eletrónico: geral@sm-castelobranco.pt\neDelivery Gateway (URL): https://www.acingov.pt\nFunção da Organização: Adquirente\nNorma jurídica da Entidade Adjudicante: Organismo de direito público\nÁrea de atividade da Autoridade Adjudicante: Serviços públicos das administrações públicas\n2 - JORNAL OFICIAL DA UNIÃO EUROPEIA\nO procedimento a que este anúncio diz respeito também é publicitado no Jornal Oficial da União Europeia? Não\n3 - AVISO\nModelo de Anúncio: Concurso público\nData de Envio do Anúncio: 09-01-2026\n5 - PROCESSO\nTipo de Procedimento: Concurso público\nPreço base do procedimento: Sim\nValor do preço base do procedimento: 28.000,00 EUR\nProcedimento com lotes? Não\n6 - OBJETO DO CONTRATO\nNúmero de referência interna: 21/2025/CP\nDesignação do contrato: Manutenção de AVAC e Sistemas de Águas Quentes Sanitárias\nDescrição: Manutenção de AVAC e Sistemas de Águas Quentes Sanitárias\nTipo de Contrato Principal: Aquisição de Serviços\nTipo de Contrato: Aquisição de Serviços\nClassificação CPV (Vocabulário Comum para os Contratos Públicos)\nObjeto principal\nVocabulário Principal: 50800000\nPreço base s/IVA: 28.000,00 EUR\n7 - INDICAÇÕES ADICIONAIS\nO contrato envolve aquisição conjunta (satisfação de várias entidades)? Não\nO contrato é adjudicado por uma central de compras? Não\n8 - TÉCNICAS\nO concurso destina-se à celebração de um acordo-quadro? Inexistência de acordo-quadro\nÉ utilizado um leilão eletrónico? Não\nÉ adotada uma fase de negociação? Não\nSistema de Aquisição Dinâmico: Inexistência de sistema de aquisição dinâmico\n9 - LOCAL DA EXECUÇÃO DO CONTRATO\nLOCAL DA EXECUÇÃO DO CONTRATO (PROCEDIMENTO)\nPaís: Portugal\nNUT III: PT16H\nLocalidade: Freguesia de Castelo Branco - Castelo Branco\nDistrito: Castelo Branco\nConcelho: Castelo Branco\nFreguesia: Freguesia de Castelo Branco - Castelo Branco\n10 - PRAZO DE EXECUÇÃO DO CONTRATO\nPrazo de execução do contrato: 730 DIAS\nPrevisão de renovações: Não\n11 - FUNDOS EU\nTêm fundos EU? Não\n12 - DOCUMENTOS DE HABILITAÇÃO\nHabilitação para o exercício da atividade profissional: Não\n13 - CONDIÇÕES DE APRESENTAÇÃO\nPlataforma eletrónica utilizada pela entidade adjudicante: ACIN\nURL para Apresentação: https://www.acingov.pt\nAdmissibilidade da apresentação de propostas variantes: Não autorizado\nPrazo para apresentação das propostas: 11-01-2026 23:59\nPrazo durante o qual os concorrentes são obrigados a manter as respetivas propostas: 90 dias a contar do termo do prazo para a apresentação das propostas\nIndicação de Subcontratação na Proposta: Inexistência de indicação de subcontratação\n14 - PRESTAÇÃO DE CAUÇÃO\nPrestação de caução: Não\n15 - FORNECIMENTO DAS PEÇAS DO CONCURSO, APRESENTAÇÃO DE PEDIDOS DE PARTICIPAÇÃO E APRESENTAÇÃO DAS PROPOSTAS\nLink para acesso às peças do concurso (URL): https://www.acingov.pt/acingovprod/2/zonaPublica/zona_publica_c/donwloadProcedurePiece/MTAxMDk3NQ==\n20 - OUTROS REQUISITOS\nInformação sobre contratos reservados. Aplica-se a contratos reservados (54º-A)? Não\n21 - CRITÉRIO DE ADJUDICAÇÃO\nMultifator: Não\nMonofator:\nNome: Preço\n24 - CONDIÇÕES DO CONTRATO\nFaturação Eletrónica: Permitido\nObrigação de Subcontratação:\nCódigo da Obrigação de Subcontratação: Não é aplicável nenhuma obrigação de subcontratação.\n25 - COMPRA PÚBLICA ESTRATÉGICA\nCompra Pública Estratégica: Inexistência de contratação pública estratégica\n26 - INFORMAÇÕES ADICIONAIS\nContrato adequado para PME: Não\nCobertura ACP (Acordo dos Contratos Públicos da Organização Mundial do Comércio): Não\n27 - IDENTIFICAÇÃO E CONTACTOS DO ÓRGÃO DE RECURSOS ADMINISTRATIVOS\nDesignação: Conselho de Administração\nEndereço: Av. Nuno Álvares Nº 32 r/c\nCódigo postal: 6000-083\nLocalidade: Castelo Branco\nTelefone: 272340500\nFax: 272340501\nEndereço eletrónico: geral@sm-castelobranco.pt\nPrazo de interposição do recurso: 5 dias\n28 - IDENTIFICAÇÃO DO(S) AUTOR(ES) DE ANÚNCIO\nNome: Engª. Sónia Cristina Cristóvão Mexia\nCargo: Administradora\n419947111",
    "nipc": "680017640",
    "distrito": "Castelo Branco",
    "concelho": "Castelo Branco",
    "freguesia": "Freguesia de Castelo Branco - Castelo Branco",
    "site": "www.sm-castelobranco.pt",
    "email": "geral@sm-castelobranco.pt",
    "designacao_contrato": "Manutenção de AVAC e Sistemas de Águas Quentes Sanitárias",
    "descricao": "Manutenção de AVAC e Sistemas de Águas Quentes Sanitárias",
    "preco_base": "28.000,00 EUR",
    "prazo_execucao": "730 DIAS",
    "prazo_apresentacao_propostas": "11-01-2026 23:59",
    "fundos_eu": "Não",
    "plataforma_eletronica": "ACIN",
    "url_procedimento": "https://www.acingov.pt",
    "autor_nome": "Engª. Sónia Cristina Cristóvão Mexia",
    "autor_cargo": "Administradora"
  },
  {
    "numero_procedimento": "N/A",
    "entidade": "Serviços Municipalizados de Castelo Branco",
    "link": "https://diariodarepublica.pt/dr/detalhe/contrato-publico/424-1003372816",
    "detalhes_completos": "1 - IDENTIFICAÇÃO E CONTACTOS DA ENTIDADE ADJUDICANTE\nDesignação da entidade adjudicante: Serviços Municipalizados de Castelo Branco\nNIPC: 680017640\nServiço/Órgão/Pessoa de contacto: Conselho de Administração\nEndereço: Av. Nuno Álvares Nº 32 r/c\nCódigo postal: 6000-083\nLocalidade: Castelo Branco\nPaís: Portugal\nNUT III: PT16H\nDistrito: Castelo Branco\nConcelho: Castelo Branco\nFreguesia: Freguesia de Castelo Branco - Castelo Branco\nTelefone: 272340500\nFax: 272340501\nEndereço da Entidade (URL): www.sm-castelobranco.pt\nEndereço Eletrónico: geral@sm-castelobranco.pt\neDelivery Gateway (URL): https://www.acingov.pt\nFunção da Organização: Adquirente\nNorma jurídica da Entidade Adjudicante: Organismo de direito público\nÁrea de atividade da Autoridade Adjudicante: Serviços públicos das administrações públicas\n2 - JORNAL OFICIAL DA UNIÃO EUROPEIA\nO procedimento a que este anúncio diz respeito também é publicitado no Jornal Oficial da União Europeia? Não\n3 - AVISO\nModelo de Anúncio: Concurso público\nData de Envio do Anúncio: 09-01-2026\n5 - PROCESSO\nTipo de Procedimento: Concurso público\nPreço base do procedimento: Sim\nValor do preço base do procedimento: 19.600,00 EUR\nProcedimento com lotes? Não\n6 - OBJETO DO CONTRATO\nNúmero de referência interna: 19/2025/CP\nDesignação do contrato: Fornecimento continuado de Sacos CãoPeão com logotipo personalizado\nDescrição: Fornecimento continuado de Sacos CãoPeão com logotipo personalizado\nTipo de Contrato Principal: Aquisição de Bens Móveis\nTipo de Contrato: Aquisição de Bens Móveis\nClassificação CPV (Vocabulário Comum para os Contratos Públicos)\nObjeto principal\nVocabulário Principal: 19640000\nPreço base s/IVA: 19.600,00 EUR\n7 - INDICAÇÕES ADICIONAIS\nO contrato envolve aquisição conjunta (satisfação de várias entidades)? Não\nO contrato é adjudicado por uma central de compras? Não\n8 - TÉCNICAS\nO concurso destina-se à celebração de um acordo-quadro? Inexistência de acordo-quadro\nÉ utilizado um leilão eletrónico? Não\nÉ adotada uma fase de negociação? Não\nSistema de Aquisição Dinâmico: Inexistência de sistema de aquisição dinâmico\n9 - LOCAL DA EXECUÇÃO DO CONTRATO\nLOCAL DA EXECUÇÃO DO CONTRATO (PROCEDIMENTO)\nPaís: Portugal\nNUT III: PT16H\nLocalidade: Freguesia de Castelo Branco - Castelo Branco\nDistrito: Castelo Branco\nConcelho: Castelo Branco\nFreguesia: Freguesia de Castelo Branco - Castelo Branco\n10 - PRAZO DE EXECUÇÃO DO CONTRATO\nPrazo de execução do contrato: 24 MESES\nPrevisão de renovações: Não\n11 - FUNDOS EU\nTêm fundos EU? Não\n12 - DOCUMENTOS DE HABILITAÇÃO\nHabilitação para o exercício da atividade profissional: Não\n13 - CONDIÇÕES DE APRESENTAÇÃO\nPlataforma eletrónica utilizada pela entidade adjudicante: ACIN\nURL para Apresentação: https://www.acingov.pt\nAdmissibilidade da apresentação de propostas variantes: Não autorizado\nPrazo para apresentação das propostas: 11-01-2026 23:59\nPrazo durante o qual os concorrentes são obrigados a manter as respetivas propostas: 66 dias a contar do termo do prazo para a apresentação das propostas\nIndicação de Subcontratação na Proposta: Inexistência de indicação de subcontratação\n14 - PRESTAÇÃO DE CAUÇÃO\nPrestação de caução: Não\n15 - FORNECIMENTO DAS PEÇAS DO CONCURSO, APRESENTAÇÃO DE PEDIDOS DE PARTICIPAÇÃO E APRESENTAÇÃO DAS PROPOSTAS\nLink para acesso às peças do concurso (URL): https://www.acingov.pt/acingovprod/2/zonaPublica/zona_publica_c/donwloadProcedurePiece/MTAxMDk4NQ==\n20 - OUTROS REQUISITOS\nInformação sobre contratos reservados. Aplica-se a contratos reservados (54º-A)? Não\n21 - CRITÉRIO DE ADJUDICAÇÃO\nMultifator: Não\nMonofator:\nNome: Preço\n24 - CONDIÇÕES DO CONTRATO\nFaturação Eletrónica: Permitido\nObrigação de Subcontratação:\nCódigo da Obrigação de Subcontratação: Não é aplicável nenhuma obrigação de subcontratação.\n25 - COMPRA PÚBLICA ESTRATÉGICA\nCompra Pública Estratégica: Inexistência de contratação pública estratégica\n26 - INFORMAÇÕES ADICIONAIS\nContrato adequado para PME: Não\nCobertura ACP (Acordo dos Contratos Públicos da Organização Mundial do Comércio): Não\n27 - IDENTIFICAÇÃO E CONTACTOS DO ÓRGÃO DE RECURSOS ADMINISTRATIVOS\nDesignação: Conselho de Administração\nEndereço: Av. Nuno Álvares Nº 32 r/c\nCódigo postal: 6000-083\nLocalidade: Castelo Branco\nTelefone: 272340500\nFax: 272340501\nEndereço eletrónico: geral@sm-castelobranco.pt\nPrazo de interposição do recurso: 5 dias\n28 - IDENTIFICAÇÃO DO(S) AUTOR(ES) DE ANÚNCIO\nNome: Engª. Sónia Cristina Cristóvão Mexia\nCargo: Administradora\n419947113",
    "nipc": "680017640",
    "distrito": "Castelo Branco",
    "concelho": "Castelo Branco",
    "freguesia": "Freguesia de Castelo Branco - Castelo Branco",
    "site": "www.sm-castelobranco.pt",
    "email": "geral@sm-castelobranco.pt",
    "designacao_contrato": "Fornecimento continuado de Sacos CãoPeão com logotipo personalizado",
    "descricao": "Fornecimento continuado de Sacos CãoPeão com logotipo personalizado",
    "preco_base": "19.600,00 EUR",
    "prazo_execucao": "24 MESES",
    "prazo_apresentacao_propostas": "11-01-2026 23:59",
    "fundos_eu": "Não",
    "plataforma_eletronica": "ACIN",
    "url_procedimento": "https://www.acingov.pt",
    "autor_nome": "Engª. Sónia Cristina Cristóvão Mexia",
    "autor_cargo": "Administradora"
  },
  {
    "numero_procedimento": "N/A",
    "entidade": "AnÃºncio de procedimento  n.Âº 425/2026  -  DiÃ¡rio da RepÃºblica n.Âº 6/2026, SÃ©rie II de 2026-01-09",
    "link": "https://diariodarepublica.pt/dr/detalhe/contrato-publico/425-1003372817"
  },
  {
    "numero_procedimento": "N/A",
    "entidade": "Município de Idanha-a-Nova",
    "link": "https://diariodarepublica.pt/dr/detalhe/contrato-publico/426-1003372818",
    "detalhes_completos": "1 - IDENTIFICAÇÃO E CONTACTOS DA ENTIDADE ADJUDICANTE\nDesignação da entidade adjudicante: Município de Idanha-a-Nova\nNIPC: 501121030\nServiço/Órgão/Pessoa de contacto: Presidente da Câmara Municipal\nEndereço: Largo do Município\nCódigo postal: 6060-163\nLocalidade: Idanha-a-Nova\nPaís: Portugal\nNUT III: PT16H\nDistrito: Castelo Branco\nConcelho: Idanha-a-Nova\nFreguesia: União das Freguesias de Idanha-a-Nova e Alcafozes\nTelefone: 277200570\nFax: 277200580\nEndereço da Entidade (URL): http://www.cm-idanhanova.pt/\nEndereço Eletrónico: geral@idanha.pt\neDelivery Gateway (URL): https://www.acingov.pt\nFunção da Organização: Adquirente\nNorma jurídica da Entidade Adjudicante: Organismo de direito público\nÁrea de atividade da Autoridade Adjudicante: Serviços públicos das administrações públicas\n2 - JORNAL OFICIAL DA UNIÃO EUROPEIA\nO procedimento a que este anúncio diz respeito também é publicitado no Jornal Oficial da União Europeia? Não\n3 - AVISO\nModelo de Anúncio: Concurso público\nData de Envio do Anúncio: 09-01-2026\n5 - PROCESSO\nTipo de Procedimento: Concurso público\nPreço base do procedimento: Sim\nValor do preço base do procedimento: 1.992.483,87 EUR\nProcedimento com lotes? Não\n6 - OBJETO DO CONTRATO\nNúmero de referência interna: CPE082-2025\nDesignação do contrato: Requalificação Escola Básica e Secundária José Silvestre Ribeiro\nDescrição: Requalificação Escola Básica e Secundária José Silvestre Ribeiro\nTipo de Contrato Principal: Empreitada de Obras Públicas\nTipo de Contrato: Empreitada de Obras Públicas\nClassificação CPV (Vocabulário Comum para os Contratos Públicos)\nObjeto principal\nVocabulário Principal: 45214220\nPreço base s/IVA: 1.992.483,87 EUR\n7 - INDICAÇÕES ADICIONAIS\nO contrato envolve aquisição conjunta (satisfação de várias entidades)? Não\nO contrato é adjudicado por uma central de compras? Não\n8 - TÉCNICAS\nO concurso destina-se à celebração de um acordo-quadro? Inexistência de acordo-quadro\nÉ utilizado um leilão eletrónico? Não\nÉ adotada uma fase de negociação? Não\nSistema de Aquisição Dinâmico: Inexistência de sistema de aquisição dinâmico\n9 - LOCAL DA EXECUÇÃO DO CONTRATO\nLOCAL DA EXECUÇÃO DO CONTRATO (PROCEDIMENTO)\nPaís: Portugal\nNUT III: PT16H\nLocalidade: Idanha-a-Nova\nDistrito: Castelo Branco\nConcelho: Idanha-a-Nova\nFreguesia: União das Freguesias de Idanha-a-Nova e Alcafozes\n10 - PRAZO DE EXECUÇÃO DO CONTRATO\nPrazo de execução do contrato: 540 DIAS\nPrevisão de renovações: Não\n11 - FUNDOS EU\nTêm fundos EU? Sim\n12 - DOCUMENTOS DE HABILITAÇÃO\nHabilitação para o exercício da atividade profissional: Sim\nTipo: Alvará\nDescrição: Nos termos do disposto nos artigos 6.º e 7.º da Lei n.º 41/2015, de 03 de Junho, será exigido o alvará emitido pelo IMPIC, correspondente: À classificação da 5.ª Subcategoria  Estuques, pinturas e outros revestimentos da 1.ª Categoria  Edifícios e património construído, na classe correspondente ao valor global da empreitada\n13 - CONDIÇÕES DE APRESENTAÇÃO\nPlataforma eletrónica utilizada pela entidade adjudicante: ACIN\nURL para Apresentação: https://www.acingov.pt\nAdmissibilidade da apresentação de propostas variantes: Não autorizado\nPrazo para apresentação das propostas: 02-02-2026 23:59\nPrazo durante o qual os concorrentes são obrigados a manter as respetivas propostas: 66 dias a contar do termo do prazo para a apresentação das propostas\nIndicação de Subcontratação na Proposta: Inexistência de indicação de subcontratação\n14 - PRESTAÇÃO DE CAUÇÃO\nPrestação de caução: Sim\nPercentagem: 5%\nDescrição da Garantia Exigida: O valor da caução é de 5.00% do preço contratual.\n15 - FORNECIMENTO DAS PEÇAS DO CONCURSO, APRESENTAÇÃO DE PEDIDOS DE PARTICIPAÇÃO E APRESENTAÇÃO DAS PROPOSTAS\nLink para acesso às peças do concurso (URL): https://www.acingov.pt/acingovprod/2/zonaPublica/zona_publica_c/donwloadProcedurePiece/OTk5NDU5\n20 - OUTROS REQUISITOS\nInformação sobre contratos reservados. Aplica-se a contratos reservados (54º-A)? Não\n21 - CRITÉRIO DE ADJUDICAÇÃO\nMultifator: Não\nMonofator:\nNome: Preço\n24 - CONDIÇÕES DO CONTRATO\nFaturação Eletrónica: Permitido\nObrigação de Subcontratação:\nCódigo da Obrigação de Subcontratação: Não é aplicável nenhuma obrigação de subcontratação.\n25 - COMPRA PÚBLICA ESTRATÉGICA\nCompra Pública Estratégica: Inexistência de contratação pública estratégica\n26 - INFORMAÇÕES ADICIONAIS\nContrato adequado para PME: Sim\nCobertura ACP (Acordo dos Contratos Públicos da Organização Mundial do Comércio): Não\n27 - IDENTIFICAÇÃO E CONTACTOS DO ÓRGÃO DE RECURSOS ADMINISTRATIVOS\nDesignação: Presidente da Câmara Municipal\nEndereço: Largo do Município\nCódigo postal: 6060-163\nLocalidade: Idanha-a-Nova\nTelefone: 277200570\nFax: 277200580\nEndereço eletrónico: geral@idanha.pt\n28 - IDENTIFICAÇÃO DO(S) AUTOR(ES) DE ANÚNCIO\nNome: Elza Maria Martins Gonçalves\nCargo: Presidente da Câmara Municipal de Idanha-a-Nova\n419947288",
    "nipc": "501121030",
    "distrito": "Castelo Branco",
    "concelho": "Idanha-a-Nova",
    "freguesia": "União das Freguesias de Idanha-a-Nova e Alcafozes",
    "site": "http://www.cm-idanhanova.pt/",
    "email": "geral@idanha.pt",
    "designacao_contrato": "Requalificação Escola Básica e Secundária José Silvestre Ribeiro",
    "descricao": "Requalificação Escola Básica e Secundária José Silvestre Ribeiro",
    "preco_base": "1.992.483,87 EUR",
    "prazo_execucao": "540 DIAS",
    "prazo_apresentacao_propostas": "02-02-2026 23:59",
    "fundos_eu": "Sim",
    "plataforma_eletronica": "ACIN",
    "url_procedimento": "https://www.acingov.pt",
    "autor_nome": "Elza Maria Martins Gonçalves",
    "autor_cargo": "Presidente da Câmara Municipal de Idanha-a-Nova"
  },
  {
    "numero_procedimento": "N/A",
    "entidade": "Águas do Tejo Atlântico, SA",
    "link": "https://diariodarepublica.pt/dr/detalhe/contrato-publico/428-1003372819",
    "detalhes_completos": "Alteração do Anúncio de procedimento n.º 30618/2025, de 2025-11-25, com o ID 419814604\n1 - IDENTIFICAÇÃO E CONTACTOS DA ENTIDADE ADJUDICANTE\nDesignação da entidade adjudicante: Águas do Tejo Atlântico, SA\nNIPC: 514387130\nServiço/Órgão/Pessoa de contacto: Direção de Engenharia\nEndereço: ETAR de Alcântara, Av. de Ceuta\nCódigo postal: 1300-254\nLocalidade: Lisboa\nPaís: Portugal\nNUT III: PT170\nDistrito: Lisboa\nConcelho: Lisboa\nFreguesia: Freguesia de Campo de Ourique\nTelefone: 213107900\nFax: 351213107901\nEndereço da Entidade (URL): www.aguasdotejoatlantico.adp.pt\nEndereço Eletrónico: compras_contratacao.adta@adp.pt\neDelivery Gateway (URL): https://www.acingov.pt\nFunção da Organização: Adquirente\nSubfunção da Organização: Organização cujo orçamento é utilizado para pagar o contrato; Organização que executa o pagamento; Organização que fornece informações adicionais sobre o processo de adjudicação; Organização que fornece mais informações sobre os prazos dos procedimentos de recurso; Organização que fornece acesso fora de linha aos documentos do concurso; Organização responsável pelo tratamento das propostas; Organização que recebe as propostas; Organização que trata os pedidos de participação; Organização que recebe pedidos de participação; Organização que fornece mais informações sobre os procedimentos de recurso; Organização que assina o contrato\nNorma jurídica da Entidade Adjudicante: Organismo de direito público\nÁrea de atividade da Entidade Adjudicante: Atividades relacionadas com a água\n2 - JORNAL OFICIAL DA UNIÃO EUROPEIA\nO procedimento a que este anúncio diz respeito também é publicitado no Jornal Oficial da União Europeia? Não\n3 - AVISO\nModelo de Anúncio: Concurso público\nData de Envio do Anúncio: 09-01-2026\n5 - PROCESSO\nTipo de Procedimento: Concurso público\nPreço base do procedimento: Sim\nValor do preço base do procedimento: 2.300.000,00 EUR\nProcedimento com lotes? Não\n6 - OBJETO DO CONTRATO\nNúmero de referência interna: TA_25_131_CP_O_016_DEN\nDesignação do contrato: Empreitada de Reabilitação do Emissário do Jamor - Fase I\nDescrição: Empreitada de Reabilitação do Emissário do Jamor - Fase I\nTipo de Contrato Principal: Empreitada de Obras Públicas\nTipo de Contrato: Empreitada de Obras Públicas\nClassificação CPV (Vocabulário Comum para os Contratos Públicos)\nObjeto principal\nVocabulário Principal: 45232460\nPreço base s/IVA: 2.300.000,00 EUR\n7 - INDICAÇÕES ADICIONAIS\nO contrato envolve aquisição conjunta (satisfação de várias entidades)? Não\nO contrato é adjudicado por uma central de compras? Não\n8 - TÉCNICAS\nO concurso destina-se à celebração de um acordo-quadro? Inexistência de acordo-quadro\nÉ utilizado um leilão eletrónico? Não\nÉ adotada uma fase de negociação? Não\nSistema de Aquisição Dinâmico: Inexistência de sistema de aquisição dinâmico\n9 - LOCAL DA EXECUÇÃO DO CONTRATO\nLOCAL DA EXECUÇÃO DO CONTRATO (PROCEDIMENTO)\nPaís: Portugal\nNUT III: PT170\nLocalidade: União das Freguesias de Algés, Linda-a-Velha e Cruz Quebrada-Dafundo\nDistrito: Lisboa\nConcelho: Oeiras\nFreguesia: União das Freguesias de Algés, Linda-a-Velha e Cruz Quebrada-Dafundo\n10 - PRAZO DE EXECUÇÃO DO CONTRATO\nPrazo de execução do contrato: 365 DIAS\nPrevisão de renovações: Não\n11 - FUNDOS EU\nTêm fundos EU? Não\n12 - DOCUMENTOS DE HABILITAÇÃO\nHabilitação para o exercício da atividade profissional: Sim\nTipo: Alvará\nDescrição: Alvará ou certificado de empreiteiro de obras públicas, contendo as seguintes habilitações:\ni) 6.ª subcategoria (Saneamento básico) da 2.ª categoria (Vias de comunicação, obras de urbanização e outras infraestruturas) da classe correspondente ao valor global da proposta;\nii) 2.ª subcategoria (Movimentação de terras) da 5.ª categoria (Outros trabalhos), da classe correspondente ao valor dos trabalhos especializados que lhe respeite, consoante a parte que a esses trabalhos cabe na proposta.\n13 - CONDIÇÕES DE APRESENTAÇÃO\nPlataforma eletrónica utilizada pela entidade adjudicante: ACIN\nURL para Apresentação: https://www.acingov.pt\nAdmissibilidade da apresentação de propostas variantes: Não autorizado\nPrazo para apresentação das propostas: 28-01-2026 23:59\nPrazo durante o qual os concorrentes são obrigados a manter as respetivas propostas: 120 dias a contar do termo do prazo para a apresentação das propostas\nIndicação de Subcontratação na Proposta: Inexistência de indicação de subcontratação\n14 - PRESTAÇÃO DE CAUÇÃO\nPrestação de caução: Sim\nPercentagem: 5%\nDescrição da Garantia Exigida: O valor da caução é de 5.00% do preço contratual.\n15 - FORNECIMENTO DAS PEÇAS DO CONCURSO, APRESENTAÇÃO DE PEDIDOS DE PARTICIPAÇÃO E APRESENTAÇÃO DAS PROPOSTAS\nLink para acesso às peças do concurso (URL): https://www.acingov.pt/acingovprod/2/zonaPublica/zona_publica_c/donwloadProcedurePiece/OTk4MTY2\n20 - OUTROS REQUISITOS\nInformação sobre contratos reservados. Aplica-se a contratos reservados (54º-A)? Não\n21 - CRITÉRIO DE ADJUDICAÇÃO\nMultifator: Sim\nFator: \nNome: Preço\nPonderação: 50%\nSubfatores: Não\nFator: \nNome: Outros\nOutro Nome: Valia Técnica\nPonderação: 50%\nSubfatores: Sim\nSubfatores: \nNome: Detalhe e consistência do Plano de Trabalhos\nPonderação : 50%; \nNome: Metodologia de execução da obra\nPonderação : 50%; \n24 - CONDIÇÕES DO CONTRATO\nFaturação Eletrónica: Necessário\nObrigação de Subcontratação:\nCódigo da Obrigação de Subcontratação: Não é aplicável nenhuma obrigação de subcontratação.\n25 - COMPRA PÚBLICA ESTRATÉGICA\nCompra Pública Estratégica: Redução dos impactos ambientais\nDescrição do Processo de Adjudicação Estratégico: Cumprimento das disposições legais e regulamentares em vigor sobre ambiente. Em particular, o que respeita à Resolução do Conselho de Ministros n.º 132/2023, de 25 de outubro (Critérios das Compras Públicas Ecológicas). No que respeita ao Regime Geral da Gestão de Resíduos, prevê-se a utilização de, pelo menos, 10% de materiais reciclados ou que incorporem materiais reciclados relativamente à quantidade total de matérias-primas usadas na obra.\nCritérios de contratos Públicos Ecológicos: Critérios de contratação pública ecológica da UE; Critérios de contratação pública ecológica nacional\nCategorias da estratégia nacional: Infraestruturas de tratamento de águas residuais\nContratos Públicos Ecológicos: A transição para uma economia circular\nDiretiva Veículos Não Poluentes: Não\nCritério de Acessibilidade: Os critérios de acessibilidade para as pessoas com deficiência estão incluídos\n26 - INFORMAÇÕES ADICIONAIS\nContrato adequado para PME: Sim\nCobertura ACP (Acordo dos Contratos Públicos da Organização Mundial do Comércio): Não\n27 - IDENTIFICAÇÃO E CONTACTOS DO ÓRGÃO DE RECURSOS ADMINISTRATIVOS\nDesignação: Conselho de Administração\nEndereço: ETAR de Alcântara, Av. de Ceuta\nCódigo postal: 1300-254\nLocalidade: Lisboa\nTelefone: 213107900\nFax: \nEndereço eletrónico: compras_contratacao.adta@adp.pt\nPrazo de interposição do recurso: 5 dias\n28 - IDENTIFICAÇÃO DO(S) AUTOR(ES) DE ANÚNCIO\nNome: Nuno Brôco\nCargo: Presidente do Conselho de Administração\n29 - ALTERAÇÃO\nMotivo da Alteração: Informações atualizadas\nIdentificador da Versão do Anúncio a Alterar: 80c49da6-5b73-4125-847f-a20d96e0c431-01\nIdentificador das Secções Alteradas do Anúncio Anterior: Condições de Apresentação\nDescrição das Alterações: Modificação do prazo para a apresentação de propostas\nAlteração dos Documentos do Concurso: Não\n419947539",
    "nipc": "514387130",
    "distrito": "Lisboa",
    "concelho": "Lisboa",
    "freguesia": "Freguesia de Campo de Ourique",
    "site": "www.aguasdotejoatlantico.adp.pt",
    "email": "compras_contratacao.adta@adp.pt",
    "designacao_contrato": "Empreitada de Reabilitação do Emissário do Jamor - Fase I",
    "descricao": "Empreitada de Reabilitação do Emissário do Jamor - Fase I",
    "preco_base": "2.300.000,00 EUR",
    "prazo_execucao": "365 DIAS",
    "prazo_apresentacao_propostas": "28-01-2026 23:59",
    "fundos_eu": "Não",
    "plataforma_eletronica": "ACIN",
    "url_procedimento": "https://www.acingov.pt",
    "autor_nome": "Nuno Brôco",
    "autor_cargo": "Presidente do Conselho de Administração"
  },
  {
    "numero_procedimento": "N/A",
    "entidade": "AnÃºncio de procedimento  n.Âº 429/2026  -  DiÃ¡rio da RepÃºblica n.Âº 6/2026, SÃ©rie II de 2026-01-09",
    "link": "https://diariodarepublica.pt/dr/detalhe/contrato-publico/429-1003372820"
  },
  {
    "numero_procedimento": "N/A",
    "entidade": "Município de Bragança",
    "link": "https://diariodarepublica.pt/dr/detalhe/contrato-publico/430-1003372821",
    "detalhes_completos": "1 - IDENTIFICAÇÃO E CONTACTOS DA ENTIDADE ADJUDICANTE\nDesignação da entidade adjudicante: Município de Bragança\nNIPC: 506215547\nServiço/Órgão/Pessoa de contacto: Presidente\nEndereço: Forte São João de Deus 5300-263 Bragança\nCódigo postal: 5300-263\nLocalidade: Bragança\nPaís: Portugal\nNUT III: PT11E\nDistrito: Braganca\nConcelho: Bragança\nFreguesia: União das Freguesias de Sé, Santa Maria e Meixedo\nTelefone: 273304216\nFax: 273304299\nEndereço da Entidade (URL): www.cm-braganca.pt\nEndereço Eletrónico: cmb@cm-braganca.pt\neDelivery Gateway (URL): https://www.acingov.pt\nFunção da Organização: Adquirente\nNorma jurídica da Entidade Adjudicante: Organismo de direito público\nÁrea de atividade da Autoridade Adjudicante: Serviços públicos das administrações públicas\n2 - JORNAL OFICIAL DA UNIÃO EUROPEIA\nO procedimento a que este anúncio diz respeito também é publicitado no Jornal Oficial da União Europeia? Não\n3 - AVISO\nModelo de Anúncio: Concurso público\nData de Envio do Anúncio: 09-01-2026\n5 - PROCESSO\nTipo de Procedimento: Concurso público\nPreço base do procedimento: Sim\nValor do preço base do procedimento: 30.000,00 EUR\nProcedimento com lotes? Não\n6 - OBJETO DO CONTRATO\nNúmero de referência interna: 44/2025-CP-DPET\nDesignação do contrato: Aquisição de serviço de transporte e encaminhamento de Sub-Produtos Animais da Categoria M1, M2 e M3 2026 - 2027\nDescrição: Aquisição de serviço de transporte e encaminhamento de Sub-Produtos Animais da Categoria M1, M2 e M3 2026 - 2027\nTipo de Contrato Principal: Aquisição de Serviços\nTipo de Contrato: Aquisição de Serviços\nClassificação CPV (Vocabulário Comum para os Contratos Públicos)\nObjeto principal\nVocabulário Principal: 90511000\nPreço base s/IVA: 30.000,00 EUR\n7 - INDICAÇÕES ADICIONAIS\nO contrato envolve aquisição conjunta (satisfação de várias entidades)? Não\nO contrato é adjudicado por uma central de compras? Não\n8 - TÉCNICAS\nO concurso destina-se à celebração de um acordo-quadro? Inexistência de acordo-quadro\nÉ utilizado um leilão eletrónico? Não\nÉ adotada uma fase de negociação? Não\nSistema de Aquisição Dinâmico: Inexistência de sistema de aquisição dinâmico\n9 - LOCAL DA EXECUÇÃO DO CONTRATO\nLOCAL DA EXECUÇÃO DO CONTRATO (PROCEDIMENTO)\nPaís: Portugal\nNUT III: PT11E\nLocalidade: União das Freguesias de Sé, Santa Maria e Meixedo\nDistrito: Braganca\nConcelho: Bragança\nFreguesia: União das Freguesias de Sé, Santa Maria e Meixedo\n10 - PRAZO DE EXECUÇÃO DO CONTRATO\nPrazo de execução do contrato: 24 MESES\nPrevisão de renovações: Não\n11 - FUNDOS EU\nTêm fundos EU? Não\n12 - DOCUMENTOS DE HABILITAÇÃO\nHabilitação para o exercício da atividade profissional: Não\n13 - CONDIÇÕES DE APRESENTAÇÃO\nPlataforma eletrónica utilizada pela entidade adjudicante: ACIN\nURL para Apresentação: https://www.acingov.pt\nAdmissibilidade da apresentação de propostas variantes: Não autorizado\nPrazo para apresentação das propostas: 15-01-2026 23:59\nPrazo durante o qual os concorrentes são obrigados a manter as respetivas propostas: 66 dias a contar do termo do prazo para a apresentação das propostas\nIndicação de Subcontratação na Proposta: Inexistência de indicação de subcontratação\n14 - PRESTAÇÃO DE CAUÇÃO\nPrestação de caução: Não\n15 - FORNECIMENTO DAS PEÇAS DO CONCURSO, APRESENTAÇÃO DE PEDIDOS DE PARTICIPAÇÃO E APRESENTAÇÃO DAS PROPOSTAS\nLink para acesso às peças do concurso (URL): https://www.acingov.pt/acingovprod/2/zonaPublica/zona_publica_c/donwloadProcedurePiece/MTAzNjEzMQ==\n20 - OUTROS REQUISITOS\nInformação sobre contratos reservados. Aplica-se a contratos reservados (54º-A)? Não\n21 - CRITÉRIO DE ADJUDICAÇÃO\nMultifator: Não\nMonofator:\nNome: Preço\n24 - CONDIÇÕES DO CONTRATO\nFaturação Eletrónica: Permitido\nObrigação de Subcontratação:\nCódigo da Obrigação de Subcontratação: Não é aplicável nenhuma obrigação de subcontratação.\n25 - COMPRA PÚBLICA ESTRATÉGICA\nCompra Pública Estratégica: Inexistência de contratação pública estratégica\n26 - INFORMAÇÕES ADICIONAIS\nContrato adequado para PME: Não\nCobertura ACP (Acordo dos Contratos Públicos da Organização Mundial do Comércio): Não\n27 - IDENTIFICAÇÃO E CONTACTOS DO ÓRGÃO DE RECURSOS ADMINISTRATIVOS\nDesignação: Câmara Municipal de Bragança\nEndereço: Forte S. J. Deus\nCódigo postal: 5300-263\nLocalidade: Bragança\nTelefone: 273304200\nFax: \nEndereço eletrónico: cmb@cm-braganca.pt\nPrazo de interposição do recurso: 5 dias\n28 - IDENTIFICAÇÃO DO(S) AUTOR(ES) DE ANÚNCIO\nNome: Isabel Cristina Fernandes Rodrigues Ferreira\nCargo: Presidente da Câmara Municipal\n419947430",
    "nipc": "506215547",
    "distrito": "Braganca",
    "concelho": "Bragança",
    "freguesia": "União das Freguesias de Sé, Santa Maria e Meixedo",
    "site": "www.cm-braganca.pt",
    "email": "cmb@cm-braganca.pt",
    "designacao_contrato": "Aquisição de serviço de transporte e encaminhamento de Sub-Produtos Animais da Categoria M1, M2 e M3 2026 - 2027",
    "descricao": "Aquisição de serviço de transporte e encaminhamento de Sub-Produtos Animais da Categoria M1, M2 e M3 2026 - 2027",
    "preco_base": "30.000,00 EUR",
    "prazo_execucao": "24 MESES",
    "prazo_apresentacao_propostas": "15-01-2026 23:59",
    "fundos_eu": "Não",
    "plataforma_eletronica": "ACIN",
    "url_procedimento": "https://www.acingov.pt",
    "autor_nome": "Isabel Cristina Fernandes Rodrigues Ferreira",
    "autor_cargo": "Presidente da Câmara Municipal"
  },
  {
    "numero_procedimento": "N/A",
    "entidade": "Freguesia de Rio Maior",
    "link": "https://diariodarepublica.pt/dr/detalhe/contrato-publico/431-1003372822",
    "detalhes_completos": "1 - IDENTIFICAÇÃO E CONTACTOS DA ENTIDADE ADJUDICANTE\nDesignação da entidade adjudicante: Freguesia de Rio Maior\nNIPC: 506806677\nEndereço: Rua Prof Manuel José Ferreira, n.º 70 - R/C\nCódigo postal: 2040-270\nLocalidade: Rio Maior\nPaís: Portugal\nNUT III: PT185\nDistrito: Santarém\nConcelho: Rio Maior\nFreguesia: Todas\nTelefone: +351 243995114\nEndereço Eletrónico: geral@jf-riomaior.pt\neDelivery Gateway (URL): https://community.vortal.biz/public/\nFunção da Organização: Adquirente\nNorma jurídica da Entidade Adjudicante: Organismo de direito público\nÁrea de atividade da Autoridade Adjudicante: Serviços públicos das administrações públicas\n2 - JORNAL OFICIAL DA UNIÃO EUROPEIA\nO procedimento a que este anúncio diz respeito também é publicitado no Jornal Oficial da União Europeia? Não\n3 - AVISO\nModelo de Anúncio: Concurso público\nData de Envio do Anúncio: 09-01-2026\n5 - PROCESSO\nTipo de Procedimento: Concurso público\nPreço base do procedimento: Sim\nValor do preço base do procedimento: 147.000,00 EUR\nProcedimento com lotes? Não\n6 - OBJETO DO CONTRATO\nNúmero de referência interna: 1/2026/FRM\nDesignação do contrato: Aquisição de Serviços de Deservagem em Meio Rural na Freguesia de Rio Maior \nDescrição: Aquisição de Serviços de Deservagem em Meio Rural na Freguesia de Rio Maior \nTipo de Contrato Principal: Aquisição de Serviços\nTipo de Contrato: Aquisição de Serviços\nClassificação CPV (Vocabulário Comum para os Contratos Públicos)\nObjeto principal\nVocabulário Principal: 90610000\nPreço base s/IVA: 147.000,00 EUR\n7 - INDICAÇÕES ADICIONAIS\nO contrato envolve aquisição conjunta (satisfação de várias entidades)? Não\nO contrato é adjudicado por uma central de compras? Não\n8 - TÉCNICAS\nO concurso destina-se à celebração de um acordo-quadro? Inexistência de acordo-quadro\nÉ utilizado um leilão eletrónico? Não\nÉ adotada uma fase de negociação? Não\nSistema de Aquisição Dinâmico: Inexistência de sistema de aquisição dinâmico\n9 - LOCAL DA EXECUÇÃO DO CONTRATO\nLOCAL DA EXECUÇÃO DO CONTRATO (PROCEDIMENTO)\nPaís: Portugal\nNUT III: PT185\nLocalidade: Santarém\nDistrito: Santarém\nConcelho: Rio Maior\nFreguesia: Freguesia de Rio Maior\n10 - PRAZO DE EXECUÇÃO DO CONTRATO\nPrazo de execução do contrato: 730 DIAS\nPrevisão de renovações: Não\n11 - FUNDOS EU\nTêm fundos EU? Não\n12 - DOCUMENTOS DE HABILITAÇÃO\nHabilitação para o exercício da atividade profissional: Não\n13 - CONDIÇÕES DE APRESENTAÇÃO\nPlataforma eletrónica utilizada pela entidade adjudicante: VORTAL\nURL para Apresentação: https://community.vortal.biz/public/\nAdmissibilidade da apresentação de propostas variantes: Não autorizado\nPrazo para apresentação das propostas: 18-01-2026 23:59\nPrazo durante o qual os concorrentes são obrigados a manter as respetivas propostas: 120 dias a contar do termo do prazo para a apresentação das propostas\nIndicação de Subcontratação na Proposta: Inexistência de indicação de subcontratação\n14 - PRESTAÇÃO DE CAUÇÃO\nPrestação de caução: Sim\nPercentagem: 5%\nDescrição da Garantia Exigida: Nos termos do Art. 90.º do CCP\n15 - FORNECIMENTO DAS PEÇAS DO CONCURSO, APRESENTAÇÃO DE PEDIDOS DE PARTICIPAÇÃO E APRESENTAÇÃO DAS PROPOSTAS\nLink para acesso às peças do concurso (URL): https://community.vortal.biz/Public/public-tender-documents/Mml1U1V1WjRnMEdwU3FieWM0cUk5Wmd4cmdyTDlCT1ROejk4L2hZTVRhelB1WDduK3dVN0UydXVmTGx5TytwQTJpcEFGb281UkpoZFNrR1BDMStncXc9PThrNDBh\n20 - OUTROS REQUISITOS\nInformação sobre contratos reservados. Aplica-se a contratos reservados (54º-A)? Não\n21 - CRITÉRIO DE ADJUDICAÇÃO\nMultifator: Não\nMonofator:\nNome: Preço\n24 - CONDIÇÕES DO CONTRATO\nFaturação Eletrónica: Permitido\nObrigação de Subcontratação:\nCódigo da Obrigação de Subcontratação: Não é aplicável nenhuma obrigação de subcontratação.\n25 - COMPRA PÚBLICA ESTRATÉGICA\nCompra Pública Estratégica: Inexistência de contratação pública estratégica\n26 - INFORMAÇÕES ADICIONAIS\nContrato adequado para PME: Sim\nCobertura ACP (Acordo dos Contratos Públicos da Organização Mundial do Comércio): Não\n27 - IDENTIFICAÇÃO E CONTACTOS DO ÓRGÃO DE RECURSOS ADMINISTRATIVOS\nDesignação: Freguesia de Rio Maior\nEndereço: Rua Prof Manuel José Ferreira, n.º 70 - R/C\nCódigo postal: 2040-270\nLocalidade: Rio Maior\nTelefone: +351 243995114\nFax: +351 243992186\nEndereço eletrónico: geral@jf-riomaior.pt\n28 - IDENTIFICAÇÃO DO(S) AUTOR(ES) DE ANÚNCIO\nNome: João Carlos Branco dos Santos Rebocho  \nCargo: Presidente da Junta de Freguesia de Rio Maior\n419947548",
    "nipc": "506806677",
    "distrito": "Santarém",
    "concelho": "Rio Maior",
    "freguesia": "Todas",
    "site": null,
    "email": "geral@jf-riomaior.pt",
    "designacao_contrato": "Aquisição de Serviços de Deservagem em Meio Rural na Freguesia de Rio Maior",
    "descricao": "Aquisição de Serviços de Deservagem em Meio Rural na Freguesia de Rio Maior",
    "preco_base": "147.000,00 EUR",
    "prazo_execucao": "730 DIAS",
    "prazo_apresentacao_propostas": "18-01-2026 23:59",
    "fundos_eu": "Não",
    "plataforma_eletronica": "VORTAL",
    "url_procedimento": "https://community.vortal.biz/public/",
    "autor_nome": "João Carlos Branco dos Santos Rebocho",
    "autor_cargo": "Presidente da Junta de Freguesia de Rio Maior"
  },
  {
    "numero_procedimento": "N/A",
    "entidade": "AnÃºncio de procedimento  n.Âº 432/2026  -  DiÃ¡rio da RepÃºblica n.Âº 6/2026, SÃ©rie II de 2026-01-09",
    "link": "https://diariodarepublica.pt/dr/detalhe/contrato-publico/432-1003372823"
  },
  {
    "numero_procedimento": "N/A",
    "entidade": "Município de Baião",
    "link": "https://diariodarepublica.pt/dr/detalhe/contrato-publico/433-1003372824",
    "detalhes_completos": "1 - IDENTIFICAÇÃO E CONTACTOS DA ENTIDADE ADJUDICANTE\nDesignação da entidade adjudicante: Município de Baião\nNIPC: 506854299\nServiço/Órgão/Pessoa de contacto: Municipio de Baião\nEndereço: Praça Heróis do Ultramar\nCódigo postal: 4640-158\nLocalidade: Campelo - Baião\nPaís: Portugal\nNUT III: PT11C\nDistrito: Porto\nConcelho: Baião\nFreguesia: União das Freguesias de Campelo e Ovil\nTelefone: 255540500\nFax: 255540510\nEndereço da Entidade (URL): www.cm-baiao.pt\nEndereço Eletrónico: compras.publicas@cm-baiao.pt\nFunção da Organização: Adquirente\nNorma jurídica da Entidade Adjudicante: Autoridade local\nÁrea de atividade da Autoridade Adjudicante: Serviços públicos das administrações públicas\n2 - JORNAL OFICIAL DA UNIÃO EUROPEIA\nO procedimento a que este anúncio diz respeito também é publicitado no Jornal Oficial da União Europeia? Não\n3 - AVISO\nModelo de Anúncio: Concurso público\nData de Envio do Anúncio: 09-01-2026\n5 - PROCESSO\nTipo de Procedimento: Concurso público\nPreço base do procedimento: Sim\nValor do preço base do procedimento: 31.756,74 EUR\nProcedimento com lotes? Não\n6 - OBJETO DO CONTRATO\nNúmero de referência interna: 93-2025\nDesignação do contrato: 93-2025-Fornecimento de Leite Escolar até 31 de Dezembro de 2027\nDescrição: Fornecimento de Leite Escolar até 31 de Dezembro de 2027\nTipo de Contrato Principal: Aquisição de Bens Móveis\nTipo de Contrato: Aquisição de Bens Móveis\nClassificação CPV (Vocabulário Comum para os Contratos Públicos)\nObjeto principal\nVocabulário Principal: 15511000\nPreço base s/IVA: 31.756,74 EUR\n7 - INDICAÇÕES ADICIONAIS\nO contrato envolve aquisição conjunta (satisfação de várias entidades)? Não\nO contrato é adjudicado por uma central de compras? Não\n8 - TÉCNICAS\nO concurso destina-se à celebração de um acordo-quadro? Inexistência de acordo-quadro\nÉ utilizado um leilão eletrónico? Não\nÉ adotada uma fase de negociação? Sim\nSistema de Aquisição Dinâmico: Inexistência de sistema de aquisição dinâmico\n9 - LOCAL DA EXECUÇÃO DO CONTRATO\nLOCAL DA EXECUÇÃO DO CONTRATO (PROCEDIMENTO)\nPaís: Portugal\nNUT III: PT11C\nLocalidade: Baião\nDistrito: Porto\nConcelho: Baião\nFreguesia: Todas\n10 - PRAZO DE EXECUÇÃO DO CONTRATO\nPrazo de execução do contrato: 2 ANOS\nPrevisão de renovações: Não\n11 - FUNDOS EU\nTêm fundos EU? Não\n12 - DOCUMENTOS DE HABILITAÇÃO\nHabilitação para o exercício da atividade profissional: Não\n13 - CONDIÇÕES DE APRESENTAÇÃO\nPlataforma eletrónica utilizada pela entidade adjudicante: ANOGOV\nURL para Apresentação: https://www.anogov.com/cm-baiao/faces/\nAdmissibilidade da apresentação de propostas variantes: Não autorizado\nPrazo para apresentação das propostas: 18-01-2026 23:00\nPrazo durante o qual os concorrentes são obrigados a manter as respetivas propostas: 66 dias a contar do termo do prazo para a apresentação das propostas\nApresentação de Catálogo Eletrónico: Necessário\nIndicação de Subcontratação na Proposta: Inexistência de indicação de subcontratação\n14 - PRESTAÇÃO DE CAUÇÃO\nPrestação de caução: Não\n15 - FORNECIMENTO DAS PEÇAS DO CONCURSO, APRESENTAÇÃO DE PEDIDOS DE PARTICIPAÇÃO E APRESENTAÇÃO DAS PROPOSTAS\nLink para acesso às peças do concurso (URL): https://www.anogov.com/cm-baiao/faces/app/acessoDocs.jsp?codigoAcesso=1XrbWf9SOZpEHscBNgMEPJvRZ3Ll8ytZbnyX3k5lCGhsKATLrT\n20 - OUTROS REQUISITOS\nInformação sobre contratos reservados. Aplica-se a contratos reservados (54º-A)? Não\n21 - CRITÉRIO DE ADJUDICAÇÃO\nMultifator: Não\nMonofator:\nNome: Qualidade\n24 - CONDIÇÕES DO CONTRATO\nFaturação Eletrónica: Permitido\nObrigação de Subcontratação:\nCódigo da Obrigação de Subcontratação: Não é aplicável nenhuma obrigação de subcontratação.\n25 - COMPRA PÚBLICA ESTRATÉGICA\nCompra Pública Estratégica: Inexistência de contratação pública estratégica\n26 - INFORMAÇÕES ADICIONAIS\nContrato adequado para PME: Não\nCobertura ACP (Acordo dos Contratos Públicos da Organização Mundial do Comércio): Não\n27 - IDENTIFICAÇÃO E CONTACTOS DO ÓRGÃO DE RECURSOS ADMINISTRATIVOS\nDesignação: Município de Baião\nEndereço: Praça Heróis do Ultramar\nCódigo postal: 4640-158\nLocalidade: Baião\nTelefone: 255540500\nFax: 255540510\nEndereço eletrónico: aprovisionamento@cm-baiao.pt\n28 - IDENTIFICAÇÃO DO(S) AUTOR(ES) DE ANÚNCIO\nNome: Ana Raquel Coelho Azevedo\nCargo: Presidente da Câmara\n419947537",
    "nipc": "506854299",
    "distrito": "Porto",
    "concelho": "Baião",
    "freguesia": "União das Freguesias de Campelo e Ovil",
    "site": "www.cm-baiao.pt",
    "email": "compras.publicas@cm-baiao.pt",
    "designacao_contrato": "93-2025-Fornecimento de Leite Escolar até 31 de Dezembro de 2027",
    "descricao": "Fornecimento de Leite Escolar até 31 de Dezembro de 2027",
    "preco_base": "31.756,74 EUR",
    "prazo_execucao": "2 ANOS",
    "prazo_apresentacao_propostas": "18-01-2026 23:00",
    "fundos_eu": "Não",
    "plataforma_eletronica": "ANOGOV",
    "url_procedimento": "https://www.anogov.com/cm-baiao/faces/",
    "autor_nome": "Ana Raquel Coelho Azevedo",
    "autor_cargo": "Presidente da Câmara"
  },
  {
    "numero_procedimento": "N/A",
    "entidade": "AnÃºncio de procedimento  n.Âº 403/2026  -  DiÃ¡rio da RepÃºblica n.Âº 6/2026, SÃ©rie II de 2026-01-09",
    "link": "https://diariodarepublica.pt/dr/detalhe/contrato-publico/403-1003400075"
  },
  {
    "numero_procedimento": "N/A",
    "entidade": "IAPMEI - Agência para a Competitividade e Inovação, IP",
    "link": "https://diariodarepublica.pt/dr/detalhe/contrato-publico/405-1003400076",
    "detalhes_completos": "1 - IDENTIFICAÇÃO E CONTACTOS DA ENTIDADE ADJUDICANTE\nDesignação da entidade adjudicante: IAPMEI - Agência para a Competitividade e Inovação, IP\nNIPC: 501373357\nServiço/Órgão/Pessoa de contacto: CD IAPMEI\nEndereço: Estrada do Paço do Lumiar, Campus do Lumiar, Edificio A\nCódigo postal: 1649-038\nLocalidade: Lisboa\nPaís: Portugal\nNUT III: PT170\nDistrito: Lisboa\nConcelho: Lisboa\nFreguesia: Freguesia de Lumiar\nTelefone: 213836000\nEndereço da Entidade (URL): www.iapmei.pt/\nEndereço Eletrónico: info@iapmei.pt\neDelivery Gateway (URL): https://www.acingov.pt\nFunção da Organização: Adquirente\nNorma jurídica da Entidade Adjudicante: Organismo de direito público\nÁrea de atividade da Autoridade Adjudicante: Serviços públicos das administrações públicas\n2 - JORNAL OFICIAL DA UNIÃO EUROPEIA\nO procedimento a que este anúncio diz respeito também é publicitado no Jornal Oficial da União Europeia? Sim\n3 - AVISO\nModelo de Anúncio: Concurso público\nData de Envio do Anúncio: 07-01-2026\n5 - PROCESSO\nTipo de Procedimento: Concurso público\nPreço base do procedimento: Sim\nValor do preço base do procedimento: 254.460,00 EUR\nProcedimento com lotes? Não\n6 - OBJETO DO CONTRATO\nNúmero de referência interna: DPCP2025CP57\nDesignação do contrato: Aquisição de serviços de higiene e limpeza para a Agência para a Competitividade e Inovação, I.P. (IAPMEI), para 2026\nDescrição: Aquisição de serviços de higiene e limpeza para a Agência para a Competitividade e Inovação, I.P. (IAPMEI), para 2026\nOpções: Não\nTipo de Contrato Principal: Aquisição de Serviços\nTipo de Contrato: Aquisição de Serviços\nClassificação CPV (Vocabulário Comum para os Contratos Públicos)\nObjeto principal\nVocabulário Principal: 90900000\nPreço base s/IVA: 254.460,00 EUR\n7 - INDICAÇÕES ADICIONAIS\nO contrato envolve aquisição conjunta (satisfação de várias entidades)? Não\nO contrato é adjudicado por uma central de compras? Não\n8 - TÉCNICAS\nO concurso destina-se à celebração de um acordo-quadro? Inexistência de acordo-quadro\nÉ utilizado um leilão eletrónico? Não\nÉ adotada uma fase de negociação? Não\nSistema de Aquisição Dinâmico: Inexistência de sistema de aquisição dinâmico\n9 - LOCAL DA EXECUÇÃO DO CONTRATO\nLOCAL DA EXECUÇÃO DO CONTRATO (PROCEDIMENTO)\nPaís: Portugal\nNUT III: PTZZZ\nLocalidade: Todas\nDistrito: Portugal Continental\nConcelho: Todos\nFreguesia: Todas\n10 - PRAZO DE EXECUÇÃO DO CONTRATO\nPrazo de execução do contrato: 11 MESES\nPrevisão de renovações: Não\n11 - FUNDOS EU\nTêm fundos EU? Não\n12 - DOCUMENTOS DE HABILITAÇÃO\nHabilitação para o exercício da atividade profissional: Não\n13 - CONDIÇÕES DE APRESENTAÇÃO\nPlataforma eletrónica utilizada pela entidade adjudicante: ACIN\nURL para Apresentação: https://www.acingov.pt\nAdmissibilidade da apresentação de propostas variantes: Não autorizado\nPrazo para apresentação das propostas: 06-02-2026 17:00\nPrazo durante o qual os concorrentes são obrigados a manter as respetivas propostas: 66 dias a contar do termo do prazo para a apresentação das propostas\nApresentação de Catálogo Eletrónico: Permitido\nIndicação de Subcontratação na Proposta: Inexistência de indicação de subcontratação\n14 - PRESTAÇÃO DE CAUÇÃO\nPrestação de caução: Não\n15 - FORNECIMENTO DAS PEÇAS DO CONCURSO, APRESENTAÇÃO DE PEDIDOS DE PARTICIPAÇÃO E APRESENTAÇÃO DAS PROPOSTAS\nLink para acesso às peças do concurso (URL): https://www.acingov.pt/acingovprod/2/zonaPublica/zona_publica_c/donwloadProcedurePiece/MTAzNjU1NQ==\n20 - OUTROS REQUISITOS\nInformação sobre contratos reservados. Aplica-se a contratos reservados (54º-A)? Não\n21 - CRITÉRIO DE ADJUDICAÇÃO\nMultifator: Não\nMonofator:\nNome: Preço\n24 - CONDIÇÕES DO CONTRATO\nFaturação Eletrónica: Permitido\nObrigação de Subcontratação:\nCódigo da Obrigação de Subcontratação: Não é aplicável nenhuma obrigação de subcontratação.\n25 - COMPRA PÚBLICA ESTRATÉGICA\nCompra Pública Estratégica: Redução dos impactos ambientais\nDescrição do Processo de Adjudicação Estratégico: Aquisição de serviços de higiene e limpeza\nCritérios de contratos Públicos Ecológicos: Critérios de contratação pública ecológica nacional\nCategorias da estratégia nacional: Serviços de limpeza de interiores\nContratos Públicos Ecológicos: A mitigação das alterações climáticas; A prevenção e o controlo da poluição\nDiretiva Veículos Não Poluentes: Não\nCritério de Acessibilidade: Os critérios de acessibilidade para as pessoas com deficiência não estão incluídos porque o contrato não se destina a pessoas singulares\n26 - INFORMAÇÕES ADICIONAIS\nContrato adequado para PME: Sim\nCobertura ACP (Acordo dos Contratos Públicos da Organização Mundial do Comércio): Não\n27 - IDENTIFICAÇÃO E CONTACTOS DO ÓRGÃO DE RECURSOS ADMINISTRATIVOS\nDesignação: CD IAPMEI\nEndereço: https://www.iapmei.pt/\nCódigo postal: 1649-038\nLocalidade: Lisboa\nTelefone: 213836009\nFax: \nEndereço eletrónico: info@iapmei.pt\n28 - IDENTIFICAÇÃO DO(S) AUTOR(ES) DE ANÚNCIO\nNome: Emanuela Alexandra Pires Monteiro\nCargo: Tecnica Superior\n419947322",
    "nipc": "501373357",
    "distrito": "Lisboa",
    "concelho": "Lisboa",
    "freguesia": "Freguesia de Lumiar",
    "site": "www.iapmei.pt/",
    "email": "info@iapmei.pt",
    "designacao_contrato": "Aquisição de serviços de higiene e limpeza para a Agência para a Competitividade e Inovação, I.P. (IAPMEI), para 2026",
    "descricao": "Aquisição de serviços de higiene e limpeza para a Agência para a Competitividade e Inovação, I.P. (IAPMEI), para 2026",
    "preco_base": "254.460,00 EUR",
    "prazo_execucao": "11 MESES",
    "prazo_apresentacao_propostas": "06-02-2026 17:00",
    "fundos_eu": "Não",
    "plataforma_eletronica": "ACIN",
    "url_procedimento": "https://www.acingov.pt",
    "autor_nome": "Emanuela Alexandra Pires Monteiro",
    "autor_cargo": "Tecnica Superior"
  },
  {
    "numero_procedimento": "N/A",
    "entidade": "AnÃºncio de procedimento  n.Âº 407/2026  -  DiÃ¡rio da RepÃºblica n.Âº 6/2026, SÃ©rie II de 2026-01-09",
    "link": "https://diariodarepublica.pt/dr/detalhe/contrato-publico/407-1003400077"
  },
  {
    "numero_procedimento": "N/A",
    "entidade": "BIKINNOV - Bike Value Innovation Center - Association",
    "link": "https://diariodarepublica.pt/dr/detalhe/contrato-publico/409-1003400078",
    "detalhes_completos": "1 - IDENTIFICAÇÃO E CONTACTOS DA ENTIDADE ADJUDICANTE\nDesignação da entidade adjudicante: BIKINNOV - Bike Value Innovation Center - Association\nNIPC: 516839268\nServiço/Órgão/Pessoa de contacto: BIKiNNOV\nEndereço: Rua da Indústria, 369, Covão, 3750-792 Águeda\nCódigo postal: 3750-792\nLocalidade: Águeda\nPaís: Portugal\nNUT III: PT16D\nDistrito: Aveiro\nConcelho: Águeda\nFreguesia: Freguesia de Valongo do Vouga\nTelefone: 234248960\nEndereço da Entidade (URL): www.bikinnov.pt\nEndereço Eletrónico: geral@bikinnov.pt\neDelivery Gateway (URL): https://www.acingov.pt\nFunção da Organização: Adquirente\nNorma jurídica da Entidade Adjudicante: Organismo de direito público\nÁrea de atividade da Autoridade Adjudicante: Serviços públicos das administrações públicas\n2 - JORNAL OFICIAL DA UNIÃO EUROPEIA\nO procedimento a que este anúncio diz respeito também é publicitado no Jornal Oficial da União Europeia? Sim\n3 - AVISO\nModelo de Anúncio: Concurso público\nData de Envio do Anúncio: 07-01-2026\n5 - PROCESSO\nTipo de Procedimento: Concurso público\nPreço base do procedimento: Sim\nValor do preço base do procedimento: 250.000,00 EUR\nProcedimento com lotes? Não\n6 - OBJETO DO CONTRATO\nNúmero de referência interna: 82-111-CTI-25\nDesignação do contrato: Eixo Desenvolvimento de Produto  Capacitação EMC\nDescrição: Eixo Desenvolvimento de Produto  Capacitação EMC\nOpções: Não\nTipo de Contrato Principal: Aquisição de Bens Móveis\nTipo de Contrato: Aquisição de Bens Móveis\nClassificação CPV (Vocabulário Comum para os Contratos Públicos)\nObjeto principal\nVocabulário Principal: 42990000\nPreço base s/IVA: 250.000,00 EUR\n7 - INDICAÇÕES ADICIONAIS\nO contrato envolve aquisição conjunta (satisfação de várias entidades)? Não\nO contrato é adjudicado por uma central de compras? Não\n8 - TÉCNICAS\nO concurso destina-se à celebração de um acordo-quadro? Inexistência de acordo-quadro\nÉ utilizado um leilão eletrónico? Não\nÉ adotada uma fase de negociação? Não\nSistema de Aquisição Dinâmico: Inexistência de sistema de aquisição dinâmico\n9 - LOCAL DA EXECUÇÃO DO CONTRATO\nLOCAL DA EXECUÇÃO DO CONTRATO (PROCEDIMENTO)\nPaís: Portugal\nNUT III: PT16D\nLocalidade: Freguesia de Valongo do Vouga\nDistrito: Aveiro\nConcelho: Águeda\nFreguesia: Freguesia de Valongo do Vouga\n10 - PRAZO DE EXECUÇÃO DO CONTRATO\nPrazo de execução do contrato: 6 MESES\nPrevisão de renovações: Não\n11 - FUNDOS EU\nTêm fundos EU? Sim\n12 - DOCUMENTOS DE HABILITAÇÃO\nHabilitação para o exercício da atividade profissional: Não\n13 - CONDIÇÕES DE APRESENTAÇÃO\nPlataforma eletrónica utilizada pela entidade adjudicante: ACIN\nURL para Apresentação: https://www.acingov.pt\nAdmissibilidade da apresentação de propostas variantes: Não autorizado\nPrazo para apresentação das propostas: 06-02-2026 17:00\nPrazo durante o qual os concorrentes são obrigados a manter as respetivas propostas: 90 dias a contar do termo do prazo para a apresentação das propostas\nApresentação de Catálogo Eletrónico: Permitido\nIndicação de Subcontratação na Proposta: Inexistência de indicação de subcontratação\n14 - PRESTAÇÃO DE CAUÇÃO\nPrestação de caução: Não\n15 - FORNECIMENTO DAS PEÇAS DO CONCURSO, APRESENTAÇÃO DE PEDIDOS DE PARTICIPAÇÃO E APRESENTAÇÃO DAS PROPOSTAS\nLink para acesso às peças do concurso (URL): https://www.acingov.pt/acingovprod/2/zonaPublica/zona_publica_c/donwloadProcedurePiece/MTAxMTUyMQ==\n20 - OUTROS REQUISITOS\nInformação sobre contratos reservados. Aplica-se a contratos reservados (54º-A)? Não\n21 - CRITÉRIO DE ADJUDICAÇÃO\nMultifator: Não\nMonofator:\nNome: Preço\n24 - CONDIÇÕES DO CONTRATO\nFaturação Eletrónica: Permitido\nObrigação de Subcontratação:\nCódigo da Obrigação de Subcontratação: Não é aplicável nenhuma obrigação de subcontratação.\n25 - COMPRA PÚBLICA ESTRATÉGICA\nCompra Pública Estratégica: Inexistência de contratação pública estratégica\n26 - INFORMAÇÕES ADICIONAIS\nContrato adequado para PME: Sim\nCobertura ACP (Acordo dos Contratos Públicos da Organização Mundial do Comércio): Não\n27 - IDENTIFICAÇÃO E CONTACTOS DO ÓRGÃO DE RECURSOS ADMINISTRATIVOS\nDesignação: BIKiNNOV\nEndereço: Rua da Indústria, 369, Covão, 3750-792 Águeda\nCódigo postal: 3750-792\nLocalidade: Águeda\nTelefone: 234248960\nFax: \nEndereço eletrónico: geral@bikinnov.pt\nPrazo de interposição do recurso: 10 dias\n28 - IDENTIFICAÇÃO DO(S) AUTOR(ES) DE ANÚNCIO\nNome: Inês Tavares\nCargo: Gestora Financeira de Projetos\n419947347",
    "nipc": "516839268",
    "distrito": "Aveiro",
    "concelho": "Águeda",
    "freguesia": "Freguesia de Valongo do Vouga",
    "site": "www.bikinnov.pt",
    "email": "geral@bikinnov.pt",
    "designacao_contrato": "Eixo Desenvolvimento de Produto  Capacitação EMC",
    "descricao": "Eixo Desenvolvimento de Produto  Capacitação EMC",
    "preco_base": "250.000,00 EUR",
    "prazo_execucao": "6 MESES",
    "prazo_apresentacao_propostas": "06-02-2026 17:00",
    "fundos_eu": "Sim",
    "plataforma_eletronica": "ACIN",
    "url_procedimento": "https://www.acingov.pt",
    "autor_nome": "Inês Tavares",
    "autor_cargo": "Gestora Financeira de Projetos"
  },
  {
    "numero_procedimento": "N/A",
    "entidade": "Municípia, Empresa de Cartografia e Sistemas de Informação, SA",
    "link": "https://diariodarepublica.pt/dr/detalhe/contrato-publico/411-1003400079",
    "detalhes_completos": "1 - IDENTIFICAÇÃO E CONTACTOS DA ENTIDADE ADJUDICANTE\nDesignação da entidade adjudicante: Municípia, Empresa de Cartografia e Sistemas de Informação, SA\nNIPC: 504475606\nEndereço: Av. Prof. Dr. Cavaco Silva, Edifício Ciência II, nº. 11, 3º B, Taguspark\nCódigo postal: 2740-120\nLocalidade: Lisboa\nPaís: Portugal\nNUT III: PT170\nDistrito: Lisboa\nConcelho: Oeiras\nFreguesia: Freguesia de Porto Salvo\nTelefone: 214228200\nFax: 214228205\nEndereço da Entidade (URL): www.municipia.pt\nEndereço Eletrónico: info@municipia.pt\neDelivery Gateway (URL): https://community.vortal.biz/public/\nFunção da Organização: Adquirente\nNorma jurídica da Entidade Adjudicante: Autoridade da administração central\nÁrea de atividade da Autoridade Adjudicante: Serviços públicos das administrações públicas\n2 - JORNAL OFICIAL DA UNIÃO EUROPEIA\nO procedimento a que este anúncio diz respeito também é publicitado no Jornal Oficial da União Europeia? Sim\n3 - AVISO\nModelo de Anúncio: Concurso público\nData de Envio do Anúncio: 07-01-2026\n5 - PROCESSO\nTipo de Procedimento: Concurso público\nPreço base do procedimento: Não\nProcedimento com lotes? Sim\nNº Máx. de Lotes Autorizado: 5\nNúmero máximo de lotes que podem ser adjudicados a um concorrente: 5\n6 - OBJETO DO CONTRATO\nNúmero de referência interna: CNCM-AQ/120/2026\nDesignação do contrato: Acordo Quadro para Aquisição de Bens para a Proteção da Pele para uso ocupacional\nDescrição: CNCM-AQ/120/2026 - Acordo Quadro para Aquisição de Bens para a Proteção da Pele para uso ocupacional\nOpções: Não\nTipo de Contrato Principal: Aquisição de Bens Móveis\nTipo de Contrato: Aquisição de Bens Móveis\nClassificação CPV (Vocabulário Comum para os Contratos Públicos)\nObjeto principal\nVocabulário Principal: 33711500\nPreço base s/IVA: 1.023,00 EUR\nLotes: \nNº: LOT-0001\nDescrição do Lote: Lote 1\nValor Estimado do Lote: 348,00 EUR\nClassificação CPV (Vocabulário Comum para os Contratos Públicos)\nObjeto principal\nVocabulário Principal: 33711500\nNº: LOT-0002\nDescrição do Lote: Lote 2\nValor Estimado do Lote: 215,00 EUR\nClassificação CPV (Vocabulário Comum para os Contratos Públicos)\nObjeto principal\nVocabulário Principal: 33711500\nNº: LOT-0003\nDescrição do Lote: Lote 3\nValor Estimado do Lote: 100,00 EUR\nClassificação CPV (Vocabulário Comum para os Contratos Públicos)\nObjeto principal\nVocabulário Principal: 33711500\nNº: LOT-0004\nDescrição do Lote: Lote 4\nValor Estimado do Lote: 73,00 EUR\nClassificação CPV (Vocabulário Comum para os Contratos Públicos)\nObjeto principal\nVocabulário Principal: 33711500\nNº: LOT-0005\nDescrição do Lote: Lote 5\nValor Estimado do Lote: 287,00 EUR\nClassificação CPV (Vocabulário Comum para os Contratos Públicos)\nObjeto principal\nVocabulário Principal: 33711500\n7 - INDICAÇÕES ADICIONAIS\nO contrato envolve aquisição conjunta (satisfação de várias entidades)? Não\nO contrato é adjudicado por uma central de compras? Não\n8 - TÉCNICAS\nO concurso destina-se à celebração de um acordo-quadro? Acordo-quadro, sem reabertura de concurso\nModalidade: Com uma entidade\nPrazo de vigência: \nValor estimado: Sim\nPara Acordo-Quadro — valor total máximo estimado para toda a duração do Acordo-Quadro: 1.023,00 EUR\nÉ utilizado um leilão eletrónico? Não\nÉ adotada uma fase de negociação? Não\nSistema de Aquisição Dinâmico: Inexistência de sistema de aquisição dinâmico\n9 - LOCAL DA EXECUÇÃO DO CONTRATO\nLOCAL DA EXECUÇÃO DO CONTRATO (PROCEDIMENTO)\nPaís: Portugal\nNUT III: PT170\nLocalidade: Lisboa\nDistrito: Lisboa\nConcelho: Oeiras\nFreguesia: Freguesia de Porto Salvo\nLOCAL DA EXECUÇÃO DO CONTRATO (LOTE)\nIdentificador do Lote: LOT-0001; LOT-0002; LOT-0003; LOT-0004; LOT-0005\nPaís: Portugal\nNUT III: PT170\nLocalidade: Lisboa\nDistrito: Lisboa\nConcelho: Oeiras\nFreguesia: Freguesia de Porto Salvo\n10 - PRAZO DE EXECUÇÃO DO CONTRATO\nIdentificador do Lote: LOT-0001; LOT-0002; LOT-0003; LOT-0004; LOT-0005\nPrazo de execução do contrato: 24 MESES\nPrevisão de renovações: Sim\nIndicar número máximo de renovações: 1\nPrazo de renovações diferente do prazo inicial: Não\n11 - FUNDOS EU\nIdentificador do Lote: LOT-0001; LOT-0002; LOT-0003; LOT-0004; LOT-0005\nTêm fundos EU? Não\n12 - DOCUMENTOS DE HABILITAÇÃO\nHabilitação para o exercício da atividade profissional: Sim\nTipo: Outros\nDescrição - Outros: Ver peças do procedimento\nDescrição: Não aplicável\n13 - CONDIÇÕES DE APRESENTAÇÃO\nPlataforma eletrónica utilizada pela entidade adjudicante: VORTAL\nURL para Apresentação: https://community.vortal.biz/public/\nAdmissibilidade da apresentação de propostas variantes: Não autorizado\nPrazo para apresentação das propostas: 10-02-2026 23:59\nPrazo durante o qual os concorrentes são obrigados a manter as respetivas propostas: 90 dias a contar do termo do prazo para a apresentação das propostas\nApresentação de Catálogo Eletrónico: Permitido\nIndicação de Subcontratação na Proposta: Inexistência de indicação de subcontratação\n14 - PRESTAÇÃO DE CAUÇÃO\nPrestação de caução: Não\n15 - FORNECIMENTO DAS PEÇAS DO CONCURSO, APRESENTAÇÃO DE PEDIDOS DE PARTICIPAÇÃO E APRESENTAÇÃO DAS PROPOSTAS\nLink para acesso às peças do concurso (URL): https://community.vortal.biz/Public/public-tender-documents/aExCK0s5dkpMQzEvQzQ1eDdMbXVRWHE4K3ROTDh5SnNRZDRiclk1RWxIMldwUkNkRjduMjBnSS9OekxZTDUxcUovRnpINGx0TzFsVG96cjlGK1kzRnc9PWkzQ2xq\n20 - OUTROS REQUISITOS\nIdentificador do Lote: LOT-0001; LOT-0002; LOT-0003; LOT-0004; LOT-0005\nInformação sobre contratos reservados. Aplica-se a contratos reservados (54º-A)? Não\n21 - CRITÉRIO DE ADJUDICAÇÃO\nO Critério de adjudicação é diferenciado por lote? Não\nMultifator: Não\nMonofator:\nNome: Outros\nOutro nome: Preço\n24 - CONDIÇÕES DO CONTRATO\nIdentificador do Lote: LOT-0001; LOT-0002; LOT-0003; LOT-0004; LOT-0005\nFaturação Eletrónica: Permitido\nObrigação de Subcontratação:\nCódigo da Obrigação de Subcontratação: Não é aplicável nenhuma obrigação de subcontratação.\n25 - COMPRA PÚBLICA ESTRATÉGICA\nCompra Pública Estratégica: Inexistência de contratação pública estratégica\n26 - INFORMAÇÕES ADICIONAIS\nIdentificador do Lote: LOT-0001; LOT-0002; LOT-0003; LOT-0004; LOT-0005\nContrato adequado para PME: Sim\nCobertura ACP (Acordo dos Contratos Públicos da Organização Mundial do Comércio): Não\n27 - IDENTIFICAÇÃO E CONTACTOS DO ÓRGÃO DE RECURSOS ADMINISTRATIVOS\nDesignação: Municípia, Empresa de Cartografia e Sistemas de Informação, S.A.\nEndereço: Av. Prof. Dr. Cavaco Silva, Edifício Ciência II, nº. 11, 3º B, Taguspark\nCódigo postal: 2740-120\nLocalidade: Oeiras\nTelefone: +351 214228209\nFax: +351 000000000\nEndereço eletrónico: info@centralconnect.pt\n28 - IDENTIFICAÇÃO DO(S) AUTOR(ES) DE ANÚNCIO\nNome: Nuno Marques\nCargo: Diretor da CONNECT\n419947365",
    "nipc": "504475606",
    "distrito": "Lisboa",
    "concelho": "Oeiras",
    "freguesia": "Freguesia de Porto Salvo",
    "site": "www.municipia.pt",
    "email": "info@municipia.pt",
    "designacao_contrato": "Acordo Quadro para Aquisição de Bens para a Proteção da Pele para uso ocupacional",
    "descricao": "CNCM-AQ/120/2026 - Acordo Quadro para Aquisição de Bens para a Proteção da Pele para uso ocupacional",
    "preco_base": "1.023,00 EUR",
    "prazo_execucao": "24 MESES",
    "prazo_apresentacao_propostas": "10-02-2026 23:59",
    "fundos_eu": "Não",
    "plataforma_eletronica": "VORTAL",
    "url_procedimento": "https://community.vortal.biz/public/",
    "autor_nome": "Nuno Marques",
    "autor_cargo": "Diretor da CONNECT"
  },
  {
    "numero_procedimento": "N/A",
    "entidade": "Comunidade Intermunicipal do Alto Alentejo",
    "link": "https://diariodarepublica.pt/dr/detalhe/contrato-publico/413-1003400080",
    "detalhes_completos": "Alteração do Anúncio de procedimento n.º 32397/2025, de 2025-12-15, com o ID 419876902\n1 - IDENTIFICAÇÃO E CONTACTOS DA ENTIDADE ADJUDICANTE\nDesignação da entidade adjudicante: Comunidade Intermunicipal do Alto Alentejo\nNIPC: 509020690\nServiço/Órgão/Pessoa de contacto: Central de Compras do Conselho Intermunicipal do Alto Alentejo\nEndereço: Rua 19 de Junho, nº26\nCódigo postal: 7300-155\nLocalidade: Portalegre\nPaís: Portugal\nNUT III: PT186\nDistrito: Portalegre\nConcelho: Portalegre\nFreguesia: União das Freguesias da Sé e São Lourenço\nTelefone: 245301440\nFax: 245301449\nEndereço da Entidade (URL): www.cimaa.pt\nEndereço Eletrónico: geral@cimaa.pt\neDelivery Gateway (URL): https://community.vortal.biz/public/\nFunção da Organização: Adquirente\nNorma jurídica da Entidade Adjudicante: Autoridade da administração central\nÁrea de atividade da Autoridade Adjudicante: Serviços públicos das administrações públicas\n2 - JORNAL OFICIAL DA UNIÃO EUROPEIA\nO procedimento a que este anúncio diz respeito também é publicitado no Jornal Oficial da União Europeia? Sim\n3 - AVISO\nModelo de Anúncio: Concurso público\nData de Envio do Anúncio: 07-01-2026\n5 - PROCESSO\nTipo de Procedimento: Concurso público\nPreço base do procedimento: Sim\nValor do preço base do procedimento: 1.800.000,00 EUR\nProcedimento com lotes? Não\n6 - OBJETO DO CONTRATO\nNúmero de referência interna: 2025/300.10.005/311\nDesignação do contrato: Fornecimento de PGU e Verticais de Smart Cities\nDescrição: A aquisição de uma Plataforma de Gestão Urbana – PGU, e dez verticais de Smart Cities para a Comunidade Intermunicipal do Alto Alentejo. O projeto tem enquadramento no Aviso N.º 01/C19-i08/2024 — Aquisição e Desenvolvimento de Plataformas de Gestão Urbana, no âmbito do investimento C19-i08 Territórios Inteligentes – AMA | Estratégia Nacional dos Territórios Inteligentes, datado de 16 de setembro de 2024.\nOpções: Não\nTipo de Contrato Principal: Aquisição de Serviços\nTipo de Contrato: Aquisição de Serviços\nClassificação CPV (Vocabulário Comum para os Contratos Públicos)\nObjeto principal\nVocabulário Principal: 72230000\nPreço base s/IVA: 1.800.000,00 EUR\n7 - INDICAÇÕES ADICIONAIS\nO contrato envolve aquisição conjunta (satisfação de várias entidades)? Não\nO contrato é adjudicado por uma central de compras? Sim\n8 - TÉCNICAS\nO concurso destina-se à celebração de um acordo-quadro? Inexistência de acordo-quadro\nÉ utilizado um leilão eletrónico? Não\nÉ adotada uma fase de negociação? Não\nSistema de Aquisição Dinâmico: Inexistência de sistema de aquisição dinâmico\n9 - LOCAL DA EXECUÇÃO DO CONTRATO\nLOCAL DA EXECUÇÃO DO CONTRATO (PROCEDIMENTO)\nPaís: Portugal\nNUT III: PT186\nLocalidade: Portalegre\nDistrito: Portalegre\nConcelho: Portalegre\nFreguesia: União das Freguesias da Sé e São Lourenço\n10 - PRAZO DE EXECUÇÃO DO CONTRATO\nPrazo de execução do contrato: 30 DIAS\nPrevisão de renovações: Não\n11 - FUNDOS EU\nTêm fundos EU? Sim\n12 - DOCUMENTOS DE HABILITAÇÃO\nHabilitação para o exercício da atividade profissional: Não\n13 - CONDIÇÕES DE APRESENTAÇÃO\nPlataforma eletrónica utilizada pela entidade adjudicante: VORTAL\nURL para Apresentação: https://community.vortal.biz/public/\nAdmissibilidade da apresentação de propostas variantes: Não autorizado\nPrazo para apresentação das propostas: 17-01-2026 23:59\nPrazo durante o qual os concorrentes são obrigados a manter as respetivas propostas: 120 dias a contar do termo do prazo para a apresentação das propostas\nApresentação de Catálogo Eletrónico: Permitido\nIndicação de Subcontratação na Proposta: Inexistência de indicação de subcontratação\n14 - PRESTAÇÃO DE CAUÇÃO\nPrestação de caução: Sim\nPercentagem: 5%\nDescrição da Garantia Exigida: De acordo com o Caderno de Encargos\n15 - FORNECIMENTO DAS PEÇAS DO CONCURSO, APRESENTAÇÃO DE PEDIDOS DE PARTICIPAÇÃO E APRESENTAÇÃO DAS PROPOSTAS\nLink para acesso às peças do concurso (URL): https://community.vortal.biz/Public/public-tender-documents/MkI2WkpTV0ZKVXZzS2V5NFRmQnJUN1lRQUVPZG43WThTVC81R0hBNHBEeWFKcGQ0aXhLTmNiWWpwdlgrK0pLMGZQbldvTXlLYThETkFFUTNKUFY1bXc9PWxYRGow\n20 - OUTROS REQUISITOS\nInformação sobre contratos reservados. Aplica-se a contratos reservados (54º-A)? Não\n21 - CRITÉRIO DE ADJUDICAÇÃO\nMultifator: Sim\nFator: \nNome: Preço\nPonderação: 60%\nSubfatores: Não\nFator: \nNome: Qualidade\nPonderação: 40%\nSubfatores: Sim\nSubfatores: \nNome: Capacitação da Equipa de Gestão de Projeto \nPonderação : 30%; \nNome: Certificação de Qualidade do Concorrente \nPonderação : 30%; \nNome: Experiência do Concorrente na Implementação de Projetos Similares\nPonderação : 25%; \nNome: Metodologia e Qualidade Técnica da Proposta \nPonderação : 15%; \n24 - CONDIÇÕES DO CONTRATO\nFaturação Eletrónica: Permitido\nObrigação de Subcontratação:\nCódigo da Obrigação de Subcontratação: Não é aplicável nenhuma obrigação de subcontratação.\n25 - COMPRA PÚBLICA ESTRATÉGICA\nCompra Pública Estratégica: Inexistência de contratação pública estratégica\n26 - INFORMAÇÕES ADICIONAIS\nContrato adequado para PME: Sim\nCobertura ACP (Acordo dos Contratos Públicos da Organização Mundial do Comércio): Não\n27 - IDENTIFICAÇÃO E CONTACTOS DO ÓRGÃO DE RECURSOS ADMINISTRATIVOS\nDesignação: Conselho Intermunicipal do Alto Alentejo\nEndereço: Rua 19 de Junho, nº26\nCódigo postal: 7300-155\nLocalidade: Portalegre\nTelefone: +351 245301440\nFax: +351 245301440\nEndereço eletrónico: cc@cimaa.pt\n28 - IDENTIFICAÇÃO DO(S) AUTOR(ES) DE ANÚNCIO\nNome: Nuno Samelo\nCargo: Jurista - Técnico Superior\n29 - ALTERAÇÃO\nMotivo da Alteração: Informações atualizadas\nIdentificador da Versão do Anúncio a Alterar: c1ba0200-72a5-44eb-98ba-827668470cae-01\nIdentificador das Secções Alteradas do Anúncio Anterior: Aviso\nDescrição das Alterações: Prazo alterado ao abrigo do artigo 64.º do CCP\nAlteração dos Documentos do Concurso: Sim\nData de alteração dos documentos do concurso: 07-01-2026\n419947368",
    "nipc": "509020690",
    "distrito": "Portalegre",
    "concelho": "Portalegre",
    "freguesia": "União das Freguesias da Sé e São Lourenço",
    "site": "www.cimaa.pt",
    "email": "geral@cimaa.pt",
    "designacao_contrato": "Fornecimento de PGU e Verticais de Smart Cities",
    "descricao": "A aquisição de uma Plataforma de Gestão Urbana – PGU, e dez verticais de Smart Cities para a Comunidade Intermunicipal do Alto Alentejo. O projeto tem enquadramento no Aviso N.º 01/C19-i08/2024 — Aquisição e Desenvolvimento de Plataformas de Gestão Urbana, no âmbito do investimento C19-i08 Territórios Inteligentes – AMA | Estratégia Nacional dos Territórios Inteligentes, datado de 16 de setembro de 2024.",
    "preco_base": "1.800.000,00 EUR",
    "prazo_execucao": "30 DIAS",
    "prazo_apresentacao_propostas": "17-01-2026 23:59",
    "fundos_eu": "Sim",
    "plataforma_eletronica": "VORTAL",
    "url_procedimento": "https://community.vortal.biz/public/",
    "autor_nome": "Nuno Samelo",
    "autor_cargo": "Jurista - Técnico Superior"
  },
  {
    "numero_procedimento": "N/A",
    "entidade": "Unidade Local de Saúde do Alto Ave, EPE",
    "link": "https://diariodarepublica.pt/dr/detalhe/contrato-publico/415-1003400081",
    "detalhes_completos": "1 - IDENTIFICAÇÃO E CONTACTOS DA ENTIDADE ADJUDICANTE\nDesignação da entidade adjudicante: Unidade Local de Saúde do Alto Ave, EPE\nNIPC: 508080827\nEndereço: Rua dos Cutileiros, Creixomil\nCódigo postal: 4835-044\nLocalidade: Guimarães\nPaís: Portugal\nNUT III: PT119\nDistrito: Braga\nConcelho: Guimarães\nFreguesia: Todas\nTelefone: 253540330\nFax: 253513592\nEndereço da Entidade (URL): http://www.hospitaldeguimaraes.min-saude.pt/\nEndereço Eletrónico: aprovisionamento@hospitaldeguimaraes.min-saude.pt\neDelivery Gateway (URL): https://community.vortal.biz/public/\nFunção da Organização: Adquirente\nNorma jurídica da Entidade Adjudicante: Organismo de direito público\nÁrea de atividade da Autoridade Adjudicante: Saúde\n2 - JORNAL OFICIAL DA UNIÃO EUROPEIA\nO procedimento a que este anúncio diz respeito também é publicitado no Jornal Oficial da União Europeia? Sim\n3 - AVISO\nModelo de Anúncio: Concurso público\nData de Envio do Anúncio: 07-01-2026\n5 - PROCESSO\nTipo de Procedimento: Concurso público\nPreço base do procedimento: Sim\nValor do preço base do procedimento: 338.915,00 EUR\nProcedimento com lotes? Sim\nNº Máx. de Lotes Autorizado: 3\nNúmero máximo de lotes que podem ser adjudicados a um concorrente: 3\n6 - OBJETO DO CONTRATO\nNúmero de referência interna:  CP/0016/2026\nDesignação do contrato: Próteses Totais da Anca \nDescrição:  CP/0016/2026-Próteses Totais da Anca \nOpções: Não\nTipo de Contrato Principal: Aquisição de Bens Móveis\nTipo de Contrato: Aquisição de Bens Móveis\nClassificação CPV (Vocabulário Comum para os Contratos Públicos)\nObjeto principal\nVocabulário Principal: 33100000\nPreço base s/IVA: 338.915,00 EUR\nLotes: \nNº: LOT-0001\nDescrição do Lote: Lote 1\nPreço base s/IVA: 255.035,00 EUR\nClassificação CPV (Vocabulário Comum para os Contratos Públicos)\nObjeto principal\nVocabulário Principal: 33100000\nNº: LOT-0002\nDescrição do Lote: Lote 2\nPreço base s/IVA: 34.020,00 EUR\nClassificação CPV (Vocabulário Comum para os Contratos Públicos)\nObjeto principal\nVocabulário Principal: 33100000\nNº: LOT-0003\nDescrição do Lote: Lote 3\nPreço base s/IVA: 49.860,00 EUR\nClassificação CPV (Vocabulário Comum para os Contratos Públicos)\nObjeto principal\nVocabulário Principal: 33100000\n7 - INDICAÇÕES ADICIONAIS\nO contrato envolve aquisição conjunta (satisfação de várias entidades)? Não\nO contrato é adjudicado por uma central de compras? Não\n8 - TÉCNICAS\nO concurso destina-se à celebração de um acordo-quadro? Inexistência de acordo-quadro\nÉ utilizado um leilão eletrónico? Não\nÉ adotada uma fase de negociação? Não\nSistema de Aquisição Dinâmico: Inexistência de sistema de aquisição dinâmico\n9 - LOCAL DA EXECUÇÃO DO CONTRATO\nLOCAL DA EXECUÇÃO DO CONTRATO (PROCEDIMENTO)\nPaís: Portugal\nNUT III: PT119\nLocalidade: Braga\nDistrito: Braga\nConcelho: Guimarães\nFreguesia: Freguesia de Creixomil - Guimarães\nLOCAL DA EXECUÇÃO DO CONTRATO (LOTE)\nIdentificador do Lote: LOT-0001; LOT-0002; LOT-0003\nPaís: Portugal\nNUT III: PT119\nLocalidade: Braga\nDistrito: Braga\nConcelho: Guimarães\nFreguesia: Freguesia de Creixomil - Guimarães\n10 - PRAZO DE EXECUÇÃO DO CONTRATO\nIdentificador do Lote: LOT-0001; LOT-0002; LOT-0003\nPrazo de execução do contrato: 12 MESES\nPrevisão de renovações: Não\n11 - FUNDOS EU\nIdentificador do Lote: LOT-0001; LOT-0002; LOT-0003\nTêm fundos EU? Não\n12 - DOCUMENTOS DE HABILITAÇÃO\nHabilitação para o exercício da atividade profissional: Não\n13 - CONDIÇÕES DE APRESENTAÇÃO\nPlataforma eletrónica utilizada pela entidade adjudicante: VORTAL\nURL para Apresentação: https://community.vortal.biz/public/\nAdmissibilidade da apresentação de propostas variantes: Não autorizado\nPrazo para apresentação das propostas: 09-02-2026 17:00\nPrazo durante o qual os concorrentes são obrigados a manter as respetivas propostas: 180 dias a contar do termo do prazo para a apresentação das propostas\nApresentação de Catálogo Eletrónico: Permitido\nIndicação de Subcontratação na Proposta: Inexistência de indicação de subcontratação\n14 - PRESTAÇÃO DE CAUÇÃO\nPrestação de caução: Não\n15 - FORNECIMENTO DAS PEÇAS DO CONCURSO, APRESENTAÇÃO DE PEDIDOS DE PARTICIPAÇÃO E APRESENTAÇÃO DAS PROPOSTAS\nLink para acesso às peças do concurso (URL): https://community.vortal.biz/Public/public-tender-documents/RGdBUWtOdXllWXRDNjEvampaS05GY3VuSHZ0Yy9OZUlNN1ZUQUVJWEUvY285bW8xa0t5R1JJSHFzOE8vN3BXUXBjdXY4aS84K0lDM2RCdkVWalRNSFE9PVBOSnFr\n20 - OUTROS REQUISITOS\nIdentificador do Lote: LOT-0001; LOT-0002; LOT-0003\nInformação sobre contratos reservados. Aplica-se a contratos reservados (54º-A)? Não\n21 - CRITÉRIO DE ADJUDICAÇÃO\nO Critério de adjudicação é diferenciado por lote? Não\nMultifator: Sim\nFator: \nNome: Preço\nPonderação: 40%\nSubfatores: Não\nFator: \nNome: Qualidade\nPonderação: 40%\nSubfatores: Não\nFator: \nNome: Qualidade\nPonderação: 20%\nSubfatores: Não\n24 - CONDIÇÕES DO CONTRATO\nIdentificador do Lote: LOT-0001; LOT-0002; LOT-0003\nFaturação Eletrónica: Permitido\nObrigação de Subcontratação:\nCódigo da Obrigação de Subcontratação: Não é aplicável nenhuma obrigação de subcontratação.\n25 - COMPRA PÚBLICA ESTRATÉGICA\nCompra Pública Estratégica: Inexistência de contratação pública estratégica\n26 - INFORMAÇÕES ADICIONAIS\nIdentificador do Lote: LOT-0001; LOT-0002; LOT-0003\nContrato adequado para PME: Sim\nCobertura ACP (Acordo dos Contratos Públicos da Organização Mundial do Comércio): Não\n27 - IDENTIFICAÇÃO E CONTACTOS DO ÓRGÃO DE RECURSOS ADMINISTRATIVOS\nDesignação: UNIDADE LOCAL DE SAUDE DO ALTO AVE\nEndereço: Rua dos Cuileiros\nCódigo postal: 4835-044\nLocalidade: Guimarães\nTelefone: +351 253540330\nFax: +351 253540330\nEndereço eletrónico: compras@ulsaave.min-saude.pt\n28 - IDENTIFICAÇÃO DO(S) AUTOR(ES) DE ANÚNCIO\nNome: Eng. Arlindo Soares\nCargo: Diretor do Serviço Compras e Logística\n419947384",
    "nipc": "508080827",
    "distrito": "Braga",
    "concelho": "Guimarães",
    "freguesia": "Todas",
    "site": "http://www.hospitaldeguimaraes.min-saude.pt/",
    "email": "aprovisionamento@hospitaldeguimaraes.min-saude.pt",
    "designacao_contrato": "Próteses Totais da Anca",
    "descricao": "CP/0016/2026-Próteses Totais da Anca",
    "preco_base": "338.915,00 EUR",
    "prazo_execucao": "12 MESES",
    "prazo_apresentacao_propostas": "09-02-2026 17:00",
    "fundos_eu": "Não",
    "plataforma_eletronica": "VORTAL",
    "url_procedimento": "https://community.vortal.biz/public/",
    "autor_nome": "Eng. Arlindo Soares",
    "autor_cargo": "Diretor do Serviço Compras e Logística"
  },
  {
    "numero_procedimento": "N/A",
    "entidade": "Entidade de Serviços Partilhados da Administração Pública, IP",
    "link": "https://diariodarepublica.pt/dr/detalhe/contrato-publico/417-1003400082",
    "detalhes_completos": "1 - IDENTIFICAÇÃO E CONTACTOS DA ENTIDADE ADJUDICANTE\nDesignação da entidade adjudicante: Entidade de Serviços Partilhados da Administração Pública, IP\nNIPC: 510342191\nEndereço: Av. Leite de Vasconcelos, 2\nCódigo postal: 2614-502\nLocalidade: Alfragide - Amadora\nPaís: Portugal\nNUT III: PTZZZ\nDistrito: Lisboa\nConcelho: Lisboa\nFreguesia: Todas\nTelefone: 214723100\nFax: 214723100\nEndereço da Entidade (URL): www.espap.gov.pt\nEndereço Eletrónico: ana.vieira@espap.gov.pt\nFunção da Organização: Adquirente\nNorma jurídica da Entidade Adjudicante: Autoridade da administração central\nÁrea de atividade da Autoridade Adjudicante: Assuntos económicos\n2 - JORNAL OFICIAL DA UNIÃO EUROPEIA\nO procedimento a que este anúncio diz respeito também é publicitado no Jornal Oficial da União Europeia? Sim\n3 - AVISO\nModelo de Anúncio: Concurso público\nData de Envio do Anúncio: 07-01-2026\n5 - PROCESSO\nTipo de Procedimento: Concurso público\nPreço base do procedimento: Sim\nValor do preço base do procedimento: 8.287.265,75 EUR\nProcedimento com lotes? Sim\nNº Máx. de Lotes Autorizado: 13\nNúmero máximo de lotes que podem ser adjudicados a um concorrente: 13\n6 - OBJETO DO CONTRATO\nNúmero de referência interna: CP/1197/2025\nDesignação do contrato: Concurso Público CP/1197/2025_HL\nDescrição: Aquisição centralizada de serviços de limpeza para 18 entidades\nOpções: Não\nTipo de Contrato Principal: Aquisição de Serviços\nTipo de Contrato: Aquisição de Serviços\nClassificação CPV (Vocabulário Comum para os Contratos Públicos)\nObjeto principal\nVocabulário Principal: 90910000\nPreço base s/IVA: 8.287.265,75 EUR\nLotes: \nNº: LOT-0001\nDescrição do Lote: Lote 1 - NORTE\nPreço base s/IVA: 811.098,60 EUR\nClassificação CPV (Vocabulário Comum para os Contratos Públicos)\nObjeto principal\nVocabulário Principal: 90910000\nNº: LOT-0002\nDescrição do Lote: Lote 2 - CENTRO\nPreço base s/IVA: 276.923,10 EUR\nClassificação CPV (Vocabulário Comum para os Contratos Públicos)\nObjeto principal\nVocabulário Principal: 90910000\nNº: LOT-0003\nDescrição do Lote: Lote 3A - LISBOA \nPreço base s/IVA: 499.453,35 EUR\nClassificação CPV (Vocabulário Comum para os Contratos Públicos)\nObjeto principal\nVocabulário Principal: 90910000\nNº: LOT-0004\nDescrição do Lote: Lote 3B - LISBOA \nPreço base s/IVA: 782.371,65 EUR\nClassificação CPV (Vocabulário Comum para os Contratos Públicos)\nObjeto principal\nVocabulário Principal: 90910000\nNº: LOT-0005\nDescrição do Lote: Lote 3C - LISBOA \nPreço base s/IVA: 1.032.862,05 EUR\nClassificação CPV (Vocabulário Comum para os Contratos Públicos)\nObjeto principal\nVocabulário Principal: 90910000\nNº: LOT-0006\nDescrição do Lote: Lote 3D - LISBOA \nPreço base s/IVA: 870.821,85 EUR\nClassificação CPV (Vocabulário Comum para os Contratos Públicos)\nObjeto principal\nVocabulário Principal: 90910000\nNº: LOT-0007\nDescrição do Lote: Lote 3E - LISBOA \nPreço base s/IVA: 1.393.599,90 EUR\nClassificação CPV (Vocabulário Comum para os Contratos Públicos)\nObjeto principal\nVocabulário Principal: 90910000\nNº: LOT-0008\nDescrição do Lote: Lote 3F - LISBOA \nPreço base s/IVA: 1.038.028,50 EUR\nClassificação CPV (Vocabulário Comum para os Contratos Públicos)\nObjeto principal\nVocabulário Principal: 90910000\nNº: LOT-0009\nDescrição do Lote: Lote 3G - LISBOA \nPreço base s/IVA: 1.051.342,80 EUR\nClassificação CPV (Vocabulário Comum para os Contratos Públicos)\nObjeto principal\nVocabulário Principal: 90910000\nNº: LOT-0010\nDescrição do Lote: Lote 4 - ALENTEJO\nPreço base s/IVA: 268.597,80 EUR\nClassificação CPV (Vocabulário Comum para os Contratos Públicos)\nObjeto principal\nVocabulário Principal: 90910000\nNº: LOT-0011\nDescrição do Lote: Lote 5 - ALGARVE\nPreço base s/IVA: 134.699,80 EUR\nClassificação CPV (Vocabulário Comum para os Contratos Públicos)\nObjeto principal\nVocabulário Principal: 90910000\nNº: LOT-0012\nDescrição do Lote: Lote 6 - AÇORES\nPreço base s/IVA: 92.131,45 EUR\nClassificação CPV (Vocabulário Comum para os Contratos Públicos)\nObjeto principal\nVocabulário Principal: 90910000\nNº: LOT-0013\nDescrição do Lote: Lote 7 - MADEIRA\nPreço base s/IVA: 35.334,90 EUR\nClassificação CPV (Vocabulário Comum para os Contratos Públicos)\nObjeto principal\nVocabulário Principal: 90910000\n7 - INDICAÇÕES ADICIONAIS\nO contrato envolve aquisição conjunta (satisfação de várias entidades)? Sim\nA entidade adjudicante atua como compradora no procedimento? Sim\nNIPC: 510342191\nDesignação da entidade adjudicante: Entidade de Serviços Partilhados da Administração Pública, IP\nUnidades Orgânicas: ESPAP\nPercentagem: 5.14%\nNIPC: 501389660\nDesignação da entidade adjudicante: Laboratório Nacional de Engenharia Civil, IP\nUnidades Orgânicas: LNEC\nPercentagem: 16.8%\nNIPC: 600084876\nDesignação da entidade adjudicante: Direção-Geral da Qualificação dos Trabalhadores em Funções Públicas\nUnidades Orgânicas: INA\nPercentagem: 0.88%\nNIPC: 600022730\nDesignação da entidade adjudicante: Academia Portuguesa da História\nUnidades Orgânicas: APH\nPercentagem: 0.13%\nNIPC: 600020630\nDesignação da entidade adjudicante: Academia Nacional de Belas Artes\nUnidades Orgânicas: ANBA\nPercentagem: 0.13%\nNIPC: 600087301\nDesignação da entidade adjudicante: Autoridade Antidopagem de Portugal\nUnidades Orgânicas: ADOP\nPercentagem: 0.38%\nNIPC: 600056120\nDesignação da entidade adjudicante: Gabinete Nacional de Segurança\nUnidades Orgânicas: GNS\nPercentagem: 2.41%\nNIPC: 600035972\nDesignação da entidade adjudicante: Direção-Geral das Autarquias Locais\nUnidades Orgânicas: DGAL\nPercentagem: 1.25%\nNIPC: 502237490\nDesignação da entidade adjudicante: Instituto Nacional de Estatística, IP\nUnidades Orgânicas: INE\nPercentagem: 16.33%\nNIPC: 504739506\nDesignação da entidade adjudicante: Instituto dos Mercados Públicos, do Imobiliário e da Construção, IP\nUnidades Orgânicas: IMPIC\nPercentagem: 6.12%\nNIPC: 502225610\nDesignação da entidade adjudicante: Instituto Português da Qualidade, IP\nUnidades Orgânicas: IPQ\nPercentagem: 4.19%\nNIPC: 600086941\nDesignação da entidade adjudicante: Comissão de Recrutamento e Seleção para a Administração Pública (CRESAP)\nUnidades Orgânicas: CRESAP\nPercentagem: 0.25%\nNIPC: 501603409\nDesignação da entidade adjudicante: Cinemateca Portuguesa - Museu do Cinema, IP\nUnidades Orgânicas: CINEMATECA\nPercentagem: 5.33%\nNIPC: 517842920\nDesignação da entidade adjudicante: Património Cultural, IP\nUnidades Orgânicas: PATRIMÓNIO\nPercentagem: 14.88%\nNIPC: 600084965\nDesignação da entidade adjudicante: Direção-Geral do Território\nUnidades Orgânicas: DGT\nPercentagem: 5.14%\nNIPC: 600082598\nDesignação da entidade adjudicante: Comissão para a Cidadania e a Igualdade de Género\nUnidades Orgânicas: CIG\nPercentagem: 1.16%\nNIPC: 517686260\nDesignação da entidade adjudicante: Agência para a Integração, Migrações e Asilo, IP\nUnidades Orgânicas: AIMA\nPercentagem: 19.24%\nNIPC: 600087034\nDesignação da entidade adjudicante: Gabinete de Prevenção e Investigação de Acidentes com Aeronaves e de Acidentes Ferroviários\nUnidades Orgânicas: GPIAAF\nPercentagem: 0.24%\nO contrato é adjudicado por uma central de compras? Sim\n8 - TÉCNICAS\nO concurso destina-se à celebração de um acordo-quadro? Inexistência de acordo-quadro\nÉ utilizado um leilão eletrónico? Não\nÉ adotada uma fase de negociação? Não\nSistema de Aquisição Dinâmico: Inexistência de sistema de aquisição dinâmico\n9 - LOCAL DA EXECUÇÃO DO CONTRATO\nLOCAL DA EXECUÇÃO DO CONTRATO (PROCEDIMENTO)\nLOCAL DA EXECUÇÃO DO CONTRATO (LOTE)\nIdentificador do Lote: LOT-0001\nPaís: Portugal\nNUT III: PTZZZ\nLocalidade: Conforme Anexo II do CE\nDistrito: Todos\nConcelho: Todos\nFreguesia: Todas\nIdentificador do Lote: LOT-0002\nPaís: Portugal\nNUT III: PTZZZ\nLocalidade: Conforme Anexo II do CE\nDistrito: Todos\nConcelho: Todos\nFreguesia: Todas\nIdentificador do Lote: LOT-0003\nPaís: Portugal\nNUT III: PTZZZ\nLocalidade: Conforme Anexo II do CE\nDistrito: Todos\nConcelho: Todos\nFreguesia: Todas\nIdentificador do Lote: LOT-0004\nPaís: Portugal\nNUT III: PTZZZ\nLocalidade: Conforme Anexo II do CE\nDistrito: Todos\nConcelho: Todos\nFreguesia: Todas\nIdentificador do Lote: LOT-0005\nPaís: Portugal\nNUT III: PTZZZ\nLocalidade: Conforme Anexo II do CE\nDistrito: Todos\nConcelho: Todos\nFreguesia: Todas\nIdentificador do Lote: LOT-0006\nPaís: Portugal\nNUT III: PTZZZ\nLocalidade: Conforme Anexo II do CE\nDistrito: Todos\nConcelho: Todos\nFreguesia: Todas\nIdentificador do Lote: LOT-0007\nPaís: Portugal\nNUT III: PTZZZ\nLocalidade: Conforme Anexo II do CE\nDistrito: Todos\nConcelho: Todos\nFreguesia: Todas\nIdentificador do Lote: LOT-0008\nPaís: Portugal\nNUT III: PTZZZ\nLocalidade: Conforme Anexo II do CE\nDistrito: Todos\nConcelho: Todos\nFreguesia: Todas\nIdentificador do Lote: LOT-0009\nPaís: Portugal\nNUT III: PTZZZ\nLocalidade: Conforme Anexo II do CE\nDistrito: Todos\nConcelho: Todos\nFreguesia: Todas\nIdentificador do Lote: LOT-0010\nPaís: Portugal\nNUT III: PTZZZ\nLocalidade: Conforme Anexo II do CE\nDistrito: Todos\nConcelho: Todos\nFreguesia: Todas\nIdentificador do Lote: LOT-0011\nPaís: Portugal\nNUT III: PTZZZ\nLocalidade: Conforme Anexo II do CE\nDistrito: Todos\nConcelho: Todos\nFreguesia: Todas\nIdentificador do Lote: LOT-0012\nPaís: Portugal\nNUT III: PTZZZ\nLocalidade: Conforme Anexo II do CE\nDistrito: Todos\nConcelho: Todos\nFreguesia: Todas\nIdentificador do Lote: LOT-0013\nPaís: Portugal\nNUT III: PTZZZ\nLocalidade: Conforme Anexo II do CE\nDistrito: Todos\nConcelho: Todos\nFreguesia: Todas\n10 - PRAZO DE EXECUÇÃO DO CONTRATO\nIdentificador do Lote: LOT-0001\nPrazo de execução do contrato: 36 MESES\nPrevisão de renovações: Não\nIdentificador do Lote: LOT-0002\nPrazo de execução do contrato: 36 MESES\nPrevisão de renovações: Não\nIdentificador do Lote: LOT-0003\nPrazo de execução do contrato: 36 MESES\nPrevisão de renovações: Não\nIdentificador do Lote: LOT-0004\nPrazo de execução do contrato: 36 MESES\nPrevisão de renovações: Não\nIdentificador do Lote: LOT-0005\nPrazo de execução do contrato: 36 MESES\nPrevisão de renovações: Não\nIdentificador do Lote: LOT-0006\nPrazo de execução do contrato: 36 MESES\nPrevisão de renovações: Não\nIdentificador do Lote: LOT-0007\nPrazo de execução do contrato: 36 MESES\nPrevisão de renovações: Não\nIdentificador do Lote: LOT-0008\nPrazo de execução do contrato: 36 MESES\nPrevisão de renovações: Não\nIdentificador do Lote: LOT-0009\nPrazo de execução do contrato: 36 MESES\nPrevisão de renovações: Não\nIdentificador do Lote: LOT-0010\nPrazo de execução do contrato: 36 MESES\nPrevisão de renovações: Não\nIdentificador do Lote: LOT-0011\nPrazo de execução do contrato: 36 MESES\nPrevisão de renovações: Não\nIdentificador do Lote: LOT-0012\nPrazo de execução do contrato: 36 MESES\nPrevisão de renovações: Não\nIdentificador do Lote: LOT-0013\nPrazo de execução do contrato: 36 MESES\nPrevisão de renovações: Não\n11 - FUNDOS EU\nIdentificador do Lote: LOT-0001; LOT-0002; LOT-0003; LOT-0004; LOT-0005; LOT-0006; LOT-0007; LOT-0008; LOT-0009; LOT-0010; LOT-0011; LOT-0012; LOT-0013\nTêm fundos EU? Não\n12 - DOCUMENTOS DE HABILITAÇÃO\nHabilitação para o exercício da atividade profissional: Não\n13 - CONDIÇÕES DE APRESENTAÇÃO\nPlataforma eletrónica utilizada pela entidade adjudicante: ANOGOV\nURL para Apresentação: https://plataforma-sncp.espap.gov.pt/espap/faces/\nAdmissibilidade da apresentação de propostas variantes: Não autorizado\nPrazo para apresentação das propostas: 06-02-2026 23:59\nPrazo durante o qual os concorrentes são obrigados a manter as respetivas propostas: 66 dias a contar do termo do prazo para a apresentação das propostas\nApresentação de Catálogo Eletrónico: Não autorizado\nIndicação de Subcontratação na Proposta: Inexistência de indicação de subcontratação\n14 - PRESTAÇÃO DE CAUÇÃO\nPrestação de caução: Sim\nPercentagem: 0.1%\nDescrição da Garantia Exigida: Conforme artigo 90.º do CCP\n15 - FORNECIMENTO DAS PEÇAS DO CONCURSO, APRESENTAÇÃO DE PEDIDOS DE PARTICIPAÇÃO E APRESENTAÇÃO DAS PROPOSTAS\nLink para acesso às peças do concurso (URL): https://plataforma-sncp.espap.gov.pt/espap/faces/app/acessoDocs.jsp?codigoAcesso=9II4IRIBN2Oc51J5bJVmknOuTUmXiTXIKshlojPekbWlYRG1H4\n20 - OUTROS REQUISITOS\nIdentificador do Lote: LOT-0001; LOT-0002; LOT-0003; LOT-0004; LOT-0005; LOT-0006; LOT-0007; LOT-0008; LOT-0009; LOT-0010; LOT-0011; LOT-0012; LOT-0013\nInformação sobre contratos reservados. Aplica-se a contratos reservados (54º-A)? Não\n21 - CRITÉRIO DE ADJUDICAÇÃO\nO Critério de adjudicação é diferenciado por lote? Não\nMultifator: Sim\nFator: \nNome: Preço\nPonderação: 97%\nSubfatores: Não\nFator: \nNome: Outros\nOutro Nome: Disponibilização de dois relatórios de avaliação da satisfação dos utilizadores dos edifícios\nPonderação: 3%\nSubfatores: Não\n24 - CONDIÇÕES DO CONTRATO\nIdentificador do Lote: LOT-0001; LOT-0002; LOT-0003; LOT-0004; LOT-0005; LOT-0006; LOT-0007; LOT-0008; LOT-0009; LOT-0010; LOT-0011; LOT-0012; LOT-0013\nFaturação Eletrónica: Necessário\nObrigação de Subcontratação:\nCódigo da Obrigação de Subcontratação: Não é aplicável nenhuma obrigação de subcontratação.\n25 - COMPRA PÚBLICA ESTRATÉGICA\nCompra Pública Estratégica: Redução dos impactos ambientais\nDescrição do Processo de Adjudicação Estratégico: N.º 8 da parte B da RCM n.º 132/2023\nCritérios de contratos Públicos Ecológicos: Critérios de contratação pública ecológica nacional\nCategorias da estratégia nacional: Serviços de limpeza de interiores\nDiretiva Veículos Não Poluentes: Não\nCritério de Acessibilidade: Os critérios de acessibilidade para as pessoas com deficiência não estão incluídos porque o contrato não se destina a pessoas singulares\n26 - INFORMAÇÕES ADICIONAIS\nIdentificador do Lote: LOT-0001\nContrato adequado para PME: Sim\nCobertura ACP (Acordo dos Contratos Públicos da Organização Mundial do Comércio): Sim\nIdentificador do Lote: LOT-0002\nContrato adequado para PME: Sim\nCobertura ACP (Acordo dos Contratos Públicos da Organização Mundial do Comércio): Sim\nIdentificador do Lote: LOT-0003\nContrato adequado para PME: Sim\nCobertura ACP (Acordo dos Contratos Públicos da Organização Mundial do Comércio): Sim\nIdentificador do Lote: LOT-0004\nContrato adequado para PME: Sim\nCobertura ACP (Acordo dos Contratos Públicos da Organização Mundial do Comércio): Sim\nIdentificador do Lote: LOT-0005\nContrato adequado para PME: Sim\nCobertura ACP (Acordo dos Contratos Públicos da Organização Mundial do Comércio): Sim\nIdentificador do Lote: LOT-0006\nContrato adequado para PME: Sim\nCobertura ACP (Acordo dos Contratos Públicos da Organização Mundial do Comércio): Sim\nIdentificador do Lote: LOT-0007\nContrato adequado para PME: Sim\nCobertura ACP (Acordo dos Contratos Públicos da Organização Mundial do Comércio): Sim\nIdentificador do Lote: LOT-0008\nContrato adequado para PME: Sim\nCobertura ACP (Acordo dos Contratos Públicos da Organização Mundial do Comércio): Sim\nIdentificador do Lote: LOT-0009\nContrato adequado para PME: Sim\nCobertura ACP (Acordo dos Contratos Públicos da Organização Mundial do Comércio): Sim\nIdentificador do Lote: LOT-0010\nContrato adequado para PME: Sim\nCobertura ACP (Acordo dos Contratos Públicos da Organização Mundial do Comércio): Sim\nIdentificador do Lote: LOT-0011\nContrato adequado para PME: Sim\nCobertura ACP (Acordo dos Contratos Públicos da Organização Mundial do Comércio): Sim\nIdentificador do Lote: LOT-0012\nContrato adequado para PME: Sim\nCobertura ACP (Acordo dos Contratos Públicos da Organização Mundial do Comércio): Sim\nIdentificador do Lote: LOT-0013\nContrato adequado para PME: Sim\nCobertura ACP (Acordo dos Contratos Públicos da Organização Mundial do Comércio): Sim\n27 - IDENTIFICAÇÃO E CONTACTOS DO ÓRGÃO DE RECURSOS ADMINISTRATIVOS\nDesignação: Conselho Diretivo da eSPap I.P.\nEndereço: Av. Leite de Vasconcelos, 2, Alfregide\nCódigo postal: 2614-502\nLocalidade: AMADORA\nEndereço eletrónico: compras@espap.gov.pt\n28 - IDENTIFICAÇÃO DO(S) AUTOR(ES) DE ANÚNCIO\nNome: Ricardo Spínola \nCargo: Responsável de núcleo\n419947395",
    "nipc": "510342191",
    "distrito": "Lisboa",
    "concelho": "Lisboa",
    "freguesia": "Todas",
    "site": "www.espap.gov.pt",
    "email": "ana.vieira@espap.gov.pt",
    "designacao_contrato": "Concurso Público CP/1197/2025_HL",
    "descricao": "Aquisição centralizada de serviços de limpeza para 18 entidades",
    "preco_base": "8.287.265,75 EUR",
    "prazo_execucao": "36 MESES",
    "prazo_apresentacao_propostas": "06-02-2026 23:59",
    "fundos_eu": "Não",
    "plataforma_eletronica": "ANOGOV",
    "url_procedimento": "https://plataforma-sncp.espap.gov.pt/espap/faces/",
    "autor_nome": "Ricardo Spínola",
    "autor_cargo": "Responsável de núcleo"
  },
  {
    "numero_procedimento": "N/A",
    "entidade": "Município de Almada",
    "link": "https://diariodarepublica.pt/dr/detalhe/contrato-publico/419-1003400083",
    "detalhes_completos": "Alteração do Anúncio de procedimento n.º 33393/2025, de 2025-12-24, com o ID 419923103\n1 - IDENTIFICAÇÃO E CONTACTOS DA ENTIDADE ADJUDICANTE\nDesignação da entidade adjudicante: Município de Almada\nNIPC: 500051054\nEndereço: Largo Luís de Camões\nCódigo postal: 2800-158\nLocalidade: Setúbal\nPaís: Portugal\nNUT III: PT170\nDistrito: Setúbal\nConcelho: Almada\nFreguesia: União das Freguesias de Almada, Cova da Piedade, Pragal e Cacilhas\nTelefone: 212724000\nFax: 212724599\nEndereço da Entidade (URL): www.m-almada.pt\nEndereço Eletrónico: almadainforma@cma.m-almada.pt\neDelivery Gateway (URL): https://community.vortal.biz/public/\nFunção da Organização: Adquirente\nNorma jurídica da Entidade Adjudicante: Autoridade local\nÁrea de atividade da Autoridade Adjudicante: Serviços públicos das administrações públicas\n2 - JORNAL OFICIAL DA UNIÃO EUROPEIA\nO procedimento a que este anúncio diz respeito também é publicitado no Jornal Oficial da União Europeia? Sim\n3 - AVISO\nModelo de Anúncio: Concurso público\nData de Envio do Anúncio: 07-01-2026\n5 - PROCESSO\nTipo de Procedimento: Concurso público\nPreço base do procedimento: Sim\nValor do preço base do procedimento: 782.222,00 EUR\nProcedimento com lotes? Não\n6 - OBJETO DO CONTRATO\nNúmero de referência interna: CPN01804S2025\nDesignação do contrato: Aquisição de serviços de comunicações globais (eletrónicas, fixa e móvel) para os Edifícios e Escolas do Município de Almada\nDescrição: Aquisição de serviços de comunicações globais (eletrónicas, fixa e móvel) para os Edifícios e Escolas do Município de Almada\nOpções: Não\nTipo de Contrato Principal: Aquisição de Serviços\nTipo de Contrato: Aquisição de Serviços\nClassificação CPV (Vocabulário Comum para os Contratos Públicos)\nObjeto principal\nVocabulário Principal: 64200000\nPreço base s/IVA: 782.222,00 EUR\n7 - INDICAÇÕES ADICIONAIS\nO contrato envolve aquisição conjunta (satisfação de várias entidades)? Não\nO contrato é adjudicado por uma central de compras? Não\n8 - TÉCNICAS\nO concurso destina-se à celebração de um acordo-quadro? Inexistência de acordo-quadro\nÉ utilizado um leilão eletrónico? Não\nÉ adotada uma fase de negociação? Não\nSistema de Aquisição Dinâmico: Inexistência de sistema de aquisição dinâmico\n9 - LOCAL DA EXECUÇÃO DO CONTRATO\nLOCAL DA EXECUÇÃO DO CONTRATO (PROCEDIMENTO)\nPaís: Portugal\nNUT III: PT170\nLocalidade: Setúbal\nDistrito: Setúbal\nConcelho: Almada\nFreguesia: Todas\n10 - PRAZO DE EXECUÇÃO DO CONTRATO\nPrazo de execução do contrato: 36 MESES\nPrevisão de renovações: Não\n11 - FUNDOS EU\nTêm fundos EU? Não\n12 - DOCUMENTOS DE HABILITAÇÃO\nHabilitação para o exercício da atividade profissional: Sim\nTipo: Outros\nDescrição - Outros: Não aplicável\nDescrição: Não aplicável\n13 - CONDIÇÕES DE APRESENTAÇÃO\nPlataforma eletrónica utilizada pela entidade adjudicante: VORTAL\nURL para Apresentação: https://community.vortal.biz/public/\nAdmissibilidade da apresentação de propostas variantes: Não autorizado\nPrazo para apresentação das propostas: 26-01-2026 23:59\nPrazo durante o qual os concorrentes são obrigados a manter as respetivas propostas: 120 dias a contar do termo do prazo para a apresentação das propostas\nApresentação de Catálogo Eletrónico: Não autorizado\nIndicação de Subcontratação na Proposta: Inexistência de indicação de subcontratação\n14 - PRESTAÇÃO DE CAUÇÃO\nPrestação de caução: Sim\nPercentagem: 5%\nDescrição da Garantia Exigida: Depósito em dinheiro ou em títulos emitidos ou garantidos pelo Estado, ou mediante garantia bancária ou seguro-caução\n15 - FORNECIMENTO DAS PEÇAS DO CONCURSO, APRESENTAÇÃO DE PEDIDOS DE PARTICIPAÇÃO E APRESENTAÇÃO DAS PROPOSTAS\nLink para acesso às peças do concurso (URL): https://community.vortal.biz/Public/public-tender-documents/N3NLMTJpWjN6ejZrSlVnS1ZXM1BSRVppMlpHQlliOWdhQmpndzYwQlV5WFdyejd6bGw0SVMyejAyNTh4eVVKVEVwdWhjTDIrQkZlQkYrU1dic2swU0E9PXd3U3hv\n20 - OUTROS REQUISITOS\nInformação sobre contratos reservados. Aplica-se a contratos reservados (54º-A)? Não\n21 - CRITÉRIO DE ADJUDICAÇÃO\nMultifator: Sim\nFator: \nNome: Preço\nPonderação: 40%\nSubfatores: Não\nFator: \nNome: Qualidade\nPonderação: 60%\nSubfatores: Não\n24 - CONDIÇÕES DO CONTRATO\nFaturação Eletrónica: Permitido\nObrigação de Subcontratação:\nCódigo da Obrigação de Subcontratação: Não é aplicável nenhuma obrigação de subcontratação.\n25 - COMPRA PÚBLICA ESTRATÉGICA\nCompra Pública Estratégica: Inexistência de contratação pública estratégica\n26 - INFORMAÇÕES ADICIONAIS\nContrato adequado para PME: Sim\nCobertura ACP (Acordo dos Contratos Públicos da Organização Mundial do Comércio): Não\n27 - IDENTIFICAÇÃO E CONTACTOS DO ÓRGÃO DE RECURSOS ADMINISTRATIVOS\nDesignação: Município de Almada\nEndereço: Largo Luís Camões\nCódigo postal: 2800-158\nLocalidade: Almada\nTelefone: +351 212724000\nFax: +351 212724000\nEndereço eletrónico: gab.presidencia@cma.m-almada.pt\n28 - IDENTIFICAÇÃO DO(S) AUTOR(ES) DE ANÚNCIO\nNome: Inês de Medeiros\nCargo: Presidente da Câmara Municipal de Almada\n29 - ALTERAÇÃO\nMotivo da Alteração: Correção pelo adquirente\nIdentificador da Versão do Anúncio a Alterar: fcf72252-bf54-4daf-88ed-ac51254655ac-01\nIdentificador das Secções Alteradas do Anúncio Anterior: Condições de Apresentação\nDescrição das Alterações: Prorrogação do prazo para apresentação de propostas\nAlteração dos Documentos do Concurso: Não\n419947400",
    "nipc": "500051054",
    "distrito": "Setúbal",
    "concelho": "Almada",
    "freguesia": "União das Freguesias de Almada, Cova da Piedade, Pragal e Cacilhas",
    "site": "www.m-almada.pt",
    "email": "almadainforma@cma.m-almada.pt",
    "designacao_contrato": "Aquisição de serviços de comunicações globais (eletrónicas, fixa e móvel) para os Edifícios e Escolas do Município de Almada",
    "descricao": "Aquisição de serviços de comunicações globais (eletrónicas, fixa e móvel) para os Edifícios e Escolas do Município de Almada",
    "preco_base": "782.222,00 EUR",
    "prazo_execucao": "36 MESES",
    "prazo_apresentacao_propostas": "26-01-2026 23:59",
    "fundos_eu": "Não",
    "plataforma_eletronica": "VORTAL",
    "url_procedimento": "https://community.vortal.biz/public/",
    "autor_nome": "Inês de Medeiros",
    "autor_cargo": "Presidente da Câmara Municipal de Almada"
  },
  {
    "numero_procedimento": "N/A",
    "entidade": "Sociedade de Desenvolvimento do Porto Santo, SA",
    "link": "https://diariodarepublica.pt/dr/detalhe/contrato-publico/421-1003400084",
    "detalhes_completos": "Alteração do Anúncio de procedimento n.º 32382/2025, de 2025-12-15, com o ID 419874545\n1 - IDENTIFICAÇÃO E CONTACTOS DA ENTIDADE ADJUDICANTE\nDesignação da entidade adjudicante: Sociedade de Desenvolvimento do Porto Santo, SA\nNIPC: 511131879\nServiço/Órgão/Pessoa de contacto: Unidade de Assessoria Jurídica, Contratação e Contencioso\nEndereço: Sede no edifício do Governo Regional, 3.º andar e escritórios na Rua Nova de São Pedro n.º 50\nCódigo postal: 9000-048\nLocalidade: Funchal\nPaís: Portugal\nNUT III: PT300\nDistrito: Região Autónoma da Madeira\nConcelho: Funchal\nFreguesia: Freguesia de São Pedro (Funchal)\nTelefone: 291215740\nFax: 291215759\nEndereço da Entidade (URL): https://sociedadesdesenvolvimento.com/\nEndereço Eletrónico: contratacaopublica@sociedadesdesenvolvimento.com\neDelivery Gateway (URL): https://www.acingov.pt\nFunção da Organização: Adquirente\nNorma jurídica da Entidade Adjudicante: Organismo de direito público\nÁrea de atividade da Autoridade Adjudicante: Serviços públicos das administrações públicas\n2 - JORNAL OFICIAL DA UNIÃO EUROPEIA\nO procedimento a que este anúncio diz respeito também é publicitado no Jornal Oficial da União Europeia? Sim\n3 - AVISO\nModelo de Anúncio: Concurso público\nData de Envio do Anúncio: 07-01-2026\n5 - PROCESSO\nTipo de Procedimento: Concurso público\nPreço base do procedimento: Sim\nValor do preço base do procedimento: 6.155.811,90 EUR\nProcedimento com lotes? Não\n6 - OBJETO DO CONTRATO\nNúmero de referência interna: CP 02/2025\nDesignação do contrato: Empreitada de Construção do Segundo Campo de Golfe do Porto Santo- Primeira Fase\nDescrição: Empreitada de Construção do Segundo Campo de Golfe do Porto Santo- Primeira Fase\nOpções: Não\nTipo de Contrato Principal: Empreitada de Obras Públicas\nTipo de Contrato: Empreitada de Obras Públicas\nClassificação CPV (Vocabulário Comum para os Contratos Públicos)\nObjeto principal\nVocabulário Principal: 45200000\nPreço base s/IVA: 6.155.811,90 EUR\n7 - INDICAÇÕES ADICIONAIS\nO contrato envolve aquisição conjunta (satisfação de várias entidades)? Não\nO contrato é adjudicado por uma central de compras? Não\n8 - TÉCNICAS\nO concurso destina-se à celebração de um acordo-quadro? Inexistência de acordo-quadro\nÉ utilizado um leilão eletrónico? Não\nÉ adotada uma fase de negociação? Não\nSistema de Aquisição Dinâmico: Inexistência de sistema de aquisição dinâmico\n9 - LOCAL DA EXECUÇÃO DO CONTRATO\nLOCAL DA EXECUÇÃO DO CONTRATO (PROCEDIMENTO)\nPaís: Portugal\nNUT III: PT300\nLocalidade: todas\nDistrito: Região Autónoma da Madeira\nConcelho: Porto Santo\nFreguesia: Todas\n10 - PRAZO DE EXECUÇÃO DO CONTRATO\nPrazo de execução do contrato: 13 MESES\nPrevisão de renovações: Não\n11 - FUNDOS EU\nTêm fundos EU? Não\n12 - DOCUMENTOS DE HABILITAÇÃO\nHabilitação para o exercício da atividade profissional: Sim\nTipo: Alvará\nDescrição:  Alvará de classificação de Empreiteiro de Obras públicas, emitido pelo Instituto dos Mercados Públicos do Imobiliário e da Construção (IMPIC, I. P.), contendo subcategoria em classe que cubra o valor global da proposta, respeitante aos trabalhos mais expressivos da mesma, sem prejuízo da exigência de habilitação noutras classes e subcategorias relativas às restantes obras e trabalhos a executar nos termos da Lei n.º 41/2015, de 3 de junho, alterada pela Lei n.º 25/2018, de 14 de junho, com as seguintes autorizações:\nA classificação como empreiteiro geral da 2.ª categoria - vias de comunicação, obras de urbanização e outras infraestruturas, a qual tem de ser de classe que cubra o valor total da proposta;\nAs seguintes classificações na classe correspondente à parte dos trabalhos a que respeitam: \n 1ª subcategoria - vias de circulação rodoviária e aeródromos, 6ª subcategoria - saneamento básico e 9ª subcategoria - ajardinamentos da 2.ª Categoria - vias de comunicação, obras de urbanização e outras infraestruturas;\n 1ª Subcategoria - Instalações elétricas de utilização de baixa tensão, 2ª Subcategoria - Redes elétricas de baixa tensão e postos de transformação, 18ª Subcategoria - Gestão técnica centralizada e 19ª Subcategoria - Outras instalações mecânicas e eletromecânicas da 4.ª Categoria  Instalações Elétricas e Mecânicas;\n 2ª Subcategoria - Movimentação de terras, 7ª Subcategoria - Drenagens e tratamento de taludes, 11ª Subcategoria - Impermeabilizações e isolamentos e 13ª Subcategoria - Caminhos agrícolas e florestais da 5.ª Categoria  Outros trabalhos.\n13 - CONDIÇÕES DE APRESENTAÇÃO\nPlataforma eletrónica utilizada pela entidade adjudicante: ACIN\nURL para Apresentação: https://www.acingov.pt\nAdmissibilidade da apresentação de propostas variantes: Não autorizado\nPrazo para apresentação das propostas: 23-01-2026 23:59\nPrazo durante o qual os concorrentes são obrigados a manter as respetivas propostas: 180 dias a contar do termo do prazo para a apresentação das propostas\nApresentação de Catálogo Eletrónico: Permitido\nIndicação de Subcontratação na Proposta: Inexistência de indicação de subcontratação\n14 - PRESTAÇÃO DE CAUÇÃO\nPrestação de caução: Sim\nPercentagem: 2%\nDescrição da Garantia Exigida: O valor da caução é de 2.00% do preço contratual.\n15 - FORNECIMENTO DAS PEÇAS DO CONCURSO, APRESENTAÇÃO DE PEDIDOS DE PARTICIPAÇÃO E APRESENTAÇÃO DAS PROPOSTAS\nLink para acesso às peças do concurso (URL): https://www.acingov.pt/acingovprod/2/zonaPublica/zona_publica_c/donwloadProcedurePiece/OTkyODA3\n20 - OUTROS REQUISITOS\nInformação sobre contratos reservados. Aplica-se a contratos reservados (54º-A)? Não\n21 - CRITÉRIO DE ADJUDICAÇÃO\nMultifator: Não\nMonofator:\nNome: Preço\n24 - CONDIÇÕES DO CONTRATO\nFaturação Eletrónica: Permitido\nObrigação de Subcontratação:\nCódigo da Obrigação de Subcontratação: Não é aplicável nenhuma obrigação de subcontratação.\n25 - COMPRA PÚBLICA ESTRATÉGICA\nCompra Pública Estratégica: Inexistência de contratação pública estratégica\n26 - INFORMAÇÕES ADICIONAIS\nContrato adequado para PME: Sim\nCobertura ACP (Acordo dos Contratos Públicos da Organização Mundial do Comércio): Não\n27 - IDENTIFICAÇÃO E CONTACTOS DO ÓRGÃO DE RECURSOS ADMINISTRATIVOS\nDesignação: Presidente do Conselho de Administração\nEndereço: Sede no Edifício do Governo Regional, 3.º andar e escritórios na Rua Nova de São Pedro n.º 50\nCódigo postal: 9000-048\nLocalidade: Funchal\nTelefone: 291215740\nFax: \nEndereço eletrónico: geral@sociedadesdesenvolvimento.com\nPrazo de interposição do recurso: 5 dias\n28 - IDENTIFICAÇÃO DO(S) AUTOR(ES) DE ANÚNCIO\nNome: Élia Fátima da Silva Rodrigues Ribeiro\nCargo: Presidente do Conselho de Administração\n29 - ALTERAÇÃO\nMotivo da Alteração: Correção pelo adquirente\nIdentificador da Versão do Anúncio a Alterar: bfa339b1-6b33-42c7-8e61-e93b6d0f61db-03\nIdentificador das Secções Alteradas do Anúncio Anterior: Condições de Apresentação; Alteração\nDescrição das Alterações: Modificação do prazo para a apresentação de propostas\nAlteração dos Documentos do Concurso: Não\n419947411",
    "nipc": "511131879",
    "distrito": "Região Autónoma da Madeira",
    "concelho": "Funchal",
    "freguesia": "Freguesia de São Pedro (Funchal)",
    "site": "https://sociedadesdesenvolvimento.com/",
    "email": "contratacaopublica@sociedadesdesenvolvimento.com",
    "designacao_contrato": "Empreitada de Construção do Segundo Campo de Golfe do Porto Santo- Primeira Fase",
    "descricao": "Empreitada de Construção do Segundo Campo de Golfe do Porto Santo- Primeira Fase",
    "preco_base": "6.155.811,90 EUR",
    "prazo_execucao": "13 MESES",
    "prazo_apresentacao_propostas": "23-01-2026 23:59",
    "fundos_eu": "Não",
    "plataforma_eletronica": "ACIN",
    "url_procedimento": "https://www.acingov.pt",
    "autor_nome": "Élia Fátima da Silva Rodrigues Ribeiro",
    "autor_cargo": "Presidente do Conselho de Administração"
  },
  {
    "numero_procedimento": "N/A",
    "entidade": "Águas de Santo André, SA",
    "link": "https://diariodarepublica.pt/dr/detalhe/contrato-publico/427-1003400086",
    "detalhes_completos": "Alteração do Anúncio de procedimento n.º 33275/2025, de 2025-12-23, com o ID 419922131\n1 - IDENTIFICAÇÃO E CONTACTOS DA ENTIDADE ADJUDICANTE\nDesignação da entidade adjudicante: Águas de Santo André, SA\nNIPC: 505600005\nServiço/Órgão/Pessoa de contacto: Direção de Operação\nEndereço: Cerca da Água - Rua dos Cravos\nCódigo postal: 7500-130\nLocalidade: Vila Nova de Santo André\nPaís: Portugal\nNUT III: PT181\nDistrito: Setúbal\nConcelho: Santiago do Cacém\nFreguesia: Freguesia de Santo André - Santiago do Cacém\nTelefone: 269708240\nFax: 351269708269\nEndereço da Entidade (URL): www.adsa.pt\nEndereço Eletrónico: geral.adsa@adp.pt\neDelivery Gateway (URL): https://www.acingov.pt\nFunção da Organização: Adquirente\nNorma jurídica da Entidade Adjudicante: Organismo de direito público\nÁrea de atividade da Entidade Adjudicante: Atividades relacionadas com a água\n2 - JORNAL OFICIAL DA UNIÃO EUROPEIA\nO procedimento a que este anúncio diz respeito também é publicitado no Jornal Oficial da União Europeia? Não\n3 - AVISO\nModelo de Anúncio: Concurso público\nData de Envio do Anúncio: 09-01-2026\n5 - PROCESSO\nTipo de Procedimento: Concurso público\nPreço base do procedimento: Sim\nValor do preço base do procedimento: 150.000,00 EUR\nProcedimento com lotes? Não\n6 - OBJETO DO CONTRATO\nNúmero de referência interna: CP 18/DOP/25\nDesignação do contrato: Execução do Programa de Monitorização do Ambiente Marinho (PMAM)\nDescrição: Execução do Programa de Monitorização do Ambiente Marinho (PMAM)\nTipo de Contrato Principal: Aquisição de Serviços\nTipo de Contrato: Aquisição de Serviços\nClassificação CPV (Vocabulário Comum para os Contratos Públicos)\nObjeto principal\nVocabulário Principal: 90733100\nPreço base s/IVA: 150.000,00 EUR\n7 - INDICAÇÕES ADICIONAIS\nO contrato envolve aquisição conjunta (satisfação de várias entidades)? Não\nO contrato é adjudicado por uma central de compras? Não\n8 - TÉCNICAS\nO concurso destina-se à celebração de um acordo-quadro? Inexistência de acordo-quadro\nÉ utilizado um leilão eletrónico? Não\nÉ adotada uma fase de negociação? Não\nSistema de Aquisição Dinâmico: Inexistência de sistema de aquisição dinâmico\n9 - LOCAL DA EXECUÇÃO DO CONTRATO\nLOCAL DA EXECUÇÃO DO CONTRATO (PROCEDIMENTO)\nPaís: Portugal\nNUT III: PT181\nLocalidade: Sines\nDistrito: Setúbal\nConcelho: Sines\nFreguesia: Freguesia de Sines\n10 - PRAZO DE EXECUÇÃO DO CONTRATO\nPrazo de execução do contrato: 3 ANOS\nPrevisão de renovações: Não\n11 - FUNDOS EU\nTêm fundos EU? Não\n12 - DOCUMENTOS DE HABILITAÇÃO\nHabilitação para o exercício da atividade profissional: Não\n13 - CONDIÇÕES DE APRESENTAÇÃO\nPlataforma eletrónica utilizada pela entidade adjudicante: ACIN\nURL para Apresentação: https://www.acingov.pt\nAdmissibilidade da apresentação de propostas variantes: Não autorizado\nPrazo para apresentação das propostas: 30-01-2026 18:00\nPrazo durante o qual os concorrentes são obrigados a manter as respetivas propostas: 120 dias a contar do termo do prazo para a apresentação das propostas\nIndicação de Subcontratação na Proposta: A parte do contrato que o proponente tenciona subcontratar\n14 - PRESTAÇÃO DE CAUÇÃO\nPrestação de caução: Sim\nPercentagem: 5%\nDescrição da Garantia Exigida: O valor da caução é de 5.00% do preço contratual.\n15 - FORNECIMENTO DAS PEÇAS DO CONCURSO, APRESENTAÇÃO DE PEDIDOS DE PARTICIPAÇÃO E APRESENTAÇÃO DAS PROPOSTAS\nLink para acesso às peças do concurso (URL): https://www.acingov.pt/acingovprod/2/zonaPublica/zona_publica_c/donwloadProcedurePiece/OTI2OTY5\n20 - OUTROS REQUISITOS\nInformação sobre contratos reservados. Aplica-se a contratos reservados (54º-A)? Não\n21 - CRITÉRIO DE ADJUDICAÇÃO\nMultifator: Não\nMonofator:\nNome: Preço\n24 - CONDIÇÕES DO CONTRATO\nFaturação Eletrónica: Necessário\nObrigação de Subcontratação:\nCódigo da Obrigação de Subcontratação: Não é aplicável nenhuma obrigação de subcontratação.\n25 - COMPRA PÚBLICA ESTRATÉGICA\nCompra Pública Estratégica: Inexistência de contratação pública estratégica\n26 - INFORMAÇÕES ADICIONAIS\nContrato adequado para PME: Sim\nCobertura ACP (Acordo dos Contratos Públicos da Organização Mundial do Comércio): Não\n27 - IDENTIFICAÇÃO E CONTACTOS DO ÓRGÃO DE RECURSOS ADMINISTRATIVOS\nDesignação: Águas de Santo André, S.A.\nEndereço: Cerca da Água - Rua dos Cravos\nCódigo postal: 7500-130\nLocalidade: Vila Nova de Santo André\nTelefone: 269708240\nFax: \nEndereço eletrónico: contratacao.adsa@adp.pt\n28 - IDENTIFICAÇÃO DO(S) AUTOR(ES) DE ANÚNCIO\nNome: Tânia Raquel Leocádio Viegas\nCargo: Gestora do Procedimento\n29 - ALTERAÇÃO\nMotivo da Alteração: Correção pelo adquirente\nIdentificador da Versão do Anúncio a Alterar: 776d5f00-3ce4-4938-b354-56eb304a6adc-01\nIdentificador das Secções Alteradas do Anúncio Anterior: Condições de Apresentação\nDescrição das Alterações: Prorrogação do prazo para entrega de propostas, em cumprimento com o disposto nos n.º 1 e n.º 3 do artigo 64.º do Código dos Contratos Públicos.\nAlteração dos Documentos do Concurso: Sim\nData de alteração dos documentos do concurso: 07-01-2026\n419947413",
    "nipc": "505600005",
    "distrito": "Setúbal",
    "concelho": "Santiago do Cacém",
    "freguesia": "Freguesia de Santo André - Santiago do Cacém",
    "site": "www.adsa.pt",
    "email": "geral.adsa@adp.pt",
    "designacao_contrato": "Execução do Programa de Monitorização do Ambiente Marinho (PMAM)",
    "descricao": "Execução do Programa de Monitorização do Ambiente Marinho (PMAM)",
    "preco_base": "150.000,00 EUR",
    "prazo_execucao": "3 ANOS",
    "prazo_apresentacao_propostas": "30-01-2026 18:00",
    "fundos_eu": "Não",
    "plataforma_eletronica": "ACIN",
    "url_procedimento": "https://www.acingov.pt",
    "autor_nome": "Tânia Raquel Leocádio Viegas",
    "autor_cargo": "Gestora do Procedimento"
  },
  {
    "numero_procedimento": "N/A",
    "entidade": "Águas de Santo André, SA",
    "link": "https://diariodarepublica.pt/dr/detalhe/contrato-publico/436-1003478375",
    "detalhes_completos": "Alteração do Anúncio de procedimento n.º 30714/2025, de 2025-11-26, com o ID 419813049\n1 - IDENTIFICAÇÃO E CONTACTOS DA ENTIDADE ADJUDICANTE\nDesignação da entidade adjudicante: Águas de Santo André, SA\nNIPC: 505600005\nServiço/Órgão/Pessoa de contacto: Direção de Infraestruturas\nEndereço: Cerca da Água Rua dos Cravos\nCódigo postal: 7500-130\nLocalidade: Vila Nova de Santo André\nPaís: Portugal\nNUT III: PT181\nDistrito: Setúbal\nConcelho: Santiago do Cacém\nFreguesia: Freguesia de Santo André - Santiago do Cacém\nTelefone: 269708273\nFax: 351269708269\nEndereço da Entidade (URL): www.adsa.pt\nEndereço Eletrónico: conratacao@adp.pt\neDelivery Gateway (URL): https://www.acingov.pt\nFunção da Organização: Adquirente\nNorma jurídica da Entidade Adjudicante: Organismo de direito público\nÁrea de atividade da Entidade Adjudicante: Atividades relacionadas com a água\n2 - JORNAL OFICIAL DA UNIÃO EUROPEIA\nO procedimento a que este anúncio diz respeito também é publicitado no Jornal Oficial da União Europeia? Não\n3 - AVISO\nModelo de Anúncio: Concurso público\nData de Envio do Anúncio: 09-01-2026\n5 - PROCESSO\nTipo de Procedimento: Concurso público\nPreço base do procedimento: Sim\nValor do preço base do procedimento: 900.000,00 EUR\nProcedimento com lotes? Não\n6 - OBJETO DO CONTRATO\nNúmero de referência interna: CP 23/DIN-EN/25\nDesignação do contrato: Empreitada de execução para a \"Substituição da Caixa de Medição de Caudal e Conduta de Água Industrial à Repsol YPF, S.A.\"\nDescrição: Empreitada de execução para a \"Substituição da Caixa de Medição de Caudal e Conduta de Água Industrial à Repsol YPF, S.A.\"\nTipo de Contrato Principal: Empreitada de Obras Públicas\nTipo de Contrato: Empreitada de Obras Públicas\nClassificação CPV (Vocabulário Comum para os Contratos Públicos)\nObjeto principal\nVocabulário Principal: 45232151\nPreço base s/IVA: 900.000,00 EUR\n7 - INDICAÇÕES ADICIONAIS\nO contrato envolve aquisição conjunta (satisfação de várias entidades)? Não\nO contrato é adjudicado por uma central de compras? Não\n8 - TÉCNICAS\nO concurso destina-se à celebração de um acordo-quadro? Inexistência de acordo-quadro\nÉ utilizado um leilão eletrónico? Não\nÉ adotada uma fase de negociação? Não\nSistema de Aquisição Dinâmico: Inexistência de sistema de aquisição dinâmico\n9 - LOCAL DA EXECUÇÃO DO CONTRATO\nLOCAL DA EXECUÇÃO DO CONTRATO (PROCEDIMENTO)\nPaís: Portugal\nNUT III: PT181\nLocalidade: Freguesia de Sines\nDistrito: Setúbal\nConcelho: Sines\nFreguesia: Freguesia de Sines\n10 - PRAZO DE EXECUÇÃO DO CONTRATO\nPrazo de execução do contrato: 180 DIAS\nPrevisão de renovações: Não\n11 - FUNDOS EU\nTêm fundos EU? Não\n12 - DOCUMENTOS DE HABILITAÇÃO\nHabilitação para o exercício da atividade profissional: Sim\nTipo: Alvará\nDescrição: Artigo 18. 1. f) Documento comprovativo da titularidade de alvará ou certificado de empreiteiro de obras públicas, contendo as seguintes habilitações:\ni) 1.ª subcategoria da 1.ª categoria, da classe correspondente ao valor dos trabalhos especializados que lhe respeite, consoante a parte a que esses trabalhos cabem na proposta;\nii) 6.ª subcategoria da 2.ª categoria, da classe correspondente ao valor global da proposta;\niii) 1.ª, 10.ª, 19.ª subcategorias da 4.ª categoria, da classe correspondente ao valor dos trabalhos especializados que lhe respeite, consoante a parte a que esses trabalhos cabem na proposta;\niv) 9.ª subcategoria da 4.ª categoria, da classe correspondente ao valor total da proposta;\nv) 1.ª, 2.ª, 8.ª, 10.ª, e 11.ª subcategorias da 5ª categoria, da classe correspondente ao valor dos trabalhos especializados que lhe respeite, consoante a parte a que esses trabalhos cabem na proposta.\n13 - CONDIÇÕES DE APRESENTAÇÃO\nPlataforma eletrónica utilizada pela entidade adjudicante: ACIN\nURL para Apresentação: https://www.acingov.pt\nAdmissibilidade da apresentação de propostas variantes: Não autorizado\nPrazo para apresentação das propostas: 23-02-2026 18:00\nPrazo durante o qual os concorrentes são obrigados a manter as respetivas propostas: 90 dias a contar do termo do prazo para a apresentação das propostas\nIndicação de Subcontratação na Proposta: Inexistência de indicação de subcontratação\n14 - PRESTAÇÃO DE CAUÇÃO\nPrestação de caução: Sim\nPercentagem: 5%\nDescrição da Garantia Exigida: O valor da caução é de 5.00% do preço contratual.\n15 - FORNECIMENTO DAS PEÇAS DO CONCURSO, APRESENTAÇÃO DE PEDIDOS DE PARTICIPAÇÃO E APRESENTAÇÃO DAS PROPOSTAS\nLink para acesso às peças do concurso (URL): https://www.acingov.pt/acingovprod/2/zonaPublica/zona_publica_c/donwloadProcedurePiece/OTkyOTc4\n20 - OUTROS REQUISITOS\nInformação sobre contratos reservados. Aplica-se a contratos reservados (54º-A)? Não\n21 - CRITÉRIO DE ADJUDICAÇÃO\nMultifator: Não\nMonofator:\nNome: Preço\n24 - CONDIÇÕES DO CONTRATO\nFaturação Eletrónica: Permitido\nObrigação de Subcontratação:\nCódigo da Obrigação de Subcontratação: Não é aplicável nenhuma obrigação de subcontratação.\n25 - COMPRA PÚBLICA ESTRATÉGICA\nCompra Pública Estratégica: Inexistência de contratação pública estratégica\n26 - INFORMAÇÕES ADICIONAIS\nContrato adequado para PME: Não\nCobertura ACP (Acordo dos Contratos Públicos da Organização Mundial do Comércio): Não\n27 - IDENTIFICAÇÃO E CONTACTOS DO ÓRGÃO DE RECURSOS ADMINISTRATIVOS\nDesignação: Direção de Infraestruturas\nEndereço: Cerca da Água - Rua dos Cravos\nCódigo postal: 7500-130\nLocalidade: Vila Nova de Santo André\nTelefone: 269708240\nFax: \nEndereço eletrónico: contratacao.adsa@adp.pt\n28 - IDENTIFICAÇÃO DO(S) AUTOR(ES) DE ANÚNCIO\nNome: Mariza Cascão Ferreira de Almeida\nCargo: Gestora do Procedimento\n29 - ALTERAÇÃO\nMotivo da Alteração: Correção pelo adquirente\nIdentificador da Versão do Anúncio a Alterar: 3a3b7af1-c25a-4f15-9ad7-1a19b5b6cbe1-01\nIdentificador das Secções Alteradas do Anúncio Anterior: Condições de Apresentação\nDescrição das Alterações: Em função da aplicação do n.º 3 do artigo 64.º do «CCP»\nAlteração dos Documentos do Concurso: Sim\nData de alteração dos documentos do concurso: 08-01-2026\n419947524",
    "nipc": "505600005",
    "distrito": "Setúbal",
    "concelho": "Santiago do Cacém",
    "freguesia": "Freguesia de Santo André - Santiago do Cacém",
    "site": "www.adsa.pt",
    "email": "conratacao@adp.pt",
    "designacao_contrato": "Empreitada de execução para a \"Substituição da Caixa de Medição de Caudal e Conduta de Água Industrial à Repsol YPF, S.A.\"",
    "descricao": "Empreitada de execução para a \"Substituição da Caixa de Medição de Caudal e Conduta de Água Industrial à Repsol YPF, S.A.\"",
    "preco_base": "900.000,00 EUR",
    "prazo_execucao": "180 DIAS",
    "prazo_apresentacao_propostas": "23-02-2026 18:00",
    "fundos_eu": "Não",
    "plataforma_eletronica": "ACIN",
    "url_procedimento": "https://www.acingov.pt",
    "autor_nome": "Mariza Cascão Ferreira de Almeida",
    "autor_cargo": "Gestora do Procedimento"
  },
  {
    "numero_procedimento": "N/A",
    "entidade": "Município de Águeda",
    "link": "https://diariodarepublica.pt/dr/detalhe/contrato-publico/438-1003478782",
    "detalhes_completos": "1 - IDENTIFICAÇÃO E CONTACTOS DA ENTIDADE ADJUDICANTE\nDesignação da entidade adjudicante: Município de Águeda\nNIPC: 501090436\nServiço/Órgão/Pessoa de contacto: Serviço de Aprovisionamento e Contratação Pública\nEndereço: Praça do Município\nCódigo postal: 3754-500\nLocalidade: Águeda\nPaís: Portugal\nNUT III: PT16D\nDistrito: Aveiro\nConcelho: Águeda\nFreguesia: Todas\nTelefone: 234610070\nFax: 234610078\nEndereço da Entidade (URL): www.cm-agueda.pt\nEndereço Eletrónico: geral@cm-agueda.pt\neDelivery Gateway (URL): https://www.acingov.pt\nFunção da Organização: Adquirente\nNorma jurídica da Entidade Adjudicante: Organismo de direito público\nÁrea de atividade da Autoridade Adjudicante: Serviços públicos das administrações públicas\n2 - JORNAL OFICIAL DA UNIÃO EUROPEIA\nO procedimento a que este anúncio diz respeito também é publicitado no Jornal Oficial da União Europeia? Não\n3 - AVISO\nModelo de Anúncio: Concurso público\nData de Envio do Anúncio: 09-01-2026\n5 - PROCESSO\nTipo de Procedimento: Concurso público\nPreço base do procedimento: Sim\nValor do preço base do procedimento: 713.000,00 EUR\nProcedimento com lotes? Não\n6 - OBJETO DO CONTRATO\nNúmero de referência interna: CF/DF/EMP - 25/25\nDesignação do contrato: Repavimentação de vias do Concelho - 8ª fase\nDescrição: Repavimentação de vias do Concelho - 8ª fase\nTipo de Contrato Principal: Empreitada de Obras Públicas\nTipo de Contrato: Empreitada de Obras Públicas\nClassificação CPV (Vocabulário Comum para os Contratos Públicos)\nObjeto principal\nVocabulário Principal: 45233252\nPreço base s/IVA: 713.000,00 EUR\n7 - INDICAÇÕES ADICIONAIS\nO contrato envolve aquisição conjunta (satisfação de várias entidades)? Não\nO contrato é adjudicado por uma central de compras? Não\n8 - TÉCNICAS\nO concurso destina-se à celebração de um acordo-quadro? Inexistência de acordo-quadro\nÉ utilizado um leilão eletrónico? Não\nÉ adotada uma fase de negociação? Não\nSistema de Aquisição Dinâmico: Inexistência de sistema de aquisição dinâmico\n9 - LOCAL DA EXECUÇÃO DO CONTRATO\nLOCAL DA EXECUÇÃO DO CONTRATO (PROCEDIMENTO)\nPaís: Portugal\nNUT III: PT16D\nLocalidade: Águeda\nDistrito: Aveiro\nConcelho: Águeda\nFreguesia: União das Freguesias de Águeda e Borralha\nPaís: Portugal\nNUT III: PT16D\nLocalidade: Águeda\nDistrito: Aveiro\nConcelho: Águeda\nFreguesia: Freguesia de Valongo do Vouga\nPaís: Portugal\nNUT III: PT16D\nLocalidade: Águeda\nDistrito: Aveiro\nConcelho: Águeda\nFreguesia: União das Freguesias de Travassô e Óis da Ribeira\nPaís: Portugal\nNUT III: PT16D\nLocalidade: Águeda\nDistrito: Aveiro\nConcelho: Águeda\nFreguesia: União das Freguesias do Préstimo e Macieira de Alcoba\nPaís: Portugal\nNUT III: PT16D\nLocalidade: Águeda\nDistrito: Aveiro\nConcelho: Águeda\nFreguesia: União das Freguesias de Belazaima do Chão, Castanheira do Vouga e Agadão\nPaís: Portugal\nNUT III: PT16D\nLocalidade: Águeda\nDistrito: Aveiro\nConcelho: Águeda\nFreguesia: Freguesia de Aguada de Cima\nPaís: Portugal\nNUT III: PT16D\nLocalidade: Águeda\nDistrito: Aveiro\nConcelho: Águeda\nFreguesia: União das Freguesias de Barrô e Aguada de Baixo\nPaís: Portugal\nNUT III: PT16D\nLocalidade: Águeda\nDistrito: Aveiro\nConcelho: Águeda\nFreguesia: Freguesia de Fermentelos\nPaís: Portugal\nNUT III: PT16D\nLocalidade: Águeda\nDistrito: Aveiro\nConcelho: Águeda\nFreguesia: Freguesia de Macinhata do Vouga\nPaís: Portugal\nNUT III: PT16D\nLocalidade: Águeda\nDistrito: Aveiro\nConcelho: Águeda\nFreguesia: União das Freguesias de Trofa, Segadães e Lamas do Vouga\n10 - PRAZO DE EXECUÇÃO DO CONTRATO\nPrazo de execução do contrato: 120 DIAS\nPrevisão de renovações: Não\n11 - FUNDOS EU\nTêm fundos EU? Não\n12 - DOCUMENTOS DE HABILITAÇÃO\nHabilitação para o exercício da atividade profissional: Sim\nTipo: Alvará\nDescrição: 1ª Subcategoria da 2ª Categoria e da classe correspondente ao valor global da proposta, nos termos do disposto no artigo 8.º da Lei n.º 41/2015 de 3 de Junho, com as alterações introduzidas pela Lei n.º25/2018, de 14 de junho\n13 - CONDIÇÕES DE APRESENTAÇÃO\nPlataforma eletrónica utilizada pela entidade adjudicante: ACIN\nURL para Apresentação: https://www.acingov.pt\nAdmissibilidade da apresentação de propostas variantes: Não autorizado\nPrazo para apresentação das propostas: 09-02-2026 17:00\nPrazo durante o qual os concorrentes são obrigados a manter as respetivas propostas: 66 dias a contar do termo do prazo para a apresentação das propostas\nIndicação de Subcontratação na Proposta: Inexistência de indicação de subcontratação\n14 - PRESTAÇÃO DE CAUÇÃO\nPrestação de caução: Sim\nPercentagem: 5%\nDescrição da Garantia Exigida: O valor da caução é de 5.00% do preço contratual.\n15 - FORNECIMENTO DAS PEÇAS DO CONCURSO, APRESENTAÇÃO DE PEDIDOS DE PARTICIPAÇÃO E APRESENTAÇÃO DAS PROPOSTAS\nLink para acesso às peças do concurso (URL): https://www.acingov.pt/acingovprod/2/zonaPublica/zona_publica_c/donwloadProcedurePiece/MTAwOTMzMQ==\n20 - OUTROS REQUISITOS\nInformação sobre contratos reservados. Aplica-se a contratos reservados (54º-A)? Não\n21 - CRITÉRIO DE ADJUDICAÇÃO\nMultifator: Não\nMonofator:\nNome: Preço\n24 - CONDIÇÕES DO CONTRATO\nFaturação Eletrónica: Permitido\nObrigação de Subcontratação:\nCódigo da Obrigação de Subcontratação: Não é aplicável nenhuma obrigação de subcontratação.\n25 - COMPRA PÚBLICA ESTRATÉGICA\nCompra Pública Estratégica: Inexistência de contratação pública estratégica\n26 - INFORMAÇÕES ADICIONAIS\nContrato adequado para PME: Sim\nCobertura ACP (Acordo dos Contratos Públicos da Organização Mundial do Comércio): Não\n27 - IDENTIFICAÇÃO E CONTACTOS DO ÓRGÃO DE RECURSOS ADMINISTRATIVOS\nDesignação: Câmara Municipal de Águeda\nEndereço: Praça do Município\nCódigo postal: 3754-500\nLocalidade: Águeda\nTelefone: 234610070\nFax: \nEndereço eletrónico: geral@cm-agueda.pt\nPrazo de interposição do recurso: 5 dias\n28 - IDENTIFICAÇÃO DO(S) AUTOR(ES) DE ANÚNCIO\nNome: Jorge Henrique Fernandes de Almeida\nCargo: Presidente da Câmara Municipal de Águeda\n419947359",
    "nipc": "501090436",
    "distrito": "Aveiro",
    "concelho": "Águeda",
    "freguesia": "Todas",
    "site": "www.cm-agueda.pt",
    "email": "geral@cm-agueda.pt",
    "designacao_contrato": "Repavimentação de vias do Concelho - 8ª fase",
    "descricao": "Repavimentação de vias do Concelho - 8ª fase",
    "preco_base": "713.000,00 EUR",
    "prazo_execucao": "120 DIAS",
    "prazo_apresentacao_propostas": "09-02-2026 17:00",
    "fundos_eu": "Não",
    "plataforma_eletronica": "ACIN",
    "url_procedimento": "https://www.acingov.pt",
    "autor_nome": "Jorge Henrique Fernandes de Almeida",
    "autor_cargo": "Presidente da Câmara Municipal de Águeda"
  },
  {
    "numero_procedimento": "N/A",
    "entidade": "Cascais Envolvente - Gestão Social da Habitação, EM, SA",
    "link": "https://diariodarepublica.pt/dr/detalhe/contrato-publico/440-1003478815",
    "detalhes_completos": "1 - IDENTIFICAÇÃO E CONTACTOS DA ENTIDADE ADJUDICANTE\nDesignação da entidade adjudicante: Cascais Envolvente - Gestão Social da Habitação, EM, SA\nNIPC: 504538314\nEndereço: Complexo Multiserviços da CMC - Estrada de Manique nº 1818\nCódigo postal: 2645-131\nLocalidade: Alcabideche\nPaís: Portugal\nNUT III: PT170\nDistrito: Lisboa\nConcelho: Cascais\nFreguesia: Todas\nTelefone: 214812100\nFax: 214512109\nEndereço da Entidade (URL): https://www.cascais.pt/empresa-municipal/cascais-envolvente-\nEndereço Eletrónico: geral@cascaisenvolvente.pt\neDelivery Gateway (URL): https://www.acingov.pt\nFunção da Organização: Adquirente\nNorma jurídica da Entidade Adjudicante: Organismo de direito público\nÁrea de atividade da Autoridade Adjudicante: Serviços públicos das administrações públicas\n2 - JORNAL OFICIAL DA UNIÃO EUROPEIA\nO procedimento a que este anúncio diz respeito também é publicitado no Jornal Oficial da União Europeia? Não\n3 - AVISO\nModelo de Anúncio: Concurso público\nData de Envio do Anúncio: 09-01-2026\n5 - PROCESSO\nTipo de Procedimento: Concurso público\nPreço base do procedimento: Sim\nValor do preço base do procedimento: 25.000,00 EUR\nProcedimento com lotes? Não\n6 - OBJETO DO CONTRATO\nNúmero de referência interna: 051/2025\nDesignação do contrato: 051/2025 Aquisição de serviços para a remoção de bens e limpeza dos fogos devolutos em edifícios do parque habitacional no concelho de Cascais\nDescrição: 051/2025 Aquisição de serviços para a remoção de bens e limpeza dos fogos devolutos em edifícios do parque habitacional no concelho de Cascais\nTipo de Contrato Principal: Aquisição de Serviços\nTipo de Contrato: Aquisição de Serviços\nClassificação CPV (Vocabulário Comum para os Contratos Públicos)\nObjeto principal\nVocabulário Principal: 90911000\nPreço base s/IVA: 25.000,00 EUR\n7 - INDICAÇÕES ADICIONAIS\nO contrato envolve aquisição conjunta (satisfação de várias entidades)? Não\nO contrato é adjudicado por uma central de compras? Não\n8 - TÉCNICAS\nO concurso destina-se à celebração de um acordo-quadro? Inexistência de acordo-quadro\nÉ utilizado um leilão eletrónico? Não\nÉ adotada uma fase de negociação? Não\nSistema de Aquisição Dinâmico: Inexistência de sistema de aquisição dinâmico\n9 - LOCAL DA EXECUÇÃO DO CONTRATO\nLOCAL DA EXECUÇÃO DO CONTRATO (PROCEDIMENTO)\nPaís: Portugal\nNUT III: PT170\nLocalidade: Cascais\nDistrito: Lisboa\nConcelho: Cascais\nFreguesia: Todas\n10 - PRAZO DE EXECUÇÃO DO CONTRATO\nPrazo de execução do contrato: 365 DIAS\nPrevisão de renovações: Não\n11 - FUNDOS EU\nTêm fundos EU? Não\n12 - DOCUMENTOS DE HABILITAÇÃO\nHabilitação para o exercício da atividade profissional: Não\n13 - CONDIÇÕES DE APRESENTAÇÃO\nPlataforma eletrónica utilizada pela entidade adjudicante: ACIN\nURL para Apresentação: https://www.acingov.pt\nAdmissibilidade da apresentação de propostas variantes: Não autorizado\nPrazo para apresentação das propostas: 20-01-2026 17:00\nPrazo durante o qual os concorrentes são obrigados a manter as respetivas propostas: 66 dias a contar do termo do prazo para a apresentação das propostas\nIndicação de Subcontratação na Proposta: Inexistência de indicação de subcontratação\n14 - PRESTAÇÃO DE CAUÇÃO\nPrestação de caução: Não\n15 - FORNECIMENTO DAS PEÇAS DO CONCURSO, APRESENTAÇÃO DE PEDIDOS DE PARTICIPAÇÃO E APRESENTAÇÃO DAS PROPOSTAS\nLink para acesso às peças do concurso (URL): https://www.acingov.pt/acingovprod/2/zonaPublica/zona_publica_c/donwloadProcedurePiece/MTAzNjEzNw==\n20 - OUTROS REQUISITOS\nInformação sobre contratos reservados. Aplica-se a contratos reservados (54º-A)? Não\n21 - CRITÉRIO DE ADJUDICAÇÃO\nMultifator: Não\nMonofator:\nNome: Outros\nOutro nome: Fator Preço\n24 - CONDIÇÕES DO CONTRATO\nFaturação Eletrónica: Permitido\nObrigação de Subcontratação:\nCódigo da Obrigação de Subcontratação: Não é aplicável nenhuma obrigação de subcontratação.\n25 - COMPRA PÚBLICA ESTRATÉGICA\nCompra Pública Estratégica: Inexistência de contratação pública estratégica\n26 - INFORMAÇÕES ADICIONAIS\nContrato adequado para PME: Sim\nCobertura ACP (Acordo dos Contratos Públicos da Organização Mundial do Comércio): Não\n27 - IDENTIFICAÇÃO E CONTACTOS DO ÓRGÃO DE RECURSOS ADMINISTRATIVOS\nDesignação: Conselho de Administração da Cascais Envolvente.\nEndereço: Complexo Multiserviços da CMC Estrada de Manique nº 1818\nCódigo postal: 2645-131\nLocalidade: Alcabideche\nTelefone: 214812100\nFax: \nEndereço eletrónico: geral@cascaisenvolvente.pt\n28 - IDENTIFICAÇÃO DO(S) AUTOR(ES) DE ANÚNCIO\nNome: Filipa Fontoura\nCargo: Assistente Técnica\n419947474",
    "nipc": "504538314",
    "distrito": "Lisboa",
    "concelho": "Cascais",
    "freguesia": "Todas",
    "site": "https://www.cascais.pt/empresa-municipal/cascais-envolvente-",
    "email": "geral@cascaisenvolvente.pt",
    "designacao_contrato": "051/2025 Aquisição de serviços para a remoção de bens e limpeza dos fogos devolutos em edifícios do parque habitacional no concelho de Cascais",
    "descricao": "051/2025 Aquisição de serviços para a remoção de bens e limpeza dos fogos devolutos em edifícios do parque habitacional no concelho de Cascais",
    "preco_base": "25.000,00 EUR",
    "prazo_execucao": "365 DIAS",
    "prazo_apresentacao_propostas": "20-01-2026 17:00",
    "fundos_eu": "Não",
    "plataforma_eletronica": "ACIN",
    "url_procedimento": "https://www.acingov.pt",
    "autor_nome": "Filipa Fontoura",
    "autor_cargo": "Assistente Técnica"
  },
  {
    "numero_procedimento": "N/A",
    "entidade": "Município de Paredes de Coura",
    "link": "https://diariodarepublica.pt/dr/detalhe/contrato-publico/442-1003478861",
    "detalhes_completos": "1 - IDENTIFICAÇÃO E CONTACTOS DA ENTIDADE ADJUDICANTE\nDesignação da entidade adjudicante: Município de Paredes de Coura\nNIPC: 506632938\nEndereço: Lg. Viscde Moselos Aptd. 6\nCódigo postal: 4940-525\nLocalidade: Paredes de Coura\nPaís: Portugal\nNUT III: PT111\nDistrito: Viana do Castelo\nConcelho: Paredes de Coura\nFreguesia: Todas\nTelefone: 251780100\nFax: 251780118\nEndereço da Entidade (URL): www.paredesdecoura.pt\nEndereço Eletrónico: geral@paredesdecoura.pt\neDelivery Gateway (URL): https://community.vortal.biz/public/\nFunção da Organização: Adquirente\nNorma jurídica da Entidade Adjudicante: Autoridade local\nÁrea de atividade da Autoridade Adjudicante: Serviços públicos das administrações públicas\n2 - JORNAL OFICIAL DA UNIÃO EUROPEIA\nO procedimento a que este anúncio diz respeito também é publicitado no Jornal Oficial da União Europeia? Não\n3 - AVISO\nModelo de Anúncio: Concurso público\nData de Envio do Anúncio: 09-01-2026\n5 - PROCESSO\nTipo de Procedimento: Concurso público\nPreço base do procedimento: Sim\nValor do preço base do procedimento: 61.193,50 EUR\nProcedimento com lotes? Não\n6 - OBJETO DO CONTRATO\nNúmero de referência interna: 03/26_E\nDesignação do contrato: Execução de Muro no Covelo em Rubiães, Saneamento de Raízes e Repavimentação da Travessa de Sabariz em Romarigães, Repavimentação da Rua da Telhada e Rua do Meijal em São Martinho de Coura\nDescrição: Execução de Muro no Covelo em Rubiães, Saneamento de Raízes e Repavimentação da Travessa de Sabariz em Romarigães, Repavimentação da Rua da Telhada e Rua do Meijal em São Martinho de Coura\nTipo de Contrato Principal: Empreitada de Obras Públicas\nTipo de Contrato: Empreitada de Obras Públicas\nClassificação CPV (Vocabulário Comum para os Contratos Públicos)\nObjeto principal\nVocabulário Principal: 45262510\nPreço base s/IVA: 61.193,50 EUR\n7 - INDICAÇÕES ADICIONAIS\nO contrato envolve aquisição conjunta (satisfação de várias entidades)? Não\nO contrato é adjudicado por uma central de compras? Não\n8 - TÉCNICAS\nO concurso destina-se à celebração de um acordo-quadro? Inexistência de acordo-quadro\nÉ utilizado um leilão eletrónico? Não\nÉ adotada uma fase de negociação? Não\nSistema de Aquisição Dinâmico: Inexistência de sistema de aquisição dinâmico\n9 - LOCAL DA EXECUÇÃO DO CONTRATO\nLOCAL DA EXECUÇÃO DO CONTRATO (PROCEDIMENTO)\nPaís: Portugal\nNUT III: PT111\nLocalidade: Viana do Castelo\nDistrito: Viana do Castelo\nConcelho: Paredes de Coura\nFreguesia: Freguesia de Romarigães\n10 - PRAZO DE EXECUÇÃO DO CONTRATO\nPrazo de execução do contrato: 60 DIAS\nPrevisão de renovações: Não\n11 - FUNDOS EU\nTêm fundos EU? Não\n12 - DOCUMENTOS DE HABILITAÇÃO\nHabilitação para o exercício da atividade profissional: Sim\nTipo: Alvará\nDescrição: Alvará na 4ª subcategoria da 1ª categoria\n13 - CONDIÇÕES DE APRESENTAÇÃO\nPlataforma eletrónica utilizada pela entidade adjudicante: VORTAL\nURL para Apresentação: https://community.vortal.biz/public/\nAdmissibilidade da apresentação de propostas variantes: Não autorizado\nPrazo para apresentação das propostas: 19-01-2026 16:00\nPrazo durante o qual os concorrentes são obrigados a manter as respetivas propostas: 120 dias a contar do termo do prazo para a apresentação das propostas\nIndicação de Subcontratação na Proposta: Inexistência de indicação de subcontratação\n14 - PRESTAÇÃO DE CAUÇÃO\nPrestação de caução: Não\n15 - FORNECIMENTO DAS PEÇAS DO CONCURSO, APRESENTAÇÃO DE PEDIDOS DE PARTICIPAÇÃO E APRESENTAÇÃO DAS PROPOSTAS\nLink para acesso às peças do concurso (URL): https://community.vortal.biz/Public/public-tender-documents/bXd4YWNya05MY293bStSa3A2dWxhQWliV3ArZGNMMHVhU3ZQVzZIRWJVRU9DYVdnVlZxaXNjZ093KzF4Unk2WTRZdVBTOVNXWHB3UWZKWkovalYxY2c9PUJNXlF3\n20 - OUTROS REQUISITOS\nInformação sobre contratos reservados. Aplica-se a contratos reservados (54º-A)? Não\n21 - CRITÉRIO DE ADJUDICAÇÃO\nMultifator: Não\nMonofator:\nNome: Preço\n24 - CONDIÇÕES DO CONTRATO\nFaturação Eletrónica: Permitido\nObrigação de Subcontratação:\nCódigo da Obrigação de Subcontratação: Não é aplicável nenhuma obrigação de subcontratação.\n25 - COMPRA PÚBLICA ESTRATÉGICA\nCompra Pública Estratégica: Inexistência de contratação pública estratégica\n26 - INFORMAÇÕES ADICIONAIS\nContrato adequado para PME: Sim\nCobertura ACP (Acordo dos Contratos Públicos da Organização Mundial do Comércio): Não\n27 - IDENTIFICAÇÃO E CONTACTOS DO ÓRGÃO DE RECURSOS ADMINISTRATIVOS\nDesignação: Município de Paredes de Coura\nEndereço: Largo Visconde de Mozelos, Ap.6\nCódigo postal: 4941-909\nLocalidade: Paredes de Coura\nTelefone: +351 251780100\nFax: +351 251780100\nEndereço eletrónico: geral@paredesdecoura.pt\n28 - IDENTIFICAÇÃO DO(S) AUTOR(ES) DE ANÚNCIO\nNome: Tiago Manuel Pereira da Cunha\nCargo: Presidente\n419947535",
    "nipc": "506632938",
    "distrito": "Viana do Castelo",
    "concelho": "Paredes de Coura",
    "freguesia": "Todas",
    "site": "www.paredesdecoura.pt",
    "email": "geral@paredesdecoura.pt",
    "designacao_contrato": "Execução de Muro no Covelo em Rubiães, Saneamento de Raízes e Repavimentação da Travessa de Sabariz em Romarigães, Repavimentação da Rua da Telhada e Rua do Meijal em São Martinho de Coura",
    "descricao": "Execução de Muro no Covelo em Rubiães, Saneamento de Raízes e Repavimentação da Travessa de Sabariz em Romarigães, Repavimentação da Rua da Telhada e Rua do Meijal em São Martinho de Coura",
    "preco_base": "61.193,50 EUR",
    "prazo_execucao": "60 DIAS",
    "prazo_apresentacao_propostas": "19-01-2026 16:00",
    "fundos_eu": "Não",
    "plataforma_eletronica": "VORTAL",
    "url_procedimento": "https://community.vortal.biz/public/",
    "autor_nome": "Tiago Manuel Pereira da Cunha",
    "autor_cargo": "Presidente"
  },
  {
    "numero_procedimento": "N/A",
    "entidade": "Edia - Empresa de Desenvolvimento e Infra-Estruturas do Alqueva, SA",
    "link": "https://diariodarepublica.pt/dr/detalhe/contrato-publico/443-1003479092",
    "detalhes_completos": "1 - IDENTIFICAÇÃO E CONTACTOS DA ENTIDADE ADJUDICANTE\nDesignação da entidade adjudicante: Edia - Empresa de Desenvolvimento e Infra-Estruturas do Alqueva, SA\nNIPC: 503450189\nServiço/Órgão/Pessoa de contacto: DIE - Direção de Infraestruturas e Energia - Engª Isabel Grazina\nEndereço: Rua Zeca Afonso, nº  2 Beja\nCódigo postal: 7800-522\nLocalidade: Beja\nPaís: Portugal\nNUT III: PT184\nDistrito: Beja\nConcelho: Beja\nFreguesia: União das Freguesias de Beja (Santiago Maior e São João Baptista)\nTelefone: 284315100\nFax: 284315101\nEndereço da Entidade (URL): www.edia.pt\nEndereço Eletrónico: edia@edia.pt\neDelivery Gateway (URL): https://community.vortal.biz/public/\nFunção da Organização: Adquirente\nNorma jurídica da Entidade Adjudicante: Organismo de direito público, controlado por uma autoridade da administração central\nÁrea de atividade da Autoridade Adjudicante: Serviços públicos das administrações públicas\n2 - JORNAL OFICIAL DA UNIÃO EUROPEIA\nO procedimento a que este anúncio diz respeito também é publicitado no Jornal Oficial da União Europeia? Não\n3 - AVISO\nModelo de Anúncio: Concurso público\nData de Envio do Anúncio: 09-01-2026\n5 - PROCESSO\nTipo de Procedimento: Concurso público\nPreço base do procedimento: Sim\nValor do preço base do procedimento: 90.000,00 EUR\nProcedimento com lotes? Não\n6 - OBJETO DO CONTRATO\nNúmero de referência interna: CP 46 2026\nDesignação do contrato: Prestação de serviços de manutenção corretiva de válvulas das estações elevatórias de Pedrogão - Margem Direita e dos Caliços-Grande Reparação\nDescrição: Prestação de serviços de manutenção corretiva de válvulas das estações elevatórias de Pedrogão - Margem Direita e dos Caliços-Grande Reparação\nTipo de Contrato Principal: Aquisição de Serviços\nTipo de Contrato: Aquisição de Serviços\nClassificação CPV (Vocabulário Comum para os Contratos Públicos)\nObjeto principal\nVocabulário Principal: 50512000\nPreço base s/IVA: 90.000,00 EUR\n7 - INDICAÇÕES ADICIONAIS\nO contrato envolve aquisição conjunta (satisfação de várias entidades)? Não\nO contrato é adjudicado por uma central de compras? Não\n8 - TÉCNICAS\nO concurso destina-se à celebração de um acordo-quadro? Inexistência de acordo-quadro\nÉ utilizado um leilão eletrónico? Não\nÉ adotada uma fase de negociação? Não\nSistema de Aquisição Dinâmico: Inexistência de sistema de aquisição dinâmico\n9 - LOCAL DA EXECUÇÃO DO CONTRATO\nLOCAL DA EXECUÇÃO DO CONTRATO (PROCEDIMENTO)\nPaís: Portugal\nNUT III: PT184\nLocalidade: Beja\nDistrito: Beja\nConcelho: Beja\nFreguesia: União das Freguesias de Beja (Santiago Maior e São João Baptista)\n10 - PRAZO DE EXECUÇÃO DO CONTRATO\nPrazo de execução do contrato: 180 DIAS\nPrevisão de renovações: Não\n11 - FUNDOS EU\nTêm fundos EU? Não\n12 - DOCUMENTOS DE HABILITAÇÃO\nHabilitação para o exercício da atividade profissional: Não\n13 - CONDIÇÕES DE APRESENTAÇÃO\nPlataforma eletrónica utilizada pela entidade adjudicante: VORTAL\nURL para Apresentação: https://community.vortal.biz/public/\nAdmissibilidade da apresentação de propostas variantes: Não autorizado\nPrazo para apresentação das propostas: 19-01-2026 18:00\nPrazo durante o qual os concorrentes são obrigados a manter as respetivas propostas: 180 dias a contar do termo do prazo para a apresentação das propostas\nIndicação de Subcontratação na Proposta: Inexistência de indicação de subcontratação\n14 - PRESTAÇÃO DE CAUÇÃO\nPrestação de caução: Sim\nPercentagem: 5%\nDescrição da Garantia Exigida: de acordo com o disposto nos artigos 88.º e seguintes do CCP\n15 - FORNECIMENTO DAS PEÇAS DO CONCURSO, APRESENTAÇÃO DE PEDIDOS DE PARTICIPAÇÃO E APRESENTAÇÃO DAS PROPOSTAS\nLink para acesso às peças do concurso (URL): https://community.vortal.biz/Public/public-tender-documents/MjcrczhYNWhDWDZ4NzNCVDFqbW5ZcklUZ09KYkEwaFloc1dSR0xzWU8ydmErb3prNVBKd1VXN2E4L1BSengvQUR6VTFtQXRvckw2d3VpcUU5YXpnQVE9PTBTS0lD\n20 - OUTROS REQUISITOS\nInformação sobre contratos reservados. Aplica-se a contratos reservados (54º-A)? Não\n21 - CRITÉRIO DE ADJUDICAÇÃO\nMultifator: Não\nMonofator:\nNome: Preço\n24 - CONDIÇÕES DO CONTRATO\nFaturação Eletrónica: Permitido\nObrigação de Subcontratação:\nCódigo da Obrigação de Subcontratação: Não é aplicável nenhuma obrigação de subcontratação.\n25 - COMPRA PÚBLICA ESTRATÉGICA\nCompra Pública Estratégica: Inexistência de contratação pública estratégica\n26 - INFORMAÇÕES ADICIONAIS\nContrato adequado para PME: Sim\nCobertura ACP (Acordo dos Contratos Públicos da Organização Mundial do Comércio): Não\n27 - IDENTIFICAÇÃO E CONTACTOS DO ÓRGÃO DE RECURSOS ADMINISTRATIVOS\nDesignação: Conselho de Administração\nEndereço: Beja\nCódigo postal: 7800-522\nLocalidade: Beja\nTelefone: +351 284315100\nFax: +351 284315101\nEndereço eletrónico: edia@edia.pt\nPrazo de interposição do recurso: 5 dias\n28 - IDENTIFICAÇÃO DO(S) AUTOR(ES) DE ANÚNCIO\nNome: Ana Rita Canada\nCargo: Técnica Superior do Gabinete de Apoio Jurídico\n419947565",
    "nipc": "503450189",
    "distrito": "Beja",
    "concelho": "Beja",
    "freguesia": "União das Freguesias de Beja (Santiago Maior e São João Baptista)",
    "site": "www.edia.pt",
    "email": "edia@edia.pt",
    "designacao_contrato": "Prestação de serviços de manutenção corretiva de válvulas das estações elevatórias de Pedrogão - Margem Direita e dos Caliços-Grande Reparação",
    "descricao": "Prestação de serviços de manutenção corretiva de válvulas das estações elevatórias de Pedrogão - Margem Direita e dos Caliços-Grande Reparação",
    "preco_base": "90.000,00 EUR",
    "prazo_execucao": "180 DIAS",
    "prazo_apresentacao_propostas": "19-01-2026 18:00",
    "fundos_eu": "Não",
    "plataforma_eletronica": "VORTAL",
    "url_procedimento": "https://community.vortal.biz/public/",
    "autor_nome": "Ana Rita Canada",
    "autor_cargo": "Técnica Superior do Gabinete de Apoio Jurídico"
  },
  {
    "numero_procedimento": "N/A",
    "entidade": "AnÃºncio de procedimento  n.Âº 444/2026  -  DiÃ¡rio da RepÃºblica n.Âº 6/2026, SÃ©rie II de 2026-01-09",
    "link": "https://diariodarepublica.pt/dr/detalhe/contrato-publico/444-1003479134"
  },
  {
    "numero_procedimento": "N/A",
    "entidade": "AnÃºncio de procedimento  n.Âº 448/2026  -  DiÃ¡rio da RepÃºblica n.Âº 6/2026, SÃ©rie II de 2026-01-09",
    "link": "https://diariodarepublica.pt/dr/detalhe/contrato-publico/448-1003479510"
  },
  {
    "numero_procedimento": "N/A",
    "entidade": "Unidade Local de Saúde do Baixo Alentejo, EPE",
    "link": "https://diariodarepublica.pt/dr/detalhe/contrato-publico/452-1003479512",
    "detalhes_completos": "1 - IDENTIFICAÇÃO E CONTACTOS DA ENTIDADE ADJUDICANTE\nDesignação da entidade adjudicante: Unidade Local de Saúde do Baixo Alentejo, EPE\nNIPC: 508754275\nEndereço: Rua Dr. António Fernando Covas Lima\nCódigo postal: 7801-849\nLocalidade: Beja\nPaís: Portugal\nNUT III: PT184\nDistrito: Beja\nConcelho: Beja\nFreguesia: União das Freguesias de Beja (Santiago Maior e São João Baptista)\nTelefone: 284310201\nFax: 284310201\nEndereço da Entidade (URL): www.ulsba.min-saude.pt\nEndereço Eletrónico: concursos@ulsba.min-saude.pt\neDelivery Gateway (URL): https://community.vortal.biz/public/\nFunção da Organização: Adquirente\nNorma jurídica da Entidade Adjudicante: Organismo de direito público\nÁrea de atividade da Autoridade Adjudicante: Saúde\n2 - JORNAL OFICIAL DA UNIÃO EUROPEIA\nO procedimento a que este anúncio diz respeito também é publicitado no Jornal Oficial da União Europeia? Não\n3 - AVISO\nModelo de Anúncio: Concurso público\nData de Envio do Anúncio: 09-01-2026\n5 - PROCESSO\nTipo de Procedimento: Concurso público\nPreço base do procedimento: Sim\nValor do preço base do procedimento: 95.445,00 EUR\nProcedimento com lotes? Não\n6 - OBJETO DO CONTRATO\nNúmero de referência interna: 98000126\nDesignação do contrato: REAGENTES PARA IMUNOHISTOQUÍMICA\nDescrição: AQUISIÇÃO DE REAGENTES PARA IMUNOHISTOQUÍMICA\nTipo de Contrato Principal: Aquisição de Bens Móveis\nTipo de Contrato: Aquisição de Bens Móveis\nClassificação CPV (Vocabulário Comum para os Contratos Públicos)\nObjeto principal\nVocabulário Principal: 33696500\nPreço base s/IVA: 95.445,00 EUR\n7 - INDICAÇÕES ADICIONAIS\nO contrato envolve aquisição conjunta (satisfação de várias entidades)? Não\nO contrato é adjudicado por uma central de compras? Não\n8 - TÉCNICAS\nO concurso destina-se à celebração de um acordo-quadro? Inexistência de acordo-quadro\nÉ utilizado um leilão eletrónico? Não\nÉ adotada uma fase de negociação? Não\nSistema de Aquisição Dinâmico: Inexistência de sistema de aquisição dinâmico\n9 - LOCAL DA EXECUÇÃO DO CONTRATO\nLOCAL DA EXECUÇÃO DO CONTRATO (PROCEDIMENTO)\nPaís: Portugal\nNUT III: PT184\nLocalidade: Beja\nDistrito: Beja\nConcelho: Beja\nFreguesia: União das Freguesias de Beja (Santiago Maior e São João Baptista)\n10 - PRAZO DE EXECUÇÃO DO CONTRATO\nPrazo de execução do contrato: 3 ANOS\nPrevisão de renovações: Não\n11 - FUNDOS EU\nTêm fundos EU? Não\n12 - DOCUMENTOS DE HABILITAÇÃO\nHabilitação para o exercício da atividade profissional: Não\n13 - CONDIÇÕES DE APRESENTAÇÃO\nPlataforma eletrónica utilizada pela entidade adjudicante: VORTAL\nURL para Apresentação: https://community.vortal.biz/public/\nAdmissibilidade da apresentação de propostas variantes: Não autorizado\nPrazo para apresentação das propostas: 27-01-2026 18:00\nPrazo durante o qual os concorrentes são obrigados a manter as respetivas propostas: 180 dias a contar do termo do prazo para a apresentação das propostas\nIndicação de Subcontratação na Proposta: Inexistência de indicação de subcontratação\n14 - PRESTAÇÃO DE CAUÇÃO\nPrestação de caução: Não\n15 - FORNECIMENTO DAS PEÇAS DO CONCURSO, APRESENTAÇÃO DE PEDIDOS DE PARTICIPAÇÃO E APRESENTAÇÃO DAS PROPOSTAS\nLink para acesso às peças do concurso (URL): https://community.vortal.biz/Public/public-tender-documents/MVRmZmtrNFY1eGVDSHlNVkp1a1oyQzd2S1VrZWx3VGxhc2xybkltU0tCYVhybWM5cUp3c21YU1JNa01uR0hQWUZzak90a1VFSlhIakwyWjR4VFF4ZGc9PU40X0JO\n20 - OUTROS REQUISITOS\nInformação sobre contratos reservados. Aplica-se a contratos reservados (54º-A)? Não\n21 - CRITÉRIO DE ADJUDICAÇÃO\nMultifator: Não\nMonofator:\nNome: Preço\n24 - CONDIÇÕES DO CONTRATO\nFaturação Eletrónica: Permitido\nObrigação de Subcontratação:\nCódigo da Obrigação de Subcontratação: Não é aplicável nenhuma obrigação de subcontratação.\n25 - COMPRA PÚBLICA ESTRATÉGICA\nCompra Pública Estratégica: Inexistência de contratação pública estratégica\n26 - INFORMAÇÕES ADICIONAIS\nContrato adequado para PME: Sim\nCobertura ACP (Acordo dos Contratos Públicos da Organização Mundial do Comércio): Não\n27 - IDENTIFICAÇÃO E CONTACTOS DO ÓRGÃO DE RECURSOS ADMINISTRATIVOS\nDesignação: Unidade Local de Saúde do Baixo Alentejo E.P.E\nEndereço: RUA DR ANTONIO FERNANDO COVAS LIMA\nCódigo postal: 7801-849\nLocalidade: Beja\nTelefone: +351 284310200\nFax: +351 284318311\nEndereço eletrónico: ca@ulsba.min-saude.pt\n28 - IDENTIFICAÇÃO DO(S) AUTOR(ES) DE ANÚNCIO\nNome: Helena Isabel Ricardo da Graça\nCargo: Administradora Hospitalar - Diretora do Serviço de Aprovisionamento e Logística\n419947534",
    "nipc": "508754275",
    "distrito": "Beja",
    "concelho": "Beja",
    "freguesia": "União das Freguesias de Beja (Santiago Maior e São João Baptista)",
    "site": "www.ulsba.min-saude.pt",
    "email": "concursos@ulsba.min-saude.pt",
    "designacao_contrato": "REAGENTES PARA IMUNOHISTOQUÍMICA",
    "descricao": "AQUISIÇÃO DE REAGENTES PARA IMUNOHISTOQUÍMICA",
    "preco_base": "95.445,00 EUR",
    "prazo_execucao": "3 ANOS",
    "prazo_apresentacao_propostas": "27-01-2026 18:00",
    "fundos_eu": "Não",
    "plataforma_eletronica": "VORTAL",
    "url_procedimento": "https://community.vortal.biz/public/",
    "autor_nome": "Helena Isabel Ricardo da Graça",
    "autor_cargo": "Administradora Hospitalar - Diretora do Serviço de Aprovisionamento e Logística"
  },
  {
    "numero_procedimento": "N/A",
    "entidade": "Unidade Local de Saúde de São João, EPE",
    "link": "https://diariodarepublica.pt/dr/detalhe/contrato-publico/455-1003479514",
    "detalhes_completos": "1 - IDENTIFICAÇÃO E CONTACTOS DA ENTIDADE ADJUDICANTE\nDesignação da entidade adjudicante: Unidade Local de Saúde de São João, EPE\nNIPC: 509821197\nEndereço: Alameda Prof. Hernâni Monteiro\nCódigo postal: 4200-319\nLocalidade: Área Metropolitana do Porto\nPaís: Portugal\nNUT III: PT11A\nDistrito: Porto\nConcelho: Porto\nFreguesia: Freguesia de Paranhos - Porto\nTelefone: 225512100\nFax: 225504463\nEndereço da Entidade (URL): https://portal-chsj.min-saude.pt/\nEndereço Eletrónico: geral@ulssjoao.min-saude.pt\neDelivery Gateway (URL): https://community.vortal.biz/public/\nFunção da Organização: Adquirente\nNorma jurídica da Entidade Adjudicante: Organismo de direito público\nÁrea de atividade da Autoridade Adjudicante: Saúde\n2 - JORNAL OFICIAL DA UNIÃO EUROPEIA\nO procedimento a que este anúncio diz respeito também é publicitado no Jornal Oficial da União Europeia? Não\n3 - AVISO\nModelo de Anúncio: Concurso público\nData de Envio do Anúncio: 09-01-2026\n5 - PROCESSO\nTipo de Procedimento: Concurso público\nPreço base do procedimento: Sim\nValor do preço base do procedimento: 1.576.228,00 EUR\nProcedimento com lotes? Não\n6 - OBJETO DO CONTRATO\nNúmero de referência interna: 31001226\nDesignação do contrato: Empreitada de Requalificação da Área de Imagiologia para Resposta a Situações de Urgência - Ressonância Magnética\nDescrição: Empreitada de Requalificação da Área de Imagiologia para Resposta a Situações de Urgência - Ressonância Magnética\nTipo de Contrato Principal: Empreitada de Obras Públicas\nTipo de Contrato: Empreitada de Obras Públicas\nClassificação CPV (Vocabulário Comum para os Contratos Públicos)\nObjeto principal\nVocabulário Principal: 45215000\nPreço base s/IVA: 1.576.228,00 EUR\n7 - INDICAÇÕES ADICIONAIS\nO contrato envolve aquisição conjunta (satisfação de várias entidades)? Não\nO contrato é adjudicado por uma central de compras? Não\n8 - TÉCNICAS\nO concurso destina-se à celebração de um acordo-quadro? Inexistência de acordo-quadro\nÉ utilizado um leilão eletrónico? Não\nÉ adotada uma fase de negociação? Não\nSistema de Aquisição Dinâmico: Inexistência de sistema de aquisição dinâmico\n9 - LOCAL DA EXECUÇÃO DO CONTRATO\nLOCAL DA EXECUÇÃO DO CONTRATO (PROCEDIMENTO)\nPaís: Portugal\nNUT III: PT11A\nLocalidade: Área Metropolitana do Porto\nDistrito: Porto\nConcelho: Porto\nFreguesia: Freguesia de Paranhos - Porto\n10 - PRAZO DE EXECUÇÃO DO CONTRATO\nPrazo de execução do contrato: 120 DIAS\nPrevisão de renovações: Não\n11 - FUNDOS EU\nTêm fundos EU? Sim\n12 - DOCUMENTOS DE HABILITAÇÃO\nHabilitação para o exercício da atividade profissional: Não\n13 - CONDIÇÕES DE APRESENTAÇÃO\nPlataforma eletrónica utilizada pela entidade adjudicante: VORTAL\nURL para Apresentação: https://community.vortal.biz/public/\nAdmissibilidade da apresentação de propostas variantes: Não autorizado\nPrazo para apresentação das propostas: 30-01-2026 17:00\nPrazo durante o qual os concorrentes são obrigados a manter as respetivas propostas: 90 dias a contar do termo do prazo para a apresentação das propostas\nIndicação de Subcontratação na Proposta: Inexistência de indicação de subcontratação\n14 - PRESTAÇÃO DE CAUÇÃO\nPrestação de caução: Sim\nPercentagem: 5%\nDescrição da Garantia Exigida: Ver programa \n15 - FORNECIMENTO DAS PEÇAS DO CONCURSO, APRESENTAÇÃO DE PEDIDOS DE PARTICIPAÇÃO E APRESENTAÇÃO DAS PROPOSTAS\nLink para acesso às peças do concurso (URL): https://community.vortal.biz/Public/public-tender-documents/byt2OG9YYjNtWGRZMGtBTkNMTzV1Yk0rQjhxLzE1WGJrUFpLVG5GcGtRRVU0b2ZHcHB5b05Ya0ZuZ2p2NEJrYUNjTjM5N2dXSjlKZG5UWEw0ZjV1aVE9PV5MalQz\n20 - OUTROS REQUISITOS\nInformação sobre contratos reservados. Aplica-se a contratos reservados (54º-A)? Não\n21 - CRITÉRIO DE ADJUDICAÇÃO\nMultifator: Sim\nFator: \nNome: Preço\nPonderação: 55%\nSubfatores: Não\nFator: \nNome: Qualidade\nPonderação: 45%\nSubfatores: Não\n24 - CONDIÇÕES DO CONTRATO\nFaturação Eletrónica: Permitido\nObrigação de Subcontratação:\nCódigo da Obrigação de Subcontratação: Não é aplicável nenhuma obrigação de subcontratação.\n25 - COMPRA PÚBLICA ESTRATÉGICA\nCompra Pública Estratégica: Inexistência de contratação pública estratégica\n26 - INFORMAÇÕES ADICIONAIS\nContrato adequado para PME: Sim\nCobertura ACP (Acordo dos Contratos Públicos da Organização Mundial do Comércio): Não\n27 - IDENTIFICAÇÃO E CONTACTOS DO ÓRGÃO DE RECURSOS ADMINISTRATIVOS\nDesignação: Conselho de Administração\nEndereço: ULSSJ - Alameda Professor Hernani Monteiro\nCódigo postal: 4200-319\nLocalidade: Porto\nTelefone: +351 225512100\nFax: +351 225025766\nEndereço eletrónico: ca@ulssjoao.min-saude.pt\n28 - IDENTIFICAÇÃO DO(S) AUTOR(ES) DE ANÚNCIO\nNome: Tiago Ferreira\nCargo: Diretor do Serviço de Aprovisionameno \n419947575",
    "nipc": "509821197",
    "distrito": "Porto",
    "concelho": "Porto",
    "freguesia": "Freguesia de Paranhos - Porto",
    "site": "https://portal-chsj.min-saude.pt/",
    "email": "geral@ulssjoao.min-saude.pt",
    "designacao_contrato": "Empreitada de Requalificação da Área de Imagiologia para Resposta a Situações de Urgência - Ressonância Magnética",
    "descricao": "Empreitada de Requalificação da Área de Imagiologia para Resposta a Situações de Urgência - Ressonância Magnética",
    "preco_base": "1.576.228,00 EUR",
    "prazo_execucao": "120 DIAS",
    "prazo_apresentacao_propostas": "30-01-2026 17:00",
    "fundos_eu": "Sim",
    "plataforma_eletronica": "VORTAL",
    "url_procedimento": "https://community.vortal.biz/public/",
    "autor_nome": "Tiago Ferreira",
    "autor_cargo": "Diretor do Serviço de Aprovisionameno"
  },
  {
    "numero_procedimento": "N/A",
    "entidade": "AnÃºncio de procedimento  n.Âº 456/2026  -  DiÃ¡rio da RepÃºblica n.Âº 6/2026, SÃ©rie II de 2026-01-09",
    "link": "https://diariodarepublica.pt/dr/detalhe/contrato-publico/456-1003479515"
  },
  {
    "numero_procedimento": "N/A",
    "entidade": "Faculdade de Medicina",
    "link": "https://diariodarepublica.pt/dr/detalhe/contrato-publico/459-1003479516",
    "detalhes_completos": "1 - IDENTIFICAÇÃO E CONTACTOS DA ENTIDADE ADJUDICANTE\nDesignação da entidade adjudicante: Faculdade de Medicina\nNIPC: 502662875\nServiço/Órgão/Pessoa de contacto: Área de Compras e Património\nEndereço: AV PROF EGAS MONIZ\nCódigo postal: 1649-028\nLocalidade: LISBOA\nPaís: Portugal\nNUT III: PT170\nDistrito: Lisboa\nConcelho: Lisboa\nFreguesia: Freguesia de Alvalade - Lisboa\nTelefone: 217985100\nFax: 217985100\nEndereço da Entidade (URL): https://www.medicina.ulisboa.pt/\nEndereço Eletrónico: fmul@medicina.ulisboa.pt\neDelivery Gateway (URL): https://www.acingov.pt\nFunção da Organização: Adquirente\nNorma jurídica da Entidade Adjudicante: Organismo de direito público\nÁrea de atividade da Autoridade Adjudicante: Educação\n2 - JORNAL OFICIAL DA UNIÃO EUROPEIA\nO procedimento a que este anúncio diz respeito também é publicitado no Jornal Oficial da União Europeia? Não\n3 - AVISO\nModelo de Anúncio: Concurso público\nData de Envio do Anúncio: 09-01-2026\n5 - PROCESSO\nTipo de Procedimento: Concurso público\nPreço base do procedimento: Sim\nValor do preço base do procedimento: 121.325,87 EUR\nProcedimento com lotes? Sim\nNº Máx. de Lotes Autorizado: 3\nNúmero máximo de lotes que podem ser adjudicados a um concorrente: 3\n6 - OBJETO DO CONTRATO\nNúmero de referência interna: 2507000956\nDesignação do contrato: Aquisição de Serviços de Fiscalização e Coordenação de Segurança em Obra para diversas Empreitadas a desenvolver na Faculdade de Medicina de Lisboa em 2025/2026\nDescrição: Aquisição de Serviços de Fiscalização e Coordenação de Segurança em Obra para diversas Empreitadas a desenvolver na Faculdade de Medicina de Lisboa em 2025/2026\nTipo de Contrato Principal: Aquisição de Serviços\nTipo de Contrato: Aquisição de Serviços\nClassificação CPV (Vocabulário Comum para os Contratos Públicos)\nObjeto principal\nVocabulário Principal: 71000000\nPreço base s/IVA: 121.325,87 EUR\nLotes: \nNº: LOT-0001\nDescrição do Lote: Empreitada de substituição de Chillers e instalação de novos Chillers/Bombas de Calor - MM2 PRR Fundo Ambienta\nPreço base s/IVA: 35.876,80 EUR\nClassificação CPV (Vocabulário Comum para os Contratos Públicos)\nObjeto principal\nVocabulário Principal: 71000000\nNº: LOT-0002\nDescrição do Lote: Empreitada - Substituição de Luminárias interiores do Edifício Egas Moniz - MM1 PRR Fundo Ambiental\nPreço base s/IVA: 26.994,93 EUR\nClassificação CPV (Vocabulário Comum para os Contratos Públicos)\nObjeto principal\nVocabulário Principal: 71000000\nNº: LOT-0003\nDescrição do Lote: Empreitada de Construção de um Estabulário para a Faculdade de Medicina da Universidade de Lisboa\nPreço base s/IVA: 58.454,14 EUR\nClassificação CPV (Vocabulário Comum para os Contratos Públicos)\nObjeto principal\nVocabulário Principal: 71000000\n7 - INDICAÇÕES ADICIONAIS\nO contrato envolve aquisição conjunta (satisfação de várias entidades)? Não\nO contrato é adjudicado por uma central de compras? Não\n8 - TÉCNICAS\nO concurso destina-se à celebração de um acordo-quadro? Inexistência de acordo-quadro\nÉ utilizado um leilão eletrónico? Não\nÉ adotada uma fase de negociação? Não\nSistema de Aquisição Dinâmico: Inexistência de sistema de aquisição dinâmico\n9 - LOCAL DA EXECUÇÃO DO CONTRATO\nLOCAL DA EXECUÇÃO DO CONTRATO (PROCEDIMENTO)\nPaís: Portugal\nNUT III: PT170\nLocalidade: Freguesia de Alvalade - Lisboa\nDistrito: Lisboa\nConcelho: Lisboa\nFreguesia: Freguesia de Alvalade - Lisboa\nLOCAL DA EXECUÇÃO DO CONTRATO (LOTE)\nIdentificador do Lote: LOT-0001; LOT-0002; LOT-0003\nPaís: Portugal\nNUT III: PT170\nLocalidade: Freguesia de Alvalade - Lisboa\nDistrito: Lisboa\nConcelho: Lisboa\nFreguesia: Freguesia de Alvalade - Lisboa\n10 - PRAZO DE EXECUÇÃO DO CONTRATO\nIdentificador do Lote: LOT-0001; LOT-0002; LOT-0003\nPrazo de execução do contrato: 420 DIAS\nPrevisão de renovações: Não\n11 - FUNDOS EU\nIdentificador do Lote: LOT-0001; LOT-0002; LOT-0003\nTêm fundos EU? Não\n12 - DOCUMENTOS DE HABILITAÇÃO\nHabilitação para o exercício da atividade profissional: Não\n13 - CONDIÇÕES DE APRESENTAÇÃO\nPlataforma eletrónica utilizada pela entidade adjudicante: ACIN\nURL para Apresentação: https://www.acingov.pt\nAdmissibilidade da apresentação de propostas variantes: Não autorizado\nPrazo para apresentação das propostas: 21-01-2026 23:59\nPrazo durante o qual os concorrentes são obrigados a manter as respetivas propostas: 66 dias a contar do termo do prazo para a apresentação das propostas\nIndicação de Subcontratação na Proposta: Inexistência de indicação de subcontratação\n14 - PRESTAÇÃO DE CAUÇÃO\nPrestação de caução: Não\n15 - FORNECIMENTO DAS PEÇAS DO CONCURSO, APRESENTAÇÃO DE PEDIDOS DE PARTICIPAÇÃO E APRESENTAÇÃO DAS PROPOSTAS\nLink para acesso às peças do concurso (URL): https://www.acingov.pt/acingovprod/2/zonaPublica/zona_publica_c/donwloadProcedurePiece/MTA0MDc5Ng==\n20 - OUTROS REQUISITOS\nIdentificador do Lote: LOT-0001; LOT-0002; LOT-0003\nInformação sobre contratos reservados. Aplica-se a contratos reservados (54º-A)? Não\n21 - CRITÉRIO DE ADJUDICAÇÃO\nO Critério de adjudicação é diferenciado por lote? Não\nMultifator: Não\nMonofator:\nNome: Preço\n24 - CONDIÇÕES DO CONTRATO\nIdentificador do Lote: LOT-0001; LOT-0002; LOT-0003\nFaturação Eletrónica: Permitido\nObrigação de Subcontratação:\nCódigo da Obrigação de Subcontratação: Não é aplicável nenhuma obrigação de subcontratação.\n25 - COMPRA PÚBLICA ESTRATÉGICA\nCompra Pública Estratégica: Inexistência de contratação pública estratégica\n26 - INFORMAÇÕES ADICIONAIS\nIdentificador do Lote: LOT-0001; LOT-0002; LOT-0003\nContrato adequado para PME: Sim\nCobertura ACP (Acordo dos Contratos Públicos da Organização Mundial do Comércio): Não\n27 - IDENTIFICAÇÃO E CONTACTOS DO ÓRGÃO DE RECURSOS ADMINISTRATIVOS\nDesignação: Diretor\nEndereço: AV PROF EGAS MONIZ\nCódigo postal: 1649-028\nLocalidade: LISBOA\nTelefone: 217999582\nFax: \nEndereço eletrónico: fmul@medicina.ulisboa.pt\n28 - IDENTIFICAÇÃO DO(S) AUTOR(ES) DE ANÚNCIO\nNome: Ana Maria Lopes Lapinha\nCargo: Técnica Superior\n419947582",
    "nipc": "502662875",
    "distrito": "Lisboa",
    "concelho": "Lisboa",
    "freguesia": "Freguesia de Alvalade - Lisboa",
    "site": "https://www.medicina.ulisboa.pt/",
    "email": "fmul@medicina.ulisboa.pt",
    "designacao_contrato": "Aquisição de Serviços de Fiscalização e Coordenação de Segurança em Obra para diversas Empreitadas a desenvolver na Faculdade de Medicina de Lisboa em 2025/2026",
    "descricao": "Aquisição de Serviços de Fiscalização e Coordenação de Segurança em Obra para diversas Empreitadas a desenvolver na Faculdade de Medicina de Lisboa em 2025/2026",
    "preco_base": "121.325,87 EUR",
    "prazo_execucao": "420 DIAS",
    "prazo_apresentacao_propostas": "21-01-2026 23:59",
    "fundos_eu": "Não",
    "plataforma_eletronica": "ACIN",
    "url_procedimento": "https://www.acingov.pt",
    "autor_nome": "Ana Maria Lopes Lapinha",
    "autor_cargo": "Técnica Superior"
  },
  {
    "numero_procedimento": "N/A",
    "entidade": "Ordem dos Advogados",
    "link": "https://diariodarepublica.pt/dr/detalhe/contrato-publico/460-1003479518",
    "detalhes_completos": "1 - IDENTIFICAÇÃO E CONTACTOS DA ENTIDADE ADJUDICANTE\nDesignação da entidade adjudicante: Ordem dos Advogados\nNIPC: 500965099\nEndereço: Lg.  S.Domingos Nr. 14 1º\nCódigo postal: 1050-000\nLocalidade: Lisboa\nPaís: Portugal\nNUT III: PT170\nDistrito: Lisboa\nConcelho: Lisboa\nFreguesia: Todas\nTelefone: 218823550\nFax: 218862403\nEndereço da Entidade (URL): https://portal.oa.pt/\nEndereço Eletrónico: cons.geral@cg.oa.pt\neDelivery Gateway (URL): https://community.vortal.biz/public/\nFunção da Organização: Adquirente\nNorma jurídica da Entidade Adjudicante: Autoridade da administração central\nÁrea de atividade da Autoridade Adjudicante: Serviços públicos das administrações públicas\n2 - JORNAL OFICIAL DA UNIÃO EUROPEIA\nO procedimento a que este anúncio diz respeito também é publicitado no Jornal Oficial da União Europeia? Não\n3 - AVISO\nModelo de Anúncio: Concurso público\nData de Envio do Anúncio: 09-01-2026\n5 - PROCESSO\nTipo de Procedimento: Concurso público\nPreço base do procedimento: Sim\nValor do preço base do procedimento: 197.000,00 EUR\nProcedimento com lotes? Não\n6 - OBJETO DO CONTRATO\nNúmero de referência interna: CNC894/OA/2025  Seguro de Saúde OA\nDesignação do contrato: CNC894/OA/2025  Seguro de Saúde OA\nDescrição: CNC894/OA/2025_ Seguro de Saúde para os trabalhadores da Ordem dos Advogados\nTipo de Contrato Principal: Aquisição de Serviços\nTipo de Contrato: Aquisição de Serviços\nClassificação CPV (Vocabulário Comum para os Contratos Públicos)\nObjeto principal\nVocabulário Principal: 66512200\nPreço base s/IVA: 197.000,00 EUR\n7 - INDICAÇÕES ADICIONAIS\nO contrato envolve aquisição conjunta (satisfação de várias entidades)? Não\nO contrato é adjudicado por uma central de compras? Não\n8 - TÉCNICAS\nO concurso destina-se à celebração de um acordo-quadro? Inexistência de acordo-quadro\nÉ utilizado um leilão eletrónico? Não\nÉ adotada uma fase de negociação? Não\nSistema de Aquisição Dinâmico: Inexistência de sistema de aquisição dinâmico\n9 - LOCAL DA EXECUÇÃO DO CONTRATO\nLOCAL DA EXECUÇÃO DO CONTRATO (PROCEDIMENTO)\nPaís: Portugal\nNUT III: PT170\nLocalidade: Lisboa\nDistrito: Lisboa\nConcelho: Lisboa\nFreguesia: Todas\n10 - PRAZO DE EXECUÇÃO DO CONTRATO\nPrazo de execução do contrato: 12 MESES\nPrevisão de renovações: Não\n11 - FUNDOS EU\nTêm fundos EU? Não\n12 - DOCUMENTOS DE HABILITAÇÃO\nHabilitação para o exercício da atividade profissional: Não\n13 - CONDIÇÕES DE APRESENTAÇÃO\nPlataforma eletrónica utilizada pela entidade adjudicante: VORTAL\nURL para Apresentação: https://community.vortal.biz/public/\nAdmissibilidade da apresentação de propostas variantes: Não autorizado\nPrazo para apresentação das propostas: 15-01-2026 23:59\nPrazo durante o qual os concorrentes são obrigados a manter as respetivas propostas: 66 dias a contar do termo do prazo para a apresentação das propostas\nIndicação de Subcontratação na Proposta: Inexistência de indicação de subcontratação\n14 - PRESTAÇÃO DE CAUÇÃO\nPrestação de caução: Não\n15 - FORNECIMENTO DAS PEÇAS DO CONCURSO, APRESENTAÇÃO DE PEDIDOS DE PARTICIPAÇÃO E APRESENTAÇÃO DAS PROPOSTAS\nLink para acesso às peças do concurso (URL): https://community.vortal.biz/Public/public-tender-documents/cm41RzJYQ2E4bWp4SytzdHVkNlpNZ1NwZVVrS1pNWUszZERiZDVnT3hyb0FhQWJ3M3E5SHZSbDdtNXpGL3FLK0hOYWVaR1paZGhncEJod3hUS3gxVHc9PVNRKClM\n20 - OUTROS REQUISITOS\nInformação sobre contratos reservados. Aplica-se a contratos reservados (54º-A)? Não\n21 - CRITÉRIO DE ADJUDICAÇÃO\nMultifator: Não\nMonofator:\nNome: Outros\nOutro nome: Preço\n24 - CONDIÇÕES DO CONTRATO\nFaturação Eletrónica: Permitido\nObrigação de Subcontratação:\nCódigo da Obrigação de Subcontratação: Não é aplicável nenhuma obrigação de subcontratação.\n25 - COMPRA PÚBLICA ESTRATÉGICA\nCompra Pública Estratégica: Inexistência de contratação pública estratégica\n26 - INFORMAÇÕES ADICIONAIS\nContrato adequado para PME: Sim\nCobertura ACP (Acordo dos Contratos Públicos da Organização Mundial do Comércio): Não\n27 - IDENTIFICAÇÃO E CONTACTOS DO ÓRGÃO DE RECURSOS ADMINISTRATIVOS\nDesignação: Presidente do Conselho Geral da Ordem dos Advogados\nEndereço: Largo de S. Domingos\nCódigo postal: 1169-060\nLocalidade: Lisboa\nTelefone: +351 218823550\nFax: +351 218862403\nEndereço eletrónico: gab.bastonario@cg.oa.pt\n28 - IDENTIFICAÇÃO DO(S) AUTOR(ES) DE ANÚNCIO\nNome: Ana Rola\nCargo: serviço de compras do conselho geral da ordem dos advogados\n419947573",
    "nipc": "500965099",
    "distrito": "Lisboa",
    "concelho": "Lisboa",
    "freguesia": "Todas",
    "site": "https://portal.oa.pt/",
    "email": "cons.geral@cg.oa.pt",
    "designacao_contrato": "CNC894/OA/2025 Seguro de Saúde OA",
    "descricao": "CNC894/OA/2025_ Seguro de Saúde para os trabalhadores da Ordem dos Advogados",
    "preco_base": "197.000,00 EUR",
    "prazo_execucao": "12 MESES",
    "prazo_apresentacao_propostas": "15-01-2026 23:59",
    "fundos_eu": "Não",
    "plataforma_eletronica": "VORTAL",
    "url_procedimento": "https://community.vortal.biz/public/",
    "autor_nome": "Ana Rola",
    "autor_cargo": "serviço de compras do conselho geral da ordem dos advogados"
  },
  {
    "numero_procedimento": "N/A",
    "entidade": "Município de Tondela",
    "link": "https://diariodarepublica.pt/dr/detalhe/contrato-publico/461-1003479519",
    "detalhes_completos": "1 - IDENTIFICAÇÃO E CONTACTOS DA ENTIDADE ADJUDICANTE\nDesignação da entidade adjudicante: Município de Tondela\nNIPC: 506822680\nServiço/Órgão/Pessoa de contacto: Presidente\nEndereço: Largo da República nº 16\nCódigo postal: 3464-001\nLocalidade: Tondela\nPaís: Portugal\nNUT III: PT16G\nDistrito: Viseu\nConcelho: Tondela\nFreguesia: União das Freguesias de Tondela e Nandufe\nTelefone: 232811110\nFax: 232811120\nEndereço da Entidade (URL): www.cm-tondela.pt\nEndereço Eletrónico: obras.publicas@cm-tondela.pt\neDelivery Gateway (URL): https://www.acingov.pt\nFunção da Organização: Adquirente\nNorma jurídica da Entidade Adjudicante: Organismo de direito público\nÁrea de atividade da Autoridade Adjudicante: Serviços públicos das administrações públicas\n2 - JORNAL OFICIAL DA UNIÃO EUROPEIA\nO procedimento a que este anúncio diz respeito também é publicitado no Jornal Oficial da União Europeia? Não\n3 - AVISO\nModelo de Anúncio: Concurso público\nData de Envio do Anúncio: 09-01-2026\n5 - PROCESSO\nTipo de Procedimento: Concurso público\nPreço base do procedimento: Sim\nValor do preço base do procedimento: 94.500,00 EUR\nProcedimento com lotes? Não\n6 - OBJETO DO CONTRATO\nNúmero de referência interna: 83/2025 - F/P\nDesignação do contrato: Aquisição de serviços de Segurança e Saúde no Trabalho\nDescrição: Aquisição de serviços de Segurança e Saúde no Trabalho\nTipo de Contrato Principal: Aquisição de Serviços\nTipo de Contrato: Aquisição de Serviços\nClassificação CPV (Vocabulário Comum para os Contratos Públicos)\nObjeto principal\nVocabulário Principal: 85147000\nPreço base s/IVA: 94.500,00 EUR\n7 - INDICAÇÕES ADICIONAIS\nO contrato envolve aquisição conjunta (satisfação de várias entidades)? Não\nO contrato é adjudicado por uma central de compras? Sim\n8 - TÉCNICAS\nO concurso destina-se à celebração de um acordo-quadro? Inexistência de acordo-quadro\nÉ utilizado um leilão eletrónico? Não\nÉ adotada uma fase de negociação? Não\nSistema de Aquisição Dinâmico: Inexistência de sistema de aquisição dinâmico\n9 - LOCAL DA EXECUÇÃO DO CONTRATO\nLOCAL DA EXECUÇÃO DO CONTRATO (PROCEDIMENTO)\nPaís: Portugal\nNUT III: PT16G\nLocalidade: Tondela\nDistrito: Viseu\nConcelho: Tondela\nFreguesia: União das Freguesias de Tondela e Nandufe\n10 - PRAZO DE EXECUÇÃO DO CONTRATO\nPrazo de execução do contrato: 36 MESES\nPrevisão de renovações: Não\n11 - FUNDOS EU\nTêm fundos EU? Não\n12 - DOCUMENTOS DE HABILITAÇÃO\nHabilitação para o exercício da atividade profissional: Não\n13 - CONDIÇÕES DE APRESENTAÇÃO\nPlataforma eletrónica utilizada pela entidade adjudicante: ACIN\nURL para Apresentação: https://www.acingov.pt\nAdmissibilidade da apresentação de propostas variantes: Não autorizado\nPrazo para apresentação das propostas: 13-01-2026 23:59\nPrazo durante o qual os concorrentes são obrigados a manter as respetivas propostas: 66 dias a contar do termo do prazo para a apresentação das propostas\nIndicação de Subcontratação na Proposta: Inexistência de indicação de subcontratação\n14 - PRESTAÇÃO DE CAUÇÃO\nPrestação de caução: Não\n15 - FORNECIMENTO DAS PEÇAS DO CONCURSO, APRESENTAÇÃO DE PEDIDOS DE PARTICIPAÇÃO E APRESENTAÇÃO DAS PROPOSTAS\nLink para acesso às peças do concurso (URL): https://www.acingov.pt/acingovprod/2/zonaPublica/zona_publica_c/donwloadProcedurePiece/MTAwMTM4OQ==\n20 - OUTROS REQUISITOS\nInformação sobre contratos reservados. Aplica-se a contratos reservados (54º-A)? Não\n21 - CRITÉRIO DE ADJUDICAÇÃO\nMultifator: Sim\nFator: \nNome: Preço\nPonderação: 50%\nSubfatores: Não\nFator: \nNome: Outros\nOutro Nome: Recursos técnicos e logísticos\nPonderação: 50%\nSubfatores: Sim\nSubfatores: \nNome: B.1. Proximidade de Clínica própria à Sede do Município Edifício Paços do Concelho\nPonderação : 30%; \nNome: B.2. Possibilidade de realização de consultas em Unidade Móvel de Saúde\nPonderação : 30%; \nNome: B.3. Experiência da Equipa Técnica 40\nPonderação : 40%; \n24 - CONDIÇÕES DO CONTRATO\nFaturação Eletrónica: Permitido\nObrigação de Subcontratação:\nCódigo da Obrigação de Subcontratação: Não é aplicável nenhuma obrigação de subcontratação.\n25 - COMPRA PÚBLICA ESTRATÉGICA\nCompra Pública Estratégica: Inexistência de contratação pública estratégica\n26 - INFORMAÇÕES ADICIONAIS\nContrato adequado para PME: Não\nCobertura ACP (Acordo dos Contratos Públicos da Organização Mundial do Comércio): Não\n27 - IDENTIFICAÇÃO E CONTACTOS DO ÓRGÃO DE RECURSOS ADMINISTRATIVOS\nDesignação: Câmara Municipal de Tondela\nEndereço: Câmara Municipal de Tondela, Largo da Republica, 16\nCódigo postal: 3464-001\nLocalidade: TONDELA\nTelefone: 232811110\nFax: \nEndereço eletrónico: geral@cm-tondela.pt\nPrazo de interposição do recurso: 5 dias\n28 - IDENTIFICAÇÃO DO(S) AUTOR(ES) DE ANÚNCIO\nNome: Fátima Carla Antunes Borges\nCargo: Presidente\n419947376",
    "nipc": "506822680",
    "distrito": "Viseu",
    "concelho": "Tondela",
    "freguesia": "União das Freguesias de Tondela e Nandufe",
    "site": "www.cm-tondela.pt",
    "email": "obras.publicas@cm-tondela.pt",
    "designacao_contrato": "Aquisição de serviços de Segurança e Saúde no Trabalho",
    "descricao": "Aquisição de serviços de Segurança e Saúde no Trabalho",
    "preco_base": "94.500,00 EUR",
    "prazo_execucao": "36 MESES",
    "prazo_apresentacao_propostas": "13-01-2026 23:59",
    "fundos_eu": "Não",
    "plataforma_eletronica": "ACIN",
    "url_procedimento": "https://www.acingov.pt",
    "autor_nome": "Fátima Carla Antunes Borges",
    "autor_cargo": "Presidente"
  },
  {
    "numero_procedimento": "N/A",
    "entidade": "Município de Braga",
    "link": "https://diariodarepublica.pt/dr/detalhe/contrato-publico/462-1003479524",
    "detalhes_completos": "1 - IDENTIFICAÇÃO E CONTACTOS DA ENTIDADE ADJUDICANTE\nDesignação da entidade adjudicante: Município de Braga\nNIPC: 506901173\nEndereço: Praça do Municípal\nCódigo postal: 4700-435\nLocalidade: Braga\nPaís: Portugal\nNUT III: PT112\nDistrito: Braga\nConcelho: Braga\nFreguesia: União das Freguesias de Braga (Maximinos, Sé e Cividade)\nTelefone: 253616060\nFax: 253203151\nEndereço da Entidade (URL): www.cm-braga.pt\nEndereço Eletrónico: contratacao.publica@cm-braga.pt\neDelivery Gateway (URL): https://community.vortal.biz/public/\nFunção da Organização: Adquirente\nNorma jurídica da Entidade Adjudicante: Autoridade local\nÁrea de atividade da Autoridade Adjudicante: Serviços públicos das administrações públicas\n2 - JORNAL OFICIAL DA UNIÃO EUROPEIA\nO procedimento a que este anúncio diz respeito também é publicitado no Jornal Oficial da União Europeia? Não\n3 - AVISO\nModelo de Anúncio: Concurso público\nData de Envio do Anúncio: 09-01-2026\n5 - PROCESSO\nTipo de Procedimento: Concurso público\nPreço base do procedimento: Sim\nValor do preço base do procedimento: 305.051,79 EUR\nProcedimento com lotes? Não\n6 - OBJETO DO CONTRATO\nNúmero de referência interna: CPE.38.25.DMOSM\nDesignação do contrato: MUSEU DOS BISCAÍNHOS – REQUALIFICAÇÃO DE INSTALAÇÕES ELETROTÉCNICAS EXISTENTES\nDescrição: MUSEU DOS BISCAÍNHOS – REQUALIFICAÇÃO DE INSTALAÇÕES ELETROTÉCNICAS EXISTENTES\nTipo de Contrato Principal: Empreitada de Obras Públicas\nTipo de Contrato: Empreitada de Obras Públicas\nClassificação CPV (Vocabulário Comum para os Contratos Públicos)\nObjeto principal\nVocabulário Principal: 45453100\nPreço base s/IVA: 305.051,79 EUR\n7 - INDICAÇÕES ADICIONAIS\nO contrato envolve aquisição conjunta (satisfação de várias entidades)? Não\nO contrato é adjudicado por uma central de compras? Não\n8 - TÉCNICAS\nO concurso destina-se à celebração de um acordo-quadro? Inexistência de acordo-quadro\nÉ utilizado um leilão eletrónico? Não\nÉ adotada uma fase de negociação? Não\nSistema de Aquisição Dinâmico: Inexistência de sistema de aquisição dinâmico\n9 - LOCAL DA EXECUÇÃO DO CONTRATO\nLOCAL DA EXECUÇÃO DO CONTRATO (PROCEDIMENTO)\nPaís: Portugal\nNUT III: PT112\nLocalidade: Braga\nDistrito: Braga\nConcelho: Braga\nFreguesia: Todas\n10 - PRAZO DE EXECUÇÃO DO CONTRATO\nPrazo de execução do contrato: 120 DIAS\nPrevisão de renovações: Não\n11 - FUNDOS EU\nTêm fundos EU? Não\n12 - DOCUMENTOS DE HABILITAÇÃO\nHabilitação para o exercício da atividade profissional: Sim\nTipo: Alvará\nDescrição: De acordo com o artigo 22.º do Programa do Concurso.\n13 - CONDIÇÕES DE APRESENTAÇÃO\nPlataforma eletrónica utilizada pela entidade adjudicante: VORTAL\nURL para Apresentação: https://community.vortal.biz/public/\nAdmissibilidade da apresentação de propostas variantes: Não autorizado\nPrazo para apresentação das propostas: 25-01-2026 18:00\nPrazo durante o qual os concorrentes são obrigados a manter as respetivas propostas: 120 dias a contar do termo do prazo para a apresentação das propostas\nIndicação de Subcontratação na Proposta: Inexistência de indicação de subcontratação\n14 - PRESTAÇÃO DE CAUÇÃO\nPrestação de caução: Não\n15 - FORNECIMENTO DAS PEÇAS DO CONCURSO, APRESENTAÇÃO DE PEDIDOS DE PARTICIPAÇÃO E APRESENTAÇÃO DAS PROPOSTAS\nLink para acesso às peças do concurso (URL): https://community.vortal.biz/Public/public-tender-documents/dys4bmtIazh2bE8ybUpiRTc4TTVweWxuWFJSTVVVL2M1b3BBdW5HWWVGWmNpRHkxSUxHNU1zYWxmdmpXTXNwRWw4MFFSZzhoL3hmN1JkeU45UkNnOVE9PWpacnpF\n20 - OUTROS REQUISITOS\nInformação sobre contratos reservados. Aplica-se a contratos reservados (54º-A)? Não\n21 - CRITÉRIO DE ADJUDICAÇÃO\nMultifator: Sim\nFator: \nNome: Preço\nPonderação: 70%\nSubfatores: Não\nFator: \nNome: Outros\nOutro Nome: Prazo de Execução\nPonderação: 30%\nSubfatores: Não\n24 - CONDIÇÕES DO CONTRATO\nFaturação Eletrónica: Permitido\nObrigação de Subcontratação:\nCódigo da Obrigação de Subcontratação: Não é aplicável nenhuma obrigação de subcontratação.\n25 - COMPRA PÚBLICA ESTRATÉGICA\nCompra Pública Estratégica: Inexistência de contratação pública estratégica\n26 - INFORMAÇÕES ADICIONAIS\nContrato adequado para PME: Sim\nCobertura ACP (Acordo dos Contratos Públicos da Organização Mundial do Comércio): Não\n27 - IDENTIFICAÇÃO E CONTACTOS DO ÓRGÃO DE RECURSOS ADMINISTRATIVOS\nDesignação: Presidente da Câmara Municipal de Braga\nEndereço: Praça do Município\nCódigo postal: 4700-435\nLocalidade: Braga\nTelefone: +351 253616060\nFax: +351 253203151\nEndereço eletrónico: info@cm-braga.pt\n28 - IDENTIFICAÇÃO DO(S) AUTOR(ES) DE ANÚNCIO\nNome: Rita Gonçalves\nCargo: Técnico Superior\n419947197",
    "nipc": "506901173",
    "distrito": "Braga",
    "concelho": "Braga",
    "freguesia": "União das Freguesias de Braga (Maximinos, Sé e Cividade)",
    "site": "www.cm-braga.pt",
    "email": "contratacao.publica@cm-braga.pt",
    "designacao_contrato": "MUSEU DOS BISCAÍNHOS – REQUALIFICAÇÃO DE INSTALAÇÕES ELETROTÉCNICAS EXISTENTES",
    "descricao": "MUSEU DOS BISCAÍNHOS – REQUALIFICAÇÃO DE INSTALAÇÕES ELETROTÉCNICAS EXISTENTES",
    "preco_base": "305.051,79 EUR",
    "prazo_execucao": "120 DIAS",
    "prazo_apresentacao_propostas": "25-01-2026 18:00",
    "fundos_eu": "Não",
    "plataforma_eletronica": "VORTAL",
    "url_procedimento": "https://community.vortal.biz/public/",
    "autor_nome": "Rita Gonçalves",
    "autor_cargo": "Técnico Superior"
  },
  {
    "numero_procedimento": "N/A",
    "entidade": "AnÃºncio de procedimento  n.Âº 463/2026  -  DiÃ¡rio da RepÃºblica n.Âº 6/2026, SÃ©rie II de 2026-01-09",
    "link": "https://diariodarepublica.pt/dr/detalhe/contrato-publico/463-1003479526"
  },
  {
    "numero_procedimento": "N/A",
    "entidade": "Município de Palmela",
    "link": "https://diariodarepublica.pt/dr/detalhe/contrato-publico/464-1003479527",
    "detalhes_completos": "1 - IDENTIFICAÇÃO E CONTACTOS DA ENTIDADE ADJUDICANTE\nDesignação da entidade adjudicante: Município de Palmela\nNIPC: 506187543\nEndereço: Largo Município , Palmela\nCódigo postal: 2954-001\nLocalidade: Setúbal\nPaís: Portugal\nNUT III: PT170\nDistrito: Setúbal\nConcelho: Palmela\nFreguesia: Freguesia de Palmela\nTelefone: 212 336 600\nFax: 212 336 619\nEndereço da Entidade (URL): www.cm-palmela.pt\nEndereço Eletrónico: geral@cm-palmela.pt\neDelivery Gateway (URL): https://community.vortal.biz/public/\nFunção da Organização: Adquirente\nNorma jurídica da Entidade Adjudicante: Organismo de direito público\nÁrea de atividade da Autoridade Adjudicante: Serviços públicos das administrações públicas\n2 - JORNAL OFICIAL DA UNIÃO EUROPEIA\nO procedimento a que este anúncio diz respeito também é publicitado no Jornal Oficial da União Europeia? Não\n3 - AVISO\nModelo de Anúncio: Concurso público\nData de Envio do Anúncio: 09-01-2026\n5 - PROCESSO\nTipo de Procedimento: Concurso público\nPreço base do procedimento: Sim\nValor do preço base do procedimento: 170.800,04 EUR\nProcedimento com lotes? Não\n6 - OBJETO DO CONTRATO\nNúmero de referência interna: 0204.4.8.027/2025\nDesignação do contrato: Licenciamento de software para gestão das competências municipais na área da educação\nDescrição: Licenciamento de software para gestão das competências municipais na área da educação\nTipo de Contrato Principal: Aquisição de Serviços\nTipo de Contrato: Aquisição de Serviços\nClassificação CPV (Vocabulário Comum para os Contratos Públicos)\nObjeto principal\nVocabulário Principal: 72510000\nPreço base s/IVA: 170.800,04 EUR\n7 - INDICAÇÕES ADICIONAIS\nO contrato envolve aquisição conjunta (satisfação de várias entidades)? Não\nO contrato é adjudicado por uma central de compras? Não\n8 - TÉCNICAS\nO concurso destina-se à celebração de um acordo-quadro? Inexistência de acordo-quadro\nÉ utilizado um leilão eletrónico? Não\nÉ adotada uma fase de negociação? Não\nSistema de Aquisição Dinâmico: Inexistência de sistema de aquisição dinâmico\n9 - LOCAL DA EXECUÇÃO DO CONTRATO\nLOCAL DA EXECUÇÃO DO CONTRATO (PROCEDIMENTO)\nPaís: Portugal\nNUT III: PT170\nLocalidade: Palmela\nDistrito: Setúbal\nConcelho: Palmela\nFreguesia: Todas\n10 - PRAZO DE EXECUÇÃO DO CONTRATO\nPrazo de execução do contrato: 36 MESES\nPrevisão de renovações: Não\n11 - FUNDOS EU\nTêm fundos EU? Não\n12 - DOCUMENTOS DE HABILITAÇÃO\nHabilitação para o exercício da atividade profissional: Não\n13 - CONDIÇÕES DE APRESENTAÇÃO\nPlataforma eletrónica utilizada pela entidade adjudicante: VORTAL\nURL para Apresentação: https://community.vortal.biz/public/\nAdmissibilidade da apresentação de propostas variantes: Não autorizado\nPrazo para apresentação das propostas: 24-01-2026 23:59\nPrazo durante o qual os concorrentes são obrigados a manter as respetivas propostas: 90 dias a contar do termo do prazo para a apresentação das propostas\nIndicação de Subcontratação na Proposta: Inexistência de indicação de subcontratação\n14 - PRESTAÇÃO DE CAUÇÃO\nPrestação de caução: Sim\nPercentagem: 5%\nDescrição da Garantia Exigida: Conforme ponto 19. do Programa\n15 - FORNECIMENTO DAS PEÇAS DO CONCURSO, APRESENTAÇÃO DE PEDIDOS DE PARTICIPAÇÃO E APRESENTAÇÃO DAS PROPOSTAS\nLink para acesso às peças do concurso (URL): https://community.vortal.biz/Public/public-tender-documents/bXZlcnZsT3BvNEVqMXFaaXpXYlJta0F5L2dEMUZ2UE0rdEZuN1UvMEhmK1p4N29vblg1UTdpUGFneTVVb0lySXoxbWhyV0tLN0t6dlJQNUpoenVDbnc9PVlGN2FC\n20 - OUTROS REQUISITOS\nInformação sobre contratos reservados. Aplica-se a contratos reservados (54º-A)? Não\n21 - CRITÉRIO DE ADJUDICAÇÃO\nMultifator: Sim\nFator: \nNome: Preço\nPonderação: 30%\nSubfatores: Não\nFator: \nNome: Qualidade\nPonderação: 70%\nSubfatores: Não\n24 - CONDIÇÕES DO CONTRATO\nFaturação Eletrónica: Permitido\nObrigação de Subcontratação:\nCódigo da Obrigação de Subcontratação: Não é aplicável nenhuma obrigação de subcontratação.\n25 - COMPRA PÚBLICA ESTRATÉGICA\nCompra Pública Estratégica: Inexistência de contratação pública estratégica\n26 - INFORMAÇÕES ADICIONAIS\nContrato adequado para PME: Sim\nCobertura ACP (Acordo dos Contratos Públicos da Organização Mundial do Comércio): Não\n27 - IDENTIFICAÇÃO E CONTACTOS DO ÓRGÃO DE RECURSOS ADMINISTRATIVOS\nDesignação: Ana Teresa Vicente\nEndereço: Largo do Municipo\nCódigo postal: 2954-001\nLocalidade: Palmela\nTelefone: +351 212336600\nFax: +351 212336619\nEndereço eletrónico: compras@cm-palmela.pt\n28 - IDENTIFICAÇÃO DO(S) AUTOR(ES) DE ANÚNCIO\nNome: Ana Teresa Vicente\nCargo: Presidente da Câmara\n419947088",
    "nipc": "506187543",
    "distrito": "Setúbal",
    "concelho": "Palmela",
    "freguesia": "Freguesia de Palmela",
    "site": "www.cm-palmela.pt",
    "email": "geral@cm-palmela.pt",
    "designacao_contrato": "Licenciamento de software para gestão das competências municipais na área da educação",
    "descricao": "Licenciamento de software para gestão das competências municipais na área da educação",
    "preco_base": "170.800,04 EUR",
    "prazo_execucao": "36 MESES",
    "prazo_apresentacao_propostas": "24-01-2026 23:59",
    "fundos_eu": "Não",
    "plataforma_eletronica": "VORTAL",
    "url_procedimento": "https://community.vortal.biz/public/",
    "autor_nome": "Ana Teresa Vicente",
    "autor_cargo": "Presidente da Câmara"
  },
  {
    "numero_procedimento": "N/A",
    "entidade": "Município de Avis",
    "link": "https://diariodarepublica.pt/dr/detalhe/contrato-publico/465-1003479528",
    "detalhes_completos": "1 - IDENTIFICAÇÃO E CONTACTOS DA ENTIDADE ADJUDICANTE\nDesignação da entidade adjudicante: Município de Avis\nNIPC: 502789824\nServiço/Órgão/Pessoa de contacto: Serviço de Aprovisionamento\nEndereço: Lg. Candido Dos Reis, 11\nCódigo postal: 7480-116\nLocalidade: Portalegre\nPaís: Portugal\nNUT III: PT186\nDistrito: Portalegre\nConcelho: Avis\nFreguesia: Todas\nTelefone: 242410060\nFax: 242410099\nEndereço da Entidade (URL): www.cm-avis.pt\nEndereço Eletrónico: geral@cm-avis.pt\neDelivery Gateway (URL): https://community.vortal.biz/public/\nFunção da Organização: Adquirente\nNorma jurídica da Entidade Adjudicante: Autoridade local\nÁrea de atividade da Autoridade Adjudicante: Serviços públicos das administrações públicas\n2 - JORNAL OFICIAL DA UNIÃO EUROPEIA\nO procedimento a que este anúncio diz respeito também é publicitado no Jornal Oficial da União Europeia? Não\n3 - AVISO\nModelo de Anúncio: Concurso público\nData de Envio do Anúncio: 09-01-2026\n5 - PROCESSO\nTipo de Procedimento: Concurso público\nPreço base do procedimento: Sim\nValor do preço base do procedimento: 18.500,00 EUR\nProcedimento com lotes? Não\n6 - OBJETO DO CONTRATO\nNúmero de referência interna: AVIS/1/CPN/S/25 - ANÁLISES AGUA\nDesignação do contrato: Análises de água para consumo humano\nDescrição: Análises de água para consumo humano\nTipo de Contrato Principal: Aquisição de Serviços\nTipo de Contrato: Aquisição de Serviços\nClassificação CPV (Vocabulário Comum para os Contratos Públicos)\nObjeto principal\nVocabulário Principal: 71620000\nPreço base s/IVA: 18.500,00 EUR\n7 - INDICAÇÕES ADICIONAIS\nO contrato envolve aquisição conjunta (satisfação de várias entidades)? Não\nO contrato é adjudicado por uma central de compras? Não\n8 - TÉCNICAS\nO concurso destina-se à celebração de um acordo-quadro? Inexistência de acordo-quadro\nÉ utilizado um leilão eletrónico? Não\nÉ adotada uma fase de negociação? Não\nSistema de Aquisição Dinâmico: Inexistência de sistema de aquisição dinâmico\n9 - LOCAL DA EXECUÇÃO DO CONTRATO\nLOCAL DA EXECUÇÃO DO CONTRATO (PROCEDIMENTO)\nPaís: Portugal\nNUT III: PT186\nLocalidade: Portalegre\nDistrito: Portalegre\nConcelho: Avis\nFreguesia: Todas\n10 - PRAZO DE EXECUÇÃO DO CONTRATO\nPrazo de execução do contrato: 12 MESES\nPrevisão de renovações: Não\n11 - FUNDOS EU\nTêm fundos EU? Não\n12 - DOCUMENTOS DE HABILITAÇÃO\nHabilitação para o exercício da atividade profissional: Não\n13 - CONDIÇÕES DE APRESENTAÇÃO\nPlataforma eletrónica utilizada pela entidade adjudicante: VORTAL\nURL para Apresentação: https://community.vortal.biz/public/\nAdmissibilidade da apresentação de propostas variantes: Não autorizado\nPrazo para apresentação das propostas: 19-01-2026 16:00\nPrazo durante o qual os concorrentes são obrigados a manter as respetivas propostas: 66 dias a contar do termo do prazo para a apresentação das propostas\nIndicação de Subcontratação na Proposta: Inexistência de indicação de subcontratação\n14 - PRESTAÇÃO DE CAUÇÃO\nPrestação de caução: Não\n15 - FORNECIMENTO DAS PEÇAS DO CONCURSO, APRESENTAÇÃO DE PEDIDOS DE PARTICIPAÇÃO E APRESENTAÇÃO DAS PROPOSTAS\nLink para acesso às peças do concurso (URL): https://community.vortal.biz/Public/public-tender-documents/MVR4T2w3bmU3L2FBOVdYUHNvM01qaUZneUR3aDBmM2tzWVRWc1hXREZodUhJMzhrVHJjMzdXQ2pvU2F0cS9zZUE4VVk0Ykh4NHJGMStpVWJHOU1sNWc9PXFaQUQj\n20 - OUTROS REQUISITOS\nInformação sobre contratos reservados. Aplica-se a contratos reservados (54º-A)? Não\n21 - CRITÉRIO DE ADJUDICAÇÃO\nMultifator: Não\nMonofator:\nNome: Preço\n24 - CONDIÇÕES DO CONTRATO\nFaturação Eletrónica: Permitido\nObrigação de Subcontratação:\nCódigo da Obrigação de Subcontratação: Não é aplicável nenhuma obrigação de subcontratação.\n25 - COMPRA PÚBLICA ESTRATÉGICA\nCompra Pública Estratégica: Inexistência de contratação pública estratégica\n26 - INFORMAÇÕES ADICIONAIS\nContrato adequado para PME: Sim\nCobertura ACP (Acordo dos Contratos Públicos da Organização Mundial do Comércio): Não\n27 - IDENTIFICAÇÃO E CONTACTOS DO ÓRGÃO DE RECURSOS ADMINISTRATIVOS\nDesignação: Presidente da Câmara\nEndereço: Apartado 25\nCódigo postal: 7481-909\nLocalidade: Avis\nTelefone: +351 242410060\nFax: +351 242410090\nEndereço eletrónico: geral@cm-avis.pt\n28 - IDENTIFICAÇÃO DO(S) AUTOR(ES) DE ANÚNCIO\nNome: Manuel Maria Libério Coelho\nCargo: Presidente da Câmara\n419947601",
    "nipc": "502789824",
    "distrito": "Portalegre",
    "concelho": "Avis",
    "freguesia": "Todas",
    "site": "www.cm-avis.pt",
    "email": "geral@cm-avis.pt",
    "designacao_contrato": "Análises de água para consumo humano",
    "descricao": "Análises de água para consumo humano",
    "preco_base": "18.500,00 EUR",
    "prazo_execucao": "12 MESES",
    "prazo_apresentacao_propostas": "19-01-2026 16:00",
    "fundos_eu": "Não",
    "plataforma_eletronica": "VORTAL",
    "url_procedimento": "https://community.vortal.biz/public/",
    "autor_nome": "Manuel Maria Libério Coelho",
    "autor_cargo": "Presidente da Câmara"
  },
  {
    "numero_procedimento": "N/A",
    "entidade": "AnÃºncio de procedimento  n.Âº 466/2026  -  DiÃ¡rio da RepÃºblica n.Âº 6/2026, SÃ©rie II de 2026-01-09",
    "link": "https://diariodarepublica.pt/dr/detalhe/contrato-publico/466-1003479529"
  },
  {
    "numero_procedimento": "N/A",
    "entidade": "Loulé Concelho Global, EM, Unipessoal, SA",
    "link": "https://diariodarepublica.pt/dr/detalhe/contrato-publico/467-1003479542",
    "detalhes_completos": "1 - IDENTIFICAÇÃO E CONTACTOS DA ENTIDADE ADJUDICANTE\nDesignação da entidade adjudicante: Loulé Concelho Global, EM, Unipessoal, SA\nNIPC: 505493870\nServiço/Órgão/Pessoa de contacto: Conselho de Administração\nEndereço: Rua José Afonso, Lote 61 - R/C\nCódigo postal: 8100-592\nLocalidade: Loulé\nPaís: Portugal\nNUT III: PT150\nDistrito: Faro\nConcelho: Loulé\nFreguesia: Todas\nTelefone: 289401080\nFax: 289401089\nEndereço da Entidade (URL): www.lcglobal.pt\nEndereço Eletrónico: contratacao@lcglobal.pt\neDelivery Gateway (URL): https://www.acingov.pt\nFunção da Organização: Adquirente\nNorma jurídica da Entidade Adjudicante: Organismo de direito público\nÁrea de atividade da Autoridade Adjudicante: Serviços públicos das administrações públicas\n2 - JORNAL OFICIAL DA UNIÃO EUROPEIA\nO procedimento a que este anúncio diz respeito também é publicitado no Jornal Oficial da União Europeia? Não\n3 - AVISO\nModelo de Anúncio: Concurso público urgente\nData de Envio do Anúncio: 09-01-2026 16:29:00\n5 - PROCESSO\nTipo de Procedimento: Concurso público\nPreço base do procedimento: Sim\nValor do preço base do procedimento: 168.881,04 EUR\nProcedimento com lotes? Não\n6 - OBJETO DO CONTRATO\nNúmero de referência interna: 01/26\nDesignação do contrato: Aquisição da prestação de serviço público de transporte urbano de passageiros em autocarro no Município de Loulé\nDescrição: Aquisição da prestação de serviço público de transporte urbano de passageiros em autocarro no Município de Loulé\nTipo de Contrato Principal: Aquisição de Serviços\nTipo de Contrato: Aquisição de Serviços\nClassificação CPV (Vocabulário Comum para os Contratos Públicos)\nObjeto principal\nVocabulário Principal: 60112000\nPreço base s/IVA: 168.881,04 EUR\n7 - INDICAÇÕES ADICIONAIS\nO contrato envolve aquisição conjunta (satisfação de várias entidades)? Não\nO contrato é adjudicado por uma central de compras? Não\n8 - TÉCNICAS\nO concurso destina-se à celebração de um acordo-quadro? Inexistência de acordo-quadro\nÉ utilizado um leilão eletrónico? Não\nÉ adotada uma fase de negociação? Não\nSistema de Aquisição Dinâmico: Inexistência de sistema de aquisição dinâmico\n9 - LOCAL DA EXECUÇÃO DO CONTRATO\nLOCAL DA EXECUÇÃO DO CONTRATO (PROCEDIMENTO)\nPaís: Portugal\nNUT III: PT150\nLocalidade: Loulé\nDistrito: Faro\nConcelho: Loulé\nFreguesia: Todas\n10 - PRAZO DE EXECUÇÃO DO CONTRATO\nPrazo de execução do contrato: 60 DIAS\nPrevisão de renovações: Sim\nIndicar número máximo de renovações: 2\nPrazo de renovações diferente do prazo inicial: Sim\nIndicar o prazo de execução da renovação do contrato: 30 DIAS\n11 - FUNDOS EU\nTêm fundos EU? Não\n12 - DOCUMENTOS DE HABILITAÇÃO\nHabilitação para o exercício da atividade profissional: Não\n13 - CONDIÇÕES DE APRESENTAÇÃO\nPlataforma eletrónica utilizada pela entidade adjudicante: ACIN\nURL para Apresentação: https://www.acingov.pt\nAdmissibilidade da apresentação de propostas variantes: Não autorizado\nPrazo para apresentação das propostas: 14-01-2026 23:59\nPrazo durante o qual os concorrentes são obrigados a manter as respetivas propostas: 10 dias a contar do termo do prazo para a apresentação das propostas\nIndicação de Subcontratação na Proposta: Inexistência de indicação de subcontratação\n14 - PRESTAÇÃO DE CAUÇÃO\nPrestação de caução: Não\n15 - FORNECIMENTO DAS PEÇAS DO CONCURSO, APRESENTAÇÃO DE PEDIDOS DE PARTICIPAÇÃO E APRESENTAÇÃO DAS PROPOSTAS\nLink para acesso às peças do concurso (URL): https://www.acingov.pt/acingovprod/2/zonaPublica/zona_publica_c/donwloadProcedurePiece/MTA0MTUxMA==\n20 - OUTROS REQUISITOS\nInformação sobre contratos reservados. Aplica-se a contratos reservados (54º-A)? Não\n21 - CRITÉRIO DE ADJUDICAÇÃO\nMultifator: Não\nMonofator:\nNome: Preço\n24 - CONDIÇÕES DO CONTRATO\nFaturação Eletrónica: Necessário\nObrigação de Subcontratação:\nCódigo da Obrigação de Subcontratação: Não é aplicável nenhuma obrigação de subcontratação.\n25 - COMPRA PÚBLICA ESTRATÉGICA\nCompra Pública Estratégica: Inexistência de contratação pública estratégica\n26 - INFORMAÇÕES ADICIONAIS\nContrato adequado para PME: Sim\nCobertura ACP (Acordo dos Contratos Públicos da Organização Mundial do Comércio): Não\n27 - IDENTIFICAÇÃO E CONTACTOS DO ÓRGÃO DE RECURSOS ADMINISTRATIVOS\nDesignação: Conselho de Administração\nEndereço: Rua José Afonso, Lote 61 - R/C\nCódigo postal: 8100-592\nLocalidade: Loulé\nTelefone: 289401080\nFax: 289401089\nEndereço eletrónico: contratacao@lcglobal.pt\n28 - IDENTIFICAÇÃO DO(S) AUTOR(ES) DE ANÚNCIO\nNome: Rui Augusto Ventura Guerreiro\nCargo: Presidente do Conselho de Administração\n419947610",
    "nipc": "505493870",
    "distrito": "Faro",
    "concelho": "Loulé",
    "freguesia": "Todas",
    "site": "www.lcglobal.pt",
    "email": "contratacao@lcglobal.pt",
    "designacao_contrato": "Aquisição da prestação de serviço público de transporte urbano de passageiros em autocarro no Município de Loulé",
    "descricao": "Aquisição da prestação de serviço público de transporte urbano de passageiros em autocarro no Município de Loulé",
    "preco_base": "168.881,04 EUR",
    "prazo_execucao": "60 DIAS",
    "prazo_apresentacao_propostas": "14-01-2026 23:59",
    "fundos_eu": "Não",
    "plataforma_eletronica": "ACIN",
    "url_procedimento": "https://www.acingov.pt",
    "autor_nome": "Rui Augusto Ventura Guerreiro",
    "autor_cargo": "Presidente do Conselho de Administração"
  },
  {
    "numero_procedimento": "N/A",
    "entidade": "AnÃºncio de procedimento  n.Âº 434/2026  -  DiÃ¡rio da RepÃºblica n.Âº 6/2026, SÃ©rie II de 2026-01-09",
    "link": "https://diariodarepublica.pt/dr/detalhe/contrato-publico/434-1003750287"
  },
  {
    "numero_procedimento": "N/A",
    "entidade": "Município de Pombal",
    "link": "https://diariodarepublica.pt/dr/detalhe/contrato-publico/435-1004293681",
    "detalhes_completos": "1 - IDENTIFICAÇÃO E CONTACTOS DA ENTIDADE ADJUDICANTE\nDesignação da entidade adjudicante: Município de Pombal\nNIPC: 506334562\nServiço/Órgão/Pessoa de contacto: Secção de Obras Públicas\nEndereço: Largo do Cardal\nCódigo postal: 3100-440\nLocalidade: Pombal\nPaís: Portugal\nNUT III: PT16F\nDistrito: Leiria\nConcelho: Pombal\nFreguesia: Freguesia de Pombal - Pombal\nTelefone: 236210500\nFax: 236210599\nEndereço da Entidade (URL): https://www.cm-pombal.pt\nEndereço Eletrónico: geral@cm-pombal.pt\neDelivery Gateway (URL): https://www.acingov.pt\nFunção da Organização: Adquirente\nNorma jurídica da Entidade Adjudicante: Organismo de direito público\nÁrea de atividade da Autoridade Adjudicante: Serviços públicos das administrações públicas\n2 - JORNAL OFICIAL DA UNIÃO EUROPEIA\nO procedimento a que este anúncio diz respeito também é publicitado no Jornal Oficial da União Europeia? Não\n3 - AVISO\nModelo de Anúncio: Concurso público\nData de Envio do Anúncio: 09-01-2026\n5 - PROCESSO\nTipo de Procedimento: Concurso público\nPreço base do procedimento: Sim\nValor do preço base do procedimento: 149.600,00 EUR\nProcedimento com lotes? Não\n6 - OBJETO DO CONTRATO\nNúmero de referência interna: 64/2025\nDesignação do contrato: REFORMULAÇÃO DOS CANIS DO POSTO DA GNR (REQUALIFICAÇÃO DOS CANIS DA BRIGADA CINOTÉCNICA DA GNR / CRIAÇÃO DE INSTALAÇÕES PARA OS OPERACIONAIS E SALA PARA O SEPNA) - PROC. N.º 64/2025\nDescrição: REFORMULAÇÃO DOS CANIS DO POSTO DA GNR (REQUALIFICAÇÃO DOS CANIS DA BRIGADA CINOTÉCNICA DA GNR / CRIAÇÃO DE INSTALAÇÕES PARA OS OPERACIONAIS E SALA PARA O SEPNA) - PROC. N.º 64/2025\nTipo de Contrato Principal: Empreitada de Obras Públicas\nTipo de Contrato: Empreitada de Obras Públicas\nClassificação CPV (Vocabulário Comum para os Contratos Públicos)\nObjeto principal\nVocabulário Principal: 45216110\nPreço base s/IVA: 149.600,00 EUR\n7 - INDICAÇÕES ADICIONAIS\nO contrato envolve aquisição conjunta (satisfação de várias entidades)? Não\nO contrato é adjudicado por uma central de compras? Não\n8 - TÉCNICAS\nO concurso destina-se à celebração de um acordo-quadro? Inexistência de acordo-quadro\nÉ utilizado um leilão eletrónico? Não\nÉ adotada uma fase de negociação? Não\nSistema de Aquisição Dinâmico: Inexistência de sistema de aquisição dinâmico\n9 - LOCAL DA EXECUÇÃO DO CONTRATO\nLOCAL DA EXECUÇÃO DO CONTRATO (PROCEDIMENTO)\nPaís: Portugal\nNUT III: PT16F\nLocalidade: Pombal\nDistrito: Leiria\nConcelho: Pombal\nFreguesia: Freguesia de Pombal - Pombal\n10 - PRAZO DE EXECUÇÃO DO CONTRATO\nPrazo de execução do contrato: 240 DIAS\nPrevisão de renovações: Não\n11 - FUNDOS EU\nTêm fundos EU? Não\n12 - DOCUMENTOS DE HABILITAÇÃO\nHabilitação para o exercício da atividade profissional: Sim\nTipo: Alvará\nDescrição: - A 1.ª subcategoria, da 1.ª categoria, em classe que cubra o valor global da proposta;\n- As 4.ª e 8.ª subcategorias, da 1.ª categoria, na classe correspondente à parte dos trabalhos a que respeitem;\n13 - CONDIÇÕES DE APRESENTAÇÃO\nPlataforma eletrónica utilizada pela entidade adjudicante: ACIN\nURL para Apresentação: https://www.acingov.pt\nAdmissibilidade da apresentação de propostas variantes: Não autorizado\nPrazo para apresentação das propostas: 08-02-2026 23:59\nPrazo durante o qual os concorrentes são obrigados a manter as respetivas propostas: 66 dias a contar do termo do prazo para a apresentação das propostas\nIndicação de Subcontratação na Proposta: Inexistência de indicação de subcontratação\n14 - PRESTAÇÃO DE CAUÇÃO\nPrestação de caução: Não\n15 - FORNECIMENTO DAS PEÇAS DO CONCURSO, APRESENTAÇÃO DE PEDIDOS DE PARTICIPAÇÃO E APRESENTAÇÃO DAS PROPOSTAS\nLink para acesso às peças do concurso (URL): https://www.acingov.pt/acingovprod/2/zonaPublica/zona_publica_c/donwloadProcedurePiece/MTAwOTM3Mw==\n20 - OUTROS REQUISITOS\nInformação sobre contratos reservados. Aplica-se a contratos reservados (54º-A)? Não\n21 - CRITÉRIO DE ADJUDICAÇÃO\nMultifator: Não\nMonofator:\nNome: Preço\n24 - CONDIÇÕES DO CONTRATO\nFaturação Eletrónica: Permitido\nObrigação de Subcontratação:\nCódigo da Obrigação de Subcontratação: Não é aplicável nenhuma obrigação de subcontratação.\n25 - COMPRA PÚBLICA ESTRATÉGICA\nCompra Pública Estratégica: Inexistência de contratação pública estratégica\n26 - INFORMAÇÕES ADICIONAIS\nContrato adequado para PME: Não\nCobertura ACP (Acordo dos Contratos Públicos da Organização Mundial do Comércio): Não\n27 - IDENTIFICAÇÃO E CONTACTOS DO ÓRGÃO DE RECURSOS ADMINISTRATIVOS\nDesignação: Câmara Municipal de Pombal\nEndereço: Largo do Cardal\nCódigo postal: 3100-440\nLocalidade: Pombal\nTelefone: 236210500\nFax: \nEndereço eletrónico: geral@cm-pombal.pt\n28 - IDENTIFICAÇÃO DO(S) AUTOR(ES) DE ANÚNCIO\nNome: Pedro Alexandre Antunes Faustino Pimpão dos Santos - Lic.\nCargo: Presidente da Câmara\n419947405",
    "nipc": "506334562",
    "distrito": "Leiria",
    "concelho": "Pombal",
    "freguesia": "Freguesia de Pombal - Pombal",
    "site": "https://www.cm-pombal.pt",
    "email": "geral@cm-pombal.pt",
    "designacao_contrato": "REFORMULAÇÃO DOS CANIS DO POSTO DA GNR (REQUALIFICAÇÃO DOS CANIS DA BRIGADA CINOTÉCNICA DA GNR / CRIAÇÃO DE INSTALAÇÕES PARA OS OPERACIONAIS E SALA PARA O SEPNA) - PROC. N.º 64/2025",
    "descricao": "REFORMULAÇÃO DOS CANIS DO POSTO DA GNR (REQUALIFICAÇÃO DOS CANIS DA BRIGADA CINOTÉCNICA DA GNR / CRIAÇÃO DE INSTALAÇÕES PARA OS OPERACIONAIS E SALA PARA O SEPNA) - PROC. N.º 64/2025",
    "preco_base": "149.600,00 EUR",
    "prazo_execucao": "240 DIAS",
    "prazo_apresentacao_propostas": "08-02-2026 23:59",
    "fundos_eu": "Não",
    "plataforma_eletronica": "ACIN",
    "url_procedimento": "https://www.acingov.pt",
    "autor_nome": "Pedro Alexandre Antunes Faustino Pimpão dos Santos - Lic.",
    "autor_cargo": "Presidente da Câmara"
  },
  {
    "numero_procedimento": "N/A",
    "entidade": "Município da Amadora",
    "link": "https://diariodarepublica.pt/dr/detalhe/contrato-publico/437-1004573010",
    "detalhes_completos": "1 - IDENTIFICAÇÃO E CONTACTOS DA ENTIDADE ADJUDICANTE\nDesignação da entidade adjudicante: Município da Amadora\nNIPC: 505456010\nServiço/Órgão/Pessoa de contacto: Departamento de Obras Municipais\nEndereço: Av. do Movimento das Forças Armadas\nCódigo postal: 2700-595\nLocalidade: Lisboa\nPaís: Portugal\nNUT III: PT170\nDistrito: Lisboa\nConcelho: Amadora\nFreguesia: Todas\nTelefone: 214369000\nFax: 214369000\nEndereço da Entidade (URL): https://www.cm-amadora.pt/pt/\nEndereço Eletrónico: geral@cm-amadora.pt\neDelivery Gateway (URL): https://community.vortal.biz/public/\nFunção da Organização: Adquirente\nNorma jurídica da Entidade Adjudicante: Autoridade local\nÁrea de atividade da Autoridade Adjudicante: Serviços públicos das administrações públicas\n2 - JORNAL OFICIAL DA UNIÃO EUROPEIA\nO procedimento a que este anúncio diz respeito também é publicitado no Jornal Oficial da União Europeia? Não\n3 - AVISO\nModelo de Anúncio: Concurso público\nData de Envio do Anúncio: 09-01-2026\n5 - PROCESSO\nTipo de Procedimento: Concurso público\nPreço base do procedimento: Sim\nValor do preço base do procedimento: 550.889,54 EUR\nProcedimento com lotes? Não\n6 - OBJETO DO CONTRATO\nNúmero de referência interna: DOM 51/2025/95884\nDesignação do contrato: Eixos Principais - Pavimentação - Execução de Obra\nDescrição: A obra tem como objetivo a reparação e requalificação dos arruamentos e respetivas zonas envolventes. \nTipo de Contrato Principal: Empreitada de Obras Públicas\nTipo de Contrato: Empreitada de Obras Públicas\nClassificação CPV (Vocabulário Comum para os Contratos Públicos)\nObjeto principal\nVocabulário Principal: 45233200\nPreço base s/IVA: 550.889,54 EUR\n7 - INDICAÇÕES ADICIONAIS\nO contrato envolve aquisição conjunta (satisfação de várias entidades)? Não\nO contrato é adjudicado por uma central de compras? Não\n8 - TÉCNICAS\nO concurso destina-se à celebração de um acordo-quadro? Inexistência de acordo-quadro\nÉ utilizado um leilão eletrónico? Não\nÉ adotada uma fase de negociação? Não\nSistema de Aquisição Dinâmico: Inexistência de sistema de aquisição dinâmico\n9 - LOCAL DA EXECUÇÃO DO CONTRATO\nLOCAL DA EXECUÇÃO DO CONTRATO (PROCEDIMENTO)\nPaís: Portugal\nNUT III: PT170\nLocalidade: Lisboa\nDistrito: Lisboa\nConcelho: Amadora\nFreguesia: Todas\n10 - PRAZO DE EXECUÇÃO DO CONTRATO\nPrazo de execução do contrato: 63 DIAS\nPrevisão de renovações: Não\n11 - FUNDOS EU\nTêm fundos EU? Não\n12 - DOCUMENTOS DE HABILITAÇÃO\nHabilitação para o exercício da atividade profissional: Sim\nTipo: Alvará\nDescrição: Ponto 17 do Programa de Concurso.\n13 - CONDIÇÕES DE APRESENTAÇÃO\nPlataforma eletrónica utilizada pela entidade adjudicante: VORTAL\nURL para Apresentação: https://community.vortal.biz/public/\nAdmissibilidade da apresentação de propostas variantes: Não autorizado\nPrazo para apresentação das propostas: 08-02-2026 23:59\nPrazo durante o qual os concorrentes são obrigados a manter as respetivas propostas: 66 dias a contar do termo do prazo para a apresentação das propostas\nIndicação de Subcontratação na Proposta: Inexistência de indicação de subcontratação\n14 - PRESTAÇÃO DE CAUÇÃO\nPrestação de caução: Sim\nPercentagem: 5%\nDescrição da Garantia Exigida: Ponto 1.11 do Caderno de Encargos\n15 - FORNECIMENTO DAS PEÇAS DO CONCURSO, APRESENTAÇÃO DE PEDIDOS DE PARTICIPAÇÃO E APRESENTAÇÃO DAS PROPOSTAS\nLink para acesso às peças do concurso (URL): https://community.vortal.biz/Public/public-tender-documents/OFhzMW8vcXpSNGRkcTZUNEVwb3ZCNE9GK091Tm9zcElGZjdDOFBzZi9GVFNuR0l5ejY1OFM1MXlBUlJvUjNtd3FMMW83aS8yYUZBVUFSMTd0TEY5alE9PVVFalBm\n20 - OUTROS REQUISITOS\nInformação sobre contratos reservados. Aplica-se a contratos reservados (54º-A)? Não\n21 - CRITÉRIO DE ADJUDICAÇÃO\nMultifator: Sim\nFator: \nNome: Outros\nOutro Nome: Preço\nPonderação: 35%\nSubfatores: Não\nFator: \nNome: Qualidade\nPonderação: 65%\nSubfatores: Sim\nSubfatores: \nNome: Qualidade e Adequabilidade da Memória Descritiva\nPonderação : 70%; \nNome: Plano de Trabalhos\nPonderação : 30%; \n24 - CONDIÇÕES DO CONTRATO\nFaturação Eletrónica: Permitido\nObrigação de Subcontratação:\nCódigo da Obrigação de Subcontratação: Não é aplicável nenhuma obrigação de subcontratação.\n25 - COMPRA PÚBLICA ESTRATÉGICA\nCompra Pública Estratégica: Inexistência de contratação pública estratégica\n26 - INFORMAÇÕES ADICIONAIS\nContrato adequado para PME: Sim\nCobertura ACP (Acordo dos Contratos Públicos da Organização Mundial do Comércio): Não\n27 - IDENTIFICAÇÃO E CONTACTOS DO ÓRGÃO DE RECURSOS ADMINISTRATIVOS\nDesignação: Município da Amadora\nEndereço: Avenida Movimento das Forças Armadas, n.º 1\nCódigo postal: 2700-595\nLocalidade: Amadora\nTelefone: +351 214369000\nFax: +351 000000000\nEndereço eletrónico: geral@cm-amadora.pt\nPrazo de interposição do recurso: 5 dias\n28 - IDENTIFICAÇÃO DO(S) AUTOR(ES) DE ANÚNCIO\nNome: Vítor Ferreira\nCargo: Presidente\n419947514",
    "nipc": "505456010",
    "distrito": "Lisboa",
    "concelho": "Amadora",
    "freguesia": "Todas",
    "site": "https://www.cm-amadora.pt/pt/",
    "email": "geral@cm-amadora.pt",
    "designacao_contrato": "Eixos Principais - Pavimentação - Execução de Obra",
    "descricao": "A obra tem como objetivo a reparação e requalificação dos arruamentos e respetivas zonas envolventes.",
    "preco_base": "550.889,54 EUR",
    "prazo_execucao": "63 DIAS",
    "prazo_apresentacao_propostas": "08-02-2026 23:59",
    "fundos_eu": "Não",
    "plataforma_eletronica": "VORTAL",
    "url_procedimento": "https://community.vortal.biz/public/",
    "autor_nome": "Vítor Ferreira",
    "autor_cargo": "Presidente"
  },
  {
    "numero_procedimento": "N/A",
    "entidade": "Município de Barrancos",
    "link": "https://diariodarepublica.pt/dr/detalhe/contrato-publico/439-1004861201",
    "detalhes_completos": "1 - IDENTIFICAÇÃO E CONTACTOS DA ENTIDADE ADJUDICANTE\nDesignação da entidade adjudicante: Município de Barrancos\nNIPC: 501081216\nServiço/Órgão/Pessoa de contacto: Ana Luísa Delgado Gabinete Jurídico\nEndereço: Praça do Município, n.º 2, r/c\nCódigo postal: 7230-030\nLocalidade: Barrancos\nPaís: Portugal\nNUT III: Baixo Alentejo\nDistrito: Beja\nConcelho: Barrancos\nFreguesia: Freguesia de Barrancos\nTelefone: 285950630\nEndereço da Entidade (URL): https://www.cm-barrancos.pt\nEndereço Eletrónico: geral@cm-barrancos.pt\nFunção da Organização: \nNorma jurídica da Entidade Adjudicante: Autoridade local\nÁrea de atividade da Entidade Adjudicante: Atividades relacionadas com a água\n2 - AVISO\nData de Envio do Anúncio: 09-01-2026\n3 - PROCESSO\nModelo de Anúncio: Hasta pública de alienação de bens móveis\nPreço de licitação base do procedimento: Sim\nValor da licitação base do procedimento: 7.500,00 EUR\nContratação por Lotes? Sim\n4 - OBJETO DO CONTRATO\nNúmero de referência interna: 1/2026\nDesignação do procedimento de alienação de bens móveis: Procedimento de Hasta Pública de dois veículos agrícolas em fim de vida \nTipo de bens: Bens móveis \nLegislação aplicável: Artigo 266.º C do Código dos Contratos Públicos DL n.º 18/2008, de 29 de Janeiro, na sua versão atual\nAvaliação do bem: 7.500,00 EUR\nClassificação CPV (Vocabulário Comum para os Contratos Públicos)\nObjeto: Objeto principal\nVocabulário Principal: Tractores usados\nLotes: \nNº: LOT-0001\nDescrição do Lote: Trator Massey Ferguson  –MF-275, ano 1984 e cilindrada 3860\nPreço base s/IVA: 3.000,00 EUR\nClassificação CPV (Vocabulário Comum para os Contratos Públicos)\nObjeto: Objeto principal\nVocabulário Principal: Tractores usados\nNº: LOT-0002\nDescrição do Lote: Trator Lamborghini - Modelo 880 Plus VDP, Ano 1997, Cilindrada 4000\nPreço base s/IVA: 4.500,00 EUR\nClassificação CPV (Vocabulário Comum para os Contratos Públicos)\nObjeto: Objeto principal\nVocabulário Principal: Tractores usados\n5 - DESTINATÁRIOS\nDestinatários: Todos os interessados, nos termos da Cláusula 3.ª do Programa do Procedimento de Hasta Pública.\n6 - INDICAÇÕES ADICIONAIS\nReferência do Portal dos Contratos Públicos:N/A\nA entidade adjudicante atua como compradora no procedimento? Não\nÉ utilizado um leilão eletrónico?  Não\nÉ adotada uma fase de negociação?  Não\n7 - CONSULTA DAS PEÇAS E OBTENÇÃO DE CÓPIAS\nLink para acesso às peças do concurso (URL):https://www.cm-barrancos.pt\n8 -  PEDIDOS DE ESCLARECIMENTO SOBRE AS PEÇAS DO PROCEDIMENTO\nPedidos de esclarecimento sobre as peças do procedimento: Nos termos no previsto na Cláusula do 9.ª do Procedimento de Hasta Pública.\n9 -  DOCUMENTOS DE HABILITAÇÃO\nDocumentos de habilitação: Conforme previsto na Cláusula 10.ª do Programa do Procedimento da Hasta Pública: documentos comprovativos de que o concorrente não se encontra abrangido pelos condicionalismos descritos no artigo 55.º do Código dos Contratos Públicos.\n10 -  CONDIÇÕES DE PARTICIPAÇÃO\nCondições de participação: Poderão ser concorrentes quaisquer entidades, pessoas singulares ou coletivas, interessadas e que não se encontrem abrangidas pelos condicionalismos descritos no artigo 55.º do Código dos Contratos Públicos.\n11 - DATA, LOCAL E REGRAS ATO PÚBLICO\nData, Local e Regras do Ato Publico: Até às 16H00 do 10.º dia a contar da data de envio do presente anúncio\n12- CONDIÇÕES DE APRESENTAÇÃO\nModo de apresentação das propostas: Sitio da Internet\nLocal de apresentação das propostas:  https://cm-barrancos.pt/\nPrazo para apresentação das propostas: 23-01-2026\nPrazo durante o qual os concorrentes são obrigados a manter as respetivas propostas: 3 dias a contar do termo do prazo para a apresentação das propostas\n13- CRITÉRIO DE SELEÇÃO\nApenas o valor licitado? Sim\nFator de avaliação: \nPonderação: 0\n14 - PRESTAÇÃO DE CAUÇÃO\nPrestação de caução: Não\n15 - IDENTIFICAÇÃO DO(S) AUTOR(ES) DE ANÚNCIO\nNome: Emílio Domingues\nCargo: Presidente da Câmara Municipal de Barrancos\n419947493",
    "nipc": "501081216",
    "distrito": "Beja",
    "concelho": "Barrancos",
    "freguesia": "Freguesia de Barrancos",
    "site": "https://www.cm-barrancos.pt",
    "email": "geral@cm-barrancos.pt",
    "designacao_contrato": null,
    "descricao": null,
    "preco_base": "3.000,00 EUR",
    "prazo_execucao": null,
    "prazo_apresentacao_propostas": "23-01-2026",
    "fundos_eu": null,
    "plataforma_eletronica": null,
    "url_procedimento": null,
    "autor_nome": null,
    "autor_cargo": "Presidente da Câmara Municipal de Barrancos"
  },
  {
    "numero_procedimento": "N/A",
    "entidade": "AnÃºncio de procedimento  n.Âº 441/2026  -  DiÃ¡rio da RepÃºblica n.Âº 6/2026, SÃ©rie II de 2026-01-09",
    "link": "https://diariodarepublica.pt/dr/detalhe/contrato-publico/441-1004861226"
  },
  {
    "numero_procedimento": "N/A",
    "entidade": "Unidade Local de Saúde de Santa Maria, EPE",
    "link": "https://diariodarepublica.pt/dr/detalhe/contrato-publico/445-1005484241",
    "detalhes_completos": "Alteração do Anúncio de procedimento n.º 137/2026, de 2026-01-05, com o ID 419947118\n1 - IDENTIFICAÇÃO E CONTACTOS DA ENTIDADE ADJUDICANTE\nDesignação da entidade adjudicante: Unidade Local de Saúde de Santa Maria, EPE\nNIPC: 508481287\nEndereço: Avenida Prof. Egas Moniz\nCódigo postal: 1649-035\nLocalidade: Lisboa\nPaís: Portugal\nNUT III: PT170\nDistrito: Lisboa\nConcelho: Lisboa\nFreguesia: Freguesia de Alvalade - Lisboa\nTelefone: 217805330\nFax: 217805605\nEndereço da Entidade (URL): www.ulssm.min-saude.pt\nEndereço Eletrónico: compras@ulssm.min-saude.pt\neDelivery Gateway (URL): https://community.vortal.biz/public/\nFunção da Organização: Adquirente\nNorma jurídica da Entidade Adjudicante: Empresa pública\nÁrea de atividade da Autoridade Adjudicante: Saúde\n2 - JORNAL OFICIAL DA UNIÃO EUROPEIA\nO procedimento a que este anúncio diz respeito também é publicitado no Jornal Oficial da União Europeia? Não\n3 - AVISO\nModelo de Anúncio: Concurso público\nData de Envio do Anúncio: 09-01-2026\n5 - PROCESSO\nTipo de Procedimento: Concurso público\nPreço base do procedimento: Sim\nValor do preço base do procedimento: 38.500,00 EUR\nProcedimento com lotes? Não\n6 - OBJETO DO CONTRATO\nNúmero de referência interna: 262A000017\nDesignação do contrato: 262A000017 - Aquisição de Rolo Absorvente Pré-Cortado, ano 2026 e 2027\nDescrição: Aquisição de Rolo Absorvente Pré-Cortado, ano 2026 e 2027\nTipo de Contrato Principal: Aquisição de Bens Móveis\nTipo de Contrato: Aquisição de Bens Móveis\nClassificação CPV (Vocabulário Comum para os Contratos Públicos)\nObjeto principal\nVocabulário Principal: 33140000\nPreço base s/IVA: 38.500,00 EUR\n7 - INDICAÇÕES ADICIONAIS\nO contrato envolve aquisição conjunta (satisfação de várias entidades)? Não\nO contrato é adjudicado por uma central de compras? Não\n8 - TÉCNICAS\nO concurso destina-se à celebração de um acordo-quadro? Inexistência de acordo-quadro\nÉ utilizado um leilão eletrónico? Não\nÉ adotada uma fase de negociação? Não\nSistema de Aquisição Dinâmico: Inexistência de sistema de aquisição dinâmico\n9 - LOCAL DA EXECUÇÃO DO CONTRATO\nLOCAL DA EXECUÇÃO DO CONTRATO (PROCEDIMENTO)\nPaís: Portugal\nNUT III: PT170\nLocalidade: Lisboa\nDistrito: Lisboa\nConcelho: Lisboa\nFreguesia: Freguesia de Alvalade - Lisboa\n10 - PRAZO DE EXECUÇÃO DO CONTRATO\nPrazo de execução do contrato: 24 MESES\nPrevisão de renovações: Não\n11 - FUNDOS EU\nTêm fundos EU? Não\n12 - DOCUMENTOS DE HABILITAÇÃO\nHabilitação para o exercício da atividade profissional: Não\n13 - CONDIÇÕES DE APRESENTAÇÃO\nPlataforma eletrónica utilizada pela entidade adjudicante: VORTAL\nURL para Apresentação: https://community.vortal.biz/public/\nAdmissibilidade da apresentação de propostas variantes: Não autorizado\nPrazo para apresentação das propostas: 18-01-2026 17:00\nPrazo durante o qual os concorrentes são obrigados a manter as respetivas propostas: 180 dias a contar do termo do prazo para a apresentação das propostas\nApresentação de Catálogo Eletrónico: Permitido\nIndicação de Subcontratação na Proposta: Inexistência de indicação de subcontratação\n14 - PRESTAÇÃO DE CAUÇÃO\nPrestação de caução: Não\n15 - FORNECIMENTO DAS PEÇAS DO CONCURSO, APRESENTAÇÃO DE PEDIDOS DE PARTICIPAÇÃO E APRESENTAÇÃO DAS PROPOSTAS\nLink para acesso às peças do concurso (URL): https://community.vortal.biz/Public/public-tender-documents/R2owT3ZadWNBYVQ3SVlGN1VXZThqV1FoOU5xTXFGQ0Nlc2Vvdm05eTFmMTQ3ajZjMmM5cXJRa3ZoTXQ5ZkQ0eS80UThTYzQrMzBCeE1XK1FBY2RtclE9PSFWSENF\n20 - OUTROS REQUISITOS\nInformação sobre contratos reservados. Aplica-se a contratos reservados (54º-A)? Não\n21 - CRITÉRIO DE ADJUDICAÇÃO\nMultifator: Não\nMonofator:\nNome: Preço\n24 - CONDIÇÕES DO CONTRATO\nFaturação Eletrónica: Permitido\nObrigação de Subcontratação:\nCódigo da Obrigação de Subcontratação: Não é aplicável nenhuma obrigação de subcontratação.\n25 - COMPRA PÚBLICA ESTRATÉGICA\nCompra Pública Estratégica: Inexistência de contratação pública estratégica\n26 - INFORMAÇÕES ADICIONAIS\nContrato adequado para PME: Sim\nCobertura ACP (Acordo dos Contratos Públicos da Organização Mundial do Comércio): Não\n27 - IDENTIFICAÇÃO E CONTACTOS DO ÓRGÃO DE RECURSOS ADMINISTRATIVOS\nDesignação: Conselho de Administração\nEndereço: Av Professor Egas Moniz\nCódigo postal: 1649-035\nLocalidade: Lisboa\nTelefone: +351 217805330\nFax: +351 217805605\nEndereço eletrónico: secretariado.ca@ulssm.min-saude.pt\n28 - IDENTIFICAÇÃO DO(S) AUTOR(ES) DE ANÚNCIO\nNome: Mariana Figueira\nCargo: Assistente Técnica\n29 - ALTERAÇÃO\nMotivo da Alteração: Correção pelo adquirente\nIdentificador da Versão do Anúncio a Alterar: 81ebc648-9c83-4e35-bb09-fa3d342c6342-01\nIdentificador das Secções Alteradas do Anúncio Anterior: Condições de Apresentação\nDescrição das Alterações: Prorrogação de prazo de apresentação de propostas, por motivo de alteração das peças de procedimento.\nAlteração dos Documentos do Concurso: Sim\nData de alteração dos documentos do concurso: 09-01-2026\n419947529",
    "nipc": "508481287",
    "distrito": "Lisboa",
    "concelho": "Lisboa",
    "freguesia": "Freguesia de Alvalade - Lisboa",
    "site": "www.ulssm.min-saude.pt",
    "email": "compras@ulssm.min-saude.pt",
    "designacao_contrato": "262A000017 - Aquisição de Rolo Absorvente Pré-Cortado, ano 2026 e 2027",
    "descricao": "Aquisição de Rolo Absorvente Pré-Cortado, ano 2026 e 2027",
    "preco_base": "38.500,00 EUR",
    "prazo_execucao": "24 MESES",
    "prazo_apresentacao_propostas": "18-01-2026 17:00",
    "fundos_eu": "Não",
    "plataforma_eletronica": "VORTAL",
    "url_procedimento": "https://community.vortal.biz/public/",
    "autor_nome": "Mariana Figueira",
    "autor_cargo": "Assistente Técnica"
  },
  {
    "numero_procedimento": "N/A",
    "entidade": "Secretaria Regional de Equipamentos e Infraestruturas",
    "link": "https://diariodarepublica.pt/dr/detalhe/contrato-publico/446-1005484242",
    "detalhes_completos": "1 - IDENTIFICAÇÃO E CONTACTOS DA ENTIDADE ADJUDICANTE\nDesignação da entidade adjudicante: Secretaria Regional de Equipamentos e Infraestruturas\nNIPC: 671001329\nServiço/Órgão/Pessoa de contacto: Conforme peças do procedimento\nEndereço: Rua Dr. Pestana Júnior, nº 6\nCódigo postal: 9064-506\nLocalidade: Funchal\nPaís: Portugal\nNUT III: PT300\nDistrito: Região Autónoma da Madeira\nConcelho: Funchal\nFreguesia: Todas\nTelefone: 291212100\nFax: 291232102\nEndereço da Entidade (URL): https://www.madeira.gov.pt/srei\nEndereço Eletrónico: gabinete.srei@madeira.gov.pt\neDelivery Gateway (URL): https://www.acingov.pt\nFunção da Organização: Adquirente\nNorma jurídica da Entidade Adjudicante: Organismo de direito público\nÁrea de atividade da Autoridade Adjudicante: Serviços públicos das administrações públicas\n2 - JORNAL OFICIAL DA UNIÃO EUROPEIA\nO procedimento a que este anúncio diz respeito também é publicitado no Jornal Oficial da União Europeia? Não\n3 - AVISO\nModelo de Anúncio: Concurso público\nData de Envio do Anúncio: 09-01-2026\n5 - PROCESSO\nTipo de Procedimento: Concurso público\nPreço base do procedimento: Sim\nValor do preço base do procedimento: 105.000,00 EUR\nProcedimento com lotes? Não\n6 - OBJETO DO CONTRATO\nNúmero de referência interna: 1CPL26_ES\nDesignação do contrato: Centro de Saúde de Santo António - Implementação de Medidas de Melhoria Energética\nDescrição: Centro de Saúde de Santo António - Implementação de Medidas de Melhoria Energética\nTipo de Contrato Principal: Empreitada de Obras Públicas\nTipo de Contrato: Empreitada de Obras Públicas\nClassificação CPV (Vocabulário Comum para os Contratos Públicos)\nObjeto principal\nVocabulário Principal: 45310000\nPreço base s/IVA: 105.000,00 EUR\n7 - INDICAÇÕES ADICIONAIS\nO contrato envolve aquisição conjunta (satisfação de várias entidades)? Não\nO contrato é adjudicado por uma central de compras? Não\n8 - TÉCNICAS\nO concurso destina-se à celebração de um acordo-quadro? Inexistência de acordo-quadro\nÉ utilizado um leilão eletrónico? Não\nÉ adotada uma fase de negociação? Não\nSistema de Aquisição Dinâmico: Inexistência de sistema de aquisição dinâmico\n9 - LOCAL DA EXECUÇÃO DO CONTRATO\nLOCAL DA EXECUÇÃO DO CONTRATO (PROCEDIMENTO)\nPaís: Portugal\nNUT III: PT300\nLocalidade: Freguesia de Santo António - Funchal\nDistrito: Região Autónoma da Madeira\nConcelho: Funchal\nFreguesia: Freguesia de Santo António - Funchal\n10 - PRAZO DE EXECUÇÃO DO CONTRATO\nPrazo de execução do contrato: 90 DIAS\nPrevisão de renovações: Não\n11 - FUNDOS EU\nTêm fundos EU? Sim\n12 - DOCUMENTOS DE HABILITAÇÃO\nHabilitação para o exercício da atividade profissional: Sim\nTipo: Alvará\nDescrição: O adjudicatário deverá ser titular do alvará de empreiteiro de Obras Públicas emitido pelo IMPIC, I.P., contendo as seguintes habilitações: a 9.ª subcategoria - Instalações sem qualificação específica da 9.ª categoria - Edifícios e património construídos, na classe que cubra o valor global da proposta ou, se for o caso, declaração emitida pelo IMPIC, I.P., nos termos previstos no número 4 do artigo 3.º da Portaria número 372/2017, de 14 de dezembro.\n13 - CONDIÇÕES DE APRESENTAÇÃO\nPlataforma eletrónica utilizada pela entidade adjudicante: ACIN\nURL para Apresentação: https://www.acingov.pt\nAdmissibilidade da apresentação de propostas variantes: Não autorizado\nPrazo para apresentação das propostas: 27-01-2026 17:00\nPrazo durante o qual os concorrentes são obrigados a manter as respetivas propostas: 90 dias a contar do termo do prazo para a apresentação das propostas\nIndicação de Subcontratação na Proposta: A parte do contrato que o proponente tenciona subcontratar\n14 - PRESTAÇÃO DE CAUÇÃO\nPrestação de caução: Não\n15 - FORNECIMENTO DAS PEÇAS DO CONCURSO, APRESENTAÇÃO DE PEDIDOS DE PARTICIPAÇÃO E APRESENTAÇÃO DAS PROPOSTAS\nLink para acesso às peças do concurso (URL): https://www.acingov.pt/acingovprod/2/zonaPublica/zona_publica_c/donwloadProcedurePiece/MTAzOTU5Mg==\n20 - OUTROS REQUISITOS\nInformação sobre contratos reservados. Aplica-se a contratos reservados (54º-A)? Não\n21 - CRITÉRIO DE ADJUDICAÇÃO\nMultifator: Não\nMonofator:\nNome: Preço\n24 - CONDIÇÕES DO CONTRATO\nFaturação Eletrónica: Necessário\nObrigação de Subcontratação:\nCódigo da Obrigação de Subcontratação: Não é aplicável nenhuma obrigação de subcontratação.\n25 - COMPRA PÚBLICA ESTRATÉGICA\nCompra Pública Estratégica: Inexistência de contratação pública estratégica\n26 - INFORMAÇÕES ADICIONAIS\nContrato adequado para PME: Sim\nCobertura ACP (Acordo dos Contratos Públicos da Organização Mundial do Comércio): Não\n27 - IDENTIFICAÇÃO E CONTACTOS DO ÓRGÃO DE RECURSOS ADMINISTRATIVOS\nDesignação: Conforme Legislação aplicável\nEndereço: Conforme as peças do procedimento.\nCódigo postal: 9064-506\nLocalidade: Funchal\nTelefone: 2911145200\nFax: 2911145200\nEndereço eletrónico: gcp.drprgop@madeira.gov.pt\n28 - IDENTIFICAÇÃO DO(S) AUTOR(ES) DE ANÚNCIO\nNome: João Ricardo Luís dos Reis\nCargo: Diretor Regional\n419947555",
    "nipc": "671001329",
    "distrito": "Região Autónoma da Madeira",
    "concelho": "Funchal",
    "freguesia": "Todas",
    "site": "https://www.madeira.gov.pt/srei",
    "email": "gabinete.srei@madeira.gov.pt",
    "designacao_contrato": "Centro de Saúde de Santo António - Implementação de Medidas de Melhoria Energética",
    "descricao": "Centro de Saúde de Santo António - Implementação de Medidas de Melhoria Energética",
    "preco_base": "105.000,00 EUR",
    "prazo_execucao": "90 DIAS",
    "prazo_apresentacao_propostas": "27-01-2026 17:00",
    "fundos_eu": "Sim",
    "plataforma_eletronica": "ACIN",
    "url_procedimento": "https://www.acingov.pt",
    "autor_nome": "João Ricardo Luís dos Reis",
    "autor_cargo": "Diretor Regional"
  },
  {
    "numero_procedimento": "N/A",
    "entidade": "AnÃºncio de procedimento  n.Âº 447/2026  -  DiÃ¡rio da RepÃºblica n.Âº 6/2026, SÃ©rie II de 2026-01-09",
    "link": "https://diariodarepublica.pt/dr/detalhe/contrato-publico/447-1005484245"
  },
  {
    "numero_procedimento": "N/A",
    "entidade": "Pombal Prof - Sociedade de Educação e Ensino Profissional, SA",
    "link": "https://diariodarepublica.pt/dr/detalhe/contrato-publico/449-1005484246",
    "detalhes_completos": "1 - IDENTIFICAÇÃO E CONTACTOS DA ENTIDADE ADJUDICANTE\nDesignação da entidade adjudicante: Pombal Prof - Sociedade de Educação e Ensino Profissional, SA\nNIPC: 504609696\nServiço/Órgão/Pessoa de contacto: Conselho de Administração\nEndereço: Avenida Vasco da Gama, Parque Industrial Manuel da Mota\nCódigo postal: 3100-354\nLocalidade: Pombal\nPaís: Portugal\nNUT III: PT16F\nDistrito: Leiria\nConcelho: Pombal\nFreguesia: Freguesia de Pombal - Pombal\nTelefone: 236200810\nEndereço da Entidade (URL): https://www.etap.edu.pt/\nEndereço Eletrónico: info@etap.edu.pt\neDelivery Gateway (URL): https://www.acingov.pt\nFunção da Organização: Adquirente\nNorma jurídica da Entidade Adjudicante: Organismo de direito público\nÁrea de atividade da Autoridade Adjudicante: Serviços públicos das administrações públicas\n2 - JORNAL OFICIAL DA UNIÃO EUROPEIA\nO procedimento a que este anúncio diz respeito também é publicitado no Jornal Oficial da União Europeia? Não\n3 - AVISO\nModelo de Anúncio: Concurso público\nData de Envio do Anúncio: 09-01-2026\n5 - PROCESSO\nTipo de Procedimento: Concurso público\nPreço base do procedimento: Sim\nValor do preço base do procedimento: 72.535,75 EUR\nProcedimento com lotes? Não\n6 - OBJETO DO CONTRATO\nNúmero de referência interna: 0185-2025_CP\nDesignação do contrato: AQUISIÇÃO DE COMPUTADORES PORTÁTEIS\nDescrição: AQUISIÇÃO DE COMPUTADORES PORTÁTEIS\nTipo de Contrato Principal: Aquisição de Bens Móveis\nTipo de Contrato: Aquisição de Bens Móveis\nClassificação CPV (Vocabulário Comum para os Contratos Públicos)\nObjeto principal\nVocabulário Principal: 30213100\nPreço base s/IVA: 72.535,75 EUR\n7 - INDICAÇÕES ADICIONAIS\nO contrato envolve aquisição conjunta (satisfação de várias entidades)? Não\nO contrato é adjudicado por uma central de compras? Não\n8 - TÉCNICAS\nO concurso destina-se à celebração de um acordo-quadro? Inexistência de acordo-quadro\nÉ utilizado um leilão eletrónico? Não\nÉ adotada uma fase de negociação? Não\nSistema de Aquisição Dinâmico: Inexistência de sistema de aquisição dinâmico\n9 - LOCAL DA EXECUÇÃO DO CONTRATO\nLOCAL DA EXECUÇÃO DO CONTRATO (PROCEDIMENTO)\nPaís: Portugal\nNUT III: PT16F\nLocalidade: Freguesia de Pombal - Pombal\nDistrito: Leiria\nConcelho: Pombal\nFreguesia: Freguesia de Pombal - Pombal\n10 - PRAZO DE EXECUÇÃO DO CONTRATO\nPrazo de execução do contrato: 30 DIAS\nPrevisão de renovações: Não\n11 - FUNDOS EU\nTêm fundos EU? Não\n12 - DOCUMENTOS DE HABILITAÇÃO\nHabilitação para o exercício da atividade profissional: Não\n13 - CONDIÇÕES DE APRESENTAÇÃO\nPlataforma eletrónica utilizada pela entidade adjudicante: ACIN\nURL para Apresentação: https://www.acingov.pt\nAdmissibilidade da apresentação de propostas variantes: Não autorizado\nPrazo para apresentação das propostas: 15-01-2026 17:00\nPrazo durante o qual os concorrentes são obrigados a manter as respetivas propostas: 66 dias a contar do termo do prazo para a apresentação das propostas\nIndicação de Subcontratação na Proposta: Inexistência de indicação de subcontratação\n14 - PRESTAÇÃO DE CAUÇÃO\nPrestação de caução: Não\n15 - FORNECIMENTO DAS PEÇAS DO CONCURSO, APRESENTAÇÃO DE PEDIDOS DE PARTICIPAÇÃO E APRESENTAÇÃO DAS PROPOSTAS\nLink para acesso às peças do concurso (URL): https://www.acingov.pt/acingovprod/2/zonaPublica/zona_publica_c/donwloadProcedurePiece/MTA0MDgyOA==\n20 - OUTROS REQUISITOS\nInformação sobre contratos reservados. Aplica-se a contratos reservados (54º-A)? Não\n21 - CRITÉRIO DE ADJUDICAÇÃO\nMultifator: Sim\nFator: \nNome: Preço\nPonderação: 35%\nSubfatores: Não\nFator: \nNome: Outros\nOutro Nome: MÉRITO TÉCNICO DA PROPOSTA (MTPt)\nPonderação: 50%\nSubfatores: Sim\nSubfatores: \nNome: Pontuação do fator Prazo de Entrega (Pz)\nPonderação : 40%; \nNome: Pontuação do fator Características Técnicas(CT)\nPonderação : 60%; \nFator: \nNome: Outros\nOutro Nome: PERSONALIZAÇÃO DOS COMPUTADORES PORTÁTEIS\nPonderação: 15%\nSubfatores: Não\n24 - CONDIÇÕES DO CONTRATO\nFaturação Eletrónica: Permitido\nObrigação de Subcontratação:\nCódigo da Obrigação de Subcontratação: Não é aplicável nenhuma obrigação de subcontratação.\n25 - COMPRA PÚBLICA ESTRATÉGICA\nCompra Pública Estratégica: Redução dos impactos ambientais\nDescrição do Processo de Adjudicação Estratégico: Enquadramento estratégico: a contratação insere-se na estratégia nacional de compras públicas ecológicas (ECO360), integrando critérios de eficiência energética e conceção ecológica nos equipamentos. Reduz significativamente o consumo de papel, promovendo a desmaterialização pedagógica. Cada aluno recebe um computador, assumindo a sua manutenção e responsabilidade. O concurso exige conformidade com DNSH (Do No Significant Harm) e o respectivo equipamento deve respeitar os requisitos técnicos e ambientais do DL n.º 12/2011, garantindo a redução dos impactos ambientais desde a produção até ao ciclo de vida.\nCritérios de contratos Públicos Ecológicos: Critérios de contratação pública ecológica nacional\nCategorias da estratégia nacional: Computadores, monitores, tabletes e telemóveis inteligentes\nContratos Públicos Ecológicos: A mitigação das alterações climáticas\nDiretiva Veículos Não Poluentes: Não\nCritério de Acessibilidade: Os critérios de acessibilidade para as pessoas com deficiência não estão incluídos porque o contrato não se destina a pessoas singulares\n26 - INFORMAÇÕES ADICIONAIS\nContrato adequado para PME: Não\nCobertura ACP (Acordo dos Contratos Públicos da Organização Mundial do Comércio): Não\n27 - IDENTIFICAÇÃO E CONTACTOS DO ÓRGÃO DE RECURSOS ADMINISTRATIVOS\nDesignação: Conselho de Administração\nEndereço: Avenida Vasco da Gama, Parque Industrial Manuel da Mota\nCódigo postal: 3100-354\nLocalidade: Pombal\nTelefone: 236200810\nFax: \nEndereço eletrónico: Info@etap.edu.pt\nPrazo de interposição do recurso: 10 dias\n28 - IDENTIFICAÇÃO DO(S) AUTOR(ES) DE ANÚNCIO\nNome: Nuno Miguel Branco Ferreira\nCargo: Diretor de Formação e Projetos\n419947587",
    "nipc": "504609696",
    "distrito": "Leiria",
    "concelho": "Pombal",
    "freguesia": "Freguesia de Pombal - Pombal",
    "site": "https://www.etap.edu.pt/",
    "email": "info@etap.edu.pt",
    "designacao_contrato": "AQUISIÇÃO DE COMPUTADORES PORTÁTEIS",
    "descricao": "AQUISIÇÃO DE COMPUTADORES PORTÁTEIS",
    "preco_base": "72.535,75 EUR",
    "prazo_execucao": "30 DIAS",
    "prazo_apresentacao_propostas": "15-01-2026 17:00",
    "fundos_eu": "Não",
    "plataforma_eletronica": "ACIN",
    "url_procedimento": "https://www.acingov.pt",
    "autor_nome": "Nuno Miguel Branco Ferreira",
    "autor_cargo": "Diretor de Formação e Projetos"
  },
  {
    "numero_procedimento": "N/A",
    "entidade": "AnÃºncio de procedimento  n.Âº 450/2026  -  DiÃ¡rio da RepÃºblica n.Âº 6/2026, SÃ©rie II de 2026-01-09",
    "link": "https://diariodarepublica.pt/dr/detalhe/contrato-publico/450-1005484247"
  },
  {
    "numero_procedimento": "N/A",
    "entidade": "Agrupamento de Escolas de Arganil",
    "link": "https://diariodarepublica.pt/dr/detalhe/contrato-publico/451-1005484249",
    "detalhes_completos": "1 - IDENTIFICAÇÃO E CONTACTOS DA ENTIDADE ADJUDICANTE\nDesignação da entidade adjudicante: Agrupamento de Escolas de Arganil\nNIPC: 600084469\nEndereço: Av. das Forças Armadas\nCódigo postal: 3304-953\nLocalidade: Coimbra\nPaís: Portugal\nNUT III: PT16E\nDistrito: Coimbra\nConcelho: Arganil\nFreguesia: Todas\nTelefone: 235200180\nFax: 235200186\nEndereço da Entidade (URL): www.esarganil.pt\nEndereço Eletrónico: escola.s.arganil@gmail.com\neDelivery Gateway (URL): https://community.vortal.biz/public/\nFunção da Organização: Adquirente\nNorma jurídica da Entidade Adjudicante: Autoridade da administração central\nÁrea de atividade da Autoridade Adjudicante: Educação\n2 - JORNAL OFICIAL DA UNIÃO EUROPEIA\nO procedimento a que este anúncio diz respeito também é publicitado no Jornal Oficial da União Europeia? Não\n3 - AVISO\nModelo de Anúncio: Concurso público\nData de Envio do Anúncio: 09-01-2026\n5 - PROCESSO\nTipo de Procedimento: Concurso público\nPreço base do procedimento: Sim\nValor do preço base do procedimento: 80.000,00 EUR\nProcedimento com lotes? Sim\nNº Máx. de Lotes Autorizado: 2\nNúmero máximo de lotes que podem ser adjudicados a um concorrente: 2\n6 - OBJETO DO CONTRATO\nNúmero de referência interna: TRANSP_2026 – Aquisição de Serviços de Transportes\nDesignação do contrato: Aquisição de Serviços de Transportes\nDescrição: Aquisição de Serviços de Transportes para Atividades Letivas fora da Escola, Desporto Escolar e Deslocação Ocasional de Alunos, durante o ano económico de 2026.\nTipo de Contrato Principal: Aquisição de Serviços\nTipo de Contrato: Aquisição de Serviços\nClassificação CPV (Vocabulário Comum para os Contratos Públicos)\nObjeto principal\nVocabulário Principal: 60130000\nPreço base s/IVA: 80.000,00 EUR\nLotes: \nNº: LOT-0001\nDescrição do Lote: Lote 1 - Transporte colectivo de passageiros em minibus e/ou autocarros com condutor.\nPreço base s/IVA: 65.000,00 EUR\nClassificação CPV (Vocabulário Comum para os Contratos Públicos)\nObjeto principal\nVocabulário Principal: 60130000\nNº: LOT-0002\nDescrição do Lote: Lote 2 - Transporte colectivo de passageiros em viaturas com condutor de 1 a 8 lugares. \nPreço base s/IVA: 15.000,00 EUR\nClassificação CPV (Vocabulário Comum para os Contratos Públicos)\nObjeto principal\nVocabulário Principal: 60130000\n7 - INDICAÇÕES ADICIONAIS\nO contrato envolve aquisição conjunta (satisfação de várias entidades)? Não\nO contrato é adjudicado por uma central de compras? Não\n8 - TÉCNICAS\nO concurso destina-se à celebração de um acordo-quadro? Inexistência de acordo-quadro\nÉ utilizado um leilão eletrónico? Não\nÉ adotada uma fase de negociação? Não\nSistema de Aquisição Dinâmico: Inexistência de sistema de aquisição dinâmico\n9 - LOCAL DA EXECUÇÃO DO CONTRATO\nLOCAL DA EXECUÇÃO DO CONTRATO (PROCEDIMENTO)\nPaís: Portugal\nNUT III: PT16E\nLocalidade: Coimbra\nDistrito: Coimbra\nConcelho: Arganil\nFreguesia: Todas\nLOCAL DA EXECUÇÃO DO CONTRATO (LOTE)\nIdentificador do Lote: LOT-0001; LOT-0002\nPaís: Portugal\nNUT III: PT16E\nLocalidade: Coimbra\nDistrito: Coimbra\nConcelho: Arganil\nFreguesia: Todas\n10 - PRAZO DE EXECUÇÃO DO CONTRATO\nIdentificador do Lote: LOT-0001; LOT-0002\nPrazo de execução do contrato: 330 DIAS\nPrevisão de renovações: Não\n11 - FUNDOS EU\nIdentificador do Lote: LOT-0001; LOT-0002\nTêm fundos EU? Não\n12 - DOCUMENTOS DE HABILITAÇÃO\nHabilitação para o exercício da atividade profissional: Sim\nTipo: Alvará\nDescrição: Alvará emitido pelo Instituto da Mobilidade e dos Transportes Terrestres (IMTT) referente ao\nlicenciamento da atividade de transporte coletivo de crianças.\n13 - CONDIÇÕES DE APRESENTAÇÃO\nPlataforma eletrónica utilizada pela entidade adjudicante: VORTAL\nURL para Apresentação: https://community.vortal.biz/public/\nAdmissibilidade da apresentação de propostas variantes: Não autorizado\nPrazo para apresentação das propostas: 19-01-2026 23:59\nPrazo durante o qual os concorrentes são obrigados a manter as respetivas propostas: 66 dias a contar do termo do prazo para a apresentação das propostas\nIndicação de Subcontratação na Proposta: Inexistência de indicação de subcontratação\n14 - PRESTAÇÃO DE CAUÇÃO\nPrestação de caução: Não\n15 - FORNECIMENTO DAS PEÇAS DO CONCURSO, APRESENTAÇÃO DE PEDIDOS DE PARTICIPAÇÃO E APRESENTAÇÃO DAS PROPOSTAS\nLink para acesso às peças do concurso (URL): https://community.vortal.biz/Public/public-tender-documents/Qk5jNzJ3cndXQlpQdXhrMTVtQStlMzBoNG5MQ0pLaWJ5SEVhV3lwZzRkYlJCM0w1ekhZWTNtUFY1dlczeHRGTStvMHl0bXk2YS9KaDhXKzBnOWY0Qmc9PWhmdDY5\n20 - OUTROS REQUISITOS\nIdentificador do Lote: LOT-0001; LOT-0002\nInformação sobre contratos reservados. Aplica-se a contratos reservados (54º-A)? Não\n21 - CRITÉRIO DE ADJUDICAÇÃO\nO Critério de adjudicação é diferenciado por lote? Não\nMultifator: Não\nMonofator:\nNome: Preço\n24 - CONDIÇÕES DO CONTRATO\nIdentificador do Lote: LOT-0001; LOT-0002\nFaturação Eletrónica: Permitido\nObrigação de Subcontratação:\nCódigo da Obrigação de Subcontratação: Não é aplicável nenhuma obrigação de subcontratação.\n25 - COMPRA PÚBLICA ESTRATÉGICA\nCompra Pública Estratégica: Inexistência de contratação pública estratégica\n26 - INFORMAÇÕES ADICIONAIS\nIdentificador do Lote: LOT-0001; LOT-0002\nContrato adequado para PME: Sim\nCobertura ACP (Acordo dos Contratos Públicos da Organização Mundial do Comércio): Não\n27 - IDENTIFICAÇÃO E CONTACTOS DO ÓRGÃO DE RECURSOS ADMINISTRATIVOS\nDesignação: Conselho Administrativo do Agrupamento de Escolas de Arganil\nEndereço: Avenida das Forças Armadas\nCódigo postal: 3300-011\nLocalidade: Arganil\nTelefone: +351 235200180\nFax: +351 235200180\nEndereço eletrónico: contratos.agrup.arganil@gmail.com\n28 - IDENTIFICAÇÃO DO(S) AUTOR(ES) DE ANÚNCIO\nNome: Anabela Henriques de Matos Soares\nCargo: Diretora do Agrupamento de Escolas de Arganil\n419947554",
    "nipc": "600084469",
    "distrito": "Coimbra",
    "concelho": "Arganil",
    "freguesia": "Todas",
    "site": "www.esarganil.pt",
    "email": "escola.s.arganil@gmail.com",
    "designacao_contrato": "Aquisição de Serviços de Transportes",
    "descricao": "Aquisição de Serviços de Transportes para Atividades Letivas fora da Escola, Desporto Escolar e Deslocação Ocasional de Alunos, durante o ano económico de 2026.",
    "preco_base": "80.000,00 EUR",
    "prazo_execucao": "330 DIAS",
    "prazo_apresentacao_propostas": "19-01-2026 23:59",
    "fundos_eu": "Não",
    "plataforma_eletronica": "VORTAL",
    "url_procedimento": "https://community.vortal.biz/public/",
    "autor_nome": "Anabela Henriques de Matos Soares",
    "autor_cargo": "Diretora do Agrupamento de Escolas de Arganil"
  },
  {
    "numero_procedimento": "N/A",
    "entidade": "Santa Casa da Misericórdia de Lisboa",
    "link": "https://diariodarepublica.pt/dr/detalhe/contrato-publico/453-1005484250",
    "detalhes_completos": "1 - IDENTIFICAÇÃO E CONTACTOS DA ENTIDADE ADJUDICANTE\nDesignação da entidade adjudicante: Santa Casa da Misericórdia de Lisboa\nNIPC: 500745471\nServiço/Órgão/Pessoa de contacto: Exma. Mesa\nEndereço: Largo Trindade Coelho\nCódigo postal: 1200-470\nLocalidade: Lisboa\nPaís: Portugal\nNUT III: PT170\nDistrito: Lisboa\nConcelho: Todos\nFreguesia: Todas\nTelefone: 213235000\nFax: 213235013\nEndereço da Entidade (URL): http://www.scml.pt/\nEndereço Eletrónico: compras@scml.pt\neDelivery Gateway (URL): https://www.acingov.pt\nFunção da Organização: Adquirente\nSubfunção da Organização: Organização cujo orçamento é utilizado para pagar o contrato; Organização que executa o pagamento; Organização que fornece informações adicionais sobre o processo de adjudicação; Organização que fornece mais informações sobre os prazos dos procedimentos de recurso; Organização que fornece acesso fora de linha aos documentos do concurso; Organização responsável pelo tratamento das propostas; Organização que recebe as propostas; Organização que trata os pedidos de participação; Organização que recebe pedidos de participação; Organização que fornece mais informações sobre os procedimentos de recurso; Organização que assina o contrato\nNorma jurídica da Entidade Adjudicante: Organismo de direito público, controlado por uma autoridade da administração central\nÁrea de atividade da Autoridade Adjudicante: Proteção social\n2 - JORNAL OFICIAL DA UNIÃO EUROPEIA\nO procedimento a que este anúncio diz respeito também é publicitado no Jornal Oficial da União Europeia? Não\n3 - AVISO\nModelo de Anúncio: Concurso público\nData de Envio do Anúncio: 09-01-2026\n5 - PROCESSO\nTipo de Procedimento: Concurso público\nPreço base do procedimento: Sim\nValor do preço base do procedimento: 28.000,00 EUR\nProcedimento com lotes? Não\n6 - OBJETO DO CONTRATO\nNúmero de referência interna: 25DC39CP027\nDesignação do contrato: Empreitada de Revestimento das paredes de contenção das rampas de acesso ao estacionamento do Edifício sito na Praça José Fontana, 36-39 a Rua Sousa Martins, 24-28 e Rua Sousa Martins, 22\nDescrição: Empreitada de Revestimento das paredes de contenção das rampas de acesso ao estacionamento do Edifício sito na Praça José Fontana, 36-39 a Rua Sousa Martins, 24-28 e Rua Sousa Martins, 22 \nTipo de Contrato Principal: Empreitada de Obras Públicas\nTipo de Contrato: Empreitada de Obras Públicas\nClassificação CPV (Vocabulário Comum para os Contratos Públicos)\nObjeto principal\nVocabulário Principal: 45260000\nPreço base s/IVA: 28.000,00 EUR\n7 - INDICAÇÕES ADICIONAIS\nO contrato envolve aquisição conjunta (satisfação de várias entidades)? Não\nO contrato é adjudicado por uma central de compras? Não\n8 - TÉCNICAS\nO concurso destina-se à celebração de um acordo-quadro? Inexistência de acordo-quadro\nÉ utilizado um leilão eletrónico? Não\nÉ adotada uma fase de negociação? Não\nSistema de Aquisição Dinâmico: Inexistência de sistema de aquisição dinâmico\n9 - LOCAL DA EXECUÇÃO DO CONTRATO\nLOCAL DA EXECUÇÃO DO CONTRATO (PROCEDIMENTO)\nPaís: Portugal\nNUT III: PT170\nLocalidade: Freguesia de Misericórdia\nDistrito: Lisboa\nConcelho: Lisboa\nFreguesia: Freguesia de Misericórdia\n10 - PRAZO DE EXECUÇÃO DO CONTRATO\nPrazo de execução do contrato: 1 MESES\nPrevisão de renovações: Não\n11 - FUNDOS EU\nTêm fundos EU? Não\n12 - DOCUMENTOS DE HABILITAÇÃO\nHabilitação para o exercício da atividade profissional: Sim\nTipo: Alvará\nDescrição: Da 1ª Categoria (Edificios e Património), na classe correspondente à parte dos trabalhos a que respeitem:\nDa 5ª subcategoria \nDa 7ª subcategoria \n13 - CONDIÇÕES DE APRESENTAÇÃO\nPlataforma eletrónica utilizada pela entidade adjudicante: ACIN\nURL para Apresentação: https://www.acingov.pt\nAdmissibilidade da apresentação de propostas variantes: Não autorizado\nPrazo para apresentação das propostas: 30-01-2026 17:00\nPrazo durante o qual os concorrentes são obrigados a manter as respetivas propostas: 120 dias a contar do termo do prazo para a apresentação das propostas\nIndicação de Subcontratação na Proposta: Inexistência de indicação de subcontratação\n14 - PRESTAÇÃO DE CAUÇÃO\nPrestação de caução: Não\n15 - FORNECIMENTO DAS PEÇAS DO CONCURSO, APRESENTAÇÃO DE PEDIDOS DE PARTICIPAÇÃO E APRESENTAÇÃO DAS PROPOSTAS\nLink para acesso às peças do concurso (URL): https://www.acingov.pt/acingovprod/2/zonaPublica/zona_publica_c/donwloadProcedurePiece/MTAxMjA5OA==\n20 - OUTROS REQUISITOS\nInformação sobre contratos reservados. Aplica-se a contratos reservados (54º-A)? Não\n21 - CRITÉRIO DE ADJUDICAÇÃO\nMultifator: Não\nMonofator:\nNome: Outros\nOutro nome: Fator Preço\n24 - CONDIÇÕES DO CONTRATO\nFaturação Eletrónica: Necessário\nObrigação de Subcontratação:\nCódigo da Obrigação de Subcontratação: Não é aplicável nenhuma obrigação de subcontratação.\n25 - COMPRA PÚBLICA ESTRATÉGICA\nCompra Pública Estratégica: Inexistência de contratação pública estratégica\n26 - INFORMAÇÕES ADICIONAIS\nContrato adequado para PME: Sim\nCobertura ACP (Acordo dos Contratos Públicos da Organização Mundial do Comércio): Não\n27 - IDENTIFICAÇÃO E CONTACTOS DO ÓRGÃO DE RECURSOS ADMINISTRATIVOS\nDesignação: Direção de Compras\nEndereço: Largo Trindade Coelho\nCódigo postal: 1200-470\nLocalidade: Lisboa\nTelefone: 213235000\nFax: \nEndereço eletrónico: dicom.neei@scml.pt\nPrazo de interposição do recurso: 10 dias\n28 - IDENTIFICAÇÃO DO(S) AUTOR(ES) DE ANÚNCIO\nNome: Vanda Simão\nCargo: Diretora da Direção de Compras\n419947567",
    "nipc": "500745471",
    "distrito": "Lisboa",
    "concelho": "Todos",
    "freguesia": "Todas",
    "site": "http://www.scml.pt/",
    "email": "compras@scml.pt",
    "designacao_contrato": "Empreitada de Revestimento das paredes de contenção das rampas de acesso ao estacionamento do Edifício sito na Praça José Fontana, 36-39 a Rua Sousa Martins, 24-28 e Rua Sousa Martins, 22",
    "descricao": "Empreitada de Revestimento das paredes de contenção das rampas de acesso ao estacionamento do Edifício sito na Praça José Fontana, 36-39 a Rua Sousa Martins, 24-28 e Rua Sousa Martins, 22",
    "preco_base": "28.000,00 EUR",
    "prazo_execucao": "1 MESES",
    "prazo_apresentacao_propostas": "30-01-2026 17:00",
    "fundos_eu": "Não",
    "plataforma_eletronica": "ACIN",
    "url_procedimento": "https://www.acingov.pt",
    "autor_nome": "Vanda Simão",
    "autor_cargo": "Diretora da Direção de Compras"
  },
  {
    "numero_procedimento": "N/A",
    "entidade": "Santa Casa da Misericórdia de Lisboa",
    "link": "https://diariodarepublica.pt/dr/detalhe/contrato-publico/454-1005484251",
    "detalhes_completos": "1 - IDENTIFICAÇÃO E CONTACTOS DA ENTIDADE ADJUDICANTE\nDesignação da entidade adjudicante: Santa Casa da Misericórdia de Lisboa\nNIPC: 500745471\nServiço/Órgão/Pessoa de contacto: Exma. Mesa\nEndereço: Largo Trindade Coelho\nCódigo postal: 1200-470\nLocalidade: Lisboa\nPaís: Portugal\nNUT III: PT170\nDistrito: Lisboa\nConcelho: Todos\nFreguesia: Todas\nTelefone: 213235000\nFax: 213235013\nEndereço da Entidade (URL): http://www.scml.pt/\nEndereço Eletrónico: compras@scml.pt\neDelivery Gateway (URL): https://www.acingov.pt\nFunção da Organização: Adquirente\nSubfunção da Organização: Organização cujo orçamento é utilizado para pagar o contrato; Organização que executa o pagamento; Organização que fornece informações adicionais sobre o processo de adjudicação; Organização que fornece mais informações sobre os prazos dos procedimentos de recurso; Organização que fornece acesso fora de linha aos documentos do concurso; Organização responsável pelo tratamento das propostas; Organização que recebe as propostas; Organização que trata os pedidos de participação; Organização que recebe pedidos de participação; Organização que fornece mais informações sobre os procedimentos de recurso; Organização que assina o contrato\nNorma jurídica da Entidade Adjudicante: Organismo de direito público, controlado por uma autoridade da administração central\nÁrea de atividade da Autoridade Adjudicante: Proteção social\n2 - JORNAL OFICIAL DA UNIÃO EUROPEIA\nO procedimento a que este anúncio diz respeito também é publicitado no Jornal Oficial da União Europeia? Não\n3 - AVISO\nModelo de Anúncio: Concurso público\nData de Envio do Anúncio: 09-01-2026\n5 - PROCESSO\nTipo de Procedimento: Concurso público\nPreço base do procedimento: Sim\nValor do preço base do procedimento: 15.525,00 EUR\nProcedimento com lotes? Não\n6 - OBJETO DO CONTRATO\nNúmero de referência interna: 25DC39CP035\nDesignação do contrato: Prestação de serviços de manutenção da estufa de pintura automóvel da Aldeia de Santa Isabel\nDescrição: Prestação de serviços de manutenção da estufa de pintura automóvel da Aldeia de Santa Isabel \nTipo de Contrato Principal: Aquisição de Serviços\nTipo de Contrato: Aquisição de Serviços\nClassificação CPV (Vocabulário Comum para os Contratos Públicos)\nObjeto principal\nVocabulário Principal: 50110000\nPreço base s/IVA: 15.525,00 EUR\n7 - INDICAÇÕES ADICIONAIS\nO contrato envolve aquisição conjunta (satisfação de várias entidades)? Não\nO contrato é adjudicado por uma central de compras? Não\n8 - TÉCNICAS\nO concurso destina-se à celebração de um acordo-quadro? Inexistência de acordo-quadro\nÉ utilizado um leilão eletrónico? Não\nÉ adotada uma fase de negociação? Não\nSistema de Aquisição Dinâmico: Inexistência de sistema de aquisição dinâmico\n9 - LOCAL DA EXECUÇÃO DO CONTRATO\nLOCAL DA EXECUÇÃO DO CONTRATO (PROCEDIMENTO)\nPaís: Portugal\nNUT III: PT170\nLocalidade: Freguesia de Misericórdia\nDistrito: Lisboa\nConcelho: Lisboa\nFreguesia: Freguesia de Misericórdia\n10 - PRAZO DE EXECUÇÃO DO CONTRATO\nPrazo de execução do contrato: 36 MESES\nPrevisão de renovações: Não\n11 - FUNDOS EU\nTêm fundos EU? Não\n12 - DOCUMENTOS DE HABILITAÇÃO\nHabilitação para o exercício da atividade profissional: Não\n13 - CONDIÇÕES DE APRESENTAÇÃO\nPlataforma eletrónica utilizada pela entidade adjudicante: ACIN\nURL para Apresentação: https://www.acingov.pt\nAdmissibilidade da apresentação de propostas variantes: Não autorizado\nPrazo para apresentação das propostas: 30-01-2026 17:00\nPrazo durante o qual os concorrentes são obrigados a manter as respetivas propostas: 120 dias a contar do termo do prazo para a apresentação das propostas\nIndicação de Subcontratação na Proposta: Inexistência de indicação de subcontratação\n14 - PRESTAÇÃO DE CAUÇÃO\nPrestação de caução: Não\n15 - FORNECIMENTO DAS PEÇAS DO CONCURSO, APRESENTAÇÃO DE PEDIDOS DE PARTICIPAÇÃO E APRESENTAÇÃO DAS PROPOSTAS\nLink para acesso às peças do concurso (URL): https://www.acingov.pt/acingovprod/2/zonaPublica/zona_publica_c/donwloadProcedurePiece/MTAxMDg5NQ==\n20 - OUTROS REQUISITOS\nInformação sobre contratos reservados. Aplica-se a contratos reservados (54º-A)? Não\n21 - CRITÉRIO DE ADJUDICAÇÃO\nMultifator: Sim\nFator: \nNome: Outros\nOutro Nome: Multifator\nPonderação: 100%\nSubfatores: Não\n24 - CONDIÇÕES DO CONTRATO\nFaturação Eletrónica: Necessário\nObrigação de Subcontratação:\nCódigo da Obrigação de Subcontratação: Não é aplicável nenhuma obrigação de subcontratação.\n25 - COMPRA PÚBLICA ESTRATÉGICA\nCompra Pública Estratégica: Inexistência de contratação pública estratégica\n26 - INFORMAÇÕES ADICIONAIS\nContrato adequado para PME: Sim\nCobertura ACP (Acordo dos Contratos Públicos da Organização Mundial do Comércio): Não\n27 - IDENTIFICAÇÃO E CONTACTOS DO ÓRGÃO DE RECURSOS ADMINISTRATIVOS\nDesignação: Direção de Compras\nEndereço: Largo Trindade Coelho\nCódigo postal: 1200-470\nLocalidade: Lisboa\nTelefone: 213235000\nFax: \nEndereço eletrónico: dicom.neei@scml.pt\nPrazo de interposição do recurso: 10 dias\n28 - IDENTIFICAÇÃO DO(S) AUTOR(ES) DE ANÚNCIO\nNome: Vanda Simão\nCargo: Diretora da Direção de Compras\n419947566",
    "nipc": "500745471",
    "distrito": "Lisboa",
    "concelho": "Todos",
    "freguesia": "Todas",
    "site": "http://www.scml.pt/",
    "email": "compras@scml.pt",
    "designacao_contrato": "Prestação de serviços de manutenção da estufa de pintura automóvel da Aldeia de Santa Isabel",
    "descricao": "Prestação de serviços de manutenção da estufa de pintura automóvel da Aldeia de Santa Isabel",
    "preco_base": "15.525,00 EUR",
    "prazo_execucao": "36 MESES",
    "prazo_apresentacao_propostas": "30-01-2026 17:00",
    "fundos_eu": "Não",
    "plataforma_eletronica": "ACIN",
    "url_procedimento": "https://www.acingov.pt",
    "autor_nome": "Vanda Simão",
    "autor_cargo": "Diretora da Direção de Compras"
  },
  {
    "numero_procedimento": "N/A",
    "entidade": "Unidade Local de Saúde de São João, EPE",
    "link": "https://diariodarepublica.pt/dr/detalhe/contrato-publico/457-1005484252",
    "detalhes_completos": "1 - IDENTIFICAÇÃO E CONTACTOS DA ENTIDADE ADJUDICANTE\nDesignação da entidade adjudicante: Unidade Local de Saúde de São João, EPE\nNIPC: 509821197\nEndereço: Alameda Prof. Hernâni Monteiro\nCódigo postal: 4200-319\nLocalidade: Área Metropolitana do Porto\nPaís: Portugal\nNUT III: PT11A\nDistrito: Porto\nConcelho: Porto\nFreguesia: Freguesia de Paranhos - Porto\nTelefone: 225512100\nFax: 225504463\nEndereço da Entidade (URL): https://portal-chsj.min-saude.pt/\nEndereço Eletrónico: geral@ulssjoao.min-saude.pt\neDelivery Gateway (URL): https://community.vortal.biz/public/\nFunção da Organização: Adquirente\nNorma jurídica da Entidade Adjudicante: Organismo de direito público\nÁrea de atividade da Autoridade Adjudicante: Saúde\n2 - JORNAL OFICIAL DA UNIÃO EUROPEIA\nO procedimento a que este anúncio diz respeito também é publicitado no Jornal Oficial da União Europeia? Não\n3 - AVISO\nModelo de Anúncio: Concurso público\nData de Envio do Anúncio: 09-01-2026\n5 - PROCESSO\nTipo de Procedimento: Concurso público\nPreço base do procedimento: Sim\nValor do preço base do procedimento: 12.000,00 EUR\nProcedimento com lotes? Não\n6 - OBJETO DO CONTRATO\nNúmero de referência interna: 31001126\nDesignação do contrato: Aquisição de 1 Unidade Dentária Móvel para Serviço de Estomatologia\nDescrição: Aquisição de 1 Unidade Dentária Móvel para Serviço de Estomatologia\nTipo de Contrato Principal: Aquisição de Bens Móveis\nTipo de Contrato: Aquisição de Bens Móveis\nClassificação CPV (Vocabulário Comum para os Contratos Públicos)\nObjeto principal\nVocabulário Principal: 33100000\nPreço base s/IVA: 12.000,00 EUR\n7 - INDICAÇÕES ADICIONAIS\nO contrato envolve aquisição conjunta (satisfação de várias entidades)? Não\nO contrato é adjudicado por uma central de compras? Não\n8 - TÉCNICAS\nO concurso destina-se à celebração de um acordo-quadro? Inexistência de acordo-quadro\nÉ utilizado um leilão eletrónico? Não\nÉ adotada uma fase de negociação? Não\nSistema de Aquisição Dinâmico: Inexistência de sistema de aquisição dinâmico\n9 - LOCAL DA EXECUÇÃO DO CONTRATO\nLOCAL DA EXECUÇÃO DO CONTRATO (PROCEDIMENTO)\nPaís: Portugal\nNUT III: PT11A\nLocalidade: Área Metropolitana do Porto\nDistrito: Porto\nConcelho: Porto\nFreguesia: Freguesia de Paranhos - Porto\n10 - PRAZO DE EXECUÇÃO DO CONTRATO\nPrazo de execução do contrato: 45 DIAS\nPrevisão de renovações: Não\n11 - FUNDOS EU\nTêm fundos EU? Não\n12 - DOCUMENTOS DE HABILITAÇÃO\nHabilitação para o exercício da atividade profissional: Não\n13 - CONDIÇÕES DE APRESENTAÇÃO\nPlataforma eletrónica utilizada pela entidade adjudicante: VORTAL\nURL para Apresentação: https://community.vortal.biz/public/\nAdmissibilidade da apresentação de propostas variantes: Não autorizado\nPrazo para apresentação das propostas: 21-01-2026 17:00\nPrazo durante o qual os concorrentes são obrigados a manter as respetivas propostas: 90 dias a contar do termo do prazo para a apresentação das propostas\nIndicação de Subcontratação na Proposta: Inexistência de indicação de subcontratação\n14 - PRESTAÇÃO DE CAUÇÃO\nPrestação de caução: Não\n15 - FORNECIMENTO DAS PEÇAS DO CONCURSO, APRESENTAÇÃO DE PEDIDOS DE PARTICIPAÇÃO E APRESENTAÇÃO DAS PROPOSTAS\nLink para acesso às peças do concurso (URL): https://community.vortal.biz/Public/public-tender-documents/bnpLQWxFa2tJWWQ2aFphSTVJdUN2YkVyU1FXWEFoejNYakxVb2M5MVFVdDQ0SEg0T2dLbS82bFROTEtSdmFUUGdJRi9aa3E1R0ljd0Q1OWlpcTBLL2c9PTZ6KSgx\n20 - OUTROS REQUISITOS\nInformação sobre contratos reservados. Aplica-se a contratos reservados (54º-A)? Não\n21 - CRITÉRIO DE ADJUDICAÇÃO\nMultifator: Sim\nFator: \nNome: Preço\nPonderação: 40%\nSubfatores: Não\nFator: \nNome: Qualidade\nPonderação: 10%\nSubfatores: Não\nFator: \nNome: Qualidade\nPonderação: 10%\nSubfatores: Não\nFator: \nNome: Qualidade\nPonderação: 40%\nSubfatores: Não\n24 - CONDIÇÕES DO CONTRATO\nFaturação Eletrónica: Permitido\nObrigação de Subcontratação:\nCódigo da Obrigação de Subcontratação: Não é aplicável nenhuma obrigação de subcontratação.\n25 - COMPRA PÚBLICA ESTRATÉGICA\nCompra Pública Estratégica: Inexistência de contratação pública estratégica\n26 - INFORMAÇÕES ADICIONAIS\nContrato adequado para PME: Sim\nCobertura ACP (Acordo dos Contratos Públicos da Organização Mundial do Comércio): Não\n27 - IDENTIFICAÇÃO E CONTACTOS DO ÓRGÃO DE RECURSOS ADMINISTRATIVOS\nDesignação: Conselho de Administração\nEndereço: ULSSJ - Alameda Professor Hernani Monteiro\nCódigo postal: 4200-319\nLocalidade: Porto\nTelefone: +351 225512100\nFax: +351 225025766\nEndereço eletrónico: a@ulssjoao.min-saude.pt\n28 - IDENTIFICAÇÃO DO(S) AUTOR(ES) DE ANÚNCIO\nNome: Tiago Ferreira\nCargo: Diretor do Serviço de Aprovisionamento\n419947576",
    "nipc": "509821197",
    "distrito": "Porto",
    "concelho": "Porto",
    "freguesia": "Freguesia de Paranhos - Porto",
    "site": "https://portal-chsj.min-saude.pt/",
    "email": "geral@ulssjoao.min-saude.pt",
    "designacao_contrato": "Aquisição de 1 Unidade Dentária Móvel para Serviço de Estomatologia",
    "descricao": "Aquisição de 1 Unidade Dentária Móvel para Serviço de Estomatologia",
    "preco_base": "12.000,00 EUR",
    "prazo_execucao": "45 DIAS",
    "prazo_apresentacao_propostas": "21-01-2026 17:00",
    "fundos_eu": "Não",
    "plataforma_eletronica": "VORTAL",
    "url_procedimento": "https://community.vortal.biz/public/",
    "autor_nome": "Tiago Ferreira",
    "autor_cargo": "Diretor do Serviço de Aprovisionamento"
  },
  {
    "numero_procedimento": "N/A",
    "entidade": "Unidade Local de Saúde de São João, EPE",
    "link": "https://diariodarepublica.pt/dr/detalhe/contrato-publico/458-1005484253",
    "detalhes_completos": "1 - IDENTIFICAÇÃO E CONTACTOS DA ENTIDADE ADJUDICANTE\nDesignação da entidade adjudicante: Unidade Local de Saúde de São João, EPE\nNIPC: 509821197\nEndereço: Alameda Prof. Hernâni Monteiro\nCódigo postal: 4200-319\nLocalidade: Área Metropolitana do Porto\nPaís: Portugal\nNUT III: PT11A\nDistrito: Porto\nConcelho: Porto\nFreguesia: Freguesia de Paranhos - Porto\nTelefone: 225512100\nFax: 225504463\nEndereço da Entidade (URL): https://portal-chsj.min-saude.pt/\nEndereço Eletrónico: geral@ulssjoao.min-saude.pt\neDelivery Gateway (URL): https://community.vortal.biz/public/\nFunção da Organização: Adquirente\nNorma jurídica da Entidade Adjudicante: Organismo de direito público\nÁrea de atividade da Autoridade Adjudicante: Saúde\n2 - JORNAL OFICIAL DA UNIÃO EUROPEIA\nO procedimento a que este anúncio diz respeito também é publicitado no Jornal Oficial da União Europeia? Não\n3 - AVISO\nModelo de Anúncio: Concurso público\nData de Envio do Anúncio: 09-01-2026\n5 - PROCESSO\nTipo de Procedimento: Concurso público\nPreço base do procedimento: Sim\nValor do preço base do procedimento: 145.000,00 EUR\nProcedimento com lotes? Não\n6 - OBJETO DO CONTRATO\nNúmero de referência interna: 81001026 \nDesignação do contrato: Aquisição de serviços de objeto aquisição de Serviços de Implementação de Sistema Integrado de Operação Aérea com Drones de Transporte\nDescrição: Aquisição de serviços de objeto aquisição de Serviços de Implementação de Sistema Integrado de Operação Aérea com Drones de Transporte.\nTipo de Contrato Principal: Aquisição de Serviços\nTipo de Contrato: Aquisição de Serviços\nClassificação CPV (Vocabulário Comum para os Contratos Públicos)\nObjeto principal\nVocabulário Principal: 60444000\nPreço base s/IVA: 145.000,00 EUR\n7 - INDICAÇÕES ADICIONAIS\nO contrato envolve aquisição conjunta (satisfação de várias entidades)? Não\nO contrato é adjudicado por uma central de compras? Não\n8 - TÉCNICAS\nO concurso destina-se à celebração de um acordo-quadro? Inexistência de acordo-quadro\nÉ utilizado um leilão eletrónico? Não\nÉ adotada uma fase de negociação? Não\nSistema de Aquisição Dinâmico: Inexistência de sistema de aquisição dinâmico\n9 - LOCAL DA EXECUÇÃO DO CONTRATO\nLOCAL DA EXECUÇÃO DO CONTRATO (PROCEDIMENTO)\nPaís: Portugal\nNUT III: PT11A\nLocalidade: Área Metropolitana do Porto\nDistrito: Porto\nConcelho: Porto\nFreguesia: Freguesia de Paranhos - Porto\n10 - PRAZO DE EXECUÇÃO DO CONTRATO\nPrazo de execução do contrato: 180 DIAS\nPrevisão de renovações: Não\n11 - FUNDOS EU\nTêm fundos EU? Sim\n12 - DOCUMENTOS DE HABILITAÇÃO\nHabilitação para o exercício da atividade profissional: Não\n13 - CONDIÇÕES DE APRESENTAÇÃO\nPlataforma eletrónica utilizada pela entidade adjudicante: VORTAL\nURL para Apresentação: https://community.vortal.biz/public/\nAdmissibilidade da apresentação de propostas variantes: Não autorizado\nPrazo para apresentação das propostas: 21-01-2026 17:00\nPrazo durante o qual os concorrentes são obrigados a manter as respetivas propostas: 90 dias a contar do termo do prazo para a apresentação das propostas\nIndicação de Subcontratação na Proposta: Inexistência de indicação de subcontratação\n14 - PRESTAÇÃO DE CAUÇÃO\nPrestação de caução: Não\n15 - FORNECIMENTO DAS PEÇAS DO CONCURSO, APRESENTAÇÃO DE PEDIDOS DE PARTICIPAÇÃO E APRESENTAÇÃO DAS PROPOSTAS\nLink para acesso às peças do concurso (URL): https://community.vortal.biz/Public/public-tender-documents/cjYyZXk2aEk2Sm81NUZhdVpjb2NjZ0VtdDNva0JCdHBCLzVNV3BOL2N4MXlMSEVROTRSbmJMdmxPN2I2QWNPU0VRYVJyWWVuSHkzSkd4Nkl0ODZGWlE9PXMmUzBO\n20 - OUTROS REQUISITOS\nInformação sobre contratos reservados. Aplica-se a contratos reservados (54º-A)? Não\n21 - CRITÉRIO DE ADJUDICAÇÃO\nMultifator: Sim\nFator: \nNome: Preço\nPonderação: 50%\nSubfatores: Não\nFator: \nNome: Qualidade\nPonderação: 50%\nSubfatores: Não\n24 - CONDIÇÕES DO CONTRATO\nFaturação Eletrónica: Permitido\nObrigação de Subcontratação:\nCódigo da Obrigação de Subcontratação: Não é aplicável nenhuma obrigação de subcontratação.\n25 - COMPRA PÚBLICA ESTRATÉGICA\nCompra Pública Estratégica: Inexistência de contratação pública estratégica\n26 - INFORMAÇÕES ADICIONAIS\nContrato adequado para PME: Sim\nCobertura ACP (Acordo dos Contratos Públicos da Organização Mundial do Comércio): Não\n27 - IDENTIFICAÇÃO E CONTACTOS DO ÓRGÃO DE RECURSOS ADMINISTRATIVOS\nDesignação: Conselho de Administração\nEndereço: ULS São João - Alameda Prof. Hernani Monteiro\nCódigo postal: 4200-319\nLocalidade: Porto\nTelefone: +351 225512100\nFax: +351 225025766\nEndereço eletrónico: ca@ulssjoao.min-saude.pt\n28 - IDENTIFICAÇÃO DO(S) AUTOR(ES) DE ANÚNCIO\nNome: Eng. Tiago Ferreira\nCargo: Diretor de Serviço de Aprovisionamento\n419947574",
    "nipc": "509821197",
    "distrito": "Porto",
    "concelho": "Porto",
    "freguesia": "Freguesia de Paranhos - Porto",
    "site": "https://portal-chsj.min-saude.pt/",
    "email": "geral@ulssjoao.min-saude.pt",
    "designacao_contrato": "Aquisição de serviços de objeto aquisição de Serviços de Implementação de Sistema Integrado de Operação Aérea com Drones de Transporte",
    "descricao": "Aquisição de serviços de objeto aquisição de Serviços de Implementação de Sistema Integrado de Operação Aérea com Drones de Transporte.",
    "preco_base": "145.000,00 EUR",
    "prazo_execucao": "180 DIAS",
    "prazo_apresentacao_propostas": "21-01-2026 17:00",
    "fundos_eu": "Sim",
    "plataforma_eletronica": "VORTAL",
    "url_procedimento": "https://community.vortal.biz/public/",
    "autor_nome": "Eng. Tiago Ferreira",
    "autor_cargo": "Diretor de Serviço de Aprovisionamento"
  }
]