[
  {
    "numero_procedimento": "N/A",
    "entidade": "AnÃºncio de procedimento  n.Âº 889/2026  -  DiÃ¡rio da RepÃºblica n.Âº 11/2026, SÃ©rie II de 2026-01-16",
    "link": "https://diariodarepublica.pt/dr/detalhe/contrato-publico/889-1011550840"
  },
  {
    "numero_procedimento": "N/A",
    "entidade": "Centro Tecnológico das Indústrias Têxtil e do Vestuário de Portugal - CITEVE",
    "link": "https://diariodarepublica.pt/dr/detalhe/contrato-publico/891-1011550841",
    "detalhes_completos": "Alteração do Anúncio de procedimento n.º 611/2026, de 2026-01-13, com o ID 419947793\n1 - IDENTIFICAÇÃO E CONTACTOS DA ENTIDADE ADJUDICANTE\nDesignação da entidade adjudicante: Centro Tecnológico das Indústrias Têxtil e do Vestuário de Portugal - CITEVE\nNIPC: 502201886\nServiço/Órgão/Pessoa de contacto: DFRH\nEndereço: Rua Fernando Mesquita, 2785\nCódigo postal: 4760-034\nLocalidade: VN Famalicão\nPaís: Portugal\nNUT III: PT119\nDistrito: Braga\nConcelho: Vila Nova de Famalicão\nFreguesia: União das Freguesias de Antas e Abade de Vermoim\nTelefone: 252300300\nEndereço da Entidade (URL): www.citeve.pt\nEndereço Eletrónico: comprasccp@citeve.pt\neDelivery Gateway (URL): https://www.acingov.pt\nFunção da Organização: Adquirente\nSubfunção da Organização: Organização que recebe as propostas\nNorma jurídica da Entidade Adjudicante: Organismo de direito público\nÁrea de atividade da Autoridade Adjudicante: Serviços públicos das administrações públicas\n2 - JORNAL OFICIAL DA UNIÃO EUROPEIA\nO procedimento a que este anúncio diz respeito também é publicitado no Jornal Oficial da União Europeia? Não\n3 - AVISO\nModelo de Anúncio: Concurso público\nData de Envio do Anúncio: 15-01-2026\n5 - PROCESSO\nTipo de Procedimento: Concurso público\nPreço base do procedimento: Sim\nValor do preço base do procedimento: 210.000,00 EUR\nProcedimento com lotes? Sim\nNº Máx. de Lotes Autorizado: 2\nNúmero máximo de lotes que podem ser adjudicados a um concorrente: 2\n6 - OBJETO DO CONTRATO\nNúmero de referência interna: CPN/01/2026\nDesignação do contrato: Aquisição de Espectrómetros com Plasma Indutivamente Acoplado\nDescrição: Aquisição de Espectrómetros com Plasma Indutivamente Acoplado\nTipo de Contrato Principal: Aquisição de Bens Móveis\nTipo de Contrato: Aquisição de Bens Móveis\nClassificação CPV (Vocabulário Comum para os Contratos Públicos)\nObjeto principal\nVocabulário Principal: 38433000\nPreço base s/IVA: 210.000,00 EUR\nLotes: \nNº: LOT-0001\nDescrição do Lote: ICP-MS\nPreço base s/IVA: 70.000,00 EUR\nClassificação CPV (Vocabulário Comum para os Contratos Públicos)\nObjeto principal\nVocabulário Principal: 38433000\nNº: LOT-0002\nDescrição do Lote: ICP-OES\nPreço base s/IVA: 140.000,00 EUR\nClassificação CPV (Vocabulário Comum para os Contratos Públicos)\nObjeto principal\nVocabulário Principal: 38433000\n7 - INDICAÇÕES ADICIONAIS\nO contrato envolve aquisição conjunta (satisfação de várias entidades)? Não\nO contrato é adjudicado por uma central de compras? Não\n8 - TÉCNICAS\nO concurso destina-se à celebração de um acordo-quadro? Inexistência de acordo-quadro\nÉ utilizado um leilão eletrónico? Não\nÉ adotada uma fase de negociação? Não\nSistema de Aquisição Dinâmico: Inexistência de sistema de aquisição dinâmico\n9 - LOCAL DA EXECUÇÃO DO CONTRATO\nLOCAL DA EXECUÇÃO DO CONTRATO (PROCEDIMENTO)\nPaís: Portugal\nNUT III: PT119\nLocalidade: União das Freguesias de Antas e Abade de Vermoim\nDistrito: Braga\nConcelho: Vila Nova de Famalicão\nFreguesia: União das Freguesias de Antas e Abade de Vermoim\nLOCAL DA EXECUÇÃO DO CONTRATO (LOTE)\nIdentificador do Lote: LOT-0001; LOT-0002\nPaís: Portugal\nNUT III: PT119\nLocalidade: União das Freguesias de Antas e Abade de Vermoim\nDistrito: Braga\nConcelho: Vila Nova de Famalicão\nFreguesia: União das Freguesias de Antas e Abade de Vermoim\n10 - PRAZO DE EXECUÇÃO DO CONTRATO\nIdentificador do Lote: LOT-0001; LOT-0002\nPrazo de execução do contrato: 45 DIAS\nPrevisão de renovações: Não\n11 - FUNDOS EU\nIdentificador do Lote: LOT-0001; LOT-0002\nTêm fundos EU? Sim\n12 - DOCUMENTOS DE HABILITAÇÃO\nHabilitação para o exercício da atividade profissional: Não\n13 - CONDIÇÕES DE APRESENTAÇÃO\nPlataforma eletrónica utilizada pela entidade adjudicante: ACIN\nURL para Apresentação: https://www.acingov.pt\nAdmissibilidade da apresentação de propostas variantes: Não autorizado\nPrazo para apresentação das propostas: 22-01-2026 23:59\nPrazo durante o qual os concorrentes são obrigados a manter as respetivas propostas: 66 dias a contar do termo do prazo para a apresentação das propostas\nIndicação de Subcontratação na Proposta: Inexistência de indicação de subcontratação\n14 - PRESTAÇÃO DE CAUÇÃO\nPrestação de caução: Não\n15 - FORNECIMENTO DAS PEÇAS DO CONCURSO, APRESENTAÇÃO DE PEDIDOS DE PARTICIPAÇÃO E APRESENTAÇÃO DAS PROPOSTAS\nLink para acesso às peças do concurso (URL): https://www.acingov.pt/acingovprod/2/zonaPublica/zona_publica_c/donwloadProcedurePiece/MTA0Nzk0Ng==\n20 - OUTROS REQUISITOS\nIdentificador do Lote: LOT-0001; LOT-0002\nInformação sobre contratos reservados. Aplica-se a contratos reservados (54º-A)? Não\n21 - CRITÉRIO DE ADJUDICAÇÃO\nO Critério de adjudicação é diferenciado por lote? Não\nMultifator: Não\nMonofator:\nNome: Preço\n24 - CONDIÇÕES DO CONTRATO\nIdentificador do Lote: LOT-0001; LOT-0002\nFaturação Eletrónica: Não autorizado\nObrigação de Subcontratação:\nCódigo da Obrigação de Subcontratação: Não é aplicável nenhuma obrigação de subcontratação.\n25 - COMPRA PÚBLICA ESTRATÉGICA\nCompra Pública Estratégica: Inexistência de contratação pública estratégica\n26 - INFORMAÇÕES ADICIONAIS\nIdentificador do Lote: LOT-0001; LOT-0002\nContrato adequado para PME: Sim\nCobertura ACP (Acordo dos Contratos Públicos da Organização Mundial do Comércio): Não\n27 - IDENTIFICAÇÃO E CONTACTOS DO ÓRGÃO DE RECURSOS ADMINISTRATIVOS\nDesignação: Conselho de Administração\nEndereço: Rua Fernando Mesquita, 2785\nCódigo postal: 4760-034\nLocalidade: VN Famalicão\nTelefone: 252300300\nFax: \nEndereço eletrónico: comprasccp@citeve.pt\nPrazo de interposição do recurso: 5 dias\n28 - IDENTIFICAÇÃO DO(S) AUTOR(ES) DE ANÚNCIO\nNome: Raquel Casimiro\nCargo: Diretora Financeira\n29 - ALTERAÇÃO\nMotivo da Alteração: Correção pelo adquirente\nIdentificador da Versão do Anúncio a Alterar: ff15e5bc-e065-4baa-836d-03709a3ae667-01\nIdentificador das Secções Alteradas do Anúncio Anterior: Objeto do contrato; Condições de Apresentação\nDescrição das Alterações: Modificação do prazo para a apresentação de propostas e alteração do preço base dos Lotes do objeto do contrato para: LOT-0001 - ICP-MS, Preço base s/IVA: 140.000,00 EUR; e LOT-0002 - ICP-OES, Preço base s/IVA: 70.000,00 EUR.\nAlteração dos Documentos do Concurso: Sim\nData de alteração dos documentos do concurso: 16-01-2026\n419948113",
    "nipc": "502201886",
    "distrito": "Braga",
    "concelho": "Vila Nova de Famalicão",
    "freguesia": "União das Freguesias de Antas e Abade de Vermoim",
    "site": "www.citeve.pt",
    "email": "comprasccp@citeve.pt",
    "designacao_contrato": "Aquisição de Espectrómetros com Plasma Indutivamente Acoplado",
    "descricao": "Aquisição de Espectrómetros com Plasma Indutivamente Acoplado",
    "preco_base": "210.000,00 EUR",
    "prazo_execucao": "45 DIAS",
    "prazo_apresentacao_propostas": "22-01-2026 23:59",
    "fundos_eu": "Sim",
    "plataforma_eletronica": "ACIN",
    "url_procedimento": "https://www.acingov.pt",
    "autor_nome": "Raquel Casimiro",
    "autor_cargo": "Diretora Financeira"
  },
  {
    "numero_procedimento": "N/A",
    "entidade": "Unidade Local de Saúde do Alto Alentejo, EPE",
    "link": "https://diariodarepublica.pt/dr/detalhe/contrato-publico/893-1011550842",
    "detalhes_completos": "1 - IDENTIFICAÇÃO E CONTACTOS DA ENTIDADE ADJUDICANTE\nDesignação da entidade adjudicante: Unidade Local de Saúde do Alto Alentejo, EPE\nNIPC: 508094461\nEndereço: Av. De Santo António\nCódigo postal: 7300-853\nLocalidade: Portalegre\nPaís: Portugal\nNUT III: PT186\nDistrito: Portalegre\nConcelho: Portalegre\nFreguesia: União das Freguesias da Sé e São Lourenço\nTelefone: 245301000\nFax: 245301002\nEndereço da Entidade (URL): www.hportalegre.min-saude.pt\nEndereço Eletrónico: aprov.portalegre.elvas@ulsna.min-saude.pt\neDelivery Gateway (URL): https://community.vortal.biz/public/\nFunção da Organização: Adquirente\nNorma jurídica da Entidade Adjudicante: Empresa pública\nÁrea de atividade da Entidade Adjudicante: Atividades aeroportuárias\n2 - JORNAL OFICIAL DA UNIÃO EUROPEIA\nO procedimento a que este anúncio diz respeito também é publicitado no Jornal Oficial da União Europeia? Não\n3 - AVISO\nModelo de Anúncio: Concurso público\nData de Envio do Anúncio: 15-01-2026\n5 - PROCESSO\nTipo de Procedimento: Concurso público\nPreço base do procedimento: Sim\nValor do preço base do procedimento: 434.518,18 EUR\nProcedimento com lotes? Não\n6 - OBJETO DO CONTRATO\nNúmero de referência interna: 17108325\nDesignação do contrato: Empreitada para Requalificação do Centro de Saúde de Portalegre da Unidade Local de  Saúde do Alto Alentejo, EPE.”\nDescrição: Empreitada para Requalificação do Centro de Saúde de Portalegre da Unidade Local de \nSaúde do Alto Alentejo, EPE\nTipo de Contrato Principal: Empreitada de Obras Públicas\nTipo de Contrato: Empreitada de Obras Públicas\nClassificação CPV (Vocabulário Comum para os Contratos Públicos)\nObjeto principal\nVocabulário Principal: 45454000\nPreço base s/IVA: 434.518,18 EUR\n7 - INDICAÇÕES ADICIONAIS\nO contrato envolve aquisição conjunta (satisfação de várias entidades)? Não\nO contrato é adjudicado por uma central de compras? Não\n8 - TÉCNICAS\nO concurso destina-se à celebração de um acordo-quadro? Inexistência de acordo-quadro\nÉ utilizado um leilão eletrónico? Não\nÉ adotada uma fase de negociação? Não\nSistema de Aquisição Dinâmico: Inexistência de sistema de aquisição dinâmico\n9 - LOCAL DA EXECUÇÃO DO CONTRATO\nLOCAL DA EXECUÇÃO DO CONTRATO (PROCEDIMENTO)\nPaís: Portugal\nNUT III: PT186\nLocalidade: Portalegre\nDistrito: Portalegre\nConcelho: Portalegre\nFreguesia: Todas\n10 - PRAZO DE EXECUÇÃO DO CONTRATO\nPrazo de execução do contrato: 150 DIAS\nPrevisão de renovações: Não\n11 - FUNDOS EU\nTêm fundos EU? Sim\n12 - DOCUMENTOS DE HABILITAÇÃO\nHabilitação para o exercício da atividade profissional: Sim\nTipo: Alvará\nDescrição: Alvará de obras Publicas\n13 - CONDIÇÕES DE APRESENTAÇÃO\nPlataforma eletrónica utilizada pela entidade adjudicante: VORTAL\nURL para Apresentação: https://community.vortal.biz/public/\nAdmissibilidade da apresentação de propostas variantes: Não autorizado\nPrazo para apresentação das propostas: 30-01-2026 18:00\nPrazo durante o qual os concorrentes são obrigados a manter as respetivas propostas: 180 dias a contar do termo do prazo para a apresentação das propostas\nIndicação de Subcontratação na Proposta: Inexistência de indicação de subcontratação\n14 - PRESTAÇÃO DE CAUÇÃO\nPrestação de caução: Sim\nPercentagem: 5%\nDescrição da Garantia Exigida: Artigo 15.º Valor e modo de prestação de caução e reforço do Programa de Concurso\n15 - FORNECIMENTO DAS PEÇAS DO CONCURSO, APRESENTAÇÃO DE PEDIDOS DE PARTICIPAÇÃO E APRESENTAÇÃO DAS PROPOSTAS\nLink para acesso às peças do concurso (URL): https://community.vortal.biz/Public/public-tender-documents/T25zbGtTQWhIMTEvQkJvZFQ4K3U0dndZZlhnOG4vZkVUT0o5NW9PNXhRaDUzUFNPV0JNZGtPaWw4dk1ubVNmd3VreWtObWJTeVpjSkJEeENrNms3Nmc9PWJNNnEl\n20 - OUTROS REQUISITOS\nInformação sobre contratos reservados. Aplica-se a contratos reservados (54º-A)? Não\n21 - CRITÉRIO DE ADJUDICAÇÃO\nMultifator: Sim\nFator: \nNome: Preço\nPonderação: 70%\nSubfatores: Não\nFator: \nNome: Qualidade\nPonderação: 30%\nSubfatores: Não\n24 - CONDIÇÕES DO CONTRATO\nFaturação Eletrónica: Permitido\nObrigação de Subcontratação:\nCódigo da Obrigação de Subcontratação: Não é aplicável nenhuma obrigação de subcontratação.\n25 - COMPRA PÚBLICA ESTRATÉGICA\nCompra Pública Estratégica: Redução dos impactos ambientais\nDescrição do Processo de Adjudicação Estratégico: Conforme as peças do procedimento\nCritérios de contratos Públicos Ecológicos: Critérios de contratação pública ecológica nacional\nCategorias da estratégia nacional: Conceção, construção e gestão de edifícios de escritórios\nDiretiva Veículos Não Poluentes: Não\nCritério de Acessibilidade: Os critérios de acessibilidade para as pessoas com deficiência não estão incluídos porque o contrato não se destina a pessoas singulares\n26 - INFORMAÇÕES ADICIONAIS\nContrato adequado para PME: Sim\nCobertura ACP (Acordo dos Contratos Públicos da Organização Mundial do Comércio): Não\n27 - IDENTIFICAÇÃO E CONTACTOS DO ÓRGÃO DE RECURSOS ADMINISTRATIVOS\nDesignação: Conselho de Administração\nEndereço: AVENIDA DE SANTO ANTONIO\nCódigo postal: 7300-853\nLocalidade: Portalegre\nTelefone: +351 245301000\nFax: +351 245330359\nEndereço eletrónico: admin@ulsaale.min-saude.pt\n28 - IDENTIFICAÇÃO DO(S) AUTOR(ES) DE ANÚNCIO\nNome: José Miguel da Costa Lopes\nCargo: Presidente do Conselho de Administração\n419948090",
    "nipc": "508094461",
    "distrito": "Portalegre",
    "concelho": "Portalegre",
    "freguesia": "União das Freguesias da Sé e São Lourenço",
    "site": "www.hportalegre.min-saude.pt",
    "email": "aprov.portalegre.elvas@ulsna.min-saude.pt",
    "designacao_contrato": "Empreitada para Requalificação do Centro de Saúde de Portalegre da Unidade Local de Saúde do Alto Alentejo, EPE.”",
    "descricao": "Empreitada para Requalificação do Centro de Saúde de Portalegre da Unidade Local de",
    "preco_base": "434.518,18 EUR",
    "prazo_execucao": "150 DIAS",
    "prazo_apresentacao_propostas": "30-01-2026 18:00",
    "fundos_eu": "Sim",
    "plataforma_eletronica": "VORTAL",
    "url_procedimento": "https://community.vortal.biz/public/",
    "autor_nome": "José Miguel da Costa Lopes",
    "autor_cargo": "Presidente do Conselho de Administração"
  },
  {
    "numero_procedimento": "N/A",
    "entidade": "Unidade Local de Saúde do Alto Alentejo, EPE",
    "link": "https://diariodarepublica.pt/dr/detalhe/contrato-publico/894-1011550843",
    "detalhes_completos": "1 - IDENTIFICAÇÃO E CONTACTOS DA ENTIDADE ADJUDICANTE\nDesignação da entidade adjudicante: Unidade Local de Saúde do Alto Alentejo, EPE\nNIPC: 508094461\nEndereço: Av. De Santo António\nCódigo postal: 7300-853\nLocalidade: Portalegre\nPaís: Portugal\nNUT III: PT186\nDistrito: Portalegre\nConcelho: Portalegre\nFreguesia: União das Freguesias da Sé e São Lourenço\nTelefone: 245301000\nFax: 245301002\nEndereço da Entidade (URL): www.hportalegre.min-saude.pt\nEndereço Eletrónico: aprov.portalegre.elvas@ulsna.min-saude.pt\neDelivery Gateway (URL): https://community.vortal.biz/public/\nFunção da Organização: Adquirente\nNorma jurídica da Entidade Adjudicante: Empresa pública\nÁrea de atividade da Entidade Adjudicante: Atividades aeroportuárias\n2 - JORNAL OFICIAL DA UNIÃO EUROPEIA\nO procedimento a que este anúncio diz respeito também é publicitado no Jornal Oficial da União Europeia? Não\n3 - AVISO\nModelo de Anúncio: Concurso público\nData de Envio do Anúncio: 15-01-2026\n5 - PROCESSO\nTipo de Procedimento: Concurso público\nPreço base do procedimento: Sim\nValor do preço base do procedimento: 612.157,27 EUR\nProcedimento com lotes? Não\n6 - OBJETO DO CONTRATO\nNúmero de referência interna: 17107825\nDesignação do contrato: Empreitada para Requalificação do Centro de Saúde de Elvas da Unidade Local de Saúde do Alto Alentejo, EPE\nDescrição: Empreitada para Requalificação do Centro de Saúde de Elvas da Unidade Local de Saúde do Alto Alentejo, EPE\nTipo de Contrato Principal: Empreitada de Obras Públicas\nTipo de Contrato: Empreitada de Obras Públicas\nClassificação CPV (Vocabulário Comum para os Contratos Públicos)\nObjeto principal\nVocabulário Principal: 45454000\nPreço base s/IVA: 612.157,27 EUR\n7 - INDICAÇÕES ADICIONAIS\nO contrato envolve aquisição conjunta (satisfação de várias entidades)? Não\nO contrato é adjudicado por uma central de compras? Não\n8 - TÉCNICAS\nO concurso destina-se à celebração de um acordo-quadro? Inexistência de acordo-quadro\nÉ utilizado um leilão eletrónico? Não\nÉ adotada uma fase de negociação? Não\nSistema de Aquisição Dinâmico: Inexistência de sistema de aquisição dinâmico\n9 - LOCAL DA EXECUÇÃO DO CONTRATO\nLOCAL DA EXECUÇÃO DO CONTRATO (PROCEDIMENTO)\nPaís: Portugal\nNUT III: PT186\nLocalidade: Portalegre\nDistrito: Portalegre\nConcelho: Elvas\nFreguesia: Todas\n10 - PRAZO DE EXECUÇÃO DO CONTRATO\nPrazo de execução do contrato: 150 DIAS\nPrevisão de renovações: Não\n11 - FUNDOS EU\nTêm fundos EU? Sim\n12 - DOCUMENTOS DE HABILITAÇÃO\nHabilitação para o exercício da atividade profissional: Sim\nTipo: Alvará\nDescrição: Alvará de obras publicas\n13 - CONDIÇÕES DE APRESENTAÇÃO\nPlataforma eletrónica utilizada pela entidade adjudicante: VORTAL\nURL para Apresentação: https://community.vortal.biz/public/\nAdmissibilidade da apresentação de propostas variantes: Não autorizado\nPrazo para apresentação das propostas: 30-01-2026 18:00\nPrazo durante o qual os concorrentes são obrigados a manter as respetivas propostas: 180 dias a contar do termo do prazo para a apresentação das propostas\nIndicação de Subcontratação na Proposta: Inexistência de indicação de subcontratação\n14 - PRESTAÇÃO DE CAUÇÃO\nPrestação de caução: Sim\nPercentagem: 5%\nDescrição da Garantia Exigida: Artigo 15.º Valor e modo de prestação de caução e reforço do Programa de Conscurso\n15 - FORNECIMENTO DAS PEÇAS DO CONCURSO, APRESENTAÇÃO DE PEDIDOS DE PARTICIPAÇÃO E APRESENTAÇÃO DAS PROPOSTAS\nLink para acesso às peças do concurso (URL): https://community.vortal.biz/Public/public-tender-documents/RHl2YXhjMXkwV2k0WnczRkNsd3BFckNzZlBIUk0vekUzSjU3VjNhY1dKQU52UUlTU25iRVF1Y3VDREVrZEl6Q1ZBNUN5b2JMcGIxWjNLa0MvUUhEVmc9PXQwNDBx\n20 - OUTROS REQUISITOS\nInformação sobre contratos reservados. Aplica-se a contratos reservados (54º-A)? Não\n21 - CRITÉRIO DE ADJUDICAÇÃO\nMultifator: Sim\nFator: \nNome: Preço\nPonderação: 70%\nSubfatores: Não\nFator: \nNome: Qualidade\nPonderação: 30%\nSubfatores: Não\n24 - CONDIÇÕES DO CONTRATO\nFaturação Eletrónica: Permitido\nObrigação de Subcontratação:\nCódigo da Obrigação de Subcontratação: Não é aplicável nenhuma obrigação de subcontratação.\n25 - COMPRA PÚBLICA ESTRATÉGICA\nCompra Pública Estratégica: Redução dos impactos ambientais\nDescrição do Processo de Adjudicação Estratégico: Conforme as peças do procedimento\nCritérios de contratos Públicos Ecológicos: Critérios de contratação pública ecológica nacional\nCategorias da estratégia nacional: Conceção, construção e gestão de edifícios de escritórios\nDiretiva Veículos Não Poluentes: Não\nCritério de Acessibilidade: Os critérios de acessibilidade para as pessoas com deficiência não estão incluídos porque o contrato não se destina a pessoas singulares\n26 - INFORMAÇÕES ADICIONAIS\nContrato adequado para PME: Sim\nCobertura ACP (Acordo dos Contratos Públicos da Organização Mundial do Comércio): Não\n27 - IDENTIFICAÇÃO E CONTACTOS DO ÓRGÃO DE RECURSOS ADMINISTRATIVOS\nDesignação: Conselho de Administração\nEndereço: AVENIDA DE SANTO ANTONIO\nCódigo postal: 7300-853\nLocalidade: Portalegre\nTelefone: +351 245301000\nFax: +351 245330359\nEndereço eletrónico: admin@ulsaale.min-saude.pt\n28 - IDENTIFICAÇÃO DO(S) AUTOR(ES) DE ANÚNCIO\nNome: José Miguel da Costa Lopes\nCargo: Presidente do Conselho de Administração\n419948096",
    "nipc": "508094461",
    "distrito": "Portalegre",
    "concelho": "Portalegre",
    "freguesia": "União das Freguesias da Sé e São Lourenço",
    "site": "www.hportalegre.min-saude.pt",
    "email": "aprov.portalegre.elvas@ulsna.min-saude.pt",
    "designacao_contrato": "Empreitada para Requalificação do Centro de Saúde de Elvas da Unidade Local de Saúde do Alto Alentejo, EPE",
    "descricao": "Empreitada para Requalificação do Centro de Saúde de Elvas da Unidade Local de Saúde do Alto Alentejo, EPE",
    "preco_base": "612.157,27 EUR",
    "prazo_execucao": "150 DIAS",
    "prazo_apresentacao_propostas": "30-01-2026 18:00",
    "fundos_eu": "Sim",
    "plataforma_eletronica": "VORTAL",
    "url_procedimento": "https://community.vortal.biz/public/",
    "autor_nome": "José Miguel da Costa Lopes",
    "autor_cargo": "Presidente do Conselho de Administração"
  },
  {
    "numero_procedimento": "N/A",
    "entidade": "AnÃºncio de procedimento  n.Âº 896/2026  -  DiÃ¡rio da RepÃºblica n.Âº 11/2026, SÃ©rie II de 2026-01-16",
    "link": "https://diariodarepublica.pt/dr/detalhe/contrato-publico/896-1011550854"
  },
  {
    "numero_procedimento": "N/A",
    "entidade": "Instituto Nacional de Saúde Doutor Ricardo Jorge, IP",
    "link": "https://diariodarepublica.pt/dr/detalhe/contrato-publico/899-1011550855",
    "detalhes_completos": "1 - IDENTIFICAÇÃO E CONTACTOS DA ENTIDADE ADJUDICANTE\nDesignação da entidade adjudicante: Instituto Nacional de Saúde Doutor Ricardo Jorge, IP\nNIPC: 501427511\nEndereço: Avenida Padre Cruz\nCódigo postal: 1649-016\nLocalidade: LISBOA\nPaís: Portugal\nNUT III: PTZZZ\nDistrito: Todos\nConcelho: Todos\nFreguesia: Todas\nTelefone: 217319200\nEndereço da Entidade (URL): https://www.insa.pt/\nEndereço Eletrónico: drf.aprov@insa.min-saude.pt\neDelivery Gateway (URL): https://www.acingov.pt\nFunção da Organização: Adquirente\nNorma jurídica da Entidade Adjudicante: Organismo de direito público\nÁrea de atividade da Autoridade Adjudicante: Serviços públicos das administrações públicas\n2 - JORNAL OFICIAL DA UNIÃO EUROPEIA\nO procedimento a que este anúncio diz respeito também é publicitado no Jornal Oficial da União Europeia? Não\n3 - AVISO\nModelo de Anúncio: Concurso público\nData de Envio do Anúncio: 15-01-2026\n5 - PROCESSO\nTipo de Procedimento: Concurso público\nPreço base do procedimento: Sim\nValor do preço base do procedimento: 1.150.250,00 EUR\nProcedimento com lotes? Não\n6 - OBJETO DO CONTRATO\nNúmero de referência interna: CP 03-2026\nDesignação do contrato: CP 03-2026 Empreitada para remodelação da rede de abastecimento de água e execução das medidas de autoproteção, no âmbito da segurança contra riscos de incêndios da sede do INSA\nDescrição: CP 03-2026 Empreitada para remodelação da rede de abastecimento de água e execução das medidas de autoproteção, no âmbito da segurança contra riscos de incêndios da sede do INSA\nTipo de Contrato Principal: Empreitada de Obras Públicas\nTipo de Contrato: Empreitada de Obras Públicas\nClassificação CPV (Vocabulário Comum para os Contratos Públicos)\nObjeto principal\nVocabulário Principal: 45454000\nPreço base s/IVA: 1.150.250,00 EUR\n7 - INDICAÇÕES ADICIONAIS\nO contrato envolve aquisição conjunta (satisfação de várias entidades)? Não\nO contrato é adjudicado por uma central de compras? Não\n8 - TÉCNICAS\nO concurso destina-se à celebração de um acordo-quadro? Inexistência de acordo-quadro\nÉ utilizado um leilão eletrónico? Não\nÉ adotada uma fase de negociação? Não\nSistema de Aquisição Dinâmico: Inexistência de sistema de aquisição dinâmico\n9 - LOCAL DA EXECUÇÃO DO CONTRATO\nLOCAL DA EXECUÇÃO DO CONTRATO (PROCEDIMENTO)\nPaís: Portugal\nNUT III: PT170\nLocalidade: Freguesia de Lumiar\nDistrito: Lisboa\nConcelho: Lisboa\nFreguesia: Freguesia de Lumiar\n10 - PRAZO DE EXECUÇÃO DO CONTRATO\nPrazo de execução do contrato: 270 DIAS\nPrevisão de renovações: Não\n11 - FUNDOS EU\nTêm fundos EU? Não\n12 - DOCUMENTOS DE HABILITAÇÃO\nHabilitação para o exercício da atividade profissional: Sim\nTipo: Alvará\nDescrição: 8.ª Subcategoria da 1ªCategoria  Canalizações e condutas em edifícios\n4.ª Subcategoria da 1ª Categoria  Alvenarias, rebocos e assentamento de cantarias\n5.ª Subcategoria da 1ª Categoria Estuques, pinturas e outros revestimentos\n7.ª Subcategoria da 1ª Categoria  Trabalhos em perfis não estruturais\n2.ª Subcategoria da 1ª Categoria Estruturas metálicas\n12.ªSubcategoria da 4ª Categoria  Aquecimento, ventilação, ar condicionado e refrigeração\n10.ª Subcategoria da 4ª Categoria  Sistemas de extinção de incêndios, de segurança e de deteção\n14.ª Subcategoria da 4ª Categoria  Redes e ramais de distribuição de gás, instalações e aparelhos a gás.\n1.ª Subcategoria da 4ª Categoria  Instalações elétricas de utilização de baixa tensão com potência até 50 kVA\n13 - CONDIÇÕES DE APRESENTAÇÃO\nPlataforma eletrónica utilizada pela entidade adjudicante: ACIN\nURL para Apresentação: https://www.acingov.pt\nAdmissibilidade da apresentação de propostas variantes: Não autorizado\nPrazo para apresentação das propostas: 30-01-2026 23:59\nPrazo durante o qual os concorrentes são obrigados a manter as respetivas propostas: 66 dias a contar do termo do prazo para a apresentação das propostas\nIndicação de Subcontratação na Proposta: Inexistência de indicação de subcontratação\n14 - PRESTAÇÃO DE CAUÇÃO\nPrestação de caução: Sim\nPercentagem: 5%\nDescrição da Garantia Exigida: O valor da caução é de 5.00% do preço contratual.\n15 - FORNECIMENTO DAS PEÇAS DO CONCURSO, APRESENTAÇÃO DE PEDIDOS DE PARTICIPAÇÃO E APRESENTAÇÃO DAS PROPOSTAS\nLink para acesso às peças do concurso (URL): https://www.acingov.pt/acingovprod/2/zonaPublica/zona_publica_c/donwloadProcedurePiece/MTA0ODYxMQ==\n20 - OUTROS REQUISITOS\nInformação sobre contratos reservados. Aplica-se a contratos reservados (54º-A)? Não\n21 - CRITÉRIO DE ADJUDICAÇÃO\nMultifator: Sim\nFator: \nNome: Preço\nPonderação: 70%\nSubfatores: Não\nFator: \nNome: Outros\nOutro Nome: Garantia do TUBO INOX 316L (FG)\nPonderação: 30%\nSubfatores: Não\n24 - CONDIÇÕES DO CONTRATO\nFaturação Eletrónica: Permitido\nObrigação de Subcontratação:\nCódigo da Obrigação de Subcontratação: Não é aplicável nenhuma obrigação de subcontratação.\n25 - COMPRA PÚBLICA ESTRATÉGICA\nCompra Pública Estratégica: Inexistência de contratação pública estratégica\n26 - INFORMAÇÕES ADICIONAIS\nContrato adequado para PME: Não\nCobertura ACP (Acordo dos Contratos Públicos da Organização Mundial do Comércio): Não\n27 - IDENTIFICAÇÃO E CONTACTOS DO ÓRGÃO DE RECURSOS ADMINISTRATIVOS\nDesignação: O Conselho Diretivo\nEndereço: Av. Padre Cruz\nCódigo postal: 1649-016\nLocalidade: Lisboa\nTelefone: 217519200\nFax: 217519390\nEndereço eletrónico: drf.aprov@insa.min-saude.pt\nPrazo de interposição do recurso: 5 dias\n28 - IDENTIFICAÇÃO DO(S) AUTOR(ES) DE ANÚNCIO\nNome: Fernando de Almeida\nCargo: Presidente do Conselho Diretivo\n419948129",
    "nipc": "501427511",
    "distrito": "Todos",
    "concelho": "Todos",
    "freguesia": "Todas",
    "site": "https://www.insa.pt/",
    "email": "drf.aprov@insa.min-saude.pt",
    "designacao_contrato": "CP 03-2026 Empreitada para remodelação da rede de abastecimento de água e execução das medidas de autoproteção, no âmbito da segurança contra riscos de incêndios da sede do INSA",
    "descricao": "CP 03-2026 Empreitada para remodelação da rede de abastecimento de água e execução das medidas de autoproteção, no âmbito da segurança contra riscos de incêndios da sede do INSA",
    "preco_base": "1.150.250,00 EUR",
    "prazo_execucao": "270 DIAS",
    "prazo_apresentacao_propostas": "30-01-2026 23:59",
    "fundos_eu": "Não",
    "plataforma_eletronica": "ACIN",
    "url_procedimento": "https://www.acingov.pt",
    "autor_nome": "Fernando de Almeida",
    "autor_cargo": "Presidente do Conselho Diretivo"
  },
  {
    "numero_procedimento": "N/A",
    "entidade": "AnÃºncio de procedimento  n.Âº 900/2026  -  DiÃ¡rio da RepÃºblica n.Âº 11/2026, SÃ©rie II de 2026-01-16",
    "link": "https://diariodarepublica.pt/dr/detalhe/contrato-publico/900-1011550856"
  },
  {
    "numero_procedimento": "N/A",
    "entidade": "AnÃºncio de procedimento  n.Âº 887/2026  -  DiÃ¡rio da RepÃºblica n.Âº 11/2026, SÃ©rie II de 2026-01-16",
    "link": "https://diariodarepublica.pt/dr/detalhe/contrato-publico/887-1011718082"
  },
  {
    "numero_procedimento": "N/A",
    "entidade": "AnÃºncio de procedimento  n.Âº 888/2026  -  DiÃ¡rio da RepÃºblica n.Âº 11/2026, SÃ©rie II de 2026-01-16",
    "link": "https://diariodarepublica.pt/dr/detalhe/contrato-publico/888-1011718083"
  },
  {
    "numero_procedimento": "N/A",
    "entidade": "AnÃºncio de procedimento  n.Âº 890/2026  -  DiÃ¡rio da RepÃºblica n.Âº 11/2026, SÃ©rie II de 2026-01-16",
    "link": "https://diariodarepublica.pt/dr/detalhe/contrato-publico/890-1011718086"
  },
  {
    "numero_procedimento": "N/A",
    "entidade": "AnÃºncio de procedimento  n.Âº 892/2026  -  DiÃ¡rio da RepÃºblica n.Âº 11/2026, SÃ©rie II de 2026-01-16",
    "link": "https://diariodarepublica.pt/dr/detalhe/contrato-publico/892-1011718090"
  },
  {
    "numero_procedimento": "N/A",
    "entidade": "AnÃºncio de procedimento  n.Âº 895/2026  -  DiÃ¡rio da RepÃºblica n.Âº 11/2026, SÃ©rie II de 2026-01-16",
    "link": "https://diariodarepublica.pt/dr/detalhe/contrato-publico/895-1011718092"
  },
  {
    "numero_procedimento": "N/A",
    "entidade": "Município de Mafra",
    "link": "https://diariodarepublica.pt/dr/detalhe/contrato-publico/897-1011718093",
    "detalhes_completos": "1 - IDENTIFICAÇÃO E CONTACTOS DA ENTIDADE ADJUDICANTE\nDesignação da entidade adjudicante: Município de Mafra\nNIPC: 502177080\nEndereço: Praça do Município\nCódigo postal: 2644-001\nLocalidade: Mafra\nPaís: Portugal\nNUT III: PT170\nDistrito: Lisboa\nConcelho: Mafra\nFreguesia: Freguesia de Mafra\nTelefone: 261810143\nFax: 261810144\nEndereço da Entidade (URL): www.cm-mafra.pt\nEndereço Eletrónico: concursosccp@cm-mafra.pt\nFunção da Organização: Adquirente\nNorma jurídica da Entidade Adjudicante: Autoridade local\nÁrea de atividade da Entidade Adjudicante: Atividades aeroportuárias\n2 - JORNAL OFICIAL DA UNIÃO EUROPEIA\nO procedimento a que este anúncio diz respeito também é publicitado no Jornal Oficial da União Europeia? Não\n3 - AVISO\nModelo de Anúncio: Concurso público\nData de Envio do Anúncio: 15-01-2026\n5 - PROCESSO\nTipo de Procedimento: Concurso público\nPreço base do procedimento: Não\nProcedimento com lotes? Não\n6 - OBJETO DO CONTRATO\nNúmero de referência interna: CPBS 1/2026\nDesignação do contrato: Fornecimento de 140.000 litros de gasóleo simples a granel, para o ano 2026\nDescrição: Fornecimento de 140.000 litros de gasóleo simples a granel, para o ano 2026\nTipo de Contrato Principal: Aquisição de Bens Móveis\nTipo de Contrato: Aquisição de Bens Móveis\nClassificação CPV (Vocabulário Comum para os Contratos Públicos)\nObjeto principal\nVocabulário Principal: 09134100\n7 - INDICAÇÕES ADICIONAIS\nO contrato envolve aquisição conjunta (satisfação de várias entidades)? Não\nO contrato é adjudicado por uma central de compras? Não\n8 - TÉCNICAS\nO concurso destina-se à celebração de um acordo-quadro? Inexistência de acordo-quadro\nÉ utilizado um leilão eletrónico? Não\nÉ adotada uma fase de negociação? Sim\nSistema de Aquisição Dinâmico: Inexistência de sistema de aquisição dinâmico\n9 - LOCAL DA EXECUÇÃO DO CONTRATO\nLOCAL DA EXECUÇÃO DO CONTRATO (PROCEDIMENTO)\nPaís: Portugal\nNUT III: PT170\nLocalidade: Mafra\nDistrito: Lisboa\nConcelho: Mafra\nFreguesia: Freguesia de Mafra\n10 - PRAZO DE EXECUÇÃO DO CONTRATO\nData de Início: 16-02-2026\nData de Fim: 31-12-2026\nPrevisão de renovações: Não\n11 - FUNDOS EU\nTêm fundos EU? Não\n12 - DOCUMENTOS DE HABILITAÇÃO\nHabilitação para o exercício da atividade profissional: Não\n13 - CONDIÇÕES DE APRESENTAÇÃO\nPlataforma eletrónica utilizada pela entidade adjudicante: ANOGOV\nURL para Apresentação: https://www.anogov.com/cm-mafra/faces/\nAdmissibilidade da apresentação de propostas variantes: Não autorizado\nPrazo para apresentação das propostas: 21-01-2026 17:00\nPrazo durante o qual os concorrentes são obrigados a manter as respetivas propostas: 66 dias a contar do termo do prazo para a apresentação das propostas\nApresentação de Catálogo Eletrónico: Permitido\nIndicação de Subcontratação na Proposta: Inexistência de indicação de subcontratação\n14 - PRESTAÇÃO DE CAUÇÃO\nPrestação de caução: Não\n15 - FORNECIMENTO DAS PEÇAS DO CONCURSO, APRESENTAÇÃO DE PEDIDOS DE PARTICIPAÇÃO E APRESENTAÇÃO DAS PROPOSTAS\nLink para acesso às peças do concurso (URL): https://www.anogov.com/cm-mafra/faces/app/acessoDocs.jsp?codigoAcesso=DOrOSKEOcMTCchhj2NCZZppZx42ieMiVcmKeTzknGRIq2FKbWa\n20 - OUTROS REQUISITOS\nInformação sobre contratos reservados. Aplica-se a contratos reservados (54º-A)? Não\n21 - CRITÉRIO DE ADJUDICAÇÃO\nMultifator: Sim\nFator: \nNome: Outros\nOutro Nome: Prazo para instalação de equipamento de armazenamento e abastecimento de gasóleo\nPonderação: 20%\nSubfatores: Não\nFator: \nNome: Outros\nOutro Nome: Desconto sobre o preço unitário (litro)\nPonderação: 80%\nSubfatores: Não\n24 - CONDIÇÕES DO CONTRATO\nFaturação Eletrónica: Necessário\nObrigação de Subcontratação:\nCódigo da Obrigação de Subcontratação: Não é aplicável nenhuma obrigação de subcontratação.\n25 - COMPRA PÚBLICA ESTRATÉGICA\nCompra Pública Estratégica: Inexistência de contratação pública estratégica\n26 - INFORMAÇÕES ADICIONAIS\nContrato adequado para PME: Sim\nCobertura ACP (Acordo dos Contratos Públicos da Organização Mundial do Comércio): Não\n27 - IDENTIFICAÇÃO E CONTACTOS DO ÓRGÃO DE RECURSOS ADMINISTRATIVOS\nDesignação: Município de Mafra\nEndereço: Praça do Município\nCódigo postal: 2644-001\nLocalidade: Mafra\nEndereço eletrónico: concursosccp@cm-mafra.pt\n28 - IDENTIFICAÇÃO DO(S) AUTOR(ES) DE ANÚNCIO\nNome: Presidente\nCargo: Presidente\n419948114",
    "nipc": "502177080",
    "distrito": "Lisboa",
    "concelho": "Mafra",
    "freguesia": "Freguesia de Mafra",
    "site": "www.cm-mafra.pt",
    "email": "concursosccp@cm-mafra.pt",
    "designacao_contrato": "Fornecimento de 140.000 litros de gasóleo simples a granel, para o ano 2026",
    "descricao": "Fornecimento de 140.000 litros de gasóleo simples a granel, para o ano 2026",
    "preco_base": null,
    "prazo_execucao": null,
    "prazo_apresentacao_propostas": "21-01-2026 17:00",
    "fundos_eu": "Não",
    "plataforma_eletronica": "ANOGOV",
    "url_procedimento": "https://www.anogov.com/cm-mafra/faces/",
    "autor_nome": "Presidente",
    "autor_cargo": "Presidente"
  },
  {
    "numero_procedimento": "N/A",
    "entidade": "Polícia Judiciária",
    "link": "https://diariodarepublica.pt/dr/detalhe/contrato-publico/898-1011718094",
    "detalhes_completos": "1 - IDENTIFICAÇÃO E CONTACTOS DA ENTIDADE ADJUDICANTE\nDesignação da entidade adjudicante: Polícia Judiciária\nNIPC: 600011712\nEndereço: RUA GOMES FREIRE 174\nCódigo postal: 1169-007\nLocalidade: Lisboa\nPaís: Portugal\nNUT III: PT170\nDistrito: Lisboa\nConcelho: Lisboa\nFreguesia: Todas\nTelefone: 218641000\nFax: 213570147\nEndereço da Entidade (URL): www.pj.pt\nEndereço Eletrónico: aprovisionamento@pj.pt\neDelivery Gateway (URL): https://community.vortal.biz/public/\nFunção da Organização: Adquirente\nNorma jurídica da Entidade Adjudicante: Autoridade da administração central\nÁrea de atividade da Autoridade Adjudicante: Segurança e ordem pública\n2 - JORNAL OFICIAL DA UNIÃO EUROPEIA\nO procedimento a que este anúncio diz respeito também é publicitado no Jornal Oficial da União Europeia? Não\n3 - AVISO\nModelo de Anúncio: Concurso público\nData de Envio do Anúncio: 15-01-2026\n5 - PROCESSO\nTipo de Procedimento: Concurso público\nPreço base do procedimento: Sim\nValor do preço base do procedimento: 140.000,00 EUR\nProcedimento com lotes? Não\n6 - OBJETO DO CONTRATO\nNúmero de referência interna: PN/873/2025\nDesignação do contrato: PN/873/2025\nDescrição: Serviços de Manutenção e conservação dos espaços verdes da PJ - Lisboa, Tires e IPJCC\nTipo de Contrato Principal: Aquisição de Serviços\nTipo de Contrato: Aquisição de Serviços\nClassificação CPV (Vocabulário Comum para os Contratos Públicos)\nObjeto principal\nVocabulário Principal: 98300000\nPreço base s/IVA: 140.000,00 EUR\n7 - INDICAÇÕES ADICIONAIS\nO contrato envolve aquisição conjunta (satisfação de várias entidades)? Não\nO contrato é adjudicado por uma central de compras? Não\n8 - TÉCNICAS\nO concurso destina-se à celebração de um acordo-quadro? Inexistência de acordo-quadro\nÉ utilizado um leilão eletrónico? Não\nÉ adotada uma fase de negociação? Não\nSistema de Aquisição Dinâmico: Inexistência de sistema de aquisição dinâmico\n9 - LOCAL DA EXECUÇÃO DO CONTRATO\nLOCAL DA EXECUÇÃO DO CONTRATO (PROCEDIMENTO)\nPaís: Portugal\nNUT III: PT170\nLocalidade: Lisboa\nDistrito: Lisboa\nConcelho: Lisboa\nFreguesia: Freguesia de Arroios - Lisboa\n10 - PRAZO DE EXECUÇÃO DO CONTRATO\nPrazo de execução do contrato: 18 MESES\nPrevisão de renovações: Não\n11 - FUNDOS EU\nTêm fundos EU? Não\n12 - DOCUMENTOS DE HABILITAÇÃO\nHabilitação para o exercício da atividade profissional: Não\n13 - CONDIÇÕES DE APRESENTAÇÃO\nPlataforma eletrónica utilizada pela entidade adjudicante: VORTAL\nURL para Apresentação: https://community.vortal.biz/public/\nAdmissibilidade da apresentação de propostas variantes: Não autorizado\nPrazo para apresentação das propostas: 23-01-2026 23:59\nPrazo durante o qual os concorrentes são obrigados a manter as respetivas propostas: 66 dias a contar do termo do prazo para a apresentação das propostas\nIndicação de Subcontratação na Proposta: Inexistência de indicação de subcontratação\n14 - PRESTAÇÃO DE CAUÇÃO\nPrestação de caução: Não\n15 - FORNECIMENTO DAS PEÇAS DO CONCURSO, APRESENTAÇÃO DE PEDIDOS DE PARTICIPAÇÃO E APRESENTAÇÃO DAS PROPOSTAS\nLink para acesso às peças do concurso (URL): https://community.vortal.biz/Public/public-tender-documents/TmlFdkIxK3BvNktGVXNwMzhZRXZxejRHUlVsa2xzejROZENYM0V4R2wzUzlZU1pZQWNhTXRqZFRvL080M3dZS3p0KzdkeGMreFJndk5hL01IbTE5aUE9PXExRzAm\n20 - OUTROS REQUISITOS\nInformação sobre contratos reservados. Aplica-se a contratos reservados (54º-A)? Não\n21 - CRITÉRIO DE ADJUDICAÇÃO\nMultifator: Não\nMonofator:\nNome: Preço\n24 - CONDIÇÕES DO CONTRATO\nFaturação Eletrónica: Permitido\nObrigação de Subcontratação:\nCódigo da Obrigação de Subcontratação: Não é aplicável nenhuma obrigação de subcontratação.\n25 - COMPRA PÚBLICA ESTRATÉGICA\nCompra Pública Estratégica: Inexistência de contratação pública estratégica\n26 - INFORMAÇÕES ADICIONAIS\nContrato adequado para PME: Sim\nCobertura ACP (Acordo dos Contratos Públicos da Organização Mundial do Comércio): Não\n27 - IDENTIFICAÇÃO E CONTACTOS DO ÓRGÃO DE RECURSOS ADMINISTRATIVOS\nDesignação: Ministério da Justiça\nEndereço: Rua do Ouro, n.º 6\nCódigo postal: 1149-019\nLocalidade: Lisboa\nTelefone: +351 213222300\nFax: +351 213506015\nEndereço eletrónico: correio@sg.mj.pt\n28 - IDENTIFICAÇÃO DO(S) AUTOR(ES) DE ANÚNCIO\nNome: Sandra Dionísio\nCargo: Chefe de Setor\n419947364",
    "nipc": "600011712",
    "distrito": "Lisboa",
    "concelho": "Lisboa",
    "freguesia": "Todas",
    "site": "www.pj.pt",
    "email": "aprovisionamento@pj.pt",
    "designacao_contrato": "PN/873/2025",
    "descricao": "Serviços de Manutenção e conservação dos espaços verdes da PJ - Lisboa, Tires e IPJCC",
    "preco_base": "140.000,00 EUR",
    "prazo_execucao": "18 MESES",
    "prazo_apresentacao_propostas": "23-01-2026 23:59",
    "fundos_eu": "Não",
    "plataforma_eletronica": "VORTAL",
    "url_procedimento": "https://community.vortal.biz/public/",
    "autor_nome": "Sandra Dionísio",
    "autor_cargo": "Chefe de Setor"
  },
  {
    "numero_procedimento": "N/A",
    "entidade": "Município de Portimão",
    "link": "https://diariodarepublica.pt/dr/detalhe/contrato-publico/902-1011853868",
    "detalhes_completos": "Alteração do Anúncio de procedimento n.º 480/2026, de 2026-01-12, com o ID 419947392\n1 - IDENTIFICAÇÃO E CONTACTOS DA ENTIDADE ADJUDICANTE\nDesignação da entidade adjudicante: Município de Portimão\nNIPC: 505309939\nServiço/Órgão/Pessoa de contacto: Divisão de Compras\nEndereço: Praça 1.º de maio\nCódigo postal: 8500-543\nLocalidade: Portimão\nPaís: Portugal\nNUT III: PT150\nDistrito: Faro\nConcelho: Portimão\nFreguesia: Freguesia de Portimão\nTelefone: 282470700\nFax: 282470792\nEndereço da Entidade (URL): www.cm-portimao.pt\nEndereço Eletrónico: geral@cm-portimao.pt\neDelivery Gateway (URL): https://www.acingov.pt\nFunção da Organização: Adquirente\nNorma jurídica da Entidade Adjudicante: Organismo de direito público\nÁrea de atividade da Autoridade Adjudicante: Serviços públicos das administrações públicas\n2 - JORNAL OFICIAL DA UNIÃO EUROPEIA\nO procedimento a que este anúncio diz respeito também é publicitado no Jornal Oficial da União Europeia? Sim\n3 - AVISO\nModelo de Anúncio: Concurso público\nData de Envio do Anúncio: 14-01-2026\n5 - PROCESSO\nTipo de Procedimento: Concurso público\nPreço base do procedimento: Sim\nValor do preço base do procedimento: 340.000,00 EUR\nProcedimento com lotes? Sim\nNº Máx. de Lotes Autorizado: 2\nNúmero máximo de lotes que podem ser adjudicados a um concorrente: 2\n6 - OBJETO DO CONTRATO\nNúmero de referência interna: CPI/10/2025_41043/25\nDesignação do contrato: FISCALIZAÇÃO, GESTÃO DA QUALIDADE, COORDENAÇÃO DE SEGURANÇA E COORDENAÇÃO DE GESTÃO AMBIENTAL - HABITAÇÃO\nDescrição: FISCALIZAÇÃO, GESTÃO DA QUALIDADE, COORDENAÇÃO DE SEGURANÇA E COORDENAÇÃO DE GESTÃO AMBIENTAL - HABITAÇÃO\nOpções: Não\nTipo de Contrato Principal: Aquisição de Serviços\nTipo de Contrato: Aquisição de Serviços\nClassificação CPV (Vocabulário Comum para os Contratos Públicos)\nObjeto principal\nVocabulário Principal: 71240000\nPreço base s/IVA: 340.000,00 EUR\nLotes: \nNº: LOT-0001\nDescrição do Lote: Fiscalização, Gestão da Qualidade, Coordenação de Segurança e Gestão Ambiental da Empreitada de Construção de 204 Fogos - Bairro Coca Maravilhas, Portimão\nPreço base s/IVA: 210.000,00 EUR\nClassificação CPV (Vocabulário Comum para os Contratos Públicos)\nObjeto principal\nVocabulário Principal: 71240000\nNº: LOT-0002\nDescrição do Lote: Fiscalização, Gestão da Qualidade, Coordenação de Segurança e Gestão Ambiental da Empreitada de Cosntrução de 28 Fogos - Rua Estácio da Veiga, Bairro Pontal\nPreço base s/IVA: 130.000,00 EUR\nClassificação CPV (Vocabulário Comum para os Contratos Públicos)\nObjeto principal\nVocabulário Principal: 71240000\n7 - INDICAÇÕES ADICIONAIS\nO contrato envolve aquisição conjunta (satisfação de várias entidades)? Não\nO contrato é adjudicado por uma central de compras? Não\n8 - TÉCNICAS\nO concurso destina-se à celebração de um acordo-quadro? Inexistência de acordo-quadro\nÉ utilizado um leilão eletrónico? Não\nÉ adotada uma fase de negociação? Não\nSistema de Aquisição Dinâmico: Inexistência de sistema de aquisição dinâmico\n9 - LOCAL DA EXECUÇÃO DO CONTRATO\nLOCAL DA EXECUÇÃO DO CONTRATO (PROCEDIMENTO)\nPaís: Portugal\nNUT III: PT150\nLocalidade: Freguesia de Portimão\nDistrito: Faro\nConcelho: Portimão\nFreguesia: Freguesia de Portimão\nLOCAL DA EXECUÇÃO DO CONTRATO (LOTE)\nIdentificador do Lote: LOT-0001; LOT-0002\nPaís: Portugal\nNUT III: PT150\nLocalidade: Freguesia de Portimão\nDistrito: Faro\nConcelho: Portimão\nFreguesia: Freguesia de Portimão\n10 - PRAZO DE EXECUÇÃO DO CONTRATO\nIdentificador do Lote: LOT-0001; LOT-0002\nPrazo de execução do contrato: 36 MESES\nPrevisão de renovações: Não\n11 - FUNDOS EU\nIdentificador do Lote: LOT-0001; LOT-0002\nTêm fundos EU? Não\n12 - DOCUMENTOS DE HABILITAÇÃO\nHabilitação para o exercício da atividade profissional: Não\n13 - CONDIÇÕES DE APRESENTAÇÃO\nPlataforma eletrónica utilizada pela entidade adjudicante: ACIN\nURL para Apresentação: https://www.acingov.pt\nAdmissibilidade da apresentação de propostas variantes: Não autorizado\nPrazo para apresentação das propostas: 08-02-2026 17:00\nPrazo durante o qual os concorrentes são obrigados a manter as respetivas propostas: 180 dias a contar do termo do prazo para a apresentação das propostas\nApresentação de Catálogo Eletrónico: Permitido\nIndicação de Subcontratação na Proposta: A parte do contrato que o proponente tenciona subcontratar\n14 - PRESTAÇÃO DE CAUÇÃO\nPrestação de caução: Não\n15 - FORNECIMENTO DAS PEÇAS DO CONCURSO, APRESENTAÇÃO DE PEDIDOS DE PARTICIPAÇÃO E APRESENTAÇÃO DAS PROPOSTAS\nLink para acesso às peças do concurso (URL): https://www.acingov.pt/acingovprod/2/zonaPublica/zona_publica_c/donwloadProcedurePiece/MTAwMjM5NQ==\n20 - OUTROS REQUISITOS\nIdentificador do Lote: LOT-0001; LOT-0002\nInformação sobre contratos reservados. Aplica-se a contratos reservados (54º-A)? Não\n21 - CRITÉRIO DE ADJUDICAÇÃO\nO Critério de adjudicação é diferenciado por lote? Não\nMultifator: Sim\nFator: \nNome: Preço\nPonderação: 70%\nSubfatores: Não\nFator: \nNome: Outros\nOutro Nome: EXPERIÊNCIA PROFISSIONAL DO COORDENADOR DE FISCALIZAÇÃO\nPonderação: 15%\nSubfatores: Não\nFator: \nNome: Outros\nOutro Nome: EXPERIÊNCIA DA EQUIPA TÉCNICA EM OBRA\nPonderação: 15%\nSubfatores: Não\n24 - CONDIÇÕES DO CONTRATO\nIdentificador do Lote: LOT-0001; LOT-0002\nFaturação Eletrónica: Permitido\nObrigação de Subcontratação:\nCódigo da Obrigação de Subcontratação: O contratante tem de indicar qualquer mudança de subcontratantes durante a execução do contrato.\n25 - COMPRA PÚBLICA ESTRATÉGICA\nCompra Pública Estratégica: Inexistência de contratação pública estratégica\n26 - INFORMAÇÕES ADICIONAIS\nIdentificador do Lote: LOT-0001; LOT-0002\nContrato adequado para PME: Sim\nCobertura ACP (Acordo dos Contratos Públicos da Organização Mundial do Comércio): Não\n27 - IDENTIFICAÇÃO E CONTACTOS DO ÓRGÃO DE RECURSOS ADMINISTRATIVOS\nDesignação: Município de Portimão\nEndereço: Praça 1.º de maio\nCódigo postal: 8500-543\nLocalidade: Portimão\nTelefone: 282470700\nFax: 282470792\nEndereço eletrónico: geral@cm-portimao.pt\nPrazo de interposição do recurso: 10 dias\n28 - IDENTIFICAÇÃO DO(S) AUTOR(ES) DE ANÚNCIO\nNome: Álvaro Bila\nCargo: Presidente da Câmara Municipal de Portimão\n29 - ALTERAÇÃO\nMotivo da Alteração: Correção pelo adquirente\nIdentificador da Versão do Anúncio a Alterar: 5b0fae80-85d1-4f61-a85a-48a9b18a9cba-02\nIdentificador das Secções Alteradas do Anúncio Anterior: Critério de adjudicação\nDescrição das Alterações: Alteração do Critério de Adjudicação\nAlteração dos Documentos do Concurso: Sim\nData de alteração dos documentos do concurso: 07-01-2026\n419947709",
    "nipc": "505309939",
    "distrito": "Faro",
    "concelho": "Portimão",
    "freguesia": "Freguesia de Portimão",
    "site": "www.cm-portimao.pt",
    "email": "geral@cm-portimao.pt",
    "designacao_contrato": "FISCALIZAÇÃO, GESTÃO DA QUALIDADE, COORDENAÇÃO DE SEGURANÇA E COORDENAÇÃO DE GESTÃO AMBIENTAL - HABITAÇÃO",
    "descricao": "FISCALIZAÇÃO, GESTÃO DA QUALIDADE, COORDENAÇÃO DE SEGURANÇA E COORDENAÇÃO DE GESTÃO AMBIENTAL - HABITAÇÃO",
    "preco_base": "340.000,00 EUR",
    "prazo_execucao": "36 MESES",
    "prazo_apresentacao_propostas": "08-02-2026 17:00",
    "fundos_eu": "Não",
    "plataforma_eletronica": "ACIN",
    "url_procedimento": "https://www.acingov.pt",
    "autor_nome": "Álvaro Bila",
    "autor_cargo": "Presidente da Câmara Municipal de Portimão"
  },
  {
    "numero_procedimento": "N/A",
    "entidade": "Universidade do Porto",
    "link": "https://diariodarepublica.pt/dr/detalhe/contrato-publico/904-1011853869",
    "detalhes_completos": "Alteração do Anúncio de procedimento n.º 33131/2025, de 2025-12-22, com o ID 419909367\n1 - IDENTIFICAÇÃO E CONTACTOS DA ENTIDADE ADJUDICANTE\nDesignação da entidade adjudicante: Universidade do Porto\nNIPC: 501413197\nServiço/Órgão/Pessoa de contacto: Serviço de Compras e Gestão Contratual\nEndereço: Praça Gomes Teixeira s/n\nCódigo postal: 4099-002\nLocalidade: Porto\nPaís: Portugal\nNUT III: PT11A\nDistrito: Porto\nConcelho: Porto\nFreguesia: União das Freguesias de Cedofeita, Santo Ildefonso, Sé, Miragaia, São Nicolau e Vitória\nTelefone: 220408000\nFax: 2204081867\nEndereço da Entidade (URL): www.reit.up.pt\nEndereço Eletrónico: reitoria@reit.up.pt\neDelivery Gateway (URL): https://www.acingov.pt\nFunção da Organização: Adquirente\nNorma jurídica da Entidade Adjudicante: Organismo de direito público\nÁrea de atividade da Autoridade Adjudicante: Educação\n2 - JORNAL OFICIAL DA UNIÃO EUROPEIA\nO procedimento a que este anúncio diz respeito também é publicitado no Jornal Oficial da União Europeia? Sim\n3 - AVISO\nModelo de Anúncio: Concurso público\nData de Envio do Anúncio: 14-01-2026\n5 - PROCESSO\nTipo de Procedimento: Concurso público\nPreço base do procedimento: Sim\nValor do preço base do procedimento: 628.938,81 EUR\nProcedimento com lotes? Não\n6 - OBJETO DO CONTRATO\nNúmero de referência interna: SCGC_REIT_CPI_00006_2025\nDesignação do contrato: Concurso Público Internacional Nº SCGC_REIT_CPI_00006_2025 Fornecimento e instalação de sistema de controlo de acessos na UP\nDescrição: Concurso Público Internacional Nº SCGC_REIT_CPI_00006_2025 Fornecimento e instalação de sistema de controlo de acessos na UP \nOpções: Não\nTipo de Contrato Principal: Aquisição de Bens Móveis\nTipo de Contrato: Aquisição de Bens Móveis\nClassificação CPV (Vocabulário Comum para os Contratos Públicos)\nObjeto principal\nVocabulário Principal: 42961100\nPreço base s/IVA: 628.938,81 EUR\n7 - INDICAÇÕES ADICIONAIS\nO contrato envolve aquisição conjunta (satisfação de várias entidades)? Não\nO contrato é adjudicado por uma central de compras? Não\n8 - TÉCNICAS\nO concurso destina-se à celebração de um acordo-quadro? Inexistência de acordo-quadro\nÉ utilizado um leilão eletrónico? Não\nÉ adotada uma fase de negociação? Não\nSistema de Aquisição Dinâmico: Inexistência de sistema de aquisição dinâmico\n9 - LOCAL DA EXECUÇÃO DO CONTRATO\nLOCAL DA EXECUÇÃO DO CONTRATO (PROCEDIMENTO)\nPaís: Portugal\nNUT III: PT11A\nLocalidade: Porto\nDistrito: Porto\nConcelho: Porto\nFreguesia: Todas\n10 - PRAZO DE EXECUÇÃO DO CONTRATO\nPrazo de execução do contrato: 180 DIAS\nPrevisão de renovações: Não\n11 - FUNDOS EU\nTêm fundos EU? Não\n12 - DOCUMENTOS DE HABILITAÇÃO\nHabilitação para o exercício da atividade profissional: Não\n13 - CONDIÇÕES DE APRESENTAÇÃO\nPlataforma eletrónica utilizada pela entidade adjudicante: ACIN\nURL para Apresentação: https://www.acingov.pt\nAdmissibilidade da apresentação de propostas variantes: Não autorizado\nPrazo para apresentação das propostas: 24-01-2026 23:59\nPrazo durante o qual os concorrentes são obrigados a manter as respetivas propostas: 66 dias a contar do termo do prazo para a apresentação das propostas\nApresentação de Catálogo Eletrónico: Não autorizado\nIndicação de Subcontratação na Proposta: Inexistência de indicação de subcontratação\n14 - PRESTAÇÃO DE CAUÇÃO\nPrestação de caução: Sim\nPercentagem: 5%\nDescrição da Garantia Exigida: O valor da caução é de 5.00% do preço contratual.\n15 - FORNECIMENTO DAS PEÇAS DO CONCURSO, APRESENTAÇÃO DE PEDIDOS DE PARTICIPAÇÃO E APRESENTAÇÃO DAS PROPOSTAS\nLink para acesso às peças do concurso (URL): https://www.acingov.pt/acingovprod/2/zonaPublica/zona_publica_c/donwloadProcedurePiece/MTAwNzg5OA==\n20 - OUTROS REQUISITOS\nInformação sobre contratos reservados. Aplica-se a contratos reservados (54º-A)? Não\n21 - CRITÉRIO DE ADJUDICAÇÃO\nMultifator: Não\nMonofator:\nNome: Preço\n24 - CONDIÇÕES DO CONTRATO\nFaturação Eletrónica: Permitido\nObrigação de Subcontratação:\nCódigo da Obrigação de Subcontratação: Não é aplicável nenhuma obrigação de subcontratação.\n25 - COMPRA PÚBLICA ESTRATÉGICA\nCompra Pública Estratégica: Redução dos impactos ambientais\nDescrição do Processo de Adjudicação Estratégico: 1. O cocontratante deve garantir as melhores práticas ambientais por forma a incluir as medidas necessárias a fim de assegurar a proteção do ar, da água, do solo, e de prevenir ou reduzir a poluição sonora, a produção de resíduos e o consumo energético, com o objetivo de alcançar um nível elevado de proteção do ambiente e minimizar os impactes ambientais. 2. O cocontratante deve igualmente garantir o correto encaminhamento dos eventuais resíduos produzidos no decorrer da execução do contrato, respeitando as boas práticas ambientais previstas na legislação em vigor.\nCritérios de contratos Públicos Ecológicos: Outros critérios de contratação pública ecológica\nCategorias da estratégia nacional: Outros\nOutra categoria (Descrição): 1. O cocontratante deve garantir as melhores práticas ambientais por forma a incluir as medidas necessárias a fim de assegurar a proteção do ar, da água, do solo, e de prevenir ou reduzir a poluição sonora, a produção de resíduos e o consumo energético, com o objetivo de alcançar um nível elevado de proteção do ambiente e minimizar os impactes ambientais. 2. O cocontratante deve igualmente garantir o correto encaminhamento dos eventuais resíduos produzidos no decorrer d...\nContratos Públicos Ecológicos: A mitigação das alterações climáticas; A prevenção e o controlo da poluição\nDiretiva Veículos Não Poluentes: Não\nCritério de Acessibilidade: Os critérios de acessibilidade para as pessoas com deficiência não estão incluídos porque o contrato não se destina a pessoas singulares\n26 - INFORMAÇÕES ADICIONAIS\nContrato adequado para PME: Sim\nCobertura ACP (Acordo dos Contratos Públicos da Organização Mundial do Comércio): Não\n27 - IDENTIFICAÇÃO E CONTACTOS DO ÓRGÃO DE RECURSOS ADMINISTRATIVOS\nDesignação: Reitor da Universidade do Porto\nEndereço: Praça Gomes Teixeira, s/n\nCódigo postal: 4099-002\nLocalidade: Porto\nTelefone: 220408000\nFax: 2204081867\nEndereço eletrónico: reitoria@reit.up.pt\nPrazo de interposição do recurso: 5 dias\n28 - IDENTIFICAÇÃO DO(S) AUTOR(ES) DE ANÚNCIO\nNome: Kelly Manuela Bastos Almeida\nCargo: Técnica Superior, SCGC\n29 - ALTERAÇÃO\nMotivo da Alteração: Informações atualizadas\nIdentificador da Versão do Anúncio a Alterar: 626231cb-c09d-405f-b4d2-6a68e9feb44a-01\nIdentificador das Secções Alteradas do Anúncio Anterior: Condições de Apresentação\nDescrição das Alterações: Modificação do prazo para a apresentação de propostas\nAlteração dos Documentos do Concurso: Não\n419947754",
    "nipc": "501413197",
    "distrito": "Porto",
    "concelho": "Porto",
    "freguesia": "União das Freguesias de Cedofeita, Santo Ildefonso, Sé, Miragaia, São Nicolau e Vitória",
    "site": "www.reit.up.pt",
    "email": "reitoria@reit.up.pt",
    "designacao_contrato": "Concurso Público Internacional Nº SCGC_REIT_CPI_00006_2025 Fornecimento e instalação de sistema de controlo de acessos na UP",
    "descricao": "Concurso Público Internacional Nº SCGC_REIT_CPI_00006_2025 Fornecimento e instalação de sistema de controlo de acessos na UP",
    "preco_base": "628.938,81 EUR",
    "prazo_execucao": "180 DIAS",
    "prazo_apresentacao_propostas": "24-01-2026 23:59",
    "fundos_eu": "Não",
    "plataforma_eletronica": "ACIN",
    "url_procedimento": "https://www.acingov.pt",
    "autor_nome": "Kelly Manuela Bastos Almeida",
    "autor_cargo": "Técnica Superior, SCGC"
  },
  {
    "numero_procedimento": "N/A",
    "entidade": "AnÃºncio de procedimento  n.Âº 906/2026  -  DiÃ¡rio da RepÃºblica n.Âº 11/2026, SÃ©rie II de 2026-01-16",
    "link": "https://diariodarepublica.pt/dr/detalhe/contrato-publico/906-1011853870"
  },
  {
    "numero_procedimento": "N/A",
    "entidade": "Comunidade Intermunicipal da Região de Coimbra",
    "link": "https://diariodarepublica.pt/dr/detalhe/contrato-publico/908-1011853871",
    "detalhes_completos": "1 - IDENTIFICAÇÃO E CONTACTOS DA ENTIDADE ADJUDICANTE\nDesignação da entidade adjudicante: Comunidade Intermunicipal da Região de Coimbra\nNIPC: 508354617\nEndereço: Rua do Brasil, 131\nCódigo postal: 3030-175\nLocalidade: Coimbra\nPaís: Portugal\nNUT III: PTZZZ\nDistrito: Todos\nConcelho: Todos\nFreguesia: Todas\nTelefone: 239795200\nEndereço da Entidade (URL): https://cim-regiaodecoimbra.pt\nEndereço Eletrónico: geral@cim-regiaodecoimbra.pt\neDelivery Gateway (URL): https://www.acingov.pt\nFunção da Organização: Adquirente\nNorma jurídica da Entidade Adjudicante: Organismo de direito público\nÁrea de atividade da Autoridade Adjudicante: Serviços públicos das administrações públicas\n2 - JORNAL OFICIAL DA UNIÃO EUROPEIA\nO procedimento a que este anúncio diz respeito também é publicitado no Jornal Oficial da União Europeia? Sim\n3 - AVISO\nModelo de Anúncio: Concurso público\nData de Envio do Anúncio: 14-01-2026\n5 - PROCESSO\nTipo de Procedimento: Concurso público\nPreço base do procedimento: Sim\nValor do preço base do procedimento: 582.221,27 EUR\nProcedimento com lotes? Não\n6 - OBJETO DO CONTRATO\nNúmero de referência interna: CP28/2025\nDesignação do contrato: CP28/2025 - Aquisição de Serviços de Cibersegurança - 36 meses\nDescrição: CP28/2025 - Aquisição de Serviços de Cibersegurança - 36 meses\nOpções: Não\nTipo de Contrato Principal: Aquisição de Serviços\nTipo de Contrato: Aquisição de Serviços\nClassificação CPV (Vocabulário Comum para os Contratos Públicos)\nObjeto principal\nVocabulário Principal: 72220000\nPreço base s/IVA: 582.221,27 EUR\n7 - INDICAÇÕES ADICIONAIS\nO contrato envolve aquisição conjunta (satisfação de várias entidades)? Não\nO contrato é adjudicado por uma central de compras? Não\n8 - TÉCNICAS\nO concurso destina-se à celebração de um acordo-quadro? Inexistência de acordo-quadro\nÉ utilizado um leilão eletrónico? Não\nÉ adotada uma fase de negociação? Não\nSistema de Aquisição Dinâmico: Inexistência de sistema de aquisição dinâmico\n9 - LOCAL DA EXECUÇÃO DO CONTRATO\nLOCAL DA EXECUÇÃO DO CONTRATO (PROCEDIMENTO)\nPaís: Portugal\nNUT III: PT16E\nLocalidade: Freguesia de Santo António dos Olivais\nDistrito: Coimbra\nConcelho: Coimbra\nFreguesia: Freguesia de Santo António dos Olivais\n10 - PRAZO DE EXECUÇÃO DO CONTRATO\nPrazo de execução do contrato: 1095 DIAS\nPrevisão de renovações: Não\n11 - FUNDOS EU\nTêm fundos EU? Não\n12 - DOCUMENTOS DE HABILITAÇÃO\nHabilitação para o exercício da atividade profissional: Não\n13 - CONDIÇÕES DE APRESENTAÇÃO\nPlataforma eletrónica utilizada pela entidade adjudicante: ACIN\nURL para Apresentação: https://www.acingov.pt\nAdmissibilidade da apresentação de propostas variantes: Não autorizado\nPrazo para apresentação das propostas: 14-02-2026 23:59\nPrazo durante o qual os concorrentes são obrigados a manter as respetivas propostas: 120 dias a contar do termo do prazo para a apresentação das propostas\nApresentação de Catálogo Eletrónico: Permitido\nIndicação de Subcontratação na Proposta: Inexistência de indicação de subcontratação\n14 - PRESTAÇÃO DE CAUÇÃO\nPrestação de caução: Sim\nPercentagem: 5%\nDescrição da Garantia Exigida: O valor da caução é de 5.00% do preço contratual.\n15 - FORNECIMENTO DAS PEÇAS DO CONCURSO, APRESENTAÇÃO DE PEDIDOS DE PARTICIPAÇÃO E APRESENTAÇÃO DAS PROPOSTAS\nLink para acesso às peças do concurso (URL): https://www.acingov.pt/acingovprod/2/zonaPublica/zona_publica_c/donwloadProcedurePiece/MTA0ODE0NQ==\n20 - OUTROS REQUISITOS\nInformação sobre contratos reservados. Aplica-se a contratos reservados (54º-A)? Não\n21 - CRITÉRIO DE ADJUDICAÇÃO\nMultifator: Não\nMonofator:\nNome: Outros\nOutro nome: Fator Preço\n24 - CONDIÇÕES DO CONTRATO\nFaturação Eletrónica: Permitido\nObrigação de Subcontratação:\nCódigo da Obrigação de Subcontratação: Não é aplicável nenhuma obrigação de subcontratação.\n25 - COMPRA PÚBLICA ESTRATÉGICA\nCompra Pública Estratégica: Inexistência de contratação pública estratégica\n26 - INFORMAÇÕES ADICIONAIS\nContrato adequado para PME: Sim\nCobertura ACP (Acordo dos Contratos Públicos da Organização Mundial do Comércio): Não\n27 - IDENTIFICAÇÃO E CONTACTOS DO ÓRGÃO DE RECURSOS ADMINISTRATIVOS\nDesignação: Conselho Intermunicipal da Comunidade Intermunicipal da Região de Coimbra\nEndereço: Rua do Brasil, 131\nCódigo postal: 3030-175\nLocalidade: Coimbra\nTelefone: 239795200\nFax: 000000000\nEndereço eletrónico: geral@cim-regiaodecoimbra.pt\nPrazo de interposição do recurso: 5 dias\n28 - IDENTIFICAÇÃO DO(S) AUTOR(ES) DE ANÚNCIO\nNome: Jorge Brito\nCargo: Secretário Executivo Intermunicipal\n419947806",
    "nipc": "508354617",
    "distrito": "Todos",
    "concelho": "Todos",
    "freguesia": "Todas",
    "site": "https://cim-regiaodecoimbra.pt",
    "email": "geral@cim-regiaodecoimbra.pt",
    "designacao_contrato": "CP28/2025 - Aquisição de Serviços de Cibersegurança - 36 meses",
    "descricao": "CP28/2025 - Aquisição de Serviços de Cibersegurança - 36 meses",
    "preco_base": "582.221,27 EUR",
    "prazo_execucao": "1095 DIAS",
    "prazo_apresentacao_propostas": "14-02-2026 23:59",
    "fundos_eu": "Não",
    "plataforma_eletronica": "ACIN",
    "url_procedimento": "https://www.acingov.pt",
    "autor_nome": "Jorge Brito",
    "autor_cargo": "Secretário Executivo Intermunicipal"
  },
  {
    "numero_procedimento": "N/A",
    "entidade": "Unidade Local de Saúde da Lezíria, EPE",
    "link": "https://diariodarepublica.pt/dr/detalhe/contrato-publico/910-1011853872",
    "detalhes_completos": "Alteração do Anúncio de procedimento n.º 32790/2025, de 2025-12-18, com o ID 419878514\n1 - IDENTIFICAÇÃO E CONTACTOS DA ENTIDADE ADJUDICANTE\nDesignação da entidade adjudicante: Unidade Local de Saúde da Lezíria, EPE\nNIPC: 506361462\nEndereço: Av. Bernardo Santareno S/N\nCódigo postal: 2005-177\nLocalidade: Santarém\nPaís: Portugal\nNUT III: PT185\nDistrito: Santarém\nConcelho: Santarém\nFreguesia: União de Freguesias da Cidade de Santarém\nTelefone: 243300200\nFax: 243370220\nEndereço da Entidade (URL): www.hds.min-saude.pt\nEndereço Eletrónico: hdsca@hds.min-saude.pt\neDelivery Gateway (URL): https://community.vortal.biz/public/\nFunção da Organização: Adquirente\nNorma jurídica da Entidade Adjudicante: Organismo de direito público\nÁrea de atividade da Autoridade Adjudicante: Saúde\n2 - JORNAL OFICIAL DA UNIÃO EUROPEIA\nO procedimento a que este anúncio diz respeito também é publicitado no Jornal Oficial da União Europeia? Sim\n3 - AVISO\nModelo de Anúncio: Concurso público\nData de Envio do Anúncio: 14-01-2026\n5 - PROCESSO\nTipo de Procedimento: Concurso público\nPreço base do procedimento: Sim\nValor do preço base do procedimento: 719.000,00 EUR\nProcedimento com lotes? Não\n6 - OBJETO DO CONTRATO\nNúmero de referência interna: 180003/2025\nDesignação do contrato: Aquisição de prestação de serviços de cópia, impressão e digitalização de documentos em rede para a ULS Lezíria,  E.P.E\nDescrição: Aquisição de prestação de serviços de cópia, impressão e digitalização de documentos em rede para a ULS Lezíria,  E.P.E\nOpções: Não\nTipo de Contrato Principal: Aquisição de Serviços\nTipo de Contrato: Aquisição de Serviços\nClassificação CPV (Vocabulário Comum para os Contratos Públicos)\nObjeto principal\nVocabulário Principal: 79800000\nPreço base s/IVA: 719.000,00 EUR\n7 - INDICAÇÕES ADICIONAIS\nO contrato envolve aquisição conjunta (satisfação de várias entidades)? Não\nO contrato é adjudicado por uma central de compras? Não\n8 - TÉCNICAS\nO concurso destina-se à celebração de um acordo-quadro? Inexistência de acordo-quadro\nÉ utilizado um leilão eletrónico? Não\nÉ adotada uma fase de negociação? Não\nSistema de Aquisição Dinâmico: Inexistência de sistema de aquisição dinâmico\n9 - LOCAL DA EXECUÇÃO DO CONTRATO\nLOCAL DA EXECUÇÃO DO CONTRATO (PROCEDIMENTO)\nPaís: Portugal\nNUT III: PT185\nLocalidade: Santarém\nDistrito: Santarém\nConcelho: Santarém\nFreguesia: União de Freguesias da Cidade de Santarém\n10 - PRAZO DE EXECUÇÃO DO CONTRATO\nPrazo de execução do contrato: 36 MESES\nPrevisão de renovações: Não\n11 - FUNDOS EU\nTêm fundos EU? Não\n12 - DOCUMENTOS DE HABILITAÇÃO\nHabilitação para o exercício da atividade profissional: Não\n13 - CONDIÇÕES DE APRESENTAÇÃO\nPlataforma eletrónica utilizada pela entidade adjudicante: VORTAL\nURL para Apresentação: https://community.vortal.biz/public/\nAdmissibilidade da apresentação de propostas variantes: Não autorizado\nPrazo para apresentação das propostas: 17-01-2026 23:59\nPrazo durante o qual os concorrentes são obrigados a manter as respetivas propostas: 66 dias a contar do termo do prazo para a apresentação das propostas\nApresentação de Catálogo Eletrónico: Permitido\nIndicação de Subcontratação na Proposta: Inexistência de indicação de subcontratação\n14 - PRESTAÇÃO DE CAUÇÃO\nPrestação de caução: Não\n15 - FORNECIMENTO DAS PEÇAS DO CONCURSO, APRESENTAÇÃO DE PEDIDOS DE PARTICIPAÇÃO E APRESENTAÇÃO DAS PROPOSTAS\nLink para acesso às peças do concurso (URL): https://community.vortal.biz/Public/public-tender-documents/OUtOQ01ya1RUYWlncHVuaHdMVUhscU94d0c3UjlCOHlnR2R6WHJxbytMQndsQi9qanJJZ1Q0UEN4WUdZeWZiN050WC9odGJUOEM1TXg0Mmg5elVJeWc9PU03cjdy\n20 - OUTROS REQUISITOS\nInformação sobre contratos reservados. Aplica-se a contratos reservados (54º-A)? Não\n21 - CRITÉRIO DE ADJUDICAÇÃO\nMultifator: Sim\nFator: \nNome: Preço\nPonderação: 60%\nSubfatores: Não\nFator: \nNome: Qualidade\nPonderação: 25%\nSubfatores: Não\nFator: \nNome: Qualidade\nPonderação: 5%\nSubfatores: Não\nFator: \nNome: Outros\nOutro Nome: Requisitos Técnicos dos equipamentos\nPonderação: 10%\nSubfatores: Não\n24 - CONDIÇÕES DO CONTRATO\nFaturação Eletrónica: Permitido\nObrigação de Subcontratação:\nCódigo da Obrigação de Subcontratação: Não é aplicável nenhuma obrigação de subcontratação.\n25 - COMPRA PÚBLICA ESTRATÉGICA\nCompra Pública Estratégica: Inexistência de contratação pública estratégica\n26 - INFORMAÇÕES ADICIONAIS\nContrato adequado para PME: Sim\nCobertura ACP (Acordo dos Contratos Públicos da Organização Mundial do Comércio): Não\n27 - IDENTIFICAÇÃO E CONTACTOS DO ÓRGÃO DE RECURSOS ADMINISTRATIVOS\nDesignação: Conselho de Administração\nEndereço: Avenida Bernardo santareno S/N\nCódigo postal: 2005-177\nLocalidade: Santarém\nTelefone: +351 24300200\nFax: +351 243370220\nEndereço eletrónico: ca@ulsleziria.min-saude.pt\n28 - IDENTIFICAÇÃO DO(S) AUTOR(ES) DE ANÚNCIO\nNome: Dr. Pedro Manuel Dias de Figueiredo Pereira Marques \nCargo: Presidente do Conselho de Administração \n29 - ALTERAÇÃO\nMotivo da Alteração: Correção pelo adquirente\nIdentificador da Versão do Anúncio a Alterar: 3db2ff23-2f46-4e4f-ba2c-8908188af910-01\nIdentificador das Secções Alteradas do Anúncio Anterior: Alteração\nDescrição das Alterações: Prorrogação do prazo de apresentação de propostas para as 23:59 dia dia 21/01/2026\nAlteração dos Documentos do Concurso: Não\n419947844",
    "nipc": "506361462",
    "distrito": "Santarém",
    "concelho": "Santarém",
    "freguesia": "União de Freguesias da Cidade de Santarém",
    "site": "www.hds.min-saude.pt",
    "email": "hdsca@hds.min-saude.pt",
    "designacao_contrato": "Aquisição de prestação de serviços de cópia, impressão e digitalização de documentos em rede para a ULS Lezíria, E.P.E",
    "descricao": "Aquisição de prestação de serviços de cópia, impressão e digitalização de documentos em rede para a ULS Lezíria, E.P.E",
    "preco_base": "719.000,00 EUR",
    "prazo_execucao": "36 MESES",
    "prazo_apresentacao_propostas": "17-01-2026 23:59",
    "fundos_eu": "Não",
    "plataforma_eletronica": "VORTAL",
    "url_procedimento": "https://community.vortal.biz/public/",
    "autor_nome": "Dr. Pedro Manuel Dias de Figueiredo Pereira Marques",
    "autor_cargo": "Presidente do Conselho de Administração"
  },
  {
    "numero_procedimento": "N/A",
    "entidade": "Unidade Local de Saúde do Tâmega e Sousa, EPE",
    "link": "https://diariodarepublica.pt/dr/detalhe/contrato-publico/912-1011853873",
    "detalhes_completos": "1 - IDENTIFICAÇÃO E CONTACTOS DA ENTIDADE ADJUDICANTE\nDesignação da entidade adjudicante: Unidade Local de Saúde do Tâmega e Sousa, EPE\nNIPC: 508318262\nServiço/Órgão/Pessoa de contacto: Serviço de Compras\nEndereço: Avenida Padre Américo, Nº210\nCódigo postal: 4560-136\nLocalidade: Porto\nPaís: Portugal\nNUT III: PT11C\nDistrito: Porto\nConcelho: Penafiel\nFreguesia: Todas\nTelefone: 255714000\nEndereço da Entidade (URL): www.chtamegasousa.pt\nEndereço Eletrónico: concursos@chts.min-saude.pt\neDelivery Gateway (URL): https://community.vortal.biz/public/\nFunção da Organização: Adquirente\nNorma jurídica da Entidade Adjudicante: Empresa pública\nÁrea de atividade da Autoridade Adjudicante: Saúde\n2 - JORNAL OFICIAL DA UNIÃO EUROPEIA\nO procedimento a que este anúncio diz respeito também é publicitado no Jornal Oficial da União Europeia? Sim\n3 - AVISO\nModelo de Anúncio: Concurso público\nData de Envio do Anúncio: 14-01-2026\n5 - PROCESSO\nTipo de Procedimento: Concurso público\nPreço base do procedimento: Sim\nValor do preço base do procedimento: 895.440,00 EUR\nProcedimento com lotes? Não\n6 - OBJETO DO CONTRATO\nNúmero de referência interna: 07/CPI.25.1473\nDesignação do contrato: Aquisição de Angiógrafo\nDescrição: Aquisição de Angiógrafo\nOpções: Não\nTipo de Contrato Principal: Aquisição de Bens Móveis\nTipo de Contrato: Aquisição de Bens Móveis\nClassificação CPV (Vocabulário Comum para os Contratos Públicos)\nObjeto principal\nVocabulário Principal: 33111710\nPreço base s/IVA: 895.440,00 EUR\n7 - INDICAÇÕES ADICIONAIS\nO contrato envolve aquisição conjunta (satisfação de várias entidades)? Não\nO contrato é adjudicado por uma central de compras? Não\n8 - TÉCNICAS\nO concurso destina-se à celebração de um acordo-quadro? Inexistência de acordo-quadro\nÉ utilizado um leilão eletrónico? Não\nÉ adotada uma fase de negociação? Não\nSistema de Aquisição Dinâmico: Inexistência de sistema de aquisição dinâmico\n9 - LOCAL DA EXECUÇÃO DO CONTRATO\nLOCAL DA EXECUÇÃO DO CONTRATO (PROCEDIMENTO)\nPaís: Portugal\nNUT III: PT11C\nLocalidade: Porto\nDistrito: Porto\nConcelho: Penafiel\nFreguesia: Freguesia de Guilhufe e Urrô\n10 - PRAZO DE EXECUÇÃO DO CONTRATO\nPrazo de execução do contrato: 60 DIAS\nPrevisão de renovações: Não\n11 - FUNDOS EU\nTêm fundos EU? Sim\n12 - DOCUMENTOS DE HABILITAÇÃO\nHabilitação para o exercício da atividade profissional: Não\n13 - CONDIÇÕES DE APRESENTAÇÃO\nPlataforma eletrónica utilizada pela entidade adjudicante: VORTAL\nURL para Apresentação: https://community.vortal.biz/public/\nAdmissibilidade da apresentação de propostas variantes: Não autorizado\nPrazo para apresentação das propostas: 17-02-2026 23:59\nPrazo durante o qual os concorrentes são obrigados a manter as respetivas propostas: 180 dias a contar do termo do prazo para a apresentação das propostas\nApresentação de Catálogo Eletrónico: Não autorizado\nIndicação de Subcontratação na Proposta: Inexistência de indicação de subcontratação\n14 - PRESTAÇÃO DE CAUÇÃO\nPrestação de caução: Sim\nPercentagem: 5%\nDescrição da Garantia Exigida: conforme art. 21º do Programa de Procedimento\n15 - FORNECIMENTO DAS PEÇAS DO CONCURSO, APRESENTAÇÃO DE PEDIDOS DE PARTICIPAÇÃO E APRESENTAÇÃO DAS PROPOSTAS\nLink para acesso às peças do concurso (URL): https://community.vortal.biz/Public/public-tender-documents/NU5nWTRkaXNnajNUZkNVcnBEdjM4U3hBTTdEWlFhTERuZFlJWmN6aHhtdldoODVJN2dsbnNiSWtGYkdxRmhjcDdvS3BBM0UvSjRnUExadXBYcHh5YWc9PWMycFUh\n20 - OUTROS REQUISITOS\nInformação sobre contratos reservados. Aplica-se a contratos reservados (54º-A)? Não\n21 - CRITÉRIO DE ADJUDICAÇÃO\nMultifator: Sim\nFator: \nNome: Qualidade\nPonderação: 30%\nSubfatores: Não\nFator: \nNome: Qualidade\nPonderação: 70%\nSubfatores: Não\n24 - CONDIÇÕES DO CONTRATO\nFaturação Eletrónica: Permitido\nObrigação de Subcontratação:\nCódigo da Obrigação de Subcontratação: Não é aplicável nenhuma obrigação de subcontratação.\n25 - COMPRA PÚBLICA ESTRATÉGICA\nCompra Pública Estratégica: Inexistência de contratação pública estratégica\n26 - INFORMAÇÕES ADICIONAIS\nContrato adequado para PME: Sim\nCobertura ACP (Acordo dos Contratos Públicos da Organização Mundial do Comércio): Não\n27 - IDENTIFICAÇÃO E CONTACTOS DO ÓRGÃO DE RECURSOS ADMINISTRATIVOS\nDesignação: Unidade Local de Saúde Tâmega e Sousa\nEndereço: Avenida do Hospital Padre Américo, 210\nCódigo postal: 4560-136\nLocalidade: Penafiel\nTelefone: +351 255714000\nFax: +351 255714000\nEndereço eletrónico: administracao@ulsts.min-saude.pt\n28 - IDENTIFICAÇÃO DO(S) AUTOR(ES) DE ANÚNCIO\nNome: Unidade Local de Saúde Tâmega e Sousa\nCargo: Serviço de Compras\n419947867",
    "nipc": "508318262",
    "distrito": "Porto",
    "concelho": "Penafiel",
    "freguesia": "Todas",
    "site": "www.chtamegasousa.pt",
    "email": "concursos@chts.min-saude.pt",
    "designacao_contrato": "Aquisição de Angiógrafo",
    "descricao": "Aquisição de Angiógrafo",
    "preco_base": "895.440,00 EUR",
    "prazo_execucao": "60 DIAS",
    "prazo_apresentacao_propostas": "17-02-2026 23:59",
    "fundos_eu": "Sim",
    "plataforma_eletronica": "VORTAL",
    "url_procedimento": "https://community.vortal.biz/public/",
    "autor_nome": "Unidade Local de Saúde Tâmega e Sousa",
    "autor_cargo": "Serviço de Compras"
  },
  {
    "numero_procedimento": "N/A",
    "entidade": "AnÃºncio de procedimento  n.Âº 914/2026  -  DiÃ¡rio da RepÃºblica n.Âº 11/2026, SÃ©rie II de 2026-01-16",
    "link": "https://diariodarepublica.pt/dr/detalhe/contrato-publico/914-1011853874"
  },
  {
    "numero_procedimento": "N/A",
    "entidade": "Instituto Português de Oncologia do Porto Francisco Gentil, EPE",
    "link": "https://diariodarepublica.pt/dr/detalhe/contrato-publico/916-1011853975",
    "detalhes_completos": "Alteração do Anúncio de procedimento n.º 115/2026, de 2026-01-05, com o ID 419943354\n1 - IDENTIFICAÇÃO E CONTACTOS DA ENTIDADE ADJUDICANTE\nDesignação da entidade adjudicante: Instituto Português de Oncologia do Porto Francisco Gentil, EPE\nNIPC: 506362299\nServiço/Órgão/Pessoa de contacto: Serviço de Aprovisionamento e Logística (SAL) – Setor de Compras\nEndereço: Rua Drº António Bernardino De Almeida S/N, Porto\nCódigo postal: 4200-072\nLocalidade: Área Metropolitana do Porto\nPaís: Portugal\nNUT III: PT11A\nDistrito: Porto\nConcelho: Porto\nFreguesia: Todas\nTelefone: 225084000\nFax: 225084001\nEndereço da Entidade (URL): http://www.ipoporto.pt/\nEndereço Eletrónico: compras@ipoporto.min-saude.pt\neDelivery Gateway (URL): https://community.vortal.biz/public/\nFunção da Organização: Adquirente\nNorma jurídica da Entidade Adjudicante: Organismo de direito público\nÁrea de atividade da Autoridade Adjudicante: Saúde\n2 - JORNAL OFICIAL DA UNIÃO EUROPEIA\nO procedimento a que este anúncio diz respeito também é publicitado no Jornal Oficial da União Europeia? Sim\n3 - AVISO\nModelo de Anúncio: Concurso público\nData de Envio do Anúncio: 14-01-2026\n5 - PROCESSO\nTipo de Procedimento: Concurso público\nPreço base do procedimento: Sim\nValor do preço base do procedimento: 53.000.000,00 EUR\nProcedimento com lotes? Não\n6 - OBJETO DO CONTRATO\nNúmero de referência interna: CPI 4647/25\nDesignação do contrato: CPI 4647/25 Aquisição de Equipamento de Protonterapia para Duas Salas de Tratamento\nDescrição: CPI 4647/25 Aquisição de Equipamento de Protonterapia para Duas Salas de Tratamento\nOpções: Não\nTipo de Contrato Principal: Aquisição de Bens Móveis\nTipo de Contrato: Aquisição de Bens Móveis\nClassificação CPV (Vocabulário Comum para os Contratos Públicos)\nObjeto principal\nVocabulário Principal: 33100000\nPreço base s/IVA: 53.000.000,00 EUR\n7 - INDICAÇÕES ADICIONAIS\nO contrato envolve aquisição conjunta (satisfação de várias entidades)? Não\nO contrato é adjudicado por uma central de compras? Não\n8 - TÉCNICAS\nO concurso destina-se à celebração de um acordo-quadro? Inexistência de acordo-quadro\nÉ utilizado um leilão eletrónico? Não\nÉ adotada uma fase de negociação? Não\nSistema de Aquisição Dinâmico: Inexistência de sistema de aquisição dinâmico\n9 - LOCAL DA EXECUÇÃO DO CONTRATO\nLOCAL DA EXECUÇÃO DO CONTRATO (PROCEDIMENTO)\nPaís: Portugal\nNUT III: PT11A\nLocalidade: Área Metropolitana do Porto\nDistrito: Porto\nConcelho: Porto\nFreguesia: Freguesia de Paranhos - Porto\n10 - PRAZO DE EXECUÇÃO DO CONTRATO\nPrazo de execução do contrato: 18 MESES\nPrevisão de renovações: Não\n11 - FUNDOS EU\nTêm fundos EU? Não\n12 - DOCUMENTOS DE HABILITAÇÃO\nHabilitação para o exercício da atividade profissional: Não\n13 - CONDIÇÕES DE APRESENTAÇÃO\nPlataforma eletrónica utilizada pela entidade adjudicante: VORTAL\nURL para Apresentação: https://community.vortal.biz/public/\nAdmissibilidade da apresentação de propostas variantes: Não autorizado\nPrazo para apresentação das propostas: 20-01-2026 17:00\nPrazo durante o qual os concorrentes são obrigados a manter as respetivas propostas: 180 dias a contar do termo do prazo para a apresentação das propostas\nApresentação de Catálogo Eletrónico: Não autorizado\nIndicação de Subcontratação na Proposta: Inexistência de indicação de subcontratação\n14 - PRESTAÇÃO DE CAUÇÃO\nPrestação de caução: Sim\nPercentagem: 5%\nDescrição da Garantia Exigida: Os modos de prestação de caução são mediante garantia bancária (Anexo III) ou o depósito bancário (Anexo IV) ou seguro-caução (Anexo V)\n15 - FORNECIMENTO DAS PEÇAS DO CONCURSO, APRESENTAÇÃO DE PEDIDOS DE PARTICIPAÇÃO E APRESENTAÇÃO DAS PROPOSTAS\nLink para acesso às peças do concurso (URL): https://community.vortal.biz/Public/public-tender-documents/MTlLai9Hc3dIemhRWDBwMXB3N0ZvVUVJa2J6S3l1aTJJSHJZN0JlQVMzUkQydmxoQ2Q4SS9oZUdQbkQ2VlBUZ0YzaCttaVo2WVdScVdpbTdOYkkya2c9PUw3U0kp\n20 - OUTROS REQUISITOS\nInformação sobre contratos reservados. Aplica-se a contratos reservados (54º-A)? Não\n21 - CRITÉRIO DE ADJUDICAÇÃO\nMultifator: Sim\nFator: \nNome: Preço\nPonderação: 20%\nSubfatores: Não\nFator: \nNome: Qualidade\nPonderação: 60%\nSubfatores: Não\nFator: \nNome: Outros\nOutro Nome: Valor dos contratos de manutenção após garantia\nPonderação: 20%\nSubfatores: Não\n24 - CONDIÇÕES DO CONTRATO\nFaturação Eletrónica: Permitido\nObrigação de Subcontratação:\nCódigo da Obrigação de Subcontratação: Não é aplicável nenhuma obrigação de subcontratação.\n25 - COMPRA PÚBLICA ESTRATÉGICA\nCompra Pública Estratégica: Inexistência de contratação pública estratégica\n26 - INFORMAÇÕES ADICIONAIS\nContrato adequado para PME: Sim\nCobertura ACP (Acordo dos Contratos Públicos da Organização Mundial do Comércio): Não\n27 - IDENTIFICAÇÃO E CONTACTOS DO ÓRGÃO DE RECURSOS ADMINISTRATIVOS\nDesignação: Conselho de Administração\nEndereço: Rua Dr. António Bernardino de Almeida\nCódigo postal: 4200-072\nLocalidade: Porto\nTelefone: +351 225084000\nFax: +351 225084001\nEndereço eletrónico: compras@ipoporto.min-saude.pt\n28 - IDENTIFICAÇÃO DO(S) AUTOR(ES) DE ANÚNCIO\nNome: Sandra Luís\nCargo: Diretora do Serviço de Aprovisionamento e Logística\n29 - ALTERAÇÃO\nMotivo da Alteração: Correção pelo adquirente\nIdentificador da Versão do Anúncio a Alterar: f77063d2-e906-4645-91f7-7cd36991ff4e-01\nIdentificador das Secções Alteradas do Anúncio Anterior: Condições de Apresentação; Condições de Apresentação\nDescrição das Alterações: Alteração do prazo de apresentação de propostas prorrogado por período de 6 dias \nAlteração dos Documentos do Concurso: Sim\nData de alteração dos documentos do concurso: 20-01-2026\nIdentificador das Secções Alteradas do Anúncio Anterior: Condições de Apresentação\nDescrição das Alterações: Alteração do prazo de apresentação de propostas prorrogado por período de 6 dias \nAlteração dos Documentos do Concurso: Sim\nData de alteração dos documentos do concurso: 20-01-2026\n419947896",
    "nipc": "506362299",
    "distrito": "Porto",
    "concelho": "Porto",
    "freguesia": "Todas",
    "site": "http://www.ipoporto.pt/",
    "email": "compras@ipoporto.min-saude.pt",
    "designacao_contrato": "CPI 4647/25 Aquisição de Equipamento de Protonterapia para Duas Salas de Tratamento",
    "descricao": "CPI 4647/25 Aquisição de Equipamento de Protonterapia para Duas Salas de Tratamento",
    "preco_base": "53.000.000,00 EUR",
    "prazo_execucao": "18 MESES",
    "prazo_apresentacao_propostas": "20-01-2026 17:00",
    "fundos_eu": "Não",
    "plataforma_eletronica": "VORTAL",
    "url_procedimento": "https://community.vortal.biz/public/",
    "autor_nome": "Sandra Luís",
    "autor_cargo": "Diretora do Serviço de Aprovisionamento e Logística"
  },
  {
    "numero_procedimento": "N/A",
    "entidade": "VALNOR - Valorização e Tratamento de Resíduos Sólidos, SA",
    "link": "https://diariodarepublica.pt/dr/detalhe/contrato-publico/918-1011853976",
    "detalhes_completos": "1 - IDENTIFICAÇÃO E CONTACTOS DA ENTIDADE ADJUDICANTE\nDesignação da entidade adjudicante: VALNOR - Valorização e Tratamento de Resíduos Sólidos, SA\nNIPC: 505255090\nEndereço: CIVTRS Avis - Herdade das Marrãs \nCódigo postal: 7480-352\nLocalidade: Portalegre\nPaís: Portugal\nNUT III: PT186\nDistrito: Portalegre\nConcelho: Avis\nFreguesia: Freguesia de Figueira e Barros\nTelefone: 245610040\nFax: 245619003\nEndereço da Entidade (URL): www.valnor.pt\nEndereço Eletrónico: geral@valnor.pt\neDelivery Gateway (URL): https://community.vortal.biz/public/\nFunção da Organização: Adquirente\nNorma jurídica da Entidade Adjudicante: Autoridade da administração central\nÁrea de atividade da Autoridade Adjudicante: Serviços públicos das administrações públicas\n2 - JORNAL OFICIAL DA UNIÃO EUROPEIA\nO procedimento a que este anúncio diz respeito também é publicitado no Jornal Oficial da União Europeia? Sim\n3 - AVISO\nModelo de Anúncio: Concurso público\nData de Envio do Anúncio: 14-01-2026\n5 - PROCESSO\nTipo de Procedimento: Concurso público\nPreço base do procedimento: Sim\nValor do preço base do procedimento: 487.800,00 EUR\nProcedimento com lotes? Sim\nNº Máx. de Lotes Autorizado: 2\nNúmero máximo de lotes que podem ser adjudicados a um concorrente: 2\n6 - OBJETO DO CONTRATO\nNúmero de referência interna: CP044_FORNECIMENTO DE AUTOCOMPACTADORES\nDesignação do contrato: FORNECIMENTO DE AUTOCOMPACTADORES\nDescrição: FORNECIMENTO DE AUTOCOMPACTADORES: \nFornecimento de 7 autocompactadores estanques de 20 m3 e de 5 autocompactadores de 26 m3.\nOpções: Não\nTipo de Contrato Principal: Aquisição de Bens Móveis\nTipo de Contrato: Aquisição de Bens Móveis\nClassificação CPV (Vocabulário Comum para os Contratos Públicos)\nObjeto principal\nVocabulário Principal: 44613800\nPreço base s/IVA: 487.800,00 EUR\nLotes: \nNº: LOT-0001\nDescrição do Lote: Lote 1-Fornecimento de 7 autocompactadores estanques de 20 m3;\nPreço base s/IVA: 293.300,00 EUR\nClassificação CPV (Vocabulário Comum para os Contratos Públicos)\nObjeto principal\nVocabulário Principal: 44613800\nNº: LOT-0002\nDescrição do Lote: Lote 2-Fornecimento de 5 autocompactadores de 26 m3.\nPreço base s/IVA: 194.500,00 EUR\nClassificação CPV (Vocabulário Comum para os Contratos Públicos)\nObjeto principal\nVocabulário Principal: 44613800\n7 - INDICAÇÕES ADICIONAIS\nO contrato envolve aquisição conjunta (satisfação de várias entidades)? Não\nO contrato é adjudicado por uma central de compras? Não\n8 - TÉCNICAS\nO concurso destina-se à celebração de um acordo-quadro? Inexistência de acordo-quadro\nÉ utilizado um leilão eletrónico? Não\nÉ adotada uma fase de negociação? Não\nSistema de Aquisição Dinâmico: Inexistência de sistema de aquisição dinâmico\n9 - LOCAL DA EXECUÇÃO DO CONTRATO\nLOCAL DA EXECUÇÃO DO CONTRATO (PROCEDIMENTO)\nPaís: Portugal\nNUT III: PT186\nLocalidade: Portalegre\nDistrito: Portalegre\nConcelho: Avis\nFreguesia: Freguesia de Figueira e Barros\nLOCAL DA EXECUÇÃO DO CONTRATO (LOTE)\nIdentificador do Lote: LOT-0001; LOT-0002\nPaís: Portugal\nNUT III: PT186\nLocalidade: Figueira e Barros\nDistrito: Portalegre\nConcelho: Avis\nFreguesia: Freguesia de Figueira e Barros\n10 - PRAZO DE EXECUÇÃO DO CONTRATO\nIdentificador do Lote: LOT-0001; LOT-0002\nPrazo de execução do contrato: 6 MESES\nPrevisão de renovações: Não\n11 - FUNDOS EU\nIdentificador do Lote: LOT-0001; LOT-0002\nTêm fundos EU? Não\n12 - DOCUMENTOS DE HABILITAÇÃO\nHabilitação para o exercício da atividade profissional: Não\n13 - CONDIÇÕES DE APRESENTAÇÃO\nPlataforma eletrónica utilizada pela entidade adjudicante: VORTAL\nURL para Apresentação: https://community.vortal.biz/public/\nAdmissibilidade da apresentação de propostas variantes: Não autorizado\nPrazo para apresentação das propostas: 11-02-2026 17:00\nPrazo durante o qual os concorrentes são obrigados a manter as respetivas propostas: 66 dias a contar do termo do prazo para a apresentação das propostas\nApresentação de Catálogo Eletrónico: Não autorizado\nIndicação de Subcontratação na Proposta: Inexistência de indicação de subcontratação\n14 - PRESTAÇÃO DE CAUÇÃO\nPrestação de caução: Sim\nPercentagem: 5%\nDescrição da Garantia Exigida: A caução é prestada por depósito em dinheiro, ou em títulos emitidos ou garantidos pelo Estado, ou mediante uma garantia bancária ou um seguro-caução, ambos à primeira solicitação, em conformidade com um dos modelos constantes respetivamente dos Anexos VI, VII e VIII do Programa do Concurso.\n15 - FORNECIMENTO DAS PEÇAS DO CONCURSO, APRESENTAÇÃO DE PEDIDOS DE PARTICIPAÇÃO E APRESENTAÇÃO DAS PROPOSTAS\nLink para acesso às peças do concurso (URL): https://community.vortal.biz/Public/public-tender-documents/eEJsbWgxQ3lIZHFCMStrQzFHd1c1T1ZzOENHdUc3c1poOFNCazhyOThFbWt5eXoyejN4amVxN1psaElzNVVIQTdQR28rdzVzTnhhV1J2RXhiVzNSMXc9PUxzY0RA\n20 - OUTROS REQUISITOS\nIdentificador do Lote: LOT-0001; LOT-0002\nInformação sobre contratos reservados. Aplica-se a contratos reservados (54º-A)? Não\n21 - CRITÉRIO DE ADJUDICAÇÃO\nO Critério de adjudicação é diferenciado por lote? Não\nMultifator: Não\nMonofator:\nNome: Preço\n24 - CONDIÇÕES DO CONTRATO\nIdentificador do Lote: LOT-0001; LOT-0002\nFaturação Eletrónica: Permitido\nObrigação de Subcontratação:\nCódigo da Obrigação de Subcontratação: Não é aplicável nenhuma obrigação de subcontratação.\n25 - COMPRA PÚBLICA ESTRATÉGICA\nCompra Pública Estratégica: Inexistência de contratação pública estratégica\n26 - INFORMAÇÕES ADICIONAIS\nIdentificador do Lote: LOT-0001; LOT-0002\nContrato adequado para PME: Sim\nCobertura ACP (Acordo dos Contratos Públicos da Organização Mundial do Comércio): Não\n27 - IDENTIFICAÇÃO E CONTACTOS DO ÓRGÃO DE RECURSOS ADMINISTRATIVOS\nDesignação: Conselho de Administração da VALNOR\nEndereço: CIVTRS de Avis - Herdade das Marrãs\nCódigo postal: 7480-352\nLocalidade: Avis\nTelefone: +351 245610040\nFax: +351 245610040\nEndereço eletrónico: geral@valnor.pt\nPrazo de interposição do recurso: 5 dias\n28 - IDENTIFICAÇÃO DO(S) AUTOR(ES) DE ANÚNCIO\nNome: Nuno Heitor\nCargo: Administrador-delegado\n419947753",
    "nipc": "505255090",
    "distrito": "Portalegre",
    "concelho": "Avis",
    "freguesia": "Freguesia de Figueira e Barros",
    "site": "www.valnor.pt",
    "email": "geral@valnor.pt",
    "designacao_contrato": "FORNECIMENTO DE AUTOCOMPACTADORES",
    "descricao": "FORNECIMENTO DE AUTOCOMPACTADORES:",
    "preco_base": "487.800,00 EUR",
    "prazo_execucao": "6 MESES",
    "prazo_apresentacao_propostas": "11-02-2026 17:00",
    "fundos_eu": "Não",
    "plataforma_eletronica": "VORTAL",
    "url_procedimento": "https://community.vortal.biz/public/",
    "autor_nome": "Nuno Heitor",
    "autor_cargo": "Administrador-delegado"
  },
  {
    "numero_procedimento": "N/A",
    "entidade": "AnÃºncio de procedimento  n.Âº 920/2026  -  DiÃ¡rio da RepÃºblica n.Âº 11/2026, SÃ©rie II de 2026-01-16",
    "link": "https://diariodarepublica.pt/dr/detalhe/contrato-publico/920-1011853977"
  },
  {
    "numero_procedimento": "N/A",
    "entidade": "Unidade Local de Saúde do Alto Alentejo, EPE",
    "link": "https://diariodarepublica.pt/dr/detalhe/contrato-publico/922-1011853978",
    "detalhes_completos": "1 - IDENTIFICAÇÃO E CONTACTOS DA ENTIDADE ADJUDICANTE\nDesignação da entidade adjudicante: Unidade Local de Saúde do Alto Alentejo, EPE\nNIPC: 508094461\nEndereço: Av. De Santo António\nCódigo postal: 7300-853\nLocalidade: Portalegre\nPaís: Portugal\nNUT III: PT186\nDistrito: Portalegre\nConcelho: Portalegre\nFreguesia: União das Freguesias da Sé e São Lourenço\nTelefone: 245301000\nFax: 245301002\nEndereço da Entidade (URL): www.hportalegre.min-saude.pt\nEndereço Eletrónico: aprov.portalegre.elvas@ulsna.min-saude.pt\neDelivery Gateway (URL): https://community.vortal.biz/public/\nFunção da Organização: Adquirente\nNorma jurídica da Entidade Adjudicante: Empresa pública\nÁrea de atividade da Autoridade Adjudicante: Saúde\n2 - JORNAL OFICIAL DA UNIÃO EUROPEIA\nO procedimento a que este anúncio diz respeito também é publicitado no Jornal Oficial da União Europeia? Sim\n3 - AVISO\nModelo de Anúncio: Concurso público\nData de Envio do Anúncio: 14-01-2026\n5 - PROCESSO\nTipo de Procedimento: Concurso público\nPreço base do procedimento: Sim\nValor do preço base do procedimento: 341.706,00 EUR\nProcedimento com lotes? Sim\nNº Máx. de Lotes Autorizado: 55\nNúmero máximo de lotes que podem ser adjudicados a um concorrente: 55\n6 - OBJETO DO CONTRATO\nNúmero de referência interna: 17106725\nDesignação do contrato: Aquisição de Mobiliário Hospitalar para Diversos Serviços da ULSAALE, EPE - Projeto 18152 Investimento RE-C01_i04–Modernização e Renovação de Áreas Hospitalares e Equipamentos para Hospitais - PRR\nDescrição: Aquisição de Mobiliário Hospitalar para Diversos Serviços da ULSAALE, EPE - Projeto 18152 Investimento RE-C01_i04–Modernização e Renovação de Áreas Hospitalares e Equipamentos para Hospitais - PRR\nOpções: Não\nTipo de Contrato Principal: Aquisição de Bens Móveis\nTipo de Contrato: Aquisição de Bens Móveis\nClassificação CPV (Vocabulário Comum para os Contratos Públicos)\nObjeto principal\nVocabulário Principal: 33192000\nPreço base s/IVA: 341.706,00 EUR\nLotes: \nNº: LOT-0001\nDescrição do Lote: Lote 1\nPreço base s/IVA: 1.625,00 EUR\nClassificação CPV (Vocabulário Comum para os Contratos Públicos)\nObjeto principal\nVocabulário Principal: 33192000\nNº: LOT-0002\nDescrição do Lote: Lote 2\nPreço base s/IVA: 300,00 EUR\nClassificação CPV (Vocabulário Comum para os Contratos Públicos)\nObjeto principal\nVocabulário Principal: 33192000\nNº: LOT-0003\nDescrição do Lote: Lote 3\nPreço base s/IVA: 2.080,00 EUR\nClassificação CPV (Vocabulário Comum para os Contratos Públicos)\nObjeto principal\nVocabulário Principal: 33192000\nNº: LOT-0004\nDescrição do Lote: Lote 4\nPreço base s/IVA: 4.950,00 EUR\nClassificação CPV (Vocabulário Comum para os Contratos Públicos)\nObjeto principal\nVocabulário Principal: 33192000\nNº: LOT-0005\nDescrição do Lote: Lote 5\nPreço base s/IVA: 600,00 EUR\nClassificação CPV (Vocabulário Comum para os Contratos Públicos)\nObjeto principal\nVocabulário Principal: 33192000\nNº: LOT-0006\nDescrição do Lote: Lote 6\nPreço base s/IVA: 1.260,00 EUR\nClassificação CPV (Vocabulário Comum para os Contratos Públicos)\nObjeto principal\nVocabulário Principal: 33192000\nNº: LOT-0007\nDescrição do Lote: Lote 7\nPreço base s/IVA: 350,00 EUR\nClassificação CPV (Vocabulário Comum para os Contratos Públicos)\nObjeto principal\nVocabulário Principal: 33192000\nNº: LOT-0008\nDescrição do Lote: Lote 8\nPreço base s/IVA: 15.750,00 EUR\nClassificação CPV (Vocabulário Comum para os Contratos Públicos)\nObjeto principal\nVocabulário Principal: 33192000\nNº: LOT-0009\nDescrição do Lote: Lote 9\nPreço base s/IVA: 2.100,00 EUR\nClassificação CPV (Vocabulário Comum para os Contratos Públicos)\nObjeto principal\nVocabulário Principal: 33192000\nNº: LOT-0010\nDescrição do Lote: Lote 10\nPreço base s/IVA: 40.150,00 EUR\nClassificação CPV (Vocabulário Comum para os Contratos Públicos)\nObjeto principal\nVocabulário Principal: 33192000\nNº: LOT-0011\nDescrição do Lote: Lote 11\nPreço base s/IVA: 26.250,00 EUR\nClassificação CPV (Vocabulário Comum para os Contratos Públicos)\nObjeto principal\nVocabulário Principal: 33192000\nNº: LOT-0012\nDescrição do Lote: Lote 12\nPreço base s/IVA: 1.100,00 EUR\nClassificação CPV (Vocabulário Comum para os Contratos Públicos)\nObjeto principal\nVocabulário Principal: 33192000\nNº: LOT-0013\nDescrição do Lote: Lote 13\nPreço base s/IVA: 5.750,00 EUR\nClassificação CPV (Vocabulário Comum para os Contratos Públicos)\nObjeto principal\nVocabulário Principal: 33192000\nNº: LOT-0014\nDescrição do Lote: Lote 14\nPreço base s/IVA: 12.800,00 EUR\nClassificação CPV (Vocabulário Comum para os Contratos Públicos)\nObjeto principal\nVocabulário Principal: 33192000\nNº: LOT-0015\nDescrição do Lote: Lote 15\nPreço base s/IVA: 1.875,00 EUR\nClassificação CPV (Vocabulário Comum para os Contratos Públicos)\nObjeto principal\nVocabulário Principal: 33192000\nNº: LOT-0016\nDescrição do Lote: Lote 16\nPreço base s/IVA: 12.950,00 EUR\nClassificação CPV (Vocabulário Comum para os Contratos Públicos)\nObjeto principal\nVocabulário Principal: 33192000\nNº: LOT-0017\nDescrição do Lote: Lote 17\nPreço base s/IVA: 2.650,00 EUR\nClassificação CPV (Vocabulário Comum para os Contratos Públicos)\nObjeto principal\nVocabulário Principal: 33192000\nNº: LOT-0018\nDescrição do Lote: Lote 18\nPreço base s/IVA: 2.250,00 EUR\nClassificação CPV (Vocabulário Comum para os Contratos Públicos)\nObjeto principal\nVocabulário Principal: 33192000\nNº: LOT-0019\nDescrição do Lote: Lote 19\nPreço base s/IVA: 2.100,00 EUR\nClassificação CPV (Vocabulário Comum para os Contratos Públicos)\nObjeto principal\nVocabulário Principal: 33192000\nNº: LOT-0020\nDescrição do Lote: Lote 20\nPreço base s/IVA: 3.200,00 EUR\nClassificação CPV (Vocabulário Comum para os Contratos Públicos)\nObjeto principal\nVocabulário Principal: 33192000\nNº: LOT-0021\nDescrição do Lote: Lote 21\nPreço base s/IVA: 8.715,00 EUR\nClassificação CPV (Vocabulário Comum para os Contratos Públicos)\nObjeto principal\nVocabulário Principal: 33192000\nNº: LOT-0022\nDescrição do Lote: Lote 22\nPreço base s/IVA: 2.400,00 EUR\nClassificação CPV (Vocabulário Comum para os Contratos Públicos)\nObjeto principal\nVocabulário Principal: 33192000\nNº: LOT-0023\nDescrição do Lote: Lote 23\nPreço base s/IVA: 700,00 EUR\nClassificação CPV (Vocabulário Comum para os Contratos Públicos)\nObjeto principal\nVocabulário Principal: 33192000\nNº: LOT-0024\nDescrição do Lote: Lote 24\nPreço base s/IVA: 3.000,00 EUR\nClassificação CPV (Vocabulário Comum para os Contratos Públicos)\nObjeto principal\nVocabulário Principal: 33192000\nNº: LOT-0025\nDescrição do Lote: Lote 25\nPreço base s/IVA: 116,00 EUR\nClassificação CPV (Vocabulário Comum para os Contratos Públicos)\nObjeto principal\nVocabulário Principal: 33192000\nNº: LOT-0026\nDescrição do Lote: Lote 26\nPreço base s/IVA: 880,00 EUR\nClassificação CPV (Vocabulário Comum para os Contratos Públicos)\nObjeto principal\nVocabulário Principal: 33192000\nNº: LOT-0027\nDescrição do Lote: Lote 27\nPreço base s/IVA: 1.750,00 EUR\nClassificação CPV (Vocabulário Comum para os Contratos Públicos)\nObjeto principal\nVocabulário Principal: 33192000\nNº: LOT-0028\nDescrição do Lote: Lote 28\nPreço base s/IVA: 19.200,00 EUR\nClassificação CPV (Vocabulário Comum para os Contratos Públicos)\nObjeto principal\nVocabulário Principal: 33192000\nNº: LOT-0029\nDescrição do Lote: Lote 29\nPreço base s/IVA: 80,00 EUR\nClassificação CPV (Vocabulário Comum para os Contratos Públicos)\nObjeto principal\nVocabulário Principal: 33192000\nNº: LOT-0030\nDescrição do Lote: Lote 30\nPreço base s/IVA: 840,00 EUR\nClassificação CPV (Vocabulário Comum para os Contratos Públicos)\nObjeto principal\nVocabulário Principal: 33192000\nNº: LOT-0031\nDescrição do Lote: Lote 31\nPreço base s/IVA: 26.250,00 EUR\nClassificação CPV (Vocabulário Comum para os Contratos Públicos)\nObjeto principal\nVocabulário Principal: 33192000\nNº: LOT-0032\nDescrição do Lote: Lote 32\nPreço base s/IVA: 240,00 EUR\nClassificação CPV (Vocabulário Comum para os Contratos Públicos)\nObjeto principal\nVocabulário Principal: 33192000\nNº: LOT-0033\nDescrição do Lote: Lote 33\nPreço base s/IVA: 150,00 EUR\nClassificação CPV (Vocabulário Comum para os Contratos Públicos)\nObjeto principal\nVocabulário Principal: 33192000\nNº: LOT-0034\nDescrição do Lote: Lote 34\nPreço base s/IVA: 1.560,00 EUR\nClassificação CPV (Vocabulário Comum para os Contratos Públicos)\nObjeto principal\nVocabulário Principal: 33192000\nNº: LOT-0035\nDescrição do Lote: Lote 35\nPreço base s/IVA: 1.125,00 EUR\nClassificação CPV (Vocabulário Comum para os Contratos Públicos)\nObjeto principal\nVocabulário Principal: 33192000\nNº: LOT-0036\nDescrição do Lote: Lote 36\nPreço base s/IVA: 7.500,00 EUR\nClassificação CPV (Vocabulário Comum para os Contratos Públicos)\nObjeto principal\nVocabulário Principal: 33192000\nNº: LOT-0037\nDescrição do Lote: Lote 37\nPreço base s/IVA: 2.100,00 EUR\nClassificação CPV (Vocabulário Comum para os Contratos Públicos)\nObjeto principal\nVocabulário Principal: 33192000\nNº: LOT-0038\nDescrição do Lote: Lote 38\nPreço base s/IVA: 3.100,00 EUR\nClassificação CPV (Vocabulário Comum para os Contratos Públicos)\nObjeto principal\nVocabulário Principal: 33192000\nNº: LOT-0039\nDescrição do Lote: Lote 39\nPreço base s/IVA: 740,00 EUR\nClassificação CPV (Vocabulário Comum para os Contratos Públicos)\nObjeto principal\nVocabulário Principal: 33192000\nNº: LOT-0040\nDescrição do Lote: Lote 40\nPreço base s/IVA: 300,00 EUR\nClassificação CPV (Vocabulário Comum para os Contratos Públicos)\nObjeto principal\nVocabulário Principal: 33192000\nNº: LOT-0041\nDescrição do Lote: Lote 41\nPreço base s/IVA: 1.440,00 EUR\nClassificação CPV (Vocabulário Comum para os Contratos Públicos)\nObjeto principal\nVocabulário Principal: 33192000\nNº: LOT-0042\nDescrição do Lote: Lote 42\nPreço base s/IVA: 115,00 EUR\nClassificação CPV (Vocabulário Comum para os Contratos Públicos)\nObjeto principal\nVocabulário Principal: 33192000\nNº: LOT-0043\nDescrição do Lote: Lote 43\nPreço base s/IVA: 95,00 EUR\nClassificação CPV (Vocabulário Comum para os Contratos Públicos)\nObjeto principal\nVocabulário Principal: 33192000\nNº: LOT-0044\nDescrição do Lote: Lote 44\nPreço base s/IVA: 13.800,00 EUR\nClassificação CPV (Vocabulário Comum para os Contratos Públicos)\nObjeto principal\nVocabulário Principal: 33192000\nNº: LOT-0045\nDescrição do Lote: Lote 45\nPreço base s/IVA: 1.800,00 EUR\nClassificação CPV (Vocabulário Comum para os Contratos Públicos)\nObjeto principal\nVocabulário Principal: 33192000\nNº: LOT-0046\nDescrição do Lote: Lote 46\nPreço base s/IVA: 2.300,00 EUR\nClassificação CPV (Vocabulário Comum para os Contratos Públicos)\nObjeto principal\nVocabulário Principal: 33192000\nNº: LOT-0047\nDescrição do Lote: Lote 47\nPreço base s/IVA: 1.800,00 EUR\nClassificação CPV (Vocabulário Comum para os Contratos Públicos)\nObjeto principal\nVocabulário Principal: 33192000\nNº: LOT-0048\nDescrição do Lote: Lote 48\nPreço base s/IVA: 5.500,00 EUR\nClassificação CPV (Vocabulário Comum para os Contratos Públicos)\nObjeto principal\nVocabulário Principal: 33192000\nNº: LOT-0049\nDescrição do Lote: Lote 49\nPreço base s/IVA: 2.200,00 EUR\nClassificação CPV (Vocabulário Comum para os Contratos Públicos)\nObjeto principal\nVocabulário Principal: 33192000\nNº: LOT-0050\nDescrição do Lote: Lote 50\nPreço base s/IVA: 44.100,00 EUR\nClassificação CPV (Vocabulário Comum para os Contratos Públicos)\nObjeto principal\nVocabulário Principal: 33192000\nNº: LOT-0051\nDescrição do Lote: Lote 51\nPreço base s/IVA: 33.300,00 EUR\nClassificação CPV (Vocabulário Comum para os Contratos Públicos)\nObjeto principal\nVocabulário Principal: 33192000\nNº: LOT-0052\nDescrição do Lote: Lote 52\nPreço base s/IVA: 9.900,00 EUR\nClassificação CPV (Vocabulário Comum para os Contratos Públicos)\nObjeto principal\nVocabulário Principal: 33192000\nNº: LOT-0053\nDescrição do Lote: Lote 53\nPreço base s/IVA: 2.250,00 EUR\nClassificação CPV (Vocabulário Comum para os Contratos Públicos)\nObjeto principal\nVocabulário Principal: 33192000\nNº: LOT-0054\nDescrição do Lote: Lote 54\nPreço base s/IVA: 1.250,00 EUR\nClassificação CPV (Vocabulário Comum para os Contratos Públicos)\nObjeto principal\nVocabulário Principal: 33192000\nNº: LOT-0055\nDescrição do Lote: Lote 55\nPreço base s/IVA: 1.020,00 EUR\nClassificação CPV (Vocabulário Comum para os Contratos Públicos)\nObjeto principal\nVocabulário Principal: 33192000\n7 - INDICAÇÕES ADICIONAIS\nO contrato envolve aquisição conjunta (satisfação de várias entidades)? Não\nO contrato é adjudicado por uma central de compras? Não\n8 - TÉCNICAS\nO concurso destina-se à celebração de um acordo-quadro? Inexistência de acordo-quadro\nÉ utilizado um leilão eletrónico? Não\nÉ adotada uma fase de negociação? Não\nSistema de Aquisição Dinâmico: Inexistência de sistema de aquisição dinâmico\n9 - LOCAL DA EXECUÇÃO DO CONTRATO\nLOCAL DA EXECUÇÃO DO CONTRATO (PROCEDIMENTO)\nPaís: Portugal\nNUT III: PT186\nLocalidade: Portalegre\nDistrito: Portalegre\nConcelho: Portalegre\nFreguesia: União das Freguesias da Sé e São Lourenço\nLOCAL DA EXECUÇÃO DO CONTRATO (LOTE)\nIdentificador do Lote: LOT-0001; LOT-0002; LOT-0003; LOT-0004; LOT-0005; LOT-0006; LOT-0007; LOT-0008; LOT-0009; LOT-0010; LOT-0011; LOT-0012; LOT-0013; LOT-0014; LOT-0015; LOT-0016; LOT-0017; LOT-0018; LOT-0019; LOT-0020; LOT-0021; LOT-0022; LOT-0023; LOT-0024; LOT-0025; LOT-0026; LOT-0027; LOT-0028; LOT-0029; LOT-0030; LOT-0031; LOT-0032; LOT-0033; LOT-0034; LOT-0035; LOT-0036; LOT-0037; LOT-0038; LOT-0039; LOT-0040; LOT-0041; LOT-0042; LOT-0043; LOT-0044; LOT-0045; LOT-0046; LOT-0047; LOT-0048; LOT-0049; LOT-0050; LOT-0051; LOT-0052; LOT-0053; LOT-0054; LOT-0055\nPaís: Portugal\nNUT III: PT186\nLocalidade: Portalegre\nDistrito: Portalegre\nConcelho: Portalegre\nFreguesia: União das Freguesias da Sé e São Lourenço\n10 - PRAZO DE EXECUÇÃO DO CONTRATO\nIdentificador do Lote: LOT-0001; LOT-0002; LOT-0003; LOT-0004; LOT-0005; LOT-0006; LOT-0007; LOT-0008; LOT-0009; LOT-0010; LOT-0011; LOT-0012; LOT-0013; LOT-0014; LOT-0015; LOT-0016; LOT-0017; LOT-0018; LOT-0019; LOT-0020; LOT-0021; LOT-0022; LOT-0023; LOT-0024; LOT-0025; LOT-0026; LOT-0027; LOT-0028; LOT-0029; LOT-0030; LOT-0031; LOT-0032; LOT-0033; LOT-0034; LOT-0035; LOT-0036; LOT-0037; LOT-0038; LOT-0039; LOT-0040; LOT-0041; LOT-0042; LOT-0043; LOT-0044; LOT-0045; LOT-0046; LOT-0047; LOT-0048; LOT-0049; LOT-0050; LOT-0051; LOT-0052; LOT-0053; LOT-0054; LOT-0055\nPrazo de execução do contrato: 30 DIAS\nPrevisão de renovações: Não\n11 - FUNDOS EU\nIdentificador do Lote: LOT-0001; LOT-0002; LOT-0003; LOT-0004; LOT-0005; LOT-0006; LOT-0007; LOT-0008; LOT-0009; LOT-0010; LOT-0011; LOT-0012; LOT-0013; LOT-0014; LOT-0015; LOT-0016; LOT-0017; LOT-0018; LOT-0019; LOT-0020; LOT-0021; LOT-0022; LOT-0023; LOT-0024; LOT-0025; LOT-0026; LOT-0027; LOT-0028; LOT-0029; LOT-0030; LOT-0031; LOT-0032; LOT-0033; LOT-0034; LOT-0035; LOT-0036; LOT-0037; LOT-0038; LOT-0039; LOT-0040; LOT-0041; LOT-0042; LOT-0043; LOT-0044; LOT-0045; LOT-0046; LOT-0047; LOT-0048; LOT-0049; LOT-0050; LOT-0051; LOT-0052; LOT-0053; LOT-0054; LOT-0055\nTêm fundos EU? Sim\n12 - DOCUMENTOS DE HABILITAÇÃO\nHabilitação para o exercício da atividade profissional: Sim\nTipo: Outros\nDescrição - Outros: Os exigidos nas peças do concurso\nDescrição: Apresentação dos documentos de habilitação conforme descrito nas peças do concurso\n13 - CONDIÇÕES DE APRESENTAÇÃO\nPlataforma eletrónica utilizada pela entidade adjudicante: VORTAL\nURL para Apresentação: https://community.vortal.biz/public/\nAdmissibilidade da apresentação de propostas variantes: Não autorizado\nPrazo para apresentação das propostas: 19-02-2026 18:00\nPrazo durante o qual os concorrentes são obrigados a manter as respetivas propostas: 180 dias a contar do termo do prazo para a apresentação das propostas\nApresentação de Catálogo Eletrónico: Necessário\nIndicação de Subcontratação na Proposta: Inexistência de indicação de subcontratação\n14 - PRESTAÇÃO DE CAUÇÃO\nPrestação de caução: Não\n15 - FORNECIMENTO DAS PEÇAS DO CONCURSO, APRESENTAÇÃO DE PEDIDOS DE PARTICIPAÇÃO E APRESENTAÇÃO DAS PROPOSTAS\nLink para acesso às peças do concurso (URL): https://community.vortal.biz/Public/public-tender-documents/VE82MGJYSHlpd09kOW91RFN3SFRWSmdPWml5MTBwYXhuMG9wd2xXbVoxVDU1WkdFQ1JSWnNpM2xOdjJYU0o1NXJBeSs5b3ZhWmpwRDd5VU44VE41NHc9PWswZDRF\n20 - OUTROS REQUISITOS\nIdentificador do Lote: LOT-0001; LOT-0002; LOT-0003; LOT-0004; LOT-0005; LOT-0006; LOT-0007; LOT-0008; LOT-0009; LOT-0010; LOT-0011; LOT-0012; LOT-0013; LOT-0014; LOT-0015; LOT-0016; LOT-0017; LOT-0018; LOT-0019; LOT-0020; LOT-0021; LOT-0022; LOT-0023; LOT-0024; LOT-0025; LOT-0026; LOT-0027; LOT-0028; LOT-0029; LOT-0030; LOT-0031; LOT-0032; LOT-0033; LOT-0034; LOT-0035; LOT-0036; LOT-0037; LOT-0038; LOT-0039; LOT-0040; LOT-0041; LOT-0042; LOT-0043; LOT-0044; LOT-0045; LOT-0046; LOT-0047; LOT-0048; LOT-0049; LOT-0050; LOT-0051; LOT-0052; LOT-0053; LOT-0054; LOT-0055\nInformação sobre contratos reservados. Aplica-se a contratos reservados (54º-A)? Não\n21 - CRITÉRIO DE ADJUDICAÇÃO\nO Critério de adjudicação é diferenciado por lote? Não\nMultifator: Sim\nFator: \nNome: Preço\nPonderação: 85%\nSubfatores: Não\nFator: \nNome: Qualidade\nPonderação: 10%\nSubfatores: Não\nFator: \nNome: Qualidade\nPonderação: 5%\nSubfatores: Não\n24 - CONDIÇÕES DO CONTRATO\nIdentificador do Lote: LOT-0001; LOT-0002; LOT-0003; LOT-0004; LOT-0005; LOT-0006; LOT-0007; LOT-0008; LOT-0009; LOT-0010; LOT-0011; LOT-0012; LOT-0013; LOT-0014; LOT-0015; LOT-0016; LOT-0017; LOT-0018; LOT-0019; LOT-0020; LOT-0021; LOT-0022; LOT-0023; LOT-0024; LOT-0025; LOT-0026; LOT-0027; LOT-0028; LOT-0029; LOT-0030; LOT-0031; LOT-0032; LOT-0033; LOT-0034; LOT-0035; LOT-0036; LOT-0037; LOT-0038; LOT-0039; LOT-0040; LOT-0041; LOT-0042; LOT-0043; LOT-0044; LOT-0045; LOT-0046; LOT-0047; LOT-0048; LOT-0049; LOT-0050; LOT-0051; LOT-0052; LOT-0053; LOT-0054; LOT-0055\nFaturação Eletrónica: Permitido\nObrigação de Subcontratação:\nCódigo da Obrigação de Subcontratação: Não é aplicável nenhuma obrigação de subcontratação.\n25 - COMPRA PÚBLICA ESTRATÉGICA\nCompra Pública Estratégica: Redução dos impactos ambientais\nDescrição do Processo de Adjudicação Estratégico: Conforme as peças do procedimento\nCritérios de contratos Públicos Ecológicos: Critérios de contratação pública ecológica nacional\nCategorias da estratégia nacional: Mobiliário\nDiretiva Veículos Não Poluentes: Não\nCritério de Acessibilidade: Os critérios de acessibilidade para as pessoas com deficiência não estão incluídos porque o contrato não se destina a pessoas singulares\n26 - INFORMAÇÕES ADICIONAIS\nIdentificador do Lote: LOT-0001; LOT-0002; LOT-0003; LOT-0004; LOT-0005; LOT-0006; LOT-0007; LOT-0008; LOT-0009; LOT-0010; LOT-0011; LOT-0012; LOT-0013; LOT-0014; LOT-0015; LOT-0016; LOT-0017; LOT-0018; LOT-0019; LOT-0020; LOT-0021; LOT-0022; LOT-0023; LOT-0024; LOT-0025; LOT-0026; LOT-0027; LOT-0028; LOT-0029; LOT-0030; LOT-0031; LOT-0032; LOT-0033; LOT-0034; LOT-0035; LOT-0036; LOT-0037; LOT-0038; LOT-0039; LOT-0040; LOT-0041; LOT-0042; LOT-0043; LOT-0044; LOT-0045; LOT-0046; LOT-0047; LOT-0048; LOT-0049; LOT-0050; LOT-0051; LOT-0052; LOT-0053; LOT-0054; LOT-0055\nContrato adequado para PME: Sim\nCobertura ACP (Acordo dos Contratos Públicos da Organização Mundial do Comércio): Não\n27 - IDENTIFICAÇÃO E CONTACTOS DO ÓRGÃO DE RECURSOS ADMINISTRATIVOS\nDesignação: Conselho de Administração\nEndereço: AVENIDA DE SANTO ANTONIO\nCódigo postal: 7300-853\nLocalidade: Portalegre\nTelefone: +351 245301000\nFax: +351 245330359\nEndereço eletrónico: admin@ulsaale.min-saude.pt\n28 - IDENTIFICAÇÃO DO(S) AUTOR(ES) DE ANÚNCIO\nNome: José Miguel da Costa Lopes\nCargo: Presidente do Conselho de Administração\n419947947",
    "nipc": "508094461",
    "distrito": "Portalegre",
    "concelho": "Portalegre",
    "freguesia": "União das Freguesias da Sé e São Lourenço",
    "site": "www.hportalegre.min-saude.pt",
    "email": "aprov.portalegre.elvas@ulsna.min-saude.pt",
    "designacao_contrato": "Aquisição de Mobiliário Hospitalar para Diversos Serviços da ULSAALE, EPE - Projeto 18152 Investimento RE-C01_i04–Modernização e Renovação de Áreas Hospitalares e Equipamentos para Hospitais - PRR",
    "descricao": "Aquisição de Mobiliário Hospitalar para Diversos Serviços da ULSAALE, EPE - Projeto 18152 Investimento RE-C01_i04–Modernização e Renovação de Áreas Hospitalares e Equipamentos para Hospitais - PRR",
    "preco_base": "341.706,00 EUR",
    "prazo_execucao": "30 DIAS",
    "prazo_apresentacao_propostas": "19-02-2026 18:00",
    "fundos_eu": "Sim",
    "plataforma_eletronica": "VORTAL",
    "url_procedimento": "https://community.vortal.biz/public/",
    "autor_nome": "José Miguel da Costa Lopes",
    "autor_cargo": "Presidente do Conselho de Administração"
  },
  {
    "numero_procedimento": "N/A",
    "entidade": "Universidade de Aveiro",
    "link": "https://diariodarepublica.pt/dr/detalhe/contrato-publico/924-1011853979",
    "detalhes_completos": "Alteração do Anúncio de procedimento n.º 33100/2025, de 2025-12-22, com o ID 419891985\n1 - IDENTIFICAÇÃO E CONTACTOS DA ENTIDADE ADJUDICANTE\nDesignação da entidade adjudicante: Universidade de Aveiro\nNIPC: 501461108\nServiço/Órgão/Pessoa de contacto: Área de Aquisições e Contratos\nEndereço: Campus Universitário de Santiago\nCódigo postal: 3810-193\nLocalidade: Aveiro\nPaís: Portugal\nNUT III: PT16D\nDistrito: Aveiro\nConcelho: Todos\nFreguesia: Todas\nTelefone: 234370200\nEndereço da Entidade (URL): https://www.ua.pt/\nEndereço Eletrónico: contratacao@ua.pt\neDelivery Gateway (URL): https://www.acingov.pt\nFunção da Organização: Adquirente\nSubfunção da Organização: Organização que recebe as propostas\nNorma jurídica da Entidade Adjudicante: Organismo de direito público\nÁrea de atividade da Autoridade Adjudicante: Serviços públicos das administrações públicas\n2 - JORNAL OFICIAL DA UNIÃO EUROPEIA\nO procedimento a que este anúncio diz respeito também é publicitado no Jornal Oficial da União Europeia? Sim\n3 - AVISO\nModelo de Anúncio: Concurso público\nData de Envio do Anúncio: 14-01-2026\n5 - PROCESSO\nTipo de Procedimento: Concurso público\nPreço base do procedimento: Sim\nValor do preço base do procedimento: 202.380,74 EUR\nProcedimento com lotes? Não\n6 - OBJETO DO CONTRATO\nNúmero de referência interna: CPI 461 AAC/UA 12/25\nDesignação do contrato: Aquisição, em regime de fornecimento contínuo, de gases puros\nDescrição: Aquisição, em regime de fornecimento contínuo, de gases puros\nOpções: Não\nTipo de Contrato Principal: Aquisição de Bens Móveis\nTipo de Contrato: Aquisição de Bens Móveis\nClassificação CPV (Vocabulário Comum para os Contratos Públicos)\nObjeto principal\nVocabulário Principal: 24100000\nPreço base s/IVA: 202.380,74 EUR\n7 - INDICAÇÕES ADICIONAIS\nO contrato envolve aquisição conjunta (satisfação de várias entidades)? Não\nO contrato é adjudicado por uma central de compras? Não\n8 - TÉCNICAS\nO concurso destina-se à celebração de um acordo-quadro? Inexistência de acordo-quadro\nÉ utilizado um leilão eletrónico? Não\nÉ adotada uma fase de negociação? Não\nSistema de Aquisição Dinâmico: Inexistência de sistema de aquisição dinâmico\n9 - LOCAL DA EXECUÇÃO DO CONTRATO\nLOCAL DA EXECUÇÃO DO CONTRATO (PROCEDIMENTO)\nPaís: Portugal\nNUT III: PT16D\nLocalidade: União das Freguesias de Glória e Vera Cruz\nDistrito: Aveiro\nConcelho: Aveiro\nFreguesia: União das Freguesias de Glória e Vera Cruz\n10 - PRAZO DE EXECUÇÃO DO CONTRATO\nPrazo de execução do contrato: 24 MESES\nPrevisão de renovações: Não\n11 - FUNDOS EU\nTêm fundos EU? Não\n12 - DOCUMENTOS DE HABILITAÇÃO\nHabilitação para o exercício da atividade profissional: Não\n13 - CONDIÇÕES DE APRESENTAÇÃO\nPlataforma eletrónica utilizada pela entidade adjudicante: ACIN\nURL para Apresentação: https://www.acingov.pt\nAdmissibilidade da apresentação de propostas variantes: Não autorizado\nPrazo para apresentação das propostas: 10-02-2026 23:59\nPrazo durante o qual os concorrentes são obrigados a manter as respetivas propostas: 132 dias a contar do termo do prazo para a apresentação das propostas\nApresentação de Catálogo Eletrónico: Não autorizado\nIndicação de Subcontratação na Proposta: Inexistência de indicação de subcontratação\n14 - PRESTAÇÃO DE CAUÇÃO\nPrestação de caução: Não\n15 - FORNECIMENTO DAS PEÇAS DO CONCURSO, APRESENTAÇÃO DE PEDIDOS DE PARTICIPAÇÃO E APRESENTAÇÃO DAS PROPOSTAS\nLink para acesso às peças do concurso (URL): https://www.acingov.pt/acingovprod/2/zonaPublica/zona_publica_c/donwloadProcedurePiece/MTAwNjAwOQ==\n20 - OUTROS REQUISITOS\nInformação sobre contratos reservados. Aplica-se a contratos reservados (54º-A)? Não\n21 - CRITÉRIO DE ADJUDICAÇÃO\nMultifator: Não\nMonofator:\nNome: Preço\n24 - CONDIÇÕES DO CONTRATO\nFaturação Eletrónica: Necessário\nObrigação de Subcontratação:\nCódigo da Obrigação de Subcontratação: Não é aplicável nenhuma obrigação de subcontratação.\n25 - COMPRA PÚBLICA ESTRATÉGICA\nCompra Pública Estratégica: Inexistência de contratação pública estratégica\n26 - INFORMAÇÕES ADICIONAIS\nContrato adequado para PME: Sim\nCobertura ACP (Acordo dos Contratos Públicos da Organização Mundial do Comércio): Não\n27 - IDENTIFICAÇÃO E CONTACTOS DO ÓRGÃO DE RECURSOS ADMINISTRATIVOS\nDesignação: Reitor da Universidade de Aveiro\nEndereço: Campus Universitário de Santiago, 25\nCódigo postal: 3810-193\nLocalidade: Aveiro\nTelefone: 234370200\nFax: \nEndereço eletrónico: contratacao@ua.pt\n28 - IDENTIFICAÇÃO DO(S) AUTOR(ES) DE ANÚNCIO\nNome: Ana Isabel Pires Sousa da Silva Braga\nCargo: Chefe de Divisão\n29 - ALTERAÇÃO\nMotivo da Alteração: Correção pelo eSender\nIdentificador da Versão do Anúncio a Alterar: 582e0d7f-8ba5-4412-9431-1bb5c70f8690-01\nIdentificador das Secções Alteradas do Anúncio Anterior: O procedimento a que este anúncio diz respeito também é publicitado no Jornal Oficial da União Europeia?; Condições de Apresentação\nDescrição das Alterações: Modificação do prazo para a apresentação de propostas e peças do procedimento\nAlteração dos Documentos do Concurso: Sim\nData de alteração dos documentos do concurso: 14-01-2026\n419947952",
    "nipc": "501461108",
    "distrito": "Aveiro",
    "concelho": "Todos",
    "freguesia": "Todas",
    "site": "https://www.ua.pt/",
    "email": "contratacao@ua.pt",
    "designacao_contrato": "Aquisição, em regime de fornecimento contínuo, de gases puros",
    "descricao": "Aquisição, em regime de fornecimento contínuo, de gases puros",
    "preco_base": "202.380,74 EUR",
    "prazo_execucao": "24 MESES",
    "prazo_apresentacao_propostas": "10-02-2026 23:59",
    "fundos_eu": "Não",
    "plataforma_eletronica": "ACIN",
    "url_procedimento": "https://www.acingov.pt",
    "autor_nome": "Ana Isabel Pires Sousa da Silva Braga",
    "autor_cargo": "Chefe de Divisão"
  },
  {
    "numero_procedimento": "N/A",
    "entidade": "AnÃºncio de procedimento  n.Âº 926/2026  -  DiÃ¡rio da RepÃºblica n.Âº 11/2026, SÃ©rie II de 2026-01-16",
    "link": "https://diariodarepublica.pt/dr/detalhe/contrato-publico/926-1011853980"
  },
  {
    "numero_procedimento": "N/A",
    "entidade": "AnÃºncio de procedimento  n.Âº 928/2026  -  DiÃ¡rio da RepÃºblica n.Âº 11/2026, SÃ©rie II de 2026-01-16",
    "link": "https://diariodarepublica.pt/dr/detalhe/contrato-publico/928-1011853981"
  },
  {
    "numero_procedimento": "N/A",
    "entidade": "Unidade Local de Saúde do Nordeste, EPE",
    "link": "https://diariodarepublica.pt/dr/detalhe/contrato-publico/930-1011853982",
    "detalhes_completos": "1 - IDENTIFICAÇÃO E CONTACTOS DA ENTIDADE ADJUDICANTE\nDesignação da entidade adjudicante: Unidade Local de Saúde do Nordeste, EPE\nNIPC: 509932584\nEndereço: Praça Cavaleiro Ferreira\nCódigo postal: 5301-862\nLocalidade: Bragança\nPaís: Portugal\nNUT III: PT11E\nDistrito: Braganca\nConcelho: Bragança\nFreguesia: Todas\nTelefone: 273302851\nFax: 273302861\nEndereço da Entidade (URL): https://www.ulsne.min-saude.pt/\nEndereço Eletrónico: amartins@ulsne.min-saude.pt\neDelivery Gateway (URL): https://community.vortal.biz/public/\nFunção da Organização: Adquirente\nNorma jurídica da Entidade Adjudicante: Organismo de direito público\nÁrea de atividade da Autoridade Adjudicante: Saúde\n2 - JORNAL OFICIAL DA UNIÃO EUROPEIA\nO procedimento a que este anúncio diz respeito também é publicitado no Jornal Oficial da União Europeia? Sim\n3 - AVISO\nModelo de Anúncio: Concurso público\nData de Envio do Anúncio: 14-01-2026\n5 - PROCESSO\nTipo de Procedimento: Concurso público\nPreço base do procedimento: Sim\nValor do preço base do procedimento: 1.350.000,00 EUR\nProcedimento com lotes? Não\n6 - OBJETO DO CONTRATO\nNúmero de referência interna: 61260005\nDesignação do contrato: 61260005 - Fornecimento e instalação de tomografia computorizada\nDescrição: 61260005 - Fornecimento e instalação de tomografia computorizada\nOpções: Não\nTipo de Contrato Principal: Aquisição de Bens Móveis\nTipo de Contrato: Aquisição de Bens Móveis\nClassificação CPV (Vocabulário Comum para os Contratos Públicos)\nObjeto principal\nVocabulário Principal: 33100000\nPreço base s/IVA: 1.350.000,00 EUR\n7 - INDICAÇÕES ADICIONAIS\nO contrato envolve aquisição conjunta (satisfação de várias entidades)? Não\nO contrato é adjudicado por uma central de compras? Não\n8 - TÉCNICAS\nO concurso destina-se à celebração de um acordo-quadro? Inexistência de acordo-quadro\nÉ utilizado um leilão eletrónico? Não\nÉ adotada uma fase de negociação? Não\nSistema de Aquisição Dinâmico: Inexistência de sistema de aquisição dinâmico\n9 - LOCAL DA EXECUÇÃO DO CONTRATO\nLOCAL DA EXECUÇÃO DO CONTRATO (PROCEDIMENTO)\nPaís: Portugal\nNUT III: PT11E\nLocalidade: Bragança\nDistrito: Braganca\nConcelho: Bragança\nFreguesia: Todas\n10 - PRAZO DE EXECUÇÃO DO CONTRATO\nPrazo de execução do contrato: 90 DIAS\nPrevisão de renovações: Não\n11 - FUNDOS EU\nTêm fundos EU? Sim\n12 - DOCUMENTOS DE HABILITAÇÃO\nHabilitação para o exercício da atividade profissional: Não\n13 - CONDIÇÕES DE APRESENTAÇÃO\nPlataforma eletrónica utilizada pela entidade adjudicante: VORTAL\nURL para Apresentação: https://community.vortal.biz/public/\nAdmissibilidade da apresentação de propostas variantes: Não autorizado\nPrazo para apresentação das propostas: 13-02-2026 18:00\nPrazo durante o qual os concorrentes são obrigados a manter as respetivas propostas: 90 dias a contar do termo do prazo para a apresentação das propostas\nApresentação de Catálogo Eletrónico: Permitido\nIndicação de Subcontratação na Proposta: Inexistência de indicação de subcontratação\n14 - PRESTAÇÃO DE CAUÇÃO\nPrestação de caução: Sim\nPercentagem: 5%\nDescrição da Garantia Exigida: Garantia bancária, Seguro de caução, Depósito bancário\n15 - FORNECIMENTO DAS PEÇAS DO CONCURSO, APRESENTAÇÃO DE PEDIDOS DE PARTICIPAÇÃO E APRESENTAÇÃO DAS PROPOSTAS\nLink para acesso às peças do concurso (URL): https://community.vortal.biz/Public/public-tender-documents/aXVlcUR5VUZDRmh1Wk80RGVHQktrRW90NnhrQUJ5QVV5eW94UzZoenFyTGwrY3k5dVJ1Um1NVStZcncwNEpHQ3pUWHZIaU9hUlNFM0l3bXhxclhwc0E9PWxKNjJC\n20 - OUTROS REQUISITOS\nInformação sobre contratos reservados. Aplica-se a contratos reservados (54º-A)? Não\n21 - CRITÉRIO DE ADJUDICAÇÃO\nMultifator: Sim\nFator: \nNome: Preço\nPonderação: 35%\nSubfatores: Não\nFator: \nNome: Qualidade\nPonderação: 60%\nSubfatores: Não\nFator: \nNome: Qualidade\nPonderação: 5%\nSubfatores: Não\n24 - CONDIÇÕES DO CONTRATO\nFaturação Eletrónica: Permitido\nObrigação de Subcontratação:\nCódigo da Obrigação de Subcontratação: Não é aplicável nenhuma obrigação de subcontratação.\n25 - COMPRA PÚBLICA ESTRATÉGICA\nCompra Pública Estratégica: Inexistência de contratação pública estratégica\n26 - INFORMAÇÕES ADICIONAIS\nContrato adequado para PME: Sim\nCobertura ACP (Acordo dos Contratos Públicos da Organização Mundial do Comércio): Não\n27 - IDENTIFICAÇÃO E CONTACTOS DO ÓRGÃO DE RECURSOS ADMINISTRATIVOS\nDesignação: Unidade Local de Saúde do Nordeste, E.P:E\nEndereço: Praça Cavaleiro Ferreira\nCódigo postal: 5301-862\nLocalidade: Bragança\nTelefone: +351 273302856\nFax: +351 273302858\nEndereço eletrónico: concursos@ulsne.min-saude.pt\n28 - IDENTIFICAÇÃO DO(S) AUTOR(ES) DE ANÚNCIO\nNome: Eng. António Martins\nCargo: Diretor do serviço de compras e logística\n419947977",
    "nipc": "509932584",
    "distrito": "Braganca",
    "concelho": "Bragança",
    "freguesia": "Todas",
    "site": "https://www.ulsne.min-saude.pt/",
    "email": "amartins@ulsne.min-saude.pt",
    "designacao_contrato": "61260005 - Fornecimento e instalação de tomografia computorizada",
    "descricao": "61260005 - Fornecimento e instalação de tomografia computorizada",
    "preco_base": "1.350.000,00 EUR",
    "prazo_execucao": "90 DIAS",
    "prazo_apresentacao_propostas": "13-02-2026 18:00",
    "fundos_eu": "Sim",
    "plataforma_eletronica": "VORTAL",
    "url_procedimento": "https://community.vortal.biz/public/",
    "autor_nome": "Eng. António Martins",
    "autor_cargo": "Diretor do serviço de compras e logística"
  },
  {
    "numero_procedimento": "N/A",
    "entidade": "Instituto Pedro Nunes - Associação para a Inovação e Desenvolvimento em Ciência e Tecnologia",
    "link": "https://diariodarepublica.pt/dr/detalhe/contrato-publico/932-1011853983",
    "detalhes_completos": "1 - IDENTIFICAÇÃO E CONTACTOS DA ENTIDADE ADJUDICANTE\nDesignação da entidade adjudicante: Instituto Pedro Nunes - Associação para a Inovação e Desenvolvimento em Ciência e Tecnologia\nNIPC: 502790610\nEndereço: Instituto Pedro Nunes - Rua Pedro Nunes\nCódigo postal: 3030-139\nLocalidade: Coimbra\nPaís: Portugal\nNUT III: PT16E\nDistrito: Coimbra\nConcelho: Coimbra\nFreguesia: Freguesia de Santo António dos Olivais\nTelefone: 239700900\nFax: 239700965\nEndereço da Entidade (URL): http://www.ipn.pt\nEndereço Eletrónico: compras.ipn@ipn.pt\nFunção da Organização: Adquirente\nNorma jurídica da Entidade Adjudicante: Autoridade da administração central\nÁrea de atividade da Autoridade Adjudicante: Assuntos económicos\n2 - JORNAL OFICIAL DA UNIÃO EUROPEIA\nO procedimento a que este anúncio diz respeito também é publicitado no Jornal Oficial da União Europeia? Sim\n3 - AVISO\nModelo de Anúncio: Concurso público\nData de Envio do Anúncio: 14-01-2026\n5 - PROCESSO\nTipo de Procedimento: Concurso público\nPreço base do procedimento: Sim\nValor do preço base do procedimento: 276.000,00 EUR\nProcedimento com lotes? Não\n6 - OBJETO DO CONTRATO\nNúmero de referência interna: IPN/DIRECÇÃO/2026/002\nDesignação do contrato: Aquisição de serviços de manutenção e limpeza para os edifícios do Instituto Pedro Nunes\nDescrição: Aquisição de serviços de manutenção e limpeza para os edifícios do Instituto Pedro Nunes\nOpções: Não\nTipo de Contrato Principal: Aquisição de Serviços\nTipo de Contrato: Aquisição de Serviços\nClassificação CPV (Vocabulário Comum para os Contratos Públicos)\nObjeto principal\nVocabulário Principal: 90910000\nPreço base s/IVA: 276.000,00 EUR\n7 - INDICAÇÕES ADICIONAIS\nO contrato envolve aquisição conjunta (satisfação de várias entidades)? Não\nO contrato é adjudicado por uma central de compras? Não\n8 - TÉCNICAS\nO concurso destina-se à celebração de um acordo-quadro? Inexistência de acordo-quadro\nÉ utilizado um leilão eletrónico? Não\nÉ adotada uma fase de negociação? Não\nSistema de Aquisição Dinâmico: Inexistência de sistema de aquisição dinâmico\n9 - LOCAL DA EXECUÇÃO DO CONTRATO\nLOCAL DA EXECUÇÃO DO CONTRATO (PROCEDIMENTO)\nPaís: Portugal\nNUT III: PT16E\nLocalidade: Coimbra\nDistrito: Coimbra\nConcelho: Coimbra\nFreguesia: Freguesia de Santo António dos Olivais\n10 - PRAZO DE EXECUÇÃO DO CONTRATO\nPrazo de execução do contrato: 12 MESES\nPrevisão de renovações: Sim\nIndicar número máximo de renovações: 2\nPrazo de renovações diferente do prazo inicial: Não\n11 - FUNDOS EU\nTêm fundos EU? Não\n12 - DOCUMENTOS DE HABILITAÇÃO\nHabilitação para o exercício da atividade profissional: Não\n13 - CONDIÇÕES DE APRESENTAÇÃO\nPlataforma eletrónica utilizada pela entidade adjudicante: COMPRASPT\nURL para Apresentação: https://www.compraspt.com/cpt-ipnunes/faces/\nAdmissibilidade da apresentação de propostas variantes: Não autorizado\nPrazo para apresentação das propostas: 17-02-2026 23:59\nPrazo durante o qual os concorrentes são obrigados a manter as respetivas propostas: 66 dias a contar do termo do prazo para a apresentação das propostas\nApresentação de Catálogo Eletrónico: Permitido\nIndicação de Subcontratação na Proposta: O(s) subcontratante(s) proposto(s) necessário(s) para cumprir a obrigação de subcontratar uma percentagem mínima do contrato\n14 - PRESTAÇÃO DE CAUÇÃO\nPrestação de caução: Não\n15 - FORNECIMENTO DAS PEÇAS DO CONCURSO, APRESENTAÇÃO DE PEDIDOS DE PARTICIPAÇÃO E APRESENTAÇÃO DAS PROPOSTAS\nLink para acesso às peças do concurso (URL): https://www.compraspt.com/cpt-ipnunes/faces/app/acessoDocs.jsp?codigoAcesso=CoOId5uRGxytsIewa05w1Y25F8RvCOP9v82GmQKEahW9t0uKE6\n20 - OUTROS REQUISITOS\nInformação sobre contratos reservados. Aplica-se a contratos reservados (54º-A)? Não\n21 - CRITÉRIO DE ADJUDICAÇÃO\nMultifator: Não\nMonofator:\nNome: Preço\n24 - CONDIÇÕES DO CONTRATO\nFaturação Eletrónica: Necessário\nObrigação de Subcontratação:\nCódigo da Obrigação de Subcontratação: Não é aplicável nenhuma obrigação de subcontratação.\n25 - COMPRA PÚBLICA ESTRATÉGICA\nCompra Pública Estratégica: Inexistência de contratação pública estratégica\n26 - INFORMAÇÕES ADICIONAIS\nContrato adequado para PME: Sim\nCobertura ACP (Acordo dos Contratos Públicos da Organização Mundial do Comércio): Não\n27 - IDENTIFICAÇÃO E CONTACTOS DO ÓRGÃO DE RECURSOS ADMINISTRATIVOS\nDesignação: Instituto Pedro Nunes\nEndereço: Rua Pedro Nunes\nCódigo postal: 3030-199\nLocalidade: Coimbra\nEndereço eletrónico: info@ipn.pt\n28 - IDENTIFICAÇÃO DO(S) AUTOR(ES) DE ANÚNCIO\nNome: Ana Raquel Lima Anjo\nCargo: Coordenadora de Departamento de Contratação Publica\n419948009",
    "nipc": "502790610",
    "distrito": "Coimbra",
    "concelho": "Coimbra",
    "freguesia": "Freguesia de Santo António dos Olivais",
    "site": "http://www.ipn.pt",
    "email": "compras.ipn@ipn.pt",
    "designacao_contrato": "Aquisição de serviços de manutenção e limpeza para os edifícios do Instituto Pedro Nunes",
    "descricao": "Aquisição de serviços de manutenção e limpeza para os edifícios do Instituto Pedro Nunes",
    "preco_base": "276.000,00 EUR",
    "prazo_execucao": "12 MESES",
    "prazo_apresentacao_propostas": "17-02-2026 23:59",
    "fundos_eu": "Não",
    "plataforma_eletronica": "COMPRASPT",
    "url_procedimento": "https://www.compraspt.com/cpt-ipnunes/faces/",
    "autor_nome": "Ana Raquel Lima Anjo",
    "autor_cargo": "Coordenadora de Departamento de Contratação Publica"
  },
  {
    "numero_procedimento": "N/A",
    "entidade": "AnÃºncio de procedimento  n.Âº 901/2026  -  DiÃ¡rio da RepÃºblica n.Âº 11/2026, SÃ©rie II de 2026-01-16",
    "link": "https://diariodarepublica.pt/dr/detalhe/contrato-publico/901-1013997908"
  },
  {
    "numero_procedimento": "N/A",
    "entidade": "AnÃºncio de procedimento  n.Âº 903/2026  -  DiÃ¡rio da RepÃºblica n.Âº 11/2026, SÃ©rie II de 2026-01-16",
    "link": "https://diariodarepublica.pt/dr/detalhe/contrato-publico/903-1013997909"
  },
  {
    "numero_procedimento": "N/A",
    "entidade": "Comunidade Intermunicipal da Região de Coimbra",
    "link": "https://diariodarepublica.pt/dr/detalhe/contrato-publico/905-1013997910",
    "detalhes_completos": "1 - IDENTIFICAÇÃO E CONTACTOS DA ENTIDADE ADJUDICANTE\nDesignação da entidade adjudicante: Comunidade Intermunicipal da Região de Coimbra\nNIPC: 508354617\nEndereço: Rua do Brasil, 131\nCódigo postal: 3030-175\nLocalidade: Coimbra\nPaís: Portugal\nNUT III: PTZZZ\nDistrito: Todos\nConcelho: Todos\nFreguesia: Todas\nTelefone: 239795200\nEndereço da Entidade (URL): https://cim-regiaodecoimbra.pt\nEndereço Eletrónico: geral@cim-regiaodecoimbra.pt\neDelivery Gateway (URL): https://www.acingov.pt\nFunção da Organização: Adquirente\nNorma jurídica da Entidade Adjudicante: Organismo de direito público\nÁrea de atividade da Autoridade Adjudicante: Serviços públicos das administrações públicas\n2 - JORNAL OFICIAL DA UNIÃO EUROPEIA\nO procedimento a que este anúncio diz respeito também é publicitado no Jornal Oficial da União Europeia? Sim\n3 - AVISO\nModelo de Anúncio: Concurso público\nData de Envio do Anúncio: 14-01-2026\n5 - PROCESSO\nTipo de Procedimento: Concurso público\nPreço base do procedimento: Sim\nValor do preço base do procedimento: 640.403,55 EUR\nProcedimento com lotes? Não\n6 - OBJETO DO CONTRATO\nNúmero de referência interna: CP27/2025\nDesignação do contrato: CP27/2025 - Aquisição de Serviços de EPD/DPO (Encarregado de Proteção de Dados/Data Protector Officer) - 36 meses\nDescrição: CP27/2025 - Aquisição de Serviços de EPD/DPO (Encarregado de Proteção de Dados/Data Protector Officer) - 36 meses\nOpções: Não\nTipo de Contrato Principal: Aquisição de Serviços\nTipo de Contrato: Aquisição de Serviços\nClassificação CPV (Vocabulário Comum para os Contratos Públicos)\nObjeto principal\nVocabulário Principal: 72310000\nPreço base s/IVA: 640.403,55 EUR\n7 - INDICAÇÕES ADICIONAIS\nO contrato envolve aquisição conjunta (satisfação de várias entidades)? Não\nO contrato é adjudicado por uma central de compras? Não\n8 - TÉCNICAS\nO concurso destina-se à celebração de um acordo-quadro? Inexistência de acordo-quadro\nÉ utilizado um leilão eletrónico? Não\nÉ adotada uma fase de negociação? Não\nSistema de Aquisição Dinâmico: Inexistência de sistema de aquisição dinâmico\n9 - LOCAL DA EXECUÇÃO DO CONTRATO\nLOCAL DA EXECUÇÃO DO CONTRATO (PROCEDIMENTO)\nPaís: Portugal\nNUT III: PT16E\nLocalidade: Freguesia de Santo António dos Olivais\nDistrito: Coimbra\nConcelho: Coimbra\nFreguesia: Freguesia de Santo António dos Olivais\n10 - PRAZO DE EXECUÇÃO DO CONTRATO\nPrazo de execução do contrato: 1095 DIAS\nPrevisão de renovações: Não\n11 - FUNDOS EU\nTêm fundos EU? Não\n12 - DOCUMENTOS DE HABILITAÇÃO\nHabilitação para o exercício da atividade profissional: Não\n13 - CONDIÇÕES DE APRESENTAÇÃO\nPlataforma eletrónica utilizada pela entidade adjudicante: ACIN\nURL para Apresentação: https://www.acingov.pt\nAdmissibilidade da apresentação de propostas variantes: Não autorizado\nPrazo para apresentação das propostas: 14-02-2026 23:59\nPrazo durante o qual os concorrentes são obrigados a manter as respetivas propostas: 120 dias a contar do termo do prazo para a apresentação das propostas\nApresentação de Catálogo Eletrónico: Permitido\nIndicação de Subcontratação na Proposta: Inexistência de indicação de subcontratação\n14 - PRESTAÇÃO DE CAUÇÃO\nPrestação de caução: Sim\nPercentagem: 5%\nDescrição da Garantia Exigida: O valor da caução é de 5.00% do preço contratual.\n15 - FORNECIMENTO DAS PEÇAS DO CONCURSO, APRESENTAÇÃO DE PEDIDOS DE PARTICIPAÇÃO E APRESENTAÇÃO DAS PROPOSTAS\nLink para acesso às peças do concurso (URL): https://www.acingov.pt/acingovprod/2/zonaPublica/zona_publica_c/donwloadProcedurePiece/MTA0ODExMg==\n20 - OUTROS REQUISITOS\nInformação sobre contratos reservados. Aplica-se a contratos reservados (54º-A)? Não\n21 - CRITÉRIO DE ADJUDICAÇÃO\nMultifator: Não\nMonofator:\nNome: Preço\n24 - CONDIÇÕES DO CONTRATO\nFaturação Eletrónica: Permitido\nObrigação de Subcontratação:\nCódigo da Obrigação de Subcontratação: Não é aplicável nenhuma obrigação de subcontratação.\n25 - COMPRA PÚBLICA ESTRATÉGICA\nCompra Pública Estratégica: Inexistência de contratação pública estratégica\n26 - INFORMAÇÕES ADICIONAIS\nContrato adequado para PME: Sim\nCobertura ACP (Acordo dos Contratos Públicos da Organização Mundial do Comércio): Não\n27 - IDENTIFICAÇÃO E CONTACTOS DO ÓRGÃO DE RECURSOS ADMINISTRATIVOS\nDesignação: Conselho Intermunicipal da Comunidade Intermunicipal da Região de Coimbra\nEndereço: Rua do Brasil, 131\nCódigo postal: 3030-175\nLocalidade: Coimbra\nTelefone: 239795200\nFax: 000000000\nEndereço eletrónico: geral@cim-regiaodecoimbra.pt\nPrazo de interposição do recurso: 5 dias\n28 - IDENTIFICAÇÃO DO(S) AUTOR(ES) DE ANÚNCIO\nNome: Jorge Brito\nCargo: Secretário Executivo Intermunicipal\n419947779",
    "nipc": "508354617",
    "distrito": "Todos",
    "concelho": "Todos",
    "freguesia": "Todas",
    "site": "https://cim-regiaodecoimbra.pt",
    "email": "geral@cim-regiaodecoimbra.pt",
    "designacao_contrato": "CP27/2025 - Aquisição de Serviços de EPD/DPO (Encarregado de Proteção de Dados/Data Protector Officer) - 36 meses",
    "descricao": "CP27/2025 - Aquisição de Serviços de EPD/DPO (Encarregado de Proteção de Dados/Data Protector Officer) - 36 meses",
    "preco_base": "640.403,55 EUR",
    "prazo_execucao": "1095 DIAS",
    "prazo_apresentacao_propostas": "14-02-2026 23:59",
    "fundos_eu": "Não",
    "plataforma_eletronica": "ACIN",
    "url_procedimento": "https://www.acingov.pt",
    "autor_nome": "Jorge Brito",
    "autor_cargo": "Secretário Executivo Intermunicipal"
  },
  {
    "numero_procedimento": "N/A",
    "entidade": "Município da Moita",
    "link": "https://diariodarepublica.pt/dr/detalhe/contrato-publico/907-1013997911",
    "detalhes_completos": "1 - IDENTIFICAÇÃO E CONTACTOS DA ENTIDADE ADJUDICANTE\nDesignação da entidade adjudicante: Município da Moita\nNIPC: 506791220\nServiço/Órgão/Pessoa de contacto: Júri\nEndereço: Praça da República\nCódigo postal: 2860-397\nLocalidade: Moita\nPaís: Portugal\nNUT III: PT170\nDistrito: Setúbal\nConcelho: Moita\nFreguesia: Todas\nTelefone: 212806700\nFax: 212806700\nEndereço da Entidade (URL): www.cm-moita.pt\nEndereço Eletrónico: gab.aprovisionamento@cm-moita.pt\neDelivery Gateway (URL): https://www.acingov.pt\nFunção da Organização: Adquirente\nNorma jurídica da Entidade Adjudicante: Organismo de direito público\nÁrea de atividade da Autoridade Adjudicante: Serviços públicos das administrações públicas\n2 - JORNAL OFICIAL DA UNIÃO EUROPEIA\nO procedimento a que este anúncio diz respeito também é publicitado no Jornal Oficial da União Europeia? Sim\n3 - AVISO\nModelo de Anúncio: Concurso público\nData de Envio do Anúncio: 14-01-2026\n5 - PROCESSO\nTipo de Procedimento: Concurso público\nPreço base do procedimento: Sim\nValor do preço base do procedimento: 1.036.469,52 EUR\nProcedimento com lotes? Sim\nNº Máx. de Lotes Autorizado: 2\nNúmero máximo de lotes que podem ser adjudicados a um concorrente: 2\n6 - OBJETO DO CONTRATO\nNúmero de referência interna: 31/CP/CMM/2025\nDesignação do contrato: Aquisição, por lotes, de Combustíveis Rodoviários e AdBlue em Bomba em Postos de Abastecimento Públicos\nDescrição: Aquisição, por lotes, de Combustíveis Rodoviários e AdBlue em Bomba em Postos de Abastecimento Públicos\nOpções: Não\nTipo de Contrato Principal: Aquisição de Bens Móveis\nTipo de Contrato: Aquisição de Bens Móveis\nClassificação CPV (Vocabulário Comum para os Contratos Públicos)\nObjeto principal\nVocabulário Principal: 09100000\nPreço base s/IVA: 1.036.469,52 EUR\nLotes: \nNº: LOT-0001\nDescrição do Lote: Aquisição de Combustíveis Rodoviários em Bomba em Postos de Abastecimento Públicos\nPreço base s/IVA: 1.017.406,44 EUR\nClassificação CPV (Vocabulário Comum para os Contratos Públicos)\nObjeto principal\nVocabulário Principal: 09100000\nNº: LOT-0002\nDescrição do Lote: Aquisição de AdBlue em Bomba em Postos de Abastecimento Públicos\nPreço base s/IVA: 19.063,08 EUR\nClassificação CPV (Vocabulário Comum para os Contratos Públicos)\nObjeto principal\nVocabulário Principal: 09100000\n7 - INDICAÇÕES ADICIONAIS\nO contrato envolve aquisição conjunta (satisfação de várias entidades)? Não\nO contrato é adjudicado por uma central de compras? Não\n8 - TÉCNICAS\nO concurso destina-se à celebração de um acordo-quadro? Inexistência de acordo-quadro\nÉ utilizado um leilão eletrónico? Não\nÉ adotada uma fase de negociação? Não\nSistema de Aquisição Dinâmico: Inexistência de sistema de aquisição dinâmico\n9 - LOCAL DA EXECUÇÃO DO CONTRATO\nLOCAL DA EXECUÇÃO DO CONTRATO (PROCEDIMENTO)\nPaís: Portugal\nNUT III: PT170\nLocalidade: Moita\nDistrito: Setúbal\nConcelho: Moita\nFreguesia: Todas\nLOCAL DA EXECUÇÃO DO CONTRATO (LOTE)\nIdentificador do Lote: LOT-0001; LOT-0002\nPaís: Portugal\nNUT III: PT170\nLocalidade: Moita\nDistrito: Setúbal\nConcelho: Moita\nFreguesia: Todas\n10 - PRAZO DE EXECUÇÃO DO CONTRATO\nIdentificador do Lote: LOT-0001; LOT-0002\nData de Início: 11-05-2026\nData de Fim: 10-05-2029\nPrevisão de renovações: Não\n11 - FUNDOS EU\nIdentificador do Lote: LOT-0001; LOT-0002\nTêm fundos EU? Não\n12 - DOCUMENTOS DE HABILITAÇÃO\nHabilitação para o exercício da atividade profissional: Não\n13 - CONDIÇÕES DE APRESENTAÇÃO\nPlataforma eletrónica utilizada pela entidade adjudicante: ACIN\nURL para Apresentação: https://www.acingov.pt\nAdmissibilidade da apresentação de propostas variantes: Não autorizado\nPrazo para apresentação das propostas: 13-02-2026 23:59\nPrazo durante o qual os concorrentes são obrigados a manter as respetivas propostas: 90 dias a contar do termo do prazo para a apresentação das propostas\nApresentação de Catálogo Eletrónico: Não autorizado\nIndicação de Subcontratação na Proposta: Inexistência de indicação de subcontratação\n14 - PRESTAÇÃO DE CAUÇÃO\nPrestação de caução: Sim\nPercentagem: 5%\nDescrição da Garantia Exigida: O valor da caução é de 5.00% do preço contratual.\n15 - FORNECIMENTO DAS PEÇAS DO CONCURSO, APRESENTAÇÃO DE PEDIDOS DE PARTICIPAÇÃO E APRESENTAÇÃO DAS PROPOSTAS\nLink para acesso às peças do concurso (URL): https://www.acingov.pt/acingovprod/2/zonaPublica/zona_publica_c/donwloadProcedurePiece/MTA0ODAwNw==\n20 - OUTROS REQUISITOS\nIdentificador do Lote: LOT-0001; LOT-0002\nInformação sobre contratos reservados. Aplica-se a contratos reservados (54º-A)? Não\n21 - CRITÉRIO DE ADJUDICAÇÃO\nO Critério de adjudicação é diferenciado por lote? Não\nMultifator: Não\nMonofator:\nNome: Preço\n24 - CONDIÇÕES DO CONTRATO\nIdentificador do Lote: LOT-0001; LOT-0002\nFaturação Eletrónica: Permitido\nObrigação de Subcontratação:\nCódigo da Obrigação de Subcontratação: Não é aplicável nenhuma obrigação de subcontratação.\n25 - COMPRA PÚBLICA ESTRATÉGICA\nCompra Pública Estratégica: Inexistência de contratação pública estratégica\n26 - INFORMAÇÕES ADICIONAIS\nIdentificador do Lote: LOT-0001; LOT-0002\nContrato adequado para PME: Sim\nCobertura ACP (Acordo dos Contratos Públicos da Organização Mundial do Comércio): Não\n27 - IDENTIFICAÇÃO E CONTACTOS DO ÓRGÃO DE RECURSOS ADMINISTRATIVOS\nDesignação: Presidente da Câmara\nEndereço: Praça da República\nCódigo postal: 2860-397\nLocalidade: Moita\nTelefone: 212806700\nFax: \nEndereço eletrónico: gab.aprovisionamento@cm-moita.pt\nPrazo de interposição do recurso: 10 dias\n28 - IDENTIFICAÇÃO DO(S) AUTOR(ES) DE ANÚNCIO\nNome: Carlos Edgar Rodrigues Sá Albino\nCargo: Presidente da Câmara\n419947797",
    "nipc": "506791220",
    "distrito": "Setúbal",
    "concelho": "Moita",
    "freguesia": "Todas",
    "site": "www.cm-moita.pt",
    "email": "gab.aprovisionamento@cm-moita.pt",
    "designacao_contrato": "Aquisição, por lotes, de Combustíveis Rodoviários e AdBlue em Bomba em Postos de Abastecimento Públicos",
    "descricao": "Aquisição, por lotes, de Combustíveis Rodoviários e AdBlue em Bomba em Postos de Abastecimento Públicos",
    "preco_base": "1.036.469,52 EUR",
    "prazo_execucao": null,
    "prazo_apresentacao_propostas": "13-02-2026 23:59",
    "fundos_eu": "Não",
    "plataforma_eletronica": "ACIN",
    "url_procedimento": "https://www.acingov.pt",
    "autor_nome": "Carlos Edgar Rodrigues Sá Albino",
    "autor_cargo": "Presidente da Câmara"
  },
  {
    "numero_procedimento": "N/A",
    "entidade": "AnÃºncio de procedimento  n.Âº 909/2026  -  DiÃ¡rio da RepÃºblica n.Âº 11/2026, SÃ©rie II de 2026-01-16",
    "link": "https://diariodarepublica.pt/dr/detalhe/contrato-publico/909-1013997912"
  },
  {
    "numero_procedimento": "N/A",
    "entidade": "AnÃºncio de procedimento  n.Âº 911/2026  -  DiÃ¡rio da RepÃºblica n.Âº 11/2026, SÃ©rie II de 2026-01-16",
    "link": "https://diariodarepublica.pt/dr/detalhe/contrato-publico/911-1013997913"
  },
  {
    "numero_procedimento": "N/A",
    "entidade": "AnÃºncio de procedimento  n.Âº 913/2026  -  DiÃ¡rio da RepÃºblica n.Âº 11/2026, SÃ©rie II de 2026-01-16",
    "link": "https://diariodarepublica.pt/dr/detalhe/contrato-publico/913-1013997914"
  },
  {
    "numero_procedimento": "N/A",
    "entidade": "AnÃºncio de procedimento  n.Âº 915/2026  -  DiÃ¡rio da RepÃºblica n.Âº 11/2026, SÃ©rie II de 2026-01-16",
    "link": "https://diariodarepublica.pt/dr/detalhe/contrato-publico/915-1013997915"
  },
  {
    "numero_procedimento": "N/A",
    "entidade": "Instituto Português de Oncologia do Porto Francisco Gentil, EPE",
    "link": "https://diariodarepublica.pt/dr/detalhe/contrato-publico/917-1013997916",
    "detalhes_completos": "Alteração do Anúncio de procedimento n.º 32853/2025, de 2025-12-18, com o ID 419883033\n1 - IDENTIFICAÇÃO E CONTACTOS DA ENTIDADE ADJUDICANTE\nDesignação da entidade adjudicante: Instituto Português de Oncologia do Porto Francisco Gentil, EPE\nNIPC: 506362299\nEndereço: Rua Drº António Bernardino De Almeida S/N, Porto\nCódigo postal: 4200-072\nLocalidade: Área Metropolitana do Porto\nPaís: Portugal\nNUT III: PT11A\nDistrito: Porto\nConcelho: Porto\nFreguesia: Todas\nTelefone: 225084000\nFax: 225084001\nEndereço da Entidade (URL): http://www.ipoporto.pt/\nEndereço Eletrónico: compras@ipoporto.min-saude.pt\neDelivery Gateway (URL): https://community.vortal.biz/public/\nFunção da Organização: Adquirente\nNorma jurídica da Entidade Adjudicante: Organismo de direito público\nÁrea de atividade da Autoridade Adjudicante: Saúde\n2 - JORNAL OFICIAL DA UNIÃO EUROPEIA\nO procedimento a que este anúncio diz respeito também é publicitado no Jornal Oficial da União Europeia? Sim\n3 - AVISO\nModelo de Anúncio: Concurso público\nData de Envio do Anúncio: 14-01-2026\n5 - PROCESSO\nTipo de Procedimento: Concurso público\nPreço base do procedimento: Sim\nValor do preço base do procedimento: 850.174,93 EUR\nProcedimento com lotes? Não\n6 - OBJETO DO CONTRATO\nNúmero de referência interna: CP 4184/25\nDesignação do contrato: CP 4184/25 - Aquisição de Gases Medicinais\nDescrição: CP 4184/25 - Aquisição de Gases Medicinais\nOpções: Não\nTipo de Contrato Principal: Aquisição de Bens Móveis\nTipo de Contrato: Aquisição de Bens Móveis\nClassificação CPV (Vocabulário Comum para os Contratos Públicos)\nObjeto principal\nVocabulário Principal: 24111500\nPreço base s/IVA: 850.174,93 EUR\n7 - INDICAÇÕES ADICIONAIS\nO contrato envolve aquisição conjunta (satisfação de várias entidades)? Não\nO contrato é adjudicado por uma central de compras? Não\n8 - TÉCNICAS\nO concurso destina-se à celebração de um acordo-quadro? Inexistência de acordo-quadro\nÉ utilizado um leilão eletrónico? Não\nÉ adotada uma fase de negociação? Não\nSistema de Aquisição Dinâmico: Inexistência de sistema de aquisição dinâmico\n9 - LOCAL DA EXECUÇÃO DO CONTRATO\nLOCAL DA EXECUÇÃO DO CONTRATO (PROCEDIMENTO)\nPaís: Portugal\nNUT III: PT11A\nLocalidade: Área Metropolitana do Porto\nDistrito: Porto\nConcelho: Porto\nFreguesia: Freguesia de Paranhos - Porto\n10 - PRAZO DE EXECUÇÃO DO CONTRATO\nPrazo de execução do contrato: 3 ANOS\nPrevisão de renovações: Não\n11 - FUNDOS EU\nTêm fundos EU? Não\n12 - DOCUMENTOS DE HABILITAÇÃO\nHabilitação para o exercício da atividade profissional: Não\n13 - CONDIÇÕES DE APRESENTAÇÃO\nPlataforma eletrónica utilizada pela entidade adjudicante: VORTAL\nURL para Apresentação: https://community.vortal.biz/public/\nAdmissibilidade da apresentação de propostas variantes: Não autorizado\nPrazo para apresentação das propostas: 16-02-2026 17:00\nPrazo durante o qual os concorrentes são obrigados a manter as respetivas propostas: 120 dias a contar do termo do prazo para a apresentação das propostas\nApresentação de Catálogo Eletrónico: Não autorizado\nIndicação de Subcontratação na Proposta: Inexistência de indicação de subcontratação\n14 - PRESTAÇÃO DE CAUÇÃO\nPrestação de caução: Sim\nPercentagem: 5%\nDescrição da Garantia Exigida: garantia bancária ou depósito bancário ou seguro-caução \n15 - FORNECIMENTO DAS PEÇAS DO CONCURSO, APRESENTAÇÃO DE PEDIDOS DE PARTICIPAÇÃO E APRESENTAÇÃO DAS PROPOSTAS\nLink para acesso às peças do concurso (URL): https://community.vortal.biz/Public/public-tender-documents/bUdHOU12d2JxMlJRbXl2dHJibDI0YkprUi9Jd041cUFORW5LcXU1VWpnZndkRFl2OHFoRXhlZ1ozQ044ak0yYnluMWFta2RRVmlTdHBFcHRwNkJjdVE9PSYpTlJU\n20 - OUTROS REQUISITOS\nInformação sobre contratos reservados. Aplica-se a contratos reservados (54º-A)? Não\n21 - CRITÉRIO DE ADJUDICAÇÃO\nMultifator: Sim\nFator: \nNome: Preço\nPonderação: 60%\nSubfatores: Não\nFator: \nNome: Qualidade\nPonderação: 10%\nSubfatores: Não\nFator: \nNome: Qualidade\nPonderação: 10%\nSubfatores: Não\nFator: \nNome: Qualidade\nPonderação: 20%\nSubfatores: Não\n24 - CONDIÇÕES DO CONTRATO\nFaturação Eletrónica: Permitido\nObrigação de Subcontratação:\nCódigo da Obrigação de Subcontratação: Não é aplicável nenhuma obrigação de subcontratação.\n25 - COMPRA PÚBLICA ESTRATÉGICA\nCompra Pública Estratégica: Inexistência de contratação pública estratégica\n26 - INFORMAÇÕES ADICIONAIS\nContrato adequado para PME: Sim\nCobertura ACP (Acordo dos Contratos Públicos da Organização Mundial do Comércio): Não\n27 - IDENTIFICAÇÃO E CONTACTOS DO ÓRGÃO DE RECURSOS ADMINISTRATIVOS\nDesignação: Conselho de Administração\nEndereço: Rua Dr. António Bernardino de Almeida\nCódigo postal: 4200-072\nLocalidade: Porto\nTelefone: +351 225084000\nFax: +351 225084000\nEndereço eletrónico: compras@ipoporto.min-saude.pt\n28 - IDENTIFICAÇÃO DO(S) AUTOR(ES) DE ANÚNCIO\nNome: Dra. Sandra Luís\nCargo: Diretora do Serviço de Aprovisionamento e Logistica\n29 - ALTERAÇÃO\nMotivo da Alteração: Correção pelo adquirente\nIdentificador da Versão do Anúncio a Alterar: fe54299e-0bf5-4160-be43-9443ccb0ddf5-01\nIdentificador das Secções Alteradas do Anúncio Anterior: Condições de Apresentação\nDescrição das Alterações: Prorrogação do prazo para a apresentação de propostas.\nAlteração dos Documentos do Concurso: Sim\nData de alteração dos documentos do concurso: 14-01-2026\n419947905",
    "nipc": "506362299",
    "distrito": "Porto",
    "concelho": "Porto",
    "freguesia": "Todas",
    "site": "http://www.ipoporto.pt/",
    "email": "compras@ipoporto.min-saude.pt",
    "designacao_contrato": "CP 4184/25 - Aquisição de Gases Medicinais",
    "descricao": "CP 4184/25 - Aquisição de Gases Medicinais",
    "preco_base": "850.174,93 EUR",
    "prazo_execucao": "3 ANOS",
    "prazo_apresentacao_propostas": "16-02-2026 17:00",
    "fundos_eu": "Não",
    "plataforma_eletronica": "VORTAL",
    "url_procedimento": "https://community.vortal.biz/public/",
    "autor_nome": "Dra. Sandra Luís",
    "autor_cargo": "Diretora do Serviço de Aprovisionamento e Logistica"
  },
  {
    "numero_procedimento": "N/A",
    "entidade": "AnÃºncio de procedimento  n.Âº 919/2026  -  DiÃ¡rio da RepÃºblica n.Âº 11/2026, SÃ©rie II de 2026-01-16",
    "link": "https://diariodarepublica.pt/dr/detalhe/contrato-publico/919-1013997917"
  },
  {
    "numero_procedimento": "N/A",
    "entidade": "Associação Humanitária dos Bombeiros Voluntários de Esmoriz",
    "link": "https://diariodarepublica.pt/dr/detalhe/contrato-publico/921-1013997918",
    "detalhes_completos": "1 - IDENTIFICAÇÃO E CONTACTOS DA ENTIDADE ADJUDICANTE\nDesignação da entidade adjudicante: Associação Humanitária dos Bombeiros Voluntários de Esmoriz\nNIPC: 501163255\nEndereço: AV. dos Correios - Apartado, 49\nCódigo postal: 3886-909\nLocalidade: Ovar\nPaís: Portugal\nNUT III: PT16D\nDistrito: Aveiro\nConcelho: Ovar\nFreguesia: Todas\nTelefone: 256752122\nFax: 256752122\nEndereço da Entidade (URL): https://bvesmoriz.pt/\nEndereço Eletrónico: bombeiros.esmoriz@netvisao.pt\neDelivery Gateway (URL): https://community.vortal.biz/public/\nFunção da Organização: Adquirente\nNorma jurídica da Entidade Adjudicante: Autoridade da administração central\nÁrea de atividade da Autoridade Adjudicante: Proteção ambiental\n2 - JORNAL OFICIAL DA UNIÃO EUROPEIA\nO procedimento a que este anúncio diz respeito também é publicitado no Jornal Oficial da União Europeia? Sim\n3 - AVISO\nModelo de Anúncio: Concurso público\nData de Envio do Anúncio: 14-01-2026\n5 - PROCESSO\nTipo de Procedimento: Concurso público\nPreço base do procedimento: Sim\nValor do preço base do procedimento: 233.561,16 EUR\nProcedimento com lotes? Não\n6 - OBJETO DO CONTRATO\nNúmero de referência interna: CP02/2025\nDesignação do contrato: Aquisição de Veículo Florestal de Combate a Incêndios \nDescrição: Aquisição de Veículo Florestal de Combate a Incêndios \nOpções: Não\nTipo de Contrato Principal: Aquisição de Bens Móveis\nTipo de Contrato: Aquisição de Bens Móveis\nClassificação CPV (Vocabulário Comum para os Contratos Públicos)\nObjeto principal\nVocabulário Principal: 34144210\nPreço base s/IVA: 233.561,16 EUR\n7 - INDICAÇÕES ADICIONAIS\nO contrato envolve aquisição conjunta (satisfação de várias entidades)? Não\nO contrato é adjudicado por uma central de compras? Não\n8 - TÉCNICAS\nO concurso destina-se à celebração de um acordo-quadro? Inexistência de acordo-quadro\nÉ utilizado um leilão eletrónico? Não\nÉ adotada uma fase de negociação? Não\nSistema de Aquisição Dinâmico: Inexistência de sistema de aquisição dinâmico\n9 - LOCAL DA EXECUÇÃO DO CONTRATO\nLOCAL DA EXECUÇÃO DO CONTRATO (PROCEDIMENTO)\nPaís: Portugal\nNUT III: PT16D\nLocalidade: Aveiro\nDistrito: Aveiro\nConcelho: Ovar\nFreguesia: Todas\n10 - PRAZO DE EXECUÇÃO DO CONTRATO\nPrazo de execução do contrato: 12 MESES\nPrevisão de renovações: Não\n11 - FUNDOS EU\nTêm fundos EU? Sim\n12 - DOCUMENTOS DE HABILITAÇÃO\nHabilitação para o exercício da atividade profissional: Não\n13 - CONDIÇÕES DE APRESENTAÇÃO\nPlataforma eletrónica utilizada pela entidade adjudicante: VORTAL\nURL para Apresentação: https://community.vortal.biz/public/\nAdmissibilidade da apresentação de propostas variantes: Não autorizado\nPrazo para apresentação das propostas: 15-02-2026 17:00\nPrazo durante o qual os concorrentes são obrigados a manter as respetivas propostas: 66 dias a contar do termo do prazo para a apresentação das propostas\nApresentação de Catálogo Eletrónico: Não autorizado\nIndicação de Subcontratação na Proposta: Inexistência de indicação de subcontratação\n14 - PRESTAÇÃO DE CAUÇÃO\nPrestação de caução: Não\n15 - FORNECIMENTO DAS PEÇAS DO CONCURSO, APRESENTAÇÃO DE PEDIDOS DE PARTICIPAÇÃO E APRESENTAÇÃO DAS PROPOSTAS\nLink para acesso às peças do concurso (URL): https://community.vortal.biz/Public/public-tender-documents/aVVuNWNEcWR2WXdJYUpaOU1meE00U3hMSFNLcWd3U1BhdmtoeGk2RDVNNUR0NTR2YVJFV2pYWW9TYmdrcjZHV25STEJxTXVLK0xFc21OT1duNndwd1E9PUxucDkw\n20 - OUTROS REQUISITOS\nInformação sobre contratos reservados. Aplica-se a contratos reservados (54º-A)? Não\n21 - CRITÉRIO DE ADJUDICAÇÃO\nMultifator: Sim\nFator: \nNome: Preço\nPonderação: 10%\nSubfatores: Não\nFator: \nNome: Qualidade\nPonderação: 70%\nSubfatores: Não\nFator: \nNome: Outros\nOutro Nome: Prazo de entrega\nPonderação: 10%\nSubfatores: Não\nFator: \nNome: Outros\nOutro Nome: Prazo de garantia\nPonderação: 10%\nSubfatores: Não\n24 - CONDIÇÕES DO CONTRATO\nFaturação Eletrónica: Permitido\nObrigação de Subcontratação:\nCódigo da Obrigação de Subcontratação: Não é aplicável nenhuma obrigação de subcontratação.\n25 - COMPRA PÚBLICA ESTRATÉGICA\nCompra Pública Estratégica: Inexistência de contratação pública estratégica\n26 - INFORMAÇÕES ADICIONAIS\nContrato adequado para PME: Sim\nCobertura ACP (Acordo dos Contratos Públicos da Organização Mundial do Comércio): Não\n27 - IDENTIFICAÇÃO E CONTACTOS DO ÓRGÃO DE RECURSOS ADMINISTRATIVOS\nDesignação: Élia Maria Palma Mansinho Santos Silva\nEndereço: Avenida dos Correios, 480 3885-411 Esmoriz, Portugal\nCódigo postal: 3885-411\nLocalidade: Ovar\nTelefone: +351 256382051\nFax: +351 256382051\nEndereço eletrónico: direcao@bvesmoriz.pt\n28 - IDENTIFICAÇÃO DO(S) AUTOR(ES) DE ANÚNCIO\nNome: Daniel Lemos Marques\nCargo: Secretário\n419947933",
    "nipc": "501163255",
    "distrito": "Aveiro",
    "concelho": "Ovar",
    "freguesia": "Todas",
    "site": "https://bvesmoriz.pt/",
    "email": "bombeiros.esmoriz@netvisao.pt",
    "designacao_contrato": "Aquisição de Veículo Florestal de Combate a Incêndios",
    "descricao": "Aquisição de Veículo Florestal de Combate a Incêndios",
    "preco_base": "233.561,16 EUR",
    "prazo_execucao": "12 MESES",
    "prazo_apresentacao_propostas": "15-02-2026 17:00",
    "fundos_eu": "Sim",
    "plataforma_eletronica": "VORTAL",
    "url_procedimento": "https://community.vortal.biz/public/",
    "autor_nome": "Daniel Lemos Marques",
    "autor_cargo": "Secretário"
  },
  {
    "numero_procedimento": "N/A",
    "entidade": "AnÃºncio de procedimento  n.Âº 923/2026  -  DiÃ¡rio da RepÃºblica n.Âº 11/2026, SÃ©rie II de 2026-01-16",
    "link": "https://diariodarepublica.pt/dr/detalhe/contrato-publico/923-1013997919"
  },
  {
    "numero_procedimento": "N/A",
    "entidade": "AnÃºncio de procedimento  n.Âº 925/2026  -  DiÃ¡rio da RepÃºblica n.Âº 11/2026, SÃ©rie II de 2026-01-16",
    "link": "https://diariodarepublica.pt/dr/detalhe/contrato-publico/925-1013997920"
  },
  {
    "numero_procedimento": "N/A",
    "entidade": "AnÃºncio de procedimento  n.Âº 927/2026  -  DiÃ¡rio da RepÃºblica n.Âº 11/2026, SÃ©rie II de 2026-01-16",
    "link": "https://diariodarepublica.pt/dr/detalhe/contrato-publico/927-1013997921"
  },
  {
    "numero_procedimento": "N/A",
    "entidade": "Autoridade Nacional da Aviação Civil",
    "link": "https://diariodarepublica.pt/dr/detalhe/contrato-publico/929-1013997922",
    "detalhes_completos": "1 - IDENTIFICAÇÃO E CONTACTOS DA ENTIDADE ADJUDICANTE\nDesignação da entidade adjudicante: Autoridade Nacional da Aviação Civil\nNIPC: 504288806\nEndereço: Rua B, Edifício 4 - Aeroporto Humberto Delgado\nCódigo postal: 1749-034\nLocalidade: Lisboa\nPaís: Portugal\nNUT III: PT170\nDistrito: Lisboa\nConcelho: Lisboa\nFreguesia: Todas\nTelefone: +351212842226\nFax: 218473585\nEndereço da Entidade (URL): www.anac.pt\nEndereço Eletrónico: geral@anac.pt\neDelivery Gateway (URL): https://community.vortal.biz/public/\nFunção da Organização: Adquirente\nNorma jurídica da Entidade Adjudicante: Organismo de direito público\nÁrea de atividade da Autoridade Adjudicante: Segurança e ordem pública\n2 - JORNAL OFICIAL DA UNIÃO EUROPEIA\nO procedimento a que este anúncio diz respeito também é publicitado no Jornal Oficial da União Europeia? Sim\n3 - AVISO\nModelo de Anúncio: Concurso público\nData de Envio do Anúncio: 14-01-2026\n5 - PROCESSO\nTipo de Procedimento: Concurso público\nPreço base do procedimento: Sim\nValor do preço base do procedimento: 305.000,00 EUR\nProcedimento com lotes? Não\n6 - OBJETO DO CONTRATO\nNúmero de referência interna: 14.01.02.00207.2025\nDesignação do contrato: Aquisição de serviços de elaboração de estudo relativo ao estabelecimento de regras e procedimentos para as alterações às restrições de operação relacionadas com o ruído no aeroporto Humberto Delgado\nDescrição: Aquisição de serviços de elaboração de estudo relativo ao estabelecimento de regras e procedimentos para as alterações às restrições de operação relacionadas com o ruído no aeroporto Humberto Delgado no âmbito de uma abordagem equilibrada\nOpções: Não\nTipo de Contrato Principal: Aquisição de Serviços\nTipo de Contrato: Aquisição de Serviços\nClassificação CPV (Vocabulário Comum para os Contratos Públicos)\nObjeto principal\nVocabulário Principal: 71313100\nPreço base s/IVA: 305.000,00 EUR\n7 - INDICAÇÕES ADICIONAIS\nO contrato envolve aquisição conjunta (satisfação de várias entidades)? Não\nO contrato é adjudicado por uma central de compras? Não\n8 - TÉCNICAS\nO concurso destina-se à celebração de um acordo-quadro? Inexistência de acordo-quadro\nÉ utilizado um leilão eletrónico? Não\nÉ adotada uma fase de negociação? Não\nSistema de Aquisição Dinâmico: Inexistência de sistema de aquisição dinâmico\n9 - LOCAL DA EXECUÇÃO DO CONTRATO\nLOCAL DA EXECUÇÃO DO CONTRATO (PROCEDIMENTO)\nPaís: Portugal\nNUT III: PT170\nLocalidade: Lisboa\nDistrito: Lisboa\nConcelho: Lisboa\nFreguesia: Freguesia de Olivais\n10 - PRAZO DE EXECUÇÃO DO CONTRATO\nPrazo de execução do contrato: 180 DIAS\nPrevisão de renovações: Não\n11 - FUNDOS EU\nTêm fundos EU? Não\n12 - DOCUMENTOS DE HABILITAÇÃO\nHabilitação para o exercício da atividade profissional: Não\n13 - CONDIÇÕES DE APRESENTAÇÃO\nPlataforma eletrónica utilizada pela entidade adjudicante: VORTAL\nURL para Apresentação: https://community.vortal.biz/public/\nAdmissibilidade da apresentação de propostas variantes: Não autorizado\nPrazo para apresentação das propostas: 13-02-2026 23:59\nPrazo durante o qual os concorrentes são obrigados a manter as respetivas propostas: 66 dias a contar do termo do prazo para a apresentação das propostas\nApresentação de Catálogo Eletrónico: Não autorizado\nIndicação de Subcontratação na Proposta: Inexistência de indicação de subcontratação\n14 - PRESTAÇÃO DE CAUÇÃO\nPrestação de caução: Não\n15 - FORNECIMENTO DAS PEÇAS DO CONCURSO, APRESENTAÇÃO DE PEDIDOS DE PARTICIPAÇÃO E APRESENTAÇÃO DAS PROPOSTAS\nLink para acesso às peças do concurso (URL): https://community.vortal.biz/Public/public-tender-documents/c1RXbFFrb1JucEZYVmFKRkFnNG1JaDNjKy93TWFtNU5ETXhPWmY1aCs0SkRjZjZkVU0rNlNOVnY3MWUvdThNdnJRSWxJdmJyc1FDUlhBWTFmdU1BK3c9PUt1SzFN\n20 - OUTROS REQUISITOS\nInformação sobre contratos reservados. Aplica-se a contratos reservados (54º-A)? Não\n21 - CRITÉRIO DE ADJUDICAÇÃO\nMultifator: Sim\nFator: \nNome: Qualidade\nPonderação: 40%\nSubfatores: Não\nFator: \nNome: Qualidade\nPonderação: 35%\nSubfatores: Não\nFator: \nNome: Preço\nPonderação: 25%\nSubfatores: Não\n24 - CONDIÇÕES DO CONTRATO\nFaturação Eletrónica: Permitido\nObrigação de Subcontratação:\nCódigo da Obrigação de Subcontratação: Não é aplicável nenhuma obrigação de subcontratação.\n25 - COMPRA PÚBLICA ESTRATÉGICA\nCompra Pública Estratégica: Inexistência de contratação pública estratégica\n26 - INFORMAÇÕES ADICIONAIS\nContrato adequado para PME: Sim\nCobertura ACP (Acordo dos Contratos Públicos da Organização Mundial do Comércio): Não\n27 - IDENTIFICAÇÃO E CONTACTOS DO ÓRGÃO DE RECURSOS ADMINISTRATIVOS\nDesignação: Tribunal Administrativo de Círculo Administrativo de Lisboa\nEndereço: Av. D. João II, 1.08.01 Edifício G, 6.º\nCódigo postal: 1900-097\nLocalidade: Lisboa\nTelefone: +351 218367100\nFax: +351 211545188\nEndereço eletrónico: lisboa.tca@tribunais.pt\n28 - IDENTIFICAÇÃO DO(S) AUTOR(ES) DE ANÚNCIO\nNome: Aníbal Pinto\nCargo: Chefe do Departamento de Contratação Pública\n419947974",
    "nipc": "504288806",
    "distrito": "Lisboa",
    "concelho": "Lisboa",
    "freguesia": "Todas",
    "site": "www.anac.pt",
    "email": "geral@anac.pt",
    "designacao_contrato": "Aquisição de serviços de elaboração de estudo relativo ao estabelecimento de regras e procedimentos para as alterações às restrições de operação relacionadas com o ruído no aeroporto Humberto Delgado",
    "descricao": "Aquisição de serviços de elaboração de estudo relativo ao estabelecimento de regras e procedimentos para as alterações às restrições de operação relacionadas com o ruído no aeroporto Humberto Delgado no âmbito de uma abordagem equilibrada",
    "preco_base": "305.000,00 EUR",
    "prazo_execucao": "180 DIAS",
    "prazo_apresentacao_propostas": "13-02-2026 23:59",
    "fundos_eu": "Não",
    "plataforma_eletronica": "VORTAL",
    "url_procedimento": "https://community.vortal.biz/public/",
    "autor_nome": "Aníbal Pinto",
    "autor_cargo": "Chefe do Departamento de Contratação Pública"
  },
  {
    "numero_procedimento": "N/A",
    "entidade": "INESC ID - Instituto de Engenharia de Sistemas e Computadores, Investigação e Desenvolvimento em Lisboa",
    "link": "https://diariodarepublica.pt/dr/detalhe/contrato-publico/931-1013997923",
    "detalhes_completos": "Alteração do Anúncio de procedimento n.º 32701/2025, de 2025-12-17, com o ID 419883463\n1 - IDENTIFICAÇÃO E CONTACTOS DA ENTIDADE ADJUDICANTE\nDesignação da entidade adjudicante: INESC ID - Instituto de Engenharia de Sistemas e Computadores, Investigação e Desenvolvimento em Lisboa\nNIPC: 504547593\nServiço/Órgão/Pessoa de contacto: GJ\nEndereço: R. Alves Redol, 9\nCódigo postal: 1000-029\nLocalidade: Lisboa\nPaís: Portugal\nNUT III: PT170\nDistrito: Lisboa\nConcelho: Lisboa\nFreguesia: Freguesia de Areeiro\nTelefone: 213100300\nFax: 213145843\nEndereço da Entidade (URL): http://www.inesc-id.pt/\nEndereço Eletrónico: info@inesc-id.pt\neDelivery Gateway (URL): https://www.acingov.pt\nFunção da Organização: Adquirente\nNorma jurídica da Entidade Adjudicante: Organismo de direito público\nÁrea de atividade da Autoridade Adjudicante: Educação\n2 - JORNAL OFICIAL DA UNIÃO EUROPEIA\nO procedimento a que este anúncio diz respeito também é publicitado no Jornal Oficial da União Europeia? Sim\n3 - AVISO\nModelo de Anúncio: Concurso público\nData de Envio do Anúncio: 14-01-2026\n5 - PROCESSO\nTipo de Procedimento: Concurso público\nPreço base do procedimento: Sim\nValor do preço base do procedimento: 868.500,00 EUR\nProcedimento com lotes? Sim\nNº Máx. de Lotes Autorizado: 13\nNúmero máximo de lotes que podem ser adjudicados a um concorrente: 13\n6 - OBJETO DO CONTRATO\nNúmero de referência interna: CPI_BM 035/2025\nDesignação do contrato: Aquisição de equipamento informático\nDescrição: Aquisição de equipamento informático, de acordo com os seguintes lotes:\nLote 1 - Servidores de computação 1\nLote 2 - Servidores de computação 2\nLote 3 - Servidores de serviços (Rua Alves Redol)\nLote 4 - Servidores de serviços (Taguspark)\nLote 5 - Workstation Gráfica\nLote 6 - Servidor Compute Express Link (CXL)\nLote 7 - High-speed link\nLote 8 - Servidor de grande escalabilidade\nLote 9 - Servidor Field Programmable Gate Array (FPGA)\nLote 10 - Equipamento de rede (switches)\nLote 11 - Bastidores\nLote 12 - Uninterruptible power supplies (UPSs)\nLote 13 - Equipamento de rede (firewall)\nOpções: Não\nTipo de Contrato Principal: Aquisição de Bens Móveis\nTipo de Contrato: Aquisição de Bens Móveis\nClassificação CPV (Vocabulário Comum para os Contratos Públicos)\nObjeto principal\nVocabulário Principal: 48822000\nPreço base s/IVA: 784.000,00 EUR\nObjeto Complementar\nVocabulário Principal: 30236000\nPreço base s/IVA: 66.500,00 EUR\nObjeto Complementar\nVocabulário Principal: 32420000\nPreço base s/IVA: 8.000,00 EUR\nObjeto Complementar\nVocabulário Principal: 31154000\nPreço base s/IVA: 10.000,00 EUR\nLotes: \nNº: LOT-0001\nDescrição do Lote: Servidores de computação 1\nPreço base s/IVA: 250.000,00 EUR\nClassificação CPV (Vocabulário Comum para os Contratos Públicos)\nObjeto principal\nVocabulário Principal: 48822000\nNº: LOT-0002\nDescrição do Lote: Servidores de computação 2\nPreço base s/IVA: 210.000,00 EUR\nClassificação CPV (Vocabulário Comum para os Contratos Públicos)\nObjeto principal\nVocabulário Principal: 48822000\nNº: LOT-0003\nDescrição do Lote: Servidores de serviços (Rua Alves Redol)\nPreço base s/IVA: 140.000,00 EUR\nClassificação CPV (Vocabulário Comum para os Contratos Públicos)\nObjeto principal\nVocabulário Principal: 48822000\nNº: LOT-0004\nDescrição do Lote: Servidores de serviços (Taguspark)\nPreço base s/IVA: 120.000,00 EUR\nClassificação CPV (Vocabulário Comum para os Contratos Públicos)\nObjeto principal\nVocabulário Principal: 48822000\nNº: LOT-0005\nDescrição do Lote: Workstation Gráfica\nPreço base s/IVA: 50.000,00 EUR\nClassificação CPV (Vocabulário Comum para os Contratos Públicos)\nObjeto principal\nVocabulário Principal: 30236000\nNº: LOT-0006\nDescrição do Lote: Servidor Compute Express Link (CXL)\nPreço base s/IVA: 27.000,00 EUR\nClassificação CPV (Vocabulário Comum para os Contratos Públicos)\nObjeto principal\nVocabulário Principal: 48822000\nNº: LOT-0007\nDescrição do Lote: High-speed link\nPreço base s/IVA: 10.500,00 EUR\nClassificação CPV (Vocabulário Comum para os Contratos Públicos)\nObjeto principal\nVocabulário Principal: 30236000\nNº: LOT-0008\nDescrição do Lote: Servidor de grande escalabilidade\nPreço base s/IVA: 22.000,00 EUR\nClassificação CPV (Vocabulário Comum para os Contratos Públicos)\nObjeto principal\nVocabulário Principal: 48822000\nNº: LOT-0009\nDescrição do Lote: Servidores Field Programmable Gate Array (FPGA)\nPreço base s/IVA: 10.000,00 EUR\nClassificação CPV (Vocabulário Comum para os Contratos Públicos)\nObjeto principal\nVocabulário Principal: 48822000\nNº: LOT-0010\nDescrição do Lote: Equipamento de rede (switches)\nPreço base s/IVA: 8.000,00 EUR\nClassificação CPV (Vocabulário Comum para os Contratos Públicos)\nObjeto principal\nVocabulário Principal: 32420000\nNº: LOT-0011\nDescrição do Lote: Bastidores\nPreço base s/IVA: 6.000,00 EUR\nClassificação CPV (Vocabulário Comum para os Contratos Públicos)\nObjeto principal\nVocabulário Principal: 30236000\nNº: LOT-0012\nDescrição do Lote: Uninterruptible power supplies (UPSs)\nPreço base s/IVA: 10.000,00 EUR\nClassificação CPV (Vocabulário Comum para os Contratos Públicos)\nObjeto principal\nVocabulário Principal: 31154000\nNº: LOT-0013\nDescrição do Lote: Equipamento de rede (firewall)\nPreço base s/IVA: 5.000,00 EUR\nClassificação CPV (Vocabulário Comum para os Contratos Públicos)\nObjeto principal\nVocabulário Principal: 48822000\n7 - INDICAÇÕES ADICIONAIS\nO contrato envolve aquisição conjunta (satisfação de várias entidades)? Não\nO contrato é adjudicado por uma central de compras? Não\n8 - TÉCNICAS\nO concurso destina-se à celebração de um acordo-quadro? Inexistência de acordo-quadro\nÉ utilizado um leilão eletrónico? Não\nÉ adotada uma fase de negociação? Não\nSistema de Aquisição Dinâmico: Inexistência de sistema de aquisição dinâmico\n9 - LOCAL DA EXECUÇÃO DO CONTRATO\nLOCAL DA EXECUÇÃO DO CONTRATO (PROCEDIMENTO)\nPaís: Portugal\nNUT III: PT170\nLocalidade: Freguesia de Areeiro\nDistrito: Lisboa\nConcelho: Lisboa\nFreguesia: Freguesia de Areeiro\nLOCAL DA EXECUÇÃO DO CONTRATO (LOTE)\nIdentificador do Lote: LOT-0004\nPaís: Portugal\nNUT III: PT170\nLocalidade: Freguesia de Porto Salvo\nDistrito: Lisboa\nConcelho: Oeiras\nFreguesia: Freguesia de Porto Salvo\nIdentificador do Lote: LOT-0001; LOT-0002; LOT-0003; LOT-0005; LOT-0006; LOT-0007; LOT-0008; LOT-0009; LOT-0010; LOT-0011; LOT-0012; LOT-0013\nPaís: Portugal\nNUT III: PT170\nLocalidade: Freguesia de Areeiro\nDistrito: Lisboa\nConcelho: Lisboa\nFreguesia: Freguesia de Areeiro\n10 - PRAZO DE EXECUÇÃO DO CONTRATO\nIdentificador do Lote: LOT-0001; LOT-0002; LOT-0003; LOT-0004; LOT-0005; LOT-0006; LOT-0007; LOT-0008; LOT-0009; LOT-0010; LOT-0011; LOT-0012; LOT-0013\nPrazo de execução do contrato: 60 DIAS\nPrevisão de renovações: Não\n11 - FUNDOS EU\nIdentificador do Lote: LOT-0001; LOT-0002; LOT-0003; LOT-0004; LOT-0005; LOT-0006; LOT-0007; LOT-0008; LOT-0009; LOT-0010; LOT-0011; LOT-0012; LOT-0013\nTêm fundos EU? Sim\n12 - DOCUMENTOS DE HABILITAÇÃO\nHabilitação para o exercício da atividade profissional: Não\n13 - CONDIÇÕES DE APRESENTAÇÃO\nPlataforma eletrónica utilizada pela entidade adjudicante: ACIN\nURL para Apresentação: https://www.acingov.pt\nAdmissibilidade da apresentação de propostas variantes: Não autorizado\nPrazo para apresentação das propostas: 29-01-2026 23:59\nPrazo durante o qual os concorrentes são obrigados a manter as respetivas propostas: 66 dias a contar do termo do prazo para a apresentação das propostas\nApresentação de Catálogo Eletrónico: Não autorizado\nIndicação de Subcontratação na Proposta: Inexistência de indicação de subcontratação\n14 - PRESTAÇÃO DE CAUÇÃO\nPrestação de caução: Não\n15 - FORNECIMENTO DAS PEÇAS DO CONCURSO, APRESENTAÇÃO DE PEDIDOS DE PARTICIPAÇÃO E APRESENTAÇÃO DAS PROPOSTAS\nLink para acesso às peças do concurso (URL): https://www.acingov.pt/acingovprod/2/zonaPublica/zona_publica_c/donwloadProcedurePiece/MTAwNTk2Nw==\n20 - OUTROS REQUISITOS\nIdentificador do Lote: LOT-0001; LOT-0002; LOT-0003; LOT-0004; LOT-0005; LOT-0006; LOT-0007; LOT-0008; LOT-0009; LOT-0010; LOT-0011; LOT-0012; LOT-0013\nInformação sobre contratos reservados. Aplica-se a contratos reservados (54º-A)? Não\n21 - CRITÉRIO DE ADJUDICAÇÃO\nO Critério de adjudicação é diferenciado por lote? Não\nMultifator: Sim\nFator: \nNome: Preço\nPonderação: 70%\nSubfatores: Não\nFator: \nNome: Outros\nOutro Nome: Prazo\nPonderação: 30%\nSubfatores: Não\n24 - CONDIÇÕES DO CONTRATO\nIdentificador do Lote: LOT-0001; LOT-0002; LOT-0003; LOT-0004; LOT-0005; LOT-0006; LOT-0007; LOT-0008; LOT-0009; LOT-0010; LOT-0011; LOT-0012; LOT-0013\nFaturação Eletrónica: Necessário\nObrigação de Subcontratação:\nCódigo da Obrigação de Subcontratação: Não é aplicável nenhuma obrigação de subcontratação.\n25 - COMPRA PÚBLICA ESTRATÉGICA\nCompra Pública Estratégica: Inexistência de contratação pública estratégica\n26 - INFORMAÇÕES ADICIONAIS\nIdentificador do Lote: LOT-0001; LOT-0002; LOT-0003; LOT-0004; LOT-0005; LOT-0006; LOT-0007; LOT-0008; LOT-0009; LOT-0010; LOT-0011; LOT-0012; LOT-0013\nContrato adequado para PME: Sim\nCobertura ACP (Acordo dos Contratos Públicos da Organização Mundial do Comércio): Não\n27 - IDENTIFICAÇÃO E CONTACTOS DO ÓRGÃO DE RECURSOS ADMINISTRATIVOS\nDesignação: Comissão Executiva do INESC-ID\nEndereço: Rua Alves Redol, 9\nCódigo postal: 1000-029\nLocalidade: Lisboa\nTelefone: 213100300\nFax: 213145843\nEndereço eletrónico: eb-all@lst.inesc-id.pt\nPrazo de interposição do recurso: 10 dias\n28 - IDENTIFICAÇÃO DO(S) AUTOR(ES) DE ANÚNCIO\nNome: Paula Dias\nCargo: Jurista\n29 - ALTERAÇÃO\nMotivo da Alteração: Correção pelo adquirente\nIdentificador da Versão do Anúncio a Alterar: a1902e7e-0554-4423-b3bd-4760fd59574d-01\nIdentificador das Secções Alteradas do Anúncio Anterior: Condições de Apresentação\nDescrição das Alterações: Modificação do prazo para a apresentação de propostas\nAlteração dos Documentos do Concurso: Não\n419947975",
    "nipc": "504547593",
    "distrito": "Lisboa",
    "concelho": "Lisboa",
    "freguesia": "Freguesia de Areeiro",
    "site": "http://www.inesc-id.pt/",
    "email": "info@inesc-id.pt",
    "designacao_contrato": "Aquisição de equipamento informático",
    "descricao": "Aquisição de equipamento informático, de acordo com os seguintes lotes:",
    "preco_base": "784.000,00 EUR",
    "prazo_execucao": "60 DIAS",
    "prazo_apresentacao_propostas": "29-01-2026 23:59",
    "fundos_eu": "Sim",
    "plataforma_eletronica": "ACIN",
    "url_procedimento": "https://www.acingov.pt",
    "autor_nome": "Paula Dias",
    "autor_cargo": "Jurista"
  },
  {
    "numero_procedimento": "N/A",
    "entidade": "Município de Braga",
    "link": "https://diariodarepublica.pt/dr/detalhe/contrato-publico/938-1013997927",
    "detalhes_completos": "Alteração do Anúncio de procedimento n.º 462/2026, de 2026-01-09, com o ID 419947197\n1 - IDENTIFICAÇÃO E CONTACTOS DA ENTIDADE ADJUDICANTE\nDesignação da entidade adjudicante: Município de Braga\nNIPC: 506901173\nEndereço: Praça do Municípal\nCódigo postal: 4700-435\nLocalidade: Braga\nPaís: Portugal\nNUT III: PT112\nDistrito: Braga\nConcelho: Braga\nFreguesia: União das Freguesias de Braga (Maximinos, Sé e Cividade)\nTelefone: 253616060\nFax: 253203151\nEndereço da Entidade (URL): www.cm-braga.pt\nEndereço Eletrónico: contratacao.publica@cm-braga.pt\neDelivery Gateway (URL): https://community.vortal.biz/public/\nFunção da Organização: Adquirente\nNorma jurídica da Entidade Adjudicante: Autoridade local\nÁrea de atividade da Autoridade Adjudicante: Serviços públicos das administrações públicas\n2 - JORNAL OFICIAL DA UNIÃO EUROPEIA\nO procedimento a que este anúncio diz respeito também é publicitado no Jornal Oficial da União Europeia? Não\n3 - AVISO\nModelo de Anúncio: Concurso público\nData de Envio do Anúncio: 16-01-2026\n5 - PROCESSO\nTipo de Procedimento: Concurso público\nPreço base do procedimento: Sim\nValor do preço base do procedimento: 305.051,79 EUR\nProcedimento com lotes? Não\n6 - OBJETO DO CONTRATO\nNúmero de referência interna: CPE.38.25.DMOSM\nDesignação do contrato: MUSEU DOS BISCAÍNHOS – REQUALIFICAÇÃO DE INSTALAÇÕES ELETROTÉCNICAS EXISTENTES\nDescrição: MUSEU DOS BISCAÍNHOS – REQUALIFICAÇÃO DE INSTALAÇÕES ELETROTÉCNICAS EXISTENTES\nTipo de Contrato Principal: Empreitada de Obras Públicas\nTipo de Contrato: Empreitada de Obras Públicas\nClassificação CPV (Vocabulário Comum para os Contratos Públicos)\nObjeto principal\nVocabulário Principal: 45453100\nPreço base s/IVA: 305.051,79 EUR\n7 - INDICAÇÕES ADICIONAIS\nO contrato envolve aquisição conjunta (satisfação de várias entidades)? Não\nO contrato é adjudicado por uma central de compras? Não\n8 - TÉCNICAS\nO concurso destina-se à celebração de um acordo-quadro? Inexistência de acordo-quadro\nÉ utilizado um leilão eletrónico? Não\nÉ adotada uma fase de negociação? Não\nSistema de Aquisição Dinâmico: Inexistência de sistema de aquisição dinâmico\n9 - LOCAL DA EXECUÇÃO DO CONTRATO\nLOCAL DA EXECUÇÃO DO CONTRATO (PROCEDIMENTO)\nPaís: Portugal\nNUT III: PT112\nLocalidade: Braga\nDistrito: Braga\nConcelho: Braga\nFreguesia: Todas\n10 - PRAZO DE EXECUÇÃO DO CONTRATO\nPrazo de execução do contrato: 120 DIAS\nPrevisão de renovações: Não\n11 - FUNDOS EU\nTêm fundos EU? Não\n12 - DOCUMENTOS DE HABILITAÇÃO\nHabilitação para o exercício da atividade profissional: Sim\nTipo: Alvará\nDescrição: De acordo com o artigo 22.º do Programa do Concurso.\n13 - CONDIÇÕES DE APRESENTAÇÃO\nPlataforma eletrónica utilizada pela entidade adjudicante: VORTAL\nURL para Apresentação: https://community.vortal.biz/public/\nAdmissibilidade da apresentação de propostas variantes: Não autorizado\nPrazo para apresentação das propostas: 05-02-2026 18:00\nPrazo durante o qual os concorrentes são obrigados a manter as respetivas propostas: 120 dias a contar do termo do prazo para a apresentação das propostas\nApresentação de Catálogo Eletrónico: Permitido\nIndicação de Subcontratação na Proposta: Inexistência de indicação de subcontratação\n14 - PRESTAÇÃO DE CAUÇÃO\nPrestação de caução: Não\n15 - FORNECIMENTO DAS PEÇAS DO CONCURSO, APRESENTAÇÃO DE PEDIDOS DE PARTICIPAÇÃO E APRESENTAÇÃO DAS PROPOSTAS\nLink para acesso às peças do concurso (URL): https://community.vortal.biz/Public/public-tender-documents/dys4bmtIazh2bE8ybUpiRTc4TTVweWxuWFJSTVVVL2M1b3BBdW5HWWVGWmNpRHkxSUxHNU1zYWxmdmpXTXNwRWw4MFFSZzhoL3hmN1JkeU45UkNnOVE9PWpacnpF\n20 - OUTROS REQUISITOS\nInformação sobre contratos reservados. Aplica-se a contratos reservados (54º-A)? Não\n21 - CRITÉRIO DE ADJUDICAÇÃO\nMultifator: Sim\nFator: \nNome: Preço\nPonderação: 70%\nSubfatores: Não\nFator: \nNome: Outros\nOutro Nome: Prazo de Execução\nPonderação: 30%\nSubfatores: Não\n24 - CONDIÇÕES DO CONTRATO\nFaturação Eletrónica: Permitido\nObrigação de Subcontratação:\nCódigo da Obrigação de Subcontratação: Não é aplicável nenhuma obrigação de subcontratação.\n25 - COMPRA PÚBLICA ESTRATÉGICA\nCompra Pública Estratégica: Inexistência de contratação pública estratégica\n26 - INFORMAÇÕES ADICIONAIS\nContrato adequado para PME: Sim\nCobertura ACP (Acordo dos Contratos Públicos da Organização Mundial do Comércio): Não\n27 - IDENTIFICAÇÃO E CONTACTOS DO ÓRGÃO DE RECURSOS ADMINISTRATIVOS\nDesignação: Presidente da Câmara Municipal de Braga\nEndereço: Praça do Município\nCódigo postal: 4700-435\nLocalidade: Braga\nTelefone: +351 253616060\nFax: +351 253203151\nEndereço eletrónico: info@cm-braga.pt\n28 - IDENTIFICAÇÃO DO(S) AUTOR(ES) DE ANÚNCIO\nNome: Rita Gonçalves\nCargo: Técnico Superior\n29 - ALTERAÇÃO\nMotivo da Alteração: Informações atualizadas\nIdentificador da Versão do Anúncio a Alterar: 0ba28b48-b6e7-4f53-88f0-67d5366673e5-01\nIdentificador das Secções Alteradas do Anúncio Anterior: Condições de Apresentação\nAlteração dos Documentos do Concurso: Não\n419947795",
    "nipc": "506901173",
    "distrito": "Braga",
    "concelho": "Braga",
    "freguesia": "União das Freguesias de Braga (Maximinos, Sé e Cividade)",
    "site": "www.cm-braga.pt",
    "email": "contratacao.publica@cm-braga.pt",
    "designacao_contrato": "MUSEU DOS BISCAÍNHOS – REQUALIFICAÇÃO DE INSTALAÇÕES ELETROTÉCNICAS EXISTENTES",
    "descricao": "MUSEU DOS BISCAÍNHOS – REQUALIFICAÇÃO DE INSTALAÇÕES ELETROTÉCNICAS EXISTENTES",
    "preco_base": "305.051,79 EUR",
    "prazo_execucao": "120 DIAS",
    "prazo_apresentacao_propostas": "05-02-2026 18:00",
    "fundos_eu": "Não",
    "plataforma_eletronica": "VORTAL",
    "url_procedimento": "https://community.vortal.biz/public/",
    "autor_nome": "Rita Gonçalves",
    "autor_cargo": "Técnico Superior"
  },
  {
    "numero_procedimento": "N/A",
    "entidade": "AnÃºncio de procedimento  n.Âº 940/2026  -  DiÃ¡rio da RepÃºblica n.Âº 11/2026, SÃ©rie II de 2026-01-16",
    "link": "https://diariodarepublica.pt/dr/detalhe/contrato-publico/940-1013997928"
  },
  {
    "numero_procedimento": "N/A",
    "entidade": "AnÃºncio de procedimento  n.Âº 943/2026  -  DiÃ¡rio da RepÃºblica n.Âº 11/2026, SÃ©rie II de 2026-01-16",
    "link": "https://diariodarepublica.pt/dr/detalhe/contrato-publico/943-1013997929"
  },
  {
    "numero_procedimento": "N/A",
    "entidade": "Vimágua - Empresa de Água e Saneamento de Guimarães e Vizela, EIM, SA",
    "link": "https://diariodarepublica.pt/dr/detalhe/contrato-publico/944-1013997930",
    "detalhes_completos": "1 - IDENTIFICAÇÃO E CONTACTOS DA ENTIDADE ADJUDICANTE\nDesignação da entidade adjudicante: Vimágua - Empresa de Água e Saneamento de Guimarães e Vizela, EIM, SA\nNIPC: 505993082\nServiço/Órgão/Pessoa de contacto: Presidente do Conselho de Administração\nEndereço: Rua Rei do Pegú, 172\nCódigo postal: 4810-025\nLocalidade: Guimarães\nPaís: Portugal\nNUT III: PT119\nDistrito: Braga\nConcelho: Guimarães\nFreguesia: Todas\nTelefone: 253439560\nFax: 253410444\nEndereço da Entidade (URL): www.vimagua.pt\nEndereço Eletrónico: vimagua@vimagua.pt\neDelivery Gateway (URL): https://www.acingov.pt\nFunção da Organização: Adquirente\nNorma jurídica da Entidade Adjudicante: Organismo de direito público\nÁrea de atividade da Entidade Adjudicante: Atividades relacionadas com a água\n2 - JORNAL OFICIAL DA UNIÃO EUROPEIA\nO procedimento a que este anúncio diz respeito também é publicitado no Jornal Oficial da União Europeia? Não\n3 - AVISO\nModelo de Anúncio: Concurso público\nData de Envio do Anúncio: 16-01-2026\n5 - PROCESSO\nTipo de Procedimento: Concurso público\nPreço base do procedimento: Sim\nValor do preço base do procedimento: 31.000,00 EUR\nProcedimento com lotes? Não\n6 - OBJETO DO CONTRATO\nNúmero de referência interna: CP Nº 15/2025/BS\nDesignação do contrato: Fornecimento continuo de produtos químicos para limpeza e higienização de reservatórios\nDescrição: Fornecimento continuo de produtos químicos para limpeza e higienização de reservatórios \nTipo de Contrato Principal: Aquisição de Bens Móveis\nTipo de Contrato: Aquisição de Bens Móveis\nClassificação CPV (Vocabulário Comum para os Contratos Públicos)\nObjeto principal\nVocabulário Principal: 24962000\nPreço base s/IVA: 31.000,00 EUR\n7 - INDICAÇÕES ADICIONAIS\nO contrato envolve aquisição conjunta (satisfação de várias entidades)? Não\nO contrato é adjudicado por uma central de compras? Não\n8 - TÉCNICAS\nO concurso destina-se à celebração de um acordo-quadro? Inexistência de acordo-quadro\nÉ utilizado um leilão eletrónico? Não\nÉ adotada uma fase de negociação? Não\nSistema de Aquisição Dinâmico: Inexistência de sistema de aquisição dinâmico\n9 - LOCAL DA EXECUÇÃO DO CONTRATO\nLOCAL DA EXECUÇÃO DO CONTRATO (PROCEDIMENTO)\nPaís: Portugal\nNUT III: PT119\nLocalidade: Freguesia de Aldão\nDistrito: Braga\nConcelho: Guimarães\nFreguesia: Freguesia de Aldão\n10 - PRAZO DE EXECUÇÃO DO CONTRATO\nPrazo de execução do contrato: 24 MESES\nPrevisão de renovações: Não\n11 - FUNDOS EU\nTêm fundos EU? Não\n12 - DOCUMENTOS DE HABILITAÇÃO\nHabilitação para o exercício da atividade profissional: Sim\nTipo: Outros\nDescrição - Outros: Documento comprovativo da titularidade das habilitações legalmente exigidas para a execução do objeto do presente contrato, de acordo com o estabelecido pelo artigo 2.º da Portaria n.º 372/2017, de 14 de dezembro (caso aplicável). \nDescrição: Documentos de Habilitação\n13 - CONDIÇÕES DE APRESENTAÇÃO\nPlataforma eletrónica utilizada pela entidade adjudicante: ACIN\nURL para Apresentação: https://www.acingov.pt\nAdmissibilidade da apresentação de propostas variantes: Não autorizado\nPrazo para apresentação das propostas: 30-01-2026 17:00\nPrazo durante o qual os concorrentes são obrigados a manter as respetivas propostas: 66 dias a contar do termo do prazo para a apresentação das propostas\nIndicação de Subcontratação na Proposta: Inexistência de indicação de subcontratação\n14 - PRESTAÇÃO DE CAUÇÃO\nPrestação de caução: Não\n15 - FORNECIMENTO DAS PEÇAS DO CONCURSO, APRESENTAÇÃO DE PEDIDOS DE PARTICIPAÇÃO E APRESENTAÇÃO DAS PROPOSTAS\nLink para acesso às peças do concurso (URL): https://www.acingov.pt/acingovprod/2/zonaPublica/zona_publica_c/donwloadProcedurePiece/MTAxMjEzMg==\n20 - OUTROS REQUISITOS\nInformação sobre contratos reservados. Aplica-se a contratos reservados (54º-A)? Não\n21 - CRITÉRIO DE ADJUDICAÇÃO\nMultifator: Não\nMonofator:\nNome: Preço\n24 - CONDIÇÕES DO CONTRATO\nFaturação Eletrónica: Permitido\nObrigação de Subcontratação:\nCódigo da Obrigação de Subcontratação: Não é aplicável nenhuma obrigação de subcontratação.\n25 - COMPRA PÚBLICA ESTRATÉGICA\nCompra Pública Estratégica: Inexistência de contratação pública estratégica\n26 - INFORMAÇÕES ADICIONAIS\nContrato adequado para PME: Não\nCobertura ACP (Acordo dos Contratos Públicos da Organização Mundial do Comércio): Não\n27 - IDENTIFICAÇÃO E CONTACTOS DO ÓRGÃO DE RECURSOS ADMINISTRATIVOS\nDesignação: Conselho de Administração\nEndereço: Rua Rei do Pegú, 172\nCódigo postal: 4810-025\nLocalidade: Guimarães\nTelefone: 253439560\nFax: 253410444\nEndereço eletrónico: vimagua@vimagua.pt\nPrazo de interposição do recurso: 5 dias\n28 - IDENTIFICAÇÃO DO(S) AUTOR(ES) DE ANÚNCIO\nNome: Daniel André de Sousa Rodrigues\nCargo: Presidente do Conselho de Administração\n419948145",
    "nipc": "505993082",
    "distrito": "Braga",
    "concelho": "Guimarães",
    "freguesia": "Todas",
    "site": "www.vimagua.pt",
    "email": "vimagua@vimagua.pt",
    "designacao_contrato": "Fornecimento continuo de produtos químicos para limpeza e higienização de reservatórios",
    "descricao": "Fornecimento continuo de produtos químicos para limpeza e higienização de reservatórios",
    "preco_base": "31.000,00 EUR",
    "prazo_execucao": "24 MESES",
    "prazo_apresentacao_propostas": "30-01-2026 17:00",
    "fundos_eu": "Não",
    "plataforma_eletronica": "ACIN",
    "url_procedimento": "https://www.acingov.pt",
    "autor_nome": "Daniel André de Sousa Rodrigues",
    "autor_cargo": "Presidente do Conselho de Administração"
  },
  {
    "numero_procedimento": "N/A",
    "entidade": "AnÃºncio de procedimento  n.Âº 945/2026  -  DiÃ¡rio da RepÃºblica n.Âº 11/2026, SÃ©rie II de 2026-01-16",
    "link": "https://diariodarepublica.pt/dr/detalhe/contrato-publico/945-1013997931"
  },
  {
    "numero_procedimento": "N/A",
    "entidade": "Águas Públicas em Altitude - Serviços Intermunicipalizados, APAL-SIM",
    "link": "https://diariodarepublica.pt/dr/detalhe/contrato-publico/946-1013997932",
    "detalhes_completos": "1 - IDENTIFICAÇÃO E CONTACTOS DA ENTIDADE ADJUDICANTE\nDesignação da entidade adjudicante: Águas Públicas em Altitude - Serviços Intermunicipalizados, APAL-SIM\nNIPC: 600088006\nEndereço: Largo de São Vicente, nº7\nCódigo postal: 6300-600\nLocalidade:  Guarda \nPaís: Portugal\nNUT III: PT16J\nDistrito: Guarda\nConcelho: Guarda\nFreguesia: Freguesia de Guarda\nTelefone: 271232740\nEndereço Eletrónico: geral@apal-sim.pt\neDelivery Gateway (URL): https://community.vortal.biz/public/\nFunção da Organização: Adquirente\nNorma jurídica da Entidade Adjudicante: Empresa pública\nÁrea de atividade da Entidade Adjudicante: Atividades relacionadas com a água\n2 - JORNAL OFICIAL DA UNIÃO EUROPEIA\nO procedimento a que este anúncio diz respeito também é publicitado no Jornal Oficial da União Europeia? Não\n3 - AVISO\nModelo de Anúncio: Concurso público\nData de Envio do Anúncio: 16-01-2026\n5 - PROCESSO\nTipo de Procedimento: Concurso público\nPreço base do procedimento: Sim\nValor do preço base do procedimento: 48.500,00 EUR\nProcedimento com lotes? Não\n6 - OBJETO DO CONTRATO\nNúmero de referência interna: 032_2025\nDesignação do contrato: Aquisição de serviços de seguros diversos\nDescrição: Aquisição de serviços de seguros diversos\nTipo de Contrato Principal: Aquisição de Serviços\nTipo de Contrato: Aquisição de Serviços\nClassificação CPV (Vocabulário Comum para os Contratos Públicos)\nObjeto principal\nVocabulário Principal: 66510000\nPreço base s/IVA: 48.500,00 EUR\n7 - INDICAÇÕES ADICIONAIS\nO contrato envolve aquisição conjunta (satisfação de várias entidades)? Não\nO contrato é adjudicado por uma central de compras? Não\n8 - TÉCNICAS\nO concurso destina-se à celebração de um acordo-quadro? Inexistência de acordo-quadro\nÉ utilizado um leilão eletrónico? Não\nÉ adotada uma fase de negociação? Não\nSistema de Aquisição Dinâmico: Inexistência de sistema de aquisição dinâmico\n9 - LOCAL DA EXECUÇÃO DO CONTRATO\nLOCAL DA EXECUÇÃO DO CONTRATO (PROCEDIMENTO)\nPaís: Portugal\nNUT III: PT16J\nLocalidade: Guarda\nDistrito: Guarda\nConcelho: Guarda\nFreguesia: Freguesia de Guarda\n10 - PRAZO DE EXECUÇÃO DO CONTRATO\nPrazo de execução do contrato: 6 MESES\nPrevisão de renovações: Não\n11 - FUNDOS EU\nTêm fundos EU? Não\n12 - DOCUMENTOS DE HABILITAÇÃO\nHabilitação para o exercício da atividade profissional: Sim\nTipo: Outros\nDescrição - Outros: Conforme peças do procedimento\nDescrição: Empresas de Seguros legalmente habilitadas ao exercício da atividade Seguradora, nos termos do artigo 3º e definidas na alínea a) do artigo 5º, do Anexo I, aprovado pelo Artigo 2º da Lei 147/2015, de 9 de setembro, na sua atual redação.\n13 - CONDIÇÕES DE APRESENTAÇÃO\nPlataforma eletrónica utilizada pela entidade adjudicante: VORTAL\nURL para Apresentação: https://community.vortal.biz/public/\nAdmissibilidade da apresentação de propostas variantes: Não autorizado\nPrazo para apresentação das propostas: 26-01-2026 23:59\nPrazo durante o qual os concorrentes são obrigados a manter as respetivas propostas: 66 dias a contar do termo do prazo para a apresentação das propostas\nIndicação de Subcontratação na Proposta: Inexistência de indicação de subcontratação\n14 - PRESTAÇÃO DE CAUÇÃO\nPrestação de caução: Não\n15 - FORNECIMENTO DAS PEÇAS DO CONCURSO, APRESENTAÇÃO DE PEDIDOS DE PARTICIPAÇÃO E APRESENTAÇÃO DAS PROPOSTAS\nLink para acesso às peças do concurso (URL): https://community.vortal.biz/Public/public-tender-documents/eGhtQnhtcjAxL3B4U1dWaE1rSERnNk8yOWtCODNwK3E4Vld2SzlKMnJzdXluYXJxMGpzeG9mNEcvTzlOT3AyVENrQlRPNmdMdUhHWEVYT0t5Z2IwMWc9PWZzWjJq\n20 - OUTROS REQUISITOS\nInformação sobre contratos reservados. Aplica-se a contratos reservados (54º-A)? Não\n21 - CRITÉRIO DE ADJUDICAÇÃO\nMultifator: Não\nMonofator:\nNome: Outros\nOutro nome: Preço\n24 - CONDIÇÕES DO CONTRATO\nFaturação Eletrónica: Permitido\nObrigação de Subcontratação:\nCódigo da Obrigação de Subcontratação: Não é aplicável nenhuma obrigação de subcontratação.\n25 - COMPRA PÚBLICA ESTRATÉGICA\nCompra Pública Estratégica: Inexistência de contratação pública estratégica\n26 - INFORMAÇÕES ADICIONAIS\nContrato adequado para PME: Sim\nCobertura ACP (Acordo dos Contratos Públicos da Organização Mundial do Comércio): Não\n27 - IDENTIFICAÇÃO E CONTACTOS DO ÓRGÃO DE RECURSOS ADMINISTRATIVOS\nDesignação: Sérgio Fernando da Silva Costa\nEndereço: Largo de São Vicente, n.º 7\nCódigo postal: 6300-600\nLocalidade: Guarda\nTelefone: +351 271143450\nFax: +351 271143450\nEndereço eletrónico: contratacao@apal-sim.pt\n28 - IDENTIFICAÇÃO DO(S) AUTOR(ES) DE ANÚNCIO\nNome: Sérgio Fernando da Silva Costa\nCargo: Presidente do Conselho de Administração\n419948170",
    "nipc": "600088006",
    "distrito": "Guarda",
    "concelho": "Guarda",
    "freguesia": "Freguesia de Guarda",
    "site": null,
    "email": "geral@apal-sim.pt",
    "designacao_contrato": "Aquisição de serviços de seguros diversos",
    "descricao": "Aquisição de serviços de seguros diversos",
    "preco_base": "48.500,00 EUR",
    "prazo_execucao": "6 MESES",
    "prazo_apresentacao_propostas": "26-01-2026 23:59",
    "fundos_eu": "Não",
    "plataforma_eletronica": "VORTAL",
    "url_procedimento": "https://community.vortal.biz/public/",
    "autor_nome": "Sérgio Fernando da Silva Costa",
    "autor_cargo": "Presidente do Conselho de Administração"
  },
  {
    "numero_procedimento": "N/A",
    "entidade": "Município de Arouca",
    "link": "https://diariodarepublica.pt/dr/detalhe/contrato-publico/947-1013997933",
    "detalhes_completos": "1 - IDENTIFICAÇÃO E CONTACTOS DA ENTIDADE ADJUDICANTE\nDesignação da entidade adjudicante: Município de Arouca\nNIPC: 506808122\nServiço/Órgão/Pessoa de contacto: Presidente\nEndereço: Praça do Município\nCódigo postal: 4544-001\nLocalidade: Arouca\nPaís: Portugal\nNUT III: PT11A\nDistrito: Aveiro\nConcelho: Arouca\nFreguesia: Todas\nTelefone: 256940220\nFax: 256943045\nEndereço da Entidade (URL): www.cm-arouca.pt\nEndereço Eletrónico: geral@cm-arouca.pt\neDelivery Gateway (URL): https://www.acingov.pt\nFunção da Organização: Adquirente\nNorma jurídica da Entidade Adjudicante: Autoridade local\nÁrea de atividade da Autoridade Adjudicante: Serviços públicos das administrações públicas\n2 - JORNAL OFICIAL DA UNIÃO EUROPEIA\nO procedimento a que este anúncio diz respeito também é publicitado no Jornal Oficial da União Europeia? Não\n3 - AVISO\nModelo de Anúncio: Concurso público\nData de Envio do Anúncio: 16-01-2026\n5 - PROCESSO\nTipo de Procedimento: Concurso público\nPreço base do procedimento: Sim\nValor do preço base do procedimento: 109.593,00 EUR\nProcedimento com lotes? Sim\nNº Máx. de Lotes Autorizado: 2\nNúmero máximo de lotes que podem ser adjudicados a um concorrente: 2\n6 - OBJETO DO CONTRATO\nNúmero de referência interna: Proc nº 100/2025/EMCPA\nDesignação do contrato: Aquisição de serviços para a dinamização dos projetos de promoção de saúde mental VivaMente e bem-estar Raízes e Rumos\nDescrição: Aquisição de serviços para a dinamização dos projetos de promoção de saúde mental VivaMente e bem-estar Raízes e Rumos\nTipo de Contrato Principal: Aquisição de Serviços\nTipo de Contrato: Aquisição de Serviços\nClassificação CPV (Vocabulário Comum para os Contratos Públicos)\nObjeto principal\nVocabulário Principal: 85121270\nPreço base s/IVA: 109.593,00 EUR\nLotes: \nNº: LOT-0001\nDescrição do Lote: Vivamente\nPreço base s/IVA: 60.885,00 EUR\nClassificação CPV (Vocabulário Comum para os Contratos Públicos)\nObjeto principal\nVocabulário Principal: 85121270\nNº: LOT-0002\nDescrição do Lote: Raízes e Rumos\nPreço base s/IVA: 48.708,00 EUR\nClassificação CPV (Vocabulário Comum para os Contratos Públicos)\nObjeto principal\nVocabulário Principal: 85121270\n7 - INDICAÇÕES ADICIONAIS\nO contrato envolve aquisição conjunta (satisfação de várias entidades)? Não\nO contrato é adjudicado por uma central de compras? Não\n8 - TÉCNICAS\nO concurso destina-se à celebração de um acordo-quadro? Inexistência de acordo-quadro\nÉ utilizado um leilão eletrónico? Não\nÉ adotada uma fase de negociação? Não\nSistema de Aquisição Dinâmico: Inexistência de sistema de aquisição dinâmico\n9 - LOCAL DA EXECUÇÃO DO CONTRATO\nLOCAL DA EXECUÇÃO DO CONTRATO (PROCEDIMENTO)\nPaís: Portugal\nNUT III: PT11A\nLocalidade: AROUCA\nDistrito: Aveiro\nConcelho: Arouca\nFreguesia: Todas\nLOCAL DA EXECUÇÃO DO CONTRATO (LOTE)\nIdentificador do Lote: LOT-0001; LOT-0002\nPaís: Portugal\nNUT III: PT11A\nLocalidade: AROUCA\nDistrito: Aveiro\nConcelho: Arouca\nFreguesia: Todas\n10 - PRAZO DE EXECUÇÃO DO CONTRATO\nIdentificador do Lote: LOT-0001; LOT-0002\nPrazo de execução do contrato: 41 MESES\nPrevisão de renovações: Não\n11 - FUNDOS EU\nIdentificador do Lote: LOT-0001; LOT-0002\nTêm fundos EU? Sim\n12 - DOCUMENTOS DE HABILITAÇÃO\nHabilitação para o exercício da atividade profissional: Não\n13 - CONDIÇÕES DE APRESENTAÇÃO\nPlataforma eletrónica utilizada pela entidade adjudicante: ACIN\nURL para Apresentação: https://www.acingov.pt\nAdmissibilidade da apresentação de propostas variantes: Não autorizado\nPrazo para apresentação das propostas: 26-01-2026 23:59\nPrazo durante o qual os concorrentes são obrigados a manter as respetivas propostas: 66 dias a contar do termo do prazo para a apresentação das propostas\nIndicação de Subcontratação na Proposta: Inexistência de indicação de subcontratação\n14 - PRESTAÇÃO DE CAUÇÃO\nPrestação de caução: Não\n15 - FORNECIMENTO DAS PEÇAS DO CONCURSO, APRESENTAÇÃO DE PEDIDOS DE PARTICIPAÇÃO E APRESENTAÇÃO DAS PROPOSTAS\nLink para acesso às peças do concurso (URL): https://www.acingov.pt/acingovprod/2/zonaPublica/zona_publica_c/donwloadProcedurePiece/OTk5NDUw\n20 - OUTROS REQUISITOS\nIdentificador do Lote: LOT-0001; LOT-0002\nInformação sobre contratos reservados. Aplica-se a contratos reservados (54º-A)? Não\n21 - CRITÉRIO DE ADJUDICAÇÃO\nO Critério de adjudicação é diferenciado por lote? Não\nMultifator: Não\nMonofator:\nNome: Preço\n24 - CONDIÇÕES DO CONTRATO\nIdentificador do Lote: LOT-0001; LOT-0002\nFaturação Eletrónica: Permitido\nObrigação de Subcontratação:\nCódigo da Obrigação de Subcontratação: O contratante tem de indicar qualquer mudança de subcontratantes durante a execução do contrato.\n25 - COMPRA PÚBLICA ESTRATÉGICA\nCompra Pública Estratégica: Inexistência de contratação pública estratégica\n26 - INFORMAÇÕES ADICIONAIS\nIdentificador do Lote: LOT-0001; LOT-0002\nContrato adequado para PME: Sim\nCobertura ACP (Acordo dos Contratos Públicos da Organização Mundial do Comércio): Não\n27 - IDENTIFICAÇÃO E CONTACTOS DO ÓRGÃO DE RECURSOS ADMINISTRATIVOS\nDesignação: Município de Arouca\nEndereço: Praça do Município\nCódigo postal: 4544-001\nLocalidade: Arouca\nTelefone: 256940220\nFax: \nEndereço eletrónico: geral@cm-arouca.pt\n28 - IDENTIFICAÇÃO DO(S) AUTOR(ES) DE ANÚNCIO\nNome: Margarida Maria de Sousa Correia Belém\nCargo: Presidente da Câmara\n419947993",
    "nipc": "506808122",
    "distrito": "Aveiro",
    "concelho": "Arouca",
    "freguesia": "Todas",
    "site": "www.cm-arouca.pt",
    "email": "geral@cm-arouca.pt",
    "designacao_contrato": "Aquisição de serviços para a dinamização dos projetos de promoção de saúde mental VivaMente e bem-estar Raízes e Rumos",
    "descricao": "Aquisição de serviços para a dinamização dos projetos de promoção de saúde mental VivaMente e bem-estar Raízes e Rumos",
    "preco_base": "109.593,00 EUR",
    "prazo_execucao": "41 MESES",
    "prazo_apresentacao_propostas": "26-01-2026 23:59",
    "fundos_eu": "Sim",
    "plataforma_eletronica": "ACIN",
    "url_procedimento": "https://www.acingov.pt",
    "autor_nome": "Margarida Maria de Sousa Correia Belém",
    "autor_cargo": "Presidente da Câmara"
  },
  {
    "numero_procedimento": "N/A",
    "entidade": "Vimágua - Empresa de Água e Saneamento de Guimarães e Vizela, EIM, SA",
    "link": "https://diariodarepublica.pt/dr/detalhe/contrato-publico/950-1013997934",
    "detalhes_completos": "1 - IDENTIFICAÇÃO E CONTACTOS DA ENTIDADE ADJUDICANTE\nDesignação da entidade adjudicante: Vimágua - Empresa de Água e Saneamento de Guimarães e Vizela, EIM, SA\nNIPC: 505993082\nServiço/Órgão/Pessoa de contacto: Presidente do Conselho de Administração\nEndereço: Rua Rei do Pegú, 172\nCódigo postal: 4810-025\nLocalidade: Guimarães\nPaís: Portugal\nNUT III: PT119\nDistrito: Braga\nConcelho: Guimarães\nFreguesia: Todas\nTelefone: 253439560\nFax: 253410444\nEndereço da Entidade (URL): www.vimagua.pt\nEndereço Eletrónico: vimagua@vimagua.pt\neDelivery Gateway (URL): https://www.acingov.pt\nFunção da Organização: Adquirente\nNorma jurídica da Entidade Adjudicante: Organismo de direito público\nÁrea de atividade da Entidade Adjudicante: Atividades relacionadas com a água\n2 - JORNAL OFICIAL DA UNIÃO EUROPEIA\nO procedimento a que este anúncio diz respeito também é publicitado no Jornal Oficial da União Europeia? Não\n3 - AVISO\nModelo de Anúncio: Concurso público\nData de Envio do Anúncio: 16-01-2026\n5 - PROCESSO\nTipo de Procedimento: Concurso público\nPreço base do procedimento: Sim\nValor do preço base do procedimento: 47.068,00 EUR\nProcedimento com lotes? Sim\nNº Máx. de Lotes Autorizado: 6\nNúmero máximo de lotes que podem ser adjudicados a um concorrente: 6\n6 - OBJETO DO CONTRATO\nNúmero de referência interna: CP Nº 36/2025/BS\nDesignação do contrato: Fornecimento continuo de produtos químicos para tratamento de água para consumo humano, por lotes\nDescrição: Fornecimento continuo de produtos químicos para tratamento de água para consumo humano, por lotes\nTipo de Contrato Principal: Aquisição de Bens Móveis\nTipo de Contrato: Aquisição de Bens Móveis\nClassificação CPV (Vocabulário Comum para os Contratos Públicos)\nObjeto principal\nVocabulário Principal: 24962000\nPreço base s/IVA: 47.068,00 EUR\nLotes: \nNº: LOT-0001\nDescrição do Lote: Fornecimento de Hidróxido de Cálcio, a granel\nPreço base s/IVA: 19.385,00 EUR\nClassificação CPV (Vocabulário Comum para os Contratos Públicos)\nObjeto principal\nVocabulário Principal: 24962000\nNº: LOT-0002\nDescrição do Lote: Fornecimento de Hidróxido de Cálcio, saco de 20 Kgs\nPreço base s/IVA: 845,00 EUR\nClassificação CPV (Vocabulário Comum para os Contratos Públicos)\nObjeto principal\nVocabulário Principal: 24962000\nNº: LOT-0003\nDescrição do Lote: Fornecimento de Hipoclorito de Sódio (NaOCl)\nPreço base s/IVA: 5.110,00 EUR\nClassificação CPV (Vocabulário Comum para os Contratos Públicos)\nObjeto principal\nVocabulário Principal: 24962000\nNº: LOT-0004\nDescrição do Lote: Fornecimento de Hidróxido de Sódio (NaOH)\nPreço base s/IVA: 17.280,00 EUR\nClassificação CPV (Vocabulário Comum para os Contratos Públicos)\nObjeto principal\nVocabulário Principal: 24962000\nNº: LOT-0005\nDescrição do Lote: Fornecimento Bissulfito de Sódio (NaHSO3)\nPreço base s/IVA: 2.000,00 EUR\nClassificação CPV (Vocabulário Comum para os Contratos Públicos)\nObjeto principal\nVocabulário Principal: 24962000\nNº: LOT-0006\nDescrição do Lote: Fornecimento de Ácido Cítrico (C₆H₈O₇+H2O)\nPreço base s/IVA: 2.448,00 EUR\nClassificação CPV (Vocabulário Comum para os Contratos Públicos)\nObjeto principal\nVocabulário Principal: 24962000\n7 - INDICAÇÕES ADICIONAIS\nO contrato envolve aquisição conjunta (satisfação de várias entidades)? Não\nO contrato é adjudicado por uma central de compras? Não\n8 - TÉCNICAS\nO concurso destina-se à celebração de um acordo-quadro? Inexistência de acordo-quadro\nÉ utilizado um leilão eletrónico? Não\nÉ adotada uma fase de negociação? Não\nSistema de Aquisição Dinâmico: Inexistência de sistema de aquisição dinâmico\n9 - LOCAL DA EXECUÇÃO DO CONTRATO\nLOCAL DA EXECUÇÃO DO CONTRATO (PROCEDIMENTO)\nPaís: Portugal\nNUT III: PT119\nLocalidade: Freguesia de Aldão\nDistrito: Braga\nConcelho: Guimarães\nFreguesia: Freguesia de Aldão\nPaís: Portugal\nNUT III: PT119\nLocalidade: Freguesia de Azurém\nDistrito: Braga\nConcelho: Guimarães\nFreguesia: Freguesia de Azurém\nPaís: Portugal\nNUT III: PT119\nLocalidade: Freguesia de Prazins (Santa Eufémia)\nDistrito: Braga\nConcelho: Guimarães\nFreguesia: Freguesia de Prazins (Santa Eufémia)\nPaís: Portugal\nNUT III: PT119\nLocalidade: Freguesia de Urgezes\nDistrito: Braga\nConcelho: Guimarães\nFreguesia: Freguesia de Urgezes\nLOCAL DA EXECUÇÃO DO CONTRATO (LOTE)\nIdentificador do Lote: LOT-0001; LOT-0002; LOT-0003; LOT-0004; LOT-0005; LOT-0006\nPaís: Portugal\nNUT III: PT119\nLocalidade: Freguesia de Prazins (Santa Eufémia)\nDistrito: Braga\nConcelho: Guimarães\nFreguesia: Freguesia de Prazins (Santa Eufémia)\nIdentificador do Lote: LOT-0001; LOT-0002; LOT-0003; LOT-0004; LOT-0005; LOT-0006\nPaís: Portugal\nNUT III: PT119\nLocalidade: Freguesia de Aldão\nDistrito: Braga\nConcelho: Guimarães\nFreguesia: Freguesia de Aldão\nIdentificador do Lote: LOT-0001; LOT-0002; LOT-0003; LOT-0004; LOT-0005; LOT-0006\nPaís: Portugal\nNUT III: PT119\nLocalidade: Freguesia de Urgezes\nDistrito: Braga\nConcelho: Guimarães\nFreguesia: Freguesia de Urgezes\nIdentificador do Lote: LOT-0001; LOT-0002; LOT-0003; LOT-0004; LOT-0005; LOT-0006\nPaís: Portugal\nNUT III: PT119\nLocalidade: Freguesia de Azurém\nDistrito: Braga\nConcelho: Guimarães\nFreguesia: Freguesia de Azurém\n10 - PRAZO DE EXECUÇÃO DO CONTRATO\nIdentificador do Lote: LOT-0001; LOT-0002; LOT-0003; LOT-0004; LOT-0005; LOT-0006\nPrazo de execução do contrato: 12 MESES\nPrevisão de renovações: Não\n11 - FUNDOS EU\nIdentificador do Lote: LOT-0001; LOT-0002; LOT-0003; LOT-0004; LOT-0005; LOT-0006\nTêm fundos EU? Não\n12 - DOCUMENTOS DE HABILITAÇÃO\nHabilitação para o exercício da atividade profissional: Sim\nTipo: Outros\nDescrição - Outros: Documento comprovativo da titularidade das habilitações legalmente exigidas para a execução do objeto do presente contrato, de acordo com o estabelecido pelo artigo 2.º da Portaria n.º 372/2017, de 14 de dezembro (caso aplicável). \nDescrição: Documentos de Habilitação\n13 - CONDIÇÕES DE APRESENTAÇÃO\nPlataforma eletrónica utilizada pela entidade adjudicante: ACIN\nURL para Apresentação: https://www.acingov.pt\nAdmissibilidade da apresentação de propostas variantes: Não autorizado\nPrazo para apresentação das propostas: 30-01-2026 17:00\nPrazo durante o qual os concorrentes são obrigados a manter as respetivas propostas: 66 dias a contar do termo do prazo para a apresentação das propostas\nIndicação de Subcontratação na Proposta: Inexistência de indicação de subcontratação\n14 - PRESTAÇÃO DE CAUÇÃO\nPrestação de caução: Não\n15 - FORNECIMENTO DAS PEÇAS DO CONCURSO, APRESENTAÇÃO DE PEDIDOS DE PARTICIPAÇÃO E APRESENTAÇÃO DAS PROPOSTAS\nLink para acesso às peças do concurso (URL): https://www.acingov.pt/acingovprod/2/zonaPublica/zona_publica_c/donwloadProcedurePiece/MTAxMjE5Mg==\n20 - OUTROS REQUISITOS\nIdentificador do Lote: LOT-0001; LOT-0002; LOT-0003; LOT-0004; LOT-0005; LOT-0006\nInformação sobre contratos reservados. Aplica-se a contratos reservados (54º-A)? Não\n21 - CRITÉRIO DE ADJUDICAÇÃO\nO Critério de adjudicação é diferenciado por lote? Não\nMultifator: Não\nMonofator:\nNome: Preço\n24 - CONDIÇÕES DO CONTRATO\nIdentificador do Lote: LOT-0001; LOT-0002; LOT-0003; LOT-0004; LOT-0005; LOT-0006\nFaturação Eletrónica: Permitido\nObrigação de Subcontratação:\nCódigo da Obrigação de Subcontratação: Não é aplicável nenhuma obrigação de subcontratação.\n25 - COMPRA PÚBLICA ESTRATÉGICA\nCompra Pública Estratégica: Inexistência de contratação pública estratégica\n26 - INFORMAÇÕES ADICIONAIS\nIdentificador do Lote: LOT-0001; LOT-0002; LOT-0003; LOT-0004; LOT-0005; LOT-0006\nContrato adequado para PME: Não\nCobertura ACP (Acordo dos Contratos Públicos da Organização Mundial do Comércio): Não\n27 - IDENTIFICAÇÃO E CONTACTOS DO ÓRGÃO DE RECURSOS ADMINISTRATIVOS\nDesignação: Conselho de Administração\nEndereço: Rua Rei do Pegú, 172\nCódigo postal: 4810-025\nLocalidade: Guimarães\nTelefone: 253439560\nFax: 253410444\nEndereço eletrónico: vimagua@vimagua.pt\nPrazo de interposição do recurso: 5 dias\n28 - IDENTIFICAÇÃO DO(S) AUTOR(ES) DE ANÚNCIO\nNome: Daniel André de Sousa Rodrigues\nCargo: Presidente do Conselho de Administração\n419948172",
    "nipc": "505993082",
    "distrito": "Braga",
    "concelho": "Guimarães",
    "freguesia": "Todas",
    "site": "www.vimagua.pt",
    "email": "vimagua@vimagua.pt",
    "designacao_contrato": "Fornecimento continuo de produtos químicos para tratamento de água para consumo humano, por lotes",
    "descricao": "Fornecimento continuo de produtos químicos para tratamento de água para consumo humano, por lotes",
    "preco_base": "47.068,00 EUR",
    "prazo_execucao": "12 MESES",
    "prazo_apresentacao_propostas": "30-01-2026 17:00",
    "fundos_eu": "Não",
    "plataforma_eletronica": "ACIN",
    "url_procedimento": "https://www.acingov.pt",
    "autor_nome": "Daniel André de Sousa Rodrigues",
    "autor_cargo": "Presidente do Conselho de Administração"
  },
  {
    "numero_procedimento": "N/A",
    "entidade": "AnÃºncio de procedimento  n.Âº 951/2026  -  DiÃ¡rio da RepÃºblica n.Âº 11/2026, SÃ©rie II de 2026-01-16",
    "link": "https://diariodarepublica.pt/dr/detalhe/contrato-publico/951-1013997935"
  },
  {
    "numero_procedimento": "N/A",
    "entidade": "Município de Bragança",
    "link": "https://diariodarepublica.pt/dr/detalhe/contrato-publico/953-1013997936",
    "detalhes_completos": "1 - IDENTIFICAÇÃO E CONTACTOS DA ENTIDADE ADJUDICANTE\nDesignação da entidade adjudicante: Município de Bragança\nNIPC: 506215547\nServiço/Órgão/Pessoa de contacto: Câmara Municipal de Bragança\nEndereço: Forte São João de Deus 5300-263 Bragança\nCódigo postal: 5300-263\nLocalidade: Bragança\nPaís: Portugal\nNUT III: PT11E\nDistrito: Braganca\nConcelho: Bragança\nFreguesia: União das Freguesias de Sé, Santa Maria e Meixedo\nTelefone: 273304216\nFax: 273304299\nEndereço da Entidade (URL): www.cm-braganca.pt\nEndereço Eletrónico: cmb@cm-braganca.pt\neDelivery Gateway (URL): https://www.acingov.pt\nFunção da Organização: Adquirente\nNorma jurídica da Entidade Adjudicante: Organismo de direito público\nÁrea de atividade da Autoridade Adjudicante: Serviços públicos das administrações públicas\n2 - JORNAL OFICIAL DA UNIÃO EUROPEIA\nO procedimento a que este anúncio diz respeito também é publicitado no Jornal Oficial da União Europeia? Não\n3 - AVISO\nModelo de Anúncio: Concurso público\nData de Envio do Anúncio: 16-01-2026\n5 - PROCESSO\nTipo de Procedimento: Concurso público\nPreço base do procedimento: Sim\nValor do preço base do procedimento: 202.000,00 EUR\nProcedimento com lotes? Não\n6 - OBJETO DO CONTRATO\nNúmero de referência interna: 41/2025-CP-DISI\nDesignação do contrato: Aquisição de Serviços de Cópia e Impressão\nDescrição: Aquisição de Serviços de Cópia e Impressão\nTipo de Contrato Principal: Aquisição de Serviços\nTipo de Contrato: Aquisição de Serviços\nClassificação CPV (Vocabulário Comum para os Contratos Públicos)\nObjeto principal\nVocabulário Principal: 72611000\nPreço base s/IVA: 202.000,00 EUR\n7 - INDICAÇÕES ADICIONAIS\nO contrato envolve aquisição conjunta (satisfação de várias entidades)? Não\nO contrato é adjudicado por uma central de compras? Não\n8 - TÉCNICAS\nO concurso destina-se à celebração de um acordo-quadro? Inexistência de acordo-quadro\nÉ utilizado um leilão eletrónico? Não\nÉ adotada uma fase de negociação? Não\nSistema de Aquisição Dinâmico: Inexistência de sistema de aquisição dinâmico\n9 - LOCAL DA EXECUÇÃO DO CONTRATO\nLOCAL DA EXECUÇÃO DO CONTRATO (PROCEDIMENTO)\nPaís: Portugal\nNUT III: PT11E\nLocalidade: União das Freguesias de Sé, Santa Maria e Meixedo\nDistrito: Braganca\nConcelho: Bragança\nFreguesia: União das Freguesias de Sé, Santa Maria e Meixedo\n10 - PRAZO DE EXECUÇÃO DO CONTRATO\nPrazo de execução do contrato: 36 MESES\nPrevisão de renovações: Não\n11 - FUNDOS EU\nTêm fundos EU? Não\n12 - DOCUMENTOS DE HABILITAÇÃO\nHabilitação para o exercício da atividade profissional: Não\n13 - CONDIÇÕES DE APRESENTAÇÃO\nPlataforma eletrónica utilizada pela entidade adjudicante: ACIN\nURL para Apresentação: https://www.acingov.pt\nAdmissibilidade da apresentação de propostas variantes: Não autorizado\nPrazo para apresentação das propostas: 26-01-2026 23:59\nPrazo durante o qual os concorrentes são obrigados a manter as respetivas propostas: 66 dias a contar do termo do prazo para a apresentação das propostas\nIndicação de Subcontratação na Proposta: Inexistência de indicação de subcontratação\n14 - PRESTAÇÃO DE CAUÇÃO\nPrestação de caução: Não\n15 - FORNECIMENTO DAS PEÇAS DO CONCURSO, APRESENTAÇÃO DE PEDIDOS DE PARTICIPAÇÃO E APRESENTAÇÃO DAS PROPOSTAS\nLink para acesso às peças do concurso (URL): https://www.acingov.pt/acingovprod/2/zonaPublica/zona_publica_c/donwloadProcedurePiece/MTA0ODQ4MQ==\n20 - OUTROS REQUISITOS\nInformação sobre contratos reservados. Aplica-se a contratos reservados (54º-A)? Não\n21 - CRITÉRIO DE ADJUDICAÇÃO\nMultifator: Sim\nFator: \nNome: Outros\nOutro Nome: Multifator\nPonderação: 100%\nSubfatores: Não\n24 - CONDIÇÕES DO CONTRATO\nFaturação Eletrónica: Permitido\nObrigação de Subcontratação:\nCódigo da Obrigação de Subcontratação: Não é aplicável nenhuma obrigação de subcontratação.\n25 - COMPRA PÚBLICA ESTRATÉGICA\nCompra Pública Estratégica: Inexistência de contratação pública estratégica\n26 - INFORMAÇÕES ADICIONAIS\nContrato adequado para PME: Não\nCobertura ACP (Acordo dos Contratos Públicos da Organização Mundial do Comércio): Não\n27 - IDENTIFICAÇÃO E CONTACTOS DO ÓRGÃO DE RECURSOS ADMINISTRATIVOS\nDesignação: Câmara Municipal de Bragança\nEndereço: Forte S. J. Deus\nCódigo postal: 5300-263\nLocalidade: Bragança\nTelefone: 273304200\nFax: \nEndereço eletrónico: cmb@cm-braganca.pt\nPrazo de interposição do recurso: 5 dias\n28 - IDENTIFICAÇÃO DO(S) AUTOR(ES) DE ANÚNCIO\nNome: Isabel Cristina Fernandes Rodrigues Ferreira\nCargo: Presidente da Câmara Municipal\n419948007",
    "nipc": "506215547",
    "distrito": "Braganca",
    "concelho": "Bragança",
    "freguesia": "União das Freguesias de Sé, Santa Maria e Meixedo",
    "site": "www.cm-braganca.pt",
    "email": "cmb@cm-braganca.pt",
    "designacao_contrato": "Aquisição de Serviços de Cópia e Impressão",
    "descricao": "Aquisição de Serviços de Cópia e Impressão",
    "preco_base": "202.000,00 EUR",
    "prazo_execucao": "36 MESES",
    "prazo_apresentacao_propostas": "26-01-2026 23:59",
    "fundos_eu": "Não",
    "plataforma_eletronica": "ACIN",
    "url_procedimento": "https://www.acingov.pt",
    "autor_nome": "Isabel Cristina Fernandes Rodrigues Ferreira",
    "autor_cargo": "Presidente da Câmara Municipal"
  },
  {
    "numero_procedimento": "N/A",
    "entidade": "AnÃºncio de procedimento  n.Âº 955/2026  -  DiÃ¡rio da RepÃºblica n.Âº 11/2026, SÃ©rie II de 2026-01-16",
    "link": "https://diariodarepublica.pt/dr/detalhe/contrato-publico/955-1013997937"
  },
  {
    "numero_procedimento": "N/A",
    "entidade": "Município de Tarouca",
    "link": "https://diariodarepublica.pt/dr/detalhe/contrato-publico/957-1013997940",
    "detalhes_completos": "1 - IDENTIFICAÇÃO E CONTACTOS DA ENTIDADE ADJUDICANTE\nDesignação da entidade adjudicante: Município de Tarouca\nNIPC: 506753905\nEndereço: Avenida Dr. Alexandre Taveira Cardoso\nCódigo postal: 3610-128\nLocalidade: Tarouca\nPaís: Portugal\nNUT III: PT11D\nDistrito: Viseu\nConcelho: Tarouca\nFreguesia: Todas\nTelefone: 254677420\nFax: 2546785510\nEndereço da Entidade (URL): www.cm-tarouca.pt\nEndereço Eletrónico: camara@cm-tarouca.pt\neDelivery Gateway (URL): https://community.vortal.biz/public/\nFunção da Organização: Adquirente\nNorma jurídica da Entidade Adjudicante: Autoridade local\nÁrea de atividade da Autoridade Adjudicante: Serviços públicos das administrações públicas\n2 - JORNAL OFICIAL DA UNIÃO EUROPEIA\nO procedimento a que este anúncio diz respeito também é publicitado no Jornal Oficial da União Europeia? Não\n3 - AVISO\nModelo de Anúncio: Concurso público\nData de Envio do Anúncio: 16-01-2026\n5 - PROCESSO\nTipo de Procedimento: Concurso público\nPreço base do procedimento: Sim\nValor do preço base do procedimento: 1.373.709,27 EUR\nProcedimento com lotes? Sim\nNº Máx. de Lotes Autorizado: 3\nNúmero máximo de lotes que podem ser adjudicados a um concorrente: 3\n6 - OBJETO DO CONTRATO\nNúmero de referência interna: 1.2026.AE.CP\nDesignação do contrato: REABILITAÇÃO DAS ESCOLAS DE VÁRZEA DA SERRA, VILA CHÃ DA BEIRA E PINHEIRO - BNAUT\nDescrição: REABILITAÇÃO DAS ESCOLAS DE VÁRZEA DA SERRA, VILA CHÃ DA BEIRA E PINHEIRO - BNAUT\nTipo de Contrato Principal: Empreitada de Obras Públicas\nTipo de Contrato: Empreitada de Obras Públicas\nClassificação CPV (Vocabulário Comum para os Contratos Públicos)\nObjeto principal\nVocabulário Principal: 45210000\nPreço base s/IVA: 1.373.709,27 EUR\nLotes: \nNº: LOT-0001\nDescrição do Lote: lote 1\nPreço base s/IVA: 847.995,98 EUR\nClassificação CPV (Vocabulário Comum para os Contratos Públicos)\nObjeto principal\nVocabulário Principal: 45210000\nNº: LOT-0002\nDescrição do Lote: lote 2\nPreço base s/IVA: 379.929,45 EUR\nClassificação CPV (Vocabulário Comum para os Contratos Públicos)\nObjeto principal\nVocabulário Principal: 45210000\nNº: LOT-0003\nDescrição do Lote: lote 3\nPreço base s/IVA: 145.783,84 EUR\nClassificação CPV (Vocabulário Comum para os Contratos Públicos)\nObjeto principal\nVocabulário Principal: 45210000\n7 - INDICAÇÕES ADICIONAIS\nO contrato envolve aquisição conjunta (satisfação de várias entidades)? Não\nO contrato é adjudicado por uma central de compras? Não\n8 - TÉCNICAS\nO concurso destina-se à celebração de um acordo-quadro? Inexistência de acordo-quadro\nÉ utilizado um leilão eletrónico? Não\nÉ adotada uma fase de negociação? Não\nSistema de Aquisição Dinâmico: Inexistência de sistema de aquisição dinâmico\n9 - LOCAL DA EXECUÇÃO DO CONTRATO\nLOCAL DA EXECUÇÃO DO CONTRATO (PROCEDIMENTO)\nPaís: Portugal\nNUT III: PT11D\nLocalidade: Viseu\nDistrito: Viseu\nConcelho: Tarouca\nFreguesia: Todas\nLOCAL DA EXECUÇÃO DO CONTRATO (LOTE)\nIdentificador do Lote: LOT-0001; LOT-0002; LOT-0003\nPaís: Portugal\nNUT III: PT11D\nLocalidade: Viseu\nDistrito: Viseu\nConcelho: Tarouca\nFreguesia: Todas\n10 - PRAZO DE EXECUÇÃO DO CONTRATO\nIdentificador do Lote: LOT-0001; LOT-0002; LOT-0003\nPrazo de execução do contrato: 120 DIAS\nPrevisão de renovações: Não\n11 - FUNDOS EU\nIdentificador do Lote: LOT-0001; LOT-0002; LOT-0003\nTêm fundos EU? Não\n12 - DOCUMENTOS DE HABILITAÇÃO\nHabilitação para o exercício da atividade profissional: Não\n13 - CONDIÇÕES DE APRESENTAÇÃO\nPlataforma eletrónica utilizada pela entidade adjudicante: VORTAL\nURL para Apresentação: https://community.vortal.biz/public/\nAdmissibilidade da apresentação de propostas variantes: Não autorizado\nPrazo para apresentação das propostas: 30-01-2026 17:00\nPrazo durante o qual os concorrentes são obrigados a manter as respetivas propostas: 66 dias a contar do termo do prazo para a apresentação das propostas\nIndicação de Subcontratação na Proposta: Inexistência de indicação de subcontratação\n14 - PRESTAÇÃO DE CAUÇÃO\nPrestação de caução: Sim\nPercentagem: 5%\nDescrição da Garantia Exigida: Garantia Bancária\n15 - FORNECIMENTO DAS PEÇAS DO CONCURSO, APRESENTAÇÃO DE PEDIDOS DE PARTICIPAÇÃO E APRESENTAÇÃO DAS PROPOSTAS\nLink para acesso às peças do concurso (URL): https://community.vortal.biz/Public/public-tender-documents/dzFCQ0tVMlA0SldnTzdyc2pZRmVKT3BOam9RaUdVYVJDOG1RdTJWTGV0VlhFbThxT05qNXd3OXZrTENkYW9VUzdwSmF4eTlQV0VnY0luYTZoSlhFU1E9PUxtaSo1\n20 - OUTROS REQUISITOS\nIdentificador do Lote: LOT-0001; LOT-0002; LOT-0003\nInformação sobre contratos reservados. Aplica-se a contratos reservados (54º-A)? Não\n21 - CRITÉRIO DE ADJUDICAÇÃO\nO Critério de adjudicação é diferenciado por lote? Não\nMultifator: Não\nMonofator:\nNome: Preço\n24 - CONDIÇÕES DO CONTRATO\nIdentificador do Lote: LOT-0001; LOT-0002; LOT-0003\nFaturação Eletrónica: Permitido\nObrigação de Subcontratação:\nCódigo da Obrigação de Subcontratação: Não é aplicável nenhuma obrigação de subcontratação.\n25 - COMPRA PÚBLICA ESTRATÉGICA\nCompra Pública Estratégica: Inexistência de contratação pública estratégica\n26 - INFORMAÇÕES ADICIONAIS\nIdentificador do Lote: LOT-0001; LOT-0002; LOT-0003\nContrato adequado para PME: Sim\nCobertura ACP (Acordo dos Contratos Públicos da Organização Mundial do Comércio): Não\n27 - IDENTIFICAÇÃO E CONTACTOS DO ÓRGÃO DE RECURSOS ADMINISTRATIVOS\nDesignação: Câmara Municipal de Tarouca\nEndereço: Av. Alexandre Taveira Cardoso\nCódigo postal: 3610-128\nLocalidade: Tarouca\nTelefone: +351 254677420\nFax: +351 254678552\nEndereço eletrónico: camara@cm-tarouca.pt\n28 - IDENTIFICAÇÃO DO(S) AUTOR(ES) DE ANÚNCIO\nNome: José Damião Lopes Guedes de Melo\nCargo: Presidente da Câmara Municipal\n419948097",
    "nipc": "506753905",
    "distrito": "Viseu",
    "concelho": "Tarouca",
    "freguesia": "Todas",
    "site": "www.cm-tarouca.pt",
    "email": "camara@cm-tarouca.pt",
    "designacao_contrato": "REABILITAÇÃO DAS ESCOLAS DE VÁRZEA DA SERRA, VILA CHÃ DA BEIRA E PINHEIRO - BNAUT",
    "descricao": "REABILITAÇÃO DAS ESCOLAS DE VÁRZEA DA SERRA, VILA CHÃ DA BEIRA E PINHEIRO - BNAUT",
    "preco_base": "1.373.709,27 EUR",
    "prazo_execucao": "120 DIAS",
    "prazo_apresentacao_propostas": "30-01-2026 17:00",
    "fundos_eu": "Não",
    "plataforma_eletronica": "VORTAL",
    "url_procedimento": "https://community.vortal.biz/public/",
    "autor_nome": "José Damião Lopes Guedes de Melo",
    "autor_cargo": "Presidente da Câmara Municipal"
  },
  {
    "numero_procedimento": "N/A",
    "entidade": "Município de Albufeira",
    "link": "https://diariodarepublica.pt/dr/detalhe/contrato-publico/962-1013997945",
    "detalhes_completos": "1 - IDENTIFICAÇÃO E CONTACTOS DA ENTIDADE ADJUDICANTE\nDesignação da entidade adjudicante: Município de Albufeira\nNIPC: 503539473\nEndereço: R. Município\nCódigo postal: 8201-863\nLocalidade: Faro\nPaís: Portugal\nNUT III: PT150\nDistrito: Faro\nConcelho: Albufeira\nFreguesia: Freguesia de Albufeira e Olhos de Água\nTelefone: 289 599 500\nEndereço da Entidade (URL): www.cm-albufeira.pt\nEndereço Eletrónico: geral@cm-albufeira.pt\neDelivery Gateway (URL): https://community.vortal.biz/public/\nFunção da Organização: Adquirente\nNorma jurídica da Entidade Adjudicante: Organismo de direito público\nÁrea de atividade da Autoridade Adjudicante: Serviços públicos das administrações públicas\n2 - JORNAL OFICIAL DA UNIÃO EUROPEIA\nO procedimento a que este anúncio diz respeito também é publicitado no Jornal Oficial da União Europeia? Não\n3 - AVISO\nModelo de Anúncio: Concurso público\nData de Envio do Anúncio: 16-01-2026\n5 - PROCESSO\nTipo de Procedimento: Concurso público\nPreço base do procedimento: Sim\nValor do preço base do procedimento: 149.600,00 EUR\nProcedimento com lotes? Sim\nNº Máx. de Lotes Autorizado: 2\nNúmero máximo de lotes que podem ser adjudicados a um concorrente: 2\n6 - OBJETO DO CONTRATO\nNúmero de referência interna: DDESC/DE/2026/7\nDesignação do contrato: CONCURSO PÚBLICO PARA PARA AQUISIÇÃO DE SERVIÇOS DE ASSISTENTES TÉCNICOS (ANIMADOR SOCIOCULTURAL) E ASSISTENTES OPERACIONAIS \nDescrição: CONCURSO PÚBLICO PARA PARA AQUISIÇÃO DE SERVIÇOS DE ASSISTENTES TÉCNICOS (ANIMADOR SOCIOCULTURAL) E ASSISTENTES OPERACIONAIS PARA AS ESCOLAS, JI’ s, AAAF’ s, ATL’ s, CANTINAS ESCOLARES E OUTROS EQUIPAMENTOS EDUCATIVOS DO CONCELHO\nTipo de Contrato Principal: Aquisição de Serviços\nTipo de Contrato: Aquisição de Serviços\nClassificação CPV (Vocabulário Comum para os Contratos Públicos)\nObjeto principal\nVocabulário Principal: 79600000\nPreço base s/IVA: 149.600,00 EUR\nLotes: \nNº: LOT-0001\nDescrição do Lote: Lote 1 - Assistentes técnicos\nPreço base s/IVA: 90.000,00 EUR\nClassificação CPV (Vocabulário Comum para os Contratos Públicos)\nObjeto principal\nVocabulário Principal: 79600000\nNº: LOT-0002\nDescrição do Lote: Lote 2 - Assistentes Operacionais\nPreço base s/IVA: 59.600,00 EUR\nClassificação CPV (Vocabulário Comum para os Contratos Públicos)\nObjeto principal\nVocabulário Principal: 79600000\n7 - INDICAÇÕES ADICIONAIS\nO contrato envolve aquisição conjunta (satisfação de várias entidades)? Não\nO contrato é adjudicado por uma central de compras? Não\n8 - TÉCNICAS\nO concurso destina-se à celebração de um acordo-quadro? Inexistência de acordo-quadro\nÉ utilizado um leilão eletrónico? Não\nÉ adotada uma fase de negociação? Não\nSistema de Aquisição Dinâmico: Inexistência de sistema de aquisição dinâmico\n9 - LOCAL DA EXECUÇÃO DO CONTRATO\nLOCAL DA EXECUÇÃO DO CONTRATO (PROCEDIMENTO)\nPaís: Portugal\nNUT III: PT150\nLocalidade: Faro\nDistrito: Faro\nConcelho: Albufeira\nFreguesia: Freguesia de Albufeira e Olhos de Água\nLOCAL DA EXECUÇÃO DO CONTRATO (LOTE)\nIdentificador do Lote: LOT-0001; LOT-0002\nPaís: Portugal\nNUT III: PT150\nLocalidade: Faro\nDistrito: Faro\nConcelho: Albufeira\nFreguesia: Freguesia de Albufeira e Olhos de Água\n10 - PRAZO DE EXECUÇÃO DO CONTRATO\nIdentificador do Lote: LOT-0001; LOT-0002\nPrazo de execução do contrato: 23 MESES\nPrevisão de renovações: Não\n11 - FUNDOS EU\nIdentificador do Lote: LOT-0001; LOT-0002\nTêm fundos EU? Não\n12 - DOCUMENTOS DE HABILITAÇÃO\nHabilitação para o exercício da atividade profissional: Não\n13 - CONDIÇÕES DE APRESENTAÇÃO\nPlataforma eletrónica utilizada pela entidade adjudicante: VORTAL\nURL para Apresentação: https://community.vortal.biz/public/\nAdmissibilidade da apresentação de propostas variantes: Não autorizado\nPrazo para apresentação das propostas: 21-01-2026 23:59\nPrazo durante o qual os concorrentes são obrigados a manter as respetivas propostas: 66 dias a contar do termo do prazo para a apresentação das propostas\nIndicação de Subcontratação na Proposta: Inexistência de indicação de subcontratação\n14 - PRESTAÇÃO DE CAUÇÃO\nPrestação de caução: Não\n15 - FORNECIMENTO DAS PEÇAS DO CONCURSO, APRESENTAÇÃO DE PEDIDOS DE PARTICIPAÇÃO E APRESENTAÇÃO DAS PROPOSTAS\nLink para acesso às peças do concurso (URL): https://community.vortal.biz/Public/public-tender-documents/YmJBUWxvc3FFK011Wi9vN0MyL3JyWmRWblpwNVJqOC90UnllaUtHVllzeTdlWW1uT3NNQWdtZllrdVZCN1N2alhPR2tvVU1pYlkvRVV2dndkT01JeXc9PXYmTkdk\n20 - OUTROS REQUISITOS\nIdentificador do Lote: LOT-0001; LOT-0002\nInformação sobre contratos reservados. Aplica-se a contratos reservados (54º-A)? Não\n21 - CRITÉRIO DE ADJUDICAÇÃO\nO Critério de adjudicação é diferenciado por lote? Não\nMultifator: Não\nMonofator:\nNome: Preço\n24 - CONDIÇÕES DO CONTRATO\nIdentificador do Lote: LOT-0001; LOT-0002\nFaturação Eletrónica: Permitido\nObrigação de Subcontratação:\nCódigo da Obrigação de Subcontratação: Não é aplicável nenhuma obrigação de subcontratação.\n25 - COMPRA PÚBLICA ESTRATÉGICA\nCompra Pública Estratégica: Inexistência de contratação pública estratégica\n26 - INFORMAÇÕES ADICIONAIS\nIdentificador do Lote: LOT-0001; LOT-0002\nContrato adequado para PME: Sim\nCobertura ACP (Acordo dos Contratos Públicos da Organização Mundial do Comércio): Não\n27 - IDENTIFICAÇÃO E CONTACTOS DO ÓRGÃO DE RECURSOS ADMINISTRATIVOS\nDesignação: Rui Celestino dos Santos Cristina\nEndereço: R. do Município.\nCódigo postal: 8201-863\nLocalidade: Albufeira\nTelefone: +351 289599500\nFax: +351 289589558\nEndereço eletrónico: geral@cm-albufeira.pt\n28 - IDENTIFICAÇÃO DO(S) AUTOR(ES) DE ANÚNCIO\nNome: Rui Celestino dos Santos Cristina\nCargo: Presidente da Câmara Municipal de Albufeira\n419948058",
    "nipc": "503539473",
    "distrito": "Faro",
    "concelho": "Albufeira",
    "freguesia": "Freguesia de Albufeira e Olhos de Água",
    "site": "www.cm-albufeira.pt",
    "email": "geral@cm-albufeira.pt",
    "designacao_contrato": "CONCURSO PÚBLICO PARA PARA AQUISIÇÃO DE SERVIÇOS DE ASSISTENTES TÉCNICOS (ANIMADOR SOCIOCULTURAL) E ASSISTENTES OPERACIONAIS",
    "descricao": "CONCURSO PÚBLICO PARA PARA AQUISIÇÃO DE SERVIÇOS DE ASSISTENTES TÉCNICOS (ANIMADOR SOCIOCULTURAL) E ASSISTENTES OPERACIONAIS PARA AS ESCOLAS, JI’ s, AAAF’ s, ATL’ s, CANTINAS ESCOLARES E OUTROS EQUIPAMENTOS EDUCATIVOS DO CONCELHO",
    "preco_base": "149.600,00 EUR",
    "prazo_execucao": "23 MESES",
    "prazo_apresentacao_propostas": "21-01-2026 23:59",
    "fundos_eu": "Não",
    "plataforma_eletronica": "VORTAL",
    "url_procedimento": "https://community.vortal.biz/public/",
    "autor_nome": "Rui Celestino dos Santos Cristina",
    "autor_cargo": "Presidente da Câmara Municipal de Albufeira"
  },
  {
    "numero_procedimento": "N/A",
    "entidade": "AnÃºncio de procedimento  n.Âº 963/2026  -  DiÃ¡rio da RepÃºblica n.Âº 11/2026, SÃ©rie II de 2026-01-16",
    "link": "https://diariodarepublica.pt/dr/detalhe/contrato-publico/963-1013997947"
  },
  {
    "numero_procedimento": "N/A",
    "entidade": "AnÃºncio de procedimento  n.Âº 965/2026  -  DiÃ¡rio da RepÃºblica n.Âº 11/2026, SÃ©rie II de 2026-01-16",
    "link": "https://diariodarepublica.pt/dr/detalhe/contrato-publico/965-1013997948"
  },
  {
    "numero_procedimento": "N/A",
    "entidade": "AnÃºncio de procedimento  n.Âº 967/2026  -  DiÃ¡rio da RepÃºblica n.Âº 11/2026, SÃ©rie II de 2026-01-16",
    "link": "https://diariodarepublica.pt/dr/detalhe/contrato-publico/967-1013997949"
  },
  {
    "numero_procedimento": "N/A",
    "entidade": "Unidade Local de Saúde de Gaia/Espinho, EPE",
    "link": "https://diariodarepublica.pt/dr/detalhe/contrato-publico/968-1013997950",
    "detalhes_completos": "1 - IDENTIFICAÇÃO E CONTACTOS DA ENTIDADE ADJUDICANTE\nDesignação da entidade adjudicante: Unidade Local de Saúde de Gaia/Espinho, EPE\nNIPC: 508142156\nEndereço: R Conceição Fernandes , Vila Nova Gaia\nCódigo postal: 4434-502\nLocalidade: Área Metropolitana do Porto\nPaís: Portugal\nNUT III: PT11A\nDistrito: Porto\nConcelho: Vila Nova de Gaia\nFreguesia: Freguesia de Vilar de Andorinho\nTelefone: 227865100\nFax: 227830209\nEndereço da Entidade (URL): www.chvng.min-saude.pt\nEndereço Eletrónico: info@chvng.min-saude.pt\neDelivery Gateway (URL): https://community.vortal.biz/public/\nFunção da Organização: Adquirente\nNorma jurídica da Entidade Adjudicante: Organismo de direito público\nÁrea de atividade da Autoridade Adjudicante: Saúde\n2 - JORNAL OFICIAL DA UNIÃO EUROPEIA\nO procedimento a que este anúncio diz respeito também é publicitado no Jornal Oficial da União Europeia? Não\n3 - AVISO\nModelo de Anúncio: Concurso público\nData de Envio do Anúncio: 16-01-2026\n5 - PROCESSO\nTipo de Procedimento: Concurso público\nPreço base do procedimento: Sim\nValor do preço base do procedimento: 16.750,00 EUR\nProcedimento com lotes? Não\n6 - OBJETO DO CONTRATO\nNúmero de referência interna: 2036326\nDesignação do contrato: Aquisição de Afastador Abdominal \nDescrição: Aquisição de Afastador Abdominal \nTipo de Contrato Principal: Aquisição de Bens Móveis\nTipo de Contrato: Aquisição de Bens Móveis\nClassificação CPV (Vocabulário Comum para os Contratos Públicos)\nObjeto principal\nVocabulário Principal: 33169000\nPreço base s/IVA: 16.750,00 EUR\n7 - INDICAÇÕES ADICIONAIS\nO contrato envolve aquisição conjunta (satisfação de várias entidades)? Não\nO contrato é adjudicado por uma central de compras? Não\n8 - TÉCNICAS\nO concurso destina-se à celebração de um acordo-quadro? Inexistência de acordo-quadro\nÉ utilizado um leilão eletrónico? Não\nÉ adotada uma fase de negociação? Não\nSistema de Aquisição Dinâmico: Inexistência de sistema de aquisição dinâmico\n9 - LOCAL DA EXECUÇÃO DO CONTRATO\nLOCAL DA EXECUÇÃO DO CONTRATO (PROCEDIMENTO)\nPaís: Portugal\nNUT III: PT11A\nLocalidade: Área Metropolitana do Porto\nDistrito: Porto\nConcelho: Vila Nova de Gaia\nFreguesia: Freguesia de Vilar de Andorinho\n10 - PRAZO DE EXECUÇÃO DO CONTRATO\nPrazo de execução do contrato: 36 MESES\nPrevisão de renovações: Não\n11 - FUNDOS EU\nTêm fundos EU? Não\n12 - DOCUMENTOS DE HABILITAÇÃO\nHabilitação para o exercício da atividade profissional: Não\n13 - CONDIÇÕES DE APRESENTAÇÃO\nPlataforma eletrónica utilizada pela entidade adjudicante: VORTAL\nURL para Apresentação: https://community.vortal.biz/public/\nAdmissibilidade da apresentação de propostas variantes: Não autorizado\nPrazo para apresentação das propostas: 22-01-2026 17:00\nPrazo durante o qual os concorrentes são obrigados a manter as respetivas propostas: 180 dias a contar do termo do prazo para a apresentação das propostas\nIndicação de Subcontratação na Proposta: Inexistência de indicação de subcontratação\n14 - PRESTAÇÃO DE CAUÇÃO\nPrestação de caução: Não\n15 - FORNECIMENTO DAS PEÇAS DO CONCURSO, APRESENTAÇÃO DE PEDIDOS DE PARTICIPAÇÃO E APRESENTAÇÃO DAS PROPOSTAS\nLink para acesso às peças do concurso (URL): https://community.vortal.biz/Public/public-tender-documents/ZFgzaHhJbkRJYS9NQVdoaDNKMmRjVE5Ia2h5WkhIcnhhUlVTNHI3dGNqbTBFaUtlSlp3M0dOYnFhcjZUU3V5bXZZTlFQaDZYTkNOc0Y3N29SdE5kQXc9PU8kNm9X\n20 - OUTROS REQUISITOS\nInformação sobre contratos reservados. Aplica-se a contratos reservados (54º-A)? Não\n21 - CRITÉRIO DE ADJUDICAÇÃO\nMultifator: Sim\nFator: \nNome: Preço\nPonderação: 50%\nSubfatores: Não\nFator: \nNome: Qualidade\nPonderação: 50%\nSubfatores: Não\n24 - CONDIÇÕES DO CONTRATO\nFaturação Eletrónica: Permitido\nObrigação de Subcontratação:\nCódigo da Obrigação de Subcontratação: Não é aplicável nenhuma obrigação de subcontratação.\n25 - COMPRA PÚBLICA ESTRATÉGICA\nCompra Pública Estratégica: Inexistência de contratação pública estratégica\n26 - INFORMAÇÕES ADICIONAIS\nContrato adequado para PME: Sim\nCobertura ACP (Acordo dos Contratos Públicos da Organização Mundial do Comércio): Não\n27 - IDENTIFICAÇÃO E CONTACTOS DO ÓRGÃO DE RECURSOS ADMINISTRATIVOS\nDesignação: Conselho de Administração\nEndereço: Rua Conceição Fernandes, Vila Nova de Gaia\nCódigo postal: 4434-502\nLocalidade: Vila Nova de Gaia\nTelefone: +351 227865100\nFax: +351 227830209\nEndereço eletrónico: geral@ulsge.min-saude.pt\n28 - IDENTIFICAÇÃO DO(S) AUTOR(ES) DE ANÚNCIO\nNome: Daniela França\nCargo: Assistente Técnica\n419947863",
    "nipc": "508142156",
    "distrito": "Porto",
    "concelho": "Vila Nova de Gaia",
    "freguesia": "Freguesia de Vilar de Andorinho",
    "site": "www.chvng.min-saude.pt",
    "email": "info@chvng.min-saude.pt",
    "designacao_contrato": "Aquisição de Afastador Abdominal",
    "descricao": "Aquisição de Afastador Abdominal",
    "preco_base": "16.750,00 EUR",
    "prazo_execucao": "36 MESES",
    "prazo_apresentacao_propostas": "22-01-2026 17:00",
    "fundos_eu": "Não",
    "plataforma_eletronica": "VORTAL",
    "url_procedimento": "https://community.vortal.biz/public/",
    "autor_nome": "Daniela França",
    "autor_cargo": "Assistente Técnica"
  },
  {
    "numero_procedimento": "N/A",
    "entidade": "AnÃºncio de procedimento  n.Âº 971/2026  -  DiÃ¡rio da RepÃºblica n.Âº 11/2026, SÃ©rie II de 2026-01-16",
    "link": "https://diariodarepublica.pt/dr/detalhe/contrato-publico/971-1013997951"
  },
  {
    "numero_procedimento": "N/A",
    "entidade": "AnÃºncio de procedimento  n.Âº 972/2026  -  DiÃ¡rio da RepÃºblica n.Âº 11/2026, SÃ©rie II de 2026-01-16",
    "link": "https://diariodarepublica.pt/dr/detalhe/contrato-publico/972-1013997952"
  },
  {
    "numero_procedimento": "N/A",
    "entidade": "AnÃºncio de procedimento  n.Âº 974/2026  -  DiÃ¡rio da RepÃºblica n.Âº 11/2026, SÃ©rie II de 2026-01-16",
    "link": "https://diariodarepublica.pt/dr/detalhe/contrato-publico/974-1013997953"
  },
  {
    "numero_procedimento": "N/A",
    "entidade": "Secretaria Regional de Equipamentos e Infraestruturas",
    "link": "https://diariodarepublica.pt/dr/detalhe/contrato-publico/975-1013997955",
    "detalhes_completos": "Alteração do Anúncio de procedimento n.º 32898/2025, de 2025-12-18, com o ID 419907114\n1 - IDENTIFICAÇÃO E CONTACTOS DA ENTIDADE ADJUDICANTE\nDesignação da entidade adjudicante: Secretaria Regional de Equipamentos e Infraestruturas\nNIPC: 671001329\nServiço/Órgão/Pessoa de contacto: Conforme as peças do procedimento.\nEndereço: Rua Dr. Pestana Júnior, nº 6\nCódigo postal: 9064-506\nLocalidade: Funchal\nPaís: Portugal\nNUT III: PT300\nDistrito: Região Autónoma da Madeira\nConcelho: Funchal\nFreguesia: Todas\nTelefone: 291212100\nFax: 291232102\nEndereço da Entidade (URL): https://www.madeira.gov.pt/srei\nEndereço Eletrónico: gabinete.srei@madeira.gov.pt\neDelivery Gateway (URL): https://www.acingov.pt\nFunção da Organização: Adquirente\nNorma jurídica da Entidade Adjudicante: Organismo de direito público\nÁrea de atividade da Autoridade Adjudicante: Serviços públicos das administrações públicas\n2 - JORNAL OFICIAL DA UNIÃO EUROPEIA\nO procedimento a que este anúncio diz respeito também é publicitado no Jornal Oficial da União Europeia? Não\n3 - AVISO\nModelo de Anúncio: Concurso público\nData de Envio do Anúncio: 16-01-2026\n5 - PROCESSO\nTipo de Procedimento: Concurso público\nPreço base do procedimento: Sim\nValor do preço base do procedimento: 4.650.000,00 EUR\nProcedimento com lotes? Não\n6 - OBJETO DO CONTRATO\nNúmero de referência interna: 29CPL25_ES\nDesignação do contrato: Reabilitação Estrutural do Cais Velho e Recuperação do Pontão das Salinas na Cidade Vila Baleira - Porto Santo\nDescrição: Reabilitação Estrutural do Cais Velho e Recuperação do Pontão das Salinas na Cidade Vila Baleira - Porto Santo\nTipo de Contrato Principal: Empreitada de Obras Públicas\nTipo de Contrato: Empreitada de Obras Públicas\nClassificação CPV (Vocabulário Comum para os Contratos Públicos)\nObjeto principal\nVocabulário Principal: 45240000\nPreço base s/IVA: 4.650.000,00 EUR\n7 - INDICAÇÕES ADICIONAIS\nO contrato envolve aquisição conjunta (satisfação de várias entidades)? Não\nO contrato é adjudicado por uma central de compras? Não\n8 - TÉCNICAS\nO concurso destina-se à celebração de um acordo-quadro? Inexistência de acordo-quadro\nÉ utilizado um leilão eletrónico? Não\nÉ adotada uma fase de negociação? Não\nSistema de Aquisição Dinâmico: Inexistência de sistema de aquisição dinâmico\n9 - LOCAL DA EXECUÇÃO DO CONTRATO\nLOCAL DA EXECUÇÃO DO CONTRATO (PROCEDIMENTO)\nPaís: Portugal\nNUT III: PT300\nLocalidade: Freguesia de Porto Santo\nDistrito: Região Autónoma da Madeira\nConcelho: Porto Santo\nFreguesia: Freguesia de Porto Santo\n10 - PRAZO DE EXECUÇÃO DO CONTRATO\nPrazo de execução do contrato: 540 DIAS\nPrevisão de renovações: Não\n11 - FUNDOS EU\nTêm fundos EU? Não\n12 - DOCUMENTOS DE HABILITAÇÃO\nHabilitação para o exercício da atividade profissional: Sim\nTipo: Alvará\nDescrição: O adjudicatário deverá ser titular do alvará de empreiteiro de Obras Públicas emitido pelo IMPIC, I.P., contendo as seguintes habilitações: 2.ª subcategoria - Obras portuárias, da 3.ª categoria - Obras hidráulicas, na classe que cubra o valor global da proposta, ou, se for o caso, declaração emitida pelo IMPIC, I.P., nos termos previstos no número 4 do artigo 3.º da Portaria número 372/2017, de 14 de dezembro.\n13 - CONDIÇÕES DE APRESENTAÇÃO\nPlataforma eletrónica utilizada pela entidade adjudicante: ACIN\nURL para Apresentação: https://www.acingov.pt\nAdmissibilidade da apresentação de propostas variantes: Não autorizado\nPrazo para apresentação das propostas: 27-01-2026 17:00\nPrazo durante o qual os concorrentes são obrigados a manter as respetivas propostas: 180 dias a contar do termo do prazo para a apresentação das propostas\nIndicação de Subcontratação na Proposta: A parte do contrato que o proponente tenciona subcontratar\n14 - PRESTAÇÃO DE CAUÇÃO\nPrestação de caução: Sim\nPercentagem: 2%\nDescrição da Garantia Exigida: O valor da caução é de 2.00% do preço contratual.\n15 - FORNECIMENTO DAS PEÇAS DO CONCURSO, APRESENTAÇÃO DE PEDIDOS DE PARTICIPAÇÃO E APRESENTAÇÃO DAS PROPOSTAS\nLink para acesso às peças do concurso (URL): https://www.acingov.pt/acingovprod/2/zonaPublica/zona_publica_c/donwloadProcedurePiece/MTAwNTExOQ==\n20 - OUTROS REQUISITOS\nInformação sobre contratos reservados. Aplica-se a contratos reservados (54º-A)? Não\n21 - CRITÉRIO DE ADJUDICAÇÃO\nMultifator: Não\nMonofator:\nNome: Preço\n24 - CONDIÇÕES DO CONTRATO\nFaturação Eletrónica: Necessário\nObrigação de Subcontratação:\nCódigo da Obrigação de Subcontratação: Não é aplicável nenhuma obrigação de subcontratação.\n25 - COMPRA PÚBLICA ESTRATÉGICA\nCompra Pública Estratégica: Inexistência de contratação pública estratégica\n26 - INFORMAÇÕES ADICIONAIS\nContrato adequado para PME: Sim\nCobertura ACP (Acordo dos Contratos Públicos da Organização Mundial do Comércio): Não\n27 - IDENTIFICAÇÃO E CONTACTOS DO ÓRGÃO DE RECURSOS ADMINISTRATIVOS\nDesignação: Conforme Legislação aplicável\nEndereço: Conforme as peças do procedimento.\nCódigo postal: 9064-506\nLocalidade: Funchal\nTelefone: 2911145200\nFax: 2911145200\nEndereço eletrónico: gabinete.srei@madeira.gov.pt\nPrazo de interposição do recurso: 5 dias\n28 - IDENTIFICAÇÃO DO(S) AUTOR(ES) DE ANÚNCIO\nNome: João Ricardo Luís dos Reis\nCargo: Diretor Regional\n29 - ALTERAÇÃO\nMotivo da Alteração: Informações atualizadas\nIdentificador da Versão do Anúncio a Alterar: f2d603d1-1eff-4d36-8685-959a069631df-01\nIdentificador das Secções Alteradas do Anúncio Anterior: Condições de Apresentação\nDescrição das Alterações: Decisão de prorrogação do prazo fixado para a apresentação de propostas por despacho do Secretário Regional de Equipamentos e Infraestruturas datado de 16/01/2026.\nAlteração dos Documentos do Concurso: Não\n419948136",
    "nipc": "671001329",
    "distrito": "Região Autónoma da Madeira",
    "concelho": "Funchal",
    "freguesia": "Todas",
    "site": "https://www.madeira.gov.pt/srei",
    "email": "gabinete.srei@madeira.gov.pt",
    "designacao_contrato": "Reabilitação Estrutural do Cais Velho e Recuperação do Pontão das Salinas na Cidade Vila Baleira - Porto Santo",
    "descricao": "Reabilitação Estrutural do Cais Velho e Recuperação do Pontão das Salinas na Cidade Vila Baleira - Porto Santo",
    "preco_base": "4.650.000,00 EUR",
    "prazo_execucao": "540 DIAS",
    "prazo_apresentacao_propostas": "27-01-2026 17:00",
    "fundos_eu": "Não",
    "plataforma_eletronica": "ACIN",
    "url_procedimento": "https://www.acingov.pt",
    "autor_nome": "João Ricardo Luís dos Reis",
    "autor_cargo": "Diretor Regional"
  },
  {
    "numero_procedimento": "N/A",
    "entidade": "AnÃºncio de procedimento  n.Âº 976/2026  -  DiÃ¡rio da RepÃºblica n.Âº 11/2026, SÃ©rie II de 2026-01-16",
    "link": "https://diariodarepublica.pt/dr/detalhe/contrato-publico/976-1013997956"
  },
  {
    "numero_procedimento": "N/A",
    "entidade": "Secretaria Regional de Equipamentos e Infraestruturas",
    "link": "https://diariodarepublica.pt/dr/detalhe/contrato-publico/977-1013997957",
    "detalhes_completos": "1 - IDENTIFICAÇÃO E CONTACTOS DA ENTIDADE ADJUDICANTE\nDesignação da entidade adjudicante: Secretaria Regional de Equipamentos e Infraestruturas\nNIPC: 671001329\nServiço/Órgão/Pessoa de contacto: Conforme as peças do procedimento.\nEndereço: Rua Dr. Pestana Júnior, nº 6\nCódigo postal: 9064-506\nLocalidade: Funchal\nPaís: Portugal\nNUT III: PT300\nDistrito: Região Autónoma da Madeira\nConcelho: Funchal\nFreguesia: Todas\nTelefone: 291212100\nFax: 291232102\nEndereço da Entidade (URL): https://www.madeira.gov.pt/srei\nEndereço Eletrónico: gabinete.srei@madeira.gov.pt\neDelivery Gateway (URL): https://www.acingov.pt\nFunção da Organização: Adquirente\nNorma jurídica da Entidade Adjudicante: Organismo de direito público\nÁrea de atividade da Autoridade Adjudicante: Serviços públicos das administrações públicas\n2 - JORNAL OFICIAL DA UNIÃO EUROPEIA\nO procedimento a que este anúncio diz respeito também é publicitado no Jornal Oficial da União Europeia? Não\n3 - AVISO\nModelo de Anúncio: Concurso público\nData de Envio do Anúncio: 16-01-2026\n5 - PROCESSO\nTipo de Procedimento: Concurso público\nPreço base do procedimento: Sim\nValor do preço base do procedimento: 290.000,00 EUR\nProcedimento com lotes? Não\n6 - OBJETO DO CONTRATO\nNúmero de referência interna: 2CPL26_SREI_DRESC\nDesignação do contrato: Campo de Futebol da Camacha - Iluminação\nDescrição: Campo de Futebol da Camacha - Iluminação\nTipo de Contrato Principal: Empreitada de Obras Públicas\nTipo de Contrato: Empreitada de Obras Públicas\nClassificação CPV (Vocabulário Comum para os Contratos Públicos)\nObjeto principal\nVocabulário Principal: 45316100\nPreço base s/IVA: 290.000,00 EUR\n7 - INDICAÇÕES ADICIONAIS\nO contrato envolve aquisição conjunta (satisfação de várias entidades)? Não\nO contrato é adjudicado por uma central de compras? Não\n8 - TÉCNICAS\nO concurso destina-se à celebração de um acordo-quadro? Inexistência de acordo-quadro\nÉ utilizado um leilão eletrónico? Não\nÉ adotada uma fase de negociação? Não\nSistema de Aquisição Dinâmico: Inexistência de sistema de aquisição dinâmico\n9 - LOCAL DA EXECUÇÃO DO CONTRATO\nLOCAL DA EXECUÇÃO DO CONTRATO (PROCEDIMENTO)\nPaís: Portugal\nNUT III: PT300\nLocalidade: Freguesia de Camacha\nDistrito: Região Autónoma da Madeira\nConcelho: Santa Cruz\nFreguesia: Freguesia de Camacha\n10 - PRAZO DE EXECUÇÃO DO CONTRATO\nPrazo de execução do contrato: 120 DIAS\nPrevisão de renovações: Não\n11 - FUNDOS EU\nTêm fundos EU? Não\n12 - DOCUMENTOS DE HABILITAÇÃO\nHabilitação para o exercício da atividade profissional: Sim\nTipo: Alvará\nDescrição: O adjudicatário deverá ser titular do alvará de empreiteiro de Obras Públicas emitido pelo IMPIC, I.P., contendo as seguintes habilitações: a 1.ª subcategoria - Instalações elétricas de utilização de baixa tensão com potência até 50 KVA da 4.ª categoria - Instalações elétricas e mecânicas, na classe que cubra o valor global da proposta, ou, se for o caso, declaração emitida pelo IMPIC, I.P., nos termos previstos no número 4 do artigo 3.º da Portaria número 372/2017, de 14 de dezembro.\n13 - CONDIÇÕES DE APRESENTAÇÃO\nPlataforma eletrónica utilizada pela entidade adjudicante: ACIN\nURL para Apresentação: https://www.acingov.pt\nAdmissibilidade da apresentação de propostas variantes: Não autorizado\nPrazo para apresentação das propostas: 05-02-2026 17:00\nPrazo durante o qual os concorrentes são obrigados a manter as respetivas propostas: 180 dias a contar do termo do prazo para a apresentação das propostas\nIndicação de Subcontratação na Proposta: A parte do contrato que o proponente tenciona subcontratar\n14 - PRESTAÇÃO DE CAUÇÃO\nPrestação de caução: Não\n15 - FORNECIMENTO DAS PEÇAS DO CONCURSO, APRESENTAÇÃO DE PEDIDOS DE PARTICIPAÇÃO E APRESENTAÇÃO DAS PROPOSTAS\nLink para acesso às peças do concurso (URL): https://www.acingov.pt/acingovprod/2/zonaPublica/zona_publica_c/donwloadProcedurePiece/MTA0MDgwMQ==\n20 - OUTROS REQUISITOS\nInformação sobre contratos reservados. Aplica-se a contratos reservados (54º-A)? Não\n21 - CRITÉRIO DE ADJUDICAÇÃO\nMultifator: Não\nMonofator:\nNome: Preço\n24 - CONDIÇÕES DO CONTRATO\nFaturação Eletrónica: Necessário\nObrigação de Subcontratação:\nCódigo da Obrigação de Subcontratação: Não é aplicável nenhuma obrigação de subcontratação.\n25 - COMPRA PÚBLICA ESTRATÉGICA\nCompra Pública Estratégica: Inexistência de contratação pública estratégica\n26 - INFORMAÇÕES ADICIONAIS\nContrato adequado para PME: Sim\nCobertura ACP (Acordo dos Contratos Públicos da Organização Mundial do Comércio): Não\n27 - IDENTIFICAÇÃO E CONTACTOS DO ÓRGÃO DE RECURSOS ADMINISTRATIVOS\nDesignação: Conforme Legislação aplicável\nEndereço: Conforme as peças do procedimento.\nCódigo postal: 9064-506\nLocalidade: Funchal\nTelefone: 2911145200\nFax: 2911145200\nEndereço eletrónico: gabinete.srei@madeira.gov.pt\nPrazo de interposição do recurso: 5 dias\n28 - IDENTIFICAÇÃO DO(S) AUTOR(ES) DE ANÚNCIO\nNome: JOÃO RICARDO LUIS DOS REIS\nCargo: DIRETOR REGIONAL\n419948176",
    "nipc": "671001329",
    "distrito": "Região Autónoma da Madeira",
    "concelho": "Funchal",
    "freguesia": "Todas",
    "site": "https://www.madeira.gov.pt/srei",
    "email": "gabinete.srei@madeira.gov.pt",
    "designacao_contrato": "Campo de Futebol da Camacha - Iluminação",
    "descricao": "Campo de Futebol da Camacha - Iluminação",
    "preco_base": "290.000,00 EUR",
    "prazo_execucao": "120 DIAS",
    "prazo_apresentacao_propostas": "05-02-2026 17:00",
    "fundos_eu": "Não",
    "plataforma_eletronica": "ACIN",
    "url_procedimento": "https://www.acingov.pt",
    "autor_nome": "JOÃO RICARDO LUIS DOS REIS",
    "autor_cargo": "DIRETOR REGIONAL"
  },
  {
    "numero_procedimento": "N/A",
    "entidade": "Penafiel Verde, EM",
    "link": "https://diariodarepublica.pt/dr/detalhe/contrato-publico/979-1013997958",
    "detalhes_completos": "Alteração do Anúncio de procedimento n.º 160/2026, de 2026-01-06, com o ID 419947148\n1 - IDENTIFICAÇÃO E CONTACTOS DA ENTIDADE ADJUDICANTE\nDesignação da entidade adjudicante: Penafiel Verde, EM\nNIPC: 507700651\nEndereço: Rua Abílio Miranda\nCódigo postal: 4560-501\nLocalidade: Porto\nPaís: Portugal\nNUT III: PT11C\nDistrito: Porto\nConcelho: Penafiel\nFreguesia: Freguesia de Penafiel\nTelefone: 255710130\nFax: 255710130\nEndereço da Entidade (URL): https://www.penafielverde.pt/\nEndereço Eletrónico: contratacaopublica@penafielverde.pt\neDelivery Gateway (URL): https://community.vortal.biz/public/\nFunção da Organização: Adquirente\nNorma jurídica da Entidade Adjudicante: Empresa pública\nÁrea de atividade da Entidade Adjudicante: Serviços urbanos de caminho de ferro, de elétricos, de tróleis ou de autocarros\n2 - JORNAL OFICIAL DA UNIÃO EUROPEIA\nO procedimento a que este anúncio diz respeito também é publicitado no Jornal Oficial da União Europeia? Não\n3 - AVISO\nModelo de Anúncio: Concurso público\nData de Envio do Anúncio: 16-01-2026\n5 - PROCESSO\nTipo de Procedimento: Concurso público\nPreço base do procedimento: Sim\nValor do preço base do procedimento: 13.238,00 EUR\nProcedimento com lotes? Não\n6 - OBJETO DO CONTRATO\nNúmero de referência interna: 2025-71\nDesignação do contrato: AQUISIÇÃO DE TINAS DE RETENÇÃO E KIT'S DE EMERGÊNCIA PARA DERRAMES DE PRODUTOS QUIMICOS\nDescrição: AQUISIÇÃO DE TINAS DE RETENÇÃO E KIT'S DE EMERGÊNCIA PARA DERRAMES DE PRODUTOS QUIMICOS\nTipo de Contrato Principal: Aquisição de Bens Móveis\nTipo de Contrato: Aquisição de Bens Móveis\nClassificação CPV (Vocabulário Comum para os Contratos Públicos)\nObjeto principal\nVocabulário Principal: 44421722\nPreço base s/IVA: 13.238,00 EUR\n7 - INDICAÇÕES ADICIONAIS\nO contrato envolve aquisição conjunta (satisfação de várias entidades)? Não\nO contrato é adjudicado por uma central de compras? Não\n8 - TÉCNICAS\nO concurso destina-se à celebração de um acordo-quadro? Inexistência de acordo-quadro\nÉ utilizado um leilão eletrónico? Não\nÉ adotada uma fase de negociação? Não\nSistema de Aquisição Dinâmico: Inexistência de sistema de aquisição dinâmico\n9 - LOCAL DA EXECUÇÃO DO CONTRATO\nLOCAL DA EXECUÇÃO DO CONTRATO (PROCEDIMENTO)\nPaís: Portugal\nNUT III: PT11C\nLocalidade: Porto\nDistrito: Porto\nConcelho: Penafiel\nFreguesia: Freguesia de Penafiel\n10 - PRAZO DE EXECUÇÃO DO CONTRATO\nPrazo de execução do contrato: 6 MESES\nPrevisão de renovações: Não\n11 - FUNDOS EU\nTêm fundos EU? Não\n12 - DOCUMENTOS DE HABILITAÇÃO\nHabilitação para o exercício da atividade profissional: Não\n13 - CONDIÇÕES DE APRESENTAÇÃO\nPlataforma eletrónica utilizada pela entidade adjudicante: VORTAL\nURL para Apresentação: https://community.vortal.biz/public/\nAdmissibilidade da apresentação de propostas variantes: Não autorizado\nPrazo para apresentação das propostas: 02-02-2026 23:59\nPrazo durante o qual os concorrentes são obrigados a manter as respetivas propostas: 90 dias a contar do termo do prazo para a apresentação das propostas\nApresentação de Catálogo Eletrónico: Permitido\nIndicação de Subcontratação na Proposta: Inexistência de indicação de subcontratação\n14 - PRESTAÇÃO DE CAUÇÃO\nPrestação de caução: Não\n15 - FORNECIMENTO DAS PEÇAS DO CONCURSO, APRESENTAÇÃO DE PEDIDOS DE PARTICIPAÇÃO E APRESENTAÇÃO DAS PROPOSTAS\nLink para acesso às peças do concurso (URL): https://community.vortal.biz/Public/public-tender-documents/bmFNeFRSTk1lZnhodWQ0N1dwMEZhSE95Z3hvYURUOEFjeHBOR050UG1kTm4xK3lrUklqUWk2UEJXYWRBSUZKODJ0cGlHeTlEZUNDZFlLcGRKNE55MVE9PShJT1VU\n20 - OUTROS REQUISITOS\nInformação sobre contratos reservados. Aplica-se a contratos reservados (54º-A)? Não\n21 - CRITÉRIO DE ADJUDICAÇÃO\nMultifator: Não\nMonofator:\nNome: Preço\n24 - CONDIÇÕES DO CONTRATO\nFaturação Eletrónica: Permitido\nObrigação de Subcontratação:\nCódigo da Obrigação de Subcontratação: Não é aplicável nenhuma obrigação de subcontratação.\n25 - COMPRA PÚBLICA ESTRATÉGICA\nCompra Pública Estratégica: Inexistência de contratação pública estratégica\n26 - INFORMAÇÕES ADICIONAIS\nContrato adequado para PME: Sim\nCobertura ACP (Acordo dos Contratos Públicos da Organização Mundial do Comércio): Não\n27 - IDENTIFICAÇÃO E CONTACTOS DO ÓRGÃO DE RECURSOS ADMINISTRATIVOS\nDesignação: Conselho de Administração\nEndereço: Rua Abílio Miranda\nCódigo postal: 4560-501\nLocalidade: Penafiel\nTelefone: +351 255710130\nFax: +351 255710130\nEndereço eletrónico: contratacaopublica@penafielverde.pt\n28 - IDENTIFICAÇÃO DO(S) AUTOR(ES) DE ANÚNCIO\nNome: Fátima Sousa\nCargo: Assistente Técnico\n29 - ALTERAÇÃO\nMotivo da Alteração: Informações atualizadas\nIdentificador da Versão do Anúncio a Alterar: 792148f8-d880-4063-97f6-01757aa52388-01\nIdentificador das Secções Alteradas do Anúncio Anterior: Condições do Contrato\nDescrição das Alterações: Alterado o anexo III ao programa do concurso;\nAlteradas as características dos produtos para absorção (folhas, almofadas absorventes e Bolsa para resíduos);\nAlteração dos Documentos do Concurso: Sim\nData de alteração dos documentos do concurso: 16-01-2026\n419948237",
    "nipc": "507700651",
    "distrito": "Porto",
    "concelho": "Penafiel",
    "freguesia": "Freguesia de Penafiel",
    "site": "https://www.penafielverde.pt/",
    "email": "contratacaopublica@penafielverde.pt",
    "designacao_contrato": "AQUISIÇÃO DE TINAS DE RETENÇÃO E KIT'S DE EMERGÊNCIA PARA DERRAMES DE PRODUTOS QUIMICOS",
    "descricao": "AQUISIÇÃO DE TINAS DE RETENÇÃO E KIT'S DE EMERGÊNCIA PARA DERRAMES DE PRODUTOS QUIMICOS",
    "preco_base": "13.238,00 EUR",
    "prazo_execucao": "6 MESES",
    "prazo_apresentacao_propostas": "02-02-2026 23:59",
    "fundos_eu": "Não",
    "plataforma_eletronica": "VORTAL",
    "url_procedimento": "https://community.vortal.biz/public/",
    "autor_nome": "Fátima Sousa",
    "autor_cargo": "Assistente Técnico"
  },
  {
    "numero_procedimento": "N/A",
    "entidade": "Município da Guarda",
    "link": "https://diariodarepublica.pt/dr/detalhe/contrato-publico/983-1013997959",
    "detalhes_completos": "Alteração do Anúncio de procedimento n.º 32749/2025, de 2025-12-17, com o ID 419892965\n1 - IDENTIFICAÇÃO E CONTACTOS DA ENTIDADE ADJUDICANTE\nDesignação da entidade adjudicante: Município da Guarda\nNIPC: 501131140\nEndereço: Praça do Município, nº 1\nCódigo postal: 6301-854\nLocalidade: Guarda\nPaís: Portugal\nNUT III: PT16J\nDistrito: Guarda\nConcelho: Guarda\nFreguesia: Freguesia de Guarda\nTelefone: 271220200\nFax: 271220280\nEndereço da Entidade (URL): www.mun-guarda.pt\nEndereço Eletrónico: geral@mun-guarda.pt\neDelivery Gateway (URL): https://community.vortal.biz/public/\nFunção da Organização: Adquirente\nNorma jurídica da Entidade Adjudicante: Autoridade da administração central\nÁrea de atividade da Autoridade Adjudicante: Serviços públicos das administrações públicas\n2 - JORNAL OFICIAL DA UNIÃO EUROPEIA\nO procedimento a que este anúncio diz respeito também é publicitado no Jornal Oficial da União Europeia? Não\n3 - AVISO\nModelo de Anúncio: Concurso público\nData de Envio do Anúncio: 16-01-2026\n5 - PROCESSO\nTipo de Procedimento: Concurso público\nPreço base do procedimento: Sim\nValor do preço base do procedimento: 1.719.983,77 EUR\nProcedimento com lotes? Não\n6 - OBJETO DO CONTRATO\nNúmero de referência interna: DOPEI/RU-2025-35 Cópia\nDesignação do contrato: Reabilitação Urbana da Rua Vila de Manteigas_\nDescrição: Reabilitação Urbana da Rua Vila de Manteigas\nTipo de Contrato Principal: Empreitada de Obras Públicas\nTipo de Contrato: Empreitada de Obras Públicas\nClassificação CPV (Vocabulário Comum para os Contratos Públicos)\nObjeto principal\nVocabulário Principal: 45233000\nPreço base s/IVA: 1.719.983,77 EUR\n7 - INDICAÇÕES ADICIONAIS\nO contrato envolve aquisição conjunta (satisfação de várias entidades)? Não\nO contrato é adjudicado por uma central de compras? Não\n8 - TÉCNICAS\nO concurso destina-se à celebração de um acordo-quadro? Inexistência de acordo-quadro\nÉ utilizado um leilão eletrónico? Não\nÉ adotada uma fase de negociação? Não\nSistema de Aquisição Dinâmico: Inexistência de sistema de aquisição dinâmico\n9 - LOCAL DA EXECUÇÃO DO CONTRATO\nLOCAL DA EXECUÇÃO DO CONTRATO (PROCEDIMENTO)\nPaís: Portugal\nNUT III: PT16J\nLocalidade: Guarda\nDistrito: Guarda\nConcelho: Guarda\nFreguesia: Freguesia de Guarda\n10 - PRAZO DE EXECUÇÃO DO CONTRATO\nPrazo de execução do contrato: 270 DIAS\nPrevisão de renovações: Não\n11 - FUNDOS EU\nTêm fundos EU? Não\n12 - DOCUMENTOS DE HABILITAÇÃO\nHabilitação para o exercício da atividade profissional: Não\n13 - CONDIÇÕES DE APRESENTAÇÃO\nPlataforma eletrónica utilizada pela entidade adjudicante: VORTAL\nURL para Apresentação: https://community.vortal.biz/public/\nAdmissibilidade da apresentação de propostas variantes: Não autorizado\nPrazo para apresentação das propostas: 18-02-2026 17:00\nPrazo durante o qual os concorrentes são obrigados a manter as respetivas propostas: 66 dias a contar do termo do prazo para a apresentação das propostas\nApresentação de Catálogo Eletrónico: Permitido\nIndicação de Subcontratação na Proposta: Inexistência de indicação de subcontratação\n14 - PRESTAÇÃO DE CAUÇÃO\nPrestação de caução: Sim\nPercentagem: 5%\nDescrição da Garantia Exigida: conforme anexos ao programa de procedimento\n15 - FORNECIMENTO DAS PEÇAS DO CONCURSO, APRESENTAÇÃO DE PEDIDOS DE PARTICIPAÇÃO E APRESENTAÇÃO DAS PROPOSTAS\nLink para acesso às peças do concurso (URL): https://community.vortal.biz/Public/public-tender-documents/ZktKZ1FBQkJLUEM1cUxKYWQ3TjB5cXpHa3hVZ0xvZGVMYjVvd0psZUk5OVJUSkFlTE1mSDJqZkwvLyt0WnQxeGlvM1JTenNUTmhoVTJIVWdlZWp5S2c9PWk3MFJS\n20 - OUTROS REQUISITOS\nInformação sobre contratos reservados. Aplica-se a contratos reservados (54º-A)? Não\n21 - CRITÉRIO DE ADJUDICAÇÃO\nMultifator: Sim\nFator: \nNome: Preço\nPonderação: 40%\nSubfatores: Não\nFator: \nNome: Qualidade\nPonderação: 60%\nSubfatores: Sim\nSubfatores: \nNome: Plano de Trabalhos\nPonderação : 70%; \nNome: Memória Descritiva\nPonderação : 30%; \n24 - CONDIÇÕES DO CONTRATO\nFaturação Eletrónica: Permitido\nObrigação de Subcontratação:\nCódigo da Obrigação de Subcontratação: Não é aplicável nenhuma obrigação de subcontratação.\n25 - COMPRA PÚBLICA ESTRATÉGICA\nCompra Pública Estratégica: Inexistência de contratação pública estratégica\n26 - INFORMAÇÕES ADICIONAIS\nContrato adequado para PME: Sim\nCobertura ACP (Acordo dos Contratos Públicos da Organização Mundial do Comércio): Não\n27 - IDENTIFICAÇÃO E CONTACTOS DO ÓRGÃO DE RECURSOS ADMINISTRATIVOS\nDesignação: Presidente da Câmara Municipal da Guarda\nEndereço: Praça do Municipio_\nCódigo postal: 6301-854\nLocalidade: Guarda\nTelefone: +351 271220200\nFax: +351 271220280\nEndereço eletrónico: contratacaopublica@mun-guarda.pt\n28 - IDENTIFICAÇÃO DO(S) AUTOR(ES) DE ANÚNCIO\nNome: Sérgio Fernando da Silva Costa\nCargo: Presidente da Câmara Municipal\n29 - ALTERAÇÃO\nMotivo da Alteração: Correção pelo adquirente\nIdentificador da Versão do Anúncio a Alterar: c0ba18a9-63da-4243-9013-78b770331f03-01\nIdentificador das Secções Alteradas do Anúncio Anterior: Condições de Apresentação\nAlteração dos Documentos do Concurso: Não\n419948166",
    "nipc": "501131140",
    "distrito": "Guarda",
    "concelho": "Guarda",
    "freguesia": "Freguesia de Guarda",
    "site": "www.mun-guarda.pt",
    "email": "geral@mun-guarda.pt",
    "designacao_contrato": "Reabilitação Urbana da Rua Vila de Manteigas_",
    "descricao": "Reabilitação Urbana da Rua Vila de Manteigas",
    "preco_base": "1.719.983,77 EUR",
    "prazo_execucao": "270 DIAS",
    "prazo_apresentacao_propostas": "18-02-2026 17:00",
    "fundos_eu": "Não",
    "plataforma_eletronica": "VORTAL",
    "url_procedimento": "https://community.vortal.biz/public/",
    "autor_nome": "Sérgio Fernando da Silva Costa",
    "autor_cargo": "Presidente da Câmara Municipal"
  },
  {
    "numero_procedimento": "N/A",
    "entidade": "AnÃºncio de procedimento  n.Âº 985/2026  -  DiÃ¡rio da RepÃºblica n.Âº 11/2026, SÃ©rie II de 2026-01-16",
    "link": "https://diariodarepublica.pt/dr/detalhe/contrato-publico/985-1013997960"
  },
  {
    "numero_procedimento": "N/A",
    "entidade": "Unidade Local de Saúde do Nordeste, EPE",
    "link": "https://diariodarepublica.pt/dr/detalhe/contrato-publico/989-1013997961",
    "detalhes_completos": "1 - IDENTIFICAÇÃO E CONTACTOS DA ENTIDADE ADJUDICANTE\nDesignação da entidade adjudicante: Unidade Local de Saúde do Nordeste, EPE\nNIPC: 509932584\nEndereço: Praça Cavaleiro Ferreira\nCódigo postal: 5301-862\nLocalidade: Bragança\nPaís: Portugal\nNUT III: PT11E\nDistrito: Braganca\nConcelho: Bragança\nFreguesia: Todas\nTelefone: 273302851\nFax: 273302861\nEndereço da Entidade (URL): https://www.ulsne.min-saude.pt/\nEndereço Eletrónico: amartins@ulsne.min-saude.pt\neDelivery Gateway (URL): https://community.vortal.biz/public/\nFunção da Organização: Adquirente\nNorma jurídica da Entidade Adjudicante: Organismo de direito público\nÁrea de atividade da Autoridade Adjudicante: Saúde\n2 - JORNAL OFICIAL DA UNIÃO EUROPEIA\nO procedimento a que este anúncio diz respeito também é publicitado no Jornal Oficial da União Europeia? Não\n3 - AVISO\nModelo de Anúncio: Concurso público\nData de Envio do Anúncio: 16-01-2026\n5 - PROCESSO\nTipo de Procedimento: Concurso público\nPreço base do procedimento: Sim\nValor do preço base do procedimento: 83.250,00 EUR\nProcedimento com lotes? Sim\nNº Máx. de Lotes Autorizado: 2\nNúmero máximo de lotes que podem ser adjudicados a um concorrente: 2\n6 - OBJETO DO CONTRATO\nNúmero de referência interna: 50260013_Pastilhas e Toalhetes\nDesignação do contrato: 50260013_Aquisição de Pastilhas e Toalhetes de Limpeza e Desinfecção\nDescrição: 50260013_Aquisição de Pastilhas e Toalhetes de Limpeza e Desinfecção\nTipo de Contrato Principal: Aquisição de Bens Móveis\nTipo de Contrato: Aquisição de Bens Móveis\nClassificação CPV (Vocabulário Comum para os Contratos Públicos)\nObjeto principal\nVocabulário Principal: 33695000\nPreço base s/IVA: 83.250,00 EUR\nLotes: \nNº: LOT-0001\nDescrição do Lote: Lote 1\nPreço base s/IVA: 9.350,00 EUR\nClassificação CPV (Vocabulário Comum para os Contratos Públicos)\nObjeto principal\nVocabulário Principal: 33695000\nNº: LOT-0002\nDescrição do Lote: Lote 2\nPreço base s/IVA: 73.900,00 EUR\nClassificação CPV (Vocabulário Comum para os Contratos Públicos)\nObjeto principal\nVocabulário Principal: 33695000\n7 - INDICAÇÕES ADICIONAIS\nO contrato envolve aquisição conjunta (satisfação de várias entidades)? Não\nO contrato é adjudicado por uma central de compras? Não\n8 - TÉCNICAS\nO concurso destina-se à celebração de um acordo-quadro? Inexistência de acordo-quadro\nÉ utilizado um leilão eletrónico? Não\nÉ adotada uma fase de negociação? Não\nSistema de Aquisição Dinâmico: Inexistência de sistema de aquisição dinâmico\n9 - LOCAL DA EXECUÇÃO DO CONTRATO\nLOCAL DA EXECUÇÃO DO CONTRATO (PROCEDIMENTO)\nPaís: Portugal\nNUT III: PT11E\nLocalidade: Bragança\nDistrito: Braganca\nConcelho: Bragança\nFreguesia: Todas\nLOCAL DA EXECUÇÃO DO CONTRATO (LOTE)\nIdentificador do Lote: LOT-0001; LOT-0002\nPaís: Portugal\nNUT III: PT11E\nLocalidade: Bragança\nDistrito: Braganca\nConcelho: Bragança\nFreguesia: Todas\n10 - PRAZO DE EXECUÇÃO DO CONTRATO\nIdentificador do Lote: LOT-0001; LOT-0002\nPrazo de execução do contrato: 335 DIAS\nPrevisão de renovações: Não\n11 - FUNDOS EU\nIdentificador do Lote: LOT-0001; LOT-0002\nTêm fundos EU? Não\n12 - DOCUMENTOS DE HABILITAÇÃO\nHabilitação para o exercício da atividade profissional: Não\n13 - CONDIÇÕES DE APRESENTAÇÃO\nPlataforma eletrónica utilizada pela entidade adjudicante: VORTAL\nURL para Apresentação: https://community.vortal.biz/public/\nAdmissibilidade da apresentação de propostas variantes: Não autorizado\nPrazo para apresentação das propostas: 28-01-2026 17:00\nPrazo durante o qual os concorrentes são obrigados a manter as respetivas propostas: 90 dias a contar do termo do prazo para a apresentação das propostas\nIndicação de Subcontratação na Proposta: Inexistência de indicação de subcontratação\n14 - PRESTAÇÃO DE CAUÇÃO\nPrestação de caução: Não\n15 - FORNECIMENTO DAS PEÇAS DO CONCURSO, APRESENTAÇÃO DE PEDIDOS DE PARTICIPAÇÃO E APRESENTAÇÃO DAS PROPOSTAS\nLink para acesso às peças do concurso (URL): https://community.vortal.biz/Public/public-tender-documents/dnRhcUh2QkVUaDJPdzJNVlpNT01TUDJlSENRYUltM042bksvQmdMM0t5UXVuaVZlNkJVRjFRU1diQjFiWDRqb1VOUGNyZmpuQ2hWd0laa1FrYUt3dVE9PVhmRnhI\n20 - OUTROS REQUISITOS\nIdentificador do Lote: LOT-0001; LOT-0002\nInformação sobre contratos reservados. Aplica-se a contratos reservados (54º-A)? Não\n21 - CRITÉRIO DE ADJUDICAÇÃO\nO Critério de adjudicação é diferenciado por lote? Não\nMultifator: Não\nMonofator:\nNome: Preço\n24 - CONDIÇÕES DO CONTRATO\nIdentificador do Lote: LOT-0001; LOT-0002\nFaturação Eletrónica: Permitido\nObrigação de Subcontratação:\nCódigo da Obrigação de Subcontratação: Não é aplicável nenhuma obrigação de subcontratação.\n25 - COMPRA PÚBLICA ESTRATÉGICA\nCompra Pública Estratégica: Inexistência de contratação pública estratégica\n26 - INFORMAÇÕES ADICIONAIS\nIdentificador do Lote: LOT-0001; LOT-0002\nContrato adequado para PME: Sim\nCobertura ACP (Acordo dos Contratos Públicos da Organização Mundial do Comércio): Não\n27 - IDENTIFICAÇÃO E CONTACTOS DO ÓRGÃO DE RECURSOS ADMINISTRATIVOS\nDesignação: Departamento de Compras e Logística\nEndereço: Praça Cavaleiro Ferreira\nCódigo postal: 5301-862\nLocalidade: Bragança\nTelefone: +351 273302851\nFax: +351 273302861\nEndereço eletrónico: concursos@ulsne.min-saude.pt\n28 - IDENTIFICAÇÃO DO(S) AUTOR(ES) DE ANÚNCIO\nNome: António Martins\nCargo: Diretor do Departamento de Compras e Logística\n419948230",
    "nipc": "509932584",
    "distrito": "Braganca",
    "concelho": "Bragança",
    "freguesia": "Todas",
    "site": "https://www.ulsne.min-saude.pt/",
    "email": "amartins@ulsne.min-saude.pt",
    "designacao_contrato": "50260013_Aquisição de Pastilhas e Toalhetes de Limpeza e Desinfecção",
    "descricao": "50260013_Aquisição de Pastilhas e Toalhetes de Limpeza e Desinfecção",
    "preco_base": "83.250,00 EUR",
    "prazo_execucao": "335 DIAS",
    "prazo_apresentacao_propostas": "28-01-2026 17:00",
    "fundos_eu": "Não",
    "plataforma_eletronica": "VORTAL",
    "url_procedimento": "https://community.vortal.biz/public/",
    "autor_nome": "António Martins",
    "autor_cargo": "Diretor do Departamento de Compras e Logística"
  },
  {
    "numero_procedimento": "N/A",
    "entidade": "Município de Viana do Castelo",
    "link": "https://diariodarepublica.pt/dr/detalhe/contrato-publico/990-1013997962",
    "detalhes_completos": "1 - IDENTIFICAÇÃO E CONTACTOS DA ENTIDADE ADJUDICANTE\nDesignação da entidade adjudicante: Município de Viana do Castelo\nNIPC: 506037258\nEndereço: Passeio Mordomas da Romaria s/n\nCódigo postal: 4904-877\nLocalidade: Viana do Castelo\nPaís: Portugal\nNUT III: PT111\nDistrito: Viana do Castelo\nConcelho: Viana do Castelo\nFreguesia: União das Freguesias de Viana do Castelo (Santa Maria Maior e Monserrate) e Meadela\nTelefone: 258809300\nFax: 258809347\nEndereço da Entidade (URL): www.cm-viana-vastelo.pt\nEndereço Eletrónico: geral@cm-viana-castelo.pt\nFunção da Organização: Adquirente\nNorma jurídica da Entidade Adjudicante: Autoridade local\nÁrea de atividade da Entidade Adjudicante: Atividades aeroportuárias\n2 - JORNAL OFICIAL DA UNIÃO EUROPEIA\nO procedimento a que este anúncio diz respeito também é publicitado no Jornal Oficial da União Europeia? Não\n3 - AVISO\nModelo de Anúncio: Concurso público\nData de Envio do Anúncio: 16-01-2026\n5 - PROCESSO\nTipo de Procedimento: Concurso público\nPreço base do procedimento: Sim\nValor do preço base do procedimento: 185.866,08 EUR\nProcedimento com lotes? Não\n6 - OBJETO DO CONTRATO\nNúmero de referência interna: SEC - Proc. n.º 3/A1/26\nDesignação do contrato: Concurso público da empreitada de \"EB1/JI Mazarefes - Obras de Requalificação e Beneficiação\".\nDescrição: EB1/JI Mazarefes - Obras de Requalificação e Beneficiação\nTipo de Contrato Principal: Empreitada de Obras Públicas\nTipo de Contrato: Empreitada de Obras Públicas\nClassificação CPV (Vocabulário Comum para os Contratos Públicos)\nObjeto principal\nVocabulário Principal: 45113000\nPreço base s/IVA: 185.866,08 EUR\n7 - INDICAÇÕES ADICIONAIS\nO contrato envolve aquisição conjunta (satisfação de várias entidades)? Não\nO contrato é adjudicado por uma central de compras? Não\n8 - TÉCNICAS\nO concurso destina-se à celebração de um acordo-quadro? Inexistência de acordo-quadro\nÉ utilizado um leilão eletrónico? Não\nÉ adotada uma fase de negociação? Não\nSistema de Aquisição Dinâmico: Inexistência de sistema de aquisição dinâmico\n9 - LOCAL DA EXECUÇÃO DO CONTRATO\nLOCAL DA EXECUÇÃO DO CONTRATO (PROCEDIMENTO)\nPaís: Portugal\nNUT III: PT111\nLocalidade: Viana do Castelo\nDistrito: Viana do Castelo\nConcelho: Viana do Castelo\nFreguesia: União das Freguesias de Mazarefes e Vila Fria\n10 - PRAZO DE EXECUÇÃO DO CONTRATO\nPrazo de execução do contrato: 70 DIAS\nPrevisão de renovações: Não\n11 - FUNDOS EU\nTêm fundos EU? Não\n12 - DOCUMENTOS DE HABILITAÇÃO\nHabilitação para o exercício da atividade profissional: Sim\nTipo: Alvará\nDescrição: 5.ª Subcategoria da 1.ª categoria\n13 - CONDIÇÕES DE APRESENTAÇÃO\nPlataforma eletrónica utilizada pela entidade adjudicante: ANOGOV\nURL para Apresentação: https://www.anogov.com/cm-vianacastelo/faces/\nAdmissibilidade da apresentação de propostas variantes: Não autorizado\nPrazo para apresentação das propostas: 02-02-2026 17:00\nPrazo durante o qual os concorrentes são obrigados a manter as respetivas propostas: 66 dias a contar do termo do prazo para a apresentação das propostas\nApresentação de Catálogo Eletrónico: Permitido\nIndicação de Subcontratação na Proposta: Inexistência de indicação de subcontratação\n14 - PRESTAÇÃO DE CAUÇÃO\nPrestação de caução: Sim\nPercentagem: 5%\nDescrição da Garantia Exigida: O valor da caução é de 5% do preço contratual, nos termos previstos no n.º 1 do artigo 89.º do Código dos Contratos Públicos.\n15 - FORNECIMENTO DAS PEÇAS DO CONCURSO, APRESENTAÇÃO DE PEDIDOS DE PARTICIPAÇÃO E APRESENTAÇÃO DAS PROPOSTAS\nLink para acesso às peças do concurso (URL): https://www.anogov.com/cm-vianacastelo/faces/app/acessoDocs.jsp?codigoAcesso=P6C5xfteQh8KyoN1n9wnR96PZdHGogMeSU2mY6YP4RyxulW4zj\n20 - OUTROS REQUISITOS\nInformação sobre contratos reservados. Aplica-se a contratos reservados (54º-A)? Não\n21 - CRITÉRIO DE ADJUDICAÇÃO\nMultifator: Não\nMonofator:\nNome: Preço\n24 - CONDIÇÕES DO CONTRATO\nFaturação Eletrónica: Necessário\nObrigação de Subcontratação:\nCódigo da Obrigação de Subcontratação: Não é aplicável nenhuma obrigação de subcontratação.\n25 - COMPRA PÚBLICA ESTRATÉGICA\nCompra Pública Estratégica: Inexistência de contratação pública estratégica\n26 - INFORMAÇÕES ADICIONAIS\nContrato adequado para PME: Não\nCobertura ACP (Acordo dos Contratos Públicos da Organização Mundial do Comércio): Não\n27 - IDENTIFICAÇÃO E CONTACTOS DO ÓRGÃO DE RECURSOS ADMINISTRATIVOS\nDesignação: Presidente da Câmara Municipal de Viana do Castelo\nEndereço: Passeio das Mordomas da Romaria\nCódigo postal: 4904-877\nLocalidade: Viana do Castelo\nEndereço eletrónico: luisnobre@cm-viana-castelo.pt\nPrazo de interposição do recurso: 5 dias\n28 - IDENTIFICAÇÃO DO(S) AUTOR(ES) DE ANÚNCIO\nNome: Pedro Alexandre Rocha e Sousa\nCargo: Assistente Técnico\n419948141",
    "nipc": "506037258",
    "distrito": "Viana do Castelo",
    "concelho": "Viana do Castelo",
    "freguesia": "União das Freguesias de Viana do Castelo (Santa Maria Maior e Monserrate) e Meadela",
    "site": "www.cm-viana-vastelo.pt",
    "email": "geral@cm-viana-castelo.pt",
    "designacao_contrato": "Concurso público da empreitada de \"EB1/JI Mazarefes - Obras de Requalificação e Beneficiação\".",
    "descricao": "EB1/JI Mazarefes - Obras de Requalificação e Beneficiação",
    "preco_base": "185.866,08 EUR",
    "prazo_execucao": "70 DIAS",
    "prazo_apresentacao_propostas": "02-02-2026 17:00",
    "fundos_eu": "Não",
    "plataforma_eletronica": "ANOGOV",
    "url_procedimento": "https://www.anogov.com/cm-vianacastelo/faces/",
    "autor_nome": "Pedro Alexandre Rocha e Sousa",
    "autor_cargo": "Assistente Técnico"
  },
  {
    "numero_procedimento": "N/A",
    "entidade": "AnÃºncio de procedimento  n.Âº 991/2026  -  DiÃ¡rio da RepÃºblica n.Âº 11/2026, SÃ©rie II de 2026-01-16",
    "link": "https://diariodarepublica.pt/dr/detalhe/contrato-publico/991-1013997963"
  },
  {
    "numero_procedimento": "N/A",
    "entidade": "Santa Casa da Misericórdia de Lisboa",
    "link": "https://diariodarepublica.pt/dr/detalhe/contrato-publico/992-1013997964",
    "detalhes_completos": "1 - IDENTIFICAÇÃO E CONTACTOS DA ENTIDADE ADJUDICANTE\nDesignação da entidade adjudicante: Santa Casa da Misericórdia de Lisboa\nNIPC: 500745471\nServiço/Órgão/Pessoa de contacto: Exma. Mesa\nEndereço: Largo Trindade Coelho\nCódigo postal: 1200-470\nLocalidade: Lisboa\nPaís: Portugal\nNUT III: PT170\nDistrito: Lisboa\nConcelho: Todos\nFreguesia: Todas\nTelefone: 213235000\nFax: 213235013\nEndereço da Entidade (URL): http://www.scml.pt/\nEndereço Eletrónico: compras@scml.pt\neDelivery Gateway (URL): https://www.acingov.pt\nFunção da Organização: Adquirente\nSubfunção da Organização: Organização cujo orçamento é utilizado para pagar o contrato; Organização que executa o pagamento; Organização que fornece informações adicionais sobre o processo de adjudicação; Organização que fornece mais informações sobre os prazos dos procedimentos de recurso; Organização que fornece acesso fora de linha aos documentos do concurso; Organização responsável pelo tratamento das propostas; Organização que recebe as propostas; Organização que trata os pedidos de participação; Organização que recebe pedidos de participação; Organização que fornece mais informações sobre os procedimentos de recurso; Organização que assina o contrato\nNorma jurídica da Entidade Adjudicante: Organismo de direito público, controlado por uma autoridade da administração central\nÁrea de atividade da Autoridade Adjudicante: Proteção social\n2 - JORNAL OFICIAL DA UNIÃO EUROPEIA\nO procedimento a que este anúncio diz respeito também é publicitado no Jornal Oficial da União Europeia? Não\n3 - AVISO\nModelo de Anúncio: Concurso público\nData de Envio do Anúncio: 16-01-2026\n5 - PROCESSO\nTipo de Procedimento: Concurso público\nPreço base do procedimento: Sim\nValor do preço base do procedimento: 36.905,00 EUR\nProcedimento com lotes? Sim\nNº Máx. de Lotes Autorizado: 11\nNúmero máximo de lotes que podem ser adjudicados a um concorrente: 11\n6 - OBJETO DO CONTRATO\nNúmero de referência interna: 25DC26CP002\nDesignação do contrato: Aquisição de Ligaduras para a SCML\nDescrição: Aquisição de Ligaduras para a SCML \nTipo de Contrato Principal: Aquisição de Bens Móveis\nTipo de Contrato: Aquisição de Bens Móveis\nClassificação CPV (Vocabulário Comum para os Contratos Públicos)\nObjeto principal\nVocabulário Principal: 33141126\nPreço base s/IVA: 36.905,00 EUR\nLotes: \nNº: LOT-0001\nDescrição do Lote: COMPRESSA HOTPAC P/ HIDROCOLLATOR\nPreço base s/IVA: 9.200,00 EUR\nClassificação CPV (Vocabulário Comum para os Contratos Públicos)\nObjeto principal\nVocabulário Principal: 33141126\nNº: LOT-0002\nDescrição do Lote: KIT LIGADURA P/ ULCERA DA PERNA\nPreço base s/IVA: 135,00 EUR\nClassificação CPV (Vocabulário Comum para os Contratos Públicos)\nObjeto principal\nVocabulário Principal: 33141126\nNº: LOT-0003\nDescrição do Lote: LIGADURA ADESIVA\nPreço base s/IVA: 2.835,00 EUR\nClassificação CPV (Vocabulário Comum para os Contratos Públicos)\nObjeto principal\nVocabulário Principal: 33141126\nNº: LOT-0004\nDescrição do Lote: LIGADURA ALGODÃO\nPreço base s/IVA: 1.560,00 EUR\nClassificação CPV (Vocabulário Comum para os Contratos Públicos)\nObjeto principal\nVocabulário Principal: 33141126\nNº: LOT-0005\nDescrição do Lote: LIGADURA BIELÁSTICA COMPRESSIVA\nPreço base s/IVA: 885,00 EUR\nClassificação CPV (Vocabulário Comum para os Contratos Públicos)\nObjeto principal\nVocabulário Principal: 33141126\nNº: LOT-0006\nDescrição do Lote: LIGADURA ELASTICA\nPreço base s/IVA: 1.270,00 EUR\nClassificação CPV (Vocabulário Comum para os Contratos Públicos)\nObjeto principal\nVocabulário Principal: 33141126\nNº: LOT-0007\nDescrição do Lote: LIGADURA ELASTICA 7,5CMX4,5M ADESIVA\nPreço base s/IVA: 110,00 EUR\nClassificação CPV (Vocabulário Comum para os Contratos Públicos)\nObjeto principal\nVocabulário Principal: 33141126\nNº: LOT-0008\nDescrição do Lote: LIGADURA ELASTICA CREPE\nPreço base s/IVA: 11.670,00 EUR\nClassificação CPV (Vocabulário Comum para os Contratos Públicos)\nObjeto principal\nVocabulário Principal: 33141126\nNº: LOT-0009\nDescrição do Lote: LIGADURA FORTE COMPRESSAO\nPreço base s/IVA: 2.910,00 EUR\nClassificação CPV (Vocabulário Comum para os Contratos Públicos)\nObjeto principal\nVocabulário Principal: 33141126\nNº: LOT-0010\nDescrição do Lote: SISTEMA DE TALAS SINTÉTICAS\nPreço base s/IVA: 5.020,00 EUR\nClassificação CPV (Vocabulário Comum para os Contratos Públicos)\nObjeto principal\nVocabulário Principal: 33141760\nNº: LOT-0011\nDescrição do Lote: LIGADURA 100% ALGODAO NATURAL\nPreço base s/IVA: 1.310,00 EUR\nClassificação CPV (Vocabulário Comum para os Contratos Públicos)\nObjeto principal\nVocabulário Principal: 33141126\n7 - INDICAÇÕES ADICIONAIS\nO contrato envolve aquisição conjunta (satisfação de várias entidades)? Não\nO contrato é adjudicado por uma central de compras? Não\n8 - TÉCNICAS\nO concurso destina-se à celebração de um acordo-quadro? Inexistência de acordo-quadro\nÉ utilizado um leilão eletrónico? Não\nÉ adotada uma fase de negociação? Não\nSistema de Aquisição Dinâmico: Inexistência de sistema de aquisição dinâmico\n9 - LOCAL DA EXECUÇÃO DO CONTRATO\nLOCAL DA EXECUÇÃO DO CONTRATO (PROCEDIMENTO)\nPaís: Portugal\nNUT III: PT170\nLocalidade: Freguesia de Misericórdia\nDistrito: Lisboa\nConcelho: Lisboa\nFreguesia: Freguesia de Misericórdia\nLOCAL DA EXECUÇÃO DO CONTRATO (LOTE)\nIdentificador do Lote: LOT-0001; LOT-0002; LOT-0003; LOT-0004; LOT-0005; LOT-0006; LOT-0007; LOT-0008; LOT-0009; LOT-0010; LOT-0011\nPaís: Portugal\nNUT III: PT170\nLocalidade: Freguesia de Misericórdia\nDistrito: Lisboa\nConcelho: Lisboa\nFreguesia: Freguesia de Misericórdia\n10 - PRAZO DE EXECUÇÃO DO CONTRATO\nIdentificador do Lote: LOT-0001; LOT-0002; LOT-0003; LOT-0004; LOT-0005; LOT-0006; LOT-0007; LOT-0008; LOT-0009; LOT-0010; LOT-0011\nPrazo de execução do contrato: 12 MESES\nPrevisão de renovações: Não\n11 - FUNDOS EU\nIdentificador do Lote: LOT-0001; LOT-0002; LOT-0003; LOT-0004; LOT-0005; LOT-0006; LOT-0007; LOT-0008; LOT-0009; LOT-0010; LOT-0011\nTêm fundos EU? Não\n12 - DOCUMENTOS DE HABILITAÇÃO\nHabilitação para o exercício da atividade profissional: Não\n13 - CONDIÇÕES DE APRESENTAÇÃO\nPlataforma eletrónica utilizada pela entidade adjudicante: ACIN\nURL para Apresentação: https://www.acingov.pt\nAdmissibilidade da apresentação de propostas variantes: Não autorizado\nPrazo para apresentação das propostas: 28-01-2026 17:00\nPrazo durante o qual os concorrentes são obrigados a manter as respetivas propostas: 120 dias a contar do termo do prazo para a apresentação das propostas\nIndicação de Subcontratação na Proposta: Inexistência de indicação de subcontratação\n14 - PRESTAÇÃO DE CAUÇÃO\nPrestação de caução: Não\n15 - FORNECIMENTO DAS PEÇAS DO CONCURSO, APRESENTAÇÃO DE PEDIDOS DE PARTICIPAÇÃO E APRESENTAÇÃO DAS PROPOSTAS\nLink para acesso às peças do concurso (URL): https://www.acingov.pt/acingovprod/2/zonaPublica/zona_publica_c/donwloadProcedurePiece/MTA0OTA2MA==\n20 - OUTROS REQUISITOS\nIdentificador do Lote: LOT-0001; LOT-0002; LOT-0003; LOT-0004; LOT-0005; LOT-0006; LOT-0007; LOT-0008; LOT-0009; LOT-0010; LOT-0011\nInformação sobre contratos reservados. Aplica-se a contratos reservados (54º-A)? Não\n21 - CRITÉRIO DE ADJUDICAÇÃO\nO Critério de adjudicação é diferenciado por lote? Não\nMultifator: Não\nMonofator:\nNome: Preço\n24 - CONDIÇÕES DO CONTRATO\nIdentificador do Lote: LOT-0001; LOT-0002; LOT-0003; LOT-0004; LOT-0005; LOT-0006; LOT-0007; LOT-0008; LOT-0009; LOT-0010; LOT-0011\nFaturação Eletrónica: Permitido\nObrigação de Subcontratação:\nCódigo da Obrigação de Subcontratação: Não é aplicável nenhuma obrigação de subcontratação.\n25 - COMPRA PÚBLICA ESTRATÉGICA\nCompra Pública Estratégica: Inexistência de contratação pública estratégica\n26 - INFORMAÇÕES ADICIONAIS\nIdentificador do Lote: LOT-0001; LOT-0002; LOT-0003; LOT-0004; LOT-0005; LOT-0006; LOT-0007; LOT-0008; LOT-0009; LOT-0010; LOT-0011\nContrato adequado para PME: Sim\nCobertura ACP (Acordo dos Contratos Públicos da Organização Mundial do Comércio): Não\n27 - IDENTIFICAÇÃO E CONTACTOS DO ÓRGÃO DE RECURSOS ADMINISTRATIVOS\nDesignação: Exma. Mesa\nEndereço: Largo Trindade Coelho\nCódigo postal: 1200-470\nLocalidade: Lisboa\nTelefone: 213235000\nFax: \nEndereço eletrónico: compras@scml.pt\nPrazo de interposição do recurso: 10 dias\n28 - IDENTIFICAÇÃO DO(S) AUTOR(ES) DE ANÚNCIO\nNome: Vanda Simão\nCargo: Diretora da Direção de Compras\n419948224",
    "nipc": "500745471",
    "distrito": "Lisboa",
    "concelho": "Todos",
    "freguesia": "Todas",
    "site": "http://www.scml.pt/",
    "email": "compras@scml.pt",
    "designacao_contrato": "Aquisição de Ligaduras para a SCML",
    "descricao": "Aquisição de Ligaduras para a SCML",
    "preco_base": "36.905,00 EUR",
    "prazo_execucao": "12 MESES",
    "prazo_apresentacao_propostas": "28-01-2026 17:00",
    "fundos_eu": "Não",
    "plataforma_eletronica": "ACIN",
    "url_procedimento": "https://www.acingov.pt",
    "autor_nome": "Vanda Simão",
    "autor_cargo": "Diretora da Direção de Compras"
  },
  {
    "numero_procedimento": "N/A",
    "entidade": "AnÃºncio de procedimento  n.Âº 993/2026  -  DiÃ¡rio da RepÃºblica n.Âº 11/2026, SÃ©rie II de 2026-01-16",
    "link": "https://diariodarepublica.pt/dr/detalhe/contrato-publico/993-1013997965"
  },
  {
    "numero_procedimento": "N/A",
    "entidade": "AnÃºncio de procedimento  n.Âº 994/2026  -  DiÃ¡rio da RepÃºblica n.Âº 11/2026, SÃ©rie II de 2026-01-16",
    "link": "https://diariodarepublica.pt/dr/detalhe/contrato-publico/994-1013997966"
  },
  {
    "numero_procedimento": "N/A",
    "entidade": "AnÃºncio de procedimento  n.Âº 995/2026  -  DiÃ¡rio da RepÃºblica n.Âº 11/2026, SÃ©rie II de 2026-01-16",
    "link": "https://diariodarepublica.pt/dr/detalhe/contrato-publico/995-1013997967"
  },
  {
    "numero_procedimento": "N/A",
    "entidade": "Município de Arcos de Valdevez",
    "link": "https://diariodarepublica.pt/dr/detalhe/contrato-publico/997-1013997968",
    "detalhes_completos": "1 - IDENTIFICAÇÃO E CONTACTOS DA ENTIDADE ADJUDICANTE\nDesignação da entidade adjudicante: Município de Arcos de Valdevez\nNIPC: 505211696\nEndereço: Praça  Municipal\nCódigo postal: 4974-003\nLocalidade: Viana do Castelo\nPaís: Portugal\nNUT III: PT111\nDistrito: Viana do Castelo\nConcelho: Arcos de Valdevez\nFreguesia: União das Freguesias de Arcos de Valdevez (São Paio) e Giela\nTelefone: 258520500\nFax: 258520509\nEndereço da Entidade (URL): www.cmav.pt\nEndereço Eletrónico: geral@cmav.pt\neDelivery Gateway (URL): https://community.vortal.biz/public/\nFunção da Organização: Adquirente\nNorma jurídica da Entidade Adjudicante: Autoridade local\nÁrea de atividade da Autoridade Adjudicante: Serviços públicos das administrações públicas\n2 - JORNAL OFICIAL DA UNIÃO EUROPEIA\nO procedimento a que este anúncio diz respeito também é publicitado no Jornal Oficial da União Europeia? Não\n3 - AVISO\nModelo de Anúncio: Concurso público\nData de Envio do Anúncio: 16-01-2026\n5 - PROCESSO\nTipo de Procedimento: Concurso público\nPreço base do procedimento: Sim\nValor do preço base do procedimento: 1.515.797,07 EUR\nProcedimento com lotes? Não\n6 - OBJETO DO CONTRATO\nNúmero de referência interna: PO 582/2025\nDesignação do contrato: PO 582/2025 - Criação da Galeria Cultural Alameda\nDescrição: PO 582/2025 - Criação da Galeria Cultural Alameda\nTipo de Contrato Principal: Empreitada de Obras Públicas\nTipo de Contrato: Empreitada de Obras Públicas\nClassificação CPV (Vocabulário Comum para os Contratos Públicos)\nObjeto principal\nVocabulário Principal: 45212300\nPreço base s/IVA: 1.515.797,07 EUR\n7 - INDICAÇÕES ADICIONAIS\nO contrato envolve aquisição conjunta (satisfação de várias entidades)? Não\nO contrato é adjudicado por uma central de compras? Não\n8 - TÉCNICAS\nO concurso destina-se à celebração de um acordo-quadro? Inexistência de acordo-quadro\nÉ utilizado um leilão eletrónico? Não\nÉ adotada uma fase de negociação? Não\nSistema de Aquisição Dinâmico: Inexistência de sistema de aquisição dinâmico\n9 - LOCAL DA EXECUÇÃO DO CONTRATO\nLOCAL DA EXECUÇÃO DO CONTRATO (PROCEDIMENTO)\nPaís: Portugal\nNUT III: PT111\nLocalidade: Viana do Castelo\nDistrito: Viana do Castelo\nConcelho: Arcos de Valdevez\nFreguesia: União das Freguesias de Arcos de Valdevez (Salvador), Vila Fonche e Parada\n10 - PRAZO DE EXECUÇÃO DO CONTRATO\nPrazo de execução do contrato: 365 DIAS\nPrevisão de renovações: Não\n11 - FUNDOS EU\nTêm fundos EU? Não\n12 - DOCUMENTOS DE HABILITAÇÃO\nHabilitação para o exercício da atividade profissional: Sim\nTipo: Alvará\nDescrição: Conforme indicado no artigo 16.º do Programa de Procedimento\n13 - CONDIÇÕES DE APRESENTAÇÃO\nPlataforma eletrónica utilizada pela entidade adjudicante: VORTAL\nURL para Apresentação: https://community.vortal.biz/public/\nAdmissibilidade da apresentação de propostas variantes: Não autorizado\nPrazo para apresentação das propostas: 12-02-2026 18:00\nPrazo durante o qual os concorrentes são obrigados a manter as respetivas propostas: 120 dias a contar do termo do prazo para a apresentação das propostas\nIndicação de Subcontratação na Proposta: Inexistência de indicação de subcontratação\n14 - PRESTAÇÃO DE CAUÇÃO\nPrestação de caução: Sim\nPercentagem: 5%\nDescrição da Garantia Exigida: Conforme indicado no artigo 18.º do Programa de Procedimento\n15 - FORNECIMENTO DAS PEÇAS DO CONCURSO, APRESENTAÇÃO DE PEDIDOS DE PARTICIPAÇÃO E APRESENTAÇÃO DAS PROPOSTAS\nLink para acesso às peças do concurso (URL): https://community.vortal.biz/Public/public-tender-documents/ckNFUFRpTlIzRE9IZ1JNVlJYL1p3dFk1MFBRdnFtbU1DVXpoSlVaemxhbzg0T0lZM09DV0ViWHArVjllSEdHZFpEN1lOUUF6M0haRGtFeWN4SWdxMmc9PWZQMzdD\n20 - OUTROS REQUISITOS\nInformação sobre contratos reservados. Aplica-se a contratos reservados (54º-A)? Não\n21 - CRITÉRIO DE ADJUDICAÇÃO\nMultifator: Sim\nFator: \nNome: Preço\nPonderação: 60%\nSubfatores: Não\nFator: \nNome: Qualidade\nPonderação: 40%\nSubfatores: Sim\nSubfatores: \nNome: Memória descritiva e justificativa (MD) \nPonderação : 40%; \nNome: Plano de trabalho (PT) \nPonderação : 25%; \nNome: Plano de mão-de-obra (PM) \nPonderação : 7.5%; \nNome: Plano de equipamento (PE) \nPonderação : 7.5%; \nNome: Implementação do Plano de Segurança e Saúde da empreitada (PSS)\nPonderação : 10%; \nNome: Implementação do Plano de Gestão Ambiental (PGA)\nPonderação : 10%; \n24 - CONDIÇÕES DO CONTRATO\nFaturação Eletrónica: Permitido\nObrigação de Subcontratação:\nCódigo da Obrigação de Subcontratação: Não é aplicável nenhuma obrigação de subcontratação.\n25 - COMPRA PÚBLICA ESTRATÉGICA\nCompra Pública Estratégica: Inexistência de contratação pública estratégica\n26 - INFORMAÇÕES ADICIONAIS\nContrato adequado para PME: Sim\nCobertura ACP (Acordo dos Contratos Públicos da Organização Mundial do Comércio): Não\n27 - IDENTIFICAÇÃO E CONTACTOS DO ÓRGÃO DE RECURSOS ADMINISTRATIVOS\nDesignação: Município de Arcos de Valdevez\nEndereço: Praça Municipal\nCódigo postal: 4974-003\nLocalidade: Arcos de Valdevez\nTelefone: +351 258520500\nFax: +351 258520509\nEndereço eletrónico: geral@cmav.pt\n28 - IDENTIFICAÇÃO DO(S) AUTOR(ES) DE ANÚNCIO\nNome: Olegário Gomes Gonçalves\nCargo: Presidente da Câmara\n419948118",
    "nipc": "505211696",
    "distrito": "Viana do Castelo",
    "concelho": "Arcos de Valdevez",
    "freguesia": "União das Freguesias de Arcos de Valdevez (São Paio) e Giela",
    "site": "www.cmav.pt",
    "email": "geral@cmav.pt",
    "designacao_contrato": "PO 582/2025 - Criação da Galeria Cultural Alameda",
    "descricao": "PO 582/2025 - Criação da Galeria Cultural Alameda",
    "preco_base": "1.515.797,07 EUR",
    "prazo_execucao": "365 DIAS",
    "prazo_apresentacao_propostas": "12-02-2026 18:00",
    "fundos_eu": "Não",
    "plataforma_eletronica": "VORTAL",
    "url_procedimento": "https://community.vortal.biz/public/",
    "autor_nome": "Olegário Gomes Gonçalves",
    "autor_cargo": "Presidente da Câmara"
  },
  {
    "numero_procedimento": "N/A",
    "entidade": "Centro de Formação Profissional da Indústria do Calçado",
    "link": "https://diariodarepublica.pt/dr/detalhe/contrato-publico/998-1013997969",
    "detalhes_completos": "1 - IDENTIFICAÇÃO E CONTACTOS DA ENTIDADE ADJUDICANTE\nDesignação da entidade adjudicante: Centro de Formação Profissional da Indústria do Calçado\nNIPC: 900106590\nServiço/Órgão/Pessoa de contacto: NGAFC - Serviço de Compras\nEndereço: Rua de Visconde de S. João da Madeira, 990\nCódigo postal: 3700-265\nLocalidade: S. João da Madeira\nPaís: Portugal\nNUT III: PT11A\nDistrito: Aveiro\nConcelho: São João da Madeira\nFreguesia: Freguesia de São João da Madeira\nTelefone: 256815060\nFax: 000000000\nEndereço da Entidade (URL): www.cfpic.pt\nEndereço Eletrónico: cfpic@cfpic.pt\neDelivery Gateway (URL): https://www.acingov.pt\nFunção da Organização: Adquirente\nNorma jurídica da Entidade Adjudicante: Organismo de direito público\nÁrea de atividade da Autoridade Adjudicante: Serviços públicos das administrações públicas\n2 - JORNAL OFICIAL DA UNIÃO EUROPEIA\nO procedimento a que este anúncio diz respeito também é publicitado no Jornal Oficial da União Europeia? Não\n3 - AVISO\nModelo de Anúncio: Concurso público\nData de Envio do Anúncio: 16-01-2026\n5 - PROCESSO\nTipo de Procedimento: Concurso público\nPreço base do procedimento: Sim\nValor do preço base do procedimento: 22.275,00 EUR\nProcedimento com lotes? Não\n6 - OBJETO DO CONTRATO\nNúmero de referência interna: CP/01/2026/CFPIC\nDesignação do contrato: CP/01/2026/CFPIC - Contratação, em Regime de Avença, de serviços de Apoio Jurídico e de Contencioso para 2026\nDescrição: Contratação, em Regime de Avença, de serviços de Apoio Jurídico e de Contencioso para 2026\nTipo de Contrato Principal: Aquisição de Serviços\nTipo de Contrato: Aquisição de Serviços\nClassificação CPV (Vocabulário Comum para os Contratos Públicos)\nObjeto principal\nVocabulário Principal: 79100000\nPreço base s/IVA: 22.275,00 EUR\n7 - INDICAÇÕES ADICIONAIS\nO contrato envolve aquisição conjunta (satisfação de várias entidades)? Não\nO contrato é adjudicado por uma central de compras? Não\n8 - TÉCNICAS\nO concurso destina-se à celebração de um acordo-quadro? Inexistência de acordo-quadro\nÉ utilizado um leilão eletrónico? Não\nÉ adotada uma fase de negociação? Não\nSistema de Aquisição Dinâmico: Inexistência de sistema de aquisição dinâmico\n9 - LOCAL DA EXECUÇÃO DO CONTRATO\nLOCAL DA EXECUÇÃO DO CONTRATO (PROCEDIMENTO)\nPaís: Portugal\nNUT III: PT11A\nLocalidade: Freguesia de São João da Madeira\nDistrito: Aveiro\nConcelho: São João da Madeira\nFreguesia: Freguesia de São João da Madeira\nPaís: Portugal\nNUT III: PT11C\nLocalidade: União das Freguesias de Margaride (Santa Eulália), Várzea, Lagares, Varziela e Moure\nDistrito: Porto\nConcelho: Felgueiras\nFreguesia: União das Freguesias de Margaride (Santa Eulália), Várzea, Lagares, Varziela e Moure\n10 - PRAZO DE EXECUÇÃO DO CONTRATO\nData de Início: 01-02-2026\nData de Fim: 31-12-2026\nPrevisão de renovações: Não\n11 - FUNDOS EU\nTêm fundos EU? Não\n12 - DOCUMENTOS DE HABILITAÇÃO\nHabilitação para o exercício da atividade profissional: Sim\nTipo: Ordem Profissional\nDescrição: Certificação da Ordem dos Advogados\n13 - CONDIÇÕES DE APRESENTAÇÃO\nPlataforma eletrónica utilizada pela entidade adjudicante: ACIN\nURL para Apresentação: https://www.acingov.pt\nAdmissibilidade da apresentação de propostas variantes: Não autorizado\nPrazo para apresentação das propostas: 22-01-2026 23:59\nPrazo durante o qual os concorrentes são obrigados a manter as respetivas propostas: 66 dias a contar do termo do prazo para a apresentação das propostas\nIndicação de Subcontratação na Proposta: Inexistência de indicação de subcontratação\n14 - PRESTAÇÃO DE CAUÇÃO\nPrestação de caução: Não\n15 - FORNECIMENTO DAS PEÇAS DO CONCURSO, APRESENTAÇÃO DE PEDIDOS DE PARTICIPAÇÃO E APRESENTAÇÃO DAS PROPOSTAS\nLink para acesso às peças do concurso (URL): https://www.acingov.pt/acingovprod/2/zonaPublica/zona_publica_c/donwloadProcedurePiece/MTA0ODQzMQ==\n20 - OUTROS REQUISITOS\nInformação sobre contratos reservados. Aplica-se a contratos reservados (54º-A)? Não\n21 - CRITÉRIO DE ADJUDICAÇÃO\nMultifator: Sim\nFator: \nNome: Outros\nOutro Nome: Qualidade da Equipa (QE)\nPonderação: 70%\nSubfatores: Sim\nSubfatores: \nNome: Dimensão da Equipa afeta ao contrato\nPonderação : 40%; \nNome: Experiência da Equipa em áreas relevantes (Contratação Pública, Direito do Trabalho, Direito Civil, Direito Administrativo e Patrocínio Judiciário)\nPonderação : 60%; \nFator: \nNome: Preço\nPonderação: 30%\nSubfatores: Não\n24 - CONDIÇÕES DO CONTRATO\nFaturação Eletrónica: Não autorizado\nObrigação de Subcontratação:\nCódigo da Obrigação de Subcontratação: Não é aplicável nenhuma obrigação de subcontratação.\n25 - COMPRA PÚBLICA ESTRATÉGICA\nCompra Pública Estratégica: Inexistência de contratação pública estratégica\n26 - INFORMAÇÕES ADICIONAIS\nContrato adequado para PME: Sim\nCobertura ACP (Acordo dos Contratos Públicos da Organização Mundial do Comércio): Não\n27 - IDENTIFICAÇÃO E CONTACTOS DO ÓRGÃO DE RECURSOS ADMINISTRATIVOS\nDesignação: CONSELHO DE ADMINISTRAÇÃO\nEndereço: Rua de Visconde de S. João da Madeira, 990\nCódigo postal: 3700-265\nLocalidade: S. João da Madeira\nTelefone: 256815060\nFax: 000000000\nEndereço eletrónico: cfpic@cfpic.pt\nPrazo de interposição do recurso: 5 dias\n28 - IDENTIFICAÇÃO DO(S) AUTOR(ES) DE ANÚNCIO\nNome: Susana Maria Carvalho Pinto de Menezes Nogueira\nCargo: Diretora\n419948165",
    "nipc": "900106590",
    "distrito": "Aveiro",
    "concelho": "São João da Madeira",
    "freguesia": "Freguesia de São João da Madeira",
    "site": "www.cfpic.pt",
    "email": "cfpic@cfpic.pt",
    "designacao_contrato": "CP/01/2026/CFPIC - Contratação, em Regime de Avença, de serviços de Apoio Jurídico e de Contencioso para 2026",
    "descricao": "Contratação, em Regime de Avença, de serviços de Apoio Jurídico e de Contencioso para 2026",
    "preco_base": "22.275,00 EUR",
    "prazo_execucao": null,
    "prazo_apresentacao_propostas": "22-01-2026 23:59",
    "fundos_eu": "Não",
    "plataforma_eletronica": "ACIN",
    "url_procedimento": "https://www.acingov.pt",
    "autor_nome": "Susana Maria Carvalho Pinto de Menezes Nogueira",
    "autor_cargo": "Diretora"
  },
  {
    "numero_procedimento": "N/A",
    "entidade": "AnÃºncio de procedimento  n.Âº 933/2026  -  DiÃ¡rio da RepÃºblica n.Âº 11/2026, SÃ©rie II de 2026-01-16",
    "link": "https://diariodarepublica.pt/dr/detalhe/contrato-publico/933-1013997972"
  },
  {
    "numero_procedimento": "N/A",
    "entidade": "Unidade Local de Saúde de São José, EPE",
    "link": "https://diariodarepublica.pt/dr/detalhe/contrato-publico/935-1013997973",
    "detalhes_completos": "1 - IDENTIFICAÇÃO E CONTACTOS DA ENTIDADE ADJUDICANTE\nDesignação da entidade adjudicante: Unidade Local de Saúde de São José, EPE\nNIPC: 508080142\nEndereço: Rua José António Serrano\nCódigo postal: 1150-199\nLocalidade: Lisboa\nPaís: Portugal\nNUT III: PT170\nDistrito: Lisboa\nConcelho: Lisboa\nFreguesia: Freguesia de Arroios - Lisboa\nTelefone: 218841403\nFax: 218841025\nEndereço da Entidade (URL): www.chlc.min-saude.pt\nEndereço Eletrónico: geral@chlc.min-saude.pt\neDelivery Gateway (URL): https://community.vortal.biz/public/\nFunção da Organização: Adquirente\nNorma jurídica da Entidade Adjudicante: Organismo de direito público\nÁrea de atividade da Autoridade Adjudicante: Saúde\n2 - JORNAL OFICIAL DA UNIÃO EUROPEIA\nO procedimento a que este anúncio diz respeito também é publicitado no Jornal Oficial da União Europeia? Não\n3 - AVISO\nModelo de Anúncio: Concurso público urgente\nData de Envio do Anúncio: 16-01-2026 15:19:00\n5 - PROCESSO\nTipo de Procedimento: Concurso público\nPreço base do procedimento: Sim\nValor do preço base do procedimento: 177.907,80 EUR\nProcedimento com lotes? Sim\nNº Máx. de Lotes Autorizado: 7\nNúmero máximo de lotes que podem ser adjudicados a um concorrente: 7\n6 - OBJETO DO CONTRATO\nNúmero de referência interna: 12011426\nDesignação do contrato: Aquisição de Kits, Cateteres, Introdutores e outros dispositivos médicos, para a ULS São José, EPE\nDescrição: Aquisição de Kits, Cateteres, Introdutores e outros dispositivos médicos, para a ULS São José, EPE\nTipo de Contrato Principal: Aquisição de Bens Móveis\nTipo de Contrato: Aquisição de Bens Móveis\nClassificação CPV (Vocabulário Comum para os Contratos Públicos)\nObjeto principal\nVocabulário Principal: 33140000\nPreço base s/IVA: 177.907,80 EUR\nLotes: \nNº: LOT-0001\nDescrição do Lote: Lote 1\nPreço base s/IVA: 15.164,20 EUR\nClassificação CPV (Vocabulário Comum para os Contratos Públicos)\nObjeto principal\nVocabulário Principal: 33140000\nNº: LOT-0002\nDescrição do Lote: Lote 2\nPreço base s/IVA: 9.310,00 EUR\nClassificação CPV (Vocabulário Comum para os Contratos Públicos)\nObjeto principal\nVocabulário Principal: 33140000\nNº: LOT-0003\nDescrição do Lote: Lote 3\nPreço base s/IVA: 39.132,00 EUR\nClassificação CPV (Vocabulário Comum para os Contratos Públicos)\nObjeto principal\nVocabulário Principal: 33140000\nNº: LOT-0004\nDescrição do Lote: Lote 4\nPreço base s/IVA: 6.713,60 EUR\nClassificação CPV (Vocabulário Comum para os Contratos Públicos)\nObjeto principal\nVocabulário Principal: 33140000\nNº: LOT-0005\nDescrição do Lote: Lote 5\nPreço base s/IVA: 1.080,00 EUR\nClassificação CPV (Vocabulário Comum para os Contratos Públicos)\nObjeto principal\nVocabulário Principal: 33140000\nNº: LOT-0006\nDescrição do Lote: Lote 6\nPreço base s/IVA: 60.540,00 EUR\nClassificação CPV (Vocabulário Comum para os Contratos Públicos)\nObjeto principal\nVocabulário Principal: 33140000\nNº: LOT-0007\nDescrição do Lote: Lote 7\nPreço base s/IVA: 45.968,00 EUR\nClassificação CPV (Vocabulário Comum para os Contratos Públicos)\nObjeto principal\nVocabulário Principal: 33140000\n7 - INDICAÇÕES ADICIONAIS\nO contrato envolve aquisição conjunta (satisfação de várias entidades)? Não\nO contrato é adjudicado por uma central de compras? Não\n8 - TÉCNICAS\nO concurso destina-se à celebração de um acordo-quadro? Inexistência de acordo-quadro\nÉ utilizado um leilão eletrónico? Não\nÉ adotada uma fase de negociação? Não\nSistema de Aquisição Dinâmico: Inexistência de sistema de aquisição dinâmico\n9 - LOCAL DA EXECUÇÃO DO CONTRATO\nLOCAL DA EXECUÇÃO DO CONTRATO (PROCEDIMENTO)\nPaís: Portugal\nNUT III: PT170\nLocalidade: Lisboa\nDistrito: Lisboa\nConcelho: Lisboa\nFreguesia: Freguesia de Arroios - Lisboa\nLOCAL DA EXECUÇÃO DO CONTRATO (LOTE)\nIdentificador do Lote: LOT-0001; LOT-0002; LOT-0003; LOT-0004; LOT-0005; LOT-0006; LOT-0007\nPaís: Portugal\nNUT III: PT170\nLocalidade: Lisboa\nDistrito: Lisboa\nConcelho: Lisboa\nFreguesia: Freguesia de Arroios - Lisboa\n10 - PRAZO DE EXECUÇÃO DO CONTRATO\nIdentificador do Lote: LOT-0001; LOT-0002; LOT-0003; LOT-0004; LOT-0005; LOT-0006; LOT-0007\nPrazo de execução do contrato: 346 DIAS\nPrevisão de renovações: Não\n11 - FUNDOS EU\nIdentificador do Lote: LOT-0001; LOT-0002; LOT-0003; LOT-0004; LOT-0005; LOT-0006; LOT-0007\nTêm fundos EU? Não\n12 - DOCUMENTOS DE HABILITAÇÃO\nHabilitação para o exercício da atividade profissional: Não\n13 - CONDIÇÕES DE APRESENTAÇÃO\nPlataforma eletrónica utilizada pela entidade adjudicante: VORTAL\nURL para Apresentação: https://community.vortal.biz/public/\nAdmissibilidade da apresentação de propostas variantes: Não autorizado\nPrazo para apresentação das propostas: 21-01-2026 23:59\nPrazo durante o qual os concorrentes são obrigados a manter as respetivas propostas: 10 dias a contar do termo do prazo para a apresentação das propostas\nIndicação de Subcontratação na Proposta: Inexistência de indicação de subcontratação\n14 - PRESTAÇÃO DE CAUÇÃO\nPrestação de caução: Não\n15 - FORNECIMENTO DAS PEÇAS DO CONCURSO, APRESENTAÇÃO DE PEDIDOS DE PARTICIPAÇÃO E APRESENTAÇÃO DAS PROPOSTAS\nLink para acesso às peças do concurso (URL): https://community.vortal.biz/Public/public-tender-documents/QWF6Q2ZOaGFXMEpOUzN6OHp0Vmg1VTEya0I4VnZxUnVSb0V3WG1SOVB1TjZzZUdOWlpVTEFuSnVmd3ZETkhxMi93cGpDNmxuMkJIK2IxMVl6ZHdoeUE9PTFoaE8q\n20 - OUTROS REQUISITOS\nIdentificador do Lote: LOT-0001; LOT-0002; LOT-0003; LOT-0004; LOT-0005; LOT-0006; LOT-0007\nInformação sobre contratos reservados. Aplica-se a contratos reservados (54º-A)? Não\n21 - CRITÉRIO DE ADJUDICAÇÃO\nO Critério de adjudicação é diferenciado por lote? Não\nMultifator: Não\nMonofator:\nNome: Preço\n24 - CONDIÇÕES DO CONTRATO\nIdentificador do Lote: LOT-0001; LOT-0002; LOT-0003; LOT-0004; LOT-0005; LOT-0006; LOT-0007\nFaturação Eletrónica: Permitido\nObrigação de Subcontratação:\nCódigo da Obrigação de Subcontratação: Não é aplicável nenhuma obrigação de subcontratação.\n25 - COMPRA PÚBLICA ESTRATÉGICA\nCompra Pública Estratégica: Inexistência de contratação pública estratégica\n26 - INFORMAÇÕES ADICIONAIS\nIdentificador do Lote: LOT-0001; LOT-0002; LOT-0003; LOT-0004; LOT-0005; LOT-0006; LOT-0007\nContrato adequado para PME: Sim\nCobertura ACP (Acordo dos Contratos Públicos da Organização Mundial do Comércio): Não\n27 - IDENTIFICAÇÃO E CONTACTOS DO ÓRGÃO DE RECURSOS ADMINISTRATIVOS\nDesignação: Conselho de Administração\nEndereço: Rua António José Serrano\nCódigo postal: 1150-199\nLocalidade: Lisboa\nTelefone: +351 218841000\nFax: +351 218841283\nEndereço eletrónico: sec.vca@ulssjose.min-saude.pt\n28 - IDENTIFICAÇÃO DO(S) AUTOR(ES) DE ANÚNCIO\nNome: Área de Gestão de Compras\nCargo: Área de Gestão de Compras\n419948240",
    "nipc": "508080142",
    "distrito": "Lisboa",
    "concelho": "Lisboa",
    "freguesia": "Freguesia de Arroios - Lisboa",
    "site": "www.chlc.min-saude.pt",
    "email": "geral@chlc.min-saude.pt",
    "designacao_contrato": "Aquisição de Kits, Cateteres, Introdutores e outros dispositivos médicos, para a ULS São José, EPE",
    "descricao": "Aquisição de Kits, Cateteres, Introdutores e outros dispositivos médicos, para a ULS São José, EPE",
    "preco_base": "177.907,80 EUR",
    "prazo_execucao": "346 DIAS",
    "prazo_apresentacao_propostas": "21-01-2026 23:59",
    "fundos_eu": "Não",
    "plataforma_eletronica": "VORTAL",
    "url_procedimento": "https://community.vortal.biz/public/",
    "autor_nome": "Área de Gestão de Compras",
    "autor_cargo": "Área de Gestão de Compras"
  },
  {
    "numero_procedimento": "N/A",
    "entidade": "Município de Moimenta da Beira",
    "link": "https://diariodarepublica.pt/dr/detalhe/contrato-publico/1000-1013997974",
    "detalhes_completos": "Alteração do Anúncio de procedimento n.º 33581/2025, de 2025-12-30, com o ID 419940316\n1 - IDENTIFICAÇÃO E CONTACTOS DA ENTIDADE ADJUDICANTE\nDesignação da entidade adjudicante: Município de Moimenta da Beira\nNIPC: 506664686\nServiço/Órgão/Pessoa de contacto: PRESIDENTE\nEndereço: Largo do Tabolado\nCódigo postal: 3620-324\nLocalidade: Moimenta da Beira\nPaís: Portugal\nNUT III: PT11D\nDistrito: Viseu\nConcelho: Moimenta da Beira\nFreguesia: Freguesia de Moimenta da Beira\nTelefone: 254520070\nFax: 254520071\nEndereço da Entidade (URL): www.cm-moimenta.pt\nEndereço Eletrónico: geral@cm-moimenta.pt\neDelivery Gateway (URL): https://www.acingov.pt\nFunção da Organização: Adquirente\nNorma jurídica da Entidade Adjudicante: Organismo de direito público\nÁrea de atividade da Autoridade Adjudicante: Serviços públicos das administrações públicas\n2 - JORNAL OFICIAL DA UNIÃO EUROPEIA\nO procedimento a que este anúncio diz respeito também é publicitado no Jornal Oficial da União Europeia? Não\n3 - AVISO\nModelo de Anúncio: Concurso público\nData de Envio do Anúncio: 16-01-2026\n5 - PROCESSO\nTipo de Procedimento: Concurso público\nPreço base do procedimento: Sim\nValor do preço base do procedimento: 3.438.924,64 EUR\nProcedimento com lotes? Não\n6 - OBJETO DO CONTRATO\nNúmero de referência interna: 2267/2025\nDesignação do contrato: REQUALIFICAÇÃO DO ESPAÇO QUINTA DA VITELINHA - Green Magic Park\nDescrição: REQUALIFICAÇÃO DO ESPAÇO QUINTA DA VITELINHA - Green Magic Park\nTipo de Contrato Principal: Empreitada de Obras Públicas\nTipo de Contrato: Empreitada de Obras Públicas\nClassificação CPV (Vocabulário Comum para os Contratos Públicos)\nObjeto principal\nVocabulário Principal: 45242000\nPreço base s/IVA: 3.438.924,64 EUR\n7 - INDICAÇÕES ADICIONAIS\nO contrato envolve aquisição conjunta (satisfação de várias entidades)? Não\nO contrato é adjudicado por uma central de compras? Não\n8 - TÉCNICAS\nO concurso destina-se à celebração de um acordo-quadro? Inexistência de acordo-quadro\nÉ utilizado um leilão eletrónico? Não\nÉ adotada uma fase de negociação? Não\nSistema de Aquisição Dinâmico: Inexistência de sistema de aquisição dinâmico\n9 - LOCAL DA EXECUÇÃO DO CONTRATO\nLOCAL DA EXECUÇÃO DO CONTRATO (PROCEDIMENTO)\nPaís: Portugal\nNUT III: PT11D\nLocalidade: Freguesia de Leomil - Moimenta da Beira\nDistrito: Viseu\nConcelho: Moimenta da Beira\nFreguesia: Freguesia de Leomil - Moimenta da Beira\n10 - PRAZO DE EXECUÇÃO DO CONTRATO\nPrazo de execução do contrato: 15 MESES\nPrevisão de renovações: Não\n11 - FUNDOS EU\nTêm fundos EU? Sim\n12 - DOCUMENTOS DE HABILITAÇÃO\nHabilitação para o exercício da atividade profissional: Sim\nTipo: Alvará\nDescrição: Documentos de Habilitação\n13 - CONDIÇÕES DE APRESENTAÇÃO\nPlataforma eletrónica utilizada pela entidade adjudicante: ACIN\nURL para Apresentação: https://www.acingov.pt\nAdmissibilidade da apresentação de propostas variantes: Não autorizado\nPrazo para apresentação das propostas: 26-01-2026 23:59\nPrazo durante o qual os concorrentes são obrigados a manter as respetivas propostas: 90 dias a contar do termo do prazo para a apresentação das propostas\nIndicação de Subcontratação na Proposta: Inexistência de indicação de subcontratação\n14 - PRESTAÇÃO DE CAUÇÃO\nPrestação de caução: Sim\nPercentagem: 5%\nDescrição da Garantia Exigida: O valor da caução é de 5.00% do preço contratual.\n15 - FORNECIMENTO DAS PEÇAS DO CONCURSO, APRESENTAÇÃO DE PEDIDOS DE PARTICIPAÇÃO E APRESENTAÇÃO DAS PROPOSTAS\nLink para acesso às peças do concurso (URL): https://www.acingov.pt/acingovprod/2/zonaPublica/zona_publica_c/donwloadProcedurePiece/MTAxMDg4MA==\n20 - OUTROS REQUISITOS\nInformação sobre contratos reservados. Aplica-se a contratos reservados (54º-A)? Não\n21 - CRITÉRIO DE ADJUDICAÇÃO\nMultifator: Sim\nFator: \nNome: Preço\nPonderação: 90%\nSubfatores: Não\nFator: \nNome: Outros\nOutro Nome: Valia Técnica\nPonderação: 10%\nSubfatores: Sim\nSubfatores: \nNome: Memória Descritiva e Justificativa\nPonderação : 30%; \nNome: Plano de Trabalhos\nPonderação : 25%; \nNome: Plano de Mão-de-Obra\nPonderação : 15%; \nNome: Plano de Equipamentos\nPonderação : 15%; \nNome: Plano de Pagamentos\nPonderação : 15%; \n24 - CONDIÇÕES DO CONTRATO\nFaturação Eletrónica: Permitido\nObrigação de Subcontratação:\nCódigo da Obrigação de Subcontratação: Não é aplicável nenhuma obrigação de subcontratação.\n25 - COMPRA PÚBLICA ESTRATÉGICA\nCompra Pública Estratégica: Inexistência de contratação pública estratégica\n26 - INFORMAÇÕES ADICIONAIS\nContrato adequado para PME: Sim\nCobertura ACP (Acordo dos Contratos Públicos da Organização Mundial do Comércio): Não\n27 - IDENTIFICAÇÃO E CONTACTOS DO ÓRGÃO DE RECURSOS ADMINISTRATIVOS\nDesignação: Câmara Municipal de Moimenta da Beira\nEndereço: Largo do Tabolado\nCódigo postal: 3620-324\nLocalidade: Moimenta da Beira\nTelefone: 2545200070\nFax: \nEndereço eletrónico: geral@cm-moimenta.pt\nPrazo de interposição do recurso: 5 dias\n28 - IDENTIFICAÇÃO DO(S) AUTOR(ES) DE ANÚNCIO\nNome: Paulo Alexandre de Matos Figueiredo\nCargo: Presidente da Câmara Municipal\n29 - ALTERAÇÃO\nMotivo da Alteração: Informações atualizadas\nIdentificador da Versão do Anúncio a Alterar: 4d084149-7e38-4c6f-b18b-fd5551e531a0-01\nIdentificador das Secções Alteradas do Anúncio Anterior: Condições de Apresentação\nDescrição das Alterações: Modificação do prazo para a apresentação de propostas\nAlteração dos Documentos do Concurso: Não\n419948255",
    "nipc": "506664686",
    "distrito": "Viseu",
    "concelho": "Moimenta da Beira",
    "freguesia": "Freguesia de Moimenta da Beira",
    "site": "www.cm-moimenta.pt",
    "email": "geral@cm-moimenta.pt",
    "designacao_contrato": "REQUALIFICAÇÃO DO ESPAÇO QUINTA DA VITELINHA - Green Magic Park",
    "descricao": "REQUALIFICAÇÃO DO ESPAÇO QUINTA DA VITELINHA - Green Magic Park",
    "preco_base": "3.438.924,64 EUR",
    "prazo_execucao": "15 MESES",
    "prazo_apresentacao_propostas": "26-01-2026 23:59",
    "fundos_eu": "Sim",
    "plataforma_eletronica": "ACIN",
    "url_procedimento": "https://www.acingov.pt",
    "autor_nome": "Paulo Alexandre de Matos Figueiredo",
    "autor_cargo": "Presidente da Câmara Municipal"
  },
  {
    "numero_procedimento": "N/A",
    "entidade": "AnÃºncio de procedimento  n.Âº 936/2026  -  DiÃ¡rio da RepÃºblica n.Âº 11/2026, SÃ©rie II de 2026-01-16",
    "link": "https://diariodarepublica.pt/dr/detalhe/contrato-publico/936-1014102274"
  },
  {
    "numero_procedimento": "N/A",
    "entidade": "AnÃºncio de procedimento  n.Âº 937/2026  -  DiÃ¡rio da RepÃºblica n.Âº 11/2026, SÃ©rie II de 2026-01-16",
    "link": "https://diariodarepublica.pt/dr/detalhe/contrato-publico/937-1014142275"
  },
  {
    "numero_procedimento": "N/A",
    "entidade": "A ARCIAL - Associação para Recuperação de Cidadãos Inadaptados de Oliveira do Hospital",
    "link": "https://diariodarepublica.pt/dr/detalhe/contrato-publico/939-1014142276",
    "detalhes_completos": "1 - IDENTIFICAÇÃO E CONTACTOS DA ENTIDADE ADJUDICANTE\nDesignação da entidade adjudicante: A ARCIAL - Associação para Recuperação de Cidadãos Inadaptados de Oliveira do Hospital\nNIPC: 500980896\nServiço/Órgão/Pessoa de contacto: Direção da ARCIAL\nEndereço: Rua António Monteiro\nCódigo postal: 3400-083\nLocalidade: Oliveira do Hospital\nPaís: Portugal\nNUT III: PT16E\nDistrito: Coimbra\nConcelho: Oliveira do Hospital\nFreguesia: Todas\nTelefone: 238604300\nEndereço da Entidade (URL): https://www.arcial.pt\nEndereço Eletrónico: geral@arcial.pt\neDelivery Gateway (URL): https://www.acingov.pt\nFunção da Organização: Adquirente\nNorma jurídica da Entidade Adjudicante: Organismo de direito público\nÁrea de atividade da Autoridade Adjudicante: Serviços públicos das administrações públicas\n2 - JORNAL OFICIAL DA UNIÃO EUROPEIA\nO procedimento a que este anúncio diz respeito também é publicitado no Jornal Oficial da União Europeia? Não\n3 - AVISO\nModelo de Anúncio: Concurso público\nData de Envio do Anúncio: 16-01-2026\n5 - PROCESSO\nTipo de Procedimento: Concurso público\nPreço base do procedimento: Sim\nValor do preço base do procedimento: 291.595,60 EUR\nProcedimento com lotes? Não\n6 - OBJETO DO CONTRATO\nNúmero de referência interna: CP/1/2026\nDesignação do contrato: Empreitada de Requalificação do Edifício do Centro de Atividades e Capacitação para Inclusão (CACI) e Serviços (Lavandaria, Refeitório e Cantina)\nDescrição: Empreitada de Requalificação do Edifício do Centro de Atividades e Capacitação para Inclusão (CACI) e Serviços (Lavandaria, Refeitório e Cantina)\nTipo de Contrato Principal: Empreitada de Obras Públicas\nTipo de Contrato: Empreitada de Obras Públicas\nClassificação CPV (Vocabulário Comum para os Contratos Públicos)\nObjeto principal\nVocabulário Principal: 45454000\nPreço base s/IVA: 291.595,60 EUR\n7 - INDICAÇÕES ADICIONAIS\nO contrato envolve aquisição conjunta (satisfação de várias entidades)? Não\nO contrato é adjudicado por uma central de compras? Não\n8 - TÉCNICAS\nO concurso destina-se à celebração de um acordo-quadro? Inexistência de acordo-quadro\nÉ utilizado um leilão eletrónico? Não\nÉ adotada uma fase de negociação? Não\nSistema de Aquisição Dinâmico: Inexistência de sistema de aquisição dinâmico\n9 - LOCAL DA EXECUÇÃO DO CONTRATO\nLOCAL DA EXECUÇÃO DO CONTRATO (PROCEDIMENTO)\nPaís: Portugal\nNUT III: PT16E\nLocalidade: União das Freguesias de Oliveira do Hospital e São Paio de Gramaços\nDistrito: Coimbra\nConcelho: Oliveira do Hospital\nFreguesia: União das Freguesias de Oliveira do Hospital e São Paio de Gramaços\n10 - PRAZO DE EXECUÇÃO DO CONTRATO\nPrazo de execução do contrato: 90 DIAS\nPrevisão de renovações: Não\n11 - FUNDOS EU\nTêm fundos EU? Não\n12 - DOCUMENTOS DE HABILITAÇÃO\nHabilitação para o exercício da atividade profissional: Sim\nTipo: Alvará\nDescrição: De acordo com o artigo 22º do Programa do Procedimento \n13 - CONDIÇÕES DE APRESENTAÇÃO\nPlataforma eletrónica utilizada pela entidade adjudicante: ACIN\nURL para Apresentação: https://www.acingov.pt\nAdmissibilidade da apresentação de propostas variantes: Não autorizado\nPrazo para apresentação das propostas: 28-01-2026 23:59\nPrazo durante o qual os concorrentes são obrigados a manter as respetivas propostas: 66 dias a contar do termo do prazo para a apresentação das propostas\nIndicação de Subcontratação na Proposta: Inexistência de indicação de subcontratação\n14 - PRESTAÇÃO DE CAUÇÃO\nPrestação de caução: Sim\nPercentagem: 5%\nDescrição da Garantia Exigida: O valor da caução é de 5.00% do preço contratual.\n15 - FORNECIMENTO DAS PEÇAS DO CONCURSO, APRESENTAÇÃO DE PEDIDOS DE PARTICIPAÇÃO E APRESENTAÇÃO DAS PROPOSTAS\nLink para acesso às peças do concurso (URL): https://www.acingov.pt/acingovprod/2/zonaPublica/zona_publica_c/donwloadProcedurePiece/MTA0OTAwMQ==\n20 - OUTROS REQUISITOS\nInformação sobre contratos reservados. Aplica-se a contratos reservados (54º-A)? Não\n21 - CRITÉRIO DE ADJUDICAÇÃO\nMultifator: Não\nMonofator:\nNome: Preço\n24 - CONDIÇÕES DO CONTRATO\nFaturação Eletrónica: Permitido\nObrigação de Subcontratação:\nCódigo da Obrigação de Subcontratação: Não é aplicável nenhuma obrigação de subcontratação.\n25 - COMPRA PÚBLICA ESTRATÉGICA\nCompra Pública Estratégica: Inexistência de contratação pública estratégica\n26 - INFORMAÇÕES ADICIONAIS\nContrato adequado para PME: Não\nCobertura ACP (Acordo dos Contratos Públicos da Organização Mundial do Comércio): Não\n27 - IDENTIFICAÇÃO E CONTACTOS DO ÓRGÃO DE RECURSOS ADMINISTRATIVOS\nDesignação: Direção da ARCIAL\nEndereço: Rua António Monteiro S/N\nCódigo postal: 3400-083\nLocalidade: Oliveira do Hospital\nTelefone: 238604300\nFax: \nEndereço eletrónico: geral@arcial.pt\n28 - IDENTIFICAÇÃO DO(S) AUTOR(ES) DE ANÚNCIO\nNome: Artur Manuel Freire de Abreu\nCargo: Presidente da Direção\n419948139",
    "nipc": "500980896",
    "distrito": "Coimbra",
    "concelho": "Oliveira do Hospital",
    "freguesia": "Todas",
    "site": "https://www.arcial.pt",
    "email": "geral@arcial.pt",
    "designacao_contrato": "Empreitada de Requalificação do Edifício do Centro de Atividades e Capacitação para Inclusão (CACI) e Serviços (Lavandaria, Refeitório e Cantina)",
    "descricao": "Empreitada de Requalificação do Edifício do Centro de Atividades e Capacitação para Inclusão (CACI) e Serviços (Lavandaria, Refeitório e Cantina)",
    "preco_base": "291.595,60 EUR",
    "prazo_execucao": "90 DIAS",
    "prazo_apresentacao_propostas": "28-01-2026 23:59",
    "fundos_eu": "Não",
    "plataforma_eletronica": "ACIN",
    "url_procedimento": "https://www.acingov.pt",
    "autor_nome": "Artur Manuel Freire de Abreu",
    "autor_cargo": "Presidente da Direção"
  },
  {
    "numero_procedimento": "N/A",
    "entidade": "Município de Sintra",
    "link": "https://diariodarepublica.pt/dr/detalhe/contrato-publico/941-1014142277",
    "detalhes_completos": "1 - IDENTIFICAÇÃO E CONTACTOS DA ENTIDADE ADJUDICANTE\nDesignação da entidade adjudicante: Município de Sintra\nNIPC: 500051062\nEndereço: Largo Doutor Virgílio Horta\nCódigo postal: 2710-501\nLocalidade: Lisboa\nPaís: Portugal\nNUT III: PT170\nDistrito: Lisboa\nConcelho: Sintra\nFreguesia: União das Freguesias de Sintra (Santa Maria e São Miguel, São Martinho e São Pedro de Penaferrim)\nTelefone: 219238749\nFax: 219238790\nEndereço da Entidade (URL): www.cm-sintra.pt\nEndereço Eletrónico: dcp@cm-sintra.pt\neDelivery Gateway (URL): https://community.vortal.biz/public/\nFunção da Organização: Adquirente\nNorma jurídica da Entidade Adjudicante: Autoridade local\nÁrea de atividade da Autoridade Adjudicante: Serviços públicos das administrações públicas\n2 - JORNAL OFICIAL DA UNIÃO EUROPEIA\nO procedimento a que este anúncio diz respeito também é publicitado no Jornal Oficial da União Europeia? Não\n3 - AVISO\nModelo de Anúncio: Concurso público\nData de Envio do Anúncio: 16-01-2026\n5 - PROCESSO\nTipo de Procedimento: Concurso público\nPreço base do procedimento: Sim\nValor do preço base do procedimento: 15.000,00 EUR\nProcedimento com lotes? Não\n6 - OBJETO DO CONTRATO\nNúmero de referência interna: CT-25/01549\nDesignação do contrato: CT-25/01549: Aquisição de serviços de mudanças de mobiliário, para realojamento temporário por motivo de obras, remodelação ou restauro profundo, em regime de fornecimento contínuo, no ano de 2026\nDescrição: CT-25/01549: Serviços de mudanças de mobiliário, para realojamento temporário por motivo de obras, remodelação ou restauro profundo, em RFC, p/2026\nTipo de Contrato Principal: Aquisição de Serviços\nTipo de Contrato: Aquisição de Serviços\nClassificação CPV (Vocabulário Comum para os Contratos Públicos)\nObjeto principal\nVocabulário Principal: 60100000\nPreço base s/IVA: 15.000,00 EUR\n7 - INDICAÇÕES ADICIONAIS\nO contrato envolve aquisição conjunta (satisfação de várias entidades)? Não\nO contrato é adjudicado por uma central de compras? Não\n8 - TÉCNICAS\nO concurso destina-se à celebração de um acordo-quadro? Inexistência de acordo-quadro\nÉ utilizado um leilão eletrónico? Não\nÉ adotada uma fase de negociação? Não\nSistema de Aquisição Dinâmico: Inexistência de sistema de aquisição dinâmico\n9 - LOCAL DA EXECUÇÃO DO CONTRATO\nLOCAL DA EXECUÇÃO DO CONTRATO (PROCEDIMENTO)\nPaís: Portugal\nNUT III: PT170\nLocalidade: Lisboa\nDistrito: Lisboa\nConcelho: Sintra\nFreguesia: União das Freguesias de Sintra (Santa Maria e São Miguel, São Martinho e São Pedro de Penaferrim)\n10 - PRAZO DE EXECUÇÃO DO CONTRATO\nPrazo de execução do contrato: 1 ANOS\nPrevisão de renovações: Não\n11 - FUNDOS EU\nTêm fundos EU? Não\n12 - DOCUMENTOS DE HABILITAÇÃO\nHabilitação para o exercício da atividade profissional: Não\n13 - CONDIÇÕES DE APRESENTAÇÃO\nPlataforma eletrónica utilizada pela entidade adjudicante: VORTAL\nURL para Apresentação: https://community.vortal.biz/public/\nAdmissibilidade da apresentação de propostas variantes: Não autorizado\nPrazo para apresentação das propostas: 28-01-2026 18:00\nPrazo durante o qual os concorrentes são obrigados a manter as respetivas propostas: 66 dias a contar do termo do prazo para a apresentação das propostas\nIndicação de Subcontratação na Proposta: Inexistência de indicação de subcontratação\n14 - PRESTAÇÃO DE CAUÇÃO\nPrestação de caução: Não\n15 - FORNECIMENTO DAS PEÇAS DO CONCURSO, APRESENTAÇÃO DE PEDIDOS DE PARTICIPAÇÃO E APRESENTAÇÃO DAS PROPOSTAS\nLink para acesso às peças do concurso (URL): https://community.vortal.biz/Public/public-tender-documents/ajhOZWpLUVR2T2p5OEM1TnExMXB0Zi9mTFJaVVNYZDZzR2M0VlZaaGh6RGk3UGR0RkRXVm9HUkZUa1RnSTljaVYrZE1JT1FQV3RzUHZ0QStPVkxtaGc9PWE2I3BO\n20 - OUTROS REQUISITOS\nInformação sobre contratos reservados. Aplica-se a contratos reservados (54º-A)? Não\n21 - CRITÉRIO DE ADJUDICAÇÃO\nMultifator: Não\nMonofator:\nNome: Preço\n24 - CONDIÇÕES DO CONTRATO\nFaturação Eletrónica: Permitido\nObrigação de Subcontratação:\nCódigo da Obrigação de Subcontratação: Não é aplicável nenhuma obrigação de subcontratação.\n25 - COMPRA PÚBLICA ESTRATÉGICA\nCompra Pública Estratégica: Inexistência de contratação pública estratégica\n26 - INFORMAÇÕES ADICIONAIS\nContrato adequado para PME: Sim\nCobertura ACP (Acordo dos Contratos Públicos da Organização Mundial do Comércio): Não\n27 - IDENTIFICAÇÃO E CONTACTOS DO ÓRGÃO DE RECURSOS ADMINISTRATIVOS\nDesignação: Presidente da Câmara Municipal de Sintra\nEndereço: Largo Dr. Virgílio Horta\nCódigo postal: 2710-501\nLocalidade: Sintra\nTelefone: +351 219238750\nFax: +351 219238790\nEndereço eletrónico: dcp@cm-sintra.pt\n28 - IDENTIFICAÇÃO DO(S) AUTOR(ES) DE ANÚNCIO\nNome: Marco Almeida\nCargo: Presidente da Câmara Municipal de Sintra\n419948032",
    "nipc": "500051062",
    "distrito": "Lisboa",
    "concelho": "Sintra",
    "freguesia": "União das Freguesias de Sintra (Santa Maria e São Miguel, São Martinho e São Pedro de Penaferrim)",
    "site": "www.cm-sintra.pt",
    "email": "dcp@cm-sintra.pt",
    "designacao_contrato": "CT-25/01549: Aquisição de serviços de mudanças de mobiliário, para realojamento temporário por motivo de obras, remodelação ou restauro profundo, em regime de fornecimento contínuo, no ano de 2026",
    "descricao": "CT-25/01549: Serviços de mudanças de mobiliário, para realojamento temporário por motivo de obras, remodelação ou restauro profundo, em RFC, p/2026",
    "preco_base": "15.000,00 EUR",
    "prazo_execucao": "1 ANOS",
    "prazo_apresentacao_propostas": "28-01-2026 18:00",
    "fundos_eu": "Não",
    "plataforma_eletronica": "VORTAL",
    "url_procedimento": "https://community.vortal.biz/public/",
    "autor_nome": "Marco Almeida",
    "autor_cargo": "Presidente da Câmara Municipal de Sintra"
  },
  {
    "numero_procedimento": "N/A",
    "entidade": "AnÃºncio de procedimento  n.Âº 942/2026  -  DiÃ¡rio da RepÃºblica n.Âº 11/2026, SÃ©rie II de 2026-01-16",
    "link": "https://diariodarepublica.pt/dr/detalhe/contrato-publico/942-1014142278"
  },
  {
    "numero_procedimento": "N/A",
    "entidade": "AnÃºncio de procedimento  n.Âº 948/2026  -  DiÃ¡rio da RepÃºblica n.Âº 11/2026, SÃ©rie II de 2026-01-16",
    "link": "https://diariodarepublica.pt/dr/detalhe/contrato-publico/948-1014142279"
  },
  {
    "numero_procedimento": "N/A",
    "entidade": "SIMARSUL - Saneamento da Península de Setúbal, SA",
    "link": "https://diariodarepublica.pt/dr/detalhe/contrato-publico/949-1014197065",
    "detalhes_completos": "Alteração do Anúncio de procedimento n.º 30096/2025, de 2025-11-20, com o ID 419792727\n1 - IDENTIFICAÇÃO E CONTACTOS DA ENTIDADE ADJUDICANTE\nDesignação da entidade adjudicante: SIMARSUL - Saneamento da Península de Setúbal, SA\nNIPC: 514385901\nServiço/Órgão/Pessoa de contacto: Direção de Infraestruturas\nEndereço: Av. da Siderurgia Nacional, nº1, Edifício SN 1\nCódigo postal: 2840-075\nLocalidade: Aldeia de Paio Pires, Seixal\nPaís: Portugal\nNUT III: PT170\nDistrito: Setúbal\nConcelho: Sesimbra\nFreguesia: Todas\nTelefone: 265544000\nFax: 265544000\nEndereço da Entidade (URL): www.simarsul.adp.pt\nEndereço Eletrónico: contratacao.simarsul@adp.pt\neDelivery Gateway (URL): https://www.acingov.pt\nFunção da Organização: Adquirente\nNorma jurídica da Entidade Adjudicante: Organismo de direito público\nÁrea de atividade da Autoridade Adjudicante: Proteção ambiental\n2 - JORNAL OFICIAL DA UNIÃO EUROPEIA\nO procedimento a que este anúncio diz respeito também é publicitado no Jornal Oficial da União Europeia? Não\n3 - AVISO\nModelo de Anúncio: Concurso público\nData de Envio do Anúncio: 16-01-2026\n5 - PROCESSO\nTipo de Procedimento: Concurso público\nPreço base do procedimento: Sim\nValor do preço base do procedimento: 880.000,00 EUR\nProcedimento com lotes? Não\n6 - OBJETO DO CONTRATO\nNúmero de referência interna: 054/CP/2025\nDesignação do contrato: Empreitada de Conceção-Construção de unidades de produção de energia elétrica de fonte fotovoltaica da SIMARSUL - SOLAR III\nDescrição: Empreitada de Conceção-Construção de unidades de produção de energia elétrica de fonte fotovoltaica da SIMARSUL\nTipo de Contrato Principal: Empreitada de Obras Públicas\nTipo de Contrato: Empreitada de Obras Públicas\nClassificação CPV (Vocabulário Comum para os Contratos Públicos)\nObjeto principal\nVocabulário Principal: 45251100\nPreço base s/IVA: 880.000,00 EUR\n7 - INDICAÇÕES ADICIONAIS\nO contrato envolve aquisição conjunta (satisfação de várias entidades)? Não\nO contrato é adjudicado por uma central de compras? Não\n8 - TÉCNICAS\nO concurso destina-se à celebração de um acordo-quadro? Inexistência de acordo-quadro\nÉ utilizado um leilão eletrónico? Não\nÉ adotada uma fase de negociação? Não\nSistema de Aquisição Dinâmico: Inexistência de sistema de aquisição dinâmico\n9 - LOCAL DA EXECUÇÃO DO CONTRATO\nLOCAL DA EXECUÇÃO DO CONTRATO (PROCEDIMENTO)\nPaís: Portugal\nNUT III: PT170\nLocalidade: Freguesia de Quinta do Conde\nDistrito: Setúbal\nConcelho: Sesimbra\nFreguesia: Freguesia de Quinta do Conde\nPaís: Portugal\nNUT III: PT170\nLocalidade: União das Freguesias de Barreiro e Lavradio\nDistrito: Setúbal\nConcelho: Barreiro\nFreguesia: União das Freguesias de Barreiro e Lavradio\n10 - PRAZO DE EXECUÇÃO DO CONTRATO\nPrazo de execução do contrato: 390 DIAS\nPrevisão de renovações: Não\n11 - FUNDOS EU\nTêm fundos EU? Não\n12 - DOCUMENTOS DE HABILITAÇÃO\nHabilitação para o exercício da atividade profissional: Sim\nTipo: Alvará\nDescrição: 6.ª Subcategoria da 4.ª Categoria da classe correspondente ao valor global da proposta; (Instalações de produção de energia elétrica até 30 kV)\n4.ª Subcategoria da 4.ª Categoria da classe correspondente ao valor dos trabalhos especializados que lhe respeitem; (Redes e instalações elétricas de tensão de serviço até 30kV)\n3.ª Subcategoria da 4.ª Categoria da classe correspondente ao valor dos trabalhos especializados que lhe respeitem (Postos de transformação até 250 kVA)\n13 - CONDIÇÕES DE APRESENTAÇÃO\nPlataforma eletrónica utilizada pela entidade adjudicante: ACIN\nURL para Apresentação: https://www.acingov.pt\nAdmissibilidade da apresentação de propostas variantes: Não autorizado\nPrazo para apresentação das propostas: 03-02-2026 18:00\nPrazo durante o qual os concorrentes são obrigados a manter as respetivas propostas: 180 dias a contar do termo do prazo para a apresentação das propostas\nIndicação de Subcontratação na Proposta: Inexistência de indicação de subcontratação\n14 - PRESTAÇÃO DE CAUÇÃO\nPrestação de caução: Sim\nPercentagem: 5%\nDescrição da Garantia Exigida: O valor da caução é de 5.00% do preço contratual.\n15 - FORNECIMENTO DAS PEÇAS DO CONCURSO, APRESENTAÇÃO DE PEDIDOS DE PARTICIPAÇÃO E APRESENTAÇÃO DAS PROPOSTAS\nLink para acesso às peças do concurso (URL): https://www.acingov.pt/acingovprod/2/zonaPublica/zona_publica_c/donwloadProcedurePiece/OTk1Nzkw\n20 - OUTROS REQUISITOS\nInformação sobre contratos reservados. Aplica-se a contratos reservados (54º-A)? Não\n21 - CRITÉRIO DE ADJUDICAÇÃO\nMultifator: Sim\nFator: \nNome: Outros\nOutro Nome: Custo Global (VAL-preço e custo)\nPonderação: 90%\nSubfatores: Não\nFator: \nNome: Outros\nOutro Nome: Valia Técnica\nPonderação: 10%\nSubfatores: Não\n24 - CONDIÇÕES DO CONTRATO\nFaturação Eletrónica: Necessário\nObrigação de Subcontratação:\nCódigo da Obrigação de Subcontratação: Não é aplicável nenhuma obrigação de subcontratação.\n25 - COMPRA PÚBLICA ESTRATÉGICA\nCompra Pública Estratégica: Inexistência de contratação pública estratégica\n26 - INFORMAÇÕES ADICIONAIS\nContrato adequado para PME: Sim\nCobertura ACP (Acordo dos Contratos Públicos da Organização Mundial do Comércio): Não\n27 - IDENTIFICAÇÃO E CONTACTOS DO ÓRGÃO DE RECURSOS ADMINISTRATIVOS\nDesignação: Conselho de administração da SIMARSUL, S.A.\nEndereço: Av. da Siderurgia Nacional, nº1, Edifício SN 1\nCódigo postal: 2840-075\nLocalidade: Aldeia de Paio Pires, Seixal\nTelefone: 265544000\nFax: \nEndereço eletrónico: geral.simarsul@adp.pt\n28 - IDENTIFICAÇÃO DO(S) AUTOR(ES) DE ANÚNCIO\nNome: José Fialho\nCargo: Presidente do Conselho de Administração\n29 - ALTERAÇÃO\nMotivo da Alteração: Informações atualizadas\nIdentificador da Versão do Anúncio a Alterar: 92d0c2b6-b209-4906-9af5-7a4edbcc0207-01\nIdentificador das Secções Alteradas do Anúncio Anterior: Condições de Apresentação\nDescrição das Alterações: Modificação do prazo para a apresentação de propostas\nAlteração dos Documentos do Concurso: Não\n419948173",
    "nipc": "514385901",
    "distrito": "Setúbal",
    "concelho": "Sesimbra",
    "freguesia": "Todas",
    "site": "www.simarsul.adp.pt",
    "email": "contratacao.simarsul@adp.pt",
    "designacao_contrato": "Empreitada de Conceção-Construção de unidades de produção de energia elétrica de fonte fotovoltaica da SIMARSUL - SOLAR III",
    "descricao": "Empreitada de Conceção-Construção de unidades de produção de energia elétrica de fonte fotovoltaica da SIMARSUL",
    "preco_base": "880.000,00 EUR",
    "prazo_execucao": "390 DIAS",
    "prazo_apresentacao_propostas": "03-02-2026 18:00",
    "fundos_eu": "Não",
    "plataforma_eletronica": "ACIN",
    "url_procedimento": "https://www.acingov.pt",
    "autor_nome": "José Fialho",
    "autor_cargo": "Presidente do Conselho de Administração"
  },
  {
    "numero_procedimento": "N/A",
    "entidade": "Associação de Turismo de Lisboa - Visitors and Convention Bureau",
    "link": "https://diariodarepublica.pt/dr/detalhe/contrato-publico/952-1014197067",
    "detalhes_completos": "1 - IDENTIFICAÇÃO E CONTACTOS DA ENTIDADE ADJUDICANTE\nDesignação da entidade adjudicante: Associação de Turismo de Lisboa - Visitors and Convention Bureau\nNIPC: 501880160\nServiço/Órgão/Pessoa de contacto: André Duque\nEndereço: R do Arsenal, 15\nCódigo postal: 1100-038\nLocalidade: Lisboa\nPaís: Portugal\nNUT III: PT170\nDistrito: Lisboa\nConcelho: Lisboa\nFreguesia: Todas\nTelefone: 210312700\nFax: 210312899\nEndereço da Entidade (URL): https://www.visitlisboa.com/pt-pt\nEndereço Eletrónico: atl@visitlisboa.com\neDelivery Gateway (URL): https://community.vortal.biz/public/\nFunção da Organização: Adquirente\nNorma jurídica da Entidade Adjudicante: Organização que adjudica um contrato subvencionado por uma autoridade adjudicante\nÁrea de atividade da Autoridade Adjudicante: Atividades recreativas, culturais e religiosas\n2 - JORNAL OFICIAL DA UNIÃO EUROPEIA\nO procedimento a que este anúncio diz respeito também é publicitado no Jornal Oficial da União Europeia? Não\n3 - AVISO\nModelo de Anúncio: Concurso público\nData de Envio do Anúncio: 16-01-2026\n5 - PROCESSO\nTipo de Procedimento: Concurso público\nPreço base do procedimento: Sim\nValor do preço base do procedimento: 1.200.000,00 EUR\nProcedimento com lotes? Não\n6 - OBJETO DO CONTRATO\nNúmero de referência interna: 25.XI _EMPREITADA_CP_01_2026\nDesignação do contrato: CONCURSO PÚBLICO N.º 25.XI _EMPREITADA_CP_01_2026\nDescrição: Empreitada de obra pública de requalificação das instalações sanitárias do Museu do Palácio Nacional da Ajuda\nTipo de Contrato Principal: Empreitada de Obras Públicas\nTipo de Contrato: Empreitada de Obras Públicas\nClassificação CPV (Vocabulário Comum para os Contratos Públicos)\nObjeto principal\nVocabulário Principal: 45200000\nPreço base s/IVA: 1.200.000,00 EUR\n7 - INDICAÇÕES ADICIONAIS\nO contrato envolve aquisição conjunta (satisfação de várias entidades)? Não\nO contrato é adjudicado por uma central de compras? Não\n8 - TÉCNICAS\nO concurso destina-se à celebração de um acordo-quadro? Inexistência de acordo-quadro\nÉ utilizado um leilão eletrónico? Não\nÉ adotada uma fase de negociação? Não\nSistema de Aquisição Dinâmico: Inexistência de sistema de aquisição dinâmico\n9 - LOCAL DA EXECUÇÃO DO CONTRATO\nLOCAL DA EXECUÇÃO DO CONTRATO (PROCEDIMENTO)\nPaís: Portugal\nNUT III: PT170\nLocalidade: Lisboa\nDistrito: Lisboa\nConcelho: Lisboa\nFreguesia: Todas\n10 - PRAZO DE EXECUÇÃO DO CONTRATO\nPrazo de execução do contrato: 165 DIAS\nPrevisão de renovações: Não\n11 - FUNDOS EU\nTêm fundos EU? Sim\n12 - DOCUMENTOS DE HABILITAÇÃO\nHabilitação para o exercício da atividade profissional: Sim\nTipo: Alvará\nDescrição: i. 1.ª categoria, 4.ª subcategoria, classe 2;\nii. 1.ª categoria, 5.ª subcategoria, classe 2;\niii. 1.ª categoria, 8.ª subcategoria, classe 1;\niv. 1.ª categoria, 10.ª subcategoria, classe 4;\nv. 4.ª categoria, 1.ª subcategoria, classe 1;\nvi. 4.ª categoria, 12.ª subcategoria, classe 1; e\nvii. 5.ª categoria, 1.ª subcategoria, classe 1;\n13 - CONDIÇÕES DE APRESENTAÇÃO\nPlataforma eletrónica utilizada pela entidade adjudicante: VORTAL\nURL para Apresentação: https://community.vortal.biz/public/\nAdmissibilidade da apresentação de propostas variantes: Não autorizado\nPrazo para apresentação das propostas: 27-01-2026 23:59\nPrazo durante o qual os concorrentes são obrigados a manter as respetivas propostas: 66 dias a contar do termo do prazo para a apresentação das propostas\nApresentação de Catálogo Eletrónico: Não autorizado\nIndicação de Subcontratação na Proposta: Inexistência de indicação de subcontratação\n14 - PRESTAÇÃO DE CAUÇÃO\nPrestação de caução: Sim\nPercentagem: 5%\nDescrição da Garantia Exigida: cfr. Programa de Procedimento\n15 - FORNECIMENTO DAS PEÇAS DO CONCURSO, APRESENTAÇÃO DE PEDIDOS DE PARTICIPAÇÃO E APRESENTAÇÃO DAS PROPOSTAS\nLink para acesso às peças do concurso (URL): https://community.vortal.biz/Public/public-tender-documents/S0Q0V29jR2xrSUp4VWhCeXhCRTQrcVNQdlRWdmJJYW5aQTlOWlZMK3ErOGtIMGdYUnVmVnlqSzh0WksraS8yb3FvZkFkaGRGVUVjcE1RWCtiUVFrVGc9PTJwelBm\n20 - OUTROS REQUISITOS\nInformação sobre contratos reservados. Aplica-se a contratos reservados (54º-A)? Não\n21 - CRITÉRIO DE ADJUDICAÇÃO\nMultifator: Não\nMonofator:\nNome: Preço\n24 - CONDIÇÕES DO CONTRATO\nFaturação Eletrónica: Permitido\nObrigação de Subcontratação:\nCódigo da Obrigação de Subcontratação: Não é aplicável nenhuma obrigação de subcontratação.\n25 - COMPRA PÚBLICA ESTRATÉGICA\nCompra Pública Estratégica: Inexistência de contratação pública estratégica\n26 - INFORMAÇÕES ADICIONAIS\nContrato adequado para PME: Sim\nCobertura ACP (Acordo dos Contratos Públicos da Organização Mundial do Comércio): Não\n27 - IDENTIFICAÇÃO E CONTACTOS DO ÓRGÃO DE RECURSOS ADMINISTRATIVOS\nDesignação: Comissão Executiva da ATL\nEndereço: Rua do Arsenal n.º 23\nCódigo postal: 1100-038\nLocalidade: Lisboa\nTelefone: +351 210312700\nFax: +351 210312899\nEndereço eletrónico: atl@visitlisboa.com\nPrazo de interposição do recurso: 5 dias\n28 - IDENTIFICAÇÃO DO(S) AUTOR(ES) DE ANÚNCIO\nNome: David Coelho Mendes\nCargo: Assessoria Gabinete Juridico\n419948126",
    "nipc": "501880160",
    "distrito": "Lisboa",
    "concelho": "Lisboa",
    "freguesia": "Todas",
    "site": "https://www.visitlisboa.com/pt-pt",
    "email": "atl@visitlisboa.com",
    "designacao_contrato": "CONCURSO PÚBLICO N.º 25.XI _EMPREITADA_CP_01_2026",
    "descricao": "Empreitada de obra pública de requalificação das instalações sanitárias do Museu do Palácio Nacional da Ajuda",
    "preco_base": "1.200.000,00 EUR",
    "prazo_execucao": "165 DIAS",
    "prazo_apresentacao_propostas": "27-01-2026 23:59",
    "fundos_eu": "Sim",
    "plataforma_eletronica": "VORTAL",
    "url_procedimento": "https://community.vortal.biz/public/",
    "autor_nome": "David Coelho Mendes",
    "autor_cargo": "Assessoria Gabinete Juridico"
  },
  {
    "numero_procedimento": "N/A",
    "entidade": "ALTERNÂNCIA - Ensino e Formação Profissional, C. R. L.",
    "link": "https://diariodarepublica.pt/dr/detalhe/contrato-publico/954-1014197068",
    "detalhes_completos": "1 - IDENTIFICAÇÃO E CONTACTOS DA ENTIDADE ADJUDICANTE\nDesignação da entidade adjudicante: ALTERNÂNCIA - Ensino e Formação Profissional, C. R. L.\nNIPC: 501462244\nEndereço: RUA LUÍSA TODY\nCódigo postal: 4465-196\nLocalidade: Porto\nPaís: Portugal\nNUT III: PT11A\nDistrito: Porto\nConcelho: Matosinhos\nFreguesia: União das Freguesias de São Mamede de Infesta e Senhora da Hora\nTelefone: 229021321\nFax: 229578865\nEndereço da Entidade (URL): https://alternancia.edu.pt/\nEndereço Eletrónico: geral@alternancia.mail.pt\neDelivery Gateway (URL): https://community.vortal.biz/public/\nFunção da Organização: Adquirente\nNorma jurídica da Entidade Adjudicante: Autoridade da administração central\nÁrea de atividade da Autoridade Adjudicante: Educação\n2 - JORNAL OFICIAL DA UNIÃO EUROPEIA\nO procedimento a que este anúncio diz respeito também é publicitado no Jornal Oficial da União Europeia? Não\n3 - AVISO\nModelo de Anúncio: Concurso público\nData de Envio do Anúncio: 16-01-2026\n5 - PROCESSO\nTipo de Procedimento: Concurso público\nPreço base do procedimento: Sim\nValor do preço base do procedimento: 655.589,24 EUR\nProcedimento com lotes? Não\n6 - OBJETO DO CONTRATO\nNúmero de referência interna: CP_01_26\nDesignação do contrato: Empreitada de Remodelação de Instalações - Centro Tecnológico Industrial, Escola  Profissional Alternância\nDescrição: Empreitada de Remodelação de Instalações - Centro Tecnológico Industrial, Escola Profissional Alternância\nTipo de Contrato Principal: Empreitada de Obras Públicas\nTipo de Contrato: Empreitada de Obras Públicas\nClassificação CPV (Vocabulário Comum para os Contratos Públicos)\nObjeto principal\nVocabulário Principal: 45200000\nPreço base s/IVA: 655.589,24 EUR\n7 - INDICAÇÕES ADICIONAIS\nO contrato envolve aquisição conjunta (satisfação de várias entidades)? Não\nO contrato é adjudicado por uma central de compras? Não\n8 - TÉCNICAS\nO concurso destina-se à celebração de um acordo-quadro? Inexistência de acordo-quadro\nÉ utilizado um leilão eletrónico? Não\nÉ adotada uma fase de negociação? Não\nSistema de Aquisição Dinâmico: Inexistência de sistema de aquisição dinâmico\n9 - LOCAL DA EXECUÇÃO DO CONTRATO\nLOCAL DA EXECUÇÃO DO CONTRATO (PROCEDIMENTO)\nPaís: Portugal\nNUT III: PT11A\nLocalidade: Área Metropolitana do Porto\nDistrito: Porto\nConcelho: Porto\nFreguesia: Todas\n10 - PRAZO DE EXECUÇÃO DO CONTRATO\nPrazo de execução do contrato: 2 MESES\nPrevisão de renovações: Não\n11 - FUNDOS EU\nTêm fundos EU? Sim\n12 - DOCUMENTOS DE HABILITAÇÃO\nHabilitação para o exercício da atividade profissional: Não\n13 - CONDIÇÕES DE APRESENTAÇÃO\nPlataforma eletrónica utilizada pela entidade adjudicante: VORTAL\nURL para Apresentação: https://community.vortal.biz/public/\nAdmissibilidade da apresentação de propostas variantes: Não autorizado\nPrazo para apresentação das propostas: 23-01-2026 23:59\nPrazo durante o qual os concorrentes são obrigados a manter as respetivas propostas: 66 dias a contar do termo do prazo para a apresentação das propostas\nIndicação de Subcontratação na Proposta: Inexistência de indicação de subcontratação\n14 - PRESTAÇÃO DE CAUÇÃO\nPrestação de caução: Sim\nPercentagem: 5%\nDescrição da Garantia Exigida: Conforme Programa de Procedimento\n15 - FORNECIMENTO DAS PEÇAS DO CONCURSO, APRESENTAÇÃO DE PEDIDOS DE PARTICIPAÇÃO E APRESENTAÇÃO DAS PROPOSTAS\nLink para acesso às peças do concurso (URL): https://community.vortal.biz/Public/public-tender-documents/TDJKbTdPbmZrWUg3Si8zeU81QUcvK1hIRUFMQzVCeldFVURsVDhQaGZucGY4RU9JeE0zZkNCcEpPVEJNbzhvL1pVaTdBQ3BvcGd1VlAxSTJVQy9nR3c9PSVWaWUz\n20 - OUTROS REQUISITOS\nInformação sobre contratos reservados. Aplica-se a contratos reservados (54º-A)? Não\n21 - CRITÉRIO DE ADJUDICAÇÃO\nMultifator: Não\nMonofator:\nNome: Preço\n24 - CONDIÇÕES DO CONTRATO\nFaturação Eletrónica: Permitido\nObrigação de Subcontratação:\nCódigo da Obrigação de Subcontratação: Não é aplicável nenhuma obrigação de subcontratação.\n25 - COMPRA PÚBLICA ESTRATÉGICA\nCompra Pública Estratégica: Inexistência de contratação pública estratégica\n26 - INFORMAÇÕES ADICIONAIS\nContrato adequado para PME: Sim\nCobertura ACP (Acordo dos Contratos Públicos da Organização Mundial do Comércio): Não\n27 - IDENTIFICAÇÃO E CONTACTOS DO ÓRGÃO DE RECURSOS ADMINISTRATIVOS\nDesignação: Direção da Escola Profissional Alternância\nEndereço: RUA LUÍSA TODY\nCódigo postal: 4465-196\nLocalidade: Matosinhos\nTelefone: +351 918606461\nFax: +351 229538410\nEndereço eletrónico: alternancia.contratacaopublica@gmail.com\n28 - IDENTIFICAÇÃO DO(S) AUTOR(ES) DE ANÚNCIO\nNome: ANA MARIA DA ROCHA MENDES\nCargo: Colaboradora \n419948008",
    "nipc": "501462244",
    "distrito": "Porto",
    "concelho": "Matosinhos",
    "freguesia": "União das Freguesias de São Mamede de Infesta e Senhora da Hora",
    "site": "https://alternancia.edu.pt/",
    "email": "geral@alternancia.mail.pt",
    "designacao_contrato": "Empreitada de Remodelação de Instalações - Centro Tecnológico Industrial, Escola Profissional Alternância",
    "descricao": "Empreitada de Remodelação de Instalações - Centro Tecnológico Industrial, Escola Profissional Alternância",
    "preco_base": "655.589,24 EUR",
    "prazo_execucao": "2 MESES",
    "prazo_apresentacao_propostas": "23-01-2026 23:59",
    "fundos_eu": "Sim",
    "plataforma_eletronica": "VORTAL",
    "url_procedimento": "https://community.vortal.biz/public/",
    "autor_nome": "ANA MARIA DA ROCHA MENDES",
    "autor_cargo": "Colaboradora"
  },
  {
    "numero_procedimento": "N/A",
    "entidade": "Ordem dos Médicos",
    "link": "https://diariodarepublica.pt/dr/detalhe/contrato-publico/956-1014197071",
    "detalhes_completos": "1 - IDENTIFICAÇÃO E CONTACTOS DA ENTIDADE ADJUDICANTE\nDesignação da entidade adjudicante: Ordem dos Médicos\nNIPC: 500984492\nServiço/Órgão/Pessoa de contacto: Conselho Regional do Norte da Ordem dos Médicos\nEndereço: Rua Delfim Maia, 405\nCódigo postal: 4200-256\nLocalidade: Porto\nPaís: Portugal\nNUT III: PT11A\nDistrito: Porto\nConcelho: Porto\nFreguesia: Freguesia de Paranhos - Porto\nTelefone: 225070100\nFax: 218427199\nEndereço da Entidade (URL): https://nortemedico.pt/\nEndereço Eletrónico: sara.ferreira@nortemedico.pt\neDelivery Gateway (URL): https://www.acingov.pt\nFunção da Organização: Adquirente\nNorma jurídica da Entidade Adjudicante: Organismo de direito público\nÁrea de atividade da Autoridade Adjudicante: Serviços públicos das administrações públicas\n2 - JORNAL OFICIAL DA UNIÃO EUROPEIA\nO procedimento a que este anúncio diz respeito também é publicitado no Jornal Oficial da União Europeia? Não\n3 - AVISO\nModelo de Anúncio: Concurso público\nData de Envio do Anúncio: 16-01-2026\n5 - PROCESSO\nTipo de Procedimento: Concurso público\nPreço base do procedimento: Sim\nValor do preço base do procedimento: 50.000,00 EUR\nProcedimento com lotes? Não\n6 - OBJETO DO CONTRATO\nNúmero de referência interna: CP/1/2026\nDesignação do contrato: Aquisição de serviços de Assessoria Jurídica, pela SRNOM\nDescrição: Aquisição de serviços de assessoria jurídica na área da contratação pública e do direito administrativo e laboral, entre outras, em regime de bolsa de horas.\nTipo de Contrato Principal: Aquisição de Serviços\nTipo de Contrato: Aquisição de Serviços\nClassificação CPV (Vocabulário Comum para os Contratos Públicos)\nObjeto principal\nVocabulário Principal: 79111000\nPreço base s/IVA: 50.000,00 EUR\n7 - INDICAÇÕES ADICIONAIS\nO contrato envolve aquisição conjunta (satisfação de várias entidades)? Não\nO contrato é adjudicado por uma central de compras? Não\n8 - TÉCNICAS\nO concurso destina-se à celebração de um acordo-quadro? Inexistência de acordo-quadro\nÉ utilizado um leilão eletrónico? Não\nÉ adotada uma fase de negociação? Não\nSistema de Aquisição Dinâmico: Inexistência de sistema de aquisição dinâmico\n9 - LOCAL DA EXECUÇÃO DO CONTRATO\nLOCAL DA EXECUÇÃO DO CONTRATO (PROCEDIMENTO)\nPaís: Portugal\nNUT III: PT11A\nLocalidade: Freguesia de Paranhos - Porto\nDistrito: Porto\nConcelho: Porto\nFreguesia: Freguesia de Paranhos - Porto\n10 - PRAZO DE EXECUÇÃO DO CONTRATO\nPrazo de execução do contrato: 36 MESES\nPrevisão de renovações: Não\n11 - FUNDOS EU\nTêm fundos EU? Não\n12 - DOCUMENTOS DE HABILITAÇÃO\nHabilitação para o exercício da atividade profissional: Sim\nTipo: Ordem Profissional\nDescrição: Ordem dos Advogados\n13 - CONDIÇÕES DE APRESENTAÇÃO\nPlataforma eletrónica utilizada pela entidade adjudicante: ACIN\nURL para Apresentação: https://www.acingov.pt\nAdmissibilidade da apresentação de propostas variantes: Não autorizado\nPrazo para apresentação das propostas: 22-01-2026 23:59\nPrazo durante o qual os concorrentes são obrigados a manter as respetivas propostas: 99 dias a contar do termo do prazo para a apresentação das propostas\nIndicação de Subcontratação na Proposta: Inexistência de indicação de subcontratação\n14 - PRESTAÇÃO DE CAUÇÃO\nPrestação de caução: Não\n15 - FORNECIMENTO DAS PEÇAS DO CONCURSO, APRESENTAÇÃO DE PEDIDOS DE PARTICIPAÇÃO E APRESENTAÇÃO DAS PROPOSTAS\nLink para acesso às peças do concurso (URL): https://www.acingov.pt/acingovprod/2/zonaPublica/zona_publica_c/donwloadProcedurePiece/MTA0Nzc2OA==\n20 - OUTROS REQUISITOS\nInformação sobre contratos reservados. Aplica-se a contratos reservados (54º-A)? Não\n21 - CRITÉRIO DE ADJUDICAÇÃO\nMultifator: Sim\nFator: \nNome: Preço\nPonderação: 40%\nSubfatores: Não\nFator: \nNome: Outros\nOutro Nome: Experiência específica em contratação pública dos membros da equipa\nPonderação: 30%\nSubfatores: Não\nFator: \nNome: Outros\nOutro Nome: Qualificação dos membros da equipa\nPonderação: 30%\nSubfatores: Não\n24 - CONDIÇÕES DO CONTRATO\nFaturação Eletrónica: Não autorizado\nObrigação de Subcontratação:\nCódigo da Obrigação de Subcontratação: Não é aplicável nenhuma obrigação de subcontratação.\n25 - COMPRA PÚBLICA ESTRATÉGICA\nCompra Pública Estratégica: Inexistência de contratação pública estratégica\n26 - INFORMAÇÕES ADICIONAIS\nContrato adequado para PME: Sim\nCobertura ACP (Acordo dos Contratos Públicos da Organização Mundial do Comércio): Não\n27 - IDENTIFICAÇÃO E CONTACTOS DO ÓRGÃO DE RECURSOS ADMINISTRATIVOS\nDesignação: Conselho Superior da Ordem dos Médicos\nEndereço: Avenida Almirante Gago Coutinho, 151\nCódigo postal: 1749-084\nLocalidade: Lisboa\nTelefone: 211517100\nFax: \nEndereço eletrónico: ordemdosmedicos@ordemdosmedicos.pt\nPrazo de interposição do recurso: 30 dias\n28 - IDENTIFICAÇÃO DO(S) AUTOR(ES) DE ANÚNCIO\nNome: Helena Maria Chaves Aires Ferreira\nCargo: Chefe de Serviço\n419948123",
    "nipc": "500984492",
    "distrito": "Porto",
    "concelho": "Porto",
    "freguesia": "Freguesia de Paranhos - Porto",
    "site": "https://nortemedico.pt/",
    "email": "sara.ferreira@nortemedico.pt",
    "designacao_contrato": "Aquisição de serviços de Assessoria Jurídica, pela SRNOM",
    "descricao": "Aquisição de serviços de assessoria jurídica na área da contratação pública e do direito administrativo e laboral, entre outras, em regime de bolsa de horas.",
    "preco_base": "50.000,00 EUR",
    "prazo_execucao": "36 MESES",
    "prazo_apresentacao_propostas": "22-01-2026 23:59",
    "fundos_eu": "Não",
    "plataforma_eletronica": "ACIN",
    "url_procedimento": "https://www.acingov.pt",
    "autor_nome": "Helena Maria Chaves Aires Ferreira",
    "autor_cargo": "Chefe de Serviço"
  },
  {
    "numero_procedimento": "N/A",
    "entidade": "Universidade de Aveiro",
    "link": "https://diariodarepublica.pt/dr/detalhe/contrato-publico/958-1014253275",
    "detalhes_completos": "1 - IDENTIFICAÇÃO E CONTACTOS DA ENTIDADE ADJUDICANTE\nDesignação da entidade adjudicante: Universidade de Aveiro\nNIPC: 501461108\nServiço/Órgão/Pessoa de contacto: Ana Isabel Pires Sousa da Silva Braga\nEndereço: Campus Universitário de Santiago, Edif.25\nCódigo postal: 3810-193\nLocalidade: Aveiro\nPaís: Portugal\nNUT III: PT16D\nDistrito: Aveiro\nConcelho: Aveiro\nFreguesia: Todas\nTelefone: 234370200\nFax: 234372432\nEndereço da Entidade (URL): https://www.ua.pt/\nEndereço Eletrónico: contratacao@ua.pt\neDelivery Gateway (URL): https://www.acingov.pt\nFunção da Organização: Adquirente\nSubfunção da Organização: Organização que recebe as propostas\nNorma jurídica da Entidade Adjudicante: Organismo de direito público\nÁrea de atividade da Autoridade Adjudicante: Serviços públicos das administrações públicas\n2 - JORNAL OFICIAL DA UNIÃO EUROPEIA\nO procedimento a que este anúncio diz respeito também é publicitado no Jornal Oficial da União Europeia? Não\n3 - AVISO\nModelo de Anúncio: Concurso público\nData de Envio do Anúncio: 16-01-2026\n5 - PROCESSO\nTipo de Procedimento: Concurso público\nPreço base do procedimento: Sim\nValor do preço base do procedimento: 21.858,00 EUR\nProcedimento com lotes? Não\n6 - OBJETO DO CONTRATO\nNúmero de referência interna: CP n.º481 - AAC/STIC - 11/25\nDesignação do contrato: Aquisição do licenciamento SPSS, por 3 anos, para a Universidade de Aveiro\nDescrição: Aquisição do licenciamento SPSS, por 3 anos, para a Universidade de Aveiro\nTipo de Contrato Principal: Aquisição de Bens Móveis\nTipo de Contrato: Aquisição de Bens Móveis\nClassificação CPV (Vocabulário Comum para os Contratos Públicos)\nObjeto principal\nVocabulário Principal: 48190000\nPreço base s/IVA: 21.858,00 EUR\n7 - INDICAÇÕES ADICIONAIS\nO contrato envolve aquisição conjunta (satisfação de várias entidades)? Não\nO contrato é adjudicado por uma central de compras? Não\n8 - TÉCNICAS\nO concurso destina-se à celebração de um acordo-quadro? Inexistência de acordo-quadro\nÉ utilizado um leilão eletrónico? Não\nÉ adotada uma fase de negociação? Não\nSistema de Aquisição Dinâmico: Inexistência de sistema de aquisição dinâmico\n9 - LOCAL DA EXECUÇÃO DO CONTRATO\nLOCAL DA EXECUÇÃO DO CONTRATO (PROCEDIMENTO)\nPaís: Portugal\nNUT III: PT16D\nLocalidade: União das Freguesias de Glória e Vera Cruz\nDistrito: Aveiro\nConcelho: Aveiro\nFreguesia: União das Freguesias de Glória e Vera Cruz\n10 - PRAZO DE EXECUÇÃO DO CONTRATO\nPrazo de execução do contrato: 3 ANOS\nPrevisão de renovações: Não\n11 - FUNDOS EU\nTêm fundos EU? Não\n12 - DOCUMENTOS DE HABILITAÇÃO\nHabilitação para o exercício da atividade profissional: Não\n13 - CONDIÇÕES DE APRESENTAÇÃO\nPlataforma eletrónica utilizada pela entidade adjudicante: ACIN\nURL para Apresentação: https://www.acingov.pt\nAdmissibilidade da apresentação de propostas variantes: Não autorizado\nPrazo para apresentação das propostas: 22-01-2026 23:59\nPrazo durante o qual os concorrentes são obrigados a manter as respetivas propostas: 132 dias a contar do termo do prazo para a apresentação das propostas\nIndicação de Subcontratação na Proposta: Inexistência de indicação de subcontratação\n14 - PRESTAÇÃO DE CAUÇÃO\nPrestação de caução: Não\n15 - FORNECIMENTO DAS PEÇAS DO CONCURSO, APRESENTAÇÃO DE PEDIDOS DE PARTICIPAÇÃO E APRESENTAÇÃO DAS PROPOSTAS\nLink para acesso às peças do concurso (URL): https://www.acingov.pt/acingovprod/2/zonaPublica/zona_publica_c/donwloadProcedurePiece/MTA0ODU0MQ==\n20 - OUTROS REQUISITOS\nInformação sobre contratos reservados. Aplica-se a contratos reservados (54º-A)? Não\n21 - CRITÉRIO DE ADJUDICAÇÃO\nMultifator: Não\nMonofator:\nNome: Preço\n24 - CONDIÇÕES DO CONTRATO\nFaturação Eletrónica: Necessário\nObrigação de Subcontratação:\nCódigo da Obrigação de Subcontratação: Não é aplicável nenhuma obrigação de subcontratação.\n25 - COMPRA PÚBLICA ESTRATÉGICA\nCompra Pública Estratégica: Inexistência de contratação pública estratégica\n26 - INFORMAÇÕES ADICIONAIS\nContrato adequado para PME: Sim\nCobertura ACP (Acordo dos Contratos Públicos da Organização Mundial do Comércio): Não\n27 - IDENTIFICAÇÃO E CONTACTOS DO ÓRGÃO DE RECURSOS ADMINISTRATIVOS\nDesignação: Reitor da Universidade de Aveiro\nEndereço: Campus Universitário de Santiago, Edif.25\nCódigo postal: 3810-193\nLocalidade: Aveiro\nTelefone: 234370200\nFax: 234372434\nEndereço eletrónico: contratacao@ua.pt\n28 - IDENTIFICAÇÃO DO(S) AUTOR(ES) DE ANÚNCIO\nNome: Ana Isabel Pires Sousa da Silva Braga\nCargo: Chefe de Divisão da Área de Aquisições e Contratos\n419948189",
    "nipc": "501461108",
    "distrito": "Aveiro",
    "concelho": "Aveiro",
    "freguesia": "Todas",
    "site": "https://www.ua.pt/",
    "email": "contratacao@ua.pt",
    "designacao_contrato": "Aquisição do licenciamento SPSS, por 3 anos, para a Universidade de Aveiro",
    "descricao": "Aquisição do licenciamento SPSS, por 3 anos, para a Universidade de Aveiro",
    "preco_base": "21.858,00 EUR",
    "prazo_execucao": "3 ANOS",
    "prazo_apresentacao_propostas": "22-01-2026 23:59",
    "fundos_eu": "Não",
    "plataforma_eletronica": "ACIN",
    "url_procedimento": "https://www.acingov.pt",
    "autor_nome": "Ana Isabel Pires Sousa da Silva Braga",
    "autor_cargo": "Chefe de Divisão da Área de Aquisições e Contratos"
  },
  {
    "numero_procedimento": "N/A",
    "entidade": "Unidade Local de Saúde do Tâmega e Sousa, EPE",
    "link": "https://diariodarepublica.pt/dr/detalhe/contrato-publico/959-1014253276",
    "detalhes_completos": "1 - IDENTIFICAÇÃO E CONTACTOS DA ENTIDADE ADJUDICANTE\nDesignação da entidade adjudicante: Unidade Local de Saúde do Tâmega e Sousa, EPE\nNIPC: 508318262\nEndereço: Avenida Padre Américo, Nº210\nCódigo postal: 4560-136\nLocalidade: Porto\nPaís: Portugal\nNUT III: PT11C\nDistrito: Porto\nConcelho: Penafiel\nFreguesia: Todas\nTelefone: 255714000\nEndereço da Entidade (URL): www.chtamegasousa.pt\nEndereço Eletrónico: concursos@chts.min-saude.pt\neDelivery Gateway (URL): https://community.vortal.biz/public/\nFunção da Organização: Adquirente\nNorma jurídica da Entidade Adjudicante: Empresa pública\nÁrea de atividade da Autoridade Adjudicante: Saúde\n2 - JORNAL OFICIAL DA UNIÃO EUROPEIA\nO procedimento a que este anúncio diz respeito também é publicitado no Jornal Oficial da União Europeia? Não\n3 - AVISO\nModelo de Anúncio: Concurso público\nData de Envio do Anúncio: 16-01-2026\n5 - PROCESSO\nTipo de Procedimento: Concurso público\nPreço base do procedimento: Sim\nValor do preço base do procedimento: 19.500,00 EUR\nProcedimento com lotes? Não\n6 - OBJETO DO CONTRATO\nNúmero de referência interna: 08/CP.25.2353\nDesignação do contrato: Prestação de Serviços de Meios Complementares de Diagnóstico e Terapêutica - Exames Vestibulares\nDescrição: Prestação de Serviços de Meios Complementares de Diagnóstico e Terapêutica - Exames Vestibulares\nTipo de Contrato Principal: Aquisição de Serviços\nTipo de Contrato: Aquisição de Serviços\nClassificação CPV (Vocabulário Comum para os Contratos Públicos)\nObjeto principal\nVocabulário Principal: 85121240\nPreço base s/IVA: 19.500,00 EUR\n7 - INDICAÇÕES ADICIONAIS\nO contrato envolve aquisição conjunta (satisfação de várias entidades)? Não\nO contrato é adjudicado por uma central de compras? Não\n8 - TÉCNICAS\nO concurso destina-se à celebração de um acordo-quadro? Inexistência de acordo-quadro\nÉ utilizado um leilão eletrónico? Não\nÉ adotada uma fase de negociação? Não\nSistema de Aquisição Dinâmico: Inexistência de sistema de aquisição dinâmico\n9 - LOCAL DA EXECUÇÃO DO CONTRATO\nLOCAL DA EXECUÇÃO DO CONTRATO (PROCEDIMENTO)\nPaís: Portugal\nNUT III: PT11C\nLocalidade: Porto\nDistrito: Porto\nConcelho: Penafiel\nFreguesia: Freguesia de Guilhufe e Urrô\n10 - PRAZO DE EXECUÇÃO DO CONTRATO\nPrazo de execução do contrato: 12 MESES\nPrevisão de renovações: Não\n11 - FUNDOS EU\nTêm fundos EU? Não\n12 - DOCUMENTOS DE HABILITAÇÃO\nHabilitação para o exercício da atividade profissional: Não\n13 - CONDIÇÕES DE APRESENTAÇÃO\nPlataforma eletrónica utilizada pela entidade adjudicante: VORTAL\nURL para Apresentação: https://community.vortal.biz/public/\nAdmissibilidade da apresentação de propostas variantes: Não autorizado\nPrazo para apresentação das propostas: 25-01-2026 17:00\nPrazo durante o qual os concorrentes são obrigados a manter as respetivas propostas: 180 dias a contar do termo do prazo para a apresentação das propostas\nIndicação de Subcontratação na Proposta: Inexistência de indicação de subcontratação\n14 - PRESTAÇÃO DE CAUÇÃO\nPrestação de caução: Não\n15 - FORNECIMENTO DAS PEÇAS DO CONCURSO, APRESENTAÇÃO DE PEDIDOS DE PARTICIPAÇÃO E APRESENTAÇÃO DAS PROPOSTAS\nLink para acesso às peças do concurso (URL): https://community.vortal.biz/Public/public-tender-documents/R2dRdFA4VXpOVGl5ellQZENxT3dwZWhVaEhzSmlYQzQ0MWtNNWZZVVBTZ3V4QndDRnRtUEJ1Qy9oVmNGVlcrUFZKaGUyUkhLRVRQY3RobTlrbXpOWHc9PXdudChY\n20 - OUTROS REQUISITOS\nInformação sobre contratos reservados. Aplica-se a contratos reservados (54º-A)? Não\n21 - CRITÉRIO DE ADJUDICAÇÃO\nMultifator: Não\nMonofator:\nNome: Outros\nOutro nome: Preço\n24 - CONDIÇÕES DO CONTRATO\nFaturação Eletrónica: Permitido\nObrigação de Subcontratação:\nCódigo da Obrigação de Subcontratação: Não é aplicável nenhuma obrigação de subcontratação.\n25 - COMPRA PÚBLICA ESTRATÉGICA\nCompra Pública Estratégica: Inexistência de contratação pública estratégica\n26 - INFORMAÇÕES ADICIONAIS\nContrato adequado para PME: Sim\nCobertura ACP (Acordo dos Contratos Públicos da Organização Mundial do Comércio): Não\n27 - IDENTIFICAÇÃO E CONTACTOS DO ÓRGÃO DE RECURSOS ADMINISTRATIVOS\nDesignação: ULSTS\nEndereço: Avenida do Hospital Padre Américo, nº 210\nCódigo postal: 4560-136\nLocalidade: Penafiel\nTelefone: +351 255714000\nFax: +351 255714000\nEndereço eletrónico: administracao@ulsts.min-saude.pt\n28 - IDENTIFICAÇÃO DO(S) AUTOR(ES) DE ANÚNCIO\nNome: Unidade Local de Saúde do Tâmega e Sousa\nCargo: Serviço de Compras\n419948045",
    "nipc": "508318262",
    "distrito": "Porto",
    "concelho": "Penafiel",
    "freguesia": "Todas",
    "site": "www.chtamegasousa.pt",
    "email": "concursos@chts.min-saude.pt",
    "designacao_contrato": "Prestação de Serviços de Meios Complementares de Diagnóstico e Terapêutica - Exames Vestibulares",
    "descricao": "Prestação de Serviços de Meios Complementares de Diagnóstico e Terapêutica - Exames Vestibulares",
    "preco_base": "19.500,00 EUR",
    "prazo_execucao": "12 MESES",
    "prazo_apresentacao_propostas": "25-01-2026 17:00",
    "fundos_eu": "Não",
    "plataforma_eletronica": "VORTAL",
    "url_procedimento": "https://community.vortal.biz/public/",
    "autor_nome": "Unidade Local de Saúde do Tâmega e Sousa",
    "autor_cargo": "Serviço de Compras"
  },
  {
    "numero_procedimento": "N/A",
    "entidade": "Fundação Santo António",
    "link": "https://diariodarepublica.pt/dr/detalhe/contrato-publico/960-1014253278",
    "detalhes_completos": "1 - IDENTIFICAÇÃO E CONTACTOS DA ENTIDADE ADJUDICANTE\nDesignação da entidade adjudicante: Fundação Santo António\nNIPC: 504142992\nServiço/Órgão/Pessoa de contacto: Direção\nEndereço: Rua de Santa Maria, n.º 914\nCódigo postal: 4625-622\nLocalidade: Marco de Canaveses\nPaís: Portugal\nNUT III: PT11C\nDistrito: Porto\nConcelho: Marco de Canaveses\nFreguesia: Todas\nTelefone: 255580990\nEndereço da Entidade (URL): https://www.fundacaosantoantonio.pt/\nEndereço Eletrónico: fundacaosantoantonio@gmail.com\neDelivery Gateway (URL): https://www.acingov.pt\nFunção da Organização: Adquirente\nNorma jurídica da Entidade Adjudicante: Organismo de direito público\nÁrea de atividade da Autoridade Adjudicante: Serviços públicos das administrações públicas\n2 - JORNAL OFICIAL DA UNIÃO EUROPEIA\nO procedimento a que este anúncio diz respeito também é publicitado no Jornal Oficial da União Europeia? Não\n3 - AVISO\nModelo de Anúncio: Concurso público\nData de Envio do Anúncio: 16-01-2026\n5 - PROCESSO\nTipo de Procedimento: Concurso público\nPreço base do procedimento: Sim\nValor do preço base do procedimento: 499.950,00 EUR\nProcedimento com lotes? Não\n6 - OBJETO DO CONTRATO\nNúmero de referência interna: CP/1/2026\nDesignação do contrato: CP n.º 1/2026\nDescrição: CP n.º 1/2026\nTipo de Contrato Principal: Empreitada de Obras Públicas\nTipo de Contrato: Empreitada de Obras Públicas\nClassificação CPV (Vocabulário Comum para os Contratos Públicos)\nObjeto principal\nVocabulário Principal: 45000000\nPreço base s/IVA: 499.950,00 EUR\n7 - INDICAÇÕES ADICIONAIS\nO contrato envolve aquisição conjunta (satisfação de várias entidades)? Não\nO contrato é adjudicado por uma central de compras? Não\n8 - TÉCNICAS\nO concurso destina-se à celebração de um acordo-quadro? Inexistência de acordo-quadro\nÉ utilizado um leilão eletrónico? Não\nÉ adotada uma fase de negociação? Não\nSistema de Aquisição Dinâmico: Inexistência de sistema de aquisição dinâmico\n9 - LOCAL DA EXECUÇÃO DO CONTRATO\nLOCAL DA EXECUÇÃO DO CONTRATO (PROCEDIMENTO)\nPaís: Portugal\nNUT III: PT11C\nLocalidade: Freguesia de Vila Boa do Bispo\nDistrito: Porto\nConcelho: Marco de Canaveses\nFreguesia: Freguesia de Vila Boa do Bispo\n10 - PRAZO DE EXECUÇÃO DO CONTRATO\nPrazo de execução do contrato: 4 MESES\nPrevisão de renovações: Não\n11 - FUNDOS EU\nTêm fundos EU? Não\n12 - DOCUMENTOS DE HABILITAÇÃO\nHabilitação para o exercício da atividade profissional: Sim\nTipo: Alvará\nDescrição: Classe 3 para as subcategorias 1ª, 3ª e 6ª da 1ª Categoria.\n13 - CONDIÇÕES DE APRESENTAÇÃO\nPlataforma eletrónica utilizada pela entidade adjudicante: ACIN\nURL para Apresentação: https://www.acingov.pt\nAdmissibilidade da apresentação de propostas variantes: Não autorizado\nPrazo para apresentação das propostas: 31-01-2026 16:30\nPrazo durante o qual os concorrentes são obrigados a manter as respetivas propostas: 66 dias a contar do termo do prazo para a apresentação das propostas\nIndicação de Subcontratação na Proposta: Inexistência de indicação de subcontratação\n14 - PRESTAÇÃO DE CAUÇÃO\nPrestação de caução: Não\n15 - FORNECIMENTO DAS PEÇAS DO CONCURSO, APRESENTAÇÃO DE PEDIDOS DE PARTICIPAÇÃO E APRESENTAÇÃO DAS PROPOSTAS\nLink para acesso às peças do concurso (URL): https://www.acingov.pt/acingovprod/2/zonaPublica/zona_publica_c/donwloadProcedurePiece/MTA0OTA3Mw==\n20 - OUTROS REQUISITOS\nInformação sobre contratos reservados. Aplica-se a contratos reservados (54º-A)? Não\n21 - CRITÉRIO DE ADJUDICAÇÃO\nMultifator: Não\nMonofator:\nNome: Preço\n24 - CONDIÇÕES DO CONTRATO\nFaturação Eletrónica: Não autorizado\nObrigação de Subcontratação:\nCódigo da Obrigação de Subcontratação: Não é aplicável nenhuma obrigação de subcontratação.\n25 - COMPRA PÚBLICA ESTRATÉGICA\nCompra Pública Estratégica: Inexistência de contratação pública estratégica\n26 - INFORMAÇÕES ADICIONAIS\nContrato adequado para PME: Não\nCobertura ACP (Acordo dos Contratos Públicos da Organização Mundial do Comércio): Não\n27 - IDENTIFICAÇÃO E CONTACTOS DO ÓRGÃO DE RECURSOS ADMINISTRATIVOS\nDesignação: Direção\nEndereço: Rua de Santa Maria, n.º 914\nCódigo postal: 4625-622\nLocalidade: Marco de Canaveses\nTelefone: 255580990\nFax: 000000000\nEndereço eletrónico: fundacaosantoantonio@gmail.com\n28 - IDENTIFICAÇÃO DO(S) AUTOR(ES) DE ANÚNCIO\nNome: Manuel António Moreira\nCargo: Presidente\n419948197",
    "nipc": "504142992",
    "distrito": "Porto",
    "concelho": "Marco de Canaveses",
    "freguesia": "Todas",
    "site": "https://www.fundacaosantoantonio.pt/",
    "email": "fundacaosantoantonio@gmail.com",
    "designacao_contrato": "CP n.º 1/2026",
    "descricao": "CP n.º 1/2026",
    "preco_base": "499.950,00 EUR",
    "prazo_execucao": "4 MESES",
    "prazo_apresentacao_propostas": "31-01-2026 16:30",
    "fundos_eu": "Não",
    "plataforma_eletronica": "ACIN",
    "url_procedimento": "https://www.acingov.pt",
    "autor_nome": "Manuel António Moreira",
    "autor_cargo": "Presidente"
  },
  {
    "numero_procedimento": "N/A",
    "entidade": "Empresa Municipal de Ambiente do Porto, EM, SA",
    "link": "https://diariodarepublica.pt/dr/detalhe/contrato-publico/961-1014253279",
    "detalhes_completos": "1 - IDENTIFICAÇÃO E CONTACTOS DA ENTIDADE ADJUDICANTE\nDesignação da entidade adjudicante: Empresa Municipal de Ambiente do Porto, EM, SA\nNIPC: 514280956\nServiço/Órgão/Pessoa de contacto: Compras, Aprovisionamento e Fontes de Financiamento\nEndereço: Rua de S. Dinis, n.º 249\nCódigo postal: 4250-434\nLocalidade: PORTO\nPaís: Portugal\nNUT III: PT11A\nDistrito: Porto\nConcelho: Porto\nFreguesia: Todas\nTelefone: 228348770\nFax: 228348770\nEndereço da Entidade (URL): www.portoambiente.pt\nEndereço Eletrónico: geral@portoambiente.pt\neDelivery Gateway (URL): https://www.acingov.pt\nFunção da Organização: Adquirente\nNorma jurídica da Entidade Adjudicante: Empresa pública\nÁrea de atividade da Autoridade Adjudicante: Serviços públicos das administrações públicas\n2 - JORNAL OFICIAL DA UNIÃO EUROPEIA\nO procedimento a que este anúncio diz respeito também é publicitado no Jornal Oficial da União Europeia? Não\n3 - AVISO\nModelo de Anúncio: Concurso público\nData de Envio do Anúncio: 16-01-2026\n5 - PROCESSO\nTipo de Procedimento: Concurso público\nPreço base do procedimento: Sim\nValor do preço base do procedimento: 24.220,00 EUR\nProcedimento com lotes? Não\n6 - OBJETO DO CONTRATO\nNúmero de referência interna: CP/1/2026/EMAP\nDesignação do contrato: Aquisição de serviços de capacitação de pessoas no diagnóstico e reparação de equipamentos informáticos e de ferramentas e peças\nDescrição: Aquisição de serviços de capacitação de pessoas no diagnóstico e reparação de equipamentos informáticos e de ferramentas e peças\nTipo de Contrato Principal: Aquisição de Bens Móveis\nTipo de Contrato: Aquisição de Bens Móveis\nClassificação CPV (Vocabulário Comum para os Contratos Públicos)\nObjeto principal\nVocabulário Principal: 30200000\nPreço base s/IVA: 24.220,00 EUR\n7 - INDICAÇÕES ADICIONAIS\nO contrato envolve aquisição conjunta (satisfação de várias entidades)? Não\nO contrato é adjudicado por uma central de compras? Não\n8 - TÉCNICAS\nO concurso destina-se à celebração de um acordo-quadro? Inexistência de acordo-quadro\nÉ utilizado um leilão eletrónico? Não\nÉ adotada uma fase de negociação? Não\nSistema de Aquisição Dinâmico: Inexistência de sistema de aquisição dinâmico\n9 - LOCAL DA EXECUÇÃO DO CONTRATO\nLOCAL DA EXECUÇÃO DO CONTRATO (PROCEDIMENTO)\nPaís: Portugal\nNUT III: PT11A\nLocalidade: PORTO\nDistrito: Porto\nConcelho: Porto\nFreguesia: Todas\n10 - PRAZO DE EXECUÇÃO DO CONTRATO\nPrazo de execução do contrato: 12 MESES\nPrevisão de renovações: Não\n11 - FUNDOS EU\nTêm fundos EU? Não\n12 - DOCUMENTOS DE HABILITAÇÃO\nHabilitação para o exercício da atividade profissional: Não\n13 - CONDIÇÕES DE APRESENTAÇÃO\nPlataforma eletrónica utilizada pela entidade adjudicante: ACIN\nURL para Apresentação: https://www.acingov.pt\nAdmissibilidade da apresentação de propostas variantes: Não autorizado\nPrazo para apresentação das propostas: 23-01-2026 17:00\nPrazo durante o qual os concorrentes são obrigados a manter as respetivas propostas: 66 dias a contar do termo do prazo para a apresentação das propostas\nIndicação de Subcontratação na Proposta: Inexistência de indicação de subcontratação\n14 - PRESTAÇÃO DE CAUÇÃO\nPrestação de caução: Não\n15 - FORNECIMENTO DAS PEÇAS DO CONCURSO, APRESENTAÇÃO DE PEDIDOS DE PARTICIPAÇÃO E APRESENTAÇÃO DAS PROPOSTAS\nLink para acesso às peças do concurso (URL): https://www.acingov.pt/acingovprod/2/zonaPublica/zona_publica_c/donwloadProcedurePiece/MTA0ODkyMg==\n20 - OUTROS REQUISITOS\nInformação sobre contratos reservados. Aplica-se a contratos reservados (54º-A)? Não\n21 - CRITÉRIO DE ADJUDICAÇÃO\nMultifator: Não\nMonofator:\nNome: Outros\nOutro nome: Fator Preço\n24 - CONDIÇÕES DO CONTRATO\nFaturação Eletrónica: Permitido\nObrigação de Subcontratação:\nCódigo da Obrigação de Subcontratação: Não é aplicável nenhuma obrigação de subcontratação.\n25 - COMPRA PÚBLICA ESTRATÉGICA\nCompra Pública Estratégica: Inexistência de contratação pública estratégica\n26 - INFORMAÇÕES ADICIONAIS\nContrato adequado para PME: Sim\nCobertura ACP (Acordo dos Contratos Públicos da Organização Mundial do Comércio): Não\n27 - IDENTIFICAÇÃO E CONTACTOS DO ÓRGÃO DE RECURSOS ADMINISTRATIVOS\nDesignação: Conselho de Administração da Porto Ambiente\nEndereço: Rua de S. Dinis, n.º 249\nCódigo postal: 4250-434\nLocalidade: PORTO\nTelefone: 228348770\nFax: 228348770\nEndereço eletrónico: geral@portoambiente.pt\nPrazo de interposição do recurso: 10 dias\n28 - IDENTIFICAÇÃO DO(S) AUTOR(ES) DE ANÚNCIO\nNome: Carla Fernanda Lage da Cruz Santos\nCargo: Técnica Superior\n419948155",
    "nipc": "514280956",
    "distrito": "Porto",
    "concelho": "Porto",
    "freguesia": "Todas",
    "site": "www.portoambiente.pt",
    "email": "geral@portoambiente.pt",
    "designacao_contrato": "Aquisição de serviços de capacitação de pessoas no diagnóstico e reparação de equipamentos informáticos e de ferramentas e peças",
    "descricao": "Aquisição de serviços de capacitação de pessoas no diagnóstico e reparação de equipamentos informáticos e de ferramentas e peças",
    "preco_base": "24.220,00 EUR",
    "prazo_execucao": "12 MESES",
    "prazo_apresentacao_propostas": "23-01-2026 17:00",
    "fundos_eu": "Não",
    "plataforma_eletronica": "ACIN",
    "url_procedimento": "https://www.acingov.pt",
    "autor_nome": "Carla Fernanda Lage da Cruz Santos",
    "autor_cargo": "Técnica Superior"
  },
  {
    "numero_procedimento": "N/A",
    "entidade": "Unidade Local de Saúde da Lezíria, EPE",
    "link": "https://diariodarepublica.pt/dr/detalhe/contrato-publico/964-1014253289",
    "detalhes_completos": "1 - IDENTIFICAÇÃO E CONTACTOS DA ENTIDADE ADJUDICANTE\nDesignação da entidade adjudicante: Unidade Local de Saúde da Lezíria, EPE\nNIPC: 506361462\nEndereço: Av. Bernardo Santareno S/N\nCódigo postal: 2005-177\nLocalidade: Santarém\nPaís: Portugal\nNUT III: PT185\nDistrito: Santarém\nConcelho: Santarém\nFreguesia: União de Freguesias da Cidade de Santarém\nTelefone: 243300200\nFax: 243370220\nEndereço da Entidade (URL): www.hds.min-saude.pt\nEndereço Eletrónico: hdsca@hds.min-saude.pt\neDelivery Gateway (URL): https://community.vortal.biz/public/\nFunção da Organização: Adquirente\nNorma jurídica da Entidade Adjudicante: Organismo de direito público\nÁrea de atividade da Autoridade Adjudicante: Saúde\n2 - JORNAL OFICIAL DA UNIÃO EUROPEIA\nO procedimento a que este anúncio diz respeito também é publicitado no Jornal Oficial da União Europeia? Não\n3 - AVISO\nModelo de Anúncio: Concurso público\nData de Envio do Anúncio: 16-01-2026\n5 - PROCESSO\nTipo de Procedimento: Concurso público\nPreço base do procedimento: Sim\nValor do preço base do procedimento: 98.326,50 EUR\nProcedimento com lotes? Não\n6 - OBJETO DO CONTRATO\nNúmero de referência interna: 120026/2026\nDesignação do contrato: Aquisição de Sensores p/ Monitorização Anestésica c/ colocação de equipamentos em regime de comodato para os anos de 2026, 2027 e 2028 (36 meses)\nDescrição: Aquisição de Sensores p/ Monitorização Anestésica c/ colocação de equipamentos em regime de comodato para os anos de 2026, 2027 e 2028 (36 meses)\nTipo de Contrato Principal: Aquisição de Bens Móveis\nTipo de Contrato: Aquisição de Bens Móveis\nClassificação CPV (Vocabulário Comum para os Contratos Públicos)\nObjeto principal\nVocabulário Principal: 33140000\nPreço base s/IVA: 98.326,50 EUR\n7 - INDICAÇÕES ADICIONAIS\nO contrato envolve aquisição conjunta (satisfação de várias entidades)? Não\nO contrato é adjudicado por uma central de compras? Não\n8 - TÉCNICAS\nO concurso destina-se à celebração de um acordo-quadro? Inexistência de acordo-quadro\nÉ utilizado um leilão eletrónico? Não\nÉ adotada uma fase de negociação? Não\nSistema de Aquisição Dinâmico: Inexistência de sistema de aquisição dinâmico\n9 - LOCAL DA EXECUÇÃO DO CONTRATO\nLOCAL DA EXECUÇÃO DO CONTRATO (PROCEDIMENTO)\nPaís: Portugal\nNUT III: PTZZZ\nLocalidade: PORTUGAL\nDistrito: Todos\nConcelho: Todos\nFreguesia: Todas\n10 - PRAZO DE EXECUÇÃO DO CONTRATO\nPrazo de execução do contrato: 1096 DIAS\nPrevisão de renovações: Não\n11 - FUNDOS EU\nTêm fundos EU? Não\n12 - DOCUMENTOS DE HABILITAÇÃO\nHabilitação para o exercício da atividade profissional: Não\n13 - CONDIÇÕES DE APRESENTAÇÃO\nPlataforma eletrónica utilizada pela entidade adjudicante: VORTAL\nURL para Apresentação: https://community.vortal.biz/public/\nAdmissibilidade da apresentação de propostas variantes: Não autorizado\nPrazo para apresentação das propostas: 21-01-2026 23:59\nPrazo durante o qual os concorrentes são obrigados a manter as respetivas propostas: 66 dias a contar do termo do prazo para a apresentação das propostas\nIndicação de Subcontratação na Proposta: Inexistência de indicação de subcontratação\n14 - PRESTAÇÃO DE CAUÇÃO\nPrestação de caução: Não\n15 - FORNECIMENTO DAS PEÇAS DO CONCURSO, APRESENTAÇÃO DE PEDIDOS DE PARTICIPAÇÃO E APRESENTAÇÃO DAS PROPOSTAS\nLink para acesso às peças do concurso (URL): https://community.vortal.biz/Public/public-tender-documents/Y2dKNEdVbWFCQ3hEZi9hMWk2VktUajd5TExkdTE0OGVuQ3Exa25YaWtvY2ZDTkFwc0VkbXpjSXpYWnlYOWNtVG10UU85b3liOUtUd2huc0RVT2lnclE9PVNrUmNl\n20 - OUTROS REQUISITOS\nInformação sobre contratos reservados. Aplica-se a contratos reservados (54º-A)? Não\n21 - CRITÉRIO DE ADJUDICAÇÃO\nMultifator: Sim\nFator: \nNome: Preço\nPonderação: 60%\nSubfatores: Não\nFator: \nNome: Qualidade\nPonderação: 40%\nSubfatores: Não\n24 - CONDIÇÕES DO CONTRATO\nFaturação Eletrónica: Permitido\nObrigação de Subcontratação:\nCódigo da Obrigação de Subcontratação: Não é aplicável nenhuma obrigação de subcontratação.\n25 - COMPRA PÚBLICA ESTRATÉGICA\nCompra Pública Estratégica: Inexistência de contratação pública estratégica\n26 - INFORMAÇÕES ADICIONAIS\nContrato adequado para PME: Sim\nCobertura ACP (Acordo dos Contratos Públicos da Organização Mundial do Comércio): Não\n27 - IDENTIFICAÇÃO E CONTACTOS DO ÓRGÃO DE RECURSOS ADMINISTRATIVOS\nDesignação: Conselho de Administração da Unidade Local de Saúde da Lezíria, EPE\nEndereço: Av. Bernardo Santareno\nCódigo postal: 2005-177\nLocalidade: Santarém\nTelefone: +351 243300200\nFax: +351 243370220\nEndereço eletrónico: ca@ulsleziria.min-saude.pt\n28 - IDENTIFICAÇÃO DO(S) AUTOR(ES) DE ANÚNCIO\nNome: Pedro Manuel Dias de Figueiredo Pereira Marques\nCargo: Presidente do Conselho de Administração\n419948033",
    "nipc": "506361462",
    "distrito": "Santarém",
    "concelho": "Santarém",
    "freguesia": "União de Freguesias da Cidade de Santarém",
    "site": "www.hds.min-saude.pt",
    "email": "hdsca@hds.min-saude.pt",
    "designacao_contrato": "Aquisição de Sensores p/ Monitorização Anestésica c/ colocação de equipamentos em regime de comodato para os anos de 2026, 2027 e 2028 (36 meses)",
    "descricao": "Aquisição de Sensores p/ Monitorização Anestésica c/ colocação de equipamentos em regime de comodato para os anos de 2026, 2027 e 2028 (36 meses)",
    "preco_base": "98.326,50 EUR",
    "prazo_execucao": "1096 DIAS",
    "prazo_apresentacao_propostas": "21-01-2026 23:59",
    "fundos_eu": "Não",
    "plataforma_eletronica": "VORTAL",
    "url_procedimento": "https://community.vortal.biz/public/",
    "autor_nome": "Pedro Manuel Dias de Figueiredo Pereira Marques",
    "autor_cargo": "Presidente do Conselho de Administração"
  },
  {
    "numero_procedimento": "N/A",
    "entidade": "AnÃºncio de procedimento  n.Âº 966/2026  -  DiÃ¡rio da RepÃºblica n.Âº 11/2026, SÃ©rie II de 2026-01-16",
    "link": "https://diariodarepublica.pt/dr/detalhe/contrato-publico/966-1014253294"
  },
  {
    "numero_procedimento": "N/A",
    "entidade": "Serviços Partilhados do Ministério da Saúde, EPE",
    "link": "https://diariodarepublica.pt/dr/detalhe/contrato-publico/969-1014253326",
    "detalhes_completos": "1 - IDENTIFICAÇÃO E CONTACTOS DA ENTIDADE ADJUDICANTE\nDesignação da entidade adjudicante: Serviços Partilhados do Ministério da Saúde, EPE\nNIPC: 509540716\nEndereço: Avenida da República 61\nCódigo postal: 1050-189\nLocalidade: Lisboa\nPaís: Portugal\nNUT III: PT170\nDistrito: Lisboa\nConcelho: Lisboa\nFreguesia: Todas\nTelefone: 211545600\nFax: 211545649\nEndereço da Entidade (URL): www.spms.min-saude.pt/\nEndereço Eletrónico: contratacao@spms.min-saude.pt\neDelivery Gateway (URL): https://community.vortal.biz/public/\nFunção da Organização: Adquirente\nNorma jurídica da Entidade Adjudicante: Empresa pública\nÁrea de atividade da Autoridade Adjudicante: Saúde\n2 - JORNAL OFICIAL DA UNIÃO EUROPEIA\nO procedimento a que este anúncio diz respeito também é publicitado no Jornal Oficial da União Europeia? Não\n3 - AVISO\nModelo de Anúncio: Concurso público\nData de Envio do Anúncio: 16-01-2026\n5 - PROCESSO\nTipo de Procedimento: Concurso público\nPreço base do procedimento: Sim\nValor do preço base do procedimento: 30.000,00 EUR\nProcedimento com lotes? Não\n6 - OBJETO DO CONTRATO\nNúmero de referência interna: 20260087\nDesignação do contrato: (DAG) Concurso Público sem publicação no JOUE para Aquisição de Serviços de Logística para a SPMS, EPE (20260087)\nDescrição: (DAG) Concurso Público sem publicidade no JOUE para Aquisição de Serviços de Logística para a SPMS, EPE (20260087)\nTipo de Contrato Principal: Aquisição de Serviços\nTipo de Contrato: Aquisição de Serviços\nClassificação CPV (Vocabulário Comum para os Contratos Públicos)\nObjeto principal\nVocabulário Principal: 60100000\nPreço base s/IVA: 30.000,00 EUR\n7 - INDICAÇÕES ADICIONAIS\nO contrato envolve aquisição conjunta (satisfação de várias entidades)? Não\nO contrato é adjudicado por uma central de compras? Não\n8 - TÉCNICAS\nO concurso destina-se à celebração de um acordo-quadro? Inexistência de acordo-quadro\nÉ utilizado um leilão eletrónico? Não\nÉ adotada uma fase de negociação? Não\nSistema de Aquisição Dinâmico: Inexistência de sistema de aquisição dinâmico\n9 - LOCAL DA EXECUÇÃO DO CONTRATO\nLOCAL DA EXECUÇÃO DO CONTRATO (PROCEDIMENTO)\nPaís: Portugal\nNUT III: PT170\nLocalidade: Lisboa\nDistrito: Lisboa\nConcelho: Lisboa\nFreguesia: Todas\n10 - PRAZO DE EXECUÇÃO DO CONTRATO\nPrazo de execução do contrato: 36 MESES\nPrevisão de renovações: Não\n11 - FUNDOS EU\nTêm fundos EU? Não\n12 - DOCUMENTOS DE HABILITAÇÃO\nHabilitação para o exercício da atividade profissional: Não\n13 - CONDIÇÕES DE APRESENTAÇÃO\nPlataforma eletrónica utilizada pela entidade adjudicante: VORTAL\nURL para Apresentação: https://community.vortal.biz/public/\nAdmissibilidade da apresentação de propostas variantes: Não autorizado\nPrazo para apresentação das propostas: 27-01-2026 18:00\nPrazo durante o qual os concorrentes são obrigados a manter as respetivas propostas: 180 dias a contar do termo do prazo para a apresentação das propostas\nIndicação de Subcontratação na Proposta: Inexistência de indicação de subcontratação\n14 - PRESTAÇÃO DE CAUÇÃO\nPrestação de caução: Sim\nPercentagem: 2%\nDescrição da Garantia Exigida: Ver artigo 29.º do Programa de Concurso\n15 - FORNECIMENTO DAS PEÇAS DO CONCURSO, APRESENTAÇÃO DE PEDIDOS DE PARTICIPAÇÃO E APRESENTAÇÃO DAS PROPOSTAS\nLink para acesso às peças do concurso (URL): https://community.vortal.biz/Public/public-tender-documents/aHo0TGU0aDlaa1lsQ0dMQWVmTUh1eHpuKzBsY05KNmxaRlA3MldpaGVPRGljMXR0bXJxa0xNRkI2Mk04UExUYWJZV0lkUFV0bmtVTHoyZ3ZmWlg1T0E9PU9uI1Eo\n20 - OUTROS REQUISITOS\nInformação sobre contratos reservados. Aplica-se a contratos reservados (54º-A)? Não\n21 - CRITÉRIO DE ADJUDICAÇÃO\nMultifator: Não\nMonofator:\nNome: Preço\n24 - CONDIÇÕES DO CONTRATO\nFaturação Eletrónica: Permitido\nObrigação de Subcontratação:\nCódigo da Obrigação de Subcontratação: Não é aplicável nenhuma obrigação de subcontratação.\n25 - COMPRA PÚBLICA ESTRATÉGICA\nCompra Pública Estratégica: Inexistência de contratação pública estratégica\n26 - INFORMAÇÕES ADICIONAIS\nContrato adequado para PME: Sim\nCobertura ACP (Acordo dos Contratos Públicos da Organização Mundial do Comércio): Não\n27 - IDENTIFICAÇÃO E CONTACTOS DO ÓRGÃO DE RECURSOS ADMINISTRATIVOS\nDesignação: SPMS, EPE\nEndereço: Avenida da República, 61\nCódigo postal: 1050-189\nLocalidade: Lisboa\nTelefone: +351 211545600\nFax: +351 211545649\nEndereço eletrónico: contratacao@spms.min-saude.pt\n28 - IDENTIFICAÇÃO DO(S) AUTOR(ES) DE ANÚNCIO\nNome: Ana Gonçalves\nCargo: Coordenadora da Direção de Administração Geral\n419948206",
    "nipc": "509540716",
    "distrito": "Lisboa",
    "concelho": "Lisboa",
    "freguesia": "Todas",
    "site": "www.spms.min-saude.pt/",
    "email": "contratacao@spms.min-saude.pt",
    "designacao_contrato": "(DAG) Concurso Público sem publicação no JOUE para Aquisição de Serviços de Logística para a SPMS, EPE (20260087)",
    "descricao": "(DAG) Concurso Público sem publicidade no JOUE para Aquisição de Serviços de Logística para a SPMS, EPE (20260087)",
    "preco_base": "30.000,00 EUR",
    "prazo_execucao": "36 MESES",
    "prazo_apresentacao_propostas": "27-01-2026 18:00",
    "fundos_eu": "Não",
    "plataforma_eletronica": "VORTAL",
    "url_procedimento": "https://community.vortal.biz/public/",
    "autor_nome": "Ana Gonçalves",
    "autor_cargo": "Coordenadora da Direção de Administração Geral"
  },
  {
    "numero_procedimento": "N/A",
    "entidade": "AnÃºncio de procedimento  n.Âº 970/2026  -  DiÃ¡rio da RepÃºblica n.Âº 11/2026, SÃ©rie II de 2026-01-16",
    "link": "https://diariodarepublica.pt/dr/detalhe/contrato-publico/970-1014253327"
  },
  {
    "numero_procedimento": "N/A",
    "entidade": "Guarda Nacional Republicana",
    "link": "https://diariodarepublica.pt/dr/detalhe/contrato-publico/973-1014253328",
    "detalhes_completos": "1 - IDENTIFICAÇÃO E CONTACTOS DA ENTIDADE ADJUDICANTE\nDesignação da entidade adjudicante: Guarda Nacional Republicana\nNIPC: 600008878\nServiço/Órgão/Pessoa de contacto: Comando Territorial de Beja\nEndereço: Lg. do Carmo - Convento do Carmo\nCódigo postal: 1200-092\nLocalidade: Lisboa\nPaís: Portugal\nNUT III: PT170\nDistrito: Lisboa\nConcelho: Lisboa\nFreguesia: Todas\nTelefone: 213217000\nFax: 213217328\nEndereço da Entidade (URL): www.gnr.pt\nEndereço Eletrónico: cari.drl.da@gnr.pt\neDelivery Gateway (URL): https://community.vortal.biz/public/\nFunção da Organização: Adquirente\nNorma jurídica da Entidade Adjudicante: Organismo de direito público\nÁrea de atividade da Autoridade Adjudicante: Segurança e ordem pública\n2 - JORNAL OFICIAL DA UNIÃO EUROPEIA\nO procedimento a que este anúncio diz respeito também é publicitado no Jornal Oficial da União Europeia? Não\n3 - AVISO\nModelo de Anúncio: Concurso público\nData de Envio do Anúncio: 16-01-2026\n5 - PROCESSO\nTipo de Procedimento: Concurso público\nPreço base do procedimento: Sim\nValor do preço base do procedimento: 97.560,00 EUR\nProcedimento com lotes? Não\n6 - OBJETO DO CONTRATO\nNúmero de referência interna: Concurso Público n.º 01/CTBEJA/2026\nDesignação do contrato: Concurso Público n.º 01/CTBEJA/2026\nDescrição: Aquisição e montagem de pneumáticos para as viaturas do Comando Territorial de Beja\nTipo de Contrato Principal: Aquisição de Bens Móveis\nTipo de Contrato: Aquisição de Bens Móveis\nClassificação CPV (Vocabulário Comum para os Contratos Públicos)\nObjeto principal\nVocabulário Principal: 34351100\nPreço base s/IVA: 97.560,00 EUR\n7 - INDICAÇÕES ADICIONAIS\nO contrato envolve aquisição conjunta (satisfação de várias entidades)? Não\nO contrato é adjudicado por uma central de compras? Não\n8 - TÉCNICAS\nO concurso destina-se à celebração de um acordo-quadro? Inexistência de acordo-quadro\nÉ utilizado um leilão eletrónico? Não\nÉ adotada uma fase de negociação? Não\nSistema de Aquisição Dinâmico: Inexistência de sistema de aquisição dinâmico\n9 - LOCAL DA EXECUÇÃO DO CONTRATO\nLOCAL DA EXECUÇÃO DO CONTRATO (PROCEDIMENTO)\nPaís: Portugal\nNUT III: PTZZZ\nLocalidade: PORTUGAL\nDistrito: Todos\nConcelho: Todos\nFreguesia: Todas\n10 - PRAZO DE EXECUÇÃO DO CONTRATO\nPrazo de execução do contrato: 36 MESES\nPrevisão de renovações: Não\n11 - FUNDOS EU\nTêm fundos EU? Não\n12 - DOCUMENTOS DE HABILITAÇÃO\nHabilitação para o exercício da atividade profissional: Sim\nTipo: Outros\nDescrição - Outros: Conforme exposto no Artigo 20.º do Programa do Procedimento.\nDescrição: CAE 45320\n13 - CONDIÇÕES DE APRESENTAÇÃO\nPlataforma eletrónica utilizada pela entidade adjudicante: VORTAL\nURL para Apresentação: https://community.vortal.biz/public/\nAdmissibilidade da apresentação de propostas variantes: Não autorizado\nPrazo para apresentação das propostas: 26-01-2026 23:59\nPrazo durante o qual os concorrentes são obrigados a manter as respetivas propostas: 90 dias a contar do termo do prazo para a apresentação das propostas\nApresentação de Catálogo Eletrónico: Não autorizado\nIndicação de Subcontratação na Proposta: Inexistência de indicação de subcontratação\n14 - PRESTAÇÃO DE CAUÇÃO\nPrestação de caução: Não\n15 - FORNECIMENTO DAS PEÇAS DO CONCURSO, APRESENTAÇÃO DE PEDIDOS DE PARTICIPAÇÃO E APRESENTAÇÃO DAS PROPOSTAS\nLink para acesso às peças do concurso (URL): https://community.vortal.biz/Public/public-tender-documents/Y1RaaW5rMUtEMjhHRHUzZUFlT3FXQ1h5dHBhcTJCMXMvdjBZS21YNWFiSHZ4SCtEUUJ0Q0R1KzVVdnk1S3ZFSmpFZndYcXQxZFRIdUh4TU4rbVhZdmc9PXUrcHpD\n20 - OUTROS REQUISITOS\nInformação sobre contratos reservados. Aplica-se a contratos reservados (54º-A)? Não\n21 - CRITÉRIO DE ADJUDICAÇÃO\nMultifator: Não\nMonofator:\nNome: Preço\n24 - CONDIÇÕES DO CONTRATO\nFaturação Eletrónica: Permitido\nObrigação de Subcontratação:\nCódigo da Obrigação de Subcontratação: Não é aplicável nenhuma obrigação de subcontratação.\n25 - COMPRA PÚBLICA ESTRATÉGICA\nCompra Pública Estratégica: Inexistência de contratação pública estratégica\n26 - INFORMAÇÕES ADICIONAIS\nContrato adequado para PME: Sim\nCobertura ACP (Acordo dos Contratos Públicos da Organização Mundial do Comércio): Não\n27 - IDENTIFICAÇÃO E CONTACTOS DO ÓRGÃO DE RECURSOS ADMINISTRATIVOS\nDesignação: Tenente-General, Comandante-Geral da Guarda Nacional Republicana\nEndereço: Largo do Carmo\nCódigo postal: 1200-092\nLocalidade: Lisboa\nTelefone: +351 213217201\nFax: +351 213474819\nEndereço eletrónico: cg.gabcg@gnr.pt\n28 - IDENTIFICAÇÃO DO(S) AUTOR(ES) DE ANÚNCIO\nNome: Paulo Sérgio de Oliveira Gomes\nCargo: Comandante do Comando Territorial de Beja\n419947962",
    "nipc": "600008878",
    "distrito": "Lisboa",
    "concelho": "Lisboa",
    "freguesia": "Todas",
    "site": "www.gnr.pt",
    "email": "cari.drl.da@gnr.pt",
    "designacao_contrato": "Concurso Público n.º 01/CTBEJA/2026",
    "descricao": "Aquisição e montagem de pneumáticos para as viaturas do Comando Territorial de Beja",
    "preco_base": "97.560,00 EUR",
    "prazo_execucao": "36 MESES",
    "prazo_apresentacao_propostas": "26-01-2026 23:59",
    "fundos_eu": "Não",
    "plataforma_eletronica": "VORTAL",
    "url_procedimento": "https://community.vortal.biz/public/",
    "autor_nome": "Paulo Sérgio de Oliveira Gomes",
    "autor_cargo": "Comandante do Comando Territorial de Beja"
  },
  {
    "numero_procedimento": "N/A",
    "entidade": "Estado-Maior-General das Forças Armadas (EMGFA)",
    "link": "https://diariodarepublica.pt/dr/detalhe/contrato-publico/978-1014253329",
    "detalhes_completos": "Alteração do Anúncio de procedimento n.º 33638/2025, de 2025-12-31, com o ID 419941053\n1 - IDENTIFICAÇÃO E CONTACTOS DA ENTIDADE ADJUDICANTE\nDesignação da entidade adjudicante: Estado-Maior-General das Forças Armadas (EMGFA)\nNIPC: 600010180\nServiço/Órgão/Pessoa de contacto: Secção de Aquisições\nEndereço: Hospital das Forças Armadas  Polo do Porto Avenida da Boavista, s/n\nCódigo postal: 4050-113\nLocalidade: Porto\nPaís: Portugal\nNUT III: PT11A\nDistrito: Porto\nConcelho: Porto\nFreguesia: União das Freguesias de Cedofeita, Santo Ildefonso, Sé, Miragaia, São Nicolau e Vitória\nTelefone: 226087927\nFax: 000000000\nEndereço da Entidade (URL): https://www.hfar.pt/\nEndereço Eletrónico: hfar_pp_logistica@hfar.pt\neDelivery Gateway (URL): https://www.acingov.pt\nFunção da Organização: Adquirente\nNorma jurídica da Entidade Adjudicante: Organismo de direito público\nÁrea de atividade da Entidade Adjudicante: Atividades aeroportuárias\n2 - JORNAL OFICIAL DA UNIÃO EUROPEIA\nO procedimento a que este anúncio diz respeito também é publicitado no Jornal Oficial da União Europeia? Não\n3 - AVISO\nModelo de Anúncio: Concurso público\nData de Envio do Anúncio: 16-01-2026\n5 - PROCESSO\nTipo de Procedimento: Concurso público\nPreço base do procedimento: Sim\nValor do preço base do procedimento: 22.000,00 EUR\nProcedimento com lotes? Não\n6 - OBJETO DO CONTRATO\nNúmero de referência interna: CP PRR HFAR-PP 2025009793\nDesignação do contrato: 2025009793  Aquisição de Armário de Pressão Positiva, com Filtro HEPA para o Serviço de Gastrenterologia do HFAR-PP - Aviso PRR N.º 06/C01 i04/2025\nDescrição: 2025009793  Aquisição de Armário de Pressão Positiva, com Filtro HEPA para o Serviço de Gastrenterologia do HFAR-PP - Aviso PRR N.º 06/C01 i04/2025  \nTipo de Contrato Principal: Aquisição de Bens Móveis\nTipo de Contrato: Aquisição de Bens Móveis\nClassificação CPV (Vocabulário Comum para os Contratos Públicos)\nObjeto principal\nVocabulário Principal: 33192000\nPreço base s/IVA: 22.000,00 EUR\n7 - INDICAÇÕES ADICIONAIS\nO contrato envolve aquisição conjunta (satisfação de várias entidades)? Não\nO contrato é adjudicado por uma central de compras? Não\n8 - TÉCNICAS\nO concurso destina-se à celebração de um acordo-quadro? Inexistência de acordo-quadro\nÉ utilizado um leilão eletrónico? Não\nÉ adotada uma fase de negociação? Não\nSistema de Aquisição Dinâmico: Inexistência de sistema de aquisição dinâmico\n9 - LOCAL DA EXECUÇÃO DO CONTRATO\nLOCAL DA EXECUÇÃO DO CONTRATO (PROCEDIMENTO)\nPaís: Portugal\nNUT III: PT11A\nLocalidade: União das Freguesias de Cedofeita, Santo Ildefonso, Sé, Miragaia, São Nicolau e Vitória\nDistrito: Porto\nConcelho: Porto\nFreguesia: União das Freguesias de Cedofeita, Santo Ildefonso, Sé, Miragaia, São Nicolau e Vitória\n10 - PRAZO DE EXECUÇÃO DO CONTRATO\nPrazo de execução do contrato: 60 DIAS\nPrevisão de renovações: Não\n11 - FUNDOS EU\nTêm fundos EU? Sim\n12 - DOCUMENTOS DE HABILITAÇÃO\nHabilitação para o exercício da atividade profissional: Não\n13 - CONDIÇÕES DE APRESENTAÇÃO\nPlataforma eletrónica utilizada pela entidade adjudicante: ACIN\nURL para Apresentação: https://www.acingov.pt\nAdmissibilidade da apresentação de propostas variantes: Não autorizado\nPrazo para apresentação das propostas: 05-02-2026 23:59\nPrazo durante o qual os concorrentes são obrigados a manter as respetivas propostas: 210 dias a contar do termo do prazo para a apresentação das propostas\nIndicação de Subcontratação na Proposta: Inexistência de indicação de subcontratação\n14 - PRESTAÇÃO DE CAUÇÃO\nPrestação de caução: Não\n15 - FORNECIMENTO DAS PEÇAS DO CONCURSO, APRESENTAÇÃO DE PEDIDOS DE PARTICIPAÇÃO E APRESENTAÇÃO DAS PROPOSTAS\nLink para acesso às peças do concurso (URL): https://www.acingov.pt/acingovprod/2/zonaPublica/zona_publica_c/donwloadProcedurePiece/MTAwOTQ5MQ==\n20 - OUTROS REQUISITOS\nInformação sobre contratos reservados. Aplica-se a contratos reservados (54º-A)? Não\n21 - CRITÉRIO DE ADJUDICAÇÃO\nMultifator: Não\nMonofator:\nNome: Preço\n24 - CONDIÇÕES DO CONTRATO\nFaturação Eletrónica: Permitido\nObrigação de Subcontratação:\nCódigo da Obrigação de Subcontratação: Não é aplicável nenhuma obrigação de subcontratação.\n25 - COMPRA PÚBLICA ESTRATÉGICA\nCompra Pública Estratégica: Inexistência de contratação pública estratégica\n26 - INFORMAÇÕES ADICIONAIS\nContrato adequado para PME: Não\nCobertura ACP (Acordo dos Contratos Públicos da Organização Mundial do Comércio): Não\n27 - IDENTIFICAÇÃO E CONTACTOS DO ÓRGÃO DE RECURSOS ADMINISTRATIVOS\nDesignação: Tribunal Administrativo de Círculo de Lisboa\nEndereço: Av D. João II, Bloco G, piso 6-8, nº 1.08.01, 1990-097 Lisboa\nCódigo postal: 1990-097\nLocalidade: Lisboa\nTelefone: 218367100\nFax: 211545188\nEndereço eletrónico: lisboa.tacl@tribunais.org.pt\n28 - IDENTIFICAÇÃO DO(S) AUTOR(ES) DE ANÚNCIO\nNome: José Carlos Candeias Pinheiro Monge\nCargo: Diretor do HFAR\n29 - ALTERAÇÃO\nMotivo da Alteração: Correção pelo editor\nIdentificador da Versão do Anúncio a Alterar: 3d53e0bb-a570-41ca-a099-b6225d0e13b2-01\nIdentificador das Secções Alteradas do Anúncio Anterior: Técnicas; Condições de Apresentação\nDescrição das Alterações: Modificação do prazo para a apresentação de propostas. Modificação do Anexo A do Caderno de Encargos.\nAlteração dos Documentos do Concurso: Sim\nData de alteração dos documentos do concurso: 16-01-2026\n419948200",
    "nipc": "600010180",
    "distrito": "Porto",
    "concelho": "Porto",
    "freguesia": "União das Freguesias de Cedofeita, Santo Ildefonso, Sé, Miragaia, São Nicolau e Vitória",
    "site": "https://www.hfar.pt/",
    "email": "hfar_pp_logistica@hfar.pt",
    "designacao_contrato": "2025009793  Aquisição de Armário de Pressão Positiva, com Filtro HEPA para o Serviço de Gastrenterologia do HFAR-PP - Aviso PRR N.º 06/C01 i04/2025",
    "descricao": "2025009793  Aquisição de Armário de Pressão Positiva, com Filtro HEPA para o Serviço de Gastrenterologia do HFAR-PP - Aviso PRR N.º 06/C01 i04/2025",
    "preco_base": "22.000,00 EUR",
    "prazo_execucao": "60 DIAS",
    "prazo_apresentacao_propostas": "05-02-2026 23:59",
    "fundos_eu": "Sim",
    "plataforma_eletronica": "ACIN",
    "url_procedimento": "https://www.acingov.pt",
    "autor_nome": "José Carlos Candeias Pinheiro Monge",
    "autor_cargo": "Diretor do HFAR"
  },
  {
    "numero_procedimento": "N/A",
    "entidade": "AnÃºncio de procedimento  n.Âº 980/2026  -  DiÃ¡rio da RepÃºblica n.Âº 11/2026, SÃ©rie II de 2026-01-16",
    "link": "https://diariodarepublica.pt/dr/detalhe/contrato-publico/980-1014253330"
  },
  {
    "numero_procedimento": "N/A",
    "entidade": "Instituto do Turismo de Portugal, IP",
    "link": "https://diariodarepublica.pt/dr/detalhe/contrato-publico/981-1014253331",
    "detalhes_completos": "Alteração do Anúncio de procedimento n.º 200/2026, de 2026-01-06, com o ID 419947285\n1 - IDENTIFICAÇÃO E CONTACTOS DA ENTIDADE ADJUDICANTE\nDesignação da entidade adjudicante: Instituto do Turismo de Portugal, IP\nNIPC: 508666236\nEndereço: Rua Ivone Silva, lote 6\nCódigo postal: 1050-124\nLocalidade: Lisboa\nPaís: Portugal\nNUT III: PT170\nDistrito: Lisboa\nConcelho: Lisboa\nFreguesia: Freguesia de Avenidas Novas\nTelefone: 211140200\nFax: 211140200\nEndereço da Entidade (URL): https://www.turismodeportugal.pt\nEndereço Eletrónico: info@turismodeportugal.pt\neDelivery Gateway (URL): https://community.vortal.biz/public/\nFunção da Organização: Adquirente\nNorma jurídica da Entidade Adjudicante: Instituição, órgão ou agência da UE\nÁrea de atividade da Autoridade Adjudicante: Serviços públicos das administrações públicas\n2 - JORNAL OFICIAL DA UNIÃO EUROPEIA\nO procedimento a que este anúncio diz respeito também é publicitado no Jornal Oficial da União Europeia? Não\n3 - AVISO\nModelo de Anúncio: Concurso público\nData de Envio do Anúncio: 16-01-2026\n5 - PROCESSO\nTipo de Procedimento: Concurso público\nPreço base do procedimento: Sim\nValor do preço base do procedimento: 1.468.000,00 EUR\nProcedimento com lotes? Sim\nNº Máx. de Lotes Autorizado: 7\nNúmero máximo de lotes que podem ser adjudicados a um concorrente: 7\n6 - OBJETO DO CONTRATO\nNúmero de referência interna: P(179/2025)01/DPAC/202503510-1.\nDesignação do contrato: Empreitada em regime de conceção-construção de empreitadas para a implementação de medidas de melhoria de eficiência energética em edifícios das Escolas de Hotelaria e Turismo\nDescrição: Empreitada em regime de conceção-construção de empreitadas para a implementação de medidas de melhoria de eficiência energética em edifícios das Escolas de Hotelaria e Turismo\nTipo de Contrato Principal: Empreitada de Obras Públicas\nTipo de Contrato: Empreitada de Obras Públicas\nClassificação CPV (Vocabulário Comum para os Contratos Públicos)\nObjeto principal\nVocabulário Principal: 45300000\nPreço base s/IVA: 1.468.000,00 EUR\nLotes: \nNº: LOT-0001\nDescrição do Lote: Lote 1\nPreço base s/IVA: 65.000,00 EUR\nClassificação CPV (Vocabulário Comum para os Contratos Públicos)\nObjeto principal\nVocabulário Principal: 45300000\nNº: LOT-0002\nDescrição do Lote: Lote 2\nPreço base s/IVA: 476.000,00 EUR\nClassificação CPV (Vocabulário Comum para os Contratos Públicos)\nObjeto principal\nVocabulário Principal: 45300000\nNº: LOT-0003\nDescrição do Lote: Lote 3\nPreço base s/IVA: 338.000,00 EUR\nClassificação CPV (Vocabulário Comum para os Contratos Públicos)\nObjeto principal\nVocabulário Principal: 45300000\nNº: LOT-0004\nDescrição do Lote: Lote 4\nPreço base s/IVA: 120.000,00 EUR\nClassificação CPV (Vocabulário Comum para os Contratos Públicos)\nObjeto principal\nVocabulário Principal: 45300000\nNº: LOT-0005\nDescrição do Lote: Lote 5\nPreço base s/IVA: 136.000,00 EUR\nClassificação CPV (Vocabulário Comum para os Contratos Públicos)\nObjeto principal\nVocabulário Principal: 45300000\nNº: LOT-0006\nDescrição do Lote: Lote 6\nPreço base s/IVA: 140.000,00 EUR\nClassificação CPV (Vocabulário Comum para os Contratos Públicos)\nObjeto principal\nVocabulário Principal: 45300000\nNº: LOT-0007\nDescrição do Lote: Lote 7\nPreço base s/IVA: 193.000,00 EUR\nClassificação CPV (Vocabulário Comum para os Contratos Públicos)\nObjeto principal\nVocabulário Principal: 45300000\n7 - INDICAÇÕES ADICIONAIS\nO contrato envolve aquisição conjunta (satisfação de várias entidades)? Não\nO contrato é adjudicado por uma central de compras? Não\n8 - TÉCNICAS\nO concurso destina-se à celebração de um acordo-quadro? Inexistência de acordo-quadro\nÉ utilizado um leilão eletrónico? Não\nÉ adotada uma fase de negociação? Não\nSistema de Aquisição Dinâmico: Inexistência de sistema de aquisição dinâmico\n9 - LOCAL DA EXECUÇÃO DO CONTRATO\nLOCAL DA EXECUÇÃO DO CONTRATO (PROCEDIMENTO)\nPaís: Portugal\nNUT III: PT170\nLocalidade: Lisboa\nDistrito: Lisboa\nConcelho: Lisboa\nFreguesia: Freguesia de Avenidas Novas\nLOCAL DA EXECUÇÃO DO CONTRATO (LOTE)\nIdentificador do Lote: LOT-0001\nPaís: Portugal\nNUT III: PT111\nLocalidade: Viana Castelo\nDistrito: Viana do Castelo\nConcelho: Viana do Castelo\nFreguesia: União das Freguesias de Viana do Castelo (Santa Maria Maior e Monserrate) e Meadela\nIdentificador do Lote: LOT-0002\nPaís: Portugal\nNUT III: PT11D\nLocalidade: Lamego\nDistrito: Viseu\nConcelho: Lamego\nFreguesia: Freguesia de Lamego (Almacave e Sé)\nIdentificador do Lote: LOT-0003\nPaís: Portugal\nNUT III: PT11A\nLocalidade: Porto\nDistrito: Porto\nConcelho: Porto\nFreguesia: União das Freguesias de Lordelo do Ouro e Massarelos\nIdentificador do Lote: LOT-0004\nPaís: Portugal\nNUT III: PT170\nLocalidade: Caladas da Rainha\nDistrito: Leiria\nConcelho: Caldas da Rainha\nFreguesia: União das Freguesias de Caldas da Rainha - Nossa Senhora do Pópulo, Coto e São Gregório\nIdentificador do Lote: LOT-0005\nPaís: Portugal\nNUT III: PT170\nLocalidade: Lisboa\nDistrito: Lisboa\nConcelho: Lisboa\nFreguesia: Freguesia de Campo de Ourique\nIdentificador do Lote: LOT-0006\nPaís: Portugal\nNUT III: PT170\nLocalidade: Setúbal\nDistrito: Setúbal\nConcelho: Setúbal\nFreguesia: União das Freguesias de Setúbal (São Julião, Nossa Senhora da Anunciada e Santa Maria da Graça)\nIdentificador do Lote: LOT-0007\nPaís: Portugal\nNUT III: PT186\nLocalidade: Portalegre\nDistrito: Portalegre\nConcelho: Portalegre\nFreguesia: União das Freguesias da Sé e São Lourenço\n10 - PRAZO DE EXECUÇÃO DO CONTRATO\nIdentificador do Lote: LOT-0001; LOT-0002; LOT-0003; LOT-0004; LOT-0005; LOT-0006; LOT-0007\nPrazo de execução do contrato: 160 DIAS\nPrevisão de renovações: Não\n11 - FUNDOS EU\nIdentificador do Lote: LOT-0001; LOT-0002; LOT-0003; LOT-0004; LOT-0005; LOT-0006; LOT-0007\nTêm fundos EU? Sim\n12 - DOCUMENTOS DE HABILITAÇÃO\nHabilitação para o exercício da atividade profissional: Sim\nTipo: Alvará\nDescrição: Alvará/certificado do IMPIC e qualificações de equipa de projeto (Lei 31/2009), entre outros.\n13 - CONDIÇÕES DE APRESENTAÇÃO\nPlataforma eletrónica utilizada pela entidade adjudicante: VORTAL\nURL para Apresentação: https://community.vortal.biz/public/\nAdmissibilidade da apresentação de propostas variantes: Não autorizado\nPrazo para apresentação das propostas: 20-02-2026 23:59\nPrazo durante o qual os concorrentes são obrigados a manter as respetivas propostas: 90 dias a contar do termo do prazo para a apresentação das propostas\nApresentação de Catálogo Eletrónico: Permitido\nIndicação de Subcontratação na Proposta: Inexistência de indicação de subcontratação\n14 - PRESTAÇÃO DE CAUÇÃO\nPrestação de caução: Não\n15 - FORNECIMENTO DAS PEÇAS DO CONCURSO, APRESENTAÇÃO DE PEDIDOS DE PARTICIPAÇÃO E APRESENTAÇÃO DAS PROPOSTAS\nLink para acesso às peças do concurso (URL): https://community.vortal.biz/Public/public-tender-documents/WHJBVkpodk1LalFLMUNqSWozTEhEeUs1ZXNaYnBvd0ZZc1paTjlZYzN3dlNweFR0L21mcXFpUlc5TGdZbkh3OXMzbk9Da1o3WTJNcGtLQ1ByY1dxU2c9PU15RjBL\n20 - OUTROS REQUISITOS\nIdentificador do Lote: LOT-0001; LOT-0002; LOT-0003; LOT-0004; LOT-0005; LOT-0006; LOT-0007\nInformação sobre contratos reservados. Aplica-se a contratos reservados (54º-A)? Não\n21 - CRITÉRIO DE ADJUDICAÇÃO\nO Critério de adjudicação é diferenciado por lote? Não\nMultifator: Sim\nFator: \nNome: Preço\nPonderação: 20%\nSubfatores: Não\nFator: \nNome: Outros\nOutro Nome: Prazo\nPonderação: 35%\nSubfatores: Não\nFator: \nNome: Outros\nOutro Nome: Desempenho Energético\nPonderação: 30%\nSubfatores: Não\nFator: \nNome: Qualidade\nPonderação: 15%\nSubfatores: Não\n24 - CONDIÇÕES DO CONTRATO\nIdentificador do Lote: LOT-0001; LOT-0002; LOT-0003; LOT-0004; LOT-0005; LOT-0006; LOT-0007\nFaturação Eletrónica: Permitido\nObrigação de Subcontratação:\nCódigo da Obrigação de Subcontratação: Não é aplicável nenhuma obrigação de subcontratação.\n25 - COMPRA PÚBLICA ESTRATÉGICA\nCompra Pública Estratégica: Inexistência de contratação pública estratégica\n26 - INFORMAÇÕES ADICIONAIS\nIdentificador do Lote: LOT-0001; LOT-0002; LOT-0003; LOT-0004; LOT-0005; LOT-0006; LOT-0007\nContrato adequado para PME: Sim\nCobertura ACP (Acordo dos Contratos Públicos da Organização Mundial do Comércio): Não\n27 - IDENTIFICAÇÃO E CONTACTOS DO ÓRGÃO DE RECURSOS ADMINISTRATIVOS\nDesignação: Instituto do Turismo de Portugal, I.P,\nEndereço: Rua Ivone Silva, Lote 6\nCódigo postal: 1050-124\nLocalidade: Lisboa\nTelefone: +351 211140200\nFax: +351 211140200\nEndereço eletrónico: dcgg-concursos@turismodeportugal.pt\n28 - IDENTIFICAÇÃO DO(S) AUTOR(ES) DE ANÚNCIO\nNome: Graça Carvalho\nCargo: Técnica Superior\n29 - ALTERAÇÃO\nMotivo da Alteração: Informações atualizadas\nIdentificador da Versão do Anúncio a Alterar: 49b821c3-f95c-4000-bd6e-3a058e205054-01\nIdentificador das Secções Alteradas do Anúncio Anterior: Critério de adjudicação\nDescrição das Alterações: Critério adjudicação não é diferenciado por lotes.\nAlteração dos Documentos do Concurso: Não\nIdentificador das Secções Alteradas do Anúncio Anterior: Local da execução do contrato\nDescrição das Alterações: Diferenciar por lote do local de execução do contrato.\nAlteração dos Documentos do Concurso: Não\nIdentificador das Secções Alteradas do Anúncio Anterior: Prazo de execução do contrato\nDescrição das Alterações: Correção do prazo execução do contrato.\nAlteração dos Documentos do Concurso: Não\nIdentificador das Secções Alteradas do Anúncio Anterior: Fundos EU\nDescrição das Alterações: Fundos Europeus -sim\nAlteração dos Documentos do Concurso: Não\nIdentificador das Secções Alteradas do Anúncio Anterior: Documentos de habilitação\nDescrição das Alterações: Habilitação para o exercício atividade professional  - sim\nAlteração dos Documentos do Concurso: Não\n419948135",
    "nipc": "508666236",
    "distrito": "Lisboa",
    "concelho": "Lisboa",
    "freguesia": "Freguesia de Avenidas Novas",
    "site": "https://www.turismodeportugal.pt",
    "email": "info@turismodeportugal.pt",
    "designacao_contrato": "Empreitada em regime de conceção-construção de empreitadas para a implementação de medidas de melhoria de eficiência energética em edifícios das Escolas de Hotelaria e Turismo",
    "descricao": "Empreitada em regime de conceção-construção de empreitadas para a implementação de medidas de melhoria de eficiência energética em edifícios das Escolas de Hotelaria e Turismo",
    "preco_base": "1.468.000,00 EUR",
    "prazo_execucao": "160 DIAS",
    "prazo_apresentacao_propostas": "20-02-2026 23:59",
    "fundos_eu": "Sim",
    "plataforma_eletronica": "VORTAL",
    "url_procedimento": "https://community.vortal.biz/public/",
    "autor_nome": "Graça Carvalho",
    "autor_cargo": "Técnica Superior"
  },
  {
    "numero_procedimento": "N/A",
    "entidade": "Águas de São João, EM, SA",
    "link": "https://diariodarepublica.pt/dr/detalhe/contrato-publico/982-1014253333",
    "detalhes_completos": "1 - IDENTIFICAÇÃO E CONTACTOS DA ENTIDADE ADJUDICANTE\nDesignação da entidade adjudicante: Águas de São João, EM, SA\nNIPC: 508326567\nEndereço: Avenida da Liberdade - Edifício da Câmara Municipa\nCódigo postal: 3701-956\nLocalidade: Aveiro\nPaís: Portugal\nNUT III: PT11A\nDistrito: Aveiro\nConcelho: São João da Madeira\nFreguesia: Todas\nTelefone: 256100700\nFax: 256100709\nEndereço Eletrónico: geral@aguasdesjoao.pt\neDelivery Gateway (URL): https://community.vortal.biz/public/\nFunção da Organização: Adquirente\nNorma jurídica da Entidade Adjudicante: Empresa pública\nÁrea de atividade da Entidade Adjudicante: Atividades relacionadas com a água\n2 - JORNAL OFICIAL DA UNIÃO EUROPEIA\nO procedimento a que este anúncio diz respeito também é publicitado no Jornal Oficial da União Europeia? Não\n3 - AVISO\nModelo de Anúncio: Concurso público\nData de Envio do Anúncio: 16-01-2026\n5 - PROCESSO\nTipo de Procedimento: Concurso público\nPreço base do procedimento: Sim\nValor do preço base do procedimento: 60.000,00 EUR\nProcedimento com lotes? Não\n6 - OBJETO DO CONTRATO\nNúmero de referência interna: CPu 01/2025\nDesignação do contrato: FORNECIMENTO DE 100.000 Kg DE HIDRÓXIDO DE SÓDIO LÍQUIDO A 50%\nDescrição: Fornecimento de 100.000 kg de Hidróxido de Sódio líquido a 50 %\nTipo de Contrato Principal: Aquisição de Bens Móveis\nTipo de Contrato: Aquisição de Bens Móveis\nClassificação CPV (Vocabulário Comum para os Contratos Públicos)\nObjeto principal\nVocabulário Principal: 24300000\nPreço base s/IVA: 60.000,00 EUR\n7 - INDICAÇÕES ADICIONAIS\nO contrato envolve aquisição conjunta (satisfação de várias entidades)? Não\nO contrato é adjudicado por uma central de compras? Não\n8 - TÉCNICAS\nO concurso destina-se à celebração de um acordo-quadro? Inexistência de acordo-quadro\nÉ utilizado um leilão eletrónico? Não\nÉ adotada uma fase de negociação? Não\nSistema de Aquisição Dinâmico: Inexistência de sistema de aquisição dinâmico\n9 - LOCAL DA EXECUÇÃO DO CONTRATO\nLOCAL DA EXECUÇÃO DO CONTRATO (PROCEDIMENTO)\nPaís: Portugal\nNUT III: PT11A\nLocalidade: Aveiro\nDistrito: Aveiro\nConcelho: São João da Madeira\nFreguesia: Todas\n10 - PRAZO DE EXECUÇÃO DO CONTRATO\nPrazo de execução do contrato: 1 ANOS\nPrevisão de renovações: Não\n11 - FUNDOS EU\nTêm fundos EU? Não\n12 - DOCUMENTOS DE HABILITAÇÃO\nHabilitação para o exercício da atividade profissional: Não\n13 - CONDIÇÕES DE APRESENTAÇÃO\nPlataforma eletrónica utilizada pela entidade adjudicante: VORTAL\nURL para Apresentação: https://community.vortal.biz/public/\nAdmissibilidade da apresentação de propostas variantes: Não autorizado\nPrazo para apresentação das propostas: 26-01-2026 17:00\nPrazo durante o qual os concorrentes são obrigados a manter as respetivas propostas: 66 dias a contar do termo do prazo para a apresentação das propostas\nIndicação de Subcontratação na Proposta: Inexistência de indicação de subcontratação\n14 - PRESTAÇÃO DE CAUÇÃO\nPrestação de caução: Não\n15 - FORNECIMENTO DAS PEÇAS DO CONCURSO, APRESENTAÇÃO DE PEDIDOS DE PARTICIPAÇÃO E APRESENTAÇÃO DAS PROPOSTAS\nLink para acesso às peças do concurso (URL): https://community.vortal.biz/Public/public-tender-documents/MmY1NnpMMTJTdUZmcVV2L21IU2g2TXRBb3ZVUS9UazRHZ04vbVplbXlzNEN0cUtyMk9VWTZuOFAwTTBuUldGNjZrOHo1K09GQWp5bjh2ZlVweXkyMEE9PSk4Xys5\n20 - OUTROS REQUISITOS\nInformação sobre contratos reservados. Aplica-se a contratos reservados (54º-A)? Não\n21 - CRITÉRIO DE ADJUDICAÇÃO\nMultifator: Não\nMonofator:\nNome: Preço\n24 - CONDIÇÕES DO CONTRATO\nFaturação Eletrónica: Permitido\nObrigação de Subcontratação:\nCódigo da Obrigação de Subcontratação: Não é aplicável nenhuma obrigação de subcontratação.\n25 - COMPRA PÚBLICA ESTRATÉGICA\nCompra Pública Estratégica: Inexistência de contratação pública estratégica\n26 - INFORMAÇÕES ADICIONAIS\nContrato adequado para PME: Sim\nCobertura ACP (Acordo dos Contratos Públicos da Organização Mundial do Comércio): Não\n27 - IDENTIFICAÇÃO E CONTACTOS DO ÓRGÃO DE RECURSOS ADMINISTRATIVOS\nDesignação: Daniel Filipe Matias\nEndereço: Avenida da Liberdade - Edifício da Câmara Municipal\nCódigo postal: 3701-956\nLocalidade: São João da Madeira\nTelefone: +351 256100700\nFax: +351 256100709\nEndereço eletrónico: danielmatias@aguasdesjoao.pt\n28 - IDENTIFICAÇÃO DO(S) AUTOR(ES) DE ANÚNCIO\nNome: Daniel Filipe Matias\nCargo: Diretor Geral\n419948227",
    "nipc": "508326567",
    "distrito": "Aveiro",
    "concelho": "São João da Madeira",
    "freguesia": "Todas",
    "site": null,
    "email": "geral@aguasdesjoao.pt",
    "designacao_contrato": "FORNECIMENTO DE 100.000 Kg DE HIDRÓXIDO DE SÓDIO LÍQUIDO A 50%",
    "descricao": "Fornecimento de 100.000 kg de Hidróxido de Sódio líquido a 50 %",
    "preco_base": "60.000,00 EUR",
    "prazo_execucao": "1 ANOS",
    "prazo_apresentacao_propostas": "26-01-2026 17:00",
    "fundos_eu": "Não",
    "plataforma_eletronica": "VORTAL",
    "url_procedimento": "https://community.vortal.biz/public/",
    "autor_nome": "Daniel Filipe Matias",
    "autor_cargo": "Diretor Geral"
  },
  {
    "numero_procedimento": "N/A",
    "entidade": "Município da Guarda",
    "link": "https://diariodarepublica.pt/dr/detalhe/contrato-publico/984-1014253334",
    "detalhes_completos": "Alteração do Anúncio de procedimento n.º 32750/2025, de 2025-12-17, com o ID 419893718\n1 - IDENTIFICAÇÃO E CONTACTOS DA ENTIDADE ADJUDICANTE\nDesignação da entidade adjudicante: Município da Guarda\nNIPC: 501131140\nEndereço: Praça do Município, nº 1\nCódigo postal: 6301-854\nLocalidade: Guarda\nPaís: Portugal\nNUT III: PT16J\nDistrito: Guarda\nConcelho: Guarda\nFreguesia: Freguesia de Guarda\nTelefone: 271220200\nFax: 271220280\nEndereço da Entidade (URL): www.mun-guarda.pt\nEndereço Eletrónico: geral@mun-guarda.pt\neDelivery Gateway (URL): https://community.vortal.biz/public/\nFunção da Organização: Adquirente\nNorma jurídica da Entidade Adjudicante: Autoridade local\nÁrea de atividade da Autoridade Adjudicante: Serviços públicos das administrações públicas\n2 - JORNAL OFICIAL DA UNIÃO EUROPEIA\nO procedimento a que este anúncio diz respeito também é publicitado no Jornal Oficial da União Europeia? Não\n3 - AVISO\nModelo de Anúncio: Concurso público\nData de Envio do Anúncio: 16-01-2026\n5 - PROCESSO\nTipo de Procedimento: Concurso público\nPreço base do procedimento: Sim\nValor do preço base do procedimento: 1.229.747,90 EUR\nProcedimento com lotes? Não\n6 - OBJETO DO CONTRATO\nNúmero de referência interna: DOPEI/ED-2025-38\nDesignação do contrato: Centro de Empresas Startups\nDescrição: Centro de Empresas Startups\nTipo de Contrato Principal: Empreitada de Obras Públicas\nTipo de Contrato: Empreitada de Obras Públicas\nClassificação CPV (Vocabulário Comum para os Contratos Públicos)\nObjeto principal\nVocabulário Principal: 45200000\nPreço base s/IVA: 1.229.747,90 EUR\n7 - INDICAÇÕES ADICIONAIS\nO contrato envolve aquisição conjunta (satisfação de várias entidades)? Não\nO contrato é adjudicado por uma central de compras? Não\n8 - TÉCNICAS\nO concurso destina-se à celebração de um acordo-quadro? Inexistência de acordo-quadro\nÉ utilizado um leilão eletrónico? Não\nÉ adotada uma fase de negociação? Não\nSistema de Aquisição Dinâmico: Inexistência de sistema de aquisição dinâmico\n9 - LOCAL DA EXECUÇÃO DO CONTRATO\nLOCAL DA EXECUÇÃO DO CONTRATO (PROCEDIMENTO)\nPaís: Portugal\nNUT III: PT16J\nLocalidade: Guarda\nDistrito: Guarda\nConcelho: Guarda\nFreguesia: Freguesia de Guarda\n10 - PRAZO DE EXECUÇÃO DO CONTRATO\nPrazo de execução do contrato: 365 DIAS\nPrevisão de renovações: Não\n11 - FUNDOS EU\nTêm fundos EU? Não\n12 - DOCUMENTOS DE HABILITAÇÃO\nHabilitação para o exercício da atividade profissional: Sim\nTipo: Outros\nDescrição - Outros: Constantes das peças procedimentais\nDescrição: Constantes das peças procedimentais\n13 - CONDIÇÕES DE APRESENTAÇÃO\nPlataforma eletrónica utilizada pela entidade adjudicante: VORTAL\nURL para Apresentação: https://community.vortal.biz/public/\nAdmissibilidade da apresentação de propostas variantes: Não autorizado\nPrazo para apresentação das propostas: 15-02-2026 17:00\nPrazo durante o qual os concorrentes são obrigados a manter as respetivas propostas: 66 dias a contar do termo do prazo para a apresentação das propostas\nApresentação de Catálogo Eletrónico: Permitido\nIndicação de Subcontratação na Proposta: Inexistência de indicação de subcontratação\n14 - PRESTAÇÃO DE CAUÇÃO\nPrestação de caução: Sim\nPercentagem: 5%\nDescrição da Garantia Exigida: De acordo com o artigo 45º do programa de procedimento\n15 - FORNECIMENTO DAS PEÇAS DO CONCURSO, APRESENTAÇÃO DE PEDIDOS DE PARTICIPAÇÃO E APRESENTAÇÃO DAS PROPOSTAS\nLink para acesso às peças do concurso (URL): https://community.vortal.biz/Public/public-tender-documents/ajNGRG1KRFFkUHBjRGVjaFhZODM4T1ZOVU1mTnZ3czhYM200bmxPUGFqQmtSYWh6SHdvdjRHRHN4WWxZeUlpTTVwL1laL3pocTJ3ZWlsRjg4WE5wSXc9PTZeZmtN\n20 - OUTROS REQUISITOS\nInformação sobre contratos reservados. Aplica-se a contratos reservados (54º-A)? Não\n21 - CRITÉRIO DE ADJUDICAÇÃO\nMultifator: Sim\nFator: \nNome: Qualidade\nPonderação: 60%\nSubfatores: Sim\nSubfatores: \nNome: Plano de trabalhos\nPonderação : 70%; \nNome: Memória descritiva e justificativa do modo execução da obra\nPonderação : 30%; \nFator: \nNome: Qualidade\nPonderação: 40%\nSubfatores: Não\n24 - CONDIÇÕES DO CONTRATO\nFaturação Eletrónica: Permitido\nObrigação de Subcontratação:\nCódigo da Obrigação de Subcontratação: Não é aplicável nenhuma obrigação de subcontratação.\n25 - COMPRA PÚBLICA ESTRATÉGICA\nCompra Pública Estratégica: Inexistência de contratação pública estratégica\n26 - INFORMAÇÕES ADICIONAIS\nContrato adequado para PME: Sim\nCobertura ACP (Acordo dos Contratos Públicos da Organização Mundial do Comércio): Não\n27 - IDENTIFICAÇÃO E CONTACTOS DO ÓRGÃO DE RECURSOS ADMINISTRATIVOS\nDesignação: Presidente da Câmara Municipal\nEndereço: Praça do Municipio.\nCódigo postal: 6301-854\nLocalidade: Guarda\nTelefone: +351 271220200\nFax: +351 271220280\nEndereço eletrónico: contratacaopublica@mun-guarda.pt\n28 - IDENTIFICAÇÃO DO(S) AUTOR(ES) DE ANÚNCIO\nNome: Sérgio Fernando da Silva Costa\nCargo: Presidente da Câmara Municipal\n29 - ALTERAÇÃO\nMotivo da Alteração: Correção pelo adquirente\nIdentificador da Versão do Anúncio a Alterar: d824da8a-cbb8-4768-90f9-f80ec53f77b8-01\nIdentificador das Secções Alteradas do Anúncio Anterior: Condições de Apresentação\nDescrição das Alterações: Prorrogação prazo para apresentação de propostas\nAlteração dos Documentos do Concurso: Não\n419948149",
    "nipc": "501131140",
    "distrito": "Guarda",
    "concelho": "Guarda",
    "freguesia": "Freguesia de Guarda",
    "site": "www.mun-guarda.pt",
    "email": "geral@mun-guarda.pt",
    "designacao_contrato": "Centro de Empresas Startups",
    "descricao": "Centro de Empresas Startups",
    "preco_base": "1.229.747,90 EUR",
    "prazo_execucao": "365 DIAS",
    "prazo_apresentacao_propostas": "15-02-2026 17:00",
    "fundos_eu": "Não",
    "plataforma_eletronica": "VORTAL",
    "url_procedimento": "https://community.vortal.biz/public/",
    "autor_nome": "Sérgio Fernando da Silva Costa",
    "autor_cargo": "Presidente da Câmara Municipal"
  },
  {
    "numero_procedimento": "N/A",
    "entidade": "AnÃºncio de procedimento  n.Âº 986/2026  -  DiÃ¡rio da RepÃºblica n.Âº 11/2026, SÃ©rie II de 2026-01-16",
    "link": "https://diariodarepublica.pt/dr/detalhe/contrato-publico/986-1014253335"
  },
  {
    "numero_procedimento": "N/A",
    "entidade": "Instituto Superior de Economia e Gestão",
    "link": "https://diariodarepublica.pt/dr/detalhe/contrato-publico/987-1014253336",
    "detalhes_completos": "Alteração do Anúncio de procedimento n.º 33584/2025, de 2025-12-30, com o ID 419940138\n1 - IDENTIFICAÇÃO E CONTACTOS DA ENTIDADE ADJUDICANTE\nDesignação da entidade adjudicante: Instituto Superior de Economia e Gestão\nNIPC: 502488603\nEndereço: Rua do Quelhas, n.º 6\nCódigo postal: 1200-781\nLocalidade: Lisboa\nPaís: Portugal\nNUT III: PT170\nDistrito: Lisboa\nConcelho: Lisboa\nFreguesia: Todas\nTelefone: 213925800\nFax: 213925895\nEndereço da Entidade (URL): www.iseg.ulisboa.pt\nEndereço Eletrónico: dlat@iseg.ulisboa.pt\neDelivery Gateway (URL): https://community.vortal.biz/public/\nFunção da Organização: Adquirente\nNorma jurídica da Entidade Adjudicante: Autoridade da administração central\nÁrea de atividade da Autoridade Adjudicante: Educação\n2 - JORNAL OFICIAL DA UNIÃO EUROPEIA\nO procedimento a que este anúncio diz respeito também é publicitado no Jornal Oficial da União Europeia? Não\n3 - AVISO\nModelo de Anúncio: Concurso público\nData de Envio do Anúncio: 16-01-2026\n5 - PROCESSO\nTipo de Procedimento: Concurso público\nPreço base do procedimento: Sim\nValor do preço base do procedimento: 116.631,69 EUR\nProcedimento com lotes? Não\n6 - OBJETO DO CONTRATO\nNúmero de referência interna: Concurso Público N.º 30/ISEG/2025\nDesignação do contrato: Concurso Público para o Fornecimento e instalação de sistema de controlo de estacionamento para os 3 Parques de Estacionamento do ISEG\nDescrição: Concurso Público para o Fornecimento e instalação de sistema de controlo de estacionamento para os 3 Parques de Estacionamento do ISEG\nTipo de Contrato Principal: Aquisição de Bens Móveis\nTipo de Contrato: Aquisição de Bens Móveis\nClassificação CPV (Vocabulário Comum para os Contratos Públicos)\nObjeto principal\nVocabulário Principal: 34996300\nPreço base s/IVA: 116.631,69 EUR\n7 - INDICAÇÕES ADICIONAIS\nO contrato envolve aquisição conjunta (satisfação de várias entidades)? Não\nO contrato é adjudicado por uma central de compras? Não\n8 - TÉCNICAS\nO concurso destina-se à celebração de um acordo-quadro? Inexistência de acordo-quadro\nÉ utilizado um leilão eletrónico? Não\nÉ adotada uma fase de negociação? Não\nSistema de Aquisição Dinâmico: Inexistência de sistema de aquisição dinâmico\n9 - LOCAL DA EXECUÇÃO DO CONTRATO\nLOCAL DA EXECUÇÃO DO CONTRATO (PROCEDIMENTO)\nPaís: Portugal\nNUT III: PT170\nLocalidade: Lisboa\nDistrito: Lisboa\nConcelho: Lisboa\nFreguesia: Freguesia da Estrela\n10 - PRAZO DE EXECUÇÃO DO CONTRATO\nPrazo de execução do contrato: 90 DIAS\nPrevisão de renovações: Não\n11 - FUNDOS EU\nTêm fundos EU? Não\n12 - DOCUMENTOS DE HABILITAÇÃO\nHabilitação para o exercício da atividade profissional: Não\n13 - CONDIÇÕES DE APRESENTAÇÃO\nPlataforma eletrónica utilizada pela entidade adjudicante: VORTAL\nURL para Apresentação: https://community.vortal.biz/public/\nAdmissibilidade da apresentação de propostas variantes: Não autorizado\nPrazo para apresentação das propostas: 09-02-2026 23:59\nPrazo durante o qual os concorrentes são obrigados a manter as respetivas propostas: 66 dias a contar do termo do prazo para a apresentação das propostas\nApresentação de Catálogo Eletrónico: Permitido\nIndicação de Subcontratação na Proposta: Inexistência de indicação de subcontratação\n14 - PRESTAÇÃO DE CAUÇÃO\nPrestação de caução: Não\n15 - FORNECIMENTO DAS PEÇAS DO CONCURSO, APRESENTAÇÃO DE PEDIDOS DE PARTICIPAÇÃO E APRESENTAÇÃO DAS PROPOSTAS\nLink para acesso às peças do concurso (URL): https://community.vortal.biz/Public/public-tender-documents/c2MxL1J6Q1lVVjBnTDNJdlZMbEl6L0UxVnlXdzdlZk9odGhtVklkVG14TGJVNEFhaEdFeGNGSjBZQ0lmTFhmWFRoWUIwbjlBV2JJYTZzcW9pSUhwdUE9PWRfUlkh\n20 - OUTROS REQUISITOS\nInformação sobre contratos reservados. Aplica-se a contratos reservados (54º-A)? Não\n21 - CRITÉRIO DE ADJUDICAÇÃO\nMultifator: Sim\nFator: \nNome: Preço\nPonderação: 70%\nSubfatores: Não\nFator: \nNome: Qualidade\nPonderação: 30%\nSubfatores: Não\n24 - CONDIÇÕES DO CONTRATO\nFaturação Eletrónica: Permitido\nObrigação de Subcontratação:\nCódigo da Obrigação de Subcontratação: Não é aplicável nenhuma obrigação de subcontratação.\n25 - COMPRA PÚBLICA ESTRATÉGICA\nCompra Pública Estratégica: Inexistência de contratação pública estratégica\n26 - INFORMAÇÕES ADICIONAIS\nContrato adequado para PME: Sim\nCobertura ACP (Acordo dos Contratos Públicos da Organização Mundial do Comércio): Não\n27 - IDENTIFICAÇÃO E CONTACTOS DO ÓRGÃO DE RECURSOS ADMINISTRATIVOS\nDesignação: Presidente do ISEG\nEndereço: Rua do Quelhas 6\nCódigo postal: 1200-781\nLocalidade: Lisboa\nTelefone: +351 213925800\nFax: +351 213925800\nEndereço eletrónico: presidenciaISEG@iseg.ulisboa.pt\n28 - IDENTIFICAÇÃO DO(S) AUTOR(ES) DE ANÚNCIO\nNome: Susana Rodrigues\nCargo: Técnica Superior\n29 - ALTERAÇÃO\nMotivo da Alteração: Correção pelo adquirente\nIdentificador da Versão do Anúncio a Alterar: b27f7170-091b-43e6-a133-fe23d6bf24d3-01\nIdentificador das Secções Alteradas do Anúncio Anterior: Condições de Apresentação\nDescrição das Alterações: Alterações a aspectos fundamentais das peças do procedimento\nAlteração dos Documentos do Concurso: Sim\nData de alteração dos documentos do concurso: 15-01-2026\n419948161",
    "nipc": "502488603",
    "distrito": "Lisboa",
    "concelho": "Lisboa",
    "freguesia": "Todas",
    "site": "www.iseg.ulisboa.pt",
    "email": "dlat@iseg.ulisboa.pt",
    "designacao_contrato": "Concurso Público para o Fornecimento e instalação de sistema de controlo de estacionamento para os 3 Parques de Estacionamento do ISEG",
    "descricao": "Concurso Público para o Fornecimento e instalação de sistema de controlo de estacionamento para os 3 Parques de Estacionamento do ISEG",
    "preco_base": "116.631,69 EUR",
    "prazo_execucao": "90 DIAS",
    "prazo_apresentacao_propostas": "09-02-2026 23:59",
    "fundos_eu": "Não",
    "plataforma_eletronica": "VORTAL",
    "url_procedimento": "https://community.vortal.biz/public/",
    "autor_nome": "Susana Rodrigues",
    "autor_cargo": "Técnica Superior"
  },
  {
    "numero_procedimento": "N/A",
    "entidade": "Unidade Local de Saúde do Alto Ave, EPE",
    "link": "https://diariodarepublica.pt/dr/detalhe/contrato-publico/988-1014253337",
    "detalhes_completos": "1 - IDENTIFICAÇÃO E CONTACTOS DA ENTIDADE ADJUDICANTE\nDesignação da entidade adjudicante: Unidade Local de Saúde do Alto Ave, EPE\nNIPC: 508080827\nEndereço: Rua dos Cutileiros, Creixomil\nCódigo postal: 4835-044\nLocalidade: Guimarães\nPaís: Portugal\nNUT III: PT119\nDistrito: Braga\nConcelho: Guimarães\nFreguesia: Todas\nTelefone: 253540330\nFax: 253513592\nEndereço da Entidade (URL): http://www.hospitaldeguimaraes.min-saude.pt/\nEndereço Eletrónico: aprovisionamento@hospitaldeguimaraes.min-saude.pt\neDelivery Gateway (URL): https://community.vortal.biz/public/\nFunção da Organização: Adquirente\nNorma jurídica da Entidade Adjudicante: Organismo de direito público\nÁrea de atividade da Autoridade Adjudicante: Saúde\n2 - JORNAL OFICIAL DA UNIÃO EUROPEIA\nO procedimento a que este anúncio diz respeito também é publicitado no Jornal Oficial da União Europeia? Não\n3 - AVISO\nModelo de Anúncio: Concurso público\nData de Envio do Anúncio: 16-01-2026\n5 - PROCESSO\nTipo de Procedimento: Concurso público\nPreço base do procedimento: Sim\nValor do preço base do procedimento: 22.606,91 EUR\nProcedimento com lotes? Não\n6 - OBJETO DO CONTRATO\nNúmero de referência interna: CP/1069/2025\nDesignação do contrato: Perímetro Computorizado\nDescrição: CP/1069/2025 - Perímetro Computorizado\nTipo de Contrato Principal: Aquisição de Bens Móveis\nTipo de Contrato: Aquisição de Bens Móveis\nClassificação CPV (Vocabulário Comum para os Contratos Públicos)\nObjeto principal\nVocabulário Principal: 33100000\nPreço base s/IVA: 22.606,91 EUR\n7 - INDICAÇÕES ADICIONAIS\nO contrato envolve aquisição conjunta (satisfação de várias entidades)? Não\nO contrato é adjudicado por uma central de compras? Não\n8 - TÉCNICAS\nO concurso destina-se à celebração de um acordo-quadro? Inexistência de acordo-quadro\nÉ utilizado um leilão eletrónico? Não\nÉ adotada uma fase de negociação? Não\nSistema de Aquisição Dinâmico: Inexistência de sistema de aquisição dinâmico\n9 - LOCAL DA EXECUÇÃO DO CONTRATO\nLOCAL DA EXECUÇÃO DO CONTRATO (PROCEDIMENTO)\nPaís: Portugal\nNUT III: PT119\nLocalidade: Braga\nDistrito: Braga\nConcelho: Guimarães\nFreguesia: Freguesia de Creixomil - Guimarães\n10 - PRAZO DE EXECUÇÃO DO CONTRATO\nPrazo de execução do contrato: 60 DIAS\nPrevisão de renovações: Não\n11 - FUNDOS EU\nTêm fundos EU? Não\n12 - DOCUMENTOS DE HABILITAÇÃO\nHabilitação para o exercício da atividade profissional: Não\n13 - CONDIÇÕES DE APRESENTAÇÃO\nPlataforma eletrónica utilizada pela entidade adjudicante: VORTAL\nURL para Apresentação: https://community.vortal.biz/public/\nAdmissibilidade da apresentação de propostas variantes: Não autorizado\nPrazo para apresentação das propostas: 26-01-2026 17:00\nPrazo durante o qual os concorrentes são obrigados a manter as respetivas propostas: 180 dias a contar do termo do prazo para a apresentação das propostas\nIndicação de Subcontratação na Proposta: Inexistência de indicação de subcontratação\n14 - PRESTAÇÃO DE CAUÇÃO\nPrestação de caução: Não\n15 - FORNECIMENTO DAS PEÇAS DO CONCURSO, APRESENTAÇÃO DE PEDIDOS DE PARTICIPAÇÃO E APRESENTAÇÃO DAS PROPOSTAS\nLink para acesso às peças do concurso (URL): https://community.vortal.biz/Public/public-tender-documents/d1FuQVYyMnFSZ0JuT2RBODRhVW13V2RZZ25XaklVbXVQSFg1ZDhUQnhHbXozcksvMWZHVTFTY3hUVisxK0U1R2Z4MFJod1FHdDkyWGxQU0lKTmhVU2c9PWZeKURY\n20 - OUTROS REQUISITOS\nInformação sobre contratos reservados. Aplica-se a contratos reservados (54º-A)? Não\n21 - CRITÉRIO DE ADJUDICAÇÃO\nMultifator: Sim\nFator: \nNome: Preço\nPonderação: 50%\nSubfatores: Não\nFator: \nNome: Qualidade\nPonderação: 40%\nSubfatores: Não\nFator: \nNome: Qualidade\nPonderação: 10%\nSubfatores: Não\n24 - CONDIÇÕES DO CONTRATO\nFaturação Eletrónica: Permitido\nObrigação de Subcontratação:\nCódigo da Obrigação de Subcontratação: Não é aplicável nenhuma obrigação de subcontratação.\n25 - COMPRA PÚBLICA ESTRATÉGICA\nCompra Pública Estratégica: Inexistência de contratação pública estratégica\n26 - INFORMAÇÕES ADICIONAIS\nContrato adequado para PME: Sim\nCobertura ACP (Acordo dos Contratos Públicos da Organização Mundial do Comércio): Não\n27 - IDENTIFICAÇÃO E CONTACTOS DO ÓRGÃO DE RECURSOS ADMINISTRATIVOS\nDesignação: Unidade Local de Saúde do Alto Ave\nEndereço: Rua dos Cutileiros\nCódigo postal: 4834-044\nLocalidade: Guimarães\nTelefone: +351 253540330\nFax: +351 253540330\nEndereço eletrónico: compras@ulsaaave.mm-saude.pt\n28 - IDENTIFICAÇÃO DO(S) AUTOR(ES) DE ANÚNCIO\nNome: Eng. Arlindo Soares \nCargo: Diretor Serviço Compras e Logística \n419948089",
    "nipc": "508080827",
    "distrito": "Braga",
    "concelho": "Guimarães",
    "freguesia": "Todas",
    "site": "http://www.hospitaldeguimaraes.min-saude.pt/",
    "email": "aprovisionamento@hospitaldeguimaraes.min-saude.pt",
    "designacao_contrato": "Perímetro Computorizado",
    "descricao": "CP/1069/2025 - Perímetro Computorizado",
    "preco_base": "22.606,91 EUR",
    "prazo_execucao": "60 DIAS",
    "prazo_apresentacao_propostas": "26-01-2026 17:00",
    "fundos_eu": "Não",
    "plataforma_eletronica": "VORTAL",
    "url_procedimento": "https://community.vortal.biz/public/",
    "autor_nome": "Eng. Arlindo Soares",
    "autor_cargo": "Diretor Serviço Compras e Logística"
  },
  {
    "numero_procedimento": "N/A",
    "entidade": "Unidade Local de Saúde de São João, EPE",
    "link": "https://diariodarepublica.pt/dr/detalhe/contrato-publico/996-1014253338",
    "detalhes_completos": "1 - IDENTIFICAÇÃO E CONTACTOS DA ENTIDADE ADJUDICANTE\nDesignação da entidade adjudicante: Unidade Local de Saúde de São João, EPE\nNIPC: 509821197\nEndereço: Alameda Prof. Hernâni Monteiro\nCódigo postal: 4200-319\nLocalidade: Área Metropolitana do Porto\nPaís: Portugal\nNUT III: PT11A\nDistrito: Porto\nConcelho: Porto\nFreguesia: Freguesia de Paranhos - Porto\nTelefone: 225512100\nFax: 225504463\nEndereço da Entidade (URL): https://portal-chsj.min-saude.pt/\nEndereço Eletrónico: geral@ulssjoao.min-saude.pt\neDelivery Gateway (URL): https://community.vortal.biz/public/\nFunção da Organização: Adquirente\nNorma jurídica da Entidade Adjudicante: Organismo de direito público\nÁrea de atividade da Autoridade Adjudicante: Saúde\n2 - JORNAL OFICIAL DA UNIÃO EUROPEIA\nO procedimento a que este anúncio diz respeito também é publicitado no Jornal Oficial da União Europeia? Não\n3 - AVISO\nModelo de Anúncio: Concurso público\nData de Envio do Anúncio: 16-01-2026\n5 - PROCESSO\nTipo de Procedimento: Concurso público\nPreço base do procedimento: Sim\nValor do preço base do procedimento: 148.300,00 EUR\nProcedimento com lotes? Não\n6 - OBJETO DO CONTRATO\nNúmero de referência interna: 31002326\nDesignação do contrato: Solução de Gestão de Armazéns Avançados com RFID\nDescrição: Solução de Gestão de Armazéns Avançados com RFID\nTipo de Contrato Principal: Aquisição de Bens Móveis\nTipo de Contrato: Aquisição de Bens Móveis\nClassificação CPV (Vocabulário Comum para os Contratos Públicos)\nObjeto principal\nVocabulário Principal: 48800000\nPreço base s/IVA: 148.300,00 EUR\n7 - INDICAÇÕES ADICIONAIS\nO contrato envolve aquisição conjunta (satisfação de várias entidades)? Não\nO contrato é adjudicado por uma central de compras? Não\n8 - TÉCNICAS\nO concurso destina-se à celebração de um acordo-quadro? Inexistência de acordo-quadro\nÉ utilizado um leilão eletrónico? Não\nÉ adotada uma fase de negociação? Não\nSistema de Aquisição Dinâmico: Inexistência de sistema de aquisição dinâmico\n9 - LOCAL DA EXECUÇÃO DO CONTRATO\nLOCAL DA EXECUÇÃO DO CONTRATO (PROCEDIMENTO)\nPaís: Portugal\nNUT III: PT11A\nLocalidade: Área Metropolitana do Porto\nDistrito: Porto\nConcelho: Porto\nFreguesia: Freguesia de Paranhos - Porto\n10 - PRAZO DE EXECUÇÃO DO CONTRATO\nPrazo de execução do contrato: 24 MESES\nPrevisão de renovações: Não\n11 - FUNDOS EU\nTêm fundos EU? Não\n12 - DOCUMENTOS DE HABILITAÇÃO\nHabilitação para o exercício da atividade profissional: Não\n13 - CONDIÇÕES DE APRESENTAÇÃO\nPlataforma eletrónica utilizada pela entidade adjudicante: VORTAL\nURL para Apresentação: https://community.vortal.biz/public/\nAdmissibilidade da apresentação de propostas variantes: Não autorizado\nPrazo para apresentação das propostas: 28-01-2026 17:00\nPrazo durante o qual os concorrentes são obrigados a manter as respetivas propostas: 90 dias a contar do termo do prazo para a apresentação das propostas\nIndicação de Subcontratação na Proposta: Inexistência de indicação de subcontratação\n14 - PRESTAÇÃO DE CAUÇÃO\nPrestação de caução: Não\n15 - FORNECIMENTO DAS PEÇAS DO CONCURSO, APRESENTAÇÃO DE PEDIDOS DE PARTICIPAÇÃO E APRESENTAÇÃO DAS PROPOSTAS\nLink para acesso às peças do concurso (URL): https://community.vortal.biz/Public/public-tender-documents/ajBiY3ZSdEh1eDBkdktUZU1IUnhFSW5nekxTa2Z4TU43VFoyV29pNGxWTkxvNDFGd0NWS0Q5RjhBdVZvQWFkSEg2b2pXODhTWWVMazJhUllEV1R0dkE9PUsoJFdt\n20 - OUTROS REQUISITOS\nInformação sobre contratos reservados. Aplica-se a contratos reservados (54º-A)? Não\n21 - CRITÉRIO DE ADJUDICAÇÃO\nMultifator: Sim\nFator: \nNome: Preço\nPonderação: 50%\nSubfatores: Não\nFator: \nNome: Preço\nPonderação: 20%\nSubfatores: Não\nFator: \nNome: Outros\nOutro Nome: Prazo de garantia e licenciamento\nPonderação: 10%\nSubfatores: Não\nFator: \nNome: Qualidade\nPonderação: 20%\nSubfatores: Não\n24 - CONDIÇÕES DO CONTRATO\nFaturação Eletrónica: Permitido\nObrigação de Subcontratação:\nCódigo da Obrigação de Subcontratação: Não é aplicável nenhuma obrigação de subcontratação.\n25 - COMPRA PÚBLICA ESTRATÉGICA\nCompra Pública Estratégica: Inexistência de contratação pública estratégica\n26 - INFORMAÇÕES ADICIONAIS\nContrato adequado para PME: Sim\nCobertura ACP (Acordo dos Contratos Públicos da Organização Mundial do Comércio): Não\n27 - IDENTIFICAÇÃO E CONTACTOS DO ÓRGÃO DE RECURSOS ADMINISTRATIVOS\nDesignação: Conselho de Administração\nEndereço: ULSSJ - Alameda Professor Hernani Monteiro\nCódigo postal: 4200-319\nLocalidade: Porto\nTelefone: +351 225512100\nFax: +351 225025766\nEndereço eletrónico: ca@ulssjoao.min-saude.pt\n28 - IDENTIFICAÇÃO DO(S) AUTOR(ES) DE ANÚNCIO\nNome: Tiago Ferreira\nCargo: Diretor do Serviço de Aprovisionamento \n419948183",
    "nipc": "509821197",
    "distrito": "Porto",
    "concelho": "Porto",
    "freguesia": "Freguesia de Paranhos - Porto",
    "site": "https://portal-chsj.min-saude.pt/",
    "email": "geral@ulssjoao.min-saude.pt",
    "designacao_contrato": "Solução de Gestão de Armazéns Avançados com RFID",
    "descricao": "Solução de Gestão de Armazéns Avançados com RFID",
    "preco_base": "148.300,00 EUR",
    "prazo_execucao": "24 MESES",
    "prazo_apresentacao_propostas": "28-01-2026 17:00",
    "fundos_eu": "Não",
    "plataforma_eletronica": "VORTAL",
    "url_procedimento": "https://community.vortal.biz/public/",
    "autor_nome": "Tiago Ferreira",
    "autor_cargo": "Diretor do Serviço de Aprovisionamento"
  },
  {
    "numero_procedimento": "N/A",
    "entidade": "Unidade Local de Saúde de São José, EPE",
    "link": "https://diariodarepublica.pt/dr/detalhe/contrato-publico/934-1014253339",
    "detalhes_completos": "1 - IDENTIFICAÇÃO E CONTACTOS DA ENTIDADE ADJUDICANTE\nDesignação da entidade adjudicante: Unidade Local de Saúde de São José, EPE\nNIPC: 508080142\nEndereço: Rua José António Serrano\nCódigo postal: 1150-199\nLocalidade: Lisboa\nPaís: Portugal\nNUT III: PT170\nDistrito: Lisboa\nConcelho: Lisboa\nFreguesia: Freguesia de Arroios - Lisboa\nTelefone: 218841403\nFax: 218841025\nEndereço da Entidade (URL): www.chlc.min-saude.pt\nEndereço Eletrónico: geral@chlc.min-saude.pt\neDelivery Gateway (URL): https://community.vortal.biz/public/\nFunção da Organização: Adquirente\nNorma jurídica da Entidade Adjudicante: Organismo de direito público\nÁrea de atividade da Autoridade Adjudicante: Saúde\n2 - JORNAL OFICIAL DA UNIÃO EUROPEIA\nO procedimento a que este anúncio diz respeito também é publicitado no Jornal Oficial da União Europeia? Não\n3 - AVISO\nModelo de Anúncio: Concurso público urgente\nData de Envio do Anúncio: 16-01-2026 15:18:00\n5 - PROCESSO\nTipo de Procedimento: Concurso público\nPreço base do procedimento: Sim\nValor do preço base do procedimento: 180.317,40 EUR\nProcedimento com lotes? Sim\nNº Máx. de Lotes Autorizado: 7\nNúmero máximo de lotes que podem ser adjudicados a um concorrente: 7\n6 - OBJETO DO CONTRATO\nNúmero de referência interna: 12011626\nDesignação do contrato: Agulhas, Kits, Sistemas, Tubos, e outros dispositivos médicos, para a ULS São José, EPE\nDescrição: Agulhas, Kits, Sistemas, Tubos, e outros dispositivos médicos, para a ULS São José, EPE\nTipo de Contrato Principal: Aquisição de Bens Móveis\nTipo de Contrato: Aquisição de Bens Móveis\nClassificação CPV (Vocabulário Comum para os Contratos Públicos)\nObjeto principal\nVocabulário Principal: 33140000\nPreço base s/IVA: 180.317,40 EUR\nLotes: \nNº: LOT-0001\nDescrição do Lote: Lote 1\nPreço base s/IVA: 10.000,00 EUR\nClassificação CPV (Vocabulário Comum para os Contratos Públicos)\nObjeto principal\nVocabulário Principal: 33140000\nNº: LOT-0002\nDescrição do Lote: Lote 2\nPreço base s/IVA: 11.670,00 EUR\nClassificação CPV (Vocabulário Comum para os Contratos Públicos)\nObjeto principal\nVocabulário Principal: 33140000\nNº: LOT-0003\nDescrição do Lote: Lote 3\nPreço base s/IVA: 32.500,00 EUR\nClassificação CPV (Vocabulário Comum para os Contratos Públicos)\nObjeto principal\nVocabulário Principal: 33140000\nNº: LOT-0004\nDescrição do Lote: Lote 4\nPreço base s/IVA: 3.250,80 EUR\nClassificação CPV (Vocabulário Comum para os Contratos Públicos)\nObjeto principal\nVocabulário Principal: 33140000\nNº: LOT-0005\nDescrição do Lote: Lote 5\nPreço base s/IVA: 5.260,00 EUR\nClassificação CPV (Vocabulário Comum para os Contratos Públicos)\nObjeto principal\nVocabulário Principal: 33140000\nNº: LOT-0006\nDescrição do Lote: Lote 6\nPreço base s/IVA: 60.066,60 EUR\nClassificação CPV (Vocabulário Comum para os Contratos Públicos)\nObjeto principal\nVocabulário Principal: 33140000\nNº: LOT-0007\nDescrição do Lote: Lote 7\nPreço base s/IVA: 57.570,00 EUR\nClassificação CPV (Vocabulário Comum para os Contratos Públicos)\nObjeto principal\nVocabulário Principal: 33140000\n7 - INDICAÇÕES ADICIONAIS\nO contrato envolve aquisição conjunta (satisfação de várias entidades)? Não\nO contrato é adjudicado por uma central de compras? Não\n8 - TÉCNICAS\nO concurso destina-se à celebração de um acordo-quadro? Inexistência de acordo-quadro\nÉ utilizado um leilão eletrónico? Não\nÉ adotada uma fase de negociação? Não\nSistema de Aquisição Dinâmico: Inexistência de sistema de aquisição dinâmico\n9 - LOCAL DA EXECUÇÃO DO CONTRATO\nLOCAL DA EXECUÇÃO DO CONTRATO (PROCEDIMENTO)\nPaís: Portugal\nNUT III: PT170\nLocalidade: Lisboa\nDistrito: Lisboa\nConcelho: Lisboa\nFreguesia: Freguesia de Arroios - Lisboa\nLOCAL DA EXECUÇÃO DO CONTRATO (LOTE)\nIdentificador do Lote: LOT-0001; LOT-0002; LOT-0003; LOT-0004; LOT-0005; LOT-0006; LOT-0007\nPaís: Portugal\nNUT III: PT170\nLocalidade: Lisboa\nDistrito: Lisboa\nConcelho: Lisboa\nFreguesia: Freguesia de Arroios - Lisboa\n10 - PRAZO DE EXECUÇÃO DO CONTRATO\nIdentificador do Lote: LOT-0001; LOT-0002; LOT-0003; LOT-0004; LOT-0005; LOT-0006; LOT-0007\nPrazo de execução do contrato: 344 DIAS\nPrevisão de renovações: Não\n11 - FUNDOS EU\nIdentificador do Lote: LOT-0001; LOT-0002; LOT-0003; LOT-0004; LOT-0005; LOT-0006; LOT-0007\nTêm fundos EU? Não\n12 - DOCUMENTOS DE HABILITAÇÃO\nHabilitação para o exercício da atividade profissional: Não\n13 - CONDIÇÕES DE APRESENTAÇÃO\nPlataforma eletrónica utilizada pela entidade adjudicante: VORTAL\nURL para Apresentação: https://community.vortal.biz/public/\nAdmissibilidade da apresentação de propostas variantes: Não autorizado\nPrazo para apresentação das propostas: 21-01-2026 23:59\nPrazo durante o qual os concorrentes são obrigados a manter as respetivas propostas: 10 dias a contar do termo do prazo para a apresentação das propostas\nIndicação de Subcontratação na Proposta: Inexistência de indicação de subcontratação\n14 - PRESTAÇÃO DE CAUÇÃO\nPrestação de caução: Não\n15 - FORNECIMENTO DAS PEÇAS DO CONCURSO, APRESENTAÇÃO DE PEDIDOS DE PARTICIPAÇÃO E APRESENTAÇÃO DAS PROPOSTAS\nLink para acesso às peças do concurso (URL): https://community.vortal.biz/Public/public-tender-documents/dUptOTd2U0U4WE5lQzMrKy9GS2UreE55RXRtak5qWTZJQUZzOWtBV2hRTTBBdk8ybzlCZ2VLK2kwcC82eGZnbmhIZzFvYXhxQUxWQ2l5eWMwUmtjN3c9PUdsTFlI\n20 - OUTROS REQUISITOS\nIdentificador do Lote: LOT-0001; LOT-0002; LOT-0003; LOT-0004; LOT-0005; LOT-0006; LOT-0007\nInformação sobre contratos reservados. Aplica-se a contratos reservados (54º-A)? Não\n21 - CRITÉRIO DE ADJUDICAÇÃO\nO Critério de adjudicação é diferenciado por lote? Não\nMultifator: Não\nMonofator:\nNome: Preço\n24 - CONDIÇÕES DO CONTRATO\nIdentificador do Lote: LOT-0001; LOT-0002; LOT-0003; LOT-0004; LOT-0005; LOT-0006; LOT-0007\nFaturação Eletrónica: Permitido\nObrigação de Subcontratação:\nCódigo da Obrigação de Subcontratação: Não é aplicável nenhuma obrigação de subcontratação.\n25 - COMPRA PÚBLICA ESTRATÉGICA\nCompra Pública Estratégica: Inexistência de contratação pública estratégica\n26 - INFORMAÇÕES ADICIONAIS\nIdentificador do Lote: LOT-0001; LOT-0002; LOT-0003; LOT-0004; LOT-0005; LOT-0006; LOT-0007\nContrato adequado para PME: Sim\nCobertura ACP (Acordo dos Contratos Públicos da Organização Mundial do Comércio): Não\n27 - IDENTIFICAÇÃO E CONTACTOS DO ÓRGÃO DE RECURSOS ADMINISTRATIVOS\nDesignação: Conselho de Administração\nEndereço: Rua António José Serrano\nCódigo postal: 1150-199\nLocalidade: Lisboa\nTelefone: +351 218841000\nFax: +351 218841283\nEndereço eletrónico: sec.vca@ulssjose.min-saude.pt\n28 - IDENTIFICAÇÃO DO(S) AUTOR(ES) DE ANÚNCIO\nNome: Área de Gestão de Compras\nCargo: Área de Gestão de Compras\n419948249",
    "nipc": "508080142",
    "distrito": "Lisboa",
    "concelho": "Lisboa",
    "freguesia": "Freguesia de Arroios - Lisboa",
    "site": "www.chlc.min-saude.pt",
    "email": "geral@chlc.min-saude.pt",
    "designacao_contrato": "Agulhas, Kits, Sistemas, Tubos, e outros dispositivos médicos, para a ULS São José, EPE",
    "descricao": "Agulhas, Kits, Sistemas, Tubos, e outros dispositivos médicos, para a ULS São José, EPE",
    "preco_base": "180.317,40 EUR",
    "prazo_execucao": "344 DIAS",
    "prazo_apresentacao_propostas": "21-01-2026 23:59",
    "fundos_eu": "Não",
    "plataforma_eletronica": "VORTAL",
    "url_procedimento": "https://community.vortal.biz/public/",
    "autor_nome": "Área de Gestão de Compras",
    "autor_cargo": "Área de Gestão de Compras"
  },
  {
    "numero_procedimento": "N/A",
    "entidade": "AnÃºncio de procedimento  n.Âº 999/2026  -  DiÃ¡rio da RepÃºblica n.Âº 11/2026, SÃ©rie II de 2026-01-16",
    "link": "https://diariodarepublica.pt/dr/detalhe/contrato-publico/999-1014253341"
  },
  {
    "numero_procedimento": "N/A",
    "entidade": "Município da Ribeira Grande",
    "link": "https://diariodarepublica.pt/dr/detalhe/contrato-publico/1003-1014253344",
    "detalhes_completos": "1 - IDENTIFICAÇÃO E CONTACTOS DA ENTIDADE ADJUDICANTE\nDesignação da entidade adjudicante: Município da Ribeira Grande\nNIPC: 512013241\nEndereço: Largo Conselheiro Hintze Ribeiro, s/nº\nCódigo postal: 9600-509\nLocalidade: Ribeira Grande\nPaís: Portugal\nNUT III: PT200\nDistrito: Região Autónoma dos Açores\nConcelho: Ribeira Grande\nFreguesia: Freguesia de Ribeira Grande (Conceição)\nTelefone: 296470730\nFax: 296470730\nEndereço da Entidade (URL): https://www.cm-ribeiragrande.pt/\nEndereço Eletrónico: geralcmrg@cm-ribeiragrande.pt\nFunção da Organização: Adquirente\nNorma jurídica da Entidade Adjudicante: Autoridade local\nÁrea de atividade da Autoridade Adjudicante: Serviços públicos das administrações públicas\n2 - JORNAL OFICIAL DA UNIÃO EUROPEIA\nO procedimento a que este anúncio diz respeito também é publicitado no Jornal Oficial da União Europeia? Não\n3 - AVISO\nModelo de Anúncio: Concurso público\nData de Envio do Anúncio: 16-01-2026\n5 - PROCESSO\nTipo de Procedimento: Concurso público\nPreço base do procedimento: Sim\nValor do preço base do procedimento: 119.000,00 EUR\nProcedimento com lotes? Sim\nNº Máx. de Lotes Autorizado: 3\nNúmero máximo de lotes que podem ser adjudicados a um concorrente: 3\n6 - OBJETO DO CONTRATO\nNúmero de referência interna: 2026/300.10.005/73\nDesignação do contrato: Concurso Público para a Locação de Autocarros, por lotes, incluindo motorista\nDescrição: Concurso Público para a Locação de Autocarros, por lotes, incluindo motorista\nTipo de Contrato Principal: Aquisição de Serviços\nTipo de Contrato: Aquisição de Serviços\nClassificação CPV (Vocabulário Comum para os Contratos Públicos)\nObjeto principal\nVocabulário Principal: 60172000\nPreço base s/IVA: 119.000,00 EUR\nLotes: \nNº: LOT-0001\nDescrição do Lote: Locação de Autocarros, incluindo motorista, no âmbito do Programa de Apoio Escolar para o ano de 2026 ¿ Fundo Social Municipal\nPreço base s/IVA: 85.000,00 EUR\nClassificação CPV (Vocabulário Comum para os Contratos Públicos)\nObjeto principal\nVocabulário Principal: 60172000\nNº: LOT-0002\nDescrição do Lote: Locação de Autocarros, incluindo motorista, para apoio aos eventos municipais\nPreço base s/IVA: 29.000,00 EUR\nClassificação CPV (Vocabulário Comum para os Contratos Públicos)\nObjeto principal\nVocabulário Principal: 60172000\nNº: LOT-0003\nDescrição do Lote: Locação de Autocarros, incluindo motorista, no âmbito do Programa Municipal ¿Crescer e Empreender\nPreço base s/IVA: 5.000,00 EUR\nClassificação CPV (Vocabulário Comum para os Contratos Públicos)\nObjeto principal\nVocabulário Principal: 60172000\n7 - INDICAÇÕES ADICIONAIS\nO contrato envolve aquisição conjunta (satisfação de várias entidades)? Não\nO contrato é adjudicado por uma central de compras? Não\n8 - TÉCNICAS\nO concurso destina-se à celebração de um acordo-quadro? Inexistência de acordo-quadro\nÉ utilizado um leilão eletrónico? Não\nÉ adotada uma fase de negociação? Sim\nSistema de Aquisição Dinâmico: Inexistência de sistema de aquisição dinâmico\n9 - LOCAL DA EXECUÇÃO DO CONTRATO\nLOCAL DA EXECUÇÃO DO CONTRATO (PROCEDIMENTO)\nLOCAL DA EXECUÇÃO DO CONTRATO (LOTE)\nIdentificador do Lote: LOT-0001\nPaís: Portugal\nNUT III: PT200\nLocalidade: Ribeira Grande\nDistrito: Região Autónoma dos Açores\nConcelho: Ribeira Grande\nFreguesia: Freguesia de Ribeira Grande (Matriz)\nIdentificador do Lote: LOT-0002\nPaís: Portugal\nNUT III: PT200\nLocalidade: Ribeira Grande\nDistrito: Região Autónoma dos Açores\nConcelho: Ribeira Grande\nFreguesia: Freguesia de Ribeira Grande (Matriz)\nIdentificador do Lote: LOT-0003\nPaís: Portugal\nNUT III: PT200\nLocalidade: Ribeira Grande\nDistrito: Região Autónoma dos Açores\nConcelho: Ribeira Grande\nFreguesia: Freguesia de Ribeira Grande (Matriz)\n10 - PRAZO DE EXECUÇÃO DO CONTRATO\nIdentificador do Lote: LOT-0001\nPrazo de execução do contrato: 330 DIAS\nPrevisão de renovações: Não\nIdentificador do Lote: LOT-0002\nPrazo de execução do contrato: 330 DIAS\nPrevisão de renovações: Não\nIdentificador do Lote: LOT-0003\nPrazo de execução do contrato: 330 DIAS\nPrevisão de renovações: Não\n11 - FUNDOS EU\nIdentificador do Lote: LOT-0001; LOT-0002; LOT-0003\nTêm fundos EU? Não\n12 - DOCUMENTOS DE HABILITAÇÃO\nHabilitação para o exercício da atividade profissional: Não\n13 - CONDIÇÕES DE APRESENTAÇÃO\nPlataforma eletrónica utilizada pela entidade adjudicante: ANOGOV\nURL para Apresentação: https://www.anogov.com/cm-ribeiragrande/faces/\nAdmissibilidade da apresentação de propostas variantes: Não autorizado\nPrazo para apresentação das propostas: 23-01-2026 00:59\nPrazo durante o qual os concorrentes são obrigados a manter as respetivas propostas: 66 dias a contar do termo do prazo para a apresentação das propostas\nApresentação de Catálogo Eletrónico: Permitido\nIndicação de Subcontratação na Proposta: O(s) subcontratante(s) proposto(s) necessário(s) para cumprir a obrigação de subcontratar uma percentagem mínima do contrato\n14 - PRESTAÇÃO DE CAUÇÃO\nPrestação de caução: Não\n15 - FORNECIMENTO DAS PEÇAS DO CONCURSO, APRESENTAÇÃO DE PEDIDOS DE PARTICIPAÇÃO E APRESENTAÇÃO DAS PROPOSTAS\nLink para acesso às peças do concurso (URL): https://www.anogov.com/cm-ribeiragrande/faces/app/acessoDocs.jsp?codigoAcesso=0WbnFUIfZTxohGeiLTfZ3usgJuotydd501Svj8sjAqZyZEWg1n\n20 - OUTROS REQUISITOS\nIdentificador do Lote: LOT-0001; LOT-0002; LOT-0003\nInformação sobre contratos reservados. Aplica-se a contratos reservados (54º-A)? Não\n21 - CRITÉRIO DE ADJUDICAÇÃO\nO Critério de adjudicação é diferenciado por lote? Não\nMultifator: Sim\nFator: \nNome: Preço\nPonderação: 40%\nSubfatores: Não\nFator: \nNome: Outros\nOutro Nome: B.\tCertificação de qualidade ao nível dos transportes coletivos de passageiros (ISO 9001/2015)\nPonderação: 20%\nSubfatores: Não\nFator: \nNome: Outros\nOutro Nome: Eficiência logística e impacto ambiental \nPonderação: 40%\nSubfatores: Não\n24 - CONDIÇÕES DO CONTRATO\nIdentificador do Lote: LOT-0001; LOT-0002; LOT-0003\nFaturação Eletrónica: Permitido\nObrigação de Subcontratação:\nCódigo da Obrigação de Subcontratação: Não é aplicável nenhuma obrigação de subcontratação.\n25 - COMPRA PÚBLICA ESTRATÉGICA\nCompra Pública Estratégica: Inexistência de contratação pública estratégica\n26 - INFORMAÇÕES ADICIONAIS\nIdentificador do Lote: LOT-0001\nContrato adequado para PME: Não\nCobertura ACP (Acordo dos Contratos Públicos da Organização Mundial do Comércio): Não\nIdentificador do Lote: LOT-0002\nContrato adequado para PME: Não\nCobertura ACP (Acordo dos Contratos Públicos da Organização Mundial do Comércio): Não\nIdentificador do Lote: LOT-0003\nContrato adequado para PME: Não\nCobertura ACP (Acordo dos Contratos Públicos da Organização Mundial do Comércio): Não\n27 - IDENTIFICAÇÃO E CONTACTOS DO ÓRGÃO DE RECURSOS ADMINISTRATIVOS\nDesignação: Municipio da Ribeira Grande\nEndereço: Largo Hintze Ribeiro\nCódigo postal: 9600-509\nLocalidade: Ribeira Grande\nEndereço eletrónico: dopt@cm-ribeiragrande.pt\nPrazo de interposição do recurso: 5 dias\n28 - IDENTIFICAÇÃO DO(S) AUTOR(ES) DE ANÚNCIO\nNome: Deia Melo\nCargo: Vice-Presidente da Câmara\n419948258",
    "nipc": "512013241",
    "distrito": "Região Autónoma dos Açores",
    "concelho": "Ribeira Grande",
    "freguesia": "Freguesia de Ribeira Grande (Conceição)",
    "site": "https://www.cm-ribeiragrande.pt/",
    "email": "geralcmrg@cm-ribeiragrande.pt",
    "designacao_contrato": "Concurso Público para a Locação de Autocarros, por lotes, incluindo motorista",
    "descricao": "Concurso Público para a Locação de Autocarros, por lotes, incluindo motorista",
    "preco_base": "119.000,00 EUR",
    "prazo_execucao": "330 DIAS",
    "prazo_apresentacao_propostas": "23-01-2026 00:59",
    "fundos_eu": "Não",
    "plataforma_eletronica": "ANOGOV",
    "url_procedimento": "https://www.anogov.com/cm-ribeiragrande/faces/",
    "autor_nome": "Deia Melo",
    "autor_cargo": "Vice-Presidente da Câmara"
  },
  {
    "numero_procedimento": "N/A",
    "entidade": "Entidade de Serviços Partilhados da Administração Pública, IP",
    "link": "https://diariodarepublica.pt/dr/detalhe/contrato-publico/1004-1014253356",
    "detalhes_completos": "1 - IDENTIFICAÇÃO E CONTACTOS DA ENTIDADE ADJUDICANTE\nDesignação da entidade adjudicante: Entidade de Serviços Partilhados da Administração Pública, IP\nNIPC: 510342191\nEndereço: Avenida Leite Vasconcelos 2, Alfragide,\nCódigo postal: 2614-502\nLocalidade: Amadora\nPaís: Portugal\nNUT III: PT170\nDistrito: Lisboa\nConcelho: Amadora\nFreguesia: Freguesia de Alfragide\nTelefone: 21 472 3100\nFax: 21 472 3100\nEndereço da Entidade (URL): https://www.espap.gov.pt/\nEndereço Eletrónico: gaj@espap.gov.pt\nFunção da Organização: Adquirente\nNorma jurídica da Entidade Adjudicante: Organismo de direito público\nÁrea de atividade da Autoridade Adjudicante: Serviços públicos das administrações públicas\n2 - JORNAL OFICIAL DA UNIÃO EUROPEIA\nO procedimento a que este anúncio diz respeito também é publicitado no Jornal Oficial da União Europeia? Não\n3 - AVISO\nModelo de Anúncio: Concurso público\nData de Envio do Anúncio: 16-01-2026\n5 - PROCESSO\nTipo de Procedimento: Concurso público\nPreço base do procedimento: Sim\nValor do preço base do procedimento: 178.264,23 EUR\nProcedimento com lotes? Não\n6 - OBJETO DO CONTRATO\nNúmero de referência interna: 2025_339\nDesignação do contrato: Consultadoria para implementação de metodologia de GPTI - PRR - Proj. 15\nDescrição: Serviços de consultadoria para implementação de metodologia de GPTI - Componente 17 do PRR - Proj 15 \nTipo de Contrato Principal: Aquisição de Serviços\nTipo de Contrato: Aquisição de Serviços\nClassificação CPV (Vocabulário Comum para os Contratos Públicos)\nObjeto principal\nVocabulário Principal: 72220000\nPreço base s/IVA: 178.264,23 EUR\n7 - INDICAÇÕES ADICIONAIS\nO contrato envolve aquisição conjunta (satisfação de várias entidades)? Não\nO contrato é adjudicado por uma central de compras? Não\n8 - TÉCNICAS\nO concurso destina-se à celebração de um acordo-quadro? Inexistência de acordo-quadro\nÉ utilizado um leilão eletrónico? Não\nÉ adotada uma fase de negociação? Não\nSistema de Aquisição Dinâmico: Inexistência de sistema de aquisição dinâmico\n9 - LOCAL DA EXECUÇÃO DO CONTRATO\nLOCAL DA EXECUÇÃO DO CONTRATO (PROCEDIMENTO)\nPaís: Portugal\nNUT III: PT170\nLocalidade: Alfragide\nDistrito: Lisboa\nConcelho: Amadora\nFreguesia: Freguesia de Alfragide\n10 - PRAZO DE EXECUÇÃO DO CONTRATO\nPrazo de execução do contrato: 5 MESES\nPrevisão de renovações: Não\n11 - FUNDOS EU\nTêm fundos EU? Sim\n12 - DOCUMENTOS DE HABILITAÇÃO\nHabilitação para o exercício da atividade profissional: Não\n13 - CONDIÇÕES DE APRESENTAÇÃO\nPlataforma eletrónica utilizada pela entidade adjudicante: ANOGOV\nURL para Apresentação: https://plataforma-sncp.espap.gov.pt/espap/faces/\nAdmissibilidade da apresentação de propostas variantes: Não autorizado\nPrazo para apresentação das propostas: 02-02-2026 13:59\nPrazo durante o qual os concorrentes são obrigados a manter as respetivas propostas: 66 dias a contar do termo do prazo para a apresentação das propostas\nApresentação de Catálogo Eletrónico: Não autorizado\nIndicação de Subcontratação na Proposta: A parte do contrato que o proponente tenciona subcontratar\n14 - PRESTAÇÃO DE CAUÇÃO\nPrestação de caução: Não\n15 - FORNECIMENTO DAS PEÇAS DO CONCURSO, APRESENTAÇÃO DE PEDIDOS DE PARTICIPAÇÃO E APRESENTAÇÃO DAS PROPOSTAS\nLink para acesso às peças do concurso (URL): https://plataforma-sncp.espap.gov.pt/espap/faces/app/acessoDocs.jsp?codigoAcesso=E0F2FjGm9kk5nFrRiosvx7GIVQJ8vvLqBk4z347m4zjF7fzbHB\n20 - OUTROS REQUISITOS\nInformação sobre contratos reservados. Aplica-se a contratos reservados (54º-A)? Não\n21 - CRITÉRIO DE ADJUDICAÇÃO\nMultifator: Não\nMonofator:\nNome: Preço\n24 - CONDIÇÕES DO CONTRATO\nFaturação Eletrónica: Permitido\nObrigação de Subcontratação:\nCódigo da Obrigação de Subcontratação: Não é aplicável nenhuma obrigação de subcontratação.\n25 - COMPRA PÚBLICA ESTRATÉGICA\nCompra Pública Estratégica: Inexistência de contratação pública estratégica\n26 - INFORMAÇÕES ADICIONAIS\nContrato adequado para PME: Sim\nCobertura ACP (Acordo dos Contratos Públicos da Organização Mundial do Comércio): Sim\n27 - IDENTIFICAÇÃO E CONTACTOS DO ÓRGÃO DE RECURSOS ADMINISTRATIVOS\nDesignação: Conselho Diretivo da ESPAP, I.P.\nEndereço: Av. Leite Vasconcelos 2\nCódigo postal: 2614-502\nLocalidade: Alfragide\nEndereço eletrónico: gaj@espap.gov.pt\n28 - IDENTIFICAÇÃO DO(S) AUTOR(ES) DE ANÚNCIO\nNome: Cátia Dâmaso\nCargo: Técnica Superior - Jurista\n419948143",
    "nipc": "510342191",
    "distrito": "Lisboa",
    "concelho": "Amadora",
    "freguesia": "Freguesia de Alfragide",
    "site": "https://www.espap.gov.pt/",
    "email": "gaj@espap.gov.pt",
    "designacao_contrato": "Consultadoria para implementação de metodologia de GPTI - PRR - Proj. 15",
    "descricao": "Serviços de consultadoria para implementação de metodologia de GPTI - Componente 17 do PRR - Proj 15",
    "preco_base": "178.264,23 EUR",
    "prazo_execucao": "5 MESES",
    "prazo_apresentacao_propostas": "02-02-2026 13:59",
    "fundos_eu": "Sim",
    "plataforma_eletronica": "ANOGOV",
    "url_procedimento": "https://plataforma-sncp.espap.gov.pt/espap/faces/",
    "autor_nome": "Cátia Dâmaso",
    "autor_cargo": "Técnica Superior - Jurista"
  },
  {
    "numero_procedimento": "N/A",
    "entidade": "AnÃºncio de procedimento  n.Âº 1001/2026  -  DiÃ¡rio da RepÃºblica n.Âº 11/2026, SÃ©rie II de 2026-01-16",
    "link": "https://diariodarepublica.pt/dr/detalhe/contrato-publico/1001-1014316375"
  },
  {
    "numero_procedimento": "N/A",
    "entidade": "Município de Vila Nova de Foz Côa",
    "link": "https://diariodarepublica.pt/dr/detalhe/contrato-publico/1002-1014316377",
    "detalhes_completos": "1 - IDENTIFICAÇÃO E CONTACTOS DA ENTIDADE ADJUDICANTE\nDesignação da entidade adjudicante: Município de Vila Nova de Foz Côa\nNIPC: 506829197\nServiço/Órgão/Pessoa de contacto: DAF- Contratação Pública\nEndereço: PRAÇA DO MUNICÍPIO\nCódigo postal: 5150-642\nLocalidade: VILA NOVA DE FOZ CÔA\nPaís: Portugal\nNUT III: PT11D\nDistrito: Guarda\nConcelho: Vila Nova de Foz Coa\nFreguesia: Freguesia de Vila Nova de Foz Côa\nTelefone: 279760400\nFax: 279760438\nEndereço da Entidade (URL): http://cm-fozcoa.pt/\nEndereço Eletrónico: correio@cm-fozcoa.pt\neDelivery Gateway (URL): https://www.acingov.pt\nFunção da Organização: Adquirente\nNorma jurídica da Entidade Adjudicante: Organismo de direito público\nÁrea de atividade da Autoridade Adjudicante: Serviços públicos das administrações públicas\n2 - JORNAL OFICIAL DA UNIÃO EUROPEIA\nO procedimento a que este anúncio diz respeito também é publicitado no Jornal Oficial da União Europeia? Não\n3 - AVISO\nModelo de Anúncio: Concurso público\nData de Envio do Anúncio: 16-01-2026\n5 - PROCESSO\nTipo de Procedimento: Concurso público\nPreço base do procedimento: Sim\nValor do preço base do procedimento: 181.000,00 EUR\nProcedimento com lotes? Sim\nNº Máx. de Lotes Autorizado: 2\nNúmero máximo de lotes que podem ser adjudicados a um concorrente: 2\n6 - OBJETO DO CONTRATO\nNúmero de referência interna: CP/6/2026\nDesignação do contrato: AQUISIÇÃO DE SERVIÇOS E ALUGUER DE EQUIPAMENTOS PARA A FESTA DA AQMENDOEIRA EM FLOR 2026\nDescrição: AQUISIÇÃO DE SERVIÇOS E ALUGUER DE EQUIPAMENTOS PARA A FESTA DA AQMENDOEIRA EM FLOR 2026\nTipo de Contrato Principal: Aquisição de Bens Móveis\nTipo de Contrato: Aquisição de Bens Móveis; Aquisição de Serviços\nClassificação CPV (Vocabulário Comum para os Contratos Públicos)\nObjeto principal\nVocabulário Principal: 37535200\nPreço base s/IVA: 181.000,00 EUR\nLotes: \nNº: LOT-0001\nDescrição do Lote: Lote 1-AQUISIÇÃO DE SERVIÇOS E ALUGUER DE EQUIPAMENTOS PARA A EXPOCÔA\nPreço base s/IVA: 161.000,00 EUR\nClassificação CPV (Vocabulário Comum para os Contratos Públicos)\nObjeto principal\nVocabulário Principal: 37535200\nNº: LOT-0002\nDescrição do Lote: Lote 2-DESFILE ETNOGRÁFICO\nPreço base s/IVA: 20.000,00 EUR\nClassificação CPV (Vocabulário Comum para os Contratos Públicos)\nObjeto principal\nVocabulário Principal: 37535200\n7 - INDICAÇÕES ADICIONAIS\nO contrato envolve aquisição conjunta (satisfação de várias entidades)? Não\nO contrato é adjudicado por uma central de compras? Não\n8 - TÉCNICAS\nO concurso destina-se à celebração de um acordo-quadro? Inexistência de acordo-quadro\nÉ utilizado um leilão eletrónico? Não\nÉ adotada uma fase de negociação? Não\nSistema de Aquisição Dinâmico: Inexistência de sistema de aquisição dinâmico\n9 - LOCAL DA EXECUÇÃO DO CONTRATO\nLOCAL DA EXECUÇÃO DO CONTRATO (PROCEDIMENTO)\nPaís: Portugal\nNUT III: PT11D\nLocalidade: Freguesia de Vila Nova de Foz Côa\nDistrito: Guarda\nConcelho: Vila Nova de Foz Coa\nFreguesia: Freguesia de Vila Nova de Foz Côa\nLOCAL DA EXECUÇÃO DO CONTRATO (LOTE)\nIdentificador do Lote: LOT-0001; LOT-0002\nPaís: Portugal\nNUT III: PT11D\nLocalidade: Vila Nova de Foz Côa\nDistrito: Guarda\nConcelho: Vila Nova de Foz Coa\nFreguesia: Freguesia de Custóias - Vila Nova de Foz Côa\n10 - PRAZO DE EXECUÇÃO DO CONTRATO\nIdentificador do Lote: LOT-0001; LOT-0002\nData de Início: 06-02-2026\nData de Fim: 13-03-2026\nPrevisão de renovações: Não\n11 - FUNDOS EU\nIdentificador do Lote: LOT-0001; LOT-0002\nTêm fundos EU? Não\n12 - DOCUMENTOS DE HABILITAÇÃO\nHabilitação para o exercício da atividade profissional: Não\n13 - CONDIÇÕES DE APRESENTAÇÃO\nPlataforma eletrónica utilizada pela entidade adjudicante: ACIN\nURL para Apresentação: https://www.acingov.pt\nAdmissibilidade da apresentação de propostas variantes: Não autorizado\nPrazo para apresentação das propostas: 23-01-2026 17:30\nPrazo durante o qual os concorrentes são obrigados a manter as respetivas propostas: 66 dias a contar do termo do prazo para a apresentação das propostas\nIndicação de Subcontratação na Proposta: Inexistência de indicação de subcontratação\n14 - PRESTAÇÃO DE CAUÇÃO\nPrestação de caução: Não\n15 - FORNECIMENTO DAS PEÇAS DO CONCURSO, APRESENTAÇÃO DE PEDIDOS DE PARTICIPAÇÃO E APRESENTAÇÃO DAS PROPOSTAS\nLink para acesso às peças do concurso (URL): https://www.acingov.pt/acingovprod/2/zonaPublica/zona_publica_c/donwloadProcedurePiece/MTA0ODU0Mw==\n20 - OUTROS REQUISITOS\nIdentificador do Lote: LOT-0001; LOT-0002\nInformação sobre contratos reservados. Aplica-se a contratos reservados (54º-A)? Não\n21 - CRITÉRIO DE ADJUDICAÇÃO\nO Critério de adjudicação é diferenciado por lote? Sim\nIdentificador do lote: LOT-0001\nMultifator: Sim\nFator: \nNome: Preço\nPonderação: 40%\nSubfatores: Não\nFator: \nNome: Outros\nOutro Nome: Estética\nPonderação: 60%\nSubfatores: Não\nO Critério de adjudicação é diferenciado por lote? Sim\nIdentificador do lote: LOT-0002\nMultifator: Sim\nFator: \nNome: Preço\nPonderação: 40%\nSubfatores: Não\nFator: \nNome: Outros\nOutro Nome: Estética\nPonderação: 60%\nSubfatores: Não\n24 - CONDIÇÕES DO CONTRATO\nIdentificador do Lote: LOT-0001; LOT-0002\nFaturação Eletrónica: Permitido\nObrigação de Subcontratação:\nCódigo da Obrigação de Subcontratação: Não é aplicável nenhuma obrigação de subcontratação.\n25 - COMPRA PÚBLICA ESTRATÉGICA\nCompra Pública Estratégica: Inexistência de contratação pública estratégica\n26 - INFORMAÇÕES ADICIONAIS\nIdentificador do Lote: LOT-0001; LOT-0002\nContrato adequado para PME: Não\nCobertura ACP (Acordo dos Contratos Públicos da Organização Mundial do Comércio): Não\n27 - IDENTIFICAÇÃO E CONTACTOS DO ÓRGÃO DE RECURSOS ADMINISTRATIVOS\nDesignação: Divisão Financeira e Administrativa\nEndereço: Praça do Município\nCódigo postal: 5150-642\nLocalidade: Vila Nova de Foz Côa\nTelefone: 279760401\nFax: \nEndereço eletrónico: correio@cm-fozcoa.pt\n28 - IDENTIFICAÇÃO DO(S) AUTOR(ES) DE ANÚNCIO\nNome: Eng. Pedro Miguel De Carvalho Duarte\nCargo: Presidente de câmara\n419948215",
    "nipc": "506829197",
    "distrito": "Guarda",
    "concelho": "Vila Nova de Foz Coa",
    "freguesia": "Freguesia de Vila Nova de Foz Côa",
    "site": "http://cm-fozcoa.pt/",
    "email": "correio@cm-fozcoa.pt",
    "designacao_contrato": "AQUISIÇÃO DE SERVIÇOS E ALUGUER DE EQUIPAMENTOS PARA A FESTA DA AQMENDOEIRA EM FLOR 2026",
    "descricao": "AQUISIÇÃO DE SERVIÇOS E ALUGUER DE EQUIPAMENTOS PARA A FESTA DA AQMENDOEIRA EM FLOR 2026",
    "preco_base": "181.000,00 EUR",
    "prazo_execucao": null,
    "prazo_apresentacao_propostas": "23-01-2026 17:30",
    "fundos_eu": "Não",
    "plataforma_eletronica": "ACIN",
    "url_procedimento": "https://www.acingov.pt",
    "autor_nome": "Eng. Pedro Miguel De Carvalho Duarte",
    "autor_cargo": "Presidente de câmara"
  }
]