[
  {
    "numero_procedimento": "N/A",
    "entidade": "AnÃºncio de procedimento  n.Âº 33362/2025  -  DiÃ¡rio da RepÃºblica n.Âº 247/2025, SÃ©rie II de 2025-12-24",
    "link": "https://diariodarepublica.pt/dr/detalhe/contrato-publico/33362-992625209"
  },
  {
    "numero_procedimento": "N/A",
    "entidade": "Águas do Algarve, SA",
    "link": "https://diariodarepublica.pt/dr/detalhe/contrato-publico/33363-992625210",
    "detalhes_completos": "Alteração do Anúncio de procedimento n.º 32661/2025, de 2025-12-17, com o ID 419894788\n\n1 - IDENTIFICAÇÃO E CONTACTOS DA ENTIDADE ADJUDICANTE\nDesignação da entidade adjudicante: Águas do Algarve, SA\nNIPC: 505176300\nServiço/Órgão/Pessoa de contacto: Departamento de Compras e Logística\nEndereço: Rua do Repouso, n.º 10\nCódigo postal: 8000-302\nLocalidade: Faro\nPaís: Portugal\nNUT III: PT150\nDistrito: Faro\nConcelho: Faro\nFreguesia: União das Freguesias de Faro (Sé e São Pedro)\nTelefone: 289899070\nEndereço da Entidade (URL): www.aguasdoalgarve.pt\nEndereço Eletrónico: geral.ada@adp.pt\neDelivery Gateway (URL): https://www.acingov.pt\nFunção da Organização: Adquirente\nSubfunção da Organização: Líder do grupo\nNorma jurídica da Entidade Adjudicante: Organismo de direito público\nÁrea de atividade da Entidade Adjudicante: Atividades relacionadas com a água\n\n2 - JORNAL OFICIAL DA UNIÃO EUROPEIA\nO procedimento a que este anúncio diz respeito também é publicitado no Jornal Oficial da União Europeia? Não\n\n3 - AVISO\nModelo de Anúncio: Concurso público\nData de Envio do Anúncio: 23-12-2025\n\n5 - PROCESSO\nTipo de Procedimento: Concurso público\nPreço base do procedimento: Sim\nValor do preço base do procedimento: 90.000,00 EUR\nProcedimento com lotes? Não\n\n6 - OBJETO DO CONTRATO\nNúmero de referência interna: SE.CP-AS-01/2025_Med. Autoproteção_Seg. Incêndios\nDesignação do contrato: Aquisição de Serviços para elaboração de Medidas de Autoproteção e Projetos de Segurança Contra Risco de Incêndios\nDescrição: Aquisição de Serviços para elaboração de Medidas de Autoproteção e Projetos de Segurança Contra Risco de Incêndios\nTipo de Contrato Principal: Aquisição de Serviços\nTipo de Contrato: Aquisição de Serviços\nClassificação CPV (Vocabulário Comum para os Contratos Públicos)\nObjeto principal\nVocabulário Principal: 71317100\nPreço base s/IVA: 90.000,00 EUR\n\n7 - INDICAÇÕES ADICIONAIS\nO contrato envolve aquisição conjunta (satisfação de várias entidades)? Não\nO contrato é adjudicado por uma central de compras? Sim\n\n8 - TÉCNICAS\nO concurso destina-se à celebração de um acordo-quadro? Inexistência de acordo-quadro\nÉ utilizado um leilão eletrónico? Não\nÉ adotada uma fase de negociação? Não\nSistema de Aquisição Dinâmico: Inexistência de sistema de aquisição dinâmico\n\n9 - LOCAL DA EXECUÇÃO DO CONTRATO\nLOCAL DA EXECUÇÃO DO CONTRATO (PROCEDIMENTO)\nPaís: Portugal\nNUT III: PT150\nLocalidade: Faro\nDistrito: Faro\nConcelho: Todos\nFreguesia: Todas\n\n10 - PRAZO DE EXECUÇÃO DO CONTRATO\nPrazo de execução do contrato: 24 MESES\nPrevisão de renovações: Não\n\n11 - FUNDOS EU\nTêm fundos EU? Não\n\n12 - DOCUMENTOS DE HABILITAÇÃO\nHabilitação para o exercício da atividade profissional: Não\n\n13 - CONDIÇÕES DE APRESENTAÇÃO\nPlataforma eletrónica utilizada pela entidade adjudicante: ACIN\nURL para Apresentação: https://www.acingov.pt\nAdmissibilidade da apresentação de propostas variantes: Não autorizado\nPrazo para apresentação das propostas: 17-02-2026 00:00\nPrazo durante o qual os concorrentes são obrigados a manter as respetivas propostas: 90 dias a contar do termo do prazo para a apresentação das propostas\nIndicação de Subcontratação na Proposta: Inexistência de indicação de subcontratação\n\n14 - PRESTAÇÃO DE CAUÇÃO\nPrestação de caução: Não\n\n15 - FORNECIMENTO DAS PEÇAS DO CONCURSO, APRESENTAÇÃO DE PEDIDOS DE PARTICIPAÇÃO E APRESENTAÇÃO DAS PROPOSTAS\nLink para acesso às peças do concurso (URL): https://www.acingov.pt/acingovprod/2/zonaPublica/zona_publica_c/donwloadProcedurePiece/MTAwNzExMA==\n\n20 - OUTROS REQUISITOS\nInformação sobre contratos reservados. Aplica-se a contratos reservados (54º-A)? Não\n\n21 - CRITÉRIO DE ADJUDICAÇÃO\nMultifator: Sim\nFator: \nNome: Preço\nPonderação: 40%\nSubfatores: Não\nFator: \nNome: Outros\nOutro Nome: Qualidade Técnica da Proposta\nPonderação: 60%\nSubfatores: Sim\nSubfatores: \nNome: Metodologia e organização dos trabalhos\nPonderação : 40%; \nNome: Equipa Técnica\nPonderação : 60%; \n\n24 - CONDIÇÕES DO CONTRATO\nFaturação Eletrónica: Necessário\nObrigação de Subcontratação:\nCódigo da Obrigação de Subcontratação: Não é aplicável nenhuma obrigação de subcontratação.\n\n25 - COMPRA PÚBLICA ESTRATÉGICA\nCompra Pública Estratégica: Inexistência de contratação pública estratégica\n\n26 - INFORMAÇÕES ADICIONAIS\nContrato adequado para PME: Sim\nCobertura ACP (Acordo dos Contratos Públicos da Organização Mundial do Comércio): Não\n\n27 - IDENTIFICAÇÃO E CONTACTOS DO ÓRGÃO DE RECURSOS ADMINISTRATIVOS\nDesignação: Águas do Algarve, S.A.\nEndereço: Rua do Repouso, n.º 10\nCódigo postal: 8000-302\nLocalidade: Faro\nTelefone: 289899070\nFax: \nEndereço eletrónico: geral.ada@adp.pt\nPrazo de interposição do recurso: 5 dias\n\n28 - IDENTIFICAÇÃO DO(S) AUTOR(ES) DE ANÚNCIO\nNome: Maria Isabel Fernandes da Silva Soares\nCargo: Presidente do Conselho de Administração\n\n29 - ALTERAÇÃO\nMotivo da Alteração: Informações atualizadas\nIdentificador da Versão do Anúncio a Alterar: 1e2a2ae5-6544-4d1e-aea4-afc2d3848613-01\nIdentificador das Secções Alteradas do Anúncio Anterior: Condições de Apresentação\nDescrição das Alterações: Modificação do prazo para a apresentação de propostas\nAlteração dos Documentos do Concurso: Sim\nData de alteração dos documentos do concurso: 22-12-2025\n419928994",
    "nipc": "505176300",
    "distrito": "Faro",
    "concelho": "Faro",
    "freguesia": "União das Freguesias de Faro (Sé e São Pedro)",
    "site": "www.aguasdoalgarve.pt",
    "email": "geral.ada@adp.pt",
    "designacao_contrato": "Aquisição de Serviços para elaboração de Medidas de Autoproteção e Projetos de Segurança Contra Risco de Incêndios",
    "descricao": "Aquisição de Serviços para elaboração de Medidas de Autoproteção e Projetos de Segurança Contra Risco de Incêndios",
    "preco_base": "90.000,00 EUR",
    "prazo_execucao": "24 MESES",
    "prazo_apresentacao_propostas": "17-02-2026 00:00",
    "fundos_eu": "Não",
    "plataforma_eletronica": "ACIN",
    "url_procedimento": "https://www.acingov.pt",
    "autor_nome": "Maria Isabel Fernandes da Silva Soares",
    "autor_cargo": "Presidente do Conselho de Administração"
  },
  {
    "numero_procedimento": "N/A",
    "entidade": "Município da Moita",
    "link": "https://diariodarepublica.pt/dr/detalhe/contrato-publico/33369-992625256",
    "detalhes_completos": "1 - IDENTIFICAÇÃO E CONTACTOS DA ENTIDADE ADJUDICANTE\nDesignação da entidade adjudicante: Município da Moita\nNIPC: 506791220\nServiço/Órgão/Pessoa de contacto: Juri\nEndereço: Praça da República\nCódigo postal: 2860-007\nLocalidade: Moita\nPaís: Portugal\nNUT III: PT170\nDistrito: Setúbal\nConcelho: Moita\nFreguesia: Todas\nTelefone: 212806700\nFax: 212806700\nEndereço da Entidade (URL): https://www.cm-moita.pt/\nEndereço Eletrónico: gab.aprovisionamento@cm-moita.pt\neDelivery Gateway (URL): https://www.acingov.pt\nFunção da Organização: Adquirente\nNorma jurídica da Entidade Adjudicante: Organismo de direito público\nÁrea de atividade da Autoridade Adjudicante: Serviços públicos das administrações públicas\n\n2 - JORNAL OFICIAL DA UNIÃO EUROPEIA\nO procedimento a que este anúncio diz respeito também é publicitado no Jornal Oficial da União Europeia? Não\n\n3 - AVISO\nModelo de Anúncio: Concurso público\nData de Envio do Anúncio: 23-12-2025\n\n5 - PROCESSO\nTipo de Procedimento: Concurso público\nPreço base do procedimento: Não\nProcedimento com lotes? Não\n\n6 - OBJETO DO CONTRATO\nNúmero de referência interna: 26/CP/CMM/2025\nDesignação do contrato: Prestação de Serviço de Consultoria em Gestão de Riscos de Corretagem de Seguros, incluindo a Assessoria na Realização de Procedimento(s) Pré-Contratual(ais) para Aquisição de Serviços de Seguros\nDescrição: Prestação de Serviço de Consultoria em Gestão de Riscos de\nCorretagem de Seguros, incluindo a Assessoria na Realização de\nProcedimento(s) Pré-Contratual(ais) para Aquisição de Serviços de\nSeguros\nTipo de Contrato Principal: Aquisição de Serviços\nTipo de Contrato: Aquisição de Serviços\nClassificação CPV (Vocabulário Comum para os Contratos Públicos)\nObjeto principal\nVocabulário Principal: 66518000\n\n7 - INDICAÇÕES ADICIONAIS\nO contrato envolve aquisição conjunta (satisfação de várias entidades)? Não\nO contrato é adjudicado por uma central de compras? Não\n\n8 - TÉCNICAS\nO concurso destina-se à celebração de um acordo-quadro? Inexistência de acordo-quadro\nÉ utilizado um leilão eletrónico? Não\nÉ adotada uma fase de negociação? Não\nSistema de Aquisição Dinâmico: Inexistência de sistema de aquisição dinâmico\n\n9 - LOCAL DA EXECUÇÃO DO CONTRATO\nLOCAL DA EXECUÇÃO DO CONTRATO (PROCEDIMENTO)\nPaís: Portugal\nNUT III: PT170\nLocalidade: Moita\nDistrito: Setúbal\nConcelho: Moita\nFreguesia: Todas\n\n10 - PRAZO DE EXECUÇÃO DO CONTRATO\nPrazo de execução do contrato: 36 MESES\nPrevisão de renovações: Não\n\n11 - FUNDOS EU\nTêm fundos EU? Não\n\n12 - DOCUMENTOS DE HABILITAÇÃO\nHabilitação para o exercício da atividade profissional: Não\n\n13 - CONDIÇÕES DE APRESENTAÇÃO\nPlataforma eletrónica utilizada pela entidade adjudicante: ACIN\nURL para Apresentação: https://www.acingov.pt\nAdmissibilidade da apresentação de propostas variantes: Não autorizado\nPrazo para apresentação das propostas: 01-01-2026 23:59\nPrazo durante o qual os concorrentes são obrigados a manter as respetivas propostas: 90 dias a contar do termo do prazo para a apresentação das propostas\nIndicação de Subcontratação na Proposta: Inexistência de indicação de subcontratação\n\n14 - PRESTAÇÃO DE CAUÇÃO\nPrestação de caução: Não\n\n15 - FORNECIMENTO DAS PEÇAS DO CONCURSO, APRESENTAÇÃO DE PEDIDOS DE PARTICIPAÇÃO E APRESENTAÇÃO DAS PROPOSTAS\nLink para acesso às peças do concurso (URL): https://www.acingov.pt/acingovprod/2/zonaPublica/zona_publica_c/donwloadProcedurePiece/MTAwODk1NA==\n\n20 - OUTROS REQUISITOS\nInformação sobre contratos reservados. Aplica-se a contratos reservados (54º-A)? Não\n\n21 - CRITÉRIO DE ADJUDICAÇÃO\nMultifator: Sim\nFator: \nNome: Outros\nOutro Nome: Experiência da equipa em gestão de riscos semelhantes\nPonderação: 40%\nSubfatores: Não\nFator: \nNome: Outros\nOutro Nome: Experiência da equipa em gestão de entidades públicas e financeiras\nPonderação: 40%\nSubfatores: Não\nFator: \nNome: Outros\nOutro Nome: Existência da equipa em gestão de seguros sobre pessoas\nPonderação: 20%\nSubfatores: Não\n\n24 - CONDIÇÕES DO CONTRATO\nFaturação Eletrónica: Não autorizado\nObrigação de Subcontratação:\nCódigo da Obrigação de Subcontratação: Não é aplicável nenhuma obrigação de subcontratação.\n\n25 - COMPRA PÚBLICA ESTRATÉGICA\nCompra Pública Estratégica: Inexistência de contratação pública estratégica\n\n26 - INFORMAÇÕES ADICIONAIS\nContrato adequado para PME: Sim\nCobertura ACP (Acordo dos Contratos Públicos da Organização Mundial do Comércio): Não\n\n27 - IDENTIFICAÇÃO E CONTACTOS DO ÓRGÃO DE RECURSOS ADMINISTRATIVOS\nDesignação: Presidente da Câmara\nEndereço: Praça da República\nCódigo postal: 2860-007\nLocalidade: Moita\nTelefone: 212806700\nFax: 212806700\nEndereço eletrónico: gab.aprovisionamento@cm-moita.pt\nPrazo de interposição do recurso: 10 dias\n\n28 - IDENTIFICAÇÃO DO(S) AUTOR(ES) DE ANÚNCIO\nNome: Carlos Edgar Rodrigues Sá Albino\nCargo: Presidente de Câmara\n419922691",
    "nipc": "506791220",
    "distrito": "Setúbal",
    "concelho": "Moita",
    "freguesia": "Todas",
    "site": "https://www.cm-moita.pt/",
    "email": "gab.aprovisionamento@cm-moita.pt",
    "designacao_contrato": "Prestação de Serviço de Consultoria em Gestão de Riscos de Corretagem de Seguros, incluindo a Assessoria na Realização de Procedimento(s) Pré-Contratual(ais) para Aquisição de Serviços de Seguros",
    "descricao": "Prestação de Serviço de Consultoria em Gestão de Riscos de",
    "preco_base": null,
    "prazo_execucao": "36 MESES",
    "prazo_apresentacao_propostas": "01-01-2026 23:59",
    "fundos_eu": "Não",
    "plataforma_eletronica": "ACIN",
    "url_procedimento": "https://www.acingov.pt",
    "autor_nome": "Carlos Edgar Rodrigues Sá Albino",
    "autor_cargo": "Presidente de Câmara"
  },
  {
    "numero_procedimento": "N/A",
    "entidade": "Município de Baião",
    "link": "https://diariodarepublica.pt/dr/detalhe/contrato-publico/33370-992625259",
    "detalhes_completos": "Alteração do Anúncio de procedimento n.º 32777/2025, de 2025-12-18, com o ID 419895792\n\n1 - IDENTIFICAÇÃO E CONTACTOS DA ENTIDADE ADJUDICANTE\nDesignação da entidade adjudicante: Município de Baião\nNIPC: 506854299\nServiço/Órgão/Pessoa de contacto: Municipio de Baião\nEndereço: Praça Heróis do Ultramar\nCódigo postal: 4640-158\nLocalidade: Campelo - Baião\nPaís: Portugal\nNUT III: PT11C\nDistrito: Porto\nConcelho: Baião\nFreguesia: União das Freguesias de Campelo e Ovil\nTelefone: 255540500\nFax: 255540510\nEndereço da Entidade (URL): www.cm-baiao.pt\nEndereço Eletrónico: compras.publicas@cm-baiao.pt\nFunção da Organização: Adquirente\nNorma jurídica da Entidade Adjudicante: Autoridade local\nÁrea de atividade da Autoridade Adjudicante: Serviços públicos das administrações públicas\n\n2 - JORNAL OFICIAL DA UNIÃO EUROPEIA\nO procedimento a que este anúncio diz respeito também é publicitado no Jornal Oficial da União Europeia? Não\n\n3 - AVISO\nModelo de Anúncio: Concurso público\nData de Envio do Anúncio: 23-12-2025\n\n5 - PROCESSO\nTipo de Procedimento: Concurso público\nPreço base do procedimento: Sim\nValor do preço base do procedimento: 74.681,25 EUR\nProcedimento com lotes? Não\n\n6 - OBJETO DO CONTRATO\nNúmero de referência interna: 59-2025\nDesignação do contrato: 59-2025-Aquisição de serviços no âmbito da candidatura \"Condomínios de Aldeia: Município de Baião/Transformação da Paisagem\"\nDescrição: Aquisição de serviços no âmbito da candidatura \"Condomínios de Aldeia: Município de Baião/Transformação da Paisagem\"\nTipo de Contrato Principal: Aquisição de Serviços\nTipo de Contrato: Aquisição de Serviços\nClassificação CPV (Vocabulário Comum para os Contratos Públicos)\nObjeto principal\nVocabulário Principal: 77230000\nPreço base s/IVA: 74.681,25 EUR\n\n7 - INDICAÇÕES ADICIONAIS\nO contrato envolve aquisição conjunta (satisfação de várias entidades)? Não\nO contrato é adjudicado por uma central de compras? Não\n\n8 - TÉCNICAS\nO concurso destina-se à celebração de um acordo-quadro? Inexistência de acordo-quadro\nÉ utilizado um leilão eletrónico? Não\nÉ adotada uma fase de negociação? Não\nSistema de Aquisição Dinâmico: Inexistência de sistema de aquisição dinâmico\n\n9 - LOCAL DA EXECUÇÃO DO CONTRATO\nLOCAL DA EXECUÇÃO DO CONTRATO (PROCEDIMENTO)\nPaís: Portugal\nNUT III: PT11C\nLocalidade: Baião\nDistrito: Porto\nConcelho: Baião\nFreguesia: Todas\n\n10 - PRAZO DE EXECUÇÃO DO CONTRATO\nPrazo de execução do contrato: 3 MESES\nPrevisão de renovações: Não\n\n11 - FUNDOS EU\nTêm fundos EU? Sim\n\n12 - DOCUMENTOS DE HABILITAÇÃO\nHabilitação para o exercício da atividade profissional: Não\n\n13 - CONDIÇÕES DE APRESENTAÇÃO\nPlataforma eletrónica utilizada pela entidade adjudicante: ANOGOV\nURL para Apresentação: https://www.anogov.com/cm-baiao/faces/\nAdmissibilidade da apresentação de propostas variantes: Não autorizado\nPrazo para apresentação das propostas: 31-12-2025 23:59\nPrazo durante o qual os concorrentes são obrigados a manter as respetivas propostas: 66 dias a contar do termo do prazo para a apresentação das propostas\nApresentação de Catálogo Eletrónico: Permitido\nIndicação de Subcontratação na Proposta: Inexistência de indicação de subcontratação\n\n14 - PRESTAÇÃO DE CAUÇÃO\nPrestação de caução: Não\n\n15 - FORNECIMENTO DAS PEÇAS DO CONCURSO, APRESENTAÇÃO DE PEDIDOS DE PARTICIPAÇÃO E APRESENTAÇÃO DAS PROPOSTAS\nLink para acesso às peças do concurso (URL): https://www.anogov.com/cm-baiao/faces/app/acessoDocs.jsp?codigoAcesso=vZkJTHl1y2Y1GyJhF6MNywilCAO1Nlsaozeu9xrAXdJFusNeDu\n\n20 - OUTROS REQUISITOS\nInformação sobre contratos reservados. Aplica-se a contratos reservados (54º-A)? Não\n\n21 - CRITÉRIO DE ADJUDICAÇÃO\nMultifator: Não\nMonofator:\nNome: Preço\n\n24 - CONDIÇÕES DO CONTRATO\nFaturação Eletrónica: Permitido\nObrigação de Subcontratação:\nCódigo da Obrigação de Subcontratação: Não é aplicável nenhuma obrigação de subcontratação.\n\n25 - COMPRA PÚBLICA ESTRATÉGICA\nCompra Pública Estratégica: Inexistência de contratação pública estratégica\n\n26 - INFORMAÇÕES ADICIONAIS\nContrato adequado para PME: Não\nCobertura ACP (Acordo dos Contratos Públicos da Organização Mundial do Comércio): Não\n\n27 - IDENTIFICAÇÃO E CONTACTOS DO ÓRGÃO DE RECURSOS ADMINISTRATIVOS\nDesignação: Município de Baião\nEndereço: Praça Heróis do Ultramar\nCódigo postal: 4640-158\nLocalidade: Baião\nTelefone: 255540500\nFax: 255540510\nEndereço eletrónico: aprovisionamento@cm-baiao.pt\n\n28 - IDENTIFICAÇÃO DO(S) AUTOR(ES) DE ANÚNCIO\nNome: Ana Raquel Coelho Azevedo\nCargo: Presidente da Câmara\n\n29 - ALTERAÇÃO\nMotivo da Alteração: Informações agora disponíveis\nIdentificador da Versão do Anúncio a Alterar: effa4f8c-640e-4fa6-b19b-b5b233eaead2-01\nIdentificador das Secções Alteradas do Anúncio Anterior: Condições de Apresentação\nDescrição das Alterações: Prorrogação de prazo, passando de 23/12/2025 para 31/12/2025\nAlteração dos Documentos do Concurso: Não\n419927251",
    "nipc": "506854299",
    "distrito": "Porto",
    "concelho": "Baião",
    "freguesia": "União das Freguesias de Campelo e Ovil",
    "site": "www.cm-baiao.pt",
    "email": "compras.publicas@cm-baiao.pt",
    "designacao_contrato": "59-2025-Aquisição de serviços no âmbito da candidatura \"Condomínios de Aldeia: Município de Baião/Transformação da Paisagem\"",
    "descricao": "Aquisição de serviços no âmbito da candidatura \"Condomínios de Aldeia: Município de Baião/Transformação da Paisagem\"",
    "preco_base": "74.681,25 EUR",
    "prazo_execucao": "3 MESES",
    "prazo_apresentacao_propostas": "31-12-2025 23:59",
    "fundos_eu": "Sim",
    "plataforma_eletronica": "ANOGOV",
    "url_procedimento": "https://www.anogov.com/cm-baiao/faces/",
    "autor_nome": "Ana Raquel Coelho Azevedo",
    "autor_cargo": "Presidente da Câmara"
  },
  {
    "numero_procedimento": "N/A",
    "entidade": "Instituto Português de Oncologia de Lisboa Francisco Gentil, EPE",
    "link": "https://diariodarepublica.pt/dr/detalhe/contrato-publico/33364-992627225",
    "detalhes_completos": "1 - IDENTIFICAÇÃO E CONTACTOS DA ENTIDADE ADJUDICANTE\nDesignação da entidade adjudicante: Instituto Português de Oncologia de Lisboa Francisco Gentil, EPE\nNIPC: 506361616\nEndereço: Rua Profº Lima Basto\nCódigo postal: 1099-023\nLocalidade: Lisboa\nPaís: Portugal\nNUT III: PT170\nDistrito: Lisboa\nConcelho: Lisboa\nFreguesia: Todas\nTelefone: 217229800\nFax: 217229880\nEndereço da Entidade (URL): www.ipolisboa.min-saude.pt/\nEndereço Eletrónico: ipofg@ipolisboa.min-saude.pt\neDelivery Gateway (URL): https://community.vortal.biz/public/\nFunção da Organização: Adquirente\nNorma jurídica da Entidade Adjudicante: Organismo de direito público\nÁrea de atividade da Autoridade Adjudicante: Saúde\n\n2 - JORNAL OFICIAL DA UNIÃO EUROPEIA\nO procedimento a que este anúncio diz respeito também é publicitado no Jornal Oficial da União Europeia? Não\n\n3 - AVISO\nModelo de Anúncio: Concurso público\nData de Envio do Anúncio: 23-12-2025\n\n5 - PROCESSO\nTipo de Procedimento: Concurso público\nPreço base do procedimento: Sim\nValor do preço base do procedimento: 1.800.000,00 EUR\nProcedimento com lotes? Não\n\n6 - OBJETO DO CONTRATO\nNúmero de referência interna: PN/299/2026\nDesignação do contrato: Empreitada de Obras de Remodelação do Piso de Internamento do Serviço de Pediatria\nDescrição: Empreitada de Obras de Remodelação do Piso de Internamento do Serviço de Pediatria\nTipo de Contrato Principal: Empreitada de Obras Públicas\nTipo de Contrato: Empreitada de Obras Públicas\nClassificação CPV (Vocabulário Comum para os Contratos Públicos)\nObjeto principal\nVocabulário Principal: 45215100\nPreço base s/IVA: 1.800.000,00 EUR\n\n7 - INDICAÇÕES ADICIONAIS\nO contrato envolve aquisição conjunta (satisfação de várias entidades)? Não\nO contrato é adjudicado por uma central de compras? Não\n\n8 - TÉCNICAS\nO concurso destina-se à celebração de um acordo-quadro? Inexistência de acordo-quadro\nÉ utilizado um leilão eletrónico? Não\nÉ adotada uma fase de negociação? Não\nSistema de Aquisição Dinâmico: Inexistência de sistema de aquisição dinâmico\n\n9 - LOCAL DA EXECUÇÃO DO CONTRATO\nLOCAL DA EXECUÇÃO DO CONTRATO (PROCEDIMENTO)\nPaís: Portugal\nNUT III: PT170\nLocalidade: Lisboa\nDistrito: Lisboa\nConcelho: Lisboa\nFreguesia: Freguesia de São Domingos de Benfica\n\n10 - PRAZO DE EXECUÇÃO DO CONTRATO\nPrazo de execução do contrato: 210 DIAS\nPrevisão de renovações: Não\n\n11 - FUNDOS EU\nTêm fundos EU? Não\n\n12 - DOCUMENTOS DE HABILITAÇÃO\nHabilitação para o exercício da atividade profissional: Não\n\n13 - CONDIÇÕES DE APRESENTAÇÃO\nPlataforma eletrónica utilizada pela entidade adjudicante: VORTAL\nURL para Apresentação: https://community.vortal.biz/public/\nAdmissibilidade da apresentação de propostas variantes: Não autorizado\nPrazo para apresentação das propostas: 15-01-2026 17:59\nPrazo durante o qual os concorrentes são obrigados a manter as respetivas propostas: 120 dias a contar do termo do prazo para a apresentação das propostas\nIndicação de Subcontratação na Proposta: Inexistência de indicação de subcontratação\n\n14 - PRESTAÇÃO DE CAUÇÃO\nPrestação de caução: Não\n\n15 - FORNECIMENTO DAS PEÇAS DO CONCURSO, APRESENTAÇÃO DE PEDIDOS DE PARTICIPAÇÃO E APRESENTAÇÃO DAS PROPOSTAS\nLink para acesso às peças do concurso (URL): https://community.vortal.biz/Public/public-tender-documents/eWczNTM4endBTHhza1E3aTF5eiswYlh0SzlqaHlGTkJTbi90WllNVjJKMEVxQndrcTNPNDJDa0VncGYwa01ZcnAyVDNwcHJoUXdVY2RFM2hQQ2tvS0E9PUtRXmVX\n\n20 - OUTROS REQUISITOS\nInformação sobre contratos reservados. Aplica-se a contratos reservados (54º-A)? Não\n\n21 - CRITÉRIO DE ADJUDICAÇÃO\nMultifator: Sim\nFator: \nNome: Preço\nPonderação: 20%\nSubfatores: Não\nFator: \nNome: Preço\nPonderação: 40%\nSubfatores: Não\nFator: \nNome: Qualidade\nPonderação: 40%\nSubfatores: Não\n\n24 - CONDIÇÕES DO CONTRATO\nFaturação Eletrónica: Permitido\nObrigação de Subcontratação:\nCódigo da Obrigação de Subcontratação: Não é aplicável nenhuma obrigação de subcontratação.\n\n25 - COMPRA PÚBLICA ESTRATÉGICA\nCompra Pública Estratégica: Inexistência de contratação pública estratégica\n\n26 - INFORMAÇÕES ADICIONAIS\nContrato adequado para PME: Sim\nCobertura ACP (Acordo dos Contratos Públicos da Organização Mundial do Comércio): Não\n\n27 - IDENTIFICAÇÃO E CONTACTOS DO ÓRGÃO DE RECURSOS ADMINISTRATIVOS\nDesignação: Conselho de Administração\nEndereço: Rua Prof. Lima Basto\nCódigo postal: 1099-023\nLocalidade: Lisboa\nTelefone: +351 217229800\nFax: +351 217229880\nEndereço eletrónico: ipofg@ipolisboa.min-saude.pt\n\n28 - IDENTIFICAÇÃO DO(S) AUTOR(ES) DE ANÚNCIO\nNome: Ricardo Costa \nCargo: Técnico Superior\n419930629",
    "nipc": "506361616",
    "distrito": "Lisboa",
    "concelho": "Lisboa",
    "freguesia": "Todas",
    "site": "www.ipolisboa.min-saude.pt/",
    "email": "ipofg@ipolisboa.min-saude.pt",
    "designacao_contrato": "Empreitada de Obras de Remodelação do Piso de Internamento do Serviço de Pediatria",
    "descricao": "Empreitada de Obras de Remodelação do Piso de Internamento do Serviço de Pediatria",
    "preco_base": "1.800.000,00 EUR",
    "prazo_execucao": "210 DIAS",
    "prazo_apresentacao_propostas": "15-01-2026 17:59",
    "fundos_eu": "Não",
    "plataforma_eletronica": "VORTAL",
    "url_procedimento": "https://community.vortal.biz/public/",
    "autor_nome": "Ricardo Costa",
    "autor_cargo": "Técnico Superior"
  },
  {
    "numero_procedimento": "N/A",
    "entidade": "Unidade de Saúde da Ilha de São Miguel",
    "link": "https://diariodarepublica.pt/dr/detalhe/contrato-publico/33365-992627226",
    "detalhes_completos": "1 - IDENTIFICAÇÃO E CONTACTOS DA ENTIDADE ADJUDICANTE\nDesignação da entidade adjudicante: Unidade de Saúde da Ilha de São Miguel\nNIPC: 510148921\nServiço/Órgão/Pessoa de contacto: Aprovisionamento\nEndereço: Grotinha, 1\nCódigo postal: 9500-354\nLocalidade: Ponta Delgada\nPaís: Portugal\nNUT III: PT200\nDistrito: Região Autónoma dos Açores\nConcelho: Ponta Delgada\nFreguesia: Freguesia de Ponta Delgada (São Sebastião)\nTelefone: 296249220\nFax: 296249223\nEndereço da Entidade (URL): https://usism.azores.gov.pt/\nEndereço Eletrónico: sres-usismiguel@azores.gov.pt\neDelivery Gateway (URL): https://www.acingov.pt\nFunção da Organização: Adquirente\nNorma jurídica da Entidade Adjudicante: Organismo de direito público\nÁrea de atividade da Autoridade Adjudicante: Saúde\n\n2 - JORNAL OFICIAL DA UNIÃO EUROPEIA\nO procedimento a que este anúncio diz respeito também é publicitado no Jornal Oficial da União Europeia? Não\n\n3 - AVISO\nModelo de Anúncio: Concurso público\nData de Envio do Anúncio: 23-12-2025\n\n5 - PROCESSO\nTipo de Procedimento: Concurso público\nPreço base do procedimento: Sim\nValor do preço base do procedimento: 36.000,00 EUR\nProcedimento com lotes? Não\n\n6 - OBJETO DO CONTRATO\nNúmero de referência interna: CPN/2025/0014\nDesignação do contrato: Concessão do direito de exploração das instalações de cafetaria/bar e refeitório nos Centros de Saúde de Ponta Delgada, de Ribeira Grande, de Vila Franca do Campo, de Povoação e de Nordeste\nDescrição: Concessão do direito de exploração das instalações de cafetaria/bar e refeitório nos Centros de Saúde de Ponta Delgada, de Ribeira Grande, de Vila Franca do Campo, de Povoação e de Nordeste\nTipo de Contrato Principal: Concessão de Serviços Públicos\nTipo de Contrato: Concessão de Serviços Públicos\nClassificação CPV (Vocabulário Comum para os Contratos Públicos)\nObjeto principal\nVocabulário Principal: 55511000\nPreço base s/IVA: 36.000,00 EUR\n\n7 - INDICAÇÕES ADICIONAIS\nO contrato envolve aquisição conjunta (satisfação de várias entidades)? Não\nO contrato é adjudicado por uma central de compras? Não\n\n8 - TÉCNICAS\nO concurso destina-se à celebração de um acordo-quadro? Inexistência de acordo-quadro\nÉ utilizado um leilão eletrónico? Não\nÉ adotada uma fase de negociação? Não\nSistema de Aquisição Dinâmico: Inexistência de sistema de aquisição dinâmico\n\n9 - LOCAL DA EXECUÇÃO DO CONTRATO\nLOCAL DA EXECUÇÃO DO CONTRATO (PROCEDIMENTO)\nPaís: Portugal\nNUT III: PT200\nLocalidade: Freguesia de Ribeira Grande (Conceição)\nDistrito: Região Autónoma dos Açores\nConcelho: Ribeira Grande\nFreguesia: Freguesia de Ribeira Grande (Conceição)\nPaís: Portugal\nNUT III: PT200\nLocalidade: Freguesia de Vila Franca do Campo (São Miguel)\nDistrito: Região Autónoma dos Açores\nConcelho: Vila Franca do Campo\nFreguesia: Freguesia de Vila Franca do Campo (São Miguel)\nPaís: Portugal\nNUT III: PT200\nLocalidade: Freguesia de Povoação\nDistrito: Região Autónoma dos Açores\nConcelho: Povoação\nFreguesia: Freguesia de Povoação\nPaís: Portugal\nNUT III: PT200\nLocalidade: Freguesia de Nordeste\nDistrito: Região Autónoma dos Açores\nConcelho: Nordeste\nFreguesia: Freguesia de Nordeste\n\n10 - PRAZO DE EXECUÇÃO DO CONTRATO\nPrazo de execução do contrato: 5 ANOS\nPrevisão de renovações: Não\n\n11 - FUNDOS EU\nTêm fundos EU? Não\n\n12 - DOCUMENTOS DE HABILITAÇÃO\nHabilitação para o exercício da atividade profissional: Não\n\n13 - CONDIÇÕES DE APRESENTAÇÃO\nPlataforma eletrónica utilizada pela entidade adjudicante: ACIN\nURL para Apresentação: https://www.acingov.pt\nAdmissibilidade da apresentação de propostas variantes: Não autorizado\nPrazo para apresentação das propostas: 07-01-2026 23:59\nPrazo durante o qual os concorrentes são obrigados a manter as respetivas propostas: 66 dias a contar do termo do prazo para a apresentação das propostas\nIndicação de Subcontratação na Proposta: A parte do contrato que o proponente tenciona subcontratar\n\n14 - PRESTAÇÃO DE CAUÇÃO\nPrestação de caução: Sim\nPercentagem: 3.33%\nDescrição da Garantia Exigida: Valor correspondente a dois meses da contrapartida financeira mensal indicada na proposta e aceite pelo concedente.\n\n15 - FORNECIMENTO DAS PEÇAS DO CONCURSO, APRESENTAÇÃO DE PEDIDOS DE PARTICIPAÇÃO E APRESENTAÇÃO DAS PROPOSTAS\nLink para acesso às peças do concurso (URL): https://www.acingov.pt/acingovprod/2/zonaPublica/zona_publica_c/donwloadProcedurePiece/MTAwOTM5NQ==\n\n20 - OUTROS REQUISITOS\nInformação sobre contratos reservados. Aplica-se a contratos reservados (54º-A)? Não\n\n21 - CRITÉRIO DE ADJUDICAÇÃO\nMultifator: Sim\nFator: \nNome: Outros\nOutro Nome: Renda\nPonderação: 60%\nSubfatores: Não\nFator: \nNome: Outros\nOutro Nome: Dimensão e Variedade da Oferta\nPonderação: 40%\nSubfatores: Não\n\n24 - CONDIÇÕES DO CONTRATO\nFaturação Eletrónica: Permitido\nObrigação de Subcontratação:\nCódigo da Obrigação de Subcontratação: O contratante tem de indicar qualquer mudança de subcontratantes durante a execução do contrato.\n\n25 - COMPRA PÚBLICA ESTRATÉGICA\nCompra Pública Estratégica: Inexistência de contratação pública estratégica\n\n26 - INFORMAÇÕES ADICIONAIS\nContrato adequado para PME: Sim\nCobertura ACP (Acordo dos Contratos Públicos da Organização Mundial do Comércio): Não\n\n27 - IDENTIFICAÇÃO E CONTACTOS DO ÓRGÃO DE RECURSOS ADMINISTRATIVOS\nDesignação: Secretaria Regional da Saúde e Segurança Social\nEndereço: Solar dos Remédios\nCódigo postal: 9701-855\nLocalidade: Angra do Heroísmo\nTelefone: 295204265\nFax: \nEndereço eletrónico: sres@azores.gov.pt\nPrazo de interposição do recurso: 30 dias\n\n28 - IDENTIFICAÇÃO DO(S) AUTOR(ES) DE ANÚNCIO\nNome: Tânia Sardinha\nCargo: Assistente Técnica\n419930597",
    "nipc": "510148921",
    "distrito": "Região Autónoma dos Açores",
    "concelho": "Ponta Delgada",
    "freguesia": "Freguesia de Ponta Delgada (São Sebastião)",
    "site": "https://usism.azores.gov.pt/",
    "email": "sres-usismiguel@azores.gov.pt",
    "designacao_contrato": "Concessão do direito de exploração das instalações de cafetaria/bar e refeitório nos Centros de Saúde de Ponta Delgada, de Ribeira Grande, de Vila Franca do Campo, de Povoação e de Nordeste",
    "descricao": "Concessão do direito de exploração das instalações de cafetaria/bar e refeitório nos Centros de Saúde de Ponta Delgada, de Ribeira Grande, de Vila Franca do Campo, de Povoação e de Nordeste",
    "preco_base": "36.000,00 EUR",
    "prazo_execucao": "5 ANOS",
    "prazo_apresentacao_propostas": "07-01-2026 23:59",
    "fundos_eu": "Não",
    "plataforma_eletronica": "ACIN",
    "url_procedimento": "https://www.acingov.pt",
    "autor_nome": "Tânia Sardinha",
    "autor_cargo": "Assistente Técnica"
  },
  {
    "numero_procedimento": "N/A",
    "entidade": "Fundação INATEL",
    "link": "https://diariodarepublica.pt/dr/detalhe/contrato-publico/33366-992627227",
    "detalhes_completos": "Alteração do Anúncio de procedimento n.º 33257/2025, de 2025-12-22, com o ID 419924068\n\n1 - IDENTIFICAÇÃO E CONTACTOS DA ENTIDADE ADJUDICANTE\nDesignação da entidade adjudicante: Fundação INATEL\nNIPC: 500122237\nEndereço: Calçada de Santana, nº 180\nCódigo postal: 1169-062\nLocalidade: Lisboa\nPaís: Portugal\nNUT III: PT170\nDistrito: Lisboa\nConcelho: Lisboa\nFreguesia: Freguesia de Arroios - Lisboa\nTelefone: 210027000\nFax: 210027000\nEndereço da Entidade (URL): https://www.inatel.pt\nEndereço Eletrónico: fundacao.inatel@inatel.pt\neDelivery Gateway (URL): https://www.acingov.pt\nFunção da Organização: Adquirente\nSubfunção da Organização: Organização cujo orçamento é utilizado para pagar o contrato; Organização que executa o pagamento; Organização que fornece informações adicionais sobre o processo de adjudicação; Organização que fornece mais informações sobre os prazos dos procedimentos de recurso; Organização que fornece acesso fora de linha aos documentos do concurso; Organização responsável pelo tratamento das propostas; Organização que recebe as propostas; Organização que trata os pedidos de participação; Organização que recebe pedidos de participação; Organização que fornece mais informações sobre os procedimentos de recurso; Organização que assina o contrato\nNorma jurídica da Entidade Adjudicante: Organismo de direito público\nÁrea de atividade da Autoridade Adjudicante: Atividades recreativas, culturais e religiosas\n\n2 - JORNAL OFICIAL DA UNIÃO EUROPEIA\nO procedimento a que este anúncio diz respeito também é publicitado no Jornal Oficial da União Europeia? Não\n\n3 - AVISO\nModelo de Anúncio: Concurso público\nData de Envio do Anúncio: 23-12-2025\n\n5 - PROCESSO\nTipo de Procedimento: Concurso público\nPreço base do procedimento: Sim\nValor do preço base do procedimento: 54.736,10 EUR\nProcedimento com lotes? Sim\nNº Máx. de Lotes Autorizado: 5\nNúmero máximo de lotes que podem ser adjudicados a um concorrente: 5\n\n6 - OBJETO DO CONTRATO\nNúmero de referência interna: P.25.327/NCP\nDesignação do contrato: P.25.327/NCP\nDescrição: Concurso Publico Nacional Aquisição de Carne de Bovino (fresca)para as Unidades Hoteleiras de Santa Maria da Feira, São Pedro do Sul, Luso, Vila Ruiva e Piódão da Fundação Inatel.\nTipo de Contrato Principal: Aquisição de Bens Móveis\nTipo de Contrato: Aquisição de Bens Móveis\nClassificação CPV (Vocabulário Comum para os Contratos Públicos)\nObjeto principal\nVocabulário Principal: 15111000\nPreço base s/IVA: 54.736,10 EUR\nLotes: \nNº: LOT-0001\nDescrição do Lote: Aquisição de carne de bovino fresca\nPreço base s/IVA: 504,50 EUR\nClassificação CPV (Vocabulário Comum para os Contratos Públicos)\nObjeto principal\nVocabulário Principal: 15111000\nNº: LOT-0002\nDescrição do Lote: Aquisição carne bovino fresca\nPreço base s/IVA: 925,00 EUR\nClassificação CPV (Vocabulário Comum para os Contratos Públicos)\nObjeto principal\nVocabulário Principal: 15111000\nNº: LOT-0003\nDescrição do Lote: Aquisição de carne bovino fresca\nPreço base s/IVA: 39.617,20 EUR\nClassificação CPV (Vocabulário Comum para os Contratos Públicos)\nObjeto principal\nVocabulário Principal: 15111000\nNº: LOT-0004\nDescrição do Lote: Aquisição de carne de bovino fresca\nPreço base s/IVA: 12.260,60 EUR\nClassificação CPV (Vocabulário Comum para os Contratos Públicos)\nObjeto principal\nVocabulário Principal: 15111000\nNº: LOT-0005\nDescrição do Lote: Aquisição de carne fresca de bovino\nPreço base s/IVA: 1.428,80 EUR\nClassificação CPV (Vocabulário Comum para os Contratos Públicos)\nObjeto principal\nVocabulário Principal: 15111000\n\n7 - INDICAÇÕES ADICIONAIS\nO contrato envolve aquisição conjunta (satisfação de várias entidades)? Não\nO contrato é adjudicado por uma central de compras? Não\n\n8 - TÉCNICAS\nO concurso destina-se à celebração de um acordo-quadro? Inexistência de acordo-quadro\nÉ utilizado um leilão eletrónico? Não\nÉ adotada uma fase de negociação? Não\nSistema de Aquisição Dinâmico: Inexistência de sistema de aquisição dinâmico\n\n9 - LOCAL DA EXECUÇÃO DO CONTRATO\nLOCAL DA EXECUÇÃO DO CONTRATO (PROCEDIMENTO)\nPaís: Portugal\nNUT III: PT11A\nLocalidade: Todas\nDistrito: Aveiro\nConcelho: Santa Maria da Feira\nFreguesia: Todas\nPaís: Portugal\nNUT III: PT11A\nLocalidade: Freguesia de Luso\nDistrito: Aveiro\nConcelho: Mealhada\nFreguesia: Freguesia de Luso\nPaís: Portugal\nNUT III: PT11A\nLocalidade: Todas\nDistrito: Viseu\nConcelho: São Pedro do Sul\nFreguesia: Todas\nPaís: Portugal\nNUT III: PT181\nLocalidade: Freguesia de Vila Ruiva - Cuba\nDistrito: Beja\nConcelho: Cuba\nFreguesia: Freguesia de Vila Ruiva - Cuba\nPaís: Portugal\nNUT III: PT16E\nLocalidade: Freguesia de Piódão\nDistrito: Coimbra\nConcelho: Arganil\nFreguesia: Freguesia de Piódão\nLOCAL DA EXECUÇÃO DO CONTRATO (LOTE)\nIdentificador do Lote: LOT-0001; LOT-0002; LOT-0003; LOT-0004; LOT-0005\nPaís: Portugal\nNUT III: PT11A\nLocalidade: Todas\nDistrito: Aveiro\nConcelho: Santa Maria da Feira\nFreguesia: Todas\nIdentificador do Lote: LOT-0001; LOT-0002; LOT-0003; LOT-0004; LOT-0005\nPaís: Portugal\nNUT III: PT11A\nLocalidade: Freguesia de Luso\nDistrito: Aveiro\nConcelho: Mealhada\nFreguesia: Freguesia de Luso\nIdentificador do Lote: LOT-0001; LOT-0002; LOT-0003; LOT-0004; LOT-0005\nPaís: Portugal\nNUT III: PT181\nLocalidade: Freguesia de Vila Ruiva - Cuba\nDistrito: Beja\nConcelho: Cuba\nFreguesia: Freguesia de Vila Ruiva - Cuba\nIdentificador do Lote: LOT-0001; LOT-0002; LOT-0003; LOT-0004; LOT-0005\nPaís: Portugal\nNUT III: PT16E\nLocalidade: Freguesia de Piódão\nDistrito: Coimbra\nConcelho: Arganil\nFreguesia: Freguesia de Piódão\nIdentificador do Lote: LOT-0001; LOT-0002; LOT-0003; LOT-0004; LOT-0005\nPaís: Portugal\nNUT III: PT11A\nLocalidade: Todas\nDistrito: Viseu\nConcelho: São Pedro do Sul\nFreguesia: Todas\n\n10 - PRAZO DE EXECUÇÃO DO CONTRATO\nIdentificador do Lote: LOT-0001; LOT-0002; LOT-0003; LOT-0004; LOT-0005\nPrazo de execução do contrato: 5 MESES\nPrevisão de renovações: Não\n\n11 - FUNDOS EU\nIdentificador do Lote: LOT-0001; LOT-0002; LOT-0003; LOT-0004; LOT-0005\nTêm fundos EU? Não\n\n12 - DOCUMENTOS DE HABILITAÇÃO\nHabilitação para o exercício da atividade profissional: Não\n\n13 - CONDIÇÕES DE APRESENTAÇÃO\nPlataforma eletrónica utilizada pela entidade adjudicante: ACIN\nURL para Apresentação: https://www.acingov.pt\nAdmissibilidade da apresentação de propostas variantes: Não autorizado\nPrazo para apresentação das propostas: 06-01-2026 23:59\nPrazo durante o qual os concorrentes são obrigados a manter as respetivas propostas: 66 dias a contar do termo do prazo para a apresentação das propostas\nIndicação de Subcontratação na Proposta: Inexistência de indicação de subcontratação\n\n14 - PRESTAÇÃO DE CAUÇÃO\nPrestação de caução: Não\n\n15 - FORNECIMENTO DAS PEÇAS DO CONCURSO, APRESENTAÇÃO DE PEDIDOS DE PARTICIPAÇÃO E APRESENTAÇÃO DAS PROPOSTAS\nLink para acesso às peças do concurso (URL): https://www.acingov.pt/acingovprod/2/zonaPublica/zona_publica_c/donwloadProcedurePiece/MTAwOTA3OA==\n\n20 - OUTROS REQUISITOS\nIdentificador do Lote: LOT-0001; LOT-0002; LOT-0003; LOT-0004; LOT-0005\nInformação sobre contratos reservados. Aplica-se a contratos reservados (54º-A)? Não\n\n21 - CRITÉRIO DE ADJUDICAÇÃO\nO Critério de adjudicação é diferenciado por lote? Não\nMultifator: Não\nMonofator:\nNome: Preço\n\n24 - CONDIÇÕES DO CONTRATO\nIdentificador do Lote: LOT-0001; LOT-0002; LOT-0003; LOT-0004; LOT-0005\nFaturação Eletrónica: Permitido\nObrigação de Subcontratação:\nCódigo da Obrigação de Subcontratação: Não é aplicável nenhuma obrigação de subcontratação.\n\n25 - COMPRA PÚBLICA ESTRATÉGICA\nCompra Pública Estratégica: Inexistência de contratação pública estratégica\n\n26 - INFORMAÇÕES ADICIONAIS\nIdentificador do Lote: LOT-0001; LOT-0002; LOT-0003; LOT-0004; LOT-0005\nContrato adequado para PME: Não\nCobertura ACP (Acordo dos Contratos Públicos da Organização Mundial do Comércio): Não\n\n27 - IDENTIFICAÇÃO E CONTACTOS DO ÓRGÃO DE RECURSOS ADMINISTRATIVOS\nDesignação: Conselho de Administração Fundação Inatel\nEndereço: Calçada de Santana, nº 180\nCódigo postal: 1169-062\nLocalidade: Lisboa\nTelefone: 210027000\nFax: 210027000\nEndereço eletrónico: fundacao.inatel@inatel.pt\nPrazo de interposição do recurso: 10 dias\n\n28 - IDENTIFICAÇÃO DO(S) AUTOR(ES) DE ANÚNCIO\nNome: Tiago Alves\nCargo: Técnico\n\n29 - ALTERAÇÃO\nMotivo da Alteração: Correção pelo adquirente\nIdentificador da Versão do Anúncio a Alterar: 93445712-753a-476b-8978-3e8b69b6be81-01\nIdentificador das Secções Alteradas do Anúncio Anterior: Condições de Apresentação; Identificação do(s) autor(es) do anúncio\nDescrição das Alterações: Modificação do prazo para a apresentação de propostas Atualização do(s) autor(es) do anúncio\nAlteração dos Documentos do Concurso: Não\n419926425",
    "nipc": "500122237",
    "distrito": "Lisboa",
    "concelho": "Lisboa",
    "freguesia": "Freguesia de Arroios - Lisboa",
    "site": "https://www.inatel.pt",
    "email": "fundacao.inatel@inatel.pt",
    "designacao_contrato": "P.25.327/NCP",
    "descricao": "Concurso Publico Nacional Aquisição de Carne de Bovino (fresca)para as Unidades Hoteleiras de Santa Maria da Feira, São Pedro do Sul, Luso, Vila Ruiva e Piódão da Fundação Inatel.",
    "preco_base": "54.736,10 EUR",
    "prazo_execucao": "5 MESES",
    "prazo_apresentacao_propostas": "06-01-2026 23:59",
    "fundos_eu": "Não",
    "plataforma_eletronica": "ACIN",
    "url_procedimento": "https://www.acingov.pt",
    "autor_nome": "Tiago Alves",
    "autor_cargo": "Técnico"
  },
  {
    "numero_procedimento": "N/A",
    "entidade": "Instituto Português de Oncologia de Lisboa Francisco Gentil, EPE",
    "link": "https://diariodarepublica.pt/dr/detalhe/contrato-publico/33367-992627228",
    "detalhes_completos": "1 - IDENTIFICAÇÃO E CONTACTOS DA ENTIDADE ADJUDICANTE\nDesignação da entidade adjudicante: Instituto Português de Oncologia de Lisboa Francisco Gentil, EPE\nNIPC: 506361616\nEndereço: Rua Profº Lima Basto\nCódigo postal: 1099-023\nLocalidade: Lisboa\nPaís: Portugal\nNUT III: PT170\nDistrito: Lisboa\nConcelho: Lisboa\nFreguesia: Todas\nTelefone: 217229800\nFax: 217229880\nEndereço da Entidade (URL): www.ipolisboa.min-saude.pt/\nEndereço Eletrónico: ipofg@ipolisboa.min-saude.pt\neDelivery Gateway (URL): https://community.vortal.biz/public/\nFunção da Organização: Adquirente\nNorma jurídica da Entidade Adjudicante: Organismo de direito público\nÁrea de atividade da Autoridade Adjudicante: Saúde\n\n2 - JORNAL OFICIAL DA UNIÃO EUROPEIA\nO procedimento a que este anúncio diz respeito também é publicitado no Jornal Oficial da União Europeia? Não\n\n3 - AVISO\nModelo de Anúncio: Concurso público\nData de Envio do Anúncio: 23-12-2025\n\n5 - PROCESSO\nTipo de Procedimento: Concurso público\nPreço base do procedimento: Sim\nValor do preço base do procedimento: 2.454.548,41 EUR\nProcedimento com lotes? Não\n\n6 - OBJETO DO CONTRATO\nNúmero de referência interna: PN/250/2026\nDesignação do contrato: Empreitada de Obras de Remodelação e Beneficiação do Serviço de Anatomia Patológica\nDescrição: Empreitada de Obras de Remodelação e Beneficiação do Serviço de Anatomia Patológica\nTipo de Contrato Principal: Empreitada de Obras Públicas\nTipo de Contrato: Empreitada de Obras Públicas\nClassificação CPV (Vocabulário Comum para os Contratos Públicos)\nObjeto principal\nVocabulário Principal: 45215100\nPreço base s/IVA: 2.454.548,41 EUR\n\n7 - INDICAÇÕES ADICIONAIS\nO contrato envolve aquisição conjunta (satisfação de várias entidades)? Não\nO contrato é adjudicado por uma central de compras? Não\n\n8 - TÉCNICAS\nO concurso destina-se à celebração de um acordo-quadro? Inexistência de acordo-quadro\nÉ utilizado um leilão eletrónico? Não\nÉ adotada uma fase de negociação? Não\nSistema de Aquisição Dinâmico: Inexistência de sistema de aquisição dinâmico\n\n9 - LOCAL DA EXECUÇÃO DO CONTRATO\nLOCAL DA EXECUÇÃO DO CONTRATO (PROCEDIMENTO)\nPaís: Portugal\nNUT III: PT170\nLocalidade: Lisboa\nDistrito: Lisboa\nConcelho: Lisboa\nFreguesia: Freguesia de São Domingos de Benfica\n\n10 - PRAZO DE EXECUÇÃO DO CONTRATO\nPrazo de execução do contrato: 300 DIAS\nPrevisão de renovações: Não\n\n11 - FUNDOS EU\nTêm fundos EU? Não\n\n12 - DOCUMENTOS DE HABILITAÇÃO\nHabilitação para o exercício da atividade profissional: Não\n\n13 - CONDIÇÕES DE APRESENTAÇÃO\nPlataforma eletrónica utilizada pela entidade adjudicante: VORTAL\nURL para Apresentação: https://community.vortal.biz/public/\nAdmissibilidade da apresentação de propostas variantes: Não autorizado\nPrazo para apresentação das propostas: 15-01-2026 17:59\nPrazo durante o qual os concorrentes são obrigados a manter as respetivas propostas: 120 dias a contar do termo do prazo para a apresentação das propostas\nIndicação de Subcontratação na Proposta: Inexistência de indicação de subcontratação\n\n14 - PRESTAÇÃO DE CAUÇÃO\nPrestação de caução: Não\n\n15 - FORNECIMENTO DAS PEÇAS DO CONCURSO, APRESENTAÇÃO DE PEDIDOS DE PARTICIPAÇÃO E APRESENTAÇÃO DAS PROPOSTAS\nLink para acesso às peças do concurso (URL): https://community.vortal.biz/Public/public-tender-documents/UTFyT0VHZndLSE4wczdVOUxFWEt3ZGxiK29obmVnYlAxREo3aEdsVk9qNFV0ZnIrekZrTms0YUgwSnQ1aEQrQ0ZmcklleWZRV1dvWFhpYmdCODNrZ0E9PWpBdTJR\n\n20 - OUTROS REQUISITOS\nInformação sobre contratos reservados. Aplica-se a contratos reservados (54º-A)? Não\n\n21 - CRITÉRIO DE ADJUDICAÇÃO\nMultifator: Sim\nFator: \nNome: Preço\nPonderação: 20%\nSubfatores: Não\nFator: \nNome: Preço\nPonderação: 40%\nSubfatores: Não\nFator: \nNome: Qualidade\nPonderação: 40%\nSubfatores: Não\n\n24 - CONDIÇÕES DO CONTRATO\nFaturação Eletrónica: Permitido\nObrigação de Subcontratação:\nCódigo da Obrigação de Subcontratação: Não é aplicável nenhuma obrigação de subcontratação.\n\n25 - COMPRA PÚBLICA ESTRATÉGICA\nCompra Pública Estratégica: Inexistência de contratação pública estratégica\n\n26 - INFORMAÇÕES ADICIONAIS\nContrato adequado para PME: Sim\nCobertura ACP (Acordo dos Contratos Públicos da Organização Mundial do Comércio): Não\n\n27 - IDENTIFICAÇÃO E CONTACTOS DO ÓRGÃO DE RECURSOS ADMINISTRATIVOS\nDesignação: Conselho de Administração\nEndereço: Rua Prof. Lima Basto\nCódigo postal: 1099-023\nLocalidade: Lisboa\nTelefone: +351 217229800\nFax: +351 217229880\nEndereço eletrónico: ipofg@ipolisboa.min-saude.pt\n\n28 - IDENTIFICAÇÃO DO(S) AUTOR(ES) DE ANÚNCIO\nNome: Ricardo Costa\nCargo: Técnico Superior\n419930856",
    "nipc": "506361616",
    "distrito": "Lisboa",
    "concelho": "Lisboa",
    "freguesia": "Todas",
    "site": "www.ipolisboa.min-saude.pt/",
    "email": "ipofg@ipolisboa.min-saude.pt",
    "designacao_contrato": "Empreitada de Obras de Remodelação e Beneficiação do Serviço de Anatomia Patológica",
    "descricao": "Empreitada de Obras de Remodelação e Beneficiação do Serviço de Anatomia Patológica",
    "preco_base": "2.454.548,41 EUR",
    "prazo_execucao": "300 DIAS",
    "prazo_apresentacao_propostas": "15-01-2026 17:59",
    "fundos_eu": "Não",
    "plataforma_eletronica": "VORTAL",
    "url_procedimento": "https://community.vortal.biz/public/",
    "autor_nome": "Ricardo Costa",
    "autor_cargo": "Técnico Superior"
  },
  {
    "numero_procedimento": "N/A",
    "entidade": "Instituto Português do Mar e da Atmosfera, IP",
    "link": "https://diariodarepublica.pt/dr/detalhe/contrato-publico/33368-992627230",
    "detalhes_completos": "1 - IDENTIFICAÇÃO E CONTACTOS DA ENTIDADE ADJUDICANTE\nDesignação da entidade adjudicante: Instituto Português do Mar e da Atmosfera, IP\nNIPC: 510265600\nServiço/Órgão/Pessoa de contacto: Conselho Diretivo\nEndereço: Rua C do Aeroporto de Lisboa\nCódigo postal: 1749-077\nLocalidade: Lisboa\nPaís: Portugal\nNUT III: PT170\nDistrito: Lisboa\nConcelho: Lisboa\nFreguesia: Freguesia de Olivais\nTelefone: 218447000\nFax: 218402370\nEndereço da Entidade (URL): https://www.ipma.pt\nEndereço Eletrónico: contratacao@ipma.pt\nFunção da Organização: Adquirente\nNorma jurídica da Entidade Adjudicante: Autoridade da administração central\nÁrea de atividade da Entidade Adjudicante: Atividades aeroportuárias\n\n2 - JORNAL OFICIAL DA UNIÃO EUROPEIA\nO procedimento a que este anúncio diz respeito também é publicitado no Jornal Oficial da União Europeia? Não\n\n3 - AVISO\nModelo de Anúncio: Concurso público\nData de Envio do Anúncio: 23-12-2025\n\n5 - PROCESSO\nTipo de Procedimento: Concurso público\nPreço base do procedimento: Sim\nValor do preço base do procedimento: 330.000,00 EUR\nProcedimento com lotes? Não\n\n6 - OBJETO DO CONTRATO\nNúmero de referência interna: CP 362/IPMA/2025\nDesignação do contrato: EMPREITADA DE OBRA PÚBLICA NA MODALIDADE DE CONCEÇÃO-CONSTRUÇÃO PARA RECUPERAÇÃO DE INFRAESTRUTURAS DA REDE GEOFÍSICA - CENTRO DE SÃO TEOTÓNIO\nDescrição: EMPREITADA DE OBRA PÚBLICA NA MODALIDADE DE CONCEÇÃO-CONSTRUÇÃO PARA RECUPERAÇÃO DE INFRAESTRUTURAS DA REDE GEOFÍSICA\nTipo de Contrato Principal: Empreitada de Obras Públicas\nTipo de Contrato: Empreitada de Obras Públicas\nClassificação CPV (Vocabulário Comum para os Contratos Públicos)\nObjeto principal\nVocabulário Principal: 45454000\nPreço base s/IVA: 330.000,00 EUR\n\n7 - INDICAÇÕES ADICIONAIS\nO contrato envolve aquisição conjunta (satisfação de várias entidades)? Não\nO contrato é adjudicado por uma central de compras? Não\n\n8 - TÉCNICAS\nO concurso destina-se à celebração de um acordo-quadro? Inexistência de acordo-quadro\nÉ utilizado um leilão eletrónico? Não\nÉ adotada uma fase de negociação? Não\nSistema de Aquisição Dinâmico: Inexistência de sistema de aquisição dinâmico\n\n9 - LOCAL DA EXECUÇÃO DO CONTRATO\nLOCAL DA EXECUÇÃO DO CONTRATO (PROCEDIMENTO)\nPaís: Portugal\nNUT III: PT181\nLocalidade: São Teotónio\nDistrito: Beja\nConcelho: Odemira\nFreguesia: Freguesia de São Teotónio\n\n10 - PRAZO DE EXECUÇÃO DO CONTRATO\nPrazo de execução do contrato: 120 DIAS\nPrevisão de renovações: Não\n\n11 - FUNDOS EU\nTêm fundos EU? Não\n\n12 - DOCUMENTOS DE HABILITAÇÃO\nHabilitação para o exercício da atividade profissional: Sim\nTipo: Alvará\nDescrição: Conforme definido nas peças do procedimento concursal\n\n13 - CONDIÇÕES DE APRESENTAÇÃO\nPlataforma eletrónica utilizada pela entidade adjudicante: ANOGOV\nURL para Apresentação: https://www.anogov.com/op-ipma/faces/\nAdmissibilidade da apresentação de propostas variantes: Não autorizado\nPrazo para apresentação das propostas: 06-01-2026 23:59\nPrazo durante o qual os concorrentes são obrigados a manter as respetivas propostas: 66 dias a contar do termo do prazo para a apresentação das propostas\nApresentação de Catálogo Eletrónico: Permitido\nIndicação de Subcontratação na Proposta: Inexistência de indicação de subcontratação\n\n14 - PRESTAÇÃO DE CAUÇÃO\nPrestação de caução: Não\n\n15 - FORNECIMENTO DAS PEÇAS DO CONCURSO, APRESENTAÇÃO DE PEDIDOS DE PARTICIPAÇÃO E APRESENTAÇÃO DAS PROPOSTAS\nLink para acesso às peças do concurso (URL): https://www.anogov.com/op-ipma/faces/app/acessoDocs.jsp?codigoAcesso=VzOC2vhdorejaXSq9JsEcw1ROupPk8DqZOaidIIKEuKyhJq82I\n\n20 - OUTROS REQUISITOS\nInformação sobre contratos reservados. Aplica-se a contratos reservados (54º-A)? Não\n\n21 - CRITÉRIO DE ADJUDICAÇÃO\nMultifator: Sim\nFator: \nNome: Outros\nOutro Nome: Fator ecologia\nPonderação: 10%\nSubfatores: Não\nFator: \nNome: Outros\nOutro Nome: Valia técnica\nPonderação: 40%\nSubfatores: Não\nFator: \nNome: Preço\nPonderação: 50%\nSubfatores: Não\n\n24 - CONDIÇÕES DO CONTRATO\nFaturação Eletrónica: Permitido\nObrigação de Subcontratação:\nCódigo da Obrigação de Subcontratação: Não é aplicável nenhuma obrigação de subcontratação.\n\n25 - COMPRA PÚBLICA ESTRATÉGICA\nCompra Pública Estratégica: Inexistência de contratação pública estratégica\n\n26 - INFORMAÇÕES ADICIONAIS\nContrato adequado para PME: Sim\nCobertura ACP (Acordo dos Contratos Públicos da Organização Mundial do Comércio): Sim\n\n27 - IDENTIFICAÇÃO E CONTACTOS DO ÓRGÃO DE RECURSOS ADMINISTRATIVOS\nDesignação: Conselho Diretivo do IPMA, I.P.\nEndereço: Rua C do Aeroporto de Lisboa\nCódigo postal: 1749-077\nLocalidade: Lisboa\nEndereço eletrónico: presidencia@ipma.pt\n\n28 - IDENTIFICAÇÃO DO(S) AUTOR(ES) DE ANÚNCIO\nNome: Elisa Policarpo\nCargo: Chefe da Divisão de Contratação\n419928637",
    "nipc": "510265600",
    "distrito": "Lisboa",
    "concelho": "Lisboa",
    "freguesia": "Freguesia de Olivais",
    "site": "https://www.ipma.pt",
    "email": "contratacao@ipma.pt",
    "designacao_contrato": "EMPREITADA DE OBRA PÚBLICA NA MODALIDADE DE CONCEÇÃO-CONSTRUÇÃO PARA RECUPERAÇÃO DE INFRAESTRUTURAS DA REDE GEOFÍSICA - CENTRO DE SÃO TEOTÓNIO",
    "descricao": "EMPREITADA DE OBRA PÚBLICA NA MODALIDADE DE CONCEÇÃO-CONSTRUÇÃO PARA RECUPERAÇÃO DE INFRAESTRUTURAS DA REDE GEOFÍSICA",
    "preco_base": "330.000,00 EUR",
    "prazo_execucao": "120 DIAS",
    "prazo_apresentacao_propostas": "06-01-2026 23:59",
    "fundos_eu": "Não",
    "plataforma_eletronica": "ANOGOV",
    "url_procedimento": "https://www.anogov.com/op-ipma/faces/",
    "autor_nome": "Elisa Policarpo",
    "autor_cargo": "Chefe da Divisão de Contratação"
  },
  {
    "numero_procedimento": "N/A",
    "entidade": "Agência para o Desenvolvimento e Coesão, IP",
    "link": "https://diariodarepublica.pt/dr/detalhe/contrato-publico/33371-992627263",
    "detalhes_completos": "1 - IDENTIFICAÇÃO E CONTACTOS DA ENTIDADE ADJUDICANTE\nDesignação da entidade adjudicante: Agência para o Desenvolvimento e Coesão, IP\nNIPC: 510928374\nServiço/Órgão/Pessoa de contacto: NGCP\nEndereço: Av. 5 de Outubro, 153\nCódigo postal: 1050-053\nLocalidade: Lisboa\nPaís: Portugal\nNUT III: PT170\nDistrito: Lisboa\nConcelho: Lisboa\nFreguesia: Freguesia de Avenidas Novas\nTelefone: 218814000\nFax: 218881111\nEndereço da Entidade (URL): https://www.adcoesao.pt/\nEndereço Eletrónico: contratacao@adcoesao.pt\neDelivery Gateway (URL): https://www.acingov.pt\nFunção da Organização: Adquirente\nNorma jurídica da Entidade Adjudicante: Organismo de direito público\nÁrea de atividade da Autoridade Adjudicante: Serviços públicos das administrações públicas\n\n2 - JORNAL OFICIAL DA UNIÃO EUROPEIA\nO procedimento a que este anúncio diz respeito também é publicitado no Jornal Oficial da União Europeia? Sim\n\n3 - AVISO\nModelo de Anúncio: Concurso público\nData de Envio do Anúncio: 22-12-2025\n\n5 - PROCESSO\nTipo de Procedimento: Concurso público\nPreço base do procedimento: Sim\nValor do preço base do procedimento: 450.000,00 EUR\nProcedimento com lotes? Não\n\n6 - OBJETO DO CONTRATO\nNúmero de referência interna: R/188/2025\nDesignação do contrato: Aquisição de serviços de viagens, alojamentos e serviços conexos para 36 meses\nDescrição: Aquisição de serviços de viagens, alojamentos e serviços conexos para 36 meses\nOpções: Não\nTipo de Contrato Principal: Aquisição de Serviços\nTipo de Contrato: Aquisição de Serviços\nClassificação CPV (Vocabulário Comum para os Contratos Públicos)\nObjeto principal\nVocabulário Principal: 63510000\nPreço base s/IVA: 450.000,00 EUR\n\n7 - INDICAÇÕES ADICIONAIS\nO contrato envolve aquisição conjunta (satisfação de várias entidades)? Não\nO contrato é adjudicado por uma central de compras? Não\n\n8 - TÉCNICAS\nO concurso destina-se à celebração de um acordo-quadro? Inexistência de acordo-quadro\nÉ utilizado um leilão eletrónico? Não\nÉ adotada uma fase de negociação? Não\nSistema de Aquisição Dinâmico: Inexistência de sistema de aquisição dinâmico\n\n9 - LOCAL DA EXECUÇÃO DO CONTRATO\nLOCAL DA EXECUÇÃO DO CONTRATO (PROCEDIMENTO)\nPaís: Portugal\nNUT III: PT170\nLocalidade: Freguesia de Avenidas Novas\nDistrito: Lisboa\nConcelho: Lisboa\nFreguesia: Freguesia de Avenidas Novas\n\n10 - PRAZO DE EXECUÇÃO DO CONTRATO\nPrazo de execução do contrato: 36 MESES\nPrevisão de renovações: Não\n\n11 - FUNDOS EU\nTêm fundos EU? Sim\n\n12 - DOCUMENTOS DE HABILITAÇÃO\nHabilitação para o exercício da atividade profissional: Não\n\n13 - CONDIÇÕES DE APRESENTAÇÃO\nPlataforma eletrónica utilizada pela entidade adjudicante: ACIN\nURL para Apresentação: https://www.acingov.pt\nAdmissibilidade da apresentação de propostas variantes: Não autorizado\nPrazo para apresentação das propostas: 21-01-2026 23:59\nPrazo durante o qual os concorrentes são obrigados a manter as respetivas propostas: 120 dias a contar do termo do prazo para a apresentação das propostas\nApresentação de Catálogo Eletrónico: Permitido\nIndicação de Subcontratação na Proposta: Inexistência de indicação de subcontratação\n\n14 - PRESTAÇÃO DE CAUÇÃO\nPrestação de caução: Sim\nPercentagem: 5%\nDescrição da Garantia Exigida: O valor da caução é de 5.00% do preço contratual.\n\n15 - FORNECIMENTO DAS PEÇAS DO CONCURSO, APRESENTAÇÃO DE PEDIDOS DE PARTICIPAÇÃO E APRESENTAÇÃO DAS PROPOSTAS\nLink para acesso às peças do concurso (URL): https://www.acingov.pt/acingovprod/2/zonaPublica/zona_publica_c/donwloadProcedurePiece/MTAwNzI1OA==\n\n20 - OUTROS REQUISITOS\nInformação sobre contratos reservados. Aplica-se a contratos reservados (54º-A)? Não\n\n21 - CRITÉRIO DE ADJUDICAÇÃO\nMultifator: Sim\nFator: \nNome: Outros\nOutro Nome: Pontuação das taxas de serviço\nPonderação: 70%\nSubfatores: Não\nFator: \nNome: Outros\nOutro Nome: Desconto anual proposto\nPonderação: 30%\nSubfatores: Não\n\n24 - CONDIÇÕES DO CONTRATO\nFaturação Eletrónica: Necessário\nObrigação de Subcontratação:\nCódigo da Obrigação de Subcontratação: Não é aplicável nenhuma obrigação de subcontratação.\n\n25 - COMPRA PÚBLICA ESTRATÉGICA\nCompra Pública Estratégica: Inexistência de contratação pública estratégica\n\n26 - INFORMAÇÕES ADICIONAIS\nContrato adequado para PME: Sim\nCobertura ACP (Acordo dos Contratos Públicos da Organização Mundial do Comércio): Não\n\n27 - IDENTIFICAÇÃO E CONTACTOS DO ÓRGÃO DE RECURSOS ADMINISTRATIVOS\nDesignação: Conselho Diretivo\nEndereço: Avenida 5 de Outubro, 153\nCódigo postal: 1050-053\nLocalidade: Lisboa\nTelefone: 218814000\nFax: \nEndereço eletrónico: agencia@adcoesao.pt\n\n28 - IDENTIFICAÇÃO DO(S) AUTOR(ES) DE ANÚNCIO\nNome: Leonor Lei\nCargo: Coordenadora do NGCP\n419916868",
    "nipc": "510928374",
    "distrito": "Lisboa",
    "concelho": "Lisboa",
    "freguesia": "Freguesia de Avenidas Novas",
    "site": "https://www.adcoesao.pt/",
    "email": "contratacao@adcoesao.pt",
    "designacao_contrato": "Aquisição de serviços de viagens, alojamentos e serviços conexos para 36 meses",
    "descricao": "Aquisição de serviços de viagens, alojamentos e serviços conexos para 36 meses",
    "preco_base": "450.000,00 EUR",
    "prazo_execucao": "36 MESES",
    "prazo_apresentacao_propostas": "21-01-2026 23:59",
    "fundos_eu": "Sim",
    "plataforma_eletronica": "ACIN",
    "url_procedimento": "https://www.acingov.pt",
    "autor_nome": "Leonor Lei",
    "autor_cargo": "Coordenadora do NGCP"
  },
  {
    "numero_procedimento": "N/A",
    "entidade": "Agência para o Desenvolvimento e Coesão, IP",
    "link": "https://diariodarepublica.pt/dr/detalhe/contrato-publico/33373-992627264",
    "detalhes_completos": "1 - IDENTIFICAÇÃO E CONTACTOS DA ENTIDADE ADJUDICANTE\nDesignação da entidade adjudicante: Agência para o Desenvolvimento e Coesão, IP\nNIPC: 510928374\nServiço/Órgão/Pessoa de contacto: NGCP\nEndereço: Av. 5 de Outubro, 153 - Lisboa\nCódigo postal: 1050-053\nLocalidade: Lisboa\nPaís: Portugal\nNUT III: PT170\nDistrito: Lisboa\nConcelho: Lisboa\nFreguesia: Todas\nTelefone: 218814000\nFax: 218881111\nEndereço da Entidade (URL): www.adcoesao.pt\nEndereço Eletrónico: agencia@adcoesao.pt\neDelivery Gateway (URL): https://www.acingov.pt\nFunção da Organização: Adquirente\nNorma jurídica da Entidade Adjudicante: Organismo de direito público\nÁrea de atividade da Autoridade Adjudicante: Serviços públicos das administrações públicas\n\n2 - JORNAL OFICIAL DA UNIÃO EUROPEIA\nO procedimento a que este anúncio diz respeito também é publicitado no Jornal Oficial da União Europeia? Sim\n\n3 - AVISO\nModelo de Anúncio: Concurso público\nData de Envio do Anúncio: 22-12-2025\n\n5 - PROCESSO\nTipo de Procedimento: Concurso público\nPreço base do procedimento: Sim\nValor do preço base do procedimento: 165.000,00 EUR\nProcedimento com lotes? Não\n\n6 - OBJETO DO CONTRATO\nNúmero de referência interna: R/169/2025\nDesignação do contrato: Aquisição de serviços para a realização da Avaliação de Fundos Europeus: Contratos Locais de Desenvolvimento Social (CLDS)\nDescrição: Aquisição de serviços para a realização da Avaliação de Fundos Europeus: Contratos Locais de Desenvolvimento Social (CLDS)\nOpções: Não\nTipo de Contrato Principal: Aquisição de Serviços\nTipo de Contrato: Aquisição de Serviços\nClassificação CPV (Vocabulário Comum para os Contratos Públicos)\nObjeto principal\nVocabulário Principal: 79419000\nPreço base s/IVA: 165.000,00 EUR\n\n7 - INDICAÇÕES ADICIONAIS\nO contrato envolve aquisição conjunta (satisfação de várias entidades)? Não\nO contrato é adjudicado por uma central de compras? Não\n\n8 - TÉCNICAS\nO concurso destina-se à celebração de um acordo-quadro? Inexistência de acordo-quadro\nÉ utilizado um leilão eletrónico? Não\nÉ adotada uma fase de negociação? Não\nSistema de Aquisição Dinâmico: Inexistência de sistema de aquisição dinâmico\n\n9 - LOCAL DA EXECUÇÃO DO CONTRATO\nLOCAL DA EXECUÇÃO DO CONTRATO (PROCEDIMENTO)\nPaís: Portugal\nNUT III: PT170\nLocalidade: Lisboa\nDistrito: Lisboa\nConcelho: Todos\nFreguesia: Todas\n\n10 - PRAZO DE EXECUÇÃO DO CONTRATO\nPrazo de execução do contrato: 555 DIAS\nPrevisão de renovações: Não\n\n11 - FUNDOS EU\nTêm fundos EU? Sim\n\n12 - DOCUMENTOS DE HABILITAÇÃO\nHabilitação para o exercício da atividade profissional: Não\n\n13 - CONDIÇÕES DE APRESENTAÇÃO\nPlataforma eletrónica utilizada pela entidade adjudicante: ACIN\nURL para Apresentação: https://www.acingov.pt\nAdmissibilidade da apresentação de propostas variantes: Não autorizado\nPrazo para apresentação das propostas: 21-01-2026 23:59\nPrazo durante o qual os concorrentes são obrigados a manter as respetivas propostas: 120 dias a contar do termo do prazo para a apresentação das propostas\nApresentação de Catálogo Eletrónico: Permitido\nIndicação de Subcontratação na Proposta: Inexistência de indicação de subcontratação\n\n14 - PRESTAÇÃO DE CAUÇÃO\nPrestação de caução: Não\n\n15 - FORNECIMENTO DAS PEÇAS DO CONCURSO, APRESENTAÇÃO DE PEDIDOS DE PARTICIPAÇÃO E APRESENTAÇÃO DAS PROPOSTAS\nLink para acesso às peças do concurso (URL): https://www.acingov.pt/acingovprod/2/zonaPublica/zona_publica_c/donwloadProcedurePiece/MTAwODc4OA==\n\n20 - OUTROS REQUISITOS\nInformação sobre contratos reservados. Aplica-se a contratos reservados (54º-A)? Não\n\n21 - CRITÉRIO DE ADJUDICAÇÃO\nMultifator: Sim\nFator: \nNome: Qualidade\nPonderação: 50%\nSubfatores: Não\nFator: \nNome: Qualidade\nPonderação: 20%\nSubfatores: Não\nFator: \nNome: Preço\nPonderação: 30%\nSubfatores: Não\n\n24 - CONDIÇÕES DO CONTRATO\nFaturação Eletrónica: Permitido\nObrigação de Subcontratação:\nCódigo da Obrigação de Subcontratação: Não é aplicável nenhuma obrigação de subcontratação.\n\n25 - COMPRA PÚBLICA ESTRATÉGICA\nCompra Pública Estratégica: Inexistência de contratação pública estratégica\n\n26 - INFORMAÇÕES ADICIONAIS\nContrato adequado para PME: Sim\nCobertura ACP (Acordo dos Contratos Públicos da Organização Mundial do Comércio): Não\n\n27 - IDENTIFICAÇÃO E CONTACTOS DO ÓRGÃO DE RECURSOS ADMINISTRATIVOS\nDesignação: Conselho Diretivo\nEndereço: Av. 5 de Outubro, 153 - Lisboa\nCódigo postal: 1050-053\nLocalidade: Lisboa\nTelefone: 218814000\nFax: 218881111\nEndereço eletrónico: contratacao@adcoesao.pt\n\n28 - IDENTIFICAÇÃO DO(S) AUTOR(ES) DE ANÚNCIO\nNome: Leonor Lei\nCargo: Coordenadora NGCP\n419918982",
    "nipc": "510928374",
    "distrito": "Lisboa",
    "concelho": "Lisboa",
    "freguesia": "Todas",
    "site": "www.adcoesao.pt",
    "email": "agencia@adcoesao.pt",
    "designacao_contrato": "Aquisição de serviços para a realização da Avaliação de Fundos Europeus: Contratos Locais de Desenvolvimento Social (CLDS)",
    "descricao": "Aquisição de serviços para a realização da Avaliação de Fundos Europeus: Contratos Locais de Desenvolvimento Social (CLDS)",
    "preco_base": "165.000,00 EUR",
    "prazo_execucao": "555 DIAS",
    "prazo_apresentacao_propostas": "21-01-2026 23:59",
    "fundos_eu": "Sim",
    "plataforma_eletronica": "ACIN",
    "url_procedimento": "https://www.acingov.pt",
    "autor_nome": "Leonor Lei",
    "autor_cargo": "Coordenadora NGCP"
  },
  {
    "numero_procedimento": "N/A",
    "entidade": "Agência para o Desenvolvimento e Coesão, IP",
    "link": "https://diariodarepublica.pt/dr/detalhe/contrato-publico/33372-992662022",
    "detalhes_completos": "1 - IDENTIFICAÇÃO E CONTACTOS DA ENTIDADE ADJUDICANTE\nDesignação da entidade adjudicante: Agência para o Desenvolvimento e Coesão, IP\nNIPC: 510928374\nServiço/Órgão/Pessoa de contacto: Núcleo de Gestão de Contratos e Património\nEndereço: Avenida 5 de Outubro 153\nCódigo postal: 1050-053\nLocalidade: Lisboa\nPaís: Portugal\nNUT III: PT170\nDistrito: Lisboa\nConcelho: Lisboa\nFreguesia: Freguesia de Avenidas Novas\nTelefone: 218814000\nFax: 218881111\nEndereço da Entidade (URL): https://www.adcoesao.pt/\nEndereço Eletrónico: contratacao@adcoesao.pt\neDelivery Gateway (URL): https://www.acingov.pt\nFunção da Organização: Adquirente\nNorma jurídica da Entidade Adjudicante: Organismo de direito público\nÁrea de atividade da Autoridade Adjudicante: Serviços públicos das administrações públicas\n\n2 - JORNAL OFICIAL DA UNIÃO EUROPEIA\nO procedimento a que este anúncio diz respeito também é publicitado no Jornal Oficial da União Europeia? Sim\n\n3 - AVISO\nModelo de Anúncio: Concurso público\nData de Envio do Anúncio: 22-12-2025\n\n5 - PROCESSO\nTipo de Procedimento: Concurso público\nPreço base do procedimento: Sim\nValor do preço base do procedimento: 75.000,00 EUR\nProcedimento com lotes? Não\n\n6 - OBJETO DO CONTRATO\nNúmero de referência interna: R/127/2025\nDesignação do contrato: Aquisição de serviços técnicos e especializados para elaboração de estudo de caso sobre a iniciativa Portugal Inovação Social\nDescrição: Aquisição de serviços técnicos e especializados para elaboração de estudo de caso sobre a iniciativa Portugal Inovação Social\nOpções: Não\nTipo de Contrato Principal: Aquisição de Serviços\nTipo de Contrato: Aquisição de Serviços\nClassificação CPV (Vocabulário Comum para os Contratos Públicos)\nObjeto principal\nVocabulário Principal: 79419000\nPreço base s/IVA: 75.000,00 EUR\n\n7 - INDICAÇÕES ADICIONAIS\nO contrato envolve aquisição conjunta (satisfação de várias entidades)? Não\nO contrato é adjudicado por uma central de compras? Não\n\n8 - TÉCNICAS\nO concurso destina-se à celebração de um acordo-quadro? Inexistência de acordo-quadro\nÉ utilizado um leilão eletrónico? Não\nÉ adotada uma fase de negociação? Não\nSistema de Aquisição Dinâmico: Inexistência de sistema de aquisição dinâmico\n\n9 - LOCAL DA EXECUÇÃO DO CONTRATO\nLOCAL DA EXECUÇÃO DO CONTRATO (PROCEDIMENTO)\nPaís: Portugal\nNUT III: PT170\nLocalidade: Freguesia de Avenidas Novas\nDistrito: Lisboa\nConcelho: Lisboa\nFreguesia: Freguesia de Avenidas Novas\n\n10 - PRAZO DE EXECUÇÃO DO CONTRATO\nPrazo de execução do contrato: 204 DIAS\nPrevisão de renovações: Não\n\n11 - FUNDOS EU\nTêm fundos EU? Sim\n\n12 - DOCUMENTOS DE HABILITAÇÃO\nHabilitação para o exercício da atividade profissional: Não\n\n13 - CONDIÇÕES DE APRESENTAÇÃO\nPlataforma eletrónica utilizada pela entidade adjudicante: ACIN\nURL para Apresentação: https://www.acingov.pt\nAdmissibilidade da apresentação de propostas variantes: Não autorizado\nPrazo para apresentação das propostas: 21-01-2026 23:59\nPrazo durante o qual os concorrentes são obrigados a manter as respetivas propostas: 120 dias a contar do termo do prazo para a apresentação das propostas\nApresentação de Catálogo Eletrónico: Permitido\nIndicação de Subcontratação na Proposta: Inexistência de indicação de subcontratação\n\n14 - PRESTAÇÃO DE CAUÇÃO\nPrestação de caução: Não\n\n15 - FORNECIMENTO DAS PEÇAS DO CONCURSO, APRESENTAÇÃO DE PEDIDOS DE PARTICIPAÇÃO E APRESENTAÇÃO DAS PROPOSTAS\nLink para acesso às peças do concurso (URL): https://www.acingov.pt/acingovprod/2/zonaPublica/zona_publica_c/donwloadProcedurePiece/MTAwODgwMQ==\n\n20 - OUTROS REQUISITOS\nInformação sobre contratos reservados. Aplica-se a contratos reservados (54º-A)? Não\n\n21 - CRITÉRIO DE ADJUDICAÇÃO\nMultifator: Sim\nFator: \nNome: Preço\nPonderação: 30%\nSubfatores: Não\nFator: \nNome: Outros\nOutro Nome: Valia Técnica\nPonderação: 70%\nSubfatores: Sim\nSubfatores: \nNome: Experiência do Coordenador\nPonderação : 50%; \nNome: Experiência dos Técnicos Especialistas\nPonderação : 30%; \nNome: Experiência do Técnico\nPonderação : 20%; \n\n24 - CONDIÇÕES DO CONTRATO\nFaturação Eletrónica: Permitido\nObrigação de Subcontratação:\nCódigo da Obrigação de Subcontratação: Não é aplicável nenhuma obrigação de subcontratação.\n\n25 - COMPRA PÚBLICA ESTRATÉGICA\nCompra Pública Estratégica: Inexistência de contratação pública estratégica\n\n26 - INFORMAÇÕES ADICIONAIS\nContrato adequado para PME: Sim\nCobertura ACP (Acordo dos Contratos Públicos da Organização Mundial do Comércio): Não\n\n27 - IDENTIFICAÇÃO E CONTACTOS DO ÓRGÃO DE RECURSOS ADMINISTRATIVOS\nDesignação: Conselho Diretivo da Agência, I.P.\nEndereço: Av. 5 de Outubro, 153 - Lisboa\nCódigo postal: 1050-053\nLocalidade: Lisboa\nTelefone: 218814000\nFax: 218881111\nEndereço eletrónico: contratacao@adcoesao.pt\n\n28 - IDENTIFICAÇÃO DO(S) AUTOR(ES) DE ANÚNCIO\nNome: Leonor Lei\nCargo: Coordenadora do NGCP\n419918917",
    "nipc": "510928374",
    "distrito": "Lisboa",
    "concelho": "Lisboa",
    "freguesia": "Freguesia de Avenidas Novas",
    "site": "https://www.adcoesao.pt/",
    "email": "contratacao@adcoesao.pt",
    "designacao_contrato": "Aquisição de serviços técnicos e especializados para elaboração de estudo de caso sobre a iniciativa Portugal Inovação Social",
    "descricao": "Aquisição de serviços técnicos e especializados para elaboração de estudo de caso sobre a iniciativa Portugal Inovação Social",
    "preco_base": "75.000,00 EUR",
    "prazo_execucao": "204 DIAS",
    "prazo_apresentacao_propostas": "21-01-2026 23:59",
    "fundos_eu": "Sim",
    "plataforma_eletronica": "ACIN",
    "url_procedimento": "https://www.acingov.pt",
    "autor_nome": "Leonor Lei",
    "autor_cargo": "Coordenadora do NGCP"
  },
  {
    "numero_procedimento": "N/A",
    "entidade": "Unidade Local de Saúde de Coimbra, E. P. E.",
    "link": "https://diariodarepublica.pt/dr/detalhe/contrato-publico/33378-992662032",
    "detalhes_completos": "Alteração do Anúncio de procedimento n.º 30208/2025, de 2025-11-20, com o ID 419785307\n\n1 - IDENTIFICAÇÃO E CONTACTOS DA ENTIDADE ADJUDICANTE\nDesignação da entidade adjudicante: Unidade Local de Saúde de Coimbra, E. P. E.\nNIPC: 510103448\nEndereço: Praceta Prof. Mota Pinto\nCódigo postal: 3004-561\nLocalidade: Coimbra\nPaís: Portugal\nNUT III: PT16E\nDistrito: Coimbra\nConcelho: Coimbra\nFreguesia: Todas\nTelefone: 239400605\nFax: 239400605\nEndereço da Entidade (URL): https://www.chuc.min-saude.pt\nEndereço Eletrónico: ana.rosete@ulscoimbra.min-saude.pt\neDelivery Gateway (URL): https://community.vortal.biz/public/\nFunção da Organização: Adquirente\nNorma jurídica da Entidade Adjudicante: Organismo de direito público\nÁrea de atividade da Autoridade Adjudicante: Saúde\n\n2 - JORNAL OFICIAL DA UNIÃO EUROPEIA\nO procedimento a que este anúncio diz respeito também é publicitado no Jornal Oficial da União Europeia? Sim\n\n3 - AVISO\nModelo de Anúncio: Concurso público\nData de Envio do Anúncio: 22-12-2025\n\n5 - PROCESSO\nTipo de Procedimento: Concurso público\nPreço base do procedimento: Sim\nValor do preço base do procedimento: 1.182.600,00 EUR\nProcedimento com lotes? Não\n\n6 - OBJETO DO CONTRATO\nNúmero de referência interna: 010100122025\nDesignação do contrato: EP - NUTRIÇÃO PARENTÉRICA PERSONALIZADA - SACO IV\nDescrição: EP - NUTRIÇÃO PARENTÉRICA PERSONALIZADA - SACO IV\nOpções: Não\nTipo de Contrato Principal: Aquisição de Bens Móveis\nTipo de Contrato: Aquisição de Bens Móveis\nClassificação CPV (Vocabulário Comum para os Contratos Públicos)\nObjeto principal\nVocabulário Principal: 33600000\nPreço base s/IVA: 1.182.600,00 EUR\n\n7 - INDICAÇÕES ADICIONAIS\nO contrato envolve aquisição conjunta (satisfação de várias entidades)? Não\nO contrato é adjudicado por uma central de compras? Não\n\n8 - TÉCNICAS\nO concurso destina-se à celebração de um acordo-quadro? Inexistência de acordo-quadro\nÉ utilizado um leilão eletrónico? Não\nÉ adotada uma fase de negociação? Não\nSistema de Aquisição Dinâmico: Inexistência de sistema de aquisição dinâmico\n\n9 - LOCAL DA EXECUÇÃO DO CONTRATO\nLOCAL DA EXECUÇÃO DO CONTRATO (PROCEDIMENTO)\nPaís: Portugal\nNUT III: PT16E\nLocalidade: Coimbra\nDistrito: Coimbra\nConcelho: Coimbra\nFreguesia: Freguesia de Santo António dos Olivais\n\n10 - PRAZO DE EXECUÇÃO DO CONTRATO\nPrazo de execução do contrato: 36 MESES\nPrevisão de renovações: Sim\nIndicar número máximo de renovações: 2\nPrazo de renovações diferente do prazo inicial: Não\n\n11 - FUNDOS EU\nTêm fundos EU? Não\n\n12 - DOCUMENTOS DE HABILITAÇÃO\nHabilitação para o exercício da atividade profissional: Não\n\n13 - CONDIÇÕES DE APRESENTAÇÃO\nPlataforma eletrónica utilizada pela entidade adjudicante: VORTAL\nURL para Apresentação: https://community.vortal.biz/public/\nAdmissibilidade da apresentação de propostas variantes: Não autorizado\nPrazo para apresentação das propostas: 21-01-2026 17:00\nPrazo durante o qual os concorrentes são obrigados a manter as respetivas propostas: 180 dias a contar do termo do prazo para a apresentação das propostas\nApresentação de Catálogo Eletrónico: Não autorizado\nIndicação de Subcontratação na Proposta: Inexistência de indicação de subcontratação\n\n14 - PRESTAÇÃO DE CAUÇÃO\nPrestação de caução: Não\n\n15 - FORNECIMENTO DAS PEÇAS DO CONCURSO, APRESENTAÇÃO DE PEDIDOS DE PARTICIPAÇÃO E APRESENTAÇÃO DAS PROPOSTAS\nLink para acesso às peças do concurso (URL): https://community.vortal.biz/Public/public-tender-documents/akdrWU5UQUU1N0JPRG8zemFxU09ET0VRdFhrRkJNbnFTZXVaWFA4MXpmZ1pnZk1sVGtHZzJ6SGF0cXA5Y1p6bUdUY1ZpbnVjb1c4U3VUM3ZMTWZRd2c9PWwqbEp4\n\n20 - OUTROS REQUISITOS\nInformação sobre contratos reservados. Aplica-se a contratos reservados (54º-A)? Não\n\n21 - CRITÉRIO DE ADJUDICAÇÃO\nMultifator: Não\nMonofator:\nNome: Outros\nOutro nome: Preço\n\n24 - CONDIÇÕES DO CONTRATO\nFaturação Eletrónica: Permitido\nObrigação de Subcontratação:\nCódigo da Obrigação de Subcontratação: Não é aplicável nenhuma obrigação de subcontratação.\n\n25 - COMPRA PÚBLICA ESTRATÉGICA\nCompra Pública Estratégica: Inexistência de contratação pública estratégica\n\n26 - INFORMAÇÕES ADICIONAIS\nContrato adequado para PME: Sim\nCobertura ACP (Acordo dos Contratos Públicos da Organização Mundial do Comércio): Não\n\n27 - IDENTIFICAÇÃO E CONTACTOS DO ÓRGÃO DE RECURSOS ADMINISTRATIVOS\nDesignação: Unidade Local de Saúde de Coimbra, E.P.E.\nEndereço: Praceta Prof Mota Pinto\nCódigo postal: 3004-561\nLocalidade: Coimbra\nTelefone: +351 239400511\nFax: +351 239400511\nEndereço eletrónico: compras.mr@ulscoimbra.min-saude.pt\n\n28 - IDENTIFICAÇÃO DO(S) AUTOR(ES) DE ANÚNCIO\nNome: Afonso Santos da Costa\nCargo: Assistente Técnico\n\n29 - ALTERAÇÃO\nMotivo da Alteração: Correção pelo adquirente\nIdentificador da Versão do Anúncio a Alterar: c6b89b26-440c-4005-bd08-7175f2cf8ae2-01\nIdentificador das Secções Alteradas do Anúncio Anterior: Condições de Apresentação\nDescrição das Alterações: Prorrogação de prazos e substituição das peças do procedimento.\nAlteração dos Documentos do Concurso: Sim\nData de alteração dos documentos do concurso: 22-12-2025\n419920893",
    "nipc": "510103448",
    "distrito": "Coimbra",
    "concelho": "Coimbra",
    "freguesia": "Todas",
    "site": "https://www.chuc.min-saude.pt",
    "email": "ana.rosete@ulscoimbra.min-saude.pt",
    "designacao_contrato": "EP - NUTRIÇÃO PARENTÉRICA PERSONALIZADA - SACO IV",
    "descricao": "EP - NUTRIÇÃO PARENTÉRICA PERSONALIZADA - SACO IV",
    "preco_base": "1.182.600,00 EUR",
    "prazo_execucao": "36 MESES",
    "prazo_apresentacao_propostas": "21-01-2026 17:00",
    "fundos_eu": "Não",
    "plataforma_eletronica": "VORTAL",
    "url_procedimento": "https://community.vortal.biz/public/",
    "autor_nome": "Afonso Santos da Costa",
    "autor_cargo": "Assistente Técnico"
  },
  {
    "numero_procedimento": "N/A",
    "entidade": "AnÃºncio de procedimento  n.Âº 33381/2025  -  DiÃ¡rio da RepÃºblica n.Âº 247/2025, SÃ©rie II de 2025-12-24",
    "link": "https://diariodarepublica.pt/dr/detalhe/contrato-publico/33381-992662033"
  },
  {
    "numero_procedimento": "N/A",
    "entidade": "Unidade Local de Saúde de São José, EPE",
    "link": "https://diariodarepublica.pt/dr/detalhe/contrato-publico/33382-992662034",
    "detalhes_completos": "1 - IDENTIFICAÇÃO E CONTACTOS DA ENTIDADE ADJUDICANTE\nDesignação da entidade adjudicante: Unidade Local de Saúde de São José, EPE\nNIPC: 508080142\nEndereço: Rua José António Serrano\nCódigo postal: 1150-199\nLocalidade: Lisboa\nPaís: Portugal\nNUT III: PT170\nDistrito: Lisboa\nConcelho: Lisboa\nFreguesia: Freguesia de Arroios - Lisboa\nTelefone: 218841403\nFax: 218841025\nEndereço da Entidade (URL): www.chlc.min-saude.pt\nEndereço Eletrónico: geral@chlc.min-saude.pt\neDelivery Gateway (URL): https://community.vortal.biz/public/\nFunção da Organização: Adquirente\nNorma jurídica da Entidade Adjudicante: Organismo de direito público\nÁrea de atividade da Autoridade Adjudicante: Saúde\n\n2 - JORNAL OFICIAL DA UNIÃO EUROPEIA\nO procedimento a que este anúncio diz respeito também é publicitado no Jornal Oficial da União Europeia? Sim\n\n3 - AVISO\nModelo de Anúncio: Concurso público\nData de Envio do Anúncio: 22-12-2025\n\n5 - PROCESSO\nTipo de Procedimento: Concurso público\nPreço base do procedimento: Sim\nValor do preço base do procedimento: 524.388,48 EUR\nProcedimento com lotes? Sim\nNº Máx. de Lotes Autorizado: 27\nNúmero máximo de lotes que podem ser adjudicados a um concorrente: 27\n\n6 - OBJETO DO CONTRATO\nNúmero de referência interna: 12007926\nDesignação do contrato: Consumíveis para CPRE\nDescrição: Consumíveis para CPRE\nOpções: Não\nTipo de Contrato Principal: Aquisição de Bens Móveis\nTipo de Contrato: Aquisição de Bens Móveis\nClassificação CPV (Vocabulário Comum para os Contratos Públicos)\nObjeto principal\nVocabulário Principal: 33140000\nPreço base s/IVA: 524.388,48 EUR\nLotes: \nNº: LOT-0001\nDescrição do Lote: ANSA DE EXTRACAO DE CORPOS ESTRANHOS P/ COLANGIOPANCREATOSCOPIA\nPreço base s/IVA: 5.760,00 EUR\nClassificação CPV (Vocabulário Comum para os Contratos Públicos)\nObjeto principal\nVocabulário Principal: 33140000\nNº: LOT-0002\nDescrição do Lote: BALAO DE DILATACAO BILIAR\nPreço base s/IVA: 18.480,00 EUR\nClassificação CPV (Vocabulário Comum para os Contratos Públicos)\nObjeto principal\nVocabulário Principal: 33140000\nNº: LOT-0003\nDescrição do Lote: BALÃO DE DILATAÇÃO GASTROCOLICO EM ENDOSCOPIA\nPreço base s/IVA: 15.840,00 EUR\nClassificação CPV (Vocabulário Comum para os Contratos Públicos)\nObjeto principal\nVocabulário Principal: 33140000\nNº: LOT-0004\nDescrição do Lote: BALÃO DE DILATAÇÃO DA ACALÁSIA\nPreço base s/IVA: 6.000,00 EUR\nClassificação CPV (Vocabulário Comum para os Contratos Públicos)\nObjeto principal\nVocabulário Principal: 33140000\nNº: LOT-0005\nDescrição do Lote: BALÃO DE EXTRACÇÃO CÁLCULOS BILIARES C/ LIBERTAÇÃO DE CONTRASTE DISTAL\nPreço base s/IVA: 11.137,50 EUR\nClassificação CPV (Vocabulário Comum para os Contratos Públicos)\nObjeto principal\nVocabulário Principal: 33140000\nNº: LOT-0006\nDescrição do Lote: BALÃO DE EXTRACÇÃO CÁLCULOS BILIARES C/ LIBERTAÇÃO DE CONTRASTE PROXIMAL\nPreço base s/IVA: 11.137,50 EUR\nClassificação CPV (Vocabulário Comum para os Contratos Públicos)\nObjeto principal\nVocabulário Principal: 33140000\nNº: LOT-0007\nDescrição do Lote: BASKET EXTRACÇÃO DE CÁLCULOS BILIARES EM ENDOSCOPIA DISPOSABLE\nPreço base s/IVA: 22.695,00 EUR\nClassificação CPV (Vocabulário Comum para os Contratos Públicos)\nObjeto principal\nVocabulário Principal: 33140000\nNº: LOT-0008\nDescrição do Lote: BASKET P/ LITOTRITOR  BILIAR TOTALMENTE DESCARTÁVEL\nPreço base s/IVA: 39.312,00 EUR\nClassificação CPV (Vocabulário Comum para os Contratos Públicos)\nObjeto principal\nVocabulário Principal: 33140000\nNº: LOT-0009\nDescrição do Lote: BASKET EXTRACCAO E LITOTRICÍA DE CALCULOS BILIARES COM GUIA\nPreço base s/IVA: 18.000,00 EUR\nClassificação CPV (Vocabulário Comum para os Contratos Públicos)\nObjeto principal\nVocabulário Principal: 33140000\nNº: LOT-0010\nDescrição do Lote: CATETER DE ACESSO/VISUALIZAÇÃO DO SISTEMA PANCREATOBILIAR BASQUETE PARA COLANGIOPANCREATOSCOPIA PINCA DE BIOPSIA PARA COLANGIOPANCREATOSCOPIA\nPreço base s/IVA: 96.000,00 EUR\nClassificação CPV (Vocabulário Comum para os Contratos Públicos)\nObjeto principal\nVocabulário Principal: 33140000\nNº: LOT-0011\nDescrição do Lote: CÂNULA P/ CPRE CÓNICA\nPreço base s/IVA: 6.975,00 EUR\nClassificação CPV (Vocabulário Comum para os Contratos Públicos)\nObjeto principal\nVocabulário Principal: 33140000\nNº: LOT-0012\nDescrição do Lote: CAPA DISTAL PARA DUODENOSCOPIO PEDIATRICO\nPreço base s/IVA: 4.878,60 EUR\nClassificação CPV (Vocabulário Comum para os Contratos Públicos)\nObjeto principal\nVocabulário Principal: 33140000\nNº: LOT-0013\nDescrição do Lote: ESCOVA DE CITOLOGIA DE DUPLO LUMEN P/ DUODENOSCOPIO\nPreço base s/IVA: 4.050,00 EUR\nClassificação CPV (Vocabulário Comum para os Contratos Públicos)\nObjeto principal\nVocabulário Principal: 33140000\nNº: LOT-0014\nDescrição do Lote: ESFINCTEROTOMO BILLROTH II\nPreço base s/IVA: 2.670,00 EUR\nClassificação CPV (Vocabulário Comum para os Contratos Públicos)\nObjeto principal\nVocabulário Principal: 33140000\nNº: LOT-0015\nDescrição do Lote: ESFINCTERÓTOMOS DE DUPLO LÚMEN PRE-CORTE C/ AGULHA\nPreço base s/IVA: 10.605,00 EUR\nClassificação CPV (Vocabulário Comum para os Contratos Públicos)\nObjeto principal\nVocabulário Principal: 33140000\nNº: LOT-0016\nDescrição do Lote: ESFINCTERÓTOMOS DE TRIPLO LÚMEN DESCARTÁVEL\nPreço base s/IVA: 81.000,00 EUR\nClassificação CPV (Vocabulário Comum para os Contratos Públicos)\nObjeto principal\nVocabulário Principal: 33140000\nNº: LOT-0017\nDescrição do Lote: FIBRA DE LASER PARA LITOTRICIA/TERAPÊUTICA DA DOENÇA ONCOLOGICA EM CPRE\nPreço base s/IVA: 16.200,00 EUR\nClassificação CPV (Vocabulário Comum para os Contratos Públicos)\nObjeto principal\nVocabulário Principal: 33140000\nNº: LOT-0018\nDescrição do Lote: FIO GUIA P/ VIA BILIAR POR ENDOSCOPIA HIDRÓFILO\nPreço base s/IVA: 121.800,00 EUR\nClassificação CPV (Vocabulário Comum para os Contratos Públicos)\nObjeto principal\nVocabulário Principal: 33140000\nNº: LOT-0019\nDescrição do Lote: FIO GUIA RIGIDO P/ ENDOSCOPIA DIGESTIVA\nPreço base s/IVA: 936,00 EUR\nClassificação CPV (Vocabulário Comum para os Contratos Públicos)\nObjeto principal\nVocabulário Principal: 33140000\nNº: LOT-0020\nDescrição do Lote: KIT DE APLICAÇÃO DE PRÓTESES BILIARES\nPreço base s/IVA: 9.360,00 EUR\nClassificação CPV (Vocabulário Comum para os Contratos Públicos)\nObjeto principal\nVocabulário Principal: 33140000\nNº: LOT-0021\nDescrição do Lote: OVERTUBE P/ DIVERTICULO DE ZENKER\nPreço base s/IVA: 6.000,00 EUR\nClassificação CPV (Vocabulário Comum para os Contratos Públicos)\nObjeto principal\nVocabulário Principal: 33140000\nNº: LOT-0022\nDescrição do Lote: PINCA CROCODILO P/ENDOSCOPIA DIGESTIVA\nPreço base s/IVA: 3.042,00 EUR\nClassificação CPV (Vocabulário Comum para os Contratos Públicos)\nObjeto principal\nVocabulário Principal: 33140000\nNº: LOT-0023\nDescrição do Lote: SISTEMA DE INJECCAO CONTINUA PARA COLANGIOPANCREATOSCOPIA\nPreço base s/IVA: 900,00 EUR\nClassificação CPV (Vocabulário Comum para os Contratos Públicos)\nObjeto principal\nVocabulário Principal: 33140000\nNº: LOT-0024\nDescrição do Lote: SONDA DRENAGEM NASO – BILIAR\nPreço base s/IVA: 2.400,00 EUR\nClassificação CPV (Vocabulário Comum para os Contratos Públicos)\nObjeto principal\nVocabulário Principal: 33140000\nNº: LOT-0025\nDescrição do Lote: TUBO DE ALTA PRESSÃO P/ INSUFLADOR DE CO2\nPreço base s/IVA: 2.160,00 EUR\nClassificação CPV (Vocabulário Comum para os Contratos Públicos)\nObjeto principal\nVocabulário Principal: 33140000\nNº: LOT-0026\nDescrição do Lote: VELA DILATACAO BILIAR\nPreço base s/IVA: 929,88 EUR\nClassificação CPV (Vocabulário Comum para os Contratos Públicos)\nObjeto principal\nVocabulário Principal: 33140000\nNº: LOT-0027\nDescrição do Lote: VELA P/DILATACAO ESOFAGICA SAVARY\nPreço base s/IVA: 6.120,00 EUR\nClassificação CPV (Vocabulário Comum para os Contratos Públicos)\nObjeto principal\nVocabulário Principal: 33140000\n\n7 - INDICAÇÕES ADICIONAIS\nO contrato envolve aquisição conjunta (satisfação de várias entidades)? Não\nO contrato é adjudicado por uma central de compras? Não\n\n8 - TÉCNICAS\nO concurso destina-se à celebração de um acordo-quadro? Inexistência de acordo-quadro\nÉ utilizado um leilão eletrónico? Não\nÉ adotada uma fase de negociação? Não\nSistema de Aquisição Dinâmico: Inexistência de sistema de aquisição dinâmico\n\n9 - LOCAL DA EXECUÇÃO DO CONTRATO\nLOCAL DA EXECUÇÃO DO CONTRATO (PROCEDIMENTO)\nPaís: Portugal\nNUT III: PT170\nLocalidade: Lisboa\nDistrito: Lisboa\nConcelho: Lisboa\nFreguesia: Freguesia de Arroios - Lisboa\nLOCAL DA EXECUÇÃO DO CONTRATO (LOTE)\nIdentificador do Lote: LOT-0001; LOT-0002; LOT-0003; LOT-0004; LOT-0005; LOT-0006; LOT-0007; LOT-0008; LOT-0009; LOT-0010; LOT-0011; LOT-0012; LOT-0013; LOT-0014; LOT-0015; LOT-0016; LOT-0017; LOT-0018; LOT-0019; LOT-0020; LOT-0021; LOT-0022; LOT-0023; LOT-0024; LOT-0025; LOT-0026; LOT-0027\nPaís: Portugal\nNUT III: PT170\nLocalidade: Lisboa\nDistrito: Lisboa\nConcelho: Lisboa\nFreguesia: Freguesia de Arroios - Lisboa\n\n10 - PRAZO DE EXECUÇÃO DO CONTRATO\nIdentificador do Lote: LOT-0001; LOT-0002; LOT-0003; LOT-0004; LOT-0005; LOT-0006; LOT-0007; LOT-0008; LOT-0009; LOT-0010; LOT-0011; LOT-0012; LOT-0013; LOT-0014; LOT-0015; LOT-0016; LOT-0017; LOT-0018; LOT-0019; LOT-0020; LOT-0021; LOT-0022; LOT-0023; LOT-0024; LOT-0025; LOT-0026; LOT-0027\nPrazo de execução do contrato: 36 MESES\nPrevisão de renovações: Não\n\n11 - FUNDOS EU\nIdentificador do Lote: LOT-0001; LOT-0002; LOT-0003; LOT-0004; LOT-0005; LOT-0006; LOT-0007; LOT-0008; LOT-0009; LOT-0010; LOT-0011; LOT-0012; LOT-0013; LOT-0014; LOT-0015; LOT-0016; LOT-0017; LOT-0018; LOT-0019; LOT-0020; LOT-0021; LOT-0022; LOT-0023; LOT-0024; LOT-0025; LOT-0026; LOT-0027\nTêm fundos EU? Não\n\n12 - DOCUMENTOS DE HABILITAÇÃO\nHabilitação para o exercício da atividade profissional: Não\n\n13 - CONDIÇÕES DE APRESENTAÇÃO\nPlataforma eletrónica utilizada pela entidade adjudicante: VORTAL\nURL para Apresentação: https://community.vortal.biz/public/\nAdmissibilidade da apresentação de propostas variantes: Não autorizado\nPrazo para apresentação das propostas: 29-01-2026 23:59\nPrazo durante o qual os concorrentes são obrigados a manter as respetivas propostas: 120 dias a contar do termo do prazo para a apresentação das propostas\nApresentação de Catálogo Eletrónico: Permitido\nIndicação de Subcontratação na Proposta: Inexistência de indicação de subcontratação\n\n14 - PRESTAÇÃO DE CAUÇÃO\nPrestação de caução: Não\n\n15 - FORNECIMENTO DAS PEÇAS DO CONCURSO, APRESENTAÇÃO DE PEDIDOS DE PARTICIPAÇÃO E APRESENTAÇÃO DAS PROPOSTAS\nLink para acesso às peças do concurso (URL): https://community.vortal.biz/Public/public-tender-documents/ZFB1SThvSXdILzdiSGpyK2dLdS9jWWpaS09mQUxlN2NRUTQ0UWNORStMNzVGUmlBYmRQL3k3TGlFemJ5THY0OUN4ekVvVWtrR2JFVGN6UW82ekJjb3c9PXZRUih0\n\n20 - OUTROS REQUISITOS\nIdentificador do Lote: LOT-0001; LOT-0002; LOT-0003; LOT-0004; LOT-0005; LOT-0006; LOT-0007; LOT-0008; LOT-0009; LOT-0010; LOT-0011; LOT-0012; LOT-0013; LOT-0014; LOT-0015; LOT-0016; LOT-0017; LOT-0018; LOT-0019; LOT-0020; LOT-0021; LOT-0022; LOT-0023; LOT-0024; LOT-0025; LOT-0026; LOT-0027\nInformação sobre contratos reservados. Aplica-se a contratos reservados (54º-A)? Não\n\n21 - CRITÉRIO DE ADJUDICAÇÃO\nO Critério de adjudicação é diferenciado por lote? Não\nMultifator: Não\nMonofator:\nNome: Preço\n\n24 - CONDIÇÕES DO CONTRATO\nIdentificador do Lote: LOT-0001; LOT-0002; LOT-0003; LOT-0004; LOT-0005; LOT-0006; LOT-0007; LOT-0008; LOT-0009; LOT-0010; LOT-0011; LOT-0012; LOT-0013; LOT-0014; LOT-0015; LOT-0016; LOT-0017; LOT-0018; LOT-0019; LOT-0020; LOT-0021; LOT-0022; LOT-0023; LOT-0024; LOT-0025; LOT-0026; LOT-0027\nFaturação Eletrónica: Permitido\nObrigação de Subcontratação:\nCódigo da Obrigação de Subcontratação: Não é aplicável nenhuma obrigação de subcontratação.\n\n25 - COMPRA PÚBLICA ESTRATÉGICA\nCompra Pública Estratégica: Inexistência de contratação pública estratégica\n\n26 - INFORMAÇÕES ADICIONAIS\nIdentificador do Lote: LOT-0001; LOT-0002; LOT-0003; LOT-0004; LOT-0005; LOT-0006; LOT-0007; LOT-0008; LOT-0009; LOT-0010; LOT-0011; LOT-0012; LOT-0013; LOT-0014; LOT-0015; LOT-0016; LOT-0017; LOT-0018; LOT-0019; LOT-0020; LOT-0021; LOT-0022; LOT-0023; LOT-0024; LOT-0025; LOT-0026; LOT-0027\nContrato adequado para PME: Sim\nCobertura ACP (Acordo dos Contratos Públicos da Organização Mundial do Comércio): Não\n\n27 - IDENTIFICAÇÃO E CONTACTOS DO ÓRGÃO DE RECURSOS ADMINISTRATIVOS\nDesignação: Conselho de Administração\nEndereço: Rua José António Serrano s/n\nCódigo postal: 1150-199\nLocalidade: Lisboa\nTelefone: +351 218841000\nFax: +351 000000000\nEndereço eletrónico: sec.vca@ulssjose.min-saude.pt\n\n28 - IDENTIFICAÇÃO DO(S) AUTOR(ES) DE ANÚNCIO\nNome: Conselho de Administração\nCargo: Conselho de Administração\n419918755",
    "nipc": "508080142",
    "distrito": "Lisboa",
    "concelho": "Lisboa",
    "freguesia": "Freguesia de Arroios - Lisboa",
    "site": "www.chlc.min-saude.pt",
    "email": "geral@chlc.min-saude.pt",
    "designacao_contrato": "Consumíveis para CPRE",
    "descricao": "Consumíveis para CPRE",
    "preco_base": "524.388,48 EUR",
    "prazo_execucao": "36 MESES",
    "prazo_apresentacao_propostas": "29-01-2026 23:59",
    "fundos_eu": "Não",
    "plataforma_eletronica": "VORTAL",
    "url_procedimento": "https://community.vortal.biz/public/",
    "autor_nome": "Conselho de Administração",
    "autor_cargo": "Conselho de Administração"
  },
  {
    "numero_procedimento": "N/A",
    "entidade": "Instituto Nacional de Emergência Médica, IP",
    "link": "https://diariodarepublica.pt/dr/detalhe/contrato-publico/33384-992662035",
    "detalhes_completos": "1 - IDENTIFICAÇÃO E CONTACTOS DA ENTIDADE ADJUDICANTE\nDesignação da entidade adjudicante: Instituto Nacional de Emergência Médica, IP\nNIPC: 501356126\nServiço/Órgão/Pessoa de contacto: GGCCP\nEndereço: RUA ALMIRANTE BARROSO, 36\nCódigo postal: 1000-013\nLocalidade: LISBOA\nPaís: Portugal\nNUT III: PT170\nDistrito: Lisboa\nConcelho: Lisboa\nFreguesia: Freguesia de Arroios - Lisboa\nTelefone: 213508100\nFax: 213508100\nEndereço da Entidade (URL): https://www.inem.pt/\nEndereço Eletrónico: inem@inem.pt\neDelivery Gateway (URL): https://www.acingov.pt\nFunção da Organização: Adquirente\nSubfunção da Organização: Organização que recebe as propostas\nNorma jurídica da Entidade Adjudicante: Organismo de direito público\nÁrea de atividade da Autoridade Adjudicante: Serviços públicos das administrações públicas\n\n2 - JORNAL OFICIAL DA UNIÃO EUROPEIA\nO procedimento a que este anúncio diz respeito também é publicitado no Jornal Oficial da União Europeia? Sim\n\n3 - AVISO\nModelo de Anúncio: Concurso público\nData de Envio do Anúncio: 22-12-2025\n\n5 - PROCESSO\nTipo de Procedimento: Concurso público\nPreço base do procedimento: Sim\nValor do preço base do procedimento: 364.500,00 EUR\nProcedimento com lotes? Não\n\n6 - OBJETO DO CONTRATO\nNúmero de referência interna: CP-25/0059\nDesignação do contrato: Aquisição de Licenciamento Fortinet\nDescrição: Aquisição de Licenciamento Fortinet\nOpções: Não\nTipo de Contrato Principal: Aquisição de Serviços\nTipo de Contrato: Aquisição de Serviços\nClassificação CPV (Vocabulário Comum para os Contratos Públicos)\nObjeto principal\nVocabulário Principal: 72268000\nPreço base s/IVA: 364.500,00 EUR\n\n7 - INDICAÇÕES ADICIONAIS\nO contrato envolve aquisição conjunta (satisfação de várias entidades)? Não\nO contrato é adjudicado por uma central de compras? Não\n\n8 - TÉCNICAS\nO concurso destina-se à celebração de um acordo-quadro? Inexistência de acordo-quadro\nÉ utilizado um leilão eletrónico? Não\nÉ adotada uma fase de negociação? Não\nSistema de Aquisição Dinâmico: Inexistência de sistema de aquisição dinâmico\n\n9 - LOCAL DA EXECUÇÃO DO CONTRATO\nLOCAL DA EXECUÇÃO DO CONTRATO (PROCEDIMENTO)\nPaís: Portugal\nNUT III: PT170\nLocalidade: Freguesia de Alvalade - Lisboa\nDistrito: Lisboa\nConcelho: Lisboa\nFreguesia: Freguesia de Alvalade - Lisboa\n\n10 - PRAZO DE EXECUÇÃO DO CONTRATO\nPrazo de execução do contrato: 36 MESES\nPrevisão de renovações: Não\n\n11 - FUNDOS EU\nTêm fundos EU? Não\n\n12 - DOCUMENTOS DE HABILITAÇÃO\nHabilitação para o exercício da atividade profissional: Não\n\n13 - CONDIÇÕES DE APRESENTAÇÃO\nPlataforma eletrónica utilizada pela entidade adjudicante: ACIN\nURL para Apresentação: https://www.acingov.pt\nAdmissibilidade da apresentação de propostas variantes: Não autorizado\nPrazo para apresentação das propostas: 21-01-2026 23:59\nPrazo durante o qual os concorrentes são obrigados a manter as respetivas propostas: 66 dias a contar do termo do prazo para a apresentação das propostas\nApresentação de Catálogo Eletrónico: Permitido\nIndicação de Subcontratação na Proposta: Inexistência de indicação de subcontratação\n\n14 - PRESTAÇÃO DE CAUÇÃO\nPrestação de caução: Sim\nPercentagem: 5%\nDescrição da Garantia Exigida: O valor da caução é de 5.00% do preço contratual.\n\n15 - FORNECIMENTO DAS PEÇAS DO CONCURSO, APRESENTAÇÃO DE PEDIDOS DE PARTICIPAÇÃO E APRESENTAÇÃO DAS PROPOSTAS\nLink para acesso às peças do concurso (URL): https://www.acingov.pt/acingovprod/2/zonaPublica/zona_publica_c/donwloadProcedurePiece/MTAwODc3MA==\n\n20 - OUTROS REQUISITOS\nInformação sobre contratos reservados. Aplica-se a contratos reservados (54º-A)? Não\n\n21 - CRITÉRIO DE ADJUDICAÇÃO\nMultifator: Não\nMonofator:\nNome: Preço\n\n24 - CONDIÇÕES DO CONTRATO\nFaturação Eletrónica: Permitido\nObrigação de Subcontratação:\nCódigo da Obrigação de Subcontratação: Não é aplicável nenhuma obrigação de subcontratação.\n\n25 - COMPRA PÚBLICA ESTRATÉGICA\nCompra Pública Estratégica: Inexistência de contratação pública estratégica\n\n26 - INFORMAÇÕES ADICIONAIS\nContrato adequado para PME: Sim\nCobertura ACP (Acordo dos Contratos Públicos da Organização Mundial do Comércio): Não\n\n27 - IDENTIFICAÇÃO E CONTACTOS DO ÓRGÃO DE RECURSOS ADMINISTRATIVOS\nDesignação: Conselho Diretivo do INEM, I.P.\nEndereço: RUA ALMIRANTE BARROSO, 36\nCódigo postal: 1000-013\nLocalidade: Lisboa\nTelefone: 213508100\nFax: \nEndereço eletrónico: inem@inem.pt\n\n28 - IDENTIFICAÇÃO DO(S) AUTOR(ES) DE ANÚNCIO\nNome: Sérgio Miguel Justo de Magalhães\nCargo: Coordenador do Gabinete de Gestão de Compras e Contratação Pública\n419922237",
    "nipc": "501356126",
    "distrito": "Lisboa",
    "concelho": "Lisboa",
    "freguesia": "Freguesia de Arroios - Lisboa",
    "site": "https://www.inem.pt/",
    "email": "inem@inem.pt",
    "designacao_contrato": "Aquisição de Licenciamento Fortinet",
    "descricao": "Aquisição de Licenciamento Fortinet",
    "preco_base": "364.500,00 EUR",
    "prazo_execucao": "36 MESES",
    "prazo_apresentacao_propostas": "21-01-2026 23:59",
    "fundos_eu": "Não",
    "plataforma_eletronica": "ACIN",
    "url_procedimento": "https://www.acingov.pt",
    "autor_nome": "Sérgio Miguel Justo de Magalhães",
    "autor_cargo": "Coordenador do Gabinete de Gestão de Compras e Contratação Pública"
  },
  {
    "numero_procedimento": "N/A",
    "entidade": "Valpi Bus - Alberto Pinto & Filhos Transportes Rodoviários, SA",
    "link": "https://diariodarepublica.pt/dr/detalhe/contrato-publico/33385-992662036",
    "detalhes_completos": "1 - IDENTIFICAÇÃO E CONTACTOS DA ENTIDADE ADJUDICANTE\nDesignação da entidade adjudicante: Valpi Bus - Alberto Pinto & Filhos Transportes Rodoviários, SA\nNIPC: 500728348\nEndereço: Av. Pedro Guedes\nCódigo postal: 4560-452\nLocalidade: Área Metropolitana do Porto\nPaís: Portugal\nNUT III: PT11A\nDistrito: Porto\nConcelho: Porto\nFreguesia: Todas\nTelefone: 224157960\nFax: 224157968\nEndereço da Entidade (URL): https://www.valpibus.pt\nEndereço Eletrónico: geral@valpi.pt\neDelivery Gateway (URL): https://community.vortal.biz/public/\nFunção da Organização: Adquirente\nNorma jurídica da Entidade Adjudicante: Autoridade da administração central\nÁrea de atividade da Autoridade Adjudicante: Serviços públicos das administrações públicas\n\n2 - JORNAL OFICIAL DA UNIÃO EUROPEIA\nO procedimento a que este anúncio diz respeito também é publicitado no Jornal Oficial da União Europeia? Sim\n\n3 - AVISO\nModelo de Anúncio: Concurso público\nData de Envio do Anúncio: 22-12-2025\n\n5 - PROCESSO\nTipo de Procedimento: Concurso público\nPreço base do procedimento: Sim\nValor do preço base do procedimento: 4.969.387,70 EUR\nProcedimento com lotes? Não\n\n6 - OBJETO DO CONTRATO\nNúmero de referência interna: CP_2025_001_ValpiBus\nDesignação do contrato: Aquisição de autocarros 100% elétricos para transporte coletivo de passageiros e Instalação de infraestruturas de carregamento\nDescrição: Aquisição de 10 (dez) autocarros elétricos Standard de categoria M3, da classe I, com piso baixo integral (Low floor), incluindo baterias de tração, e fornecimento e instalação de 5 (cinco) postos de carregamento elétrico com duas tomadas CCS, com capacidade de carregamento simultâneo para 10 (dez) viaturas elétricas, incluindo o respetivo Posto de Seccionamento e Posto de Transformação de Cliente (PS+PTC), todos os sistemas de gestão e controlo de carregamento, respetiva obra de instalação e ligação à rede elétrica de serviço público (RESP) e respetivos licenciamentos exigidos por lei.\n\nOpções: Não\nTipo de Contrato Principal: Aquisição de Bens Móveis\nTipo de Contrato: Aquisição de Bens Móveis\nClassificação CPV (Vocabulário Comum para os Contratos Públicos)\nObjeto principal\nVocabulário Principal: 34144910\nPreço base s/IVA: 4.450.000,00 EUR\nObjeto Complementar\nVocabulário Principal: 31158000\nPreço base s/IVA: 519.387,70 EUR\n\n7 - INDICAÇÕES ADICIONAIS\nO contrato envolve aquisição conjunta (satisfação de várias entidades)? Não\nO contrato é adjudicado por uma central de compras? Não\n\n8 - TÉCNICAS\nO concurso destina-se à celebração de um acordo-quadro? Inexistência de acordo-quadro\nÉ utilizado um leilão eletrónico? Não\nÉ adotada uma fase de negociação? Não\nSistema de Aquisição Dinâmico: Inexistência de sistema de aquisição dinâmico\n\n9 - LOCAL DA EXECUÇÃO DO CONTRATO\nLOCAL DA EXECUÇÃO DO CONTRATO (PROCEDIMENTO)\nPaís: Portugal\nNUT III: PT11A\nLocalidade: Área Metropolitana do Porto\nDistrito: Porto\nConcelho: Porto\nFreguesia: Todas\n\n10 - PRAZO DE EXECUÇÃO DO CONTRATO\nPrazo de execução do contrato: 140 DIAS\nPrevisão de renovações: Não\n\n11 - FUNDOS EU\nTêm fundos EU? Sim\n\n12 - DOCUMENTOS DE HABILITAÇÃO\nHabilitação para o exercício da atividade profissional: Não\n\n13 - CONDIÇÕES DE APRESENTAÇÃO\nPlataforma eletrónica utilizada pela entidade adjudicante: VORTAL\nURL para Apresentação: https://community.vortal.biz/public/\nAdmissibilidade da apresentação de propostas variantes: Não autorizado\nPrazo para apresentação das propostas: 03-01-2026 23:59\nPrazo durante o qual os concorrentes são obrigados a manter as respetivas propostas: 66 dias a contar do termo do prazo para a apresentação das propostas\nApresentação de Catálogo Eletrónico: Permitido\nIndicação de Subcontratação na Proposta: Inexistência de indicação de subcontratação\n\n14 - PRESTAÇÃO DE CAUÇÃO\nPrestação de caução: Sim\nPercentagem: 5%\nDescrição da Garantia Exigida: Depósito, garantia bancária ou seguro-caução\n\n15 - FORNECIMENTO DAS PEÇAS DO CONCURSO, APRESENTAÇÃO DE PEDIDOS DE PARTICIPAÇÃO E APRESENTAÇÃO DAS PROPOSTAS\nLink para acesso às peças do concurso (URL): https://community.vortal.biz/Public/public-tender-documents/Q21NeGpzOEhBZzRsZ3VDSUhqTnR2Z1I4Yis3eWZNR2JTNnJtcHVnMmVvOVIxUlpRTE50TmJkaWpWWXlIY0lzWkJiS2QxbVpWZFdmQU9iOVJBanJSdkE9PXNVUF9J\n\n20 - OUTROS REQUISITOS\nInformação sobre contratos reservados. Aplica-se a contratos reservados (54º-A)? Não\n\n21 - CRITÉRIO DE ADJUDICAÇÃO\nMultifator: Sim\nFator: \nNome: Qualidade\nPonderação: 90%\nSubfatores: Sim\nSubfatores: \nNome: Preço\nPonderação : 70%; \nNome: Prazo de entrega\nPonderação : 10%; \nNome: Técnica viaturas\nPonderação : 20%; \nFator: \nNome: Qualidade\nPonderação: 10%\nSubfatores: Sim\nSubfatores: \nNome: Preço\nPonderação : 70%; \nNome: Técnica infraestruturas\nPonderação : 30%; \n\n24 - CONDIÇÕES DO CONTRATO\nFaturação Eletrónica: Permitido\nObrigação de Subcontratação:\nCódigo da Obrigação de Subcontratação: Não é aplicável nenhuma obrigação de subcontratação.\n\n25 - COMPRA PÚBLICA ESTRATÉGICA\nCompra Pública Estratégica: Inexistência de contratação pública estratégica\n\n26 - INFORMAÇÕES ADICIONAIS\nContrato adequado para PME: Sim\nCobertura ACP (Acordo dos Contratos Públicos da Organização Mundial do Comércio): Não\n\n27 - IDENTIFICAÇÃO E CONTACTOS DO ÓRGÃO DE RECURSOS ADMINISTRATIVOS\nDesignação: Valpi Bus – Alberto Pinto & Filhos Transportes Rodoviários, S.A\nEndereço: Avenida Pedro Guedes\nCódigo postal: 4560-166\nLocalidade: Penafiel\nTelefone: +351 224157960\nFax: +351 224157960\nEndereço eletrónico: tiago.goncalves@valpibus.pt\n\n28 - IDENTIFICAÇÃO DO(S) AUTOR(ES) DE ANÚNCIO\nNome: José Mendes\nCargo: Responsável pela condução procedimento\n419919338",
    "nipc": "500728348",
    "distrito": "Porto",
    "concelho": "Porto",
    "freguesia": "Todas",
    "site": "https://www.valpibus.pt",
    "email": "geral@valpi.pt",
    "designacao_contrato": "Aquisição de autocarros 100% elétricos para transporte coletivo de passageiros e Instalação de infraestruturas de carregamento",
    "descricao": "Aquisição de 10 (dez) autocarros elétricos Standard de categoria M3, da classe I, com piso baixo integral (Low floor), incluindo baterias de tração, e fornecimento e instalação de 5 (cinco) postos de carregamento elétrico com duas tomadas CCS, com capacidade de carregamento simultâneo para 10 (dez) viaturas elétricas, incluindo o respetivo Posto de Seccionamento e Posto de Transformação de Cliente (PS+PTC), todos os sistemas de gestão e controlo de carregamento, respetiva obra de instalação e ligação à rede elétrica de serviço público (RESP) e respetivos licenciamentos exigidos por lei.",
    "preco_base": "4.450.000,00 EUR",
    "prazo_execucao": "140 DIAS",
    "prazo_apresentacao_propostas": "03-01-2026 23:59",
    "fundos_eu": "Sim",
    "plataforma_eletronica": "VORTAL",
    "url_procedimento": "https://community.vortal.biz/public/",
    "autor_nome": "José Mendes",
    "autor_cargo": "Responsável pela condução procedimento"
  },
  {
    "numero_procedimento": "N/A",
    "entidade": "Santa Casa da Misericórdia de Lisboa",
    "link": "https://diariodarepublica.pt/dr/detalhe/contrato-publico/33389-992662037",
    "detalhes_completos": "1 - IDENTIFICAÇÃO E CONTACTOS DA ENTIDADE ADJUDICANTE\nDesignação da entidade adjudicante: Santa Casa da Misericórdia de Lisboa\nNIPC: 500745471\nServiço/Órgão/Pessoa de contacto: Direção de Compras\nEndereço: Rua das Taipas, n.º 1\nCódigo postal: 1250-264\nLocalidade: Lisboa\nPaís: Portugal\nNUT III: PT170\nDistrito: Lisboa\nConcelho: Lisboa\nFreguesia: Todas\nTelefone: 213235000\nFax: 213235013\nEndereço da Entidade (URL): http://www.scml.pt/\nEndereço Eletrónico: dicom.nas@scml.pt\neDelivery Gateway (URL): https://www.acingov.pt\nFunção da Organização: Adquirente\nSubfunção da Organização: Organização cujo orçamento é utilizado para pagar o contrato; Organização que executa o pagamento; Organização que fornece informações adicionais sobre o processo de adjudicação; Organização que fornece mais informações sobre os prazos dos procedimentos de recurso; Organização que fornece acesso fora de linha aos documentos do concurso; Organização responsável pelo tratamento das propostas; Organização que recebe as propostas; Organização que trata os pedidos de participação; Organização que recebe pedidos de participação; Organização que fornece mais informações sobre os procedimentos de recurso; Organização que assina o contrato\nNorma jurídica da Entidade Adjudicante: Organismo de direito público, controlado por uma autoridade da administração central\nÁrea de atividade da Autoridade Adjudicante: Proteção social\n\n2 - JORNAL OFICIAL DA UNIÃO EUROPEIA\nO procedimento a que este anúncio diz respeito também é publicitado no Jornal Oficial da União Europeia? Sim\n\n3 - AVISO\nModelo de Anúncio: Concurso público\nData de Envio do Anúncio: 22-12-2025\n\n5 - PROCESSO\nTipo de Procedimento: Concurso público\nPreço base do procedimento: Sim\nValor do preço base do procedimento: 276.870,00 EUR\nProcedimento com lotes? Sim\nNº Máx. de Lotes Autorizado: 8\nNúmero máximo de lotes que podem ser adjudicados a um concorrente: 8\n\n6 - OBJETO DO CONTRATO\nNúmero de referência interna: 25DC32CPI015\nDesignação do contrato: Aquisição de Material de Incontinência\nDescrição: Aquisição de Material de Incontinência\nOpções: Não\nTipo de Contrato Principal: Aquisição de Bens Móveis\nTipo de Contrato: Aquisição de Bens Móveis\nClassificação CPV (Vocabulário Comum para os Contratos Públicos)\nObjeto principal\nVocabulário Principal: 33751000\nPreço base s/IVA: 276.870,00 EUR\nLotes: \nNº: LOT-0001\nDescrição do Lote: Resguardos descartáveis 90cm (+/-5cm)  x 60 cm (+/-5cm)\nPreço base s/IVA: 224.000,00 EUR\nClassificação CPV (Vocabulário Comum para os Contratos Públicos)\nObjeto principal\nVocabulário Principal: 33751000\nNº: LOT-0002\nDescrição do Lote: Resguardos descartáveis (180 a 190cm x 80 a 90 cm) \nPreço base s/IVA: 23.670,00 EUR\nClassificação CPV (Vocabulário Comum para os Contratos Públicos)\nObjeto principal\nVocabulário Principal: 33751000\nNº: LOT-0003\nDescrição do Lote: Resguardos descartáveis 60cm (+/-5cm)  x 60 cm (+/-5cm)\nPreço base s/IVA: 18.750,00 EUR\nClassificação CPV (Vocabulário Comum para os Contratos Públicos)\nObjeto principal\nVocabulário Principal: 33751000\nNº: LOT-0004\nDescrição do Lote: Fralda cueca criança (12/14 a 18/20kg)\nPreço base s/IVA: 1.980,00 EUR\nClassificação CPV (Vocabulário Comum para os Contratos Públicos)\nObjeto principal\nVocabulário Principal: 33751000\nNº: LOT-0005\nDescrição do Lote: Fralda cueca criança tamanho 7 xl plus - 16/17 a 26/29 Kg\nPreço base s/IVA: 2.250,00 EUR\nClassificação CPV (Vocabulário Comum para os Contratos Públicos)\nObjeto principal\nVocabulário Principal: 33751000\nNº: LOT-0006\nDescrição do Lote: Fralda cueca criança tamanho 9 - 22 a 37 Kg (+/-2kg)\nPreço base s/IVA: 1.430,00 EUR\nClassificação CPV (Vocabulário Comum para os Contratos Públicos)\nObjeto principal\nVocabulário Principal: 33751000\nNº: LOT-0007\nDescrição do Lote: Fralda cueca criança (mínimo 27kg a 60kg máximo)\nPreço base s/IVA: 2.760,00 EUR\nClassificação CPV (Vocabulário Comum para os Contratos Públicos)\nObjeto principal\nVocabulário Principal: 33751000\nNº: LOT-0008\nDescrição do Lote: Penso de Incontinência Masculino\nPreço base s/IVA: 2.030,00 EUR\nClassificação CPV (Vocabulário Comum para os Contratos Públicos)\nObjeto principal\nVocabulário Principal: 33751000\n\n7 - INDICAÇÕES ADICIONAIS\nO contrato envolve aquisição conjunta (satisfação de várias entidades)? Não\nO contrato é adjudicado por uma central de compras? Não\n\n8 - TÉCNICAS\nO concurso destina-se à celebração de um acordo-quadro? Inexistência de acordo-quadro\nÉ utilizado um leilão eletrónico? Não\nÉ adotada uma fase de negociação? Não\nSistema de Aquisição Dinâmico: Inexistência de sistema de aquisição dinâmico\n\n9 - LOCAL DA EXECUÇÃO DO CONTRATO\nLOCAL DA EXECUÇÃO DO CONTRATO (PROCEDIMENTO)\nPaís: Portugal\nNUT III: PT170\nLocalidade: Grande Lisboa\nDistrito: Lisboa\nConcelho: Lisboa\nFreguesia: Todas\nLOCAL DA EXECUÇÃO DO CONTRATO (LOTE)\nIdentificador do Lote: LOT-0001; LOT-0002; LOT-0003; LOT-0004; LOT-0005; LOT-0006; LOT-0007; LOT-0008\nPaís: Portugal\nNUT III: PT170\nLocalidade: Grande Lisboa\nDistrito: Lisboa\nConcelho: Lisboa\nFreguesia: Todas\n\n10 - PRAZO DE EXECUÇÃO DO CONTRATO\nIdentificador do Lote: LOT-0001; LOT-0002; LOT-0003; LOT-0004; LOT-0005; LOT-0006; LOT-0007; LOT-0008\nPrazo de execução do contrato: 24 MESES\nPrevisão de renovações: Não\n\n11 - FUNDOS EU\nIdentificador do Lote: LOT-0001; LOT-0002; LOT-0003; LOT-0004; LOT-0005; LOT-0006; LOT-0007; LOT-0008\nTêm fundos EU? Não\n\n12 - DOCUMENTOS DE HABILITAÇÃO\nHabilitação para o exercício da atividade profissional: Não\n\n13 - CONDIÇÕES DE APRESENTAÇÃO\nPlataforma eletrónica utilizada pela entidade adjudicante: ACIN\nURL para Apresentação: https://www.acingov.pt\nAdmissibilidade da apresentação de propostas variantes: Não autorizado\nPrazo para apresentação das propostas: 21-01-2026 17:00\nPrazo durante o qual os concorrentes são obrigados a manter as respetivas propostas: 120 dias a contar do termo do prazo para a apresentação das propostas\nApresentação de Catálogo Eletrónico: Permitido\nIndicação de Subcontratação na Proposta: Inexistência de indicação de subcontratação\n\n14 - PRESTAÇÃO DE CAUÇÃO\nPrestação de caução: Não\n\n15 - FORNECIMENTO DAS PEÇAS DO CONCURSO, APRESENTAÇÃO DE PEDIDOS DE PARTICIPAÇÃO E APRESENTAÇÃO DAS PROPOSTAS\nLink para acesso às peças do concurso (URL): https://www.acingov.pt/acingovprod/2/zonaPublica/zona_publica_c/donwloadProcedurePiece/MTAwODgxMg==\n\n20 - OUTROS REQUISITOS\nIdentificador do Lote: LOT-0001; LOT-0002; LOT-0003; LOT-0004; LOT-0005; LOT-0006; LOT-0007; LOT-0008\nInformação sobre contratos reservados. Aplica-se a contratos reservados (54º-A)? Não\n\n21 - CRITÉRIO DE ADJUDICAÇÃO\nO Critério de adjudicação é diferenciado por lote? Não\nMultifator: Não\nMonofator:\nNome: Preço\n\n24 - CONDIÇÕES DO CONTRATO\nIdentificador do Lote: LOT-0001; LOT-0002; LOT-0003; LOT-0004; LOT-0005; LOT-0006; LOT-0007; LOT-0008\nFaturação Eletrónica: Necessário\nObrigação de Subcontratação:\nCódigo da Obrigação de Subcontratação: Não é aplicável nenhuma obrigação de subcontratação.\n\n25 - COMPRA PÚBLICA ESTRATÉGICA\nCompra Pública Estratégica: Inexistência de contratação pública estratégica\n\n26 - INFORMAÇÕES ADICIONAIS\nIdentificador do Lote: LOT-0001; LOT-0002; LOT-0003; LOT-0004; LOT-0005; LOT-0006; LOT-0007; LOT-0008\nContrato adequado para PME: Sim\nCobertura ACP (Acordo dos Contratos Públicos da Organização Mundial do Comércio): Não\n\n27 - IDENTIFICAÇÃO E CONTACTOS DO ÓRGÃO DE RECURSOS ADMINISTRATIVOS\nDesignação: Exma Mesa da SCML\nEndereço: Largo Trindade Coelho\nCódigo postal: 1200-470\nLocalidade: Lisboa\nTelefone: 213235000\nFax: \nEndereço eletrónico: dicom.nas@scml.pt\nPrazo de interposição do recurso: 10 dias\n\n28 - IDENTIFICAÇÃO DO(S) AUTOR(ES) DE ANÚNCIO\nNome: Vanda Simão\nCargo: Diretora da Direção de Compras\n419920666",
    "nipc": "500745471",
    "distrito": "Lisboa",
    "concelho": "Lisboa",
    "freguesia": "Todas",
    "site": "http://www.scml.pt/",
    "email": "dicom.nas@scml.pt",
    "designacao_contrato": "Aquisição de Material de Incontinência",
    "descricao": "Aquisição de Material de Incontinência",
    "preco_base": "276.870,00 EUR",
    "prazo_execucao": "24 MESES",
    "prazo_apresentacao_propostas": "21-01-2026 17:00",
    "fundos_eu": "Não",
    "plataforma_eletronica": "ACIN",
    "url_procedimento": "https://www.acingov.pt",
    "autor_nome": "Vanda Simão",
    "autor_cargo": "Diretora da Direção de Compras"
  },
  {
    "numero_procedimento": "N/A",
    "entidade": "Associação Humanitária dos Bombeiros Voluntários de Viatodos",
    "link": "https://diariodarepublica.pt/dr/detalhe/contrato-publico/33391-992662038",
    "detalhes_completos": "1 - IDENTIFICAÇÃO E CONTACTOS DA ENTIDADE ADJUDICANTE\nDesignação da entidade adjudicante: Associação Humanitária dos Bombeiros Voluntários de Viatodos\nNIPC: 501440038\nEndereço: Rua dos Bombeiros Voluntários, nº 5\nCódigo postal: 4775-270\nLocalidade: Braga\nPaís: Portugal\nNUT III: PT112\nDistrito: Braga\nConcelho: Barcelos\nFreguesia: União das Freguesias de Viatodos, Grimancelos, Minhotães e Monte de Fralães\nTelefone: 252960800\nEndereço da Entidade (URL): https://bombeirosviatodos.pt/\nEndereço Eletrónico: direcao@bombeirosviatodos.org\neDelivery Gateway (URL): https://community.vortal.biz/public/\nFunção da Organização: Adquirente\nNorma jurídica da Entidade Adjudicante: Contratante do domínio da defesa\nÁrea de atividade da Autoridade Adjudicante: Proteção ambiental\n\n2 - JORNAL OFICIAL DA UNIÃO EUROPEIA\nO procedimento a que este anúncio diz respeito também é publicitado no Jornal Oficial da União Europeia? Sim\n\n3 - AVISO\nModelo de Anúncio: Concurso público\nData de Envio do Anúncio: 22-12-2025\n\n5 - PROCESSO\nTipo de Procedimento: Concurso público\nPreço base do procedimento: Sim\nValor do preço base do procedimento: 255.000,00 EUR\nProcedimento com lotes? Não\n\n6 - OBJETO DO CONTRATO\nNúmero de referência interna: CP02/25\nDesignação do contrato: Aquisição de uma Viatura Florestal de Combate a Incêndios (VFCI) para a Associação Humanitária de Bombeiros Voluntários de Viatodos\nDescrição: Aquisição de uma Viatura Florestal de Combate a Incêndios (VFCI) para a Associação Humanitária de Bombeiros Voluntários de Viatodos\nOpções: Não\nTipo de Contrato Principal: Aquisição de Bens Móveis\nTipo de Contrato: Aquisição de Bens Móveis\nClassificação CPV (Vocabulário Comum para os Contratos Públicos)\nObjeto principal\nVocabulário Principal: 34144210\nPreço base s/IVA: 255.000,00 EUR\n\n7 - INDICAÇÕES ADICIONAIS\nO contrato envolve aquisição conjunta (satisfação de várias entidades)? Não\nO contrato é adjudicado por uma central de compras? Não\n\n8 - TÉCNICAS\nO concurso destina-se à celebração de um acordo-quadro? Inexistência de acordo-quadro\nÉ utilizado um leilão eletrónico? Não\nÉ adotada uma fase de negociação? Não\nSistema de Aquisição Dinâmico: Inexistência de sistema de aquisição dinâmico\n\n9 - LOCAL DA EXECUÇÃO DO CONTRATO\nLOCAL DA EXECUÇÃO DO CONTRATO (PROCEDIMENTO)\nPaís: Portugal\nNUT III: PT112\nLocalidade: Braga\nDistrito: Braga\nConcelho: Barcelos\nFreguesia: União das Freguesias de Viatodos, Grimancelos, Minhotães e Monte de Fralães\n\n10 - PRAZO DE EXECUÇÃO DO CONTRATO\nPrazo de execução do contrato: 200 DIAS\nPrevisão de renovações: Não\n\n11 - FUNDOS EU\nTêm fundos EU? Sim\n\n12 - DOCUMENTOS DE HABILITAÇÃO\nHabilitação para o exercício da atividade profissional: Não\n\n13 - CONDIÇÕES DE APRESENTAÇÃO\nPlataforma eletrónica utilizada pela entidade adjudicante: VORTAL\nURL para Apresentação: https://community.vortal.biz/public/\nAdmissibilidade da apresentação de propostas variantes: Não autorizado\nPrazo para apresentação das propostas: 21-01-2026 23:59\nPrazo durante o qual os concorrentes são obrigados a manter as respetivas propostas: 66 dias a contar do termo do prazo para a apresentação das propostas\nApresentação de Catálogo Eletrónico: Permitido\nIndicação de Subcontratação na Proposta: Inexistência de indicação de subcontratação\n\n14 - PRESTAÇÃO DE CAUÇÃO\nPrestação de caução: Não\n\n15 - FORNECIMENTO DAS PEÇAS DO CONCURSO, APRESENTAÇÃO DE PEDIDOS DE PARTICIPAÇÃO E APRESENTAÇÃO DAS PROPOSTAS\nLink para acesso às peças do concurso (URL): https://community.vortal.biz/Public/public-tender-documents/S1ZFdStVOVVQVlBSZ01veE93TFkrckl0YjlIZ3BNcVdYb1VpVGtNdlNvTHpJZHVkemhJODBCZmsyTlYxR202ZWg0WmR6dTRpWW5Hakx1UFVhV3ZTamc9PSpwNDVq\n\n20 - OUTROS REQUISITOS\nInformação sobre contratos reservados. Aplica-se a contratos reservados (54º-A)? Não\n\n21 - CRITÉRIO DE ADJUDICAÇÃO\nMultifator: Sim\nFator: \nNome: Preço\nPonderação: 40%\nSubfatores: Não\nFator: \nNome: Qualidade\nPonderação: 40%\nSubfatores: Não\nFator: \nNome: Outros\nOutro Nome: Prazo de Garantia\nPonderação: 5%\nSubfatores: Não\nFator: \nNome: Outros\nOutro Nome: Prazo de Entrega\nPonderação: 15%\nSubfatores: Não\n\n24 - CONDIÇÕES DO CONTRATO\nFaturação Eletrónica: Permitido\nObrigação de Subcontratação:\nCódigo da Obrigação de Subcontratação: Não é aplicável nenhuma obrigação de subcontratação.\n\n25 - COMPRA PÚBLICA ESTRATÉGICA\nCompra Pública Estratégica: Inexistência de contratação pública estratégica\n\n26 - INFORMAÇÕES ADICIONAIS\nContrato adequado para PME: Sim\nCobertura ACP (Acordo dos Contratos Públicos da Organização Mundial do Comércio): Não\n\n27 - IDENTIFICAÇÃO E CONTACTOS DO ÓRGÃO DE RECURSOS ADMINISTRATIVOS\nDesignação: Direção da Associação Humanitária de Bombeiros Voluntários de Viatodos\nEndereço: Rua dos Bombeiros Voluntários, nº 5\nCódigo postal: 4775-270\nLocalidade: Barcelos\nTelefone: +351 252960800\nFax: +351 252960800\nEndereço eletrónico: direcao@bombeirosviatodos.org\n\n28 - IDENTIFICAÇÃO DO(S) AUTOR(ES) DE ANÚNCIO\nNome: José Lemos de Azevedo,\nCargo: Presidente da Direção\n419922448",
    "nipc": "501440038",
    "distrito": "Braga",
    "concelho": "Barcelos",
    "freguesia": "União das Freguesias de Viatodos, Grimancelos, Minhotães e Monte de Fralães",
    "site": "https://bombeirosviatodos.pt/",
    "email": "direcao@bombeirosviatodos.org",
    "designacao_contrato": "Aquisição de uma Viatura Florestal de Combate a Incêndios (VFCI) para a Associação Humanitária de Bombeiros Voluntários de Viatodos",
    "descricao": "Aquisição de uma Viatura Florestal de Combate a Incêndios (VFCI) para a Associação Humanitária de Bombeiros Voluntários de Viatodos",
    "preco_base": "255.000,00 EUR",
    "prazo_execucao": "200 DIAS",
    "prazo_apresentacao_propostas": "21-01-2026 23:59",
    "fundos_eu": "Sim",
    "plataforma_eletronica": "VORTAL",
    "url_procedimento": "https://community.vortal.biz/public/",
    "autor_nome": "José Lemos de Azevedo,",
    "autor_cargo": "Presidente da Direção"
  },
  {
    "numero_procedimento": "N/A",
    "entidade": "Expressdiagram - Transportes Rodoviários, L.da",
    "link": "https://diariodarepublica.pt/dr/detalhe/contrato-publico/33392-992662039",
    "detalhes_completos": "1 - IDENTIFICAÇÃO E CONTACTOS DA ENTIDADE ADJUDICANTE\nDesignação da entidade adjudicante: Expressdiagram - Transportes Rodoviários, L.da\nNIPC: 516524240\nEndereço: Av. Pedro Guedes, s/n\nCódigo postal: 4560-452\nLocalidade: Porto\nPaís: Portugal\nNUT III: PT11C\nDistrito: Porto\nConcelho: Penafiel\nFreguesia: Freguesia de Penafiel\nTelefone: 224157960\nEndereço da Entidade (URL): https://www.iberinform.pt/empresa/24964845/expressdiagram-transportes-rodoviarios-lda\nEndereço Eletrónico: geral@valpibus.pt\neDelivery Gateway (URL): https://community.vortal.biz/public/\nFunção da Organização: Adquirente\nNorma jurídica da Entidade Adjudicante: Entidade com direitos especiais ou exclusivos\nÁrea de atividade da Autoridade Adjudicante: Serviços públicos das administrações públicas\n\n2 - JORNAL OFICIAL DA UNIÃO EUROPEIA\nO procedimento a que este anúncio diz respeito também é publicitado no Jornal Oficial da União Europeia? Sim\n\n3 - AVISO\nModelo de Anúncio: Concurso público\nData de Envio do Anúncio: 22-12-2025\n\n5 - PROCESSO\nTipo de Procedimento: Concurso público\nPreço base do procedimento: Sim\nValor do preço base do procedimento: 4.974.387,70 EUR\nProcedimento com lotes? Não\n\n6 - OBJETO DO CONTRATO\nNúmero de referência interna: CP_2025_001_EXPRESSDIAGRAM\nDesignação do contrato: Aquisição de autocarros 100% elétricos para transporte coletivo de passageiros e Instalação de infraestruturas de carregamento\nDescrição: Aquisição de 10 (dez) autocarros elétricos Standard de categoria M3, da classe I, com piso baixo integral (Low floor), incluindo baterias de tração, e fornecimento e instalação de 5 (cinco) postos de carregamento elétrico, com capacidade de carregamento simultâneo para 10 (dez) viaturas elétricas, incluindo o respetivo Posto de Transformação (PT) e todos os sistemas de gestão e controlo de carregamento, respetiva obra de instalação e ligação à rede elétrica. \n\nOpções: Não\nTipo de Contrato Principal: Aquisição de Bens Móveis\nTipo de Contrato: Aquisição de Bens Móveis\nClassificação CPV (Vocabulário Comum para os Contratos Públicos)\nObjeto principal\nVocabulário Principal: 34144910\nPreço base s/IVA: 4.455.000,00 EUR\nObjeto Complementar\nVocabulário Principal: 31158000\nPreço base s/IVA: 519.387,70 EUR\n\n7 - INDICAÇÕES ADICIONAIS\nO contrato envolve aquisição conjunta (satisfação de várias entidades)? Não\nO contrato é adjudicado por uma central de compras? Não\n\n8 - TÉCNICAS\nO concurso destina-se à celebração de um acordo-quadro? Inexistência de acordo-quadro\nÉ utilizado um leilão eletrónico? Não\nÉ adotada uma fase de negociação? Não\nSistema de Aquisição Dinâmico: Inexistência de sistema de aquisição dinâmico\n\n9 - LOCAL DA EXECUÇÃO DO CONTRATO\nLOCAL DA EXECUÇÃO DO CONTRATO (PROCEDIMENTO)\nPaís: Portugal\nNUT III: PT11C\nLocalidade: Porto\nDistrito: Porto\nConcelho: Penafiel\nFreguesia: Freguesia de Penafiel\n\n10 - PRAZO DE EXECUÇÃO DO CONTRATO\nPrazo de execução do contrato: 140 DIAS\nPrevisão de renovações: Não\n\n11 - FUNDOS EU\nTêm fundos EU? Sim\n\n12 - DOCUMENTOS DE HABILITAÇÃO\nHabilitação para o exercício da atividade profissional: Não\n\n13 - CONDIÇÕES DE APRESENTAÇÃO\nPlataforma eletrónica utilizada pela entidade adjudicante: VORTAL\nURL para Apresentação: https://community.vortal.biz/public/\nAdmissibilidade da apresentação de propostas variantes: Não autorizado\nPrazo para apresentação das propostas: 03-01-2026 23:59\nPrazo durante o qual os concorrentes são obrigados a manter as respetivas propostas: 66 dias a contar do termo do prazo para a apresentação das propostas\nApresentação de Catálogo Eletrónico: Permitido\nIndicação de Subcontratação na Proposta: Inexistência de indicação de subcontratação\n\n14 - PRESTAÇÃO DE CAUÇÃO\nPrestação de caução: Sim\nPercentagem: 5%\nDescrição da Garantia Exigida: Depósito, garantia bancária ou seguro-caução\n\n15 - FORNECIMENTO DAS PEÇAS DO CONCURSO, APRESENTAÇÃO DE PEDIDOS DE PARTICIPAÇÃO E APRESENTAÇÃO DAS PROPOSTAS\nLink para acesso às peças do concurso (URL): https://community.vortal.biz/Public/public-tender-documents/QzRHcXd5ZDlYMXM3MUZUNHkrQk1jQWdxcmU5YkgwSmwveStvUmxKdG9BTDh0Z3pFeElGVzVlTUE0R1JhQkhlL3lnMDRTWEJCZTZPZUJXR2xFTnlpb2c9PUQodEQz\n\n20 - OUTROS REQUISITOS\nInformação sobre contratos reservados. Aplica-se a contratos reservados (54º-A)? Não\n\n21 - CRITÉRIO DE ADJUDICAÇÃO\nMultifator: Sim\nFator: \nNome: Qualidade\nPonderação: 90%\nSubfatores: Sim\nSubfatores: \nNome: Preço \nPonderação : 70%; \nNome: Prazo de entrega\nPonderação : 10%; \nNome: Componente Técnica viaturas\nPonderação : 20%; \nFator: \nNome: Qualidade\nPonderação: 10%\nSubfatores: Sim\nSubfatores: \nNome: Preço\nPonderação : 70%; \nNome: Técnica infraestruturas\nPonderação : 30%; \n\n24 - CONDIÇÕES DO CONTRATO\nFaturação Eletrónica: Permitido\nObrigação de Subcontratação:\nCódigo da Obrigação de Subcontratação: Não é aplicável nenhuma obrigação de subcontratação.\n\n25 - COMPRA PÚBLICA ESTRATÉGICA\nCompra Pública Estratégica: Inexistência de contratação pública estratégica\n\n26 - INFORMAÇÕES ADICIONAIS\nContrato adequado para PME: Sim\nCobertura ACP (Acordo dos Contratos Públicos da Organização Mundial do Comércio): Não\n\n27 - IDENTIFICAÇÃO E CONTACTOS DO ÓRGÃO DE RECURSOS ADMINISTRATIVOS\nDesignação: EXPRESSDIAGRAM – TRANSPORTES RODOVIÁRIOS, LDA\nEndereço: Avenida Pedro Guedes, 256\nCódigo postal: 4560-452\nLocalidade: Penafiel\nTelefone: +351 224157960\nFax: +351 224157960\nEndereço eletrónico: pedrobrancoxavier@gmail.com\n\n28 - IDENTIFICAÇÃO DO(S) AUTOR(ES) DE ANÚNCIO\nNome: Tiago Fernando Gonçalves Neves\nCargo: Responsável pela condução do procedimento\n419919427",
    "nipc": "516524240",
    "distrito": "Porto",
    "concelho": "Penafiel",
    "freguesia": "Freguesia de Penafiel",
    "site": "https://www.iberinform.pt/empresa/24964845/expressdiagram-transportes-rodoviarios-lda",
    "email": "geral@valpibus.pt",
    "designacao_contrato": "Aquisição de autocarros 100% elétricos para transporte coletivo de passageiros e Instalação de infraestruturas de carregamento",
    "descricao": "Aquisição de 10 (dez) autocarros elétricos Standard de categoria M3, da classe I, com piso baixo integral (Low floor), incluindo baterias de tração, e fornecimento e instalação de 5 (cinco) postos de carregamento elétrico, com capacidade de carregamento simultâneo para 10 (dez) viaturas elétricas, incluindo o respetivo Posto de Transformação (PT) e todos os sistemas de gestão e controlo de carregamento, respetiva obra de instalação e ligação à rede elétrica.",
    "preco_base": "4.455.000,00 EUR",
    "prazo_execucao": "140 DIAS",
    "prazo_apresentacao_propostas": "03-01-2026 23:59",
    "fundos_eu": "Sim",
    "plataforma_eletronica": "VORTAL",
    "url_procedimento": "https://community.vortal.biz/public/",
    "autor_nome": "Tiago Fernando Gonçalves Neves",
    "autor_cargo": "Responsável pela condução do procedimento"
  },
  {
    "numero_procedimento": "N/A",
    "entidade": "Município de Almada",
    "link": "https://diariodarepublica.pt/dr/detalhe/contrato-publico/33393-992662040",
    "detalhes_completos": "Alteração do Anúncio de procedimento n.º 33094/2025, de 2025-12-22, com o ID 419896578\n\n1 - IDENTIFICAÇÃO E CONTACTOS DA ENTIDADE ADJUDICANTE\nDesignação da entidade adjudicante: Município de Almada\nNIPC: 500051054\nEndereço: Largo Luís de Camões\nCódigo postal: 2800-158\nLocalidade: Setúbal\nPaís: Portugal\nNUT III: PT170\nDistrito: Setúbal\nConcelho: Almada\nFreguesia: União das Freguesias de Almada, Cova da Piedade, Pragal e Cacilhas\nTelefone: 212724000\nFax: 212724599\nEndereço da Entidade (URL): www.m-almada.pt\nEndereço Eletrónico: almadainforma@cma.m-almada.pt\neDelivery Gateway (URL): https://community.vortal.biz/public/\nFunção da Organização: Adquirente\nNorma jurídica da Entidade Adjudicante: Autoridade local\nÁrea de atividade da Autoridade Adjudicante: Serviços públicos das administrações públicas\n\n2 - JORNAL OFICIAL DA UNIÃO EUROPEIA\nO procedimento a que este anúncio diz respeito também é publicitado no Jornal Oficial da União Europeia? Sim\n\n3 - AVISO\nModelo de Anúncio: Concurso público\nData de Envio do Anúncio: 22-12-2025\n\n5 - PROCESSO\nTipo de Procedimento: Concurso público\nPreço base do procedimento: Sim\nValor do preço base do procedimento: 782.222,00 EUR\nProcedimento com lotes? Não\n\n6 - OBJETO DO CONTRATO\nNúmero de referência interna: CPN01804S2025\nDesignação do contrato: Aquisição de serviços de comunicações globais (eletrónicas, fixa e móvel) para os Edifícios e Escolas do Município de Almada\nDescrição: Aquisição de serviços de comunicações globais (eletrónicas, fixa e móvel) para os Edifícios e Escolas do Município de Almada\nOpções: Não\nTipo de Contrato Principal: Aquisição de Serviços\nTipo de Contrato: Aquisição de Serviços\nClassificação CPV (Vocabulário Comum para os Contratos Públicos)\nObjeto principal\nVocabulário Principal: 64200000\nPreço base s/IVA: 782.222,00 EUR\n\n7 - INDICAÇÕES ADICIONAIS\nO contrato envolve aquisição conjunta (satisfação de várias entidades)? Não\nO contrato é adjudicado por uma central de compras? Não\n\n8 - TÉCNICAS\nO concurso destina-se à celebração de um acordo-quadro? Inexistência de acordo-quadro\nÉ utilizado um leilão eletrónico? Não\nÉ adotada uma fase de negociação? Não\nSistema de Aquisição Dinâmico: Inexistência de sistema de aquisição dinâmico\n\n9 - LOCAL DA EXECUÇÃO DO CONTRATO\nLOCAL DA EXECUÇÃO DO CONTRATO (PROCEDIMENTO)\nPaís: Portugal\nNUT III: PT170\nLocalidade: Setúbal\nDistrito: Setúbal\nConcelho: Almada\nFreguesia: Todas\n\n10 - PRAZO DE EXECUÇÃO DO CONTRATO\nPrazo de execução do contrato: 36 MESES\nPrevisão de renovações: Não\n\n11 - FUNDOS EU\nTêm fundos EU? Não\n\n12 - DOCUMENTOS DE HABILITAÇÃO\nHabilitação para o exercício da atividade profissional: Sim\nTipo: Outros\nDescrição - Outros: Não aplicável\nDescrição: Não aplicável\n\n13 - CONDIÇÕES DE APRESENTAÇÃO\nPlataforma eletrónica utilizada pela entidade adjudicante: VORTAL\nURL para Apresentação: https://community.vortal.biz/public/\nAdmissibilidade da apresentação de propostas variantes: Não autorizado\nPrazo para apresentação das propostas: 17-01-2026 23:59\nPrazo durante o qual os concorrentes são obrigados a manter as respetivas propostas: 120 dias a contar do termo do prazo para a apresentação das propostas\nApresentação de Catálogo Eletrónico: Não autorizado\nIndicação de Subcontratação na Proposta: Inexistência de indicação de subcontratação\n\n14 - PRESTAÇÃO DE CAUÇÃO\nPrestação de caução: Sim\nPercentagem: 5%\nDescrição da Garantia Exigida: Depósito em dinheiro ou em títulos emitidos ou garantidos pelo Estado, ou mediante garantia bancária ou seguro-caução\n\n15 - FORNECIMENTO DAS PEÇAS DO CONCURSO, APRESENTAÇÃO DE PEDIDOS DE PARTICIPAÇÃO E APRESENTAÇÃO DAS PROPOSTAS\nLink para acesso às peças do concurso (URL): https://community.vortal.biz/Public/public-tender-documents/N3NLMTJpWjN6ejZrSlVnS1ZXM1BSRVppMlpHQlliOWdhQmpndzYwQlV5WFdyejd6bGw0SVMyejAyNTh4eVVKVEVwdWhjTDIrQkZlQkYrU1dic2swU0E9PXd3U3hv\n\n20 - OUTROS REQUISITOS\nInformação sobre contratos reservados. Aplica-se a contratos reservados (54º-A)? Não\n\n21 - CRITÉRIO DE ADJUDICAÇÃO\nMultifator: Sim\nFator: \nNome: Preço\nPonderação: 40%\nSubfatores: Não\nFator: \nNome: Qualidade\nPonderação: 60%\nSubfatores: Não\n\n24 - CONDIÇÕES DO CONTRATO\nFaturação Eletrónica: Permitido\nObrigação de Subcontratação:\nCódigo da Obrigação de Subcontratação: Não é aplicável nenhuma obrigação de subcontratação.\n\n25 - COMPRA PÚBLICA ESTRATÉGICA\nCompra Pública Estratégica: Inexistência de contratação pública estratégica\n\n26 - INFORMAÇÕES ADICIONAIS\nContrato adequado para PME: Sim\nCobertura ACP (Acordo dos Contratos Públicos da Organização Mundial do Comércio): Não\n\n27 - IDENTIFICAÇÃO E CONTACTOS DO ÓRGÃO DE RECURSOS ADMINISTRATIVOS\nDesignação: Município de Almada\nEndereço: Largo Luís Camões\nCódigo postal: 2800-158\nLocalidade: Almada\nTelefone: +351 212724000\nFax: +351 212724000\nEndereço eletrónico: gab.presidencia@cma.m-almada.pt\n\n28 - IDENTIFICAÇÃO DO(S) AUTOR(ES) DE ANÚNCIO\nNome: Inês de Medeiros\nCargo: Presidente da Câmara Municipal de Almada\n\n29 - ALTERAÇÃO\nMotivo da Alteração: Correção pelo adquirente\nIdentificador da Versão do Anúncio a Alterar: 6fb5dc0e-9fc1-43f5-820d-c67628b0f841-01\nIdentificador das Secções Alteradas do Anúncio Anterior: Condições de Apresentação\nAlteração dos Documentos do Concurso: Não\n419923103",
    "nipc": "500051054",
    "distrito": "Setúbal",
    "concelho": "Almada",
    "freguesia": "União das Freguesias de Almada, Cova da Piedade, Pragal e Cacilhas",
    "site": "www.m-almada.pt",
    "email": "almadainforma@cma.m-almada.pt",
    "designacao_contrato": "Aquisição de serviços de comunicações globais (eletrónicas, fixa e móvel) para os Edifícios e Escolas do Município de Almada",
    "descricao": "Aquisição de serviços de comunicações globais (eletrónicas, fixa e móvel) para os Edifícios e Escolas do Município de Almada",
    "preco_base": "782.222,00 EUR",
    "prazo_execucao": "36 MESES",
    "prazo_apresentacao_propostas": "17-01-2026 23:59",
    "fundos_eu": "Não",
    "plataforma_eletronica": "VORTAL",
    "url_procedimento": "https://community.vortal.biz/public/",
    "autor_nome": "Inês de Medeiros",
    "autor_cargo": "Presidente da Câmara Municipal de Almada"
  },
  {
    "numero_procedimento": "N/A",
    "entidade": "Instituto do Turismo de Portugal, IP",
    "link": "https://diariodarepublica.pt/dr/detalhe/contrato-publico/33394-992662041",
    "detalhes_completos": "1 - IDENTIFICAÇÃO E CONTACTOS DA ENTIDADE ADJUDICANTE\nDesignação da entidade adjudicante: Instituto do Turismo de Portugal, IP\nNIPC: 508666236\nEndereço: Rua Ivone Silva, lote 6\nCódigo postal: 1050-124\nLocalidade: Lisboa\nPaís: Portugal\nNUT III: PT170\nDistrito: Lisboa\nConcelho: Lisboa\nFreguesia: Freguesia de Avenidas Novas\nTelefone: 211140200\nFax: 211140200\nEndereço da Entidade (URL): https://www.turismodeportugal.pt\nEndereço Eletrónico: info@turismodeportugal.pt\neDelivery Gateway (URL): https://community.vortal.biz/public/\nFunção da Organização: Adquirente\nNorma jurídica da Entidade Adjudicante: Instituição, órgão ou agência da UE\nÁrea de atividade da Autoridade Adjudicante: Serviços públicos das administrações públicas\n\n2 - JORNAL OFICIAL DA UNIÃO EUROPEIA\nO procedimento a que este anúncio diz respeito também é publicitado no Jornal Oficial da União Europeia? Sim\n\n3 - AVISO\nModelo de Anúncio: Concurso público\nData de Envio do Anúncio: 22-12-2025\n\n5 - PROCESSO\nTipo de Procedimento: Concurso público\nPreço base do procedimento: Sim\nValor do preço base do procedimento: 279.650,00 EUR\nProcedimento com lotes? Não\n\n6 - OBJETO DO CONTRATO\nNúmero de referência interna: P(178/2025) 01/DPAC/202503642\nDesignação do contrato: Aquisição de serviços de limpeza e higiene, com fornecimento de consumíveis de casa de banho para as Instalações do Turismo de Portugal, em todo o território Nacional.\nDescrição: Aquisição de serviços de limpeza e higiene, com fornecimento de consumíveis de casa de banho para as Instalações do Turismo de Portugal, em todo o território Nacional.\nOpções: Não\nTipo de Contrato Principal: Aquisição de Serviços\nTipo de Contrato: Aquisição de Serviços\nClassificação CPV (Vocabulário Comum para os Contratos Públicos)\nObjeto principal\nVocabulário Principal: 90910000\nPreço base s/IVA: 279.650,00 EUR\n\n7 - INDICAÇÕES ADICIONAIS\nO contrato envolve aquisição conjunta (satisfação de várias entidades)? Não\nO contrato é adjudicado por uma central de compras? Não\n\n8 - TÉCNICAS\nO concurso destina-se à celebração de um acordo-quadro? Inexistência de acordo-quadro\nÉ utilizado um leilão eletrónico? Não\nÉ adotada uma fase de negociação? Não\nSistema de Aquisição Dinâmico: Inexistência de sistema de aquisição dinâmico\n\n9 - LOCAL DA EXECUÇÃO DO CONTRATO\nLOCAL DA EXECUÇÃO DO CONTRATO (PROCEDIMENTO)\nPaís: Portugal\nNUT III: PT170\nLocalidade: Lisboa\nDistrito: Lisboa\nConcelho: Lisboa\nFreguesia: Freguesia de Avenidas Novas\n\n10 - PRAZO DE EXECUÇÃO DO CONTRATO\nPrazo de execução do contrato: 2 MESES\nPrevisão de renovações: Não\n\n11 - FUNDOS EU\nTêm fundos EU? Não\n\n12 - DOCUMENTOS DE HABILITAÇÃO\nHabilitação para o exercício da atividade profissional: Não\n\n13 - CONDIÇÕES DE APRESENTAÇÃO\nPlataforma eletrónica utilizada pela entidade adjudicante: VORTAL\nURL para Apresentação: https://community.vortal.biz/public/\nAdmissibilidade da apresentação de propostas variantes: Não autorizado\nPrazo para apresentação das propostas: 21-01-2026 23:59\nPrazo durante o qual os concorrentes são obrigados a manter as respetivas propostas: 66 dias a contar do termo do prazo para a apresentação das propostas\nApresentação de Catálogo Eletrónico: Não autorizado\nIndicação de Subcontratação na Proposta: Inexistência de indicação de subcontratação\n\n14 - PRESTAÇÃO DE CAUÇÃO\nPrestação de caução: Não\n\n15 - FORNECIMENTO DAS PEÇAS DO CONCURSO, APRESENTAÇÃO DE PEDIDOS DE PARTICIPAÇÃO E APRESENTAÇÃO DAS PROPOSTAS\nLink para acesso às peças do concurso (URL): https://community.vortal.biz/Public/public-tender-documents/KzI0NTh0U0J6SmZBZFNqdHQwV3JrNEFPRXNKbnZwa1UxV205dnI1QytMTEtFUllWSzJ6Wjl6WGFrT002VWxaOFk1YlB3TjllaW9HU3ZSaFBacDc2UUE9PTVfbGor\n\n20 - OUTROS REQUISITOS\nInformação sobre contratos reservados. Aplica-se a contratos reservados (54º-A)? Não\n\n21 - CRITÉRIO DE ADJUDICAÇÃO\nMultifator: Não\nMonofator:\nNome: Outros\nOutro nome: Preço\n\n24 - CONDIÇÕES DO CONTRATO\nFaturação Eletrónica: Permitido\nObrigação de Subcontratação:\nCódigo da Obrigação de Subcontratação: Não é aplicável nenhuma obrigação de subcontratação.\n\n25 - COMPRA PÚBLICA ESTRATÉGICA\nCompra Pública Estratégica: Inexistência de contratação pública estratégica\n\n26 - INFORMAÇÕES ADICIONAIS\nContrato adequado para PME: Sim\nCobertura ACP (Acordo dos Contratos Públicos da Organização Mundial do Comércio): Não\n\n27 - IDENTIFICAÇÃO E CONTACTOS DO ÓRGÃO DE RECURSOS ADMINISTRATIVOS\nDesignação: Conselho Diretivo do Turismo de Portugal, I.P.\nEndereço: Rua Ivone Silva, Lote 6\nCódigo postal: 1050-124\nLocalidade: Lisboa\nTelefone: +351 211140200\nFax: +351 211140600\nEndereço eletrónico: dcgg-concursos@turismodeportugal.pt\n\n28 - IDENTIFICAÇÃO DO(S) AUTOR(ES) DE ANÚNCIO\nNome: Graça Carvalho\nCargo: Técnica superior\n419921151",
    "nipc": "508666236",
    "distrito": "Lisboa",
    "concelho": "Lisboa",
    "freguesia": "Freguesia de Avenidas Novas",
    "site": "https://www.turismodeportugal.pt",
    "email": "info@turismodeportugal.pt",
    "designacao_contrato": "Aquisição de serviços de limpeza e higiene, com fornecimento de consumíveis de casa de banho para as Instalações do Turismo de Portugal, em todo o território Nacional.",
    "descricao": "Aquisição de serviços de limpeza e higiene, com fornecimento de consumíveis de casa de banho para as Instalações do Turismo de Portugal, em todo o território Nacional.",
    "preco_base": "279.650,00 EUR",
    "prazo_execucao": "2 MESES",
    "prazo_apresentacao_propostas": "21-01-2026 23:59",
    "fundos_eu": "Não",
    "plataforma_eletronica": "VORTAL",
    "url_procedimento": "https://community.vortal.biz/public/",
    "autor_nome": "Graça Carvalho",
    "autor_cargo": "Técnica superior"
  },
  {
    "numero_procedimento": "N/A",
    "entidade": "Unidade Local de Saúde de Santa Maria, EPE",
    "link": "https://diariodarepublica.pt/dr/detalhe/contrato-publico/33400-992662042",
    "detalhes_completos": "Alteração do Anúncio de procedimento n.º 33014/2025, de 2025-12-19, com o ID 419894252\n\n1 - IDENTIFICAÇÃO E CONTACTOS DA ENTIDADE ADJUDICANTE\nDesignação da entidade adjudicante: Unidade Local de Saúde de Santa Maria, EPE\nNIPC: 508481287\nEndereço: Avenida Prof. Egas Moniz\nCódigo postal: 1649-035\nLocalidade: Lisboa\nPaís: Portugal\nNUT III: PT170\nDistrito: Lisboa\nConcelho: Lisboa\nFreguesia: Freguesia de Alvalade - Lisboa\nTelefone: 217805330\nFax: 217805605\nEndereço da Entidade (URL): www.ulssm.min-saude.pt\nEndereço Eletrónico: compras@ulssm.min-saude.pt\neDelivery Gateway (URL): https://community.vortal.biz/public/\nFunção da Organização: Adquirente\nNorma jurídica da Entidade Adjudicante: Empresa pública\nÁrea de atividade da Autoridade Adjudicante: Saúde\n\n2 - JORNAL OFICIAL DA UNIÃO EUROPEIA\nO procedimento a que este anúncio diz respeito também é publicitado no Jornal Oficial da União Europeia? Sim\n\n3 - AVISO\nModelo de Anúncio: Concurso público\nData de Envio do Anúncio: 22-12-2025\n\n5 - PROCESSO\nTipo de Procedimento: Concurso público\nPreço base do procedimento: Sim\nValor do preço base do procedimento: 413.878,81 EUR\nProcedimento com lotes? Sim\nNº Máx. de Lotes Autorizado: 16\nNúmero máximo de lotes que podem ser adjudicados a um concorrente: 16\n\n6 - OBJETO DO CONTRATO\nNúmero de referência interna: 262A000013\nDesignação do contrato: 262A000013 - Aquisição de artigos de proteção, ano 2026 a 2027\nDescrição: 262A000013 - Aquisição de artigos de proteção, ano 2026 a 2027\nOpções: Não\nTipo de Contrato Principal: Aquisição de Bens Móveis\nTipo de Contrato: Aquisição de Bens Móveis\nClassificação CPV (Vocabulário Comum para os Contratos Públicos)\nObjeto principal\nVocabulário Principal: 33140000\nPreço base s/IVA: 413.878,81 EUR\nLotes: \nNº: LOT-0001\nDescrição do Lote: Lote 1\nPreço base s/IVA: 26.048,71 EUR\nClassificação CPV (Vocabulário Comum para os Contratos Públicos)\nObjeto principal\nVocabulário Principal: 33140000\nNº: LOT-0002\nDescrição do Lote: Lote 2\nPreço base s/IVA: 123.816,00 EUR\nClassificação CPV (Vocabulário Comum para os Contratos Públicos)\nObjeto principal\nVocabulário Principal: 33140000\nNº: LOT-0003\nDescrição do Lote: Lote 3\nPreço base s/IVA: 78.869,76 EUR\nClassificação CPV (Vocabulário Comum para os Contratos Públicos)\nObjeto principal\nVocabulário Principal: 33140000\nNº: LOT-0004\nDescrição do Lote: Lote 4\nPreço base s/IVA: 100.893,60 EUR\nClassificação CPV (Vocabulário Comum para os Contratos Públicos)\nObjeto principal\nVocabulário Principal: 33140000\nNº: LOT-0005\nDescrição do Lote: Lote 5\nPreço base s/IVA: 19.852,80 EUR\nClassificação CPV (Vocabulário Comum para os Contratos Públicos)\nObjeto principal\nVocabulário Principal: 33140000\nNº: LOT-0006\nDescrição do Lote: Lote 6\nPreço base s/IVA: 648,00 EUR\nClassificação CPV (Vocabulário Comum para os Contratos Públicos)\nObjeto principal\nVocabulário Principal: 33140000\nNº: LOT-0007\nDescrição do Lote: Lote 7\nPreço base s/IVA: 1.419,04 EUR\nClassificação CPV (Vocabulário Comum para os Contratos Públicos)\nObjeto principal\nVocabulário Principal: 33140000\nNº: LOT-0008\nDescrição do Lote: Lote 8\nPreço base s/IVA: 22.724,00 EUR\nClassificação CPV (Vocabulário Comum para os Contratos Públicos)\nObjeto principal\nVocabulário Principal: 33140000\nNº: LOT-0009\nDescrição do Lote: Lote 9\nPreço base s/IVA: 9.632,00 EUR\nClassificação CPV (Vocabulário Comum para os Contratos Públicos)\nObjeto principal\nVocabulário Principal: 33140000\nNº: LOT-0010\nDescrição do Lote: Lote 10\nPreço base s/IVA: 3.072,00 EUR\nClassificação CPV (Vocabulário Comum para os Contratos Públicos)\nObjeto principal\nVocabulário Principal: 33140000\nNº: LOT-0011\nDescrição do Lote: Lote 11\nPreço base s/IVA: 399,00 EUR\nClassificação CPV (Vocabulário Comum para os Contratos Públicos)\nObjeto principal\nVocabulário Principal: 33140000\nNº: LOT-0012\nDescrição do Lote: Lote 12\nPreço base s/IVA: 16.495,50 EUR\nClassificação CPV (Vocabulário Comum para os Contratos Públicos)\nObjeto principal\nVocabulário Principal: 33140000\nNº: LOT-0013\nDescrição do Lote: Lote 13\nPreço base s/IVA: 896,00 EUR\nClassificação CPV (Vocabulário Comum para os Contratos Públicos)\nObjeto principal\nVocabulário Principal: 33140000\nNº: LOT-0014\nDescrição do Lote: Lote 14\nPreço base s/IVA: 740,00 EUR\nClassificação CPV (Vocabulário Comum para os Contratos Públicos)\nObjeto principal\nVocabulário Principal: 33140000\nNº: LOT-0015\nDescrição do Lote: Lote 15\nPreço base s/IVA: 6.900,00 EUR\nClassificação CPV (Vocabulário Comum para os Contratos Públicos)\nObjeto principal\nVocabulário Principal: 33140000\nNº: LOT-0016\nDescrição do Lote: Lote 16\nPreço base s/IVA: 1.472,40 EUR\nClassificação CPV (Vocabulário Comum para os Contratos Públicos)\nObjeto principal\nVocabulário Principal: 33140000\n\n7 - INDICAÇÕES ADICIONAIS\nO contrato envolve aquisição conjunta (satisfação de várias entidades)? Não\nO contrato é adjudicado por uma central de compras? Não\n\n8 - TÉCNICAS\nO concurso destina-se à celebração de um acordo-quadro? Inexistência de acordo-quadro\nÉ utilizado um leilão eletrónico? Não\nÉ adotada uma fase de negociação? Não\nSistema de Aquisição Dinâmico: Inexistência de sistema de aquisição dinâmico\n\n9 - LOCAL DA EXECUÇÃO DO CONTRATO\nLOCAL DA EXECUÇÃO DO CONTRATO (PROCEDIMENTO)\nPaís: Portugal\nNUT III: PT170\nLocalidade: Lisboa\nDistrito: Lisboa\nConcelho: Lisboa\nFreguesia: Freguesia de Alvalade - Lisboa\nLOCAL DA EXECUÇÃO DO CONTRATO (LOTE)\nIdentificador do Lote: LOT-0001; LOT-0002; LOT-0003; LOT-0004; LOT-0005; LOT-0006; LOT-0007; LOT-0008; LOT-0009; LOT-0010; LOT-0011; LOT-0012; LOT-0013; LOT-0014; LOT-0015; LOT-0016\nPaís: Portugal\nNUT III: PT170\nLocalidade: Lisboa\nDistrito: Lisboa\nConcelho: Lisboa\nFreguesia: Freguesia de Alvalade - Lisboa\n\n10 - PRAZO DE EXECUÇÃO DO CONTRATO\nIdentificador do Lote: LOT-0001; LOT-0002; LOT-0003; LOT-0004; LOT-0005; LOT-0006; LOT-0007; LOT-0008; LOT-0009; LOT-0010; LOT-0011; LOT-0012; LOT-0013; LOT-0014; LOT-0015; LOT-0016\nPrazo de execução do contrato: 24 MESES\nPrevisão de renovações: Não\n\n11 - FUNDOS EU\nIdentificador do Lote: LOT-0001; LOT-0002; LOT-0003; LOT-0004; LOT-0005; LOT-0006; LOT-0007; LOT-0008; LOT-0009; LOT-0010; LOT-0011; LOT-0012; LOT-0013; LOT-0014; LOT-0015; LOT-0016\nTêm fundos EU? Não\n\n12 - DOCUMENTOS DE HABILITAÇÃO\nHabilitação para o exercício da atividade profissional: Não\n\n13 - CONDIÇÕES DE APRESENTAÇÃO\nPlataforma eletrónica utilizada pela entidade adjudicante: VORTAL\nURL para Apresentação: https://community.vortal.biz/public/\nAdmissibilidade da apresentação de propostas variantes: Não autorizado\nPrazo para apresentação das propostas: 23-01-2026 17:00\nPrazo durante o qual os concorrentes são obrigados a manter as respetivas propostas: 180 dias a contar do termo do prazo para a apresentação das propostas\nApresentação de Catálogo Eletrónico: Permitido\nIndicação de Subcontratação na Proposta: Inexistência de indicação de subcontratação\n\n14 - PRESTAÇÃO DE CAUÇÃO\nPrestação de caução: Não\n\n15 - FORNECIMENTO DAS PEÇAS DO CONCURSO, APRESENTAÇÃO DE PEDIDOS DE PARTICIPAÇÃO E APRESENTAÇÃO DAS PROPOSTAS\nLink para acesso às peças do concurso (URL): https://community.vortal.biz/Public/public-tender-documents/V2NaQmJIYk5wZ0VjRXpuRzJoTUgyeUIreUNkK1B2MFE2dGVCeXNjdHJTSXRwajdySnpMUlJPU205MnQxb2NaV3UrS1FBSGdrNHIwK0x3V01kUGQ3Y2c9PXNKeSg3\n\n20 - OUTROS REQUISITOS\nIdentificador do Lote: LOT-0001; LOT-0002; LOT-0003; LOT-0004; LOT-0005; LOT-0006; LOT-0007; LOT-0008; LOT-0009; LOT-0010; LOT-0011; LOT-0012; LOT-0013; LOT-0014; LOT-0015; LOT-0016\nInformação sobre contratos reservados. Aplica-se a contratos reservados (54º-A)? Não\n\n21 - CRITÉRIO DE ADJUDICAÇÃO\nO Critério de adjudicação é diferenciado por lote? Não\nMultifator: Não\nMonofator:\nNome: Preço\n\n24 - CONDIÇÕES DO CONTRATO\nIdentificador do Lote: LOT-0001; LOT-0002; LOT-0003; LOT-0004; LOT-0005; LOT-0006; LOT-0007; LOT-0008; LOT-0009; LOT-0010; LOT-0011; LOT-0012; LOT-0013; LOT-0014; LOT-0015; LOT-0016\nFaturação Eletrónica: Permitido\nObrigação de Subcontratação:\nCódigo da Obrigação de Subcontratação: Não é aplicável nenhuma obrigação de subcontratação.\n\n25 - COMPRA PÚBLICA ESTRATÉGICA\nCompra Pública Estratégica: Inexistência de contratação pública estratégica\n\n26 - INFORMAÇÕES ADICIONAIS\nIdentificador do Lote: LOT-0001; LOT-0002; LOT-0003; LOT-0004; LOT-0005; LOT-0006; LOT-0007; LOT-0008; LOT-0009; LOT-0010; LOT-0011; LOT-0012; LOT-0013; LOT-0014; LOT-0015; LOT-0016\nContrato adequado para PME: Sim\nCobertura ACP (Acordo dos Contratos Públicos da Organização Mundial do Comércio): Não\n\n27 - IDENTIFICAÇÃO E CONTACTOS DO ÓRGÃO DE RECURSOS ADMINISTRATIVOS\nDesignação: Conselho de  Administração\nEndereço: Av Professor Egas Moniz\nCódigo postal: 1649-035\nLocalidade: Lisboa\nTelefone: +351 217805330\nFax: +351 217805605\nEndereço eletrónico: secretariado.ca@ulssm.min-saude.pt\n\n28 - IDENTIFICAÇÃO DO(S) AUTOR(ES) DE ANÚNCIO\nNome: Mariana Figueira\nCargo: Assistente Técnica\n\n29 - ALTERAÇÃO\nMotivo da Alteração: Correção pelo adquirente\nIdentificador da Versão do Anúncio a Alterar: 7ac38821-438e-46fe-9ceb-0bcacd0476b4-01\nIdentificador das Secções Alteradas do Anúncio Anterior: Condições de Apresentação\nDescrição das Alterações: Substituição das peças procedimentais, dado que as peças iniciais estavam incorretas.\nAlteração dos Documentos do Concurso: Sim\nData de alteração dos documentos do concurso: 22-12-2025\n419920682",
    "nipc": "508481287",
    "distrito": "Lisboa",
    "concelho": "Lisboa",
    "freguesia": "Freguesia de Alvalade - Lisboa",
    "site": "www.ulssm.min-saude.pt",
    "email": "compras@ulssm.min-saude.pt",
    "designacao_contrato": "262A000013 - Aquisição de artigos de proteção, ano 2026 a 2027",
    "descricao": "262A000013 - Aquisição de artigos de proteção, ano 2026 a 2027",
    "preco_base": "413.878,81 EUR",
    "prazo_execucao": "24 MESES",
    "prazo_apresentacao_propostas": "23-01-2026 17:00",
    "fundos_eu": "Não",
    "plataforma_eletronica": "VORTAL",
    "url_procedimento": "https://community.vortal.biz/public/",
    "autor_nome": "Mariana Figueira",
    "autor_cargo": "Assistente Técnica"
  },
  {
    "numero_procedimento": "N/A",
    "entidade": "Serviços Partilhados do Ministério da Saúde, EPE",
    "link": "https://diariodarepublica.pt/dr/detalhe/contrato-publico/33401-992662043",
    "detalhes_completos": "1 - IDENTIFICAÇÃO E CONTACTOS DA ENTIDADE ADJUDICANTE\nDesignação da entidade adjudicante: Serviços Partilhados do Ministério da Saúde, EPE\nNIPC: 509540716\nEndereço: Avenida da República 61\nCódigo postal: 1050-189\nLocalidade: Lisboa\nPaís: Portugal\nNUT III: PT170\nDistrito: Lisboa\nConcelho: Lisboa\nFreguesia: Todas\nTelefone: 211545600\nFax: 211545649\nEndereço da Entidade (URL): www.spms.min-saude.pt/\nEndereço Eletrónico: contratacao@spms.min-saude.pt\neDelivery Gateway (URL): https://community.vortal.biz/public/\nFunção da Organização: Adquirente\nNorma jurídica da Entidade Adjudicante: Empresa pública\nÁrea de atividade da Autoridade Adjudicante: Saúde\n\n2 - JORNAL OFICIAL DA UNIÃO EUROPEIA\nO procedimento a que este anúncio diz respeito também é publicitado no Jornal Oficial da União Europeia? Sim\n\n3 - AVISO\nModelo de Anúncio: Concurso público\nData de Envio do Anúncio: 22-12-2025\n\n5 - PROCESSO\nTipo de Procedimento: Concurso público\nPreço base do procedimento: Sim\nValor do preço base do procedimento: 422.104,32 EUR\nProcedimento com lotes? Não\n\n6 - OBJETO DO CONTRATO\nNúmero de referência interna: 20260022\nDesignação do contrato: (DAG) Aquisição de Serviços de Consultores Séniores no âmbito da Continuidade de Negócio (20260022)\nDescrição: (DAG) Aquisição de Serviços de Consultores Séniores no âmbito da Continuidade de Negócio (20260022)\nOpções: Não\nTipo de Contrato Principal: Aquisição de Serviços\nTipo de Contrato: Aquisição de Serviços\nClassificação CPV (Vocabulário Comum para os Contratos Públicos)\nObjeto principal\nVocabulário Principal: 72221000\nPreço base s/IVA: 422.104,32 EUR\n\n7 - INDICAÇÕES ADICIONAIS\nO contrato envolve aquisição conjunta (satisfação de várias entidades)? Não\nO contrato é adjudicado por uma central de compras? Não\n\n8 - TÉCNICAS\nO concurso destina-se à celebração de um acordo-quadro? Inexistência de acordo-quadro\nÉ utilizado um leilão eletrónico? Não\nÉ adotada uma fase de negociação? Não\nSistema de Aquisição Dinâmico: Inexistência de sistema de aquisição dinâmico\n\n9 - LOCAL DA EXECUÇÃO DO CONTRATO\nLOCAL DA EXECUÇÃO DO CONTRATO (PROCEDIMENTO)\nPaís: Portugal\nNUT III: PT170\nLocalidade: Lisboa\nDistrito: Lisboa\nConcelho: Lisboa\nFreguesia: Freguesia de Avenidas Novas\n\n10 - PRAZO DE EXECUÇÃO DO CONTRATO\nPrazo de execução do contrato: 36 MESES\nPrevisão de renovações: Não\n\n11 - FUNDOS EU\nTêm fundos EU? Não\n\n12 - DOCUMENTOS DE HABILITAÇÃO\nHabilitação para o exercício da atividade profissional: Não\n\n13 - CONDIÇÕES DE APRESENTAÇÃO\nPlataforma eletrónica utilizada pela entidade adjudicante: VORTAL\nURL para Apresentação: https://community.vortal.biz/public/\nAdmissibilidade da apresentação de propostas variantes: Não autorizado\nPrazo para apresentação das propostas: 20-01-2026 18:00\nPrazo durante o qual os concorrentes são obrigados a manter as respetivas propostas: 180 dias a contar do termo do prazo para a apresentação das propostas\nApresentação de Catálogo Eletrónico: Permitido\nIndicação de Subcontratação na Proposta: Inexistência de indicação de subcontratação\n\n14 - PRESTAÇÃO DE CAUÇÃO\nPrestação de caução: Sim\nPercentagem: 4%\nDescrição da Garantia Exigida: Ver artigo 29.º do Programa de Concurso\n\n15 - FORNECIMENTO DAS PEÇAS DO CONCURSO, APRESENTAÇÃO DE PEDIDOS DE PARTICIPAÇÃO E APRESENTAÇÃO DAS PROPOSTAS\nLink para acesso às peças do concurso (URL): https://community.vortal.biz/Public/public-tender-documents/TTQ4eUtRVFpHL2EzL3dmUUV2ZHlJeENQNVB1aWFJM2tmRWduYnRiWHNSYUV6RDRCNCtwOWVJbFhDa1QxWFdTOWZHYncvZGJUaUlhbm5kaGVyN1NDTlE9PTVyM2ZK\n\n20 - OUTROS REQUISITOS\nInformação sobre contratos reservados. Aplica-se a contratos reservados (54º-A)? Não\n\n21 - CRITÉRIO DE ADJUDICAÇÃO\nMultifator: Não\nMonofator:\nNome: Preço\n\n24 - CONDIÇÕES DO CONTRATO\nFaturação Eletrónica: Permitido\nObrigação de Subcontratação:\nCódigo da Obrigação de Subcontratação: Não é aplicável nenhuma obrigação de subcontratação.\n\n25 - COMPRA PÚBLICA ESTRATÉGICA\nCompra Pública Estratégica: Inexistência de contratação pública estratégica\n\n26 - INFORMAÇÕES ADICIONAIS\nContrato adequado para PME: Sim\nCobertura ACP (Acordo dos Contratos Públicos da Organização Mundial do Comércio): Não\n\n27 - IDENTIFICAÇÃO E CONTACTOS DO ÓRGÃO DE RECURSOS ADMINISTRATIVOS\nDesignação: Serviços Partilhados do Ministério da Sáúde, EPE\nEndereço: Avenida da República n.º 61\nCódigo postal: 1050-189\nLocalidade: Lisboa\nTelefone: +351 211545600\nFax: +351 211545649\nEndereço eletrónico: contratacao@spms.min-saude.pt\n\n28 - IDENTIFICAÇÃO DO(S) AUTOR(ES) DE ANÚNCIO\nNome: Laura Raposo\nCargo: Diretora da Direção de Administração Geral\n419921427",
    "nipc": "509540716",
    "distrito": "Lisboa",
    "concelho": "Lisboa",
    "freguesia": "Todas",
    "site": "www.spms.min-saude.pt/",
    "email": "contratacao@spms.min-saude.pt",
    "designacao_contrato": "(DAG) Aquisição de Serviços de Consultores Séniores no âmbito da Continuidade de Negócio (20260022)",
    "descricao": "(DAG) Aquisição de Serviços de Consultores Séniores no âmbito da Continuidade de Negócio (20260022)",
    "preco_base": "422.104,32 EUR",
    "prazo_execucao": "36 MESES",
    "prazo_apresentacao_propostas": "20-01-2026 18:00",
    "fundos_eu": "Não",
    "plataforma_eletronica": "VORTAL",
    "url_procedimento": "https://community.vortal.biz/public/",
    "autor_nome": "Laura Raposo",
    "autor_cargo": "Diretora da Direção de Administração Geral"
  },
  {
    "numero_procedimento": "N/A",
    "entidade": "AnÃºncio de procedimento  n.Âº 33402/2025  -  DiÃ¡rio da RepÃºblica n.Âº 247/2025, SÃ©rie II de 2025-12-24",
    "link": "https://diariodarepublica.pt/dr/detalhe/contrato-publico/33402-992662044"
  },
  {
    "numero_procedimento": "N/A",
    "entidade": "AdP - Águas de Portugal, SGPS, SA",
    "link": "https://diariodarepublica.pt/dr/detalhe/contrato-publico/33403-992662045",
    "detalhes_completos": "1 - IDENTIFICAÇÃO E CONTACTOS DA ENTIDADE ADJUDICANTE\nDesignação da entidade adjudicante: AdP - Águas de Portugal, SGPS, SA\nNIPC: 503093742\nServiço/Órgão/Pessoa de contacto: David Barranqueiro\nEndereço: Rua Visconde de Seabra, n.º 3 - 4 piso\nCódigo postal: 1700-421\nLocalidade: Lisboa\nPaís: Portugal\nNUT III: PT170\nDistrito: Lisboa\nConcelho: Lisboa\nFreguesia: Freguesia de Alvalade - Lisboa\nTelefone: +351 212 469 400\nFax: +351 212 469 401\nEndereço da Entidade (URL): www.adp.pt\nEndereço Eletrónico: compras@adp.pt\neDelivery Gateway (URL): https://www.acingov.pt\nFunção da Organização: Adquirente\nSubfunção da Organização: Organização cujo orçamento é utilizado para pagar o contrato; Organização que executa o pagamento; Líder do grupo; Organização que fornece informações adicionais sobre o processo de adjudicação; Organização que fornece mais informações sobre os prazos dos procedimentos de recurso; Organização que fornece acesso fora de linha aos documentos do concurso; Organização responsável pelo tratamento das propostas; Organização que recebe as propostas; Organização que trata os pedidos de participação; Organização que recebe pedidos de participação; Organização que fornece mais informações sobre os procedimentos de recurso; Organização que assina o contrato\nNorma jurídica da Entidade Adjudicante: Organismo de direito público\nÁrea de atividade da Autoridade Adjudicante: Proteção ambiental\n\n2 - JORNAL OFICIAL DA UNIÃO EUROPEIA\nO procedimento a que este anúncio diz respeito também é publicitado no Jornal Oficial da União Europeia? Sim\n\n3 - AVISO\nModelo de Anúncio: Concurso limitado por prévia qualificação\nData de Envio do Anúncio: 22-12-2025\n\n5 - PROCESSO\nTipo de Procedimento: Concurso limitado por prévia qualificação\nPreço base do procedimento: Sim\nValor do preço base do procedimento: 698.000,00 EUR\nProcedimento com lotes? Não\n\n6 - OBJETO DO CONTRATO\nNúmero de referência interna: 2025_043CLPQ\nDesignação do contrato: 2025_043CLPQ - Aquisição de serviços de implementação da evolução dos sistemas SAP no Grupo Águas de Portugal\nDescrição: 2025_043CLPQ - Aquisição de serviços de implementação da evolução dos sistemas SAP no Grupo Águas de Portugal \nOpções: Não\nTipo de Contrato Principal: Aquisição de Serviços\nTipo de Contrato: Aquisição de Serviços\nClassificação CPV (Vocabulário Comum para os Contratos Públicos)\nObjeto principal\nVocabulário Principal: 72220000\nPreço base s/IVA: 698.000,00 EUR\n\n7 - INDICAÇÕES ADICIONAIS\nO contrato envolve aquisição conjunta (satisfação de várias entidades)? Não\nO contrato é adjudicado por uma central de compras? Não\n\n8 - TÉCNICAS\nO concurso destina-se à celebração de um acordo-quadro? Inexistência de acordo-quadro\nÉ utilizado um leilão eletrónico? Não\nSistema de Aquisição Dinâmico: Inexistência de sistema de aquisição dinâmico\n\n9 - LOCAL DA EXECUÇÃO DO CONTRATO\nLOCAL DA EXECUÇÃO DO CONTRATO (PROCEDIMENTO)\nPaís: Portugal\nNUT III: PT170\nLocalidade: Freguesia de Alvalade - Lisboa\nDistrito: Lisboa\nConcelho: Lisboa\nFreguesia: Freguesia de Alvalade - Lisboa\n\n10 - PRAZO DE EXECUÇÃO DO CONTRATO\nPrazo de execução do contrato: 18 MESES\nPrevisão de renovações: Não\n\n11 - FUNDOS EU\nTêm fundos EU? Não\n\n12 - DOCUMENTOS DE HABILITAÇÃO\nHabilitação para o exercício da atividade profissional: Não\n\n13 - CONDIÇÕES DE APRESENTAÇÃO\nPlataforma eletrónica utilizada pela entidade adjudicante: ACIN\nURL para Apresentação: https://www.acingov.pt\nAdmissibilidade da apresentação de propostas variantes: Não autorizado\nPrazo para apresentação das candidaturas: 21-01-2026 18:00\nPrazo para a decisão de qualificação: 70 dias a contar do termo do prazo para a apresentação das candidaturas\nRequisitos mínimos \nRequisitos mínimos de capacidade técnica: Ter concluído, no mínimo, 2 (dois) projetos de migração SAP ECC para SAP S4HANA Cloud ERP Private, recorrendo a uma estratégia Bluefield com migração seletiva de dados, em organizações com o mínimo de 2.000 (dois mil) trabalhadores/as.\nRequisitos mínimos de capacidade financeira: Média aritmética do volume de negócios, nos últimos 3 (três) exercícios cujas Declarações Anuais de Informação Contabilística e Fiscal já tenham sido entregues e validadas para efeitos fiscais, igual ou superior a 1.396.000,00 (um milhão trezentos e noventa e seis mil euros).\nPrazo durante o qual os concorrentes são obrigados a manter as respetivas propostas: 90 dias a contar do termo do prazo para a apresentação das propostas\nApresentação de Catálogo Eletrónico: Não autorizado\nIndicação de Subcontratação na Proposta: Inexistência de indicação de subcontratação\n\n14 - PRESTAÇÃO DE CAUÇÃO\nPrestação de caução: Sim\nPercentagem: 2%\nDescrição da Garantia Exigida: O valor da caução é de 2.00% do preço contratual.\n\n15 - FORNECIMENTO DAS PEÇAS DO CONCURSO, APRESENTAÇÃO DE PEDIDOS DE PARTICIPAÇÃO E APRESENTAÇÃO DAS PROPOSTAS\nLink para acesso às peças do concurso (URL): https://www.acingov.pt/acingovprod/2/zonaPublica/zona_publica_c/donwloadProcedurePiece/MTAwODgwOQ==\n\n20 - OUTROS REQUISITOS\nInformação sobre contratos reservados. Aplica-se a contratos reservados (54º-A)? Não\n\n21 - CRITÉRIO DE ADJUDICAÇÃO\nMultifator: Não\nMonofator:\nNome: Preço\n\n24 - CONDIÇÕES DO CONTRATO\nFaturação Eletrónica: Necessário\nObrigação de Subcontratação:\nCódigo da Obrigação de Subcontratação: Não é aplicável nenhuma obrigação de subcontratação.\n\n25 - COMPRA PÚBLICA ESTRATÉGICA\nCompra Pública Estratégica: Inexistência de contratação pública estratégica\n\n26 - INFORMAÇÕES ADICIONAIS\nContrato adequado para PME: Sim\nCobertura ACP (Acordo dos Contratos Públicos da Organização Mundial do Comércio): Não\n\n27 - IDENTIFICAÇÃO E CONTACTOS DO ÓRGÃO DE RECURSOS ADMINISTRATIVOS\nDesignação: Comissão Executiva da AdP - Águas de Portugal, SGPS, S.A\nEndereço: Rua Visconde de Seabra, 3, 4.º piso\nCódigo postal: 1700-421\nLocalidade: Lisboa\nTelefone: 351212469400\nFax: 351212469401\nEndereço eletrónico: compras@adp.pt\nPrazo de interposição do recurso: 5 dias\n\n28 - IDENTIFICAÇÃO DO(S) AUTOR(ES) DE ANÚNCIO\nNome: David Barranqueiro\nCargo: Diretor de Compras\n419922934",
    "nipc": "503093742",
    "distrito": "Lisboa",
    "concelho": "Lisboa",
    "freguesia": "Freguesia de Alvalade - Lisboa",
    "site": "www.adp.pt",
    "email": "compras@adp.pt",
    "designacao_contrato": "2025_043CLPQ - Aquisição de serviços de implementação da evolução dos sistemas SAP no Grupo Águas de Portugal",
    "descricao": "2025_043CLPQ - Aquisição de serviços de implementação da evolução dos sistemas SAP no Grupo Águas de Portugal",
    "preco_base": "698.000,00 EUR",
    "prazo_execucao": "18 MESES",
    "prazo_apresentacao_propostas": null,
    "fundos_eu": "Não",
    "plataforma_eletronica": "ACIN",
    "url_procedimento": "https://www.acingov.pt",
    "autor_nome": "David Barranqueiro",
    "autor_cargo": "Diretor de Compras"
  },
  {
    "numero_procedimento": "N/A",
    "entidade": "Entidade de Serviços Partilhados da Administração Pública, IP",
    "link": "https://diariodarepublica.pt/dr/detalhe/contrato-publico/33375-992674276",
    "detalhes_completos": "1 - IDENTIFICAÇÃO E CONTACTOS DA ENTIDADE ADJUDICANTE\nDesignação da entidade adjudicante: Entidade de Serviços Partilhados da Administração Pública, IP\nNIPC: 510342191\nEndereço: Av. Leite de Vasconcelos, 2, Alfragide\nCódigo postal: 2614-502\nLocalidade: Amadora\nPaís: Portugal\nNUT III: PT170\nDistrito: Lisboa\nConcelho: Amadora\nFreguesia: Freguesia de Alfragide\nTelefone: 214723390\nFax: 214723390\nEndereço da Entidade (URL): www.espap.gov.pt\nEndereço Eletrónico: contacto@espap.gov.pt\nFunção da Organização: Adquirente\nNorma jurídica da Entidade Adjudicante: Autoridade da administração central\nÁrea de atividade da Autoridade Adjudicante: Assuntos económicos\n\n2 - JORNAL OFICIAL DA UNIÃO EUROPEIA\nO procedimento a que este anúncio diz respeito também é publicitado no Jornal Oficial da União Europeia? Sim\n\n3 - AVISO\nModelo de Anúncio: Concurso público\nData de Envio do Anúncio: 22-12-2025\n\n5 - PROCESSO\nTipo de Procedimento: Concurso público\nPreço base do procedimento: Não\nProcedimento com lotes? Não\n\n6 - OBJETO DO CONTRATO\nNúmero de referência interna: AQ-Papel-2025\nDesignação do contrato: Acordo Quadro para o fornecimento de Papel para Fotocópia e Impressão\nDescrição: Acordo Quadro para o fornecimento de Papel para Fotocópia e Impressão\nOpções: Não\nTipo de Contrato Principal: Aquisição de Bens Móveis\nTipo de Contrato: Aquisição de Bens Móveis\nClassificação CPV (Vocabulário Comum para os Contratos Públicos)\nObjeto Complementar\nVocabulário Principal: 30197643\nObjeto principal\nVocabulário Principal: 30197630\n\n7 - INDICAÇÕES ADICIONAIS\nO contrato envolve aquisição conjunta (satisfação de várias entidades)? Não\nO contrato é adjudicado por uma central de compras? Sim\n\n8 - TÉCNICAS\nO concurso destina-se à celebração de um acordo-quadro? Acordo-quadro, com reabertura de concurso\nModalidade: Com várias entidades\nPrazo de vigência: 1 anos\nValor estimado: Sim\nPara Acordo-Quadro — valor total máximo estimado para toda a duração do Acordo-Quadro: 32.000.000,00 EUR\nÉ utilizado um leilão eletrónico? Não\nÉ adotada uma fase de negociação? Não\nSistema de Aquisição Dinâmico: Inexistência de sistema de aquisição dinâmico\n\n9 - LOCAL DA EXECUÇÃO DO CONTRATO\nLOCAL DA EXECUÇÃO DO CONTRATO (PROCEDIMENTO)\nPaís: Portugal\nNUT III: PTZZZ\nLocalidade: Todas\nDistrito: Todos\nConcelho: Todos\nFreguesia: Todas\n\n10 - PRAZO DE EXECUÇÃO DO CONTRATO\nPrazo de execução do contrato: 1 ANOS\nPrevisão de renovações: Sim\nIndicar número máximo de renovações: 3\nPrazo de renovações diferente do prazo inicial: Não\n\n11 - FUNDOS EU\nTêm fundos EU? Não\n\n12 - DOCUMENTOS DE HABILITAÇÃO\nHabilitação para o exercício da atividade profissional: Não\n\n13 - CONDIÇÕES DE APRESENTAÇÃO\nPlataforma eletrónica utilizada pela entidade adjudicante: ANOGOV\nURL para Apresentação: https://plataforma-sncp.espap.gov.pt/espap/faces/\nAdmissibilidade da apresentação de propostas variantes: Não autorizado\nPrazo para apresentação das propostas: 26-01-2026 23:59\nPrazo durante o qual os concorrentes são obrigados a manter as respetivas propostas: 120 dias a contar do termo do prazo para a apresentação das propostas\nApresentação de Catálogo Eletrónico: Permitido\nIndicação de Subcontratação na Proposta: A parte do contrato que o proponente tenciona subcontratar\n\n14 - PRESTAÇÃO DE CAUÇÃO\nPrestação de caução: Não\n\n15 - FORNECIMENTO DAS PEÇAS DO CONCURSO, APRESENTAÇÃO DE PEDIDOS DE PARTICIPAÇÃO E APRESENTAÇÃO DAS PROPOSTAS\nLink para acesso às peças do concurso (URL): https://plataforma-sncp.espap.gov.pt/espap/faces/app/acessoDocs.jsp?codigoAcesso=kOerqDIDvVFjs14UiEYvHWcTw8ZyLnrPP0SBW2dykutuL9AEsq\n\n20 - OUTROS REQUISITOS\nInformação sobre contratos reservados. Aplica-se a contratos reservados (54º-A)? Não\n\n21 - CRITÉRIO DE ADJUDICAÇÃO\nMultifator: Sim\nFator: \nNome: Preço\nPonderação: 95%\nSubfatores: Não\nFator: \nNome: Sustentabilidade ambiental ou social\nPonderação: 5%\nSubfatores: Não\n\n24 - CONDIÇÕES DO CONTRATO\nFaturação Eletrónica: Permitido\nObrigação de Subcontratação:\nCódigo da Obrigação de Subcontratação: Não é aplicável nenhuma obrigação de subcontratação.\n\n25 - COMPRA PÚBLICA ESTRATÉGICA\nCompra Pública Estratégica: Redução dos impactos ambientais\nDescrição do Processo de Adjudicação Estratégico: Critério ecológico para propostas com embalagens secundárias recicladas\nCritérios de contratos Públicos Ecológicos: Critérios de contratação pública ecológica da UE\nCategorias da estratégia nacional: Papel de cópia e impressão\nContratos Públicos Ecológicos: A transição para uma economia circular\nDiretiva Veículos Não Poluentes: Não\nCritério de Acessibilidade: Os critérios de acessibilidade para as pessoas com deficiência não estão incluídos porque o contrato não se destina a pessoas singulares\n\n26 - INFORMAÇÕES ADICIONAIS\nContrato adequado para PME: Sim\nCobertura ACP (Acordo dos Contratos Públicos da Organização Mundial do Comércio): Não\n\n27 - IDENTIFICAÇÃO E CONTACTOS DO ÓRGÃO DE RECURSOS ADMINISTRATIVOS\nDesignação: Entidade de Serviços Partilhados da Administração Pública, I.P. - Conselho Diretivo\nEndereço: Av. Leite de Vasconcelos, 2\nCódigo postal: 2614-261\nLocalidade: Alfragide - Amadora\nEndereço eletrónico: contacto@espap.gov.pt\n\n28 - IDENTIFICAÇÃO DO(S) AUTOR(ES) DE ANÚNCIO\nNome: Carla Caeiro\nCargo: Gestora de Categoria - Direção dos Serviços Partilhados de Compras Públicas (NPG SNCP)\n419900148",
    "nipc": "510342191",
    "distrito": "Lisboa",
    "concelho": "Amadora",
    "freguesia": "Freguesia de Alfragide",
    "site": "www.espap.gov.pt",
    "email": "contacto@espap.gov.pt",
    "designacao_contrato": "Acordo Quadro para o fornecimento de Papel para Fotocópia e Impressão",
    "descricao": "Acordo Quadro para o fornecimento de Papel para Fotocópia e Impressão",
    "preco_base": null,
    "prazo_execucao": "1 ANOS",
    "prazo_apresentacao_propostas": "26-01-2026 23:59",
    "fundos_eu": "Não",
    "plataforma_eletronica": "ANOGOV",
    "url_procedimento": "https://plataforma-sncp.espap.gov.pt/espap/faces/",
    "autor_nome": "Carla Caeiro",
    "autor_cargo": "Gestora de Categoria - Direção dos Serviços Partilhados de Compras Públicas (NPG SNCP)"
  },
  {
    "numero_procedimento": "N/A",
    "entidade": "Águas do Norte, SA",
    "link": "https://diariodarepublica.pt/dr/detalhe/contrato-publico/33376-992674277",
    "detalhes_completos": "1 - IDENTIFICAÇÃO E CONTACTOS DA ENTIDADE ADJUDICANTE\nDesignação da entidade adjudicante: Águas do Norte, SA\nNIPC: 513606084\nServiço/Órgão/Pessoa de contacto: Compras e Logística\nEndereço: Rua Dom Pedro de Castro, n.º 1A\nCódigo postal: 5000-669\nLocalidade: Vila Real\nPaís: Portugal\nNUT III: PT11D\nDistrito: Vila Real\nConcelho: Vila Real\nFreguesia: Freguesia de Vila Real\nTelefone: 259309370\nFax: 259309371\nEndereço da Entidade (URL): www.adnorte.pt\nEndereço Eletrónico: geral.adnorte@adp.pt\neDelivery Gateway (URL): https://www.acingov.pt\nFunção da Organização: Adquirente\nNorma jurídica da Entidade Adjudicante: Organismo de direito público\nÁrea de atividade da Autoridade Adjudicante: Serviços públicos das administrações públicas\n\n2 - JORNAL OFICIAL DA UNIÃO EUROPEIA\nO procedimento a que este anúncio diz respeito também é publicitado no Jornal Oficial da União Europeia? Sim\n\n3 - AVISO\nModelo de Anúncio: Concurso público\nData de Envio do Anúncio: 22-12-2025\n\n5 - PROCESSO\nTipo de Procedimento: Concurso público\nPreço base do procedimento: Sim\nValor do preço base do procedimento: 1.064.448,00 EUR\nProcedimento com lotes? Não\n\n6 - OBJETO DO CONTRATO\nNúmero de referência interna: PRC_0502/2025_DEX\nDesignação do contrato: PRC_0502/2025_DEX - Aquisição de coagulantes orgânicos para o Centro de Exploração do Vale do Ave da Águas do Norte, S.A.\nDescrição: PRC_0502/2025_DEX - Aquisição de coagulantes orgânicos para o Centro de Exploração do Vale do Ave da Águas do Norte, S.A.\nOpções: Não\nTipo de Contrato Principal: Aquisição de Bens Móveis\nTipo de Contrato: Aquisição de Bens Móveis\nClassificação CPV (Vocabulário Comum para os Contratos Públicos)\nObjeto principal\nVocabulário Principal: 24962000\nPreço base s/IVA: 1.064.448,00 EUR\n\n7 - INDICAÇÕES ADICIONAIS\nO contrato envolve aquisição conjunta (satisfação de várias entidades)? Não\nO contrato é adjudicado por uma central de compras? Não\n\n8 - TÉCNICAS\nO concurso destina-se à celebração de um acordo-quadro? Inexistência de acordo-quadro\nÉ utilizado um leilão eletrónico? Não\nÉ adotada uma fase de negociação? Não\nSistema de Aquisição Dinâmico: Inexistência de sistema de aquisição dinâmico\n\n9 - LOCAL DA EXECUÇÃO DO CONTRATO\nLOCAL DA EXECUÇÃO DO CONTRATO (PROCEDIMENTO)\nPaís: Portugal\nNUT III: PT119\nLocalidade: Freguesia de Serzedelo - Guimarães\nDistrito: Braga\nConcelho: Guimarães\nFreguesia: Freguesia de Serzedelo - Guimarães\nPaís: Portugal\nNUT III: PT119\nLocalidade: Freguesia de Fradelos - Vila Nova de Famalicão\nDistrito: Braga\nConcelho: Vila Nova de Famalicão\nFreguesia: Freguesia de Fradelos - Vila Nova de Famalicão\nPaís: Portugal\nNUT III: PT11A\nLocalidade: Todas\nDistrito: Porto\nConcelho: Santo Tirso\nFreguesia: Todas\n\n10 - PRAZO DE EXECUÇÃO DO CONTRATO\nPrazo de execução do contrato: 12 MESES\nPrevisão de renovações: Sim\nIndicar número máximo de renovações: 11\nPrazo de renovações diferente do prazo inicial: Não\n\n11 - FUNDOS EU\nTêm fundos EU? Não\n\n12 - DOCUMENTOS DE HABILITAÇÃO\nHabilitação para o exercício da atividade profissional: Sim\nTipo: Certificado\nDescrição: Registo de acordo com o Regulamento (CE) n.º 1907/2006, do Parlamento Europeu e do Conselho, de 18 de dezembro de 2006, relativo ao registo, avaliação, autorização e restrição dos produtos químicos (REACH), com a redação em vigor.\n\n13 - CONDIÇÕES DE APRESENTAÇÃO\nPlataforma eletrónica utilizada pela entidade adjudicante: ACIN\nURL para Apresentação: https://www.acingov.pt\nAdmissibilidade da apresentação de propostas variantes: Não autorizado\nPrazo para apresentação das propostas: 06-01-2026 17:00\nPrazo durante o qual os concorrentes são obrigados a manter as respetivas propostas: 120 dias a contar do termo do prazo para a apresentação das propostas\nApresentação de Catálogo Eletrónico: Não autorizado\nIndicação de Subcontratação na Proposta: Inexistência de indicação de subcontratação\n\n14 - PRESTAÇÃO DE CAUÇÃO\nPrestação de caução: Sim\nPercentagem: 2%\nDescrição da Garantia Exigida: O valor da caução é de 2.00% do preço contratual.\n\n15 - FORNECIMENTO DAS PEÇAS DO CONCURSO, APRESENTAÇÃO DE PEDIDOS DE PARTICIPAÇÃO E APRESENTAÇÃO DAS PROPOSTAS\nLink para acesso às peças do concurso (URL): https://www.acingov.pt/acingovprod/2/zonaPublica/zona_publica_c/donwloadProcedurePiece/MTAwODgxNA==\n\n20 - OUTROS REQUISITOS\nInformação sobre contratos reservados. Aplica-se a contratos reservados (54º-A)? Não\n\n21 - CRITÉRIO DE ADJUDICAÇÃO\nMultifator: Não\nMonofator:\nNome: Preço\n\n24 - CONDIÇÕES DO CONTRATO\nFaturação Eletrónica: Permitido\nObrigação de Subcontratação:\nCódigo da Obrigação de Subcontratação: Não é aplicável nenhuma obrigação de subcontratação.\n\n25 - COMPRA PÚBLICA ESTRATÉGICA\nCompra Pública Estratégica: Inexistência de contratação pública estratégica\n\n26 - INFORMAÇÕES ADICIONAIS\nContrato adequado para PME: Sim\nCobertura ACP (Acordo dos Contratos Públicos da Organização Mundial do Comércio): Não\n\n27 - IDENTIFICAÇÃO E CONTACTOS DO ÓRGÃO DE RECURSOS ADMINISTRATIVOS\nDesignação: Conselho de Administração da Águas do Norte, S.A.\nEndereço: Rua Dom Pedro de Castro, n.º 1A\nCódigo postal: 5000-669\nLocalidade: Vila Real\nTelefone: 259309370\nFax: 259309371\nEndereço eletrónico: geral.adnorte@adp.pt\n\n28 - IDENTIFICAÇÃO DO(S) AUTOR(ES) DE ANÚNCIO\nNome: Alice Maria Carvalho Alves\nCargo: Técnica Superior de Compras e Logística\n419918569",
    "nipc": "513606084",
    "distrito": "Vila Real",
    "concelho": "Vila Real",
    "freguesia": "Freguesia de Vila Real",
    "site": "www.adnorte.pt",
    "email": "geral.adnorte@adp.pt",
    "designacao_contrato": "PRC_0502/2025_DEX - Aquisição de coagulantes orgânicos para o Centro de Exploração do Vale do Ave da Águas do Norte, S.A.",
    "descricao": "PRC_0502/2025_DEX - Aquisição de coagulantes orgânicos para o Centro de Exploração do Vale do Ave da Águas do Norte, S.A.",
    "preco_base": "1.064.448,00 EUR",
    "prazo_execucao": "12 MESES",
    "prazo_apresentacao_propostas": "06-01-2026 17:00",
    "fundos_eu": "Não",
    "plataforma_eletronica": "ACIN",
    "url_procedimento": "https://www.acingov.pt",
    "autor_nome": "Alice Maria Carvalho Alves",
    "autor_cargo": "Técnica Superior de Compras e Logística"
  },
  {
    "numero_procedimento": "N/A",
    "entidade": "Entidade de Serviços Partilhados da Administração Pública, IP",
    "link": "https://diariodarepublica.pt/dr/detalhe/contrato-publico/33377-992674278",
    "detalhes_completos": "1 - IDENTIFICAÇÃO E CONTACTOS DA ENTIDADE ADJUDICANTE\nDesignação da entidade adjudicante: Entidade de Serviços Partilhados da Administração Pública, IP\nNIPC: 510342191\nEndereço: Av. Leite de Vasconcelos, 2, Alfragide\nCódigo postal: 2614-502\nLocalidade: Amadora\nPaís: Portugal\nNUT III: PT170\nDistrito: Lisboa\nConcelho: Amadora\nFreguesia: Freguesia de Alfragide\nTelefone: 214723390\nFax: 214723390\nEndereço da Entidade (URL): www.espap.gov.pt\nEndereço Eletrónico: contacto@espap.gov.pt\nFunção da Organização: Adquirente\nNorma jurídica da Entidade Adjudicante: Autoridade da administração central\nÁrea de atividade da Autoridade Adjudicante: Assuntos económicos\n\n2 - JORNAL OFICIAL DA UNIÃO EUROPEIA\nO procedimento a que este anúncio diz respeito também é publicitado no Jornal Oficial da União Europeia? Sim\n\n3 - AVISO\nModelo de Anúncio: Concurso limitado por prévia qualificação\nData de Envio do Anúncio: 22-12-2025\n\n5 - PROCESSO\nTipo de Procedimento: Concurso limitado por prévia qualificação\nPreço base do procedimento: Sim\nValor do preço base do procedimento: 300.000.000,00 EUR\nProcedimento com lotes? Não\n\n6 - OBJETO DO CONTRATO\nNúmero de referência interna: AQ-VA-2025\nDesignação do contrato: Acordo Quadro de Viagens e Alojamentos\nDescrição: Acordo Quadro de Viagens e Alojamentos\nOpções: Não\nTipo de Contrato Principal: Aquisição de Serviços\nTipo de Contrato: Aquisição de Serviços\nClassificação CPV (Vocabulário Comum para os Contratos Públicos)\nObjeto principal\nVocabulário Principal: 63510000\nPreço base s/IVA: 300.000.000,00 EUR\n\n7 - INDICAÇÕES ADICIONAIS\nO contrato envolve aquisição conjunta (satisfação de várias entidades)? Não\nO contrato é adjudicado por uma central de compras? Sim\n\n8 - TÉCNICAS\nO concurso destina-se à celebração de um acordo-quadro? Acordo-quadro, com reabertura de concurso\nModalidade: Com várias entidades\nPrazo de vigência: 1 anos\nValor estimado: Sim\nPara Acordo-Quadro — valor total máximo estimado para toda a duração do Acordo-Quadro: 300.000.000,00 EUR\nÉ utilizado um leilão eletrónico? Não\nSistema de Aquisição Dinâmico: Inexistência de sistema de aquisição dinâmico\n\n9 - LOCAL DA EXECUÇÃO DO CONTRATO\nLOCAL DA EXECUÇÃO DO CONTRATO (PROCEDIMENTO)\nPaís: Portugal\nNUT III: PTZZZ\nLocalidade: Todas\nDistrito: Todos\nConcelho: Todos\nFreguesia: Todas\n\n10 - PRAZO DE EXECUÇÃO DO CONTRATO\nPrazo de execução do contrato: 1 ANOS\nPrevisão de renovações: Não\n\n11 - FUNDOS EU\nTêm fundos EU? Não\n\n12 - DOCUMENTOS DE HABILITAÇÃO\nHabilitação para o exercício da atividade profissional: Não\n\n13 - CONDIÇÕES DE APRESENTAÇÃO\nPlataforma eletrónica utilizada pela entidade adjudicante: ANOGOV\nURL para Apresentação: https://plataforma-sncp.espap.gov.pt/espap/faces/\nAdmissibilidade da apresentação de propostas variantes: Não autorizado\nPrazo para apresentação das candidaturas: 04-02-2026 23:59\nRequisitos mínimos \nRequisitos mínimos de capacidade técnica: Conforme peças do procedimento.\nRequisitos mínimos de capacidade financeira: Conforme peças do procedimento.\nPrazo durante o qual os concorrentes são obrigados a manter as respetivas propostas: 120 dias a contar do termo do prazo para a apresentação das propostas\nApresentação de Catálogo Eletrónico: Permitido\nIndicação de Subcontratação na Proposta: Inexistência de indicação de subcontratação\n\n14 - PRESTAÇÃO DE CAUÇÃO\nPrestação de caução: Não\n\n15 - FORNECIMENTO DAS PEÇAS DO CONCURSO, APRESENTAÇÃO DE PEDIDOS DE PARTICIPAÇÃO E APRESENTAÇÃO DAS PROPOSTAS\nLink para acesso às peças do concurso (URL): https://plataforma-sncp.espap.gov.pt/espap/faces/app/acessoDocs.jsp?codigoAcesso=BpUb7TzpHeld2YNBJ7qGtAV3iJTVzikqUUUTu0pPw9OFVbQneO\n\n20 - OUTROS REQUISITOS\nInformação sobre contratos reservados. Aplica-se a contratos reservados (54º-A)? Não\n\n21 - CRITÉRIO DE ADJUDICAÇÃO\nMultifator: Não\nMonofator:\nNome: Preço\n\n24 - CONDIÇÕES DO CONTRATO\nFaturação Eletrónica: Permitido\nObrigação de Subcontratação:\nCódigo da Obrigação de Subcontratação: Não é aplicável nenhuma obrigação de subcontratação.\n\n25 - COMPRA PÚBLICA ESTRATÉGICA\nCompra Pública Estratégica: Redução dos impactos ambientais\nDescrição do Processo de Adjudicação Estratégico: Conforme peças do procedimento.\nCritérios de contratos Públicos Ecológicos: Outros critérios de contratação pública ecológica\nCategorias da estratégia nacional: Transporte rodoviário\nDiretiva Veículos Não Poluentes: Não\nCritério de Acessibilidade: Os critérios de acessibilidade para as pessoas com deficiência estão incluídos\n\n26 - INFORMAÇÕES ADICIONAIS\nContrato adequado para PME: Sim\nCobertura ACP (Acordo dos Contratos Públicos da Organização Mundial do Comércio): Não\n\n27 - IDENTIFICAÇÃO E CONTACTOS DO ÓRGÃO DE RECURSOS ADMINISTRATIVOS\nDesignação: Conselho Diretivo da ESPAP, I.P.\nEndereço: Av. Leite de Vasconcelos 2\nCódigo postal: 2614-502\nLocalidade: Alfragide\nTelefone: 214723100\nFax: \nEndereço eletrónico: contacto@espap.gov.pt\n\n28 - IDENTIFICAÇÃO DO(S) AUTOR(ES) DE ANÚNCIO\nNome: Ana José Silva\nCargo: Gestora de Categoria\n419920041",
    "nipc": "510342191",
    "distrito": "Lisboa",
    "concelho": "Amadora",
    "freguesia": "Freguesia de Alfragide",
    "site": "www.espap.gov.pt",
    "email": "contacto@espap.gov.pt",
    "designacao_contrato": "Acordo Quadro de Viagens e Alojamentos",
    "descricao": "Acordo Quadro de Viagens e Alojamentos",
    "preco_base": "300.000.000,00 EUR",
    "prazo_execucao": "1 ANOS",
    "prazo_apresentacao_propostas": null,
    "fundos_eu": "Não",
    "plataforma_eletronica": "ANOGOV",
    "url_procedimento": "https://plataforma-sncp.espap.gov.pt/espap/faces/",
    "autor_nome": "Ana José Silva",
    "autor_cargo": "Gestora de Categoria"
  },
  {
    "numero_procedimento": "N/A",
    "entidade": "Município de Leiria",
    "link": "https://diariodarepublica.pt/dr/detalhe/contrato-publico/33379-992674279",
    "detalhes_completos": "1 - IDENTIFICAÇÃO E CONTACTOS DA ENTIDADE ADJUDICANTE\nDesignação da entidade adjudicante: Município de Leiria\nNIPC: 505181266\nEndereço: Largo da República\nCódigo postal: 2414-006\nLocalidade: Leiria\nPaís: Portugal\nNUT III: PT16F\nDistrito: Leiria\nConcelho: Leiria\nFreguesia: União das Freguesias de Leiria, Pousos, Barreira e Cortes\nTelefone: 244839500\nFax: 244839500\nEndereço da Entidade (URL): www.cm-leiria.pt\nEndereço Eletrónico: cmleiria@cm-leiria.pt\nFunção da Organização: Adquirente\nNorma jurídica da Entidade Adjudicante: Autoridade local\nÁrea de atividade da Autoridade Adjudicante: Serviços públicos das administrações públicas\n\n2 - JORNAL OFICIAL DA UNIÃO EUROPEIA\nO procedimento a que este anúncio diz respeito também é publicitado no Jornal Oficial da União Europeia? Sim\n\n3 - AVISO\nModelo de Anúncio: Concurso público\nData de Envio do Anúncio: 22-12-2025\n\n5 - PROCESSO\nTipo de Procedimento: Concurso público\nPreço base do procedimento: Sim\nValor do preço base do procedimento: 30.910,46 EUR\nProcedimento com lotes? Não\n\n6 - OBJETO DO CONTRATO\nNúmero de referência interna: CPN (i) 148/2025/DICP\nDesignação do contrato: CPN (i) 148/2025/DICP - MANUTENÇÃO E CONSERVAÇÃO DE ESPAÇOS VERDES PÚBLICOS NOA ESPAÇOS EXISTENTES NA VILA PORTELA\nDescrição: CPN (i) 148/2025/DICP - MANUTENÇÃO E CONSERVAÇÃO DE ESPAÇOS VERDES PÚBLICOS NOA ESPAÇOS EXISTENTES NA VILA PORTELA\nOpções: Não\nTipo de Contrato Principal: Aquisição de Serviços\nTipo de Contrato: Aquisição de Serviços\nClassificação CPV (Vocabulário Comum para os Contratos Públicos)\nObjeto principal\nVocabulário Principal: 77310000\nPreço base s/IVA: 30.910,46 EUR\n\n7 - INDICAÇÕES ADICIONAIS\nO contrato envolve aquisição conjunta (satisfação de várias entidades)? Não\nO contrato é adjudicado por uma central de compras? Não\n\n8 - TÉCNICAS\nO concurso destina-se à celebração de um acordo-quadro? Inexistência de acordo-quadro\nÉ utilizado um leilão eletrónico? Não\nÉ adotada uma fase de negociação? Não\nSistema de Aquisição Dinâmico: Inexistência de sistema de aquisição dinâmico\n\n9 - LOCAL DA EXECUÇÃO DO CONTRATO\nLOCAL DA EXECUÇÃO DO CONTRATO (PROCEDIMENTO)\nPaís: Portugal\nNUT III: PT16F\nLocalidade: Leiria\nDistrito: Leiria\nConcelho: Leiria\nFreguesia: União das Freguesias de Leiria, Pousos, Barreira e Cortes\n\n10 - PRAZO DE EXECUÇÃO DO CONTRATO\nPrazo de execução do contrato: 7 MESES\nPrevisão de renovações: Não\n\n11 - FUNDOS EU\nTêm fundos EU? Não\n\n12 - DOCUMENTOS DE HABILITAÇÃO\nHabilitação para o exercício da atividade profissional: Não\n\n13 - CONDIÇÕES DE APRESENTAÇÃO\nPlataforma eletrónica utilizada pela entidade adjudicante: ANOGOV\nURL para Apresentação: https://www.anogov.com/cm-leiria/faces/\nAdmissibilidade da apresentação de propostas variantes: Não autorizado\nPrazo para apresentação das propostas: 21-01-2026 23:59\nPrazo durante o qual os concorrentes são obrigados a manter as respetivas propostas: 120 dias a contar do termo do prazo para a apresentação das propostas\nApresentação de Catálogo Eletrónico: Não autorizado\nIndicação de Subcontratação na Proposta: Inexistência de indicação de subcontratação\n\n14 - PRESTAÇÃO DE CAUÇÃO\nPrestação de caução: Não\n\n15 - FORNECIMENTO DAS PEÇAS DO CONCURSO, APRESENTAÇÃO DE PEDIDOS DE PARTICIPAÇÃO E APRESENTAÇÃO DAS PROPOSTAS\nLink para acesso às peças do concurso (URL): https://www.anogov.com/cm-leiria/faces/app/acessoDocs.jsp?codigoAcesso=Ix038NEqvQ3XqgD24uvXVUmvsEe5mh5XSQRK0pbsDGVtEckB8J\n\n20 - OUTROS REQUISITOS\nInformação sobre contratos reservados. Aplica-se a contratos reservados (54º-A)? Não\n\n21 - CRITÉRIO DE ADJUDICAÇÃO\nMultifator: Não\nMonofator:\nNome: Preço\n\n24 - CONDIÇÕES DO CONTRATO\nFaturação Eletrónica: Permitido\nObrigação de Subcontratação:\nCódigo da Obrigação de Subcontratação: Não é aplicável nenhuma obrigação de subcontratação.\n\n25 - COMPRA PÚBLICA ESTRATÉGICA\nCompra Pública Estratégica: Inexistência de contratação pública estratégica\n\n26 - INFORMAÇÕES ADICIONAIS\nContrato adequado para PME: Sim\nCobertura ACP (Acordo dos Contratos Públicos da Organização Mundial do Comércio): Não\n\n27 - IDENTIFICAÇÃO E CONTACTOS DO ÓRGÃO DE RECURSOS ADMINISTRATIVOS\nDesignação: Presidente da Câmara Municipal de Leiria\nEndereço: Largo da República\nCódigo postal: 2414-006\nLocalidade: Leiria\nEndereço eletrónico: cmleiria@cm-leiria.pt\n\n28 - IDENTIFICAÇÃO DO(S) AUTOR(ES) DE ANÚNCIO\nNome: Gonçalo Lopes\nCargo: Presidente da Câmara Municipal de Leiria\n419916292",
    "nipc": "505181266",
    "distrito": "Leiria",
    "concelho": "Leiria",
    "freguesia": "União das Freguesias de Leiria, Pousos, Barreira e Cortes",
    "site": "www.cm-leiria.pt",
    "email": "cmleiria@cm-leiria.pt",
    "designacao_contrato": "CPN (i) 148/2025/DICP - MANUTENÇÃO E CONSERVAÇÃO DE ESPAÇOS VERDES PÚBLICOS NOA ESPAÇOS EXISTENTES NA VILA PORTELA",
    "descricao": "CPN (i) 148/2025/DICP - MANUTENÇÃO E CONSERVAÇÃO DE ESPAÇOS VERDES PÚBLICOS NOA ESPAÇOS EXISTENTES NA VILA PORTELA",
    "preco_base": "30.910,46 EUR",
    "prazo_execucao": "7 MESES",
    "prazo_apresentacao_propostas": "21-01-2026 23:59",
    "fundos_eu": "Não",
    "plataforma_eletronica": "ANOGOV",
    "url_procedimento": "https://www.anogov.com/cm-leiria/faces/",
    "autor_nome": "Gonçalo Lopes",
    "autor_cargo": "Presidente da Câmara Municipal de Leiria"
  },
  {
    "numero_procedimento": "N/A",
    "entidade": "Autoridade Nacional de Segurança Rodoviária",
    "link": "https://diariodarepublica.pt/dr/detalhe/contrato-publico/33380-992674280",
    "detalhes_completos": "1 - IDENTIFICAÇÃO E CONTACTOS DA ENTIDADE ADJUDICANTE\nDesignação da entidade adjudicante: Autoridade Nacional de Segurança Rodoviária\nNIPC: 600082563\nServiço/Órgão/Pessoa de contacto: Secção Contratação Pública\nEndereço: Av. Casal de Cabanas nº 1\nCódigo postal: 2734-507\nLocalidade: Barcarena\nPaís: Portugal\nNUT III: PT170\nDistrito: Lisboa\nConcelho: Oeiras\nFreguesia: Freguesia de Barcarena\nTelefone: 214236800\nFax: 214236800\nEndereço da Entidade (URL): www.ansr.pt\nEndereço Eletrónico: contratacao@ansr.pt\neDelivery Gateway (URL): https://www.acingov.pt\nFunção da Organização: Adquirente\nNorma jurídica da Entidade Adjudicante: Organismo de direito público\nÁrea de atividade da Autoridade Adjudicante: Serviços públicos das administrações públicas\n\n2 - JORNAL OFICIAL DA UNIÃO EUROPEIA\nO procedimento a que este anúncio diz respeito também é publicitado no Jornal Oficial da União Europeia? Sim\n\n3 - AVISO\nModelo de Anúncio: Concurso público\nData de Envio do Anúncio: 22-12-2025\n\n5 - PROCESSO\nTipo de Procedimento: Concurso público\nPreço base do procedimento: Sim\nValor do preço base do procedimento: 849.000,00 EUR\nProcedimento com lotes? Não\n\n6 - OBJETO DO CONTRATO\nNúmero de referência interna: CPi 08.ANSR.2023\nDesignação do contrato: CPi 08.ANSR.2023 - Aquisição de serviços de custódia, gestão e transporte para arquivo\nDescrição: Aquisição de serviços de custódia, gestão e transporte para arquivo \nOpções: Não\nTipo de Contrato Principal: Aquisição de Serviços\nTipo de Contrato: Aquisição de Serviços\nClassificação CPV (Vocabulário Comum para os Contratos Públicos)\nObjeto principal\nVocabulário Principal: 79995100\nPreço base s/IVA: 849.000,00 EUR\n\n7 - INDICAÇÕES ADICIONAIS\nO contrato envolve aquisição conjunta (satisfação de várias entidades)? Não\nO contrato é adjudicado por uma central de compras? Não\n\n8 - TÉCNICAS\nO concurso destina-se à celebração de um acordo-quadro? Inexistência de acordo-quadro\nÉ utilizado um leilão eletrónico? Não\nÉ adotada uma fase de negociação? Não\nSistema de Aquisição Dinâmico: Inexistência de sistema de aquisição dinâmico\n\n9 - LOCAL DA EXECUÇÃO DO CONTRATO\nLOCAL DA EXECUÇÃO DO CONTRATO (PROCEDIMENTO)\nPaís: Portugal\nNUT III: PT170\nLocalidade: Freguesia de Barcarena\nDistrito: Lisboa\nConcelho: Oeiras\nFreguesia: Freguesia de Barcarena\n\n10 - PRAZO DE EXECUÇÃO DO CONTRATO\nPrazo de execução do contrato: 36 MESES\nPrevisão de renovações: Não\n\n11 - FUNDOS EU\nTêm fundos EU? Não\n\n12 - DOCUMENTOS DE HABILITAÇÃO\nHabilitação para o exercício da atividade profissional: Não\n\n13 - CONDIÇÕES DE APRESENTAÇÃO\nPlataforma eletrónica utilizada pela entidade adjudicante: ACIN\nURL para Apresentação: https://www.acingov.pt\nAdmissibilidade da apresentação de propostas variantes: Não autorizado\nPrazo para apresentação das propostas: 21-01-2026 23:59\nPrazo durante o qual os concorrentes são obrigados a manter as respetivas propostas: 66 dias a contar do termo do prazo para a apresentação das propostas\nApresentação de Catálogo Eletrónico: Não autorizado\nIndicação de Subcontratação na Proposta: Inexistência de indicação de subcontratação\n\n14 - PRESTAÇÃO DE CAUÇÃO\nPrestação de caução: Sim\nPercentagem: 5%\nDescrição da Garantia Exigida: O valor da caução é de 5.00% do preço contratual.\n\n15 - FORNECIMENTO DAS PEÇAS DO CONCURSO, APRESENTAÇÃO DE PEDIDOS DE PARTICIPAÇÃO E APRESENTAÇÃO DAS PROPOSTAS\nLink para acesso às peças do concurso (URL): https://www.acingov.pt/acingovprod/2/zonaPublica/zona_publica_c/donwloadProcedurePiece/MTAwODUzNQ==\n\n20 - OUTROS REQUISITOS\nInformação sobre contratos reservados. Aplica-se a contratos reservados (54º-A)? Não\n\n21 - CRITÉRIO DE ADJUDICAÇÃO\nMultifator: Não\nMonofator:\nNome: Preço\n\n24 - CONDIÇÕES DO CONTRATO\nFaturação Eletrónica: Permitido\nObrigação de Subcontratação:\nCódigo da Obrigação de Subcontratação: Não é aplicável nenhuma obrigação de subcontratação.\n\n25 - COMPRA PÚBLICA ESTRATÉGICA\nCompra Pública Estratégica: Inexistência de contratação pública estratégica\n\n26 - INFORMAÇÕES ADICIONAIS\nContrato adequado para PME: Não\nCobertura ACP (Acordo dos Contratos Públicos da Organização Mundial do Comércio): Não\n\n27 - IDENTIFICAÇÃO E CONTACTOS DO ÓRGÃO DE RECURSOS ADMINISTRATIVOS\nDesignação: SGMAI\nEndereço: Praça do Comércio Ala Oriental, 15\nCódigo postal: 1149-015\nLocalidade: Lisboa\nTelefone: 213409000\nFax: 213409000\nEndereço eletrónico: sec.geral.mai@sg.mai.gov.pt\nPrazo de interposição do recurso: 10 dias\n\n28 - IDENTIFICAÇÃO DO(S) AUTOR(ES) DE ANÚNCIO\nNome: Pedro Jose Clemente\nCargo: Presidente\n419921792",
    "nipc": "600082563",
    "distrito": "Lisboa",
    "concelho": "Oeiras",
    "freguesia": "Freguesia de Barcarena",
    "site": "www.ansr.pt",
    "email": "contratacao@ansr.pt",
    "designacao_contrato": "CPi 08.ANSR.2023 - Aquisição de serviços de custódia, gestão e transporte para arquivo",
    "descricao": "Aquisição de serviços de custódia, gestão e transporte para arquivo",
    "preco_base": "849.000,00 EUR",
    "prazo_execucao": "36 MESES",
    "prazo_apresentacao_propostas": "21-01-2026 23:59",
    "fundos_eu": "Não",
    "plataforma_eletronica": "ACIN",
    "url_procedimento": "https://www.acingov.pt",
    "autor_nome": "Pedro Jose Clemente",
    "autor_cargo": "Presidente"
  },
  {
    "numero_procedimento": "N/A",
    "entidade": "Unidade Local de Saúde de São José, EPE",
    "link": "https://diariodarepublica.pt/dr/detalhe/contrato-publico/33383-992674281",
    "detalhes_completos": "1 - IDENTIFICAÇÃO E CONTACTOS DA ENTIDADE ADJUDICANTE\nDesignação da entidade adjudicante: Unidade Local de Saúde de São José, EPE\nNIPC: 508080142\nEndereço: Rua José António Serrano\nCódigo postal: 1150-199\nLocalidade: Lisboa\nPaís: Portugal\nNUT III: PT170\nDistrito: Lisboa\nConcelho: Lisboa\nFreguesia: Freguesia de Arroios - Lisboa\nTelefone: 218841403\nFax: 218841025\nEndereço da Entidade (URL): www.chlc.min-saude.pt\nEndereço Eletrónico: geral@chlc.min-saude.pt\neDelivery Gateway (URL): https://community.vortal.biz/public/\nFunção da Organização: Adquirente\nNorma jurídica da Entidade Adjudicante: Organismo de direito público\nÁrea de atividade da Autoridade Adjudicante: Saúde\n\n2 - JORNAL OFICIAL DA UNIÃO EUROPEIA\nO procedimento a que este anúncio diz respeito também é publicitado no Jornal Oficial da União Europeia? Sim\n\n3 - AVISO\nModelo de Anúncio: Concurso público\nData de Envio do Anúncio: 22-12-2025\n\n5 - PROCESSO\nTipo de Procedimento: Concurso público\nPreço base do procedimento: Sim\nValor do preço base do procedimento: 445.392,00 EUR\nProcedimento com lotes? Sim\nNº Máx. de Lotes Autorizado: 3\nNúmero máximo de lotes que podem ser adjudicados a um concorrente: 3\n\n6 - OBJETO DO CONTRATO\nNúmero de referência interna: 12005626\nDesignação do contrato: 12005626 - Material para deformidade infantil juvenil e de adolescentes\nDescrição: 12005626 - Material para deformidade infantil juvenil e de adolescentes\nOpções: Não\nTipo de Contrato Principal: Aquisição de Bens Móveis\nTipo de Contrato: Aquisição de Bens Móveis\nClassificação CPV (Vocabulário Comum para os Contratos Públicos)\nObjeto principal\nVocabulário Principal: 33100000\nPreço base s/IVA: 445.392,00 EUR\nLotes: \nNº: LOT-0001\nDescrição do Lote: Lote 1\nPreço base s/IVA: 71.360,00 EUR\nClassificação CPV (Vocabulário Comum para os Contratos Públicos)\nObjeto principal\nVocabulário Principal: 33100000\nNº: LOT-0002\nDescrição do Lote: Lote 2\nPreço base s/IVA: 48.432,00 EUR\nClassificação CPV (Vocabulário Comum para os Contratos Públicos)\nObjeto principal\nVocabulário Principal: 33100000\nNº: LOT-0003\nDescrição do Lote: Lote 3\nPreço base s/IVA: 325.600,00 EUR\nClassificação CPV (Vocabulário Comum para os Contratos Públicos)\nObjeto principal\nVocabulário Principal: 33100000\n\n7 - INDICAÇÕES ADICIONAIS\nO contrato envolve aquisição conjunta (satisfação de várias entidades)? Não\nO contrato é adjudicado por uma central de compras? Não\n\n8 - TÉCNICAS\nO concurso destina-se à celebração de um acordo-quadro? Inexistência de acordo-quadro\nÉ utilizado um leilão eletrónico? Não\nÉ adotada uma fase de negociação? Não\nSistema de Aquisição Dinâmico: Inexistência de sistema de aquisição dinâmico\n\n9 - LOCAL DA EXECUÇÃO DO CONTRATO\nLOCAL DA EXECUÇÃO DO CONTRATO (PROCEDIMENTO)\nPaís: Portugal\nNUT III: PT170\nLocalidade: Lisboa\nDistrito: Lisboa\nConcelho: Lisboa\nFreguesia: Freguesia de Arroios - Lisboa\nLOCAL DA EXECUÇÃO DO CONTRATO (LOTE)\nIdentificador do Lote: LOT-0001; LOT-0002; LOT-0003\nPaís: Portugal\nNUT III: PT170\nLocalidade: Lisboa\nDistrito: Lisboa\nConcelho: Lisboa\nFreguesia: Freguesia de Arroios - Lisboa\n\n10 - PRAZO DE EXECUÇÃO DO CONTRATO\nIdentificador do Lote: LOT-0001; LOT-0002; LOT-0003\nPrazo de execução do contrato: 1 ANOS\nPrevisão de renovações: Não\n\n11 - FUNDOS EU\nIdentificador do Lote: LOT-0001; LOT-0002; LOT-0003\nTêm fundos EU? Não\n\n12 - DOCUMENTOS DE HABILITAÇÃO\nHabilitação para o exercício da atividade profissional: Não\n\n13 - CONDIÇÕES DE APRESENTAÇÃO\nPlataforma eletrónica utilizada pela entidade adjudicante: VORTAL\nURL para Apresentação: https://community.vortal.biz/public/\nAdmissibilidade da apresentação de propostas variantes: Não autorizado\nPrazo para apresentação das propostas: 24-01-2026 23:59\nPrazo durante o qual os concorrentes são obrigados a manter as respetivas propostas: 120 dias a contar do termo do prazo para a apresentação das propostas\nApresentação de Catálogo Eletrónico: Permitido\nIndicação de Subcontratação na Proposta: Inexistência de indicação de subcontratação\n\n14 - PRESTAÇÃO DE CAUÇÃO\nPrestação de caução: Não\n\n15 - FORNECIMENTO DAS PEÇAS DO CONCURSO, APRESENTAÇÃO DE PEDIDOS DE PARTICIPAÇÃO E APRESENTAÇÃO DAS PROPOSTAS\nLink para acesso às peças do concurso (URL): https://community.vortal.biz/Public/public-tender-documents/RWk4SEF5Q2Q5MTB1ODBEeHJrT21vMXM3ZFdSZDlneGYzdGZVdENTa21SZ0RyM2lEMWFvWWprOXRwNXBIaC9DYkVXL3A5L2xaWURoZGlxZkVWV0hTSWc9PXVuTmRe\n\n20 - OUTROS REQUISITOS\nIdentificador do Lote: LOT-0001; LOT-0002; LOT-0003\nInformação sobre contratos reservados. Aplica-se a contratos reservados (54º-A)? Não\n\n21 - CRITÉRIO DE ADJUDICAÇÃO\nO Critério de adjudicação é diferenciado por lote? Não\nMultifator: Não\nMonofator:\nNome: Preço\n\n24 - CONDIÇÕES DO CONTRATO\nIdentificador do Lote: LOT-0001; LOT-0002; LOT-0003\nFaturação Eletrónica: Permitido\nObrigação de Subcontratação:\nCódigo da Obrigação de Subcontratação: Não é aplicável nenhuma obrigação de subcontratação.\n\n25 - COMPRA PÚBLICA ESTRATÉGICA\nCompra Pública Estratégica: Inexistência de contratação pública estratégica\n\n26 - INFORMAÇÕES ADICIONAIS\nIdentificador do Lote: LOT-0001; LOT-0002; LOT-0003\nContrato adequado para PME: Sim\nCobertura ACP (Acordo dos Contratos Públicos da Organização Mundial do Comércio): Não\n\n27 - IDENTIFICAÇÃO E CONTACTOS DO ÓRGÃO DE RECURSOS ADMINISTRATIVOS\nDesignação: Conselho de Administração\nEndereço: Rua José António Serrano s/n\nCódigo postal: 1150-199\nLocalidade: Lisboa\nTelefone: +351 218841000\nFax: +351 218841023\nEndereço eletrónico: sec.vca@ulssjose.min-saude.pt\n\n28 - IDENTIFICAÇÃO DO(S) AUTOR(ES) DE ANÚNCIO\nNome: Conselho de Administração\nCargo: Conselho de Administração\n419919921",
    "nipc": "508080142",
    "distrito": "Lisboa",
    "concelho": "Lisboa",
    "freguesia": "Freguesia de Arroios - Lisboa",
    "site": "www.chlc.min-saude.pt",
    "email": "geral@chlc.min-saude.pt",
    "designacao_contrato": "12005626 - Material para deformidade infantil juvenil e de adolescentes",
    "descricao": "12005626 - Material para deformidade infantil juvenil e de adolescentes",
    "preco_base": "445.392,00 EUR",
    "prazo_execucao": "1 ANOS",
    "prazo_apresentacao_propostas": "24-01-2026 23:59",
    "fundos_eu": "Não",
    "plataforma_eletronica": "VORTAL",
    "url_procedimento": "https://community.vortal.biz/public/",
    "autor_nome": "Conselho de Administração",
    "autor_cargo": "Conselho de Administração"
  },
  {
    "numero_procedimento": "N/A",
    "entidade": "Comunidade Intermunicipal do Douro",
    "link": "https://diariodarepublica.pt/dr/detalhe/contrato-publico/33386-992674282",
    "detalhes_completos": "1 - IDENTIFICAÇÃO E CONTACTOS DA ENTIDADE ADJUDICANTE\nDesignação da entidade adjudicante: Comunidade Intermunicipal do Douro\nNIPC: 508779200\nEndereço: Avenida Carvalho Araújo, 7\nCódigo postal: 5000-657\nLocalidade:  Vila Real \nPaís: Portugal\nNUT III: PT11D\nDistrito: Vila Real\nConcelho: Vila Real\nFreguesia: Todas\nTelefone: 259309732\nEndereço da Entidade (URL): www.cimdouro.pt\nEndereço Eletrónico: joao.rodrigues@cimdouro.pt\neDelivery Gateway (URL): https://community.vortal.biz/public/\nFunção da Organização: Adquirente\nNorma jurídica da Entidade Adjudicante: Autoridade local\nÁrea de atividade da Autoridade Adjudicante: Serviços públicos das administrações públicas\n\n2 - JORNAL OFICIAL DA UNIÃO EUROPEIA\nO procedimento a que este anúncio diz respeito também é publicitado no Jornal Oficial da União Europeia? Não\n\n3 - AVISO\nModelo de Anúncio: Concurso público\nData de Envio do Anúncio: 24-12-2025\n\n5 - PROCESSO\nTipo de Procedimento: Concurso público\nPreço base do procedimento: Sim\nValor do preço base do procedimento: 97.500,00 EUR\nProcedimento com lotes? Não\n\n6 - OBJETO DO CONTRATO\nNúmero de referência interna: 07/2025/CP Cópia\nDesignação do contrato: Aquisição de Serviços para Conceção/Construção do Stand da CIMDOURO, para participação na Feira Internacional de Turismo de Lisboa - BTL'26\nDescrição: Aquisição de Serviços para Conceção/Construção do Stand da CIMDOURO, para participação na Feira Internacional de Turismo de Lisboa - BTL'26\nTipo de Contrato Principal: Locação de Bens Móveis\nTipo de Contrato: Locação de Bens Móveis\nClassificação CPV (Vocabulário Comum para os Contratos Públicos)\nObjeto principal\nVocabulário Principal: 39154100\nPreço base s/IVA: 97.500,00 EUR\n\n7 - INDICAÇÕES ADICIONAIS\nO contrato envolve aquisição conjunta (satisfação de várias entidades)? Não\nO contrato é adjudicado por uma central de compras? Não\n\n8 - TÉCNICAS\nO concurso destina-se à celebração de um acordo-quadro? Inexistência de acordo-quadro\nÉ utilizado um leilão eletrónico? Não\nÉ adotada uma fase de negociação? Não\nSistema de Aquisição Dinâmico: Inexistência de sistema de aquisição dinâmico\n\n9 - LOCAL DA EXECUÇÃO DO CONTRATO\nLOCAL DA EXECUÇÃO DO CONTRATO (PROCEDIMENTO)\nPaís: Portugal\nNUT III: PT170\nLocalidade: Lisboa\nDistrito: Lisboa\nConcelho: Lisboa\nFreguesia: Todas\n\n10 - PRAZO DE EXECUÇÃO DO CONTRATO\nPrazo de execução do contrato: 60 DIAS\nPrevisão de renovações: Não\n\n11 - FUNDOS EU\nTêm fundos EU? Não\n\n12 - DOCUMENTOS DE HABILITAÇÃO\nHabilitação para o exercício da atividade profissional: Não\n\n13 - CONDIÇÕES DE APRESENTAÇÃO\nPlataforma eletrónica utilizada pela entidade adjudicante: VORTAL\nURL para Apresentação: https://community.vortal.biz/public/\nAdmissibilidade da apresentação de propostas variantes: Não autorizado\nPrazo para apresentação das propostas: 01-01-2026 19:00\nPrazo durante o qual os concorrentes são obrigados a manter as respetivas propostas: 66 dias a contar do termo do prazo para a apresentação das propostas\nIndicação de Subcontratação na Proposta: Inexistência de indicação de subcontratação\n\n14 - PRESTAÇÃO DE CAUÇÃO\nPrestação de caução: Não\n\n15 - FORNECIMENTO DAS PEÇAS DO CONCURSO, APRESENTAÇÃO DE PEDIDOS DE PARTICIPAÇÃO E APRESENTAÇÃO DAS PROPOSTAS\nLink para acesso às peças do concurso (URL): https://community.vortal.biz/Public/public-tender-documents/RlVDdldTWTBVOWpQZlBHRWFQUytMblQ2WXZQak85TDdhZlBFcjhYMzMxcUUzaFBFTlBsNkdxSlFWdjBRV2tEdnYvTEZlcWFOdFFWVk9vNmlBVDhPVUE9PSkyYlko\n\n20 - OUTROS REQUISITOS\nInformação sobre contratos reservados. Aplica-se a contratos reservados (54º-A)? Não\n\n21 - CRITÉRIO DE ADJUDICAÇÃO\nMultifator: Sim\nFator: \nNome: Preço\nPonderação: 40%\nSubfatores: Não\nFator: \nNome: Qualidade\nPonderação: 60%\nSubfatores: Sim\nSubfatores: \nNome: Apreciação das características estéticas e layout da proposta\nPonderação : 70%; \nNome: Apreciação das características de funcionalidade\nPonderação : 30%; \n\n24 - CONDIÇÕES DO CONTRATO\nFaturação Eletrónica: Permitido\nObrigação de Subcontratação:\nCódigo da Obrigação de Subcontratação: Não é aplicável nenhuma obrigação de subcontratação.\n\n25 - COMPRA PÚBLICA ESTRATÉGICA\nCompra Pública Estratégica: Inexistência de contratação pública estratégica\n\n26 - INFORMAÇÕES ADICIONAIS\nContrato adequado para PME: Sim\nCobertura ACP (Acordo dos Contratos Públicos da Organização Mundial do Comércio): Não\n\n27 - IDENTIFICAÇÃO E CONTACTOS DO ÓRGÃO DE RECURSOS ADMINISTRATIVOS\nDesignação: Comunidade Intermunicipal do Douro\nEndereço: Avenida Carvalho Araújo, 7\nCódigo postal: 5000-657\nLocalidade: Vila Real\nTelefone: +351 259309731\nFax: +351 259309731\nEndereço eletrónico: correio@cimdouro.pt\n\n28 - IDENTIFICAÇÃO DO(S) AUTOR(ES) DE ANÚNCIO\nNome: João Rodrigues\nCargo: 1.º Secretário Executivo Intermunicipal\n419931706",
    "nipc": "508779200",
    "distrito": "Vila Real",
    "concelho": "Vila Real",
    "freguesia": "Todas",
    "site": "www.cimdouro.pt",
    "email": "joao.rodrigues@cimdouro.pt",
    "designacao_contrato": "Aquisição de Serviços para Conceção/Construção do Stand da CIMDOURO, para participação na Feira Internacional de Turismo de Lisboa - BTL'26",
    "descricao": "Aquisição de Serviços para Conceção/Construção do Stand da CIMDOURO, para participação na Feira Internacional de Turismo de Lisboa - BTL'26",
    "preco_base": "97.500,00 EUR",
    "prazo_execucao": "60 DIAS",
    "prazo_apresentacao_propostas": "01-01-2026 19:00",
    "fundos_eu": "Não",
    "plataforma_eletronica": "VORTAL",
    "url_procedimento": "https://community.vortal.biz/public/",
    "autor_nome": "João Rodrigues",
    "autor_cargo": "1.º Secretário Executivo Intermunicipal"
  },
  {
    "numero_procedimento": "N/A",
    "entidade": "Instituto Politécnico de Bragança",
    "link": "https://diariodarepublica.pt/dr/detalhe/contrato-publico/33387-992674283",
    "detalhes_completos": "1 - IDENTIFICAÇÃO E CONTACTOS DA ENTIDADE ADJUDICANTE\nDesignação da entidade adjudicante: Instituto Politécnico de Bragança\nNIPC: 600013758\nServiço/Órgão/Pessoa de contacto: Vice-Presidente do IPB, Prof. Doutor Albano Agostinho Gomes Alves\nEndereço: Campus de Santa Apolónia\nCódigo postal: 5300-253\nLocalidade: Bragança\nPaís: Portugal\nNUT III: PT11E\nDistrito: Braganca\nConcelho: Bragança\nFreguesia: União das Freguesias de Sé, Santa Maria e Meixedo\nTelefone: 273303200\nFax: 273325405\nEndereço da Entidade (URL): www.ipb.pt\nEndereço Eletrónico: ipb@ipb.pt\neDelivery Gateway (URL): https://www.acingov.pt\nFunção da Organização: Adquirente\nNorma jurídica da Entidade Adjudicante: Organismo de direito público\nÁrea de atividade da Autoridade Adjudicante: Educação\n\n2 - JORNAL OFICIAL DA UNIÃO EUROPEIA\nO procedimento a que este anúncio diz respeito também é publicitado no Jornal Oficial da União Europeia? Sim\n\n3 - AVISO\nModelo de Anúncio: Concurso público\nData de Envio do Anúncio: 22-12-2025\n\n5 - PROCESSO\nTipo de Procedimento: Concurso público\nPreço base do procedimento: Sim\nValor do preço base do procedimento: 382.000,00 EUR\nProcedimento com lotes? Não\n\n6 - OBJETO DO CONTRATO\nNúmero de referência interna: 100/CPIB/2025\nDesignação do contrato: Aquisição de Sistema de Produção Flexível Indústria 4.0\nDescrição: Aquisição de Sistema de Produção Flexível Indústria 4.0\nOpções: Não\nTipo de Contrato Principal: Aquisição de Bens Móveis\nTipo de Contrato: Aquisição de Bens Móveis\nClassificação CPV (Vocabulário Comum para os Contratos Públicos)\nObjeto principal\nVocabulário Principal: 38970000\nPreço base s/IVA: 382.000,00 EUR\n\n7 - INDICAÇÕES ADICIONAIS\nO contrato envolve aquisição conjunta (satisfação de várias entidades)? Não\nO contrato é adjudicado por uma central de compras? Não\n\n8 - TÉCNICAS\nO concurso destina-se à celebração de um acordo-quadro? Inexistência de acordo-quadro\nÉ utilizado um leilão eletrónico? Não\nÉ adotada uma fase de negociação? Não\nSistema de Aquisição Dinâmico: Inexistência de sistema de aquisição dinâmico\n\n9 - LOCAL DA EXECUÇÃO DO CONTRATO\nLOCAL DA EXECUÇÃO DO CONTRATO (PROCEDIMENTO)\nPaís: Portugal\nNUT III: PT11E\nLocalidade: União das Freguesias de Sé, Santa Maria e Meixedo\nDistrito: Braganca\nConcelho: Bragança\nFreguesia: União das Freguesias de Sé, Santa Maria e Meixedo\n\n10 - PRAZO DE EXECUÇÃO DO CONTRATO\nPrazo de execução do contrato: 90 DIAS\nPrevisão de renovações: Não\n\n11 - FUNDOS EU\nTêm fundos EU? Não\n\n12 - DOCUMENTOS DE HABILITAÇÃO\nHabilitação para o exercício da atividade profissional: Não\n\n13 - CONDIÇÕES DE APRESENTAÇÃO\nPlataforma eletrónica utilizada pela entidade adjudicante: ACIN\nURL para Apresentação: https://www.acingov.pt\nAdmissibilidade da apresentação de propostas variantes: Não autorizado\nPrazo para apresentação das propostas: 21-01-2026 20:00\nPrazo durante o qual os concorrentes são obrigados a manter as respetivas propostas: 66 dias a contar do termo do prazo para a apresentação das propostas\nApresentação de Catálogo Eletrónico: Permitido\nIndicação de Subcontratação na Proposta: Inexistência de indicação de subcontratação\n\n14 - PRESTAÇÃO DE CAUÇÃO\nPrestação de caução: Não\n\n15 - FORNECIMENTO DAS PEÇAS DO CONCURSO, APRESENTAÇÃO DE PEDIDOS DE PARTICIPAÇÃO E APRESENTAÇÃO DAS PROPOSTAS\nLink para acesso às peças do concurso (URL): https://www.acingov.pt/acingovprod/2/zonaPublica/zona_publica_c/donwloadProcedurePiece/MTAwNzQzMg==\n\n20 - OUTROS REQUISITOS\nInformação sobre contratos reservados. Aplica-se a contratos reservados (54º-A)? Não\n\n21 - CRITÉRIO DE ADJUDICAÇÃO\nMultifator: Sim\nFator: \nNome: Preço\nPonderação: 45%\nSubfatores: Não\nFator: \nNome: Qualidade\nPonderação: 35%\nSubfatores: Não\nFator: \nNome: Outros\nOutro Nome: Garantia\nPonderação: 20%\nSubfatores: Não\n\n24 - CONDIÇÕES DO CONTRATO\nFaturação Eletrónica: Necessário\nObrigação de Subcontratação:\nCódigo da Obrigação de Subcontratação: Não é aplicável nenhuma obrigação de subcontratação.\n\n25 - COMPRA PÚBLICA ESTRATÉGICA\nCompra Pública Estratégica: Inexistência de contratação pública estratégica\n\n26 - INFORMAÇÕES ADICIONAIS\nContrato adequado para PME: Não\nCobertura ACP (Acordo dos Contratos Públicos da Organização Mundial do Comércio): Não\n\n27 - IDENTIFICAÇÃO E CONTACTOS DO ÓRGÃO DE RECURSOS ADMINISTRATIVOS\nDesignação: Presidentes do IPB\nEndereço: Campus de Santa Apolónia\nCódigo postal: 5300-253\nLocalidade: Bragança\nTelefone: 273330803\nFax: \nEndereço eletrónico: ipb@ipb.pt\nPrazo de interposição do recurso: 5 dias\n\n28 - IDENTIFICAÇÃO DO(S) AUTOR(ES) DE ANÚNCIO\nNome: Albano Agostinho Gomes Alves\nCargo: Vice-Presidente do IPB\n419921646",
    "nipc": "600013758",
    "distrito": "Braganca",
    "concelho": "Bragança",
    "freguesia": "União das Freguesias de Sé, Santa Maria e Meixedo",
    "site": "www.ipb.pt",
    "email": "ipb@ipb.pt",
    "designacao_contrato": "Aquisição de Sistema de Produção Flexível Indústria 4.0",
    "descricao": "Aquisição de Sistema de Produção Flexível Indústria 4.0",
    "preco_base": "382.000,00 EUR",
    "prazo_execucao": "90 DIAS",
    "prazo_apresentacao_propostas": "21-01-2026 20:00",
    "fundos_eu": "Não",
    "plataforma_eletronica": "ACIN",
    "url_procedimento": "https://www.acingov.pt",
    "autor_nome": "Albano Agostinho Gomes Alves",
    "autor_cargo": "Vice-Presidente do IPB"
  },
  {
    "numero_procedimento": "N/A",
    "entidade": "Rádio e Televisão de Portugal, SA",
    "link": "https://diariodarepublica.pt/dr/detalhe/contrato-publico/33388-992674284",
    "detalhes_completos": "1 - IDENTIFICAÇÃO E CONTACTOS DA ENTIDADE ADJUDICANTE\nDesignação da entidade adjudicante: Rádio e Televisão de Portugal, SA\nNIPC: 500225680\nEndereço: Avenida Marechal Gomes da Costa, 37\nCódigo postal: 1849-030\nLocalidade: Lisboa\nPaís: Portugal\nNUT III: PT170\nDistrito: Lisboa\nConcelho: Lisboa\nFreguesia: Todas\nTelefone: 217947000\nFax: 217947570\nEndereço da Entidade (URL): www.rpt.pt\nEndereço Eletrónico: dir.comercial@rtp.pt\neDelivery Gateway (URL): https://community.vortal.biz/public/\nFunção da Organização: Adquirente\nNorma jurídica da Entidade Adjudicante: Autoridade da administração central\nÁrea de atividade da Autoridade Adjudicante: Serviços públicos das administrações públicas\n\n2 - JORNAL OFICIAL DA UNIÃO EUROPEIA\nO procedimento a que este anúncio diz respeito também é publicitado no Jornal Oficial da União Europeia? Sim\n\n3 - AVISO\nModelo de Anúncio: Concurso público\nData de Envio do Anúncio: 22-12-2025\n\n5 - PROCESSO\nTipo de Procedimento: Concurso público\nPreço base do procedimento: Sim\nValor do preço base do procedimento: 700.000,00 EUR\nProcedimento com lotes? Sim\nNº Máx. de Lotes Autorizado: 2\nNúmero máximo de lotes que podem ser adjudicados a um concorrente: 2\n\n6 - OBJETO DO CONTRATO\nNúmero de referência interna: RTP-CP 28/2025-CF\nDesignação do contrato: CP 28/2025 - Aquisição de serviços de impressão, cópias e gestão documental\nDescrição: CP 28/2025 - Aquisição de serviços de impressão, cópias e gestão documental\nOpções: Não\nTipo de Contrato Principal: Aquisição de Serviços\nTipo de Contrato: Aquisição de Serviços\nClassificação CPV (Vocabulário Comum para os Contratos Públicos)\nObjeto principal\nVocabulário Principal: 79800000\nPreço base s/IVA: 445.000,00 EUR\nObjeto Complementar\nVocabulário Principal: 72512000\nPreço base s/IVA: 255.000,00 EUR\nLotes: \nNº: LOT-0001\nDescrição do Lote: Lote 1 – Aquisição de instalação e manutenção dos equipamentos necessários à realização de impressões, cópias, digitalizações e faxes, incluindo os softwares especificados\nPreço base s/IVA: 445.000,00 EUR\nClassificação CPV (Vocabulário Comum para os Contratos Públicos)\nObjeto principal\nVocabulário Principal: 79800000\nObjeto Complementar\nVocabulário Principal: 72512000\nNº: LOT-0002\nDescrição do Lote: Lote 2 - Aquisição de serviços de outsourcing em gestão documental.\nPreço base s/IVA: 255.000,00 EUR\nClassificação CPV (Vocabulário Comum para os Contratos Públicos)\nObjeto principal\nVocabulário Principal: 79800000\nObjeto Complementar\nVocabulário Principal: 72512000\n\n7 - INDICAÇÕES ADICIONAIS\nO contrato envolve aquisição conjunta (satisfação de várias entidades)? Não\nO contrato é adjudicado por uma central de compras? Não\n\n8 - TÉCNICAS\nO concurso destina-se à celebração de um acordo-quadro? Inexistência de acordo-quadro\nÉ utilizado um leilão eletrónico? Não\nÉ adotada uma fase de negociação? Não\nSistema de Aquisição Dinâmico: Inexistência de sistema de aquisição dinâmico\n\n9 - LOCAL DA EXECUÇÃO DO CONTRATO\nLOCAL DA EXECUÇÃO DO CONTRATO (PROCEDIMENTO)\nPaís: Portugal\nNUT III: PT170\nLocalidade: Lisboa\nDistrito: Lisboa\nConcelho: Lisboa\nFreguesia: Todas\nLOCAL DA EXECUÇÃO DO CONTRATO (LOTE)\nIdentificador do Lote: LOT-0001; LOT-0002\nPaís: Portugal\nNUT III: PT170\nLocalidade: Lisboa\nDistrito: Lisboa\nConcelho: Lisboa\nFreguesia: Todas\n\n10 - PRAZO DE EXECUÇÃO DO CONTRATO\nIdentificador do Lote: LOT-0001; LOT-0002\nPrazo de execução do contrato: 5 ANOS\nPrevisão de renovações: Não\n\n11 - FUNDOS EU\nIdentificador do Lote: LOT-0001; LOT-0002\nTêm fundos EU? Não\n\n12 - DOCUMENTOS DE HABILITAÇÃO\nHabilitação para o exercício da atividade profissional: Não\n\n13 - CONDIÇÕES DE APRESENTAÇÃO\nPlataforma eletrónica utilizada pela entidade adjudicante: VORTAL\nURL para Apresentação: https://community.vortal.biz/public/\nAdmissibilidade da apresentação de propostas variantes: Não autorizado\nPrazo para apresentação das propostas: 26-01-2026 18:00\nPrazo durante o qual os concorrentes são obrigados a manter as respetivas propostas: 67 dias a contar do termo do prazo para a apresentação das propostas\nApresentação de Catálogo Eletrónico: Não autorizado\nIndicação de Subcontratação na Proposta: Inexistência de indicação de subcontratação\n\n14 - PRESTAÇÃO DE CAUÇÃO\nPrestação de caução: Sim\nPercentagem: 5%\nDescrição da Garantia Exigida: Conforme Programa de Concurso\n\n15 - FORNECIMENTO DAS PEÇAS DO CONCURSO, APRESENTAÇÃO DE PEDIDOS DE PARTICIPAÇÃO E APRESENTAÇÃO DAS PROPOSTAS\nLink para acesso às peças do concurso (URL): https://community.vortal.biz/Public/public-tender-documents/UjUyZ0FibUNNZkFudXhVQlFZQmR3VzA1MnhpTTBJc3RLWEtma0Y5NGpGbzVuN1Z1b1VDTEc4UURjRWowL1NiQStrTTF3QXFiWUNuUGx1d1J2bUJHM0E9PUJ5VDhw\n\n20 - OUTROS REQUISITOS\nIdentificador do Lote: LOT-0001; LOT-0002\nInformação sobre contratos reservados. Aplica-se a contratos reservados (54º-A)? Não\n\n21 - CRITÉRIO DE ADJUDICAÇÃO\nO Critério de adjudicação é diferenciado por lote? Sim\nIdentificador do lote: LOT-0001\nMultifator: Sim\nFator: \nNome: Preço\nPonderação: 65%\nSubfatores: Não\nFator: \nNome: Preço\nPonderação: 4%\nSubfatores: Não\nFator: \nNome: Preço\nPonderação: 4%\nSubfatores: Não\nFator: \nNome: Qualidade\nPonderação: 4%\nSubfatores: Não\nFator: \nNome: Qualidade\nPonderação: 4%\nSubfatores: Não\nFator: \nNome: Qualidade\nPonderação: 19%\nSubfatores: Não\nO Critério de adjudicação é diferenciado por lote? Sim\nIdentificador do lote: LOT-0002\nMultifator: Não\nMonofator:\nNome: Outros\nOutro nome: Preço\n\n24 - CONDIÇÕES DO CONTRATO\nIdentificador do Lote: LOT-0001; LOT-0002\nFaturação Eletrónica: Permitido\nObrigação de Subcontratação:\nCódigo da Obrigação de Subcontratação: Não é aplicável nenhuma obrigação de subcontratação.\n\n25 - COMPRA PÚBLICA ESTRATÉGICA\nCompra Pública Estratégica: Redução dos impactos ambientais\nDescrição do Processo de Adjudicação Estratégico: Conforme as peças do procedimento\nCritérios de contratos Públicos Ecológicos: Critérios de contratação pública ecológica nacional\nCategorias da estratégia nacional: Outros\nOutra categoria (Descrição): N/A\nDiretiva Veículos Não Poluentes: Não\nCritério de Acessibilidade: Os critérios de acessibilidade para as pessoas com deficiência não estão incluídos porque o contrato não se destina a pessoas singulares\n\n26 - INFORMAÇÕES ADICIONAIS\nIdentificador do Lote: LOT-0001; LOT-0002\nContrato adequado para PME: Sim\nCobertura ACP (Acordo dos Contratos Públicos da Organização Mundial do Comércio): Não\n\n27 - IDENTIFICAÇÃO E CONTACTOS DO ÓRGÃO DE RECURSOS ADMINISTRATIVOS\nDesignação: Conselho de Administração da RTP\nEndereço: Av. Marechal Gomes da Costa, 37\nCódigo postal: 1849-030\nLocalidade: Lisboa\nTelefone: +351 217947000\nFax: +351 217947570\nEndereço eletrónico: compras@rtp.pt\n\n28 - IDENTIFICAÇÃO DO(S) AUTOR(ES) DE ANÚNCIO\nNome: Pedro Reis\nCargo: Diretor de Gestão de património\n419921995",
    "nipc": "500225680",
    "distrito": "Lisboa",
    "concelho": "Lisboa",
    "freguesia": "Todas",
    "site": "www.rpt.pt",
    "email": "dir.comercial@rtp.pt",
    "designacao_contrato": "CP 28/2025 - Aquisição de serviços de impressão, cópias e gestão documental",
    "descricao": "CP 28/2025 - Aquisição de serviços de impressão, cópias e gestão documental",
    "preco_base": "445.000,00 EUR",
    "prazo_execucao": "5 ANOS",
    "prazo_apresentacao_propostas": "26-01-2026 18:00",
    "fundos_eu": "Não",
    "plataforma_eletronica": "VORTAL",
    "url_procedimento": "https://community.vortal.biz/public/",
    "autor_nome": "Pedro Reis",
    "autor_cargo": "Diretor de Gestão de património"
  },
  {
    "numero_procedimento": "N/A",
    "entidade": "Entidade Nacional para o Setor Energético, EPE",
    "link": "https://diariodarepublica.pt/dr/detalhe/contrato-publico/33390-992674285",
    "detalhes_completos": "1 - IDENTIFICAÇÃO E CONTACTOS DA ENTIDADE ADJUDICANTE\nDesignação da entidade adjudicante: Entidade Nacional para o Setor Energético, EPE\nNIPC: 506084361\nEndereço: Estrada do Paço do Lumiar Campus Lumiar Edf. D 1.º\nCódigo postal: 1649-038\nLocalidade: Lisboa\nPaís: Portugal\nNUT III: PT170\nDistrito: Lisboa\nConcelho: Lisboa\nFreguesia: Freguesia de Lumiar\nTelefone: 213114140\nFax: 213114149\nEndereço da Entidade (URL): https://www.ense-epe.pt/\nEndereço Eletrónico: geral@ense-epe.pt\neDelivery Gateway (URL): https://community.vortal.biz/public/\nFunção da Organização: Adquirente\nNorma jurídica da Entidade Adjudicante: Organismo de direito público\nÁrea de atividade da Autoridade Adjudicante: Proteção ambiental\n\n2 - JORNAL OFICIAL DA UNIÃO EUROPEIA\nO procedimento a que este anúncio diz respeito também é publicitado no Jornal Oficial da União Europeia? Sim\n\n3 - AVISO\nModelo de Anúncio: Concurso público\nData de Envio do Anúncio: 22-12-2025\n\n5 - PROCESSO\nTipo de Procedimento: Concurso público\nPreço base do procedimento: Sim\nValor do preço base do procedimento: 769.900,00 EUR\nProcedimento com lotes? Não\n\n6 - OBJETO DO CONTRATO\nNúmero de referência interna: CPAQ 7/2025\nDesignação do contrato: Aquisição de Serviços de Vigilância e Segurança ENSE / DPNL\nDescrição: Aquisição de Serviços de Vigilância e Segurança ENSE / DPNL\nOpções: Não\nTipo de Contrato Principal: Aquisição de Serviços\nTipo de Contrato: Aquisição de Serviços\nClassificação CPV (Vocabulário Comum para os Contratos Públicos)\nObjeto principal\nVocabulário Principal: 79710000\nPreço base s/IVA: 769.900,00 EUR\n\n7 - INDICAÇÕES ADICIONAIS\nO contrato envolve aquisição conjunta (satisfação de várias entidades)? Não\nO contrato é adjudicado por uma central de compras? Não\n\n8 - TÉCNICAS\nO concurso destina-se à celebração de um acordo-quadro? Inexistência de acordo-quadro\nÉ utilizado um leilão eletrónico? Não\nÉ adotada uma fase de negociação? Não\nSistema de Aquisição Dinâmico: Inexistência de sistema de aquisição dinâmico\n\n9 - LOCAL DA EXECUÇÃO DO CONTRATO\nLOCAL DA EXECUÇÃO DO CONTRATO (PROCEDIMENTO)\nPaís: Portugal\nNUT III: PT170\nLocalidade: Setúbal\nDistrito: Setúbal\nConcelho: Almada\nFreguesia: União das Freguesias de Caparica e Trafaria\n\n10 - PRAZO DE EXECUÇÃO DO CONTRATO\nPrazo de execução do contrato: 3 ANOS\nPrevisão de renovações: Não\n\n11 - FUNDOS EU\nTêm fundos EU? Não\n\n12 - DOCUMENTOS DE HABILITAÇÃO\nHabilitação para o exercício da atividade profissional: Não\n\n13 - CONDIÇÕES DE APRESENTAÇÃO\nPlataforma eletrónica utilizada pela entidade adjudicante: VORTAL\nURL para Apresentação: https://community.vortal.biz/public/\nAdmissibilidade da apresentação de propostas variantes: Não autorizado\nPrazo para apresentação das propostas: 23-01-2026 23:59\nPrazo durante o qual os concorrentes são obrigados a manter as respetivas propostas: 120 dias a contar do termo do prazo para a apresentação das propostas\nApresentação de Catálogo Eletrónico: Permitido\nIndicação de Subcontratação na Proposta: Inexistência de indicação de subcontratação\n\n14 - PRESTAÇÃO DE CAUÇÃO\nPrestação de caução: Não\n\n15 - FORNECIMENTO DAS PEÇAS DO CONCURSO, APRESENTAÇÃO DE PEDIDOS DE PARTICIPAÇÃO E APRESENTAÇÃO DAS PROPOSTAS\nLink para acesso às peças do concurso (URL): https://community.vortal.biz/Public/public-tender-documents/eHc2Wm9RMmxvMm9mdEwvTEVSMDg2Z0NZaHFCMk1hTjRxTXJHODlKaTFnYkRqcDcwQXlKdnVTdGN4c2NCVjJKQ2tWenRrUTNtK05yVmlQWWJUcityNUE9PVlMaygp\n\n20 - OUTROS REQUISITOS\nInformação sobre contratos reservados. Aplica-se a contratos reservados (54º-A)? Não\n\n21 - CRITÉRIO DE ADJUDICAÇÃO\nMultifator: Sim\nFator: \nNome: Preço\nPonderação: 60%\nSubfatores: Não\nFator: \nNome: Outros\nOutro Nome: Experiência Recursos Humanos\nPonderação: 15%\nSubfatores: Não\nFator: \nNome: Outros\nOutro Nome: Plano De Segurança\nPonderação: 25%\nSubfatores: Não\n\n24 - CONDIÇÕES DO CONTRATO\nFaturação Eletrónica: Permitido\nObrigação de Subcontratação:\nCódigo da Obrigação de Subcontratação: Não é aplicável nenhuma obrigação de subcontratação.\n\n25 - COMPRA PÚBLICA ESTRATÉGICA\nCompra Pública Estratégica: Inexistência de contratação pública estratégica\n\n26 - INFORMAÇÕES ADICIONAIS\nContrato adequado para PME: Sim\nCobertura ACP (Acordo dos Contratos Públicos da Organização Mundial do Comércio): Não\n\n27 - IDENTIFICAÇÃO E CONTACTOS DO ÓRGÃO DE RECURSOS ADMINISTRATIVOS\nDesignação: Conselho de Administração\nEndereço: Estrada do Paço do Lumiar Campus do Lumiar, Edifício D - 1º Andar\nCódigo postal: 1649-038\nLocalidade: Lisboa\nTelefone: +351 213114140\nFax: +351 213114149\nEndereço eletrónico: ense@ense-epe.pt\n\n28 - IDENTIFICAÇÃO DO(S) AUTOR(ES) DE ANÚNCIO\nNome: ENSE\nCargo: Jusrista\n419921549",
    "nipc": "506084361",
    "distrito": "Lisboa",
    "concelho": "Lisboa",
    "freguesia": "Freguesia de Lumiar",
    "site": "https://www.ense-epe.pt/",
    "email": "geral@ense-epe.pt",
    "designacao_contrato": "Aquisição de Serviços de Vigilância e Segurança ENSE / DPNL",
    "descricao": "Aquisição de Serviços de Vigilância e Segurança ENSE / DPNL",
    "preco_base": "769.900,00 EUR",
    "prazo_execucao": "3 ANOS",
    "prazo_apresentacao_propostas": "23-01-2026 23:59",
    "fundos_eu": "Não",
    "plataforma_eletronica": "VORTAL",
    "url_procedimento": "https://community.vortal.biz/public/",
    "autor_nome": "ENSE",
    "autor_cargo": "Jusrista"
  },
  {
    "numero_procedimento": "N/A",
    "entidade": "Instituto da Conservação da Natureza e das Florestas, IP",
    "link": "https://diariodarepublica.pt/dr/detalhe/contrato-publico/33374-992674286",
    "detalhes_completos": "1 - IDENTIFICAÇÃO E CONTACTOS DA ENTIDADE ADJUDICANTE\nDesignação da entidade adjudicante: Instituto da Conservação da Natureza e das Florestas, IP\nNIPC: 510342647\nEndereço: Av. Dr. Alfredo Magalhães Ramalho, nº 1\nCódigo postal: 1495-165\nLocalidade: Lisboa\nPaís: Portugal\nNUT III: PT170\nDistrito: Lisboa\nConcelho: Oeiras\nFreguesia: União das Freguesias de Algés, Linda-a-Velha e Cruz Quebrada-Dafundo\nTelefone: 213124800\nFax: 213124800\nEndereço da Entidade (URL): https://www.icnf.pt/\nEndereço Eletrónico: geral@icnf.pt\neDelivery Gateway (URL): https://community.vortal.biz/public/\nFunção da Organização: Adquirente\nNorma jurídica da Entidade Adjudicante: Instituição, órgão ou agência da UE\nÁrea de atividade da Autoridade Adjudicante: Proteção ambiental\n\n2 - JORNAL OFICIAL DA UNIÃO EUROPEIA\nO procedimento a que este anúncio diz respeito também é publicitado no Jornal Oficial da União Europeia? Não\n\n3 - AVISO\nModelo de Anúncio: Concurso público urgente\nData de Envio do Anúncio: 24-12-2025 14:29:00\n\n5 - PROCESSO\nTipo de Procedimento: Concurso público\nPreço base do procedimento: Sim\nValor do preço base do procedimento: 194.295,04 EUR\nProcedimento com lotes? Não\n\n6 - OBJETO DO CONTRATO\nNúmero de referência interna: CP/49/2025/ICNF/SEDE\nDesignação do contrato: Aquisição combustíveis rodoviários\nDescrição: Aquisição de combustíveis rodoviários de 01.01 a 15.02.2026\nTipo de Contrato Principal: Aquisição de Bens Móveis\nTipo de Contrato: Aquisição de Bens Móveis\nClassificação CPV (Vocabulário Comum para os Contratos Públicos)\nObjeto principal\nVocabulário Principal: 09100000\nPreço base s/IVA: 194.295,04 EUR\n\n7 - INDICAÇÕES ADICIONAIS\nO contrato envolve aquisição conjunta (satisfação de várias entidades)? Não\nO contrato é adjudicado por uma central de compras? Não\n\n8 - TÉCNICAS\nO concurso destina-se à celebração de um acordo-quadro? Inexistência de acordo-quadro\nÉ utilizado um leilão eletrónico? Não\nÉ adotada uma fase de negociação? Não\nSistema de Aquisição Dinâmico: Inexistência de sistema de aquisição dinâmico\n\n9 - LOCAL DA EXECUÇÃO DO CONTRATO\nLOCAL DA EXECUÇÃO DO CONTRATO (PROCEDIMENTO)\nPaís: Portugal\nNUT III: PT170\nLocalidade: Lisboa\nDistrito: Lisboa\nConcelho: Lisboa\nFreguesia: Freguesia de Avenidas Novas\n\n10 - PRAZO DE EXECUÇÃO DO CONTRATO\nPrazo de execução do contrato: 46 DIAS\nPrevisão de renovações: Não\n\n11 - FUNDOS EU\nTêm fundos EU? Não\n\n12 - DOCUMENTOS DE HABILITAÇÃO\nHabilitação para o exercício da atividade profissional: Não\n\n13 - CONDIÇÕES DE APRESENTAÇÃO\nPlataforma eletrónica utilizada pela entidade adjudicante: VORTAL\nURL para Apresentação: https://community.vortal.biz/public/\nAdmissibilidade da apresentação de propostas variantes: Não autorizado\nPrazo para apresentação das propostas: 26-12-2025 23:59\nPrazo durante o qual os concorrentes são obrigados a manter as respetivas propostas: 10 dias a contar do termo do prazo para a apresentação das propostas\nIndicação de Subcontratação na Proposta: Inexistência de indicação de subcontratação\n\n14 - PRESTAÇÃO DE CAUÇÃO\nPrestação de caução: Não\n\n15 - FORNECIMENTO DAS PEÇAS DO CONCURSO, APRESENTAÇÃO DE PEDIDOS DE PARTICIPAÇÃO E APRESENTAÇÃO DAS PROPOSTAS\nLink para acesso às peças do concurso (URL): https://community.vortal.biz/Public/public-tender-documents/VS9RSWh5YjZUdnNidi8rMWU3bFQ5cGdhbGxRNnVGelNzTE1zc0JjV1ZEVkhHaU1xZVBWd1Vvb2JEWHdlUWhXSW16U3JSa01qMEVSV1FnZnVqTk12QWc9PVNSXmxY\n\n20 - OUTROS REQUISITOS\nInformação sobre contratos reservados. Aplica-se a contratos reservados (54º-A)? Não\n\n21 - CRITÉRIO DE ADJUDICAÇÃO\nMultifator: Não\nMonofator:\nNome: Preço\n\n24 - CONDIÇÕES DO CONTRATO\nFaturação Eletrónica: Permitido\nObrigação de Subcontratação:\nCódigo da Obrigação de Subcontratação: Não é aplicável nenhuma obrigação de subcontratação.\n\n25 - COMPRA PÚBLICA ESTRATÉGICA\nCompra Pública Estratégica: Inexistência de contratação pública estratégica\n\n26 - INFORMAÇÕES ADICIONAIS\nContrato adequado para PME: Sim\nCobertura ACP (Acordo dos Contratos Públicos da Organização Mundial do Comércio): Não\n\n27 - IDENTIFICAÇÃO E CONTACTOS DO ÓRGÃO DE RECURSOS ADMINISTRATIVOS\nDesignação: Conselho Diretivo do ICNF, IP\nEndereço: Av. Dr. Alfredo Magalhães Ramalho 1\nCódigo postal: 1495-165\nLocalidade: Oeiras\nTelefone: +351 213507900\nFax: +351 213507900\nEndereço eletrónico: geral@icnf.pt\n\n28 - IDENTIFICAÇÃO DO(S) AUTOR(ES) DE ANÚNCIO\nNome: Sónia Santos Moreira\nCargo: Chefe de Divisão\n419932151",
    "nipc": "510342647",
    "distrito": "Lisboa",
    "concelho": "Oeiras",
    "freguesia": "União das Freguesias de Algés, Linda-a-Velha e Cruz Quebrada-Dafundo",
    "site": "https://www.icnf.pt/",
    "email": "geral@icnf.pt",
    "designacao_contrato": "Aquisição combustíveis rodoviários",
    "descricao": "Aquisição de combustíveis rodoviários de 01.01 a 15.02.2026",
    "preco_base": "194.295,04 EUR",
    "prazo_execucao": "46 DIAS",
    "prazo_apresentacao_propostas": "26-12-2025 23:59",
    "fundos_eu": "Não",
    "plataforma_eletronica": "VORTAL",
    "url_procedimento": "https://community.vortal.biz/public/",
    "autor_nome": "Sónia Santos Moreira",
    "autor_cargo": "Chefe de Divisão"
  },
  {
    "numero_procedimento": "N/A",
    "entidade": "Secretaria-Geral do Ministério da Justiça",
    "link": "https://diariodarepublica.pt/dr/detalhe/contrato-publico/33395-992674287",
    "detalhes_completos": "1 - IDENTIFICAÇÃO E CONTACTOS DA ENTIDADE ADJUDICANTE\nDesignação da entidade adjudicante: Secretaria-Geral do Ministério da Justiça\nNIPC: 600017613\nEndereço: Rua do Ouro, nº 6\nCódigo postal: 1149-019\nLocalidade: Lisboa\nPaís: Portugal\nNUT III: PT170\nDistrito: Lisboa\nConcelho: Lisboa\nFreguesia: Todas\nTelefone: 213222300\nFax: 213423198\nEndereço da Entidade (URL): www.mj.gov.pt\nEndereço Eletrónico: correio@sg.mj.pt\neDelivery Gateway (URL): https://community.vortal.biz/public/\nFunção da Organização: Adquirente\nNorma jurídica da Entidade Adjudicante: Autoridade da administração central\nÁrea de atividade da Autoridade Adjudicante: Serviços públicos das administrações públicas\n\n2 - JORNAL OFICIAL DA UNIÃO EUROPEIA\nO procedimento a que este anúncio diz respeito também é publicitado no Jornal Oficial da União Europeia? Sim\n\n3 - AVISO\nModelo de Anúncio: Concurso público\nData de Envio do Anúncio: 22-12-2025\n\n5 - PROCESSO\nTipo de Procedimento: Concurso público\nPreço base do procedimento: Sim\nValor do preço base do procedimento: 1.008.988,00 EUR\nProcedimento com lotes? Não\n\n6 - OBJETO DO CONTRATO\nNúmero de referência interna: CPI 04/2025/eBUPi/SGMJ\nDesignação do contrato: Aquisição de serviços de implementação destinados a endereçar a manutenção e evolução da Plataforma BUPi\nDescrição: Aquisição de serviços de implementação destinados a endereçar a manutenção e evolução da Plataforma BUPi\nOpções: Não\nTipo de Contrato Principal: Aquisição de Serviços\nTipo de Contrato: Aquisição de Serviços\nClassificação CPV (Vocabulário Comum para os Contratos Públicos)\nObjeto principal\nVocabulário Principal: 72227000\nPreço base s/IVA: 1.008.988,00 EUR\n\n7 - INDICAÇÕES ADICIONAIS\nO contrato envolve aquisição conjunta (satisfação de várias entidades)? Não\nO contrato é adjudicado por uma central de compras? Não\n\n8 - TÉCNICAS\nO concurso destina-se à celebração de um acordo-quadro? Inexistência de acordo-quadro\nÉ utilizado um leilão eletrónico? Não\nÉ adotada uma fase de negociação? Não\nSistema de Aquisição Dinâmico: Inexistência de sistema de aquisição dinâmico\n\n9 - LOCAL DA EXECUÇÃO DO CONTRATO\nLOCAL DA EXECUÇÃO DO CONTRATO (PROCEDIMENTO)\nPaís: Portugal\nNUT III: PT170\nLocalidade: Lisboa\nDistrito: Lisboa\nConcelho: Lisboa\nFreguesia: Todas\n\n10 - PRAZO DE EXECUÇÃO DO CONTRATO\nPrazo de execução do contrato: 5 MESES\nPrevisão de renovações: Não\n\n11 - FUNDOS EU\nTêm fundos EU? Sim\n\n12 - DOCUMENTOS DE HABILITAÇÃO\nHabilitação para o exercício da atividade profissional: Não\n\n13 - CONDIÇÕES DE APRESENTAÇÃO\nPlataforma eletrónica utilizada pela entidade adjudicante: VORTAL\nURL para Apresentação: https://community.vortal.biz/public/\nAdmissibilidade da apresentação de propostas variantes: Não autorizado\nPrazo para apresentação das propostas: 21-01-2026 23:59\nPrazo durante o qual os concorrentes são obrigados a manter as respetivas propostas: 90 dias a contar do termo do prazo para a apresentação das propostas\nApresentação de Catálogo Eletrónico: Permitido\nIndicação de Subcontratação na Proposta: Inexistência de indicação de subcontratação\n\n14 - PRESTAÇÃO DE CAUÇÃO\nPrestação de caução: Sim\nPercentagem: 5%\nDescrição da Garantia Exigida: Artigo 22.º do PP\n\n15 - FORNECIMENTO DAS PEÇAS DO CONCURSO, APRESENTAÇÃO DE PEDIDOS DE PARTICIPAÇÃO E APRESENTAÇÃO DAS PROPOSTAS\nLink para acesso às peças do concurso (URL): https://community.vortal.biz/Public/public-tender-documents/eEEvazV6RDBwbHYvZVE0VnBpemNXa1Fpbys4MDgxeFd5Wm5sUmpDNWg1ZUxTSUIxWGtDUmhqWW1XMnNzWXpjZE9TcElMa0Y0UHUvOHJrMm5Mc1hqTHc9PSpVdjdK\n\n20 - OUTROS REQUISITOS\nInformação sobre contratos reservados. Aplica-se a contratos reservados (54º-A)? Não\n\n21 - CRITÉRIO DE ADJUDICAÇÃO\nMultifator: Sim\nFator: \nNome: Preço\nPonderação: 50%\nSubfatores: Não\nFator: \nNome: Qualidade\nPonderação: 50%\nSubfatores: Não\n\n24 - CONDIÇÕES DO CONTRATO\nFaturação Eletrónica: Permitido\nObrigação de Subcontratação:\nCódigo da Obrigação de Subcontratação: Não é aplicável nenhuma obrigação de subcontratação.\n\n25 - COMPRA PÚBLICA ESTRATÉGICA\nCompra Pública Estratégica: Inexistência de contratação pública estratégica\n\n26 - INFORMAÇÕES ADICIONAIS\nContrato adequado para PME: Sim\nCobertura ACP (Acordo dos Contratos Públicos da Organização Mundial do Comércio): Não\n\n27 - IDENTIFICAÇÃO E CONTACTOS DO ÓRGÃO DE RECURSOS ADMINISTRATIVOS\nDesignação: Secretaria-Geral do Ministério da Justiça\nEndereço: Rua do Ouro, 6\nCódigo postal: 1149-019\nLocalidade: Lisboa\nTelefone: +351 213222300\nFax: +351 213222300\nEndereço eletrónico: correio@sg.mj.pt\n\n28 - IDENTIFICAÇÃO DO(S) AUTOR(ES) DE ANÚNCIO\nNome: André Santos\nCargo: Técnico Especialista\n419922683",
    "nipc": "600017613",
    "distrito": "Lisboa",
    "concelho": "Lisboa",
    "freguesia": "Todas",
    "site": "www.mj.gov.pt",
    "email": "correio@sg.mj.pt",
    "designacao_contrato": "Aquisição de serviços de implementação destinados a endereçar a manutenção e evolução da Plataforma BUPi",
    "descricao": "Aquisição de serviços de implementação destinados a endereçar a manutenção e evolução da Plataforma BUPi",
    "preco_base": "1.008.988,00 EUR",
    "prazo_execucao": "5 MESES",
    "prazo_apresentacao_propostas": "21-01-2026 23:59",
    "fundos_eu": "Sim",
    "plataforma_eletronica": "VORTAL",
    "url_procedimento": "https://community.vortal.biz/public/",
    "autor_nome": "André Santos",
    "autor_cargo": "Técnico Especialista"
  },
  {
    "numero_procedimento": "N/A",
    "entidade": "Universidade do Porto",
    "link": "https://diariodarepublica.pt/dr/detalhe/contrato-publico/33396-992674288",
    "detalhes_completos": "1 - IDENTIFICAÇÃO E CONTACTOS DA ENTIDADE ADJUDICANTE\nDesignação da entidade adjudicante: Universidade do Porto\nNIPC: 501413197\nServiço/Órgão/Pessoa de contacto: Serviço de Compras e Gestão Contratual da U. Porto | Bruno Mateus\nEndereço: Praça Gomes Teixeira s/n\nCódigo postal: 4099-002\nLocalidade: Porto\nPaís: Portugal\nNUT III: PT11A\nDistrito: Porto\nConcelho: Porto\nFreguesia: União das Freguesias de Cedofeita, Santo Ildefonso, Sé, Miragaia, São Nicolau e Vitória\nTelefone: 220408000\nFax: 2204081867\nEndereço da Entidade (URL): www.reit.up.pt\nEndereço Eletrónico: reitoria@reit.up.pt\neDelivery Gateway (URL): https://www.acingov.pt\nFunção da Organização: Adquirente\nNorma jurídica da Entidade Adjudicante: Organismo de direito público\nÁrea de atividade da Autoridade Adjudicante: Educação\n\n2 - JORNAL OFICIAL DA UNIÃO EUROPEIA\nO procedimento a que este anúncio diz respeito também é publicitado no Jornal Oficial da União Europeia? Sim\n\n3 - AVISO\nModelo de Anúncio: Concurso público\nData de Envio do Anúncio: 22-12-2025\n\n5 - PROCESSO\nTipo de Procedimento: Concurso público\nPreço base do procedimento: Sim\nValor do preço base do procedimento: 382.705,98 EUR\nProcedimento com lotes? Sim\nNº Máx. de Lotes Autorizado: 9\nNúmero máximo de lotes que podem ser adjudicados a um concorrente: 9\n\n6 - OBJETO DO CONTRATO\nNúmero de referência interna: SCGC_REIT_CPI_00008_2025\nDesignação do contrato: Aquisição de mobiliário e sinalética para o Edifício Abel Salazar da U. Porto (Lotes)\nDescrição: Aquisição de mobiliário para a Residência Jayme Rios de Souza da U. Porto (Lotes) - PRR\nOpções: Não\nTipo de Contrato Principal: Aquisição de Bens Móveis\nTipo de Contrato: Aquisição de Bens Móveis\nClassificação CPV (Vocabulário Comum para os Contratos Públicos)\nObjeto principal\nVocabulário Principal: 39143110\nPreço base s/IVA: 382.705,98 EUR\nLotes: \nNº: LOT-0001\nDescrição do Lote: Mesas e armários\nPreço base s/IVA: 28.677,25 EUR\nClassificação CPV (Vocabulário Comum para os Contratos Públicos)\nObjeto principal\nVocabulário Principal: 39121000\nNº: LOT-0002\nDescrição do Lote: Cadeiras\nPreço base s/IVA: 47.931,52 EUR\nClassificação CPV (Vocabulário Comum para os Contratos Públicos)\nObjeto principal\nVocabulário Principal: 39112000\nNº: LOT-0003\nDescrição do Lote: Sofás\nPreço base s/IVA: 10.560,00 EUR\nClassificação CPV (Vocabulário Comum para os Contratos Públicos)\nObjeto principal\nVocabulário Principal: 39113200\nNº: LOT-0004\nDescrição do Lote: Cacifos e estantes\nPreço base s/IVA: 11.492,79 EUR\nClassificação CPV (Vocabulário Comum para os Contratos Públicos)\nObjeto principal\nVocabulário Principal: 39112000\nNº: LOT-0005\nDescrição do Lote: Camas e mobiliário de quartos\nPreço base s/IVA: 117.099,02 EUR\nClassificação CPV (Vocabulário Comum para os Contratos Públicos)\nObjeto principal\nVocabulário Principal: 39143110\nNº: LOT-0006\nDescrição do Lote: Complementos\nPreço base s/IVA: 51.511,80 EUR\nClassificação CPV (Vocabulário Comum para os Contratos Públicos)\nObjeto principal\nVocabulário Principal: 39150000\nNº: LOT-0007\nDescrição do Lote: Acessórios de desporto\nPreço base s/IVA: 2.000,00 EUR\nClassificação CPV (Vocabulário Comum para os Contratos Públicos)\nObjeto principal\nVocabulário Principal: 39150000\nNº: LOT-0008\nDescrição do Lote: Candeeiro de parede\nPreço base s/IVA: 29.702,40 EUR\nClassificação CPV (Vocabulário Comum para os Contratos Públicos)\nObjeto principal\nVocabulário Principal: 39150000\nNº: LOT-0009\nDescrição do Lote: Cortinas e estores\nPreço base s/IVA: 83.731,20 EUR\nClassificação CPV (Vocabulário Comum para os Contratos Públicos)\nObjeto principal\nVocabulário Principal: 39515400\n\n7 - INDICAÇÕES ADICIONAIS\nO contrato envolve aquisição conjunta (satisfação de várias entidades)? Não\nO contrato é adjudicado por uma central de compras? Não\n\n8 - TÉCNICAS\nO concurso destina-se à celebração de um acordo-quadro? Inexistência de acordo-quadro\nÉ utilizado um leilão eletrónico? Não\nÉ adotada uma fase de negociação? Não\nSistema de Aquisição Dinâmico: Inexistência de sistema de aquisição dinâmico\n\n9 - LOCAL DA EXECUÇÃO DO CONTRATO\nLOCAL DA EXECUÇÃO DO CONTRATO (PROCEDIMENTO)\nPaís: Portugal\nNUT III: PT11A\nLocalidade: Porto\nDistrito: Porto\nConcelho: Porto\nFreguesia: Todas\nLOCAL DA EXECUÇÃO DO CONTRATO (LOTE)\nIdentificador do Lote: LOT-0001; LOT-0002; LOT-0003; LOT-0004; LOT-0005; LOT-0006; LOT-0007; LOT-0008; LOT-0009\nPaís: Portugal\nNUT III: PT11A\nLocalidade: Porto\nDistrito: Porto\nConcelho: Porto\nFreguesia: Todas\n\n10 - PRAZO DE EXECUÇÃO DO CONTRATO\nIdentificador do Lote: LOT-0001; LOT-0002; LOT-0003; LOT-0004; LOT-0005; LOT-0006; LOT-0007; LOT-0008; LOT-0009\nData de Início: 16-04-2026\nData de Fim: 31-05-2026\nPrevisão de renovações: Não\n\n11 - FUNDOS EU\nIdentificador do Lote: LOT-0001; LOT-0002; LOT-0003; LOT-0004; LOT-0005; LOT-0006; LOT-0007; LOT-0008; LOT-0009\nTêm fundos EU? Sim\n\n12 - DOCUMENTOS DE HABILITAÇÃO\nHabilitação para o exercício da atividade profissional: Não\n\n13 - CONDIÇÕES DE APRESENTAÇÃO\nPlataforma eletrónica utilizada pela entidade adjudicante: ACIN\nURL para Apresentação: https://www.acingov.pt\nAdmissibilidade da apresentação de propostas variantes: Não autorizado\nPrazo para apresentação das propostas: 21-01-2026 23:59\nPrazo durante o qual os concorrentes são obrigados a manter as respetivas propostas: 66 dias a contar do termo do prazo para a apresentação das propostas\nApresentação de Catálogo Eletrónico: Permitido\nIndicação de Subcontratação na Proposta: Inexistência de indicação de subcontratação\n\n14 - PRESTAÇÃO DE CAUÇÃO\nPrestação de caução: Não\n\n15 - FORNECIMENTO DAS PEÇAS DO CONCURSO, APRESENTAÇÃO DE PEDIDOS DE PARTICIPAÇÃO E APRESENTAÇÃO DAS PROPOSTAS\nLink para acesso às peças do concurso (URL): https://www.acingov.pt/acingovprod/2/zonaPublica/zona_publica_c/donwloadProcedurePiece/MTAwODg1NA==\n\n20 - OUTROS REQUISITOS\nIdentificador do Lote: LOT-0001; LOT-0002; LOT-0003; LOT-0004; LOT-0005; LOT-0006; LOT-0007; LOT-0008; LOT-0009\nInformação sobre contratos reservados. Aplica-se a contratos reservados (54º-A)? Não\n\n21 - CRITÉRIO DE ADJUDICAÇÃO\nO Critério de adjudicação é diferenciado por lote? Não\nMultifator: Não\nMonofator:\nNome: Preço\n\n24 - CONDIÇÕES DO CONTRATO\nIdentificador do Lote: LOT-0001; LOT-0002; LOT-0003; LOT-0004; LOT-0005; LOT-0006; LOT-0007; LOT-0008; LOT-0009\nFaturação Eletrónica: Necessário\nObrigação de Subcontratação:\nCódigo da Obrigação de Subcontratação: Não é aplicável nenhuma obrigação de subcontratação.\n\n25 - COMPRA PÚBLICA ESTRATÉGICA\nCompra Pública Estratégica: Redução dos impactos ambientais\nDescrição do Processo de Adjudicação Estratégico: O cocontratante deve garantir as melhores práticas ambientais por forma a incluir as medidas necessárias a fim de assegurar a proteção do ar, da água, do solo, e de prevenir ou reduzir a poluição sonora, a produção de resíduos e o consumo energético, com o objetivo de alcançar um nível elevado de proteção do ambiente e minimizar os impactes ambientais. O cocontratante deve igualmente garantir o correto encaminhamento dos eventuais resíduos produzidos no decorrer da execução do contrato, respeitando as boas práticas ambientais previstas na legislação em vigor.\nCritérios de contratos Públicos Ecológicos: Outros critérios de contratação pública ecológica\nCategorias da estratégia nacional: Mobiliário\nContratos Públicos Ecológicos: A proteção e o restauro da biodiversidade e dos ecossistemas; A transição para uma economia circular; A adaptação às alterações climáticas; A mitigação das alterações climáticas; A prevenção e o controlo da poluição\nDiretiva Veículos Não Poluentes: Não\nCritério de Acessibilidade: Os critérios de acessibilidade para as pessoas com deficiência não estão incluídos porque o contrato não se destina a pessoas singulares\n\n26 - INFORMAÇÕES ADICIONAIS\nIdentificador do Lote: LOT-0001; LOT-0002; LOT-0003; LOT-0004; LOT-0005; LOT-0006; LOT-0007; LOT-0008; LOT-0009\nContrato adequado para PME: Sim\nCobertura ACP (Acordo dos Contratos Públicos da Organização Mundial do Comércio): Não\n\n27 - IDENTIFICAÇÃO E CONTACTOS DO ÓRGÃO DE RECURSOS ADMINISTRATIVOS\nDesignação: Reitor da Universidade do Porto\nEndereço: Praça Gomes Teixeira s/n\nCódigo postal: 4099-002\nLocalidade: Porto\nTelefone: 220408797\nFax: 220408797\nEndereço eletrónico: compras@sp.up.pt\nPrazo de interposição do recurso: 5 dias\n\n28 - IDENTIFICAÇÃO DO(S) AUTOR(ES) DE ANÚNCIO\nNome: Bruno André Mesquita da Silva Mateus\nCargo: Técnico Superior\n419921273",
    "nipc": "501413197",
    "distrito": "Porto",
    "concelho": "Porto",
    "freguesia": "União das Freguesias de Cedofeita, Santo Ildefonso, Sé, Miragaia, São Nicolau e Vitória",
    "site": "www.reit.up.pt",
    "email": "reitoria@reit.up.pt",
    "designacao_contrato": "Aquisição de mobiliário e sinalética para o Edifício Abel Salazar da U. Porto (Lotes)",
    "descricao": "Aquisição de mobiliário para a Residência Jayme Rios de Souza da U. Porto (Lotes) - PRR",
    "preco_base": "382.705,98 EUR",
    "prazo_execucao": null,
    "prazo_apresentacao_propostas": "21-01-2026 23:59",
    "fundos_eu": "Sim",
    "plataforma_eletronica": "ACIN",
    "url_procedimento": "https://www.acingov.pt",
    "autor_nome": "Bruno André Mesquita da Silva Mateus",
    "autor_cargo": "Técnico Superior"
  },
  {
    "numero_procedimento": "N/A",
    "entidade": "Guarda Nacional Republicana",
    "link": "https://diariodarepublica.pt/dr/detalhe/contrato-publico/33397-992674289",
    "detalhes_completos": "1 - IDENTIFICAÇÃO E CONTACTOS DA ENTIDADE ADJUDICANTE\nDesignação da entidade adjudicante: Guarda Nacional Republicana\nNIPC: 600008878\nEndereço: Lg. do Carmo - Convento do Carmo\nCódigo postal: 1200-092\nLocalidade: Lisboa\nPaís: Portugal\nNUT III: PT170\nDistrito: Lisboa\nConcelho: Lisboa\nFreguesia: Todas\nTelefone: 213217000\nFax: 213217328\nEndereço da Entidade (URL): www.gnr.pt\nEndereço Eletrónico: cari.drl.da@gnr.pt\neDelivery Gateway (URL): https://community.vortal.biz/public/\nFunção da Organização: Adquirente\nNorma jurídica da Entidade Adjudicante: Organismo de direito público\nÁrea de atividade da Autoridade Adjudicante: Segurança e ordem pública\n\n2 - JORNAL OFICIAL DA UNIÃO EUROPEIA\nO procedimento a que este anúncio diz respeito também é publicitado no Jornal Oficial da União Europeia? Sim\n\n3 - AVISO\nModelo de Anúncio: Concurso público\nData de Envio do Anúncio: 22-12-2025\n\n5 - PROCESSO\nTipo de Procedimento: Concurso público\nPreço base do procedimento: Sim\nValor do preço base do procedimento: 267.550,00 EUR\nProcedimento com lotes? Não\n\n6 - OBJETO DO CONTRATO\nNúmero de referência interna: CP n.º 30/DRL/DA/2025\nDesignação do contrato: Aquisição de Um Sistema Backoffice Centralizado de Gestão de Cinemómetros\nDescrição: CP n.º 30/DRL/DA/2025 - Aquisição de Um Sistema Backoffice Centralizado de Gestão de Cinemómetros\nOpções: Não\nTipo de Contrato Principal: Aquisição de Serviços\nTipo de Contrato: Aquisição de Serviços\nClassificação CPV (Vocabulário Comum para os Contratos Públicos)\nObjeto principal\nVocabulário Principal: 72310000\nPreço base s/IVA: 267.550,00 EUR\n\n7 - INDICAÇÕES ADICIONAIS\nO contrato envolve aquisição conjunta (satisfação de várias entidades)? Não\nO contrato é adjudicado por uma central de compras? Não\n\n8 - TÉCNICAS\nO concurso destina-se à celebração de um acordo-quadro? Inexistência de acordo-quadro\nÉ utilizado um leilão eletrónico? Não\nÉ adotada uma fase de negociação? Não\nSistema de Aquisição Dinâmico: Inexistência de sistema de aquisição dinâmico\n\n9 - LOCAL DA EXECUÇÃO DO CONTRATO\nLOCAL DA EXECUÇÃO DO CONTRATO (PROCEDIMENTO)\nPaís: Portugal\nNUT III: PT170\nLocalidade: Lisboa\nDistrito: Lisboa\nConcelho: Lisboa\nFreguesia: Freguesia de Santa Maria Maior - Lisboa\n\n10 - PRAZO DE EXECUÇÃO DO CONTRATO\nPrazo de execução do contrato: 2 ANOS\nPrevisão de renovações: Não\n\n11 - FUNDOS EU\nTêm fundos EU? Não\n\n12 - DOCUMENTOS DE HABILITAÇÃO\nHabilitação para o exercício da atividade profissional: Sim\nTipo: Outros\nDescrição - Outros: BT-0015(d)-Procedure\nDescrição: Documentos conforme especificados nas peças procedimentais.\n\n13 - CONDIÇÕES DE APRESENTAÇÃO\nPlataforma eletrónica utilizada pela entidade adjudicante: VORTAL\nURL para Apresentação: https://community.vortal.biz/public/\nAdmissibilidade da apresentação de propostas variantes: Não autorizado\nPrazo para apresentação das propostas: 21-01-2026 23:59\nPrazo durante o qual os concorrentes são obrigados a manter as respetivas propostas: 180 dias a contar do termo do prazo para a apresentação das propostas\nApresentação de Catálogo Eletrónico: Permitido\nIndicação de Subcontratação na Proposta: Inexistência de indicação de subcontratação\n\n14 - PRESTAÇÃO DE CAUÇÃO\nPrestação de caução: Não\n\n15 - FORNECIMENTO DAS PEÇAS DO CONCURSO, APRESENTAÇÃO DE PEDIDOS DE PARTICIPAÇÃO E APRESENTAÇÃO DAS PROPOSTAS\nLink para acesso às peças do concurso (URL): https://community.vortal.biz/Public/public-tender-documents/QXZHMjV5ODRQWkpYQ2FHd2Z4UXlKK241N2JrSkUyckVWZmdnL25rUVlpNkNQVWNjT0t6dFhGMHd6WEdxcE4yWXU4dEx5d0pKWDNsYXNpenBudHJDS2c9PXAxMUdA\n\n20 - OUTROS REQUISITOS\nInformação sobre contratos reservados. Aplica-se a contratos reservados (54º-A)? Não\n\n21 - CRITÉRIO DE ADJUDICAÇÃO\nMultifator: Sim\nFator: \nNome: Preço\nPonderação: 30%\nSubfatores: Não\nFator: \nNome: Outros\nOutro Nome: Pontuação Fator Quantidade\nPonderação: 70%\nSubfatores: Não\n\n24 - CONDIÇÕES DO CONTRATO\nFaturação Eletrónica: Permitido\nObrigação de Subcontratação:\nCódigo da Obrigação de Subcontratação: Não é aplicável nenhuma obrigação de subcontratação.\n\n25 - COMPRA PÚBLICA ESTRATÉGICA\nCompra Pública Estratégica: Inexistência de contratação pública estratégica\n\n26 - INFORMAÇÕES ADICIONAIS\nContrato adequado para PME: Sim\nCobertura ACP (Acordo dos Contratos Públicos da Organização Mundial do Comércio): Não\n\n27 - IDENTIFICAÇÃO E CONTACTOS DO ÓRGÃO DE RECURSOS ADMINISTRATIVOS\nDesignação: Tenente-General Comandante-Geral da Guarda Nacional Republicana\nEndereço: Largo do Carmo\nCódigo postal: 1200-092\nLocalidade: Lisboa\nTelefone: +351 213217000\nFax: +351 213474819\nEndereço eletrónico: cg.gabcg@gnr.pt\n\n28 - IDENTIFICAÇÃO DO(S) AUTOR(ES) DE ANÚNCIO\nNome: Miguel Ângelo Reis Alves Amorim\nCargo: Diretor da Direção de Recursos Logísticos da Guarda Nacional Republicana\n419921938",
    "nipc": "600008878",
    "distrito": "Lisboa",
    "concelho": "Lisboa",
    "freguesia": "Todas",
    "site": "www.gnr.pt",
    "email": "cari.drl.da@gnr.pt",
    "designacao_contrato": "Aquisição de Um Sistema Backoffice Centralizado de Gestão de Cinemómetros",
    "descricao": "CP n.º 30/DRL/DA/2025 - Aquisição de Um Sistema Backoffice Centralizado de Gestão de Cinemómetros",
    "preco_base": "267.550,00 EUR",
    "prazo_execucao": "2 ANOS",
    "prazo_apresentacao_propostas": "21-01-2026 23:59",
    "fundos_eu": "Não",
    "plataforma_eletronica": "VORTAL",
    "url_procedimento": "https://community.vortal.biz/public/",
    "autor_nome": "Miguel Ângelo Reis Alves Amorim",
    "autor_cargo": "Diretor da Direção de Recursos Logísticos da Guarda Nacional Republicana"
  },
  {
    "numero_procedimento": "N/A",
    "entidade": "Unidade Local de Saúde de Lisboa Ocidental, EPE",
    "link": "https://diariodarepublica.pt/dr/detalhe/contrato-publico/33398-992674290",
    "detalhes_completos": "1 - IDENTIFICAÇÃO E CONTACTOS DA ENTIDADE ADJUDICANTE\nDesignação da entidade adjudicante: Unidade Local de Saúde de Lisboa Ocidental, EPE\nNIPC: 507618319\nEndereço: Santa Maria de Belém  Estrada do Forte do Alto do Duque\nCódigo postal: 1449-005\nLocalidade: Lisboa\nPaís: Portugal\nNUT III: PT170\nDistrito: Lisboa\nConcelho: Lisboa\nFreguesia: Todas\nTelefone: 210431000\nFax: 210431642\nEndereço da Entidade (URL): www.chlo.min-saude.pt/\nEndereço Eletrónico: comprasgeral@ulslo.min-saude.pt\neDelivery Gateway (URL): https://community.vortal.biz/public/\nFunção da Organização: Adquirente\nNorma jurídica da Entidade Adjudicante: Organismo de direito público\nÁrea de atividade da Autoridade Adjudicante: Saúde\n\n2 - JORNAL OFICIAL DA UNIÃO EUROPEIA\nO procedimento a que este anúncio diz respeito também é publicitado no Jornal Oficial da União Europeia? Sim\n\n3 - AVISO\nModelo de Anúncio: Concurso público\nData de Envio do Anúncio: 22-12-2025\n\n5 - PROCESSO\nTipo de Procedimento: Concurso público\nPreço base do procedimento: Sim\nValor do preço base do procedimento: 381.063,55 EUR\nProcedimento com lotes? Sim\nNº Máx. de Lotes Autorizado: 2\nNúmero máximo de lotes que podem ser adjudicados a um concorrente: 2\n\n6 - OBJETO DO CONTRATO\nNúmero de referência interna: 147000426 - MCDT área TAC\nDesignação do contrato: PRESTAÇÃO DE SERVIÇOS DE REALIZAÇÃO DE MEIOS COMPLEMENTARES DE DIAGNÓSTICO E TERAPÊUTICA, EM TAC, A UTENTES DA UNIDADE LOCAL DE SAÚDE DE LISBOA OCIDENTAL, E.P.E. PARA O ANO DE 2026\nDescrição: PRESTAÇÃO DE SERVIÇOS DE REALIZAÇÃO DE MEIOS COMPLEMENTARES DE DIAGNÓSTICO E TERAPÊUTICA, EM TAC, A UTENTES DA UNIDADE LOCAL DE SAÚDE DE LISBOA OCIDENTAL, E.P.E. PARA O ANO DE 2026\nOpções: Não\nTipo de Contrato Principal: Aquisição de Serviços\nTipo de Contrato: Aquisição de Serviços\nClassificação CPV (Vocabulário Comum para os Contratos Públicos)\nObjeto principal\nVocabulário Principal: 85150000\nPreço base s/IVA: 381.063,55 EUR\nLotes: \nNº: LOT-0001\nDescrição do Lote: Lote 1\nPreço base s/IVA: 6.604,80 EUR\nClassificação CPV (Vocabulário Comum para os Contratos Públicos)\nObjeto principal\nVocabulário Principal: 85150000\nNº: LOT-0002\nDescrição do Lote: Lote 2\nPreço base s/IVA: 374.458,75 EUR\nClassificação CPV (Vocabulário Comum para os Contratos Públicos)\nObjeto principal\nVocabulário Principal: 85150000\n\n7 - INDICAÇÕES ADICIONAIS\nO contrato envolve aquisição conjunta (satisfação de várias entidades)? Não\nO contrato é adjudicado por uma central de compras? Não\n\n8 - TÉCNICAS\nO concurso destina-se à celebração de um acordo-quadro? Inexistência de acordo-quadro\nÉ utilizado um leilão eletrónico? Não\nÉ adotada uma fase de negociação? Não\nSistema de Aquisição Dinâmico: Inexistência de sistema de aquisição dinâmico\n\n9 - LOCAL DA EXECUÇÃO DO CONTRATO\nLOCAL DA EXECUÇÃO DO CONTRATO (PROCEDIMENTO)\nPaís: Portugal\nNUT III: PT170\nLocalidade: Lisboa\nDistrito: Lisboa\nConcelho: Lisboa\nFreguesia: Todas\nLOCAL DA EXECUÇÃO DO CONTRATO (LOTE)\nIdentificador do Lote: LOT-0001; LOT-0002\nPaís: Portugal\nNUT III: PT170\nLocalidade: Lisboa\nDistrito: Lisboa\nConcelho: Lisboa\nFreguesia: Todas\n\n10 - PRAZO DE EXECUÇÃO DO CONTRATO\nIdentificador do Lote: LOT-0001; LOT-0002\nPrazo de execução do contrato: 12 MESES\nPrevisão de renovações: Não\n\n11 - FUNDOS EU\nIdentificador do Lote: LOT-0001; LOT-0002\nTêm fundos EU? Não\n\n12 - DOCUMENTOS DE HABILITAÇÃO\nHabilitação para o exercício da atividade profissional: Não\n\n13 - CONDIÇÕES DE APRESENTAÇÃO\nPlataforma eletrónica utilizada pela entidade adjudicante: VORTAL\nURL para Apresentação: https://community.vortal.biz/public/\nAdmissibilidade da apresentação de propostas variantes: Não autorizado\nPrazo para apresentação das propostas: 26-01-2026 17:00\nPrazo durante o qual os concorrentes são obrigados a manter as respetivas propostas: 120 dias a contar do termo do prazo para a apresentação das propostas\nApresentação de Catálogo Eletrónico: Não autorizado\nIndicação de Subcontratação na Proposta: Inexistência de indicação de subcontratação\n\n14 - PRESTAÇÃO DE CAUÇÃO\nPrestação de caução: Não\n\n15 - FORNECIMENTO DAS PEÇAS DO CONCURSO, APRESENTAÇÃO DE PEDIDOS DE PARTICIPAÇÃO E APRESENTAÇÃO DAS PROPOSTAS\nLink para acesso às peças do concurso (URL): https://community.vortal.biz/Public/public-tender-documents/N1VxdTZ1aGx4RS9ZeUYzRS9GK3R3aUFLeWxhN0Z5dkNFc2dCRjBKa1JDYW9ydk9Udmp0bnVMQktrcjdMUDdlMUltVThGb1pac0w5QWRCUEpYdWhKa0E9PUZPbnFW\n\n20 - OUTROS REQUISITOS\nIdentificador do Lote: LOT-0001; LOT-0002\nInformação sobre contratos reservados. Aplica-se a contratos reservados (54º-A)? Não\n\n21 - CRITÉRIO DE ADJUDICAÇÃO\nO Critério de adjudicação é diferenciado por lote? Não\nMultifator: Não\nMonofator:\nNome: Outros\nOutro nome: Preço\n\n24 - CONDIÇÕES DO CONTRATO\nIdentificador do Lote: LOT-0001; LOT-0002\nFaturação Eletrónica: Permitido\nObrigação de Subcontratação:\nCódigo da Obrigação de Subcontratação: Não é aplicável nenhuma obrigação de subcontratação.\n\n25 - COMPRA PÚBLICA ESTRATÉGICA\nCompra Pública Estratégica: Inexistência de contratação pública estratégica\n\n26 - INFORMAÇÕES ADICIONAIS\nIdentificador do Lote: LOT-0001; LOT-0002\nContrato adequado para PME: Sim\nCobertura ACP (Acordo dos Contratos Públicos da Organização Mundial do Comércio): Não\n\n27 - IDENTIFICAÇÃO E CONTACTOS DO ÓRGÃO DE RECURSOS ADMINISTRATIVOS\nDesignação: Conselho de Administração\nEndereço: Estrada do alto do forte do duque\nCódigo postal: 1449-005\nLocalidade: Lisboa\nTelefone: +351 210431000\nFax: +351 210431639\nEndereço eletrónico: compras.adm.hot.ps.inv@ulslo.min-saude.pt\n\n28 - IDENTIFICAÇÃO DO(S) AUTOR(ES) DE ANÚNCIO\nNome: Eduardo Neves\nCargo: Assistente Técnico\n419916851",
    "nipc": "507618319",
    "distrito": "Lisboa",
    "concelho": "Lisboa",
    "freguesia": "Todas",
    "site": "www.chlo.min-saude.pt/",
    "email": "comprasgeral@ulslo.min-saude.pt",
    "designacao_contrato": "PRESTAÇÃO DE SERVIÇOS DE REALIZAÇÃO DE MEIOS COMPLEMENTARES DE DIAGNÓSTICO E TERAPÊUTICA, EM TAC, A UTENTES DA UNIDADE LOCAL DE SAÚDE DE LISBOA OCIDENTAL, E.P.E. PARA O ANO DE 2026",
    "descricao": "PRESTAÇÃO DE SERVIÇOS DE REALIZAÇÃO DE MEIOS COMPLEMENTARES DE DIAGNÓSTICO E TERAPÊUTICA, EM TAC, A UTENTES DA UNIDADE LOCAL DE SAÚDE DE LISBOA OCIDENTAL, E.P.E. PARA O ANO DE 2026",
    "preco_base": "381.063,55 EUR",
    "prazo_execucao": "12 MESES",
    "prazo_apresentacao_propostas": "26-01-2026 17:00",
    "fundos_eu": "Não",
    "plataforma_eletronica": "VORTAL",
    "url_procedimento": "https://community.vortal.biz/public/",
    "autor_nome": "Eduardo Neves",
    "autor_cargo": "Assistente Técnico"
  },
  {
    "numero_procedimento": "N/A",
    "entidade": "Unidade Local de Saúde de Santa Maria, EPE",
    "link": "https://diariodarepublica.pt/dr/detalhe/contrato-publico/33399-992674291",
    "detalhes_completos": "1 - IDENTIFICAÇÃO E CONTACTOS DA ENTIDADE ADJUDICANTE\nDesignação da entidade adjudicante: Unidade Local de Saúde de Santa Maria, EPE\nNIPC: 508481287\nEndereço: Avenida Prof. Egas Moniz\nCódigo postal: 1649-035\nLocalidade: Lisboa\nPaís: Portugal\nNUT III: PT170\nDistrito: Lisboa\nConcelho: Lisboa\nFreguesia: Freguesia de Alvalade - Lisboa\nTelefone: 217805330\nFax: 217805605\nEndereço da Entidade (URL): www.ulssm.min-saude.pt\nEndereço Eletrónico: compras@ulssm.min-saude.pt\neDelivery Gateway (URL): https://community.vortal.biz/public/\nFunção da Organização: Adquirente\nNorma jurídica da Entidade Adjudicante: Empresa pública\nÁrea de atividade da Autoridade Adjudicante: Saúde\n\n2 - JORNAL OFICIAL DA UNIÃO EUROPEIA\nO procedimento a que este anúncio diz respeito também é publicitado no Jornal Oficial da União Europeia? Sim\n\n3 - AVISO\nModelo de Anúncio: Concurso público\nData de Envio do Anúncio: 22-12-2025\n\n5 - PROCESSO\nTipo de Procedimento: Concurso público\nPreço base do procedimento: Sim\nValor do preço base do procedimento: 255.544,00 EUR\nProcedimento com lotes? Sim\nNº Máx. de Lotes Autorizado: 11\nNúmero máximo de lotes que podem ser adjudicados a um concorrente: 11\n\n6 - OBJETO DO CONTRATO\nNúmero de referência interna: 262A000137\nDesignação do contrato: 262A000137 - Aquisição de Cateteres para o Serviço de Cardiologia, durante o ano 2026\nDescrição: Cateteres para o Serviço de Cardiologia\nOpções: Não\nTipo de Contrato Principal: Aquisição de Bens Móveis\nTipo de Contrato: Aquisição de Bens Móveis\nClassificação CPV (Vocabulário Comum para os Contratos Públicos)\nObjeto principal\nVocabulário Principal: 33190000\nPreço base s/IVA: 255.544,00 EUR\nLotes: \nNº: LOT-0001\nDescrição do Lote: Lote 1\nPreço base s/IVA: 204,00 EUR\nClassificação CPV (Vocabulário Comum para os Contratos Públicos)\nObjeto principal\nVocabulário Principal: 33190000\nNº: LOT-0002\nDescrição do Lote: Lote 2\nPreço base s/IVA: 64.740,00 EUR\nClassificação CPV (Vocabulário Comum para os Contratos Públicos)\nObjeto principal\nVocabulário Principal: 33190000\nNº: LOT-0003\nDescrição do Lote: Lote 3\nPreço base s/IVA: 14.378,00 EUR\nClassificação CPV (Vocabulário Comum para os Contratos Públicos)\nObjeto principal\nVocabulário Principal: 33190000\nNº: LOT-0004\nDescrição do Lote: Lote 4\nPreço base s/IVA: 3.600,00 EUR\nClassificação CPV (Vocabulário Comum para os Contratos Públicos)\nObjeto principal\nVocabulário Principal: 33190000\nNº: LOT-0005\nDescrição do Lote: Lote 5\nPreço base s/IVA: 33.932,00 EUR\nClassificação CPV (Vocabulário Comum para os Contratos Públicos)\nObjeto principal\nVocabulário Principal: 33190000\nNº: LOT-0006\nDescrição do Lote: Lote 6\nPreço base s/IVA: 1.292,00 EUR\nClassificação CPV (Vocabulário Comum para os Contratos Públicos)\nObjeto principal\nVocabulário Principal: 33190000\nNº: LOT-0007\nDescrição do Lote: Lote 7\nPreço base s/IVA: 85.725,00 EUR\nClassificação CPV (Vocabulário Comum para os Contratos Públicos)\nObjeto principal\nVocabulário Principal: 33190000\nNº: LOT-0008\nDescrição do Lote: Lote 8\nPreço base s/IVA: 440,00 EUR\nClassificação CPV (Vocabulário Comum para os Contratos Públicos)\nObjeto principal\nVocabulário Principal: 33190000\nNº: LOT-0009\nDescrição do Lote: Lote 9\nPreço base s/IVA: 8.025,00 EUR\nClassificação CPV (Vocabulário Comum para os Contratos Públicos)\nObjeto principal\nVocabulário Principal: 33190000\nNº: LOT-0010\nDescrição do Lote: Lote 10\nPreço base s/IVA: 14.858,00 EUR\nClassificação CPV (Vocabulário Comum para os Contratos Públicos)\nObjeto principal\nVocabulário Principal: 33190000\nNº: LOT-0011\nDescrição do Lote: Lote 11\nPreço base s/IVA: 28.350,00 EUR\nClassificação CPV (Vocabulário Comum para os Contratos Públicos)\nObjeto principal\nVocabulário Principal: 33190000\n\n7 - INDICAÇÕES ADICIONAIS\nO contrato envolve aquisição conjunta (satisfação de várias entidades)? Não\nO contrato é adjudicado por uma central de compras? Não\n\n8 - TÉCNICAS\nO concurso destina-se à celebração de um acordo-quadro? Inexistência de acordo-quadro\nÉ utilizado um leilão eletrónico? Não\nÉ adotada uma fase de negociação? Não\nSistema de Aquisição Dinâmico: Inexistência de sistema de aquisição dinâmico\n\n9 - LOCAL DA EXECUÇÃO DO CONTRATO\nLOCAL DA EXECUÇÃO DO CONTRATO (PROCEDIMENTO)\nPaís: Portugal\nNUT III: PT170\nLocalidade: Lisboa\nDistrito: Lisboa\nConcelho: Lisboa\nFreguesia: Freguesia de Alvalade - Lisboa\nLOCAL DA EXECUÇÃO DO CONTRATO (LOTE)\nIdentificador do Lote: LOT-0001; LOT-0002; LOT-0003; LOT-0004; LOT-0005; LOT-0006; LOT-0007; LOT-0008; LOT-0009; LOT-0010; LOT-0011\nPaís: Portugal\nNUT III: PT170\nLocalidade: Lisboa\nDistrito: Lisboa\nConcelho: Lisboa\nFreguesia: Freguesia de Alvalade - Lisboa\n\n10 - PRAZO DE EXECUÇÃO DO CONTRATO\nIdentificador do Lote: LOT-0001; LOT-0002; LOT-0003; LOT-0004; LOT-0005; LOT-0006; LOT-0007; LOT-0008; LOT-0009; LOT-0010; LOT-0011\nPrazo de execução do contrato: 12 MESES\nPrevisão de renovações: Não\n\n11 - FUNDOS EU\nIdentificador do Lote: LOT-0001; LOT-0002; LOT-0003; LOT-0004; LOT-0005; LOT-0006; LOT-0007; LOT-0008; LOT-0009; LOT-0010; LOT-0011\nTêm fundos EU? Não\n\n12 - DOCUMENTOS DE HABILITAÇÃO\nHabilitação para o exercício da atividade profissional: Não\n\n13 - CONDIÇÕES DE APRESENTAÇÃO\nPlataforma eletrónica utilizada pela entidade adjudicante: VORTAL\nURL para Apresentação: https://community.vortal.biz/public/\nAdmissibilidade da apresentação de propostas variantes: Não autorizado\nPrazo para apresentação das propostas: 21-01-2026 23:59\nPrazo durante o qual os concorrentes são obrigados a manter as respetivas propostas: 66 dias a contar do termo do prazo para a apresentação das propostas\nApresentação de Catálogo Eletrónico: Permitido\nIndicação de Subcontratação na Proposta: Inexistência de indicação de subcontratação\n\n14 - PRESTAÇÃO DE CAUÇÃO\nPrestação de caução: Não\n\n15 - FORNECIMENTO DAS PEÇAS DO CONCURSO, APRESENTAÇÃO DE PEDIDOS DE PARTICIPAÇÃO E APRESENTAÇÃO DAS PROPOSTAS\nLink para acesso às peças do concurso (URL): https://community.vortal.biz/Public/public-tender-documents/M0pHbTE4WENlSm8vcTNwekxYcGQ0amZsRjI3WDdqLzJNcWkra1NneFpER212dndhb3AzVUZVYmRDcXArS2Q4R2FvbnNrWU5JWGlEZVBZU25IU0pSY3c9PVJHQ2dF\n\n20 - OUTROS REQUISITOS\nIdentificador do Lote: LOT-0001; LOT-0002; LOT-0003; LOT-0004; LOT-0005; LOT-0006; LOT-0007; LOT-0008; LOT-0009; LOT-0010; LOT-0011\nInformação sobre contratos reservados. Aplica-se a contratos reservados (54º-A)? Não\n\n21 - CRITÉRIO DE ADJUDICAÇÃO\nO Critério de adjudicação é diferenciado por lote? Não\nMultifator: Não\nMonofator:\nNome: Preço\n\n24 - CONDIÇÕES DO CONTRATO\nIdentificador do Lote: LOT-0001; LOT-0002; LOT-0003; LOT-0004; LOT-0005; LOT-0006; LOT-0007; LOT-0008; LOT-0009; LOT-0010; LOT-0011\nFaturação Eletrónica: Permitido\nObrigação de Subcontratação:\nCódigo da Obrigação de Subcontratação: Não é aplicável nenhuma obrigação de subcontratação.\n\n25 - COMPRA PÚBLICA ESTRATÉGICA\nCompra Pública Estratégica: Inexistência de contratação pública estratégica\n\n26 - INFORMAÇÕES ADICIONAIS\nIdentificador do Lote: LOT-0001; LOT-0002; LOT-0003; LOT-0004; LOT-0005; LOT-0006; LOT-0007; LOT-0008; LOT-0009; LOT-0010; LOT-0011\nContrato adequado para PME: Sim\nCobertura ACP (Acordo dos Contratos Públicos da Organização Mundial do Comércio): Não\n\n27 - IDENTIFICAÇÃO E CONTACTOS DO ÓRGÃO DE RECURSOS ADMINISTRATIVOS\nDesignação: Conselho de Administração\nEndereço: Av. Prof. Egas Moniz\nCódigo postal: 1649-035\nLocalidade: Lisboa\nTelefone: +351 217805330\nFax: +351 217805330\nEndereço eletrónico: secretariado.ca@ulssm.min-saude.pt\n\n28 - IDENTIFICAÇÃO DO(S) AUTOR(ES) DE ANÚNCIO\nNome: Conceição Conde\nCargo: Ass. técnica\n419920382",
    "nipc": "508481287",
    "distrito": "Lisboa",
    "concelho": "Lisboa",
    "freguesia": "Freguesia de Alvalade - Lisboa",
    "site": "www.ulssm.min-saude.pt",
    "email": "compras@ulssm.min-saude.pt",
    "designacao_contrato": "262A000137 - Aquisição de Cateteres para o Serviço de Cardiologia, durante o ano 2026",
    "descricao": "Cateteres para o Serviço de Cardiologia",
    "preco_base": "255.544,00 EUR",
    "prazo_execucao": "12 MESES",
    "prazo_apresentacao_propostas": "21-01-2026 23:59",
    "fundos_eu": "Não",
    "plataforma_eletronica": "VORTAL",
    "url_procedimento": "https://community.vortal.biz/public/",
    "autor_nome": "Conceição Conde",
    "autor_cargo": "Ass. técnica"
  },
  {
    "numero_procedimento": "N/A",
    "entidade": "INSTICOOP - Instituto Internacional Cooperativo de Formação Profissional, CRL",
    "link": "https://diariodarepublica.pt/dr/detalhe/contrato-publico/33404-992674292",
    "detalhes_completos": "1 - IDENTIFICAÇÃO E CONTACTOS DA ENTIDADE ADJUDICANTE\nDesignação da entidade adjudicante: INSTICOOP - Instituto Internacional Cooperativo de Formação Profissional, CRL\nNIPC: 509082629\nEndereço: Rua da Escola, nº 32\nCódigo postal: 4600-789\nLocalidade: Porto\nPaís: Portugal\nNUT III: PT11C\nDistrito: Porto\nConcelho: Amarante\nFreguesia: Freguesia de Vila Caiz\nTelefone: +351 255098383\nEndereço da Entidade (URL): https://epalc.pt/\nEndereço Eletrónico: estudoseprojectos.insticoop@gmail.com\neDelivery Gateway (URL): https://community.vortal.biz/public/\nFunção da Organização: Adquirente\nNorma jurídica da Entidade Adjudicante: Organismo de direito público\nÁrea de atividade da Autoridade Adjudicante: Educação\n\n2 - JORNAL OFICIAL DA UNIÃO EUROPEIA\nO procedimento a que este anúncio diz respeito também é publicitado no Jornal Oficial da União Europeia? Sim\n\n3 - AVISO\nModelo de Anúncio: Concurso público\nData de Envio do Anúncio: 22-12-2025\n\n5 - PROCESSO\nTipo de Procedimento: Concurso público\nPreço base do procedimento: Sim\nValor do preço base do procedimento: 1.025.000,00 EUR\nProcedimento com lotes? Sim\nNº Máx. de Lotes Autorizado: 2\nNúmero máximo de lotes que podem ser adjudicados a um concorrente: 2\n\n6 - OBJETO DO CONTRATO\nNúmero de referência interna: CPI_Nº 01_25\nDesignação do contrato: Aquisição de infraestrutura tecnológica, equipamentos e mobiliário destinados à prática educativa e formativa no Centro Tecnológico Especializado em Energias renováveis \nDescrição: Aquisição de infraestrutura tecnológica, equipamentos e mobiliário destinados »a prática educativa e formativa no Centro Tecnológico Especializado de Energias Renováveis - Componente 6 \"Qualificações e Competências\" do Plano de Recuperação e Resiliência (PRR), aprovado pela Decisão de Execução do Conselho da União Europeia de 16 de junho de 2021, previsto no investimento RE-C06-i01: Modernização da oferta e dos Estabelecimentos de ensino e da formação profissional               \nOpções: Não\nTipo de Contrato Principal: Aquisição de Bens Móveis\nTipo de Contrato: Aquisição de Bens Móveis\nClassificação CPV (Vocabulário Comum para os Contratos Públicos)\nObjeto principal\nVocabulário Principal: 30230000\nPreço base s/IVA: 730.000,00 EUR\nObjeto Complementar\nVocabulário Principal: 39100000\nPreço base s/IVA: 295.000,00 EUR\nLotes: \nNº: LOT-0001\nDescrição do Lote: Lote 1 - Informática e Equipamentos\nPreço base s/IVA: 730.000,00 EUR\nClassificação CPV (Vocabulário Comum para os Contratos Públicos)\nObjeto principal\nVocabulário Principal: 30230000\nObjeto Complementar\nVocabulário Principal: 39100000\nNº: LOT-0002\nDescrição do Lote: Lote 2 - Mobiliário\nPreço base s/IVA: 295.000,00 EUR\nClassificação CPV (Vocabulário Comum para os Contratos Públicos)\nObjeto principal\nVocabulário Principal: 30230000\nObjeto Complementar\nVocabulário Principal: 39100000\n\n7 - INDICAÇÕES ADICIONAIS\nO contrato envolve aquisição conjunta (satisfação de várias entidades)? Não\nO contrato é adjudicado por uma central de compras? Não\n\n8 - TÉCNICAS\nO concurso destina-se à celebração de um acordo-quadro? Inexistência de acordo-quadro\nÉ utilizado um leilão eletrónico? Não\nÉ adotada uma fase de negociação? Não\nSistema de Aquisição Dinâmico: Inexistência de sistema de aquisição dinâmico\n\n9 - LOCAL DA EXECUÇÃO DO CONTRATO\nLOCAL DA EXECUÇÃO DO CONTRATO (PROCEDIMENTO)\nPaís: Portugal\nNUT III: PT11C\nLocalidade: Porto\nDistrito: Porto\nConcelho: Amarante\nFreguesia: Freguesia de Vila Caiz\nLOCAL DA EXECUÇÃO DO CONTRATO (LOTE)\nIdentificador do Lote: LOT-0001; LOT-0002\nPaís: Portugal\nNUT III: PT11C\nLocalidade: Porto\nDistrito: Porto\nConcelho: Amarante\nFreguesia: Freguesia de Vila Caiz\n\n10 - PRAZO DE EXECUÇÃO DO CONTRATO\nIdentificador do Lote: LOT-0001; LOT-0002\nPrazo de execução do contrato: 3 MESES\nPrevisão de renovações: Não\n\n11 - FUNDOS EU\nIdentificador do Lote: LOT-0001; LOT-0002\nTêm fundos EU? Não\n\n12 - DOCUMENTOS DE HABILITAÇÃO\nHabilitação para o exercício da atividade profissional: Não\n\n13 - CONDIÇÕES DE APRESENTAÇÃO\nPlataforma eletrónica utilizada pela entidade adjudicante: VORTAL\nURL para Apresentação: https://community.vortal.biz/public/\nAdmissibilidade da apresentação de propostas variantes: Não autorizado\nPrazo para apresentação das propostas: 31-12-2025 23:59\nPrazo durante o qual os concorrentes são obrigados a manter as respetivas propostas: 66 dias a contar do termo do prazo para a apresentação das propostas\nApresentação de Catálogo Eletrónico: Não autorizado\nIndicação de Subcontratação na Proposta: Inexistência de indicação de subcontratação\n\n14 - PRESTAÇÃO DE CAUÇÃO\nPrestação de caução: Sim\nPercentagem: 3%\nDescrição da Garantia Exigida: A caução é prestada por depósito em dinheiro ou em títulos emitidos ou garantidos pelo Estado, ou mediante garantia bancária ou seguro-caução, nos termos definidos no artigo 90.º do CCP\n\n15 - FORNECIMENTO DAS PEÇAS DO CONCURSO, APRESENTAÇÃO DE PEDIDOS DE PARTICIPAÇÃO E APRESENTAÇÃO DAS PROPOSTAS\nLink para acesso às peças do concurso (URL): https://community.vortal.biz/Public/public-tender-documents/czhGRFNsVzZHZnM3bitDdmVGUThSeW10UEw5S0RCcStrdzQyRXBvSVRrcDZsb2trL01pWWtJU0tvUTNTZDNURlppa2crVWVTRUd4YnNCL1JPZk81Y1E9PUclKnY5\n\n20 - OUTROS REQUISITOS\nIdentificador do Lote: LOT-0001; LOT-0002\nInformação sobre contratos reservados. Aplica-se a contratos reservados (54º-A)? Não\n\n21 - CRITÉRIO DE ADJUDICAÇÃO\nO Critério de adjudicação é diferenciado por lote? Não\nMultifator: Sim\nFator: \nNome: Preço\nPonderação: 60%\nSubfatores: Não\nFator: \nNome: Qualidade\nPonderação: 40%\nSubfatores: Não\n\n24 - CONDIÇÕES DO CONTRATO\nIdentificador do Lote: LOT-0001; LOT-0002\nFaturação Eletrónica: Permitido\nObrigação de Subcontratação:\nCódigo da Obrigação de Subcontratação: Não é aplicável nenhuma obrigação de subcontratação.\n\n25 - COMPRA PÚBLICA ESTRATÉGICA\nCompra Pública Estratégica: Redução dos impactos ambientais\nDescrição do Processo de Adjudicação Estratégico: Conforme as peças do procedimento\nCritérios de contratos Públicos Ecológicos: Critérios de contratação pública ecológica nacional\nCategorias da estratégia nacional: Mobiliário\nDiretiva Veículos Não Poluentes: Não\nCritério de Acessibilidade: Os critérios de acessibilidade para as pessoas com deficiência estão incluídos\n\n26 - INFORMAÇÕES ADICIONAIS\nIdentificador do Lote: LOT-0001; LOT-0002\nContrato adequado para PME: Sim\nCobertura ACP (Acordo dos Contratos Públicos da Organização Mundial do Comércio): Não\n\n27 - IDENTIFICAÇÃO E CONTACTOS DO ÓRGÃO DE RECURSOS ADMINISTRATIVOS\nDesignação: Maria Manuela Ribeiro Monteiro\nEndereço: Rua da Escola, nº 32\nCódigo postal: 4600-789\nLocalidade: Amarante\nTelefone: +351 255098383\nFax: +351 255098383\nEndereço eletrónico: manuela.monteiro@epalc.pt\n\n28 - IDENTIFICAÇÃO DO(S) AUTOR(ES) DE ANÚNCIO\nNome: Guilherme Teixeira\nCargo: Diretor\n419882053",
    "nipc": "509082629",
    "distrito": "Porto",
    "concelho": "Amarante",
    "freguesia": "Freguesia de Vila Caiz",
    "site": "https://epalc.pt/",
    "email": "estudoseprojectos.insticoop@gmail.com",
    "designacao_contrato": "Aquisição de infraestrutura tecnológica, equipamentos e mobiliário destinados à prática educativa e formativa no Centro Tecnológico Especializado em Energias renováveis",
    "descricao": "Aquisição de infraestrutura tecnológica, equipamentos e mobiliário destinados »a prática educativa e formativa no Centro Tecnológico Especializado de Energias Renováveis - Componente 6 \"Qualificações e Competências\" do Plano de Recuperação e Resiliência (PRR), aprovado pela Decisão de Execução do Conselho da União Europeia de 16 de junho de 2021, previsto no investimento RE-C06-i01: Modernização da oferta e dos Estabelecimentos de ensino e da formação profissional",
    "preco_base": "730.000,00 EUR",
    "prazo_execucao": "3 MESES",
    "prazo_apresentacao_propostas": "31-12-2025 23:59",
    "fundos_eu": "Não",
    "plataforma_eletronica": "VORTAL",
    "url_procedimento": "https://community.vortal.biz/public/",
    "autor_nome": "Guilherme Teixeira",
    "autor_cargo": "Diretor"
  },
  {
    "numero_procedimento": "N/A",
    "entidade": "Município de Moimenta da Beira",
    "link": "https://diariodarepublica.pt/dr/detalhe/contrato-publico/33405-992674293",
    "detalhes_completos": "Alteração do Anúncio de procedimento n.º 31807/2025, de 2025-12-09, com o ID 419849573\n\n1 - IDENTIFICAÇÃO E CONTACTOS DA ENTIDADE ADJUDICANTE\nDesignação da entidade adjudicante: Município de Moimenta da Beira\nNIPC: 506664686\nServiço/Órgão/Pessoa de contacto: PRESIDENTE\nEndereço: Largo do Tabolado\nCódigo postal: 3620-324\nLocalidade: Moimenta da Beira\nPaís: Portugal\nNUT III: PT11D\nDistrito: Viseu\nConcelho: Moimenta da Beira\nFreguesia: Freguesia de Moimenta da Beira\nTelefone: 254520070\nFax: 254520071\nEndereço da Entidade (URL): www.cm-moimenta.pt\nEndereço Eletrónico: geral@cm-moimenta.pt\neDelivery Gateway (URL): https://www.acingov.pt\nFunção da Organização: Adquirente\nNorma jurídica da Entidade Adjudicante: Organismo de direito público\nÁrea de atividade da Autoridade Adjudicante: Serviços públicos das administrações públicas\n\n2 - JORNAL OFICIAL DA UNIÃO EUROPEIA\nO procedimento a que este anúncio diz respeito também é publicitado no Jornal Oficial da União Europeia? Sim\n\n3 - AVISO\nModelo de Anúncio: Concurso público\nData de Envio do Anúncio: 22-12-2025\n\n5 - PROCESSO\nTipo de Procedimento: Concurso público\nPreço base do procedimento: Sim\nValor do preço base do procedimento: 650.000,00 EUR\nProcedimento com lotes? Não\n\n6 - OBJETO DO CONTRATO\nNúmero de referência interna: 3445/2025\nDesignação do contrato: ELABORAÇÃO DO PROJETO DE EXECUÇÃO E DE UM ESTUDO DE IMPACTE AMBIENTAL DO APROVEITAMENTO HIDROAGRÍCOLA DA BOAVISTA  MOIMENTA DA BEIRA\nDescrição: ELABORAÇÃO DO PROJETO DE EXECUÇÃO E DE UM ESTUDO DE IMPACTE AMBIENTAL DO APROVEITAMENTO HIDROAGRÍCOLA DA BOAVISTA  MOIMENTA DA BEIRA\nOpções: Não\nTipo de Contrato Principal: Aquisição de Serviços\nTipo de Contrato: Aquisição de Serviços\nClassificação CPV (Vocabulário Comum para os Contratos Públicos)\nObjeto principal\nVocabulário Principal: 71250000\nPreço base s/IVA: 650.000,00 EUR\n\n7 - INDICAÇÕES ADICIONAIS\nO contrato envolve aquisição conjunta (satisfação de várias entidades)? Não\nO contrato é adjudicado por uma central de compras? Não\n\n8 - TÉCNICAS\nO concurso destina-se à celebração de um acordo-quadro? Inexistência de acordo-quadro\nÉ utilizado um leilão eletrónico? Não\nÉ adotada uma fase de negociação? Não\nSistema de Aquisição Dinâmico: Inexistência de sistema de aquisição dinâmico\n\n9 - LOCAL DA EXECUÇÃO DO CONTRATO\nLOCAL DA EXECUÇÃO DO CONTRATO (PROCEDIMENTO)\nPaís: Portugal\nNUT III: PT11D\nLocalidade: Freguesia de Rua\nDistrito: Viseu\nConcelho: Moimenta da Beira\nFreguesia: Freguesia de Rua\nPaís: Portugal\nNUT III: PT11D\nLocalidade: Freguesia de Arcozelos\nDistrito: Viseu\nConcelho: Moimenta da Beira\nFreguesia: Freguesia de Arcozelos\nPaís: Portugal\nNUT III: PT11D\nLocalidade: Freguesia de Caria - Moimenta da Beira\nDistrito: Viseu\nConcelho: Moimenta da Beira\nFreguesia: Freguesia de Caria - Moimenta da Beira\n\n10 - PRAZO DE EXECUÇÃO DO CONTRATO\nPrazo de execução do contrato: 11 MESES\nPrevisão de renovações: Não\n\n11 - FUNDOS EU\nTêm fundos EU? Sim\n\n12 - DOCUMENTOS DE HABILITAÇÃO\nHabilitação para o exercício da atividade profissional: Sim\nTipo: Ordem Profissional\nDescrição: Documentos de Habilitação\n\n13 - CONDIÇÕES DE APRESENTAÇÃO\nPlataforma eletrónica utilizada pela entidade adjudicante: ACIN\nURL para Apresentação: https://www.acingov.pt\nAdmissibilidade da apresentação de propostas variantes: Não autorizado\nPrazo para apresentação das propostas: 12-01-2026 23:59\nPrazo durante o qual os concorrentes são obrigados a manter as respetivas propostas: 90 dias a contar do termo do prazo para a apresentação das propostas\nApresentação de Catálogo Eletrónico: Permitido\nIndicação de Subcontratação na Proposta: Inexistência de indicação de subcontratação\n\n14 - PRESTAÇÃO DE CAUÇÃO\nPrestação de caução: Sim\nPercentagem: 5%\nDescrição da Garantia Exigida: O valor da caução é de 5.00% do preço contratual.\n\n15 - FORNECIMENTO DAS PEÇAS DO CONCURSO, APRESENTAÇÃO DE PEDIDOS DE PARTICIPAÇÃO E APRESENTAÇÃO DAS PROPOSTAS\nLink para acesso às peças do concurso (URL): https://www.acingov.pt/acingovprod/2/zonaPublica/zona_publica_c/donwloadProcedurePiece/MTAwMTQxNA==\n\n20 - OUTROS REQUISITOS\nInformação sobre contratos reservados. Aplica-se a contratos reservados (54º-A)? Não\n\n21 - CRITÉRIO DE ADJUDICAÇÃO\nMultifator: Sim\nFator: \nNome: Preço\nPonderação: 80%\nSubfatores: Não\nFator: \nNome: Outros\nOutro Nome: Valia Técnica\nPonderação: 20%\nSubfatores: Sim\nSubfatores: \nNome: Metodologia de execução dos trabalhos propostos\nPonderação : 40%; \nNome: Programa de trabalhos com demonstração da efetiva capacidade de cumprimento do(s) prazo(s) estipulado(s). Descrição da metodologia de controlo da qualidade do projeto de execução e do estudo de impacte ambiental\nPonderação : 30%; \nNome: Adequação e coerência das competências e experiência dos elementos que integram a(s) equipa(s) técnica(s) afeta(s) à execução do contrato, (elaboração do projeto de execução e elaboração do estudo de impacte ambiental), à luz da natureza dos trabalhos, da(s) metodologia(s) proposta(s), do organograma funcional, do cronograma e tempos de afetação\nPonderação : 30%; \n\n24 - CONDIÇÕES DO CONTRATO\nFaturação Eletrónica: Permitido\nObrigação de Subcontratação:\nCódigo da Obrigação de Subcontratação: Não é aplicável nenhuma obrigação de subcontratação.\n\n25 - COMPRA PÚBLICA ESTRATÉGICA\nCompra Pública Estratégica: Inexistência de contratação pública estratégica\n\n26 - INFORMAÇÕES ADICIONAIS\nContrato adequado para PME: Não\nCobertura ACP (Acordo dos Contratos Públicos da Organização Mundial do Comércio): Não\n\n27 - IDENTIFICAÇÃO E CONTACTOS DO ÓRGÃO DE RECURSOS ADMINISTRATIVOS\nDesignação: Câmara Municipal de Moimenta da Beira\nEndereço: Largo do Tabolado\nCódigo postal: 3620-324\nLocalidade: Moimenta da Beira\nTelefone: 2545200070\nFax: \nEndereço eletrónico: geral@cm-moimenta.pt\nPrazo de interposição do recurso: 5 dias\n\n28 - IDENTIFICAÇÃO DO(S) AUTOR(ES) DE ANÚNCIO\nNome: Paulo Alexandre de Matos Figueiredo\nCargo: Presidente da Câmara Municipal\n\n29 - ALTERAÇÃO\nMotivo da Alteração: Informações atualizadas\nIdentificador da Versão do Anúncio a Alterar: fdc2e990-27bf-4fc3-9195-4a2054d7924c-01\nIdentificador das Secções Alteradas do Anúncio Anterior: Condições de Apresentação\nDescrição das Alterações: Modificação do prazo para a apresentação de propostas\nAlteração dos Documentos do Concurso: Não\n419924254",
    "nipc": "506664686",
    "distrito": "Viseu",
    "concelho": "Moimenta da Beira",
    "freguesia": "Freguesia de Moimenta da Beira",
    "site": "www.cm-moimenta.pt",
    "email": "geral@cm-moimenta.pt",
    "designacao_contrato": "ELABORAÇÃO DO PROJETO DE EXECUÇÃO E DE UM ESTUDO DE IMPACTE AMBIENTAL DO APROVEITAMENTO HIDROAGRÍCOLA DA BOAVISTA  MOIMENTA DA BEIRA",
    "descricao": "ELABORAÇÃO DO PROJETO DE EXECUÇÃO E DE UM ESTUDO DE IMPACTE AMBIENTAL DO APROVEITAMENTO HIDROAGRÍCOLA DA BOAVISTA  MOIMENTA DA BEIRA",
    "preco_base": "650.000,00 EUR",
    "prazo_execucao": "11 MESES",
    "prazo_apresentacao_propostas": "12-01-2026 23:59",
    "fundos_eu": "Sim",
    "plataforma_eletronica": "ACIN",
    "url_procedimento": "https://www.acingov.pt",
    "autor_nome": "Paulo Alexandre de Matos Figueiredo",
    "autor_cargo": "Presidente da Câmara Municipal"
  }
]