[
  {
    "numero_procedimento": "N/A",
    "entidade": "AnÃºncio de procedimento  n.Âº 2025/2026  -  DiÃ¡rio da RepÃºblica n.Âº 20/2026, SÃ©rie II de 2026-01-29",
    "link": "https://diariodarepublica.pt/dr/detalhe/contrato-publico/2025-1028060286"
  },
  {
    "numero_procedimento": "N/A",
    "entidade": "AnÃºncio de procedimento  n.Âº 2026/2026  -  DiÃ¡rio da RepÃºblica n.Âº 20/2026, SÃ©rie II de 2026-01-29",
    "link": "https://diariodarepublica.pt/dr/detalhe/contrato-publico/2026-1028060287"
  },
  {
    "numero_procedimento": "N/A",
    "entidade": "Unidade Local de Saúde de Amadora/Sintra, EPE",
    "link": "https://diariodarepublica.pt/dr/detalhe/contrato-publico/2027-1028060288",
    "detalhes_completos": "1 - IDENTIFICAÇÃO E CONTACTOS DA ENTIDADE ADJUDICANTE\nDesignação da entidade adjudicante: Unidade Local de Saúde de Amadora/Sintra, EPE\nNIPC: 503035416\nEndereço: VIA RÁPIDA LISBOA-SINTRA IC19\nCódigo postal: 2720-276\nLocalidade: Lisboa\nPaís: Portugal\nNUT III: PT170\nDistrito: Lisboa\nConcelho: Amadora\nFreguesia: Freguesia de Venteira\nTelefone: 214348200\nFax: 214345566\nEndereço da Entidade (URL): https://hff.min-saude.pt/\nEndereço Eletrónico: logistica@ulsasi.min-saude.pt\neDelivery Gateway (URL): https://community.vortal.biz/public/\nFunção da Organização: Adquirente\nNorma jurídica da Entidade Adjudicante: Organismo de direito público\nÁrea de atividade da Autoridade Adjudicante: Saúde\n2 - JORNAL OFICIAL DA UNIÃO EUROPEIA\nO procedimento a que este anúncio diz respeito também é publicitado no Jornal Oficial da União Europeia? Não\n3 - AVISO\nModelo de Anúncio: Concurso público\nData de Envio do Anúncio: 28-01-2026\n5 - PROCESSO\nTipo de Procedimento: Concurso público\nPreço base do procedimento: Sim\nValor do preço base do procedimento: 48.266,40 EUR\nProcedimento com lotes? Sim\nNº Máx. de Lotes Autorizado: 4\nNúmero máximo de lotes que podem ser adjudicados a um concorrente: 4\n6 - OBJETO DO CONTRATO\nNúmero de referência interna: 11F0061626\nDesignação do contrato: 11F0061626 Aquisição de Algálias para o armazém da Unidade Local Saúde Amadora/Sintra, E.P.E., para o ano de 2026\nDescrição: Aquisição de Algálias para o armazém da Unidade Local Saúde Amadora/Sintra, E.P.E., para o ano de 2026\nTipo de Contrato Principal: Aquisição de Bens Móveis\nTipo de Contrato: Aquisição de Bens Móveis\nClassificação CPV (Vocabulário Comum para os Contratos Públicos)\nObjeto principal\nVocabulário Principal: 33698000\nPreço base s/IVA: 48.266,40 EUR\nLotes: \nNº: LOT-0001\nDescrição do Lote: Lote 1\nPreço base s/IVA: 27.600,00 EUR\nClassificação CPV (Vocabulário Comum para os Contratos Públicos)\nObjeto principal\nVocabulário Principal: 33698000\nNº: LOT-0002\nDescrição do Lote: Lote 2\nPreço base s/IVA: 14.970,50 EUR\nClassificação CPV (Vocabulário Comum para os Contratos Públicos)\nObjeto principal\nVocabulário Principal: 33698000\nNº: LOT-0003\nDescrição do Lote: Lote 3\nPreço base s/IVA: 897,10 EUR\nClassificação CPV (Vocabulário Comum para os Contratos Públicos)\nObjeto principal\nVocabulário Principal: 33698000\nNº: LOT-0004\nDescrição do Lote: Lote 4\nPreço base s/IVA: 4.798,80 EUR\nClassificação CPV (Vocabulário Comum para os Contratos Públicos)\nObjeto principal\nVocabulário Principal: 33698000\n7 - INDICAÇÕES ADICIONAIS\nO contrato envolve aquisição conjunta (satisfação de várias entidades)? Não\nO contrato é adjudicado por uma central de compras? Não\n8 - TÉCNICAS\nO concurso destina-se à celebração de um acordo-quadro? Inexistência de acordo-quadro\nÉ utilizado um leilão eletrónico? Não\nÉ adotada uma fase de negociação? Não\nSistema de Aquisição Dinâmico: Inexistência de sistema de aquisição dinâmico\n9 - LOCAL DA EXECUÇÃO DO CONTRATO\nLOCAL DA EXECUÇÃO DO CONTRATO (PROCEDIMENTO)\nPaís: Portugal\nNUT III: PT170\nLocalidade: Lisboa\nDistrito: Lisboa\nConcelho: Amadora\nFreguesia: Freguesia de Venteira\nLOCAL DA EXECUÇÃO DO CONTRATO (LOTE)\nIdentificador do Lote: LOT-0001; LOT-0002; LOT-0003; LOT-0004\nPaís: Portugal\nNUT III: PT170\nLocalidade: Lisboa\nDistrito: Lisboa\nConcelho: Amadora\nFreguesia: Freguesia de Venteira\n10 - PRAZO DE EXECUÇÃO DO CONTRATO\nIdentificador do Lote: LOT-0001; LOT-0002; LOT-0003; LOT-0004\nPrazo de execução do contrato: 12 MESES\nPrevisão de renovações: Não\n11 - FUNDOS EU\nIdentificador do Lote: LOT-0001; LOT-0002; LOT-0003; LOT-0004\nTêm fundos EU? Não\n12 - DOCUMENTOS DE HABILITAÇÃO\nHabilitação para o exercício da atividade profissional: Não\n13 - CONDIÇÕES DE APRESENTAÇÃO\nPlataforma eletrónica utilizada pela entidade adjudicante: VORTAL\nURL para Apresentação: https://community.vortal.biz/public/\nAdmissibilidade da apresentação de propostas variantes: Não autorizado\nPrazo para apresentação das propostas: 05-02-2026 17:00\nPrazo durante o qual os concorrentes são obrigados a manter as respetivas propostas: 120 dias a contar do termo do prazo para a apresentação das propostas\nIndicação de Subcontratação na Proposta: Inexistência de indicação de subcontratação\n14 - PRESTAÇÃO DE CAUÇÃO\nPrestação de caução: Não\n15 - FORNECIMENTO DAS PEÇAS DO CONCURSO, APRESENTAÇÃO DE PEDIDOS DE PARTICIPAÇÃO E APRESENTAÇÃO DAS PROPOSTAS\nLink para acesso às peças do concurso (URL): https://community.vortal.biz/Public/public-tender-documents/K0VLTXJBQVduN1RKVGt2dzA5dmtlbExXcU1Sb2ZxY2VRMFJTU1VxakFWcnBWRWJkM2tvMW5RSEY1RE9PR0xkOS8rVWpWRmVlTEcwYWswcjZqSlhXQnc9PUtUaFly\n20 - OUTROS REQUISITOS\nIdentificador do Lote: LOT-0001; LOT-0002; LOT-0003; LOT-0004\nInformação sobre contratos reservados. Aplica-se a contratos reservados (54º-A)? Não\n21 - CRITÉRIO DE ADJUDICAÇÃO\nO Critério de adjudicação é diferenciado por lote? Não\nMultifator: Não\nMonofator:\nNome: Preço\n24 - CONDIÇÕES DO CONTRATO\nIdentificador do Lote: LOT-0001; LOT-0002; LOT-0003; LOT-0004\nFaturação Eletrónica: Permitido\nObrigação de Subcontratação:\nCódigo da Obrigação de Subcontratação: Não é aplicável nenhuma obrigação de subcontratação.\n25 - COMPRA PÚBLICA ESTRATÉGICA\nCompra Pública Estratégica: Inexistência de contratação pública estratégica\n26 - INFORMAÇÕES ADICIONAIS\nIdentificador do Lote: LOT-0001; LOT-0002; LOT-0003; LOT-0004\nContrato adequado para PME: Sim\nCobertura ACP (Acordo dos Contratos Públicos da Organização Mundial do Comércio): Não\n27 - IDENTIFICAÇÃO E CONTACTOS DO ÓRGÃO DE RECURSOS ADMINISTRATIVOS\nDesignação: Unidade Local de Saúde Amadora/Sintra E.P.E.\nEndereço: Hospital Professor Doutor Fernando Fonseca, EPE, Estrada IC, 19\nCódigo postal: 2720-276\nLocalidade: Amadora\nTelefone: +351 214348200\nFax: +351 214345566\nEndereço eletrónico: logistica@ulsasi.min-saude.pt\n28 - IDENTIFICAÇÃO DO(S) AUTOR(ES) DE ANÚNCIO\nNome: Marta Almeida\nCargo: Técnica Superior \n419949279",
    "nipc": "503035416",
    "distrito": "Lisboa",
    "concelho": "Amadora",
    "freguesia": "Freguesia de Venteira",
    "site": "https://hff.min-saude.pt/",
    "email": "logistica@ulsasi.min-saude.pt",
    "designacao_contrato": "11F0061626 Aquisição de Algálias para o armazém da Unidade Local Saúde Amadora/Sintra, E.P.E., para o ano de 2026",
    "descricao": "Aquisição de Algálias para o armazém da Unidade Local Saúde Amadora/Sintra, E.P.E., para o ano de 2026",
    "preco_base": "48.266,40 EUR",
    "prazo_execucao": "12 MESES",
    "prazo_apresentacao_propostas": "05-02-2026 17:00",
    "fundos_eu": "Não",
    "plataforma_eletronica": "VORTAL",
    "url_procedimento": "https://community.vortal.biz/public/",
    "autor_nome": "Marta Almeida",
    "autor_cargo": "Técnica Superior"
  },
  {
    "numero_procedimento": "N/A",
    "entidade": "ViniPortugal - Associação Interprofissional do Vinho",
    "link": "https://diariodarepublica.pt/dr/detalhe/contrato-publico/2028-1028060289",
    "detalhes_completos": "1 - IDENTIFICAÇÃO E CONTACTOS DA ENTIDADE ADJUDICANTE\nDesignação da entidade adjudicante: ViniPortugal - Associação Interprofissional do Vinho\nNIPC: 503736864\nEndereço: Rua Mouzinho da Silveira, 5 \nCódigo postal: 2560-312\nLocalidade: Lisboa\nPaís: Portugal\nNUT III: PT16B\nDistrito: Lisboa\nConcelho: Torres Vedras\nFreguesia: Todas\nTelefone: 213569890\nFax: 213569895\nEndereço da Entidade (URL): https://viniportugal.pt/pt/\nEndereço Eletrónico: geral@viniportugal.pt\neDelivery Gateway (URL): https://community.vortal.biz/public/\nFunção da Organização: Adquirente\nNorma jurídica da Entidade Adjudicante: Organismo de direito público\nÁrea de atividade da Autoridade Adjudicante: Educação\n2 - JORNAL OFICIAL DA UNIÃO EUROPEIA\nO procedimento a que este anúncio diz respeito também é publicitado no Jornal Oficial da União Europeia? Não\n3 - AVISO\nModelo de Anúncio: Concurso público\nData de Envio do Anúncio: 28-01-2026\n5 - PROCESSO\nTipo de Procedimento: Concurso público\nPreço base do procedimento: Sim\nValor do preço base do procedimento: 80.000,00 EUR\nProcedimento com lotes? Não\n6 - OBJETO DO CONTRATO\nNúmero de referência interna: 2026.04\nDesignação do contrato: Prestação do Serviço de Envio de Vinhos, para as acções da Marca Wines of Portugal para os mercados da Europa 2026\nDescrição: Prestação do Serviço de Envio de Vinhos, para as acções da Marca Wines of Portugal para os mercados da Europa 2026\nTipo de Contrato Principal: Aquisição de Serviços\nTipo de Contrato: Aquisição de Serviços\nClassificação CPV (Vocabulário Comum para os Contratos Públicos)\nObjeto principal\nVocabulário Principal: 79342200\nPreço base s/IVA: 80.000,00 EUR\n7 - INDICAÇÕES ADICIONAIS\nO contrato envolve aquisição conjunta (satisfação de várias entidades)? Não\nO contrato é adjudicado por uma central de compras? Não\n8 - TÉCNICAS\nO concurso destina-se à celebração de um acordo-quadro? Inexistência de acordo-quadro\nÉ utilizado um leilão eletrónico? Não\nÉ adotada uma fase de negociação? Não\nSistema de Aquisição Dinâmico: Inexistência de sistema de aquisição dinâmico\n9 - LOCAL DA EXECUÇÃO DO CONTRATO\nLOCAL DA EXECUÇÃO DO CONTRATO (PROCEDIMENTO)\nPaís: Portugal\nNUT III: PT170\nLocalidade: Lisboa\nDistrito: Lisboa\nConcelho: Lisboa\nFreguesia: Todas\n10 - PRAZO DE EXECUÇÃO DO CONTRATO\nPrazo de execução do contrato: 1 ANOS\nPrevisão de renovações: Não\n11 - FUNDOS EU\nTêm fundos EU? Não\n12 - DOCUMENTOS DE HABILITAÇÃO\nHabilitação para o exercício da atividade profissional: Não\n13 - CONDIÇÕES DE APRESENTAÇÃO\nPlataforma eletrónica utilizada pela entidade adjudicante: VORTAL\nURL para Apresentação: https://community.vortal.biz/public/\nAdmissibilidade da apresentação de propostas variantes: Não autorizado\nPrazo para apresentação das propostas: 04-02-2026 17:00\nPrazo durante o qual os concorrentes são obrigados a manter as respetivas propostas: 180 dias a contar do termo do prazo para a apresentação das propostas\nIndicação de Subcontratação na Proposta: Inexistência de indicação de subcontratação\n14 - PRESTAÇÃO DE CAUÇÃO\nPrestação de caução: Não\n15 - FORNECIMENTO DAS PEÇAS DO CONCURSO, APRESENTAÇÃO DE PEDIDOS DE PARTICIPAÇÃO E APRESENTAÇÃO DAS PROPOSTAS\nLink para acesso às peças do concurso (URL): https://community.vortal.biz/Public/public-tender-documents/eDFrTnhJcTV6L25nUmRQVWdjY1hLTGlTUmlQTC9XQTE2OG9LUTVIMGdJNUM0R00yMy9lajNlTGFoWURxTFdNM2dYNUNPdVpGY3FsZk10WWZpSnBnTUE9PUhhZiop\n20 - OUTROS REQUISITOS\nInformação sobre contratos reservados. Aplica-se a contratos reservados (54º-A)? Não\n21 - CRITÉRIO DE ADJUDICAÇÃO\nMultifator: Sim\nFator: \nNome: Preço\nPonderação: 70%\nSubfatores: Não\nFator: \nNome: Qualidade\nPonderação: 30%\nSubfatores: Sim\nSubfatores: \nNome: Qualidade Técnica Total\nPonderação : 100%; \n24 - CONDIÇÕES DO CONTRATO\nFaturação Eletrónica: Permitido\nObrigação de Subcontratação:\nCódigo da Obrigação de Subcontratação: Não é aplicável nenhuma obrigação de subcontratação.\n25 - COMPRA PÚBLICA ESTRATÉGICA\nCompra Pública Estratégica: Inexistência de contratação pública estratégica\n26 - INFORMAÇÕES ADICIONAIS\nContrato adequado para PME: Sim\nCobertura ACP (Acordo dos Contratos Públicos da Organização Mundial do Comércio): Não\n27 - IDENTIFICAÇÃO E CONTACTOS DO ÓRGÃO DE RECURSOS ADMINISTRATIVOS\nDesignação: Pedro Fernandes\nEndereço: Rua Mouzinho da Silveira, n.º5\nCódigo postal: 1250-165\nLocalidade: Lisboa\nTelefone: +351 213569890\nFax: +351 213569890\nEndereço eletrónico: processo-concursal@viniportugal.pt\n28 - IDENTIFICAÇÃO DO(S) AUTOR(ES) DE ANÚNCIO\nNome: Pedro Fernandes\nCargo: Director Financeiro\n419949415",
    "nipc": "503736864",
    "distrito": "Lisboa",
    "concelho": "Torres Vedras",
    "freguesia": "Todas",
    "site": "https://viniportugal.pt/pt/",
    "email": "geral@viniportugal.pt",
    "designacao_contrato": "Prestação do Serviço de Envio de Vinhos, para as acções da Marca Wines of Portugal para os mercados da Europa 2026",
    "descricao": "Prestação do Serviço de Envio de Vinhos, para as acções da Marca Wines of Portugal para os mercados da Europa 2026",
    "preco_base": "80.000,00 EUR",
    "prazo_execucao": "1 ANOS",
    "prazo_apresentacao_propostas": "04-02-2026 17:00",
    "fundos_eu": "Não",
    "plataforma_eletronica": "VORTAL",
    "url_procedimento": "https://community.vortal.biz/public/",
    "autor_nome": "Pedro Fernandes",
    "autor_cargo": "Director Financeiro"
  },
  {
    "numero_procedimento": "N/A",
    "entidade": "Município do Porto",
    "link": "https://diariodarepublica.pt/dr/detalhe/contrato-publico/2020-1028060999",
    "detalhes_completos": "Alteração do Anúncio de procedimento n.º 1132/2026, de 2026-01-19, com o ID 419948303\n1 - IDENTIFICAÇÃO E CONTACTOS DA ENTIDADE ADJUDICANTE\nDesignação da entidade adjudicante: Município do Porto\nNIPC: 501306099\nServiço/Órgão/Pessoa de contacto: Divisão Municipal de Compras Gerais\nEndereço: R. Bolhão, 162\nCódigo postal: 4000-111\nLocalidade: Porto\nPaís: Portugal\nNUT III: PT11A\nDistrito: Porto\nConcelho: Porto\nFreguesia: União das Freguesias de Cedofeita, Santo Ildefonso, Sé, Miragaia, São Nicolau e Vitória\nTelefone: 222097216\nFax: 222097296\nEndereço da Entidade (URL): http://www.cm-porto.pt\nEndereço Eletrónico: dmcompras@cm-porto.pt\neDelivery Gateway (URL): https://www.acingov.pt\nFunção da Organização: Adquirente\nNorma jurídica da Entidade Adjudicante: Autoridade local\nÁrea de atividade da Autoridade Adjudicante: Serviços públicos das administrações públicas\n2 - JORNAL OFICIAL DA UNIÃO EUROPEIA\nO procedimento a que este anúncio diz respeito também é publicitado no Jornal Oficial da União Europeia? Não\n3 - AVISO\nModelo de Anúncio: Concurso público\nData de Envio do Anúncio: 28-01-2026\n5 - PROCESSO\nTipo de Procedimento: Concurso público\nPreço base do procedimento: Sim\nValor do preço base do procedimento: 115.000,00 EUR\nProcedimento com lotes? Não\n6 - OBJETO DO CONTRATO\nNúmero de referência interna: CP/63/2025/DMCG\nDesignação do contrato: Aquisição de serviços para Comunicação e avaliação da presença do Greater Porto no MIPIM 2026\nDescrição: Serviços Comunicação MIPIM 2026\nTipo de Contrato Principal: Aquisição de Serviços\nTipo de Contrato: Aquisição de Serviços\nClassificação CPV (Vocabulário Comum para os Contratos Públicos)\nObjeto principal\nVocabulário Principal: 79933000\nPreço base s/IVA: 115.000,00 EUR\n7 - INDICAÇÕES ADICIONAIS\nO contrato envolve aquisição conjunta (satisfação de várias entidades)? Sim\nA entidade adjudicante atua como compradora no procedimento? Sim\nNIPC: 501306099\nDesignação da entidade adjudicante: Município do Porto\nUnidades Orgânicas: DMEconomia\nPercentagem: 33.34%\nNIPC: 501305912\nDesignação da entidade adjudicante: Município de Matosinhos\nUnidades Orgânicas: Divisão de Atividades Económicas e Investimento\nPercentagem: 33.33%\nNIPC: 506064433\nDesignação da entidade adjudicante: GAIURB - Urbanismo e Habitação, EEM\nUnidades Orgânicas: Gaiurb, EM\nPercentagem: 33.33%\nO contrato é adjudicado por uma central de compras? Não\n8 - TÉCNICAS\nO concurso destina-se à celebração de um acordo-quadro? Inexistência de acordo-quadro\nÉ utilizado um leilão eletrónico? Não\nÉ adotada uma fase de negociação? Não\nSistema de Aquisição Dinâmico: Inexistência de sistema de aquisição dinâmico\n9 - LOCAL DA EXECUÇÃO DO CONTRATO\nLOCAL DA EXECUÇÃO DO CONTRATO (PROCEDIMENTO)\nPaís: Portugal\nNUT III: PT11A\nLocalidade: Porto\nDistrito: Porto\nConcelho: Porto\nFreguesia: Todas\n10 - PRAZO DE EXECUÇÃO DO CONTRATO\nPrazo de execução do contrato: 305 DIAS\nPrevisão de renovações: Não\n11 - FUNDOS EU\nTêm fundos EU? Não\n12 - DOCUMENTOS DE HABILITAÇÃO\nHabilitação para o exercício da atividade profissional: Não\n13 - CONDIÇÕES DE APRESENTAÇÃO\nPlataforma eletrónica utilizada pela entidade adjudicante: ACIN\nURL para Apresentação: https://www.acingov.pt\nAdmissibilidade da apresentação de propostas variantes: Não autorizado\nPrazo para apresentação das propostas: 02-02-2026 17:00\nPrazo durante o qual os concorrentes são obrigados a manter as respetivas propostas: 66 dias a contar do termo do prazo para a apresentação das propostas\nIndicação de Subcontratação na Proposta: Inexistência de indicação de subcontratação\n14 - PRESTAÇÃO DE CAUÇÃO\nPrestação de caução: Não\n15 - FORNECIMENTO DAS PEÇAS DO CONCURSO, APRESENTAÇÃO DE PEDIDOS DE PARTICIPAÇÃO E APRESENTAÇÃO DAS PROPOSTAS\nLink para acesso às peças do concurso (URL): https://www.acingov.pt/acingovprod/2/zonaPublica/zona_publica_c/donwloadProcedurePiece/MTAwNzM1OQ==\n20 - OUTROS REQUISITOS\nInformação sobre contratos reservados. Aplica-se a contratos reservados (54º-A)? Não\n21 - CRITÉRIO DE ADJUDICAÇÃO\nMultifator: Sim\nFator: \nNome: Preço\nPonderação: 40%\nSubfatores: Não\nFator: \nNome: Outros\nOutro Nome: Mérito da Solução (MS)\nPonderação: 60%\nSubfatores: Sim\nSubfatores: \nNome: Suportes de Comunicação (SC)\nPonderação : 60%; \nNome: Avaliação da presença (AP)\nPonderação : 40%; \n24 - CONDIÇÕES DO CONTRATO\nFaturação Eletrónica: Necessário\nObrigação de Subcontratação:\nCódigo da Obrigação de Subcontratação: Não é aplicável nenhuma obrigação de subcontratação.\n25 - COMPRA PÚBLICA ESTRATÉGICA\nCompra Pública Estratégica: Inexistência de contratação pública estratégica\n26 - INFORMAÇÕES ADICIONAIS\nContrato adequado para PME: Sim\nCobertura ACP (Acordo dos Contratos Públicos da Organização Mundial do Comércio): Não\n27 - IDENTIFICAÇÃO E CONTACTOS DO ÓRGÃO DE RECURSOS ADMINISTRATIVOS\nDesignação: Divisão Municipal de Compras Gerais\nEndereço: Rua do Bolhão,162.º-6º\nCódigo postal: 4000-111\nLocalidade: Porto\nTelefone: 222097216\nFax: \nEndereço eletrónico: dmcompras@cm-porto.pt\n28 - IDENTIFICAÇÃO DO(S) AUTOR(ES) DE ANÚNCIO\nNome: Vera Sampaio\nCargo: Chefe de Divisão Municipal de Compras Gerais\n29 - ALTERAÇÃO\nMotivo da Alteração: Informações atualizadas\nIdentificador da Versão do Anúncio a Alterar: 0d2b0082-8871-425e-85c7-56a8534fb1cf-01\nIdentificador das Secções Alteradas do Anúncio Anterior: Condições de Apresentação\nDescrição das Alterações: Modificação do prazo para a apresentação de propostas\nAlteração dos Documentos do Concurso: Não\n419949364",
    "nipc": "501306099",
    "distrito": "Porto",
    "concelho": "Porto",
    "freguesia": "União das Freguesias de Cedofeita, Santo Ildefonso, Sé, Miragaia, São Nicolau e Vitória",
    "site": "http://www.cm-porto.pt",
    "email": "dmcompras@cm-porto.pt",
    "designacao_contrato": "Aquisição de serviços para Comunicação e avaliação da presença do Greater Porto no MIPIM 2026",
    "descricao": "Serviços Comunicação MIPIM 2026",
    "preco_base": "115.000,00 EUR",
    "prazo_execucao": "305 DIAS",
    "prazo_apresentacao_propostas": "02-02-2026 17:00",
    "fundos_eu": "Não",
    "plataforma_eletronica": "ACIN",
    "url_procedimento": "https://www.acingov.pt",
    "autor_nome": "Vera Sampaio",
    "autor_cargo": "Chefe de Divisão Municipal de Compras Gerais"
  },
  {
    "numero_procedimento": "N/A",
    "entidade": "Unidade Local de Saúde de Coimbra, EPE",
    "link": "https://diariodarepublica.pt/dr/detalhe/contrato-publico/2021-1028061000",
    "detalhes_completos": "1 - IDENTIFICAÇÃO E CONTACTOS DA ENTIDADE ADJUDICANTE\nDesignação da entidade adjudicante: Unidade Local de Saúde de Coimbra, EPE\nNIPC: 510103448\nEndereço: Praceta Prof. Mota Pinto\nCódigo postal: 3004-561\nLocalidade: Coimbra\nPaís: Portugal\nNUT III: PT16E\nDistrito: Coimbra\nConcelho: Coimbra\nFreguesia: Todas\nTelefone: 239400605\nFax: 239400605\nEndereço da Entidade (URL): https://www.chuc.min-saude.pt\nEndereço Eletrónico: ana.rosete@ulscoimbra.min-saude.pt\neDelivery Gateway (URL): https://community.vortal.biz/public/\nFunção da Organização: Adquirente\nNorma jurídica da Entidade Adjudicante: Organismo de direito público\nÁrea de atividade da Autoridade Adjudicante: Saúde\n2 - JORNAL OFICIAL DA UNIÃO EUROPEIA\nO procedimento a que este anúncio diz respeito também é publicitado no Jornal Oficial da União Europeia? Não\n3 - AVISO\nModelo de Anúncio: Concurso público\nData de Envio do Anúncio: 28-01-2026\n5 - PROCESSO\nTipo de Procedimento: Concurso público\nPreço base do procedimento: Sim\nValor do preço base do procedimento: 28.935,04 EUR\nProcedimento com lotes? Sim\nNº Máx. de Lotes Autorizado: 34\nNúmero máximo de lotes que podem ser adjudicados a um concorrente: 34\n6 - OBJETO DO CONTRATO\nNúmero de referência interna: 010000022026\nDesignação do contrato: REAGENTES P/O SERVIÇO DE ANATOMIA PATOLÓGICA/IMUNO-HEMOTERAPIA \nDescrição: REAGENTES P/O SERVIÇO DE ANATOMIA PATOLÓGICA/IMUNO-HEMOTERAPIA \nTipo de Contrato Principal: Aquisição de Bens Móveis\nTipo de Contrato: Aquisição de Bens Móveis\nClassificação CPV (Vocabulário Comum para os Contratos Públicos)\nObjeto principal\nVocabulário Principal: 33696500\nPreço base s/IVA: 28.935,04 EUR\nLotes: \nNº: LOT-0001\nDescrição do Lote: Lote 1\nPreço base s/IVA: 48,22 EUR\nClassificação CPV (Vocabulário Comum para os Contratos Públicos)\nObjeto principal\nVocabulário Principal: 33696500\nNº: LOT-0002\nDescrição do Lote: Lote 2\nPreço base s/IVA: 70,64 EUR\nClassificação CPV (Vocabulário Comum para os Contratos Públicos)\nObjeto principal\nVocabulário Principal: 33696500\nNº: LOT-0003\nDescrição do Lote: Lote 3\nPreço base s/IVA: 1.191,00 EUR\nClassificação CPV (Vocabulário Comum para os Contratos Públicos)\nObjeto principal\nVocabulário Principal: 33696500\nNº: LOT-0004\nDescrição do Lote: Lote 4\nPreço base s/IVA: 224,00 EUR\nClassificação CPV (Vocabulário Comum para os Contratos Públicos)\nObjeto principal\nVocabulário Principal: 33696500\nNº: LOT-0005\nDescrição do Lote: Lote 5\nPreço base s/IVA: 232,48 EUR\nClassificação CPV (Vocabulário Comum para os Contratos Públicos)\nObjeto principal\nVocabulário Principal: 33696500\nNº: LOT-0006\nDescrição do Lote: Lote 6\nPreço base s/IVA: 1.200,00 EUR\nClassificação CPV (Vocabulário Comum para os Contratos Públicos)\nObjeto principal\nVocabulário Principal: 33696500\nNº: LOT-0007\nDescrição do Lote: Lote 7\nPreço base s/IVA: 22,00 EUR\nClassificação CPV (Vocabulário Comum para os Contratos Públicos)\nObjeto principal\nVocabulário Principal: 33696500\nNº: LOT-0008\nDescrição do Lote: Lote 8\nPreço base s/IVA: 3,00 EUR\nClassificação CPV (Vocabulário Comum para os Contratos Públicos)\nObjeto principal\nVocabulário Principal: 33696500\nNº: LOT-0009\nDescrição do Lote: Lote 9\nPreço base s/IVA: 50,00 EUR\nClassificação CPV (Vocabulário Comum para os Contratos Públicos)\nObjeto principal\nVocabulário Principal: 33696500\nNº: LOT-0010\nDescrição do Lote: Lote 10\nPreço base s/IVA: 250,00 EUR\nClassificação CPV (Vocabulário Comum para os Contratos Públicos)\nObjeto principal\nVocabulário Principal: 33696500\nNº: LOT-0011\nDescrição do Lote: Lote 11\nPreço base s/IVA: 0,12 EUR\nClassificação CPV (Vocabulário Comum para os Contratos Públicos)\nObjeto principal\nVocabulário Principal: 33696500\nNº: LOT-0012\nDescrição do Lote: Lote 12\nPreço base s/IVA: 18,40 EUR\nClassificação CPV (Vocabulário Comum para os Contratos Públicos)\nObjeto principal\nVocabulário Principal: 33696500\nNº: LOT-0013\nDescrição do Lote: Lote 13\nPreço base s/IVA: 100,00 EUR\nClassificação CPV (Vocabulário Comum para os Contratos Públicos)\nObjeto principal\nVocabulário Principal: 33696500\nNº: LOT-0014\nDescrição do Lote: Lote 14\nPreço base s/IVA: 8.280,00 EUR\nClassificação CPV (Vocabulário Comum para os Contratos Públicos)\nObjeto principal\nVocabulário Principal: 33696500\nNº: LOT-0015\nDescrição do Lote: Lote 15\nPreço base s/IVA: 890,68 EUR\nClassificação CPV (Vocabulário Comum para os Contratos Públicos)\nObjeto principal\nVocabulário Principal: 33696500\nNº: LOT-0016\nDescrição do Lote: Lote 16\nPreço base s/IVA: 58,80 EUR\nClassificação CPV (Vocabulário Comum para os Contratos Públicos)\nObjeto principal\nVocabulário Principal: 33696500\nNº: LOT-0017\nDescrição do Lote: Lote 17\nPreço base s/IVA: 10,00 EUR\nClassificação CPV (Vocabulário Comum para os Contratos Públicos)\nObjeto principal\nVocabulário Principal: 33696500\nNº: LOT-0018\nDescrição do Lote: Lote 18\nPreço base s/IVA: 3.000,00 EUR\nClassificação CPV (Vocabulário Comum para os Contratos Públicos)\nObjeto principal\nVocabulário Principal: 33696500\nNº: LOT-0019\nDescrição do Lote: Lote 19\nPreço base s/IVA: 300,00 EUR\nClassificação CPV (Vocabulário Comum para os Contratos Públicos)\nObjeto principal\nVocabulário Principal: 33696500\nNº: LOT-0020\nDescrição do Lote: Lote 20\nPreço base s/IVA: 900,00 EUR\nClassificação CPV (Vocabulário Comum para os Contratos Públicos)\nObjeto principal\nVocabulário Principal: 33696500\nNº: LOT-0021\nDescrição do Lote: Lote 21\nPreço base s/IVA: 127,50 EUR\nClassificação CPV (Vocabulário Comum para os Contratos Públicos)\nObjeto principal\nVocabulário Principal: 33696500\nNº: LOT-0022\nDescrição do Lote: Lote 22\nPreço base s/IVA: 624,00 EUR\nClassificação CPV (Vocabulário Comum para os Contratos Públicos)\nObjeto principal\nVocabulário Principal: 33696500\nNº: LOT-0023\nDescrição do Lote: Lote 23\nPreço base s/IVA: 510,00 EUR\nClassificação CPV (Vocabulário Comum para os Contratos Públicos)\nObjeto principal\nVocabulário Principal: 33696500\nNº: LOT-0024\nDescrição do Lote: Lote 24\nPreço base s/IVA: 100,00 EUR\nClassificação CPV (Vocabulário Comum para os Contratos Públicos)\nObjeto principal\nVocabulário Principal: 33696500\nNº: LOT-0025\nDescrição do Lote: Lote 25\nPreço base s/IVA: 100,00 EUR\nClassificação CPV (Vocabulário Comum para os Contratos Públicos)\nObjeto principal\nVocabulário Principal: 33696500\nNº: LOT-0026\nDescrição do Lote: Lote 26\nPreço base s/IVA: 4.256,00 EUR\nClassificação CPV (Vocabulário Comum para os Contratos Públicos)\nObjeto principal\nVocabulário Principal: 33696500\nNº: LOT-0027\nDescrição do Lote: Lote 27\nPreço base s/IVA: 465,60 EUR\nClassificação CPV (Vocabulário Comum para os Contratos Públicos)\nObjeto principal\nVocabulário Principal: 33696500\nNº: LOT-0028\nDescrição do Lote: Lote 28\nPreço base s/IVA: 450,00 EUR\nClassificação CPV (Vocabulário Comum para os Contratos Públicos)\nObjeto principal\nVocabulário Principal: 33696500\nNº: LOT-0029\nDescrição do Lote: Lote 29\nPreço base s/IVA: 178,20 EUR\nClassificação CPV (Vocabulário Comum para os Contratos Públicos)\nObjeto principal\nVocabulário Principal: 33696500\nNº: LOT-0030\nDescrição do Lote: Lote 30\nPreço base s/IVA: 307,20 EUR\nClassificação CPV (Vocabulário Comum para os Contratos Públicos)\nObjeto principal\nVocabulário Principal: 33696500\nNº: LOT-0031\nDescrição do Lote: Lote 31\nPreço base s/IVA: 2.159,40 EUR\nClassificação CPV (Vocabulário Comum para os Contratos Públicos)\nObjeto principal\nVocabulário Principal: 33696500\nNº: LOT-0032\nDescrição do Lote: Lote 32\nPreço base s/IVA: 57,52 EUR\nClassificação CPV (Vocabulário Comum para os Contratos Públicos)\nObjeto principal\nVocabulário Principal: 33696500\nNº: LOT-0033\nDescrição do Lote: Lote 33\nPreço base s/IVA: 13,28 EUR\nClassificação CPV (Vocabulário Comum para os Contratos Públicos)\nObjeto principal\nVocabulário Principal: 33696500\nNº: LOT-0034\nDescrição do Lote: Lote 34\nPreço base s/IVA: 2.737,00 EUR\nClassificação CPV (Vocabulário Comum para os Contratos Públicos)\nObjeto principal\nVocabulário Principal: 33696500\n7 - INDICAÇÕES ADICIONAIS\nO contrato envolve aquisição conjunta (satisfação de várias entidades)? Não\nO contrato é adjudicado por uma central de compras? Não\n8 - TÉCNICAS\nO concurso destina-se à celebração de um acordo-quadro? Inexistência de acordo-quadro\nÉ utilizado um leilão eletrónico? Não\nÉ adotada uma fase de negociação? Não\nSistema de Aquisição Dinâmico: Inexistência de sistema de aquisição dinâmico\n9 - LOCAL DA EXECUÇÃO DO CONTRATO\nLOCAL DA EXECUÇÃO DO CONTRATO (PROCEDIMENTO)\nPaís: Portugal\nNUT III: PT16E\nLocalidade: Coimbra\nDistrito: Coimbra\nConcelho: Coimbra\nFreguesia: Freguesia de Santo António dos Olivais\nLOCAL DA EXECUÇÃO DO CONTRATO (LOTE)\nIdentificador do Lote: LOT-0001; LOT-0002; LOT-0003; LOT-0004; LOT-0005; LOT-0006; LOT-0007; LOT-0008; LOT-0009; LOT-0010; LOT-0011; LOT-0012; LOT-0013; LOT-0014; LOT-0015; LOT-0016; LOT-0017; LOT-0018; LOT-0019; LOT-0020; LOT-0021; LOT-0022; LOT-0023; LOT-0024; LOT-0025; LOT-0026; LOT-0027; LOT-0028; LOT-0029; LOT-0030; LOT-0031; LOT-0032; LOT-0033; LOT-0034\nPaís: Portugal\nNUT III: PT16E\nLocalidade: Coimbra\nDistrito: Coimbra\nConcelho: Coimbra\nFreguesia: Freguesia de Santo António dos Olivais\n10 - PRAZO DE EXECUÇÃO DO CONTRATO\nIdentificador do Lote: LOT-0001; LOT-0002; LOT-0003; LOT-0004; LOT-0005; LOT-0006; LOT-0007; LOT-0008; LOT-0009; LOT-0010; LOT-0011; LOT-0012; LOT-0013; LOT-0014; LOT-0015; LOT-0016; LOT-0017; LOT-0018; LOT-0019; LOT-0020; LOT-0021; LOT-0022; LOT-0023; LOT-0024; LOT-0025; LOT-0026; LOT-0027; LOT-0028; LOT-0029; LOT-0030; LOT-0031; LOT-0032; LOT-0033; LOT-0034\nPrazo de execução do contrato: 11 MESES\nPrevisão de renovações: Não\n11 - FUNDOS EU\nIdentificador do Lote: LOT-0001; LOT-0002; LOT-0003; LOT-0004; LOT-0005; LOT-0006; LOT-0007; LOT-0008; LOT-0009; LOT-0010; LOT-0011; LOT-0012; LOT-0013; LOT-0014; LOT-0015; LOT-0016; LOT-0017; LOT-0018; LOT-0019; LOT-0020; LOT-0021; LOT-0022; LOT-0023; LOT-0024; LOT-0025; LOT-0026; LOT-0027; LOT-0028; LOT-0029; LOT-0030; LOT-0031; LOT-0032; LOT-0033; LOT-0034\nTêm fundos EU? Não\n12 - DOCUMENTOS DE HABILITAÇÃO\nHabilitação para o exercício da atividade profissional: Sim\nTipo: Certificado\nDescrição: n/a\n13 - CONDIÇÕES DE APRESENTAÇÃO\nPlataforma eletrónica utilizada pela entidade adjudicante: VORTAL\nURL para Apresentação: https://community.vortal.biz/public/\nAdmissibilidade da apresentação de propostas variantes: Não autorizado\nPrazo para apresentação das propostas: 09-02-2026 17:00\nPrazo durante o qual os concorrentes são obrigados a manter as respetivas propostas: 180 dias a contar do termo do prazo para a apresentação das propostas\nIndicação de Subcontratação na Proposta: Inexistência de indicação de subcontratação\n14 - PRESTAÇÃO DE CAUÇÃO\nPrestação de caução: Não\n15 - FORNECIMENTO DAS PEÇAS DO CONCURSO, APRESENTAÇÃO DE PEDIDOS DE PARTICIPAÇÃO E APRESENTAÇÃO DAS PROPOSTAS\nLink para acesso às peças do concurso (URL): https://community.vortal.biz/Public/public-tender-documents/TGcrUnZDajZycDJSY1BBRWJJdDU3bFg5ejNKM0p0ZjhDSjRCdENBZUFza0RiT2U0S0JQUjdxWG5kd3RmSnY4SGozMXArMmtWNWFEeWo1ZzZKQ0FqaFE9PUV0MXk4\n20 - OUTROS REQUISITOS\nIdentificador do Lote: LOT-0001; LOT-0002; LOT-0003; LOT-0004; LOT-0005; LOT-0006; LOT-0007; LOT-0008; LOT-0009; LOT-0010; LOT-0011; LOT-0012; LOT-0013; LOT-0014; LOT-0015; LOT-0016; LOT-0017; LOT-0018; LOT-0019; LOT-0020; LOT-0021; LOT-0022; LOT-0023; LOT-0024; LOT-0025; LOT-0026; LOT-0027; LOT-0028; LOT-0029; LOT-0030; LOT-0031; LOT-0032; LOT-0033; LOT-0034\nInformação sobre contratos reservados. Aplica-se a contratos reservados (54º-A)? Não\n21 - CRITÉRIO DE ADJUDICAÇÃO\nO Critério de adjudicação é diferenciado por lote? Não\nMultifator: Sim\nFator: \nNome: Qualidade\nPonderação: 60%\nSubfatores: Não\nFator: \nNome: Preço\nPonderação: 40%\nSubfatores: Não\n24 - CONDIÇÕES DO CONTRATO\nIdentificador do Lote: LOT-0001; LOT-0002; LOT-0003; LOT-0004; LOT-0005; LOT-0006; LOT-0007; LOT-0008; LOT-0009; LOT-0010; LOT-0011; LOT-0012; LOT-0013; LOT-0014; LOT-0015; LOT-0016; LOT-0017; LOT-0018; LOT-0019; LOT-0020; LOT-0021; LOT-0022; LOT-0023; LOT-0024; LOT-0025; LOT-0026; LOT-0027; LOT-0028; LOT-0029; LOT-0030; LOT-0031; LOT-0032; LOT-0033; LOT-0034\nFaturação Eletrónica: Permitido\nObrigação de Subcontratação:\nCódigo da Obrigação de Subcontratação: Não é aplicável nenhuma obrigação de subcontratação.\n25 - COMPRA PÚBLICA ESTRATÉGICA\nCompra Pública Estratégica: Inexistência de contratação pública estratégica\n26 - INFORMAÇÕES ADICIONAIS\nIdentificador do Lote: LOT-0001; LOT-0002; LOT-0003; LOT-0004; LOT-0005; LOT-0006; LOT-0007; LOT-0008; LOT-0009; LOT-0010; LOT-0011; LOT-0012; LOT-0013; LOT-0014; LOT-0015; LOT-0016; LOT-0017; LOT-0018; LOT-0019; LOT-0020; LOT-0021; LOT-0022; LOT-0023; LOT-0024; LOT-0025; LOT-0026; LOT-0027; LOT-0028; LOT-0029; LOT-0030; LOT-0031; LOT-0032; LOT-0033; LOT-0034\nContrato adequado para PME: Sim\nCobertura ACP (Acordo dos Contratos Públicos da Organização Mundial do Comércio): Não\n27 - IDENTIFICAÇÃO E CONTACTOS DO ÓRGÃO DE RECURSOS ADMINISTRATIVOS\nDesignação: Uls Coimbra EPE.\nEndereço: Praceta Prof Mota Pinto\nCódigo postal: 3004-561\nLocalidade: Coimbra\nTelefone: +351 203400400\nFax: +351 239822291\nEndereço eletrónico: casec@ulscoimbra.min-saude.pt\n28 - IDENTIFICAÇÃO DO(S) AUTOR(ES) DE ANÚNCIO\nNome: Olga Maria Gomes Leitão\nCargo: Assistente Técnica\n419949391",
    "nipc": "510103448",
    "distrito": "Coimbra",
    "concelho": "Coimbra",
    "freguesia": "Todas",
    "site": "https://www.chuc.min-saude.pt",
    "email": "ana.rosete@ulscoimbra.min-saude.pt",
    "designacao_contrato": "REAGENTES P/O SERVIÇO DE ANATOMIA PATOLÓGICA/IMUNO-HEMOTERAPIA",
    "descricao": "REAGENTES P/O SERVIÇO DE ANATOMIA PATOLÓGICA/IMUNO-HEMOTERAPIA",
    "preco_base": "28.935,04 EUR",
    "prazo_execucao": "11 MESES",
    "prazo_apresentacao_propostas": "09-02-2026 17:00",
    "fundos_eu": "Não",
    "plataforma_eletronica": "VORTAL",
    "url_procedimento": "https://community.vortal.biz/public/",
    "autor_nome": "Olga Maria Gomes Leitão",
    "autor_cargo": "Assistente Técnica"
  },
  {
    "numero_procedimento": "N/A",
    "entidade": "AnÃºncio de procedimento  n.Âº 2022/2026  -  DiÃ¡rio da RepÃºblica n.Âº 20/2026, SÃ©rie II de 2026-01-29",
    "link": "https://diariodarepublica.pt/dr/detalhe/contrato-publico/2022-1028061001"
  },
  {
    "numero_procedimento": "N/A",
    "entidade": "AnÃºncio de procedimento  n.Âº 2023/2026  -  DiÃ¡rio da RepÃºblica n.Âº 20/2026, SÃ©rie II de 2026-01-29",
    "link": "https://diariodarepublica.pt/dr/detalhe/contrato-publico/2023-1028061002"
  },
  {
    "numero_procedimento": "N/A",
    "entidade": "AnÃºncio de procedimento  n.Âº 2024/2026  -  DiÃ¡rio da RepÃºblica n.Âº 20/2026, SÃ©rie II de 2026-01-29",
    "link": "https://diariodarepublica.pt/dr/detalhe/contrato-publico/2024-1028061004"
  },
  {
    "numero_procedimento": "N/A",
    "entidade": "AnÃºncio de procedimento  n.Âº 2029/2026  -  DiÃ¡rio da RepÃºblica n.Âº 20/2026, SÃ©rie II de 2026-01-29",
    "link": "https://diariodarepublica.pt/dr/detalhe/contrato-publico/2029-1028061008"
  },
  {
    "numero_procedimento": "N/A",
    "entidade": "Ágora - Cultura e Desporto do Porto, EM, SA",
    "link": "https://diariodarepublica.pt/dr/detalhe/contrato-publico/2030-1028061010",
    "detalhes_completos": "1 - IDENTIFICAÇÃO E CONTACTOS DA ENTIDADE ADJUDICANTE\nDesignação da entidade adjudicante: Ágora - Cultura e Desporto do Porto, EM, SA\nNIPC: 507718640\nServiço/Órgão/Pessoa de contacto: Conselho de Administração\nEndereço: Rua Bartolomeu Velho, 648\nCódigo postal: 4150-124\nLocalidade: Porto\nPaís: Portugal\nNUT III: PT11A\nDistrito: Porto\nConcelho: Porto\nFreguesia: União das Freguesias de Aldoar, Foz do Douro e Nevogilde\nTelefone: 226199860\nFax: 226199869\nEndereço da Entidade (URL): www.agoraporto.pt\nEndereço Eletrónico: geral@agoraporto.pt\neDelivery Gateway (URL): https://www.acingov.pt\nFunção da Organização: Adquirente\nNorma jurídica da Entidade Adjudicante: Organismo de direito público\nÁrea de atividade da Autoridade Adjudicante: Serviços públicos das administrações públicas\n2 - JORNAL OFICIAL DA UNIÃO EUROPEIA\nO procedimento a que este anúncio diz respeito também é publicitado no Jornal Oficial da União Europeia? Não\n3 - AVISO\nModelo de Anúncio: Concurso público\nData de Envio do Anúncio: 28-01-2026\n5 - PROCESSO\nTipo de Procedimento: Concurso público\nPreço base do procedimento: Sim\nValor do preço base do procedimento: 101.698,00 EUR\nProcedimento com lotes? Sim\nNº Máx. de Lotes Autorizado: 4\nNúmero máximo de lotes que podem ser adjudicados a um concorrente: 4\n6 - OBJETO DO CONTRATO\nNúmero de referência interna: CP/75/2025\nDesignação do contrato: Serviços de fotografia para o período que decorre de 01 de março 2026 a 31 de dezembro de 2026\nDescrição: Serviços de fotografia para o ano de 2026\nTipo de Contrato Principal: Aquisição de Serviços\nTipo de Contrato: Aquisição de Serviços\nClassificação CPV (Vocabulário Comum para os Contratos Públicos)\nObjeto principal\nVocabulário Principal: 79961000\nPreço base s/IVA: 101.698,00 EUR\nLotes: \nNº: LOT-0001\nDescrição do Lote: Serviços de fotografia -Eventos\nPreço base s/IVA: 34.167,00 EUR\nClassificação CPV (Vocabulário Comum para os Contratos Públicos)\nObjeto principal\nVocabulário Principal: 79961000\nNº: LOT-0002\nDescrição do Lote: Serviços de Fotografia - Cena\nPreço base s/IVA: 16.131,00 EUR\nClassificação CPV (Vocabulário Comum para os Contratos Públicos)\nObjeto principal\nVocabulário Principal: 79961000\nNº: LOT-0003\nDescrição do Lote: Serviços de Fotografia - Documental\nPreço base s/IVA: 40.400,00 EUR\nClassificação CPV (Vocabulário Comum para os Contratos Públicos)\nObjeto principal\nVocabulário Principal: 79961000\nNº: LOT-0004\nDescrição do Lote: Serviços de Fotografia - Exposições\nPreço base s/IVA: 11.000,00 EUR\nClassificação CPV (Vocabulário Comum para os Contratos Públicos)\nObjeto principal\nVocabulário Principal: 79961000\n7 - INDICAÇÕES ADICIONAIS\nO contrato envolve aquisição conjunta (satisfação de várias entidades)? Não\nO contrato é adjudicado por uma central de compras? Sim\n8 - TÉCNICAS\nO concurso destina-se à celebração de um acordo-quadro? Inexistência de acordo-quadro\nÉ utilizado um leilão eletrónico? Não\nÉ adotada uma fase de negociação? Não\nSistema de Aquisição Dinâmico: Inexistência de sistema de aquisição dinâmico\n9 - LOCAL DA EXECUÇÃO DO CONTRATO\nLOCAL DA EXECUÇÃO DO CONTRATO (PROCEDIMENTO)\nPaís: Portugal\nNUT III: PT11A\nLocalidade: Porto\nDistrito: Porto\nConcelho: Porto\nFreguesia: Todas\nLOCAL DA EXECUÇÃO DO CONTRATO (LOTE)\nIdentificador do Lote: LOT-0001; LOT-0002; LOT-0003; LOT-0004\nPaís: Portugal\nNUT III: PT11A\nLocalidade: Porto\nDistrito: Porto\nConcelho: Porto\nFreguesia: Todas\n10 - PRAZO DE EXECUÇÃO DO CONTRATO\nIdentificador do Lote: LOT-0001; LOT-0002; LOT-0003; LOT-0004\nPrazo de execução do contrato: 306 DIAS\nPrevisão de renovações: Não\n11 - FUNDOS EU\nIdentificador do Lote: LOT-0001; LOT-0002; LOT-0003; LOT-0004\nTêm fundos EU? Não\n12 - DOCUMENTOS DE HABILITAÇÃO\nHabilitação para o exercício da atividade profissional: Não\n13 - CONDIÇÕES DE APRESENTAÇÃO\nPlataforma eletrónica utilizada pela entidade adjudicante: ACIN\nURL para Apresentação: https://www.acingov.pt\nAdmissibilidade da apresentação de propostas variantes: Não autorizado\nPrazo para apresentação das propostas: 02-02-2026 17:00\nPrazo durante o qual os concorrentes são obrigados a manter as respetivas propostas: 66 dias a contar do termo do prazo para a apresentação das propostas\nIndicação de Subcontratação na Proposta: Inexistência de indicação de subcontratação\n14 - PRESTAÇÃO DE CAUÇÃO\nPrestação de caução: Não\n15 - FORNECIMENTO DAS PEÇAS DO CONCURSO, APRESENTAÇÃO DE PEDIDOS DE PARTICIPAÇÃO E APRESENTAÇÃO DAS PROPOSTAS\nLink para acesso às peças do concurso (URL): https://www.acingov.pt/acingovprod/2/zonaPublica/zona_publica_c/donwloadProcedurePiece/MTAwOTQwNA==\n20 - OUTROS REQUISITOS\nIdentificador do Lote: LOT-0001; LOT-0002; LOT-0003; LOT-0004\nInformação sobre contratos reservados. Aplica-se a contratos reservados (54º-A)? Não\n21 - CRITÉRIO DE ADJUDICAÇÃO\nO Critério de adjudicação é diferenciado por lote? Não\nMultifator: Sim\nFator: \nNome: Preço\nPonderação: 50%\nSubfatores: Não\nFator: \nNome: Outros\nOutro Nome: Valia Técnica\nPonderação: 50%\nSubfatores: Sim\nSubfatores: \nNome: Adequação do Portfólio do pessoal encarregado da execução do contrato\nPonderação : 70%; \nNome: Experiência do pessoal encarregado da execução do contrato\nPonderação : 30%; \n24 - CONDIÇÕES DO CONTRATO\nIdentificador do Lote: LOT-0001; LOT-0002; LOT-0003; LOT-0004\nFaturação Eletrónica: Permitido\nObrigação de Subcontratação:\nCódigo da Obrigação de Subcontratação: Não é aplicável nenhuma obrigação de subcontratação.\n25 - COMPRA PÚBLICA ESTRATÉGICA\nCompra Pública Estratégica: Inexistência de contratação pública estratégica\n26 - INFORMAÇÕES ADICIONAIS\nIdentificador do Lote: LOT-0001; LOT-0002; LOT-0003; LOT-0004\nContrato adequado para PME: Não\nCobertura ACP (Acordo dos Contratos Públicos da Organização Mundial do Comércio): Não\n27 - IDENTIFICAÇÃO E CONTACTOS DO ÓRGÃO DE RECURSOS ADMINISTRATIVOS\nDesignação: Conselho de Administração\nEndereço: Rua da Constituição 2555\nCódigo postal: 4250-173\nLocalidade: Porto\nTelefone: 226199860\nFax: \nEndereço eletrónico: geral@agoraporto.pt\n28 - IDENTIFICAÇÃO DO(S) AUTOR(ES) DE ANÚNCIO\nNome: Beatriz Penedo de Freitas Radiche Leite\nCargo: Técnica superior\n419949114",
    "nipc": "507718640",
    "distrito": "Porto",
    "concelho": "Porto",
    "freguesia": "União das Freguesias de Aldoar, Foz do Douro e Nevogilde",
    "site": "www.agoraporto.pt",
    "email": "geral@agoraporto.pt",
    "designacao_contrato": "Serviços de fotografia para o período que decorre de 01 de março 2026 a 31 de dezembro de 2026",
    "descricao": "Serviços de fotografia para o ano de 2026",
    "preco_base": "101.698,00 EUR",
    "prazo_execucao": "306 DIAS",
    "prazo_apresentacao_propostas": "02-02-2026 17:00",
    "fundos_eu": "Não",
    "plataforma_eletronica": "ACIN",
    "url_procedimento": "https://www.acingov.pt",
    "autor_nome": "Beatriz Penedo de Freitas Radiche Leite",
    "autor_cargo": "Técnica superior"
  },
  {
    "numero_procedimento": "N/A",
    "entidade": "Agrupamento de Escolas Eng. Duarte Pacheco, Loulé",
    "link": "https://diariodarepublica.pt/dr/detalhe/contrato-publico/2031-1028146474",
    "detalhes_completos": "1 - IDENTIFICAÇÃO E CONTACTOS DA ENTIDADE ADJUDICANTE\nDesignação da entidade adjudicante: Agrupamento de Escolas Eng. Duarte Pacheco, Loulé\nNIPC: 600081281\nEndereço: Rua José António Madeira - Apartado 193\nCódigo postal: 8100-670\nLocalidade: Faro\nPaís: Portugal\nNUT III: PT150\nDistrito: Faro\nConcelho: Loulé\nFreguesia: Freguesia de Loulé (São Sebastião)\nTelefone: 289373600\nEndereço da Entidade (URL): https://aedpacheco.pt/\nEndereço Eletrónico: agrupamento@aedpacheco.edu.pt\neDelivery Gateway (URL): https://community.vortal.biz/public/\nFunção da Organização: Adquirente\nNorma jurídica da Entidade Adjudicante: Organismo de direito público\nÁrea de atividade da Autoridade Adjudicante: Educação\n2 - JORNAL OFICIAL DA UNIÃO EUROPEIA\nO procedimento a que este anúncio diz respeito também é publicitado no Jornal Oficial da União Europeia? Não\n3 - AVISO\nModelo de Anúncio: Concurso público\nData de Envio do Anúncio: 28-01-2026\n5 - PROCESSO\nTipo de Procedimento: Concurso público\nPreço base do procedimento: Sim\nValor do preço base do procedimento: 105.874,00 EUR\nProcedimento com lotes? Sim\nNº Máx. de Lotes Autorizado: 2\nNúmero máximo de lotes que podem ser adjudicados a um concorrente: 2\n6 - OBJETO DO CONTRATO\nNúmero de referência interna: Conc_Publ_02_2026\nDesignação do contrato: CONCURSO PÚBLICO PARA A CELEBRAÇÃO DE CONTRATOS PARA A AQUISIÇÃO CONTINUADA DE PEIXE CONGELADO E LEGUMES CONGELADOS\nDescrição: CONCURSO PÚBLICO PARA A CELEBRAÇÃO DE CONTRATOS PARA A AQUISIÇÃO CONTINUADA DE PEIXE CONGELADO E LEGUMES CONGELADOS PARA AS ESCOLAS DO AGRUPAMENTO DE ESCOLAS ENGENHEIRO DUARTE PACHECO.\nTipo de Contrato Principal: Aquisição de Bens Móveis\nTipo de Contrato: Aquisição de Bens Móveis\nClassificação CPV (Vocabulário Comum para os Contratos Públicos)\nObjeto principal\nVocabulário Principal: 15220000\nPreço base s/IVA: 103.141,00 EUR\nObjeto Complementar\nVocabulário Principal: 15331170\nPreço base s/IVA: 2.733,00 EUR\nLotes: \nNº: LOT-0001\nDescrição do Lote: Lote 1 - Peixe Congelado\nPreço base s/IVA: 103.141,00 EUR\nClassificação CPV (Vocabulário Comum para os Contratos Públicos)\nObjeto principal\nVocabulário Principal: 15220000\nObjeto Complementar\nVocabulário Principal: 15331170\nNº: LOT-0002\nDescrição do Lote: Lote 2 - Produtos Hortícolas Congelados\nPreço base s/IVA: 2.733,00 EUR\nClassificação CPV (Vocabulário Comum para os Contratos Públicos)\nObjeto principal\nVocabulário Principal: 15220000\nObjeto Complementar\nVocabulário Principal: 15331170\n7 - INDICAÇÕES ADICIONAIS\nO contrato envolve aquisição conjunta (satisfação de várias entidades)? Não\nO contrato é adjudicado por uma central de compras? Não\n8 - TÉCNICAS\nO concurso destina-se à celebração de um acordo-quadro? Inexistência de acordo-quadro\nÉ utilizado um leilão eletrónico? Não\nÉ adotada uma fase de negociação? Não\nSistema de Aquisição Dinâmico: Inexistência de sistema de aquisição dinâmico\n9 - LOCAL DA EXECUÇÃO DO CONTRATO\nLOCAL DA EXECUÇÃO DO CONTRATO (PROCEDIMENTO)\nPaís: Portugal\nNUT III: PT150\nLocalidade: Faro\nDistrito: Faro\nConcelho: Loulé\nFreguesia: Todas\nLOCAL DA EXECUÇÃO DO CONTRATO (LOTE)\nIdentificador do Lote: LOT-0001; LOT-0002\nPaís: Portugal\nNUT III: PT150\nLocalidade: Faro\nDistrito: Faro\nConcelho: Loulé\nFreguesia: Todas\n10 - PRAZO DE EXECUÇÃO DO CONTRATO\nIdentificador do Lote: LOT-0001; LOT-0002\nPrazo de execução do contrato: 1 ANOS\nPrevisão de renovações: Não\n11 - FUNDOS EU\nIdentificador do Lote: LOT-0001; LOT-0002\nTêm fundos EU? Não\n12 - DOCUMENTOS DE HABILITAÇÃO\nHabilitação para o exercício da atividade profissional: Não\n13 - CONDIÇÕES DE APRESENTAÇÃO\nPlataforma eletrónica utilizada pela entidade adjudicante: VORTAL\nURL para Apresentação: https://community.vortal.biz/public/\nAdmissibilidade da apresentação de propostas variantes: Não autorizado\nPrazo para apresentação das propostas: 04-02-2026 23:59\nPrazo durante o qual os concorrentes são obrigados a manter as respetivas propostas: 66 dias a contar do termo do prazo para a apresentação das propostas\nIndicação de Subcontratação na Proposta: Inexistência de indicação de subcontratação\n14 - PRESTAÇÃO DE CAUÇÃO\nPrestação de caução: Não\n15 - FORNECIMENTO DAS PEÇAS DO CONCURSO, APRESENTAÇÃO DE PEDIDOS DE PARTICIPAÇÃO E APRESENTAÇÃO DAS PROPOSTAS\nLink para acesso às peças do concurso (URL): https://community.vortal.biz/Public/public-tender-documents/Rmd6bkQ5TWl0K2F0QU9iQWxlY2dvOGxBemcyLzZEK2NIM0ZYdm91bEVsaVMvcDVFR0pGRHB6UjJxWEhUaEE4bGRCdWtPd0JOMXRuR1FIaHcrNmZFWWc9PVQjOEh5\n20 - OUTROS REQUISITOS\nIdentificador do Lote: LOT-0001; LOT-0002\nInformação sobre contratos reservados. Aplica-se a contratos reservados (54º-A)? Não\n21 - CRITÉRIO DE ADJUDICAÇÃO\nO Critério de adjudicação é diferenciado por lote? Não\nMultifator: Não\nMonofator:\nNome: Preço\n24 - CONDIÇÕES DO CONTRATO\nIdentificador do Lote: LOT-0001; LOT-0002\nFaturação Eletrónica: Permitido\nObrigação de Subcontratação:\nCódigo da Obrigação de Subcontratação: Não é aplicável nenhuma obrigação de subcontratação.\n25 - COMPRA PÚBLICA ESTRATÉGICA\nCompra Pública Estratégica: Inexistência de contratação pública estratégica\n26 - INFORMAÇÕES ADICIONAIS\nIdentificador do Lote: LOT-0001; LOT-0002\nContrato adequado para PME: Sim\nCobertura ACP (Acordo dos Contratos Públicos da Organização Mundial do Comércio): Não\n27 - IDENTIFICAÇÃO E CONTACTOS DO ÓRGÃO DE RECURSOS ADMINISTRATIVOS\nDesignação: Conselho Administrativo do Agrupamento de Escolas Engenheiro Duarte Pacheco\nEndereço: Rua José António Madeira\nCódigo postal: 8100-670\nLocalidade: Loulé\nTelefone: +351 289373600\nFax: +351 289373600\nEndereço eletrónico: agrupamento@aedpacheco.edu.pt\n28 - IDENTIFICAÇÃO DO(S) AUTOR(ES) DE ANÚNCIO\nNome: Carlos Alberto Antunes Fernandes\nCargo: Diretor do Agrupamento\n419949413",
    "nipc": "600081281",
    "distrito": "Faro",
    "concelho": "Loulé",
    "freguesia": "Freguesia de Loulé (São Sebastião)",
    "site": "https://aedpacheco.pt/",
    "email": "agrupamento@aedpacheco.edu.pt",
    "designacao_contrato": "CONCURSO PÚBLICO PARA A CELEBRAÇÃO DE CONTRATOS PARA A AQUISIÇÃO CONTINUADA DE PEIXE CONGELADO E LEGUMES CONGELADOS",
    "descricao": "CONCURSO PÚBLICO PARA A CELEBRAÇÃO DE CONTRATOS PARA A AQUISIÇÃO CONTINUADA DE PEIXE CONGELADO E LEGUMES CONGELADOS PARA AS ESCOLAS DO AGRUPAMENTO DE ESCOLAS ENGENHEIRO DUARTE PACHECO.",
    "preco_base": "103.141,00 EUR",
    "prazo_execucao": "1 ANOS",
    "prazo_apresentacao_propostas": "04-02-2026 23:59",
    "fundos_eu": "Não",
    "plataforma_eletronica": "VORTAL",
    "url_procedimento": "https://community.vortal.biz/public/",
    "autor_nome": "Carlos Alberto Antunes Fernandes",
    "autor_cargo": "Diretor do Agrupamento"
  },
  {
    "numero_procedimento": "N/A",
    "entidade": "AnÃºncio de procedimento  n.Âº 2033/2026  -  DiÃ¡rio da RepÃºblica n.Âº 20/2026, SÃ©rie II de 2026-01-29",
    "link": "https://diariodarepublica.pt/dr/detalhe/contrato-publico/2033-1028852136"
  },
  {
    "numero_procedimento": "N/A",
    "entidade": "Unidade Local de Saúde da Região de Leiria, EPE",
    "link": "https://diariodarepublica.pt/dr/detalhe/contrato-publico/2035-1028852137",
    "detalhes_completos": "Alteração do Anúncio de procedimento n.º 1650/2026, de 2026-01-26, com o ID 419948494\n1 - IDENTIFICAÇÃO E CONTACTOS DA ENTIDADE ADJUDICANTE\nDesignação da entidade adjudicante: Unidade Local de Saúde da Região de Leiria, EPE\nNIPC: 509822932\nEndereço: Rua das Olhalvas, Pousos\nCódigo postal: 2410-197\nLocalidade: Leiria\nPaís: Portugal\nNUT III: PT16F\nDistrito: Leiria\nConcelho: Leiria\nFreguesia: União das Freguesias de Leiria, Pousos, Barreira e Cortes\nTelefone: 244817010\nEndereço da Entidade (URL): https://www.ulsrl.min-saude.pt\nEndereço Eletrónico: aprovisionamento.geral@ulsrl.min-saude.pt\neDelivery Gateway (URL): https://community.vortal.biz/public/\nFunção da Organização: Adquirente\nNorma jurídica da Entidade Adjudicante: Empresa pública, controlada por uma autoridade da administração central\nÁrea de atividade da Autoridade Adjudicante: Saúde\n2 - JORNAL OFICIAL DA UNIÃO EUROPEIA\nO procedimento a que este anúncio diz respeito também é publicitado no Jornal Oficial da União Europeia? Sim\n3 - AVISO\nModelo de Anúncio: Concurso público\nData de Envio do Anúncio: 27-01-2026\n5 - PROCESSO\nTipo de Procedimento: Concurso público\nPreço base do procedimento: Sim\nValor do preço base do procedimento: 347.719,20 EUR\nProcedimento com lotes? Sim\nNº Máx. de Lotes Autorizado: 2\nNúmero máximo de lotes que podem ser adjudicados a um concorrente: 2\n6 - OBJETO DO CONTRATO\nNúmero de referência interna: A1/86/2026 - Soluções e consumíveis hemofiltração Cópia\nDesignação do contrato: A1/86/2026 - Soluções e consumíveis hemofiltração\nDescrição: A1/86/2026 - Soluções e consumíveis hemofiltração\nOpções: Não\nTipo de Contrato Principal: Aquisição de Bens Móveis\nTipo de Contrato: Aquisição de Bens Móveis\nClassificação CPV (Vocabulário Comum para os Contratos Públicos)\nObjeto principal\nVocabulário Principal: 33600000\nPreço base s/IVA: 347.719,20 EUR\nLotes: \nNº: LOT-0001\nDescrição do Lote: Lote 1\nPreço base s/IVA: 317.969,20 EUR\nClassificação CPV (Vocabulário Comum para os Contratos Públicos)\nObjeto principal\nVocabulário Principal: 33600000\nNº: LOT-0002\nDescrição do Lote: Lote 2\nPreço base s/IVA: 29.750,00 EUR\nClassificação CPV (Vocabulário Comum para os Contratos Públicos)\nObjeto principal\nVocabulário Principal: 33600000\n7 - INDICAÇÕES ADICIONAIS\nO contrato envolve aquisição conjunta (satisfação de várias entidades)? Não\nO contrato é adjudicado por uma central de compras? Não\n8 - TÉCNICAS\nO concurso destina-se à celebração de um acordo-quadro? Inexistência de acordo-quadro\nÉ utilizado um leilão eletrónico? Não\nÉ adotada uma fase de negociação? Não\nSistema de Aquisição Dinâmico: Inexistência de sistema de aquisição dinâmico\n9 - LOCAL DA EXECUÇÃO DO CONTRATO\nLOCAL DA EXECUÇÃO DO CONTRATO (PROCEDIMENTO)\nPaís: Portugal\nNUT III: PT16F\nLocalidade: Leiria\nDistrito: Leiria\nConcelho: Leiria\nFreguesia: Todas\nLOCAL DA EXECUÇÃO DO CONTRATO (LOTE)\nIdentificador do Lote: LOT-0001; LOT-0002\nPaís: Portugal\nNUT III: PT16F\nLocalidade: Leiria\nDistrito: Leiria\nConcelho: Leiria\nFreguesia: Todas\n10 - PRAZO DE EXECUÇÃO DO CONTRATO\nIdentificador do Lote: LOT-0001; LOT-0002\nPrazo de execução do contrato: 36 MESES\nPrevisão de renovações: Não\n11 - FUNDOS EU\nIdentificador do Lote: LOT-0001; LOT-0002\nTêm fundos EU? Não\n12 - DOCUMENTOS DE HABILITAÇÃO\nHabilitação para o exercício da atividade profissional: Não\n13 - CONDIÇÕES DE APRESENTAÇÃO\nPlataforma eletrónica utilizada pela entidade adjudicante: VORTAL\nURL para Apresentação: https://community.vortal.biz/public/\nAdmissibilidade da apresentação de propostas variantes: Não autorizado\nPrazo para apresentação das propostas: 20-02-2026 18:00\nPrazo durante o qual os concorrentes são obrigados a manter as respetivas propostas: 90 dias a contar do termo do prazo para a apresentação das propostas\nApresentação de Catálogo Eletrónico: Necessário\nIndicação de Subcontratação na Proposta: Inexistência de indicação de subcontratação\n14 - PRESTAÇÃO DE CAUÇÃO\nPrestação de caução: Não\n15 - FORNECIMENTO DAS PEÇAS DO CONCURSO, APRESENTAÇÃO DE PEDIDOS DE PARTICIPAÇÃO E APRESENTAÇÃO DAS PROPOSTAS\nLink para acesso às peças do concurso (URL): https://community.vortal.biz/Public/public-tender-documents/WjBmUEc5T1NTSnFYQ1RvTk9BVjFxUTBmK2JGOFZNMVM3R2M2RWxxMnhJbXgzaTYyc1pEdkdoRGZOR2tSWnplN3RtTThyRC84aDlmRzBYenRLOXRHS1E9PXZoTGpG\n20 - OUTROS REQUISITOS\nIdentificador do Lote: LOT-0001; LOT-0002\nInformação sobre contratos reservados. Aplica-se a contratos reservados (54º-A)? Não\n21 - CRITÉRIO DE ADJUDICAÇÃO\nO Critério de adjudicação é diferenciado por lote? Não\nMultifator: Não\nMonofator:\nNome: Preço\n24 - CONDIÇÕES DO CONTRATO\nIdentificador do Lote: LOT-0001; LOT-0002\nFaturação Eletrónica: Permitido\nObrigação de Subcontratação:\nCódigo da Obrigação de Subcontratação: Não é aplicável nenhuma obrigação de subcontratação.\n25 - COMPRA PÚBLICA ESTRATÉGICA\nCompra Pública Estratégica: Inexistência de contratação pública estratégica\n26 - INFORMAÇÕES ADICIONAIS\nIdentificador do Lote: LOT-0001; LOT-0002\nContrato adequado para PME: Sim\nCobertura ACP (Acordo dos Contratos Públicos da Organização Mundial do Comércio): Não\n27 - IDENTIFICAÇÃO E CONTACTOS DO ÓRGÃO DE RECURSOS ADMINISTRATIVOS\nDesignação: Conselho de Administração\nEndereço: Rua das Olhavas\nCódigo postal: 2410-266\nLocalidade: Leiria\nTelefone: +351 244817000\nFax: +351 244817000\nEndereço eletrónico: secca@ulsrl.min-saude.pt\n28 - IDENTIFICAÇÃO DO(S) AUTOR(ES) DE ANÚNCIO\nNome: Manuel Jose de Carvalho\nCargo: Presidente Conselho de Administração\n29 - ALTERAÇÃO\nMotivo da Alteração: Correção pelo editor\nIdentificador da Versão do Anúncio a Alterar: d608d276-4bd9-43ab-89fd-a5a580d33abd-01\nIdentificador das Secções Alteradas do Anúncio Anterior: Objeto do contrato\nDescrição das Alterações: Alteração das datas de publicação\nAlteração dos Documentos do Concurso: Não\n419949066",
    "nipc": "509822932",
    "distrito": "Leiria",
    "concelho": "Leiria",
    "freguesia": "União das Freguesias de Leiria, Pousos, Barreira e Cortes",
    "site": "https://www.ulsrl.min-saude.pt",
    "email": "aprovisionamento.geral@ulsrl.min-saude.pt",
    "designacao_contrato": "A1/86/2026 - Soluções e consumíveis hemofiltração",
    "descricao": "A1/86/2026 - Soluções e consumíveis hemofiltração",
    "preco_base": "347.719,20 EUR",
    "prazo_execucao": "36 MESES",
    "prazo_apresentacao_propostas": "20-02-2026 18:00",
    "fundos_eu": "Não",
    "plataforma_eletronica": "VORTAL",
    "url_procedimento": "https://community.vortal.biz/public/",
    "autor_nome": "Manuel Jose de Carvalho",
    "autor_cargo": "Presidente Conselho de Administração"
  },
  {
    "numero_procedimento": "N/A",
    "entidade": "AnÃºncio de procedimento  n.Âº 2037/2026  -  DiÃ¡rio da RepÃºblica n.Âº 20/2026, SÃ©rie II de 2026-01-29",
    "link": "https://diariodarepublica.pt/dr/detalhe/contrato-publico/2037-1028852138"
  },
  {
    "numero_procedimento": "N/A",
    "entidade": "AnÃºncio de procedimento  n.Âº 2039/2026  -  DiÃ¡rio da RepÃºblica n.Âº 20/2026, SÃ©rie II de 2026-01-29",
    "link": "https://diariodarepublica.pt/dr/detalhe/contrato-publico/2039-1028852139"
  },
  {
    "numero_procedimento": "N/A",
    "entidade": "AnÃºncio de procedimento  n.Âº 2041/2026  -  DiÃ¡rio da RepÃºblica n.Âº 20/2026, SÃ©rie II de 2026-01-29",
    "link": "https://diariodarepublica.pt/dr/detalhe/contrato-publico/2041-1028852140"
  },
  {
    "numero_procedimento": "N/A",
    "entidade": "AnÃºncio de procedimento  n.Âº 2043/2026  -  DiÃ¡rio da RepÃºblica n.Âº 20/2026, SÃ©rie II de 2026-01-29",
    "link": "https://diariodarepublica.pt/dr/detalhe/contrato-publico/2043-1028852141"
  },
  {
    "numero_procedimento": "N/A",
    "entidade": "AnÃºncio de procedimento  n.Âº 2045/2026  -  DiÃ¡rio da RepÃºblica n.Âº 20/2026, SÃ©rie II de 2026-01-29",
    "link": "https://diariodarepublica.pt/dr/detalhe/contrato-publico/2045-1028852142"
  },
  {
    "numero_procedimento": "N/A",
    "entidade": "AnÃºncio de procedimento  n.Âº 2047/2026  -  DiÃ¡rio da RepÃºblica n.Âº 20/2026, SÃ©rie II de 2026-01-29",
    "link": "https://diariodarepublica.pt/dr/detalhe/contrato-publico/2047-1028852143"
  },
  {
    "numero_procedimento": "N/A",
    "entidade": "AnÃºncio de procedimento  n.Âº 2049/2026  -  DiÃ¡rio da RepÃºblica n.Âº 20/2026, SÃ©rie II de 2026-01-29",
    "link": "https://diariodarepublica.pt/dr/detalhe/contrato-publico/2049-1028852144"
  },
  {
    "numero_procedimento": "N/A",
    "entidade": "AnÃºncio de procedimento  n.Âº 2051/2026  -  DiÃ¡rio da RepÃºblica n.Âº 20/2026, SÃ©rie II de 2026-01-29",
    "link": "https://diariodarepublica.pt/dr/detalhe/contrato-publico/2051-1028852145"
  },
  {
    "numero_procedimento": "N/A",
    "entidade": "AnÃºncio de procedimento  n.Âº 2053/2026  -  DiÃ¡rio da RepÃºblica n.Âº 20/2026, SÃ©rie II de 2026-01-29",
    "link": "https://diariodarepublica.pt/dr/detalhe/contrato-publico/2053-1028852146"
  },
  {
    "numero_procedimento": "N/A",
    "entidade": "Autoridade Nacional de Emergência e Proteção Civil",
    "link": "https://diariodarepublica.pt/dr/detalhe/contrato-publico/2055-1028852147",
    "detalhes_completos": "1 - IDENTIFICAÇÃO E CONTACTOS DA ENTIDADE ADJUDICANTE\nDesignação da entidade adjudicante: Autoridade Nacional de Emergência e Proteção Civil\nNIPC: 600082490\nEndereço: Av. Do Forte\nCódigo postal: 2794-112\nLocalidade: Oeiras\nPaís: Portugal\nNUT III: PT170\nDistrito: Lisboa\nConcelho: Oeiras\nFreguesia: Todas\nTelefone: 214247100\nFax: 214247180\nEndereço da Entidade (URL): www.prociv.pt\nEndereço Eletrónico: geral@prociv.pt\neDelivery Gateway (URL): https://community.vortal.biz/public/\nFunção da Organização: Adquirente\nNorma jurídica da Entidade Adjudicante: Autoridade da administração central\nÁrea de atividade da Autoridade Adjudicante: Segurança e ordem pública\n2 - JORNAL OFICIAL DA UNIÃO EUROPEIA\nO procedimento a que este anúncio diz respeito também é publicitado no Jornal Oficial da União Europeia? Sim\n3 - AVISO\nModelo de Anúncio: Concurso público\nData de Envio do Anúncio: 27-01-2026\n5 - PROCESSO\nTipo de Procedimento: Concurso público\nPreço base do procedimento: Sim\nValor do preço base do procedimento: 383.940,00 EUR\nProcedimento com lotes? Não\n6 - OBJETO DO CONTRATO\nNúmero de referência interna: 66/ANEPC/2025\nDesignação do contrato: Aquisição de serviços de comunicações via satélite\nDescrição: Aquisição de serviços de comunicações via satélite\nOpções: Não\nTipo de Contrato Principal: Aquisição de Serviços\nTipo de Contrato: Aquisição de Serviços\nClassificação CPV (Vocabulário Comum para os Contratos Públicos)\nObjeto principal\nVocabulário Principal: 64200000\nPreço base s/IVA: 383.940,00 EUR\n7 - INDICAÇÕES ADICIONAIS\nO contrato envolve aquisição conjunta (satisfação de várias entidades)? Não\nO contrato é adjudicado por uma central de compras? Não\n8 - TÉCNICAS\nO concurso destina-se à celebração de um acordo-quadro? Inexistência de acordo-quadro\nÉ utilizado um leilão eletrónico? Não\nÉ adotada uma fase de negociação? Não\nSistema de Aquisição Dinâmico: Inexistência de sistema de aquisição dinâmico\n9 - LOCAL DA EXECUÇÃO DO CONTRATO\nLOCAL DA EXECUÇÃO DO CONTRATO (PROCEDIMENTO)\nPaís: Portugal\nNUT III: PT170\nLocalidade: Lisboa\nDistrito: Lisboa\nConcelho: Oeiras\nFreguesia: Todas\n10 - PRAZO DE EXECUÇÃO DO CONTRATO\nPrazo de execução do contrato: 36 MESES\nPrevisão de renovações: Não\n11 - FUNDOS EU\nTêm fundos EU? Não\n12 - DOCUMENTOS DE HABILITAÇÃO\nHabilitação para o exercício da atividade profissional: Não\n13 - CONDIÇÕES DE APRESENTAÇÃO\nPlataforma eletrónica utilizada pela entidade adjudicante: VORTAL\nURL para Apresentação: https://community.vortal.biz/public/\nAdmissibilidade da apresentação de propostas variantes: Não autorizado\nPrazo para apresentação das propostas: 11-02-2026 23:59\nPrazo durante o qual os concorrentes são obrigados a manter as respetivas propostas: 180 dias a contar do termo do prazo para a apresentação das propostas\nApresentação de Catálogo Eletrónico: Não autorizado\nIndicação de Subcontratação na Proposta: Inexistência de indicação de subcontratação\n14 - PRESTAÇÃO DE CAUÇÃO\nPrestação de caução: Não\n15 - FORNECIMENTO DAS PEÇAS DO CONCURSO, APRESENTAÇÃO DE PEDIDOS DE PARTICIPAÇÃO E APRESENTAÇÃO DAS PROPOSTAS\nLink para acesso às peças do concurso (URL): https://community.vortal.biz/Public/public-tender-documents/dEJ4MzYrQkNmSzZWL2t6dVc4MDFXTzhGSGQveXVVcmtsZVFGS3RnQXVMV1hQczB4Y3phRG56aWw3OVl4ZlBXdDByT2JWODNmSC9MMXZRSWtRMkJ4Smc9PWNFTVAm\n20 - OUTROS REQUISITOS\nInformação sobre contratos reservados. Aplica-se a contratos reservados (54º-A)? Não\n21 - CRITÉRIO DE ADJUDICAÇÃO\nMultifator: Não\nMonofator:\nNome: Preço\n24 - CONDIÇÕES DO CONTRATO\nFaturação Eletrónica: Permitido\nObrigação de Subcontratação:\nCódigo da Obrigação de Subcontratação: Não é aplicável nenhuma obrigação de subcontratação.\n25 - COMPRA PÚBLICA ESTRATÉGICA\nCompra Pública Estratégica: Inexistência de contratação pública estratégica\n26 - INFORMAÇÕES ADICIONAIS\nContrato adequado para PME: Sim\nCobertura ACP (Acordo dos Contratos Públicos da Organização Mundial do Comércio): Não\n27 - IDENTIFICAÇÃO E CONTACTOS DO ÓRGÃO DE RECURSOS ADMINISTRATIVOS\nDesignação: Secretário de Estado da Proteção Civil\nEndereço: Praça do Comércio\nCódigo postal: 1149-015\nLocalidade: Lisboa\nTelefone: +351 213233000\nFax: +351 213233000\nEndereço eletrónico: gabinete.sepc@mai.gov.pt\n28 - IDENTIFICAÇÃO DO(S) AUTOR(ES) DE ANÚNCIO\nNome: José Manuel Moura\nCargo: Presidente da ANEPC\n419949174",
    "nipc": "600082490",
    "distrito": "Lisboa",
    "concelho": "Oeiras",
    "freguesia": "Todas",
    "site": "www.prociv.pt",
    "email": "geral@prociv.pt",
    "designacao_contrato": "Aquisição de serviços de comunicações via satélite",
    "descricao": "Aquisição de serviços de comunicações via satélite",
    "preco_base": "383.940,00 EUR",
    "prazo_execucao": "36 MESES",
    "prazo_apresentacao_propostas": "11-02-2026 23:59",
    "fundos_eu": "Não",
    "plataforma_eletronica": "VORTAL",
    "url_procedimento": "https://community.vortal.biz/public/",
    "autor_nome": "José Manuel Moura",
    "autor_cargo": "Presidente da ANEPC"
  },
  {
    "numero_procedimento": "N/A",
    "entidade": "AnÃºncio de procedimento  n.Âº 2057/2026  -  DiÃ¡rio da RepÃºblica n.Âº 20/2026, SÃ©rie II de 2026-01-29",
    "link": "https://diariodarepublica.pt/dr/detalhe/contrato-publico/2057-1028852148"
  },
  {
    "numero_procedimento": "N/A",
    "entidade": "Município de Caminha",
    "link": "https://diariodarepublica.pt/dr/detalhe/contrato-publico/2059-1028852149",
    "detalhes_completos": "1 - IDENTIFICAÇÃO E CONTACTOS DA ENTIDADE ADJUDICANTE\nDesignação da entidade adjudicante: Município de Caminha\nNIPC: 500843139\nServiço/Órgão/Pessoa de contacto: Gabinete de Candidaturas, Empreitadas e Aprovisionamento\nEndereço: Largo Calouste Gulbenkian\nCódigo postal: 4910-113\nLocalidade: Caminha\nPaís: Portugal\nNUT III: PTZZZ\nDistrito: Todos\nConcelho: Todos\nFreguesia: Todas\nTelefone: 258710300\nFax: 258710319\nEndereço da Entidade (URL): www.cm-caminha.pt\nEndereço Eletrónico: geral@cm-caminha.pt\neDelivery Gateway (URL): https://www.acingov.pt\nFunção da Organização: Adquirente\nNorma jurídica da Entidade Adjudicante: Organismo de direito público\nÁrea de atividade da Autoridade Adjudicante: Serviços públicos das administrações públicas\n2 - JORNAL OFICIAL DA UNIÃO EUROPEIA\nO procedimento a que este anúncio diz respeito também é publicitado no Jornal Oficial da União Europeia? Sim\n3 - AVISO\nModelo de Anúncio: Concurso público\nData de Envio do Anúncio: 27-01-2026\n5 - PROCESSO\nTipo de Procedimento: Concurso público\nPreço base do procedimento: Sim\nValor do preço base do procedimento: 250.000,00 EUR\nProcedimento com lotes? Não\n6 - OBJETO DO CONTRATO\nNúmero de referência interna: 13/2026\nDesignação do contrato: Aquisição e gestão de matérias-primas para os refeitórios do Agrupamento de Escolas do concelho de Caminha\nDescrição: Aquisição e gestão de matérias-primas para os refeitórios do Agrupamento de Escolas do concelho de Caminha\nOpções: Não\nTipo de Contrato Principal: Aquisição de Bens Móveis\nTipo de Contrato: Aquisição de Bens Móveis\nClassificação CPV (Vocabulário Comum para os Contratos Públicos)\nObjeto principal\nVocabulário Principal: 15800000\nPreço base s/IVA: 250.000,00 EUR\n7 - INDICAÇÕES ADICIONAIS\nO contrato envolve aquisição conjunta (satisfação de várias entidades)? Não\nO contrato é adjudicado por uma central de compras? Não\n8 - TÉCNICAS\nO concurso destina-se à celebração de um acordo-quadro? Inexistência de acordo-quadro\nÉ utilizado um leilão eletrónico? Não\nÉ adotada uma fase de negociação? Não\nSistema de Aquisição Dinâmico: Inexistência de sistema de aquisição dinâmico\n9 - LOCAL DA EXECUÇÃO DO CONTRATO\nLOCAL DA EXECUÇÃO DO CONTRATO (PROCEDIMENTO)\nPaís: Portugal\nNUT III: PT111\nLocalidade: União das Freguesias de Caminha (Matriz) e Vilarelho\nDistrito: Viana do Castelo\nConcelho: Caminha\nFreguesia: Todas\n10 - PRAZO DE EXECUÇÃO DO CONTRATO\nData de Início: 02-03-2026\nData de Fim: 31-12-2026\nPrevisão de renovações: Não\n11 - FUNDOS EU\nTêm fundos EU? Não\n12 - DOCUMENTOS DE HABILITAÇÃO\nHabilitação para o exercício da atividade profissional: Não\n13 - CONDIÇÕES DE APRESENTAÇÃO\nPlataforma eletrónica utilizada pela entidade adjudicante: ACIN\nURL para Apresentação: https://www.acingov.pt\nAdmissibilidade da apresentação de propostas variantes: Não autorizado\nPrazo para apresentação das propostas: 02-03-2026 23:59\nPrazo durante o qual os concorrentes são obrigados a manter as respetivas propostas: 66 dias a contar do termo do prazo para a apresentação das propostas\nApresentação de Catálogo Eletrónico: Permitido\nIndicação de Subcontratação na Proposta: Inexistência de indicação de subcontratação\n14 - PRESTAÇÃO DE CAUÇÃO\nPrestação de caução: Sim\nPercentagem: 5%\nDescrição da Garantia Exigida: O valor da caução é de 5.00% do preço contratual.\n15 - FORNECIMENTO DAS PEÇAS DO CONCURSO, APRESENTAÇÃO DE PEDIDOS DE PARTICIPAÇÃO E APRESENTAÇÃO DAS PROPOSTAS\nLink para acesso às peças do concurso (URL): https://www.acingov.pt/acingovprod/2/zonaPublica/zona_publica_c/donwloadProcedurePiece/MTA1MDc1Mw==\n20 - OUTROS REQUISITOS\nInformação sobre contratos reservados. Aplica-se a contratos reservados (54º-A)? Não\n21 - CRITÉRIO DE ADJUDICAÇÃO\nMultifator: Não\nMonofator:\nNome: Preço\n24 - CONDIÇÕES DO CONTRATO\nFaturação Eletrónica: Permitido\nObrigação de Subcontratação:\nCódigo da Obrigação de Subcontratação: Não é aplicável nenhuma obrigação de subcontratação.\n25 - COMPRA PÚBLICA ESTRATÉGICA\nCompra Pública Estratégica: Inexistência de contratação pública estratégica\n26 - INFORMAÇÕES ADICIONAIS\nContrato adequado para PME: Não\nCobertura ACP (Acordo dos Contratos Públicos da Organização Mundial do Comércio): Não\n27 - IDENTIFICAÇÃO E CONTACTOS DO ÓRGÃO DE RECURSOS ADMINISTRATIVOS\nDesignação: Tribunal Administrativo e Fiscal de Braga\nEndereço: Rua de Damão, n.º 220\nCódigo postal: 4710-232\nLocalidade: Braga\nTelefone: 253208800\nFax: 213506000\nEndereço eletrónico: braga.taf@tribunais.org.pt\n28 - IDENTIFICAÇÃO DO(S) AUTOR(ES) DE ANÚNCIO\nNome: Ana Veloso Dourado Ferreira\nCargo: Chefe da Divisão de Administração e Finanças Municipais\n419949193",
    "nipc": "500843139",
    "distrito": "Todos",
    "concelho": "Todos",
    "freguesia": "Todas",
    "site": "www.cm-caminha.pt",
    "email": "geral@cm-caminha.pt",
    "designacao_contrato": "Aquisição e gestão de matérias-primas para os refeitórios do Agrupamento de Escolas do concelho de Caminha",
    "descricao": "Aquisição e gestão de matérias-primas para os refeitórios do Agrupamento de Escolas do concelho de Caminha",
    "preco_base": "250.000,00 EUR",
    "prazo_execucao": null,
    "prazo_apresentacao_propostas": "02-03-2026 23:59",
    "fundos_eu": "Não",
    "plataforma_eletronica": "ACIN",
    "url_procedimento": "https://www.acingov.pt",
    "autor_nome": "Ana Veloso Dourado Ferreira",
    "autor_cargo": "Chefe da Divisão de Administração e Finanças Municipais"
  },
  {
    "numero_procedimento": "N/A",
    "entidade": "AnÃºncio de procedimento  n.Âº 2061/2026  -  DiÃ¡rio da RepÃºblica n.Âº 20/2026, SÃ©rie II de 2026-01-29",
    "link": "https://diariodarepublica.pt/dr/detalhe/contrato-publico/2061-1028852150"
  },
  {
    "numero_procedimento": "N/A",
    "entidade": "AnÃºncio de procedimento  n.Âº 2063/2026  -  DiÃ¡rio da RepÃºblica n.Âº 20/2026, SÃ©rie II de 2026-01-29",
    "link": "https://diariodarepublica.pt/dr/detalhe/contrato-publico/2063-1028852151"
  },
  {
    "numero_procedimento": "N/A",
    "entidade": "AnÃºncio de procedimento  n.Âº 2065/2026  -  DiÃ¡rio da RepÃºblica n.Âº 20/2026, SÃ©rie II de 2026-01-29",
    "link": "https://diariodarepublica.pt/dr/detalhe/contrato-publico/2065-1028852152"
  },
  {
    "numero_procedimento": "N/A",
    "entidade": "Secretaria-Geral do Governo",
    "link": "https://diariodarepublica.pt/dr/detalhe/contrato-publico/2067-1028852153",
    "detalhes_completos": "1 - IDENTIFICAÇÃO E CONTACTOS DA ENTIDADE ADJUDICANTE\nDesignação da entidade adjudicante: Secretaria-Geral do Governo\nNIPC: 600088103\nServiço/Órgão/Pessoa de contacto: Secretaria Geral do Governo\nEndereço: Avenida João XXI, 63\nCódigo postal: 1000-300\nLocalidade: Lisboa\nPaís: Portugal\nNUT III: PT170\nDistrito: Lisboa\nConcelho: Todos\nFreguesia: Todas\nTelefone: 969762129\nEndereço da Entidade (URL): https://www.sg.pcm.gov.pt\nEndereço Eletrónico: contratacao@sggoverno.gov.pt\neDelivery Gateway (URL): https://www.acingov.pt\nFunção da Organização: Adquirente\nSubfunção da Organização: Organização cujo orçamento é utilizado para pagar o contrato; Organização que executa o pagamento; Organização que fornece informações adicionais sobre o processo de adjudicação; Organização que fornece mais informações sobre os prazos dos procedimentos de recurso; Organização responsável pelo tratamento das propostas; Organização que recebe as propostas; Organização que trata os pedidos de participação; Organização que recebe pedidos de participação; Organização que fornece mais informações sobre os procedimentos de recurso; Organização que assina o contrato\nNorma jurídica da Entidade Adjudicante: Organismo de direito público\nÁrea de atividade da Autoridade Adjudicante: Serviços públicos das administrações públicas\n2 - JORNAL OFICIAL DA UNIÃO EUROPEIA\nO procedimento a que este anúncio diz respeito também é publicitado no Jornal Oficial da União Europeia? Sim\n3 - AVISO\nModelo de Anúncio: Concurso público\nData de Envio do Anúncio: 27-01-2026\n5 - PROCESSO\nTipo de Procedimento: Concurso público\nPreço base do procedimento: Sim\nValor do preço base do procedimento: 1.149.984,00 EUR\nProcedimento com lotes? Sim\nNº Máx. de Lotes Autorizado: 4\nNúmero máximo de lotes que podem ser adjudicados a um concorrente: 4\n6 - OBJETO DO CONTRATO\nNúmero de referência interna: CP/1042/2025\nDesignação do contrato: Aquisição de serviços de desenvolvimento aplicacional e de manutenção das aplicações e ferramentas informáticas que suportam os Sistemas de Informação associados à atividade do COMPETE 2030 e dos Sistemas de Incentivos dos Programas do PT2030\nDescrição: Aquisição de serviços de desenvolvimento aplicacional e de manutenção das aplicações e ferramentas informáticas que suportam os Sistemas de Informação associados à atividade do COMPETE 2030 e dos Sistemas de Incentivos dos Programas do PT2030\nOpções: Não\nTipo de Contrato Principal: Aquisição de Serviços\nTipo de Contrato: Aquisição de Serviços\nClassificação CPV (Vocabulário Comum para os Contratos Públicos)\nObjeto principal\nVocabulário Principal: 79610000\nPreço base s/IVA: 1.149.984,00 EUR\nLotes: \nNº: LOT-0001\nDescrição do Lote: Serviços de desenvolvimento de formulários e ferramentas no âmbito dos sistemas de informação associados à atividade da Autoridade de Gestão e dos Sistemas de Incentivos dos Programas do PT2030\nPreço base s/IVA: 245.520,00 EUR\nClassificação CPV (Vocabulário Comum para os Contratos Públicos)\nObjeto principal\nVocabulário Principal: 79610000\nNº: LOT-0002\nDescrição do Lote: Serviços informáticos para desenvolvimento do sistema de informação operacional da Autoridade de Gestão do COMPETE 2030 (SGO2030) e manutenção de sistemas de informação de anteriores Quadros Comunitários de Apoio da responsabilidade da Autoridade de Gestão do COMPETE 2030\nPreço base s/IVA: 329.472,00 EUR\nClassificação CPV (Vocabulário Comum para os Contratos Públicos)\nObjeto principal\nVocabulário Principal: 79610000\nNº: LOT-0003\nDescrição do Lote: Serviços de informática para manutenção e evolução da articulação com o HUB de dados do PT 2030\nPreço base s/IVA: 307.296,00 EUR\nClassificação CPV (Vocabulário Comum para os Contratos Públicos)\nObjeto principal\nVocabulário Principal: 79610000\nNº: LOT-0004\nDescrição do Lote: Serviços de informática para exploração e análise de dados\nPreço base s/IVA: 267.696,00 EUR\nClassificação CPV (Vocabulário Comum para os Contratos Públicos)\nObjeto principal\nVocabulário Principal: 79610000\n7 - INDICAÇÕES ADICIONAIS\nO contrato envolve aquisição conjunta (satisfação de várias entidades)? Não\nO contrato é adjudicado por uma central de compras? Não\n8 - TÉCNICAS\nO concurso destina-se à celebração de um acordo-quadro? Inexistência de acordo-quadro\nÉ utilizado um leilão eletrónico? Não\nÉ adotada uma fase de negociação? Não\nSistema de Aquisição Dinâmico: Inexistência de sistema de aquisição dinâmico\n9 - LOCAL DA EXECUÇÃO DO CONTRATO\nLOCAL DA EXECUÇÃO DO CONTRATO (PROCEDIMENTO)\nPaís: Portugal\nNUT III: PT170\nLocalidade: Freguesia de Parque das Nações\nDistrito: Lisboa\nConcelho: Lisboa\nFreguesia: Freguesia de Parque das Nações\nLOCAL DA EXECUÇÃO DO CONTRATO (LOTE)\nIdentificador do Lote: LOT-0001; LOT-0002; LOT-0003; LOT-0004\nPaís: Portugal\nNUT III: PT170\nLocalidade: Freguesia de Parque das Nações\nDistrito: Lisboa\nConcelho: Lisboa\nFreguesia: Freguesia de Parque das Nações\n10 - PRAZO DE EXECUÇÃO DO CONTRATO\nIdentificador do Lote: LOT-0001; LOT-0002; LOT-0003; LOT-0004\nPrazo de execução do contrato: 18 MESES\nPrevisão de renovações: Não\n11 - FUNDOS EU\nIdentificador do Lote: LOT-0001; LOT-0002; LOT-0003; LOT-0004\nTêm fundos EU? Sim\n12 - DOCUMENTOS DE HABILITAÇÃO\nHabilitação para o exercício da atividade profissional: Não\n13 - CONDIÇÕES DE APRESENTAÇÃO\nPlataforma eletrónica utilizada pela entidade adjudicante: ACIN\nURL para Apresentação: https://www.acingov.pt\nAdmissibilidade da apresentação de propostas variantes: Não autorizado\nPrazo para apresentação das propostas: 26-02-2026 23:59\nPrazo durante o qual os concorrentes são obrigados a manter as respetivas propostas: 120 dias a contar do termo do prazo para a apresentação das propostas\nApresentação de Catálogo Eletrónico: Não autorizado\nIndicação de Subcontratação na Proposta: Inexistência de indicação de subcontratação\n14 - PRESTAÇÃO DE CAUÇÃO\nPrestação de caução: Sim\nPercentagem: 5%\nDescrição da Garantia Exigida: O valor da caução é de 5.00% do preço contratual.\n15 - FORNECIMENTO DAS PEÇAS DO CONCURSO, APRESENTAÇÃO DE PEDIDOS DE PARTICIPAÇÃO E APRESENTAÇÃO DAS PROPOSTAS\nLink para acesso às peças do concurso (URL): https://www.acingov.pt/acingovprod/2/zonaPublica/zona_publica_c/donwloadProcedurePiece/MTA0OTk2MA==\n20 - OUTROS REQUISITOS\nIdentificador do Lote: LOT-0001; LOT-0002; LOT-0003; LOT-0004\nInformação sobre contratos reservados. Aplica-se a contratos reservados (54º-A)? Não\n21 - CRITÉRIO DE ADJUDICAÇÃO\nO Critério de adjudicação é diferenciado por lote? Não\nMultifator: Sim\nFator: \nNome: Preço\nPonderação: 50%\nSubfatores: Não\nFator: \nNome: Outros\nOutro Nome: Capacidade Técnica (CT)\nPonderação: 40%\nSubfatores: Não\nFator: \nNome: Outros\nOutro Nome: Prazo de alocação dos recursos (PZ)\nPonderação: 10%\nSubfatores: Não\n24 - CONDIÇÕES DO CONTRATO\nIdentificador do Lote: LOT-0001; LOT-0002; LOT-0003; LOT-0004\nFaturação Eletrónica: Permitido\nObrigação de Subcontratação:\nCódigo da Obrigação de Subcontratação: Não é aplicável nenhuma obrigação de subcontratação.\n25 - COMPRA PÚBLICA ESTRATÉGICA\nCompra Pública Estratégica: Inexistência de contratação pública estratégica\n26 - INFORMAÇÕES ADICIONAIS\nIdentificador do Lote: LOT-0001; LOT-0002; LOT-0003; LOT-0004\nContrato adequado para PME: Sim\nCobertura ACP (Acordo dos Contratos Públicos da Organização Mundial do Comércio): Não\n27 - IDENTIFICAÇÃO E CONTACTOS DO ÓRGÃO DE RECURSOS ADMINISTRATIVOS\nDesignação: Ministro da Presidência\nEndereço: Av. João XXI, n.º 63\nCódigo postal: 1000-300\nLocalidade: Lisboa\nTelefone: 217911600\nFax: \nEndereço eletrónico: compras@sggoverno.gov.pt\n28 - IDENTIFICAÇÃO DO(S) AUTOR(ES) DE ANÚNCIO\nNome: Sofia Magalhães\nCargo: Técnica Superior Especialista em Coordenação Transversal de Administração e Políticas Públicas\n419949219",
    "nipc": "600088103",
    "distrito": "Lisboa",
    "concelho": "Todos",
    "freguesia": "Todas",
    "site": "https://www.sg.pcm.gov.pt",
    "email": "contratacao@sggoverno.gov.pt",
    "designacao_contrato": "Aquisição de serviços de desenvolvimento aplicacional e de manutenção das aplicações e ferramentas informáticas que suportam os Sistemas de Informação associados à atividade do COMPETE 2030 e dos Sistemas de Incentivos dos Programas do PT2030",
    "descricao": "Aquisição de serviços de desenvolvimento aplicacional e de manutenção das aplicações e ferramentas informáticas que suportam os Sistemas de Informação associados à atividade do COMPETE 2030 e dos Sistemas de Incentivos dos Programas do PT2030",
    "preco_base": "1.149.984,00 EUR",
    "prazo_execucao": "18 MESES",
    "prazo_apresentacao_propostas": "26-02-2026 23:59",
    "fundos_eu": "Sim",
    "plataforma_eletronica": "ACIN",
    "url_procedimento": "https://www.acingov.pt",
    "autor_nome": "Sofia Magalhães",
    "autor_cargo": "Técnica Superior Especialista em Coordenação Transversal de Administração e Políticas Públicas"
  },
  {
    "numero_procedimento": "N/A",
    "entidade": "AnÃºncio de procedimento  n.Âº 2069/2026  -  DiÃ¡rio da RepÃºblica n.Âº 20/2026, SÃ©rie II de 2026-01-29",
    "link": "https://diariodarepublica.pt/dr/detalhe/contrato-publico/2069-1028852154"
  },
  {
    "numero_procedimento": "N/A",
    "entidade": "AnÃºncio de procedimento  n.Âº 2071/2026  -  DiÃ¡rio da RepÃºblica n.Âº 20/2026, SÃ©rie II de 2026-01-29",
    "link": "https://diariodarepublica.pt/dr/detalhe/contrato-publico/2071-1028852155"
  },
  {
    "numero_procedimento": "N/A",
    "entidade": "AnÃºncio de procedimento  n.Âº 2073/2026  -  DiÃ¡rio da RepÃºblica n.Âº 20/2026, SÃ©rie II de 2026-01-29",
    "link": "https://diariodarepublica.pt/dr/detalhe/contrato-publico/2073-1028852156"
  },
  {
    "numero_procedimento": "N/A",
    "entidade": "CTE - Centro de Formação para a Transição Energética",
    "link": "https://diariodarepublica.pt/dr/detalhe/contrato-publico/2075-1028852157",
    "detalhes_completos": "1 - IDENTIFICAÇÃO E CONTACTOS DA ENTIDADE ADJUDICANTE\nDesignação da entidade adjudicante: CTE - Centro de Formação para a Transição Energética\nNIPC: 517950634\nServiço/Órgão/Pessoa de contacto: Conselho de administração\nEndereço: Rua das Camarinhas - Bairro das Flores \nCódigo postal: 7500-130\nLocalidade: Vila Nova de Santo André\nPaís: Portugal\nNUT III: PT181\nDistrito: Setúbal\nConcelho: Santiago do Cacém\nFreguesia: Freguesia de Santo André - Santiago do Cacém\nTelefone: 938714777\nEndereço da Entidade (URL): https://cfte.pt/Home.html\nEndereço Eletrónico: geral@cfte.pt\neDelivery Gateway (URL): https://www.acingov.pt\nFunção da Organização: Adquirente\nSubfunção da Organização: Organização que recebe as propostas\nNorma jurídica da Entidade Adjudicante: Organismo de direito público\nÁrea de atividade da Autoridade Adjudicante: Serviços públicos das administrações públicas\n2 - JORNAL OFICIAL DA UNIÃO EUROPEIA\nO procedimento a que este anúncio diz respeito também é publicitado no Jornal Oficial da União Europeia? Sim\n3 - AVISO\nModelo de Anúncio: Concurso público\nData de Envio do Anúncio: 27-01-2026\n5 - PROCESSO\nTipo de Procedimento: Concurso público\nPreço base do procedimento: Sim\nValor do preço base do procedimento: 336.000,00 EUR\nProcedimento com lotes? Não\n6 - OBJETO DO CONTRATO\nNúmero de referência interna: CPI/04/2026\nDesignação do contrato: Aquisição de plataformas elevatórias para trabalhos em altura\nDescrição: Aquisição de plataformas elevatórias para trabalhos em altura\nOpções: Não\nTipo de Contrato Principal: Aquisição de Bens Móveis\nTipo de Contrato: Aquisição de Bens Móveis\nClassificação CPV (Vocabulário Comum para os Contratos Públicos)\nObjeto principal\nVocabulário Principal: 42400000\nPreço base s/IVA: 336.000,00 EUR\n7 - INDICAÇÕES ADICIONAIS\nO contrato envolve aquisição conjunta (satisfação de várias entidades)? Não\nO contrato é adjudicado por uma central de compras? Não\n8 - TÉCNICAS\nO concurso destina-se à celebração de um acordo-quadro? Inexistência de acordo-quadro\nÉ utilizado um leilão eletrónico? Não\nÉ adotada uma fase de negociação? Não\nSistema de Aquisição Dinâmico: Inexistência de sistema de aquisição dinâmico\n9 - LOCAL DA EXECUÇÃO DO CONTRATO\nLOCAL DA EXECUÇÃO DO CONTRATO (PROCEDIMENTO)\nPaís: Portugal\nNUT III: PT181\nLocalidade: Freguesia de Santo André - Santiago do Cacém\nDistrito: Setúbal\nConcelho: Santiago do Cacém\nFreguesia: Freguesia de Santo André - Santiago do Cacém\n10 - PRAZO DE EXECUÇÃO DO CONTRATO\nPrazo de execução do contrato: 32 DIAS\nPrevisão de renovações: Não\n11 - FUNDOS EU\nTêm fundos EU? Sim\n12 - DOCUMENTOS DE HABILITAÇÃO\nHabilitação para o exercício da atividade profissional: Não\n13 - CONDIÇÕES DE APRESENTAÇÃO\nPlataforma eletrónica utilizada pela entidade adjudicante: ACIN\nURL para Apresentação: https://www.acingov.pt\nAdmissibilidade da apresentação de propostas variantes: Não autorizado\nPrazo para apresentação das propostas: 26-02-2026 17:00\nPrazo durante o qual os concorrentes são obrigados a manter as respetivas propostas: 66 dias a contar do termo do prazo para a apresentação das propostas\nApresentação de Catálogo Eletrónico: Não autorizado\nIndicação de Subcontratação na Proposta: Inexistência de indicação de subcontratação\n14 - PRESTAÇÃO DE CAUÇÃO\nPrestação de caução: Não\n15 - FORNECIMENTO DAS PEÇAS DO CONCURSO, APRESENTAÇÃO DE PEDIDOS DE PARTICIPAÇÃO E APRESENTAÇÃO DAS PROPOSTAS\nLink para acesso às peças do concurso (URL): https://www.acingov.pt/acingovprod/2/zonaPublica/zona_publica_c/donwloadProcedurePiece/MTA1MTg4MA==\n20 - OUTROS REQUISITOS\nInformação sobre contratos reservados. Aplica-se a contratos reservados (54º-A)? Não\n21 - CRITÉRIO DE ADJUDICAÇÃO\nMultifator: Não\nMonofator:\nNome: Preço\n24 - CONDIÇÕES DO CONTRATO\nFaturação Eletrónica: Não autorizado\nObrigação de Subcontratação:\nCódigo da Obrigação de Subcontratação: Não é aplicável nenhuma obrigação de subcontratação.\n25 - COMPRA PÚBLICA ESTRATÉGICA\nCompra Pública Estratégica: Inexistência de contratação pública estratégica\n26 - INFORMAÇÕES ADICIONAIS\nContrato adequado para PME: Não\nCobertura ACP (Acordo dos Contratos Públicos da Organização Mundial do Comércio): Não\n27 - IDENTIFICAÇÃO E CONTACTOS DO ÓRGÃO DE RECURSOS ADMINISTRATIVOS\nDesignação: Conselho de Administração\nEndereço: Rua das Camarinhas-Bairro das Flores\nCódigo postal: 7500-130\nLocalidade: Vila Nova de Santo André, Santiago do Cacém\nTelefone: 269038629\nFax: 000000000\nEndereço eletrónico: geral@cfte.pt\nPrazo de interposição do recurso: 10 dias\n28 - IDENTIFICAÇÃO DO(S) AUTOR(ES) DE ANÚNCIO\nNome: Arnaldo Frade\nCargo: Presidente\n419949267",
    "nipc": "517950634",
    "distrito": "Setúbal",
    "concelho": "Santiago do Cacém",
    "freguesia": "Freguesia de Santo André - Santiago do Cacém",
    "site": "https://cfte.pt/Home.html",
    "email": "geral@cfte.pt",
    "designacao_contrato": "Aquisição de plataformas elevatórias para trabalhos em altura",
    "descricao": "Aquisição de plataformas elevatórias para trabalhos em altura",
    "preco_base": "336.000,00 EUR",
    "prazo_execucao": "32 DIAS",
    "prazo_apresentacao_propostas": "26-02-2026 17:00",
    "fundos_eu": "Sim",
    "plataforma_eletronica": "ACIN",
    "url_procedimento": "https://www.acingov.pt",
    "autor_nome": "Arnaldo Frade",
    "autor_cargo": "Presidente"
  },
  {
    "numero_procedimento": "N/A",
    "entidade": "CTE - Centro de Formação para a Transição Energética",
    "link": "https://diariodarepublica.pt/dr/detalhe/contrato-publico/2077-1028852158",
    "detalhes_completos": "1 - IDENTIFICAÇÃO E CONTACTOS DA ENTIDADE ADJUDICANTE\nDesignação da entidade adjudicante: CTE - Centro de Formação para a Transição Energética\nNIPC: 517950634\nServiço/Órgão/Pessoa de contacto: Conselho de Administração\nEndereço: Rua das Camarinhas-Bairro das Flores\nCódigo postal: 7500-130\nLocalidade: Vila Nova de Santo André\nPaís: Portugal\nNUT III: PT181\nDistrito: Setúbal\nConcelho: Santiago do Cacém\nFreguesia: Freguesia de Santo André - Santiago do Cacém\nTelefone: 269038629\nFax: 269038629\nEndereço da Entidade (URL): https://formacao.cfte.pt/\nEndereço Eletrónico: geral@cfte.pt\neDelivery Gateway (URL): https://www.acingov.pt\nFunção da Organização: Adquirente\nSubfunção da Organização: Organização que recebe as propostas\nNorma jurídica da Entidade Adjudicante: Organismo de direito público\nÁrea de atividade da Autoridade Adjudicante: Serviços públicos das administrações públicas\n2 - JORNAL OFICIAL DA UNIÃO EUROPEIA\nO procedimento a que este anúncio diz respeito também é publicitado no Jornal Oficial da União Europeia? Sim\n3 - AVISO\nModelo de Anúncio: Concurso público\nData de Envio do Anúncio: 27-01-2026\n5 - PROCESSO\nTipo de Procedimento: Concurso público\nPreço base do procedimento: Sim\nValor do preço base do procedimento: 733.890,80 EUR\nProcedimento com lotes? Sim\nNº Máx. de Lotes Autorizado: 2\nNúmero máximo de lotes que podem ser adjudicados a um concorrente: 2\n6 - OBJETO DO CONTRATO\nNúmero de referência interna: CPI 05/2026\nDesignação do contrato: Aquisição de Equipamentos e Sistemas Didáticos para Laboratório de Eletrónica e Energias Renováveis, por lotes\nDescrição: Aquisição de Equipamentos e Sistemas Didáticos para Laboratório de Eletrónica e Energias Renováveis, por lotes\nOpções: Não\nTipo de Contrato Principal: Aquisição de Bens Móveis\nTipo de Contrato: Aquisição de Bens Móveis\nClassificação CPV (Vocabulário Comum para os Contratos Públicos)\nObjeto principal\nVocabulário Principal: 38500000\nPreço base s/IVA: 437.240,00 EUR\nObjeto Complementar\nVocabulário Principal: 38970000\nPreço base s/IVA: 296.650,80 EUR\nLotes: \nNº: LOT-0001\nDescrição do Lote: Equipamentos, Instrumentação e Bancada Técnica para Laboratório de Eletrónica\nPreço base s/IVA: 437.240,00 EUR\nClassificação CPV (Vocabulário Comum para os Contratos Públicos)\nObjeto principal\nVocabulário Principal: 38500000\nNº: LOT-0002\nDescrição do Lote: Sistemas Didáticos e de Simulação para Energias Renováveis\nPreço base s/IVA: 296.650,80 EUR\nClassificação CPV (Vocabulário Comum para os Contratos Públicos)\nObjeto principal\nVocabulário Principal: 38970000\n7 - INDICAÇÕES ADICIONAIS\nO contrato envolve aquisição conjunta (satisfação de várias entidades)? Não\nO contrato é adjudicado por uma central de compras? Não\n8 - TÉCNICAS\nO concurso destina-se à celebração de um acordo-quadro? Inexistência de acordo-quadro\nÉ utilizado um leilão eletrónico? Não\nÉ adotada uma fase de negociação? Não\nSistema de Aquisição Dinâmico: Inexistência de sistema de aquisição dinâmico\n9 - LOCAL DA EXECUÇÃO DO CONTRATO\nLOCAL DA EXECUÇÃO DO CONTRATO (PROCEDIMENTO)\nPaís: Portugal\nNUT III: PT181\nLocalidade: Freguesia de Santo André - Santiago do Cacém\nDistrito: Setúbal\nConcelho: Santiago do Cacém\nFreguesia: Freguesia de Santo André - Santiago do Cacém\nLOCAL DA EXECUÇÃO DO CONTRATO (LOTE)\nIdentificador do Lote: LOT-0001; LOT-0002\nPaís: Portugal\nNUT III: PT181\nLocalidade: Freguesia de Santo André - Santiago do Cacém\nDistrito: Setúbal\nConcelho: Santiago do Cacém\nFreguesia: Freguesia de Santo André - Santiago do Cacém\n10 - PRAZO DE EXECUÇÃO DO CONTRATO\nIdentificador do Lote: LOT-0001; LOT-0002\nPrazo de execução do contrato: 32 DIAS\nPrevisão de renovações: Não\n11 - FUNDOS EU\nIdentificador do Lote: LOT-0001; LOT-0002\nTêm fundos EU? Sim\n12 - DOCUMENTOS DE HABILITAÇÃO\nHabilitação para o exercício da atividade profissional: Não\n13 - CONDIÇÕES DE APRESENTAÇÃO\nPlataforma eletrónica utilizada pela entidade adjudicante: ACIN\nURL para Apresentação: https://www.acingov.pt\nAdmissibilidade da apresentação de propostas variantes: Não autorizado\nPrazo para apresentação das propostas: 26-02-2026 17:00\nPrazo durante o qual os concorrentes são obrigados a manter as respetivas propostas: 66 dias a contar do termo do prazo para a apresentação das propostas\nApresentação de Catálogo Eletrónico: Permitido\nIndicação de Subcontratação na Proposta: Inexistência de indicação de subcontratação\n14 - PRESTAÇÃO DE CAUÇÃO\nPrestação de caução: Sim\nPercentagem: 5%\nDescrição da Garantia Exigida: O valor da caução é de 5.00% do preço contratual.\n15 - FORNECIMENTO DAS PEÇAS DO CONCURSO, APRESENTAÇÃO DE PEDIDOS DE PARTICIPAÇÃO E APRESENTAÇÃO DAS PROPOSTAS\nLink para acesso às peças do concurso (URL): https://www.acingov.pt/acingovprod/2/zonaPublica/zona_publica_c/donwloadProcedurePiece/MTA1MTg3OQ==\n20 - OUTROS REQUISITOS\nIdentificador do Lote: LOT-0001; LOT-0002\nInformação sobre contratos reservados. Aplica-se a contratos reservados (54º-A)? Não\n21 - CRITÉRIO DE ADJUDICAÇÃO\nO Critério de adjudicação é diferenciado por lote? Não\nMultifator: Não\nMonofator:\nNome: Preço\n24 - CONDIÇÕES DO CONTRATO\nIdentificador do Lote: LOT-0001; LOT-0002\nFaturação Eletrónica: Permitido\nObrigação de Subcontratação:\nCódigo da Obrigação de Subcontratação: Não é aplicável nenhuma obrigação de subcontratação.\n25 - COMPRA PÚBLICA ESTRATÉGICA\nCompra Pública Estratégica: Inexistência de contratação pública estratégica\n26 - INFORMAÇÕES ADICIONAIS\nIdentificador do Lote: LOT-0001; LOT-0002\nContrato adequado para PME: Sim\nCobertura ACP (Acordo dos Contratos Públicos da Organização Mundial do Comércio): Não\n27 - IDENTIFICAÇÃO E CONTACTOS DO ÓRGÃO DE RECURSOS ADMINISTRATIVOS\nDesignação: Conselho dministrativo\nEndereço: Vila Nova de Santo André\nCódigo postal: 7500-130\nLocalidade: Vila Nova de Santo André\nTelefone: 938714777\nFax: 938714777\nEndereço eletrónico: geral@cfte.pt\nPrazo de interposição do recurso: 10 dias\n28 - IDENTIFICAÇÃO DO(S) AUTOR(ES) DE ANÚNCIO\nNome: Arnaldo Frade\nCargo: Presidente\n419949278",
    "nipc": "517950634",
    "distrito": "Setúbal",
    "concelho": "Santiago do Cacém",
    "freguesia": "Freguesia de Santo André - Santiago do Cacém",
    "site": "https://formacao.cfte.pt/",
    "email": "geral@cfte.pt",
    "designacao_contrato": "Aquisição de Equipamentos e Sistemas Didáticos para Laboratório de Eletrónica e Energias Renováveis, por lotes",
    "descricao": "Aquisição de Equipamentos e Sistemas Didáticos para Laboratório de Eletrónica e Energias Renováveis, por lotes",
    "preco_base": "437.240,00 EUR",
    "prazo_execucao": "32 DIAS",
    "prazo_apresentacao_propostas": "26-02-2026 17:00",
    "fundos_eu": "Sim",
    "plataforma_eletronica": "ACIN",
    "url_procedimento": "https://www.acingov.pt",
    "autor_nome": "Arnaldo Frade",
    "autor_cargo": "Presidente"
  },
  {
    "numero_procedimento": "N/A",
    "entidade": "AnÃºncio de procedimento  n.Âº 2079/2026  -  DiÃ¡rio da RepÃºblica n.Âº 20/2026, SÃ©rie II de 2026-01-29",
    "link": "https://diariodarepublica.pt/dr/detalhe/contrato-publico/2079-1028852159"
  },
  {
    "numero_procedimento": "N/A",
    "entidade": "AnÃºncio de procedimento  n.Âº 2083/2026  -  DiÃ¡rio da RepÃºblica n.Âº 20/2026, SÃ©rie II de 2026-01-29",
    "link": "https://diariodarepublica.pt/dr/detalhe/contrato-publico/2083-1028852161"
  },
  {
    "numero_procedimento": "N/A",
    "entidade": "Município de Tomar",
    "link": "https://diariodarepublica.pt/dr/detalhe/contrato-publico/2084-1028852162",
    "detalhes_completos": "1 - IDENTIFICAÇÃO E CONTACTOS DA ENTIDADE ADJUDICANTE\nDesignação da entidade adjudicante: Município de Tomar\nNIPC: 506738914\nServiço/Órgão/Pessoa de contacto: Divisão Financeira / Unidade de Contratação e Património\nEndereço: Praça da República\nCódigo postal: 2300-550\nLocalidade: Tomar\nPaís: Portugal\nNUT III: PT16I\nDistrito: Santarém\nConcelho: Tomar\nFreguesia: União das Freguesias de Tomar (São João Baptista) e Santa Maria dos Olivais\nTelefone: 249329806\nFax: 249329809\nEndereço da Entidade (URL): www.cm-tomar.pt\nEndereço Eletrónico: presidencia@cm-tomar.pt\neDelivery Gateway (URL): https://www.acingov.pt\nFunção da Organização: Adquirente\nNorma jurídica da Entidade Adjudicante: Organismo de direito público\nÁrea de atividade da Autoridade Adjudicante: Serviços públicos das administrações públicas\n2 - JORNAL OFICIAL DA UNIÃO EUROPEIA\nO procedimento a que este anúncio diz respeito também é publicitado no Jornal Oficial da União Europeia? Não\n3 - AVISO\nModelo de Anúncio: Concurso público\nData de Envio do Anúncio: 29-01-2026\n5 - PROCESSO\nTipo de Procedimento: Concurso público\nPreço base do procedimento: Sim\nValor do preço base do procedimento: 166.736,00 EUR\nProcedimento com lotes? Sim\nNº Máx. de Lotes Autorizado: 2\nNúmero máximo de lotes que podem ser adjudicados a um concorrente: 2\n6 - OBJETO DO CONTRATO\nNúmero de referência interna: 10/2026\nDesignação do contrato: Aquisição de serviços de apoio ao funcionamento das instalações e equipamentos de âmbito turístico e outros equipamentos e eventos de índole cultural\nDescrição: Aquisição de serviços de apoio ao funcionamento das instalações e equipamentos de âmbito turístico e outros equipamentos e eventos de índole cultural\nTipo de Contrato Principal: Aquisição de Serviços\nTipo de Contrato: Aquisição de Serviços\nClassificação CPV (Vocabulário Comum para os Contratos Públicos)\nObjeto principal\nVocabulário Principal: 63513000\nPreço base s/IVA: 166.736,00 EUR\nLotes: \nNº: LOT-0001\nDescrição do Lote: Instalações e equipamentos de âmbito turístico (museus, salas de exposição, espaços patrimoniais, posto de turismo) - preço base de 8,00/hora (valor a que acresce o IVA à taxa legal em vigor), baseado numa estimativa aproximada de 18.654 horas de funcionamento, o que perfaz um total de 149.232,00 (12 meses)\nPreço base s/IVA: 149.232,00 EUR\nClassificação CPV (Vocabulário Comum para os Contratos Públicos)\nObjeto principal\nVocabulário Principal: 63513000\nNº: LOT-0002\nDescrição do Lote: Lote 2 - Instalações e eventos de âmbito cultural (Cine-teatro Paraíso e montagem de eventos)  preço base de 8,00/hora (valor a que acresce o IVA à taxa legal em vigor), baseado numa estimativa aproximada de 2.188 horas de funcionamento, o que perfaz um total de 17.504,00 (12 meses)\nPreço base s/IVA: 17.504,00 EUR\nClassificação CPV (Vocabulário Comum para os Contratos Públicos)\nObjeto principal\nVocabulário Principal: 63513000\n7 - INDICAÇÕES ADICIONAIS\nO contrato envolve aquisição conjunta (satisfação de várias entidades)? Não\nO contrato é adjudicado por uma central de compras? Não\n8 - TÉCNICAS\nO concurso destina-se à celebração de um acordo-quadro? Inexistência de acordo-quadro\nÉ utilizado um leilão eletrónico? Não\nÉ adotada uma fase de negociação? Não\nSistema de Aquisição Dinâmico: Inexistência de sistema de aquisição dinâmico\n9 - LOCAL DA EXECUÇÃO DO CONTRATO\nLOCAL DA EXECUÇÃO DO CONTRATO (PROCEDIMENTO)\nPaís: Portugal\nNUT III: PT16I\nLocalidade: União das Freguesias de Tomar (São João Baptista) e Santa Maria dos Olivais\nDistrito: Santarém\nConcelho: Tomar\nFreguesia: União das Freguesias de Tomar (São João Baptista) e Santa Maria dos Olivais\nLOCAL DA EXECUÇÃO DO CONTRATO (LOTE)\nIdentificador do Lote: LOT-0001; LOT-0002\nPaís: Portugal\nNUT III: PT16I\nLocalidade: União das Freguesias de Tomar (São João Baptista) e Santa Maria dos Olivais\nDistrito: Santarém\nConcelho: Tomar\nFreguesia: União das Freguesias de Tomar (São João Baptista) e Santa Maria dos Olivais\n10 - PRAZO DE EXECUÇÃO DO CONTRATO\nIdentificador do Lote: LOT-0001; LOT-0002\nPrazo de execução do contrato: 365 DIAS\nPrevisão de renovações: Não\n11 - FUNDOS EU\nIdentificador do Lote: LOT-0001; LOT-0002\nTêm fundos EU? Não\n12 - DOCUMENTOS DE HABILITAÇÃO\nHabilitação para o exercício da atividade profissional: Não\n13 - CONDIÇÕES DE APRESENTAÇÃO\nPlataforma eletrónica utilizada pela entidade adjudicante: ACIN\nURL para Apresentação: https://www.acingov.pt\nAdmissibilidade da apresentação de propostas variantes: Não autorizado\nPrazo para apresentação das propostas: 12-02-2026 23:59\nPrazo durante o qual os concorrentes são obrigados a manter as respetivas propostas: 66 dias a contar do termo do prazo para a apresentação das propostas\nIndicação de Subcontratação na Proposta: Inexistência de indicação de subcontratação\n14 - PRESTAÇÃO DE CAUÇÃO\nPrestação de caução: Não\n15 - FORNECIMENTO DAS PEÇAS DO CONCURSO, APRESENTAÇÃO DE PEDIDOS DE PARTICIPAÇÃO E APRESENTAÇÃO DAS PROPOSTAS\nLink para acesso às peças do concurso (URL): https://www.acingov.pt/acingovprod/2/zonaPublica/zona_publica_c/donwloadProcedurePiece/MTA1MDAxOQ==\n20 - OUTROS REQUISITOS\nIdentificador do Lote: LOT-0001; LOT-0002\nInformação sobre contratos reservados. Aplica-se a contratos reservados (54º-A)? Não\n21 - CRITÉRIO DE ADJUDICAÇÃO\nO Critério de adjudicação é diferenciado por lote? Não\nMultifator: Não\nMonofator:\nNome: Preço\n24 - CONDIÇÕES DO CONTRATO\nIdentificador do Lote: LOT-0001; LOT-0002\nFaturação Eletrónica: Permitido\nObrigação de Subcontratação:\nCódigo da Obrigação de Subcontratação: Não é aplicável nenhuma obrigação de subcontratação.\n25 - COMPRA PÚBLICA ESTRATÉGICA\nCompra Pública Estratégica: Inexistência de contratação pública estratégica\n26 - INFORMAÇÕES ADICIONAIS\nIdentificador do Lote: LOT-0001; LOT-0002\nContrato adequado para PME: Sim\nCobertura ACP (Acordo dos Contratos Públicos da Organização Mundial do Comércio): Não\n27 - IDENTIFICAÇÃO E CONTACTOS DO ÓRGÃO DE RECURSOS ADMINISTRATIVOS\nDesignação: Município de Tomar\nEndereço: Praça da República\nCódigo postal: 2300-550\nLocalidade: Tomar\nTelefone: 249329806\nFax: 249329809\nEndereço eletrónico: contratacaopublica@cm-tomar.pt\nPrazo de interposição do recurso: 5 dias\n28 - IDENTIFICAÇÃO DO(S) AUTOR(ES) DE ANÚNCIO\nNome: Tiago Manuel Henriques Ferreira Carrão\nCargo: Presidente da Câmara Municipal\n419948832",
    "nipc": "506738914",
    "distrito": "Santarém",
    "concelho": "Tomar",
    "freguesia": "União das Freguesias de Tomar (São João Baptista) e Santa Maria dos Olivais",
    "site": "www.cm-tomar.pt",
    "email": "presidencia@cm-tomar.pt",
    "designacao_contrato": "Aquisição de serviços de apoio ao funcionamento das instalações e equipamentos de âmbito turístico e outros equipamentos e eventos de índole cultural",
    "descricao": "Aquisição de serviços de apoio ao funcionamento das instalações e equipamentos de âmbito turístico e outros equipamentos e eventos de índole cultural",
    "preco_base": "166.736,00 EUR",
    "prazo_execucao": "365 DIAS",
    "prazo_apresentacao_propostas": "12-02-2026 23:59",
    "fundos_eu": "Não",
    "plataforma_eletronica": "ACIN",
    "url_procedimento": "https://www.acingov.pt",
    "autor_nome": "Tiago Manuel Henriques Ferreira Carrão",
    "autor_cargo": "Presidente da Câmara Municipal"
  },
  {
    "numero_procedimento": "N/A",
    "entidade": "Instituto Português de Oncologia de Coimbra Francisco Gentil, EPE",
    "link": "https://diariodarepublica.pt/dr/detalhe/contrato-publico/2088-1028852163",
    "detalhes_completos": "1 - IDENTIFICAÇÃO E CONTACTOS DA ENTIDADE ADJUDICANTE\nDesignação da entidade adjudicante: Instituto Português de Oncologia de Coimbra Francisco Gentil, EPE\nNIPC: 506361438\nEndereço: Av. Bissaya Barreto, 98\nCódigo postal: 3000-075\nLocalidade: Coimbra\nPaís: Portugal\nNUT III: PT16E\nDistrito: Coimbra\nConcelho: Coimbra\nFreguesia: Freguesia de Santo António dos Olivais\nTelefone: 239400226\nFax: 239400226\nEndereço da Entidade (URL): www.ipocoimbra.min-saude.pt\nEndereço Eletrónico: aprovc@ipocoimbra.min-saude.pt\neDelivery Gateway (URL): https://community.vortal.biz/public/\nFunção da Organização: Adquirente\nNorma jurídica da Entidade Adjudicante: Autoridade da administração central\nÁrea de atividade da Autoridade Adjudicante: Saúde\n2 - JORNAL OFICIAL DA UNIÃO EUROPEIA\nO procedimento a que este anúncio diz respeito também é publicitado no Jornal Oficial da União Europeia? Não\n3 - AVISO\nModelo de Anúncio: Concurso público\nData de Envio do Anúncio: 29-01-2026\n5 - PROCESSO\nTipo de Procedimento: Concurso público\nPreço base do procedimento: Sim\nValor do preço base do procedimento: 77.784,51 EUR\nProcedimento com lotes? Sim\nNº Máx. de Lotes Autorizado: 2\nNúmero máximo de lotes que podem ser adjudicados a um concorrente: 2\n6 - OBJETO DO CONTRATO\nNúmero de referência interna: 595AC26\nDesignação do contrato: PRODUTOS CONTRASTE RADIOLÓGICO COM DISP 1 INJECTOR\nDescrição: PRODUTOS CONTRASTE RADIOLÓGICO COM DISP 1 INJECTOR\nTipo de Contrato Principal: Aquisição de Bens Móveis\nTipo de Contrato: Aquisição de Bens Móveis\nClassificação CPV (Vocabulário Comum para os Contratos Públicos)\nObjeto principal\nVocabulário Principal: 33100000\nPreço base s/IVA: 77.784,51 EUR\nLotes: \nNº: LOT-0001\nDescrição do Lote: P.CONT. HIDROSSOLUVEIS, ADM. ORAL/RECTAL-100 ML\nPreço base s/IVA: 1.344,51 EUR\nClassificação CPV (Vocabulário Comum para os Contratos Públicos)\nObjeto principal\nVocabulário Principal: 33100000\nNº: LOT-0002\nDescrição do Lote: P.CONT.IOD.BAIXA OSM.NAO IONICO 350- 370 MG I, 500 ML\nPreço base s/IVA: 76.440,00 EUR\nClassificação CPV (Vocabulário Comum para os Contratos Públicos)\nObjeto principal\nVocabulário Principal: 33100000\n7 - INDICAÇÕES ADICIONAIS\nO contrato envolve aquisição conjunta (satisfação de várias entidades)? Não\nO contrato é adjudicado por uma central de compras? Não\n8 - TÉCNICAS\nO concurso destina-se à celebração de um acordo-quadro? Inexistência de acordo-quadro\nÉ utilizado um leilão eletrónico? Não\nÉ adotada uma fase de negociação? Não\nSistema de Aquisição Dinâmico: Inexistência de sistema de aquisição dinâmico\n9 - LOCAL DA EXECUÇÃO DO CONTRATO\nLOCAL DA EXECUÇÃO DO CONTRATO (PROCEDIMENTO)\nPaís: Portugal\nNUT III: PT16E\nLocalidade: PORTUGAL\nDistrito: Coimbra\nConcelho: Coimbra\nFreguesia: Freguesia de Santo António dos Olivais\nLOCAL DA EXECUÇÃO DO CONTRATO (LOTE)\nIdentificador do Lote: LOT-0001; LOT-0002\nPaís: Portugal\nNUT III: PT16E\nLocalidade: PORTUGAL\nDistrito: Coimbra\nConcelho: Coimbra\nFreguesia: Freguesia de Santo António dos Olivais\n10 - PRAZO DE EXECUÇÃO DO CONTRATO\nIdentificador do Lote: LOT-0001; LOT-0002\nPrazo de execução do contrato: 365 DIAS\nPrevisão de renovações: Não\n11 - FUNDOS EU\nIdentificador do Lote: LOT-0001; LOT-0002\nTêm fundos EU? Não\n12 - DOCUMENTOS DE HABILITAÇÃO\nHabilitação para o exercício da atividade profissional: Não\n13 - CONDIÇÕES DE APRESENTAÇÃO\nPlataforma eletrónica utilizada pela entidade adjudicante: VORTAL\nURL para Apresentação: https://community.vortal.biz/public/\nAdmissibilidade da apresentação de propostas variantes: Não autorizado\nPrazo para apresentação das propostas: 09-02-2026 23:59\nPrazo durante o qual os concorrentes são obrigados a manter as respetivas propostas: 120 dias a contar do termo do prazo para a apresentação das propostas\nIndicação de Subcontratação na Proposta: Inexistência de indicação de subcontratação\n14 - PRESTAÇÃO DE CAUÇÃO\nPrestação de caução: Não\n15 - FORNECIMENTO DAS PEÇAS DO CONCURSO, APRESENTAÇÃO DE PEDIDOS DE PARTICIPAÇÃO E APRESENTAÇÃO DAS PROPOSTAS\nLink para acesso às peças do concurso (URL): https://community.vortal.biz/Public/public-tender-documents/R2ZYejc2ZkFBbHlvcUNDam1WMjhjcnRoMmlKb1QvbVBqTUNwMGFpaHoyejFvTUpCaWxNQjF3bGtBMVY0blcyNk5JYVhZTmtGbjVSNzFSTkJudC9MS3c9PTBmelNL\n20 - OUTROS REQUISITOS\nIdentificador do Lote: LOT-0001; LOT-0002\nInformação sobre contratos reservados. Aplica-se a contratos reservados (54º-A)? Não\n21 - CRITÉRIO DE ADJUDICAÇÃO\nO Critério de adjudicação é diferenciado por lote? Não\nMultifator: Não\nMonofator:\nNome: Preço\n24 - CONDIÇÕES DO CONTRATO\nIdentificador do Lote: LOT-0001; LOT-0002\nFaturação Eletrónica: Permitido\nObrigação de Subcontratação:\nCódigo da Obrigação de Subcontratação: Não é aplicável nenhuma obrigação de subcontratação.\n25 - COMPRA PÚBLICA ESTRATÉGICA\nCompra Pública Estratégica: Inexistência de contratação pública estratégica\n26 - INFORMAÇÕES ADICIONAIS\nIdentificador do Lote: LOT-0001; LOT-0002\nContrato adequado para PME: Sim\nCobertura ACP (Acordo dos Contratos Públicos da Organização Mundial do Comércio): Não\n27 - IDENTIFICAÇÃO E CONTACTOS DO ÓRGÃO DE RECURSOS ADMINISTRATIVOS\nDesignação: Conselho de Administração do IPO Coimbra\nEndereço: Av. Bissaya Barreto Nº 98\nCódigo postal: 3000-075\nLocalidade: Coimbra\nTelefone: +351 239400200\nFax: +351 000000000\nEndereço eletrónico: secad@ipocoimbra.min-saude.pt\n28 - IDENTIFICAÇÃO DO(S) AUTOR(ES) DE ANÚNCIO\nNome: Teresa Goulão\nCargo: Diretora Serviço de Aprovisionamento\n419949419",
    "nipc": "506361438",
    "distrito": "Coimbra",
    "concelho": "Coimbra",
    "freguesia": "Freguesia de Santo António dos Olivais",
    "site": "www.ipocoimbra.min-saude.pt",
    "email": "aprovc@ipocoimbra.min-saude.pt",
    "designacao_contrato": "PRODUTOS CONTRASTE RADIOLÓGICO COM DISP 1 INJECTOR",
    "descricao": "PRODUTOS CONTRASTE RADIOLÓGICO COM DISP 1 INJECTOR",
    "preco_base": "77.784,51 EUR",
    "prazo_execucao": "365 DIAS",
    "prazo_apresentacao_propostas": "09-02-2026 23:59",
    "fundos_eu": "Não",
    "plataforma_eletronica": "VORTAL",
    "url_procedimento": "https://community.vortal.biz/public/",
    "autor_nome": "Teresa Goulão",
    "autor_cargo": "Diretora Serviço de Aprovisionamento"
  },
  {
    "numero_procedimento": "N/A",
    "entidade": "AnÃºncio de procedimento  n.Âº 2089/2026  -  DiÃ¡rio da RepÃºblica n.Âº 20/2026, SÃ©rie II de 2026-01-29",
    "link": "https://diariodarepublica.pt/dr/detalhe/contrato-publico/2089-1028852164"
  },
  {
    "numero_procedimento": "N/A",
    "entidade": "AnÃºncio de procedimento  n.Âº 2091/2026  -  DiÃ¡rio da RepÃºblica n.Âº 20/2026, SÃ©rie II de 2026-01-29",
    "link": "https://diariodarepublica.pt/dr/detalhe/contrato-publico/2091-1028852165"
  },
  {
    "numero_procedimento": "N/A",
    "entidade": "AnÃºncio de procedimento  n.Âº 2092/2026  -  DiÃ¡rio da RepÃºblica n.Âº 20/2026, SÃ©rie II de 2026-01-29",
    "link": "https://diariodarepublica.pt/dr/detalhe/contrato-publico/2092-1028852166"
  },
  {
    "numero_procedimento": "N/A",
    "entidade": "AnÃºncio de procedimento  n.Âº 2094/2026  -  DiÃ¡rio da RepÃºblica n.Âº 20/2026, SÃ©rie II de 2026-01-29",
    "link": "https://diariodarepublica.pt/dr/detalhe/contrato-publico/2094-1028852167"
  },
  {
    "numero_procedimento": "N/A",
    "entidade": "AnÃºncio de procedimento  n.Âº 2096/2026  -  DiÃ¡rio da RepÃºblica n.Âº 20/2026, SÃ©rie II de 2026-01-29",
    "link": "https://diariodarepublica.pt/dr/detalhe/contrato-publico/2096-1028852168"
  },
  {
    "numero_procedimento": "N/A",
    "entidade": "AnÃºncio de procedimento  n.Âº 2097/2026  -  DiÃ¡rio da RepÃºblica n.Âº 20/2026, SÃ©rie II de 2026-01-29",
    "link": "https://diariodarepublica.pt/dr/detalhe/contrato-publico/2097-1028852169"
  },
  {
    "numero_procedimento": "N/A",
    "entidade": "Município de Mirandela",
    "link": "https://diariodarepublica.pt/dr/detalhe/contrato-publico/2098-1028852170",
    "detalhes_completos": "1 - IDENTIFICAÇÃO E CONTACTOS DA ENTIDADE ADJUDICANTE\nDesignação da entidade adjudicante: Município de Mirandela\nNIPC: 506881784\nEndereço: Largo do Município\nCódigo postal: 5370-288\nLocalidade: Bragança\nPaís: Portugal\nNUT III: PT11E\nDistrito: Braganca\nConcelho: Mirandela\nFreguesia: Freguesia de Mirandela\nTelefone: 278200200\nFax: 278265753\nEndereço da Entidade (URL): www.cm-mirandela.pt\nEndereço Eletrónico: geral@cm-mirandela.pt\neDelivery Gateway (URL): https://community.vortal.biz/public/\nFunção da Organização: Adquirente\nNorma jurídica da Entidade Adjudicante: Autoridade local\nÁrea de atividade da Autoridade Adjudicante: Serviços públicos das administrações públicas\n2 - JORNAL OFICIAL DA UNIÃO EUROPEIA\nO procedimento a que este anúncio diz respeito também é publicitado no Jornal Oficial da União Europeia? Não\n3 - AVISO\nModelo de Anúncio: Concurso público\nData de Envio do Anúncio: 29-01-2026\n5 - PROCESSO\nTipo de Procedimento: Concurso público\nPreço base do procedimento: Sim\nValor do preço base do procedimento: 179.000,00 EUR\nProcedimento com lotes? Não\n6 - OBJETO DO CONTRATO\nNúmero de referência interna: CP1285DAG\nDesignação do contrato: Requalificação da Rua de Santa Luzia\nDescrição: Requalificação da Rua de Santa Luzia\nTipo de Contrato Principal: Empreitada de Obras Públicas\nTipo de Contrato: Empreitada de Obras Públicas\nClassificação CPV (Vocabulário Comum para os Contratos Públicos)\nObjeto principal\nVocabulário Principal: 45233252\nPreço base s/IVA: 179.000,00 EUR\n7 - INDICAÇÕES ADICIONAIS\nO contrato envolve aquisição conjunta (satisfação de várias entidades)? Não\nO contrato é adjudicado por uma central de compras? Não\n8 - TÉCNICAS\nO concurso destina-se à celebração de um acordo-quadro? Inexistência de acordo-quadro\nÉ utilizado um leilão eletrónico? Não\nÉ adotada uma fase de negociação? Não\nSistema de Aquisição Dinâmico: Inexistência de sistema de aquisição dinâmico\n9 - LOCAL DA EXECUÇÃO DO CONTRATO\nLOCAL DA EXECUÇÃO DO CONTRATO (PROCEDIMENTO)\nPaís: Portugal\nNUT III: PT11E\nLocalidade: Bragança\nDistrito: Braganca\nConcelho: Mirandela\nFreguesia: Freguesia de Mirandela\n10 - PRAZO DE EXECUÇÃO DO CONTRATO\nPrazo de execução do contrato: 180 DIAS\nPrevisão de renovações: Não\n11 - FUNDOS EU\nTêm fundos EU? Não\n12 - DOCUMENTOS DE HABILITAÇÃO\nHabilitação para o exercício da atividade profissional: Sim\nTipo: Alvará\nDescrição: Documento comprovativo da titularidade de alvará ou certificado de empreiteiro de obras públicas, emitido pelo Instituto dos Mercados Públicos, do Imobiliário e da Construção, I. P. (IMPIC, I. P.), contendo as habilitações adequadas e necessárias à execução da obra a realizar, identificadas detalhadamente no artigo 17.º do Programa do Procedimento.\n13 - CONDIÇÕES DE APRESENTAÇÃO\nPlataforma eletrónica utilizada pela entidade adjudicante: VORTAL\nURL para Apresentação: https://community.vortal.biz/public/\nAdmissibilidade da apresentação de propostas variantes: Não autorizado\nPrazo para apresentação das propostas: 19-02-2026 17:00\nPrazo durante o qual os concorrentes são obrigados a manter as respetivas propostas: 66 dias a contar do termo do prazo para a apresentação das propostas\nIndicação de Subcontratação na Proposta: Inexistência de indicação de subcontratação\n14 - PRESTAÇÃO DE CAUÇÃO\nPrestação de caução: Sim\nPercentagem: 5%\nDescrição da Garantia Exigida: Exigibilidade de caução (de acordo com o artigo 88º do CCP)\n15 - FORNECIMENTO DAS PEÇAS DO CONCURSO, APRESENTAÇÃO DE PEDIDOS DE PARTICIPAÇÃO E APRESENTAÇÃO DAS PROPOSTAS\nLink para acesso às peças do concurso (URL): https://community.vortal.biz/Public/public-tender-documents/RDNPaFBqZFc3Q3QzNlNmdWJldWYxLzhZelpFRC9IUFFRWU5jMmxzQXBlNzZaOW9DYzkxeXMrcEJ3aWdla29tMFFLQVpDUzR2NFdYTjRvRUlod3VVS1E9PWg1ZzVY\n20 - OUTROS REQUISITOS\nInformação sobre contratos reservados. Aplica-se a contratos reservados (54º-A)? Não\n21 - CRITÉRIO DE ADJUDICAÇÃO\nMultifator: Não\nMonofator:\nNome: Outros\nOutro nome: Preço\n24 - CONDIÇÕES DO CONTRATO\nFaturação Eletrónica: Permitido\nObrigação de Subcontratação:\nCódigo da Obrigação de Subcontratação: Não é aplicável nenhuma obrigação de subcontratação.\n25 - COMPRA PÚBLICA ESTRATÉGICA\nCompra Pública Estratégica: Inexistência de contratação pública estratégica\n26 - INFORMAÇÕES ADICIONAIS\nContrato adequado para PME: Sim\nCobertura ACP (Acordo dos Contratos Públicos da Organização Mundial do Comércio): Não\n27 - IDENTIFICAÇÃO E CONTACTOS DO ÓRGÃO DE RECURSOS ADMINISTRATIVOS\nDesignação: Orlando Ferreira Pires\nEndereço: Paço dos Távoras, Praça do Município\nCódigo postal: 5370-288\nLocalidade: Mirandela\nTelefone: +351 351278200200\nFax: +351 351278265753\nEndereço eletrónico: aprovisionamento@cm-mirandela.pt\n28 - IDENTIFICAÇÃO DO(S) AUTOR(ES) DE ANÚNCIO\nNome: orlando Ferreira Pires\nCargo: Vice-Presidente da Câmara Municipal de Mirandela\n419949425",
    "nipc": "506881784",
    "distrito": "Braganca",
    "concelho": "Mirandela",
    "freguesia": "Freguesia de Mirandela",
    "site": "www.cm-mirandela.pt",
    "email": "geral@cm-mirandela.pt",
    "designacao_contrato": "Requalificação da Rua de Santa Luzia",
    "descricao": "Requalificação da Rua de Santa Luzia",
    "preco_base": "179.000,00 EUR",
    "prazo_execucao": "180 DIAS",
    "prazo_apresentacao_propostas": "19-02-2026 17:00",
    "fundos_eu": "Não",
    "plataforma_eletronica": "VORTAL",
    "url_procedimento": "https://community.vortal.biz/public/",
    "autor_nome": "orlando Ferreira Pires",
    "autor_cargo": "Vice-Presidente da Câmara Municipal de Mirandela"
  },
  {
    "numero_procedimento": "N/A",
    "entidade": "ViniPortugal - Associação Interprofissional do Vinho",
    "link": "https://diariodarepublica.pt/dr/detalhe/contrato-publico/2101-1028852171",
    "detalhes_completos": "1 - IDENTIFICAÇÃO E CONTACTOS DA ENTIDADE ADJUDICANTE\nDesignação da entidade adjudicante: ViniPortugal - Associação Interprofissional do Vinho\nNIPC: 503736864\nEndereço: Rua Mouzinho da Silveira, 5 \nCódigo postal: 2560-312\nLocalidade: Lisboa\nPaís: Portugal\nNUT III: PT16B\nDistrito: Lisboa\nConcelho: Torres Vedras\nFreguesia: Todas\nTelefone: 213569890\nFax: 213569895\nEndereço da Entidade (URL): https://viniportugal.pt/pt/\nEndereço Eletrónico: geral@viniportugal.pt\neDelivery Gateway (URL): https://community.vortal.biz/public/\nFunção da Organização: Adquirente\nNorma jurídica da Entidade Adjudicante: Organismo de direito público\nÁrea de atividade da Autoridade Adjudicante: Educação\n2 - JORNAL OFICIAL DA UNIÃO EUROPEIA\nO procedimento a que este anúncio diz respeito também é publicitado no Jornal Oficial da União Europeia? Não\n3 - AVISO\nModelo de Anúncio: Concurso público\nData de Envio do Anúncio: 29-01-2026\n5 - PROCESSO\nTipo de Procedimento: Concurso público\nPreço base do procedimento: Sim\nValor do preço base do procedimento: 70.000,00 EUR\nProcedimento com lotes? Não\n6 - OBJETO DO CONTRATO\nNúmero de referência interna: 2026.07\nDesignação do contrato: Prestação do Serviço de Envio de Vinhos, para as acções da Marca Wines of Portugal para os mercados da Ásia 2026\nDescrição: Prestação do Serviço de Envio de Vinhos, para as acções da Marca Wines of Portugal para os mercados da Ásia 2026\nTipo de Contrato Principal: Aquisição de Serviços\nTipo de Contrato: Aquisição de Serviços\nClassificação CPV (Vocabulário Comum para os Contratos Públicos)\nObjeto principal\nVocabulário Principal: 79342200\nPreço base s/IVA: 70.000,00 EUR\n7 - INDICAÇÕES ADICIONAIS\nO contrato envolve aquisição conjunta (satisfação de várias entidades)? Não\nO contrato é adjudicado por uma central de compras? Não\n8 - TÉCNICAS\nO concurso destina-se à celebração de um acordo-quadro? Inexistência de acordo-quadro\nÉ utilizado um leilão eletrónico? Não\nÉ adotada uma fase de negociação? Não\nSistema de Aquisição Dinâmico: Inexistência de sistema de aquisição dinâmico\n9 - LOCAL DA EXECUÇÃO DO CONTRATO\nLOCAL DA EXECUÇÃO DO CONTRATO (PROCEDIMENTO)\nPaís: Portugal\nNUT III: PT170\nLocalidade: Lisboa\nDistrito: Lisboa\nConcelho: Lisboa\nFreguesia: Todas\n10 - PRAZO DE EXECUÇÃO DO CONTRATO\nPrazo de execução do contrato: 1 ANOS\nPrevisão de renovações: Não\n11 - FUNDOS EU\nTêm fundos EU? Não\n12 - DOCUMENTOS DE HABILITAÇÃO\nHabilitação para o exercício da atividade profissional: Não\n13 - CONDIÇÕES DE APRESENTAÇÃO\nPlataforma eletrónica utilizada pela entidade adjudicante: VORTAL\nURL para Apresentação: https://community.vortal.biz/public/\nAdmissibilidade da apresentação de propostas variantes: Não autorizado\nPrazo para apresentação das propostas: 04-02-2026 17:00\nPrazo durante o qual os concorrentes são obrigados a manter as respetivas propostas: 180 dias a contar do termo do prazo para a apresentação das propostas\nIndicação de Subcontratação na Proposta: Inexistência de indicação de subcontratação\n14 - PRESTAÇÃO DE CAUÇÃO\nPrestação de caução: Não\n15 - FORNECIMENTO DAS PEÇAS DO CONCURSO, APRESENTAÇÃO DE PEDIDOS DE PARTICIPAÇÃO E APRESENTAÇÃO DAS PROPOSTAS\nLink para acesso às peças do concurso (URL): https://community.vortal.biz/Public/public-tender-documents/K25vdU9zSGZlazNnYXRoejkxMnhGTWczZmhuQnBGT0puSWl2SjVqNnJBcVlJZ1djQUkzQzA5UTNSSHBKcmlKekE5Smw4T3dzZzQ5cDNRWFhDVFhJa3c9PTVaNSRm\n20 - OUTROS REQUISITOS\nInformação sobre contratos reservados. Aplica-se a contratos reservados (54º-A)? Não\n21 - CRITÉRIO DE ADJUDICAÇÃO\nMultifator: Sim\nFator: \nNome: Preço\nPonderação: 70%\nSubfatores: Não\nFator: \nNome: Qualidade\nPonderação: 30%\nSubfatores: Sim\nSubfatores: \nNome: Qualidade Técnica Total\nPonderação : 100%; \n24 - CONDIÇÕES DO CONTRATO\nFaturação Eletrónica: Permitido\nObrigação de Subcontratação:\nCódigo da Obrigação de Subcontratação: Não é aplicável nenhuma obrigação de subcontratação.\n25 - COMPRA PÚBLICA ESTRATÉGICA\nCompra Pública Estratégica: Inexistência de contratação pública estratégica\n26 - INFORMAÇÕES ADICIONAIS\nContrato adequado para PME: Sim\nCobertura ACP (Acordo dos Contratos Públicos da Organização Mundial do Comércio): Não\n27 - IDENTIFICAÇÃO E CONTACTOS DO ÓRGÃO DE RECURSOS ADMINISTRATIVOS\nDesignação: Pedro Fernandes\nEndereço: Rua Mouzinho da Silveira, n.º5\nCódigo postal: 1250-165\nLocalidade: Lisboa\nTelefone: +351 213569890\nFax: +351 213569890\nEndereço eletrónico: processo-concursal@viniportugal.pt\n28 - IDENTIFICAÇÃO DO(S) AUTOR(ES) DE ANÚNCIO\nNome: Pedro Fernandes\nCargo: Director Financeiro\n419949486",
    "nipc": "503736864",
    "distrito": "Lisboa",
    "concelho": "Torres Vedras",
    "freguesia": "Todas",
    "site": "https://viniportugal.pt/pt/",
    "email": "geral@viniportugal.pt",
    "designacao_contrato": "Prestação do Serviço de Envio de Vinhos, para as acções da Marca Wines of Portugal para os mercados da Ásia 2026",
    "descricao": "Prestação do Serviço de Envio de Vinhos, para as acções da Marca Wines of Portugal para os mercados da Ásia 2026",
    "preco_base": "70.000,00 EUR",
    "prazo_execucao": "1 ANOS",
    "prazo_apresentacao_propostas": "04-02-2026 17:00",
    "fundos_eu": "Não",
    "plataforma_eletronica": "VORTAL",
    "url_procedimento": "https://community.vortal.biz/public/",
    "autor_nome": "Pedro Fernandes",
    "autor_cargo": "Director Financeiro"
  },
  {
    "numero_procedimento": "N/A",
    "entidade": "AnÃºncio de procedimento  n.Âº 2102/2026  -  DiÃ¡rio da RepÃºblica n.Âº 20/2026, SÃ©rie II de 2026-01-29",
    "link": "https://diariodarepublica.pt/dr/detalhe/contrato-publico/2102-1028852172"
  },
  {
    "numero_procedimento": "N/A",
    "entidade": "AnÃºncio de procedimento  n.Âº 2104/2026  -  DiÃ¡rio da RepÃºblica n.Âº 20/2026, SÃ©rie II de 2026-01-29",
    "link": "https://diariodarepublica.pt/dr/detalhe/contrato-publico/2104-1028852173"
  },
  {
    "numero_procedimento": "N/A",
    "entidade": "Município de Vila Real",
    "link": "https://diariodarepublica.pt/dr/detalhe/contrato-publico/2106-1028852174",
    "detalhes_completos": "1 - IDENTIFICAÇÃO E CONTACTOS DA ENTIDADE ADJUDICANTE\nDesignação da entidade adjudicante: Município de Vila Real\nNIPC: 506359670\nEndereço: Av. Carvalho Araújo 1\nCódigo postal: 5000-657\nLocalidade: Vila Real\nPaís: Portugal\nNUT III: PT11D\nDistrito: Vila Real\nConcelho: Vila Real\nFreguesia: Todas\nTelefone: 259308100\nFax: 259308161\nEndereço da Entidade (URL): www.cm-vilareal.pt\nEndereço Eletrónico: geral@cm-vilareal.pt\neDelivery Gateway (URL): https://community.vortal.biz/public/\nFunção da Organização: Adquirente\nNorma jurídica da Entidade Adjudicante: Autoridade local\nÁrea de atividade da Autoridade Adjudicante: Serviços públicos das administrações públicas\n2 - JORNAL OFICIAL DA UNIÃO EUROPEIA\nO procedimento a que este anúncio diz respeito também é publicitado no Jornal Oficial da União Europeia? Não\n3 - AVISO\nModelo de Anúncio: Concurso público\nData de Envio do Anúncio: 29-01-2026\n5 - PROCESSO\nTipo de Procedimento: Concurso público\nPreço base do procedimento: Sim\nValor do preço base do procedimento: 499.105,94 EUR\nProcedimento com lotes? Não\n6 - OBJETO DO CONTRATO\nNúmero de referência interna: CMVR-1/CPN/E/26\nDesignação do contrato: Execução da empreitada de \"Ligação à Avª 1º de Maio - Parque Corgo, Zonas Naturais\"\nDescrição: Execução da empreitada de \"Ligação à Avª 1º de Maio - Parque Corgo, Zonas Naturais\"\nTipo de Contrato Principal: Empreitada de Obras Públicas\nTipo de Contrato: Empreitada de Obras Públicas\nClassificação CPV (Vocabulário Comum para os Contratos Públicos)\nObjeto principal\nVocabulário Principal: 45220000\nPreço base s/IVA: 499.105,94 EUR\n7 - INDICAÇÕES ADICIONAIS\nO contrato envolve aquisição conjunta (satisfação de várias entidades)? Não\nO contrato é adjudicado por uma central de compras? Não\n8 - TÉCNICAS\nO concurso destina-se à celebração de um acordo-quadro? Inexistência de acordo-quadro\nÉ utilizado um leilão eletrónico? Não\nÉ adotada uma fase de negociação? Não\nSistema de Aquisição Dinâmico: Inexistência de sistema de aquisição dinâmico\n9 - LOCAL DA EXECUÇÃO DO CONTRATO\nLOCAL DA EXECUÇÃO DO CONTRATO (PROCEDIMENTO)\nPaís: Portugal\nNUT III: PT11D\nLocalidade: Vila Real\nDistrito: Vila Real\nConcelho: Vila Real\nFreguesia: Freguesia de Vila Real\n10 - PRAZO DE EXECUÇÃO DO CONTRATO\nPrazo de execução do contrato: 180 DIAS\nPrevisão de renovações: Não\n11 - FUNDOS EU\nTêm fundos EU? Não\n12 - DOCUMENTOS DE HABILITAÇÃO\nHabilitação para o exercício da atividade profissional: Sim\nTipo: Alvará\nDescrição: Alvará\n13 - CONDIÇÕES DE APRESENTAÇÃO\nPlataforma eletrónica utilizada pela entidade adjudicante: VORTAL\nURL para Apresentação: https://community.vortal.biz/public/\nAdmissibilidade da apresentação de propostas variantes: Não autorizado\nPrazo para apresentação das propostas: 19-02-2026 17:00\nPrazo durante o qual os concorrentes são obrigados a manter as respetivas propostas: 66 dias a contar do termo do prazo para a apresentação das propostas\nIndicação de Subcontratação na Proposta: Inexistência de indicação de subcontratação\n14 - PRESTAÇÃO DE CAUÇÃO\nPrestação de caução: Sim\nPercentagem: 5%\nDescrição da Garantia Exigida: Programa de Procedimento\n15 - FORNECIMENTO DAS PEÇAS DO CONCURSO, APRESENTAÇÃO DE PEDIDOS DE PARTICIPAÇÃO E APRESENTAÇÃO DAS PROPOSTAS\nLink para acesso às peças do concurso (URL): https://community.vortal.biz/Public/public-tender-documents/TW1JUzhLdjJqY2JBVGdzNmFlMGJSYUlxSjVBZ01KSjNidlpaYmg0cEtNaEJQb0I4UXlFOHlBZnRSbnV5eWpJclU1TWZpb1FwUkc0MXB0ZWNxYnJwcWc9PUZNeUQw\n20 - OUTROS REQUISITOS\nInformação sobre contratos reservados. Aplica-se a contratos reservados (54º-A)? Não\n21 - CRITÉRIO DE ADJUDICAÇÃO\nMultifator: Não\nMonofator:\nNome: Preço\n24 - CONDIÇÕES DO CONTRATO\nFaturação Eletrónica: Permitido\nObrigação de Subcontratação:\nCódigo da Obrigação de Subcontratação: Não é aplicável nenhuma obrigação de subcontratação.\n25 - COMPRA PÚBLICA ESTRATÉGICA\nCompra Pública Estratégica: Inexistência de contratação pública estratégica\n26 - INFORMAÇÕES ADICIONAIS\nContrato adequado para PME: Sim\nCobertura ACP (Acordo dos Contratos Públicos da Organização Mundial do Comércio): Não\n27 - IDENTIFICAÇÃO E CONTACTOS DO ÓRGÃO DE RECURSOS ADMINISTRATIVOS\nDesignação: Câmara Municipal de Vila Real\nEndereço: Avenida Carvalho Araújo,\nCódigo postal: 5000-657\nLocalidade: Vila Real\nTelefone: +351 259308100\nFax: +351 259308161\nEndereço eletrónico: geral@cm-vilareal.pt\n28 - IDENTIFICAÇÃO DO(S) AUTOR(ES) DE ANÚNCIO\nNome: Alexandre Manuel Mouta Favaios\nCargo: Presidente da Câmara Municipal de Vila Real\n419949480",
    "nipc": "506359670",
    "distrito": "Vila Real",
    "concelho": "Vila Real",
    "freguesia": "Todas",
    "site": "www.cm-vilareal.pt",
    "email": "geral@cm-vilareal.pt",
    "designacao_contrato": "Execução da empreitada de \"Ligação à Avª 1º de Maio - Parque Corgo, Zonas Naturais\"",
    "descricao": "Execução da empreitada de \"Ligação à Avª 1º de Maio - Parque Corgo, Zonas Naturais\"",
    "preco_base": "499.105,94 EUR",
    "prazo_execucao": "180 DIAS",
    "prazo_apresentacao_propostas": "19-02-2026 17:00",
    "fundos_eu": "Não",
    "plataforma_eletronica": "VORTAL",
    "url_procedimento": "https://community.vortal.biz/public/",
    "autor_nome": "Alexandre Manuel Mouta Favaios",
    "autor_cargo": "Presidente da Câmara Municipal de Vila Real"
  },
  {
    "numero_procedimento": "N/A",
    "entidade": "AnÃºncio de procedimento  n.Âº 2032/2026  -  DiÃ¡rio da RepÃºblica n.Âº 20/2026, SÃ©rie II de 2026-01-29",
    "link": "https://diariodarepublica.pt/dr/detalhe/contrato-publico/2032-1028852398"
  },
  {
    "numero_procedimento": "N/A",
    "entidade": "Unidade Local de Saúde do Estuário do Tejo, EPE",
    "link": "https://diariodarepublica.pt/dr/detalhe/contrato-publico/2034-1028852399",
    "detalhes_completos": "Alteração do Anúncio de procedimento n.º 1637/2026, de 2026-01-26, com o ID 419948608\n1 - IDENTIFICAÇÃO E CONTACTOS DA ENTIDADE ADJUDICANTE\nDesignação da entidade adjudicante: Unidade Local de Saúde do Estuário do Tejo, EPE\nNIPC: 516487493\nServiço/Órgão/Pessoa de contacto: Serviço de Compras e Aprovisionamento\nEndereço: Estrada Carlos Lima Costa, n.º2, Povos \nCódigo postal: 2600-009\nLocalidade: Lisboa\nPaís: Portugal\nNUT III: PT170\nDistrito: Lisboa\nConcelho: Vila Franca de Xira\nFreguesia: Freguesia de Vila Franca de Xira\nTelefone: 263006500\nEndereço da Entidade (URL): https://www.hospitalvilafrancadexira.pt\nEndereço Eletrónico: hvfxira@hvfx.min-saude.pt\neDelivery Gateway (URL): https://community.vortal.biz/public/\nFunção da Organização: Adquirente\nNorma jurídica da Entidade Adjudicante: Empresa pública\nÁrea de atividade da Autoridade Adjudicante: Saúde\n2 - JORNAL OFICIAL DA UNIÃO EUROPEIA\nO procedimento a que este anúncio diz respeito também é publicitado no Jornal Oficial da União Europeia? Sim\n3 - AVISO\nModelo de Anúncio: Concurso público\nData de Envio do Anúncio: 27-01-2026\n5 - PROCESSO\nTipo de Procedimento: Concurso público\nPreço base do procedimento: Sim\nValor do preço base do procedimento: 595.064,40 EUR\nProcedimento com lotes? Não\n6 - OBJETO DO CONTRATO\nNúmero de referência interna:  07/0000004/2026\nDesignação do contrato: Aquisição de serviços de atendimento telefónico\nDescrição: Aquisição de serviços de atendimento telefónico\nOpções: Não\nTipo de Contrato Principal: Aquisição de Serviços\nTipo de Contrato: Aquisição de Serviços\nClassificação CPV (Vocabulário Comum para os Contratos Públicos)\nObjeto principal\nVocabulário Principal: 79510000\nPreço base s/IVA: 595.064,40 EUR\n7 - INDICAÇÕES ADICIONAIS\nO contrato envolve aquisição conjunta (satisfação de várias entidades)? Não\nO contrato é adjudicado por uma central de compras? Não\n8 - TÉCNICAS\nO concurso destina-se à celebração de um acordo-quadro? Inexistência de acordo-quadro\nÉ utilizado um leilão eletrónico? Não\nÉ adotada uma fase de negociação? Não\nSistema de Aquisição Dinâmico: Inexistência de sistema de aquisição dinâmico\n9 - LOCAL DA EXECUÇÃO DO CONTRATO\nLOCAL DA EXECUÇÃO DO CONTRATO (PROCEDIMENTO)\nPaís: Portugal\nNUT III: PT170\nLocalidade: Lisboa\nDistrito: Lisboa\nConcelho: Vila Franca de Xira\nFreguesia: Todas\n10 - PRAZO DE EXECUÇÃO DO CONTRATO\nPrazo de execução do contrato: 24 MESES\nPrevisão de renovações: Não\n11 - FUNDOS EU\nTêm fundos EU? Não\n12 - DOCUMENTOS DE HABILITAÇÃO\nHabilitação para o exercício da atividade profissional: Não\n13 - CONDIÇÕES DE APRESENTAÇÃO\nPlataforma eletrónica utilizada pela entidade adjudicante: VORTAL\nURL para Apresentação: https://community.vortal.biz/public/\nAdmissibilidade da apresentação de propostas variantes: Não autorizado\nPrazo para apresentação das propostas: 25-02-2026 17:00\nPrazo durante o qual os concorrentes são obrigados a manter as respetivas propostas: 120 dias a contar do termo do prazo para a apresentação das propostas\nApresentação de Catálogo Eletrónico: Permitido\nIndicação de Subcontratação na Proposta: Inexistência de indicação de subcontratação\n14 - PRESTAÇÃO DE CAUÇÃO\nPrestação de caução: Não\n15 - FORNECIMENTO DAS PEÇAS DO CONCURSO, APRESENTAÇÃO DE PEDIDOS DE PARTICIPAÇÃO E APRESENTAÇÃO DAS PROPOSTAS\nLink para acesso às peças do concurso (URL): https://community.vortal.biz/Public/public-tender-documents/OWsxZFh3U0UwaTU1QUFPM0phUVZKNzVLWXJ1TE16aXN0c0M5N3RxOFpQOHkrdTNlUUN1Q3FtUmgyRkkwbGpPRmpZSWpFLzlpdjBrcnZ4TGYvYnNOUFE9PXVHal9A\n20 - OUTROS REQUISITOS\nInformação sobre contratos reservados. Aplica-se a contratos reservados (54º-A)? Não\n21 - CRITÉRIO DE ADJUDICAÇÃO\nMultifator: Não\nMonofator:\nNome: Preço\n24 - CONDIÇÕES DO CONTRATO\nFaturação Eletrónica: Permitido\nObrigação de Subcontratação:\nCódigo da Obrigação de Subcontratação: Não é aplicável nenhuma obrigação de subcontratação.\n25 - COMPRA PÚBLICA ESTRATÉGICA\nCompra Pública Estratégica: Inexistência de contratação pública estratégica\n26 - INFORMAÇÕES ADICIONAIS\nContrato adequado para PME: Sim\nCobertura ACP (Acordo dos Contratos Públicos da Organização Mundial do Comércio): Sim\n27 - IDENTIFICAÇÃO E CONTACTOS DO ÓRGÃO DE RECURSOS ADMINISTRATIVOS\nDesignação: Conselho de Administração\nEndereço: Estrada Carlos Lima Costa, n.º 2, Povos\nCódigo postal: 2600-009\nLocalidade: Vila Franca de Xira\nTelefone: +351 263006500\nFax: +351 263006652\nEndereço eletrónico: aprov@ulsetejo.min-saude.pt\n28 - IDENTIFICAÇÃO DO(S) AUTOR(ES) DE ANÚNCIO\nNome: Ana Taklim\nCargo: Técnico Superior\n29 - ALTERAÇÃO\nMotivo da Alteração: Correção pelo adquirente\nIdentificador da Versão do Anúncio a Alterar: 31457887-57c6-4e30-8c20-6ac0bc0eb35b-01\nIdentificador das Secções Alteradas do Anúncio Anterior: O procedimento a que este anúncio diz respeito também é publicitado no Jornal Oficial da União Europeia?\nDescrição das Alterações: Prazo para apresentação de propostas\nAlteração dos Documentos do Concurso: Não\n419949022",
    "nipc": "516487493",
    "distrito": "Lisboa",
    "concelho": "Vila Franca de Xira",
    "freguesia": "Freguesia de Vila Franca de Xira",
    "site": "https://www.hospitalvilafrancadexira.pt",
    "email": "hvfxira@hvfx.min-saude.pt",
    "designacao_contrato": "Aquisição de serviços de atendimento telefónico",
    "descricao": "Aquisição de serviços de atendimento telefónico",
    "preco_base": "595.064,40 EUR",
    "prazo_execucao": "24 MESES",
    "prazo_apresentacao_propostas": "25-02-2026 17:00",
    "fundos_eu": "Não",
    "plataforma_eletronica": "VORTAL",
    "url_procedimento": "https://community.vortal.biz/public/",
    "autor_nome": "Ana Taklim",
    "autor_cargo": "Técnico Superior"
  },
  {
    "numero_procedimento": "N/A",
    "entidade": "AnÃºncio de procedimento  n.Âº 2036/2026  -  DiÃ¡rio da RepÃºblica n.Âº 20/2026, SÃ©rie II de 2026-01-29",
    "link": "https://diariodarepublica.pt/dr/detalhe/contrato-publico/2036-1028852400"
  },
  {
    "numero_procedimento": "N/A",
    "entidade": "AnÃºncio de procedimento  n.Âº 2038/2026  -  DiÃ¡rio da RepÃºblica n.Âº 20/2026, SÃ©rie II de 2026-01-29",
    "link": "https://diariodarepublica.pt/dr/detalhe/contrato-publico/2038-1028852401"
  },
  {
    "numero_procedimento": "N/A",
    "entidade": "AnÃºncio de procedimento  n.Âº 2040/2026  -  DiÃ¡rio da RepÃºblica n.Âº 20/2026, SÃ©rie II de 2026-01-29",
    "link": "https://diariodarepublica.pt/dr/detalhe/contrato-publico/2040-1028852402"
  },
  {
    "numero_procedimento": "N/A",
    "entidade": "Freguesia de Algueirão-Mem Martins",
    "link": "https://diariodarepublica.pt/dr/detalhe/contrato-publico/2042-1028852403",
    "detalhes_completos": "1 - IDENTIFICAÇÃO E CONTACTOS DA ENTIDADE ADJUDICANTE\nDesignação da entidade adjudicante: Freguesia de Algueirão-Mem Martins\nNIPC: 506882799\nServiço/Órgão/Pessoa de contacto: Rafael Rufo\nEndereço: R. Domingos Saraiva, 6A\nCódigo postal: 2725-286\nLocalidade: Algueirão-Mem Martins\nPaís: Portugal\nNUT III: PT170\nDistrito: Lisboa\nConcelho: Sintra\nFreguesia: Freguesia de Algueirão-Mem Martins\nTelefone: 219229450\nFax: 219229459\nEndereço da Entidade (URL): http://www.jfamm.pt/\nEndereço Eletrónico: geral@jfamm.pt\nFunção da Organização: Adquirente\nNorma jurídica da Entidade Adjudicante: Autoridade local\nÁrea de atividade da Autoridade Adjudicante: Serviços públicos das administrações públicas\n2 - JORNAL OFICIAL DA UNIÃO EUROPEIA\nO procedimento a que este anúncio diz respeito também é publicitado no Jornal Oficial da União Europeia? Sim\n3 - AVISO\nModelo de Anúncio: Concurso público\nData de Envio do Anúncio: 27-01-2026\n5 - PROCESSO\nTipo de Procedimento: Concurso público\nPreço base do procedimento: Sim\nValor do preço base do procedimento: 730.602,12 EUR\nProcedimento com lotes? Sim\nNº Máx. de Lotes Autorizado: 2\nNúmero máximo de lotes que podem ser adjudicados a um concorrente: 2\n6 - OBJETO DO CONTRATO\nNúmero de referência interna: Processo Nº002/2026\nDesignação do contrato: Aquisição de Serviços de Manutenção e Conservação de Espaços Verdes\nDescrição: Aquisição de serviços de manutenção e conservação de espaços verdes sob gestão da Freguesia de Algueirão-Mem Martins\nOpções: Não\nTipo de Contrato Principal: Aquisição de Serviços\nTipo de Contrato: Aquisição de Serviços\nClassificação CPV (Vocabulário Comum para os Contratos Públicos)\nObjeto principal\nVocabulário Principal: 71421000\nPreço base s/IVA: 730.602,12 EUR\nLotes: \nNº: LOT-0003\nDescrição do Lote: Lote n.º 3\nPreço base s/IVA: 231.329,82 EUR\nClassificação CPV (Vocabulário Comum para os Contratos Públicos)\nObjeto principal\nVocabulário Principal: 71421000\nNº: LOT-0002\nDescrição do Lote: Lote n.º 2\nPreço base s/IVA: 189.624,46 EUR\nClassificação CPV (Vocabulário Comum para os Contratos Públicos)\nObjeto principal\nVocabulário Principal: 71421000\nNº: LOT-0001\nDescrição do Lote: Lote n.º 1 \nPreço base s/IVA: 309.647,84 EUR\nClassificação CPV (Vocabulário Comum para os Contratos Públicos)\nObjeto principal\nVocabulário Principal: 71421000\n7 - INDICAÇÕES ADICIONAIS\nO contrato envolve aquisição conjunta (satisfação de várias entidades)? Não\nO contrato é adjudicado por uma central de compras? Não\n8 - TÉCNICAS\nO concurso destina-se à celebração de um acordo-quadro? Inexistência de acordo-quadro\nÉ utilizado um leilão eletrónico? Não\nÉ adotada uma fase de negociação? Sim\nSistema de Aquisição Dinâmico: Inexistência de sistema de aquisição dinâmico\n9 - LOCAL DA EXECUÇÃO DO CONTRATO\nLOCAL DA EXECUÇÃO DO CONTRATO (PROCEDIMENTO)\nLOCAL DA EXECUÇÃO DO CONTRATO (LOTE)\nIdentificador do Lote: LOT-0001\nPaís: Portugal\nNUT III: PT170\nLocalidade: Algueirão-Mem Martins\nDistrito: Lisboa\nConcelho: Sintra\nFreguesia: Freguesia de Algueirão-Mem Martins\nIdentificador do Lote: LOT-0002\nPaís: Portugal\nNUT III: PT170\nLocalidade: Algueirão-Mem Martins\nDistrito: Lisboa\nConcelho: Sintra\nFreguesia: Freguesia de Algueirão-Mem Martins\nIdentificador do Lote: LOT-0003\nPaís: Portugal\nNUT III: PT170\nLocalidade: Algueirão-Mem Martins\nDistrito: Lisboa\nConcelho: Sintra\nFreguesia: Freguesia de Algueirão-Mem Martins\n10 - PRAZO DE EXECUÇÃO DO CONTRATO\nIdentificador do Lote: LOT-0001\nPrazo de execução do contrato: 12 MESES\nPrevisão de renovações: Sim\nIndicar número máximo de renovações: 1\nPrazo de renovações diferente do prazo inicial: Não\nIdentificador do Lote: LOT-0002\nPrazo de execução do contrato: 12 MESES\nPrevisão de renovações: Sim\nIndicar número máximo de renovações: 1\nPrazo de renovações diferente do prazo inicial: Não\nIdentificador do Lote: LOT-0003\nPrazo de execução do contrato: 12 MESES\nPrevisão de renovações: Sim\nIndicar número máximo de renovações: 1\nPrazo de renovações diferente do prazo inicial: Não\n11 - FUNDOS EU\nIdentificador do Lote: LOT-0001; LOT-0002; LOT-0003\nTêm fundos EU? Não\n12 - DOCUMENTOS DE HABILITAÇÃO\nHabilitação para o exercício da atividade profissional: Não\n13 - CONDIÇÕES DE APRESENTAÇÃO\nPlataforma eletrónica utilizada pela entidade adjudicante: COMPRASPT\nURL para Apresentação: https://www.compraspt.com/cpt-jfamm/faces/\nAdmissibilidade da apresentação de propostas variantes: Não autorizado\nPrazo para apresentação das propostas: 16-02-2026 23:59\nPrazo durante o qual os concorrentes são obrigados a manter as respetivas propostas: 120 dias a contar do termo do prazo para a apresentação das propostas\nApresentação de Catálogo Eletrónico: Necessário\nIndicação de Subcontratação na Proposta: Inexistência de indicação de subcontratação\n14 - PRESTAÇÃO DE CAUÇÃO\nPrestação de caução: Sim\nPercentagem: 5%\nDescrição da Garantia Exigida: Garantia bancária ou seguro - caução, nos termos dos modelos constantes dos Anexos IV e V ao presente Programa do Procedimento.\n15 - FORNECIMENTO DAS PEÇAS DO CONCURSO, APRESENTAÇÃO DE PEDIDOS DE PARTICIPAÇÃO E APRESENTAÇÃO DAS PROPOSTAS\nLink para acesso às peças do concurso (URL): https://www.compraspt.com/cpt-jfamm/faces/app/acessoDocs.jsp?codigoAcesso=hxlY7KaGSAyLwY7UmpCovEFl4C2gjn8zxpmx4tbUhHrGuVxH6I\n20 - OUTROS REQUISITOS\nIdentificador do Lote: LOT-0001; LOT-0002; LOT-0003\nInformação sobre contratos reservados. Aplica-se a contratos reservados (54º-A)? Não\n21 - CRITÉRIO DE ADJUDICAÇÃO\nO Critério de adjudicação é diferenciado por lote? Não\nMultifator: Sim\nFator: \nNome: Outros\nOutro Nome: Equipamentos\nPonderação: 15%\nSubfatores: Não\nFator: \nNome: Outros\nOutro Nome: Equipa Operacional\nPonderação: 15%\nSubfatores: Não\nFator: \nNome: Preço\nPonderação: 70%\nSubfatores: Não\n24 - CONDIÇÕES DO CONTRATO\nIdentificador do Lote: LOT-0001; LOT-0002; LOT-0003\nFaturação Eletrónica: Permitido\nObrigação de Subcontratação:\nCódigo da Obrigação de Subcontratação: Não é aplicável nenhuma obrigação de subcontratação.\n25 - COMPRA PÚBLICA ESTRATÉGICA\nCompra Pública Estratégica: Inexistência de contratação pública estratégica\n26 - INFORMAÇÕES ADICIONAIS\nIdentificador do Lote: LOT-0001\nContrato adequado para PME: Não\nCobertura ACP (Acordo dos Contratos Públicos da Organização Mundial do Comércio): Não\nIdentificador do Lote: LOT-0002\nContrato adequado para PME: Não\nCobertura ACP (Acordo dos Contratos Públicos da Organização Mundial do Comércio): Não\nIdentificador do Lote: LOT-0003\nContrato adequado para PME: Não\nCobertura ACP (Acordo dos Contratos Públicos da Organização Mundial do Comércio): Não\n27 - IDENTIFICAÇÃO E CONTACTOS DO ÓRGÃO DE RECURSOS ADMINISTRATIVOS\nDesignação: Junta de Freguesia de Algueirão-Mem Martins\nEndereço: Estrada de Mem Martins Nº222\nCódigo postal: 2725-383\nLocalidade: Mem Martins\nEndereço eletrónico: geral@jfamm.pt\n28 - IDENTIFICAÇÃO DO(S) AUTOR(ES) DE ANÚNCIO\nNome: Rafael Reinaldo Rodrigues Rufo\nCargo: Técnico de Sistemas e Tecnologias de Informação\n419949139",
    "nipc": "506882799",
    "distrito": "Lisboa",
    "concelho": "Sintra",
    "freguesia": "Freguesia de Algueirão-Mem Martins",
    "site": "http://www.jfamm.pt/",
    "email": "geral@jfamm.pt",
    "designacao_contrato": "Aquisição de Serviços de Manutenção e Conservação de Espaços Verdes",
    "descricao": "Aquisição de serviços de manutenção e conservação de espaços verdes sob gestão da Freguesia de Algueirão-Mem Martins",
    "preco_base": "730.602,12 EUR",
    "prazo_execucao": "12 MESES",
    "prazo_apresentacao_propostas": "16-02-2026 23:59",
    "fundos_eu": "Não",
    "plataforma_eletronica": "COMPRASPT",
    "url_procedimento": "https://www.compraspt.com/cpt-jfamm/faces/",
    "autor_nome": "Rafael Reinaldo Rodrigues Rufo",
    "autor_cargo": "Técnico de Sistemas e Tecnologias de Informação"
  },
  {
    "numero_procedimento": "N/A",
    "entidade": "APL - Administração do Porto de Lisboa, SA",
    "link": "https://diariodarepublica.pt/dr/detalhe/contrato-publico/2044-1028852404",
    "detalhes_completos": "1 - IDENTIFICAÇÃO E CONTACTOS DA ENTIDADE ADJUDICANTE\nDesignação da entidade adjudicante: APL - Administração do Porto de Lisboa, SA\nNIPC: 501202021\nServiço/Órgão/Pessoa de contacto: Divisão de Contratação Pública e Logística Corporativa\nEndereço: Gare Marítima de Alcântara\nCódigo postal: 1350-355\nLocalidade: Lisboa\nPaís: Portugal\nNUT III: PT170\nDistrito: Lisboa\nConcelho: Lisboa\nFreguesia: Todas\nTelefone: 213611000\nFax: 213611005\nEndereço da Entidade (URL): www.portodelisboa.pt\nEndereço Eletrónico: geral@portodelisboa.pt\neDelivery Gateway (URL): https://www.acingov.pt\nFunção da Organização: Adquirente\nNorma jurídica da Entidade Adjudicante: Organismo de direito público\nÁrea de atividade da Autoridade Adjudicante: Serviços públicos das administrações públicas\n2 - JORNAL OFICIAL DA UNIÃO EUROPEIA\nO procedimento a que este anúncio diz respeito também é publicitado no Jornal Oficial da União Europeia? Sim\n3 - AVISO\nModelo de Anúncio: Concurso público\nData de Envio do Anúncio: 27-01-2026\n5 - PROCESSO\nTipo de Procedimento: Concurso público\nPreço base do procedimento: Sim\nValor do preço base do procedimento: 250.350,00 EUR\nProcedimento com lotes? Não\n6 - OBJETO DO CONTRATO\nNúmero de referência interna: 142-CP-2025\nDesignação do contrato: PRESTAÇÃO DE SERVIÇOS DE TRANSPORTE DE PILOTOS E PESSOAL MARÍTIMO DA ADMINISTRAÇÃO DO PORTO DE LISBOA\nDescrição: TRANSPORTE DE PILOTOS E PESSOAL MARÍTIMO DA ADMINISTRAÇÃO DO PORTO DE LISBOA\nOpções: Não\nTipo de Contrato Principal: Aquisição de Serviços\nTipo de Contrato: Aquisição de Serviços\nClassificação CPV (Vocabulário Comum para os Contratos Públicos)\nObjeto principal\nVocabulário Principal: 60130000\nPreço base s/IVA: 250.350,00 EUR\n7 - INDICAÇÕES ADICIONAIS\nO contrato envolve aquisição conjunta (satisfação de várias entidades)? Não\nO contrato é adjudicado por uma central de compras? Não\n8 - TÉCNICAS\nO concurso destina-se à celebração de um acordo-quadro? Inexistência de acordo-quadro\nÉ utilizado um leilão eletrónico? Não\nÉ adotada uma fase de negociação? Não\nSistema de Aquisição Dinâmico: Inexistência de sistema de aquisição dinâmico\n9 - LOCAL DA EXECUÇÃO DO CONTRATO\nLOCAL DA EXECUÇÃO DO CONTRATO (PROCEDIMENTO)\nPaís: Portugal\nNUT III: PT170\nLocalidade: Freguesia da Estrela\nDistrito: Lisboa\nConcelho: Lisboa\nFreguesia: Freguesia da Estrela\n10 - PRAZO DE EXECUÇÃO DO CONTRATO\nPrazo de execução do contrato: 30 MESES\nPrevisão de renovações: Não\n11 - FUNDOS EU\nTêm fundos EU? Não\n12 - DOCUMENTOS DE HABILITAÇÃO\nHabilitação para o exercício da atividade profissional: Não\n13 - CONDIÇÕES DE APRESENTAÇÃO\nPlataforma eletrónica utilizada pela entidade adjudicante: ACIN\nURL para Apresentação: https://www.acingov.pt\nAdmissibilidade da apresentação de propostas variantes: Não autorizado\nPrazo para apresentação das propostas: 25-02-2026 23:59\nPrazo durante o qual os concorrentes são obrigados a manter as respetivas propostas: 120 dias a contar do termo do prazo para a apresentação das propostas\nApresentação de Catálogo Eletrónico: Não autorizado\nIndicação de Subcontratação na Proposta: Inexistência de indicação de subcontratação\n14 - PRESTAÇÃO DE CAUÇÃO\nPrestação de caução: Não\n15 - FORNECIMENTO DAS PEÇAS DO CONCURSO, APRESENTAÇÃO DE PEDIDOS DE PARTICIPAÇÃO E APRESENTAÇÃO DAS PROPOSTAS\nLink para acesso às peças do concurso (URL): https://www.acingov.pt/acingovprod/2/zonaPublica/zona_publica_c/donwloadProcedurePiece/MTA0OTE0NQ==\n20 - OUTROS REQUISITOS\nInformação sobre contratos reservados. Aplica-se a contratos reservados (54º-A)? Não\n21 - CRITÉRIO DE ADJUDICAÇÃO\nMultifator: Não\nMonofator:\nNome: Outros\nOutro nome: Fator Preço\n24 - CONDIÇÕES DO CONTRATO\nFaturação Eletrónica: Permitido\nObrigação de Subcontratação:\nCódigo da Obrigação de Subcontratação: Não é aplicável nenhuma obrigação de subcontratação.\n25 - COMPRA PÚBLICA ESTRATÉGICA\nCompra Pública Estratégica: Inexistência de contratação pública estratégica\n26 - INFORMAÇÕES ADICIONAIS\nContrato adequado para PME: Sim\nCobertura ACP (Acordo dos Contratos Públicos da Organização Mundial do Comércio): Não\n27 - IDENTIFICAÇÃO E CONTACTOS DO ÓRGÃO DE RECURSOS ADMINISTRATIVOS\nDesignação: Não aplicável\nEndereço: na\nCódigo postal: 1399-012\nLocalidade: lisboa\nTelefone: 213922000\nFax: \nEndereço eletrónico: geral@portodelisboa.pt\n28 - IDENTIFICAÇÃO DO(S) AUTOR(ES) DE ANÚNCIO\nNome: Mariana Teixeira\nCargo: Divisão de Contratação Pública\n419949141",
    "nipc": "501202021",
    "distrito": "Lisboa",
    "concelho": "Lisboa",
    "freguesia": "Todas",
    "site": "www.portodelisboa.pt",
    "email": "geral@portodelisboa.pt",
    "designacao_contrato": "PRESTAÇÃO DE SERVIÇOS DE TRANSPORTE DE PILOTOS E PESSOAL MARÍTIMO DA ADMINISTRAÇÃO DO PORTO DE LISBOA",
    "descricao": "TRANSPORTE DE PILOTOS E PESSOAL MARÍTIMO DA ADMINISTRAÇÃO DO PORTO DE LISBOA",
    "preco_base": "250.350,00 EUR",
    "prazo_execucao": "30 MESES",
    "prazo_apresentacao_propostas": "25-02-2026 23:59",
    "fundos_eu": "Não",
    "plataforma_eletronica": "ACIN",
    "url_procedimento": "https://www.acingov.pt",
    "autor_nome": "Mariana Teixeira",
    "autor_cargo": "Divisão de Contratação Pública"
  },
  {
    "numero_procedimento": "N/A",
    "entidade": "AnÃºncio de procedimento  n.Âº 2046/2026  -  DiÃ¡rio da RepÃºblica n.Âº 20/2026, SÃ©rie II de 2026-01-29",
    "link": "https://diariodarepublica.pt/dr/detalhe/contrato-publico/2046-1028852405"
  },
  {
    "numero_procedimento": "N/A",
    "entidade": "AnÃºncio de procedimento  n.Âº 2048/2026  -  DiÃ¡rio da RepÃºblica n.Âº 20/2026, SÃ©rie II de 2026-01-29",
    "link": "https://diariodarepublica.pt/dr/detalhe/contrato-publico/2048-1028852406"
  },
  {
    "numero_procedimento": "N/A",
    "entidade": "AnÃºncio de procedimento  n.Âº 2050/2026  -  DiÃ¡rio da RepÃºblica n.Âº 20/2026, SÃ©rie II de 2026-01-29",
    "link": "https://diariodarepublica.pt/dr/detalhe/contrato-publico/2050-1028852407"
  },
  {
    "numero_procedimento": "N/A",
    "entidade": "AnÃºncio de procedimento  n.Âº 2052/2026  -  DiÃ¡rio da RepÃºblica n.Âº 20/2026, SÃ©rie II de 2026-01-29",
    "link": "https://diariodarepublica.pt/dr/detalhe/contrato-publico/2052-1028852408"
  },
  {
    "numero_procedimento": "N/A",
    "entidade": "AnÃºncio de procedimento  n.Âº 2054/2026  -  DiÃ¡rio da RepÃºblica n.Âº 20/2026, SÃ©rie II de 2026-01-29",
    "link": "https://diariodarepublica.pt/dr/detalhe/contrato-publico/2054-1028852409"
  },
  {
    "numero_procedimento": "N/A",
    "entidade": "AnÃºncio de procedimento  n.Âº 2056/2026  -  DiÃ¡rio da RepÃºblica n.Âº 20/2026, SÃ©rie II de 2026-01-29",
    "link": "https://diariodarepublica.pt/dr/detalhe/contrato-publico/2056-1028852410"
  },
  {
    "numero_procedimento": "N/A",
    "entidade": "AnÃºncio de procedimento  n.Âº 2058/2026  -  DiÃ¡rio da RepÃºblica n.Âº 20/2026, SÃ©rie II de 2026-01-29",
    "link": "https://diariodarepublica.pt/dr/detalhe/contrato-publico/2058-1028852411"
  },
  {
    "numero_procedimento": "N/A",
    "entidade": "TML - Transportes Metropolitanos de Lisboa, EMT, SA",
    "link": "https://diariodarepublica.pt/dr/detalhe/contrato-publico/2060-1028852412",
    "detalhes_completos": "1 - IDENTIFICAÇÃO E CONTACTOS DA ENTIDADE ADJUDICANTE\nDesignação da entidade adjudicante: TML - Transportes Metropolitanos de Lisboa, EMT, SA\nNIPC: 516150359\nEndereço: Rua Cruz de Santa Apolónia, 23, 25 e 25-A \nCódigo postal: 1100-187\nLocalidade: Lisboa\nPaís: Portugal\nNUT III: PT170\nDistrito: Lisboa\nConcelho: Lisboa\nFreguesia: Freguesia de São Vicente\nTelefone: 218121379\nFax: 218121379\nEndereço da Entidade (URL): https://www.tmlmobilidade.pt/\nEndereço Eletrónico: contratacao@tmlmobilidade.pt\neDelivery Gateway (URL): https://community.vortal.biz/public/\nFunção da Organização: Adquirente\nNorma jurídica da Entidade Adjudicante: Autoridade da administração central\nÁrea de atividade da Autoridade Adjudicante: Serviços públicos das administrações públicas\n2 - JORNAL OFICIAL DA UNIÃO EUROPEIA\nO procedimento a que este anúncio diz respeito também é publicitado no Jornal Oficial da União Europeia? Sim\n3 - AVISO\nModelo de Anúncio: Concurso público\nData de Envio do Anúncio: 27-01-2026\n5 - PROCESSO\nTipo de Procedimento: Concurso público\nPreço base do procedimento: Sim\nValor do preço base do procedimento: 700.000,00 EUR\nProcedimento com lotes? Não\n6 - OBJETO DO CONTRATO\nNúmero de referência interna: CPI01/2026\nDesignação do contrato: Aquisição de serviços especializados de implementação de aplicações de carácter comercial\nDescrição: Aquisição de serviços especializados de implementação de aplicações de carácter comercial\nOpções: Não\nTipo de Contrato Principal: Aquisição de Serviços\nTipo de Contrato: Aquisição de Serviços\nClassificação CPV (Vocabulário Comum para os Contratos Públicos)\nObjeto principal\nVocabulário Principal: 72211000\nPreço base s/IVA: 700.000,00 EUR\n7 - INDICAÇÕES ADICIONAIS\nO contrato envolve aquisição conjunta (satisfação de várias entidades)? Não\nO contrato é adjudicado por uma central de compras? Não\n8 - TÉCNICAS\nO concurso destina-se à celebração de um acordo-quadro? Inexistência de acordo-quadro\nÉ utilizado um leilão eletrónico? Não\nÉ adotada uma fase de negociação? Não\nSistema de Aquisição Dinâmico: Inexistência de sistema de aquisição dinâmico\n9 - LOCAL DA EXECUÇÃO DO CONTRATO\nLOCAL DA EXECUÇÃO DO CONTRATO (PROCEDIMENTO)\nPaís: Portugal\nNUT III: PT170\nLocalidade: Lisboa\nDistrito: Lisboa\nConcelho: Lisboa\nFreguesia: Freguesia de São Vicente\n10 - PRAZO DE EXECUÇÃO DO CONTRATO\nPrazo de execução do contrato: 1 ANOS\nPrevisão de renovações: Não\n11 - FUNDOS EU\nTêm fundos EU? Não\n12 - DOCUMENTOS DE HABILITAÇÃO\nHabilitação para o exercício da atividade profissional: Não\n13 - CONDIÇÕES DE APRESENTAÇÃO\nPlataforma eletrónica utilizada pela entidade adjudicante: VORTAL\nURL para Apresentação: https://community.vortal.biz/public/\nAdmissibilidade da apresentação de propostas variantes: Não autorizado\nPrazo para apresentação das propostas: 26-02-2026 23:59\nPrazo durante o qual os concorrentes são obrigados a manter as respetivas propostas: 66 dias a contar do termo do prazo para a apresentação das propostas\nApresentação de Catálogo Eletrónico: Não autorizado\nIndicação de Subcontratação na Proposta: Inexistência de indicação de subcontratação\n14 - PRESTAÇÃO DE CAUÇÃO\nPrestação de caução: Sim\nPercentagem: 5%\nDescrição da Garantia Exigida: Ver Programa de Concurso\n15 - FORNECIMENTO DAS PEÇAS DO CONCURSO, APRESENTAÇÃO DE PEDIDOS DE PARTICIPAÇÃO E APRESENTAÇÃO DAS PROPOSTAS\nLink para acesso às peças do concurso (URL): https://community.vortal.biz/Public/public-tender-documents/NFN6NWRmd2R3RSticXgvSXFwTXVxU3ByelB3QkNhODlHOWVvRW9KaFBMbklxNUgrQ1Q0NGFxeHpZVjNGM0ZiYjFYMFF4OHdZWCt4UmZuQXRwZWFvWnc9PSFyTXR3\n20 - OUTROS REQUISITOS\nInformação sobre contratos reservados. Aplica-se a contratos reservados (54º-A)? Não\n21 - CRITÉRIO DE ADJUDICAÇÃO\nMultifator: Não\nMonofator:\nNome: Outros\nOutro nome: Preço\n24 - CONDIÇÕES DO CONTRATO\nFaturação Eletrónica: Permitido\nObrigação de Subcontratação:\nCódigo da Obrigação de Subcontratação: Não é aplicável nenhuma obrigação de subcontratação.\n25 - COMPRA PÚBLICA ESTRATÉGICA\nCompra Pública Estratégica: Inexistência de contratação pública estratégica\n26 - INFORMAÇÕES ADICIONAIS\nContrato adequado para PME: Sim\nCobertura ACP (Acordo dos Contratos Públicos da Organização Mundial do Comércio): Não\n27 - IDENTIFICAÇÃO E CONTACTOS DO ÓRGÃO DE RECURSOS ADMINISTRATIVOS\nDesignação: Conselho de Administração da TML\nEndereço: Rua Cruz de Santa Apolónia 23, 25 e 25 A\nCódigo postal: 1100-187\nLocalidade: Lisboa\nTelefone: +351 218121379\nFax: +351 218121379\nEndereço eletrónico: contratacao@tmlmobilidade.pt\n28 - IDENTIFICAÇÃO DO(S) AUTOR(ES) DE ANÚNCIO\nNome: Diogo Sereno\nCargo: Jurista\n419949196",
    "nipc": "516150359",
    "distrito": "Lisboa",
    "concelho": "Lisboa",
    "freguesia": "Freguesia de São Vicente",
    "site": "https://www.tmlmobilidade.pt/",
    "email": "contratacao@tmlmobilidade.pt",
    "designacao_contrato": "Aquisição de serviços especializados de implementação de aplicações de carácter comercial",
    "descricao": "Aquisição de serviços especializados de implementação de aplicações de carácter comercial",
    "preco_base": "700.000,00 EUR",
    "prazo_execucao": "1 ANOS",
    "prazo_apresentacao_propostas": "26-02-2026 23:59",
    "fundos_eu": "Não",
    "plataforma_eletronica": "VORTAL",
    "url_procedimento": "https://community.vortal.biz/public/",
    "autor_nome": "Diogo Sereno",
    "autor_cargo": "Jurista"
  },
  {
    "numero_procedimento": "N/A",
    "entidade": "AnÃºncio de procedimento  n.Âº 2062/2026  -  DiÃ¡rio da RepÃºblica n.Âº 20/2026, SÃ©rie II de 2026-01-29",
    "link": "https://diariodarepublica.pt/dr/detalhe/contrato-publico/2062-1028852413"
  },
  {
    "numero_procedimento": "N/A",
    "entidade": "Associação de Municípios das Terras de Santa Maria",
    "link": "https://diariodarepublica.pt/dr/detalhe/contrato-publico/2064-1028852414",
    "detalhes_completos": "Alteração do Anúncio de procedimento n.º 33336/2025, de 2025-12-23, com o ID 419916146\n1 - IDENTIFICAÇÃO E CONTACTOS DA ENTIDADE ADJUDICANTE\nDesignação da entidade adjudicante: Associação de Municípios das Terras de Santa Maria\nNIPC: 501651888\nEndereço: Villa Balbina - Lugar do Parrinho\nCódigo postal: 3700-189\nLocalidade: S. João da Madeira\nPaís: Portugal\nNUT III: PT187\nDistrito: Aveiro\nConcelho: São João da Madeira\nFreguesia: Freguesia de São João da Madeira\nTelefone: 256830020\nFax: 256830021\nEndereço da Entidade (URL): www.amtsm.pt\nEndereço Eletrónico: geral@amtsm.pt\nFunção da Organização: Adquirente\nNorma jurídica da Entidade Adjudicante: Organismo de direito público\nÁrea de atividade da Entidade Adjudicante: Atividades relacionadas com a água\nÁrea de atividade da Autoridade Adjudicante: Serviços públicos das administrações públicas\n2 - JORNAL OFICIAL DA UNIÃO EUROPEIA\nO procedimento a que este anúncio diz respeito também é publicitado no Jornal Oficial da União Europeia? Sim\n3 - AVISO\nModelo de Anúncio: Concurso público\nData de Envio do Anúncio: 27-01-2026\n5 - PROCESSO\nTipo de Procedimento: Concurso público\nPreço base do procedimento: Sim\nValor do preço base do procedimento: 26.875.003,00 EUR\nProcedimento com lotes? Sim\nNº Máx. de Lotes Autorizado: 3\nNúmero máximo de lotes que podem ser adjudicados a um concorrente: 3\n6 - OBJETO DO CONTRATO\nNúmero de referência interna: CCP/21/2025\nDesignação do contrato: Concurso Público por Lotes, com publicidade Internacional, para a celebração do Contrato de empreitada da Beneficiação do Subsistema do Salgueiro\nDescrição: Beneficiação do Subsistema do Salgueiro, incluindo Remodelação da ETAR do Salgueiro, Beneficiação dos Emissários do Subsistema do Salgueiro e construção de Parque Urbano Inundável\nOpções: Não\nTipo de Contrato Principal: Empreitada de Obras Públicas\nTipo de Contrato: Empreitada de Obras Públicas\nClassificação CPV (Vocabulário Comum para os Contratos Públicos)\nObjeto principal\nVocabulário Principal: 45000000\nPreço base s/IVA: 26.875.003,00 EUR\nLotes: \nNº: LOT-0001\nDescrição do Lote: Remodelação da ETAR do Salgueiro\nPreço base s/IVA: 19.662.807,00 EUR\nClassificação CPV (Vocabulário Comum para os Contratos Públicos)\nObjeto principal\nVocabulário Principal: 45000000\nNº: LOT-0002\nDescrição do Lote: Beneficiação dos Emissários do Subsistema do Salgueiro\nPreço base s/IVA: 6.391.458,00 EUR\nClassificação CPV (Vocabulário Comum para os Contratos Públicos)\nObjeto principal\nVocabulário Principal: 45000000\nNº: LOT-0003\nDescrição do Lote: Parque Urbano Inundável junto à ETAR do Salgueiro\nPreço base s/IVA: 820.738,00 EUR\nClassificação CPV (Vocabulário Comum para os Contratos Públicos)\nObjeto principal\nVocabulário Principal: 45000000\n7 - INDICAÇÕES ADICIONAIS\nO contrato envolve aquisição conjunta (satisfação de várias entidades)? Não\nO contrato é adjudicado por uma central de compras? Não\n8 - TÉCNICAS\nO concurso destina-se à celebração de um acordo-quadro? Inexistência de acordo-quadro\nÉ utilizado um leilão eletrónico? Não\nÉ adotada uma fase de negociação? Não\nSistema de Aquisição Dinâmico: Inexistência de sistema de aquisição dinâmico\n9 - LOCAL DA EXECUÇÃO DO CONTRATO\nLOCAL DA EXECUÇÃO DO CONTRATO (PROCEDIMENTO)\nLOCAL DA EXECUÇÃO DO CONTRATO (LOTE)\nIdentificador do Lote: LOT-0001\nPaís: Portugal\nNUT III: PT11A\nLocalidade: Santiago de Riba-Ul\nDistrito: Aveiro\nConcelho: Oliveira de Azemeis\nFreguesia: União das Freguesias de Oliveira de Azeméis, Santiago de Riba-Ul, Ul, Macinhata da Seixa e Madail\nIdentificador do Lote: LOT-0002\nPaís: Portugal\nNUT III: PT11A\nLocalidade: Santiago de Riba-Ul\nDistrito: Aveiro\nConcelho: Oliveira de Azemeis\nFreguesia: União das Freguesias de Oliveira de Azeméis, Santiago de Riba-Ul, Ul, Macinhata da Seixa e Madail\nIdentificador do Lote: LOT-0003\nPaís: Portugal\nNUT III: PT11A\nLocalidade: Santiago de Riba-Ul\nDistrito: Aveiro\nConcelho: Oliveira de Azemeis\nFreguesia: União das Freguesias de Oliveira de Azeméis, Santiago de Riba-Ul, Ul, Macinhata da Seixa e Madail\n10 - PRAZO DE EXECUÇÃO DO CONTRATO\nIdentificador do Lote: LOT-0001\nPrazo de execução do contrato: 730 DIAS\nPrevisão de renovações: Não\nIdentificador do Lote: LOT-0002\nPrazo de execução do contrato: 730 DIAS\nPrevisão de renovações: Não\nIdentificador do Lote: LOT-0003\nPrazo de execução do contrato: 270 DIAS\nPrevisão de renovações: Não\n11 - FUNDOS EU\nIdentificador do Lote: LOT-0001; LOT-0002; LOT-0003\nTêm fundos EU? Sim\n12 - DOCUMENTOS DE HABILITAÇÃO\nHabilitação para o exercício da atividade profissional: Sim\nTipo: Alvará\nDescrição: i) 1.ª subcategoria da 1.ª categoria, da classe correspondente ao valor dos trabalhos especializados que lhe respeite, consoante a parte que a esses trabalhos cabe na proposta do Lote A; ii) 6.ª subcategoria da 2.ª categoria, da classe correspondente ao valor dos trabalhos especializados que lhe respeite, consoante a parte que a esses trabalhos cabe na proposta do Lote A; iii) 3.ª, 4.ª, 6.ª e 13.ª subcategorias da 4ª categoria, da classe correspondente ao valor dos trabalhos especializados que lhe respeite, consoante a parte que a esses trabalhos cabe na proposta do Lote A; iv) 1.ª, 2.ª, 8.ª e 11.ª subcategorias da 5ª categoria, da classe correspondente ao valor dos trabalhos especializados que lhe respeite, consoante a parte que a esses trabalhos cabe na proposta do Lote A; v) 1.ª subcategoria da 1.ª categoria, da classe correspondente ao valor dos trabalhos especializados que lhe respeite, consoante a parte que a esses trabalhos cabe na proposta do Lote B; vi) 1.ª subcategoria da 2.ª categoria, da classe correspondente ao valor dos trabalhos especializados que lhe respeite, consoante a parte que a esses trabalhos cabe na proposta do Lote B; vii) 6.ª subcategoria da 3.ª categoria, da classe correspondente ao valor dos trabalhos especializados que lhe respeite, consoante a parte que a esses trabalhos cabe na proposta do Lote B; viii) 2.ª, 8.ª e 11.ª subcategorias da 5ª categoria, da classe correspondente ao valor dos trabalhos especializados que lhe respeite, consoante a parte que a esses trabalhos cabe na proposta do Lote B; ix) 9.ª e 10.ª subcategorias da 2.ª categoria, da classe correspondente ao valor dos trabalhos especializados que lhe respeite, consoante a parte que a esses trabalhos cabe na proposta do Lote C; x) 2.ª subcategoria da 5.ª categoria, da classe correspondente ao valor dos trabalhos especializados que lhe respeite, consoante a parte que a esses trabalhos cabe na proposta do Lote C.\n13 - CONDIÇÕES DE APRESENTAÇÃO\nPlataforma eletrónica utilizada pela entidade adjudicante: ANOGOV\nURL para Apresentação: https://www.anogov.com/ap-tsm/faces/\nAdmissibilidade da apresentação de propostas variantes: Não autorizado\nPrazo para apresentação das propostas: 22-02-2026 23:59\nPrazo durante o qual os concorrentes são obrigados a manter as respetivas propostas: 120 dias a contar do termo do prazo para a apresentação das propostas\nApresentação de Catálogo Eletrónico: Necessário\nIndicação de Subcontratação na Proposta: A parte do contrato que o proponente tenciona subcontratar\n14 - PRESTAÇÃO DE CAUÇÃO\nPrestação de caução: Sim\nPercentagem: 5%\nDescrição da Garantia Exigida: 5% (cinco por cento) do preço contratual, prestada por garantia bancária, por seguro-caução ou por depósito em dinheiro ou títulos\n15 - FORNECIMENTO DAS PEÇAS DO CONCURSO, APRESENTAÇÃO DE PEDIDOS DE PARTICIPAÇÃO E APRESENTAÇÃO DAS PROPOSTAS\nLink para acesso às peças do concurso (URL): https://www.anogov.com/ap-tsm/faces/app/acessoDocs.jsp?codigoAcesso=xO8nJwUnzpKzrnddKXDLNWp9MiYjzZ8zGzp0eQ61AI8zKAFhUl\n20 - OUTROS REQUISITOS\nIdentificador do Lote: LOT-0001; LOT-0002; LOT-0003\nInformação sobre contratos reservados. Aplica-se a contratos reservados (54º-A)? Não\n21 - CRITÉRIO DE ADJUDICAÇÃO\nO Critério de adjudicação é diferenciado por lote? Não\nMultifator: Sim\nFator: \nNome: Qualidade\nPonderação: 40%\nSubfatores: Sim\nSubfatores: \nNome: B.2.3\tPlano de Pagamentos\nPonderação : 18.75%; \nNome: B.2.1\tCronograma de Trabalhos\nPonderação : 25%; \nNome: B.1.3 Descrição dos condicionalismos existentes\nPonderação : 7.5%; \nNome: B.2.2\tPlano de Meios\nPonderação : 18.75%; \nNome: B.1.5 Descrição das soluções construtivas para execução de desvios, reposição e/ou substituição de infraestruturas de serviços afetados\nPonderação : 3.75%; \nNome: B.1.4 Descrição do sistema de desvios de caudal em coletores em funcionamento\nPonderação : 7.5%; \nNome: B.1.1 Descrição do modo de execução da obra e dos ensaios a realizar\nPonderação : 11.25%; \nNome: B.1.2 Descrição das soluções construtivas para execução de obras especiais\nPonderação : 7.5%; \nFator: \nNome: Preço\nPonderação: 60%\nSubfatores: Não\n24 - CONDIÇÕES DO CONTRATO\nIdentificador do Lote: LOT-0001; LOT-0002; LOT-0003\nFaturação Eletrónica: Necessário\nObrigação de Subcontratação:\nCódigo da Obrigação de Subcontratação: Não é aplicável nenhuma obrigação de subcontratação.\n25 - COMPRA PÚBLICA ESTRATÉGICA\nCompra Pública Estratégica: Inexistência de contratação pública estratégica\n26 - INFORMAÇÕES ADICIONAIS\nIdentificador do Lote: LOT-0001\nContrato adequado para PME: Não\nCobertura ACP (Acordo dos Contratos Públicos da Organização Mundial do Comércio): Não\nIdentificador do Lote: LOT-0002\nContrato adequado para PME: Não\nCobertura ACP (Acordo dos Contratos Públicos da Organização Mundial do Comércio): Não\nIdentificador do Lote: LOT-0003\nContrato adequado para PME: Não\nCobertura ACP (Acordo dos Contratos Públicos da Organização Mundial do Comércio): Não\n27 - IDENTIFICAÇÃO E CONTACTOS DO ÓRGÃO DE RECURSOS ADMINISTRATIVOS\nDesignação: Associação de Municípios de Terras de Santa Maria\nEndereço: Rua Milheirós de Poiares, Villa Balbina ¿ Lugar do Parrinho\nCódigo postal: 3700-189\nLocalidade: S. João da Madeira\nTelefone: 256830020\nFax: \nEndereço eletrónico: geral@amtsm.pt\nPrazo de interposição do recurso: 5 dias\n28 - IDENTIFICAÇÃO DO(S) AUTOR(ES) DE ANÚNCIO\nNome: Teresa Pouzada\nCargo: Secretária-Geral da AMTSM\n29 - ALTERAÇÃO\nMotivo da Alteração: Informações atualizadas\nIdentificador da Versão do Anúncio a Alterar: 6d9eaac9-c7bf-43a3-87dd-ce89850093db-02\nIdentificador das Secções Alteradas do Anúncio Anterior: Condições de Apresentação\nDescrição das Alterações: Prorrogação de prazo\nAlteração dos Documentos do Concurso: Não\n419949208",
    "nipc": "501651888",
    "distrito": "Aveiro",
    "concelho": "São João da Madeira",
    "freguesia": "Freguesia de São João da Madeira",
    "site": "www.amtsm.pt",
    "email": "geral@amtsm.pt",
    "designacao_contrato": "Concurso Público por Lotes, com publicidade Internacional, para a celebração do Contrato de empreitada da Beneficiação do Subsistema do Salgueiro",
    "descricao": "Beneficiação do Subsistema do Salgueiro, incluindo Remodelação da ETAR do Salgueiro, Beneficiação dos Emissários do Subsistema do Salgueiro e construção de Parque Urbano Inundável",
    "preco_base": "26.875.003,00 EUR",
    "prazo_execucao": "730 DIAS",
    "prazo_apresentacao_propostas": "22-02-2026 23:59",
    "fundos_eu": "Sim",
    "plataforma_eletronica": "ANOGOV",
    "url_procedimento": "https://www.anogov.com/ap-tsm/faces/",
    "autor_nome": "Teresa Pouzada",
    "autor_cargo": "Secretária-Geral da AMTSM"
  },
  {
    "numero_procedimento": "N/A",
    "entidade": "Município de Évora",
    "link": "https://diariodarepublica.pt/dr/detalhe/contrato-publico/2066-1028852415",
    "detalhes_completos": "1 - IDENTIFICAÇÃO E CONTACTOS DA ENTIDADE ADJUDICANTE\nDesignação da entidade adjudicante: Município de Évora\nNIPC: 504828576\nEndereço: Pç.  Sertório, Nr. 1\nCódigo postal: 7004-506\nLocalidade: Évora\nPaís: Portugal\nNUT III: PT187\nDistrito: Évora\nConcelho: Évora\nFreguesia: Todas\nTelefone: 266777000\nFax: 266702950\nEndereço da Entidade (URL): https://www.cm-evora.pt/\nEndereço Eletrónico: cmevora@cm-evora.pt\neDelivery Gateway (URL): https://community.vortal.biz/public/\nFunção da Organização: Adquirente\nNorma jurídica da Entidade Adjudicante: Organismo de direito público\nÁrea de atividade da Autoridade Adjudicante: Serviços públicos das administrações públicas\n2 - JORNAL OFICIAL DA UNIÃO EUROPEIA\nO procedimento a que este anúncio diz respeito também é publicitado no Jornal Oficial da União Europeia? Sim\n3 - AVISO\nModelo de Anúncio: Concurso público\nData de Envio do Anúncio: 27-01-2026\n5 - PROCESSO\nTipo de Procedimento: Concurso público\nPreço base do procedimento: Sim\nValor do preço base do procedimento: 303.135,00 EUR\nProcedimento com lotes? Não\n6 - OBJETO DO CONTRATO\nNúmero de referência interna: 2/2026_CPI_BAIRRO_COMERCIAL_DIGITAL_PRR_PR_5375\nDesignação do contrato: CONTRATAÇÃO DE SERVIÇOS E FORNECIMENTO DA COMPONENTE DE COMUNICAÇÃO DO \"BAIRRO COMERCIAL DIGITAL DE ÉVORA\" PRR – PROJETO BAIRROS COMERCIAIS DIGITAIS - PROJETO Nº 5375.\nDescrição: CONCURSO PÚBLICO INTERNACIONAL NOS TERMOS DA ALÍNEA A) DO N°1 DO ART'.20º DO CCP PARA CONTRATAÇÃO DE SERVIÇOS E FORNECIMENTO DA COMPONENTE DE COMUNICAÇÃO DO \"BAIRRO COMERCIAL DIGITAL DE ÉVORA\" PRR – PROJETO BAIRROS COMERCIAIS DIGITAIS - PROJETO Nº 5375.\nOpções: Não\nTipo de Contrato Principal: Aquisição de Serviços\nTipo de Contrato: Aquisição de Serviços\nClassificação CPV (Vocabulário Comum para os Contratos Públicos)\nObjeto principal\nVocabulário Principal: 72400000\nPreço base s/IVA: 303.135,00 EUR\n7 - INDICAÇÕES ADICIONAIS\nO contrato envolve aquisição conjunta (satisfação de várias entidades)? Não\nO contrato é adjudicado por uma central de compras? Não\n8 - TÉCNICAS\nO concurso destina-se à celebração de um acordo-quadro? Inexistência de acordo-quadro\nÉ utilizado um leilão eletrónico? Não\nÉ adotada uma fase de negociação? Não\nSistema de Aquisição Dinâmico: Inexistência de sistema de aquisição dinâmico\n9 - LOCAL DA EXECUÇÃO DO CONTRATO\nLOCAL DA EXECUÇÃO DO CONTRATO (PROCEDIMENTO)\nPaís: Portugal\nNUT III: PT187\nLocalidade: Évora\nDistrito: Évora\nConcelho: Évora\nFreguesia: União das Freguesias de Évora (São Mamede, Sé, São Pedro e Santo Antão)\n10 - PRAZO DE EXECUÇÃO DO CONTRATO\nPrazo de execução do contrato: 31 DIAS\nPrevisão de renovações: Não\n11 - FUNDOS EU\nTêm fundos EU? Sim\n12 - DOCUMENTOS DE HABILITAÇÃO\nHabilitação para o exercício da atividade profissional: Não\n13 - CONDIÇÕES DE APRESENTAÇÃO\nPlataforma eletrónica utilizada pela entidade adjudicante: VORTAL\nURL para Apresentação: https://community.vortal.biz/public/\nAdmissibilidade da apresentação de propostas variantes: Não autorizado\nPrazo para apresentação das propostas: 14-02-2026 23:59\nPrazo durante o qual os concorrentes são obrigados a manter as respetivas propostas: 66 dias a contar do termo do prazo para a apresentação das propostas\nApresentação de Catálogo Eletrónico: Permitido\nIndicação de Subcontratação na Proposta: Inexistência de indicação de subcontratação\n14 - PRESTAÇÃO DE CAUÇÃO\nPrestação de caução: Não\n15 - FORNECIMENTO DAS PEÇAS DO CONCURSO, APRESENTAÇÃO DE PEDIDOS DE PARTICIPAÇÃO E APRESENTAÇÃO DAS PROPOSTAS\nLink para acesso às peças do concurso (URL): https://community.vortal.biz/Public/public-tender-documents/Z294aGZLNlIvWDVHT3FaRnZRRFlFSGdjNk13dUtJK1MybzlhK2JUQzhKN2NwY21QTUxJSUw5MC9KUzk3ejkxdUVMN0tXcU1UUFBHT05wQlNTQ21JV0E9PU0hclZk\n20 - OUTROS REQUISITOS\nInformação sobre contratos reservados. Aplica-se a contratos reservados (54º-A)? Não\n21 - CRITÉRIO DE ADJUDICAÇÃO\nMultifator: Sim\nFator: \nNome: Preço\nPonderação: 30%\nSubfatores: Não\nFator: \nNome: Qualidade\nPonderação: 70%\nSubfatores: Não\n24 - CONDIÇÕES DO CONTRATO\nFaturação Eletrónica: Permitido\nObrigação de Subcontratação:\nCódigo da Obrigação de Subcontratação: Não é aplicável nenhuma obrigação de subcontratação.\n25 - COMPRA PÚBLICA ESTRATÉGICA\nCompra Pública Estratégica: Redução dos impactos ambientais\nDescrição do Processo de Adjudicação Estratégico: Conforme as peças do procedimento\nCritérios de contratos Públicos Ecológicos: Critérios de contratação pública ecológica nacional\nCategorias da estratégia nacional: Centros de dados, salas de servidores e serviços em nuvem\nDiretiva Veículos Não Poluentes: Não\nCritério de Acessibilidade: Os critérios de acessibilidade para as pessoas com deficiência não estão incluídos porque o contrato não se destina a pessoas singulares\n26 - INFORMAÇÕES ADICIONAIS\nContrato adequado para PME: Sim\nCobertura ACP (Acordo dos Contratos Públicos da Organização Mundial do Comércio): Não\n27 - IDENTIFICAÇÃO E CONTACTOS DO ÓRGÃO DE RECURSOS ADMINISTRATIVOS\nDesignação: Município de Évora\nEndereço: Praça Sertório, nº1\nCódigo postal: 7004-506\nLocalidade: Évora\nTelefone: +351 266777000\nFax: +351 266777000\nEndereço eletrónico: cme.dagf.aprovisionamento@cm-evora.pt\n28 - IDENTIFICAÇÃO DO(S) AUTOR(ES) DE ANÚNCIO\nNome: Jerónimo José\nCargo: Vice-Presidente da Câmara\n419949215",
    "nipc": "504828576",
    "distrito": "Évora",
    "concelho": "Évora",
    "freguesia": "Todas",
    "site": "https://www.cm-evora.pt/",
    "email": "cmevora@cm-evora.pt",
    "designacao_contrato": "CONTRATAÇÃO DE SERVIÇOS E FORNECIMENTO DA COMPONENTE DE COMUNICAÇÃO DO \"BAIRRO COMERCIAL DIGITAL DE ÉVORA\" PRR – PROJETO BAIRROS COMERCIAIS DIGITAIS - PROJETO Nº 5375.",
    "descricao": "CONCURSO PÚBLICO INTERNACIONAL NOS TERMOS DA ALÍNEA A) DO N°1 DO ART'.20º DO CCP PARA CONTRATAÇÃO DE SERVIÇOS E FORNECIMENTO DA COMPONENTE DE COMUNICAÇÃO DO \"BAIRRO COMERCIAL DIGITAL DE ÉVORA\" PRR – PROJETO BAIRROS COMERCIAIS DIGITAIS - PROJETO Nº 5375.",
    "preco_base": "303.135,00 EUR",
    "prazo_execucao": "31 DIAS",
    "prazo_apresentacao_propostas": "14-02-2026 23:59",
    "fundos_eu": "Sim",
    "plataforma_eletronica": "VORTAL",
    "url_procedimento": "https://community.vortal.biz/public/",
    "autor_nome": "Jerónimo José",
    "autor_cargo": "Vice-Presidente da Câmara"
  },
  {
    "numero_procedimento": "N/A",
    "entidade": "AnÃºncio de procedimento  n.Âº 2068/2026  -  DiÃ¡rio da RepÃºblica n.Âº 20/2026, SÃ©rie II de 2026-01-29",
    "link": "https://diariodarepublica.pt/dr/detalhe/contrato-publico/2068-1028852416"
  },
  {
    "numero_procedimento": "N/A",
    "entidade": "Unidade Local de Saúde da Cova da Beira, EPE",
    "link": "https://diariodarepublica.pt/dr/detalhe/contrato-publico/2070-1028852417",
    "detalhes_completos": "Alteração do Anúncio de procedimento n.º 33183/2025, de 2025-12-22, com o ID 419917312\n1 - IDENTIFICAÇÃO E CONTACTOS DA ENTIDADE ADJUDICANTE\nDesignação da entidade adjudicante: Unidade Local de Saúde da Cova da Beira, EPE\nNIPC: 506361659\nEndereço: Quinta do Alvito\nCódigo postal: 6200-251\nLocalidade: Castelo Branco\nPaís: Portugal\nNUT III: PT16J\nDistrito: Castelo Branco\nConcelho: Covilhã\nFreguesia: União das Freguesias de Covilhã e Canhoso\nTelefone: 275330030\nFax: 275330023\nEndereço da Entidade (URL): https://www.chcbeira.min-saude.pt\nEndereço Eletrónico: aprovisionamento@chcbeira.min-saude.pt\neDelivery Gateway (URL): https://community.vortal.biz/public/\nFunção da Organização: Adquirente\nNorma jurídica da Entidade Adjudicante: Organismo de direito público\nÁrea de atividade da Autoridade Adjudicante: Saúde\n2 - JORNAL OFICIAL DA UNIÃO EUROPEIA\nO procedimento a que este anúncio diz respeito também é publicitado no Jornal Oficial da União Europeia? Sim\n3 - AVISO\nModelo de Anúncio: Concurso público\nData de Envio do Anúncio: 27-01-2026\n5 - PROCESSO\nTipo de Procedimento: Concurso público\nPreço base do procedimento: Sim\nValor do preço base do procedimento: 2.415.055,37 EUR\nProcedimento com lotes? Não\n6 - OBJETO DO CONTRATO\nNúmero de referência interna: CP 134/2025\nDesignação do contrato: Aquisição e instalação de uma Ressonância Magnética 1.5T \nDescrição: Aquisição e instalação de uma Ressonância Magnética 1.5T para a Unidade Local de Saúde da Cova da Beira no âmbito da concretização do Investimento RE-C01-i04 – “Modernização e renovação de áreas hospitalares e equipamentos para hospitais”, do Plano de Recuperação e Resiliência (PRR), designadamente no Aviso Nº 06/C01-i04/2025.\nOpções: Não\nTipo de Contrato Principal: Aquisição de Bens Móveis\nTipo de Contrato: Aquisição de Bens Móveis\nClassificação CPV (Vocabulário Comum para os Contratos Públicos)\nObjeto principal\nVocabulário Principal: 33113000\nPreço base s/IVA: 2.415.055,37 EUR\n7 - INDICAÇÕES ADICIONAIS\nO contrato envolve aquisição conjunta (satisfação de várias entidades)? Não\nO contrato é adjudicado por uma central de compras? Não\n8 - TÉCNICAS\nO concurso destina-se à celebração de um acordo-quadro? Inexistência de acordo-quadro\nÉ utilizado um leilão eletrónico? Não\nÉ adotada uma fase de negociação? Não\nSistema de Aquisição Dinâmico: Inexistência de sistema de aquisição dinâmico\n9 - LOCAL DA EXECUÇÃO DO CONTRATO\nLOCAL DA EXECUÇÃO DO CONTRATO (PROCEDIMENTO)\nPaís: Portugal\nNUT III: PT16J\nLocalidade: Castelo Branco\nDistrito: Castelo Branco\nConcelho: Covilhã\nFreguesia: União das Freguesias de Covilhã e Canhoso\n10 - PRAZO DE EXECUÇÃO DO CONTRATO\nPrazo de execução do contrato: 6 MESES\nPrevisão de renovações: Não\n11 - FUNDOS EU\nTêm fundos EU? Sim\n12 - DOCUMENTOS DE HABILITAÇÃO\nHabilitação para o exercício da atividade profissional: Não\n13 - CONDIÇÕES DE APRESENTAÇÃO\nPlataforma eletrónica utilizada pela entidade adjudicante: VORTAL\nURL para Apresentação: https://community.vortal.biz/public/\nAdmissibilidade da apresentação de propostas variantes: Não autorizado\nPrazo para apresentação das propostas: 06-02-2026 18:00\nPrazo durante o qual os concorrentes são obrigados a manter as respetivas propostas: 120 dias a contar do termo do prazo para a apresentação das propostas\nApresentação de Catálogo Eletrónico: Não autorizado\nIndicação de Subcontratação na Proposta: Inexistência de indicação de subcontratação\n14 - PRESTAÇÃO DE CAUÇÃO\nPrestação de caução: Sim\nPercentagem: 2.5%\nDescrição da Garantia Exigida: De acordo com o programa do procedimento\n15 - FORNECIMENTO DAS PEÇAS DO CONCURSO, APRESENTAÇÃO DE PEDIDOS DE PARTICIPAÇÃO E APRESENTAÇÃO DAS PROPOSTAS\nLink para acesso às peças do concurso (URL): https://community.vortal.biz/Public/public-tender-documents/eVBpY0pyT09Gd1JKME0rT2VmVzdRQkVNS2N2dVhEZUhBQmRaeEUrR3o4N1h3ekc4YjFWaUtCWUs4QTluS3dTMnQ2bm9uaTBkMW5ENFhsVkdGcTh4SlE9PVokM1A3\n20 - OUTROS REQUISITOS\nInformação sobre contratos reservados. Aplica-se a contratos reservados (54º-A)? Não\n21 - CRITÉRIO DE ADJUDICAÇÃO\nMultifator: Sim\nFator: \nNome: Preço\nPonderação: 20%\nSubfatores: Não\nFator: \nNome: Qualidade\nPonderação: 10%\nSubfatores: Não\nFator: \nNome: Qualidade\nPonderação: 70%\nSubfatores: Não\n24 - CONDIÇÕES DO CONTRATO\nFaturação Eletrónica: Permitido\nObrigação de Subcontratação:\nCódigo da Obrigação de Subcontratação: Não é aplicável nenhuma obrigação de subcontratação.\n25 - COMPRA PÚBLICA ESTRATÉGICA\nCompra Pública Estratégica: Inexistência de contratação pública estratégica\n26 - INFORMAÇÕES ADICIONAIS\nContrato adequado para PME: Sim\nCobertura ACP (Acordo dos Contratos Públicos da Organização Mundial do Comércio): Não\n27 - IDENTIFICAÇÃO E CONTACTOS DO ÓRGÃO DE RECURSOS ADMINISTRATIVOS\nDesignação: ULSCBEIRA, EPE\nEndereço: Quinta do Alvito\nCódigo postal: 6200-251\nLocalidade: Covilhã\nTelefone: +351 275330000\nFax: +351 2753300001\nEndereço eletrónico: aprovisionamento@ulscbeira.min-saude.pt\n28 - IDENTIFICAÇÃO DO(S) AUTOR(ES) DE ANÚNCIO\nNome: Dr. João Pedro Marques Gomes\nCargo: Presidente do Conselho de Administração\n29 - ALTERAÇÃO\nMotivo da Alteração: Correção pelo adquirente\nIdentificador da Versão do Anúncio a Alterar: 657f1f37-a291-4965-a204-9298a6336ed7-01\nIdentificador das Secções Alteradas do Anúncio Anterior: Condições de Apresentação\nAlteração dos Documentos do Concurso: Não\n419949232",
    "nipc": "506361659",
    "distrito": "Castelo Branco",
    "concelho": "Covilhã",
    "freguesia": "União das Freguesias de Covilhã e Canhoso",
    "site": "https://www.chcbeira.min-saude.pt",
    "email": "aprovisionamento@chcbeira.min-saude.pt",
    "designacao_contrato": "Aquisição e instalação de uma Ressonância Magnética 1.5T",
    "descricao": "Aquisição e instalação de uma Ressonância Magnética 1.5T para a Unidade Local de Saúde da Cova da Beira no âmbito da concretização do Investimento RE-C01-i04 – “Modernização e renovação de áreas hospitalares e equipamentos para hospitais”, do Plano de Recuperação e Resiliência (PRR), designadamente no Aviso Nº 06/C01-i04/2025.",
    "preco_base": "2.415.055,37 EUR",
    "prazo_execucao": "6 MESES",
    "prazo_apresentacao_propostas": "06-02-2026 18:00",
    "fundos_eu": "Sim",
    "plataforma_eletronica": "VORTAL",
    "url_procedimento": "https://community.vortal.biz/public/",
    "autor_nome": "Dr. João Pedro Marques Gomes",
    "autor_cargo": "Presidente do Conselho de Administração"
  },
  {
    "numero_procedimento": "N/A",
    "entidade": "Município de Vila do Conde",
    "link": "https://diariodarepublica.pt/dr/detalhe/contrato-publico/2072-1028852418",
    "detalhes_completos": "1 - IDENTIFICAÇÃO E CONTACTOS DA ENTIDADE ADJUDICANTE\nDesignação da entidade adjudicante: Município de Vila do Conde\nNIPC: 505804786\nServiço/Órgão/Pessoa de contacto: D.C.P. Divisão de Contratação Pública\nEndereço: Praça Vasco da Gama\nCódigo postal: 4480-754\nLocalidade: Vila do Conde\nPaís: Portugal\nNUT III: PT11A\nDistrito: Porto\nConcelho: Vila do Conde\nFreguesia: Todas\nTelefone: 252248400\nFax: 252641853\nEndereço da Entidade (URL): https://www.cm-viladoconde.pt\nEndereço Eletrónico: geral@cm-viladoconde.pt\neDelivery Gateway (URL): https://www.acingov.pt\nFunção da Organização: Adquirente\nNorma jurídica da Entidade Adjudicante: Organismo de direito público\nÁrea de atividade da Autoridade Adjudicante: Serviços públicos das administrações públicas\n2 - JORNAL OFICIAL DA UNIÃO EUROPEIA\nO procedimento a que este anúncio diz respeito também é publicitado no Jornal Oficial da União Europeia? Sim\n3 - AVISO\nModelo de Anúncio: Concurso público\nData de Envio do Anúncio: 27-01-2026\n5 - PROCESSO\nTipo de Procedimento: Concurso público\nPreço base do procedimento: Sim\nValor do preço base do procedimento: 350.000,00 EUR\nProcedimento com lotes? Não\n6 - OBJETO DO CONTRATO\nNúmero de referência interna: CPI/3/2026\nDesignação do contrato: CIVIDADE DE BAGUNTE - EXPOSIÇÃO PERMANENTE\nDescrição: CIVIDADE DE BAGUNTE - EXPOSIÇÃO PERMANENTE\nOpções: Não\nTipo de Contrato Principal: Aquisição de Serviços\nTipo de Contrato: Aquisição de Bens Móveis; Aquisição de Serviços\nClassificação CPV (Vocabulário Comum para os Contratos Públicos)\nObjeto principal\nVocabulário Principal: 79956000\nPreço base s/IVA: 350.000,00 EUR\n7 - INDICAÇÕES ADICIONAIS\nO contrato envolve aquisição conjunta (satisfação de várias entidades)? Não\nO contrato é adjudicado por uma central de compras? Não\n8 - TÉCNICAS\nO concurso destina-se à celebração de um acordo-quadro? Inexistência de acordo-quadro\nÉ utilizado um leilão eletrónico? Não\nÉ adotada uma fase de negociação? Não\nSistema de Aquisição Dinâmico: Inexistência de sistema de aquisição dinâmico\n9 - LOCAL DA EXECUÇÃO DO CONTRATO\nLOCAL DA EXECUÇÃO DO CONTRATO (PROCEDIMENTO)\nPaís: Portugal\nNUT III: PT11A\nLocalidade: União das Freguesias de Bagunte, Ferreiró, Outeiro Maior e Parada\nDistrito: Porto\nConcelho: Vila do Conde\nFreguesia: União das Freguesias de Bagunte, Ferreiró, Outeiro Maior e Parada\n10 - PRAZO DE EXECUÇÃO DO CONTRATO\nPrazo de execução do contrato: 12 MESES\nPrevisão de renovações: Não\n11 - FUNDOS EU\nTêm fundos EU? Não\n12 - DOCUMENTOS DE HABILITAÇÃO\nHabilitação para o exercício da atividade profissional: Não\n13 - CONDIÇÕES DE APRESENTAÇÃO\nPlataforma eletrónica utilizada pela entidade adjudicante: ACIN\nURL para Apresentação: https://www.acingov.pt\nAdmissibilidade da apresentação de propostas variantes: Não autorizado\nPrazo para apresentação das propostas: 26-02-2026 23:59\nPrazo durante o qual os concorrentes são obrigados a manter as respetivas propostas: 66 dias a contar do termo do prazo para a apresentação das propostas\nApresentação de Catálogo Eletrónico: Permitido\nIndicação de Subcontratação na Proposta: Inexistência de indicação de subcontratação\n14 - PRESTAÇÃO DE CAUÇÃO\nPrestação de caução: Não\n15 - FORNECIMENTO DAS PEÇAS DO CONCURSO, APRESENTAÇÃO DE PEDIDOS DE PARTICIPAÇÃO E APRESENTAÇÃO DAS PROPOSTAS\nLink para acesso às peças do concurso (URL): https://www.acingov.pt/acingovprod/2/zonaPublica/zona_publica_c/donwloadProcedurePiece/MTA1MTQzOQ==\n20 - OUTROS REQUISITOS\nInformação sobre contratos reservados. Aplica-se a contratos reservados (54º-A)? Não\n21 - CRITÉRIO DE ADJUDICAÇÃO\nMultifator: Sim\nFator: \nNome: Outros\nOutro Nome: QUALIDADE E MÉRITO TÉCNICO\nPonderação: 45%\nSubfatores: Sim\nSubfatores: \nNome: A1 - MEMÓRIA DESCRITIVA\nPonderação : 20%; \nNome: A2 - QUALIDADE EQUIPAMENTOS MULTIMÉDIA PROPOSTOS\nPonderação : 30%; \nNome: A3 - QUALIDADE DA EQUIPA\nPonderação : 50%; \nFator: \nNome: Preço\nPonderação: 50%\nSubfatores: Não\nFator: \nNome: Outros\nOutro Nome: PRAZO\nPonderação: 5%\nSubfatores: Não\n24 - CONDIÇÕES DO CONTRATO\nFaturação Eletrónica: Permitido\nObrigação de Subcontratação:\nCódigo da Obrigação de Subcontratação: Não é aplicável nenhuma obrigação de subcontratação.\n25 - COMPRA PÚBLICA ESTRATÉGICA\nCompra Pública Estratégica: Inexistência de contratação pública estratégica\n26 - INFORMAÇÕES ADICIONAIS\nContrato adequado para PME: Sim\nCobertura ACP (Acordo dos Contratos Públicos da Organização Mundial do Comércio): Não\n27 - IDENTIFICAÇÃO E CONTACTOS DO ÓRGÃO DE RECURSOS ADMINISTRATIVOS\nDesignação: Câmara Municipal de Vila do Conde\nEndereço: Praça Vasco da Gama, s/n\nCódigo postal: 4480-754\nLocalidade: Vila do Conde\nTelefone: 252248400\nFax: \nEndereço eletrónico: geral@cm-viladoconde.pt\nPrazo de interposição do recurso: 5 dias\n28 - IDENTIFICAÇÃO DO(S) AUTOR(ES) DE ANÚNCIO\nNome: Vítor Costa\nCargo: Presidente\n419949238",
    "nipc": "505804786",
    "distrito": "Porto",
    "concelho": "Vila do Conde",
    "freguesia": "Todas",
    "site": "https://www.cm-viladoconde.pt",
    "email": "geral@cm-viladoconde.pt",
    "designacao_contrato": "CIVIDADE DE BAGUNTE - EXPOSIÇÃO PERMANENTE",
    "descricao": "CIVIDADE DE BAGUNTE - EXPOSIÇÃO PERMANENTE",
    "preco_base": "350.000,00 EUR",
    "prazo_execucao": "12 MESES",
    "prazo_apresentacao_propostas": "26-02-2026 23:59",
    "fundos_eu": "Não",
    "plataforma_eletronica": "ACIN",
    "url_procedimento": "https://www.acingov.pt",
    "autor_nome": "Vítor Costa",
    "autor_cargo": "Presidente"
  },
  {
    "numero_procedimento": "N/A",
    "entidade": "AnÃºncio de procedimento  n.Âº 2074/2026  -  DiÃ¡rio da RepÃºblica n.Âº 20/2026, SÃ©rie II de 2026-01-29",
    "link": "https://diariodarepublica.pt/dr/detalhe/contrato-publico/2074-1028852419"
  },
  {
    "numero_procedimento": "N/A",
    "entidade": "AnÃºncio de procedimento  n.Âº 2076/2026  -  DiÃ¡rio da RepÃºblica n.Âº 20/2026, SÃ©rie II de 2026-01-29",
    "link": "https://diariodarepublica.pt/dr/detalhe/contrato-publico/2076-1028852420"
  },
  {
    "numero_procedimento": "N/A",
    "entidade": "AR - Águas do Ribatejo, EIM, SA",
    "link": "https://diariodarepublica.pt/dr/detalhe/contrato-publico/2078-1028852421",
    "detalhes_completos": "1 - IDENTIFICAÇÃO E CONTACTOS DA ENTIDADE ADJUDICANTE\nDesignação da entidade adjudicante: AR - Águas do Ribatejo, EIM, SA\nNIPC: 508345464\nEndereço: Rua Gaspar Costa Ramalho, nº38\nCódigo postal: 2120-098\nLocalidade: Santarém\nPaís: Portugal\nNUT III: PT185\nDistrito: Santarém\nConcelho: Salvaterra de Magos\nFreguesia: União das Freguesias de Salvaterra de Magos e Foros de Salvaterra\nTelefone: 243303240\nEndereço da Entidade (URL): www.aguasdoribatejo.com\nEndereço Eletrónico: geral@aguasdoribatejo.com\neDelivery Gateway (URL): https://community.vortal.biz/public/\nFunção da Organização: Adquirente\nNorma jurídica da Entidade Adjudicante: Empresa pública\nÁrea de atividade da Autoridade Adjudicante: Proteção ambiental\n2 - JORNAL OFICIAL DA UNIÃO EUROPEIA\nO procedimento a que este anúncio diz respeito também é publicitado no Jornal Oficial da União Europeia? Sim\n3 - AVISO\nModelo de Anúncio: Concurso público\nData de Envio do Anúncio: 27-01-2026\n5 - PROCESSO\nTipo de Procedimento: Concurso público\nPreço base do procedimento: Sim\nValor do preço base do procedimento: 90.000,00 EUR\nProcedimento com lotes? Não\n6 - OBJETO DO CONTRATO\nNúmero de referência interna: FPS/006/2026\nDesignação do contrato: Fiscalização da empreitada de execução da ampliação do Subsistema de Abastecimento de Benavente/Vale Tripeiro e Samora Correia\nDescrição: Prestação de serviços para a fiscalização da empreitada de execução da ampliação do Subsistema de Abastecimento de Benavente/Vale Tripeiro e Samora Correia\nOpções: Não\nTipo de Contrato Principal: Aquisição de Serviços\nTipo de Contrato: Aquisição de Serviços\nClassificação CPV (Vocabulário Comum para os Contratos Públicos)\nObjeto principal\nVocabulário Principal: 71247000\nPreço base s/IVA: 90.000,00 EUR\n7 - INDICAÇÕES ADICIONAIS\nO contrato envolve aquisição conjunta (satisfação de várias entidades)? Não\nO contrato é adjudicado por uma central de compras? Não\n8 - TÉCNICAS\nO concurso destina-se à celebração de um acordo-quadro? Inexistência de acordo-quadro\nÉ utilizado um leilão eletrónico? Não\nÉ adotada uma fase de negociação? Não\nSistema de Aquisição Dinâmico: Inexistência de sistema de aquisição dinâmico\n9 - LOCAL DA EXECUÇÃO DO CONTRATO\nLOCAL DA EXECUÇÃO DO CONTRATO (PROCEDIMENTO)\nPaís: Portugal\nNUT III: PT185\nLocalidade: Benavente\nDistrito: Santarém\nConcelho: Benavente\nFreguesia: Freguesia de Benavente\n10 - PRAZO DE EXECUÇÃO DO CONTRATO\nPrazo de execução do contrato: 20 MESES\nPrevisão de renovações: Não\n11 - FUNDOS EU\nTêm fundos EU? Não\n12 - DOCUMENTOS DE HABILITAÇÃO\nHabilitação para o exercício da atividade profissional: Sim\nTipo: Outros\nDescrição - Outros: Conforme programa de concurso e caderno de encargos\nDescrição: Conforme programa do concurso.\n13 - CONDIÇÕES DE APRESENTAÇÃO\nPlataforma eletrónica utilizada pela entidade adjudicante: VORTAL\nURL para Apresentação: https://community.vortal.biz/public/\nAdmissibilidade da apresentação de propostas variantes: Não autorizado\nPrazo para apresentação das propostas: 27-02-2026 23:59\nPrazo durante o qual os concorrentes são obrigados a manter as respetivas propostas: 180 dias a contar do termo do prazo para a apresentação das propostas\nApresentação de Catálogo Eletrónico: Permitido\nIndicação de Subcontratação na Proposta: Inexistência de indicação de subcontratação\n14 - PRESTAÇÃO DE CAUÇÃO\nPrestação de caução: Sim\nPercentagem: 5%\nDescrição da Garantia Exigida: Conforme programa do concurso.\n15 - FORNECIMENTO DAS PEÇAS DO CONCURSO, APRESENTAÇÃO DE PEDIDOS DE PARTICIPAÇÃO E APRESENTAÇÃO DAS PROPOSTAS\nLink para acesso às peças do concurso (URL): https://community.vortal.biz/Public/public-tender-documents/MDlrMm14c3FHMEExYjROQWxMaFFkN0QzekhadHpxMHRCRElrMGJLUjNMNnVuOUxZK3RaNEI2dHhxcDlweERwUkhGb2VqdkNBYk1vU2d3ejhDdG5zOHc9PVpCKnUk\n20 - OUTROS REQUISITOS\nInformação sobre contratos reservados. Aplica-se a contratos reservados (54º-A)? Não\n21 - CRITÉRIO DE ADJUDICAÇÃO\nMultifator: Não\nMonofator:\nNome: Preço\n24 - CONDIÇÕES DO CONTRATO\nFaturação Eletrónica: Permitido\nObrigação de Subcontratação:\nCódigo da Obrigação de Subcontratação: Não é aplicável nenhuma obrigação de subcontratação.\n25 - COMPRA PÚBLICA ESTRATÉGICA\nCompra Pública Estratégica: Inexistência de contratação pública estratégica\n26 - INFORMAÇÕES ADICIONAIS\nContrato adequado para PME: Sim\nCobertura ACP (Acordo dos Contratos Públicos da Organização Mundial do Comércio): Não\n27 - IDENTIFICAÇÃO E CONTACTOS DO ÓRGÃO DE RECURSOS ADMINISTRATIVOS\nDesignação: Conselho de Administração da AR - Águas do Ribatejo, EIM, SA\nEndereço: Rua Gaspar Costa Ramalho, 38\nCódigo postal: 2120-098\nLocalidade: Salvaterra de Magos\nTelefone: +351 263509400\nFax: +351 263509499\nEndereço eletrónico: geral@aguasdoribatejo.com\n28 - IDENTIFICAÇÃO DO(S) AUTOR(ES) DE ANÚNCIO\nNome: Sonia Isabel Fernandes Sanfona Cruz Mendes\nCargo: Presidente do Conselho de Administração\n419949277",
    "nipc": "508345464",
    "distrito": "Santarém",
    "concelho": "Salvaterra de Magos",
    "freguesia": "União das Freguesias de Salvaterra de Magos e Foros de Salvaterra",
    "site": "www.aguasdoribatejo.com",
    "email": "geral@aguasdoribatejo.com",
    "designacao_contrato": "Fiscalização da empreitada de execução da ampliação do Subsistema de Abastecimento de Benavente/Vale Tripeiro e Samora Correia",
    "descricao": "Prestação de serviços para a fiscalização da empreitada de execução da ampliação do Subsistema de Abastecimento de Benavente/Vale Tripeiro e Samora Correia",
    "preco_base": "90.000,00 EUR",
    "prazo_execucao": "20 MESES",
    "prazo_apresentacao_propostas": "27-02-2026 23:59",
    "fundos_eu": "Não",
    "plataforma_eletronica": "VORTAL",
    "url_procedimento": "https://community.vortal.biz/public/",
    "autor_nome": "Sonia Isabel Fernandes Sanfona Cruz Mendes",
    "autor_cargo": "Presidente do Conselho de Administração"
  },
  {
    "numero_procedimento": "N/A",
    "entidade": "AnÃºncio de procedimento  n.Âº 2080/2026  -  DiÃ¡rio da RepÃºblica n.Âº 20/2026, SÃ©rie II de 2026-01-29",
    "link": "https://diariodarepublica.pt/dr/detalhe/contrato-publico/2080-1028852422"
  },
  {
    "numero_procedimento": "N/A",
    "entidade": "Município de Sintra",
    "link": "https://diariodarepublica.pt/dr/detalhe/contrato-publico/2081-1028852423",
    "detalhes_completos": "1 - IDENTIFICAÇÃO E CONTACTOS DA ENTIDADE ADJUDICANTE\nDesignação da entidade adjudicante: Município de Sintra\nNIPC: 500051062\nEndereço: Largo Doutor Virgílio Horta\nCódigo postal: 2710-501\nLocalidade: Lisboa\nPaís: Portugal\nNUT III: PT170\nDistrito: Lisboa\nConcelho: Sintra\nFreguesia: União das Freguesias de Sintra (Santa Maria e São Miguel, São Martinho e São Pedro de Penaferrim)\nTelefone: 219238749\nFax: 219238790\nEndereço da Entidade (URL): www.cm-sintra.pt\nEndereço Eletrónico: dcp@cm-sintra.pt\neDelivery Gateway (URL): https://community.vortal.biz/public/\nFunção da Organização: Adquirente\nNorma jurídica da Entidade Adjudicante: Autoridade local\nÁrea de atividade da Autoridade Adjudicante: Serviços públicos das administrações públicas\n2 - JORNAL OFICIAL DA UNIÃO EUROPEIA\nO procedimento a que este anúncio diz respeito também é publicitado no Jornal Oficial da União Europeia? Não\n3 - AVISO\nModelo de Anúncio: Concurso público\nData de Envio do Anúncio: 29-01-2026\n5 - PROCESSO\nTipo de Procedimento: Concurso público\nPreço base do procedimento: Sim\nValor do preço base do procedimento: 47.355,00 EUR\nProcedimento com lotes? Não\n6 - OBJETO DO CONTRATO\nNúmero de referência interna: CT-26/00062\nDesignação do contrato: CT-26/00062 – Aquisição de têxteis e outros bens em Regime de Fornecimento contínuo para 2026\nDescrição: CT-26/00062 – Aquisição de têxteis e outros bens em Regime de Fornecimento contínuo para 2026\nTipo de Contrato Principal: Aquisição de Bens Móveis\nTipo de Contrato: Aquisição de Bens Móveis\nClassificação CPV (Vocabulário Comum para os Contratos Públicos)\nObjeto principal\nVocabulário Principal: 19200000\nPreço base s/IVA: 47.355,00 EUR\n7 - INDICAÇÕES ADICIONAIS\nO contrato envolve aquisição conjunta (satisfação de várias entidades)? Não\nO contrato é adjudicado por uma central de compras? Não\n8 - TÉCNICAS\nO concurso destina-se à celebração de um acordo-quadro? Inexistência de acordo-quadro\nÉ utilizado um leilão eletrónico? Não\nÉ adotada uma fase de negociação? Não\nSistema de Aquisição Dinâmico: Inexistência de sistema de aquisição dinâmico\n9 - LOCAL DA EXECUÇÃO DO CONTRATO\nLOCAL DA EXECUÇÃO DO CONTRATO (PROCEDIMENTO)\nPaís: Portugal\nNUT III: PT170\nLocalidade: Lisboa\nDistrito: Lisboa\nConcelho: Sintra\nFreguesia: União das Freguesias de Sintra (Santa Maria e São Miguel, São Martinho e São Pedro de Penaferrim)\n10 - PRAZO DE EXECUÇÃO DO CONTRATO\nPrazo de execução do contrato: 1 ANOS\nPrevisão de renovações: Não\n11 - FUNDOS EU\nTêm fundos EU? Não\n12 - DOCUMENTOS DE HABILITAÇÃO\nHabilitação para o exercício da atividade profissional: Não\n13 - CONDIÇÕES DE APRESENTAÇÃO\nPlataforma eletrónica utilizada pela entidade adjudicante: VORTAL\nURL para Apresentação: https://community.vortal.biz/public/\nAdmissibilidade da apresentação de propostas variantes: Não autorizado\nPrazo para apresentação das propostas: 10-02-2026 18:00\nPrazo durante o qual os concorrentes são obrigados a manter as respetivas propostas: 66 dias a contar do termo do prazo para a apresentação das propostas\nIndicação de Subcontratação na Proposta: Inexistência de indicação de subcontratação\n14 - PRESTAÇÃO DE CAUÇÃO\nPrestação de caução: Não\n15 - FORNECIMENTO DAS PEÇAS DO CONCURSO, APRESENTAÇÃO DE PEDIDOS DE PARTICIPAÇÃO E APRESENTAÇÃO DAS PROPOSTAS\nLink para acesso às peças do concurso (URL): https://community.vortal.biz/Public/public-tender-documents/NjFNZHJldXFZSDJVRTlOaXZ1T1ZJWDFaNkw0a0RVekJXMU9nU2JPV0J4blhDUDhoa0pTQ3h1Nk9mbDBST3RlOG42MFYrblczUGl1QXk0TmF2WG5XdXc9PV5WOFQq\n20 - OUTROS REQUISITOS\nInformação sobre contratos reservados. Aplica-se a contratos reservados (54º-A)? Não\n21 - CRITÉRIO DE ADJUDICAÇÃO\nMultifator: Não\nMonofator:\nNome: Preço\n24 - CONDIÇÕES DO CONTRATO\nFaturação Eletrónica: Permitido\nObrigação de Subcontratação:\nCódigo da Obrigação de Subcontratação: Não é aplicável nenhuma obrigação de subcontratação.\n25 - COMPRA PÚBLICA ESTRATÉGICA\nCompra Pública Estratégica: Inexistência de contratação pública estratégica\n26 - INFORMAÇÕES ADICIONAIS\nContrato adequado para PME: Sim\nCobertura ACP (Acordo dos Contratos Públicos da Organização Mundial do Comércio): Não\n27 - IDENTIFICAÇÃO E CONTACTOS DO ÓRGÃO DE RECURSOS ADMINISTRATIVOS\nDesignação: Presidente da Câmara\nEndereço: Largo Dr. Virgílio Horta\nCódigo postal: 2714-501\nLocalidade: Sintra\nTelefone: +351 219238736\nFax: +351 219238790\nEndereço eletrónico: dcp@cm-sintra.pt\n28 - IDENTIFICAÇÃO DO(S) AUTOR(ES) DE ANÚNCIO\nNome: Marco Almeida\nCargo: Presidente da Câmara Municipal de Sintra\n419949290",
    "nipc": "500051062",
    "distrito": "Lisboa",
    "concelho": "Sintra",
    "freguesia": "União das Freguesias de Sintra (Santa Maria e São Miguel, São Martinho e São Pedro de Penaferrim)",
    "site": "www.cm-sintra.pt",
    "email": "dcp@cm-sintra.pt",
    "designacao_contrato": "CT-26/00062 – Aquisição de têxteis e outros bens em Regime de Fornecimento contínuo para 2026",
    "descricao": "CT-26/00062 – Aquisição de têxteis e outros bens em Regime de Fornecimento contínuo para 2026",
    "preco_base": "47.355,00 EUR",
    "prazo_execucao": "1 ANOS",
    "prazo_apresentacao_propostas": "10-02-2026 18:00",
    "fundos_eu": "Não",
    "plataforma_eletronica": "VORTAL",
    "url_procedimento": "https://community.vortal.biz/public/",
    "autor_nome": "Marco Almeida",
    "autor_cargo": "Presidente da Câmara Municipal de Sintra"
  },
  {
    "numero_procedimento": "N/A",
    "entidade": "Município de Sintra",
    "link": "https://diariodarepublica.pt/dr/detalhe/contrato-publico/2082-1028852424",
    "detalhes_completos": "1 - IDENTIFICAÇÃO E CONTACTOS DA ENTIDADE ADJUDICANTE\nDesignação da entidade adjudicante: Município de Sintra\nNIPC: 500051062\nEndereço: Largo Doutor Virgílio Horta\nCódigo postal: 2710-501\nLocalidade: Lisboa\nPaís: Portugal\nNUT III: PT170\nDistrito: Lisboa\nConcelho: Sintra\nFreguesia: União das Freguesias de Sintra (Santa Maria e São Miguel, São Martinho e São Pedro de Penaferrim)\nTelefone: 219238749\nFax: 219238790\nEndereço da Entidade (URL): www.cm-sintra.pt\nEndereço Eletrónico: dcp@cm-sintra.pt\neDelivery Gateway (URL): https://community.vortal.biz/public/\nFunção da Organização: Adquirente\nNorma jurídica da Entidade Adjudicante: Autoridade local\nÁrea de atividade da Autoridade Adjudicante: Serviços públicos das administrações públicas\n2 - JORNAL OFICIAL DA UNIÃO EUROPEIA\nO procedimento a que este anúncio diz respeito também é publicitado no Jornal Oficial da União Europeia? Não\n3 - AVISO\nModelo de Anúncio: Concurso público\nData de Envio do Anúncio: 29-01-2026\n5 - PROCESSO\nTipo de Procedimento: Concurso público\nPreço base do procedimento: Sim\nValor do preço base do procedimento: 20.000,00 EUR\nProcedimento com lotes? Não\n6 - OBJETO DO CONTRATO\nNúmero de referência interna: CT-26/00029\nDesignação do contrato: CT-26/00029 – Afagamento, enceramento e envernizamento de superfícies de madeira, em RFC, para 2026\nDescrição: CT-26/00029 – Afagamento, enceramento e envernizamento de superfícies de madeira, em RFC, para 2026\nTipo de Contrato Principal: Aquisição de Serviços\nTipo de Contrato: Aquisição de Serviços\nClassificação CPV (Vocabulário Comum para os Contratos Públicos)\nObjeto principal\nVocabulário Principal: 98390000\nPreço base s/IVA: 20.000,00 EUR\n7 - INDICAÇÕES ADICIONAIS\nO contrato envolve aquisição conjunta (satisfação de várias entidades)? Não\nO contrato é adjudicado por uma central de compras? Não\n8 - TÉCNICAS\nO concurso destina-se à celebração de um acordo-quadro? Inexistência de acordo-quadro\nÉ utilizado um leilão eletrónico? Não\nÉ adotada uma fase de negociação? Não\nSistema de Aquisição Dinâmico: Inexistência de sistema de aquisição dinâmico\n9 - LOCAL DA EXECUÇÃO DO CONTRATO\nLOCAL DA EXECUÇÃO DO CONTRATO (PROCEDIMENTO)\nPaís: Portugal\nNUT III: PT170\nLocalidade: Lisboa\nDistrito: Lisboa\nConcelho: Sintra\nFreguesia: União das Freguesias de Sintra (Santa Maria e São Miguel, São Martinho e São Pedro de Penaferrim)\n10 - PRAZO DE EXECUÇÃO DO CONTRATO\nPrazo de execução do contrato: 240 DIAS\nPrevisão de renovações: Não\n11 - FUNDOS EU\nTêm fundos EU? Não\n12 - DOCUMENTOS DE HABILITAÇÃO\nHabilitação para o exercício da atividade profissional: Não\n13 - CONDIÇÕES DE APRESENTAÇÃO\nPlataforma eletrónica utilizada pela entidade adjudicante: VORTAL\nURL para Apresentação: https://community.vortal.biz/public/\nAdmissibilidade da apresentação de propostas variantes: Não autorizado\nPrazo para apresentação das propostas: 10-02-2026 18:00\nPrazo durante o qual os concorrentes são obrigados a manter as respetivas propostas: 66 dias a contar do termo do prazo para a apresentação das propostas\nIndicação de Subcontratação na Proposta: Inexistência de indicação de subcontratação\n14 - PRESTAÇÃO DE CAUÇÃO\nPrestação de caução: Não\n15 - FORNECIMENTO DAS PEÇAS DO CONCURSO, APRESENTAÇÃO DE PEDIDOS DE PARTICIPAÇÃO E APRESENTAÇÃO DAS PROPOSTAS\nLink para acesso às peças do concurso (URL): https://community.vortal.biz/Public/public-tender-documents/NVg4QTJtQlFCVmtYQXJacFN5cGV4MnYrM2ttekpDZE5FS3d1dE5PLysvV09TYktxVVpjbWhlTis0V1F3bktWSFo0QTZDVUtpNHJYL2ZDanJzL29WcUE9PWh2bDNN\n20 - OUTROS REQUISITOS\nInformação sobre contratos reservados. Aplica-se a contratos reservados (54º-A)? Não\n21 - CRITÉRIO DE ADJUDICAÇÃO\nMultifator: Não\nMonofator:\nNome: Preço\n24 - CONDIÇÕES DO CONTRATO\nFaturação Eletrónica: Permitido\nObrigação de Subcontratação:\nCódigo da Obrigação de Subcontratação: Não é aplicável nenhuma obrigação de subcontratação.\n25 - COMPRA PÚBLICA ESTRATÉGICA\nCompra Pública Estratégica: Inexistência de contratação pública estratégica\n26 - INFORMAÇÕES ADICIONAIS\nContrato adequado para PME: Sim\nCobertura ACP (Acordo dos Contratos Públicos da Organização Mundial do Comércio): Não\n27 - IDENTIFICAÇÃO E CONTACTOS DO ÓRGÃO DE RECURSOS ADMINISTRATIVOS\nDesignação: Presidente da Câmara Municipal de Sintra\nEndereço: Largo Dr. Virgílio Horta\nCódigo postal: 2714-501\nLocalidade: Sintra\nTelefone: +351 219238749\nFax: +351 219238790\nEndereço eletrónico: dcp@cm-sintra.pt\n28 - IDENTIFICAÇÃO DO(S) AUTOR(ES) DE ANÚNCIO\nNome: Marco Almeida\nCargo: Presidente da Câmara Municipal de Sintra\n419949289",
    "nipc": "500051062",
    "distrito": "Lisboa",
    "concelho": "Sintra",
    "freguesia": "União das Freguesias de Sintra (Santa Maria e São Miguel, São Martinho e São Pedro de Penaferrim)",
    "site": "www.cm-sintra.pt",
    "email": "dcp@cm-sintra.pt",
    "designacao_contrato": "CT-26/00029 – Afagamento, enceramento e envernizamento de superfícies de madeira, em RFC, para 2026",
    "descricao": "CT-26/00029 – Afagamento, enceramento e envernizamento de superfícies de madeira, em RFC, para 2026",
    "preco_base": "20.000,00 EUR",
    "prazo_execucao": "240 DIAS",
    "prazo_apresentacao_propostas": "10-02-2026 18:00",
    "fundos_eu": "Não",
    "plataforma_eletronica": "VORTAL",
    "url_procedimento": "https://community.vortal.biz/public/",
    "autor_nome": "Marco Almeida",
    "autor_cargo": "Presidente da Câmara Municipal de Sintra"
  },
  {
    "numero_procedimento": "N/A",
    "entidade": "Estado Maior da Força Aérea",
    "link": "https://diariodarepublica.pt/dr/detalhe/contrato-publico/2085-1028852430",
    "detalhes_completos": "1 - IDENTIFICAÇÃO E CONTACTOS DA ENTIDADE ADJUDICANTE\nDesignação da entidade adjudicante: Estado Maior da Força Aérea\nNIPC: 600010686\nServiço/Órgão/Pessoa de contacto: Ministério da Defesa Nacional  Comando da Logística da Força Aérea  DIREÇÃO DE MANUTENÇÃO DE SISTEMAS DE ARMAS\nEndereço: Avenida da Força Aérea Portuguesa, Nº1\nCódigo postal: 2614-506\nLocalidade: Amadora\nPaís: Portugal\nNUT III: PT170\nDistrito: Lisboa\nConcelho: Amadora\nFreguesia: Freguesia de Alfragide\nTelefone: 214723726\nFax: 214723850\nEndereço da Entidade (URL): http://www.emfa.pt/www/contactos\nEndereço Eletrónico: CLAFA.AQUIS@EMFA.GOV.PT\neDelivery Gateway (URL): https://www.acingov.pt\nFunção da Organização: Adquirente\nNorma jurídica da Entidade Adjudicante: Organismo de direito público\nÁrea de atividade da Autoridade Adjudicante: Defesa\n2 - JORNAL OFICIAL DA UNIÃO EUROPEIA\nO procedimento a que este anúncio diz respeito também é publicitado no Jornal Oficial da União Europeia? Não\n3 - AVISO\nModelo de Anúncio: Concurso público\nData de Envio do Anúncio: 29-01-2026\n5 - PROCESSO\nTipo de Procedimento: Concurso público\nPreço base do procedimento: Sim\nValor do preço base do procedimento: 37.110,03 EUR\nProcedimento com lotes? Sim\nNº Máx. de Lotes Autorizado: 3\nNúmero máximo de lotes que podem ser adjudicados a um concorrente: 3\n6 - OBJETO DO CONTRATO\nNúmero de referência interna: DMAS 5026000465\nDesignação do contrato: CONCURSO PÚBLICO PARA REVISÃO GERAL DE GARRAFAS DE OXIGÉNIO DAS FROTAS P-3C E C-130H\nDescrição: CONCURSO PÚBLICO PARA REVISÃO GERAL DE GARRAFAS DE OXIGÉNIO DAS FROTAS P-3C E C-130H\nTipo de Contrato Principal: Aquisição de Serviços\nTipo de Contrato: Aquisição de Serviços\nClassificação CPV (Vocabulário Comum para os Contratos Públicos)\nObjeto principal\nVocabulário Principal: 50210000\nPreço base s/IVA: 37.110,03 EUR\nLotes: \nNº: LOT-0001\nDescrição do Lote: Cylinder and Regulator\nPreço base s/IVA: 24.370,83 EUR\nClassificação CPV (Vocabulário Comum para os Contratos Públicos)\nObjeto principal\nVocabulário Principal: 50210000\nNº: LOT-0002\nDescrição do Lote: Cylinder and Regulator\nPreço base s/IVA: 3.283,20 EUR\nClassificação CPV (Vocabulário Comum para os Contratos Públicos)\nObjeto principal\nVocabulário Principal: 50210000\nNº: LOT-0003\nDescrição do Lote: Cylinder and Regulator\nPreço base s/IVA: 9.456,00 EUR\nClassificação CPV (Vocabulário Comum para os Contratos Públicos)\nObjeto principal\nVocabulário Principal: 50210000\n7 - INDICAÇÕES ADICIONAIS\nO contrato envolve aquisição conjunta (satisfação de várias entidades)? Não\nO contrato é adjudicado por uma central de compras? Não\n8 - TÉCNICAS\nO concurso destina-se à celebração de um acordo-quadro? Inexistência de acordo-quadro\nÉ utilizado um leilão eletrónico? Não\nÉ adotada uma fase de negociação? Não\nSistema de Aquisição Dinâmico: Inexistência de sistema de aquisição dinâmico\n9 - LOCAL DA EXECUÇÃO DO CONTRATO\nLOCAL DA EXECUÇÃO DO CONTRATO (PROCEDIMENTO)\nPaís: Portugal\nNUT III: PT16H\nLocalidade: União das Freguesias de Beja (Santiago Maior e São João Baptista)\nDistrito: Beja\nConcelho: Beja\nFreguesia: União das Freguesias de Beja (Santiago Maior e São João Baptista)\nPaís: Portugal\nNUT III: PT170\nLocalidade: União das Freguesias de Montijo e Afonsoeiro\nDistrito: Setúbal\nConcelho: Montijo\nFreguesia: União das Freguesias de Montijo e Afonsoeiro\nLOCAL DA EXECUÇÃO DO CONTRATO (LOTE)\nIdentificador do Lote: LOT-0001; LOT-0002; LOT-0003\nPaís: Portugal\nNUT III: PT16H\nLocalidade: União das Freguesias de Beja (Santiago Maior e São João Baptista)\nDistrito: Beja\nConcelho: Beja\nFreguesia: União das Freguesias de Beja (Santiago Maior e São João Baptista)\nIdentificador do Lote: LOT-0001; LOT-0002; LOT-0003\nPaís: Portugal\nNUT III: PT170\nLocalidade: União das Freguesias de Montijo e Afonsoeiro\nDistrito: Setúbal\nConcelho: Montijo\nFreguesia: União das Freguesias de Montijo e Afonsoeiro\n10 - PRAZO DE EXECUÇÃO DO CONTRATO\nIdentificador do Lote: LOT-0001; LOT-0002; LOT-0003\nPrazo de execução do contrato: 120 DIAS\nPrevisão de renovações: Não\n11 - FUNDOS EU\nIdentificador do Lote: LOT-0001; LOT-0002; LOT-0003\nTêm fundos EU? Não\n12 - DOCUMENTOS DE HABILITAÇÃO\nHabilitação para o exercício da atividade profissional: Não\n13 - CONDIÇÕES DE APRESENTAÇÃO\nPlataforma eletrónica utilizada pela entidade adjudicante: ACIN\nURL para Apresentação: https://www.acingov.pt\nAdmissibilidade da apresentação de propostas variantes: Não autorizado\nPrazo para apresentação das propostas: 09-02-2026 23:00\nPrazo durante o qual os concorrentes são obrigados a manter as respetivas propostas: 66 dias a contar do termo do prazo para a apresentação das propostas\nIndicação de Subcontratação na Proposta: Inexistência de indicação de subcontratação\n14 - PRESTAÇÃO DE CAUÇÃO\nPrestação de caução: Não\n15 - FORNECIMENTO DAS PEÇAS DO CONCURSO, APRESENTAÇÃO DE PEDIDOS DE PARTICIPAÇÃO E APRESENTAÇÃO DAS PROPOSTAS\nLink para acesso às peças do concurso (URL): https://www.acingov.pt/acingovprod/2/zonaPublica/zona_publica_c/donwloadProcedurePiece/MTA1MjA5OA==\n20 - OUTROS REQUISITOS\nIdentificador do Lote: LOT-0001; LOT-0002; LOT-0003\nInformação sobre contratos reservados. Aplica-se a contratos reservados (54º-A)? Não\n21 - CRITÉRIO DE ADJUDICAÇÃO\nO Critério de adjudicação é diferenciado por lote? Não\nMultifator: Não\nMonofator:\nNome: Preço\n24 - CONDIÇÕES DO CONTRATO\nIdentificador do Lote: LOT-0001; LOT-0002; LOT-0003\nFaturação Eletrónica: Permitido\nObrigação de Subcontratação:\nCódigo da Obrigação de Subcontratação: Não é aplicável nenhuma obrigação de subcontratação.\n25 - COMPRA PÚBLICA ESTRATÉGICA\nCompra Pública Estratégica: Inexistência de contratação pública estratégica\n26 - INFORMAÇÕES ADICIONAIS\nIdentificador do Lote: LOT-0001; LOT-0002; LOT-0003\nContrato adequado para PME: Sim\nCobertura ACP (Acordo dos Contratos Públicos da Organização Mundial do Comércio): Não\n27 - IDENTIFICAÇÃO E CONTACTOS DO ÓRGÃO DE RECURSOS ADMINISTRATIVOS\nDesignação: DIREÇÃO DE MANUTENÇÃO DE SISTEMAS DE ARMAS\nEndereço: Avenida da Força Aérea Portuguesa, Nº1\nCódigo postal: 2614-506\nLocalidade: Amadora\nTelefone: 214723726\nFax: 214723850\nEndereço eletrónico: clafa.aquis@emfa.gov.pt\n28 - IDENTIFICAÇÃO DO(S) AUTOR(ES) DE ANÚNCIO\nNome: COR/ADMAER/FILIPE RODRIGUES\nCargo: CHEFE DO GAP\n419949430",
    "nipc": "600010686",
    "distrito": "Lisboa",
    "concelho": "Amadora",
    "freguesia": "Freguesia de Alfragide",
    "site": "http://www.emfa.pt/www/contactos",
    "email": "CLAFA.AQUIS@EMFA.GOV.PT",
    "designacao_contrato": "CONCURSO PÚBLICO PARA REVISÃO GERAL DE GARRAFAS DE OXIGÉNIO DAS FROTAS P-3C E C-130H",
    "descricao": "CONCURSO PÚBLICO PARA REVISÃO GERAL DE GARRAFAS DE OXIGÉNIO DAS FROTAS P-3C E C-130H",
    "preco_base": "37.110,03 EUR",
    "prazo_execucao": "120 DIAS",
    "prazo_apresentacao_propostas": "09-02-2026 23:00",
    "fundos_eu": "Não",
    "plataforma_eletronica": "ACIN",
    "url_procedimento": "https://www.acingov.pt",
    "autor_nome": "COR/ADMAER/FILIPE RODRIGUES",
    "autor_cargo": "CHEFE DO GAP"
  },
  {
    "numero_procedimento": "N/A",
    "entidade": "AnÃºncio de procedimento  n.Âº 2086/2026  -  DiÃ¡rio da RepÃºblica n.Âº 20/2026, SÃ©rie II de 2026-01-29",
    "link": "https://diariodarepublica.pt/dr/detalhe/contrato-publico/2086-1028852431"
  },
  {
    "numero_procedimento": "N/A",
    "entidade": "AnÃºncio de procedimento  n.Âº 2087/2026  -  DiÃ¡rio da RepÃºblica n.Âº 20/2026, SÃ©rie II de 2026-01-29",
    "link": "https://diariodarepublica.pt/dr/detalhe/contrato-publico/2087-1028852432"
  },
  {
    "numero_procedimento": "N/A",
    "entidade": "AnÃºncio de procedimento  n.Âº 2090/2026  -  DiÃ¡rio da RepÃºblica n.Âº 20/2026, SÃ©rie II de 2026-01-29",
    "link": "https://diariodarepublica.pt/dr/detalhe/contrato-publico/2090-1029684017"
  },
  {
    "numero_procedimento": "N/A",
    "entidade": "AnÃºncio de procedimento  n.Âº 2093/2026  -  DiÃ¡rio da RepÃºblica n.Âº 20/2026, SÃ©rie II de 2026-01-29",
    "link": "https://diariodarepublica.pt/dr/detalhe/contrato-publico/2093-1029684019"
  },
  {
    "numero_procedimento": "N/A",
    "entidade": "Município de Faro",
    "link": "https://diariodarepublica.pt/dr/detalhe/contrato-publico/2095-1029684020",
    "detalhes_completos": "1 - IDENTIFICAÇÃO E CONTACTOS DA ENTIDADE ADJUDICANTE\nDesignação da entidade adjudicante: Município de Faro\nNIPC: 506579425\nServiço/Órgão/Pessoa de contacto: Divisão de Contratação Pública\nEndereço: Largo da Sé\nCódigo postal: 8004-001\nLocalidade: Faro\nPaís: Portugal\nNUT III: PT150\nDistrito: Faro\nConcelho: Faro\nFreguesia: Todas\nTelefone: 289870870\nFax: 289870039\nEndereço da Entidade (URL): www.cm-faro.pt\nEndereço Eletrónico: geral@cm-faro.pt\neDelivery Gateway (URL): https://www.acingov.pt\nFunção da Organização: Adquirente\nNorma jurídica da Entidade Adjudicante: Organismo de direito público\nÁrea de atividade da Autoridade Adjudicante: Serviços públicos das administrações públicas\n2 - JORNAL OFICIAL DA UNIÃO EUROPEIA\nO procedimento a que este anúncio diz respeito também é publicitado no Jornal Oficial da União Europeia? Não\n3 - AVISO\nModelo de Anúncio: Concurso público\nData de Envio do Anúncio: 29-01-2026\n5 - PROCESSO\nTipo de Procedimento: Concurso público\nPreço base do procedimento: Sim\nValor do preço base do procedimento: 121.951,22 EUR\nProcedimento com lotes? Não\n6 - OBJETO DO CONTRATO\nNúmero de referência interna: 2026/300.10.005/44\nDesignação do contrato: Aquisição de serviços para a Assessoria Técnica Especializada\nDescrição: Aquisição de serviços para a Assessoria Técnica Especializada\nTipo de Contrato Principal: Aquisição de Serviços\nTipo de Contrato: Aquisição de Serviços\nClassificação CPV (Vocabulário Comum para os Contratos Públicos)\nObjeto principal\nVocabulário Principal: 79411000\nPreço base s/IVA: 121.951,22 EUR\n7 - INDICAÇÕES ADICIONAIS\nO contrato envolve aquisição conjunta (satisfação de várias entidades)? Não\nO contrato é adjudicado por uma central de compras? Não\n8 - TÉCNICAS\nO concurso destina-se à celebração de um acordo-quadro? Inexistência de acordo-quadro\nÉ utilizado um leilão eletrónico? Não\nÉ adotada uma fase de negociação? Não\nSistema de Aquisição Dinâmico: Inexistência de sistema de aquisição dinâmico\n9 - LOCAL DA EXECUÇÃO DO CONTRATO\nLOCAL DA EXECUÇÃO DO CONTRATO (PROCEDIMENTO)\nPaís: Portugal\nNUT III: PT150\nLocalidade: Faro\nDistrito: Faro\nConcelho: Faro\nFreguesia: Todas\n10 - PRAZO DE EXECUÇÃO DO CONTRATO\nPrazo de execução do contrato: 15 MESES\nPrevisão de renovações: Não\n11 - FUNDOS EU\nTêm fundos EU? Não\n12 - DOCUMENTOS DE HABILITAÇÃO\nHabilitação para o exercício da atividade profissional: Não\n13 - CONDIÇÕES DE APRESENTAÇÃO\nPlataforma eletrónica utilizada pela entidade adjudicante: ACIN\nURL para Apresentação: https://www.acingov.pt\nAdmissibilidade da apresentação de propostas variantes: Não autorizado\nPrazo para apresentação das propostas: 04-02-2026 23:59\nPrazo durante o qual os concorrentes são obrigados a manter as respetivas propostas: 90 dias a contar do termo do prazo para a apresentação das propostas\nIndicação de Subcontratação na Proposta: Inexistência de indicação de subcontratação\n14 - PRESTAÇÃO DE CAUÇÃO\nPrestação de caução: Não\n15 - FORNECIMENTO DAS PEÇAS DO CONCURSO, APRESENTAÇÃO DE PEDIDOS DE PARTICIPAÇÃO E APRESENTAÇÃO DAS PROPOSTAS\nLink para acesso às peças do concurso (URL): https://www.acingov.pt/acingovprod/2/zonaPublica/zona_publica_c/donwloadProcedurePiece/MTA1MTA0OQ==\n20 - OUTROS REQUISITOS\nInformação sobre contratos reservados. Aplica-se a contratos reservados (54º-A)? Não\n21 - CRITÉRIO DE ADJUDICAÇÃO\nMultifator: Sim\nFator: \nNome: Preço\nPonderação: 20%\nSubfatores: Não\nFator: \nNome: Outros\nOutro Nome: PESSOAL ENCARREGADO DE EXECUÇÃO DO CONTRATO (EP)\nPonderação: 80%\nSubfatores: Sim\nSubfatores: \nNome: SUBFATOR 2.1  NE - Número de Elementos da Equipa Afeta ao Projeto\nPonderação : 10%; \nNome: SUBFATOR 2.2  PE - Perfil da Equipa Afeta ao Projeto\nPonderação : 10%; \nNome: SUBFATOR 2.3  GP1 - Perfil do Gestor de Projeto  experiência no mesmo âmbito em entidades da Administração local\nPonderação : 50%; \nNome: SUBFATOR 2.4  GP2 - Perfil do Gestor de Projeto  experiência em outros âmbitos em entidades da Administração Local\nPonderação : 30%; \n24 - CONDIÇÕES DO CONTRATO\nFaturação Eletrónica: Necessário\nObrigação de Subcontratação:\nCódigo da Obrigação de Subcontratação: Não é aplicável nenhuma obrigação de subcontratação.\n25 - COMPRA PÚBLICA ESTRATÉGICA\nCompra Pública Estratégica: Inexistência de contratação pública estratégica\n26 - INFORMAÇÕES ADICIONAIS\nContrato adequado para PME: Sim\nCobertura ACP (Acordo dos Contratos Públicos da Organização Mundial do Comércio): Não\n27 - IDENTIFICAÇÃO E CONTACTOS DO ÓRGÃO DE RECURSOS ADMINISTRATIVOS\nDesignação: Câmara Municipal de Faro\nEndereço: Largo da Sé\nCódigo postal: 8004-001\nLocalidade: Faro\nTelefone: 289870870\nFax: \nEndereço eletrónico: geral@cm-faro.pt\nPrazo de interposição do recurso: 10 dias\n28 - IDENTIFICAÇÃO DO(S) AUTOR(ES) DE ANÚNCIO\nNome: António Miguel Ventura Pina\nCargo: Presidente da Câmara Municipal de Faro\n419949341",
    "nipc": "506579425",
    "distrito": "Faro",
    "concelho": "Faro",
    "freguesia": "Todas",
    "site": "www.cm-faro.pt",
    "email": "geral@cm-faro.pt",
    "designacao_contrato": "Aquisição de serviços para a Assessoria Técnica Especializada",
    "descricao": "Aquisição de serviços para a Assessoria Técnica Especializada",
    "preco_base": "121.951,22 EUR",
    "prazo_execucao": "15 MESES",
    "prazo_apresentacao_propostas": "04-02-2026 23:59",
    "fundos_eu": "Não",
    "plataforma_eletronica": "ACIN",
    "url_procedimento": "https://www.acingov.pt",
    "autor_nome": "António Miguel Ventura Pina",
    "autor_cargo": "Presidente da Câmara Municipal de Faro"
  },
  {
    "numero_procedimento": "N/A",
    "entidade": "AnÃºncio de procedimento  n.Âº 2099/2026  -  DiÃ¡rio da RepÃºblica n.Âº 20/2026, SÃ©rie II de 2026-01-29",
    "link": "https://diariodarepublica.pt/dr/detalhe/contrato-publico/2099-1029684021"
  },
  {
    "numero_procedimento": "N/A",
    "entidade": "AnÃºncio de procedimento  n.Âº 2100/2026  -  DiÃ¡rio da RepÃºblica n.Âº 20/2026, SÃ©rie II de 2026-01-29",
    "link": "https://diariodarepublica.pt/dr/detalhe/contrato-publico/2100-1029684022"
  },
  {
    "numero_procedimento": "N/A",
    "entidade": "AnÃºncio de procedimento  n.Âº 2103/2026  -  DiÃ¡rio da RepÃºblica n.Âº 20/2026, SÃ©rie II de 2026-01-29",
    "link": "https://diariodarepublica.pt/dr/detalhe/contrato-publico/2103-1029684024"
  },
  {
    "numero_procedimento": "N/A",
    "entidade": "AnÃºncio de procedimento  n.Âº 2105/2026  -  DiÃ¡rio da RepÃºblica n.Âº 20/2026, SÃ©rie II de 2026-01-29",
    "link": "https://diariodarepublica.pt/dr/detalhe/contrato-publico/2105-1029684025"
  },
  {
    "numero_procedimento": "N/A",
    "entidade": "AnÃºncio de procedimento  n.Âº 2110/2026  -  DiÃ¡rio da RepÃºblica n.Âº 20/2026, SÃ©rie II de 2026-01-29",
    "link": "https://diariodarepublica.pt/dr/detalhe/contrato-publico/2110-1029684029"
  },
  {
    "numero_procedimento": "N/A",
    "entidade": "AnÃºncio de procedimento  n.Âº 2111/2026  -  DiÃ¡rio da RepÃºblica n.Âº 20/2026, SÃ©rie II de 2026-01-29",
    "link": "https://diariodarepublica.pt/dr/detalhe/contrato-publico/2111-1029684030"
  },
  {
    "numero_procedimento": "N/A",
    "entidade": "AnÃºncio de procedimento  n.Âº 2112/2026  -  DiÃ¡rio da RepÃºblica n.Âº 20/2026, SÃ©rie II de 2026-01-29",
    "link": "https://diariodarepublica.pt/dr/detalhe/contrato-publico/2112-1029684031"
  },
  {
    "numero_procedimento": "N/A",
    "entidade": "AnÃºncio de procedimento  n.Âº 2115/2026  -  DiÃ¡rio da RepÃºblica n.Âº 20/2026, SÃ©rie II de 2026-01-29",
    "link": "https://diariodarepublica.pt/dr/detalhe/contrato-publico/2115-1029684037"
  },
  {
    "numero_procedimento": "N/A",
    "entidade": "AnÃºncio de procedimento  n.Âº 2118/2026  -  DiÃ¡rio da RepÃºblica n.Âº 20/2026, SÃ©rie II de 2026-01-29",
    "link": "https://diariodarepublica.pt/dr/detalhe/contrato-publico/2118-1029684044"
  },
  {
    "numero_procedimento": "N/A",
    "entidade": "AnÃºncio de procedimento  n.Âº 2121/2026  -  DiÃ¡rio da RepÃºblica n.Âº 20/2026, SÃ©rie II de 2026-01-29",
    "link": "https://diariodarepublica.pt/dr/detalhe/contrato-publico/2121-1029684050"
  },
  {
    "numero_procedimento": "N/A",
    "entidade": "Município de Cabeceiras de Basto",
    "link": "https://diariodarepublica.pt/dr/detalhe/contrato-publico/2122-1029684051",
    "detalhes_completos": "1 - IDENTIFICAÇÃO E CONTACTOS DA ENTIDADE ADJUDICANTE\nDesignação da entidade adjudicante: Município de Cabeceiras de Basto\nNIPC: 505330334\nEndereço: Praça da República\nCódigo postal: 4860-355\nLocalidade: Cabeceiras de Basto\nPaís: Portugal\nNUT III: PT119\nDistrito: Braga\nConcelho: Cabeceiras de Basto\nFreguesia: Todas\nTelefone: 253669100\nFax: 253669209\nEndereço da Entidade (URL): http://www.cm-cabeceiras-basto.pt\nEndereço Eletrónico: servicoatendimentounico@cabeceirasdebasto.pt\neDelivery Gateway (URL): https://community.vortal.biz/public/\nFunção da Organização: Adquirente\nNorma jurídica da Entidade Adjudicante: Autoridade da administração central\nÁrea de atividade da Autoridade Adjudicante: Serviços públicos das administrações públicas\n2 - JORNAL OFICIAL DA UNIÃO EUROPEIA\nO procedimento a que este anúncio diz respeito também é publicitado no Jornal Oficial da União Europeia? Não\n3 - AVISO\nModelo de Anúncio: Concurso público\nData de Envio do Anúncio: 29-01-2026\n5 - PROCESSO\nTipo de Procedimento: Concurso público\nPreço base do procedimento: Sim\nValor do preço base do procedimento: 60.600,00 EUR\nProcedimento com lotes? Não\n6 - OBJETO DO CONTRATO\nNúmero de referência interna: Processo n.º 16/2026\nDesignação do contrato: serviços de Patrocínio e de Assessoria Jurídica em Processos Extrajudiciais, na modalidade de avença\nDescrição: serviços de Patrocínio e de Assessoria Jurídica em Processos Extrajudiciais, na modalidade de avença\nTipo de Contrato Principal: Aquisição de Serviços\nTipo de Contrato: Aquisição de Serviços\nClassificação CPV (Vocabulário Comum para os Contratos Públicos)\nObjeto principal\nVocabulário Principal: 79110000\nPreço base s/IVA: 60.600,00 EUR\n7 - INDICAÇÕES ADICIONAIS\nO contrato envolve aquisição conjunta (satisfação de várias entidades)? Não\nO contrato é adjudicado por uma central de compras? Não\n8 - TÉCNICAS\nO concurso destina-se à celebração de um acordo-quadro? Inexistência de acordo-quadro\nÉ utilizado um leilão eletrónico? Não\nÉ adotada uma fase de negociação? Não\nSistema de Aquisição Dinâmico: Inexistência de sistema de aquisição dinâmico\n9 - LOCAL DA EXECUÇÃO DO CONTRATO\nLOCAL DA EXECUÇÃO DO CONTRATO (PROCEDIMENTO)\nPaís: Portugal\nNUT III: PT119\nLocalidade: Braga\nDistrito: Braga\nConcelho: Cabeceiras de Basto\nFreguesia: Todas\n10 - PRAZO DE EXECUÇÃO DO CONTRATO\nPrazo de execução do contrato: 24 MESES\nPrevisão de renovações: Não\n11 - FUNDOS EU\nTêm fundos EU? Não\n12 - DOCUMENTOS DE HABILITAÇÃO\nHabilitação para o exercício da atividade profissional: Não\n13 - CONDIÇÕES DE APRESENTAÇÃO\nPlataforma eletrónica utilizada pela entidade adjudicante: VORTAL\nURL para Apresentação: https://community.vortal.biz/public/\nAdmissibilidade da apresentação de propostas variantes: Não autorizado\nPrazo para apresentação das propostas: 04-02-2026 18:00\nPrazo durante o qual os concorrentes são obrigados a manter as respetivas propostas: 66 dias a contar do termo do prazo para a apresentação das propostas\nIndicação de Subcontratação na Proposta: Inexistência de indicação de subcontratação\n14 - PRESTAÇÃO DE CAUÇÃO\nPrestação de caução: Não\n15 - FORNECIMENTO DAS PEÇAS DO CONCURSO, APRESENTAÇÃO DE PEDIDOS DE PARTICIPAÇÃO E APRESENTAÇÃO DAS PROPOSTAS\nLink para acesso às peças do concurso (URL): https://community.vortal.biz/Public/public-tender-documents/aGxlVnFIL2VkWk1rdG1qZXBMTnUwSVJxY1VwMHczamoxNGs4MVoxa2hiMHJ1V0RjVk1CNllvcDNDYjFQYjlGUm9VcllPK3RmRWxObTZKSHQ1aEtVdHc9PV5NNl5x\n20 - OUTROS REQUISITOS\nInformação sobre contratos reservados. Aplica-se a contratos reservados (54º-A)? Não\n21 - CRITÉRIO DE ADJUDICAÇÃO\nMultifator: Não\nMonofator:\nNome: Preço\n24 - CONDIÇÕES DO CONTRATO\nFaturação Eletrónica: Permitido\nObrigação de Subcontratação:\nCódigo da Obrigação de Subcontratação: Não é aplicável nenhuma obrigação de subcontratação.\n25 - COMPRA PÚBLICA ESTRATÉGICA\nCompra Pública Estratégica: Inexistência de contratação pública estratégica\n26 - INFORMAÇÕES ADICIONAIS\nContrato adequado para PME: Sim\nCobertura ACP (Acordo dos Contratos Públicos da Organização Mundial do Comércio): Não\n27 - IDENTIFICAÇÃO E CONTACTOS DO ÓRGÃO DE RECURSOS ADMINISTRATIVOS\nDesignação: Município de Cabeceiras de Basto\nEndereço: Praça da República, n467, Refofos de Basto\nCódigo postal: 4860-355\nLocalidade: Cabeceiras de Basto\nTelefone: +351 253669100\nFax: +351 253662726\nEndereço eletrónico: sbarroso@cabeceirasdebasto.pt\n28 - IDENTIFICAÇÃO DO(S) AUTOR(ES) DE ANÚNCIO\nNome: Manuel António Mendes Teixeira\nCargo: Presidente da Câmara\n419949473",
    "nipc": "505330334",
    "distrito": "Braga",
    "concelho": "Cabeceiras de Basto",
    "freguesia": "Todas",
    "site": "http://www.cm-cabeceiras-basto.pt",
    "email": "servicoatendimentounico@cabeceirasdebasto.pt",
    "designacao_contrato": "serviços de Patrocínio e de Assessoria Jurídica em Processos Extrajudiciais, na modalidade de avença",
    "descricao": "serviços de Patrocínio e de Assessoria Jurídica em Processos Extrajudiciais, na modalidade de avença",
    "preco_base": "60.600,00 EUR",
    "prazo_execucao": "24 MESES",
    "prazo_apresentacao_propostas": "04-02-2026 18:00",
    "fundos_eu": "Não",
    "plataforma_eletronica": "VORTAL",
    "url_procedimento": "https://community.vortal.biz/public/",
    "autor_nome": "Manuel António Mendes Teixeira",
    "autor_cargo": "Presidente da Câmara"
  },
  {
    "numero_procedimento": "N/A",
    "entidade": "Município de Oliveira de Azeméis",
    "link": "https://diariodarepublica.pt/dr/detalhe/contrato-publico/2127-1029684052",
    "detalhes_completos": "1 - IDENTIFICAÇÃO E CONTACTOS DA ENTIDADE ADJUDICANTE\nDesignação da entidade adjudicante: Município de Oliveira de Azeméis\nNIPC: 506302970\nEndereço: Largo da Républica\nCódigo postal: 3720-240\nLocalidade: Oliveira de Azeméis\nPaís: Portugal\nNUT III: PT11A\nDistrito: Aveiro\nConcelho: Oliveira de Azemeis\nFreguesia: União das Freguesias de Oliveira de Azeméis, Santiago de Riba-Ul, Ul, Macinhata da Seixa e Madail\nTelefone: 256600600\nFax: 256600626\nEndereço da Entidade (URL): www.cm-oaz.pt\nEndereço Eletrónico: geral@cm-oaz.pt\neDelivery Gateway (URL): https://www.acingov.pt\nFunção da Organização: Adquirente\nNorma jurídica da Entidade Adjudicante: Organismo de direito público\nÁrea de atividade da Autoridade Adjudicante: Serviços públicos das administrações públicas\n2 - JORNAL OFICIAL DA UNIÃO EUROPEIA\nO procedimento a que este anúncio diz respeito também é publicitado no Jornal Oficial da União Europeia? Não\n3 - AVISO\nModelo de Anúncio: Concurso público\nData de Envio do Anúncio: 29-01-2026\n5 - PROCESSO\nTipo de Procedimento: Concurso público\nPreço base do procedimento: Sim\nValor do preço base do procedimento: 189.289,99 EUR\nProcedimento com lotes? Não\n6 - OBJETO DO CONTRATO\nNúmero de referência interna: CP/4/2026 (01/2026/DOMTE)\nDesignação do contrato: Melhoria de condições de acessibilidade nas escolas do concelho de Oliveira de Azeméis\nDescrição: Melhoria de condições de acessibilidade nas escolas do concelho de Oliveira de Azeméis\nTipo de Contrato Principal: Empreitada de Obras Públicas\nTipo de Contrato: Empreitada de Obras Públicas\nClassificação CPV (Vocabulário Comum para os Contratos Públicos)\nObjeto principal\nVocabulário Principal: 45233253\nPreço base s/IVA: 189.289,99 EUR\n7 - INDICAÇÕES ADICIONAIS\nO contrato envolve aquisição conjunta (satisfação de várias entidades)? Não\nO contrato é adjudicado por uma central de compras? Não\n8 - TÉCNICAS\nO concurso destina-se à celebração de um acordo-quadro? Inexistência de acordo-quadro\nÉ utilizado um leilão eletrónico? Não\nÉ adotada uma fase de negociação? Não\nSistema de Aquisição Dinâmico: Inexistência de sistema de aquisição dinâmico\n9 - LOCAL DA EXECUÇÃO DO CONTRATO\nLOCAL DA EXECUÇÃO DO CONTRATO (PROCEDIMENTO)\nPaís: Portugal\nNUT III: PT11A\nLocalidade: Todas\nDistrito: Aveiro\nConcelho: Oliveira de Azemeis\nFreguesia: Todas\n10 - PRAZO DE EXECUÇÃO DO CONTRATO\nPrazo de execução do contrato: 30 DIAS\nPrevisão de renovações: Não\n11 - FUNDOS EU\nTêm fundos EU? Sim\n12 - DOCUMENTOS DE HABILITAÇÃO\nHabilitação para o exercício da atividade profissional: Sim\nTipo: Alvará\nDescrição: A 8.ª e 11ª Subcategorias da 2.ª Categoria  Vias de comunicação, Obras de Urbanização e outras Infraestruturas, a qual tem de ser de classe que cubra o valor global da proposta\n13 - CONDIÇÕES DE APRESENTAÇÃO\nPlataforma eletrónica utilizada pela entidade adjudicante: ACIN\nURL para Apresentação: https://www.acingov.pt\nAdmissibilidade da apresentação de propostas variantes: Não autorizado\nPrazo para apresentação das propostas: 12-02-2026 17:00\nPrazo durante o qual os concorrentes são obrigados a manter as respetivas propostas: 110 dias a contar do termo do prazo para a apresentação das propostas\nIndicação de Subcontratação na Proposta: Inexistência de indicação de subcontratação\n14 - PRESTAÇÃO DE CAUÇÃO\nPrestação de caução: Não\n15 - FORNECIMENTO DAS PEÇAS DO CONCURSO, APRESENTAÇÃO DE PEDIDOS DE PARTICIPAÇÃO E APRESENTAÇÃO DAS PROPOSTAS\nLink para acesso às peças do concurso (URL): https://www.acingov.pt/acingovprod/2/zonaPublica/zona_publica_c/donwloadProcedurePiece/MTA1MDUyNQ==\n20 - OUTROS REQUISITOS\nInformação sobre contratos reservados. Aplica-se a contratos reservados (54º-A)? Não\n21 - CRITÉRIO DE ADJUDICAÇÃO\nMultifator: Não\nMonofator:\nNome: Preço\n24 - CONDIÇÕES DO CONTRATO\nFaturação Eletrónica: Permitido\nObrigação de Subcontratação:\nCódigo da Obrigação de Subcontratação: Não é aplicável nenhuma obrigação de subcontratação.\n25 - COMPRA PÚBLICA ESTRATÉGICA\nCompra Pública Estratégica: Inexistência de contratação pública estratégica\n26 - INFORMAÇÕES ADICIONAIS\nContrato adequado para PME: Sim\nCobertura ACP (Acordo dos Contratos Públicos da Organização Mundial do Comércio): Não\n27 - IDENTIFICAÇÃO E CONTACTOS DO ÓRGÃO DE RECURSOS ADMINISTRATIVOS\nDesignação: Presidente da Câmara Municipal\nEndereço: Largo da República\nCódigo postal: 3720-240\nLocalidade: Oliveira de Azeméis\nTelefone: 256600600\nFax: \nEndereço eletrónico: presidencia@cm-oaz.pt\n28 - IDENTIFICAÇÃO DO(S) AUTOR(ES) DE ANÚNCIO\nNome: Joaquim Jorge Ferreira\nCargo: Presidente da Câmara Municipal\n419949437",
    "nipc": "506302970",
    "distrito": "Aveiro",
    "concelho": "Oliveira de Azemeis",
    "freguesia": "União das Freguesias de Oliveira de Azeméis, Santiago de Riba-Ul, Ul, Macinhata da Seixa e Madail",
    "site": "www.cm-oaz.pt",
    "email": "geral@cm-oaz.pt",
    "designacao_contrato": "Melhoria de condições de acessibilidade nas escolas do concelho de Oliveira de Azeméis",
    "descricao": "Melhoria de condições de acessibilidade nas escolas do concelho de Oliveira de Azeméis",
    "preco_base": "189.289,99 EUR",
    "prazo_execucao": "30 DIAS",
    "prazo_apresentacao_propostas": "12-02-2026 17:00",
    "fundos_eu": "Sim",
    "plataforma_eletronica": "ACIN",
    "url_procedimento": "https://www.acingov.pt",
    "autor_nome": "Joaquim Jorge Ferreira",
    "autor_cargo": "Presidente da Câmara Municipal"
  },
  {
    "numero_procedimento": "N/A",
    "entidade": "Município de Oeiras",
    "link": "https://diariodarepublica.pt/dr/detalhe/contrato-publico/2129-1029684054",
    "detalhes_completos": "1 - IDENTIFICAÇÃO E CONTACTOS DA ENTIDADE ADJUDICANTE\nDesignação da entidade adjudicante: Município de Oeiras\nNIPC: 500745943\nEndereço: Largo Marquês de Pombal\nCódigo postal: 2784-501\nLocalidade: Lisboa\nPaís: Portugal\nNUT III: PT170\nDistrito: Lisboa\nConcelho: Oeiras\nFreguesia: União das Freguesias de Oeiras e São Julião da Barra, Paço de Arcos e Caxias\nTelefone: 214408300\nFax: 214408712\nEndereço da Entidade (URL): www.cm-oeiras.pt\nEndereço Eletrónico: divisao.contratacaopublica@cm-oeiras.pt\neDelivery Gateway (URL): https://community.vortal.biz/public/\nFunção da Organização: Adquirente\nNorma jurídica da Entidade Adjudicante: Autoridade local\nÁrea de atividade da Autoridade Adjudicante: Serviços públicos das administrações públicas\n2 - JORNAL OFICIAL DA UNIÃO EUROPEIA\nO procedimento a que este anúncio diz respeito também é publicitado no Jornal Oficial da União Europeia? Não\n3 - AVISO\nModelo de Anúncio: Concurso público\nData de Envio do Anúncio: 29-01-2026\n5 - PROCESSO\nTipo de Procedimento: Concurso público\nPreço base do procedimento: Sim\nValor do preço base do procedimento: 103.568,10 EUR\nProcedimento com lotes? Não\n6 - OBJETO DO CONTRATO\nNúmero de referência interna: 12/DCP/2026\nDesignação do contrato: Aquisição da prestação de serviços de Security Ratings e monitorização contínua da postura de cibersegurança\nDescrição: Aquisição da prestação de serviços de Security Ratings e monitorização contínua da postura de cibersegurança\nTipo de Contrato Principal: Aquisição de Serviços\nTipo de Contrato: Aquisição de Serviços\nClassificação CPV (Vocabulário Comum para os Contratos Públicos)\nObjeto principal\nVocabulário Principal: 72590000\nPreço base s/IVA: 103.568,10 EUR\n7 - INDICAÇÕES ADICIONAIS\nO contrato envolve aquisição conjunta (satisfação de várias entidades)? Não\nO contrato é adjudicado por uma central de compras? Não\n8 - TÉCNICAS\nO concurso destina-se à celebração de um acordo-quadro? Inexistência de acordo-quadro\nÉ utilizado um leilão eletrónico? Não\nÉ adotada uma fase de negociação? Não\nSistema de Aquisição Dinâmico: Inexistência de sistema de aquisição dinâmico\n9 - LOCAL DA EXECUÇÃO DO CONTRATO\nLOCAL DA EXECUÇÃO DO CONTRATO (PROCEDIMENTO)\nPaís: Portugal\nNUT III: PT170\nLocalidade: Lisboa\nDistrito: Lisboa\nConcelho: Oeiras\nFreguesia: União das Freguesias de Oeiras e São Julião da Barra, Paço de Arcos e Caxias\n10 - PRAZO DE EXECUÇÃO DO CONTRATO\nPrazo de execução do contrato: 36 MESES\nPrevisão de renovações: Não\n11 - FUNDOS EU\nTêm fundos EU? Não\n12 - DOCUMENTOS DE HABILITAÇÃO\nHabilitação para o exercício da atividade profissional: Não\n13 - CONDIÇÕES DE APRESENTAÇÃO\nPlataforma eletrónica utilizada pela entidade adjudicante: VORTAL\nURL para Apresentação: https://community.vortal.biz/public/\nAdmissibilidade da apresentação de propostas variantes: Não autorizado\nPrazo para apresentação das propostas: 11-02-2026 17:00\nPrazo durante o qual os concorrentes são obrigados a manter as respetivas propostas: 66 dias a contar do termo do prazo para a apresentação das propostas\nIndicação de Subcontratação na Proposta: Inexistência de indicação de subcontratação\n14 - PRESTAÇÃO DE CAUÇÃO\nPrestação de caução: Não\n15 - FORNECIMENTO DAS PEÇAS DO CONCURSO, APRESENTAÇÃO DE PEDIDOS DE PARTICIPAÇÃO E APRESENTAÇÃO DAS PROPOSTAS\nLink para acesso às peças do concurso (URL): https://community.vortal.biz/Public/public-tender-documents/dWdXaXJXenp0QkNxVUVlUjlzUlhrd2JKTWR1MUIxcFJHdzEvUmZSZ2RSNnhIRkZRZWhiTkVkNkpmUjMzVGwyaE5CS2NNWWRZbDhWcmQrWjZ0a0tsMXc9PUwraG0r\n20 - OUTROS REQUISITOS\nInformação sobre contratos reservados. Aplica-se a contratos reservados (54º-A)? Não\n21 - CRITÉRIO DE ADJUDICAÇÃO\nMultifator: Não\nMonofator:\nNome: Preço\n24 - CONDIÇÕES DO CONTRATO\nFaturação Eletrónica: Permitido\nObrigação de Subcontratação:\nCódigo da Obrigação de Subcontratação: Não é aplicável nenhuma obrigação de subcontratação.\n25 - COMPRA PÚBLICA ESTRATÉGICA\nCompra Pública Estratégica: Inexistência de contratação pública estratégica\n26 - INFORMAÇÕES ADICIONAIS\nContrato adequado para PME: Sim\nCobertura ACP (Acordo dos Contratos Públicos da Organização Mundial do Comércio): Não\n27 - IDENTIFICAÇÃO E CONTACTOS DO ÓRGÃO DE RECURSOS ADMINISTRATIVOS\nDesignação: Divisão de Contratação  Pública\nEndereço: Largo Marquês de Pombal\nCódigo postal: 2785-501\nLocalidade: Oeiras\nTelefone: +351 214408300\nFax: +351 214408300\nEndereço eletrónico: divisao.contratacaopublica@oeiras.pt\n28 - IDENTIFICAÇÃO DO(S) AUTOR(ES) DE ANÚNCIO\nNome: Dr. Isaltino Morais\nCargo: Presidente C.M.O.\n419949452",
    "nipc": "500745943",
    "distrito": "Lisboa",
    "concelho": "Oeiras",
    "freguesia": "União das Freguesias de Oeiras e São Julião da Barra, Paço de Arcos e Caxias",
    "site": "www.cm-oeiras.pt",
    "email": "divisao.contratacaopublica@cm-oeiras.pt",
    "designacao_contrato": "Aquisição da prestação de serviços de Security Ratings e monitorização contínua da postura de cibersegurança",
    "descricao": "Aquisição da prestação de serviços de Security Ratings e monitorização contínua da postura de cibersegurança",
    "preco_base": "103.568,10 EUR",
    "prazo_execucao": "36 MESES",
    "prazo_apresentacao_propostas": "11-02-2026 17:00",
    "fundos_eu": "Não",
    "plataforma_eletronica": "VORTAL",
    "url_procedimento": "https://community.vortal.biz/public/",
    "autor_nome": "Dr. Isaltino Morais",
    "autor_cargo": "Presidente C.M.O."
  },
  {
    "numero_procedimento": "N/A",
    "entidade": "Estado Maior da Força Aérea",
    "link": "https://diariodarepublica.pt/dr/detalhe/contrato-publico/2131-1029684068",
    "detalhes_completos": "1 - IDENTIFICAÇÃO E CONTACTOS DA ENTIDADE ADJUDICANTE\nDesignação da entidade adjudicante: Estado Maior da Força Aérea\nNIPC: 600010686\nServiço/Órgão/Pessoa de contacto: Ministério da Defesa Nacional  Força Aérea  Comando da Logística  Direção de Manutenção de Sistemas de Armas\nEndereço: Avenida da Força Aérea Portuguesa, Nº1\nCódigo postal: 2614-506\nLocalidade: Amadora\nPaís: Portugal\nNUT III: PT170\nDistrito: Lisboa\nConcelho: Todos\nFreguesia: Todas\nTelefone: 214723861\nEndereço da Entidade (URL): http://www.emfa.pt/www/contactos\nEndereço Eletrónico: clafa.gadial@emfa.gov.pt\neDelivery Gateway (URL): https://www.acingov.pt\nFunção da Organização: Adquirente\nNorma jurídica da Entidade Adjudicante: Organismo de direito público\nÁrea de atividade da Autoridade Adjudicante: Defesa\n2 - JORNAL OFICIAL DA UNIÃO EUROPEIA\nO procedimento a que este anúncio diz respeito também é publicitado no Jornal Oficial da União Europeia? Não\n3 - AVISO\nModelo de Anúncio: Concurso público\nData de Envio do Anúncio: 29-01-2026\n5 - PROCESSO\nTipo de Procedimento: Concurso público\nPreço base do procedimento: Sim\nValor do preço base do procedimento: 135.000,00 EUR\nProcedimento com lotes? Sim\nNº Máx. de Lotes Autorizado: 2\nNúmero máximo de lotes que podem ser adjudicados a um concorrente: 2\n6 - OBJETO DO CONTRATO\nNúmero de referência interna: DMSA 5026000383\nDesignação do contrato: DMSA 5026000383 - AQUISIÇÃO DE PNEUS NLG E MLG PARA AERONAVE F-16\nDescrição: DMSA 5026000383 - AQUISIÇÃO DE PNEUS NLG E MLG PARA AERONAVE F-16\nTipo de Contrato Principal: Aquisição de Bens Móveis\nTipo de Contrato: Aquisição de Bens Móveis\nClassificação CPV (Vocabulário Comum para os Contratos Públicos)\nObjeto principal\nVocabulário Principal: 34731800\nPreço base s/IVA: 135.000,00 EUR\nLotes: \nNº: LOT-0001\nDescrição do Lote: NLG BIAS TIRE - TIRE, PNEUMATIC, TUBELESS, 18 x 5.7-8, 18 PLY RATING\nPreço base s/IVA: 18.000,00 EUR\nClassificação CPV (Vocabulário Comum para os Contratos Públicos)\nObjeto principal\nVocabulário Principal: 34731800\nNº: LOT-0002\nDescrição do Lote: MLG RADIAL TIRE - TIRE, PNEUMATIC, TUBELESS, 25.5 X 8.0-14, 20 PLY RATING\nPreço base s/IVA: 117.000,00 EUR\nClassificação CPV (Vocabulário Comum para os Contratos Públicos)\nObjeto principal\nVocabulário Principal: 34731800\n7 - INDICAÇÕES ADICIONAIS\nO contrato envolve aquisição conjunta (satisfação de várias entidades)? Não\nO contrato é adjudicado por uma central de compras? Não\n8 - TÉCNICAS\nO concurso destina-se à celebração de um acordo-quadro? Inexistência de acordo-quadro\nÉ utilizado um leilão eletrónico? Não\nÉ adotada uma fase de negociação? Não\nSistema de Aquisição Dinâmico: Inexistência de sistema de aquisição dinâmico\n9 - LOCAL DA EXECUÇÃO DO CONTRATO\nLOCAL DA EXECUÇÃO DO CONTRATO (PROCEDIMENTO)\nPaís: Portugal\nNUT III: PT16F\nLocalidade: Conforme as Peças do Procedimento\nDistrito: Leiria\nConcelho: Leiria\nFreguesia: União das Freguesias de Monte Real e Carvide\nLOCAL DA EXECUÇÃO DO CONTRATO (LOTE)\nIdentificador do Lote: LOT-0001; LOT-0002\nPaís: Portugal\nNUT III: PT16F\nLocalidade: Conforme as Peças do Procedimento\nDistrito: Leiria\nConcelho: Leiria\nFreguesia: União das Freguesias de Monte Real e Carvide\n10 - PRAZO DE EXECUÇÃO DO CONTRATO\nIdentificador do Lote: LOT-0001; LOT-0002\nPrazo de execução do contrato: 250 DIAS\nPrevisão de renovações: Não\n11 - FUNDOS EU\nIdentificador do Lote: LOT-0001; LOT-0002\nTêm fundos EU? Não\n12 - DOCUMENTOS DE HABILITAÇÃO\nHabilitação para o exercício da atividade profissional: Não\n13 - CONDIÇÕES DE APRESENTAÇÃO\nPlataforma eletrónica utilizada pela entidade adjudicante: ACIN\nURL para Apresentação: https://www.acingov.pt\nAdmissibilidade da apresentação de propostas variantes: Não autorizado\nPrazo para apresentação das propostas: 13-02-2026 23:00\nPrazo durante o qual os concorrentes são obrigados a manter as respetivas propostas: 66 dias a contar do termo do prazo para a apresentação das propostas\nIndicação de Subcontratação na Proposta: Inexistência de indicação de subcontratação\n14 - PRESTAÇÃO DE CAUÇÃO\nPrestação de caução: Não\n15 - FORNECIMENTO DAS PEÇAS DO CONCURSO, APRESENTAÇÃO DE PEDIDOS DE PARTICIPAÇÃO E APRESENTAÇÃO DAS PROPOSTAS\nLink para acesso às peças do concurso (URL): https://www.acingov.pt/acingovprod/2/zonaPublica/zona_publica_c/donwloadProcedurePiece/MTA1MjQ0Ng==\n20 - OUTROS REQUISITOS\nIdentificador do Lote: LOT-0001; LOT-0002\nInformação sobre contratos reservados. Aplica-se a contratos reservados (54º-A)? Não\n21 - CRITÉRIO DE ADJUDICAÇÃO\nO Critério de adjudicação é diferenciado por lote? Não\nMultifator: Não\nMonofator:\nNome: Preço\n24 - CONDIÇÕES DO CONTRATO\nIdentificador do Lote: LOT-0001; LOT-0002\nFaturação Eletrónica: Permitido\nObrigação de Subcontratação:\nCódigo da Obrigação de Subcontratação: Não é aplicável nenhuma obrigação de subcontratação.\n25 - COMPRA PÚBLICA ESTRATÉGICA\nCompra Pública Estratégica: Inexistência de contratação pública estratégica\n26 - INFORMAÇÕES ADICIONAIS\nIdentificador do Lote: LOT-0001; LOT-0002\nContrato adequado para PME: Sim\nCobertura ACP (Acordo dos Contratos Públicos da Organização Mundial do Comércio): Não\n27 - IDENTIFICAÇÃO E CONTACTOS DO ÓRGÃO DE RECURSOS ADMINISTRATIVOS\nDesignação: Chefe do Estado-Maior da Força Aérea\nEndereço: Avenida da Força Aérea Portuguesa, Nº1\nCódigo postal: 2614-506\nLocalidade: Amadora\nTelefone: 214723861\nFax: \nEndereço eletrónico: CLAFA.AQUIS@EMFA.GOV.PT\n28 - IDENTIFICAÇÃO DO(S) AUTOR(ES) DE ANÚNCIO\nNome: COR/ADMAER/FILIPE RODRIGUES\nCargo: CHEFE DO GAP\n419949510",
    "nipc": "600010686",
    "distrito": "Lisboa",
    "concelho": "Todos",
    "freguesia": "Todas",
    "site": "http://www.emfa.pt/www/contactos",
    "email": "clafa.gadial@emfa.gov.pt",
    "designacao_contrato": "DMSA 5026000383 - AQUISIÇÃO DE PNEUS NLG E MLG PARA AERONAVE F-16",
    "descricao": "DMSA 5026000383 - AQUISIÇÃO DE PNEUS NLG E MLG PARA AERONAVE F-16",
    "preco_base": "135.000,00 EUR",
    "prazo_execucao": "250 DIAS",
    "prazo_apresentacao_propostas": "13-02-2026 23:00",
    "fundos_eu": "Não",
    "plataforma_eletronica": "ACIN",
    "url_procedimento": "https://www.acingov.pt",
    "autor_nome": "COR/ADMAER/FILIPE RODRIGUES",
    "autor_cargo": "CHEFE DO GAP"
  },
  {
    "numero_procedimento": "N/A",
    "entidade": "Unidade Local de Saúde de Coimbra, EPE",
    "link": "https://diariodarepublica.pt/dr/detalhe/contrato-publico/2107-1029684175",
    "detalhes_completos": "1 - IDENTIFICAÇÃO E CONTACTOS DA ENTIDADE ADJUDICANTE\nDesignação da entidade adjudicante: Unidade Local de Saúde de Coimbra, EPE\nNIPC: 510103448\nEndereço: Praceta Prof. Mota Pinto\nCódigo postal: 3004-561\nLocalidade: Coimbra\nPaís: Portugal\nNUT III: PT16E\nDistrito: Coimbra\nConcelho: Coimbra\nFreguesia: Todas\nTelefone: 239400605\nFax: 239400605\nEndereço da Entidade (URL): https://www.chuc.min-saude.pt\nEndereço Eletrónico: ana.rosete@ulscoimbra.min-saude.pt\neDelivery Gateway (URL): https://community.vortal.biz/public/\nFunção da Organização: Adquirente\nNorma jurídica da Entidade Adjudicante: Organismo de direito público\nÁrea de atividade da Autoridade Adjudicante: Saúde\n2 - JORNAL OFICIAL DA UNIÃO EUROPEIA\nO procedimento a que este anúncio diz respeito também é publicitado no Jornal Oficial da União Europeia? Não\n3 - AVISO\nModelo de Anúncio: Concurso público\nData de Envio do Anúncio: 29-01-2026\n5 - PROCESSO\nTipo de Procedimento: Concurso público\nPreço base do procedimento: Sim\nValor do preço base do procedimento: 58.718,87 EUR\nProcedimento com lotes? Sim\nNº Máx. de Lotes Autorizado: 75\nNúmero máximo de lotes que podem ser adjudicados a um concorrente: 75\n6 - OBJETO DO CONTRATO\nNúmero de referência interna: 010000032026\nDesignação do contrato: Controlo Externo da Qual. Analitica- Aquis. de Prog. Aval. Externa da qual. p/areas de Bioquimica\nDescrição: Controlo Externo da Qual. Analitica- Aquis. de Prog. Aval. Externa da qual. p/areas de Bioquimica\nTipo de Contrato Principal: Aquisição de Bens Móveis\nTipo de Contrato: Aquisição de Bens Móveis\nClassificação CPV (Vocabulário Comum para os Contratos Públicos)\nObjeto principal\nVocabulário Principal: 33696500\nPreço base s/IVA: 58.718,87 EUR\nLotes: \nNº: LOT-0001\nDescrição do Lote: Lote 1\nPreço base s/IVA: 1.479,72 EUR\nClassificação CPV (Vocabulário Comum para os Contratos Públicos)\nObjeto principal\nVocabulário Principal: 33696500\nNº: LOT-0002\nDescrição do Lote: Lote 2\nPreço base s/IVA: 779,20 EUR\nClassificação CPV (Vocabulário Comum para os Contratos Públicos)\nObjeto principal\nVocabulário Principal: 33696500\nNº: LOT-0003\nDescrição do Lote: Lote 3\nPreço base s/IVA: 823,40 EUR\nClassificação CPV (Vocabulário Comum para os Contratos Públicos)\nObjeto principal\nVocabulário Principal: 33696500\nNº: LOT-0004\nDescrição do Lote: Lote 4\nPreço base s/IVA: 1.693,50 EUR\nClassificação CPV (Vocabulário Comum para os Contratos Públicos)\nObjeto principal\nVocabulário Principal: 33696500\nNº: LOT-0005\nDescrição do Lote: Lote 5\nPreço base s/IVA: 635,00 EUR\nClassificação CPV (Vocabulário Comum para os Contratos Públicos)\nObjeto principal\nVocabulário Principal: 33696500\nNº: LOT-0006\nDescrição do Lote: Lote 6\nPreço base s/IVA: 2.877,00 EUR\nClassificação CPV (Vocabulário Comum para os Contratos Públicos)\nObjeto principal\nVocabulário Principal: 33696500\nNº: LOT-0007\nDescrição do Lote: Lote 7\nPreço base s/IVA: 245,00 EUR\nClassificação CPV (Vocabulário Comum para os Contratos Públicos)\nObjeto principal\nVocabulário Principal: 33696500\nNº: LOT-0008\nDescrição do Lote: Lote 8\nPreço base s/IVA: 1.144,00 EUR\nClassificação CPV (Vocabulário Comum para os Contratos Públicos)\nObjeto principal\nVocabulário Principal: 33696500\nNº: LOT-0009\nDescrição do Lote: Lote 9\nPreço base s/IVA: 1.346,00 EUR\nClassificação CPV (Vocabulário Comum para os Contratos Públicos)\nObjeto principal\nVocabulário Principal: 33696500\nNº: LOT-0010\nDescrição do Lote: Lote 10\nPreço base s/IVA: 282,00 EUR\nClassificação CPV (Vocabulário Comum para os Contratos Públicos)\nObjeto principal\nVocabulário Principal: 33696500\nNº: LOT-0011\nDescrição do Lote: Lote 11\nPreço base s/IVA: 248,00 EUR\nClassificação CPV (Vocabulário Comum para os Contratos Públicos)\nObjeto principal\nVocabulário Principal: 33696500\nNº: LOT-0012\nDescrição do Lote: Lote 12\nPreço base s/IVA: 186,00 EUR\nClassificação CPV (Vocabulário Comum para os Contratos Públicos)\nObjeto principal\nVocabulário Principal: 33696500\nNº: LOT-0013\nDescrição do Lote: Lote 13\nPreço base s/IVA: 690,00 EUR\nClassificação CPV (Vocabulário Comum para os Contratos Públicos)\nObjeto principal\nVocabulário Principal: 33696500\nNº: LOT-0014\nDescrição do Lote: Lote 14\nPreço base s/IVA: 312,00 EUR\nClassificação CPV (Vocabulário Comum para os Contratos Públicos)\nObjeto principal\nVocabulário Principal: 33696500\nNº: LOT-0015\nDescrição do Lote: Lote 15\nPreço base s/IVA: 649,50 EUR\nClassificação CPV (Vocabulário Comum para os Contratos Públicos)\nObjeto principal\nVocabulário Principal: 33696500\nNº: LOT-0016\nDescrição do Lote: Lote 16\nPreço base s/IVA: 316,00 EUR\nClassificação CPV (Vocabulário Comum para os Contratos Públicos)\nObjeto principal\nVocabulário Principal: 33696500\nNº: LOT-0017\nDescrição do Lote: Lote 17\nPreço base s/IVA: 352,00 EUR\nClassificação CPV (Vocabulário Comum para os Contratos Públicos)\nObjeto principal\nVocabulário Principal: 33696500\nNº: LOT-0018\nDescrição do Lote: Lote 18\nPreço base s/IVA: 300,00 EUR\nClassificação CPV (Vocabulário Comum para os Contratos Públicos)\nObjeto principal\nVocabulário Principal: 33696500\nNº: LOT-0019\nDescrição do Lote: Lote 19\nPreço base s/IVA: 518,00 EUR\nClassificação CPV (Vocabulário Comum para os Contratos Públicos)\nObjeto principal\nVocabulário Principal: 33696500\nNº: LOT-0020\nDescrição do Lote: Lote 20\nPreço base s/IVA: 530,00 EUR\nClassificação CPV (Vocabulário Comum para os Contratos Públicos)\nObjeto principal\nVocabulário Principal: 33696500\nNº: LOT-0021\nDescrição do Lote: Lote 21\nPreço base s/IVA: 683,00 EUR\nClassificação CPV (Vocabulário Comum para os Contratos Públicos)\nObjeto principal\nVocabulário Principal: 33696500\nNº: LOT-0022\nDescrição do Lote: Lote 22\nPreço base s/IVA: 302,00 EUR\nClassificação CPV (Vocabulário Comum para os Contratos Públicos)\nObjeto principal\nVocabulário Principal: 33696500\nNº: LOT-0023\nDescrição do Lote: Lote 23\nPreço base s/IVA: 370,00 EUR\nClassificação CPV (Vocabulário Comum para os Contratos Públicos)\nObjeto principal\nVocabulário Principal: 33696500\nNº: LOT-0024\nDescrição do Lote: Lote 24\nPreço base s/IVA: 388,00 EUR\nClassificação CPV (Vocabulário Comum para os Contratos Públicos)\nObjeto principal\nVocabulário Principal: 33696500\nNº: LOT-0025\nDescrição do Lote: Lote 25\nPreço base s/IVA: 457,00 EUR\nClassificação CPV (Vocabulário Comum para os Contratos Públicos)\nObjeto principal\nVocabulário Principal: 33696500\nNº: LOT-0026\nDescrição do Lote: Lote 26\nPreço base s/IVA: 618,00 EUR\nClassificação CPV (Vocabulário Comum para os Contratos Públicos)\nObjeto principal\nVocabulário Principal: 33696500\nNº: LOT-0027\nDescrição do Lote: Lote 27\nPreço base s/IVA: 370,00 EUR\nClassificação CPV (Vocabulário Comum para os Contratos Públicos)\nObjeto principal\nVocabulário Principal: 33696500\nNº: LOT-0028\nDescrição do Lote: Lote 28\nPreço base s/IVA: 344,00 EUR\nClassificação CPV (Vocabulário Comum para os Contratos Públicos)\nObjeto principal\nVocabulário Principal: 33696500\nNº: LOT-0029\nDescrição do Lote: Lote 29\nPreço base s/IVA: 284,00 EUR\nClassificação CPV (Vocabulário Comum para os Contratos Públicos)\nObjeto principal\nVocabulário Principal: 33696500\nNº: LOT-0030\nDescrição do Lote: Lote 30\nPreço base s/IVA: 395,00 EUR\nClassificação CPV (Vocabulário Comum para os Contratos Públicos)\nObjeto principal\nVocabulário Principal: 33696500\nNº: LOT-0031\nDescrição do Lote: Lote 31\nPreço base s/IVA: 1.174,00 EUR\nClassificação CPV (Vocabulário Comum para os Contratos Públicos)\nObjeto principal\nVocabulário Principal: 33696500\nNº: LOT-0032\nDescrição do Lote: Lote 32\nPreço base s/IVA: 990,00 EUR\nClassificação CPV (Vocabulário Comum para os Contratos Públicos)\nObjeto principal\nVocabulário Principal: 33696500\nNº: LOT-0033\nDescrição do Lote: Lote 33\nPreço base s/IVA: 990,00 EUR\nClassificação CPV (Vocabulário Comum para os Contratos Públicos)\nObjeto principal\nVocabulário Principal: 33696500\nNº: LOT-0034\nDescrição do Lote: Lote 34\nPreço base s/IVA: 990,00 EUR\nClassificação CPV (Vocabulário Comum para os Contratos Públicos)\nObjeto principal\nVocabulário Principal: 33696500\nNº: LOT-0035\nDescrição do Lote: Lote 35\nPreço base s/IVA: 1.893,00 EUR\nClassificação CPV (Vocabulário Comum para os Contratos Públicos)\nObjeto principal\nVocabulário Principal: 33696500\nNº: LOT-0036\nDescrição do Lote: Lote 36\nPreço base s/IVA: 520,00 EUR\nClassificação CPV (Vocabulário Comum para os Contratos Públicos)\nObjeto principal\nVocabulário Principal: 33696500\nNº: LOT-0037\nDescrição do Lote: Lote 37\nPreço base s/IVA: 802,00 EUR\nClassificação CPV (Vocabulário Comum para os Contratos Públicos)\nObjeto principal\nVocabulário Principal: 33696500\nNº: LOT-0038\nDescrição do Lote: Lote 38\nPreço base s/IVA: 1.640,00 EUR\nClassificação CPV (Vocabulário Comum para os Contratos Públicos)\nObjeto principal\nVocabulário Principal: 33696500\nNº: LOT-0039\nDescrição do Lote: Lote 39\nPreço base s/IVA: 1.790,00 EUR\nClassificação CPV (Vocabulário Comum para os Contratos Públicos)\nObjeto principal\nVocabulário Principal: 33696500\nNº: LOT-0040\nDescrição do Lote: Lote 40\nPreço base s/IVA: 1.028,00 EUR\nClassificação CPV (Vocabulário Comum para os Contratos Públicos)\nObjeto principal\nVocabulário Principal: 33696500\nNº: LOT-0041\nDescrição do Lote: Lote 41\nPreço base s/IVA: 855,00 EUR\nClassificação CPV (Vocabulário Comum para os Contratos Públicos)\nObjeto principal\nVocabulário Principal: 33696500\nNº: LOT-0042\nDescrição do Lote: Lote 42\nPreço base s/IVA: 905,00 EUR\nClassificação CPV (Vocabulário Comum para os Contratos Públicos)\nObjeto principal\nVocabulário Principal: 33696500\nNº: LOT-0043\nDescrição do Lote: Lote 43\nPreço base s/IVA: 904,00 EUR\nClassificação CPV (Vocabulário Comum para os Contratos Públicos)\nObjeto principal\nVocabulário Principal: 33696500\nNº: LOT-0044\nDescrição do Lote: Lote 44\nPreço base s/IVA: 904,00 EUR\nClassificação CPV (Vocabulário Comum para os Contratos Públicos)\nObjeto principal\nVocabulário Principal: 33696500\nNº: LOT-0045\nDescrição do Lote: Lote 45\nPreço base s/IVA: 904,00 EUR\nClassificação CPV (Vocabulário Comum para os Contratos Públicos)\nObjeto principal\nVocabulário Principal: 33696500\nNº: LOT-0046\nDescrição do Lote: Lote 46\nPreço base s/IVA: 904,00 EUR\nClassificação CPV (Vocabulário Comum para os Contratos Públicos)\nObjeto principal\nVocabulário Principal: 33696500\nNº: LOT-0047\nDescrição do Lote: Lote 47\nPreço base s/IVA: 870,00 EUR\nClassificação CPV (Vocabulário Comum para os Contratos Públicos)\nObjeto principal\nVocabulário Principal: 33696500\nNº: LOT-0048\nDescrição do Lote: Lote 48\nPreço base s/IVA: 1.995,00 EUR\nClassificação CPV (Vocabulário Comum para os Contratos Públicos)\nObjeto principal\nVocabulário Principal: 33696500\nNº: LOT-0049\nDescrição do Lote: Lote 49\nPreço base s/IVA: 762,00 EUR\nClassificação CPV (Vocabulário Comum para os Contratos Públicos)\nObjeto principal\nVocabulário Principal: 33696500\nNº: LOT-0050\nDescrição do Lote: Lote 50\nPreço base s/IVA: 920,00 EUR\nClassificação CPV (Vocabulário Comum para os Contratos Públicos)\nObjeto principal\nVocabulário Principal: 33696500\nNº: LOT-0051\nDescrição do Lote: Lote 51\nPreço base s/IVA: 995,00 EUR\nClassificação CPV (Vocabulário Comum para os Contratos Públicos)\nObjeto principal\nVocabulário Principal: 33696500\nNº: LOT-0052\nDescrição do Lote: Lote 52\nPreço base s/IVA: 1.058,00 EUR\nClassificação CPV (Vocabulário Comum para os Contratos Públicos)\nObjeto principal\nVocabulário Principal: 33696500\nNº: LOT-0053\nDescrição do Lote: Lote 53\nPreço base s/IVA: 842,00 EUR\nClassificação CPV (Vocabulário Comum para os Contratos Públicos)\nObjeto principal\nVocabulário Principal: 33696500\nNº: LOT-0054\nDescrição do Lote: Lote 54\nPreço base s/IVA: 528,00 EUR\nClassificação CPV (Vocabulário Comum para os Contratos Públicos)\nObjeto principal\nVocabulário Principal: 33696500\nNº: LOT-0055\nDescrição do Lote: Lote 55\nPreço base s/IVA: 578,00 EUR\nClassificação CPV (Vocabulário Comum para os Contratos Públicos)\nObjeto principal\nVocabulário Principal: 33696500\nNº: LOT-0056\nDescrição do Lote: Lote 56\nPreço base s/IVA: 650,00 EUR\nClassificação CPV (Vocabulário Comum para os Contratos Públicos)\nObjeto principal\nVocabulário Principal: 33696500\nNº: LOT-0057\nDescrição do Lote: Lote 57\nPreço base s/IVA: 600,00 EUR\nClassificação CPV (Vocabulário Comum para os Contratos Públicos)\nObjeto principal\nVocabulário Principal: 33696500\nNº: LOT-0058\nDescrição do Lote: Lote 58\nPreço base s/IVA: 635,00 EUR\nClassificação CPV (Vocabulário Comum para os Contratos Públicos)\nObjeto principal\nVocabulário Principal: 33696500\nNº: LOT-0059\nDescrição do Lote: Lote 59\nPreço base s/IVA: 623,00 EUR\nClassificação CPV (Vocabulário Comum para os Contratos Públicos)\nObjeto principal\nVocabulário Principal: 33696500\nNº: LOT-0060\nDescrição do Lote: Lote 60\nPreço base s/IVA: 623,00 EUR\nClassificação CPV (Vocabulário Comum para os Contratos Públicos)\nObjeto principal\nVocabulário Principal: 33696500\nNº: LOT-0061\nDescrição do Lote: Lote 61\nPreço base s/IVA: 633,00 EUR\nClassificação CPV (Vocabulário Comum para os Contratos Públicos)\nObjeto principal\nVocabulário Principal: 33696500\nNº: LOT-0062\nDescrição do Lote: Lote 62\nPreço base s/IVA: 913,50 EUR\nClassificação CPV (Vocabulário Comum para os Contratos Públicos)\nObjeto principal\nVocabulário Principal: 33696500\nNº: LOT-0063\nDescrição do Lote: Lote 63\nPreço base s/IVA: 885,15 EUR\nClassificação CPV (Vocabulário Comum para os Contratos Públicos)\nObjeto principal\nVocabulário Principal: 33696500\nNº: LOT-0064\nDescrição do Lote: Lote 64\nPreço base s/IVA: 662,00 EUR\nClassificação CPV (Vocabulário Comum para os Contratos Públicos)\nObjeto principal\nVocabulário Principal: 33696500\nNº: LOT-0065\nDescrição do Lote: Lote 65\nPreço base s/IVA: 604,00 EUR\nClassificação CPV (Vocabulário Comum para os Contratos Públicos)\nObjeto principal\nVocabulário Principal: 33696500\nNº: LOT-0066\nDescrição do Lote: Lote 66\nPreço base s/IVA: 604,00 EUR\nClassificação CPV (Vocabulário Comum para os Contratos Públicos)\nObjeto principal\nVocabulário Principal: 33696500\nNº: LOT-0067\nDescrição do Lote: Lote 67\nPreço base s/IVA: 617,00 EUR\nClassificação CPV (Vocabulário Comum para os Contratos Públicos)\nObjeto principal\nVocabulário Principal: 33696500\nNº: LOT-0068\nDescrição do Lote: Lote 68\nPreço base s/IVA: 577,50 EUR\nClassificação CPV (Vocabulário Comum para os Contratos Públicos)\nObjeto principal\nVocabulário Principal: 33696500\nNº: LOT-0069\nDescrição do Lote: Lote 69\nPreço base s/IVA: 609,00 EUR\nClassificação CPV (Vocabulário Comum para os Contratos Públicos)\nObjeto principal\nVocabulário Principal: 33696500\nNº: LOT-0070\nDescrição do Lote: Lote 70\nPreço base s/IVA: 609,00 EUR\nClassificação CPV (Vocabulário Comum para os Contratos Públicos)\nObjeto principal\nVocabulário Principal: 33696500\nNº: LOT-0071\nDescrição do Lote: Lote 71\nPreço base s/IVA: 627,90 EUR\nClassificação CPV (Vocabulário Comum para os Contratos Públicos)\nObjeto principal\nVocabulário Principal: 33696500\nNº: LOT-0072\nDescrição do Lote: Lote 72\nPreço base s/IVA: 609,00 EUR\nClassificação CPV (Vocabulário Comum para os Contratos Públicos)\nObjeto principal\nVocabulário Principal: 33696500\nNº: LOT-0073\nDescrição do Lote: Lote 73\nPreço base s/IVA: 640,50 EUR\nClassificação CPV (Vocabulário Comum para os Contratos Públicos)\nObjeto principal\nVocabulário Principal: 33696500\nNº: LOT-0074\nDescrição do Lote: Lote 74\nPreço base s/IVA: 735,00 EUR\nClassificação CPV (Vocabulário Comum para os Contratos Públicos)\nObjeto principal\nVocabulário Principal: 33696500\nNº: LOT-0075\nDescrição do Lote: Lote 75\nPreço base s/IVA: 903,00 EUR\nClassificação CPV (Vocabulário Comum para os Contratos Públicos)\nObjeto principal\nVocabulário Principal: 33696500\n7 - INDICAÇÕES ADICIONAIS\nO contrato envolve aquisição conjunta (satisfação de várias entidades)? Não\nO contrato é adjudicado por uma central de compras? Não\n8 - TÉCNICAS\nO concurso destina-se à celebração de um acordo-quadro? Inexistência de acordo-quadro\nÉ utilizado um leilão eletrónico? Não\nÉ adotada uma fase de negociação? Não\nSistema de Aquisição Dinâmico: Inexistência de sistema de aquisição dinâmico\n9 - LOCAL DA EXECUÇÃO DO CONTRATO\nLOCAL DA EXECUÇÃO DO CONTRATO (PROCEDIMENTO)\nPaís: Portugal\nNUT III: PT16E\nLocalidade: Coimbra\nDistrito: Coimbra\nConcelho: Coimbra\nFreguesia: Freguesia de Santo António dos Olivais\nLOCAL DA EXECUÇÃO DO CONTRATO (LOTE)\nIdentificador do Lote: LOT-0001; LOT-0002; LOT-0003; LOT-0004; LOT-0005; LOT-0006; LOT-0007; LOT-0008; LOT-0009; LOT-0010; LOT-0011; LOT-0012; LOT-0013; LOT-0014; LOT-0015; LOT-0016; LOT-0017; LOT-0018; LOT-0019; LOT-0020; LOT-0021; LOT-0022; LOT-0023; LOT-0024; LOT-0025; LOT-0026; LOT-0027; LOT-0028; LOT-0029; LOT-0030; LOT-0031; LOT-0032; LOT-0033; LOT-0034; LOT-0035; LOT-0036; LOT-0037; LOT-0038; LOT-0039; LOT-0040; LOT-0041; LOT-0042; LOT-0043; LOT-0044; LOT-0045; LOT-0046; LOT-0047; LOT-0048; LOT-0049; LOT-0050; LOT-0051; LOT-0052; LOT-0053; LOT-0054; LOT-0055; LOT-0056; LOT-0057; LOT-0058; LOT-0059; LOT-0060; LOT-0061; LOT-0062; LOT-0063; LOT-0064; LOT-0065; LOT-0066; LOT-0067; LOT-0068; LOT-0069; LOT-0070; LOT-0071; LOT-0072; LOT-0073; LOT-0074; LOT-0075\nPaís: Portugal\nNUT III: PT16E\nLocalidade: Coimbra\nDistrito: Coimbra\nConcelho: Coimbra\nFreguesia: Freguesia de Santo António dos Olivais\n10 - PRAZO DE EXECUÇÃO DO CONTRATO\nIdentificador do Lote: LOT-0001; LOT-0002; LOT-0003; LOT-0004; LOT-0005; LOT-0006; LOT-0007; LOT-0008; LOT-0009; LOT-0010; LOT-0011; LOT-0012; LOT-0013; LOT-0014; LOT-0015; LOT-0016; LOT-0017; LOT-0018; LOT-0019; LOT-0020; LOT-0021; LOT-0022; LOT-0023; LOT-0024; LOT-0025; LOT-0026; LOT-0027; LOT-0028; LOT-0029; LOT-0030; LOT-0031; LOT-0032; LOT-0033; LOT-0034; LOT-0035; LOT-0036; LOT-0037; LOT-0038; LOT-0039; LOT-0040; LOT-0041; LOT-0042; LOT-0043; LOT-0044; LOT-0045; LOT-0046; LOT-0047; LOT-0048; LOT-0049; LOT-0050; LOT-0051; LOT-0052; LOT-0053; LOT-0054; LOT-0055; LOT-0056; LOT-0057; LOT-0058; LOT-0059; LOT-0060; LOT-0061; LOT-0062; LOT-0063; LOT-0064; LOT-0065; LOT-0066; LOT-0067; LOT-0068; LOT-0069; LOT-0070; LOT-0071; LOT-0072; LOT-0073; LOT-0074; LOT-0075\nPrazo de execução do contrato: 11 MESES\nPrevisão de renovações: Não\n11 - FUNDOS EU\nIdentificador do Lote: LOT-0001; LOT-0002; LOT-0003; LOT-0004; LOT-0005; LOT-0006; LOT-0007; LOT-0008; LOT-0009; LOT-0010; LOT-0011; LOT-0012; LOT-0013; LOT-0014; LOT-0015; LOT-0016; LOT-0017; LOT-0018; LOT-0019; LOT-0020; LOT-0021; LOT-0022; LOT-0023; LOT-0024; LOT-0025; LOT-0026; LOT-0027; LOT-0028; LOT-0029; LOT-0030; LOT-0031; LOT-0032; LOT-0033; LOT-0034; LOT-0035; LOT-0036; LOT-0037; LOT-0038; LOT-0039; LOT-0040; LOT-0041; LOT-0042; LOT-0043; LOT-0044; LOT-0045; LOT-0046; LOT-0047; LOT-0048; LOT-0049; LOT-0050; LOT-0051; LOT-0052; LOT-0053; LOT-0054; LOT-0055; LOT-0056; LOT-0057; LOT-0058; LOT-0059; LOT-0060; LOT-0061; LOT-0062; LOT-0063; LOT-0064; LOT-0065; LOT-0066; LOT-0067; LOT-0068; LOT-0069; LOT-0070; LOT-0071; LOT-0072; LOT-0073; LOT-0074; LOT-0075\nTêm fundos EU? Não\n12 - DOCUMENTOS DE HABILITAÇÃO\nHabilitação para o exercício da atividade profissional: Sim\nTipo: Certificado\nDescrição: n/a\n13 - CONDIÇÕES DE APRESENTAÇÃO\nPlataforma eletrónica utilizada pela entidade adjudicante: VORTAL\nURL para Apresentação: https://community.vortal.biz/public/\nAdmissibilidade da apresentação de propostas variantes: Não autorizado\nPrazo para apresentação das propostas: 10-02-2026 17:00\nPrazo durante o qual os concorrentes são obrigados a manter as respetivas propostas: 180 dias a contar do termo do prazo para a apresentação das propostas\nIndicação de Subcontratação na Proposta: Inexistência de indicação de subcontratação\n14 - PRESTAÇÃO DE CAUÇÃO\nPrestação de caução: Não\n15 - FORNECIMENTO DAS PEÇAS DO CONCURSO, APRESENTAÇÃO DE PEDIDOS DE PARTICIPAÇÃO E APRESENTAÇÃO DAS PROPOSTAS\nLink para acesso às peças do concurso (URL): https://community.vortal.biz/Public/public-tender-documents/WG9KRmhNanBXeWYxNmJycFlPd1d2c3FsQjNnVU42UUlaaHViY2NvZXl3RFJrMUkwK3Jab1I0dkI5VmRHS3p5R2owTHQ5di9HMWdkYmVzbWl1NWJENWc9PVVzRXB4\n20 - OUTROS REQUISITOS\nIdentificador do Lote: LOT-0001; LOT-0002; LOT-0003; LOT-0004; LOT-0005; LOT-0006; LOT-0007; LOT-0008; LOT-0009; LOT-0010; LOT-0011; LOT-0012; LOT-0013; LOT-0014; LOT-0015; LOT-0016; LOT-0017; LOT-0018; LOT-0019; LOT-0020; LOT-0021; LOT-0022; LOT-0023; LOT-0024; LOT-0025; LOT-0026; LOT-0027; LOT-0028; LOT-0029; LOT-0030; LOT-0031; LOT-0032; LOT-0033; LOT-0034; LOT-0035; LOT-0036; LOT-0037; LOT-0038; LOT-0039; LOT-0040; LOT-0041; LOT-0042; LOT-0043; LOT-0044; LOT-0045; LOT-0046; LOT-0047; LOT-0048; LOT-0049; LOT-0050; LOT-0051; LOT-0052; LOT-0053; LOT-0054; LOT-0055; LOT-0056; LOT-0057; LOT-0058; LOT-0059; LOT-0060; LOT-0061; LOT-0062; LOT-0063; LOT-0064; LOT-0065; LOT-0066; LOT-0067; LOT-0068; LOT-0069; LOT-0070; LOT-0071; LOT-0072; LOT-0073; LOT-0074; LOT-0075\nInformação sobre contratos reservados. Aplica-se a contratos reservados (54º-A)? Não\n21 - CRITÉRIO DE ADJUDICAÇÃO\nO Critério de adjudicação é diferenciado por lote? Não\nMultifator: Sim\nFator: \nNome: Qualidade\nPonderação: 60%\nSubfatores: Não\nFator: \nNome: Preço\nPonderação: 40%\nSubfatores: Não\n24 - CONDIÇÕES DO CONTRATO\nIdentificador do Lote: LOT-0001; LOT-0002; LOT-0003; LOT-0004; LOT-0005; LOT-0006; LOT-0007; LOT-0008; LOT-0009; LOT-0010; LOT-0011; LOT-0012; LOT-0013; LOT-0014; LOT-0015; LOT-0016; LOT-0017; LOT-0018; LOT-0019; LOT-0020; LOT-0021; LOT-0022; LOT-0023; LOT-0024; LOT-0025; LOT-0026; LOT-0027; LOT-0028; LOT-0029; LOT-0030; LOT-0031; LOT-0032; LOT-0033; LOT-0034; LOT-0035; LOT-0036; LOT-0037; LOT-0038; LOT-0039; LOT-0040; LOT-0041; LOT-0042; LOT-0043; LOT-0044; LOT-0045; LOT-0046; LOT-0047; LOT-0048; LOT-0049; LOT-0050; LOT-0051; LOT-0052; LOT-0053; LOT-0054; LOT-0055; LOT-0056; LOT-0057; LOT-0058; LOT-0059; LOT-0060; LOT-0061; LOT-0062; LOT-0063; LOT-0064; LOT-0065; LOT-0066; LOT-0067; LOT-0068; LOT-0069; LOT-0070; LOT-0071; LOT-0072; LOT-0073; LOT-0074; LOT-0075\nFaturação Eletrónica: Permitido\nObrigação de Subcontratação:\nCódigo da Obrigação de Subcontratação: Não é aplicável nenhuma obrigação de subcontratação.\n25 - COMPRA PÚBLICA ESTRATÉGICA\nCompra Pública Estratégica: Inexistência de contratação pública estratégica\n26 - INFORMAÇÕES ADICIONAIS\nIdentificador do Lote: LOT-0001; LOT-0002; LOT-0003; LOT-0004; LOT-0005; LOT-0006; LOT-0007; LOT-0008; LOT-0009; LOT-0010; LOT-0011; LOT-0012; LOT-0013; LOT-0014; LOT-0015; LOT-0016; LOT-0017; LOT-0018; LOT-0019; LOT-0020; LOT-0021; LOT-0022; LOT-0023; LOT-0024; LOT-0025; LOT-0026; LOT-0027; LOT-0028; LOT-0029; LOT-0030; LOT-0031; LOT-0032; LOT-0033; LOT-0034; LOT-0035; LOT-0036; LOT-0037; LOT-0038; LOT-0039; LOT-0040; LOT-0041; LOT-0042; LOT-0043; LOT-0044; LOT-0045; LOT-0046; LOT-0047; LOT-0048; LOT-0049; LOT-0050; LOT-0051; LOT-0052; LOT-0053; LOT-0054; LOT-0055; LOT-0056; LOT-0057; LOT-0058; LOT-0059; LOT-0060; LOT-0061; LOT-0062; LOT-0063; LOT-0064; LOT-0065; LOT-0066; LOT-0067; LOT-0068; LOT-0069; LOT-0070; LOT-0071; LOT-0072; LOT-0073; LOT-0074; LOT-0075\nContrato adequado para PME: Sim\nCobertura ACP (Acordo dos Contratos Públicos da Organização Mundial do Comércio): Não\n27 - IDENTIFICAÇÃO E CONTACTOS DO ÓRGÃO DE RECURSOS ADMINISTRATIVOS\nDesignação: ULS  Coimbra EPE\nEndereço: Praceta Professor Mota Pinto\nCódigo postal: 3004-561\nLocalidade: Coimbra\nTelefone: +351 239400400\nFax: +351 23982291\nEndereço eletrónico: casec@ulscoimbra.min-saude.pt\n28 - IDENTIFICAÇÃO DO(S) AUTOR(ES) DE ANÚNCIO\nNome: Eulalia Cristina Ferreira dos Santos\nCargo: Assistente Operacional\n419949432",
    "nipc": "510103448",
    "distrito": "Coimbra",
    "concelho": "Coimbra",
    "freguesia": "Todas",
    "site": "https://www.chuc.min-saude.pt",
    "email": "ana.rosete@ulscoimbra.min-saude.pt",
    "designacao_contrato": "Controlo Externo da Qual. Analitica- Aquis. de Prog. Aval. Externa da qual. p/areas de Bioquimica",
    "descricao": "Controlo Externo da Qual. Analitica- Aquis. de Prog. Aval. Externa da qual. p/areas de Bioquimica",
    "preco_base": "58.718,87 EUR",
    "prazo_execucao": "11 MESES",
    "prazo_apresentacao_propostas": "10-02-2026 17:00",
    "fundos_eu": "Não",
    "plataforma_eletronica": "VORTAL",
    "url_procedimento": "https://community.vortal.biz/public/",
    "autor_nome": "Eulalia Cristina Ferreira dos Santos",
    "autor_cargo": "Assistente Operacional"
  },
  {
    "numero_procedimento": "N/A",
    "entidade": "AnÃºncio de procedimento  n.Âº 2108/2026  -  DiÃ¡rio da RepÃºblica n.Âº 20/2026, SÃ©rie II de 2026-01-29",
    "link": "https://diariodarepublica.pt/dr/detalhe/contrato-publico/2108-1029684176"
  },
  {
    "numero_procedimento": "N/A",
    "entidade": "INESC TEC - Instituto de Engenharia de Sistemas e Computadores, Tecnologia e Ciência",
    "link": "https://diariodarepublica.pt/dr/detalhe/contrato-publico/2109-1029684177",
    "detalhes_completos": "1 - IDENTIFICAÇÃO E CONTACTOS DA ENTIDADE ADJUDICANTE\nDesignação da entidade adjudicante: INESC TEC - Instituto de Engenharia de Sistemas e Computadores, Tecnologia e Ciência\nNIPC: 504441361\nServiço/Órgão/Pessoa de contacto: Apoio Jurídico\nEndereço: INESC TEC - Campus da FEUP Rua Dr. Roberto Frias\nCódigo postal: 4200-465\nLocalidade: Porto\nPaís: Portugal\nNUT III: PT11A\nDistrito: Porto\nConcelho: Porto\nFreguesia: Freguesia de Paranhos - Porto\nTelefone: 222094000\nFax: 222094050\nEndereço da Entidade (URL): www.inesctec.pt\nEndereço Eletrónico: apoio-juridico@inesctec.pt\neDelivery Gateway (URL): https://www.acingov.pt\nFunção da Organização: Adquirente\nNorma jurídica da Entidade Adjudicante: Organismo de direito público\nÁrea de atividade da Autoridade Adjudicante: Educação\n2 - JORNAL OFICIAL DA UNIÃO EUROPEIA\nO procedimento a que este anúncio diz respeito também é publicitado no Jornal Oficial da União Europeia? Não\n3 - AVISO\nModelo de Anúncio: Concurso público\nData de Envio do Anúncio: 29-01-2026\n5 - PROCESSO\nTipo de Procedimento: Concurso público\nPreço base do procedimento: Sim\nValor do preço base do procedimento: 195.000,00 EUR\nProcedimento com lotes? Não\n6 - OBJETO DO CONTRATO\nNúmero de referência interna: AS 0001/2026\nDesignação do contrato: Aquisição de serviços de limpeza de edifícios\nDescrição: Aquisição de serviços de limpeza de edifícios\nTipo de Contrato Principal: Aquisição de Serviços\nTipo de Contrato: Aquisição de Serviços\nClassificação CPV (Vocabulário Comum para os Contratos Públicos)\nObjeto principal\nVocabulário Principal: 90911200\nPreço base s/IVA: 195.000,00 EUR\n7 - INDICAÇÕES ADICIONAIS\nO contrato envolve aquisição conjunta (satisfação de várias entidades)? Não\nO contrato é adjudicado por uma central de compras? Não\n8 - TÉCNICAS\nO concurso destina-se à celebração de um acordo-quadro? Inexistência de acordo-quadro\nÉ utilizado um leilão eletrónico? Não\nÉ adotada uma fase de negociação? Não\nSistema de Aquisição Dinâmico: Inexistência de sistema de aquisição dinâmico\n9 - LOCAL DA EXECUÇÃO DO CONTRATO\nLOCAL DA EXECUÇÃO DO CONTRATO (PROCEDIMENTO)\nPaís: Portugal\nNUT III: PT11A\nLocalidade: Freguesia de Paranhos - Porto\nDistrito: Porto\nConcelho: Porto\nFreguesia: Freguesia de Paranhos - Porto\n10 - PRAZO DE EXECUÇÃO DO CONTRATO\nPrazo de execução do contrato: 365 DIAS\nPrevisão de renovações: Sim\nIndicar número máximo de renovações: 1\nPrazo de renovações diferente do prazo inicial: Não\n11 - FUNDOS EU\nTêm fundos EU? Não\n12 - DOCUMENTOS DE HABILITAÇÃO\nHabilitação para o exercício da atividade profissional: Não\n13 - CONDIÇÕES DE APRESENTAÇÃO\nPlataforma eletrónica utilizada pela entidade adjudicante: ACIN\nURL para Apresentação: https://www.acingov.pt\nAdmissibilidade da apresentação de propostas variantes: Não autorizado\nPrazo para apresentação das propostas: 04-02-2026 17:00\nPrazo durante o qual os concorrentes são obrigados a manter as respetivas propostas: 66 dias a contar do termo do prazo para a apresentação das propostas\nIndicação de Subcontratação na Proposta: Inexistência de indicação de subcontratação\n14 - PRESTAÇÃO DE CAUÇÃO\nPrestação de caução: Sim\nPercentagem: 3%\nDescrição da Garantia Exigida: O valor da caução é de 3.00% do preço contratual.\n15 - FORNECIMENTO DAS PEÇAS DO CONCURSO, APRESENTAÇÃO DE PEDIDOS DE PARTICIPAÇÃO E APRESENTAÇÃO DAS PROPOSTAS\nLink para acesso às peças do concurso (URL): https://www.acingov.pt/acingovprod/2/zonaPublica/zona_publica_c/donwloadProcedurePiece/MTA1MTk4MQ==\n20 - OUTROS REQUISITOS\nInformação sobre contratos reservados. Aplica-se a contratos reservados (54º-A)? Não\n21 - CRITÉRIO DE ADJUDICAÇÃO\nMultifator: Não\nMonofator:\nNome: Preço\n24 - CONDIÇÕES DO CONTRATO\nFaturação Eletrónica: Permitido\nObrigação de Subcontratação:\nCódigo da Obrigação de Subcontratação: Não é aplicável nenhuma obrigação de subcontratação.\n25 - COMPRA PÚBLICA ESTRATÉGICA\nCompra Pública Estratégica: Inexistência de contratação pública estratégica\n26 - INFORMAÇÕES ADICIONAIS\nContrato adequado para PME: Não\nCobertura ACP (Acordo dos Contratos Públicos da Organização Mundial do Comércio): Não\n27 - IDENTIFICAÇÃO E CONTACTOS DO ÓRGÃO DE RECURSOS ADMINISTRATIVOS\nDesignação: Conselho de Administração\nEndereço: INESC TEC - Campus da FEUP Rua Dr. Roberto Frias\nCódigo postal: 4200-465\nLocalidade: Porto\nTelefone: 222094000\nFax: 222094050\nEndereço eletrónico: apoio-juridico@inesctec.pt\nPrazo de interposição do recurso: 5 dias\n28 - IDENTIFICAÇÃO DO(S) AUTOR(ES) DE ANÚNCIO\nNome: Rita Ribeiro de Barros\nCargo: Responsável Apoio Jurídico\n419949331",
    "nipc": "504441361",
    "distrito": "Porto",
    "concelho": "Porto",
    "freguesia": "Freguesia de Paranhos - Porto",
    "site": "www.inesctec.pt",
    "email": "apoio-juridico@inesctec.pt",
    "designacao_contrato": "Aquisição de serviços de limpeza de edifícios",
    "descricao": "Aquisição de serviços de limpeza de edifícios",
    "preco_base": "195.000,00 EUR",
    "prazo_execucao": "365 DIAS",
    "prazo_apresentacao_propostas": "04-02-2026 17:00",
    "fundos_eu": "Não",
    "plataforma_eletronica": "ACIN",
    "url_procedimento": "https://www.acingov.pt",
    "autor_nome": "Rita Ribeiro de Barros",
    "autor_cargo": "Responsável Apoio Jurídico"
  },
  {
    "numero_procedimento": "N/A",
    "entidade": "AnÃºncio de procedimento  n.Âº 2113/2026  -  DiÃ¡rio da RepÃºblica n.Âº 20/2026, SÃ©rie II de 2026-01-29",
    "link": "https://diariodarepublica.pt/dr/detalhe/contrato-publico/2113-1029684178"
  },
  {
    "numero_procedimento": "N/A",
    "entidade": "AnÃºncio de procedimento  n.Âº 2114/2026  -  DiÃ¡rio da RepÃºblica n.Âº 20/2026, SÃ©rie II de 2026-01-29",
    "link": "https://diariodarepublica.pt/dr/detalhe/contrato-publico/2114-1029684179"
  },
  {
    "numero_procedimento": "N/A",
    "entidade": "AnÃºncio de procedimento  n.Âº 2116/2026  -  DiÃ¡rio da RepÃºblica n.Âº 20/2026, SÃ©rie II de 2026-01-29",
    "link": "https://diariodarepublica.pt/dr/detalhe/contrato-publico/2116-1029684186"
  },
  {
    "numero_procedimento": "N/A",
    "entidade": "AnÃºncio de procedimento  n.Âº 2117/2026  -  DiÃ¡rio da RepÃºblica n.Âº 20/2026, SÃ©rie II de 2026-01-29",
    "link": "https://diariodarepublica.pt/dr/detalhe/contrato-publico/2117-1029684187"
  },
  {
    "numero_procedimento": "N/A",
    "entidade": "Unidade Local de Saúde da Lezíria, EPE",
    "link": "https://diariodarepublica.pt/dr/detalhe/contrato-publico/2119-1029684188",
    "detalhes_completos": "1 - IDENTIFICAÇÃO E CONTACTOS DA ENTIDADE ADJUDICANTE\nDesignação da entidade adjudicante: Unidade Local de Saúde da Lezíria, EPE\nNIPC: 506361462\nEndereço: Av. Bernardo Santareno S/N\nCódigo postal: 2005-177\nLocalidade: Santarém\nPaís: Portugal\nNUT III: PT185\nDistrito: Santarém\nConcelho: Santarém\nFreguesia: União de Freguesias da Cidade de Santarém\nTelefone: 243300200\nFax: 243370220\nEndereço da Entidade (URL): www.hds.min-saude.pt\nEndereço Eletrónico: hdsca@hds.min-saude.pt\neDelivery Gateway (URL): https://community.vortal.biz/public/\nFunção da Organização: Adquirente\nNorma jurídica da Entidade Adjudicante: Organismo de direito público\nÁrea de atividade da Autoridade Adjudicante: Saúde\n2 - JORNAL OFICIAL DA UNIÃO EUROPEIA\nO procedimento a que este anúncio diz respeito também é publicitado no Jornal Oficial da União Europeia? Não\n3 - AVISO\nModelo de Anúncio: Concurso público\nData de Envio do Anúncio: 29-01-2026\n5 - PROCESSO\nTipo de Procedimento: Concurso público\nPreço base do procedimento: Sim\nValor do preço base do procedimento: 199.600,41 EUR\nProcedimento com lotes? Sim\nNº Máx. de Lotes Autorizado: 19\nNúmero máximo de lotes que podem ser adjudicados a um concorrente: 19\n6 - OBJETO DO CONTRATO\nNúmero de referência interna: 1110002/2026\nDesignação do contrato: Aquisição de Antisséticos e Desinfetantes (2026-2028)\nDescrição: Aquisição de Antisséticos e Desinfetantes (2026-2028)\nTipo de Contrato Principal: Aquisição de Bens Móveis\nTipo de Contrato: Aquisição de Bens Móveis\nClassificação CPV (Vocabulário Comum para os Contratos Públicos)\nObjeto principal\nVocabulário Principal: 33600000\nPreço base s/IVA: 199.600,41 EUR\nLotes: \nNº: LOT-0001\nDescrição do Lote: Lote 1\nPreço base s/IVA: 43,20 EUR\nClassificação CPV (Vocabulário Comum para os Contratos Públicos)\nObjeto principal\nVocabulário Principal: 33600000\nNº: LOT-0002\nDescrição do Lote: Lote 2\nPreço base s/IVA: 162,00 EUR\nClassificação CPV (Vocabulário Comum para os Contratos Públicos)\nObjeto principal\nVocabulário Principal: 33600000\nNº: LOT-0003\nDescrição do Lote: Lote 3\nPreço base s/IVA: 2.848,32 EUR\nClassificação CPV (Vocabulário Comum para os Contratos Públicos)\nObjeto principal\nVocabulário Principal: 33600000\nNº: LOT-0004\nDescrição do Lote: Lote 4\nPreço base s/IVA: 864,00 EUR\nClassificação CPV (Vocabulário Comum para os Contratos Públicos)\nObjeto principal\nVocabulário Principal: 33600000\nNº: LOT-0005\nDescrição do Lote: Lote 5\nPreço base s/IVA: 32.797,44 EUR\nClassificação CPV (Vocabulário Comum para os Contratos Públicos)\nObjeto principal\nVocabulário Principal: 33600000\nNº: LOT-0006\nDescrição do Lote: Lote 6\nPreço base s/IVA: 5.475,00 EUR\nClassificação CPV (Vocabulário Comum para os Contratos Públicos)\nObjeto principal\nVocabulário Principal: 33600000\nNº: LOT-0007\nDescrição do Lote: Lote 7\nPreço base s/IVA: 8.136,00 EUR\nClassificação CPV (Vocabulário Comum para os Contratos Públicos)\nObjeto principal\nVocabulário Principal: 33600000\nNº: LOT-0008\nDescrição do Lote: Lote 8\nPreço base s/IVA: 15.527,70 EUR\nClassificação CPV (Vocabulário Comum para os Contratos Públicos)\nObjeto principal\nVocabulário Principal: 33600000\nNº: LOT-0009\nDescrição do Lote: Lote 9\nPreço base s/IVA: 28.576,80 EUR\nClassificação CPV (Vocabulário Comum para os Contratos Públicos)\nObjeto principal\nVocabulário Principal: 33600000\nNº: LOT-0010\nDescrição do Lote: Lote 10\nPreço base s/IVA: 9.073,35 EUR\nClassificação CPV (Vocabulário Comum para os Contratos Públicos)\nObjeto principal\nVocabulário Principal: 33600000\nNº: LOT-0011\nDescrição do Lote: Lote 11\nPreço base s/IVA: 5.970,00 EUR\nClassificação CPV (Vocabulário Comum para os Contratos Públicos)\nObjeto principal\nVocabulário Principal: 33600000\nNº: LOT-0012\nDescrição do Lote: Lote 12\nPreço base s/IVA: 1.536,00 EUR\nClassificação CPV (Vocabulário Comum para os Contratos Públicos)\nObjeto principal\nVocabulário Principal: 33600000\nNº: LOT-0013\nDescrição do Lote: Lote 13\nPreço base s/IVA: 16.161,60 EUR\nClassificação CPV (Vocabulário Comum para os Contratos Públicos)\nObjeto principal\nVocabulário Principal: 33600000\nNº: LOT-0014\nDescrição do Lote: Lote 14\nPreço base s/IVA: 9.954,00 EUR\nClassificação CPV (Vocabulário Comum para os Contratos Públicos)\nObjeto principal\nVocabulário Principal: 33600000\nNº: LOT-0015\nDescrição do Lote: Lote 15\nPreço base s/IVA: 2.160,00 EUR\nClassificação CPV (Vocabulário Comum para os Contratos Públicos)\nObjeto principal\nVocabulário Principal: 33600000\nNº: LOT-0016\nDescrição do Lote: Lote 16\nPreço base s/IVA: 25.020,00 EUR\nClassificação CPV (Vocabulário Comum para os Contratos Públicos)\nObjeto principal\nVocabulário Principal: 33600000\nNº: LOT-0017\nDescrição do Lote: Lote 17\nPreço base s/IVA: 14.580,00 EUR\nClassificação CPV (Vocabulário Comum para os Contratos Públicos)\nObjeto principal\nVocabulário Principal: 33600000\nNº: LOT-0018\nDescrição do Lote: Lote 18\nPreço base s/IVA: 13.104,00 EUR\nClassificação CPV (Vocabulário Comum para os Contratos Públicos)\nObjeto principal\nVocabulário Principal: 33600000\nNº: LOT-0019\nDescrição do Lote: Lote 19\nPreço base s/IVA: 7.611,00 EUR\nClassificação CPV (Vocabulário Comum para os Contratos Públicos)\nObjeto principal\nVocabulário Principal: 33600000\n7 - INDICAÇÕES ADICIONAIS\nO contrato envolve aquisição conjunta (satisfação de várias entidades)? Não\nO contrato é adjudicado por uma central de compras? Não\n8 - TÉCNICAS\nO concurso destina-se à celebração de um acordo-quadro? Inexistência de acordo-quadro\nÉ utilizado um leilão eletrónico? Não\nÉ adotada uma fase de negociação? Não\nSistema de Aquisição Dinâmico: Inexistência de sistema de aquisição dinâmico\n9 - LOCAL DA EXECUÇÃO DO CONTRATO\nLOCAL DA EXECUÇÃO DO CONTRATO (PROCEDIMENTO)\nPaís: Portugal\nNUT III: PTZZZ\nLocalidade: PORTUGAL\nDistrito: Todos\nConcelho: Todos\nFreguesia: Todas\nLOCAL DA EXECUÇÃO DO CONTRATO (LOTE)\nIdentificador do Lote: LOT-0001; LOT-0002; LOT-0003; LOT-0004; LOT-0005; LOT-0006; LOT-0007; LOT-0008; LOT-0009; LOT-0010; LOT-0011; LOT-0012; LOT-0013; LOT-0014; LOT-0015; LOT-0016; LOT-0017; LOT-0018; LOT-0019\nPaís: Portugal\nNUT III: PTZZZ\nLocalidade: PORTUGAL\nDistrito: Todos\nConcelho: Todos\nFreguesia: Todas\n10 - PRAZO DE EXECUÇÃO DO CONTRATO\nIdentificador do Lote: LOT-0001; LOT-0002; LOT-0003; LOT-0004; LOT-0005; LOT-0006; LOT-0007; LOT-0008; LOT-0009; LOT-0010; LOT-0011; LOT-0012; LOT-0013; LOT-0014; LOT-0015; LOT-0016; LOT-0017; LOT-0018; LOT-0019\nPrazo de execução do contrato: 36 MESES\nPrevisão de renovações: Não\n11 - FUNDOS EU\nIdentificador do Lote: LOT-0001; LOT-0002; LOT-0003; LOT-0004; LOT-0005; LOT-0006; LOT-0007; LOT-0008; LOT-0009; LOT-0010; LOT-0011; LOT-0012; LOT-0013; LOT-0014; LOT-0015; LOT-0016; LOT-0017; LOT-0018; LOT-0019\nTêm fundos EU? Não\n12 - DOCUMENTOS DE HABILITAÇÃO\nHabilitação para o exercício da atividade profissional: Não\n13 - CONDIÇÕES DE APRESENTAÇÃO\nPlataforma eletrónica utilizada pela entidade adjudicante: VORTAL\nURL para Apresentação: https://community.vortal.biz/public/\nAdmissibilidade da apresentação de propostas variantes: Não autorizado\nPrazo para apresentação das propostas: 04-02-2026 23:59\nPrazo durante o qual os concorrentes são obrigados a manter as respetivas propostas: 66 dias a contar do termo do prazo para a apresentação das propostas\nIndicação de Subcontratação na Proposta: Inexistência de indicação de subcontratação\n14 - PRESTAÇÃO DE CAUÇÃO\nPrestação de caução: Não\n15 - FORNECIMENTO DAS PEÇAS DO CONCURSO, APRESENTAÇÃO DE PEDIDOS DE PARTICIPAÇÃO E APRESENTAÇÃO DAS PROPOSTAS\nLink para acesso às peças do concurso (URL): https://community.vortal.biz/Public/public-tender-documents/cTZDTUQzdmtLKzRnb0FCOUcyOTlXNS9pWkFwdnRYNXVDWG1GTlZOKzRjN0JyUzZNbG44UjZKb29ZbmZhOEg0NC9HQ3VZTFJxWnR1OExZcDBQK0pKZFE9PTdeekcm\n20 - OUTROS REQUISITOS\nIdentificador do Lote: LOT-0001; LOT-0002; LOT-0003; LOT-0004; LOT-0005; LOT-0006; LOT-0007; LOT-0008; LOT-0009; LOT-0010; LOT-0011; LOT-0012; LOT-0013; LOT-0014; LOT-0015; LOT-0016; LOT-0017; LOT-0018; LOT-0019\nInformação sobre contratos reservados. Aplica-se a contratos reservados (54º-A)? Não\n21 - CRITÉRIO DE ADJUDICAÇÃO\nO Critério de adjudicação é diferenciado por lote? Não\nMultifator: Não\nMonofator:\nNome: Preço\n24 - CONDIÇÕES DO CONTRATO\nIdentificador do Lote: LOT-0001; LOT-0002; LOT-0003; LOT-0004; LOT-0005; LOT-0006; LOT-0007; LOT-0008; LOT-0009; LOT-0010; LOT-0011; LOT-0012; LOT-0013; LOT-0014; LOT-0015; LOT-0016; LOT-0017; LOT-0018; LOT-0019\nFaturação Eletrónica: Permitido\nObrigação de Subcontratação:\nCódigo da Obrigação de Subcontratação: Não é aplicável nenhuma obrigação de subcontratação.\n25 - COMPRA PÚBLICA ESTRATÉGICA\nCompra Pública Estratégica: Inexistência de contratação pública estratégica\n26 - INFORMAÇÕES ADICIONAIS\nIdentificador do Lote: LOT-0001; LOT-0002; LOT-0003; LOT-0004; LOT-0005; LOT-0006; LOT-0007; LOT-0008; LOT-0009; LOT-0010; LOT-0011; LOT-0012; LOT-0013; LOT-0014; LOT-0015; LOT-0016; LOT-0017; LOT-0018; LOT-0019\nContrato adequado para PME: Sim\nCobertura ACP (Acordo dos Contratos Públicos da Organização Mundial do Comércio): Não\n27 - IDENTIFICAÇÃO E CONTACTOS DO ÓRGÃO DE RECURSOS ADMINISTRATIVOS\nDesignação: Conselho de Administração da ULSLezíria, EPE\nEndereço: Avenida Bernardo santareno S/N\nCódigo postal: 2005-177\nLocalidade: Santarém\nTelefone: +351 243300200\nFax: +351 243370220\nEndereço eletrónico: ca@ulsleziria.min-saude.pt\n28 - IDENTIFICAÇÃO DO(S) AUTOR(ES) DE ANÚNCIO\nNome: Pedro Manuel Dias de Figueiredo Pereira Marques\nCargo: Presidente do Conselho de Administração\n419949422",
    "nipc": "506361462",
    "distrito": "Santarém",
    "concelho": "Santarém",
    "freguesia": "União de Freguesias da Cidade de Santarém",
    "site": "www.hds.min-saude.pt",
    "email": "hdsca@hds.min-saude.pt",
    "designacao_contrato": "Aquisição de Antisséticos e Desinfetantes (2026-2028)",
    "descricao": "Aquisição de Antisséticos e Desinfetantes (2026-2028)",
    "preco_base": "199.600,41 EUR",
    "prazo_execucao": "36 MESES",
    "prazo_apresentacao_propostas": "04-02-2026 23:59",
    "fundos_eu": "Não",
    "plataforma_eletronica": "VORTAL",
    "url_procedimento": "https://community.vortal.biz/public/",
    "autor_nome": "Pedro Manuel Dias de Figueiredo Pereira Marques",
    "autor_cargo": "Presidente do Conselho de Administração"
  },
  {
    "numero_procedimento": "N/A",
    "entidade": "Município de Alcochete",
    "link": "https://diariodarepublica.pt/dr/detalhe/contrato-publico/2120-1029684191",
    "detalhes_completos": "1 - IDENTIFICAÇÃO E CONTACTOS DA ENTIDADE ADJUDICANTE\nDesignação da entidade adjudicante: Município de Alcochete\nNIPC: 506788490\nEndereço: Largo São João. Edifício Paços Concelho\nCódigo postal: 2894-001\nLocalidade: Setúbal\nPaís: Portugal\nNUT III: PT170\nDistrito: Setúbal\nConcelho: Alcochete\nFreguesia: Freguesia de Alcochete\nTelefone: 212348600\nFax: 212348690\nEndereço da Entidade (URL): www.cm-alcochete.pt\nEndereço Eletrónico: geral@cm-alcochete.pt\neDelivery Gateway (URL): https://community.vortal.biz/public/\nFunção da Organização: Adquirente\nNorma jurídica da Entidade Adjudicante: Autoridade local\nÁrea de atividade da Autoridade Adjudicante: Serviços públicos das administrações públicas\n2 - JORNAL OFICIAL DA UNIÃO EUROPEIA\nO procedimento a que este anúncio diz respeito também é publicitado no Jornal Oficial da União Europeia? Não\n3 - AVISO\nModelo de Anúncio: Concurso público\nData de Envio do Anúncio: 29-01-2026\n5 - PROCESSO\nTipo de Procedimento: Concurso público\nPreço base do procedimento: Sim\nValor do preço base do procedimento: 180.000,00 EUR\nProcedimento com lotes? Não\n6 - OBJETO DO CONTRATO\nNúmero de referência interna: Processo Nº. 01/26/CP\nDesignação do contrato: Concessão de uso privativo de área dominial para fins de exploração de estabelecimento de restauração/bar, com esplanada, na Frente Rib.de Alcochete–Avenida D. Manuel I (Largo Barão de Samora Correia)\nDescrição: Concessão de uso privativo de área dominial para fins de exploração de estabelecimento de restauração/bar, com esplanada, na Frente Ribeirinha de Alcochete – Avenida D. Manuel I (Largo Barão de Samora Correia)\nTipo de Contrato Principal: Concessão de Serviços Públicos\nTipo de Contrato: Concessão de Serviços Públicos\nClassificação CPV (Vocabulário Comum para os Contratos Públicos)\nObjeto principal\nVocabulário Principal: 55300000\nPreço base s/IVA: 180.000,00 EUR\n7 - INDICAÇÕES ADICIONAIS\nO contrato envolve aquisição conjunta (satisfação de várias entidades)? Não\nO contrato é adjudicado por uma central de compras? Não\n8 - TÉCNICAS\nO concurso destina-se à celebração de um acordo-quadro? Inexistência de acordo-quadro\nÉ utilizado um leilão eletrónico? Não\nÉ adotada uma fase de negociação? Não\nSistema de Aquisição Dinâmico: Inexistência de sistema de aquisição dinâmico\n9 - LOCAL DA EXECUÇÃO DO CONTRATO\nLOCAL DA EXECUÇÃO DO CONTRATO (PROCEDIMENTO)\nPaís: Portugal\nNUT III: PT170\nLocalidade: Setúbal\nDistrito: Setúbal\nConcelho: Alcochete\nFreguesia: Freguesia de Alcochete\n10 - PRAZO DE EXECUÇÃO DO CONTRATO\nPrazo de execução do contrato: 6 ANOS\nPrevisão de renovações: Não\n11 - FUNDOS EU\nTêm fundos EU? Não\n12 - DOCUMENTOS DE HABILITAÇÃO\nHabilitação para o exercício da atividade profissional: Não\n13 - CONDIÇÕES DE APRESENTAÇÃO\nPlataforma eletrónica utilizada pela entidade adjudicante: VORTAL\nURL para Apresentação: https://community.vortal.biz/public/\nAdmissibilidade da apresentação de propostas variantes: Não autorizado\nPrazo para apresentação das propostas: 02-03-2026 23:59\nPrazo durante o qual os concorrentes são obrigados a manter as respetivas propostas: 90 dias a contar do termo do prazo para a apresentação das propostas\nIndicação de Subcontratação na Proposta: Inexistência de indicação de subcontratação\n14 - PRESTAÇÃO DE CAUÇÃO\nPrestação de caução: Sim\nPercentagem: 2%\nDescrição da Garantia Exigida: Conforme programa de concurso\n15 - FORNECIMENTO DAS PEÇAS DO CONCURSO, APRESENTAÇÃO DE PEDIDOS DE PARTICIPAÇÃO E APRESENTAÇÃO DAS PROPOSTAS\nLink para acesso às peças do concurso (URL): https://community.vortal.biz/Public/public-tender-documents/TUdoUDFiaWtFZ01tVHRoZzdnbkxrUWtnVCtvMG1Tem85cTZ3YW9CMGdDQXUySmZ6ZERmN2hyQzZ6R20rMzRWQXREWDVuL3R4dEQ2ZUVHMDBKWU1aaFE9PUh0X0RV\n20 - OUTROS REQUISITOS\nInformação sobre contratos reservados. Aplica-se a contratos reservados (54º-A)? Não\n21 - CRITÉRIO DE ADJUDICAÇÃO\nMultifator: Não\nMonofator:\nNome: Preço\n24 - CONDIÇÕES DO CONTRATO\nFaturação Eletrónica: Permitido\nObrigação de Subcontratação:\nCódigo da Obrigação de Subcontratação: Não é aplicável nenhuma obrigação de subcontratação.\n25 - COMPRA PÚBLICA ESTRATÉGICA\nCompra Pública Estratégica: Inexistência de contratação pública estratégica\n26 - INFORMAÇÕES ADICIONAIS\nContrato adequado para PME: Sim\nCobertura ACP (Acordo dos Contratos Públicos da Organização Mundial do Comércio): Não\n27 - IDENTIFICAÇÃO E CONTACTOS DO ÓRGÃO DE RECURSOS ADMINISTRATIVOS\nDesignação: Fernando Manuel Gonçalves Pina Pinto\nEndereço: Largo S. João\nCódigo postal: 2894-001\nLocalidade: Alcochete\nTelefone: +351 212348600\nFax: +351 212348691\nEndereço eletrónico: gp@cm-alcochete.pt\n28 - IDENTIFICAÇÃO DO(S) AUTOR(ES) DE ANÚNCIO\nNome: Fernando Manuel Gonçalves Pina Pinto\nCargo: Presidente da Câmara\n419949455",
    "nipc": "506788490",
    "distrito": "Setúbal",
    "concelho": "Alcochete",
    "freguesia": "Freguesia de Alcochete",
    "site": "www.cm-alcochete.pt",
    "email": "geral@cm-alcochete.pt",
    "designacao_contrato": "Concessão de uso privativo de área dominial para fins de exploração de estabelecimento de restauração/bar, com esplanada, na Frente Rib.de Alcochete–Avenida D. Manuel I (Largo Barão de Samora Correia)",
    "descricao": "Concessão de uso privativo de área dominial para fins de exploração de estabelecimento de restauração/bar, com esplanada, na Frente Ribeirinha de Alcochete – Avenida D. Manuel I (Largo Barão de Samora Correia)",
    "preco_base": "180.000,00 EUR",
    "prazo_execucao": "6 ANOS",
    "prazo_apresentacao_propostas": "02-03-2026 23:59",
    "fundos_eu": "Não",
    "plataforma_eletronica": "VORTAL",
    "url_procedimento": "https://community.vortal.biz/public/",
    "autor_nome": "Fernando Manuel Gonçalves Pina Pinto",
    "autor_cargo": "Presidente da Câmara"
  },
  {
    "numero_procedimento": "N/A",
    "entidade": "AnÃºncio de procedimento  n.Âº 2123/2026  -  DiÃ¡rio da RepÃºblica n.Âº 20/2026, SÃ©rie II de 2026-01-29",
    "link": "https://diariodarepublica.pt/dr/detalhe/contrato-publico/2123-1029684205"
  },
  {
    "numero_procedimento": "N/A",
    "entidade": "Instituto Politécnico do Cávado e do Ave",
    "link": "https://diariodarepublica.pt/dr/detalhe/contrato-publico/2124-1029684206",
    "detalhes_completos": "1 - IDENTIFICAÇÃO E CONTACTOS DA ENTIDADE ADJUDICANTE\nDesignação da entidade adjudicante: Instituto Politécnico do Cávado e do Ave\nNIPC: 503494933\nServiço/Órgão/Pessoa de contacto: Divisão de Contratação Pública\nEndereço: Campus do IPCA - Vila Frescainha S. Martinho\nCódigo postal: 4750-810\nLocalidade: Barcelos\nPaís: Portugal\nNUT III: PT112\nDistrito: Braga\nConcelho: Barcelos\nFreguesia: União das Freguesias de Barcelos, Vila Boa e Vila Frescainha (São Martinho e São Pedro)\nTelefone: 253802190\nFax: 253802190\nEndereço da Entidade (URL): www.ipca.pt\nEndereço Eletrónico: geral@ipca.pt\neDelivery Gateway (URL): https://www.acingov.pt\nFunção da Organização: Adquirente\nNorma jurídica da Entidade Adjudicante: Organismo de direito público\nÁrea de atividade da Autoridade Adjudicante: Educação\n2 - JORNAL OFICIAL DA UNIÃO EUROPEIA\nO procedimento a que este anúncio diz respeito também é publicitado no Jornal Oficial da União Europeia? Não\n3 - AVISO\nModelo de Anúncio: Concurso público\nData de Envio do Anúncio: 29-01-2026\n5 - PROCESSO\nTipo de Procedimento: Concurso público\nPreço base do procedimento: Sim\nValor do preço base do procedimento: 155.610,00 EUR\nProcedimento com lotes? Não\n6 - OBJETO DO CONTRATO\nNúmero de referência interna: CP-001/2026\nDesignação do contrato: Aquisição de uma concessão de exploração do espaço de lavandaria self-service da residência de alojamento estudantil B-CRIC\nDescrição: Aquisição de uma concessão de exploração do espaço de lavandaria self-service da residência de alojamento estudantil B-CRIC\nTipo de Contrato Principal: Concessão de Serviços Públicos\nTipo de Contrato: Concessão de Serviços Públicos\nClassificação CPV (Vocabulário Comum para os Contratos Públicos)\nObjeto principal\nVocabulário Principal: 98311200\nPreço base s/IVA: 155.610,00 EUR\n7 - INDICAÇÕES ADICIONAIS\nO contrato envolve aquisição conjunta (satisfação de várias entidades)? Não\nO contrato é adjudicado por uma central de compras? Não\n8 - TÉCNICAS\nO concurso destina-se à celebração de um acordo-quadro? Inexistência de acordo-quadro\nÉ utilizado um leilão eletrónico? Não\nÉ adotada uma fase de negociação? Não\nSistema de Aquisição Dinâmico: Inexistência de sistema de aquisição dinâmico\n9 - LOCAL DA EXECUÇÃO DO CONTRATO\nLOCAL DA EXECUÇÃO DO CONTRATO (PROCEDIMENTO)\nPaís: Portugal\nNUT III: PT112\nLocalidade: União das Freguesias de Barcelos, Vila Boa e Vila Frescainha (São Martinho e São Pedro)\nDistrito: Braga\nConcelho: Barcelos\nFreguesia: União das Freguesias de Barcelos, Vila Boa e Vila Frescainha (São Martinho e São Pedro)\n10 - PRAZO DE EXECUÇÃO DO CONTRATO\nPrazo de execução do contrato: 3 ANOS\nPrevisão de renovações: Não\n11 - FUNDOS EU\nTêm fundos EU? Sim\n12 - DOCUMENTOS DE HABILITAÇÃO\nHabilitação para o exercício da atividade profissional: Não\n13 - CONDIÇÕES DE APRESENTAÇÃO\nPlataforma eletrónica utilizada pela entidade adjudicante: ACIN\nURL para Apresentação: https://www.acingov.pt\nAdmissibilidade da apresentação de propostas variantes: Não autorizado\nPrazo para apresentação das propostas: 05-02-2026 23:59\nPrazo durante o qual os concorrentes são obrigados a manter as respetivas propostas: 120 dias a contar do termo do prazo para a apresentação das propostas\nIndicação de Subcontratação na Proposta: Inexistência de indicação de subcontratação\n14 - PRESTAÇÃO DE CAUÇÃO\nPrestação de caução: Não\n15 - FORNECIMENTO DAS PEÇAS DO CONCURSO, APRESENTAÇÃO DE PEDIDOS DE PARTICIPAÇÃO E APRESENTAÇÃO DAS PROPOSTAS\nLink para acesso às peças do concurso (URL): https://www.acingov.pt/acingovprod/2/zonaPublica/zona_publica_c/donwloadProcedurePiece/MTA1MjM1Mg==\n20 - OUTROS REQUISITOS\nInformação sobre contratos reservados. Aplica-se a contratos reservados (54º-A)? Não\n21 - CRITÉRIO DE ADJUDICAÇÃO\nMultifator: Não\nMonofator:\nNome: Preço\n24 - CONDIÇÕES DO CONTRATO\nFaturação Eletrónica: Permitido\nObrigação de Subcontratação:\nCódigo da Obrigação de Subcontratação: Não é aplicável nenhuma obrigação de subcontratação.\n25 - COMPRA PÚBLICA ESTRATÉGICA\nCompra Pública Estratégica: Inexistência de contratação pública estratégica\n26 - INFORMAÇÕES ADICIONAIS\nContrato adequado para PME: Sim\nCobertura ACP (Acordo dos Contratos Públicos da Organização Mundial do Comércio): Não\n27 - IDENTIFICAÇÃO E CONTACTOS DO ÓRGÃO DE RECURSOS ADMINISTRATIVOS\nDesignação: Presidente do Instituto Politécnico do Cávado e do Ave\nEndereço: Serviços Centrais - Campus do IPCA - Vila Frescainha S. Martinho\nCódigo postal: 4750-850\nLocalidade: Barcelos\nTelefone: 253802190\nFax: 253802190\nEndereço eletrónico: geral@ipca.pt\n28 - IDENTIFICAÇÃO DO(S) AUTOR(ES) DE ANÚNCIO\nNome: Alice Carvalho\nCargo: Assistente Técnica\n419949459",
    "nipc": "503494933",
    "distrito": "Braga",
    "concelho": "Barcelos",
    "freguesia": "União das Freguesias de Barcelos, Vila Boa e Vila Frescainha (São Martinho e São Pedro)",
    "site": "www.ipca.pt",
    "email": "geral@ipca.pt",
    "designacao_contrato": "Aquisição de uma concessão de exploração do espaço de lavandaria self-service da residência de alojamento estudantil B-CRIC",
    "descricao": "Aquisição de uma concessão de exploração do espaço de lavandaria self-service da residência de alojamento estudantil B-CRIC",
    "preco_base": "155.610,00 EUR",
    "prazo_execucao": "3 ANOS",
    "prazo_apresentacao_propostas": "05-02-2026 23:59",
    "fundos_eu": "Sim",
    "plataforma_eletronica": "ACIN",
    "url_procedimento": "https://www.acingov.pt",
    "autor_nome": "Alice Carvalho",
    "autor_cargo": "Assistente Técnica"
  },
  {
    "numero_procedimento": "N/A",
    "entidade": "AnÃºncio de procedimento  n.Âº 2125/2026  -  DiÃ¡rio da RepÃºblica n.Âº 20/2026, SÃ©rie II de 2026-01-29",
    "link": "https://diariodarepublica.pt/dr/detalhe/contrato-publico/2125-1029684207"
  },
  {
    "numero_procedimento": "N/A",
    "entidade": "AnÃºncio de procedimento  n.Âº 2126/2026  -  DiÃ¡rio da RepÃºblica n.Âº 20/2026, SÃ©rie II de 2026-01-29",
    "link": "https://diariodarepublica.pt/dr/detalhe/contrato-publico/2126-1029684208"
  },
  {
    "numero_procedimento": "N/A",
    "entidade": "Instituto do Emprego e da Formação Profissional, IP",
    "link": "https://diariodarepublica.pt/dr/detalhe/contrato-publico/2128-1029684209",
    "detalhes_completos": "1 - IDENTIFICAÇÃO E CONTACTOS DA ENTIDADE ADJUDICANTE\nDesignação da entidade adjudicante: Instituto do Emprego e da Formação Profissional, IP\nNIPC: 501442600\nEndereço: Rua de Xabregas, n.º52\nCódigo postal: 1949-003\nLocalidade: Lisboa\nPaís: Portugal\nNUT III: PT170\nDistrito: Lisboa\nConcelho: Lisboa\nFreguesia: Freguesia de Beato\nTelefone: 215803000\nFax: 215803617\nEndereço da Entidade (URL): www.iefp.pt\nEndereço Eletrónico: pg-af@iefp.pt\neDelivery Gateway (URL): https://www.acingov.pt\nFunção da Organização: Adquirente\nNorma jurídica da Entidade Adjudicante: Organismo de direito público\nÁrea de atividade da Autoridade Adjudicante: Serviços públicos das administrações públicas\n2 - JORNAL OFICIAL DA UNIÃO EUROPEIA\nO procedimento a que este anúncio diz respeito também é publicitado no Jornal Oficial da União Europeia? Não\n3 - AVISO\nModelo de Anúncio: Concurso público\nData de Envio do Anúncio: 29-01-2026\n5 - PROCESSO\nTipo de Procedimento: Concurso público\nPreço base do procedimento: Sim\nValor do preço base do procedimento: 3.000,00 EUR\nProcedimento com lotes? Não\n6 - OBJETO DO CONTRATO\nNúmero de referência interna: PR2025762/410\nDesignação do contrato: Concessão de exploração da Cafetaria do CEFP de Portimão e colocação de Equipamentos de venda automática na instalações do CEFP do Barlavento\nDescrição: Concessão de exploração da Cafetaria do CEFP de Portimão e colocação de Equipamentos de venda automática na instalações do CEFP do Barlavento\nTipo de Contrato Principal: Concessão de Serviços Públicos\nTipo de Contrato: Concessão de Serviços Públicos\nClassificação CPV (Vocabulário Comum para os Contratos Públicos)\nObjeto principal\nVocabulário Principal: 55330000\nPreço base s/IVA: 3.000,00 EUR\n7 - INDICAÇÕES ADICIONAIS\nO contrato envolve aquisição conjunta (satisfação de várias entidades)? Não\nO contrato é adjudicado por uma central de compras? Não\n8 - TÉCNICAS\nO concurso destina-se à celebração de um acordo-quadro? Inexistência de acordo-quadro\nÉ utilizado um leilão eletrónico? Não\nÉ adotada uma fase de negociação? Não\nSistema de Aquisição Dinâmico: Inexistência de sistema de aquisição dinâmico\n9 - LOCAL DA EXECUÇÃO DO CONTRATO\nLOCAL DA EXECUÇÃO DO CONTRATO (PROCEDIMENTO)\nPaís: Portugal\nNUT III: PT150\nLocalidade: Portimão\nDistrito: Faro\nConcelho: Portimão\nFreguesia: Freguesia de Portimão\n10 - PRAZO DE EXECUÇÃO DO CONTRATO\nPrazo de execução do contrato: 12 MESES\nPrevisão de renovações: Sim\nIndicar número máximo de renovações: 3\nPrazo de renovações diferente do prazo inicial: Não\n11 - FUNDOS EU\nTêm fundos EU? Não\n12 - DOCUMENTOS DE HABILITAÇÃO\nHabilitação para o exercício da atividade profissional: Não\n13 - CONDIÇÕES DE APRESENTAÇÃO\nPlataforma eletrónica utilizada pela entidade adjudicante: ACIN\nURL para Apresentação: https://www.acingov.pt\nAdmissibilidade da apresentação de propostas variantes: Não autorizado\nPrazo para apresentação das propostas: 13-02-2026 18:00\nPrazo durante o qual os concorrentes são obrigados a manter as respetivas propostas: 120 dias a contar do termo do prazo para a apresentação das propostas\nIndicação de Subcontratação na Proposta: Inexistência de indicação de subcontratação\n14 - PRESTAÇÃO DE CAUÇÃO\nPrestação de caução: Não\n15 - FORNECIMENTO DAS PEÇAS DO CONCURSO, APRESENTAÇÃO DE PEDIDOS DE PARTICIPAÇÃO E APRESENTAÇÃO DAS PROPOSTAS\nLink para acesso às peças do concurso (URL): https://www.acingov.pt/acingovprod/2/zonaPublica/zona_publica_c/donwloadProcedurePiece/MTA1MDM3MA==\n20 - OUTROS REQUISITOS\nInformação sobre contratos reservados. Aplica-se a contratos reservados (54º-A)? Não\n21 - CRITÉRIO DE ADJUDICAÇÃO\nMultifator: Não\nMonofator:\nNome: Outros\nOutro nome: Fator Preço\n24 - CONDIÇÕES DO CONTRATO\nFaturação Eletrónica: Permitido\nObrigação de Subcontratação:\nCódigo da Obrigação de Subcontratação: Não é aplicável nenhuma obrigação de subcontratação.\n25 - COMPRA PÚBLICA ESTRATÉGICA\nCompra Pública Estratégica: Inexistência de contratação pública estratégica\n26 - INFORMAÇÕES ADICIONAIS\nContrato adequado para PME: Não\nCobertura ACP (Acordo dos Contratos Públicos da Organização Mundial do Comércio): Não\n27 - IDENTIFICAÇÃO E CONTACTOS DO ÓRGÃO DE RECURSOS ADMINISTRATIVOS\nDesignação: Delegação Regional do Algarve\nEndereço: Rua Dr. Cândido Guerreiro, n.º 45 1.º Edifício Nascente\nCódigo postal: 8000-318\nLocalidade: Faro\nTelefone: 289152600\nFax: \nEndereço eletrónico: delegacao.algarve@iefp.pt\n28 - IDENTIFICAÇÃO DO(S) AUTOR(ES) DE ANÚNCIO\nNome: Ana Isabel Branco Vieira\nCargo: Diretora do Centro Emprego e Formação Profissional do Barlavento\n419949499",
    "nipc": "501442600",
    "distrito": "Lisboa",
    "concelho": "Lisboa",
    "freguesia": "Freguesia de Beato",
    "site": "www.iefp.pt",
    "email": "pg-af@iefp.pt",
    "designacao_contrato": "Concessão de exploração da Cafetaria do CEFP de Portimão e colocação de Equipamentos de venda automática na instalações do CEFP do Barlavento",
    "descricao": "Concessão de exploração da Cafetaria do CEFP de Portimão e colocação de Equipamentos de venda automática na instalações do CEFP do Barlavento",
    "preco_base": "3.000,00 EUR",
    "prazo_execucao": "12 MESES",
    "prazo_apresentacao_propostas": "13-02-2026 18:00",
    "fundos_eu": "Não",
    "plataforma_eletronica": "ACIN",
    "url_procedimento": "https://www.acingov.pt",
    "autor_nome": "Ana Isabel Branco Vieira",
    "autor_cargo": "Diretora do Centro Emprego e Formação Profissional do Barlavento"
  },
  {
    "numero_procedimento": "N/A",
    "entidade": "AnÃºncio de procedimento  n.Âº 2130/2026  -  DiÃ¡rio da RepÃºblica n.Âº 20/2026, SÃ©rie II de 2026-01-29",
    "link": "https://diariodarepublica.pt/dr/detalhe/contrato-publico/2130-1029684211"
  },
  {
    "numero_procedimento": "N/A",
    "entidade": "AnÃºncio de procedimento  n.Âº 2132/2026  -  DiÃ¡rio da RepÃºblica n.Âº 20/2026, SÃ©rie II de 2026-01-29",
    "link": "https://diariodarepublica.pt/dr/detalhe/contrato-publico/2132-1029684212"
  },
  {
    "numero_procedimento": "N/A",
    "entidade": "Município de Santa Cruz das Flores",
    "link": "https://diariodarepublica.pt/dr/detalhe/contrato-publico/2133-1029684214",
    "detalhes_completos": "Alteração do Anúncio de procedimento n.º 1346/2026, de 2026-01-21, com o ID 419948607\n1 - IDENTIFICAÇÃO E CONTACTOS DA ENTIDADE ADJUDICANTE\nDesignação da entidade adjudicante: Município de Santa Cruz das Flores\nNIPC: 512079110\nEndereço: Rua Senador André de Freitas, n.º 13\nCódigo postal: 9970-337\nLocalidade: Santa Cruz das Flores\nPaís: Portugal\nNUT III: PT200\nDistrito: Região Autónoma dos Açores\nConcelho: Santa Cruz das Flores\nFreguesia: Freguesia de Santa Cruz das Flores\nTelefone: 292590700\nFax: Sem Aplicação \nEndereço da Entidade (URL): https://www.cmscflores.pt/\nEndereço Eletrónico: geral@cmscflores.pt\nFunção da Organização: Adquirente\nNorma jurídica da Entidade Adjudicante: Autoridade local\nÁrea de atividade da Entidade Adjudicante: Atividades aeroportuárias\n2 - JORNAL OFICIAL DA UNIÃO EUROPEIA\nO procedimento a que este anúncio diz respeito também é publicitado no Jornal Oficial da União Europeia? Não\n3 - AVISO\nModelo de Anúncio: Concurso público\nData de Envio do Anúncio: 29-01-2026\n5 - PROCESSO\nTipo de Procedimento: Concurso público\nPreço base do procedimento: Sim\nValor do preço base do procedimento: 115.350,00 EUR\nProcedimento com lotes? Não\n6 - OBJETO DO CONTRATO\nNúmero de referência interna: 05/2026\nDesignação do contrato: Concurso Público: Aquisição e Implementação de uma Rede de Comunicação Digital de Emergência\nDescrição: Concurso Público: Aquisição e Implementação de uma Rede de Comunicação Digital de Emergência\nTipo de Contrato Principal: Aquisição de Bens Móveis\nTipo de Contrato: Aquisição de Bens Móveis\nClassificação CPV (Vocabulário Comum para os Contratos Públicos)\nObjeto principal\nVocabulário Principal: 32500000\nPreço base s/IVA: 115.350,00 EUR\n7 - INDICAÇÕES ADICIONAIS\nO contrato envolve aquisição conjunta (satisfação de várias entidades)? Não\nO contrato é adjudicado por uma central de compras? Não\n8 - TÉCNICAS\nO concurso destina-se à celebração de um acordo-quadro? Inexistência de acordo-quadro\nÉ utilizado um leilão eletrónico? Não\nÉ adotada uma fase de negociação? Não\nSistema de Aquisição Dinâmico: Inexistência de sistema de aquisição dinâmico\n9 - LOCAL DA EXECUÇÃO DO CONTRATO\nLOCAL DA EXECUÇÃO DO CONTRATO (PROCEDIMENTO)\nPaís: Portugal\nNUT III: PT200\nLocalidade: Santa Cruz das Flores \nDistrito: Região Autónoma dos Açores\nConcelho: Santa Cruz das Flores\nFreguesia: Freguesia de Santa Cruz das Flores\n10 - PRAZO DE EXECUÇÃO DO CONTRATO\nPrazo de execução do contrato: 6 MESES\nPrevisão de renovações: Não\n11 - FUNDOS EU\nTêm fundos EU? Sim\n12 - DOCUMENTOS DE HABILITAÇÃO\nHabilitação para o exercício da atividade profissional: Não\n13 - CONDIÇÕES DE APRESENTAÇÃO\nPlataforma eletrónica utilizada pela entidade adjudicante: ANOGOV\nURL para Apresentação: https://www.anogov.com/op-cmstacruzflores/faces/\nAdmissibilidade da apresentação de propostas variantes: Não autorizado\nPrazo para apresentação das propostas: 10-02-2026 23:59\nPrazo durante o qual os concorrentes são obrigados a manter as respetivas propostas: 90 dias a contar do termo do prazo para a apresentação das propostas\nApresentação de Catálogo Eletrónico: Permitido\nIndicação de Subcontratação na Proposta: Inexistência de indicação de subcontratação\n14 - PRESTAÇÃO DE CAUÇÃO\nPrestação de caução: Não\n15 - FORNECIMENTO DAS PEÇAS DO CONCURSO, APRESENTAÇÃO DE PEDIDOS DE PARTICIPAÇÃO E APRESENTAÇÃO DAS PROPOSTAS\nLink para acesso às peças do concurso (URL): https://www.anogov.com/op-cmstacruzflores/faces/app/acessoDocs.jsp?codigoAcesso=eVjCTQS5XmSa6XzqYvtMzijiY91Y4t01mDqF1yYUU1DCgOMLek\n20 - OUTROS REQUISITOS\nInformação sobre contratos reservados. Aplica-se a contratos reservados (54º-A)? Não\n21 - CRITÉRIO DE ADJUDICAÇÃO\nMultifator: Não\nMonofator:\nNome: Preço\n24 - CONDIÇÕES DO CONTRATO\nFaturação Eletrónica: Permitido\nObrigação de Subcontratação:\nCódigo da Obrigação de Subcontratação: Não é aplicável nenhuma obrigação de subcontratação.\n25 - COMPRA PÚBLICA ESTRATÉGICA\nCompra Pública Estratégica: Inexistência de contratação pública estratégica\n26 - INFORMAÇÕES ADICIONAIS\nContrato adequado para PME: Sim\nCobertura ACP (Acordo dos Contratos Públicos da Organização Mundial do Comércio): Não\n27 - IDENTIFICAÇÃO E CONTACTOS DO ÓRGÃO DE RECURSOS ADMINISTRATIVOS\nDesignação: Município de Santa Cruz das Flores\nEndereço: Rua Senador André de Freitas, 13\nCódigo postal: 9970-337\nLocalidade: Santa Cruz das Flores\nEndereço eletrónico: geral@cmscflores.pt\n28 - IDENTIFICAÇÃO DO(S) AUTOR(ES) DE ANÚNCIO\nNome: Maria Elisabete Avelar Nóia \nCargo: Presidente da Câmara Municipal de Santa Cruz das Flores \n29 - ALTERAÇÃO\nMotivo da Alteração: Correção pelo adquirente\nIdentificador da Versão do Anúncio a Alterar: 53a20c0b-9648-4538-8ae3-bedc269b3f6d-01\nIdentificador das Secções Alteradas do Anúncio Anterior: Alteração\nDescrição das Alterações: Correção de erros e omissões nas Peças do Procedimento e prorrogação do prazo fixado para apresentação de propostas\nAlteração dos Documentos do Concurso: Sim\nData de alteração dos documentos do concurso: 29-01-2026\n419949522",
    "nipc": "512079110",
    "distrito": "Região Autónoma dos Açores",
    "concelho": "Santa Cruz das Flores",
    "freguesia": "Freguesia de Santa Cruz das Flores",
    "site": "https://www.cmscflores.pt/",
    "email": "geral@cmscflores.pt",
    "designacao_contrato": "Concurso Público: Aquisição e Implementação de uma Rede de Comunicação Digital de Emergência",
    "descricao": "Concurso Público: Aquisição e Implementação de uma Rede de Comunicação Digital de Emergência",
    "preco_base": "115.350,00 EUR",
    "prazo_execucao": "6 MESES",
    "prazo_apresentacao_propostas": "10-02-2026 23:59",
    "fundos_eu": "Sim",
    "plataforma_eletronica": "ANOGOV",
    "url_procedimento": "https://www.anogov.com/op-cmstacruzflores/faces/",
    "autor_nome": "Maria Elisabete Avelar Nóia",
    "autor_cargo": "Presidente da Câmara Municipal de Santa Cruz das Flores"
  },
  {
    "numero_procedimento": "N/A",
    "entidade": "Direção-Geral de Reinserção e Serviços Prisionais",
    "link": "https://diariodarepublica.pt/dr/detalhe/contrato-publico/2134-1029684215",
    "detalhes_completos": "1 - IDENTIFICAÇÃO E CONTACTOS DA ENTIDADE ADJUDICANTE\nDesignação da entidade adjudicante: Direção-Geral de Reinserção e Serviços Prisionais\nNIPC: 600085171\nEndereço: Travessa da Cruz do Torel, nº1\nCódigo postal: 1150-122\nLocalidade: Lisboa\nPaís: Portugal\nNUT III: PT170\nDistrito: Todos\nConcelho: Todos\nFreguesia: Todas\nTelefone: 218812200\nFax: 213259470\nEndereço da Entidade (URL): https://dgrsp.justica.gov.pt/\nEndereço Eletrónico: correio@sg.mj.pt\neDelivery Gateway (URL): https://www.acingov.pt\nFunção da Organização: Adquirente\nNorma jurídica da Entidade Adjudicante: Organismo de direito público\nÁrea de atividade da Autoridade Adjudicante: Serviços públicos das administrações públicas\n2 - JORNAL OFICIAL DA UNIÃO EUROPEIA\nO procedimento a que este anúncio diz respeito também é publicitado no Jornal Oficial da União Europeia? Não\n3 - AVISO\nModelo de Anúncio: Concurso público\nData de Envio do Anúncio: 29-01-2026\n5 - PROCESSO\nTipo de Procedimento: Concurso público\nPreço base do procedimento: Sim\nValor do preço base do procedimento: 495.000,00 EUR\nProcedimento com lotes? Não\n6 - OBJETO DO CONTRATO\nNúmero de referência interna: 300.10.005/2025/296\nDesignação do contrato: Empreitada de obras públicas para construção de duas torres de vigia (guaritas) no Estabelecimento Prisional de Vale de Judeus\nDescrição: Empreitada de obras públicas para construção de duas torres de vigia (guaritas) no Estabelecimento Prisional de Vale de Judeus\nTipo de Contrato Principal: Empreitada de Obras Públicas\nTipo de Contrato: Empreitada de Obras Públicas\nClassificação CPV (Vocabulário Comum para os Contratos Públicos)\nObjeto principal\nVocabulário Principal: 45340000\nPreço base s/IVA: 495.000,00 EUR\n7 - INDICAÇÕES ADICIONAIS\nO contrato envolve aquisição conjunta (satisfação de várias entidades)? Não\nO contrato é adjudicado por uma central de compras? Não\n8 - TÉCNICAS\nO concurso destina-se à celebração de um acordo-quadro? Inexistência de acordo-quadro\nÉ utilizado um leilão eletrónico? Não\nÉ adotada uma fase de negociação? Não\nSistema de Aquisição Dinâmico: Inexistência de sistema de aquisição dinâmico\n9 - LOCAL DA EXECUÇÃO DO CONTRATO\nLOCAL DA EXECUÇÃO DO CONTRATO (PROCEDIMENTO)\nPaís: Portugal\nNUT III: PTZZZ\nLocalidade: Freguesia de Alcoentre\nDistrito: Lisboa\nConcelho: Azambuja\nFreguesia: Freguesia de Alcoentre\n10 - PRAZO DE EXECUÇÃO DO CONTRATO\nPrazo de execução do contrato: 8 MESES\nPrevisão de renovações: Não\n11 - FUNDOS EU\nTêm fundos EU? Não\n12 - DOCUMENTOS DE HABILITAÇÃO\nHabilitação para o exercício da atividade profissional: Não\n13 - CONDIÇÕES DE APRESENTAÇÃO\nPlataforma eletrónica utilizada pela entidade adjudicante: ACIN\nURL para Apresentação: https://www.acingov.pt\nAdmissibilidade da apresentação de propostas variantes: Não autorizado\nPrazo para apresentação das propostas: 04-02-2026 23:59\nPrazo durante o qual os concorrentes são obrigados a manter as respetivas propostas: 66 dias a contar do termo do prazo para a apresentação das propostas\nIndicação de Subcontratação na Proposta: Inexistência de indicação de subcontratação\n14 - PRESTAÇÃO DE CAUÇÃO\nPrestação de caução: Não\n15 - FORNECIMENTO DAS PEÇAS DO CONCURSO, APRESENTAÇÃO DE PEDIDOS DE PARTICIPAÇÃO E APRESENTAÇÃO DAS PROPOSTAS\nLink para acesso às peças do concurso (URL): https://www.acingov.pt/acingovprod/2/zonaPublica/zona_publica_c/donwloadProcedurePiece/MTAwNDk5Nw==\n20 - OUTROS REQUISITOS\nInformação sobre contratos reservados. Aplica-se a contratos reservados (54º-A)? Não\n21 - CRITÉRIO DE ADJUDICAÇÃO\nMultifator: Não\nMonofator:\nNome: Preço\n24 - CONDIÇÕES DO CONTRATO\nFaturação Eletrónica: Permitido\nObrigação de Subcontratação:\nCódigo da Obrigação de Subcontratação: Não é aplicável nenhuma obrigação de subcontratação.\n25 - COMPRA PÚBLICA ESTRATÉGICA\nCompra Pública Estratégica: Inexistência de contratação pública estratégica\n26 - INFORMAÇÕES ADICIONAIS\nContrato adequado para PME: Não\nCobertura ACP (Acordo dos Contratos Públicos da Organização Mundial do Comércio): Não\n27 - IDENTIFICAÇÃO E CONTACTOS DO ÓRGÃO DE RECURSOS ADMINISTRATIVOS\nDesignação: Ministério da Justiça\nEndereço: Praça do Comércio\nCódigo postal: 1149-019\nLocalidade: Lisboa\nTelefone: 218812200\nFax: \nEndereço eletrónico: correio@sg.mj.pt\n28 - IDENTIFICAÇÃO DO(S) AUTOR(ES) DE ANÚNCIO\nNome: Rute Sofia Belchior\nCargo: Diretor de Serviços\n419949516",
    "nipc": "600085171",
    "distrito": "Todos",
    "concelho": "Todos",
    "freguesia": "Todas",
    "site": "https://dgrsp.justica.gov.pt/",
    "email": "correio@sg.mj.pt",
    "designacao_contrato": "Empreitada de obras públicas para construção de duas torres de vigia (guaritas) no Estabelecimento Prisional de Vale de Judeus",
    "descricao": "Empreitada de obras públicas para construção de duas torres de vigia (guaritas) no Estabelecimento Prisional de Vale de Judeus",
    "preco_base": "495.000,00 EUR",
    "prazo_execucao": "8 MESES",
    "prazo_apresentacao_propostas": "04-02-2026 23:59",
    "fundos_eu": "Não",
    "plataforma_eletronica": "ACIN",
    "url_procedimento": "https://www.acingov.pt",
    "autor_nome": "Rute Sofia Belchior",
    "autor_cargo": "Diretor de Serviços"
  },
  {
    "numero_procedimento": "N/A",
    "entidade": "Unidade Local de Saúde de Lisboa Ocidental, EPE",
    "link": "https://diariodarepublica.pt/dr/detalhe/contrato-publico/2135-1029684216",
    "detalhes_completos": "1 - IDENTIFICAÇÃO E CONTACTOS DA ENTIDADE ADJUDICANTE\nDesignação da entidade adjudicante: Unidade Local de Saúde de Lisboa Ocidental, EPE\nNIPC: 507618319\nEndereço: Santa Maria de Belém  Estrada do Forte do Alto do Duque\nCódigo postal: 1449-005\nLocalidade: Lisboa\nPaís: Portugal\nNUT III: PT170\nDistrito: Lisboa\nConcelho: Lisboa\nFreguesia: Todas\nTelefone: 210431000\nFax: 210431642\nEndereço da Entidade (URL): www.chlo.min-saude.pt/\nEndereço Eletrónico: comprasgeral@ulslo.min-saude.pt\neDelivery Gateway (URL): https://community.vortal.biz/public/\nFunção da Organização: Adquirente\nNorma jurídica da Entidade Adjudicante: Organismo de direito público\nÁrea de atividade da Autoridade Adjudicante: Saúde\n2 - JORNAL OFICIAL DA UNIÃO EUROPEIA\nO procedimento a que este anúncio diz respeito também é publicitado no Jornal Oficial da União Europeia? Não\n3 - AVISO\nModelo de Anúncio: Concurso público\nData de Envio do Anúncio: 29-01-2026\n5 - PROCESSO\nTipo de Procedimento: Concurso público\nPreço base do procedimento: Sim\nValor do preço base do procedimento: 148.500,00 EUR\nProcedimento com lotes? Não\n6 - OBJETO DO CONTRATO\nNúmero de referência interna: 149000126\nDesignação do contrato: Empreitada de substituição pavimento betuminoso e impermeabilização da laje exterior piso -2 HSFX\nDescrição: Empreitada de substituição pavimento betuminoso e impermeabilização da laje exterior piso -2 HSFX\nTipo de Contrato Principal: Empreitada de Obras Públicas\nTipo de Contrato: Empreitada de Obras Públicas\nClassificação CPV (Vocabulário Comum para os Contratos Públicos)\nObjeto principal\nVocabulário Principal: 45233251\nPreço base s/IVA: 148.500,00 EUR\n7 - INDICAÇÕES ADICIONAIS\nO contrato envolve aquisição conjunta (satisfação de várias entidades)? Não\nO contrato é adjudicado por uma central de compras? Não\n8 - TÉCNICAS\nO concurso destina-se à celebração de um acordo-quadro? Inexistência de acordo-quadro\nÉ utilizado um leilão eletrónico? Não\nÉ adotada uma fase de negociação? Não\nSistema de Aquisição Dinâmico: Inexistência de sistema de aquisição dinâmico\n9 - LOCAL DA EXECUÇÃO DO CONTRATO\nLOCAL DA EXECUÇÃO DO CONTRATO (PROCEDIMENTO)\nPaís: Portugal\nNUT III: PT170\nLocalidade: Lisboa\nDistrito: Lisboa\nConcelho: Lisboa\nFreguesia: Todas\n10 - PRAZO DE EXECUÇÃO DO CONTRATO\nPrazo de execução do contrato: 75 DIAS\nPrevisão de renovações: Não\n11 - FUNDOS EU\nTêm fundos EU? Não\n12 - DOCUMENTOS DE HABILITAÇÃO\nHabilitação para o exercício da atividade profissional: Não\n13 - CONDIÇÕES DE APRESENTAÇÃO\nPlataforma eletrónica utilizada pela entidade adjudicante: VORTAL\nURL para Apresentação: https://community.vortal.biz/public/\nAdmissibilidade da apresentação de propostas variantes: Não autorizado\nPrazo para apresentação das propostas: 19-02-2026 17:00\nPrazo durante o qual os concorrentes são obrigados a manter as respetivas propostas: 120 dias a contar do termo do prazo para a apresentação das propostas\nIndicação de Subcontratação na Proposta: Inexistência de indicação de subcontratação\n14 - PRESTAÇÃO DE CAUÇÃO\nPrestação de caução: Não\n15 - FORNECIMENTO DAS PEÇAS DO CONCURSO, APRESENTAÇÃO DE PEDIDOS DE PARTICIPAÇÃO E APRESENTAÇÃO DAS PROPOSTAS\nLink para acesso às peças do concurso (URL): https://community.vortal.biz/Public/public-tender-documents/WVhGbkIwclZ2UGRHemxuMDhzVkF4TFlHdEdaWkFycTF4QTNEd2NhblZMT1Y4SDFWeGxsV3NqbVlxZlZBQWt3TER3TUxTbWNwQTg3eGx2K0VZWk00ZlE9PVp1X08o\n20 - OUTROS REQUISITOS\nInformação sobre contratos reservados. Aplica-se a contratos reservados (54º-A)? Não\n21 - CRITÉRIO DE ADJUDICAÇÃO\nMultifator: Não\nMonofator:\nNome: Outros\nOutro nome: Preço\n24 - CONDIÇÕES DO CONTRATO\nFaturação Eletrónica: Permitido\nObrigação de Subcontratação:\nCódigo da Obrigação de Subcontratação: Não é aplicável nenhuma obrigação de subcontratação.\n25 - COMPRA PÚBLICA ESTRATÉGICA\nCompra Pública Estratégica: Inexistência de contratação pública estratégica\n26 - INFORMAÇÕES ADICIONAIS\nContrato adequado para PME: Sim\nCobertura ACP (Acordo dos Contratos Públicos da Organização Mundial do Comércio): Não\n27 - IDENTIFICAÇÃO E CONTACTOS DO ÓRGÃO DE RECURSOS ADMINISTRATIVOS\nDesignação: Conselho de Administração\nEndereço: Estrada do alto do forte do duque\nCódigo postal: 1449-005\nLocalidade: Lisboa\nTelefone: +351 210431000\nFax: +351 210431639\nEndereço eletrónico: secca@ulslo.min-saude.pt\n28 - IDENTIFICAÇÃO DO(S) AUTOR(ES) DE ANÚNCIO\nNome: Eduardo Neves\nCargo: Assistente Técnico\n419949492",
    "nipc": "507618319",
    "distrito": "Lisboa",
    "concelho": "Lisboa",
    "freguesia": "Todas",
    "site": "www.chlo.min-saude.pt/",
    "email": "comprasgeral@ulslo.min-saude.pt",
    "designacao_contrato": "Empreitada de substituição pavimento betuminoso e impermeabilização da laje exterior piso -2 HSFX",
    "descricao": "Empreitada de substituição pavimento betuminoso e impermeabilização da laje exterior piso -2 HSFX",
    "preco_base": "148.500,00 EUR",
    "prazo_execucao": "75 DIAS",
    "prazo_apresentacao_propostas": "19-02-2026 17:00",
    "fundos_eu": "Não",
    "plataforma_eletronica": "VORTAL",
    "url_procedimento": "https://community.vortal.biz/public/",
    "autor_nome": "Eduardo Neves",
    "autor_cargo": "Assistente Técnico"
  },
  {
    "numero_procedimento": "N/A",
    "entidade": "Autoridade Nacional de Comunicações",
    "link": "https://diariodarepublica.pt/dr/detalhe/contrato-publico/2136-1029684220",
    "detalhes_completos": "1 - IDENTIFICAÇÃO E CONTACTOS DA ENTIDADE ADJUDICANTE\nDesignação da entidade adjudicante: Autoridade Nacional de Comunicações\nNIPC: 502017368\nEndereço: Rua Ramalho Ortigão, 51\nCódigo postal: 1099-099\nLocalidade: Lisboa\nPaís: Portugal\nNUT III: PT170\nDistrito: Lisboa\nConcelho: Lisboa\nFreguesia: Freguesia de Avenidas Novas\nTelefone: 217211000\nEndereço Eletrónico: info@anacom.pt\nFunção da Organização: Adquirente\nNorma jurídica da Entidade Adjudicante: Organismo de direito público\nÁrea de atividade da Autoridade Adjudicante: Serviços públicos das administrações públicas\n2 - JORNAL OFICIAL DA UNIÃO EUROPEIA\nO procedimento a que este anúncio diz respeito também é publicitado no Jornal Oficial da União Europeia? Não\n3 - AVISO\nModelo de Anúncio: Concurso público\nData de Envio do Anúncio: 29-01-2026\n5 - PROCESSO\nTipo de Procedimento: Concurso público\nPreço base do procedimento: Sim\nValor do preço base do procedimento: 178.724,00 EUR\nProcedimento com lotes? Não\n6 - OBJETO DO CONTRATO\nNúmero de referência interna: PA00120250001478\nDesignação do contrato: Serviços de comunicações para a rede de supervisão do espectro (nomeadamente o SINCRER)\nDescrição: Aquisição de serviços de comunicações para a rede de supervisão do espectro (nomeadamente o Sistema Nacional de Controlo Remoto das Estações Radioelétricas - SINCRER) \nTipo de Contrato Principal: Aquisição de Serviços\nTipo de Contrato: Aquisição de Serviços\nClassificação CPV (Vocabulário Comum para os Contratos Públicos)\nObjeto principal\nVocabulário Principal: 64200000\nPreço base s/IVA: 178.724,00 EUR\n7 - INDICAÇÕES ADICIONAIS\nO contrato envolve aquisição conjunta (satisfação de várias entidades)? Não\nO contrato é adjudicado por uma central de compras? Não\n8 - TÉCNICAS\nO concurso destina-se à celebração de um acordo-quadro? Inexistência de acordo-quadro\nÉ utilizado um leilão eletrónico? Não\nÉ adotada uma fase de negociação? Não\nSistema de Aquisição Dinâmico: Inexistência de sistema de aquisição dinâmico\n9 - LOCAL DA EXECUÇÃO DO CONTRATO\nLOCAL DA EXECUÇÃO DO CONTRATO (PROCEDIMENTO)\nPaís: Portugal\nNUT III: PT170\nLocalidade: Portugal\nDistrito: Lisboa\nConcelho: Lisboa\nFreguesia: Freguesia de Avenidas Novas\n10 - PRAZO DE EXECUÇÃO DO CONTRATO\nPrazo de execução do contrato: 3 ANOS\nPrevisão de renovações: Não\n11 - FUNDOS EU\nTêm fundos EU? Não\n12 - DOCUMENTOS DE HABILITAÇÃO\nHabilitação para o exercício da atividade profissional: Não\n13 - CONDIÇÕES DE APRESENTAÇÃO\nPlataforma eletrónica utilizada pela entidade adjudicante: VORTAL\nURL para Apresentação: https://pt.vortal.biz\nAdmissibilidade da apresentação de propostas variantes: Não autorizado\nPrazo para apresentação das propostas: 16-02-2026 17:00\nPrazo durante o qual os concorrentes são obrigados a manter as respetivas propostas: 120 dias a contar do termo do prazo para a apresentação das propostas\nIndicação de Subcontratação na Proposta: Inexistência de indicação de subcontratação\n14 - PRESTAÇÃO DE CAUÇÃO\nPrestação de caução: Não\n15 - FORNECIMENTO DAS PEÇAS DO CONCURSO, APRESENTAÇÃO DE PEDIDOS DE PARTICIPAÇÃO E APRESENTAÇÃO DAS PROPOSTAS\nLink para acesso às peças do concurso (URL): https://www.vortal.biz/pt-pt/login/\n20 - OUTROS REQUISITOS\nInformação sobre contratos reservados. Aplica-se a contratos reservados (54º-A)? Não\n21 - CRITÉRIO DE ADJUDICAÇÃO\nMultifator: Não\nMonofator:\nNome: Preço\n24 - CONDIÇÕES DO CONTRATO\nFaturação Eletrónica: Permitido\n25 - COMPRA PÚBLICA ESTRATÉGICA\nCompra Pública Estratégica: Inexistência de contratação pública estratégica\n26 - INFORMAÇÕES ADICIONAIS\nContrato adequado para PME: Sim\nCobertura ACP (Acordo dos Contratos Públicos da Organização Mundial do Comércio): Não\n27 - IDENTIFICAÇÃO E CONTACTOS DO ÓRGÃO DE RECURSOS ADMINISTRATIVOS\nDesignação: Conselho de Administração da ANACOM\nEndereço: Rua Ramalho Ortigão, 51\nCódigo postal: 1099-099\nLocalidade: Lisboa\nEndereço eletrónico: info@anacom.pt\n28 - IDENTIFICAÇÃO DO(S) AUTOR(ES) DE ANÚNCIO\nNome: João Gonçalo de Oliveira Estrela\nCargo: Coordenador da equipa de Compras da Direção-Geral de Gestão de Pessoas e de Recursos Financeiros\n419947888",
    "nipc": "502017368",
    "distrito": "Lisboa",
    "concelho": "Lisboa",
    "freguesia": "Freguesia de Avenidas Novas",
    "site": null,
    "email": "info@anacom.pt",
    "designacao_contrato": "Serviços de comunicações para a rede de supervisão do espectro (nomeadamente o SINCRER)",
    "descricao": "Aquisição de serviços de comunicações para a rede de supervisão do espectro (nomeadamente o Sistema Nacional de Controlo Remoto das Estações Radioelétricas - SINCRER)",
    "preco_base": "178.724,00 EUR",
    "prazo_execucao": "3 ANOS",
    "prazo_apresentacao_propostas": "16-02-2026 17:00",
    "fundos_eu": "Não",
    "plataforma_eletronica": "VORTAL",
    "url_procedimento": "https://pt.vortal.biz",
    "autor_nome": "João Gonçalo de Oliveira Estrela",
    "autor_cargo": "Coordenador da equipa de Compras da Direção-Geral de Gestão de Pessoas e de Recursos Financeiros"
  },
  {
    "numero_procedimento": "N/A",
    "entidade": "Ambifaro - Gestão de Equipamentos Municipais, EM",
    "link": "https://diariodarepublica.pt/dr/detalhe/contrato-publico/2138-1029684222",
    "detalhes_completos": "Alteração do Anúncio de procedimento n.º 1243/2026, de 2026-01-20, com o ID 419948410\n1 - IDENTIFICAÇÃO E CONTACTOS DA ENTIDADE ADJUDICANTE\nDesignação da entidade adjudicante: Ambifaro - Gestão de Equipamentos Municipais, EM\nNIPC: 504497782\nServiço/Órgão/Pessoa de contacto: Unidade de Contratação Pública\nEndereço: Largo Dr. Francisco Sá Carneiro- Edifício do Mercado Municipal de Faro; piso 2\nCódigo postal: 8000-151\nLocalidade: Faro\nPaís: Portugal\nNUT III: PT150\nDistrito: Faro\nConcelho: Faro\nFreguesia: União das Freguesias de Faro (Sé e São Pedro)\nTelefone: 289897250\nFax: 000000000\nEndereço da Entidade (URL): www.ambifaro.pt\nEndereço Eletrónico: geral@ambifaro.pt\neDelivery Gateway (URL): https://www.acingov.pt\nFunção da Organização: Adquirente\nNorma jurídica da Entidade Adjudicante: Organismo de direito público\nÁrea de atividade da Autoridade Adjudicante: Serviços públicos das administrações públicas\n2 - JORNAL OFICIAL DA UNIÃO EUROPEIA\nO procedimento a que este anúncio diz respeito também é publicitado no Jornal Oficial da União Europeia? Não\n3 - AVISO\nModelo de Anúncio: Concurso público\nData de Envio do Anúncio: 29-01-2026\n5 - PROCESSO\nTipo de Procedimento: Concurso público\nPreço base do procedimento: Sim\nValor do preço base do procedimento: 175.000,00 EUR\nProcedimento com lotes? Não\n6 - OBJETO DO CONTRATO\nNúmero de referência interna: 1/2026\nDesignação do contrato: Aquisição de serviços de gestão integral de contraordenações rodoviárias e sistema de cobranças\nDescrição: Aquisição de serviços de gestão integral de contraordenações rodoviárias e sistema de cobranças\nTipo de Contrato Principal: Aquisição de Serviços\nTipo de Contrato: Aquisição de Serviços\nClassificação CPV (Vocabulário Comum para os Contratos Públicos)\nObjeto principal\nVocabulário Principal: 72268000\nPreço base s/IVA: 175.000,00 EUR\n7 - INDICAÇÕES ADICIONAIS\nO contrato envolve aquisição conjunta (satisfação de várias entidades)? Não\nO contrato é adjudicado por uma central de compras? Não\n8 - TÉCNICAS\nO concurso destina-se à celebração de um acordo-quadro? Inexistência de acordo-quadro\nÉ utilizado um leilão eletrónico? Não\nÉ adotada uma fase de negociação? Não\nSistema de Aquisição Dinâmico: Inexistência de sistema de aquisição dinâmico\n9 - LOCAL DA EXECUÇÃO DO CONTRATO\nLOCAL DA EXECUÇÃO DO CONTRATO (PROCEDIMENTO)\nPaís: Portugal\nNUT III: PT150\nLocalidade: Faro\nDistrito: Faro\nConcelho: Faro\nFreguesia: União das Freguesias de Faro (Sé e São Pedro)\n10 - PRAZO DE EXECUÇÃO DO CONTRATO\nPrazo de execução do contrato: 36 MESES\nPrevisão de renovações: Não\n11 - FUNDOS EU\nTêm fundos EU? Não\n12 - DOCUMENTOS DE HABILITAÇÃO\nHabilitação para o exercício da atividade profissional: Não\n13 - CONDIÇÕES DE APRESENTAÇÃO\nPlataforma eletrónica utilizada pela entidade adjudicante: ACIN\nURL para Apresentação: https://www.acingov.pt\nAdmissibilidade da apresentação de propostas variantes: Não autorizado\nPrazo para apresentação das propostas: 08-02-2026 23:59\nPrazo durante o qual os concorrentes são obrigados a manter as respetivas propostas: 120 dias a contar do termo do prazo para a apresentação das propostas\nIndicação de Subcontratação na Proposta: Inexistência de indicação de subcontratação\n14 - PRESTAÇÃO DE CAUÇÃO\nPrestação de caução: Não\n15 - FORNECIMENTO DAS PEÇAS DO CONCURSO, APRESENTAÇÃO DE PEDIDOS DE PARTICIPAÇÃO E APRESENTAÇÃO DAS PROPOSTAS\nLink para acesso às peças do concurso (URL): https://www.acingov.pt/acingovprod/2/zonaPublica/zona_publica_c/donwloadProcedurePiece/MTA0OTA2OA==\n20 - OUTROS REQUISITOS\nInformação sobre contratos reservados. Aplica-se a contratos reservados (54º-A)? Não\n21 - CRITÉRIO DE ADJUDICAÇÃO\nMultifator: Sim\nFator: \nNome: Preço\nPonderação: 60%\nSubfatores: Sim\nSubfatores: \nNome: FP= 0,50x (0,20 x Psgc + 0,80 x Pvi) + 0,25% x (0,20 x Psia + 0,70 x Piaj) + 0,10 x (0,25 x Psc + 0,25 X Psmc + 0,25 x Psmc + 0,25 x Pcom% + 0,25 x Pcom) + 0,05 x (0,50 x Pigc + 0,50 xPiia) + 0,10 x (0,50 xPgc + 0,25 x Pt1500 + 0,15 x Pt3000 + 0,10 x Pt>3000) Psgc  Pontuação para o subfactor Valor mensal para a solução do serviço de Gestão de contraordenações; Pvi  Pontuação para o subfactor Valor por interação; Psia  Pontuação para o subfactor Valor mensal para a solução de Instrução Administrativa; Pviaj  Pontuação para o subfactor Valor por Instrução Administrativa com apoio jurídico Psc  Pontuação para o subfactor Valor mensal para a solução de cobrança e disponibilidade de entidades; Psmc  Pontuação para o subfactor Valor mensal para o suporte ao sistema e manutenção corretiva; Pcom% - Pontuação para o subfactor Valor da comissão por transação; Pcom - Pontuação para o subfactor Valor máximo da comissão; Pigc  Pontuação para o subfactor Valor pela implementação da solução de Gestão de Contraordenações e formação aos utilizadores; Piia - Pontuação para o subfactor Valor pela implementação da solução da Instrução Administrativa e formação aos utilizadores; Psc  Pontuação para o subfactor Valor mensal para a solução de gestão da correspondência; Ptr1500 - Pontuação para o subfactor Valor máximo da comissão para tratamento de respostas até 1500 objetos inclusive; Ptr3000 - Pontuação para o subfactor Valor máximo da comissão para tratamento de respostas até 3000 objetos inclusive; Ptr>3000 - Pontuação para o subfactor Valor máximo da comissão para tratamento de respostas superior a 3000 objetos; Para efeitos do disposto no número anterior, os concorrentes serão ordenados segundo a classificação final obtida, por ordem decrescente, tendo por base os seguintes fatores/subfactores: Contraordenações (50%) Solução de gestão de contraordenações (20%) Este subfactor pretende avaliar o valor mensal em euro tipo fee para disponibilização da plataforma de gestão de contraordenações: Psgc=100-Pc/Pm x 100 Onde: Psgc  Pontuação para o subfactor Valor mensal para a solução do serviço de Gestão de contraordenações; Pm  Preço máximo; Pc  Preço apresentado pelo concorrente. Serão considerados valores iguais ou inferiores ao preço base unitário. Ou seja, se o preço proposto for superior a 165,00 a proposta será excluída. Se o preço proposto for de 0,00, será atribuída a pontuação máxima. Valor por interação (80%) Este subfactor pretende avaliar o valor em euro de cada interação de acordo com o que está definido no Caderno de Encargos. Pvi=100-Pc/Pm x 100 Onde: Pvi  Pontuação para o subfactor Valor por interação; Pm  Preço máximo; Pc  Preço apresentado pelo concorrente. Serão considerados valores iguais ou inferiores ao preço base unitário. Ou seja, se o preço proposto for superior a 1,95 por interação, a proposta será excluída. Se o preço proposto for de 0,00 por interação, será atribuída a pontuação máxima. Instrução e Decisão (25%) Solução de Instrução Administrativa (20%) Este subfactor pretende avaliar o valor mensal em euro tipo fee para disponibilização da plataforma de gestão de instrução e decisão administrativa: Psia=100-Pc/Pm x 100 Onde: Psia  Pontuação para o subfactor Valor mensal para a solução de Instrução Administrativa; Pm  Preço máximo; Pc  Preço apresentado pelo concorrente. Serão considerados valores iguais ou inferiores ao preço base unitário. Ou seja, se o preço proposto for superior a 165,00 a proposta será excluída. Se o preço proposto for de 0,00, será atribuída a pontuação máxima. Valor por Instrução Administrativa com apoio jurídico (70%) Este subfactor pretende avaliar o valor em euro de cada processo com serviços jurídicos: Pviaj=100-Pc/Pm x 100 Onde: Pviaj  Pontuação para o subfactor Valor por Instrução Administrativa com apoio jurídico Pm  Preço máximo; Pc  Preço apresentado pelo concorrente. Serão considerados valores iguais ou inferiores ao preço base unitário. Ou seja, se o preço proposto for superior a 6,05 a proposta será excluída. Se o preço proposto for de 0,00, será atribuída a pontuação máxima.. Cobrança (10%) Solução de cobrança e disponibilidade de entidades (25%) Este subfactor pretende avaliar o valor mensal em euro tipo fee para disponibilização da plataforma de gestão de cobranças e disponibilidade de entidades: Psc=100-Pc/Pm x 100 Onde: Psc  Pontuação para o subfactor Valor mensal para a solução de cobrança e disponibilidade de entidades; Pm  Preço máximo; Pc  Preço apresentado pelo concorrente. Serão considerados valores iguais ou inferiores ao preço base unitário. Ou seja, se o preço proposto for superior a 550,00 a proposta será excluída. Se o preço proposto for de 0,00, será atribuída a pontuação máxima. Suporte ao sistema e manutenção corretiva (25%) Este subfactor pretende avaliar o valor mensal em euro tipo fee para efetuar o suporte e manutenção corretiva da plataforma de gestão de cobranças e disponibilidade de entidades: Psmc=100-Pc/Pm x 100 Onde: Psmc  Pontuação para o subfactor Valor mensal para o suporte ao sistema e manutenção corretiva; Pm  Preço máximo; Pc  Preço apresentado pelo concorrente. Serão considerados valores iguais ou inferiores ao preço base unitário. Ou seja, se o preço proposto for superior a 27,50 a proposta será excluída. Se o preço proposto for de 0,00, será atribuída a pontuação máxima. Valor da comissão por transação (25%) Este subfactor pretende avali...\nPonderação : 100%; \nFator: \nNome: Outros\nOutro Nome: Avaliação Demo\nPonderação: 25%\nSubfatores: Sim\nSubfatores: \nNome: Ad = (F1x0,25) + (F2x0,25) + (F3x0,25) + (UI1x0,10) + (UI2x0,10) + (UI3x0,05) Sendo que: Avaliação da Demo A preencher possui: Ponderação % Sim Não Funcionalidade F1-Deteção automática dos dados respeitantes às infrações  O sistema consegue identificar corretamente os dados registados (infração, local, veículo) 25% F2-Geração e gestão de autos de contraordenação  O sistema permite registar, processar e emitir as notificações ou PIC de forma eficiente 25% F3-Possibilidade da pesquisa de Auto por número de processo e verificação do estado e prazo da conclusão da análise da decisão em fase de instrução administrativa 25% Usabilidade e Interface UI1-Facilidade de uso  O sistema é intuitivo para os operadores, exigindo pouca formação 10% UI2-Rapidez na navegação  A interface permite acesso ágil às informações e execução de tarefas sem atrasos 10% UI3-Design e clareza  Os menus, botões e alertas são bem organizados e de fácil compreensão 5% Cotação a atribuir: F1  1 em caso afirmativo e 0 em caso negativo; F2  1 em caso afirmativo e 0 em caso negativo; F3  1 em caso afirmativo e 0 em caso negativo; UI1 - 1 em caso afirmativo e 0 em caso negativo; UI2 - 1 em caso afirmativo e 0 em caso negativo; UI3 - 1 em caso afirmativo e 0 em caso negativo; com peso especifico de 100%.\nPonderação : 100%; \nFator: \nNome: Outros\nOutro Nome: Avaliação Curriculum Vitae\nPonderação: 15%\nSubfatores: Sim\nSubfatores: \nNome: Acv = cotação x 0,15 Cotação a atribuir: Experiência inferior a 5 anos  0 Experiência entre 5 a 9 anos  0,075 Com experiência igual ou superior a 10 anos  0,15 com peso especifico de 100%\nPonderação : 100%; \n24 - CONDIÇÕES DO CONTRATO\nFaturação Eletrónica: Permitido\nObrigação de Subcontratação:\nCódigo da Obrigação de Subcontratação: Não é aplicável nenhuma obrigação de subcontratação.\n25 - COMPRA PÚBLICA ESTRATÉGICA\nCompra Pública Estratégica: Inexistência de contratação pública estratégica\n26 - INFORMAÇÕES ADICIONAIS\nContrato adequado para PME: Não\nCobertura ACP (Acordo dos Contratos Públicos da Organização Mundial do Comércio): Não\n27 - IDENTIFICAÇÃO E CONTACTOS DO ÓRGÃO DE RECURSOS ADMINISTRATIVOS\nDesignação: Tribunal Administrativo e Fiscal de Loulé\nEndereço: Rua Dr.ª Laura Ayres, n.º 4\nCódigo postal: 8100-810\nLocalidade: Loulé\nTelefone: 289400390\nFax: 213506010\nEndereço eletrónico: correio@loule.taf.mj.pt\nPrazo de interposição do recurso: 30 dias\n28 - IDENTIFICAÇÃO DO(S) AUTOR(ES) DE ANÚNCIO\nNome: João Paulo Pereira\nCargo: Administrador Executivo\n29 - ALTERAÇÃO\nMotivo da Alteração: Informações atualizadas\nIdentificador da Versão do Anúncio a Alterar: dc7ccc59-2c32-41a0-bb98-3c4b280d67bd-01\nIdentificador das Secções Alteradas do Anúncio Anterior: Condições de Apresentação\nDescrição das Alterações: Modificação do prazo para a apresentação de propostas\nAlteração dos Documentos do Concurso: Sim\nData de alteração dos documentos do concurso: 29-01-2026\n419949529",
    "nipc": "504497782",
    "distrito": "Faro",
    "concelho": "Faro",
    "freguesia": "União das Freguesias de Faro (Sé e São Pedro)",
    "site": "www.ambifaro.pt",
    "email": "geral@ambifaro.pt",
    "designacao_contrato": "Aquisição de serviços de gestão integral de contraordenações rodoviárias e sistema de cobranças",
    "descricao": "Aquisição de serviços de gestão integral de contraordenações rodoviárias e sistema de cobranças",
    "preco_base": "175.000,00 EUR",
    "prazo_execucao": "36 MESES",
    "prazo_apresentacao_propostas": "08-02-2026 23:59",
    "fundos_eu": "Não",
    "plataforma_eletronica": "ACIN",
    "url_procedimento": "https://www.acingov.pt",
    "autor_nome": "João Paulo Pereira",
    "autor_cargo": "Administrador Executivo"
  },
  {
    "numero_procedimento": "N/A",
    "entidade": "Município das Caldas da Rainha",
    "link": "https://diariodarepublica.pt/dr/detalhe/contrato-publico/2139-1029684224",
    "detalhes_completos": "1 - IDENTIFICAÇÃO E CONTACTOS DA ENTIDADE ADJUDICANTE\nDesignação da entidade adjudicante: Município das Caldas da Rainha\nNIPC: 501222634\nServiço/Órgão/Pessoa de contacto: Secção de Contratação Pública e Aprovisionamento\nEndereço: Praça 25 de Abril\nCódigo postal: 2500-110\nLocalidade: Caldas da Rainha\nPaís: Portugal\nNUT III: PT16B\nDistrito: Leiria\nConcelho: Caldas da Rainha\nFreguesia: União das Freguesias de Caldas da Rainha - Nossa Senhora do Pópulo, Coto e São Gregório\nTelefone: 262240000\nFax: 262839729\nEndereço da Entidade (URL): www.mcr.pt\nEndereço Eletrónico: contratacao.publica@mcr.pt\neDelivery Gateway (URL): https://www.acingov.pt\nFunção da Organização: Adquirente\nSubfunção da Organização: Organização cujo orçamento é utilizado para pagar o contrato; Organização que executa o pagamento; Organização que fornece informações adicionais sobre o processo de adjudicação; Organização que fornece mais informações sobre os prazos dos procedimentos de recurso; Organização que fornece acesso fora de linha aos documentos do concurso; Organização responsável pelo tratamento das propostas; Organização que recebe as propostas; Organização que trata os pedidos de participação; Organização que recebe pedidos de participação; Organização que fornece mais informações sobre os procedimentos de recurso; Organização que assina o contrato\nNorma jurídica da Entidade Adjudicante: Organismo de direito público\nÁrea de atividade da Autoridade Adjudicante: Serviços públicos das administrações públicas\n2 - JORNAL OFICIAL DA UNIÃO EUROPEIA\nO procedimento a que este anúncio diz respeito também é publicitado no Jornal Oficial da União Europeia? Não\n3 - AVISO\nModelo de Anúncio: Concurso público\nData de Envio do Anúncio: 29-01-2026\n5 - PROCESSO\nTipo de Procedimento: Concurso público\nPreço base do procedimento: Sim\nValor do preço base do procedimento: 57.360,00 EUR\nProcedimento com lotes? Não\n6 - OBJETO DO CONTRATO\nNúmero de referência interna: CP_01/2026-BS\nDesignação do contrato: Aquisição de Serviços de Análises Laboratoriais às Águas Termais\nDescrição: Aquisição de Serviços de Análises Laboratoriais às Águas Termais\nTipo de Contrato Principal: Aquisição de Serviços\nTipo de Contrato: Aquisição de Serviços\nClassificação CPV (Vocabulário Comum para os Contratos Públicos)\nObjeto principal\nVocabulário Principal: 98332000\nPreço base s/IVA: 57.360,00 EUR\n7 - INDICAÇÕES ADICIONAIS\nO contrato envolve aquisição conjunta (satisfação de várias entidades)? Não\nO contrato é adjudicado por uma central de compras? Não\n8 - TÉCNICAS\nO concurso destina-se à celebração de um acordo-quadro? Inexistência de acordo-quadro\nÉ utilizado um leilão eletrónico? Não\nÉ adotada uma fase de negociação? Não\nSistema de Aquisição Dinâmico: Inexistência de sistema de aquisição dinâmico\n9 - LOCAL DA EXECUÇÃO DO CONTRATO\nLOCAL DA EXECUÇÃO DO CONTRATO (PROCEDIMENTO)\nPaís: Portugal\nNUT III: PT16B\nLocalidade: Caldas da Rainha\nDistrito: Leiria\nConcelho: Caldas da Rainha\nFreguesia: União das Freguesias de Caldas da Rainha - Nossa Senhora do Pópulo, Coto e São Gregório\n10 - PRAZO DE EXECUÇÃO DO CONTRATO\nPrazo de execução do contrato: 3 ANOS\nPrevisão de renovações: Não\n11 - FUNDOS EU\nTêm fundos EU? Não\n12 - DOCUMENTOS DE HABILITAÇÃO\nHabilitação para o exercício da atividade profissional: Não\n13 - CONDIÇÕES DE APRESENTAÇÃO\nPlataforma eletrónica utilizada pela entidade adjudicante: ACIN\nURL para Apresentação: https://www.acingov.pt\nAdmissibilidade da apresentação de propostas variantes: Não autorizado\nPrazo para apresentação das propostas: 10-02-2026 23:59\nPrazo durante o qual os concorrentes são obrigados a manter as respetivas propostas: 66 dias a contar do termo do prazo para a apresentação das propostas\nIndicação de Subcontratação na Proposta: Inexistência de indicação de subcontratação\n14 - PRESTAÇÃO DE CAUÇÃO\nPrestação de caução: Não\n15 - FORNECIMENTO DAS PEÇAS DO CONCURSO, APRESENTAÇÃO DE PEDIDOS DE PARTICIPAÇÃO E APRESENTAÇÃO DAS PROPOSTAS\nLink para acesso às peças do concurso (URL): https://www.acingov.pt/acingovprod/2/zonaPublica/zona_publica_c/donwloadProcedurePiece/MTA1MjAzMg==\n20 - OUTROS REQUISITOS\nInformação sobre contratos reservados. Aplica-se a contratos reservados (54º-A)? Não\n21 - CRITÉRIO DE ADJUDICAÇÃO\nMultifator: Não\nMonofator:\nNome: Outros\nOutro nome: Fator Preço\n24 - CONDIÇÕES DO CONTRATO\nFaturação Eletrónica: Permitido\nObrigação de Subcontratação:\nCódigo da Obrigação de Subcontratação: Não é aplicável nenhuma obrigação de subcontratação.\n25 - COMPRA PÚBLICA ESTRATÉGICA\nCompra Pública Estratégica: Inexistência de contratação pública estratégica\n26 - INFORMAÇÕES ADICIONAIS\nContrato adequado para PME: Sim\nCobertura ACP (Acordo dos Contratos Públicos da Organização Mundial do Comércio): Não\n27 - IDENTIFICAÇÃO E CONTACTOS DO ÓRGÃO DE RECURSOS ADMINISTRATIVOS\nDesignação: Município das Caldas da Rainha\nEndereço: Praça 25 de Abril\nCódigo postal: 2500-110\nLocalidade: Caldas da Rainha\nTelefone: 262240000\nFax: 262839729\nEndereço eletrónico: contratacao.publica@mcr.pt\nPrazo de interposição do recurso: 10 dias\n28 - IDENTIFICAÇÃO DO(S) AUTOR(ES) DE ANÚNCIO\nNome: Vítor Manuel Calisto Marques\nCargo: Presidente da Câmara Municipal\n419949532",
    "nipc": "501222634",
    "distrito": "Leiria",
    "concelho": "Caldas da Rainha",
    "freguesia": "União das Freguesias de Caldas da Rainha - Nossa Senhora do Pópulo, Coto e São Gregório",
    "site": "www.mcr.pt",
    "email": "contratacao.publica@mcr.pt",
    "designacao_contrato": "Aquisição de Serviços de Análises Laboratoriais às Águas Termais",
    "descricao": "Aquisição de Serviços de Análises Laboratoriais às Águas Termais",
    "preco_base": "57.360,00 EUR",
    "prazo_execucao": "3 ANOS",
    "prazo_apresentacao_propostas": "10-02-2026 23:59",
    "fundos_eu": "Não",
    "plataforma_eletronica": "ACIN",
    "url_procedimento": "https://www.acingov.pt",
    "autor_nome": "Vítor Manuel Calisto Marques",
    "autor_cargo": "Presidente da Câmara Municipal"
  },
  {
    "numero_procedimento": "N/A",
    "entidade": "AnÃºncio de procedimento  n.Âº 2137/2026  -  DiÃ¡rio da RepÃºblica n.Âº 20/2026, SÃ©rie II de 2026-01-29",
    "link": "https://diariodarepublica.pt/dr/detalhe/contrato-publico/2137-1029821677"
  },
  {
    "numero_procedimento": "N/A",
    "entidade": "AnÃºncio de procedimento  n.Âº 2140/2026  -  DiÃ¡rio da RepÃºblica n.Âº 20/2026, SÃ©rie II de 2026-01-29",
    "link": "https://diariodarepublica.pt/dr/detalhe/contrato-publico/2140-1029821682"
  },
  {
    "numero_procedimento": "N/A",
    "entidade": "Entidade de Serviços Partilhados da Administração Pública, IP",
    "link": "https://diariodarepublica.pt/dr/detalhe/contrato-publico/2141-1029821686",
    "detalhes_completos": "Alteração do Anúncio de procedimento n.º 1004/2026, de 2026-01-16, com o ID 419948143\n1 - IDENTIFICAÇÃO E CONTACTOS DA ENTIDADE ADJUDICANTE\nDesignação da entidade adjudicante: Entidade de Serviços Partilhados da Administração Pública, IP\nNIPC: 510342191\nEndereço: Avenida Leite Vasconcelos 2, Alfragide,\nCódigo postal: 2614-502\nLocalidade: Amadora\nPaís: Portugal\nNUT III: PT170\nDistrito: Lisboa\nConcelho: Amadora\nFreguesia: Freguesia de Alfragide\nTelefone: 21 472 3100\nFax: 21 472 3100\nEndereço da Entidade (URL): https://www.espap.gov.pt/\nEndereço Eletrónico: gaj@espap.gov.pt\nFunção da Organização: Adquirente\nNorma jurídica da Entidade Adjudicante: Organismo de direito público\nÁrea de atividade da Autoridade Adjudicante: Serviços públicos das administrações públicas\n2 - JORNAL OFICIAL DA UNIÃO EUROPEIA\nO procedimento a que este anúncio diz respeito também é publicitado no Jornal Oficial da União Europeia? Não\n3 - AVISO\nModelo de Anúncio: Concurso público\nData de Envio do Anúncio: 29-01-2026\n5 - PROCESSO\nTipo de Procedimento: Concurso público\nPreço base do procedimento: Sim\nValor do preço base do procedimento: 178.264,23 EUR\nProcedimento com lotes? Não\n6 - OBJETO DO CONTRATO\nNúmero de referência interna: 2025_339\nDesignação do contrato: Consultadoria para implementação de metodologia de GPTI - PRR - Proj. 15\nDescrição: Serviços de consultadoria para implementação de metodologia de GPTI - Componente 17 do PRR - Proj 15 \nTipo de Contrato Principal: Aquisição de Serviços\nTipo de Contrato: Aquisição de Serviços\nClassificação CPV (Vocabulário Comum para os Contratos Públicos)\nObjeto principal\nVocabulário Principal: 72220000\nPreço base s/IVA: 178.264,23 EUR\n7 - INDICAÇÕES ADICIONAIS\nO contrato envolve aquisição conjunta (satisfação de várias entidades)? Não\nO contrato é adjudicado por uma central de compras? Não\n8 - TÉCNICAS\nO concurso destina-se à celebração de um acordo-quadro? Inexistência de acordo-quadro\nÉ utilizado um leilão eletrónico? Não\nÉ adotada uma fase de negociação? Não\nSistema de Aquisição Dinâmico: Inexistência de sistema de aquisição dinâmico\n9 - LOCAL DA EXECUÇÃO DO CONTRATO\nLOCAL DA EXECUÇÃO DO CONTRATO (PROCEDIMENTO)\nPaís: Portugal\nNUT III: PT170\nLocalidade: Alfragide\nDistrito: Lisboa\nConcelho: Amadora\nFreguesia: Freguesia de Alfragide\n10 - PRAZO DE EXECUÇÃO DO CONTRATO\nPrazo de execução do contrato: 5 MESES\nPrevisão de renovações: Não\n11 - FUNDOS EU\nTêm fundos EU? Sim\n12 - DOCUMENTOS DE HABILITAÇÃO\nHabilitação para o exercício da atividade profissional: Não\n13 - CONDIÇÕES DE APRESENTAÇÃO\nPlataforma eletrónica utilizada pela entidade adjudicante: ANOGOV\nURL para Apresentação: https://plataforma-sncp.espap.gov.pt/espap/faces/\nAdmissibilidade da apresentação de propostas variantes: Não autorizado\nPrazo para apresentação das propostas: 05-02-2026 23:59\nPrazo durante o qual os concorrentes são obrigados a manter as respetivas propostas: 66 dias a contar do termo do prazo para a apresentação das propostas\nApresentação de Catálogo Eletrónico: Não autorizado\nIndicação de Subcontratação na Proposta: A parte do contrato que o proponente tenciona subcontratar\n14 - PRESTAÇÃO DE CAUÇÃO\nPrestação de caução: Não\n15 - FORNECIMENTO DAS PEÇAS DO CONCURSO, APRESENTAÇÃO DE PEDIDOS DE PARTICIPAÇÃO E APRESENTAÇÃO DAS PROPOSTAS\nLink para acesso às peças do concurso (URL): https://plataforma-sncp.espap.gov.pt/espap/faces/app/acessoDocs.jsp?codigoAcesso=E0F2FjGm9kk5nFrRiosvx7GIVQJ8vvLqBk4z347m4zjF7fzbHB\n20 - OUTROS REQUISITOS\nInformação sobre contratos reservados. Aplica-se a contratos reservados (54º-A)? Não\n21 - CRITÉRIO DE ADJUDICAÇÃO\nMultifator: Não\nMonofator:\nNome: Preço\n24 - CONDIÇÕES DO CONTRATO\nFaturação Eletrónica: Permitido\nObrigação de Subcontratação:\nCódigo da Obrigação de Subcontratação: Não é aplicável nenhuma obrigação de subcontratação.\n25 - COMPRA PÚBLICA ESTRATÉGICA\nCompra Pública Estratégica: Inexistência de contratação pública estratégica\n26 - INFORMAÇÕES ADICIONAIS\nContrato adequado para PME: Sim\nCobertura ACP (Acordo dos Contratos Públicos da Organização Mundial do Comércio): Sim\n27 - IDENTIFICAÇÃO E CONTACTOS DO ÓRGÃO DE RECURSOS ADMINISTRATIVOS\nDesignação: Conselho Diretivo da ESPAP, I.P.\nEndereço: Av. Leite Vasconcelos 2\nCódigo postal: 2614-502\nLocalidade: Alfragide\nEndereço eletrónico: gaj@espap.gov.pt\n28 - IDENTIFICAÇÃO DO(S) AUTOR(ES) DE ANÚNCIO\nNome: Cátia Dâmaso\nCargo: Técnica Superior - Jurista\n29 - ALTERAÇÃO\nMotivo da Alteração: Correção pelo adquirente\nIdentificador da Versão do Anúncio a Alterar: 264b7c70-d3ab-4393-ab50-2ccc61597a13-01\nIdentificador das Secções Alteradas do Anúncio Anterior: Condições de Apresentação\nDescrição das Alterações: Prorrogação do prazo de apresentação de propostas\nAlteração dos Documentos do Concurso: Não\n419949470",
    "nipc": "510342191",
    "distrito": "Lisboa",
    "concelho": "Amadora",
    "freguesia": "Freguesia de Alfragide",
    "site": "https://www.espap.gov.pt/",
    "email": "gaj@espap.gov.pt",
    "designacao_contrato": "Consultadoria para implementação de metodologia de GPTI - PRR - Proj. 15",
    "descricao": "Serviços de consultadoria para implementação de metodologia de GPTI - Componente 17 do PRR - Proj 15",
    "preco_base": "178.264,23 EUR",
    "prazo_execucao": "5 MESES",
    "prazo_apresentacao_propostas": "05-02-2026 23:59",
    "fundos_eu": "Sim",
    "plataforma_eletronica": "ANOGOV",
    "url_procedimento": "https://plataforma-sncp.espap.gov.pt/espap/faces/",
    "autor_nome": "Cátia Dâmaso",
    "autor_cargo": "Técnica Superior - Jurista"
  }
]