[
  {
    "numero_procedimento": "N/A",
    "entidade": "AGERE- Empresa de Águas Efluentes e Resíduos de Braga, EM",
    "link": "https://diariodarepublica.pt/dr/detalhe/contrato-publico/33467-992879821",
    "detalhes_completos": "Alteração do Anúncio de procedimento n.º 32812/2025, de 2025-12-18, com o ID 419905276\n\n1 - IDENTIFICAÇÃO E CONTACTOS DA ENTIDADE ADJUDICANTE\nDesignação da entidade adjudicante: AGERE- Empresa de Águas Efluentes e Resíduos de Braga, EM\nNIPC: 504807692\nEndereço: Praça Conde de Agrolongo, 115\nCódigo postal: 4700-312\nLocalidade: Braga\nPaís: Portugal\nNUT III: PT112\nDistrito: Braga\nConcelho: Braga\nFreguesia: Todas\nTelefone: 253205000\nFax: 253205075\nEndereço da Entidade (URL): www.agere.pt\nEndereço Eletrónico: agere@agere.pt\neDelivery Gateway (URL): https://community.vortal.biz/public/\nFunção da Organização: Adquirente\nNorma jurídica da Entidade Adjudicante: Empresa pública\nÁrea de atividade da Entidade Adjudicante: Atividades relacionadas com a água\n\n2 - JORNAL OFICIAL DA UNIÃO EUROPEIA\nO procedimento a que este anúncio diz respeito também é publicitado no Jornal Oficial da União Europeia? Não\n\n3 - AVISO\nModelo de Anúncio: Concurso público\nData de Envio do Anúncio: 28-12-2025\n\n5 - PROCESSO\nTipo de Procedimento: Concurso público\nPreço base do procedimento: Sim\nValor do preço base do procedimento: 67.000,00 EUR\nProcedimento com lotes? Não\n\n6 - OBJETO DO CONTRATO\nNúmero de referência interna: CP DC 48/2025\nDesignação do contrato: PRESTAÇÃO DE SERVIÇOS DE TRABALHO TEMPORÁRIO\nDescrição: PRESTAÇÃO DE SERVIÇOS DE TRABALHO TEMPORÁRIO\nTipo de Contrato Principal: Aquisição de Serviços\nTipo de Contrato: Aquisição de Serviços\nClassificação CPV (Vocabulário Comum para os Contratos Públicos)\nObjeto principal\nVocabulário Principal: 79620000\nPreço base s/IVA: 67.000,00 EUR\n\n7 - INDICAÇÕES ADICIONAIS\nO contrato envolve aquisição conjunta (satisfação de várias entidades)? Não\nO contrato é adjudicado por uma central de compras? Não\n\n8 - TÉCNICAS\nO concurso destina-se à celebração de um acordo-quadro? Inexistência de acordo-quadro\nÉ utilizado um leilão eletrónico? Não\nÉ adotada uma fase de negociação? Não\nSistema de Aquisição Dinâmico: Inexistência de sistema de aquisição dinâmico\n\n9 - LOCAL DA EXECUÇÃO DO CONTRATO\nLOCAL DA EXECUÇÃO DO CONTRATO (PROCEDIMENTO)\nPaís: Portugal\nNUT III: PT112\nLocalidade: Braga\nDistrito: Braga\nConcelho: Braga\nFreguesia: União das Freguesias de Braga (São José de São Lázaro e São João do Souto)\n\n10 - PRAZO DE EXECUÇÃO DO CONTRATO\nPrazo de execução do contrato: 12 MESES\nPrevisão de renovações: Não\n\n11 - FUNDOS EU\nTêm fundos EU? Não\n\n12 - DOCUMENTOS DE HABILITAÇÃO\nHabilitação para o exercício da atividade profissional: Não\n\n13 - CONDIÇÕES DE APRESENTAÇÃO\nPlataforma eletrónica utilizada pela entidade adjudicante: VORTAL\nURL para Apresentação: https://community.vortal.biz/public/\nAdmissibilidade da apresentação de propostas variantes: Não autorizado\nPrazo para apresentação das propostas: 05-01-2026 17:00\nPrazo durante o qual os concorrentes são obrigados a manter as respetivas propostas: 66 dias a contar do termo do prazo para a apresentação das propostas\nIndicação de Subcontratação na Proposta: Inexistência de indicação de subcontratação\n\n14 - PRESTAÇÃO DE CAUÇÃO\nPrestação de caução: Não\n\n15 - FORNECIMENTO DAS PEÇAS DO CONCURSO, APRESENTAÇÃO DE PEDIDOS DE PARTICIPAÇÃO E APRESENTAÇÃO DAS PROPOSTAS\nLink para acesso às peças do concurso (URL): https://community.vortal.biz/Public/public-tender-documents/K1RGZlJ3SlRWb3JXWFRZTFVLK3BNb1IzWllubHNCZUU1dVVmK1FPU1grbm9NT21CWmlVSTc3NGtnRXY3U2JuL2RVL2pENlF2T2pyYVRkR0NhSVY5MGc9PStIXzcx\n\n20 - OUTROS REQUISITOS\nInformação sobre contratos reservados. Aplica-se a contratos reservados (54º-A)? Não\n\n21 - CRITÉRIO DE ADJUDICAÇÃO\nMultifator: Não\nMonofator:\nNome: Preço\n\n24 - CONDIÇÕES DO CONTRATO\nFaturação Eletrónica: Permitido\nObrigação de Subcontratação:\nCódigo da Obrigação de Subcontratação: Não é aplicável nenhuma obrigação de subcontratação.\n\n25 - COMPRA PÚBLICA ESTRATÉGICA\nCompra Pública Estratégica: Inexistência de contratação pública estratégica\n\n26 - INFORMAÇÕES ADICIONAIS\nContrato adequado para PME: Sim\nCobertura ACP (Acordo dos Contratos Públicos da Organização Mundial do Comércio): Não\n\n27 - IDENTIFICAÇÃO E CONTACTOS DO ÓRGÃO DE RECURSOS ADMINISTRATIVOS\nDesignação: Conselho de Administração da AGERE EM\nEndereço: Praça Conde de Agrolongo, 115\nCódigo postal: 4700-312\nLocalidade: Braga\nTelefone: +351 253205001\nFax: +351 253205075\nEndereço eletrónico: administracao@agere.pt\n\n28 - IDENTIFICAÇÃO DO(S) AUTOR(ES) DE ANÚNCIO\nNome: Engª Paula Campos\nCargo: Administradora Executiva\n\n29 - ALTERAÇÃO\nMotivo da Alteração: Informações agora disponíveis\nIdentificador da Versão do Anúncio a Alterar: d346137f-b97e-4dcb-8b4a-442c5ab124a4-01\nIdentificador das Secções Alteradas do Anúncio Anterior: Condições de Apresentação\nDescrição das Alterações: Alteração do Prazo de entrega\nAlteração dos Documentos do Concurso: Não\n419933091",
    "nipc": "504807692",
    "distrito": "Braga",
    "concelho": "Braga",
    "freguesia": "Todas",
    "site": "www.agere.pt",
    "email": "agere@agere.pt",
    "designacao_contrato": "PRESTAÇÃO DE SERVIÇOS DE TRABALHO TEMPORÁRIO",
    "descricao": "PRESTAÇÃO DE SERVIÇOS DE TRABALHO TEMPORÁRIO",
    "preco_base": "67.000,00 EUR",
    "prazo_execucao": "12 MESES",
    "prazo_apresentacao_propostas": "05-01-2026 17:00",
    "fundos_eu": "Não",
    "plataforma_eletronica": "VORTAL",
    "url_procedimento": "https://community.vortal.biz/public/",
    "autor_nome": "Engª Paula Campos",
    "autor_cargo": "Administradora Executiva"
  },
  {
    "numero_procedimento": "N/A",
    "entidade": "Unidade Local de Saúde de Santa Maria, EPE",
    "link": "https://diariodarepublica.pt/dr/detalhe/contrato-publico/33468-992879822",
    "detalhes_completos": "Alteração do Anúncio de procedimento n.º 31096/2025, de 2025-11-28, com o ID 419819757\n\n1 - IDENTIFICAÇÃO E CONTACTOS DA ENTIDADE ADJUDICANTE\nDesignação da entidade adjudicante: Unidade Local de Saúde de Santa Maria, EPE\nNIPC: 508481287\nEndereço: Avenida Prof. Egas Moniz\nCódigo postal: 1649-035\nLocalidade: Lisboa\nPaís: Portugal\nNUT III: PT170\nDistrito: Lisboa\nConcelho: Lisboa\nFreguesia: Freguesia de Alvalade - Lisboa\nTelefone: 217805330\nFax: 217805605\nEndereço da Entidade (URL): www.ulssm.min-saude.pt\nEndereço Eletrónico: compras@ulssm.min-saude.pt\neDelivery Gateway (URL): https://community.vortal.biz/public/\nFunção da Organização: Adquirente\nNorma jurídica da Entidade Adjudicante: Empresa pública\nÁrea de atividade da Autoridade Adjudicante: Saúde\n\n2 - JORNAL OFICIAL DA UNIÃO EUROPEIA\nO procedimento a que este anúncio diz respeito também é publicitado no Jornal Oficial da União Europeia? Sim\n\n3 - AVISO\nModelo de Anúncio: Concurso público\nData de Envio do Anúncio: 26-12-2025\n\n5 - PROCESSO\nTipo de Procedimento: Concurso público\nPreço base do procedimento: Sim\nValor do preço base do procedimento: 970.501,50 EUR\nProcedimento com lotes? Sim\nNº Máx. de Lotes Autorizado: 5\nNúmero máximo de lotes que podem ser adjudicados a um concorrente: 5\n\n6 - OBJETO DO CONTRATO\nNúmero de referência interna: 262A00032\nDesignação do contrato: 262A000032 - Aquisição de Kit's de tabuleiro para o Serviço de Cardiologia, durante os anos de 2026, 2027 e 2028\nDescrição: Aquisição de Kit's de tabuleiro para o Serviço de Cardiologia, durante os anos de 2026, 2027 e 2028\nOpções: Não\nTipo de Contrato Principal: Aquisição de Bens Móveis\nTipo de Contrato: Aquisição de Bens Móveis\nClassificação CPV (Vocabulário Comum para os Contratos Públicos)\nObjeto principal\nVocabulário Principal: 33190000\nPreço base s/IVA: 970.501,50 EUR\nLotes: \nNº: LOT-0001\nDescrição do Lote: Lote 1\nPreço base s/IVA: 664.200,00 EUR\nClassificação CPV (Vocabulário Comum para os Contratos Públicos)\nObjeto principal\nVocabulário Principal: 33190000\nNº: LOT-0002\nDescrição do Lote: Lote 2\nPreço base s/IVA: 23.940,00 EUR\nClassificação CPV (Vocabulário Comum para os Contratos Públicos)\nObjeto principal\nVocabulário Principal: 33190000\nNº: LOT-0003\nDescrição do Lote: Lote 3\nPreço base s/IVA: 106.590,00 EUR\nClassificação CPV (Vocabulário Comum para os Contratos Públicos)\nObjeto principal\nVocabulário Principal: 33190000\nNº: LOT-0004\nDescrição do Lote: Lote 4\nPreço base s/IVA: 116.707,50 EUR\nClassificação CPV (Vocabulário Comum para os Contratos Públicos)\nObjeto principal\nVocabulário Principal: 33190000\nNº: LOT-0005\nDescrição do Lote: Lote 5\nPreço base s/IVA: 59.064,00 EUR\nClassificação CPV (Vocabulário Comum para os Contratos Públicos)\nObjeto principal\nVocabulário Principal: 33190000\n\n7 - INDICAÇÕES ADICIONAIS\nO contrato envolve aquisição conjunta (satisfação de várias entidades)? Não\nO contrato é adjudicado por uma central de compras? Não\n\n8 - TÉCNICAS\nO concurso destina-se à celebração de um acordo-quadro? Inexistência de acordo-quadro\nÉ utilizado um leilão eletrónico? Não\nÉ adotada uma fase de negociação? Não\nSistema de Aquisição Dinâmico: Inexistência de sistema de aquisição dinâmico\n\n9 - LOCAL DA EXECUÇÃO DO CONTRATO\nLOCAL DA EXECUÇÃO DO CONTRATO (PROCEDIMENTO)\nPaís: Portugal\nNUT III: PT170\nLocalidade: Lisboa\nDistrito: Lisboa\nConcelho: Lisboa\nFreguesia: Freguesia de Alvalade - Lisboa\nLOCAL DA EXECUÇÃO DO CONTRATO (LOTE)\nIdentificador do Lote: LOT-0001; LOT-0002; LOT-0003; LOT-0004; LOT-0005\nPaís: Portugal\nNUT III: PT170\nLocalidade: Lisboa\nDistrito: Lisboa\nConcelho: Lisboa\nFreguesia: Freguesia de Alvalade - Lisboa\n\n10 - PRAZO DE EXECUÇÃO DO CONTRATO\nIdentificador do Lote: LOT-0001; LOT-0002; LOT-0003; LOT-0004; LOT-0005\nPrazo de execução do contrato: 3 ANOS\nPrevisão de renovações: Não\n\n11 - FUNDOS EU\nIdentificador do Lote: LOT-0001; LOT-0002; LOT-0003; LOT-0004; LOT-0005\nTêm fundos EU? Não\n\n12 - DOCUMENTOS DE HABILITAÇÃO\nHabilitação para o exercício da atividade profissional: Não\n\n13 - CONDIÇÕES DE APRESENTAÇÃO\nPlataforma eletrónica utilizada pela entidade adjudicante: VORTAL\nURL para Apresentação: https://community.vortal.biz/public/\nAdmissibilidade da apresentação de propostas variantes: Não autorizado\nPrazo para apresentação das propostas: 26-12-2025 23:59\nPrazo durante o qual os concorrentes são obrigados a manter as respetivas propostas: 66 dias a contar do termo do prazo para a apresentação das propostas\nApresentação de Catálogo Eletrónico: Permitido\nIndicação de Subcontratação na Proposta: Inexistência de indicação de subcontratação\n\n14 - PRESTAÇÃO DE CAUÇÃO\nPrestação de caução: Sim\nPercentagem: 5%\nDescrição da Garantia Exigida: conforme peças\n\n15 - FORNECIMENTO DAS PEÇAS DO CONCURSO, APRESENTAÇÃO DE PEDIDOS DE PARTICIPAÇÃO E APRESENTAÇÃO DAS PROPOSTAS\nLink para acesso às peças do concurso (URL): https://community.vortal.biz/Public/public-tender-documents/WW1keDBFbFlRN29iOENaOEQxQitHRTdvTDc3QnMyek5EWnhuL0lzTXJqRE9qY24rNlphT2M2WEc1b2tHUjVKZU5lbkJhOFdEdURHV296V0RnRTUrUWc9PXp4IUVX\n\n20 - OUTROS REQUISITOS\nIdentificador do Lote: LOT-0001; LOT-0002; LOT-0003; LOT-0004; LOT-0005\nInformação sobre contratos reservados. Aplica-se a contratos reservados (54º-A)? Não\n\n21 - CRITÉRIO DE ADJUDICAÇÃO\nO Critério de adjudicação é diferenciado por lote? Não\nMultifator: Não\nMonofator:\nNome: Preço\n\n24 - CONDIÇÕES DO CONTRATO\nIdentificador do Lote: LOT-0001; LOT-0002; LOT-0003; LOT-0004; LOT-0005\nFaturação Eletrónica: Permitido\nObrigação de Subcontratação:\nCódigo da Obrigação de Subcontratação: Não é aplicável nenhuma obrigação de subcontratação.\n\n25 - COMPRA PÚBLICA ESTRATÉGICA\nCompra Pública Estratégica: Inexistência de contratação pública estratégica\n\n26 - INFORMAÇÕES ADICIONAIS\nIdentificador do Lote: LOT-0001; LOT-0002; LOT-0003; LOT-0004; LOT-0005\nContrato adequado para PME: Sim\nCobertura ACP (Acordo dos Contratos Públicos da Organização Mundial do Comércio): Não\n\n27 - IDENTIFICAÇÃO E CONTACTOS DO ÓRGÃO DE RECURSOS ADMINISTRATIVOS\nDesignação: Conselho de Administração\nEndereço: Av. Prof. Egas Moniz\nCódigo postal: 1649-035\nLocalidade: Lisboa\nTelefone: +351 217805330\nFax: +351 217805330\nEndereço eletrónico: secretariado.ca@ulssm.min-saude.pt\n\n28 - IDENTIFICAÇÃO DO(S) AUTOR(ES) DE ANÚNCIO\nNome: Conceição Conde\nCargo: Ass técnica\n\n29 - ALTERAÇÃO\nMotivo da Alteração: Correção pelo adquirente\nIdentificador da Versão do Anúncio a Alterar: 7a9eaf5d-90ad-4af3-96f2-15ca725a9b44-01\nIdentificador das Secções Alteradas do Anúncio Anterior: Condições de Apresentação\nDescrição das Alterações: Prorrogação do prazo de apresentação de propostas\nAlteração dos Documentos do Concurso: Não\n419932346",
    "nipc": "508481287",
    "distrito": "Lisboa",
    "concelho": "Lisboa",
    "freguesia": "Freguesia de Alvalade - Lisboa",
    "site": "www.ulssm.min-saude.pt",
    "email": "compras@ulssm.min-saude.pt",
    "designacao_contrato": "262A000032 - Aquisição de Kit's de tabuleiro para o Serviço de Cardiologia, durante os anos de 2026, 2027 e 2028",
    "descricao": "Aquisição de Kit's de tabuleiro para o Serviço de Cardiologia, durante os anos de 2026, 2027 e 2028",
    "preco_base": "970.501,50 EUR",
    "prazo_execucao": "3 ANOS",
    "prazo_apresentacao_propostas": "26-12-2025 23:59",
    "fundos_eu": "Não",
    "plataforma_eletronica": "VORTAL",
    "url_procedimento": "https://community.vortal.biz/public/",
    "autor_nome": "Conceição Conde",
    "autor_cargo": "Ass técnica"
  },
  {
    "numero_procedimento": "N/A",
    "entidade": "Instituto de Informática, IP",
    "link": "https://diariodarepublica.pt/dr/detalhe/contrato-publico/33470-992879823",
    "detalhes_completos": "1 - IDENTIFICAÇÃO E CONTACTOS DA ENTIDADE ADJUDICANTE\nDesignação da entidade adjudicante: Instituto de Informática, IP\nNIPC: 504322915\nServiço/Órgão/Pessoa de contacto: Área de Contratação Pública\nEndereço: Avenida Professor Dr. Cavaco Silva, n.º 17, Edifício Ciência I\nCódigo postal: 2740-120\nLocalidade: Porto Salvo\nPaís: Portugal\nNUT III: PT170\nDistrito: Lisboa\nConcelho: Oeiras\nFreguesia: Freguesia de Porto Salvo\nTelefone: 214230000\nEndereço da Entidade (URL): http://www.seg-social.pt\nEndereço Eletrónico: ii-contratacao@seg-social.pt\neDelivery Gateway (URL): https://www.acingov.pt\nFunção da Organização: Adquirente\nNorma jurídica da Entidade Adjudicante: Organismo de direito público\nÁrea de atividade da Autoridade Adjudicante: Proteção social\n\n2 - JORNAL OFICIAL DA UNIÃO EUROPEIA\nO procedimento a que este anúncio diz respeito também é publicitado no Jornal Oficial da União Europeia? Sim\n\n3 - AVISO\nModelo de Anúncio: Concurso público\nData de Envio do Anúncio: 26-12-2025\n\n5 - PROCESSO\nTipo de Procedimento: Concurso público\nPreço base do procedimento: Sim\nValor do preço base do procedimento: 240.900,00 EUR\nProcedimento com lotes? Não\n\n6 - OBJETO DO CONTRATO\nNúmero de referência interna: 2325000288\nDesignação do contrato: 2325000288 - Serviços de Gestão e Administração de Soluções em Tecnologia Cloudera, no âmbito da solução Big Data\nDescrição: 2325000288 - Serviços de Gestão e Administração de Soluções em Tecnologia Cloudera, no âmbito da solução Big Data\nOpções: Não\nTipo de Contrato Principal: Aquisição de Serviços\nTipo de Contrato: Aquisição de Serviços\nClassificação CPV (Vocabulário Comum para os Contratos Públicos)\nObjeto principal\nVocabulário Principal: 72590000\nPreço base s/IVA: 240.900,00 EUR\n\n7 - INDICAÇÕES ADICIONAIS\nO contrato envolve aquisição conjunta (satisfação de várias entidades)? Não\nO contrato é adjudicado por uma central de compras? Não\n\n8 - TÉCNICAS\nO concurso destina-se à celebração de um acordo-quadro? Inexistência de acordo-quadro\nÉ utilizado um leilão eletrónico? Não\nÉ adotada uma fase de negociação? Não\nSistema de Aquisição Dinâmico: Inexistência de sistema de aquisição dinâmico\n\n9 - LOCAL DA EXECUÇÃO DO CONTRATO\nLOCAL DA EXECUÇÃO DO CONTRATO (PROCEDIMENTO)\nPaís: Portugal\nNUT III: PT170\nLocalidade: Freguesia de Porto Salvo\nDistrito: Lisboa\nConcelho: Oeiras\nFreguesia: Freguesia de Porto Salvo\n\n10 - PRAZO DE EXECUÇÃO DO CONTRATO\nPrazo de execução do contrato: 36 MESES\nPrevisão de renovações: Não\n\n11 - FUNDOS EU\nTêm fundos EU? Não\n\n12 - DOCUMENTOS DE HABILITAÇÃO\nHabilitação para o exercício da atividade profissional: Não\n\n13 - CONDIÇÕES DE APRESENTAÇÃO\nPlataforma eletrónica utilizada pela entidade adjudicante: ACIN\nURL para Apresentação: https://www.acingov.pt\nAdmissibilidade da apresentação de propostas variantes: Não autorizado\nPrazo para apresentação das propostas: 26-01-2026 23:59\nPrazo durante o qual os concorrentes são obrigados a manter as respetivas propostas: 66 dias a contar do termo do prazo para a apresentação das propostas\nApresentação de Catálogo Eletrónico: Não autorizado\nIndicação de Subcontratação na Proposta: Inexistência de indicação de subcontratação\n\n14 - PRESTAÇÃO DE CAUÇÃO\nPrestação de caução: Não\n\n15 - FORNECIMENTO DAS PEÇAS DO CONCURSO, APRESENTAÇÃO DE PEDIDOS DE PARTICIPAÇÃO E APRESENTAÇÃO DAS PROPOSTAS\nLink para acesso às peças do concurso (URL): https://www.acingov.pt/acingovprod/2/zonaPublica/zona_publica_c/donwloadProcedurePiece/MTAxMDUzMA==\n\n20 - OUTROS REQUISITOS\nInformação sobre contratos reservados. Aplica-se a contratos reservados (54º-A)? Não\n\n21 - CRITÉRIO DE ADJUDICAÇÃO\nMultifator: Sim\nFator: \nNome: Preço\nPonderação: 20%\nSubfatores: Não\nFator: \nNome: Outros\nOutro Nome: Mérito Técnico\nPonderação: 40%\nSubfatores: Não\nFator: \nNome: Outros\nOutro Nome: Competência e Experiência Profissional\nPonderação: 40%\nSubfatores: Não\n\n24 - CONDIÇÕES DO CONTRATO\nFaturação Eletrónica: Permitido\nObrigação de Subcontratação:\nCódigo da Obrigação de Subcontratação: Não é aplicável nenhuma obrigação de subcontratação.\n\n25 - COMPRA PÚBLICA ESTRATÉGICA\nCompra Pública Estratégica: Inexistência de contratação pública estratégica\n\n26 - INFORMAÇÕES ADICIONAIS\nContrato adequado para PME: Sim\nCobertura ACP (Acordo dos Contratos Públicos da Organização Mundial do Comércio): Não\n\n27 - IDENTIFICAÇÃO E CONTACTOS DO ÓRGÃO DE RECURSOS ADMINISTRATIVOS\nDesignação: Conselho Diretivo\nEndereço: Avenida Professor Dr. Cavaco Silva, n.º 17, Edifício Ciência I\nCódigo postal: 2740-120\nLocalidade: Porto Salvo\nTelefone: 214230000\nFax: 214230000\nEndereço eletrónico: ii-contratacao@seg-social.pt\nPrazo de interposição do recurso: 5 dias\n\n28 - IDENTIFICAÇÃO DO(S) AUTOR(ES) DE ANÚNCIO\nNome: Helga Patricia Fino da Silva Beirão Paulo\nCargo: Diretora do Departamento de Organização e Gestão de Pessoas\n419932573",
    "nipc": "504322915",
    "distrito": "Lisboa",
    "concelho": "Oeiras",
    "freguesia": "Freguesia de Porto Salvo",
    "site": "http://www.seg-social.pt",
    "email": "ii-contratacao@seg-social.pt",
    "designacao_contrato": "2325000288 - Serviços de Gestão e Administração de Soluções em Tecnologia Cloudera, no âmbito da solução Big Data",
    "descricao": "2325000288 - Serviços de Gestão e Administração de Soluções em Tecnologia Cloudera, no âmbito da solução Big Data",
    "preco_base": "240.900,00 EUR",
    "prazo_execucao": "36 MESES",
    "prazo_apresentacao_propostas": "26-01-2026 23:59",
    "fundos_eu": "Não",
    "plataforma_eletronica": "ACIN",
    "url_procedimento": "https://www.acingov.pt",
    "autor_nome": "Helga Patricia Fino da Silva Beirão Paulo",
    "autor_cargo": "Diretora do Departamento de Organização e Gestão de Pessoas"
  },
  {
    "numero_procedimento": "N/A",
    "entidade": "Município das Caldas da Rainha",
    "link": "https://diariodarepublica.pt/dr/detalhe/contrato-publico/33474-992879837",
    "detalhes_completos": "1 - IDENTIFICAÇÃO E CONTACTOS DA ENTIDADE ADJUDICANTE\nDesignação da entidade adjudicante: Município das Caldas da Rainha\nNIPC: 501222634\nEndereço: PRAÇA 25 DE ABRIL\nCódigo postal: 2500-110\nLocalidade: Leiria\nPaís: Portugal\nNUT III: PT16B\nDistrito: Leiria\nConcelho: Caldas da Rainha\nFreguesia: União das Freguesias de Caldas da Rainha - Nossa Senhora do Pópulo, Coto e São Gregório\nTelefone: 262240000\nFax: 262839729\nEndereço da Entidade (URL): www.mcr.pt\nEndereço Eletrónico: contratacao.publica@mcr.pt\neDelivery Gateway (URL): https://community.vortal.biz/public/\nFunção da Organização: Adquirente\nNorma jurídica da Entidade Adjudicante: Organismo de direito público\nÁrea de atividade da Autoridade Adjudicante: Serviços públicos das administrações públicas\n\n2 - JORNAL OFICIAL DA UNIÃO EUROPEIA\nO procedimento a que este anúncio diz respeito também é publicitado no Jornal Oficial da União Europeia? Não\n\n3 - AVISO\nModelo de Anúncio: Concurso público\nData de Envio do Anúncio: 29-12-2025\n\n5 - PROCESSO\nTipo de Procedimento: Concurso público\nPreço base do procedimento: Sim\nValor do preço base do procedimento: 225.000,00 EUR\nProcedimento com lotes? Não\n\n6 - OBJETO DO CONTRATO\nNúmero de referência interna: 2025-48A\nDesignação do contrato: Construção de Pontões (Estrada Principal - Casais da Bica)\nDescrição: Construção de Pontões (Estrada Principal - Casais da Bica)\nTipo de Contrato Principal: Empreitada de Obras Públicas\nTipo de Contrato: Empreitada de Obras Públicas\nClassificação CPV (Vocabulário Comum para os Contratos Públicos)\nObjeto principal\nVocabulário Principal: 45221100\nPreço base s/IVA: 225.000,00 EUR\n\n7 - INDICAÇÕES ADICIONAIS\nO contrato envolve aquisição conjunta (satisfação de várias entidades)? Não\nO contrato é adjudicado por uma central de compras? Não\n\n8 - TÉCNICAS\nO concurso destina-se à celebração de um acordo-quadro? Inexistência de acordo-quadro\nÉ utilizado um leilão eletrónico? Não\nÉ adotada uma fase de negociação? Não\nSistema de Aquisição Dinâmico: Inexistência de sistema de aquisição dinâmico\n\n9 - LOCAL DA EXECUÇÃO DO CONTRATO\nLOCAL DA EXECUÇÃO DO CONTRATO (PROCEDIMENTO)\nPaís: Portugal\nNUT III: PT16B\nLocalidade: Leiria\nDistrito: Leiria\nConcelho: Caldas da Rainha\nFreguesia: Freguesia de A dos Francos\n\n10 - PRAZO DE EXECUÇÃO DO CONTRATO\nPrazo de execução do contrato: 150 DIAS\nPrevisão de renovações: Não\n\n11 - FUNDOS EU\nTêm fundos EU? Não\n\n12 - DOCUMENTOS DE HABILITAÇÃO\nHabilitação para o exercício da atividade profissional: Sim\nTipo: Alvará\nDescrição: Detenção do alvará de empreiteiro de obras públicas, emitido pelo IMPIC ou certificado de empreiteiro de obras públicas que contenha a habilitação da 1.ª subcategoria da 2.ª categoria, em classe que cubra o preço total da proposta\n\n13 - CONDIÇÕES DE APRESENTAÇÃO\nPlataforma eletrónica utilizada pela entidade adjudicante: VORTAL\nURL para Apresentação: https://community.vortal.biz/public/\nAdmissibilidade da apresentação de propostas variantes: Não autorizado\nPrazo para apresentação das propostas: 19-01-2026 23:59\nPrazo durante o qual os concorrentes são obrigados a manter as respetivas propostas: 150 dias a contar do termo do prazo para a apresentação das propostas\nIndicação de Subcontratação na Proposta: Inexistência de indicação de subcontratação\n\n14 - PRESTAÇÃO DE CAUÇÃO\nPrestação de caução: Sim\nPercentagem: 5%\nDescrição da Garantia Exigida: A caução poderá ser apresentada por qualquer das modalidades previstas no artigo 90.º do Código dos Contratos Públicos\n\n15 - FORNECIMENTO DAS PEÇAS DO CONCURSO, APRESENTAÇÃO DE PEDIDOS DE PARTICIPAÇÃO E APRESENTAÇÃO DAS PROPOSTAS\nLink para acesso às peças do concurso (URL): https://community.vortal.biz/Public/public-tender-documents/TVhrNk4vN1hLRHBRbXg2REVUOElrdVJIK1JZWS82cEUzbjMvOHJqUUpFN0hSYzNwS2VmaE5uT1VZNGp5YjI3aG1IOFdLK1BTb0lJY3FteExMQnJSRlE9PXZOKExS\n\n20 - OUTROS REQUISITOS\nInformação sobre contratos reservados. Aplica-se a contratos reservados (54º-A)? Não\n\n21 - CRITÉRIO DE ADJUDICAÇÃO\nMultifator: Não\nMonofator:\nNome: Preço\n\n24 - CONDIÇÕES DO CONTRATO\nFaturação Eletrónica: Permitido\nObrigação de Subcontratação:\nCódigo da Obrigação de Subcontratação: Não é aplicável nenhuma obrigação de subcontratação.\n\n25 - COMPRA PÚBLICA ESTRATÉGICA\nCompra Pública Estratégica: Inexistência de contratação pública estratégica\n\n26 - INFORMAÇÕES ADICIONAIS\nContrato adequado para PME: Sim\nCobertura ACP (Acordo dos Contratos Públicos da Organização Mundial do Comércio): Não\n\n27 - IDENTIFICAÇÃO E CONTACTOS DO ÓRGÃO DE RECURSOS ADMINISTRATIVOS\nDesignação: Tribunal Administrativo e Fiscal de Leiria\nEndereço: Rua João Paulo II, CV RC\nCódigo postal: 2410-112\nLocalidade: Leiria\nTelefone: +351 244870600\nFax: +351 244870601\nEndereço eletrónico: leiria.taf@tribunais.org.pt\n\n28 - IDENTIFICAÇÃO DO(S) AUTOR(ES) DE ANÚNCIO\nNome: Vítor Manuel Calisto Marques\nCargo: Presidente Câmara Municipal\n419933391",
    "nipc": "501222634",
    "distrito": "Leiria",
    "concelho": "Caldas da Rainha",
    "freguesia": "União das Freguesias de Caldas da Rainha - Nossa Senhora do Pópulo, Coto e São Gregório",
    "site": "www.mcr.pt",
    "email": "contratacao.publica@mcr.pt",
    "designacao_contrato": "Construção de Pontões (Estrada Principal - Casais da Bica)",
    "descricao": "Construção de Pontões (Estrada Principal - Casais da Bica)",
    "preco_base": "225.000,00 EUR",
    "prazo_execucao": "150 DIAS",
    "prazo_apresentacao_propostas": "19-01-2026 23:59",
    "fundos_eu": "Não",
    "plataforma_eletronica": "VORTAL",
    "url_procedimento": "https://community.vortal.biz/public/",
    "autor_nome": "Vítor Manuel Calisto Marques",
    "autor_cargo": "Presidente Câmara Municipal"
  },
  {
    "numero_procedimento": "N/A",
    "entidade": "Direção-Geral do Livro, dos Arquivos e das Bibliotecas",
    "link": "https://diariodarepublica.pt/dr/detalhe/contrato-publico/33477-992879838",
    "detalhes_completos": "1 - IDENTIFICAÇÃO E CONTACTOS DA ENTIDADE ADJUDICANTE\nDesignação da entidade adjudicante: Direção-Geral do Livro, dos Arquivos e das Bibliotecas\nNIPC: 600084892\nEndereço: Edifício da Torre do Tombo, Alameda da Universidade\nCódigo postal: 1649-010\nLocalidade: Lisboa\nPaís: Portugal\nNUT III: PT170\nDistrito: Lisboa\nConcelho: Lisboa\nFreguesia: Todas\nTelefone: 210037100\nFax: 210037100\nEndereço da Entidade (URL): https://dglab.gov.pt/\nEndereço Eletrónico: secretariado@dglab.gov.pt\neDelivery Gateway (URL): https://community.vortal.biz/public/\nFunção da Organização: Adquirente\nNorma jurídica da Entidade Adjudicante: Organismo de direito público, controlado por uma autoridade da administração central\nÁrea de atividade da Autoridade Adjudicante: Serviços públicos das administrações públicas\n\n2 - JORNAL OFICIAL DA UNIÃO EUROPEIA\nO procedimento a que este anúncio diz respeito também é publicitado no Jornal Oficial da União Europeia? Não\n\n3 - AVISO\nModelo de Anúncio: Concurso público\nData de Envio do Anúncio: 29-12-2025\n\n5 - PROCESSO\nTipo de Procedimento: Concurso público\nPreço base do procedimento: Sim\nValor do preço base do procedimento: 142.900,00 EUR\nProcedimento com lotes? Não\n\n6 - OBJETO DO CONTRATO\nNúmero de referência interna: Concurso Público n.º 26/2025\nDesignação do contrato: Aquisição de serviços de digitalização de 700.000 imagens de documentos manuscritos do Arquivo Nacional da Torre do Tombo\nDescrição: Aquisição de serviços de digitalização de 700.000 imagens de documentos manuscritos do Arquivo Nacional da Torre do Tombo\nTipo de Contrato Principal: Aquisição de Serviços\nTipo de Contrato: Aquisição de Serviços\nClassificação CPV (Vocabulário Comum para os Contratos Públicos)\nObjeto principal\nVocabulário Principal: 92512000\nPreço base s/IVA: 142.900,00 EUR\n\n7 - INDICAÇÕES ADICIONAIS\nO contrato envolve aquisição conjunta (satisfação de várias entidades)? Não\nO contrato é adjudicado por uma central de compras? Não\n\n8 - TÉCNICAS\nO concurso destina-se à celebração de um acordo-quadro? Inexistência de acordo-quadro\nÉ utilizado um leilão eletrónico? Não\nÉ adotada uma fase de negociação? Não\nSistema de Aquisição Dinâmico: Inexistência de sistema de aquisição dinâmico\n\n9 - LOCAL DA EXECUÇÃO DO CONTRATO\nLOCAL DA EXECUÇÃO DO CONTRATO (PROCEDIMENTO)\nPaís: Portugal\nNUT III: PT170\nLocalidade: Lisboa\nDistrito: Lisboa\nConcelho: Lisboa\nFreguesia: Freguesia de Alvalade - Lisboa\n\n10 - PRAZO DE EXECUÇÃO DO CONTRATO\nPrazo de execução do contrato: 3 MESES\nPrevisão de renovações: Não\n\n11 - FUNDOS EU\nTêm fundos EU? Sim\n\n12 - DOCUMENTOS DE HABILITAÇÃO\nHabilitação para o exercício da atividade profissional: Não\n\n13 - CONDIÇÕES DE APRESENTAÇÃO\nPlataforma eletrónica utilizada pela entidade adjudicante: VORTAL\nURL para Apresentação: https://community.vortal.biz/public/\nAdmissibilidade da apresentação de propostas variantes: Não autorizado\nPrazo para apresentação das propostas: 04-01-2026 23:59\nPrazo durante o qual os concorrentes são obrigados a manter as respetivas propostas: 66 dias a contar do termo do prazo para a apresentação das propostas\nIndicação de Subcontratação na Proposta: Inexistência de indicação de subcontratação\n\n14 - PRESTAÇÃO DE CAUÇÃO\nPrestação de caução: Não\n\n15 - FORNECIMENTO DAS PEÇAS DO CONCURSO, APRESENTAÇÃO DE PEDIDOS DE PARTICIPAÇÃO E APRESENTAÇÃO DAS PROPOSTAS\nLink para acesso às peças do concurso (URL): https://community.vortal.biz/Public/public-tender-documents/V0RwMGgrQXpJL1FhaFNqa09rK3VCazhxQnZXTkljUm9QNFFiNzMrSThEY2tNNXdYYndxNzJoaHhXbEFHTnZLYlRNdzZLM21ucmJwMy92YURCRThkYmc9PVM0IXMj\n\n20 - OUTROS REQUISITOS\nInformação sobre contratos reservados. Aplica-se a contratos reservados (54º-A)? Não\n\n21 - CRITÉRIO DE ADJUDICAÇÃO\nMultifator: Não\nMonofator:\nNome: Outros\nOutro nome: Preço\n\n24 - CONDIÇÕES DO CONTRATO\nFaturação Eletrónica: Permitido\nObrigação de Subcontratação:\nCódigo da Obrigação de Subcontratação: Não é aplicável nenhuma obrigação de subcontratação.\n\n25 - COMPRA PÚBLICA ESTRATÉGICA\nCompra Pública Estratégica: Inexistência de contratação pública estratégica\n\n26 - INFORMAÇÕES ADICIONAIS\nContrato adequado para PME: Sim\nCobertura ACP (Acordo dos Contratos Públicos da Organização Mundial do Comércio): Não\n\n27 - IDENTIFICAÇÃO E CONTACTOS DO ÓRGÃO DE RECURSOS ADMINISTRATIVOS\nDesignação: Ministra da Cultura, Juventude e Desporto\nEndereço: Campus XXI, Avenida João XXI, n.º 63, 7.º piso\nCódigo postal: 1000-300\nLocalidade: Lisboa\nTelefone: +351 213927600\nFax: +351 213927600\nEndereço eletrónico: gabinete.mcjd@mcjd.gov.pt\n\n28 - IDENTIFICAÇÃO DO(S) AUTOR(ES) DE ANÚNCIO\nNome: Luís Filipe Reis dos Santos\nCargo: Diretor-Geral \n419933529",
    "nipc": "600084892",
    "distrito": "Lisboa",
    "concelho": "Lisboa",
    "freguesia": "Todas",
    "site": "https://dglab.gov.pt/",
    "email": "secretariado@dglab.gov.pt",
    "designacao_contrato": "Aquisição de serviços de digitalização de 700.000 imagens de documentos manuscritos do Arquivo Nacional da Torre do Tombo",
    "descricao": "Aquisição de serviços de digitalização de 700.000 imagens de documentos manuscritos do Arquivo Nacional da Torre do Tombo",
    "preco_base": "142.900,00 EUR",
    "prazo_execucao": "3 MESES",
    "prazo_apresentacao_propostas": "04-01-2026 23:59",
    "fundos_eu": "Sim",
    "plataforma_eletronica": "VORTAL",
    "url_procedimento": "https://community.vortal.biz/public/",
    "autor_nome": "Luís Filipe Reis dos Santos",
    "autor_cargo": "Diretor-Geral"
  },
  {
    "numero_procedimento": "N/A",
    "entidade": "Secretaria Regional de Agricultura e Pescas",
    "link": "https://diariodarepublica.pt/dr/detalhe/contrato-publico/33481-992879839",
    "detalhes_completos": "1 - IDENTIFICAÇÃO E CONTACTOS DA ENTIDADE ADJUDICANTE\nDesignação da entidade adjudicante: Secretaria Regional de Agricultura e Pescas\nNIPC: 671001299\nServiço/Órgão/Pessoa de contacto: Direção de Serviços de Apoio à Gestão\nEndereço: Rua Dr. Pestana Júnior, nº 6 - 5º Andar\nCódigo postal: 9064-506\nLocalidade: Funchal\nPaís: Portugal\nNUT III: PT300\nDistrito: Região Autónoma da Madeira\nConcelho: Todos\nFreguesia: Todas\nTelefone: 291145600\nFax: 291225112\nEndereço da Entidade (URL): www.madeira.gov.pt\nEndereço Eletrónico: gabinete.srap@madeira.gov.pt\neDelivery Gateway (URL): https://www.acingov.pt\nFunção da Organização: Adquirente\nSubfunção da Organização: Organização que recebe as propostas\nNorma jurídica da Entidade Adjudicante: Organismo de direito público\nÁrea de atividade da Autoridade Adjudicante: Serviços públicos das administrações públicas\n\n2 - JORNAL OFICIAL DA UNIÃO EUROPEIA\nO procedimento a que este anúncio diz respeito também é publicitado no Jornal Oficial da União Europeia? Não\n\n3 - AVISO\nModelo de Anúncio: Concurso público\nData de Envio do Anúncio: 29-12-2025\n\n5 - PROCESSO\nTipo de Procedimento: Concurso público\nPreço base do procedimento: Sim\nValor do preço base do procedimento: 34.587,71 EUR\nProcedimento com lotes? Não\n\n6 - OBJETO DO CONTRATO\nNúmero de referência interna: CP N.º19/SRAP-DRA/2025\nDesignação do contrato: Aquisição de quatro (4) máquinas lavar pavimentos para a Rede de Centros de Abastecimento Agrícola da RAM\nDescrição: Aquisição de quatro (4) máquinas lavar pavimentos para a Rede de Centros de Abastecimento Agrícola da RAM\nTipo de Contrato Principal: Aquisição de Bens Móveis\nTipo de Contrato: Aquisição de Bens Móveis\nClassificação CPV (Vocabulário Comum para os Contratos Públicos)\nObjeto principal\nVocabulário Principal: 39713410\nPreço base s/IVA: 34.587,71 EUR\n\n7 - INDICAÇÕES ADICIONAIS\nO contrato envolve aquisição conjunta (satisfação de várias entidades)? Não\nO contrato é adjudicado por uma central de compras? Não\n\n8 - TÉCNICAS\nO concurso destina-se à celebração de um acordo-quadro? Inexistência de acordo-quadro\nÉ utilizado um leilão eletrónico? Não\nÉ adotada uma fase de negociação? Não\nSistema de Aquisição Dinâmico: Inexistência de sistema de aquisição dinâmico\n\n9 - LOCAL DA EXECUÇÃO DO CONTRATO\nLOCAL DA EXECUÇÃO DO CONTRATO (PROCEDIMENTO)\nPaís: Portugal\nNUT III: PT300\nLocalidade: Freguesia de São Martinho - Funchal\nDistrito: Região Autónoma da Madeira\nConcelho: Funchal\nFreguesia: Freguesia de São Martinho - Funchal\n\n10 - PRAZO DE EXECUÇÃO DO CONTRATO\nPrazo de execução do contrato: 35 DIAS\nPrevisão de renovações: Não\n\n11 - FUNDOS EU\nTêm fundos EU? Não\n\n12 - DOCUMENTOS DE HABILITAÇÃO\nHabilitação para o exercício da atividade profissional: Não\n\n13 - CONDIÇÕES DE APRESENTAÇÃO\nPlataforma eletrónica utilizada pela entidade adjudicante: ACIN\nURL para Apresentação: https://www.acingov.pt\nAdmissibilidade da apresentação de propostas variantes: Não autorizado\nPrazo para apresentação das propostas: 19-01-2026 17:00\nPrazo durante o qual os concorrentes são obrigados a manter as respetivas propostas: 120 dias a contar do termo do prazo para a apresentação das propostas\nIndicação de Subcontratação na Proposta: Inexistência de indicação de subcontratação\n\n14 - PRESTAÇÃO DE CAUÇÃO\nPrestação de caução: Não\n\n15 - FORNECIMENTO DAS PEÇAS DO CONCURSO, APRESENTAÇÃO DE PEDIDOS DE PARTICIPAÇÃO E APRESENTAÇÃO DAS PROPOSTAS\nLink para acesso às peças do concurso (URL): https://www.acingov.pt/acingovprod/2/zonaPublica/zona_publica_c/donwloadProcedurePiece/MTAwOTM4Mg==\n\n20 - OUTROS REQUISITOS\nInformação sobre contratos reservados. Aplica-se a contratos reservados (54º-A)? Não\n\n21 - CRITÉRIO DE ADJUDICAÇÃO\nMultifator: Não\nMonofator:\nNome: Preço\n\n24 - CONDIÇÕES DO CONTRATO\nFaturação Eletrónica: Permitido\nObrigação de Subcontratação:\nCódigo da Obrigação de Subcontratação: Não é aplicável nenhuma obrigação de subcontratação.\n\n25 - COMPRA PÚBLICA ESTRATÉGICA\nCompra Pública Estratégica: Inexistência de contratação pública estratégica\n\n26 - INFORMAÇÕES ADICIONAIS\nContrato adequado para PME: Não\nCobertura ACP (Acordo dos Contratos Públicos da Organização Mundial do Comércio): Não\n\n27 - IDENTIFICAÇÃO E CONTACTOS DO ÓRGÃO DE RECURSOS ADMINISTRATIVOS\nDesignação: Secretário Regional de Agricultura e Pescas\nEndereço: Rua Dr. Pestana Júnior, nº 6 - 5º Andar\nCódigo postal: 9064-506\nLocalidade: Funchal\nTelefone: 291145600\nFax: \nEndereço eletrónico: gabinete.srap@madeira.gov.pt\nPrazo de interposição do recurso: 30 dias\n\n28 - IDENTIFICAÇÃO DO(S) AUTOR(ES) DE ANÚNCIO\nNome: Nuno Dinarte de Gouveia Maciel\nCargo: Secretário Regional de Agricultura e Pescas\n419933748",
    "nipc": "671001299",
    "distrito": "Região Autónoma da Madeira",
    "concelho": "Todos",
    "freguesia": "Todas",
    "site": "www.madeira.gov.pt",
    "email": "gabinete.srap@madeira.gov.pt",
    "designacao_contrato": "Aquisição de quatro (4) máquinas lavar pavimentos para a Rede de Centros de Abastecimento Agrícola da RAM",
    "descricao": "Aquisição de quatro (4) máquinas lavar pavimentos para a Rede de Centros de Abastecimento Agrícola da RAM",
    "preco_base": "34.587,71 EUR",
    "prazo_execucao": "35 DIAS",
    "prazo_apresentacao_propostas": "19-01-2026 17:00",
    "fundos_eu": "Não",
    "plataforma_eletronica": "ACIN",
    "url_procedimento": "https://www.acingov.pt",
    "autor_nome": "Nuno Dinarte de Gouveia Maciel",
    "autor_cargo": "Secretário Regional de Agricultura e Pescas"
  },
  {
    "numero_procedimento": "N/A",
    "entidade": "CRPG - Centro de Reabilitação Profissional",
    "link": "https://diariodarepublica.pt/dr/detalhe/contrato-publico/33483-992879840",
    "detalhes_completos": "1 - IDENTIFICAÇÃO E CONTACTOS DA ENTIDADE ADJUDICANTE\nDesignação da entidade adjudicante: CRPG - Centro de Reabilitação Profissional\nNIPC: 504791834\nServiço/Órgão/Pessoa de contacto: Serviços Financeiros\nEndereço: Av. João Paulo II, 961\nCódigo postal: 4410-406\nLocalidade: Vila Nova de Gaia\nPaís: Portugal\nNUT III: PT11A\nDistrito: Porto\nConcelho: Vila Nova de Gaia\nFreguesia: Freguesia de Arcozelo - Vila Nova de Gaia\nTelefone: 227537700\nFax: 227537700\nEndereço da Entidade (URL): www.crpg.pt\nEndereço Eletrónico: compras@crpg.pt\neDelivery Gateway (URL): https://www.acingov.pt\nFunção da Organização: Adquirente\nSubfunção da Organização: Organização que executa o pagamento; Organização que fornece informações adicionais sobre o processo de adjudicação; Organização responsável pelo tratamento das propostas; Organização que recebe as propostas; Organização que assina o contrato\nNorma jurídica da Entidade Adjudicante: Organismo de direito público\nÁrea de atividade da Autoridade Adjudicante: Educação\n\n2 - JORNAL OFICIAL DA UNIÃO EUROPEIA\nO procedimento a que este anúncio diz respeito também é publicitado no Jornal Oficial da União Europeia? Não\n\n3 - AVISO\nModelo de Anúncio: Concurso público\nData de Envio do Anúncio: 29-12-2025\n\n5 - PROCESSO\nTipo de Procedimento: Concurso público\nPreço base do procedimento: Sim\nValor do preço base do procedimento: 220.980,00 EUR\nProcedimento com lotes? Sim\nNº Máx. de Lotes Autorizado: 2\nNúmero máximo de lotes que podem ser adjudicados a um concorrente: 2\n\n6 - OBJETO DO CONTRATO\nNúmero de referência interna: PO.003.2025_18\nDesignação do contrato: Aquisição de equipamento informático no âmbito do PRR\nDescrição: Aquisição de equipamento informático no âmbito do PRR\nTipo de Contrato Principal: Aquisição de Bens Móveis\nTipo de Contrato: Aquisição de Bens Móveis\nClassificação CPV (Vocabulário Comum para os Contratos Públicos)\nObjeto principal\nVocabulário Principal: 30230000\nPreço base s/IVA: 220.980,00 EUR\nLotes: \nNº: LOT-0001\nDescrição do Lote: Computadores All-in-one e desktop\nPreço base s/IVA: 91.050,00 EUR\nClassificação CPV (Vocabulário Comum para os Contratos Públicos)\nObjeto principal\nVocabulário Principal: 30230000\nNº: LOT-0002\nDescrição do Lote: Computadores portáteis e híbridos\nPreço base s/IVA: 129.930,00 EUR\nClassificação CPV (Vocabulário Comum para os Contratos Públicos)\nObjeto principal\nVocabulário Principal: 30230000\n\n7 - INDICAÇÕES ADICIONAIS\nO contrato envolve aquisição conjunta (satisfação de várias entidades)? Não\nO contrato é adjudicado por uma central de compras? Não\n\n8 - TÉCNICAS\nO concurso destina-se à celebração de um acordo-quadro? Inexistência de acordo-quadro\nÉ utilizado um leilão eletrónico? Não\nÉ adotada uma fase de negociação? Não\nSistema de Aquisição Dinâmico: Inexistência de sistema de aquisição dinâmico\n\n9 - LOCAL DA EXECUÇÃO DO CONTRATO\nLOCAL DA EXECUÇÃO DO CONTRATO (PROCEDIMENTO)\nPaís: Portugal\nNUT III: PT11A\nLocalidade: V. N. Gaia\nDistrito: Porto\nConcelho: Vila Nova de Gaia\nFreguesia: Todas\nLOCAL DA EXECUÇÃO DO CONTRATO (LOTE)\nIdentificador do Lote: LOT-0001; LOT-0002\nPaís: Portugal\nNUT III: PT11A\nLocalidade: V. N. Gaia\nDistrito: Porto\nConcelho: Vila Nova de Gaia\nFreguesia: Todas\n\n10 - PRAZO DE EXECUÇÃO DO CONTRATO\nIdentificador do Lote: LOT-0001; LOT-0002\nPrazo de execução do contrato: 60 DIAS\nPrevisão de renovações: Não\n\n11 - FUNDOS EU\nIdentificador do Lote: LOT-0001; LOT-0002\nTêm fundos EU? Sim\n\n12 - DOCUMENTOS DE HABILITAÇÃO\nHabilitação para o exercício da atividade profissional: Não\n\n13 - CONDIÇÕES DE APRESENTAÇÃO\nPlataforma eletrónica utilizada pela entidade adjudicante: ACIN\nURL para Apresentação: https://www.acingov.pt\nAdmissibilidade da apresentação de propostas variantes: Não autorizado\nPrazo para apresentação das propostas: 12-01-2026 17:00\nPrazo durante o qual os concorrentes são obrigados a manter as respetivas propostas: 90 dias a contar do termo do prazo para a apresentação das propostas\nIndicação de Subcontratação na Proposta: Inexistência de indicação de subcontratação\n\n14 - PRESTAÇÃO DE CAUÇÃO\nPrestação de caução: Não\n\n15 - FORNECIMENTO DAS PEÇAS DO CONCURSO, APRESENTAÇÃO DE PEDIDOS DE PARTICIPAÇÃO E APRESENTAÇÃO DAS PROPOSTAS\nLink para acesso às peças do concurso (URL): https://www.acingov.pt/acingovprod/2/zonaPublica/zona_publica_c/donwloadProcedurePiece/MTAwOTEwNA==\n\n20 - OUTROS REQUISITOS\nIdentificador do Lote: LOT-0001; LOT-0002\nInformação sobre contratos reservados. Aplica-se a contratos reservados (54º-A)? Não\n\n21 - CRITÉRIO DE ADJUDICAÇÃO\nO Critério de adjudicação é diferenciado por lote? Não\nMultifator: Não\nMonofator:\nNome: Preço\n\n24 - CONDIÇÕES DO CONTRATO\nIdentificador do Lote: LOT-0001; LOT-0002\nFaturação Eletrónica: Permitido\nObrigação de Subcontratação:\nCódigo da Obrigação de Subcontratação: Não é aplicável nenhuma obrigação de subcontratação.\n\n25 - COMPRA PÚBLICA ESTRATÉGICA\nCompra Pública Estratégica: Inexistência de contratação pública estratégica\n\n26 - INFORMAÇÕES ADICIONAIS\nIdentificador do Lote: LOT-0001; LOT-0002\nContrato adequado para PME: Sim\nCobertura ACP (Acordo dos Contratos Públicos da Organização Mundial do Comércio): Não\n\n27 - IDENTIFICAÇÃO E CONTACTOS DO ÓRGÃO DE RECURSOS ADMINISTRATIVOS\nDesignação: Conselho de Administração\nEndereço: Av. João Paulo II\nCódigo postal: 4410-406\nLocalidade: Arcozelo VNG\nTelefone: 227537700\nFax: 227537700\nEndereço eletrónico: compras@crpg.pt\n\n28 - IDENTIFICAÇÃO DO(S) AUTOR(ES) DE ANÚNCIO\nNome: Luísa Mónica Bourbon Salazar\nCargo: Diretora\n419934088",
    "nipc": "504791834",
    "distrito": "Porto",
    "concelho": "Vila Nova de Gaia",
    "freguesia": "Freguesia de Arcozelo - Vila Nova de Gaia",
    "site": "www.crpg.pt",
    "email": "compras@crpg.pt",
    "designacao_contrato": "Aquisição de equipamento informático no âmbito do PRR",
    "descricao": "Aquisição de equipamento informático no âmbito do PRR",
    "preco_base": "220.980,00 EUR",
    "prazo_execucao": "60 DIAS",
    "prazo_apresentacao_propostas": "12-01-2026 17:00",
    "fundos_eu": "Sim",
    "plataforma_eletronica": "ACIN",
    "url_procedimento": "https://www.acingov.pt",
    "autor_nome": "Luísa Mónica Bourbon Salazar",
    "autor_cargo": "Diretora"
  },
  {
    "numero_procedimento": "N/A",
    "entidade": "Unidade Local de Saúde de Santo António, EPE",
    "link": "https://diariodarepublica.pt/dr/detalhe/contrato-publico/33471-992879841",
    "detalhes_completos": "1 - IDENTIFICAÇÃO E CONTACTOS DA ENTIDADE ADJUDICANTE\nDesignação da entidade adjudicante: Unidade Local de Saúde de Santo António, EPE\nNIPC: 517392259\nEndereço: Largo Prof. Abel Salazar\nCódigo postal: 4099-001\nLocalidade: Área Metropolitana do Porto\nPaís: Portugal\nNUT III: PT11A\nDistrito: Porto\nConcelho: Porto\nFreguesia: Todas\nTelefone: 222077500\nFax: 223320318\nEndereço da Entidade (URL): www.hgsa.pt\nEndereço Eletrónico: helpdesk.b-on@hgsa.min-saude.pt\neDelivery Gateway (URL): https://community.vortal.biz/public/\nFunção da Organização: Adquirente\nNorma jurídica da Entidade Adjudicante: Organismo de direito público\nÁrea de atividade da Autoridade Adjudicante: Saúde\n\n2 - JORNAL OFICIAL DA UNIÃO EUROPEIA\nO procedimento a que este anúncio diz respeito também é publicitado no Jornal Oficial da União Europeia? Não\n\n3 - AVISO\nModelo de Anúncio: Concurso público urgente\nData de Envio do Anúncio: 29-12-2025 10:53:00\n\n5 - PROCESSO\nTipo de Procedimento: Concurso público\nPreço base do procedimento: Sim\nValor do preço base do procedimento: 146.300,00 EUR\nProcedimento com lotes? Não\n\n6 - OBJETO DO CONTRATO\nNúmero de referência interna: CPU/1626/2025\nDesignação do contrato: Concurso Público Urgente nº 1626/2025: Aquisição de 200 (Duzentos) Computadores para ULS de Santo António, EPE\nDescrição: Concurso Público Urgente nº 1626/2025: Aquisição de 200 (Duzentos) Computadores para ULS de Santo António, EPE\nTipo de Contrato Principal: Aquisição de Bens Móveis\nTipo de Contrato: Aquisição de Bens Móveis\nClassificação CPV (Vocabulário Comum para os Contratos Públicos)\nObjeto principal\nVocabulário Principal: 30200000\nPreço base s/IVA: 146.300,00 EUR\n\n7 - INDICAÇÕES ADICIONAIS\nO contrato envolve aquisição conjunta (satisfação de várias entidades)? Não\nO contrato é adjudicado por uma central de compras? Não\n\n8 - TÉCNICAS\nO concurso destina-se à celebração de um acordo-quadro? Inexistência de acordo-quadro\nÉ utilizado um leilão eletrónico? Não\nÉ adotada uma fase de negociação? Não\nSistema de Aquisição Dinâmico: Inexistência de sistema de aquisição dinâmico\n\n9 - LOCAL DA EXECUÇÃO DO CONTRATO\nLOCAL DA EXECUÇÃO DO CONTRATO (PROCEDIMENTO)\nPaís: Portugal\nNUT III: PT11A\nLocalidade: Área Metropolitana do Porto\nDistrito: Porto\nConcelho: Porto\nFreguesia: Todas\n\n10 - PRAZO DE EXECUÇÃO DO CONTRATO\nPrazo de execução do contrato: 90 DIAS\nPrevisão de renovações: Não\n\n11 - FUNDOS EU\nTêm fundos EU? Não\n\n12 - DOCUMENTOS DE HABILITAÇÃO\nHabilitação para o exercício da atividade profissional: Não\n\n13 - CONDIÇÕES DE APRESENTAÇÃO\nPlataforma eletrónica utilizada pela entidade adjudicante: VORTAL\nURL para Apresentação: https://community.vortal.biz/public/\nAdmissibilidade da apresentação de propostas variantes: Não autorizado\nPrazo para apresentação das propostas: 02-01-2026 23:59\nPrazo durante o qual os concorrentes são obrigados a manter as respetivas propostas: 10 dias a contar do termo do prazo para a apresentação das propostas\nIndicação de Subcontratação na Proposta: Inexistência de indicação de subcontratação\n\n14 - PRESTAÇÃO DE CAUÇÃO\nPrestação de caução: Não\n\n15 - FORNECIMENTO DAS PEÇAS DO CONCURSO, APRESENTAÇÃO DE PEDIDOS DE PARTICIPAÇÃO E APRESENTAÇÃO DAS PROPOSTAS\nLink para acesso às peças do concurso (URL): https://community.vortal.biz/Public/public-tender-documents/allQVk9mdmJyR0tqMm4rbzZDd1VXQ3lWMUNqMUhuZS9CaU1kdTVXTGFLRGJHRUpkZGppVjNFYW5ieFYwQ0t2WFdtUEhKTTBwaHZPWU5UL0kzVGh5SEE9PXI4ckpT\n\n20 - OUTROS REQUISITOS\nInformação sobre contratos reservados. Aplica-se a contratos reservados (54º-A)? Não\n\n21 - CRITÉRIO DE ADJUDICAÇÃO\nMultifator: Não\nMonofator:\nNome: Outros\nOutro nome: Preço\n\n24 - CONDIÇÕES DO CONTRATO\nFaturação Eletrónica: Permitido\nObrigação de Subcontratação:\nCódigo da Obrigação de Subcontratação: Não é aplicável nenhuma obrigação de subcontratação.\n\n25 - COMPRA PÚBLICA ESTRATÉGICA\nCompra Pública Estratégica: Inexistência de contratação pública estratégica\n\n26 - INFORMAÇÕES ADICIONAIS\nContrato adequado para PME: Sim\nCobertura ACP (Acordo dos Contratos Públicos da Organização Mundial do Comércio): Não\n\n27 - IDENTIFICAÇÃO E CONTACTOS DO ÓRGÃO DE RECURSOS ADMINISTRATIVOS\nDesignação: Conselho de Administração da ULS Santo António, EPE\nEndereço: Largo do Professor Abel Salazar\nCódigo postal: 4099-001\nLocalidade: Porto\nTelefone: +351 22277529\nFax: +351 223320318\nEndereço eletrónico: sandralobao.aprov@ulssa.min-saude.pt\n\n28 - IDENTIFICAÇÃO DO(S) AUTOR(ES) DE ANÚNCIO\nNome: Sandra Lobão\nCargo: Assistente Técnica\n419933756",
    "nipc": "517392259",
    "distrito": "Porto",
    "concelho": "Porto",
    "freguesia": "Todas",
    "site": "www.hgsa.pt",
    "email": "helpdesk.b-on@hgsa.min-saude.pt",
    "designacao_contrato": "Concurso Público Urgente nº 1626/2025: Aquisição de 200 (Duzentos) Computadores para ULS de Santo António, EPE",
    "descricao": "Concurso Público Urgente nº 1626/2025: Aquisição de 200 (Duzentos) Computadores para ULS de Santo António, EPE",
    "preco_base": "146.300,00 EUR",
    "prazo_execucao": "90 DIAS",
    "prazo_apresentacao_propostas": "02-01-2026 23:59",
    "fundos_eu": "Não",
    "plataforma_eletronica": "VORTAL",
    "url_procedimento": "https://community.vortal.biz/public/",
    "autor_nome": "Sandra Lobão",
    "autor_cargo": "Assistente Técnica"
  },
  {
    "numero_procedimento": "N/A",
    "entidade": "AGERE- Empresa de Águas Efluentes e Resíduos de Braga, EM",
    "link": "https://diariodarepublica.pt/dr/detalhe/contrato-publico/33486-992879842",
    "detalhes_completos": "1 - IDENTIFICAÇÃO E CONTACTOS DA ENTIDADE ADJUDICANTE\nDesignação da entidade adjudicante: AGERE- Empresa de Águas Efluentes e Resíduos de Braga, EM\nNIPC: 504807692\nEndereço: Praça Conde de Agrolongo, 115\nCódigo postal: 4700-312\nLocalidade: Braga\nPaís: Portugal\nNUT III: PT112\nDistrito: Braga\nConcelho: Braga\nFreguesia: Todas\nTelefone: 253205000\nFax: 253205075\nEndereço da Entidade (URL): www.agere.pt\nEndereço Eletrónico: agere@agere.pt\neDelivery Gateway (URL): https://community.vortal.biz/public/\nFunção da Organização: Adquirente\nNorma jurídica da Entidade Adjudicante: Empresa pública\nÁrea de atividade da Entidade Adjudicante: Atividades relacionadas com a água\n\n2 - JORNAL OFICIAL DA UNIÃO EUROPEIA\nO procedimento a que este anúncio diz respeito também é publicitado no Jornal Oficial da União Europeia? Não\n\n3 - AVISO\nModelo de Anúncio: Concurso público\nData de Envio do Anúncio: 29-12-2025\n\n5 - PROCESSO\nTipo de Procedimento: Concurso público\nPreço base do procedimento: Sim\nValor do preço base do procedimento: 75.181,00 EUR\nProcedimento com lotes? Não\n\n6 - OBJETO DO CONTRATO\nNúmero de referência interna: CP DC 49/2025\nDesignação do contrato: LEASING PARA AQUISIÇÃO DE EQUIPAMENTO MÓVEL E ACESSÓRIOS PARA BOMBAGEM EM SISTEMAS PÚBLICOS DE DRENAGEM DE ÁGUAS RESIDUAIS (MOTOBOMBA).\nDescrição: LEASING PARA AQUISIÇÃO DE EQUIPAMENTO MÓVEL E ACESSÓRIOS PARA BOMBAGEM EM SISTEMAS PÚBLICOS DE DRENAGEM DE ÁGUAS RESIDUAIS (MOTOBOMBA).\nTipo de Contrato Principal: Aquisição de Serviços\nTipo de Contrato: Aquisição de Serviços\nClassificação CPV (Vocabulário Comum para os Contratos Públicos)\nObjeto principal\nVocabulário Principal: 66114000\nPreço base s/IVA: 75.181,00 EUR\n\n7 - INDICAÇÕES ADICIONAIS\nO contrato envolve aquisição conjunta (satisfação de várias entidades)? Não\nO contrato é adjudicado por uma central de compras? Não\n\n8 - TÉCNICAS\nO concurso destina-se à celebração de um acordo-quadro? Inexistência de acordo-quadro\nÉ utilizado um leilão eletrónico? Não\nÉ adotada uma fase de negociação? Não\nSistema de Aquisição Dinâmico: Inexistência de sistema de aquisição dinâmico\n\n9 - LOCAL DA EXECUÇÃO DO CONTRATO\nLOCAL DA EXECUÇÃO DO CONTRATO (PROCEDIMENTO)\nPaís: Portugal\nNUT III: PT112\nLocalidade: Braga\nDistrito: Braga\nConcelho: Braga\nFreguesia: União das Freguesias de Braga (São José de São Lázaro e São João do Souto)\n\n10 - PRAZO DE EXECUÇÃO DO CONTRATO\nPrazo de execução do contrato: 60 MESES\nPrevisão de renovações: Não\n\n11 - FUNDOS EU\nTêm fundos EU? Não\n\n12 - DOCUMENTOS DE HABILITAÇÃO\nHabilitação para o exercício da atividade profissional: Não\n\n13 - CONDIÇÕES DE APRESENTAÇÃO\nPlataforma eletrónica utilizada pela entidade adjudicante: VORTAL\nURL para Apresentação: https://community.vortal.biz/public/\nAdmissibilidade da apresentação de propostas variantes: Não autorizado\nPrazo para apresentação das propostas: 12-01-2026 17:00\nPrazo durante o qual os concorrentes são obrigados a manter as respetivas propostas: 66 dias a contar do termo do prazo para a apresentação das propostas\nIndicação de Subcontratação na Proposta: Inexistência de indicação de subcontratação\n\n14 - PRESTAÇÃO DE CAUÇÃO\nPrestação de caução: Não\n\n15 - FORNECIMENTO DAS PEÇAS DO CONCURSO, APRESENTAÇÃO DE PEDIDOS DE PARTICIPAÇÃO E APRESENTAÇÃO DAS PROPOSTAS\nLink para acesso às peças do concurso (URL): https://community.vortal.biz/Public/public-tender-documents/QXczSGtHdWJhVzJGdkV5M3lXbWRGZWZRZ1lHTDdEOEl3T3N3bHRpSmZxWFNnM2VlZXM1ckY1TXBTb1VaSFlIWDdLVGQzbjNtQ0k5UGpnN2xraUxMNGc9PTFxMCNa\n\n20 - OUTROS REQUISITOS\nInformação sobre contratos reservados. Aplica-se a contratos reservados (54º-A)? Não\n\n21 - CRITÉRIO DE ADJUDICAÇÃO\nMultifator: Não\nMonofator:\nNome: Preço\n\n24 - CONDIÇÕES DO CONTRATO\nFaturação Eletrónica: Permitido\nObrigação de Subcontratação:\nCódigo da Obrigação de Subcontratação: Não é aplicável nenhuma obrigação de subcontratação.\n\n25 - COMPRA PÚBLICA ESTRATÉGICA\nCompra Pública Estratégica: Inexistência de contratação pública estratégica\n\n26 - INFORMAÇÕES ADICIONAIS\nContrato adequado para PME: Sim\nCobertura ACP (Acordo dos Contratos Públicos da Organização Mundial do Comércio): Não\n\n27 - IDENTIFICAÇÃO E CONTACTOS DO ÓRGÃO DE RECURSOS ADMINISTRATIVOS\nDesignação: Conselho de Administração da AGERE EM\nEndereço: Praça Conde de Agrolongo, 115\nCódigo postal: 4700-312\nLocalidade: Braga\nTelefone: +351 253205001\nFax: +351 253205075\nEndereço eletrónico: administracao@agere.pt\n\n28 - IDENTIFICAÇÃO DO(S) AUTOR(ES) DE ANÚNCIO\nNome: Engª Paula Campos\nCargo: Administradora Executiva\n419934452",
    "nipc": "504807692",
    "distrito": "Braga",
    "concelho": "Braga",
    "freguesia": "Todas",
    "site": "www.agere.pt",
    "email": "agere@agere.pt",
    "designacao_contrato": "LEASING PARA AQUISIÇÃO DE EQUIPAMENTO MÓVEL E ACESSÓRIOS PARA BOMBAGEM EM SISTEMAS PÚBLICOS DE DRENAGEM DE ÁGUAS RESIDUAIS (MOTOBOMBA).",
    "descricao": "LEASING PARA AQUISIÇÃO DE EQUIPAMENTO MÓVEL E ACESSÓRIOS PARA BOMBAGEM EM SISTEMAS PÚBLICOS DE DRENAGEM DE ÁGUAS RESIDUAIS (MOTOBOMBA).",
    "preco_base": "75.181,00 EUR",
    "prazo_execucao": "60 MESES",
    "prazo_apresentacao_propostas": "12-01-2026 17:00",
    "fundos_eu": "Não",
    "plataforma_eletronica": "VORTAL",
    "url_procedimento": "https://community.vortal.biz/public/",
    "autor_nome": "Engª Paula Campos",
    "autor_cargo": "Administradora Executiva"
  },
  {
    "numero_procedimento": "N/A",
    "entidade": "Instituto Politécnico de Viseu",
    "link": "https://diariodarepublica.pt/dr/detalhe/contrato-publico/33488-992879843",
    "detalhes_completos": "1 - IDENTIFICAÇÃO E CONTACTOS DA ENTIDADE ADJUDICANTE\nDesignação da entidade adjudicante: Instituto Politécnico de Viseu\nNIPC: 680033548\nServiço/Órgão/Pessoa de contacto: Departamento Técnico do Instituto Politécnico de Viseu\nEndereço: Av.ª José Maria Vale de Andrade - Campus Politécnico\nCódigo postal: 3504-510\nLocalidade: Viseu\nPaís: Portugal\nNUT III: PT16G\nDistrito: Viseu\nConcelho: Viseu\nFreguesia: Freguesia de Viseu\nTelefone: 232480700\nFax: 232480750\nEndereço da Entidade (URL): www.ipv.pt\nEndereço Eletrónico: ipv@sc.ipv.pt\neDelivery Gateway (URL): https://www.acingov.pt\nFunção da Organização: Adquirente\nSubfunção da Organização: Organização que recebe as propostas\nNorma jurídica da Entidade Adjudicante: Organismo de direito público\nÁrea de atividade da Entidade Adjudicante: Serviços postais\n\n2 - JORNAL OFICIAL DA UNIÃO EUROPEIA\nO procedimento a que este anúncio diz respeito também é publicitado no Jornal Oficial da União Europeia? Não\n\n3 - AVISO\nModelo de Anúncio: Concurso público\nData de Envio do Anúncio: 29-12-2025\n\n5 - PROCESSO\nTipo de Procedimento: Concurso público\nPreço base do procedimento: Sim\nValor do preço base do procedimento: 56.150,00 EUR\nProcedimento com lotes? Não\n\n6 - OBJETO DO CONTRATO\nNúmero de referência interna: Concurso público nº 27/IPV/2025\nDesignação do contrato: Concurso Público n.º 27/2025  Aquisição de equipamentos de robótica para o Instituto Politécnico de Viseu no âmbito do projeto PRR - LFA - Impulso Jovens Steam e Impulso Adulto\nDescrição: Concurso Público n.º 27/2025  Aquisição de equipamentos de robótica para o Instituto Politécnico de Viseu no âmbito do projeto PRR - LFA - Impulso Jovens Steam e Impulso Adulto\nTipo de Contrato Principal: Aquisição de Bens Móveis\nTipo de Contrato: Aquisição de Bens Móveis\nClassificação CPV (Vocabulário Comum para os Contratos Públicos)\nObjeto principal\nVocabulário Principal: 31720000\nPreço base s/IVA: 56.150,00 EUR\n\n7 - INDICAÇÕES ADICIONAIS\nO contrato envolve aquisição conjunta (satisfação de várias entidades)? Não\nO contrato é adjudicado por uma central de compras? Não\n\n8 - TÉCNICAS\nO concurso destina-se à celebração de um acordo-quadro? Inexistência de acordo-quadro\nÉ utilizado um leilão eletrónico? Não\nÉ adotada uma fase de negociação? Não\nSistema de Aquisição Dinâmico: Inexistência de sistema de aquisição dinâmico\n\n9 - LOCAL DA EXECUÇÃO DO CONTRATO\nLOCAL DA EXECUÇÃO DO CONTRATO (PROCEDIMENTO)\nPaís: Portugal\nNUT III: PT16G\nLocalidade: Freguesia de Viseu\nDistrito: Viseu\nConcelho: Viseu\nFreguesia: Freguesia de Viseu\n\n10 - PRAZO DE EXECUÇÃO DO CONTRATO\nPrazo de execução do contrato: 60 DIAS\nPrevisão de renovações: Não\n\n11 - FUNDOS EU\nTêm fundos EU? Sim\n\n12 - DOCUMENTOS DE HABILITAÇÃO\nHabilitação para o exercício da atividade profissional: Não\n\n13 - CONDIÇÕES DE APRESENTAÇÃO\nPlataforma eletrónica utilizada pela entidade adjudicante: ACIN\nURL para Apresentação: https://www.acingov.pt\nAdmissibilidade da apresentação de propostas variantes: Não autorizado\nPrazo para apresentação das propostas: 12-01-2026 23:59\nPrazo durante o qual os concorrentes são obrigados a manter as respetivas propostas: 66 dias a contar do termo do prazo para a apresentação das propostas\nIndicação de Subcontratação na Proposta: Inexistência de indicação de subcontratação\n\n14 - PRESTAÇÃO DE CAUÇÃO\nPrestação de caução: Não\n\n15 - FORNECIMENTO DAS PEÇAS DO CONCURSO, APRESENTAÇÃO DE PEDIDOS DE PARTICIPAÇÃO E APRESENTAÇÃO DAS PROPOSTAS\nLink para acesso às peças do concurso (URL): https://www.acingov.pt/acingovprod/2/zonaPublica/zona_publica_c/donwloadProcedurePiece/MTAwNTY2NA==\n\n20 - OUTROS REQUISITOS\nInformação sobre contratos reservados. Aplica-se a contratos reservados (54º-A)? Não\n\n21 - CRITÉRIO DE ADJUDICAÇÃO\nMultifator: Sim\nFator: \nNome: Preço\nPonderação: 90%\nSubfatores: Não\nFator: \nNome: Sustentabilidade ambiental ou social\nPonderação: 10%\nSubfatores: Não\n\n24 - CONDIÇÕES DO CONTRATO\nFaturação Eletrónica: Permitido\nObrigação de Subcontratação:\nCódigo da Obrigação de Subcontratação: Não é aplicável nenhuma obrigação de subcontratação.\n\n25 - COMPRA PÚBLICA ESTRATÉGICA\nCompra Pública Estratégica: Inexistência de contratação pública estratégica\n\n26 - INFORMAÇÕES ADICIONAIS\nContrato adequado para PME: Não\nCobertura ACP (Acordo dos Contratos Públicos da Organização Mundial do Comércio): Não\n\n27 - IDENTIFICAÇÃO E CONTACTOS DO ÓRGÃO DE RECURSOS ADMINISTRATIVOS\nDesignação: Presidente do Instituto Politécnico de Viseu\nEndereço: Av.ª José Maria Vale de Andrade - Campus Politécnico\nCódigo postal: 3504-510\nLocalidade: Viseu\nTelefone: 232480700\nFax: 232480750\nEndereço eletrónico: ipv@sc.ipv.pt\n\n28 - IDENTIFICAÇÃO DO(S) AUTOR(ES) DE ANÚNCIO\nNome: José dos Santos Costa\nCargo: Presidente do Instituto Politécnico de Viseu\n419934469",
    "nipc": "680033548",
    "distrito": "Viseu",
    "concelho": "Viseu",
    "freguesia": "Freguesia de Viseu",
    "site": "www.ipv.pt",
    "email": "ipv@sc.ipv.pt",
    "designacao_contrato": "Concurso Público n.º 27/2025  Aquisição de equipamentos de robótica para o Instituto Politécnico de Viseu no âmbito do projeto PRR - LFA - Impulso Jovens Steam e Impulso Adulto",
    "descricao": "Concurso Público n.º 27/2025  Aquisição de equipamentos de robótica para o Instituto Politécnico de Viseu no âmbito do projeto PRR - LFA - Impulso Jovens Steam e Impulso Adulto",
    "preco_base": "56.150,00 EUR",
    "prazo_execucao": "60 DIAS",
    "prazo_apresentacao_propostas": "12-01-2026 23:59",
    "fundos_eu": "Sim",
    "plataforma_eletronica": "ACIN",
    "url_procedimento": "https://www.acingov.pt",
    "autor_nome": "José dos Santos Costa",
    "autor_cargo": "Presidente do Instituto Politécnico de Viseu"
  },
  {
    "numero_procedimento": "N/A",
    "entidade": "Instituto Politécnico de Viseu",
    "link": "https://diariodarepublica.pt/dr/detalhe/contrato-publico/33489-992879844",
    "detalhes_completos": "1 - IDENTIFICAÇÃO E CONTACTOS DA ENTIDADE ADJUDICANTE\nDesignação da entidade adjudicante: Instituto Politécnico de Viseu\nNIPC: 680033548\nServiço/Órgão/Pessoa de contacto: Departamento Técnico do Instituto Politécnico de Viseu\nEndereço: Av.ª José Maria Vale de Andrade - Campus Politécnico\nCódigo postal: 3504-510\nLocalidade: Viseu\nPaís: Portugal\nNUT III: PT16G\nDistrito: Viseu\nConcelho: Viseu\nFreguesia: Freguesia de Viseu\nTelefone: 232480700\nFax: 232480750\nEndereço da Entidade (URL): www.ipv.pt\nEndereço Eletrónico: ipv@sc.ipv.pt\neDelivery Gateway (URL): https://www.acingov.pt\nFunção da Organização: Adquirente\nSubfunção da Organização: Organização que recebe as propostas\nNorma jurídica da Entidade Adjudicante: Organismo de direito público\nÁrea de atividade da Entidade Adjudicante: Serviços postais\n\n2 - JORNAL OFICIAL DA UNIÃO EUROPEIA\nO procedimento a que este anúncio diz respeito também é publicitado no Jornal Oficial da União Europeia? Não\n\n3 - AVISO\nModelo de Anúncio: Concurso público\nData de Envio do Anúncio: 29-12-2025\n\n5 - PROCESSO\nTipo de Procedimento: Concurso público\nPreço base do procedimento: Sim\nValor do preço base do procedimento: 23.119,00 EUR\nProcedimento com lotes? Sim\nNº Máx. de Lotes Autorizado: 4\nNúmero máximo de lotes que podem ser adjudicados a um concorrente: 4\n\n6 - OBJETO DO CONTRATO\nNúmero de referência interna: Concurso público nº 25/2025\nDesignação do contrato: Concurso Público n.º 25/IPV/2025  Aquisição de um equipamento de Realidade Aumentada (RA)/realidade mista (RX) no âmbito do projeto GreenAuto do Instituto Politécnico de Viseu\nDescrição: Concurso Público n.º 25/IPV/2025  Aquisição de um equipamento de Realidade Aumentada (RA)/realidade mista (RX) no âmbito do projeto GreenAuto do Instituto Politécnico de Viseu \nTipo de Contrato Principal: Aquisição de Bens Móveis\nTipo de Contrato: Aquisição de Bens Móveis\nClassificação CPV (Vocabulário Comum para os Contratos Públicos)\nObjeto principal\nVocabulário Principal: 30213100\nPreço base s/IVA: 23.119,00 EUR\nLotes: \nNº: LOT-0001\nDescrição do Lote: MacBook pro 14\"  Preto; Ecrã líquido; CPU-Apple M5 com 10 núcleos; Apple M5 GPU de 10 núcleos; neural engine - 16 núcleos; RAM-32GB; SSD 2TB; Adaptador de corrente USB-C 70W\nPreço base s/IVA: 6.370,00 EUR\nClassificação CPV (Vocabulário Comum para os Contratos Públicos)\nObjeto principal\nVocabulário Principal: 30213100\nNº: LOT-0002\nDescrição do Lote: 2.1 Portátil HP  Intel Core Ultra 7 255U 12C 2.2 4TB SSD Disco Externo SanDisk Extreme PRO V2 USB 3.2 2.3 2TB SSD Disco Externo SanDisk Extreme USB 3.2 Gen 2\nPreço base s/IVA: 2.394,00 EUR\nClassificação CPV (Vocabulário Comum para os Contratos Públicos)\nObjeto principal\nVocabulário Principal: 30213100\nNº: LOT-0003\nDescrição do Lote: Equipamento de realidade aumentada/mista - Magic Leap 2 developer pro edition\nPreço base s/IVA: 7.380,00 EUR\nClassificação CPV (Vocabulário Comum para os Contratos Públicos)\nObjeto principal\nVocabulário Principal: 30213100\nNº: LOT-0004\nDescrição do Lote: Processador + Motherboard, Placa Gráfica, Caixa, Fonte Modular, discos, kit de refrigeração e montagem\nPreço base s/IVA: 6.975,00 EUR\nClassificação CPV (Vocabulário Comum para os Contratos Públicos)\nObjeto principal\nVocabulário Principal: 30213100\n\n7 - INDICAÇÕES ADICIONAIS\nO contrato envolve aquisição conjunta (satisfação de várias entidades)? Não\nO contrato é adjudicado por uma central de compras? Não\n\n8 - TÉCNICAS\nO concurso destina-se à celebração de um acordo-quadro? Inexistência de acordo-quadro\nÉ utilizado um leilão eletrónico? Não\nÉ adotada uma fase de negociação? Não\nSistema de Aquisição Dinâmico: Inexistência de sistema de aquisição dinâmico\n\n9 - LOCAL DA EXECUÇÃO DO CONTRATO\nLOCAL DA EXECUÇÃO DO CONTRATO (PROCEDIMENTO)\nPaís: Portugal\nNUT III: PT16G\nLocalidade: Freguesia de Viseu\nDistrito: Viseu\nConcelho: Viseu\nFreguesia: Freguesia de Viseu\nLOCAL DA EXECUÇÃO DO CONTRATO (LOTE)\nIdentificador do Lote: LOT-0001; LOT-0002; LOT-0003; LOT-0004\nPaís: Portugal\nNUT III: PT16G\nLocalidade: Freguesia de Viseu\nDistrito: Viseu\nConcelho: Viseu\nFreguesia: Freguesia de Viseu\n\n10 - PRAZO DE EXECUÇÃO DO CONTRATO\nIdentificador do Lote: LOT-0001; LOT-0002; LOT-0003; LOT-0004\nPrazo de execução do contrato: 30 DIAS\nPrevisão de renovações: Não\n\n11 - FUNDOS EU\nIdentificador do Lote: LOT-0001; LOT-0002; LOT-0003; LOT-0004\nTêm fundos EU? Sim\n\n12 - DOCUMENTOS DE HABILITAÇÃO\nHabilitação para o exercício da atividade profissional: Não\n\n13 - CONDIÇÕES DE APRESENTAÇÃO\nPlataforma eletrónica utilizada pela entidade adjudicante: ACIN\nURL para Apresentação: https://www.acingov.pt\nAdmissibilidade da apresentação de propostas variantes: Não autorizado\nPrazo para apresentação das propostas: 10-01-2026 23:59\nPrazo durante o qual os concorrentes são obrigados a manter as respetivas propostas: 66 dias a contar do termo do prazo para a apresentação das propostas\nIndicação de Subcontratação na Proposta: Inexistência de indicação de subcontratação\n\n14 - PRESTAÇÃO DE CAUÇÃO\nPrestação de caução: Não\n\n15 - FORNECIMENTO DAS PEÇAS DO CONCURSO, APRESENTAÇÃO DE PEDIDOS DE PARTICIPAÇÃO E APRESENTAÇÃO DAS PROPOSTAS\nLink para acesso às peças do concurso (URL): https://www.acingov.pt/acingovprod/2/zonaPublica/zona_publica_c/donwloadProcedurePiece/MTAwNTc4Mw==\n\n20 - OUTROS REQUISITOS\nIdentificador do Lote: LOT-0001; LOT-0002; LOT-0003; LOT-0004\nInformação sobre contratos reservados. Aplica-se a contratos reservados (54º-A)? Não\n\n21 - CRITÉRIO DE ADJUDICAÇÃO\nO Critério de adjudicação é diferenciado por lote? Não\nMultifator: Sim\nFator: \nNome: Preço\nPonderação: 90%\nSubfatores: Não\nFator: \nNome: Sustentabilidade ambiental ou social\nPonderação: 10%\nSubfatores: Não\n\n24 - CONDIÇÕES DO CONTRATO\nIdentificador do Lote: LOT-0001; LOT-0002; LOT-0003; LOT-0004\nFaturação Eletrónica: Permitido\nObrigação de Subcontratação:\nCódigo da Obrigação de Subcontratação: Não é aplicável nenhuma obrigação de subcontratação.\n\n25 - COMPRA PÚBLICA ESTRATÉGICA\nCompra Pública Estratégica: Inexistência de contratação pública estratégica\n\n26 - INFORMAÇÕES ADICIONAIS\nIdentificador do Lote: LOT-0001; LOT-0002; LOT-0003; LOT-0004\nContrato adequado para PME: Sim\nCobertura ACP (Acordo dos Contratos Públicos da Organização Mundial do Comércio): Não\n\n27 - IDENTIFICAÇÃO E CONTACTOS DO ÓRGÃO DE RECURSOS ADMINISTRATIVOS\nDesignação: Presidente do Instituto Politécnico de Viseu\nEndereço: Av.ª José Maria Vale de Andrade - Campus Politécnico\nCódigo postal: 3504-510\nLocalidade: Viseu\nTelefone: 232480700\nFax: 232480750\nEndereço eletrónico: ipv@sc.ipv.pt\n\n28 - IDENTIFICAÇÃO DO(S) AUTOR(ES) DE ANÚNCIO\nNome: Professor Doutor José dos Santos Costa\nCargo: Presidente do Instituto Politécnico de Viseu\n419934299",
    "nipc": "680033548",
    "distrito": "Viseu",
    "concelho": "Viseu",
    "freguesia": "Freguesia de Viseu",
    "site": "www.ipv.pt",
    "email": "ipv@sc.ipv.pt",
    "designacao_contrato": "Concurso Público n.º 25/IPV/2025  Aquisição de um equipamento de Realidade Aumentada (RA)/realidade mista (RX) no âmbito do projeto GreenAuto do Instituto Politécnico de Viseu",
    "descricao": "Concurso Público n.º 25/IPV/2025  Aquisição de um equipamento de Realidade Aumentada (RA)/realidade mista (RX) no âmbito do projeto GreenAuto do Instituto Politécnico de Viseu",
    "preco_base": "23.119,00 EUR",
    "prazo_execucao": "30 DIAS",
    "prazo_apresentacao_propostas": "10-01-2026 23:59",
    "fundos_eu": "Sim",
    "plataforma_eletronica": "ACIN",
    "url_procedimento": "https://www.acingov.pt",
    "autor_nome": "Professor Doutor José dos Santos Costa",
    "autor_cargo": "Presidente do Instituto Politécnico de Viseu"
  },
  {
    "numero_procedimento": "N/A",
    "entidade": "Município de Leiria",
    "link": "https://diariodarepublica.pt/dr/detalhe/contrato-publico/33490-992879845",
    "detalhes_completos": "1 - IDENTIFICAÇÃO E CONTACTOS DA ENTIDADE ADJUDICANTE\nDesignação da entidade adjudicante: Município de Leiria\nNIPC: 505181266\nEndereço: Largo da República\nCódigo postal: 2414-006\nLocalidade: Leiria\nPaís: Portugal\nNUT III: PT16F\nDistrito: Leiria\nConcelho: Leiria\nFreguesia: União das Freguesias de Leiria, Pousos, Barreira e Cortes\nTelefone: 244839500\nFax: 244839500\nEndereço da Entidade (URL): www.cm-leiria.pt\nEndereço Eletrónico: cmleiria@cm-leiria.pt\nFunção da Organização: Adquirente\nNorma jurídica da Entidade Adjudicante: Autoridade local\nÁrea de atividade da Autoridade Adjudicante: Serviços públicos das administrações públicas\n\n2 - JORNAL OFICIAL DA UNIÃO EUROPEIA\nO procedimento a que este anúncio diz respeito também é publicitado no Jornal Oficial da União Europeia? Não\n\n3 - AVISO\nModelo de Anúncio: Concurso público\nData de Envio do Anúncio: 29-12-2025\n\n5 - PROCESSO\nTipo de Procedimento: Concurso público\nPreço base do procedimento: Sim\nValor do preço base do procedimento: 50.538,00 EUR\nProcedimento com lotes? Não\n\n6 - OBJETO DO CONTRATO\nNúmero de referência interna: CPN 151/2025/DICP\nDesignação do contrato: CPN 151/2025/DICP - Locação de baias para eventos 2026 - inclui transporte, montagem e desmontagem\nDescrição: CPN 151/2025/DICP - Locação de baias para eventos 2026 - inclui transporte, montagem e desmontagem\nTipo de Contrato Principal: Aquisição de Bens Móveis\nTipo de Contrato: Aquisição de Bens Móveis\nClassificação CPV (Vocabulário Comum para os Contratos Públicos)\nObjeto principal\nVocabulário Principal: 34928300\nPreço base s/IVA: 50.538,00 EUR\n\n7 - INDICAÇÕES ADICIONAIS\nO contrato envolve aquisição conjunta (satisfação de várias entidades)? Não\nO contrato é adjudicado por uma central de compras? Não\n\n8 - TÉCNICAS\nO concurso destina-se à celebração de um acordo-quadro? Inexistência de acordo-quadro\nÉ utilizado um leilão eletrónico? Não\nÉ adotada uma fase de negociação? Não\nSistema de Aquisição Dinâmico: Inexistência de sistema de aquisição dinâmico\n\n9 - LOCAL DA EXECUÇÃO DO CONTRATO\nLOCAL DA EXECUÇÃO DO CONTRATO (PROCEDIMENTO)\nPaís: Portugal\nNUT III: PT16F\nLocalidade: Leiria\nDistrito: Leiria\nConcelho: Leiria\nFreguesia: União das Freguesias de Leiria, Pousos, Barreira e Cortes\n\n10 - PRAZO DE EXECUÇÃO DO CONTRATO\nPrazo de execução do contrato: 12 MESES\nPrevisão de renovações: Não\n\n11 - FUNDOS EU\nTêm fundos EU? Não\n\n12 - DOCUMENTOS DE HABILITAÇÃO\nHabilitação para o exercício da atividade profissional: Não\n\n13 - CONDIÇÕES DE APRESENTAÇÃO\nPlataforma eletrónica utilizada pela entidade adjudicante: ANOGOV\nURL para Apresentação: https://www.anogov.com/cm-leiria/faces/\nAdmissibilidade da apresentação de propostas variantes: Não autorizado\nPrazo para apresentação das propostas: 04-01-2026 23:59\nPrazo durante o qual os concorrentes são obrigados a manter as respetivas propostas: 120 dias a contar do termo do prazo para a apresentação das propostas\nApresentação de Catálogo Eletrónico: Não autorizado\nIndicação de Subcontratação na Proposta: Inexistência de indicação de subcontratação\n\n14 - PRESTAÇÃO DE CAUÇÃO\nPrestação de caução: Não\n\n15 - FORNECIMENTO DAS PEÇAS DO CONCURSO, APRESENTAÇÃO DE PEDIDOS DE PARTICIPAÇÃO E APRESENTAÇÃO DAS PROPOSTAS\nLink para acesso às peças do concurso (URL): https://www.anogov.com/cm-leiria/faces/app/acessoDocs.jsp?codigoAcesso=AevfzNVptFPuwU8HxjOgveFkeoBgNVmeF5UWYPyuesf6RlxRbF\n\n20 - OUTROS REQUISITOS\nInformação sobre contratos reservados. Aplica-se a contratos reservados (54º-A)? Não\n\n21 - CRITÉRIO DE ADJUDICAÇÃO\nMultifator: Sim\nFator: \nNome: Preço\nPonderação: 60%\nSubfatores: Não\nFator: \nNome: Outros\nOutro Nome: GE: Gestão de Equipamento\nPonderação: 10%\nSubfatores: Não\nFator: \nNome: Outros\nOutro Nome: VTP: Valia Técnica da Proposta\nPonderação: 30%\nSubfatores: Não\n\n24 - CONDIÇÕES DO CONTRATO\nFaturação Eletrónica: Permitido\nObrigação de Subcontratação:\nCódigo da Obrigação de Subcontratação: Não é aplicável nenhuma obrigação de subcontratação.\n\n25 - COMPRA PÚBLICA ESTRATÉGICA\nCompra Pública Estratégica: Inexistência de contratação pública estratégica\n\n26 - INFORMAÇÕES ADICIONAIS\nContrato adequado para PME: Sim\nCobertura ACP (Acordo dos Contratos Públicos da Organização Mundial do Comércio): Não\n\n27 - IDENTIFICAÇÃO E CONTACTOS DO ÓRGÃO DE RECURSOS ADMINISTRATIVOS\nDesignação: Presidente da Câmara Municipal de Leiria\nEndereço: Largo da República\nCódigo postal: 2414-006\nLocalidade: Leiria\nTelefone: 244839500\nFax: \nEndereço eletrónico: cmleiria@cm-leiria.pt\n\n28 - IDENTIFICAÇÃO DO(S) AUTOR(ES) DE ANÚNCIO\nNome: Gonçalo Lopes\nCargo: Presidente da Câmara Municipal de Leiria\n419934566",
    "nipc": "505181266",
    "distrito": "Leiria",
    "concelho": "Leiria",
    "freguesia": "União das Freguesias de Leiria, Pousos, Barreira e Cortes",
    "site": "www.cm-leiria.pt",
    "email": "cmleiria@cm-leiria.pt",
    "designacao_contrato": "CPN 151/2025/DICP - Locação de baias para eventos 2026 - inclui transporte, montagem e desmontagem",
    "descricao": "CPN 151/2025/DICP - Locação de baias para eventos 2026 - inclui transporte, montagem e desmontagem",
    "preco_base": "50.538,00 EUR",
    "prazo_execucao": "12 MESES",
    "prazo_apresentacao_propostas": "04-01-2026 23:59",
    "fundos_eu": "Não",
    "plataforma_eletronica": "ANOGOV",
    "url_procedimento": "https://www.anogov.com/cm-leiria/faces/",
    "autor_nome": "Gonçalo Lopes",
    "autor_cargo": "Presidente da Câmara Municipal de Leiria"
  },
  {
    "numero_procedimento": "N/A",
    "entidade": "Centro Social Paroquial de Alfena",
    "link": "https://diariodarepublica.pt/dr/detalhe/contrato-publico/33492-992879846",
    "detalhes_completos": "1 - IDENTIFICAÇÃO E CONTACTOS DA ENTIDADE ADJUDICANTE\nDesignação da entidade adjudicante: Centro Social Paroquial de Alfena\nNIPC: 501114599\nEndereço: Rua do Centro Social, s/n\nCódigo postal: 4445-066\nLocalidade: Área Metropolitana do Porto\nPaís: Portugal\nNUT III: PT11A\nDistrito: Porto\nConcelho: Valongo\nFreguesia: Freguesia de Alfena\nTelefone: 229698080\nFax: 229698080\nEndereço Eletrónico: geral@cspalfena.com\neDelivery Gateway (URL): https://community.vortal.biz/public/\nFunção da Organização: Adquirente\nNorma jurídica da Entidade Adjudicante: Organismo de direito público\nÁrea de atividade da Autoridade Adjudicante: Proteção social\n\n2 - JORNAL OFICIAL DA UNIÃO EUROPEIA\nO procedimento a que este anúncio diz respeito também é publicitado no Jornal Oficial da União Europeia? Não\n\n3 - AVISO\nModelo de Anúncio: Concurso público\nData de Envio do Anúncio: 29-12-2025\n\n5 - PROCESSO\nTipo de Procedimento: Concurso público\nPreço base do procedimento: Sim\nValor do preço base do procedimento: 1.128.272,98 EUR\nProcedimento com lotes? Não\n\n6 - OBJETO DO CONTRATO\nNúmero de referência interna: CP 01/2025\nDesignação do contrato: Estrutura Residencial para Pessoas Idosas 1 - Reabilitação\nDescrição: Intervenção de reabilitação parcial no interior da Estrutura Residencial para Pessoas Idosas 1, com foco principal na renovação integral dos espaços de alojamento (entenda-se, quartos e respetivas instalações sanitárias).\nTipo de Contrato Principal: Empreitada de Obras Públicas\nTipo de Contrato: Empreitada de Obras Públicas\nClassificação CPV (Vocabulário Comum para os Contratos Públicos)\nObjeto principal\nVocabulário Principal: 45215212\nPreço base s/IVA: 1.128.272,98 EUR\n\n7 - INDICAÇÕES ADICIONAIS\nO contrato envolve aquisição conjunta (satisfação de várias entidades)? Não\nO contrato é adjudicado por uma central de compras? Não\n\n8 - TÉCNICAS\nO concurso destina-se à celebração de um acordo-quadro? Inexistência de acordo-quadro\nÉ utilizado um leilão eletrónico? Não\nÉ adotada uma fase de negociação? Não\nSistema de Aquisição Dinâmico: Inexistência de sistema de aquisição dinâmico\n\n9 - LOCAL DA EXECUÇÃO DO CONTRATO\nLOCAL DA EXECUÇÃO DO CONTRATO (PROCEDIMENTO)\nPaís: Portugal\nNUT III: PT11A\nLocalidade: Área Metropolitana do Porto\nDistrito: Porto\nConcelho: Valongo\nFreguesia: Freguesia de Alfena\n\n10 - PRAZO DE EXECUÇÃO DO CONTRATO\nPrazo de execução do contrato: 6 MESES\nPrevisão de renovações: Não\n\n11 - FUNDOS EU\nTêm fundos EU? Sim\n\n12 - DOCUMENTOS DE HABILITAÇÃO\nHabilitação para o exercício da atividade profissional: Sim\nTipo: Alvará\nDescrição: Alvará de empreiteiro de obras públicas, habilitado para executar os trabalhos de acordo com o procedimento.\n\n13 - CONDIÇÕES DE APRESENTAÇÃO\nPlataforma eletrónica utilizada pela entidade adjudicante: VORTAL\nURL para Apresentação: https://community.vortal.biz/public/\nAdmissibilidade da apresentação de propostas variantes: Não autorizado\nPrazo para apresentação das propostas: 31-01-2026 17:00\nPrazo durante o qual os concorrentes são obrigados a manter as respetivas propostas: 66 dias a contar do termo do prazo para a apresentação das propostas\nIndicação de Subcontratação na Proposta: Inexistência de indicação de subcontratação\n\n14 - PRESTAÇÃO DE CAUÇÃO\nPrestação de caução: Sim\nPercentagem: 5%\nDescrição da Garantia Exigida: Conforme previsto no artigo 23º do Programa do Procedimento\n\n15 - FORNECIMENTO DAS PEÇAS DO CONCURSO, APRESENTAÇÃO DE PEDIDOS DE PARTICIPAÇÃO E APRESENTAÇÃO DAS PROPOSTAS\nLink para acesso às peças do concurso (URL): https://community.vortal.biz/Public/public-tender-documents/aC9nczJac1BpdmFaSERFR2l1MDZ4ZUlDaWQzNjRpM0o4Q05sbTBRdmlLRHVOWGR4ZENXa1lVNFIvaXhPRjBYK0tBZ1pYNTl5aTV6T1BGRHpHWVd1VFE9PVJuRikp\n\n20 - OUTROS REQUISITOS\nInformação sobre contratos reservados. Aplica-se a contratos reservados (54º-A)? Não\n\n21 - CRITÉRIO DE ADJUDICAÇÃO\nMultifator: Não\nMonofator:\nNome: Preço\n\n24 - CONDIÇÕES DO CONTRATO\nFaturação Eletrónica: Permitido\nObrigação de Subcontratação:\nCódigo da Obrigação de Subcontratação: Não é aplicável nenhuma obrigação de subcontratação.\n\n25 - COMPRA PÚBLICA ESTRATÉGICA\nCompra Pública Estratégica: Inexistência de contratação pública estratégica\n\n26 - INFORMAÇÕES ADICIONAIS\nContrato adequado para PME: Sim\nCobertura ACP (Acordo dos Contratos Públicos da Organização Mundial do Comércio): Não\n\n27 - IDENTIFICAÇÃO E CONTACTOS DO ÓRGÃO DE RECURSOS ADMINISTRATIVOS\nDesignação: Direção do Centro Social e Paroquial de Alfena\nEndereço: Rua do Centro Social, s/n\nCódigo postal: 4445-066\nLocalidade: Valongo\nTelefone: +351 912121362\nFax: +351 912121362\nEndereço eletrónico: direccao@cspalfena.com\n\n28 - IDENTIFICAÇÃO DO(S) AUTOR(ES) DE ANÚNCIO\nNome: Andreia Sousa Moreira\nCargo: Diretora de Serviços\n419934541",
    "nipc": "501114599",
    "distrito": "Porto",
    "concelho": "Valongo",
    "freguesia": "Freguesia de Alfena",
    "site": null,
    "email": "geral@cspalfena.com",
    "designacao_contrato": "Estrutura Residencial para Pessoas Idosas 1 - Reabilitação",
    "descricao": "Intervenção de reabilitação parcial no interior da Estrutura Residencial para Pessoas Idosas 1, com foco principal na renovação integral dos espaços de alojamento (entenda-se, quartos e respetivas instalações sanitárias).",
    "preco_base": "1.128.272,98 EUR",
    "prazo_execucao": "6 MESES",
    "prazo_apresentacao_propostas": "31-01-2026 17:00",
    "fundos_eu": "Sim",
    "plataforma_eletronica": "VORTAL",
    "url_procedimento": "https://community.vortal.biz/public/",
    "autor_nome": "Andreia Sousa Moreira",
    "autor_cargo": "Diretora de Serviços"
  },
  {
    "numero_procedimento": "N/A",
    "entidade": "Instituto do Emprego e da Formação Profissional, IP",
    "link": "https://diariodarepublica.pt/dr/detalhe/contrato-publico/33493-992879853",
    "detalhes_completos": "1 - IDENTIFICAÇÃO E CONTACTOS DA ENTIDADE ADJUDICANTE\nDesignação da entidade adjudicante: Instituto do Emprego e da Formação Profissional, IP\nNIPC: 501442600\nServiço/Órgão/Pessoa de contacto: Direção de Serviços de Gestão Administrativa e Financeira\nEndereço: Rua de Xabregas nº 52\nCódigo postal: 1949-003\nLocalidade: LISBOA\nPaís: Portugal\nNUT III: PT170\nDistrito: Lisboa\nConcelho: Lisboa\nFreguesia: Freguesia de Beato\nTelefone: 215803000\nFax: 215803617\nEndereço da Entidade (URL): http://www.iefp.pt\nEndereço Eletrónico: pg-af@iefp.pt\neDelivery Gateway (URL): https://www.acingov.pt\nFunção da Organização: Adquirente\nNorma jurídica da Entidade Adjudicante: Organismo de direito público\nÁrea de atividade da Autoridade Adjudicante: Serviços públicos das administrações públicas\n\n2 - JORNAL OFICIAL DA UNIÃO EUROPEIA\nO procedimento a que este anúncio diz respeito também é publicitado no Jornal Oficial da União Europeia? Não\n\n3 - AVISO\nModelo de Anúncio: Concurso público\nData de Envio do Anúncio: 29-12-2025\n\n5 - PROCESSO\nTipo de Procedimento: Concurso público\nPreço base do procedimento: Sim\nValor do preço base do procedimento: 90.000,00 EUR\nProcedimento com lotes? Não\n\n6 - OBJETO DO CONTRATO\nNúmero de referência interna: PR2025210/453\nDesignação do contrato: Aquisição de serviços especializados para sistemas de backup críticos do Instituto do Emprego e Formação Profissional, I.P.\nDescrição: Aquisição de serviços especializados para sistemas de backup críticos do Instituto do Emprego e Formação Profissional, I.P.\nTipo de Contrato Principal: Aquisição de Serviços\nTipo de Contrato: Aquisição de Serviços\nClassificação CPV (Vocabulário Comum para os Contratos Públicos)\nObjeto principal\nVocabulário Principal: 72253200\nPreço base s/IVA: 90.000,00 EUR\n\n7 - INDICAÇÕES ADICIONAIS\nO contrato envolve aquisição conjunta (satisfação de várias entidades)? Não\nO contrato é adjudicado por uma central de compras? Não\n\n8 - TÉCNICAS\nO concurso destina-se à celebração de um acordo-quadro? Inexistência de acordo-quadro\nÉ utilizado um leilão eletrónico? Não\nÉ adotada uma fase de negociação? Não\nSistema de Aquisição Dinâmico: Inexistência de sistema de aquisição dinâmico\n\n9 - LOCAL DA EXECUÇÃO DO CONTRATO\nLOCAL DA EXECUÇÃO DO CONTRATO (PROCEDIMENTO)\nPaís: Portugal\nNUT III: PT170\nLocalidade: Freguesia de Beato\nDistrito: Lisboa\nConcelho: Lisboa\nFreguesia: Freguesia de Beato\n\n10 - PRAZO DE EXECUÇÃO DO CONTRATO\nPrazo de execução do contrato: 24 MESES\nPrevisão de renovações: Não\n\n11 - FUNDOS EU\nTêm fundos EU? Não\n\n12 - DOCUMENTOS DE HABILITAÇÃO\nHabilitação para o exercício da atividade profissional: Não\n\n13 - CONDIÇÕES DE APRESENTAÇÃO\nPlataforma eletrónica utilizada pela entidade adjudicante: ACIN\nURL para Apresentação: https://www.acingov.pt\nAdmissibilidade da apresentação de propostas variantes: Não autorizado\nPrazo para apresentação das propostas: 14-01-2026 23:59\nPrazo durante o qual os concorrentes são obrigados a manter as respetivas propostas: 90 dias a contar do termo do prazo para a apresentação das propostas\nIndicação de Subcontratação na Proposta: Inexistência de indicação de subcontratação\n\n14 - PRESTAÇÃO DE CAUÇÃO\nPrestação de caução: Não\n\n15 - FORNECIMENTO DAS PEÇAS DO CONCURSO, APRESENTAÇÃO DE PEDIDOS DE PARTICIPAÇÃO E APRESENTAÇÃO DAS PROPOSTAS\nLink para acesso às peças do concurso (URL): https://www.acingov.pt/acingovprod/2/zonaPublica/zona_publica_c/donwloadProcedurePiece/MTAxMDQ2MQ==\n\n20 - OUTROS REQUISITOS\nInformação sobre contratos reservados. Aplica-se a contratos reservados (54º-A)? Não\n\n21 - CRITÉRIO DE ADJUDICAÇÃO\nMultifator: Não\nMonofator:\nNome: Preço\n\n24 - CONDIÇÕES DO CONTRATO\nFaturação Eletrónica: Permitido\nObrigação de Subcontratação:\nCódigo da Obrigação de Subcontratação: Não é aplicável nenhuma obrigação de subcontratação.\n\n25 - COMPRA PÚBLICA ESTRATÉGICA\nCompra Pública Estratégica: Inexistência de contratação pública estratégica\n\n26 - INFORMAÇÕES ADICIONAIS\nContrato adequado para PME: Sim\nCobertura ACP (Acordo dos Contratos Públicos da Organização Mundial do Comércio): Não\n\n27 - IDENTIFICAÇÃO E CONTACTOS DO ÓRGÃO DE RECURSOS ADMINISTRATIVOS\nDesignação: Instituto do Emprego e Formação Profissionla, I.P.\nEndereço: Rua de Xabregas nº 52\nCódigo postal: 1949-003\nLocalidade: Lisboa\nTelefone: 215803000\nFax: 215803617\nEndereço eletrónico: pg-af@iefp.pt\nPrazo de interposição do recurso: 30 dias\n\n28 - IDENTIFICAÇÃO DO(S) AUTOR(ES) DE ANÚNCIO\nNome: Maria Isabel Salgado\nCargo: Técnica Superior\n419935198",
    "nipc": "501442600",
    "distrito": "Lisboa",
    "concelho": "Lisboa",
    "freguesia": "Freguesia de Beato",
    "site": "http://www.iefp.pt",
    "email": "pg-af@iefp.pt",
    "designacao_contrato": "Aquisição de serviços especializados para sistemas de backup críticos do Instituto do Emprego e Formação Profissional, I.P.",
    "descricao": "Aquisição de serviços especializados para sistemas de backup críticos do Instituto do Emprego e Formação Profissional, I.P.",
    "preco_base": "90.000,00 EUR",
    "prazo_execucao": "24 MESES",
    "prazo_apresentacao_propostas": "14-01-2026 23:59",
    "fundos_eu": "Não",
    "plataforma_eletronica": "ACIN",
    "url_procedimento": "https://www.acingov.pt",
    "autor_nome": "Maria Isabel Salgado",
    "autor_cargo": "Técnica Superior"
  },
  {
    "numero_procedimento": "N/A",
    "entidade": "Município de Mirandela",
    "link": "https://diariodarepublica.pt/dr/detalhe/contrato-publico/33494-992879854",
    "detalhes_completos": "Alteração do Anúncio de procedimento n.º 32485/2025, de 2025-12-15, com o ID 419881657\n\n1 - IDENTIFICAÇÃO E CONTACTOS DA ENTIDADE ADJUDICANTE\nDesignação da entidade adjudicante: Município de Mirandela\nNIPC: 506881784\nServiço/Órgão/Pessoa de contacto: Subunidade Orgânica de Contratação Pública\nEndereço: Largo do Município\nCódigo postal: 5370-288\nLocalidade: Bragança\nPaís: Portugal\nNUT III: PT11E\nDistrito: Braganca\nConcelho: Mirandela\nFreguesia: Freguesia de Mirandela\nTelefone: 278200200\nFax: 278265753\nEndereço da Entidade (URL): www.cm-mirandela.pt\nEndereço Eletrónico: geral@cm-mirandela.pt\neDelivery Gateway (URL): https://community.vortal.biz/public/\nFunção da Organização: Adquirente\nNorma jurídica da Entidade Adjudicante: Autoridade local\nÁrea de atividade da Autoridade Adjudicante: Serviços públicos das administrações públicas\n\n2 - JORNAL OFICIAL DA UNIÃO EUROPEIA\nO procedimento a que este anúncio diz respeito também é publicitado no Jornal Oficial da União Europeia? Não\n\n3 - AVISO\nModelo de Anúncio: Concurso público\nData de Envio do Anúncio: 29-12-2025\n\n5 - PROCESSO\nTipo de Procedimento: Concurso público\nPreço base do procedimento: Sim\nValor do preço base do procedimento: 22.000,00 EUR\nProcedimento com lotes? Não\n\n6 - OBJETO DO CONTRATO\nNúmero de referência interna: CP1268DAG\nDesignação do contrato: AQUISIÇÃO DE UMA VIATURA MÉDICO-VETERINÁRIA\nDescrição: AQUISIÇÃO DE UMA VIATURA MÉDICO-VETERINÁRIA\nTipo de Contrato Principal: Aquisição de Bens Móveis\nTipo de Contrato: Aquisição de Bens Móveis\nClassificação CPV (Vocabulário Comum para os Contratos Públicos)\nObjeto principal\nVocabulário Principal: 34100000\nPreço base s/IVA: 22.000,00 EUR\n\n7 - INDICAÇÕES ADICIONAIS\nO contrato envolve aquisição conjunta (satisfação de várias entidades)? Não\nO contrato é adjudicado por uma central de compras? Não\n\n8 - TÉCNICAS\nO concurso destina-se à celebração de um acordo-quadro? Inexistência de acordo-quadro\nÉ utilizado um leilão eletrónico? Não\nÉ adotada uma fase de negociação? Não\nSistema de Aquisição Dinâmico: Inexistência de sistema de aquisição dinâmico\n\n9 - LOCAL DA EXECUÇÃO DO CONTRATO\nLOCAL DA EXECUÇÃO DO CONTRATO (PROCEDIMENTO)\nPaís: Portugal\nNUT III: PT11E\nLocalidade: Bragança\nDistrito: Braganca\nConcelho: Mirandela\nFreguesia: Freguesia de Mirandela\n\n10 - PRAZO DE EXECUÇÃO DO CONTRATO\nPrazo de execução do contrato: 90 DIAS\nPrevisão de renovações: Não\n\n11 - FUNDOS EU\nTêm fundos EU? Não\n\n12 - DOCUMENTOS DE HABILITAÇÃO\nHabilitação para o exercício da atividade profissional: Não\n\n13 - CONDIÇÕES DE APRESENTAÇÃO\nPlataforma eletrónica utilizada pela entidade adjudicante: VORTAL\nURL para Apresentação: https://community.vortal.biz/public/\nAdmissibilidade da apresentação de propostas variantes: Não autorizado\nPrazo para apresentação das propostas: 30-12-2025 17:00\nPrazo durante o qual os concorrentes são obrigados a manter as respetivas propostas: 66 dias a contar do termo do prazo para a apresentação das propostas\nApresentação de Catálogo Eletrónico: Permitido\nIndicação de Subcontratação na Proposta: Inexistência de indicação de subcontratação\n\n14 - PRESTAÇÃO DE CAUÇÃO\nPrestação de caução: Não\n\n15 - FORNECIMENTO DAS PEÇAS DO CONCURSO, APRESENTAÇÃO DE PEDIDOS DE PARTICIPAÇÃO E APRESENTAÇÃO DAS PROPOSTAS\nLink para acesso às peças do concurso (URL): https://community.vortal.biz/Public/public-tender-documents/OGJFb1dQZW82bjd3TXRSWkl0WWQ3M09kWnhOR1UrUndLT2ZPNlNiaU1jT0VQZ0hzdGZCZkFLSVVtaGNlN0Z6MUZaZklBaXd5VXJVdGRNWHllK29PeHc9PVhXNWZ6\n\n20 - OUTROS REQUISITOS\nInformação sobre contratos reservados. Aplica-se a contratos reservados (54º-A)? Não\n\n21 - CRITÉRIO DE ADJUDICAÇÃO\nMultifator: Não\nMonofator:\nNome: Preço\n\n24 - CONDIÇÕES DO CONTRATO\nFaturação Eletrónica: Permitido\nObrigação de Subcontratação:\nCódigo da Obrigação de Subcontratação: Não é aplicável nenhuma obrigação de subcontratação.\n\n25 - COMPRA PÚBLICA ESTRATÉGICA\nCompra Pública Estratégica: Inexistência de contratação pública estratégica\n\n26 - INFORMAÇÕES ADICIONAIS\nContrato adequado para PME: Sim\nCobertura ACP (Acordo dos Contratos Públicos da Organização Mundial do Comércio): Não\n\n27 - IDENTIFICAÇÃO E CONTACTOS DO ÓRGÃO DE RECURSOS ADMINISTRATIVOS\nDesignação: Órgão Executivo da Câmara Municipal de Mirandela\nEndereço: Paço dos Távoras, Praça do Município\nCódigo postal: 5370-288\nLocalidade: Mirandela\nTelefone: +351 278200200\nFax: +351 278200200\nEndereço eletrónico: aprovisionamento@cm-mirandela.pt\n\n28 - IDENTIFICAÇÃO DO(S) AUTOR(ES) DE ANÚNCIO\nNome: Vitor Manuel Correia\nCargo: Presidente da Câmara Municipal de Mirandela\n\n29 - ALTERAÇÃO\nMotivo da Alteração: Correção pelo adquirente\nIdentificador da Versão do Anúncio a Alterar: e2d0b7f5-e2c6-4a27-a1fe-0d5aada04eac-01\nIdentificador das Secções Alteradas do Anúncio Anterior: Condições de Apresentação\nDescrição das Alterações: Na sequência do despacho que concede tolerância de ponto para o dia 26 de dezembro de 2025, informa-se que, nos termos da alínea f) do artigo 87.º do Código do Procedimento Administrativo, aplicável por força do n.º 1 do artigo 470.º do Código dos Contratos Públicos, o prazo limite para a apresentação de propostas é alterado, passando a terminar às 17h00 do dia 30 de dezembro de 2025.\nAlteração dos Documentos do Concurso: Não\n419932484",
    "nipc": "506881784",
    "distrito": "Braganca",
    "concelho": "Mirandela",
    "freguesia": "Freguesia de Mirandela",
    "site": "www.cm-mirandela.pt",
    "email": "geral@cm-mirandela.pt",
    "designacao_contrato": "AQUISIÇÃO DE UMA VIATURA MÉDICO-VETERINÁRIA",
    "descricao": "AQUISIÇÃO DE UMA VIATURA MÉDICO-VETERINÁRIA",
    "preco_base": "22.000,00 EUR",
    "prazo_execucao": "90 DIAS",
    "prazo_apresentacao_propostas": "30-12-2025 17:00",
    "fundos_eu": "Não",
    "plataforma_eletronica": "VORTAL",
    "url_procedimento": "https://community.vortal.biz/public/",
    "autor_nome": "Vitor Manuel Correia",
    "autor_cargo": "Presidente da Câmara Municipal de Mirandela"
  },
  {
    "numero_procedimento": "N/A",
    "entidade": "Direção-Geral do Livro, dos Arquivos e das Bibliotecas",
    "link": "https://diariodarepublica.pt/dr/detalhe/contrato-publico/33495-992879855",
    "detalhes_completos": "1 - IDENTIFICAÇÃO E CONTACTOS DA ENTIDADE ADJUDICANTE\nDesignação da entidade adjudicante: Direção-Geral do Livro, dos Arquivos e das Bibliotecas\nNIPC: 600084892\nEndereço: Edifício da Torre do Tombo, Alameda da Universidade\nCódigo postal: 1649-010\nLocalidade: Lisboa\nPaís: Portugal\nNUT III: PT170\nDistrito: Lisboa\nConcelho: Lisboa\nFreguesia: Todas\nTelefone: 210037100\nFax: 210037100\nEndereço da Entidade (URL): https://dglab.gov.pt/\nEndereço Eletrónico: secretariado@dglab.gov.pt\neDelivery Gateway (URL): https://community.vortal.biz/public/\nFunção da Organização: Adquirente\nNorma jurídica da Entidade Adjudicante: Organismo de direito público, controlado por uma autoridade da administração central\nÁrea de atividade da Autoridade Adjudicante: Serviços públicos das administrações públicas\n\n2 - JORNAL OFICIAL DA UNIÃO EUROPEIA\nO procedimento a que este anúncio diz respeito também é publicitado no Jornal Oficial da União Europeia? Não\n\n3 - AVISO\nModelo de Anúncio: Concurso público\nData de Envio do Anúncio: 29-12-2025\n\n5 - PROCESSO\nTipo de Procedimento: Concurso público\nPreço base do procedimento: Sim\nValor do preço base do procedimento: 115.000,00 EUR\nProcedimento com lotes? Não\n\n6 - OBJETO DO CONTRATO\nNúmero de referência interna: Concurso Público n.º 27/2025\nDesignação do contrato: Aquisição de serviços de acondicionamento, rotulagem, transporte, higienização superficial da documentação, arrumação de documentação que constitui o acervo do Arquivo Histórico, Corrente e Intermédio\nDescrição: Aquisição de serviços de acondicionamento, rotulagem, transporte, higienização superficial da documentação, arrumação de documentação que constitui o acervo do Arquivo Histórico, Corrente e Intermédio, e bibliográfico da Biblioteca e Arquivo Histórico da Economia e produção de guias de transporte\nTipo de Contrato Principal: Aquisição de Serviços\nTipo de Contrato: Aquisição de Serviços\nClassificação CPV (Vocabulário Comum para os Contratos Públicos)\nObjeto principal\nVocabulário Principal: 92512000\nPreço base s/IVA: 115.000,00 EUR\n\n7 - INDICAÇÕES ADICIONAIS\nO contrato envolve aquisição conjunta (satisfação de várias entidades)? Não\nO contrato é adjudicado por uma central de compras? Não\n\n8 - TÉCNICAS\nO concurso destina-se à celebração de um acordo-quadro? Inexistência de acordo-quadro\nÉ utilizado um leilão eletrónico? Não\nÉ adotada uma fase de negociação? Não\nSistema de Aquisição Dinâmico: Inexistência de sistema de aquisição dinâmico\n\n9 - LOCAL DA EXECUÇÃO DO CONTRATO\nLOCAL DA EXECUÇÃO DO CONTRATO (PROCEDIMENTO)\nPaís: Portugal\nNUT III: PT170\nLocalidade: Lisboa\nDistrito: Lisboa\nConcelho: Lisboa\nFreguesia: Freguesia de Santo António - Lisboa\n\n10 - PRAZO DE EXECUÇÃO DO CONTRATO\nPrazo de execução do contrato: 5 MESES\nPrevisão de renovações: Não\n\n11 - FUNDOS EU\nTêm fundos EU? Não\n\n12 - DOCUMENTOS DE HABILITAÇÃO\nHabilitação para o exercício da atividade profissional: Sim\nTipo: Certificado\nDescrição: No mínimo um técnico superior com perfil adequado às tarefas solicitadas, nomeadamente, com formação na área dos arquivos [qualquer licenciatura, complementada por pós-graduação/especialização em Ciências Documentais (opção Arquivo) ou por Mestrado na área de arquivo]\n\n13 - CONDIÇÕES DE APRESENTAÇÃO\nPlataforma eletrónica utilizada pela entidade adjudicante: VORTAL\nURL para Apresentação: https://community.vortal.biz/public/\nAdmissibilidade da apresentação de propostas variantes: Não autorizado\nPrazo para apresentação das propostas: 04-01-2026 23:59\nPrazo durante o qual os concorrentes são obrigados a manter as respetivas propostas: 66 dias a contar do termo do prazo para a apresentação das propostas\nIndicação de Subcontratação na Proposta: Inexistência de indicação de subcontratação\n\n14 - PRESTAÇÃO DE CAUÇÃO\nPrestação de caução: Não\n\n15 - FORNECIMENTO DAS PEÇAS DO CONCURSO, APRESENTAÇÃO DE PEDIDOS DE PARTICIPAÇÃO E APRESENTAÇÃO DAS PROPOSTAS\nLink para acesso às peças do concurso (URL): https://community.vortal.biz/Public/public-tender-documents/Ymd6WGFteEkwVHowVDZCMHFIc1hsTWt5VFoxaGtteUZWNjVraGp4NlBhWHFXakJCQnVSVk8yYU5kajh0V0xiQ3RMQWFXT1UxaFE1TGhSTXR5ZHpzTEE9PVkyZVlI\n\n20 - OUTROS REQUISITOS\nInformação sobre contratos reservados. Aplica-se a contratos reservados (54º-A)? Não\n\n21 - CRITÉRIO DE ADJUDICAÇÃO\nMultifator: Não\nMonofator:\nNome: Outros\nOutro nome: Preço\n\n24 - CONDIÇÕES DO CONTRATO\nFaturação Eletrónica: Permitido\nObrigação de Subcontratação:\nCódigo da Obrigação de Subcontratação: Não é aplicável nenhuma obrigação de subcontratação.\n\n25 - COMPRA PÚBLICA ESTRATÉGICA\nCompra Pública Estratégica: Inexistência de contratação pública estratégica\n\n26 - INFORMAÇÕES ADICIONAIS\nContrato adequado para PME: Sim\nCobertura ACP (Acordo dos Contratos Públicos da Organização Mundial do Comércio): Não\n\n27 - IDENTIFICAÇÃO E CONTACTOS DO ÓRGÃO DE RECURSOS ADMINISTRATIVOS\nDesignação: Ministra da Cultura, Juventude e Desporto\nEndereço: Campus XXI, Avenida João XXI, n.º 63, 7.º piso\nCódigo postal: 1000-300\nLocalidade: Lisboa\nTelefone: +351 213927600\nFax: +351 213927600\nEndereço eletrónico: gabinete.mcjd@mcjd.gov.pt\n\n28 - IDENTIFICAÇÃO DO(S) AUTOR(ES) DE ANÚNCIO\nNome: Luís Filipe Reis dos Santos\nCargo: Diretor-Geral \n419935862",
    "nipc": "600084892",
    "distrito": "Lisboa",
    "concelho": "Lisboa",
    "freguesia": "Todas",
    "site": "https://dglab.gov.pt/",
    "email": "secretariado@dglab.gov.pt",
    "designacao_contrato": "Aquisição de serviços de acondicionamento, rotulagem, transporte, higienização superficial da documentação, arrumação de documentação que constitui o acervo do Arquivo Histórico, Corrente e Intermédio",
    "descricao": "Aquisição de serviços de acondicionamento, rotulagem, transporte, higienização superficial da documentação, arrumação de documentação que constitui o acervo do Arquivo Histórico, Corrente e Intermédio, e bibliográfico da Biblioteca e Arquivo Histórico da Economia e produção de guias de transporte",
    "preco_base": "115.000,00 EUR",
    "prazo_execucao": "5 MESES",
    "prazo_apresentacao_propostas": "04-01-2026 23:59",
    "fundos_eu": "Não",
    "plataforma_eletronica": "VORTAL",
    "url_procedimento": "https://community.vortal.biz/public/",
    "autor_nome": "Luís Filipe Reis dos Santos",
    "autor_cargo": "Diretor-Geral"
  },
  {
    "numero_procedimento": "N/A",
    "entidade": "ADENE - Agência para a Energia",
    "link": "https://diariodarepublica.pt/dr/detalhe/contrato-publico/33496-992879856",
    "detalhes_completos": "1 - IDENTIFICAÇÃO E CONTACTOS DA ENTIDADE ADJUDICANTE\nDesignação da entidade adjudicante: ADENE - Agência para a Energia\nNIPC: 501618392\nServiço/Órgão/Pessoa de contacto: Conselho de Administração\nEndereço: Avenida 5 de Outubro, N 208, 2.º Piso\nCódigo postal: 1050-065\nLocalidade: Lisboa\nPaís: Portugal\nNUT III: PTZZZ\nDistrito: Todos\nConcelho: Todos\nFreguesia: Todas\nTelefone: 214722800\nFax: 000000000\nEndereço da Entidade (URL): https://www.adene.pt/\nEndereço Eletrónico: compras@adene.pt\neDelivery Gateway (URL): https://www.acingov.pt\nFunção da Organização: Adquirente\nNorma jurídica da Entidade Adjudicante: Organismo de direito público\nÁrea de atividade da Autoridade Adjudicante: Serviços públicos das administrações públicas\n\n2 - JORNAL OFICIAL DA UNIÃO EUROPEIA\nO procedimento a que este anúncio diz respeito também é publicitado no Jornal Oficial da União Europeia? Não\n\n3 - AVISO\nModelo de Anúncio: Concurso público\nData de Envio do Anúncio: 29-12-2025\n\n5 - PROCESSO\nTipo de Procedimento: Concurso público\nPreço base do procedimento: Sim\nValor do preço base do procedimento: 150.000,00 EUR\nProcedimento com lotes? Não\n\n6 - OBJETO DO CONTRATO\nNúmero de referência interna: ADENE_CP_349_2025_DSM\nDesignação do contrato: ADENE_CP_349_2025_DSM - Concurso Público para a Aquisição de serviços de manutenção corretiva e preventiva, evolução e adaptação do Portal casA+ e do Portal Rede Espaço Energia, em regime de bolsa de horas\nDescrição: ADENE_CP_349_2025_DSM - Aquisição de serviços de manutenção corretiva e preventiva, evolução e adaptação do Portal casA+ e do Portal Rede Espaço Energia, em regime de bolsa de horas\nTipo de Contrato Principal: Aquisição de Serviços\nTipo de Contrato: Aquisição de Serviços\nClassificação CPV (Vocabulário Comum para os Contratos Públicos)\nObjeto principal\nVocabulário Principal: 72212100\nPreço base s/IVA: 150.000,00 EUR\n\n7 - INDICAÇÕES ADICIONAIS\nO contrato envolve aquisição conjunta (satisfação de várias entidades)? Não\nO contrato é adjudicado por uma central de compras? Não\n\n8 - TÉCNICAS\nO concurso destina-se à celebração de um acordo-quadro? Inexistência de acordo-quadro\nÉ utilizado um leilão eletrónico? Não\nÉ adotada uma fase de negociação? Não\nSistema de Aquisição Dinâmico: Inexistência de sistema de aquisição dinâmico\n\n9 - LOCAL DA EXECUÇÃO DO CONTRATO\nLOCAL DA EXECUÇÃO DO CONTRATO (PROCEDIMENTO)\nPaís: Portugal\nNUT III: PTZZZ\nLocalidade: Todas\nDistrito: Todos\nConcelho: Todos\nFreguesia: Todas\n\n10 - PRAZO DE EXECUÇÃO DO CONTRATO\nPrazo de execução do contrato: 3 ANOS\nPrevisão de renovações: Não\n\n11 - FUNDOS EU\nTêm fundos EU? Não\n\n12 - DOCUMENTOS DE HABILITAÇÃO\nHabilitação para o exercício da atividade profissional: Não\n\n13 - CONDIÇÕES DE APRESENTAÇÃO\nPlataforma eletrónica utilizada pela entidade adjudicante: ACIN\nURL para Apresentação: https://www.acingov.pt\nAdmissibilidade da apresentação de propostas variantes: Não autorizado\nPrazo para apresentação das propostas: 19-01-2026 23:59\nPrazo durante o qual os concorrentes são obrigados a manter as respetivas propostas: 120 dias a contar do termo do prazo para a apresentação das propostas\nIndicação de Subcontratação na Proposta: Inexistência de indicação de subcontratação\n\n14 - PRESTAÇÃO DE CAUÇÃO\nPrestação de caução: Não\n\n15 - FORNECIMENTO DAS PEÇAS DO CONCURSO, APRESENTAÇÃO DE PEDIDOS DE PARTICIPAÇÃO E APRESENTAÇÃO DAS PROPOSTAS\nLink para acesso às peças do concurso (URL): https://www.acingov.pt/acingovprod/2/zonaPublica/zona_publica_c/donwloadProcedurePiece/MTAwOTIwMw==\n\n20 - OUTROS REQUISITOS\nInformação sobre contratos reservados. Aplica-se a contratos reservados (54º-A)? Não\n\n21 - CRITÉRIO DE ADJUDICAÇÃO\nMultifator: Sim\nFator: \nNome: Preço\nPonderação: 50%\nSubfatores: Não\nFator: \nNome: Outros\nOutro Nome: Experiência do Gestor de Projeto em Soluções, Tecnologia ou Plataforma\nPonderação: 25%\nSubfatores: Não\nFator: \nNome: Outros\nOutro Nome: Adequação técnica (nas vertentes funcional e tecnológica) da equipa proposta\nPonderação: 25%\nSubfatores: Não\n\n24 - CONDIÇÕES DO CONTRATO\nFaturação Eletrónica: Permitido\nObrigação de Subcontratação:\nCódigo da Obrigação de Subcontratação: Não é aplicável nenhuma obrigação de subcontratação.\n\n25 - COMPRA PÚBLICA ESTRATÉGICA\nCompra Pública Estratégica: Inexistência de contratação pública estratégica\n\n26 - INFORMAÇÕES ADICIONAIS\nContrato adequado para PME: Sim\nCobertura ACP (Acordo dos Contratos Públicos da Organização Mundial do Comércio): Não\n\n27 - IDENTIFICAÇÃO E CONTACTOS DO ÓRGÃO DE RECURSOS ADMINISTRATIVOS\nDesignação: Conselho de Administração\nEndereço: Avenida 5 de Outubro, N 208, 2.º Piso\nCódigo postal: 1050-065\nLocalidade: Lisboa\nTelefone: 214722800\nFax: 000000000\nEndereço eletrónico: compras@adene.pt\nPrazo de interposição do recurso: 5 dias\n\n28 - IDENTIFICAÇÃO DO(S) AUTOR(ES) DE ANÚNCIO\nNome: UJC\nCargo: UJC\n419935562",
    "nipc": "501618392",
    "distrito": "Todos",
    "concelho": "Todos",
    "freguesia": "Todas",
    "site": "https://www.adene.pt/",
    "email": "compras@adene.pt",
    "designacao_contrato": "ADENE_CP_349_2025_DSM - Concurso Público para a Aquisição de serviços de manutenção corretiva e preventiva, evolução e adaptação do Portal casA+ e do Portal Rede Espaço Energia, em regime de bolsa de horas",
    "descricao": "ADENE_CP_349_2025_DSM - Aquisição de serviços de manutenção corretiva e preventiva, evolução e adaptação do Portal casA+ e do Portal Rede Espaço Energia, em regime de bolsa de horas",
    "preco_base": "150.000,00 EUR",
    "prazo_execucao": "3 ANOS",
    "prazo_apresentacao_propostas": "19-01-2026 23:59",
    "fundos_eu": "Não",
    "plataforma_eletronica": "ACIN",
    "url_procedimento": "https://www.acingov.pt",
    "autor_nome": "UJC",
    "autor_cargo": "UJC"
  },
  {
    "numero_procedimento": "N/A",
    "entidade": "Instituto Nacional de Medicina Legal e Ciências Forenses, IP",
    "link": "https://diariodarepublica.pt/dr/detalhe/contrato-publico/33499-992879857",
    "detalhes_completos": "1 - IDENTIFICAÇÃO E CONTACTOS DA ENTIDADE ADJUDICANTE\nDesignação da entidade adjudicante: Instituto Nacional de Medicina Legal e Ciências Forenses, IP\nNIPC: 508203970\nEndereço: Azinhaga de Santa Comba- Pólo das Ciências da Saúde\nCódigo postal: 3000-548\nLocalidade: Coimbra\nPaís: Portugal\nNUT III: PT16E\nDistrito: Coimbra\nConcelho: Coimbra\nFreguesia: Freguesia de Santo António dos Olivais\nTelefone: 239854220\nFax: 239836470\nEndereço da Entidade (URL): www.inml.mj.pt\nEndereço Eletrónico: aprovisionamento.norte@inmlcf.mj.pt\neDelivery Gateway (URL): https://community.vortal.biz/public/\nFunção da Organização: Adquirente\nNorma jurídica da Entidade Adjudicante: Organismo de direito público\nÁrea de atividade da Autoridade Adjudicante: Segurança e ordem pública\n\n2 - JORNAL OFICIAL DA UNIÃO EUROPEIA\nO procedimento a que este anúncio diz respeito também é publicitado no Jornal Oficial da União Europeia? Não\n\n3 - AVISO\nModelo de Anúncio: Concurso público\nData de Envio do Anúncio: 29-12-2025\n\n5 - PROCESSO\nTipo de Procedimento: Concurso público\nPreço base do procedimento: Sim\nValor do preço base do procedimento: 170.560,00 EUR\nProcedimento com lotes? Não\n\n6 - OBJETO DO CONTRATO\nNúmero de referência interna: PN/201/2025 - NPD 5262009693 Cópia\nDesignação do contrato: Aquisição de serviços de recolha, transporte e tratamento de resíduos do tipo hospitalar para o Instituto Nacional de Medicina Legal e Ciências Forenses I.P.\nDescrição: PN/201/2025_NPD 5262009693: Aquisição de serviços de recolha, transporte e tratamento de resíduos do tipo hospitalar para o Instituto Nacional de Medicina Legal e Ciências Forenses I.P.\nTipo de Contrato Principal: Aquisição de Serviços\nTipo de Contrato: Aquisição de Serviços\nClassificação CPV (Vocabulário Comum para os Contratos Públicos)\nObjeto principal\nVocabulário Principal: 90524400\nPreço base s/IVA: 170.560,00 EUR\n\n7 - INDICAÇÕES ADICIONAIS\nO contrato envolve aquisição conjunta (satisfação de várias entidades)? Não\nO contrato é adjudicado por uma central de compras? Não\n\n8 - TÉCNICAS\nO concurso destina-se à celebração de um acordo-quadro? Inexistência de acordo-quadro\nÉ utilizado um leilão eletrónico? Não\nÉ adotada uma fase de negociação? Não\nSistema de Aquisição Dinâmico: Inexistência de sistema de aquisição dinâmico\n\n9 - LOCAL DA EXECUÇÃO DO CONTRATO\nLOCAL DA EXECUÇÃO DO CONTRATO (PROCEDIMENTO)\nPaís: Portugal\nNUT III: PT16E\nLocalidade: Coimbra\nDistrito: Coimbra\nConcelho: Coimbra\nFreguesia: Freguesia de Santo António dos Olivais\n\n10 - PRAZO DE EXECUÇÃO DO CONTRATO\nPrazo de execução do contrato: 2 ANOS\nPrevisão de renovações: Não\n\n11 - FUNDOS EU\nTêm fundos EU? Não\n\n12 - DOCUMENTOS DE HABILITAÇÃO\nHabilitação para o exercício da atividade profissional: Não\n\n13 - CONDIÇÕES DE APRESENTAÇÃO\nPlataforma eletrónica utilizada pela entidade adjudicante: VORTAL\nURL para Apresentação: https://community.vortal.biz/public/\nAdmissibilidade da apresentação de propostas variantes: Não autorizado\nPrazo para apresentação das propostas: 07-01-2026 23:59\nPrazo durante o qual os concorrentes são obrigados a manter as respetivas propostas: 66 dias a contar do termo do prazo para a apresentação das propostas\nIndicação de Subcontratação na Proposta: Inexistência de indicação de subcontratação\n\n14 - PRESTAÇÃO DE CAUÇÃO\nPrestação de caução: Não\n\n15 - FORNECIMENTO DAS PEÇAS DO CONCURSO, APRESENTAÇÃO DE PEDIDOS DE PARTICIPAÇÃO E APRESENTAÇÃO DAS PROPOSTAS\nLink para acesso às peças do concurso (URL): https://community.vortal.biz/Public/public-tender-documents/ZGxsMW1YM0dBUlF4YjZ1UUtteVJrdC83VE9OSURRSmU3QWExNnM2UGpaYW92cHNQU1NzSDlyRlRiR3BPTHdvK3RNdzhhT1k1K3c3eStTNG4vMEFFQ2c9PU5wT1FG\n\n20 - OUTROS REQUISITOS\nInformação sobre contratos reservados. Aplica-se a contratos reservados (54º-A)? Não\n\n21 - CRITÉRIO DE ADJUDICAÇÃO\nMultifator: Não\nMonofator:\nNome: Preço\n\n24 - CONDIÇÕES DO CONTRATO\nFaturação Eletrónica: Permitido\nObrigação de Subcontratação:\nCódigo da Obrigação de Subcontratação: Não é aplicável nenhuma obrigação de subcontratação.\n\n25 - COMPRA PÚBLICA ESTRATÉGICA\nCompra Pública Estratégica: Inexistência de contratação pública estratégica\n\n26 - INFORMAÇÕES ADICIONAIS\nContrato adequado para PME: Sim\nCobertura ACP (Acordo dos Contratos Públicos da Organização Mundial do Comércio): Não\n\n27 - IDENTIFICAÇÃO E CONTACTOS DO ÓRGÃO DE RECURSOS ADMINISTRATIVOS\nDesignação: Conselho Diretivo\nEndereço: Azinhaga de Santa Comba, Polo das Ciências da Saúde (Polo III)\nCódigo postal: 3000-548\nLocalidade: Coimbra\nTelefone: +351 239854220\nFax: +351 239854220\nEndereço eletrónico: correio@inmlcf.mj.pt\n\n28 - IDENTIFICAÇÃO DO(S) AUTOR(ES) DE ANÚNCIO\nNome: Nuno Ferreira de Almeida\nCargo: Diretor do Departamento de Administração Geral\n419935376",
    "nipc": "508203970",
    "distrito": "Coimbra",
    "concelho": "Coimbra",
    "freguesia": "Freguesia de Santo António dos Olivais",
    "site": "www.inml.mj.pt",
    "email": "aprovisionamento.norte@inmlcf.mj.pt",
    "designacao_contrato": "Aquisição de serviços de recolha, transporte e tratamento de resíduos do tipo hospitalar para o Instituto Nacional de Medicina Legal e Ciências Forenses I.P.",
    "descricao": "PN/201/2025_NPD 5262009693: Aquisição de serviços de recolha, transporte e tratamento de resíduos do tipo hospitalar para o Instituto Nacional de Medicina Legal e Ciências Forenses I.P.",
    "preco_base": "170.560,00 EUR",
    "prazo_execucao": "2 ANOS",
    "prazo_apresentacao_propostas": "07-01-2026 23:59",
    "fundos_eu": "Não",
    "plataforma_eletronica": "VORTAL",
    "url_procedimento": "https://community.vortal.biz/public/",
    "autor_nome": "Nuno Ferreira de Almeida",
    "autor_cargo": "Diretor do Departamento de Administração Geral"
  },
  {
    "numero_procedimento": "N/A",
    "entidade": "Estado-Maior do Exército",
    "link": "https://diariodarepublica.pt/dr/detalhe/contrato-publico/33500-992879858",
    "detalhes_completos": "1 - IDENTIFICAÇÃO E CONTACTOS DA ENTIDADE ADJUDICANTE\nDesignação da entidade adjudicante: Estado-Maior do Exército\nNIPC: 600021610\nEndereço: Avenida Infante Santo, 49, 2º piso\nCódigo postal: 1399-056\nLocalidade: Lisboa\nPaís: Portugal\nNUT III: PT170\nDistrito: Lisboa\nConcelho: Lisboa\nFreguesia: Freguesia da Estrela\nTelefone: 213912000\nFax: 213912000\nEndereço da Entidade (URL): https://www.exercito.pt/\nEndereço Eletrónico: cmdlog@exercito.pt\neDelivery Gateway (URL): https://www.acingov.pt\nFunção da Organização: Adquirente\nSubfunção da Organização: Organização cujo orçamento é utilizado para pagar o contrato; Organização que executa o pagamento; Organização que fornece mais informações sobre os prazos dos procedimentos de recurso; Organização responsável pelo tratamento das propostas; Organização que recebe as propostas; Organização que trata os pedidos de participação; Organização que recebe pedidos de participação; Organização que assina o contrato\nNorma jurídica da Entidade Adjudicante: Organismo de direito público\nÁrea de atividade da Autoridade Adjudicante: Defesa\n\n2 - JORNAL OFICIAL DA UNIÃO EUROPEIA\nO procedimento a que este anúncio diz respeito também é publicitado no Jornal Oficial da União Europeia? Não\n\n3 - AVISO\nModelo de Anúncio: Concurso público\nData de Envio do Anúncio: 29-12-2025\n\n5 - PROCESSO\nTipo de Procedimento: Concurso público\nPreço base do procedimento: Sim\nValor do preço base do procedimento: 172.280,00 EUR\nProcedimento com lotes? Não\n\n6 - OBJETO DO CONTRATO\nNúmero de referência interna: EOP 40.341.115.039/25 R2\nDesignação do contrato: 4025026705/DA/ EOP 40.341.115.039/25 R2 - PM 049/LISBOA - Fábrica Militar de Santa Clara - \"Remodelação da rede elétrica para instalação do CPVFE\"\nDescrição: 4025026705/DA/ EOP 40.341.115.039/25 R2 - PM 049/LISBOA - Fábrica Militar de Santa Clara - \"Remodelação da rede elétrica para instalação do CPVFE\"\nTipo de Contrato Principal: Empreitada de Obras Públicas\nTipo de Contrato: Empreitada de Obras Públicas\nClassificação CPV (Vocabulário Comum para os Contratos Públicos)\nObjeto principal\nVocabulário Principal: 45310000\nPreço base s/IVA: 172.280,00 EUR\n\n7 - INDICAÇÕES ADICIONAIS\nO contrato envolve aquisição conjunta (satisfação de várias entidades)? Não\nO contrato é adjudicado por uma central de compras? Não\n\n8 - TÉCNICAS\nO concurso destina-se à celebração de um acordo-quadro? Inexistência de acordo-quadro\nÉ utilizado um leilão eletrónico? Não\nÉ adotada uma fase de negociação? Não\nSistema de Aquisição Dinâmico: Inexistência de sistema de aquisição dinâmico\n\n9 - LOCAL DA EXECUÇÃO DO CONTRATO\nLOCAL DA EXECUÇÃO DO CONTRATO (PROCEDIMENTO)\nPaís: Portugal\nNUT III: PT170\nLocalidade: Freguesia de São Vicente\nDistrito: Lisboa\nConcelho: Lisboa\nFreguesia: Freguesia de São Vicente\n\n10 - PRAZO DE EXECUÇÃO DO CONTRATO\nPrazo de execução do contrato: 120 DIAS\nPrevisão de renovações: Não\n\n11 - FUNDOS EU\nTêm fundos EU? Não\n\n12 - DOCUMENTOS DE HABILITAÇÃO\nHabilitação para o exercício da atividade profissional: Sim\nTipo: Alvará\nDescrição: (1) 5ª Subcategoria da 1ª Categoria, em classe que cubra o valor global da proposta; \n(2) 8ª Subcategoria da 1ª Categoria; 9ª Subcategoria da 1ª Categoria; 1ª Subcategoria da 4ª Categoria; 2ª Subcategoria da 5ª Categoria, em classes que cubram o valor dos trabalhos a que respeitem\n\n13 - CONDIÇÕES DE APRESENTAÇÃO\nPlataforma eletrónica utilizada pela entidade adjudicante: ACIN\nURL para Apresentação: https://www.acingov.pt\nAdmissibilidade da apresentação de propostas variantes: Não autorizado\nPrazo para apresentação das propostas: 19-01-2026 23:59\nPrazo durante o qual os concorrentes são obrigados a manter as respetivas propostas: 90 dias a contar do termo do prazo para a apresentação das propostas\nIndicação de Subcontratação na Proposta: Inexistência de indicação de subcontratação\n\n14 - PRESTAÇÃO DE CAUÇÃO\nPrestação de caução: Sim\nPercentagem: 5%\nDescrição da Garantia Exigida: O valor da caução é de 5.00% do preço contratual.\n\n15 - FORNECIMENTO DAS PEÇAS DO CONCURSO, APRESENTAÇÃO DE PEDIDOS DE PARTICIPAÇÃO E APRESENTAÇÃO DAS PROPOSTAS\nLink para acesso às peças do concurso (URL): https://www.acingov.pt/acingovprod/2/zonaPublica/zona_publica_c/donwloadProcedurePiece/MTAwNzU2Mw==\n\n20 - OUTROS REQUISITOS\nInformação sobre contratos reservados. Aplica-se a contratos reservados (54º-A)? Não\n\n21 - CRITÉRIO DE ADJUDICAÇÃO\nMultifator: Não\nMonofator:\nNome: Preço\n\n24 - CONDIÇÕES DO CONTRATO\nFaturação Eletrónica: Permitido\nObrigação de Subcontratação:\nCódigo da Obrigação de Subcontratação: Não é aplicável nenhuma obrigação de subcontratação.\n\n25 - COMPRA PÚBLICA ESTRATÉGICA\nCompra Pública Estratégica: Inexistência de contratação pública estratégica\n\n26 - INFORMAÇÕES ADICIONAIS\nContrato adequado para PME: Sim\nCobertura ACP (Acordo dos Contratos Públicos da Organização Mundial do Comércio): Não\n\n27 - IDENTIFICAÇÃO E CONTACTOS DO ÓRGÃO DE RECURSOS ADMINISTRATIVOS\nDesignação: Chefe de Estado-Maior do Exército\nEndereço: Campo de Santa Clara\nCódigo postal: 1149-056\nLocalidade: Lisboa\nTelefone: 218815700\nFax: 218815712\nEndereço eletrónico: die@exercito.pt\n\n28 - IDENTIFICAÇÃO DO(S) AUTOR(ES) DE ANÚNCIO\nNome: Brigadeiro-General Albino Marques Lameiras\nCargo: Diretor de Aquisições\n419935068",
    "nipc": "600021610",
    "distrito": "Lisboa",
    "concelho": "Lisboa",
    "freguesia": "Freguesia da Estrela",
    "site": "https://www.exercito.pt/",
    "email": "cmdlog@exercito.pt",
    "designacao_contrato": "4025026705/DA/ EOP 40.341.115.039/25 R2 - PM 049/LISBOA - Fábrica Militar de Santa Clara - \"Remodelação da rede elétrica para instalação do CPVFE\"",
    "descricao": "4025026705/DA/ EOP 40.341.115.039/25 R2 - PM 049/LISBOA - Fábrica Militar de Santa Clara - \"Remodelação da rede elétrica para instalação do CPVFE\"",
    "preco_base": "172.280,00 EUR",
    "prazo_execucao": "120 DIAS",
    "prazo_apresentacao_propostas": "19-01-2026 23:59",
    "fundos_eu": "Não",
    "plataforma_eletronica": "ACIN",
    "url_procedimento": "https://www.acingov.pt",
    "autor_nome": "Brigadeiro-General Albino Marques Lameiras",
    "autor_cargo": "Diretor de Aquisições"
  },
  {
    "numero_procedimento": "N/A",
    "entidade": "Município de Alenquer",
    "link": "https://diariodarepublica.pt/dr/detalhe/contrato-publico/33501-992879859",
    "detalhes_completos": "1 - IDENTIFICAÇÃO E CONTACTOS DA ENTIDADE ADJUDICANTE\nDesignação da entidade adjudicante: Município de Alenquer\nNIPC: 501305734\nServiço/Órgão/Pessoa de contacto: Divisão de Contratação Pública\nEndereço: Praça Luís de Camões\nCódigo postal: 2580-318\nLocalidade: Alenquer\nPaís: Portugal\nNUT III: PT16B\nDistrito: Lisboa\nConcelho: Alenquer\nFreguesia: União das Freguesias de Alenquer (Santo Estêvão e Triana)\nTelefone: 263730900\nFax: 263711504\nEndereço da Entidade (URL): www.cm-alenquer.pt\nEndereço Eletrónico: contratacao.publica@cm-alenquer.pt\neDelivery Gateway (URL): https://www.acingov.pt\nFunção da Organização: Adquirente\nNorma jurídica da Entidade Adjudicante: Organismo de direito público\nÁrea de atividade da Autoridade Adjudicante: Serviços públicos das administrações públicas\n\n2 - JORNAL OFICIAL DA UNIÃO EUROPEIA\nO procedimento a que este anúncio diz respeito também é publicitado no Jornal Oficial da União Europeia? Não\n\n3 - AVISO\nModelo de Anúncio: Concurso público\nData de Envio do Anúncio: 29-12-2025\n\n5 - PROCESSO\nTipo de Procedimento: Concurso público\nPreço base do procedimento: Sim\nValor do preço base do procedimento: 197.187,40 EUR\nProcedimento com lotes? Não\n\n6 - OBJETO DO CONTRATO\nNúmero de referência interna: Proc. 151/2025\nDesignação do contrato: Proc. 151/2025_CMA: fornecimento contínuo de leite escolar aos estabelecimentos de educação pré-escolar e do 1º ciclo do ensino básico dos quatro Agrupamentos de Escolas do Município de Alenquer\nDescrição: Fornecimento contínuo de leite escolar aos estabelecimentos de educação pré-escolar e do 1º ciclo do ensino básico dos quatro Agrupamentos de Escolas do Município de Alenquer\nTipo de Contrato Principal: Aquisição de Bens Móveis\nTipo de Contrato: Aquisição de Bens Móveis\nClassificação CPV (Vocabulário Comum para os Contratos Públicos)\nObjeto principal\nVocabulário Principal: 15511000\nPreço base s/IVA: 197.187,40 EUR\n\n7 - INDICAÇÕES ADICIONAIS\nO contrato envolve aquisição conjunta (satisfação de várias entidades)? Não\nO contrato é adjudicado por uma central de compras? Não\n\n8 - TÉCNICAS\nO concurso destina-se à celebração de um acordo-quadro? Inexistência de acordo-quadro\nÉ utilizado um leilão eletrónico? Não\nÉ adotada uma fase de negociação? Não\nSistema de Aquisição Dinâmico: Inexistência de sistema de aquisição dinâmico\n\n9 - LOCAL DA EXECUÇÃO DO CONTRATO\nLOCAL DA EXECUÇÃO DO CONTRATO (PROCEDIMENTO)\nPaís: Portugal\nNUT III: PT16B\nLocalidade: Alenquer\nDistrito: Lisboa\nConcelho: Alenquer\nFreguesia: Todas\n\n10 - PRAZO DE EXECUÇÃO DO CONTRATO\nPrazo de execução do contrato: 12 MESES\nPrevisão de renovações: Sim\nIndicar número máximo de renovações: 1\nPrazo de renovações diferente do prazo inicial: Não\n\n11 - FUNDOS EU\nTêm fundos EU? Não\n\n12 - DOCUMENTOS DE HABILITAÇÃO\nHabilitação para o exercício da atividade profissional: Não\n\n13 - CONDIÇÕES DE APRESENTAÇÃO\nPlataforma eletrónica utilizada pela entidade adjudicante: ACIN\nURL para Apresentação: https://www.acingov.pt\nAdmissibilidade da apresentação de propostas variantes: Não autorizado\nPrazo para apresentação das propostas: 07-01-2026 23:59\nPrazo durante o qual os concorrentes são obrigados a manter as respetivas propostas: 66 dias a contar do termo do prazo para a apresentação das propostas\nIndicação de Subcontratação na Proposta: Inexistência de indicação de subcontratação\n\n14 - PRESTAÇÃO DE CAUÇÃO\nPrestação de caução: Não\n\n15 - FORNECIMENTO DAS PEÇAS DO CONCURSO, APRESENTAÇÃO DE PEDIDOS DE PARTICIPAÇÃO E APRESENTAÇÃO DAS PROPOSTAS\nLink para acesso às peças do concurso (URL): https://www.acingov.pt/acingovprod/2/zonaPublica/zona_publica_c/donwloadProcedurePiece/MTAwOTE1NA==\n\n20 - OUTROS REQUISITOS\nInformação sobre contratos reservados. Aplica-se a contratos reservados (54º-A)? Não\n\n21 - CRITÉRIO DE ADJUDICAÇÃO\nMultifator: Não\nMonofator:\nNome: Outros\nOutro nome: Fator Preço\n\n24 - CONDIÇÕES DO CONTRATO\nFaturação Eletrónica: Permitido\nObrigação de Subcontratação:\nCódigo da Obrigação de Subcontratação: Não é aplicável nenhuma obrigação de subcontratação.\n\n25 - COMPRA PÚBLICA ESTRATÉGICA\nCompra Pública Estratégica: Realização dos objetivos sociais\nCategorias da estratégia nacional: Outros\nOutra categoria (Descrição): N/A\nContratos Públicos Sociais: Outros\nCritério de Acessibilidade: Os critérios de acessibilidade para as pessoas com deficiência não estão incluídos porque o contrato não se destina a pessoas singulares\n\n26 - INFORMAÇÕES ADICIONAIS\nContrato adequado para PME: Sim\nCobertura ACP (Acordo dos Contratos Públicos da Organização Mundial do Comércio): Não\n\n27 - IDENTIFICAÇÃO E CONTACTOS DO ÓRGÃO DE RECURSOS ADMINISTRATIVOS\nDesignação: Câmara Municipal de Alenquer\nEndereço: Praça Luís de Camões, Alenquer.\nCódigo postal: 2580-318\nLocalidade: Alenquer\nTelefone: 263370900\nFax: \nEndereço eletrónico: contratacao.publica@cm-alenquer.pt\nPrazo de interposição do recurso: 5 dias\n\n28 - IDENTIFICAÇÃO DO(S) AUTOR(ES) DE ANÚNCIO\nNome: João Miguel Maçarico Nicolau\nCargo: Presidente da Câmara\n419935765",
    "nipc": "501305734",
    "distrito": "Lisboa",
    "concelho": "Alenquer",
    "freguesia": "União das Freguesias de Alenquer (Santo Estêvão e Triana)",
    "site": "www.cm-alenquer.pt",
    "email": "contratacao.publica@cm-alenquer.pt",
    "designacao_contrato": "Proc. 151/2025_CMA: fornecimento contínuo de leite escolar aos estabelecimentos de educação pré-escolar e do 1º ciclo do ensino básico dos quatro Agrupamentos de Escolas do Município de Alenquer",
    "descricao": "Fornecimento contínuo de leite escolar aos estabelecimentos de educação pré-escolar e do 1º ciclo do ensino básico dos quatro Agrupamentos de Escolas do Município de Alenquer",
    "preco_base": "197.187,40 EUR",
    "prazo_execucao": "12 MESES",
    "prazo_apresentacao_propostas": "07-01-2026 23:59",
    "fundos_eu": "Não",
    "plataforma_eletronica": "ACIN",
    "url_procedimento": "https://www.acingov.pt",
    "autor_nome": "João Miguel Maçarico Nicolau",
    "autor_cargo": "Presidente da Câmara"
  },
  {
    "numero_procedimento": "N/A",
    "entidade": "Unidade Local de Saúde da Região de Leiria, EPE",
    "link": "https://diariodarepublica.pt/dr/detalhe/contrato-publico/33505-992879860",
    "detalhes_completos": "1 - IDENTIFICAÇÃO E CONTACTOS DA ENTIDADE ADJUDICANTE\nDesignação da entidade adjudicante: Unidade Local de Saúde da Região de Leiria, EPE\nNIPC: 509822932\nEndereço: Rua das Olhalvas, Pousos\nCódigo postal: 2410-197\nLocalidade: Leiria\nPaís: Portugal\nNUT III: PT16F\nDistrito: Leiria\nConcelho: Leiria\nFreguesia: União das Freguesias de Leiria, Pousos, Barreira e Cortes\nTelefone: 244817010\nEndereço da Entidade (URL): https://www.ulsrl.min-saude.pt\nEndereço Eletrónico: aprovisionamento.geral@ulsrl.min-saude.pt\neDelivery Gateway (URL): https://community.vortal.biz/public/\nFunção da Organização: Adquirente\nNorma jurídica da Entidade Adjudicante: Empresa pública, controlada por uma autoridade da administração central\nÁrea de atividade da Autoridade Adjudicante: Saúde\n\n2 - JORNAL OFICIAL DA UNIÃO EUROPEIA\nO procedimento a que este anúncio diz respeito também é publicitado no Jornal Oficial da União Europeia? Não\n\n3 - AVISO\nModelo de Anúncio: Concurso público\nData de Envio do Anúncio: 29-12-2025\n\n5 - PROCESSO\nTipo de Procedimento: Concurso público\nPreço base do procedimento: Sim\nValor do preço base do procedimento: 54.155,00 EUR\nProcedimento com lotes? Sim\nNº Máx. de Lotes Autorizado: 5\nNúmero máximo de lotes que podem ser adjudicados a um concorrente: 5\n\n6 - OBJETO DO CONTRATO\nNúmero de referência interna: A2/95/2026 - Material Diverso de Urologia\nDesignação do contrato: A2/95/2026 - Material Diverso de Urologia\nDescrição: A2/95/2026 - Material Diverso de Urologia\nTipo de Contrato Principal: Aquisição de Bens Móveis\nTipo de Contrato: Aquisição de Bens Móveis\nClassificação CPV (Vocabulário Comum para os Contratos Públicos)\nObjeto principal\nVocabulário Principal: 33140000\nPreço base s/IVA: 54.155,00 EUR\nLotes: \nNº: LOT-0001\nDescrição do Lote: Lote 1\nPreço base s/IVA: 8.350,00 EUR\nClassificação CPV (Vocabulário Comum para os Contratos Públicos)\nObjeto principal\nVocabulário Principal: 33140000\nNº: LOT-0002\nDescrição do Lote: Lote 2\nPreço base s/IVA: 749,50 EUR\nClassificação CPV (Vocabulário Comum para os Contratos Públicos)\nObjeto principal\nVocabulário Principal: 33140000\nNº: LOT-0003\nDescrição do Lote: Lote 3\nPreço base s/IVA: 3.645,50 EUR\nClassificação CPV (Vocabulário Comum para os Contratos Públicos)\nObjeto principal\nVocabulário Principal: 33140000\nNº: LOT-0004\nDescrição do Lote: Lote 4\nPreço base s/IVA: 39.150,00 EUR\nClassificação CPV (Vocabulário Comum para os Contratos Públicos)\nObjeto principal\nVocabulário Principal: 33140000\nNº: LOT-0005\nDescrição do Lote: Lote 5\nPreço base s/IVA: 2.260,00 EUR\nClassificação CPV (Vocabulário Comum para os Contratos Públicos)\nObjeto principal\nVocabulário Principal: 33140000\n\n7 - INDICAÇÕES ADICIONAIS\nO contrato envolve aquisição conjunta (satisfação de várias entidades)? Não\nO contrato é adjudicado por uma central de compras? Não\n\n8 - TÉCNICAS\nO concurso destina-se à celebração de um acordo-quadro? Inexistência de acordo-quadro\nÉ utilizado um leilão eletrónico? Não\nÉ adotada uma fase de negociação? Não\nSistema de Aquisição Dinâmico: Inexistência de sistema de aquisição dinâmico\n\n9 - LOCAL DA EXECUÇÃO DO CONTRATO\nLOCAL DA EXECUÇÃO DO CONTRATO (PROCEDIMENTO)\nPaís: Portugal\nNUT III: PT16F\nLocalidade: Leiria\nDistrito: Leiria\nConcelho: Leiria\nFreguesia: Todas\nLOCAL DA EXECUÇÃO DO CONTRATO (LOTE)\nIdentificador do Lote: LOT-0001; LOT-0002; LOT-0003; LOT-0004; LOT-0005\nPaís: Portugal\nNUT III: PT16F\nLocalidade: Leiria\nDistrito: Leiria\nConcelho: Leiria\nFreguesia: Todas\n\n10 - PRAZO DE EXECUÇÃO DO CONTRATO\nIdentificador do Lote: LOT-0001; LOT-0002; LOT-0003; LOT-0004; LOT-0005\nPrazo de execução do contrato: 24 MESES\nPrevisão de renovações: Não\n\n11 - FUNDOS EU\nIdentificador do Lote: LOT-0001; LOT-0002; LOT-0003; LOT-0004; LOT-0005\nTêm fundos EU? Não\n\n12 - DOCUMENTOS DE HABILITAÇÃO\nHabilitação para o exercício da atividade profissional: Não\n\n13 - CONDIÇÕES DE APRESENTAÇÃO\nPlataforma eletrónica utilizada pela entidade adjudicante: VORTAL\nURL para Apresentação: https://community.vortal.biz/public/\nAdmissibilidade da apresentação de propostas variantes: Não autorizado\nPrazo para apresentação das propostas: 08-01-2026 18:00\nPrazo durante o qual os concorrentes são obrigados a manter as respetivas propostas: 90 dias a contar do termo do prazo para a apresentação das propostas\nIndicação de Subcontratação na Proposta: Inexistência de indicação de subcontratação\n\n14 - PRESTAÇÃO DE CAUÇÃO\nPrestação de caução: Não\n\n15 - FORNECIMENTO DAS PEÇAS DO CONCURSO, APRESENTAÇÃO DE PEDIDOS DE PARTICIPAÇÃO E APRESENTAÇÃO DAS PROPOSTAS\nLink para acesso às peças do concurso (URL): https://community.vortal.biz/Public/public-tender-documents/ZDNvUDhYeSthUEZPeTNPZnJ6S09VQ2N4M3Y3S21NZ1dkb2IyUGhOQlFITlcycWdyNlExdGIveVI5N1luamlnYm1JNmZLaVB1Q2NGUFlJUmJRS1hEemc9PVNEMiMq\n\n20 - OUTROS REQUISITOS\nIdentificador do Lote: LOT-0001; LOT-0002; LOT-0003; LOT-0004; LOT-0005\nInformação sobre contratos reservados. Aplica-se a contratos reservados (54º-A)? Não\n\n21 - CRITÉRIO DE ADJUDICAÇÃO\nO Critério de adjudicação é diferenciado por lote? Não\nMultifator: Sim\nFator: \nNome: Preço\nPonderação: 60%\nSubfatores: Não\nFator: \nNome: Qualidade\nPonderação: 40%\nSubfatores: Não\n\n24 - CONDIÇÕES DO CONTRATO\nIdentificador do Lote: LOT-0001; LOT-0002; LOT-0003; LOT-0004; LOT-0005\nFaturação Eletrónica: Permitido\nObrigação de Subcontratação:\nCódigo da Obrigação de Subcontratação: Não é aplicável nenhuma obrigação de subcontratação.\n\n25 - COMPRA PÚBLICA ESTRATÉGICA\nCompra Pública Estratégica: Inexistência de contratação pública estratégica\n\n26 - INFORMAÇÕES ADICIONAIS\nIdentificador do Lote: LOT-0001; LOT-0002; LOT-0003; LOT-0004; LOT-0005\nContrato adequado para PME: Sim\nCobertura ACP (Acordo dos Contratos Públicos da Organização Mundial do Comércio): Não\n\n27 - IDENTIFICAÇÃO E CONTACTOS DO ÓRGÃO DE RECURSOS ADMINISTRATIVOS\nDesignação: Unidade Local de Saúde da Região de Leiria\nEndereço: Rua das Olhalvas\nCódigo postal: 2425-197\nLocalidade: Leiria\nTelefone: +351 244817010\nFax: +351 244817000\nEndereço eletrónico: secca@ulsrl.min-saude.pt\n\n28 - IDENTIFICAÇÃO DO(S) AUTOR(ES) DE ANÚNCIO\nNome: Manuel José Santos de Carvalho\nCargo: Presidente do Conselho de Administração\n419933959",
    "nipc": "509822932",
    "distrito": "Leiria",
    "concelho": "Leiria",
    "freguesia": "União das Freguesias de Leiria, Pousos, Barreira e Cortes",
    "site": "https://www.ulsrl.min-saude.pt",
    "email": "aprovisionamento.geral@ulsrl.min-saude.pt",
    "designacao_contrato": "A2/95/2026 - Material Diverso de Urologia",
    "descricao": "A2/95/2026 - Material Diverso de Urologia",
    "preco_base": "54.155,00 EUR",
    "prazo_execucao": "24 MESES",
    "prazo_apresentacao_propostas": "08-01-2026 18:00",
    "fundos_eu": "Não",
    "plataforma_eletronica": "VORTAL",
    "url_procedimento": "https://community.vortal.biz/public/",
    "autor_nome": "Manuel José Santos de Carvalho",
    "autor_cargo": "Presidente do Conselho de Administração"
  },
  {
    "numero_procedimento": "N/A",
    "entidade": "Unidade Local de Saúde da Região de Leiria, EPE",
    "link": "https://diariodarepublica.pt/dr/detalhe/contrato-publico/33506-992879861",
    "detalhes_completos": "1 - IDENTIFICAÇÃO E CONTACTOS DA ENTIDADE ADJUDICANTE\nDesignação da entidade adjudicante: Unidade Local de Saúde da Região de Leiria, EPE\nNIPC: 509822932\nEndereço: Rua das Olhalvas, Pousos\nCódigo postal: 2410-197\nLocalidade: Leiria\nPaís: Portugal\nNUT III: PT16F\nDistrito: Leiria\nConcelho: Leiria\nFreguesia: União das Freguesias de Leiria, Pousos, Barreira e Cortes\nTelefone: 244817010\nEndereço da Entidade (URL): https://www.ulsrl.min-saude.pt\nEndereço Eletrónico: aprovisionamento.geral@ulsrl.min-saude.pt\neDelivery Gateway (URL): https://community.vortal.biz/public/\nFunção da Organização: Adquirente\nNorma jurídica da Entidade Adjudicante: Empresa pública, controlada por uma autoridade da administração central\nÁrea de atividade da Autoridade Adjudicante: Saúde\n\n2 - JORNAL OFICIAL DA UNIÃO EUROPEIA\nO procedimento a que este anúncio diz respeito também é publicitado no Jornal Oficial da União Europeia? Não\n\n3 - AVISO\nModelo de Anúncio: Concurso público\nData de Envio do Anúncio: 29-12-2025\n\n5 - PROCESSO\nTipo de Procedimento: Concurso público\nPreço base do procedimento: Sim\nValor do preço base do procedimento: 21.585,60 EUR\nProcedimento com lotes? Não\n\n6 - OBJETO DO CONTRATO\nNúmero de referência interna: A6/102/2026 – Baterias de UPS’s e Similares \nDesignação do contrato: A6/102/2026 – Baterias de UPS’s e Similares - 2026\nDescrição: A6/102/2026 – Baterias de UPS’s e Similares - 2026\nTipo de Contrato Principal: Aquisição de Bens Móveis\nTipo de Contrato: Aquisição de Bens Móveis\nClassificação CPV (Vocabulário Comum para os Contratos Públicos)\nObjeto principal\nVocabulário Principal: 31400000\nPreço base s/IVA: 21.585,60 EUR\n\n7 - INDICAÇÕES ADICIONAIS\nO contrato envolve aquisição conjunta (satisfação de várias entidades)? Não\nO contrato é adjudicado por uma central de compras? Não\n\n8 - TÉCNICAS\nO concurso destina-se à celebração de um acordo-quadro? Inexistência de acordo-quadro\nÉ utilizado um leilão eletrónico? Não\nÉ adotada uma fase de negociação? Não\nSistema de Aquisição Dinâmico: Inexistência de sistema de aquisição dinâmico\n\n9 - LOCAL DA EXECUÇÃO DO CONTRATO\nLOCAL DA EXECUÇÃO DO CONTRATO (PROCEDIMENTO)\nPaís: Portugal\nNUT III: PT16F\nLocalidade: Leiria\nDistrito: Leiria\nConcelho: Leiria\nFreguesia: Todas\n\n10 - PRAZO DE EXECUÇÃO DO CONTRATO\nPrazo de execução do contrato: 60 DIAS\nPrevisão de renovações: Não\n\n11 - FUNDOS EU\nTêm fundos EU? Não\n\n12 - DOCUMENTOS DE HABILITAÇÃO\nHabilitação para o exercício da atividade profissional: Não\n\n13 - CONDIÇÕES DE APRESENTAÇÃO\nPlataforma eletrónica utilizada pela entidade adjudicante: VORTAL\nURL para Apresentação: https://community.vortal.biz/public/\nAdmissibilidade da apresentação de propostas variantes: Não autorizado\nPrazo para apresentação das propostas: 19-01-2026 18:00\nPrazo durante o qual os concorrentes são obrigados a manter as respetivas propostas: 90 dias a contar do termo do prazo para a apresentação das propostas\nIndicação de Subcontratação na Proposta: Inexistência de indicação de subcontratação\n\n14 - PRESTAÇÃO DE CAUÇÃO\nPrestação de caução: Não\n\n15 - FORNECIMENTO DAS PEÇAS DO CONCURSO, APRESENTAÇÃO DE PEDIDOS DE PARTICIPAÇÃO E APRESENTAÇÃO DAS PROPOSTAS\nLink para acesso às peças do concurso (URL): https://community.vortal.biz/Public/public-tender-documents/eFNHMWpBQ1Q0Mk54N3BSeEdtanEvRkpmNHR4RjU2c0NDRXdFL0RORlJjR0VXMkovRGdUWUtjME8wSFl4RUtaaWxEbmJzeWR4V2UzZDlHaEFBOE5veUE9PUpRUzRT\n\n20 - OUTROS REQUISITOS\nInformação sobre contratos reservados. Aplica-se a contratos reservados (54º-A)? Não\n\n21 - CRITÉRIO DE ADJUDICAÇÃO\nMultifator: Não\nMonofator:\nNome: Preço\n\n24 - CONDIÇÕES DO CONTRATO\nFaturação Eletrónica: Permitido\nObrigação de Subcontratação:\nCódigo da Obrigação de Subcontratação: Não é aplicável nenhuma obrigação de subcontratação.\n\n25 - COMPRA PÚBLICA ESTRATÉGICA\nCompra Pública Estratégica: Inexistência de contratação pública estratégica\n\n26 - INFORMAÇÕES ADICIONAIS\nContrato adequado para PME: Sim\nCobertura ACP (Acordo dos Contratos Públicos da Organização Mundial do Comércio): Não\n\n27 - IDENTIFICAÇÃO E CONTACTOS DO ÓRGÃO DE RECURSOS ADMINISTRATIVOS\nDesignação: Conselho de Administração\nEndereço: Rua das Olhalvas - Pousos\nCódigo postal: 2410-197\nLocalidade: Leiria\nTelefone: +351 244817010\nFax: +351 244817010\nEndereço eletrónico: secca@ulsrl.min-saude.pt\n\n28 - IDENTIFICAÇÃO DO(S) AUTOR(ES) DE ANÚNCIO\nNome: Manuel José Santos de Carvalho\nCargo: Presidente do Conselho de Administração\n419934703",
    "nipc": "509822932",
    "distrito": "Leiria",
    "concelho": "Leiria",
    "freguesia": "União das Freguesias de Leiria, Pousos, Barreira e Cortes",
    "site": "https://www.ulsrl.min-saude.pt",
    "email": "aprovisionamento.geral@ulsrl.min-saude.pt",
    "designacao_contrato": "A6/102/2026 – Baterias de UPS’s e Similares - 2026",
    "descricao": "A6/102/2026 – Baterias de UPS’s e Similares - 2026",
    "preco_base": "21.585,60 EUR",
    "prazo_execucao": "60 DIAS",
    "prazo_apresentacao_propostas": "19-01-2026 18:00",
    "fundos_eu": "Não",
    "plataforma_eletronica": "VORTAL",
    "url_procedimento": "https://community.vortal.biz/public/",
    "autor_nome": "Manuel José Santos de Carvalho",
    "autor_cargo": "Presidente do Conselho de Administração"
  },
  {
    "numero_procedimento": "N/A",
    "entidade": "Unidade Local de Saúde do Oeste, EPE",
    "link": "https://diariodarepublica.pt/dr/detalhe/contrato-publico/33507-992879862",
    "detalhes_completos": "1 - IDENTIFICAÇÃO E CONTACTOS DA ENTIDADE ADJUDICANTE\nDesignação da entidade adjudicante: Unidade Local de Saúde do Oeste, EPE\nNIPC: 514993871\nEndereço: Rua Diário de Notícias\nCódigo postal: 2500-176\nLocalidade: Leiria\nPaís: Portugal\nNUT III: PT16B\nDistrito: Leiria\nConcelho: Caldas da Rainha\nFreguesia: União das Freguesias de Caldas da Rainha - Nossa Senhora do Pópulo, Coto e São Gregório\nTelefone: 262830300\nFax: 262830300\nEndereço da Entidade (URL): https://www.choeste.min-saude.pt\nEndereço Eletrónico: aprovisionamento@choeste.min-saude.pt\neDelivery Gateway (URL): https://community.vortal.biz/public/\nFunção da Organização: Adquirente\nNorma jurídica da Entidade Adjudicante: Organismo de direito público\nÁrea de atividade da Autoridade Adjudicante: Saúde\n\n2 - JORNAL OFICIAL DA UNIÃO EUROPEIA\nO procedimento a que este anúncio diz respeito também é publicitado no Jornal Oficial da União Europeia? Não\n\n3 - AVISO\nModelo de Anúncio: Concurso público\nData de Envio do Anúncio: 29-12-2025\n\n5 - PROCESSO\nTipo de Procedimento: Concurso público\nPreço base do procedimento: Sim\nValor do preço base do procedimento: 135.095,00 EUR\nProcedimento com lotes? Não\n\n6 - OBJETO DO CONTRATO\nNúmero de referência interna: 19/1258/2025\nDesignação do contrato: Aquisição de Endpoints de Segurança para a Unidade Local de Saúde do Oeste, E.P.E.\nDescrição: Aquisição de Endpoints de Segurança para a Unidade Local de Saúde do Oeste, E.P.E.\nTipo de Contrato Principal: Aquisição de Bens Móveis\nTipo de Contrato: Aquisição de Bens Móveis\nClassificação CPV (Vocabulário Comum para os Contratos Públicos)\nObjeto principal\nVocabulário Principal: 48730000\nPreço base s/IVA: 135.095,00 EUR\n\n7 - INDICAÇÕES ADICIONAIS\nO contrato envolve aquisição conjunta (satisfação de várias entidades)? Não\nO contrato é adjudicado por uma central de compras? Não\n\n8 - TÉCNICAS\nO concurso destina-se à celebração de um acordo-quadro? Inexistência de acordo-quadro\nÉ utilizado um leilão eletrónico? Não\nÉ adotada uma fase de negociação? Não\nSistema de Aquisição Dinâmico: Inexistência de sistema de aquisição dinâmico\n\n9 - LOCAL DA EXECUÇÃO DO CONTRATO\nLOCAL DA EXECUÇÃO DO CONTRATO (PROCEDIMENTO)\nPaís: Portugal\nNUT III: PT16B\nLocalidade: Leiria\nDistrito: Leiria\nConcelho: Caldas da Rainha\nFreguesia: União das Freguesias de Caldas da Rainha - Nossa Senhora do Pópulo, Coto e São Gregório\n\n10 - PRAZO DE EXECUÇÃO DO CONTRATO\nPrazo de execução do contrato: 36 MESES\nPrevisão de renovações: Não\n\n11 - FUNDOS EU\nTêm fundos EU? Não\n\n12 - DOCUMENTOS DE HABILITAÇÃO\nHabilitação para o exercício da atividade profissional: Não\n\n13 - CONDIÇÕES DE APRESENTAÇÃO\nPlataforma eletrónica utilizada pela entidade adjudicante: VORTAL\nURL para Apresentação: https://community.vortal.biz/public/\nAdmissibilidade da apresentação de propostas variantes: Não autorizado\nPrazo para apresentação das propostas: 07-01-2026 17:00\nPrazo durante o qual os concorrentes são obrigados a manter as respetivas propostas: 120 dias a contar do termo do prazo para a apresentação das propostas\nIndicação de Subcontratação na Proposta: Inexistência de indicação de subcontratação\n\n14 - PRESTAÇÃO DE CAUÇÃO\nPrestação de caução: Não\n\n15 - FORNECIMENTO DAS PEÇAS DO CONCURSO, APRESENTAÇÃO DE PEDIDOS DE PARTICIPAÇÃO E APRESENTAÇÃO DAS PROPOSTAS\nLink para acesso às peças do concurso (URL): https://community.vortal.biz/Public/public-tender-documents/LzdodTJHVXRwL0hObXFGRkhRTmptd0kxbFc2MlVEWStYWDgrL05LQWl3Wk9mT3QwOFVMWlhQVnk3MzAydUdqU3NSM0hQcjVQRHZENzJ5ZVczZk83SHc9PWlNeGY2\n\n20 - OUTROS REQUISITOS\nInformação sobre contratos reservados. Aplica-se a contratos reservados (54º-A)? Não\n\n21 - CRITÉRIO DE ADJUDICAÇÃO\nMultifator: Não\nMonofator:\nNome: Preço\n\n24 - CONDIÇÕES DO CONTRATO\nFaturação Eletrónica: Permitido\nObrigação de Subcontratação:\nCódigo da Obrigação de Subcontratação: Não é aplicável nenhuma obrigação de subcontratação.\n\n25 - COMPRA PÚBLICA ESTRATÉGICA\nCompra Pública Estratégica: Inexistência de contratação pública estratégica\n\n26 - INFORMAÇÕES ADICIONAIS\nContrato adequado para PME: Sim\nCobertura ACP (Acordo dos Contratos Públicos da Organização Mundial do Comércio): Não\n\n27 - IDENTIFICAÇÃO E CONTACTOS DO ÓRGÃO DE RECURSOS ADMINISTRATIVOS\nDesignação: Unidade Local de Saúde do Oeste, E.P.E\nEndereço: Rua Diário de Notícias\nCódigo postal: 2500-176\nLocalidade: Caldas da Rainha\nTelefone: +351 262830300\nFax: +351 262834757\nEndereço eletrónico: secretariado.ca@choeste.min-saude.pt\n\n28 - IDENTIFICAÇÃO DO(S) AUTOR(ES) DE ANÚNCIO\nNome: Elsa Maria Baião Ferreira Airoso Banza\nCargo: Presidente do Conselho de Administração\n419936137",
    "nipc": "514993871",
    "distrito": "Leiria",
    "concelho": "Caldas da Rainha",
    "freguesia": "União das Freguesias de Caldas da Rainha - Nossa Senhora do Pópulo, Coto e São Gregório",
    "site": "https://www.choeste.min-saude.pt",
    "email": "aprovisionamento@choeste.min-saude.pt",
    "designacao_contrato": "Aquisição de Endpoints de Segurança para a Unidade Local de Saúde do Oeste, E.P.E.",
    "descricao": "Aquisição de Endpoints de Segurança para a Unidade Local de Saúde do Oeste, E.P.E.",
    "preco_base": "135.095,00 EUR",
    "prazo_execucao": "36 MESES",
    "prazo_apresentacao_propostas": "07-01-2026 17:00",
    "fundos_eu": "Não",
    "plataforma_eletronica": "VORTAL",
    "url_procedimento": "https://community.vortal.biz/public/",
    "autor_nome": "Elsa Maria Baião Ferreira Airoso Banza",
    "autor_cargo": "Presidente do Conselho de Administração"
  },
  {
    "numero_procedimento": "N/A",
    "entidade": "Unidade Local de Saúde da Região de Leiria, EPE",
    "link": "https://diariodarepublica.pt/dr/detalhe/contrato-publico/33508-992879863",
    "detalhes_completos": "1 - IDENTIFICAÇÃO E CONTACTOS DA ENTIDADE ADJUDICANTE\nDesignação da entidade adjudicante: Unidade Local de Saúde da Região de Leiria, EPE\nNIPC: 509822932\nEndereço: Rua das Olhalvas, Pousos\nCódigo postal: 2410-197\nLocalidade: Leiria\nPaís: Portugal\nNUT III: PT16F\nDistrito: Leiria\nConcelho: Leiria\nFreguesia: União das Freguesias de Leiria, Pousos, Barreira e Cortes\nTelefone: 244817010\nEndereço da Entidade (URL): https://www.ulsrl.min-saude.pt\nEndereço Eletrónico: aprovisionamento.geral@ulsrl.min-saude.pt\neDelivery Gateway (URL): https://community.vortal.biz/public/\nFunção da Organização: Adquirente\nNorma jurídica da Entidade Adjudicante: Empresa pública, controlada por uma autoridade da administração central\nÁrea de atividade da Autoridade Adjudicante: Saúde\n\n2 - JORNAL OFICIAL DA UNIÃO EUROPEIA\nO procedimento a que este anúncio diz respeito também é publicitado no Jornal Oficial da União Europeia? Não\n\n3 - AVISO\nModelo de Anúncio: Concurso público\nData de Envio do Anúncio: 29-12-2025\n\n5 - PROCESSO\nTipo de Procedimento: Concurso público\nPreço base do procedimento: Sim\nValor do preço base do procedimento: 140.379,48 EUR\nProcedimento com lotes? Sim\nNº Máx. de Lotes Autorizado: 6\nNúmero máximo de lotes que podem ser adjudicados a um concorrente: 6\n\n6 - OBJETO DO CONTRATO\nNúmero de referência interna: A1/3677/2025 – NUTRIÇÃO ENTÉRICA II\nDesignação do contrato: A1/3677/2025 – NUTRIÇÃO ENTÉRICA II\nDescrição: A1/3677/2025 – NUTRIÇÃO ENTÉRICA II\nTipo de Contrato Principal: Aquisição de Bens Móveis\nTipo de Contrato: Aquisição de Bens Móveis\nClassificação CPV (Vocabulário Comum para os Contratos Públicos)\nObjeto principal\nVocabulário Principal: 33600000\nPreço base s/IVA: 140.379,48 EUR\nLotes: \nNº: LOT-0001\nDescrição do Lote: Lote 1\nPreço base s/IVA: 40.870,44 EUR\nClassificação CPV (Vocabulário Comum para os Contratos Públicos)\nObjeto principal\nVocabulário Principal: 33600000\nNº: LOT-0002\nDescrição do Lote: Lote 2\nPreço base s/IVA: 48.652,80 EUR\nClassificação CPV (Vocabulário Comum para os Contratos Públicos)\nObjeto principal\nVocabulário Principal: 33600000\nNº: LOT-0003\nDescrição do Lote: Lote 3\nPreço base s/IVA: 492,48 EUR\nClassificação CPV (Vocabulário Comum para os Contratos Públicos)\nObjeto principal\nVocabulário Principal: 33600000\nNº: LOT-0004\nDescrição do Lote: Lote 4\nPreço base s/IVA: 4.231,92 EUR\nClassificação CPV (Vocabulário Comum para os Contratos Públicos)\nObjeto principal\nVocabulário Principal: 33600000\nNº: LOT-0005\nDescrição do Lote: Lote 5\nPreço base s/IVA: 35.239,68 EUR\nClassificação CPV (Vocabulário Comum para os Contratos Públicos)\nObjeto principal\nVocabulário Principal: 33600000\nNº: LOT-0006\nDescrição do Lote: Lote 6\nPreço base s/IVA: 10.892,16 EUR\nClassificação CPV (Vocabulário Comum para os Contratos Públicos)\nObjeto principal\nVocabulário Principal: 33600000\n\n7 - INDICAÇÕES ADICIONAIS\nO contrato envolve aquisição conjunta (satisfação de várias entidades)? Não\nO contrato é adjudicado por uma central de compras? Não\n\n8 - TÉCNICAS\nO concurso destina-se à celebração de um acordo-quadro? Inexistência de acordo-quadro\nÉ utilizado um leilão eletrónico? Não\nÉ adotada uma fase de negociação? Não\nSistema de Aquisição Dinâmico: Inexistência de sistema de aquisição dinâmico\n\n9 - LOCAL DA EXECUÇÃO DO CONTRATO\nLOCAL DA EXECUÇÃO DO CONTRATO (PROCEDIMENTO)\nPaís: Portugal\nNUT III: PT16F\nLocalidade: Leiria\nDistrito: Leiria\nConcelho: Leiria\nFreguesia: União das Freguesias de Leiria, Pousos, Barreira e Cortes\nLOCAL DA EXECUÇÃO DO CONTRATO (LOTE)\nIdentificador do Lote: LOT-0001; LOT-0002; LOT-0003; LOT-0004; LOT-0005; LOT-0006\nPaís: Portugal\nNUT III: PT16F\nLocalidade: Leiria\nDistrito: Leiria\nConcelho: Leiria\nFreguesia: União das Freguesias de Leiria, Pousos, Barreira e Cortes\n\n10 - PRAZO DE EXECUÇÃO DO CONTRATO\nIdentificador do Lote: LOT-0001; LOT-0002; LOT-0003; LOT-0004; LOT-0005; LOT-0006\nPrazo de execução do contrato: 36 MESES\nPrevisão de renovações: Não\n\n11 - FUNDOS EU\nIdentificador do Lote: LOT-0001; LOT-0002; LOT-0003; LOT-0004; LOT-0005; LOT-0006\nTêm fundos EU? Não\n\n12 - DOCUMENTOS DE HABILITAÇÃO\nHabilitação para o exercício da atividade profissional: Não\n\n13 - CONDIÇÕES DE APRESENTAÇÃO\nPlataforma eletrónica utilizada pela entidade adjudicante: VORTAL\nURL para Apresentação: https://community.vortal.biz/public/\nAdmissibilidade da apresentação de propostas variantes: Não autorizado\nPrazo para apresentação das propostas: 08-01-2026 18:00\nPrazo durante o qual os concorrentes são obrigados a manter as respetivas propostas: 90 dias a contar do termo do prazo para a apresentação das propostas\nIndicação de Subcontratação na Proposta: Inexistência de indicação de subcontratação\n\n14 - PRESTAÇÃO DE CAUÇÃO\nPrestação de caução: Não\n\n15 - FORNECIMENTO DAS PEÇAS DO CONCURSO, APRESENTAÇÃO DE PEDIDOS DE PARTICIPAÇÃO E APRESENTAÇÃO DAS PROPOSTAS\nLink para acesso às peças do concurso (URL): https://community.vortal.biz/Public/public-tender-documents/UG1mM21VbFZqWXpzanpEeUE4RnYwT3dmSkFQZEZLVU5oL0E4cTl2REp6Y1IwbUM0bDNBWWpEaUZnZDZ5d01DRlVMVUtka2tiQXBLV3F4NzNpZTBxbnc9PXVAbDY5\n\n20 - OUTROS REQUISITOS\nIdentificador do Lote: LOT-0001; LOT-0002; LOT-0003; LOT-0004; LOT-0005; LOT-0006\nInformação sobre contratos reservados. Aplica-se a contratos reservados (54º-A)? Não\n\n21 - CRITÉRIO DE ADJUDICAÇÃO\nO Critério de adjudicação é diferenciado por lote? Não\nMultifator: Não\nMonofator:\nNome: Preço\n\n24 - CONDIÇÕES DO CONTRATO\nIdentificador do Lote: LOT-0001; LOT-0002; LOT-0003; LOT-0004; LOT-0005; LOT-0006\nFaturação Eletrónica: Permitido\nObrigação de Subcontratação:\nCódigo da Obrigação de Subcontratação: Não é aplicável nenhuma obrigação de subcontratação.\n\n25 - COMPRA PÚBLICA ESTRATÉGICA\nCompra Pública Estratégica: Inexistência de contratação pública estratégica\n\n26 - INFORMAÇÕES ADICIONAIS\nIdentificador do Lote: LOT-0001; LOT-0002; LOT-0003; LOT-0004; LOT-0005; LOT-0006\nContrato adequado para PME: Sim\nCobertura ACP (Acordo dos Contratos Públicos da Organização Mundial do Comércio): Não\n\n27 - IDENTIFICAÇÃO E CONTACTOS DO ÓRGÃO DE RECURSOS ADMINISTRATIVOS\nDesignação: Conselho de Administração da ULS RL EPE\nEndereço: Rua das Olhalvas - Pousos\nCódigo postal: 2410-197\nLocalidade: Leiria\nTelefone: +351 244817010\nFax: +351 244817010\nEndereço eletrónico: secca@ulsrl.min-saude.pt\n\n28 - IDENTIFICAÇÃO DO(S) AUTOR(ES) DE ANÚNCIO\nNome: Manuel José de Carvalho\nCargo: Presidente do Conselho de Administração\n419934444",
    "nipc": "509822932",
    "distrito": "Leiria",
    "concelho": "Leiria",
    "freguesia": "União das Freguesias de Leiria, Pousos, Barreira e Cortes",
    "site": "https://www.ulsrl.min-saude.pt",
    "email": "aprovisionamento.geral@ulsrl.min-saude.pt",
    "designacao_contrato": "A1/3677/2025 – NUTRIÇÃO ENTÉRICA II",
    "descricao": "A1/3677/2025 – NUTRIÇÃO ENTÉRICA II",
    "preco_base": "140.379,48 EUR",
    "prazo_execucao": "36 MESES",
    "prazo_apresentacao_propostas": "08-01-2026 18:00",
    "fundos_eu": "Não",
    "plataforma_eletronica": "VORTAL",
    "url_procedimento": "https://community.vortal.biz/public/",
    "autor_nome": "Manuel José de Carvalho",
    "autor_cargo": "Presidente do Conselho de Administração"
  },
  {
    "numero_procedimento": "N/A",
    "entidade": "Guarda Nacional Republicana",
    "link": "https://diariodarepublica.pt/dr/detalhe/contrato-publico/33509-992879864",
    "detalhes_completos": "1 - IDENTIFICAÇÃO E CONTACTOS DA ENTIDADE ADJUDICANTE\nDesignação da entidade adjudicante: Guarda Nacional Republicana\nNIPC: 600008878\nEndereço: Lg. do Carmo - Convento do Carmo\nCódigo postal: 1200-092\nLocalidade: Lisboa\nPaís: Portugal\nNUT III: PT170\nDistrito: Lisboa\nConcelho: Lisboa\nFreguesia: Todas\nTelefone: 213217000\nFax: 213217328\nEndereço da Entidade (URL): www.gnr.pt\nEndereço Eletrónico: cari.drl.da@gnr.pt\neDelivery Gateway (URL): https://community.vortal.biz/public/\nFunção da Organização: Adquirente\nNorma jurídica da Entidade Adjudicante: Organismo de direito público\nÁrea de atividade da Autoridade Adjudicante: Segurança e ordem pública\n\n2 - JORNAL OFICIAL DA UNIÃO EUROPEIA\nO procedimento a que este anúncio diz respeito também é publicitado no Jornal Oficial da União Europeia? Não\n\n3 - AVISO\nModelo de Anúncio: Concurso público\nData de Envio do Anúncio: 29-12-2025\n\n5 - PROCESSO\nTipo de Procedimento: Concurso público\nPreço base do procedimento: Sim\nValor do preço base do procedimento: 55.000,00 EUR\nProcedimento com lotes? Não\n\n6 - OBJETO DO CONTRATO\nNúmero de referência interna: CP_03_SRLF_UI_2026\nDesignação do contrato: SUBSTITUIÇÃO DA COBERTURA EXTERIOR DO EDIFÍCIO DE ALOJAMENTO DE GUARDAS DO GIC/UI EM QUELUZ\nDescrição: CP_03_SRLF_UI_2026_SUBSTITUIÇÃO DA COBERTURA EXTERIOR DO EDIFÍCIO DE ALOJAMENTO DE GUARDAS DO GIC/UI EM QUELUZ\nTipo de Contrato Principal: Empreitada de Obras Públicas\nTipo de Contrato: Empreitada de Obras Públicas\nClassificação CPV (Vocabulário Comum para os Contratos Públicos)\nObjeto principal\nVocabulário Principal: 45400000\nPreço base s/IVA: 55.000,00 EUR\n\n7 - INDICAÇÕES ADICIONAIS\nO contrato envolve aquisição conjunta (satisfação de várias entidades)? Não\nO contrato é adjudicado por uma central de compras? Não\n\n8 - TÉCNICAS\nO concurso destina-se à celebração de um acordo-quadro? Inexistência de acordo-quadro\nÉ utilizado um leilão eletrónico? Não\nÉ adotada uma fase de negociação? Não\nSistema de Aquisição Dinâmico: Inexistência de sistema de aquisição dinâmico\n\n9 - LOCAL DA EXECUÇÃO DO CONTRATO\nLOCAL DA EXECUÇÃO DO CONTRATO (PROCEDIMENTO)\nPaís: Portugal\nNUT III: PT170\nLocalidade: Lisboa\nDistrito: Lisboa\nConcelho: Lisboa\nFreguesia: Todas\n\n10 - PRAZO DE EXECUÇÃO DO CONTRATO\nPrazo de execução do contrato: 40 DIAS\nPrevisão de renovações: Não\n\n11 - FUNDOS EU\nTêm fundos EU? Não\n\n12 - DOCUMENTOS DE HABILITAÇÃO\nHabilitação para o exercício da atividade profissional: Não\n\n13 - CONDIÇÕES DE APRESENTAÇÃO\nPlataforma eletrónica utilizada pela entidade adjudicante: VORTAL\nURL para Apresentação: https://community.vortal.biz/public/\nAdmissibilidade da apresentação de propostas variantes: Não autorizado\nPrazo para apresentação das propostas: 10-01-2026 23:59\nPrazo durante o qual os concorrentes são obrigados a manter as respetivas propostas: 180 dias a contar do termo do prazo para a apresentação das propostas\nIndicação de Subcontratação na Proposta: Inexistência de indicação de subcontratação\n\n14 - PRESTAÇÃO DE CAUÇÃO\nPrestação de caução: Não\n\n15 - FORNECIMENTO DAS PEÇAS DO CONCURSO, APRESENTAÇÃO DE PEDIDOS DE PARTICIPAÇÃO E APRESENTAÇÃO DAS PROPOSTAS\nLink para acesso às peças do concurso (URL): https://community.vortal.biz/Public/public-tender-documents/V09BclpHeHVLV3k3N1o1V2M4Lyt6SFg0OFU5dHg2NGNrVnc3emQza1Y1M1pzVThjU2RaT3ZoVDV2MmRKNmVCMXM0WWxmZnBSRzI4UTBCdlVzMkVyZ3c9PURsVGZ1\n\n20 - OUTROS REQUISITOS\nInformação sobre contratos reservados. Aplica-se a contratos reservados (54º-A)? Não\n\n21 - CRITÉRIO DE ADJUDICAÇÃO\nMultifator: Não\nMonofator:\nNome: Outros\nOutro nome: Preço\n\n24 - CONDIÇÕES DO CONTRATO\nFaturação Eletrónica: Permitido\nObrigação de Subcontratação:\nCódigo da Obrigação de Subcontratação: Não é aplicável nenhuma obrigação de subcontratação.\n\n25 - COMPRA PÚBLICA ESTRATÉGICA\nCompra Pública Estratégica: Inexistência de contratação pública estratégica\n\n26 - INFORMAÇÕES ADICIONAIS\nContrato adequado para PME: Sim\nCobertura ACP (Acordo dos Contratos Públicos da Organização Mundial do Comércio): Não\n\n27 - IDENTIFICAÇÃO E CONTACTOS DO ÓRGÃO DE RECURSOS ADMINISTRATIVOS\nDesignação: Guarda Nacional Republicana\nEndereço: Largo do Carmo\nCódigo postal: 1200-092\nLocalidade: Lisboa\nTelefone: +351 213217000\nFax: +351 213474819\nEndereço eletrónico: gnr@gnr.pt\n\n28 - IDENTIFICAÇÃO DO(S) AUTOR(ES) DE ANÚNCIO\nNome:  Ricardo Farinha\nCargo: Cabo\n419935449",
    "nipc": "600008878",
    "distrito": "Lisboa",
    "concelho": "Lisboa",
    "freguesia": "Todas",
    "site": "www.gnr.pt",
    "email": "cari.drl.da@gnr.pt",
    "designacao_contrato": "SUBSTITUIÇÃO DA COBERTURA EXTERIOR DO EDIFÍCIO DE ALOJAMENTO DE GUARDAS DO GIC/UI EM QUELUZ",
    "descricao": "CP_03_SRLF_UI_2026_SUBSTITUIÇÃO DA COBERTURA EXTERIOR DO EDIFÍCIO DE ALOJAMENTO DE GUARDAS DO GIC/UI EM QUELUZ",
    "preco_base": "55.000,00 EUR",
    "prazo_execucao": "40 DIAS",
    "prazo_apresentacao_propostas": "10-01-2026 23:59",
    "fundos_eu": "Não",
    "plataforma_eletronica": "VORTAL",
    "url_procedimento": "https://community.vortal.biz/public/",
    "autor_nome": "Ricardo Farinha",
    "autor_cargo": "Cabo"
  },
  {
    "numero_procedimento": "N/A",
    "entidade": "Município de Condeixa-a-Nova",
    "link": "https://diariodarepublica.pt/dr/detalhe/contrato-publico/33511-992879865",
    "detalhes_completos": "Alteração do Anúncio de procedimento n.º 33465/2025, de 2025-12-26, com o ID 419930872\n\n1 - IDENTIFICAÇÃO E CONTACTOS DA ENTIDADE ADJUDICANTE\nDesignação da entidade adjudicante: Município de Condeixa-a-Nova\nNIPC: 501275380\nServiço/Órgão/Pessoa de contacto: Municipio de Condeixa-a-Nova  - 239949120 - geral@cm-condeixa.pt\nEndereço: Largo Artur Barreto\nCódigo postal: 3150-124\nLocalidade: Condeixa-a-Nova\nPaís: Portugal\nNUT III: PT16E\nDistrito: Coimbra\nConcelho: Condeixa-a-Nova\nFreguesia: União das Freguesias de Condeixa-a-Velha e Condeixa-a-Nova\nTelefone: 239949120\nEndereço da Entidade (URL): http://cm-condeixa.pt/\nEndereço Eletrónico: geral@cm-condeixa.pt\neDelivery Gateway (URL): https://community.vortal.biz/public/\nFunção da Organização: Adquirente\nNorma jurídica da Entidade Adjudicante: Autoridade local\nÁrea de atividade da Autoridade Adjudicante: Serviços públicos das administrações públicas\n\n2 - JORNAL OFICIAL DA UNIÃO EUROPEIA\nO procedimento a que este anúncio diz respeito também é publicitado no Jornal Oficial da União Europeia? Não\n\n3 - AVISO\nModelo de Anúncio: Concurso público\nData de Envio do Anúncio: 29-12-2025\n\n5 - PROCESSO\nTipo de Procedimento: Concurso público\nPreço base do procedimento: Sim\nValor do preço base do procedimento: 354.000,00 EUR\nProcedimento com lotes? Não\n\n6 - OBJETO DO CONTRATO\nNúmero de referência interna: 106/2025\nDesignação do contrato: Alargamento do complexo arqueológico de Conimbriga - Conimbriga - Restauro das Muralhas - Setor F \nDescrição: Alargamento do complexo arqueológico de Conimbriga - Conimbriga - Restauro das Muralhas - Setor F\nTipo de Contrato Principal: Empreitada de Obras Públicas\nTipo de Contrato: Empreitada de Obras Públicas\nClassificação CPV (Vocabulário Comum para os Contratos Públicos)\nObjeto principal\nVocabulário Principal: 45454100\nPreço base s/IVA: 354.000,00 EUR\n\n7 - INDICAÇÕES ADICIONAIS\nO contrato envolve aquisição conjunta (satisfação de várias entidades)? Não\nO contrato é adjudicado por uma central de compras? Não\n\n8 - TÉCNICAS\nO concurso destina-se à celebração de um acordo-quadro? Inexistência de acordo-quadro\nÉ utilizado um leilão eletrónico? Não\nÉ adotada uma fase de negociação? Não\nSistema de Aquisição Dinâmico: Inexistência de sistema de aquisição dinâmico\n\n9 - LOCAL DA EXECUÇÃO DO CONTRATO\nLOCAL DA EXECUÇÃO DO CONTRATO (PROCEDIMENTO)\nPaís: Portugal\nNUT III: PT16E\nLocalidade: Coimbra\nDistrito: Coimbra\nConcelho: Condeixa-a-Nova\nFreguesia: União das Freguesias de Condeixa-a-Velha e Condeixa-a-Nova\n\n10 - PRAZO DE EXECUÇÃO DO CONTRATO\nPrazo de execução do contrato: 270 DIAS\nPrevisão de renovações: Não\n\n11 - FUNDOS EU\nTêm fundos EU? Sim\n\n12 - DOCUMENTOS DE HABILITAÇÃO\nHabilitação para o exercício da atividade profissional: Sim\nTipo: Alvará\nDescrição: Alvará de empreiteiro de obras públicas contendo a 10º subcategoria da 1ª categoria, em classe que cubra o valor da proposta. \n\n13 - CONDIÇÕES DE APRESENTAÇÃO\nPlataforma eletrónica utilizada pela entidade adjudicante: VORTAL\nURL para Apresentação: https://community.vortal.biz/public/\nAdmissibilidade da apresentação de propostas variantes: Não autorizado\nPrazo para apresentação das propostas: 27-12-2025 18:00\nPrazo durante o qual os concorrentes são obrigados a manter as respetivas propostas: 66 dias a contar do termo do prazo para a apresentação das propostas\nApresentação de Catálogo Eletrónico: Permitido\nIndicação de Subcontratação na Proposta: Inexistência de indicação de subcontratação\n\n14 - PRESTAÇÃO DE CAUÇÃO\nPrestação de caução: Sim\nPercentagem: 5%\nDescrição da Garantia Exigida: Mediante garantia bancária, seguro caução ou depósito de dinheiro ou titulos emitidos ou garantidos pelo estado.\n\n15 - FORNECIMENTO DAS PEÇAS DO CONCURSO, APRESENTAÇÃO DE PEDIDOS DE PARTICIPAÇÃO E APRESENTAÇÃO DAS PROPOSTAS\nLink para acesso às peças do concurso (URL): https://community.vortal.biz/Public/public-tender-documents/aHZaQUJickROcU1YbEp2OGpOb3hwLzAycS8wd3hGbTJpZlBtNytwNW00TitLRDBsQ1JKRDZmR05nM0o2MVBNSUgyYmdNMEhjZkhTKzhxL0Frd3A1MWc9PXpeb3VN\n\n20 - OUTROS REQUISITOS\nInformação sobre contratos reservados. Aplica-se a contratos reservados (54º-A)? Não\n\n21 - CRITÉRIO DE ADJUDICAÇÃO\nMultifator: Sim\nFator: \nNome: Preço\nPonderação: 60%\nSubfatores: Não\nFator: \nNome: Qualidade\nPonderação: 40%\nSubfatores: Não\n\n24 - CONDIÇÕES DO CONTRATO\nFaturação Eletrónica: Permitido\nObrigação de Subcontratação:\nCódigo da Obrigação de Subcontratação: Não é aplicável nenhuma obrigação de subcontratação.\n\n25 - COMPRA PÚBLICA ESTRATÉGICA\nCompra Pública Estratégica: Inexistência de contratação pública estratégica\n\n26 - INFORMAÇÕES ADICIONAIS\nContrato adequado para PME: Sim\nCobertura ACP (Acordo dos Contratos Públicos da Organização Mundial do Comércio): Não\n\n27 - IDENTIFICAÇÃO E CONTACTOS DO ÓRGÃO DE RECURSOS ADMINISTRATIVOS\nDesignação: Câmara Municipal de Condeixa-a-Nova\nEndereço: Largo Artur Barreto\nCódigo postal: 3150-124\nLocalidade: Condeixa-a-Nova\nTelefone: +351 239949120\nFax: +351 239949120\nEndereço eletrónico: geral@cm-condeixa.pt\n\n28 - IDENTIFICAÇÃO DO(S) AUTOR(ES) DE ANÚNCIO\nNome: Liliana Marques Pimentel\nCargo: Presidente da Câmara\n\n29 - ALTERAÇÃO\nMotivo da Alteração: Correção pelo editor\nIdentificador da Versão do Anúncio a Alterar: 5d578edf-81b4-4a15-8f1f-75db662ddd25-01\nIdentificador das Secções Alteradas do Anúncio Anterior: Aviso\nDescrição das Alterações: Informam-se todos os interessados que o último dia para apresentação das propostas é dia 2 de Janeiro de 2026 pelas 18h:00m\nAlteração dos Documentos do Concurso: Não\n419932557",
    "nipc": "501275380",
    "distrito": "Coimbra",
    "concelho": "Condeixa-a-Nova",
    "freguesia": "União das Freguesias de Condeixa-a-Velha e Condeixa-a-Nova",
    "site": "http://cm-condeixa.pt/",
    "email": "geral@cm-condeixa.pt",
    "designacao_contrato": "Alargamento do complexo arqueológico de Conimbriga - Conimbriga - Restauro das Muralhas - Setor F",
    "descricao": "Alargamento do complexo arqueológico de Conimbriga - Conimbriga - Restauro das Muralhas - Setor F",
    "preco_base": "354.000,00 EUR",
    "prazo_execucao": "270 DIAS",
    "prazo_apresentacao_propostas": "27-12-2025 18:00",
    "fundos_eu": "Sim",
    "plataforma_eletronica": "VORTAL",
    "url_procedimento": "https://community.vortal.biz/public/",
    "autor_nome": "Liliana Marques Pimentel",
    "autor_cargo": "Presidente da Câmara"
  },
  {
    "numero_procedimento": "N/A",
    "entidade": "Freguesia de Benfica",
    "link": "https://diariodarepublica.pt/dr/detalhe/contrato-publico/33512-992879866",
    "detalhes_completos": "1 - IDENTIFICAÇÃO E CONTACTOS DA ENTIDADE ADJUDICANTE\nDesignação da entidade adjudicante: Freguesia de Benfica\nNIPC: 506602222\nEndereço: Av. Gomes Pereira, 17\nCódigo postal: 1549-019\nLocalidade: Lisboa\nPaís: Portugal\nNUT III: PT170\nDistrito: Lisboa\nConcelho: Lisboa\nFreguesia: Freguesia de Benfica\nTelefone: 217123000\nFax: 217123000\nEndereço Eletrónico: geral@jf-benfica.pt\neDelivery Gateway (URL): https://community.vortal.biz/public/\nFunção da Organização: Adquirente\nNorma jurídica da Entidade Adjudicante: Organismo de direito público\nÁrea de atividade da Autoridade Adjudicante: Serviços públicos das administrações públicas\n\n2 - JORNAL OFICIAL DA UNIÃO EUROPEIA\nO procedimento a que este anúncio diz respeito também é publicitado no Jornal Oficial da União Europeia? Não\n\n3 - AVISO\nModelo de Anúncio: Concurso público\nData de Envio do Anúncio: 29-12-2025\n\n5 - PROCESSO\nTipo de Procedimento: Concurso público\nPreço base do procedimento: Sim\nValor do preço base do procedimento: 70.000,00 EUR\nProcedimento com lotes? Não\n\n6 - OBJETO DO CONTRATO\nNúmero de referência interna: Concurso Público n.º 15/2025 \nDesignação do contrato: Concurso Público n.º 15/2025 – Aquisição de serviços de seguros para a Junta de Freguesia de Benfica referentes a frota automóvel, Multirriscos e Responsabilidade Civil para o período de 12 meses\nDescrição: Concurso Público n.º 15/2025 – Aquisição de serviços de seguros para a Junta de Freguesia de Benfica referentes a frota automóvel, Multirriscos e Responsabilidade Civil para o período de 12 meses\nTipo de Contrato Principal: Aquisição de Serviços\nTipo de Contrato: Aquisição de Serviços\nClassificação CPV (Vocabulário Comum para os Contratos Públicos)\nObjeto principal\nVocabulário Principal: 66515200\nPreço base s/IVA: 70.000,00 EUR\n\n7 - INDICAÇÕES ADICIONAIS\nO contrato envolve aquisição conjunta (satisfação de várias entidades)? Não\nO contrato é adjudicado por uma central de compras? Não\n\n8 - TÉCNICAS\nO concurso destina-se à celebração de um acordo-quadro? Inexistência de acordo-quadro\nÉ utilizado um leilão eletrónico? Não\nÉ adotada uma fase de negociação? Não\nSistema de Aquisição Dinâmico: Inexistência de sistema de aquisição dinâmico\n\n9 - LOCAL DA EXECUÇÃO DO CONTRATO\nLOCAL DA EXECUÇÃO DO CONTRATO (PROCEDIMENTO)\nPaís: Portugal\nNUT III: PT170\nLocalidade: Lisboa\nDistrito: Lisboa\nConcelho: Lisboa\nFreguesia: Freguesia de Benfica\n\n10 - PRAZO DE EXECUÇÃO DO CONTRATO\nPrazo de execução do contrato: 12 MESES\nPrevisão de renovações: Não\n\n11 - FUNDOS EU\nTêm fundos EU? Não\n\n12 - DOCUMENTOS DE HABILITAÇÃO\nHabilitação para o exercício da atividade profissional: Não\n\n13 - CONDIÇÕES DE APRESENTAÇÃO\nPlataforma eletrónica utilizada pela entidade adjudicante: VORTAL\nURL para Apresentação: https://community.vortal.biz/public/\nAdmissibilidade da apresentação de propostas variantes: Não autorizado\nPrazo para apresentação das propostas: 10-01-2026 23:59\nPrazo durante o qual os concorrentes são obrigados a manter as respetivas propostas: 90 dias a contar do termo do prazo para a apresentação das propostas\nIndicação de Subcontratação na Proposta: Inexistência de indicação de subcontratação\n\n14 - PRESTAÇÃO DE CAUÇÃO\nPrestação de caução: Não\n\n15 - FORNECIMENTO DAS PEÇAS DO CONCURSO, APRESENTAÇÃO DE PEDIDOS DE PARTICIPAÇÃO E APRESENTAÇÃO DAS PROPOSTAS\nLink para acesso às peças do concurso (URL): https://community.vortal.biz/Public/public-tender-documents/cVVFVkdqMFRoM3l5cndtM3dJRkpMSlFxdWM2bmlzSVYwZ2JBbU1NTDE3aHlRdlRkT09MbzFaNFJKK1JJOEdnSmU2cFJvcXovL0svNkI3cmNPYjRkWnc9PXZyRyo4\n\n20 - OUTROS REQUISITOS\nInformação sobre contratos reservados. Aplica-se a contratos reservados (54º-A)? Não\n\n21 - CRITÉRIO DE ADJUDICAÇÃO\nMultifator: Não\nMonofator:\nNome: Outros\nOutro nome: Preço\n\n24 - CONDIÇÕES DO CONTRATO\nFaturação Eletrónica: Permitido\nObrigação de Subcontratação:\nCódigo da Obrigação de Subcontratação: Não é aplicável nenhuma obrigação de subcontratação.\n\n25 - COMPRA PÚBLICA ESTRATÉGICA\nCompra Pública Estratégica: Inexistência de contratação pública estratégica\n\n26 - INFORMAÇÕES ADICIONAIS\nContrato adequado para PME: Sim\nCobertura ACP (Acordo dos Contratos Públicos da Organização Mundial do Comércio): Não\n\n27 - IDENTIFICAÇÃO E CONTACTOS DO ÓRGÃO DE RECURSOS ADMINISTRATIVOS\nDesignação: Junta de Freguesia de Benfica\nEndereço: Avenida Gomes Pereira nº17\nCódigo postal: 1549-019\nLocalidade: Lisboa\nTelefone: +351 217123000\nFax: +351 217123000\nEndereço eletrónico: contratacao@jf-benfica.pt\n\n28 - IDENTIFICAÇÃO DO(S) AUTOR(ES) DE ANÚNCIO\nNome: Ricardo João de Oliveira Marques \nCargo: Presidente da Junta de Freguesia de Benfica \n419933586",
    "nipc": "506602222",
    "distrito": "Lisboa",
    "concelho": "Lisboa",
    "freguesia": "Freguesia de Benfica",
    "site": null,
    "email": "geral@jf-benfica.pt",
    "designacao_contrato": "Concurso Público n.º 15/2025 – Aquisição de serviços de seguros para a Junta de Freguesia de Benfica referentes a frota automóvel, Multirriscos e Responsabilidade Civil para o período de 12 meses",
    "descricao": "Concurso Público n.º 15/2025 – Aquisição de serviços de seguros para a Junta de Freguesia de Benfica referentes a frota automóvel, Multirriscos e Responsabilidade Civil para o período de 12 meses",
    "preco_base": "70.000,00 EUR",
    "prazo_execucao": "12 MESES",
    "prazo_apresentacao_propostas": "10-01-2026 23:59",
    "fundos_eu": "Não",
    "plataforma_eletronica": "VORTAL",
    "url_procedimento": "https://community.vortal.biz/public/",
    "autor_nome": "Ricardo João de Oliveira Marques",
    "autor_cargo": "Presidente da Junta de Freguesia de Benfica"
  },
  {
    "numero_procedimento": "N/A",
    "entidade": "E-REDES - Distribuição de Eletricidade, SA",
    "link": "https://diariodarepublica.pt/dr/detalhe/contrato-publico/33466-992908294",
    "detalhes_completos": "1 - IDENTIFICAÇÃO E CONTACTOS DA ENTIDADE ADJUDICANTE\nDesignação da entidade adjudicante: E-REDES - Distribuição de Eletricidade, SA\nNIPC: 504394029\nEndereço: Rua D. Luís I, n.º 12\nCódigo postal: 1249-008\nLocalidade: Lisboa\nPaís: Portugal\nNUT III: PT170\nDistrito: Lisboa\nConcelho: Lisboa\nFreguesia: Freguesia de Misericórdia\nTelefone: 218100100\nFax: 218100100\nEndereço da Entidade (URL): https://www.e-redes.pt\nEndereço Eletrónico: qualificacao.fornecedores@e-redes.pt\neDelivery Gateway (URL): https://community.vortal.biz/public/\nFunção da Organização: Adquirente\nNorma jurídica da Entidade Adjudicante: Entidade com direitos especiais ou exclusivos\nÁrea de atividade da Entidade Adjudicante: Atividades relacionadas com a eletricidade\n\n2 - JORNAL OFICIAL DA UNIÃO EUROPEIA\nO procedimento a que este anúncio diz respeito também é publicitado no Jornal Oficial da União Europeia? Sim\n\n3 - AVISO\nModelo de Anúncio: Concurso limitado por prévia qualificação\nData de Envio do Anúncio: 25-12-2025\n\n5 - PROCESSO\nTipo de Procedimento: Concurso limitado por prévia qualificação\nPreço base do procedimento: Não\nProcedimento com lotes? Não\n\n6 - OBJETO DO CONTRATO\nNúmero de referência interna: WS2876464566\nDesignação do contrato: Geradores\nDescrição: Fornecimento de Geradores de 630 KVA e 250 KVA\nOpções: Não\nTipo de Contrato Principal: Aquisição de Bens Móveis\nTipo de Contrato: Aquisição de Bens Móveis\nClassificação CPV (Vocabulário Comum para os Contratos Públicos)\nObjeto principal\nVocabulário Principal: 31100000\n\n7 - INDICAÇÕES ADICIONAIS\nO contrato envolve aquisição conjunta (satisfação de várias entidades)? Não\nO contrato é adjudicado por uma central de compras? Não\n\n8 - TÉCNICAS\nO concurso destina-se à celebração de um acordo-quadro? Inexistência de acordo-quadro\nÉ utilizado um leilão eletrónico? Não\nSistema de Aquisição Dinâmico: Inexistência de sistema de aquisição dinâmico\n\n9 - LOCAL DA EXECUÇÃO DO CONTRATO\nLOCAL DA EXECUÇÃO DO CONTRATO (PROCEDIMENTO)\nPaís: Portugal\nNUT III: PT170\nLocalidade: Lisboa\nDistrito: Lisboa\nConcelho: Lisboa\nFreguesia: Freguesia de Misericórdia\n\n10 - PRAZO DE EXECUÇÃO DO CONTRATO\nPrazo de execução do contrato: 12 MESES\nPrevisão de renovações: Não\n\n11 - FUNDOS EU\nTêm fundos EU? Não\n\n12 - DOCUMENTOS DE HABILITAÇÃO\nHabilitação para o exercício da atividade profissional: Não\n\n13 - CONDIÇÕES DE APRESENTAÇÃO\nPlataforma eletrónica utilizada pela entidade adjudicante: VORTAL\nURL para Apresentação: https://community.vortal.biz/public/\nAdmissibilidade da apresentação de propostas variantes: Não autorizado\nPrazo para apresentação das candidaturas: 24-01-2026 18:00\nRequisitos mínimos \nRequisitos mínimos de capacidade técnica: Conforme Caderno de Encargos\nRequisitos mínimos de capacidade financeira: Conforme Caderno de Encargos\nPrazo durante o qual os concorrentes são obrigados a manter as respetivas propostas: 120 dias a contar do termo do prazo para a apresentação das propostas\nApresentação de Catálogo Eletrónico: Não autorizado\nIndicação de Subcontratação na Proposta: Inexistência de indicação de subcontratação\n\n14 - PRESTAÇÃO DE CAUÇÃO\nPrestação de caução: Não\n\n15 - FORNECIMENTO DAS PEÇAS DO CONCURSO, APRESENTAÇÃO DE PEDIDOS DE PARTICIPAÇÃO E APRESENTAÇÃO DAS PROPOSTAS\nLink para acesso às peças do concurso (URL): https://community.vortal.biz/Public/public-tender-documents/cnJnNEt4SGpRTmR1UW9TbkVYK2oxQVZ3byt5SjZUVnZuM2tmNG5oTHA2NHZEbFM5RVZYMU1PYjNjc1UrSUpYT2dKZ0pXTGprcmxITXR0SCtsd3lSNVE9PXF1Q20m\n\n20 - OUTROS REQUISITOS\nInformação sobre contratos reservados. Aplica-se a contratos reservados (54º-A)? Não\n\n21 - CRITÉRIO DE ADJUDICAÇÃO\nMultifator: Não\nMonofator:\nNome: Outros\nOutro nome: Preço\n\n24 - CONDIÇÕES DO CONTRATO\nFaturação Eletrónica: Permitido\nObrigação de Subcontratação:\nCódigo da Obrigação de Subcontratação: Não é aplicável nenhuma obrigação de subcontratação.\n\n25 - COMPRA PÚBLICA ESTRATÉGICA\nCompra Pública Estratégica: Inexistência de contratação pública estratégica\n\n26 - INFORMAÇÕES ADICIONAIS\nContrato adequado para PME: Sim\nCobertura ACP (Acordo dos Contratos Públicos da Organização Mundial do Comércio): Não\n\n27 - IDENTIFICAÇÃO E CONTACTOS DO ÓRGÃO DE RECURSOS ADMINISTRATIVOS\nDesignação: E-REDES - Distribuição de Eletricidade, S.A.\nEndereço: Rua D. Luís I, n.º 12\nCódigo postal: 1249-008\nLocalidade: Lisboa\nTelefone: +351 210021400\nFax: +351 210021400\nEndereço eletrónico: qualificacao.fornecedores@e-redes.pt\n\n28 - IDENTIFICAÇÃO DO(S) AUTOR(ES) DE ANÚNCIO\nNome: Margarida Martins Almeida\nCargo: Gestora de Fornecedores e Sustentabilidade\n419919581",
    "nipc": "504394029",
    "distrito": "Lisboa",
    "concelho": "Lisboa",
    "freguesia": "Freguesia de Misericórdia",
    "site": "https://www.e-redes.pt",
    "email": "qualificacao.fornecedores@e-redes.pt",
    "designacao_contrato": "Geradores",
    "descricao": "Fornecimento de Geradores de 630 KVA e 250 KVA",
    "preco_base": null,
    "prazo_execucao": "12 MESES",
    "prazo_apresentacao_propostas": null,
    "fundos_eu": "Não",
    "plataforma_eletronica": "VORTAL",
    "url_procedimento": "https://community.vortal.biz/public/",
    "autor_nome": "Margarida Martins Almeida",
    "autor_cargo": "Gestora de Fornecedores e Sustentabilidade"
  },
  {
    "numero_procedimento": "N/A",
    "entidade": "Metro Mondego, SA",
    "link": "https://diariodarepublica.pt/dr/detalhe/contrato-publico/33469-992908295",
    "detalhes_completos": "1 - IDENTIFICAÇÃO E CONTACTOS DA ENTIDADE ADJUDICANTE\nDesignação da entidade adjudicante: Metro Mondego, SA\nNIPC: 503671320\nServiço/Órgão/Pessoa de contacto: Conselho de Administração\nEndereço: Rua de Olivença n.º 11 1.º\nCódigo postal: 3000-306\nLocalidade: Coimbra\nPaís: Portugal\nNUT III: PT16E\nDistrito: Coimbra\nConcelho: Coimbra\nFreguesia: União das Freguesias de Coimbra (Sé Nova, Santa Cruz, Almedina e São Bartolomeu)\nTelefone: 239488100\nFax: 239488100\nEndereço da Entidade (URL): https://metromondego.pt/pt\nEndereço Eletrónico: metro@metromondego.pt\neDelivery Gateway (URL): https://www.acingov.pt\nFunção da Organização: Adquirente\nNorma jurídica da Entidade Adjudicante: Organismo de direito público\nÁrea de atividade da Autoridade Adjudicante: Serviços públicos das administrações públicas\n\n2 - JORNAL OFICIAL DA UNIÃO EUROPEIA\nO procedimento a que este anúncio diz respeito também é publicitado no Jornal Oficial da União Europeia? Sim\n\n3 - AVISO\nModelo de Anúncio: Concurso público\nData de Envio do Anúncio: 26-12-2025\n\n5 - PROCESSO\nTipo de Procedimento: Concurso público\nPreço base do procedimento: Sim\nValor do preço base do procedimento: 1.090.406,00 EUR\nProcedimento com lotes? Não\n\n6 - OBJETO DO CONTRATO\nNúmero de referência interna: 2025_03_DO\nDesignação do contrato: Prestação de serviços de limpeza de instalações (PMO), veículos e estações\nDescrição: Prestação de serviços de limpeza de instalações (PMO), veículos e estações\nOpções: Não\nTipo de Contrato Principal: Aquisição de Serviços\nTipo de Contrato: Aquisição de Serviços\nClassificação CPV (Vocabulário Comum para os Contratos Públicos)\nObjeto principal\nVocabulário Principal: 90911200\nPreço base s/IVA: 763.284,20 EUR\nObjeto Complementar\nVocabulário Principal: 90917000\nPreço base s/IVA: 327.121,80 EUR\n\n7 - INDICAÇÕES ADICIONAIS\nO contrato envolve aquisição conjunta (satisfação de várias entidades)? Não\nO contrato é adjudicado por uma central de compras? Não\n\n8 - TÉCNICAS\nO concurso destina-se à celebração de um acordo-quadro? Inexistência de acordo-quadro\nÉ utilizado um leilão eletrónico? Não\nÉ adotada uma fase de negociação? Não\nSistema de Aquisição Dinâmico: Inexistência de sistema de aquisição dinâmico\n\n9 - LOCAL DA EXECUÇÃO DO CONTRATO\nLOCAL DA EXECUÇÃO DO CONTRATO (PROCEDIMENTO)\nPaís: Portugal\nNUT III: PT16E\nLocalidade: Coimbra\nDistrito: Coimbra\nConcelho: Coimbra\nFreguesia: Todas\nPaís: Portugal\nNUT III: PT16E\nLocalidade: Miranda do Corvo\nDistrito: Coimbra\nConcelho: Miranda do Corvo\nFreguesia: Todas\nPaís: Portugal\nNUT III: PT16E\nLocalidade: Lousã\nDistrito: Coimbra\nConcelho: Lousã\nFreguesia: Todas\n\n10 - PRAZO DE EXECUÇÃO DO CONTRATO\nPrazo de execução do contrato: 36 MESES\nPrevisão de renovações: Não\n\n11 - FUNDOS EU\nTêm fundos EU? Não\n\n12 - DOCUMENTOS DE HABILITAÇÃO\nHabilitação para o exercício da atividade profissional: Não\n\n13 - CONDIÇÕES DE APRESENTAÇÃO\nPlataforma eletrónica utilizada pela entidade adjudicante: ACIN\nURL para Apresentação: https://www.acingov.pt\nAdmissibilidade da apresentação de propostas variantes: Não autorizado\nPrazo para apresentação das propostas: 09-02-2026 17:59\nPrazo durante o qual os concorrentes são obrigados a manter as respetivas propostas: 120 dias a contar do termo do prazo para a apresentação das propostas\nApresentação de Catálogo Eletrónico: Permitido\nIndicação de Subcontratação na Proposta: Inexistência de indicação de subcontratação\n\n14 - PRESTAÇÃO DE CAUÇÃO\nPrestação de caução: Sim\nPercentagem: 5%\nDescrição da Garantia Exigida: O valor da caução é de 5.00% do preço contratual.\n\n15 - FORNECIMENTO DAS PEÇAS DO CONCURSO, APRESENTAÇÃO DE PEDIDOS DE PARTICIPAÇÃO E APRESENTAÇÃO DAS PROPOSTAS\nLink para acesso às peças do concurso (URL): https://www.acingov.pt/acingovprod/2/zonaPublica/zona_publica_c/donwloadProcedurePiece/MTAwODg4MA==\n\n20 - OUTROS REQUISITOS\nInformação sobre contratos reservados. Aplica-se a contratos reservados (54º-A)? Não\n\n21 - CRITÉRIO DE ADJUDICAÇÃO\nMultifator: Não\nMonofator:\nNome: Preço\n\n24 - CONDIÇÕES DO CONTRATO\nFaturação Eletrónica: Permitido\nObrigação de Subcontratação:\nCódigo da Obrigação de Subcontratação: Não é aplicável nenhuma obrigação de subcontratação.\n\n25 - COMPRA PÚBLICA ESTRATÉGICA\nCompra Pública Estratégica: Inexistência de contratação pública estratégica\n\n26 - INFORMAÇÕES ADICIONAIS\nContrato adequado para PME: Não\nCobertura ACP (Acordo dos Contratos Públicos da Organização Mundial do Comércio): Não\n\n27 - IDENTIFICAÇÃO E CONTACTOS DO ÓRGÃO DE RECURSOS ADMINISTRATIVOS\nDesignação: Conselho de Administração da Metro Mondego, S.A.\nEndereço: Rua de Olivença n.º 11 1.º\nCódigo postal: 3000-306\nLocalidade: Coimbra\nTelefone: 239488100\nFax: 239488100\nEndereço eletrónico: metro@metromondego.pt\n\n28 - IDENTIFICAÇÃO DO(S) AUTOR(ES) DE ANÚNCIO\nNome: Filipa Alexandra da Costa Rodrigues\nCargo: Técnica Superior\n419932435",
    "nipc": "503671320",
    "distrito": "Coimbra",
    "concelho": "Coimbra",
    "freguesia": "União das Freguesias de Coimbra (Sé Nova, Santa Cruz, Almedina e São Bartolomeu)",
    "site": "https://metromondego.pt/pt",
    "email": "metro@metromondego.pt",
    "designacao_contrato": "Prestação de serviços de limpeza de instalações (PMO), veículos e estações",
    "descricao": "Prestação de serviços de limpeza de instalações (PMO), veículos e estações",
    "preco_base": "763.284,20 EUR",
    "prazo_execucao": "36 MESES",
    "prazo_apresentacao_propostas": "09-02-2026 17:59",
    "fundos_eu": "Não",
    "plataforma_eletronica": "ACIN",
    "url_procedimento": "https://www.acingov.pt",
    "autor_nome": "Filipa Alexandra da Costa Rodrigues",
    "autor_cargo": "Técnica Superior"
  },
  {
    "numero_procedimento": "N/A",
    "entidade": "Município das Caldas da Rainha",
    "link": "https://diariodarepublica.pt/dr/detalhe/contrato-publico/33475-992908298",
    "detalhes_completos": "1 - IDENTIFICAÇÃO E CONTACTOS DA ENTIDADE ADJUDICANTE\nDesignação da entidade adjudicante: Município das Caldas da Rainha\nNIPC: 501222634\nEndereço: PRAÇA 25 DE ABRIL\nCódigo postal: 2500-110\nLocalidade: Leiria\nPaís: Portugal\nNUT III: PT16B\nDistrito: Leiria\nConcelho: Caldas da Rainha\nFreguesia: União das Freguesias de Caldas da Rainha - Nossa Senhora do Pópulo, Coto e São Gregório\nTelefone: 262240000\nFax: 262839729\nEndereço da Entidade (URL): www.mcr.pt\nEndereço Eletrónico: contratacao.publica@mcr.pt\neDelivery Gateway (URL): https://community.vortal.biz/public/\nFunção da Organização: Adquirente\nNorma jurídica da Entidade Adjudicante: Organismo de direito público\nÁrea de atividade da Autoridade Adjudicante: Serviços públicos das administrações públicas\n\n2 - JORNAL OFICIAL DA UNIÃO EUROPEIA\nO procedimento a que este anúncio diz respeito também é publicitado no Jornal Oficial da União Europeia? Não\n\n3 - AVISO\nModelo de Anúncio: Concurso público\nData de Envio do Anúncio: 29-12-2025\n\n5 - PROCESSO\nTipo de Procedimento: Concurso público\nPreço base do procedimento: Sim\nValor do preço base do procedimento: 300.000,00 EUR\nProcedimento com lotes? Não\n\n6 - OBJETO DO CONTRATO\nNúmero de referência interna: 2024/78-1\nDesignação do contrato: Arruamentos da Cidade e Outros 2024 (Estacionamento na Cutileira)\nDescrição: Estacionamento na Cutileira\nTipo de Contrato Principal: Empreitada de Obras Públicas\nTipo de Contrato: Empreitada de Obras Públicas\nClassificação CPV (Vocabulário Comum para os Contratos Públicos)\nObjeto principal\nVocabulário Principal: 45223300\nPreço base s/IVA: 300.000,00 EUR\n\n7 - INDICAÇÕES ADICIONAIS\nO contrato envolve aquisição conjunta (satisfação de várias entidades)? Não\nO contrato é adjudicado por uma central de compras? Não\n\n8 - TÉCNICAS\nO concurso destina-se à celebração de um acordo-quadro? Inexistência de acordo-quadro\nÉ utilizado um leilão eletrónico? Não\nÉ adotada uma fase de negociação? Não\nSistema de Aquisição Dinâmico: Inexistência de sistema de aquisição dinâmico\n\n9 - LOCAL DA EXECUÇÃO DO CONTRATO\nLOCAL DA EXECUÇÃO DO CONTRATO (PROCEDIMENTO)\nPaís: Portugal\nNUT III: PT16B\nLocalidade: Leiria\nDistrito: Leiria\nConcelho: Caldas da Rainha\nFreguesia: União das Freguesias de Caldas da Rainha - Nossa Senhora do Pópulo, Coto e São Gregório\n\n10 - PRAZO DE EXECUÇÃO DO CONTRATO\nPrazo de execução do contrato: 150 DIAS\nPrevisão de renovações: Não\n\n11 - FUNDOS EU\nTêm fundos EU? Não\n\n12 - DOCUMENTOS DE HABILITAÇÃO\nHabilitação para o exercício da atividade profissional: Sim\nTipo: Alvará\nDescrição: Detenção do alvará de empreiteiro de obras públicas, emitido pelo IMPIC ou certificado de empreiteiro de obras públicas que contenha a habilitação da 1.ª subcategoria da 2.ª categoria, em classe que cubra o preço total da proposta\n\n13 - CONDIÇÕES DE APRESENTAÇÃO\nPlataforma eletrónica utilizada pela entidade adjudicante: VORTAL\nURL para Apresentação: https://community.vortal.biz/public/\nAdmissibilidade da apresentação de propostas variantes: Não autorizado\nPrazo para apresentação das propostas: 19-01-2026 23:59\nPrazo durante o qual os concorrentes são obrigados a manter as respetivas propostas: 150 dias a contar do termo do prazo para a apresentação das propostas\nIndicação de Subcontratação na Proposta: Inexistência de indicação de subcontratação\n\n14 - PRESTAÇÃO DE CAUÇÃO\nPrestação de caução: Sim\nPercentagem: 5%\nDescrição da Garantia Exigida: A caução poderá ser apresentada por qualquer das modalidades previstas no artigo 90.º do Código dos Contratos Públicos\n\n15 - FORNECIMENTO DAS PEÇAS DO CONCURSO, APRESENTAÇÃO DE PEDIDOS DE PARTICIPAÇÃO E APRESENTAÇÃO DAS PROPOSTAS\nLink para acesso às peças do concurso (URL): https://community.vortal.biz/Public/public-tender-documents/ck5OcUREUytxbklzK2tMaGY1Yjl1cElJVW1TVGJWa1NvSkkxczNyT0hLaEZiWjQ0ZHZCcm85M3NVZk92T1BXeGcyQmF6NU5PRFpZU0xsUWpDMkhlQ2c9PXFzUXRs\n\n20 - OUTROS REQUISITOS\nInformação sobre contratos reservados. Aplica-se a contratos reservados (54º-A)? Não\n\n21 - CRITÉRIO DE ADJUDICAÇÃO\nMultifator: Não\nMonofator:\nNome: Preço\n\n24 - CONDIÇÕES DO CONTRATO\nFaturação Eletrónica: Permitido\nObrigação de Subcontratação:\nCódigo da Obrigação de Subcontratação: Não é aplicável nenhuma obrigação de subcontratação.\n\n25 - COMPRA PÚBLICA ESTRATÉGICA\nCompra Pública Estratégica: Inexistência de contratação pública estratégica\n\n26 - INFORMAÇÕES ADICIONAIS\nContrato adequado para PME: Sim\nCobertura ACP (Acordo dos Contratos Públicos da Organização Mundial do Comércio): Não\n\n27 - IDENTIFICAÇÃO E CONTACTOS DO ÓRGÃO DE RECURSOS ADMINISTRATIVOS\nDesignação: Tribunal Administrativo e Fiscal de Leiria\nEndereço: Rua João Paulo II, CV RC\nCódigo postal: 2410-112\nLocalidade: Leiria\nTelefone: +351 244870600\nFax: +351 244870600\nEndereço eletrónico: leiria.taf@tribunais.org.pt\n\n28 - IDENTIFICAÇÃO DO(S) AUTOR(ES) DE ANÚNCIO\nNome: Vítor Manuel Calisto Marques\nCargo: Presidente da Câmara Municipal\n419933504",
    "nipc": "501222634",
    "distrito": "Leiria",
    "concelho": "Caldas da Rainha",
    "freguesia": "União das Freguesias de Caldas da Rainha - Nossa Senhora do Pópulo, Coto e São Gregório",
    "site": "www.mcr.pt",
    "email": "contratacao.publica@mcr.pt",
    "designacao_contrato": "Arruamentos da Cidade e Outros 2024 (Estacionamento na Cutileira)",
    "descricao": "Estacionamento na Cutileira",
    "preco_base": "300.000,00 EUR",
    "prazo_execucao": "150 DIAS",
    "prazo_apresentacao_propostas": "19-01-2026 23:59",
    "fundos_eu": "Não",
    "plataforma_eletronica": "VORTAL",
    "url_procedimento": "https://community.vortal.biz/public/",
    "autor_nome": "Vítor Manuel Calisto Marques",
    "autor_cargo": "Presidente da Câmara Municipal"
  },
  {
    "numero_procedimento": "N/A",
    "entidade": "Município de Carregal do Sal",
    "link": "https://diariodarepublica.pt/dr/detalhe/contrato-publico/33476-992908299",
    "detalhes_completos": "1 - IDENTIFICAÇÃO E CONTACTOS DA ENTIDADE ADJUDICANTE\nDesignação da entidade adjudicante: Município de Carregal do Sal\nNIPC: 506684920\nServiço/Órgão/Pessoa de contacto: Presidente da Câmara\nEndereço: Praça do Município Atílio dos Santos Nunes\nCódigo postal: 3430-167\nLocalidade: Carregal do sal\nPaís: Portugal\nNUT III: PT16G\nDistrito: Viseu\nConcelho: Carregal do Sal\nFreguesia: Todas\nTelefone: 232960400\nFax: 23296409\nEndereço da Entidade (URL): https://www.cm-carregal.pt/\nEndereço Eletrónico: geral@cm-carregal.pt\neDelivery Gateway (URL): https://www.acingov.pt\nFunção da Organização: Adquirente\nNorma jurídica da Entidade Adjudicante: Organismo de direito público\nÁrea de atividade da Autoridade Adjudicante: Serviços públicos das administrações públicas\n\n2 - JORNAL OFICIAL DA UNIÃO EUROPEIA\nO procedimento a que este anúncio diz respeito também é publicitado no Jornal Oficial da União Europeia? Não\n\n3 - AVISO\nModelo de Anúncio: Concurso público\nData de Envio do Anúncio: 29-12-2025\n\n5 - PROCESSO\nTipo de Procedimento: Concurso público\nPreço base do procedimento: Sim\nValor do preço base do procedimento: 4.450.000,00 EUR\nProcedimento com lotes? Não\n\n6 - OBJETO DO CONTRATO\nNúmero de referência interna: 17/2025\nDesignação do contrato: Centro de Acolhimento e Integração de Refugiados Aristides de Sousa Mendes- BNAUT\nDescrição: Centro de Acolhimento e Integração de Refugiados Aristides de Sousa Mendes- BNAUT \nTipo de Contrato Principal: Empreitada de Obras Públicas\nTipo de Contrato: Empreitada de Obras Públicas\nClassificação CPV (Vocabulário Comum para os Contratos Públicos)\nObjeto principal\nVocabulário Principal: 45211200\nPreço base s/IVA: 4.450.000,00 EUR\n\n7 - INDICAÇÕES ADICIONAIS\nO contrato envolve aquisição conjunta (satisfação de várias entidades)? Não\nO contrato é adjudicado por uma central de compras? Não\n\n8 - TÉCNICAS\nO concurso destina-se à celebração de um acordo-quadro? Inexistência de acordo-quadro\nÉ utilizado um leilão eletrónico? Não\nÉ adotada uma fase de negociação? Não\nSistema de Aquisição Dinâmico: Inexistência de sistema de aquisição dinâmico\n\n9 - LOCAL DA EXECUÇÃO DO CONTRATO\nLOCAL DA EXECUÇÃO DO CONTRATO (PROCEDIMENTO)\nPaís: Portugal\nNUT III: PT16G\nLocalidade: Freguesia de Cabanas de Viriato\nDistrito: Viseu\nConcelho: Carregal do Sal\nFreguesia: Freguesia de Cabanas de Viriato\n\n10 - PRAZO DE EXECUÇÃO DO CONTRATO\nPrazo de execução do contrato: 270 DIAS\nPrevisão de renovações: Não\n\n11 - FUNDOS EU\nTêm fundos EU? Sim\n\n12 - DOCUMENTOS DE HABILITAÇÃO\nHabilitação para o exercício da atividade profissional: Sim\nTipo: Alvará\nDescrição: a) A 1ª subcategoria da 1ª categoria, em classe correspondente ao valor da proposta;\nb)A 2ª, 4ª, 5ª, 6ª, 7ª, 8ª e a 9ª subcategorias da 1ª categoria, a 1ª, 6ª, 9ª, 10ª, 11ª, 12ª e 19ª subcategorias da 4ª categoria, e a 1ª, 2ª, 8ª, 10ª, 11ª e 12ª subcategorias da 5ª categoria, as quais têm de ser de classe correspondente à parte dos trabalhos a que respeitem;\n\n13 - CONDIÇÕES DE APRESENTAÇÃO\nPlataforma eletrónica utilizada pela entidade adjudicante: ACIN\nURL para Apresentação: https://www.acingov.pt\nAdmissibilidade da apresentação de propostas variantes: Não autorizado\nPrazo para apresentação das propostas: 19-01-2026 23:59\nPrazo durante o qual os concorrentes são obrigados a manter as respetivas propostas: 120 dias a contar do termo do prazo para a apresentação das propostas\nIndicação de Subcontratação na Proposta: Inexistência de indicação de subcontratação\n\n14 - PRESTAÇÃO DE CAUÇÃO\nPrestação de caução: Sim\nPercentagem: 5%\nDescrição da Garantia Exigida: O valor da caução é de 5.00% do preço contratual.\n\n15 - FORNECIMENTO DAS PEÇAS DO CONCURSO, APRESENTAÇÃO DE PEDIDOS DE PARTICIPAÇÃO E APRESENTAÇÃO DAS PROPOSTAS\nLink para acesso às peças do concurso (URL): https://www.acingov.pt/acingovprod/2/zonaPublica/zona_publica_c/donwloadProcedurePiece/MTAwNDkzMA==\n\n20 - OUTROS REQUISITOS\nInformação sobre contratos reservados. Aplica-se a contratos reservados (54º-A)? Não\n\n21 - CRITÉRIO DE ADJUDICAÇÃO\nMultifator: Sim\nFator: \nNome: Preço\nPonderação: 60%\nSubfatores: Não\nFator: \nNome: Outros\nOutro Nome: Valia Técnica\nPonderação: 40%\nSubfatores: Sim\nSubfatores: \nNome: Memória descritiva e justificativa (Mdj)\nPonderação : 50%; \nNome: Plano de trabalhos (Pt)\nPonderação : 20%; \nNome: Plano de mão de obra (Pm)\nPonderação : 15%; \nNome: Plano de equipamentos (Pe)\nPonderação : 15%; \n\n24 - CONDIÇÕES DO CONTRATO\nFaturação Eletrónica: Permitido\nObrigação de Subcontratação:\nCódigo da Obrigação de Subcontratação: Não é aplicável nenhuma obrigação de subcontratação.\n\n25 - COMPRA PÚBLICA ESTRATÉGICA\nCompra Pública Estratégica: Inexistência de contratação pública estratégica\n\n26 - INFORMAÇÕES ADICIONAIS\nContrato adequado para PME: Não\nCobertura ACP (Acordo dos Contratos Públicos da Organização Mundial do Comércio): Não\n\n27 - IDENTIFICAÇÃO E CONTACTOS DO ÓRGÃO DE RECURSOS ADMINISTRATIVOS\nDesignação: Presidente da Câmara\nEndereço: Praça do Município Atílio dos Santos Nunes\nCódigo postal: 3430-167\nLocalidade: Carregal do sal\nTelefone: 232960400\nFax: 232960409\nEndereço eletrónico: geral@cm-carregal.pt\nPrazo de interposição do recurso: 5 dias\n\n28 - IDENTIFICAÇÃO DO(S) AUTOR(ES) DE ANÚNCIO\nNome: Paulo Jorge Catalino de Almeida Ferraz\nCargo: Presidente da Câmara\n419933512",
    "nipc": "506684920",
    "distrito": "Viseu",
    "concelho": "Carregal do Sal",
    "freguesia": "Todas",
    "site": "https://www.cm-carregal.pt/",
    "email": "geral@cm-carregal.pt",
    "designacao_contrato": "Centro de Acolhimento e Integração de Refugiados Aristides de Sousa Mendes- BNAUT",
    "descricao": "Centro de Acolhimento e Integração de Refugiados Aristides de Sousa Mendes- BNAUT",
    "preco_base": "4.450.000,00 EUR",
    "prazo_execucao": "270 DIAS",
    "prazo_apresentacao_propostas": "19-01-2026 23:59",
    "fundos_eu": "Sim",
    "plataforma_eletronica": "ACIN",
    "url_procedimento": "https://www.acingov.pt",
    "autor_nome": "Paulo Jorge Catalino de Almeida Ferraz",
    "autor_cargo": "Presidente da Câmara"
  },
  {
    "numero_procedimento": "N/A",
    "entidade": "Estado Maior da Força Aérea",
    "link": "https://diariodarepublica.pt/dr/detalhe/contrato-publico/33478-992908310",
    "detalhes_completos": "1 - IDENTIFICAÇÃO E CONTACTOS DA ENTIDADE ADJUDICANTE\nDesignação da entidade adjudicante: Estado Maior da Força Aérea\nNIPC: 600010686\nServiço/Órgão/Pessoa de contacto: Comando da Logística da Força Aérea  Direção de Infraestruturas\nEndereço: Avenida da Força Aérea Portuguesa, Nº1, Edif. A, Piso 6\nCódigo postal: 2614-506\nLocalidade: Amadora\nPaís: Portugal\nNUT III: PT170\nDistrito: Lisboa\nConcelho: Amadora\nFreguesia: Freguesia de Alfragide\nTelefone: 214723696\nEndereço da Entidade (URL): www.emfa.pt\nEndereço Eletrónico: di.rprojetos.chf@emfa.gov.pt\neDelivery Gateway (URL): https://www.acingov.pt\nFunção da Organização: Adquirente\nNorma jurídica da Entidade Adjudicante: Organismo de direito público\nÁrea de atividade da Autoridade Adjudicante: Defesa\n\n2 - JORNAL OFICIAL DA UNIÃO EUROPEIA\nO procedimento a que este anúncio diz respeito também é publicitado no Jornal Oficial da União Europeia? Não\n\n3 - AVISO\nModelo de Anúncio: Concurso público\nData de Envio do Anúncio: 29-12-2025\n\n5 - PROCESSO\nTipo de Procedimento: Concurso público\nPreço base do procedimento: Sim\nValor do preço base do procedimento: 2.850.000,00 EUR\nProcedimento com lotes? Não\n\n6 - OBJETO DO CONTRATO\nNúmero de referência interna: CP 12/DI/2025\nDesignação do contrato: CONSTRUÇÃO DE EDIFÍCIO PARA A ESQUADRA DE VOO DO SA A-29N NA BA11 - BEJA\nDescrição: CONSTRUÇÃO DE EDIFÍCIO PARA A ESQUADRA DE VOO DO SA A-29N NA BA11 - BEJA\nTipo de Contrato Principal: Empreitada de Obras Públicas\nTipo de Contrato: Empreitada de Obras Públicas\nClassificação CPV (Vocabulário Comum para os Contratos Públicos)\nObjeto principal\nVocabulário Principal: 45216200\nPreço base s/IVA: 2.850.000,00 EUR\n\n7 - INDICAÇÕES ADICIONAIS\nO contrato envolve aquisição conjunta (satisfação de várias entidades)? Não\nO contrato é adjudicado por uma central de compras? Não\n\n8 - TÉCNICAS\nO concurso destina-se à celebração de um acordo-quadro? Inexistência de acordo-quadro\nÉ utilizado um leilão eletrónico? Não\nÉ adotada uma fase de negociação? Não\nSistema de Aquisição Dinâmico: Inexistência de sistema de aquisição dinâmico\n\n9 - LOCAL DA EXECUÇÃO DO CONTRATO\nLOCAL DA EXECUÇÃO DO CONTRATO (PROCEDIMENTO)\nPaís: Portugal\nNUT III: PT184\nLocalidade: União das Freguesias de Trigaches e São Brissos\nDistrito: Beja\nConcelho: Beja\nFreguesia: União das Freguesias de Trigaches e São Brissos\n\n10 - PRAZO DE EXECUÇÃO DO CONTRATO\nPrazo de execução do contrato: 420 DIAS\nPrevisão de renovações: Não\n\n11 - FUNDOS EU\nTêm fundos EU? Não\n\n12 - DOCUMENTOS DE HABILITAÇÃO\nHabilitação para o exercício da atividade profissional: Sim\nTipo: Alvará\nDescrição: A 1.ª subcategoria da 1.ª categoria, a qual tem que ser de classe que cubra o valor global da proposta e integrar-se na categoria em que o tipo de obra se enquadra;\nAs 2.ª, 4.ª, 5.ª, 6.ª, 7.ª e 8.ª subcategorias da 1.ª categoria, as 1.ª, 3.ª, 9.ª, 10.ª e 12.ª subcategorias da 4.ª categoria e as 2.ª, 8.ª, 10.ª, 11.ª e 12.ª subcategorias da 5.ª categoria, na classe correspondente à parte dos trabalhos a que respeitem.\n\n13 - CONDIÇÕES DE APRESENTAÇÃO\nPlataforma eletrónica utilizada pela entidade adjudicante: ACIN\nURL para Apresentação: https://www.acingov.pt\nAdmissibilidade da apresentação de propostas variantes: Não autorizado\nPrazo para apresentação das propostas: 28-01-2026 23:00\nPrazo durante o qual os concorrentes são obrigados a manter as respetivas propostas: 66 dias a contar do termo do prazo para a apresentação das propostas\nIndicação de Subcontratação na Proposta: Inexistência de indicação de subcontratação\n\n14 - PRESTAÇÃO DE CAUÇÃO\nPrestação de caução: Sim\nPercentagem: 5%\nDescrição da Garantia Exigida: O valor da caução é de 5.00% do preço contratual.\n\n15 - FORNECIMENTO DAS PEÇAS DO CONCURSO, APRESENTAÇÃO DE PEDIDOS DE PARTICIPAÇÃO E APRESENTAÇÃO DAS PROPOSTAS\nLink para acesso às peças do concurso (URL): https://www.acingov.pt/acingovprod/2/zonaPublica/zona_publica_c/donwloadProcedurePiece/MTAwOTU0OA==\n\n20 - OUTROS REQUISITOS\nInformação sobre contratos reservados. Aplica-se a contratos reservados (54º-A)? Não\n\n21 - CRITÉRIO DE ADJUDICAÇÃO\nMultifator: Não\nMonofator:\nNome: Preço\n\n24 - CONDIÇÕES DO CONTRATO\nFaturação Eletrónica: Permitido\nObrigação de Subcontratação:\nCódigo da Obrigação de Subcontratação: Não é aplicável nenhuma obrigação de subcontratação.\n\n25 - COMPRA PÚBLICA ESTRATÉGICA\nCompra Pública Estratégica: Inexistência de contratação pública estratégica\n\n26 - INFORMAÇÕES ADICIONAIS\nContrato adequado para PME: Não\nCobertura ACP (Acordo dos Contratos Públicos da Organização Mundial do Comércio): Não\n\n27 - IDENTIFICAÇÃO E CONTACTOS DO ÓRGÃO DE RECURSOS ADMINISTRATIVOS\nDesignação: Chefe do Estado-Maior da Força Aérea\nEndereço: Avenida da Força Aérea Portuguesa, Nº1\nCódigo postal: 2614-506\nLocalidade: Amadora\nEndereço eletrónico: clafa.secpub@emfa.gov.pt\n\n28 - IDENTIFICAÇÃO DO(S) AUTOR(ES) DE ANÚNCIO\nNome: COR/ADMAER/FILIPE RODRIGUES\nCargo: CHEFE DO GAP\n419933861",
    "nipc": "600010686",
    "distrito": "Lisboa",
    "concelho": "Amadora",
    "freguesia": "Freguesia de Alfragide",
    "site": "www.emfa.pt",
    "email": "di.rprojetos.chf@emfa.gov.pt",
    "designacao_contrato": "CONSTRUÇÃO DE EDIFÍCIO PARA A ESQUADRA DE VOO DO SA A-29N NA BA11 - BEJA",
    "descricao": "CONSTRUÇÃO DE EDIFÍCIO PARA A ESQUADRA DE VOO DO SA A-29N NA BA11 - BEJA",
    "preco_base": "2.850.000,00 EUR",
    "prazo_execucao": "420 DIAS",
    "prazo_apresentacao_propostas": "28-01-2026 23:00",
    "fundos_eu": "Não",
    "plataforma_eletronica": "ACIN",
    "url_procedimento": "https://www.acingov.pt",
    "autor_nome": "COR/ADMAER/FILIPE RODRIGUES",
    "autor_cargo": "CHEFE DO GAP"
  },
  {
    "numero_procedimento": "N/A",
    "entidade": "Secretaria Regional de Agricultura e Pescas",
    "link": "https://diariodarepublica.pt/dr/detalhe/contrato-publico/33479-992908311",
    "detalhes_completos": "1 - IDENTIFICAÇÃO E CONTACTOS DA ENTIDADE ADJUDICANTE\nDesignação da entidade adjudicante: Secretaria Regional de Agricultura e Pescas\nNIPC: 671001299\nServiço/Órgão/Pessoa de contacto: Direção de Serviços de Apoio à Gestão\nEndereço: Rua Dr. Pestana Júnior, nº 6 - 5º Andar\nCódigo postal: 9064-506\nLocalidade: Funchal\nPaís: Portugal\nNUT III: PT300\nDistrito: Região Autónoma da Madeira\nConcelho: Todos\nFreguesia: Todas\nTelefone: 291145600\nFax: 291225112\nEndereço da Entidade (URL): www.madeira.gov.pt\nEndereço Eletrónico: gabinete.srap@madeira.gov.pt\neDelivery Gateway (URL): https://www.acingov.pt\nFunção da Organização: Adquirente\nSubfunção da Organização: Organização que recebe as propostas\nNorma jurídica da Entidade Adjudicante: Organismo de direito público\nÁrea de atividade da Autoridade Adjudicante: Serviços públicos das administrações públicas\n\n2 - JORNAL OFICIAL DA UNIÃO EUROPEIA\nO procedimento a que este anúncio diz respeito também é publicitado no Jornal Oficial da União Europeia? Não\n\n3 - AVISO\nModelo de Anúncio: Concurso público\nData de Envio do Anúncio: 29-12-2025\n\n5 - PROCESSO\nTipo de Procedimento: Concurso público\nPreço base do procedimento: Sim\nValor do preço base do procedimento: 85.125,67 EUR\nProcedimento com lotes? Não\n\n6 - OBJETO DO CONTRATO\nNúmero de referência interna: CP N.º18/SRAP-DRA/2025\nDesignação do contrato: Aquisição de dois (2) empilhadores elétricos para a Rede de Centros de Abastecimento Agrícola da RAM\nDescrição: Aquisição de dois (2) empilhadores elétricos para a Rede de Centros de Abastecimento Agrícola da RAM\nTipo de Contrato Principal: Aquisição de Bens Móveis\nTipo de Contrato: Aquisição de Bens Móveis\nClassificação CPV (Vocabulário Comum para os Contratos Públicos)\nObjeto principal\nVocabulário Principal: 42415000\nPreço base s/IVA: 85.125,67 EUR\n\n7 - INDICAÇÕES ADICIONAIS\nO contrato envolve aquisição conjunta (satisfação de várias entidades)? Não\nO contrato é adjudicado por uma central de compras? Não\n\n8 - TÉCNICAS\nO concurso destina-se à celebração de um acordo-quadro? Inexistência de acordo-quadro\nÉ utilizado um leilão eletrónico? Não\nÉ adotada uma fase de negociação? Não\nSistema de Aquisição Dinâmico: Inexistência de sistema de aquisição dinâmico\n\n9 - LOCAL DA EXECUÇÃO DO CONTRATO\nLOCAL DA EXECUÇÃO DO CONTRATO (PROCEDIMENTO)\nPaís: Portugal\nNUT III: PT300\nLocalidade: Freguesia de São Martinho - Funchal\nDistrito: Região Autónoma da Madeira\nConcelho: Funchal\nFreguesia: Freguesia de São Martinho - Funchal\n\n10 - PRAZO DE EXECUÇÃO DO CONTRATO\nPrazo de execução do contrato: 120 DIAS\nPrevisão de renovações: Não\n\n11 - FUNDOS EU\nTêm fundos EU? Sim\n\n12 - DOCUMENTOS DE HABILITAÇÃO\nHabilitação para o exercício da atividade profissional: Não\n\n13 - CONDIÇÕES DE APRESENTAÇÃO\nPlataforma eletrónica utilizada pela entidade adjudicante: ACIN\nURL para Apresentação: https://www.acingov.pt\nAdmissibilidade da apresentação de propostas variantes: Não autorizado\nPrazo para apresentação das propostas: 19-01-2026 17:00\nPrazo durante o qual os concorrentes são obrigados a manter as respetivas propostas: 120 dias a contar do termo do prazo para a apresentação das propostas\nIndicação de Subcontratação na Proposta: Inexistência de indicação de subcontratação\n\n14 - PRESTAÇÃO DE CAUÇÃO\nPrestação de caução: Não\n\n15 - FORNECIMENTO DAS PEÇAS DO CONCURSO, APRESENTAÇÃO DE PEDIDOS DE PARTICIPAÇÃO E APRESENTAÇÃO DAS PROPOSTAS\nLink para acesso às peças do concurso (URL): https://www.acingov.pt/acingovprod/2/zonaPublica/zona_publica_c/donwloadProcedurePiece/MTAwOTM2NQ==\n\n20 - OUTROS REQUISITOS\nInformação sobre contratos reservados. Aplica-se a contratos reservados (54º-A)? Não\n\n21 - CRITÉRIO DE ADJUDICAÇÃO\nMultifator: Não\nMonofator:\nNome: Preço\n\n24 - CONDIÇÕES DO CONTRATO\nFaturação Eletrónica: Permitido\nObrigação de Subcontratação:\nCódigo da Obrigação de Subcontratação: Não é aplicável nenhuma obrigação de subcontratação.\n\n25 - COMPRA PÚBLICA ESTRATÉGICA\nCompra Pública Estratégica: Inexistência de contratação pública estratégica\n\n26 - INFORMAÇÕES ADICIONAIS\nContrato adequado para PME: Não\nCobertura ACP (Acordo dos Contratos Públicos da Organização Mundial do Comércio): Não\n\n27 - IDENTIFICAÇÃO E CONTACTOS DO ÓRGÃO DE RECURSOS ADMINISTRATIVOS\nDesignação: Secretário Regional de Agricultura e Pescas\nEndereço: Rua Dr. Pestana Júnior, nº 6 - 5º Andar\nCódigo postal: 9064-506\nLocalidade: Funchal\nTelefone: 291145600\nFax: \nEndereço eletrónico: gabinete.srap@madeira.gov.pt\nPrazo de interposição do recurso: 30 dias\n\n28 - IDENTIFICAÇÃO DO(S) AUTOR(ES) DE ANÚNCIO\nNome: Nuno Dinarte de Gouveia Maciel\nCargo: Secretário Regional de Agricultura e Pescas\n419933667",
    "nipc": "671001299",
    "distrito": "Região Autónoma da Madeira",
    "concelho": "Todos",
    "freguesia": "Todas",
    "site": "www.madeira.gov.pt",
    "email": "gabinete.srap@madeira.gov.pt",
    "designacao_contrato": "Aquisição de dois (2) empilhadores elétricos para a Rede de Centros de Abastecimento Agrícola da RAM",
    "descricao": "Aquisição de dois (2) empilhadores elétricos para a Rede de Centros de Abastecimento Agrícola da RAM",
    "preco_base": "85.125,67 EUR",
    "prazo_execucao": "120 DIAS",
    "prazo_apresentacao_propostas": "19-01-2026 17:00",
    "fundos_eu": "Sim",
    "plataforma_eletronica": "ACIN",
    "url_procedimento": "https://www.acingov.pt",
    "autor_nome": "Nuno Dinarte de Gouveia Maciel",
    "autor_cargo": "Secretário Regional de Agricultura e Pescas"
  },
  {
    "numero_procedimento": "N/A",
    "entidade": "Estrutura de Missão «Recuperar Portugal»",
    "link": "https://diariodarepublica.pt/dr/detalhe/contrato-publico/33480-992908312",
    "detalhes_completos": "Alteração do Anúncio de procedimento n.º 32490/2025, de 2025-12-15, com o ID 419884062\n\n1 - IDENTIFICAÇÃO E CONTACTOS DA ENTIDADE ADJUDICANTE\nDesignação da entidade adjudicante: Estrutura de Missão «Recuperar Portugal»\nNIPC: 600087590\nServiço/Órgão/Pessoa de contacto: Núcleo de Contratação Pública\nEndereço: Avenida João Crisóstomo n.º 11\nCódigo postal: 1000-177\nLocalidade: Lisboa\nPaís: Portugal\nNUT III: PT170\nDistrito: Lisboa\nConcelho: Lisboa\nFreguesia: Freguesia de Avenidas Novas\nTelefone: 218801120\nFax: 218801120\nEndereço da Entidade (URL): https://recuperarportugal.gov.pt\nEndereço Eletrónico: contratacao@recuperarportugal.gov.pt\neDelivery Gateway (URL): https://www.acingov.pt\nFunção da Organização: Adquirente\nNorma jurídica da Entidade Adjudicante: Organismo de direito público\nÁrea de atividade da Entidade Adjudicante: Serviços postais\n\n2 - JORNAL OFICIAL DA UNIÃO EUROPEIA\nO procedimento a que este anúncio diz respeito também é publicitado no Jornal Oficial da União Europeia? Não\n\n3 - AVISO\nModelo de Anúncio: Concurso público\nData de Envio do Anúncio: 29-12-2025\n\n5 - PROCESSO\nTipo de Procedimento: Concurso público\nPreço base do procedimento: Sim\nValor do preço base do procedimento: 100.000,00 EUR\nProcedimento com lotes? Não\n\n6 - OBJETO DO CONTRATO\nNúmero de referência interna: CP/EMRP/7/2025\nDesignação do contrato: Aquisição de serviços para realização de estudo tendente à avaliação de Fundos Europeus: Mobilização dos Apoios à Eficiência Energética\nDescrição: Aquisição de serviços para realização de estudo tendente à avaliação de Fundos Europeus: Mobilização dos Apoios à Eficiência Energética\nTipo de Contrato Principal: Aquisição de Serviços\nTipo de Contrato: Aquisição de Serviços\nClassificação CPV (Vocabulário Comum para os Contratos Públicos)\nObjeto principal\nVocabulário Principal: 79419000\nPreço base s/IVA: 100.000,00 EUR\n\n7 - INDICAÇÕES ADICIONAIS\nO contrato envolve aquisição conjunta (satisfação de várias entidades)? Não\nO contrato é adjudicado por uma central de compras? Não\n\n8 - TÉCNICAS\nO concurso destina-se à celebração de um acordo-quadro? Inexistência de acordo-quadro\nÉ utilizado um leilão eletrónico? Não\nÉ adotada uma fase de negociação? Não\nSistema de Aquisição Dinâmico: Inexistência de sistema de aquisição dinâmico\n\n9 - LOCAL DA EXECUÇÃO DO CONTRATO\nLOCAL DA EXECUÇÃO DO CONTRATO (PROCEDIMENTO)\nPaís: Portugal\nNUT III: PT170\nLocalidade: LisboaLisboa\nDistrito: Lisboa\nConcelho: Lisboa\nFreguesia: Freguesia de Avenidas Novas\n\n10 - PRAZO DE EXECUÇÃO DO CONTRATO\nPrazo de execução do contrato: 12 MESES\nPrevisão de renovações: Sim\nIndicar número máximo de renovações: 1\nPrazo de renovações diferente do prazo inicial: Sim\nIndicar o prazo de execução da renovação do contrato: 3 MESES\n\n11 - FUNDOS EU\nTêm fundos EU? Não\n\n12 - DOCUMENTOS DE HABILITAÇÃO\nHabilitação para o exercício da atividade profissional: Não\n\n13 - CONDIÇÕES DE APRESENTAÇÃO\nPlataforma eletrónica utilizada pela entidade adjudicante: ACIN\nURL para Apresentação: https://www.acingov.pt\nAdmissibilidade da apresentação de propostas variantes: Não autorizado\nPrazo para apresentação das propostas: 08-01-2026 23:59\nPrazo durante o qual os concorrentes são obrigados a manter as respetivas propostas: 90 dias a contar do termo do prazo para a apresentação das propostas\nIndicação de Subcontratação na Proposta: Inexistência de indicação de subcontratação\n\n14 - PRESTAÇÃO DE CAUÇÃO\nPrestação de caução: Não\n\n15 - FORNECIMENTO DAS PEÇAS DO CONCURSO, APRESENTAÇÃO DE PEDIDOS DE PARTICIPAÇÃO E APRESENTAÇÃO DAS PROPOSTAS\nLink para acesso às peças do concurso (URL): https://www.acingov.pt/acingovprod/2/zonaPublica/zona_publica_c/donwloadProcedurePiece/MTAwNTI1OQ==\n\n20 - OUTROS REQUISITOS\nInformação sobre contratos reservados. Aplica-se a contratos reservados (54º-A)? Não\n\n21 - CRITÉRIO DE ADJUDICAÇÃO\nMultifator: Sim\nFator: \nNome: Outros\nOutro Nome: Qualidade técnica da Proposta - Metodologia\nPonderação: 50%\nSubfatores: Sim\nSubfatores: \nNome: Métodos de Avaliação\nPonderação : 40%; \nNome: Matriz de Avaliação\nPonderação : 30%; \nNome: Matriz de técnicas de recolha e tratamento de informação\nPonderação : 30%; \nFator: \nNome: Outros\nOutro Nome: Experiência da equipa de avaliação\nPonderação: 20%\nSubfatores: Sim\nSubfatores: \nNome: Formação Académica da Equipa de avaliação proposta\nPonderação : 50%; \nNome: Experiência Profissional da Equipa de avaliação Proposta\nPonderação : 50%; \nFator: \nNome: Preço\nPonderação: 30%\nSubfatores: Não\n\n24 - CONDIÇÕES DO CONTRATO\nFaturação Eletrónica: Permitido\nObrigação de Subcontratação:\nCódigo da Obrigação de Subcontratação: Não é aplicável nenhuma obrigação de subcontratação.\n\n25 - COMPRA PÚBLICA ESTRATÉGICA\nCompra Pública Estratégica: Inexistência de contratação pública estratégica\n\n26 - INFORMAÇÕES ADICIONAIS\nContrato adequado para PME: Não\nCobertura ACP (Acordo dos Contratos Públicos da Organização Mundial do Comércio): Não\n\n27 - IDENTIFICAÇÃO E CONTACTOS DO ÓRGÃO DE RECURSOS ADMINISTRATIVOS\nDesignação: Presidente da EMRP\nEndereço: Avenida João Crisóstomo n.º 11\nCódigo postal: 1000-177\nLocalidade: Lisboa\nTelefone: 218801120\nFax: 218801120\nEndereço eletrónico: contratacao@recuperarportugal.gov.pt\nPrazo de interposição do recurso: 30 dias\n\n28 - IDENTIFICAÇÃO DO(S) AUTOR(ES) DE ANÚNCIO\nNome: Liliana Branco\nCargo: Chefe de Núcleo Contratação Pública\n\n29 - ALTERAÇÃO\nMotivo da Alteração: Informações atualizadas\nIdentificador da Versão do Anúncio a Alterar: a02c48bb-91c7-4a99-8ea9-da71d8dbb12d-01\nIdentificador das Secções Alteradas do Anúncio Anterior: Condições de Apresentação\nDescrição das Alterações: Modificação do prazo para a apresentação de propostas\nAlteração dos Documentos do Concurso: Não\n419933301",
    "nipc": "600087590",
    "distrito": "Lisboa",
    "concelho": "Lisboa",
    "freguesia": "Freguesia de Avenidas Novas",
    "site": "https://recuperarportugal.gov.pt",
    "email": "contratacao@recuperarportugal.gov.pt",
    "designacao_contrato": "Aquisição de serviços para realização de estudo tendente à avaliação de Fundos Europeus: Mobilização dos Apoios à Eficiência Energética",
    "descricao": "Aquisição de serviços para realização de estudo tendente à avaliação de Fundos Europeus: Mobilização dos Apoios à Eficiência Energética",
    "preco_base": "100.000,00 EUR",
    "prazo_execucao": "12 MESES",
    "prazo_apresentacao_propostas": "08-01-2026 23:59",
    "fundos_eu": "Não",
    "plataforma_eletronica": "ACIN",
    "url_procedimento": "https://www.acingov.pt",
    "autor_nome": "Liliana Branco",
    "autor_cargo": "Chefe de Núcleo Contratação Pública"
  },
  {
    "numero_procedimento": "N/A",
    "entidade": "CRPG - Centro de Reabilitação Profissional",
    "link": "https://diariodarepublica.pt/dr/detalhe/contrato-publico/33482-992908313",
    "detalhes_completos": "1 - IDENTIFICAÇÃO E CONTACTOS DA ENTIDADE ADJUDICANTE\nDesignação da entidade adjudicante: CRPG - Centro de Reabilitação Profissional\nNIPC: 504791834\nServiço/Órgão/Pessoa de contacto: Serviços Financeiros\nEndereço: Av. João Paulo II, 961\nCódigo postal: 4410-406\nLocalidade: Vila Nova de Gaia\nPaís: Portugal\nNUT III: PT11A\nDistrito: Porto\nConcelho: Vila Nova de Gaia\nFreguesia: Freguesia de Arcozelo - Vila Nova de Gaia\nTelefone: 227537700\nFax: 227537700\nEndereço da Entidade (URL): www.crpg.pt\nEndereço Eletrónico: compras@crpg.pt\neDelivery Gateway (URL): https://www.acingov.pt\nFunção da Organização: Adquirente\nSubfunção da Organização: Organização que executa o pagamento; Organização que fornece informações adicionais sobre o processo de adjudicação; Organização responsável pelo tratamento das propostas; Organização que recebe as propostas; Organização que assina o contrato\nNorma jurídica da Entidade Adjudicante: Organismo de direito público\nÁrea de atividade da Autoridade Adjudicante: Educação\n\n2 - JORNAL OFICIAL DA UNIÃO EUROPEIA\nO procedimento a que este anúncio diz respeito também é publicitado no Jornal Oficial da União Europeia? Não\n\n3 - AVISO\nModelo de Anúncio: Concurso público\nData de Envio do Anúncio: 29-12-2025\n\n5 - PROCESSO\nTipo de Procedimento: Concurso público\nPreço base do procedimento: Sim\nValor do preço base do procedimento: 150.000,00 EUR\nProcedimento com lotes? Não\n\n6 - OBJETO DO CONTRATO\nNúmero de referência interna: PO.003.2025_16\nDesignação do contrato: Aquisição de infraestrutura de servidores no âmbito do PRR\nDescrição: Aquisição de infraestrutura de servidores no âmbito do PRR\nTipo de Contrato Principal: Aquisição de Bens Móveis\nTipo de Contrato: Aquisição de Bens Móveis\nClassificação CPV (Vocabulário Comum para os Contratos Públicos)\nObjeto principal\nVocabulário Principal: 48820000\nPreço base s/IVA: 150.000,00 EUR\n\n7 - INDICAÇÕES ADICIONAIS\nO contrato envolve aquisição conjunta (satisfação de várias entidades)? Não\nO contrato é adjudicado por uma central de compras? Não\n\n8 - TÉCNICAS\nO concurso destina-se à celebração de um acordo-quadro? Inexistência de acordo-quadro\nÉ utilizado um leilão eletrónico? Não\nÉ adotada uma fase de negociação? Não\nSistema de Aquisição Dinâmico: Inexistência de sistema de aquisição dinâmico\n\n9 - LOCAL DA EXECUÇÃO DO CONTRATO\nLOCAL DA EXECUÇÃO DO CONTRATO (PROCEDIMENTO)\nPaís: Portugal\nNUT III: PT11A\nLocalidade: Freguesia de Arcozelo - Vila Nova de Gaia\nDistrito: Porto\nConcelho: Vila Nova de Gaia\nFreguesia: Freguesia de Arcozelo - Vila Nova de Gaia\n\n10 - PRAZO DE EXECUÇÃO DO CONTRATO\nPrazo de execução do contrato: 60 DIAS\nPrevisão de renovações: Não\n\n11 - FUNDOS EU\nTêm fundos EU? Sim\n\n12 - DOCUMENTOS DE HABILITAÇÃO\nHabilitação para o exercício da atividade profissional: Não\n\n13 - CONDIÇÕES DE APRESENTAÇÃO\nPlataforma eletrónica utilizada pela entidade adjudicante: ACIN\nURL para Apresentação: https://www.acingov.pt\nAdmissibilidade da apresentação de propostas variantes: Não autorizado\nPrazo para apresentação das propostas: 12-01-2026 17:00\nPrazo durante o qual os concorrentes são obrigados a manter as respetivas propostas: 90 dias a contar do termo do prazo para a apresentação das propostas\nIndicação de Subcontratação na Proposta: Inexistência de indicação de subcontratação\n\n14 - PRESTAÇÃO DE CAUÇÃO\nPrestação de caução: Não\n\n15 - FORNECIMENTO DAS PEÇAS DO CONCURSO, APRESENTAÇÃO DE PEDIDOS DE PARTICIPAÇÃO E APRESENTAÇÃO DAS PROPOSTAS\nLink para acesso às peças do concurso (URL): https://www.acingov.pt/acingovprod/2/zonaPublica/zona_publica_c/donwloadProcedurePiece/MTAwOTE1Mw==\n\n20 - OUTROS REQUISITOS\nInformação sobre contratos reservados. Aplica-se a contratos reservados (54º-A)? Não\n\n21 - CRITÉRIO DE ADJUDICAÇÃO\nMultifator: Não\nMonofator:\nNome: Preço\n\n24 - CONDIÇÕES DO CONTRATO\nFaturação Eletrónica: Permitido\nObrigação de Subcontratação:\nCódigo da Obrigação de Subcontratação: Não é aplicável nenhuma obrigação de subcontratação.\n\n25 - COMPRA PÚBLICA ESTRATÉGICA\nCompra Pública Estratégica: Inexistência de contratação pública estratégica\n\n26 - INFORMAÇÕES ADICIONAIS\nContrato adequado para PME: Sim\nCobertura ACP (Acordo dos Contratos Públicos da Organização Mundial do Comércio): Não\n\n27 - IDENTIFICAÇÃO E CONTACTOS DO ÓRGÃO DE RECURSOS ADMINISTRATIVOS\nDesignação: Conselho de Administração\nEndereço: Av. João Paulo II, 961\nCódigo postal: 4410-406\nLocalidade: Vila Nova de Gaia\nTelefone: 227537700\nFax: 227537700\nEndereço eletrónico: compras@crpg.pt\n\n28 - IDENTIFICAÇÃO DO(S) AUTOR(ES) DE ANÚNCIO\nNome: Luisa Mónica Bourbon Salazar\nCargo: Diretora\n419934039",
    "nipc": "504791834",
    "distrito": "Porto",
    "concelho": "Vila Nova de Gaia",
    "freguesia": "Freguesia de Arcozelo - Vila Nova de Gaia",
    "site": "www.crpg.pt",
    "email": "compras@crpg.pt",
    "designacao_contrato": "Aquisição de infraestrutura de servidores no âmbito do PRR",
    "descricao": "Aquisição de infraestrutura de servidores no âmbito do PRR",
    "preco_base": "150.000,00 EUR",
    "prazo_execucao": "60 DIAS",
    "prazo_apresentacao_propostas": "12-01-2026 17:00",
    "fundos_eu": "Sim",
    "plataforma_eletronica": "ACIN",
    "url_procedimento": "https://www.acingov.pt",
    "autor_nome": "Luisa Mónica Bourbon Salazar",
    "autor_cargo": "Diretora"
  },
  {
    "numero_procedimento": "N/A",
    "entidade": "Universidade de Trás-os-Montes e Alto Douro",
    "link": "https://diariodarepublica.pt/dr/detalhe/contrato-publico/33484-992908314",
    "detalhes_completos": "1 - IDENTIFICAÇÃO E CONTACTOS DA ENTIDADE ADJUDICANTE\nDesignação da entidade adjudicante: Universidade de Trás-os-Montes e Alto Douro\nNIPC: 501345361\nServiço/Órgão/Pessoa de contacto: Universidade de Trás-os-Montes e Alto Douro\nEndereço: Quinta de Prados\nCódigo postal: 5000-801\nLocalidade: Vila Real\nPaís: Portugal\nNUT III: PT11D\nDistrito: Vila Real\nConcelho: Vila Real\nFreguesia: Freguesia de Folhadela\nTelefone: 259350000\nFax: 259350000\nEndereço da Entidade (URL): www.utad.pt\nEndereço Eletrónico: centcompras@utad.pt\nFunção da Organização: Adquirente\nNorma jurídica da Entidade Adjudicante: Organismo de direito público\nÁrea de atividade da Entidade Adjudicante: Atividades aeroportuárias\n\n2 - JORNAL OFICIAL DA UNIÃO EUROPEIA\nO procedimento a que este anúncio diz respeito também é publicitado no Jornal Oficial da União Europeia? Não\n\n3 - AVISO\nModelo de Anúncio: Concurso público\nData de Envio do Anúncio: 29-12-2025\n\n5 - PROCESSO\nTipo de Procedimento: Concurso público\nPreço base do procedimento: Sim\nValor do preço base do procedimento: 40.000,00 EUR\nProcedimento com lotes? Não\n\n6 - OBJETO DO CONTRATO\nNúmero de referência interna: CP_PC 1007/2025\nDesignação do contrato: Aquisição de Serviço para o Desenvolvimento e Implementação de uma Plataforma Digital de Informação\nDescrição: Aquisição de Serviço para o Desenvolvimento e Implementação de uma Plataforma Digital de Informação\nTipo de Contrato Principal: Aquisição de Serviços\nTipo de Contrato: Aquisição de Serviços\nClassificação CPV (Vocabulário Comum para os Contratos Públicos)\nObjeto principal\nVocabulário Principal: 72263000\nPreço base s/IVA: 40.000,00 EUR\n\n7 - INDICAÇÕES ADICIONAIS\nO contrato envolve aquisição conjunta (satisfação de várias entidades)? Não\nO contrato é adjudicado por uma central de compras? Não\n\n8 - TÉCNICAS\nO concurso destina-se à celebração de um acordo-quadro? Inexistência de acordo-quadro\nÉ utilizado um leilão eletrónico? Não\nÉ adotada uma fase de negociação? Não\nSistema de Aquisição Dinâmico: Inexistência de sistema de aquisição dinâmico\n\n9 - LOCAL DA EXECUÇÃO DO CONTRATO\nLOCAL DA EXECUÇÃO DO CONTRATO (PROCEDIMENTO)\nPaís: Portugal\nNUT III: PT11D\nLocalidade: Vila Real\nDistrito: Vila Real\nConcelho: Vila Real\nFreguesia: Freguesia de Folhadela\n\n10 - PRAZO DE EXECUÇÃO DO CONTRATO\nPrazo de execução do contrato: 5 MESES\nPrevisão de renovações: Não\n\n11 - FUNDOS EU\nTêm fundos EU? Não\n\n12 - DOCUMENTOS DE HABILITAÇÃO\nHabilitação para o exercício da atividade profissional: Não\n\n13 - CONDIÇÕES DE APRESENTAÇÃO\nPlataforma eletrónica utilizada pela entidade adjudicante: ANOGOV\nURL para Apresentação: https://www.anogov.com/me-utad/faces/\nAdmissibilidade da apresentação de propostas variantes: Não autorizado\nPrazo para apresentação das propostas: 05-01-2026 23:59\nPrazo durante o qual os concorrentes são obrigados a manter as respetivas propostas: 66 dias a contar do termo do prazo para a apresentação das propostas\nApresentação de Catálogo Eletrónico: Não autorizado\nIndicação de Subcontratação na Proposta: O(s) subcontratante(s) proposto(s) necessário(s) para cumprir a obrigação de subcontratar uma percentagem mínima do contrato\n\n14 - PRESTAÇÃO DE CAUÇÃO\nPrestação de caução: Não\n\n15 - FORNECIMENTO DAS PEÇAS DO CONCURSO, APRESENTAÇÃO DE PEDIDOS DE PARTICIPAÇÃO E APRESENTAÇÃO DAS PROPOSTAS\nLink para acesso às peças do concurso (URL): https://www.anogov.com/me-utad/faces/app/acessoDocs.jsp?codigoAcesso=OtI6dmBwCgdM68SzbNUfaqGi7MM4JZObSgaKHmenBYBK16oChW\n\n20 - OUTROS REQUISITOS\nInformação sobre contratos reservados. Aplica-se a contratos reservados (54º-A)? Não\n\n21 - CRITÉRIO DE ADJUDICAÇÃO\nMultifator: Não\nMonofator:\nNome: Preço\n\n24 - CONDIÇÕES DO CONTRATO\nFaturação Eletrónica: Permitido\nObrigação de Subcontratação:\nCódigo da Obrigação de Subcontratação: Não é aplicável nenhuma obrigação de subcontratação.\n\n25 - COMPRA PÚBLICA ESTRATÉGICA\nCompra Pública Estratégica: Inexistência de contratação pública estratégica\n\n26 - INFORMAÇÕES ADICIONAIS\nContrato adequado para PME: Sim\nCobertura ACP (Acordo dos Contratos Públicos da Organização Mundial do Comércio): Não\n\n27 - IDENTIFICAÇÃO E CONTACTOS DO ÓRGÃO DE RECURSOS ADMINISTRATIVOS\nDesignação: Universidade de Trás-os-Montes e Alto Douro\nEndereço: Quinta de Prados\nCódigo postal: 5000-801\nLocalidade: Vila Real\nEndereço eletrónico: centcompras@utad.pt\nPrazo de interposição do recurso: 10 dias\n\n28 - IDENTIFICAÇÃO DO(S) AUTOR(ES) DE ANÚNCIO\nNome: Fernanda M Augusto\nCargo: Técnica Superior\n419933853",
    "nipc": "501345361",
    "distrito": "Vila Real",
    "concelho": "Vila Real",
    "freguesia": "Freguesia de Folhadela",
    "site": "www.utad.pt",
    "email": "centcompras@utad.pt",
    "designacao_contrato": "Aquisição de Serviço para o Desenvolvimento e Implementação de uma Plataforma Digital de Informação",
    "descricao": "Aquisição de Serviço para o Desenvolvimento e Implementação de uma Plataforma Digital de Informação",
    "preco_base": "40.000,00 EUR",
    "prazo_execucao": "5 MESES",
    "prazo_apresentacao_propostas": "05-01-2026 23:59",
    "fundos_eu": "Não",
    "plataforma_eletronica": "ANOGOV",
    "url_procedimento": "https://www.anogov.com/me-utad/faces/",
    "autor_nome": "Fernanda M Augusto",
    "autor_cargo": "Técnica Superior"
  },
  {
    "numero_procedimento": "N/A",
    "entidade": "Imprensa Nacional - Casa da Moeda, SA",
    "link": "https://diariodarepublica.pt/dr/detalhe/contrato-publico/33485-992908315",
    "detalhes_completos": "Alteração do Anúncio de procedimento n.º 33331/2025, de 2025-12-23, com o ID 419928978\n\n1 - IDENTIFICAÇÃO E CONTACTOS DA ENTIDADE ADJUDICANTE\nDesignação da entidade adjudicante: Imprensa Nacional - Casa da Moeda, SA\nNIPC: 500792887\nServiço/Órgão/Pessoa de contacto: Imprensa Nacional Casa da Moeda, SA\nEndereço: Av. António José de Almeida\nCódigo postal: 1000-042\nLocalidade: Lisboa\nPaís: Portugal\nNUT III: PT170\nDistrito: Lisboa\nConcelho: Lisboa\nFreguesia: Freguesia de Avenidas Novas\nTelefone: 217810700\nFax: 217810700\nEndereço da Entidade (URL): www.incm.pt\nEndereço Eletrónico: compras@incm.pt\neDelivery Gateway (URL): https://www.acingov.pt\nFunção da Organização: Adquirente\nNorma jurídica da Entidade Adjudicante: Organismo de direito público\nÁrea de atividade da Autoridade Adjudicante: Serviços públicos das administrações públicas\n\n2 - JORNAL OFICIAL DA UNIÃO EUROPEIA\nO procedimento a que este anúncio diz respeito também é publicitado no Jornal Oficial da União Europeia? Não\n\n3 - AVISO\nModelo de Anúncio: Concurso público\nData de Envio do Anúncio: 29-12-2025\n\n5 - PROCESSO\nTipo de Procedimento: Concurso público\nPreço base do procedimento: Sim\nValor do preço base do procedimento: 220.000,00 EUR\nProcedimento com lotes? Sim\nNº Máx. de Lotes Autorizado: 2\nNúmero máximo de lotes que podem ser adjudicados a um concorrente: 2\n\n6 - OBJETO DO CONTRATO\nNúmero de referência interna: 491/2025\nDesignação do contrato: Aquisição de Serviços de Gestão de Resíduos Industriais\nDescrição: Aquisição de Serviços de Gestão de Resíduos Industriais \nTipo de Contrato Principal: Aquisição de Serviços\nTipo de Contrato: Aquisição de Serviços\nClassificação CPV (Vocabulário Comum para os Contratos Públicos)\nObjeto principal\nVocabulário Principal: 90511000\nPreço base s/IVA: 220.000,00 EUR\nLotes: \nNº: LOT-0001\nDescrição do Lote: Recolha e transporte de resíduos industriais banais\nPreço base s/IVA: 190.000,00 EUR\nClassificação CPV (Vocabulário Comum para os Contratos Públicos)\nObjeto principal\nVocabulário Principal: 90511000\nNº: LOT-0002\nDescrição do Lote: Transporte de resíduos com medidas de segurança\nPreço base s/IVA: 30.000,00 EUR\nClassificação CPV (Vocabulário Comum para os Contratos Públicos)\nObjeto principal\nVocabulário Principal: 90511000\n\n7 - INDICAÇÕES ADICIONAIS\nO contrato envolve aquisição conjunta (satisfação de várias entidades)? Não\nO contrato é adjudicado por uma central de compras? Não\n\n8 - TÉCNICAS\nO concurso destina-se à celebração de um acordo-quadro? Inexistência de acordo-quadro\nÉ utilizado um leilão eletrónico? Não\nÉ adotada uma fase de negociação? Não\nSistema de Aquisição Dinâmico: Inexistência de sistema de aquisição dinâmico\n\n9 - LOCAL DA EXECUÇÃO DO CONTRATO\nLOCAL DA EXECUÇÃO DO CONTRATO (PROCEDIMENTO)\nPaís: Portugal\nNUT III: PT170\nLocalidade: Freguesia de Avenidas Novas\nDistrito: Lisboa\nConcelho: Lisboa\nFreguesia: Freguesia de Avenidas Novas\nLOCAL DA EXECUÇÃO DO CONTRATO (LOTE)\nIdentificador do Lote: LOT-0001; LOT-0002\nPaís: Portugal\nNUT III: PT170\nLocalidade: Freguesia de Avenidas Novas\nDistrito: Lisboa\nConcelho: Lisboa\nFreguesia: Freguesia de Avenidas Novas\n\n10 - PRAZO DE EXECUÇÃO DO CONTRATO\nIdentificador do Lote: LOT-0001; LOT-0002\nPrazo de execução do contrato: 36 MESES\nPrevisão de renovações: Não\n\n11 - FUNDOS EU\nIdentificador do Lote: LOT-0001; LOT-0002\nTêm fundos EU? Não\n\n12 - DOCUMENTOS DE HABILITAÇÃO\nHabilitação para o exercício da atividade profissional: Não\n\n13 - CONDIÇÕES DE APRESENTAÇÃO\nPlataforma eletrónica utilizada pela entidade adjudicante: ACIN\nURL para Apresentação: https://www.acingov.pt\nAdmissibilidade da apresentação de propostas variantes: Não autorizado\nPrazo para apresentação das propostas: 19-01-2026 17:00\nPrazo durante o qual os concorrentes são obrigados a manter as respetivas propostas: 66 dias a contar do termo do prazo para a apresentação das propostas\nIndicação de Subcontratação na Proposta: Inexistência de indicação de subcontratação\n\n14 - PRESTAÇÃO DE CAUÇÃO\nPrestação de caução: Não\n\n15 - FORNECIMENTO DAS PEÇAS DO CONCURSO, APRESENTAÇÃO DE PEDIDOS DE PARTICIPAÇÃO E APRESENTAÇÃO DAS PROPOSTAS\nLink para acesso às peças do concurso (URL): https://www.acingov.pt/acingovprod/2/zonaPublica/zona_publica_c/donwloadProcedurePiece/MTAwOTMzNw==\n\n20 - OUTROS REQUISITOS\nIdentificador do Lote: LOT-0001; LOT-0002\nInformação sobre contratos reservados. Aplica-se a contratos reservados (54º-A)? Não\n\n21 - CRITÉRIO DE ADJUDICAÇÃO\nO Critério de adjudicação é diferenciado por lote? Sim\nIdentificador do lote: LOT-0001\nMultifator: Sim\nFator: \nNome: Outros\nOutro Nome: A  Preço total de custos (Recolha, Transporte, Custo de tratamento)\nPonderação: 80%\nSubfatores: Não\nFator: \nNome: Outros\nOutro Nome: B  Tratamento com proveitos para a INCM\nPonderação: 10%\nSubfatores: Não\nFator: \nNome: Outros\nOutro Nome: C  N.º de itens/códigos sem custo de tratamento\nPonderação: 10%\nSubfatores: Não\nO Critério de adjudicação é diferenciado por lote? Sim\nIdentificador do lote: LOT-0002\nMultifator: Não\nMonofator:\nNome: Preço\n\n24 - CONDIÇÕES DO CONTRATO\nIdentificador do Lote: LOT-0001; LOT-0002\nFaturação Eletrónica: Permitido\nObrigação de Subcontratação:\nCódigo da Obrigação de Subcontratação: Não é aplicável nenhuma obrigação de subcontratação.\n\n25 - COMPRA PÚBLICA ESTRATÉGICA\nCompra Pública Estratégica: Inexistência de contratação pública estratégica\n\n26 - INFORMAÇÕES ADICIONAIS\nIdentificador do Lote: LOT-0001; LOT-0002\nContrato adequado para PME: Não\nCobertura ACP (Acordo dos Contratos Públicos da Organização Mundial do Comércio): Não\n\n27 - IDENTIFICAÇÃO E CONTACTOS DO ÓRGÃO DE RECURSOS ADMINISTRATIVOS\nDesignação: INCM\nEndereço: Av. Antonio José Almeida\nCódigo postal: 1000-042\nLocalidade: Lisboa\nTelefone: 217810893\nFax: \nEndereço eletrónico: compras@incm.pt\n\n28 - IDENTIFICAÇÃO DO(S) AUTOR(ES) DE ANÚNCIO\nNome: Dora Moita\nCargo: Presidente Conselho Administração\n\n29 - ALTERAÇÃO\nMotivo da Alteração: Correção pelo adquirente\nIdentificador da Versão do Anúncio a Alterar: 36832f98-d7d7-4634-a8a4-9e3eb60e98fc-01\nIdentificador das Secções Alteradas do Anúncio Anterior: Condições de Apresentação; Identificação do(s) autor(es) do anúncio\nDescrição das Alterações: Modificação do prazo para a apresentação de propostas Atualização do(s) autor(es) do anúncio\nAlteração dos Documentos do Concurso: Não\n419933829",
    "nipc": "500792887",
    "distrito": "Lisboa",
    "concelho": "Lisboa",
    "freguesia": "Freguesia de Avenidas Novas",
    "site": "www.incm.pt",
    "email": "compras@incm.pt",
    "designacao_contrato": "Aquisição de Serviços de Gestão de Resíduos Industriais",
    "descricao": "Aquisição de Serviços de Gestão de Resíduos Industriais",
    "preco_base": "220.000,00 EUR",
    "prazo_execucao": "36 MESES",
    "prazo_apresentacao_propostas": "19-01-2026 17:00",
    "fundos_eu": "Não",
    "plataforma_eletronica": "ACIN",
    "url_procedimento": "https://www.acingov.pt",
    "autor_nome": "Dora Moita",
    "autor_cargo": "Presidente Conselho Administração"
  },
  {
    "numero_procedimento": "N/A",
    "entidade": "Unidade Local de Saúde do Oeste, EPE",
    "link": "https://diariodarepublica.pt/dr/detalhe/contrato-publico/33487-992908316",
    "detalhes_completos": "1 - IDENTIFICAÇÃO E CONTACTOS DA ENTIDADE ADJUDICANTE\nDesignação da entidade adjudicante: Unidade Local de Saúde do Oeste, EPE\nNIPC: 514993871\nEndereço: Rua Diário de Notícias\nCódigo postal: 2500-176\nLocalidade: Leiria\nPaís: Portugal\nNUT III: PT16B\nDistrito: Leiria\nConcelho: Caldas da Rainha\nFreguesia: União das Freguesias de Caldas da Rainha - Nossa Senhora do Pópulo, Coto e São Gregório\nTelefone: 262830300\nFax: 262830300\nEndereço da Entidade (URL): https://www.choeste.min-saude.pt\nEndereço Eletrónico: aprovisionamento@choeste.min-saude.pt\neDelivery Gateway (URL): https://community.vortal.biz/public/\nFunção da Organização: Adquirente\nNorma jurídica da Entidade Adjudicante: Organismo de direito público\nÁrea de atividade da Autoridade Adjudicante: Saúde\n\n2 - JORNAL OFICIAL DA UNIÃO EUROPEIA\nO procedimento a que este anúncio diz respeito também é publicitado no Jornal Oficial da União Europeia? Não\n\n3 - AVISO\nModelo de Anúncio: Concurso público\nData de Envio do Anúncio: 29-12-2025\n\n5 - PROCESSO\nTipo de Procedimento: Concurso público\nPreço base do procedimento: Sim\nValor do preço base do procedimento: 220.950,00 EUR\nProcedimento com lotes? Não\n\n6 - OBJETO DO CONTRATO\nNúmero de referência interna: 11/80/2026 \nDesignação do contrato: Reagentes de Paíneis Diagnóstico Sindrómico Rápido por Biologia Molecular c/ colocação de equipamento\nDescrição: Reagentes de Paíneis Diagnóstico Sindrómico Rápido por Biologia Molecular c/ colocação de equipamento\nTipo de Contrato Principal: Aquisição de Bens Móveis\nTipo de Contrato: Aquisição de Bens Móveis\nClassificação CPV (Vocabulário Comum para os Contratos Públicos)\nObjeto principal\nVocabulário Principal: 33696500\nPreço base s/IVA: 220.950,00 EUR\n\n7 - INDICAÇÕES ADICIONAIS\nO contrato envolve aquisição conjunta (satisfação de várias entidades)? Não\nO contrato é adjudicado por uma central de compras? Não\n\n8 - TÉCNICAS\nO concurso destina-se à celebração de um acordo-quadro? Inexistência de acordo-quadro\nÉ utilizado um leilão eletrónico? Não\nÉ adotada uma fase de negociação? Não\nSistema de Aquisição Dinâmico: Inexistência de sistema de aquisição dinâmico\n\n9 - LOCAL DA EXECUÇÃO DO CONTRATO\nLOCAL DA EXECUÇÃO DO CONTRATO (PROCEDIMENTO)\nPaís: Portugal\nNUT III: PT16B\nLocalidade: Leiria\nDistrito: Leiria\nConcelho: Caldas da Rainha\nFreguesia: União das Freguesias de Caldas da Rainha - Nossa Senhora do Pópulo, Coto e São Gregório\n\n10 - PRAZO DE EXECUÇÃO DO CONTRATO\nPrazo de execução do contrato: 36 MESES\nPrevisão de renovações: Não\n\n11 - FUNDOS EU\nTêm fundos EU? Não\n\n12 - DOCUMENTOS DE HABILITAÇÃO\nHabilitação para o exercício da atividade profissional: Não\n\n13 - CONDIÇÕES DE APRESENTAÇÃO\nPlataforma eletrónica utilizada pela entidade adjudicante: VORTAL\nURL para Apresentação: https://community.vortal.biz/public/\nAdmissibilidade da apresentação de propostas variantes: Não autorizado\nPrazo para apresentação das propostas: 09-01-2026 17:00\nPrazo durante o qual os concorrentes são obrigados a manter as respetivas propostas: 120 dias a contar do termo do prazo para a apresentação das propostas\nIndicação de Subcontratação na Proposta: Inexistência de indicação de subcontratação\n\n14 - PRESTAÇÃO DE CAUÇÃO\nPrestação de caução: Não\n\n15 - FORNECIMENTO DAS PEÇAS DO CONCURSO, APRESENTAÇÃO DE PEDIDOS DE PARTICIPAÇÃO E APRESENTAÇÃO DAS PROPOSTAS\nLink para acesso às peças do concurso (URL): https://community.vortal.biz/Public/public-tender-documents/dGg3bzhjUUkrdjM3ZlQ2dmZCZWdPVlA2TE8xS1doaUgyUlBVNnp0R3kzMnNhMTkwckhzaWl6eTFBWUZLN1BhdzRBK2ZPRTJabEYyVWs0QjZDMEpCSEE9PWFlZGth\n\n20 - OUTROS REQUISITOS\nInformação sobre contratos reservados. Aplica-se a contratos reservados (54º-A)? Não\n\n21 - CRITÉRIO DE ADJUDICAÇÃO\nMultifator: Sim\nFator: \nNome: Preço\nPonderação: 50%\nSubfatores: Não\nFator: \nNome: Qualidade\nPonderação: 50%\nSubfatores: Não\n\n24 - CONDIÇÕES DO CONTRATO\nFaturação Eletrónica: Permitido\nObrigação de Subcontratação:\nCódigo da Obrigação de Subcontratação: Não é aplicável nenhuma obrigação de subcontratação.\n\n25 - COMPRA PÚBLICA ESTRATÉGICA\nCompra Pública Estratégica: Inexistência de contratação pública estratégica\n\n26 - INFORMAÇÕES ADICIONAIS\nContrato adequado para PME: Sim\nCobertura ACP (Acordo dos Contratos Públicos da Organização Mundial do Comércio): Não\n\n27 - IDENTIFICAÇÃO E CONTACTOS DO ÓRGÃO DE RECURSOS ADMINISTRATIVOS\nDesignação: Conselho de Administração da Unidade Local de Saúde do Oeste EPE\nEndereço: Rua Diário de Notícias\nCódigo postal: 2500-176\nLocalidade: Caldas da Rainha\nTelefone: +351 262830300\nFax: +351 262830300\nEndereço eletrónico: secretariado.ca@ulso.min-saude.pt\n\n28 - IDENTIFICAÇÃO DO(S) AUTOR(ES) DE ANÚNCIO\nNome: Drª Elsa Maria Baião Ferreira Airoso Banza\nCargo: Presidente Conselho de Administração\n419934314",
    "nipc": "514993871",
    "distrito": "Leiria",
    "concelho": "Caldas da Rainha",
    "freguesia": "União das Freguesias de Caldas da Rainha - Nossa Senhora do Pópulo, Coto e São Gregório",
    "site": "https://www.choeste.min-saude.pt",
    "email": "aprovisionamento@choeste.min-saude.pt",
    "designacao_contrato": "Reagentes de Paíneis Diagnóstico Sindrómico Rápido por Biologia Molecular c/ colocação de equipamento",
    "descricao": "Reagentes de Paíneis Diagnóstico Sindrómico Rápido por Biologia Molecular c/ colocação de equipamento",
    "preco_base": "220.950,00 EUR",
    "prazo_execucao": "36 MESES",
    "prazo_apresentacao_propostas": "09-01-2026 17:00",
    "fundos_eu": "Não",
    "plataforma_eletronica": "VORTAL",
    "url_procedimento": "https://community.vortal.biz/public/",
    "autor_nome": "Drª Elsa Maria Baião Ferreira Airoso Banza",
    "autor_cargo": "Presidente Conselho de Administração"
  },
  {
    "numero_procedimento": "N/A",
    "entidade": "Associação de Turismo de Lisboa - Visitors and Convention Bureau",
    "link": "https://diariodarepublica.pt/dr/detalhe/contrato-publico/33491-992908318",
    "detalhes_completos": "1 - IDENTIFICAÇÃO E CONTACTOS DA ENTIDADE ADJUDICANTE\nDesignação da entidade adjudicante: Associação de Turismo de Lisboa - Visitors and Convention Bureau\nNIPC: 501880160\nEndereço: R do Arsenal, 15\nCódigo postal: 1100-038\nLocalidade: Lisboa\nPaís: Portugal\nNUT III: PT170\nDistrito: Lisboa\nConcelho: Lisboa\nFreguesia: Todas\nTelefone: 210312700\nFax: 210312899\nEndereço da Entidade (URL): https://www.visitlisboa.com/pt-pt\nEndereço Eletrónico: atl@visitlisboa.com\neDelivery Gateway (URL): https://community.vortal.biz/public/\nFunção da Organização: Adquirente\nNorma jurídica da Entidade Adjudicante: Organização que adjudica um contrato subvencionado por uma autoridade adjudicante\nÁrea de atividade da Autoridade Adjudicante: Serviços públicos das administrações públicas\n\n2 - JORNAL OFICIAL DA UNIÃO EUROPEIA\nO procedimento a que este anúncio diz respeito também é publicitado no Jornal Oficial da União Europeia? Não\n\n3 - AVISO\nModelo de Anúncio: Concurso público\nData de Envio do Anúncio: 29-12-2025\n\n5 - PROCESSO\nTipo de Procedimento: Concurso público\nPreço base do procedimento: Sim\nValor do preço base do procedimento: 1.250.000,00 EUR\nProcedimento com lotes? Não\n\n6 - OBJETO DO CONTRATO\nNúmero de referência interna: 17.II_EMPREITADA_CP_01_2025\nDesignação do contrato: CONCURSO PÚBLICO N.º 17.II_EMPREITADA_CP_01_2025\nDescrição: Empreitada de obra pública de requalificação do Parque Botânico do Monteiro-Mor do Museu Nacional do Traje\nTipo de Contrato Principal: Empreitada de Obras Públicas\nTipo de Contrato: Empreitada de Obras Públicas\nClassificação CPV (Vocabulário Comum para os Contratos Públicos)\nObjeto principal\nVocabulário Principal: 45212000\nPreço base s/IVA: 1.250.000,00 EUR\n\n7 - INDICAÇÕES ADICIONAIS\nO contrato envolve aquisição conjunta (satisfação de várias entidades)? Não\nO contrato é adjudicado por uma central de compras? Não\n\n8 - TÉCNICAS\nO concurso destina-se à celebração de um acordo-quadro? Inexistência de acordo-quadro\nÉ utilizado um leilão eletrónico? Não\nÉ adotada uma fase de negociação? Não\nSistema de Aquisição Dinâmico: Inexistência de sistema de aquisição dinâmico\n\n9 - LOCAL DA EXECUÇÃO DO CONTRATO\nLOCAL DA EXECUÇÃO DO CONTRATO (PROCEDIMENTO)\nPaís: Portugal\nNUT III: PT170\nLocalidade: Lisboa\nDistrito: Lisboa\nConcelho: Lisboa\nFreguesia: Todas\n\n10 - PRAZO DE EXECUÇÃO DO CONTRATO\nPrazo de execução do contrato: 6 MESES\nPrevisão de renovações: Não\n\n11 - FUNDOS EU\nTêm fundos EU? Sim\n\n12 - DOCUMENTOS DE HABILITAÇÃO\nHabilitação para o exercício da atividade profissional: Sim\nTipo: Alvará\nDescrição: i. 1.ª categoria, 1.ª subcategoria, classe 1;\nii. 1.ª categoria, 4.ª subcategoria, classe 1;\niii. 1.ª categoria, 5.ª subcategoria, classe 1;\niv. 1.ª categoria, 8.ª subcategoria, classe 1;\nv. 1.ª categoria, 10.ª subcategoria, classe 4;\nvi. 5.ª categoria, 4.ª subcategoria, classe 1;\nvii. 5.ª categoria, 9.ª subcategoria, classe 1; e\nviii. 5.ª categoria, 12.ª subcategoria, classe 1;\n\n13 - CONDIÇÕES DE APRESENTAÇÃO\nPlataforma eletrónica utilizada pela entidade adjudicante: VORTAL\nURL para Apresentação: https://community.vortal.biz/public/\nAdmissibilidade da apresentação de propostas variantes: Não autorizado\nPrazo para apresentação das propostas: 19-01-2026 23:59\nPrazo durante o qual os concorrentes são obrigados a manter as respetivas propostas: 66 dias a contar do termo do prazo para a apresentação das propostas\nIndicação de Subcontratação na Proposta: Inexistência de indicação de subcontratação\n\n14 - PRESTAÇÃO DE CAUÇÃO\nPrestação de caução: Sim\nPercentagem: 5%\nDescrição da Garantia Exigida: É exigida a prestação de caução, no valor de 5% do preço contratual, em conformidade com o disposto nos artigos 88.º, n.º 1 e n.º 2 alínea a) e 89.º, n.º 1, ambos do CCP;\n\n15 - FORNECIMENTO DAS PEÇAS DO CONCURSO, APRESENTAÇÃO DE PEDIDOS DE PARTICIPAÇÃO E APRESENTAÇÃO DAS PROPOSTAS\nLink para acesso às peças do concurso (URL): https://community.vortal.biz/Public/public-tender-documents/ZlV6L1FFY1FOQkhNRlI4ditjUzh1MTlIZkJUcGprelRCS3k2azdmTE9jd3FzRkMwd0tsME9ZcHlTZWF4RWVPS0d3c3pGZkExQjdiNFRiMVFXWTJNZEE9PU56cl9M\n\n20 - OUTROS REQUISITOS\nInformação sobre contratos reservados. Aplica-se a contratos reservados (54º-A)? Não\n\n21 - CRITÉRIO DE ADJUDICAÇÃO\nMultifator: Não\nMonofator:\nNome: Preço\n\n24 - CONDIÇÕES DO CONTRATO\nFaturação Eletrónica: Permitido\nObrigação de Subcontratação:\nCódigo da Obrigação de Subcontratação: Não é aplicável nenhuma obrigação de subcontratação.\n\n25 - COMPRA PÚBLICA ESTRATÉGICA\nCompra Pública Estratégica: Inexistência de contratação pública estratégica\n\n26 - INFORMAÇÕES ADICIONAIS\nContrato adequado para PME: Sim\nCobertura ACP (Acordo dos Contratos Públicos da Organização Mundial do Comércio): Não\n\n27 - IDENTIFICAÇÃO E CONTACTOS DO ÓRGÃO DE RECURSOS ADMINISTRATIVOS\nDesignação: Comissão Executiva ATL\nEndereço: Rua do Arsenal n.º 23\nCódigo postal: 1100-038\nLocalidade: Lisboa\nTelefone: +351 210312700\nFax: +351 210312899\nEndereço eletrónico: atl@visitlisboa.com\n\n28 - IDENTIFICAÇÃO DO(S) AUTOR(ES) DE ANÚNCIO\nNome: David Mendes Coelho\nCargo: Assessoria Gabinete Jurídico\n419934688",
    "nipc": "501880160",
    "distrito": "Lisboa",
    "concelho": "Lisboa",
    "freguesia": "Todas",
    "site": "https://www.visitlisboa.com/pt-pt",
    "email": "atl@visitlisboa.com",
    "designacao_contrato": "CONCURSO PÚBLICO N.º 17.II_EMPREITADA_CP_01_2025",
    "descricao": "Empreitada de obra pública de requalificação do Parque Botânico do Monteiro-Mor do Museu Nacional do Traje",
    "preco_base": "1.250.000,00 EUR",
    "prazo_execucao": "6 MESES",
    "prazo_apresentacao_propostas": "19-01-2026 23:59",
    "fundos_eu": "Sim",
    "plataforma_eletronica": "VORTAL",
    "url_procedimento": "https://community.vortal.biz/public/",
    "autor_nome": "David Mendes Coelho",
    "autor_cargo": "Assessoria Gabinete Jurídico"
  },
  {
    "numero_procedimento": "N/A",
    "entidade": "Parques de Sintra - Monte da Lua, SA",
    "link": "https://diariodarepublica.pt/dr/detalhe/contrato-publico/33497-992908343",
    "detalhes_completos": "1 - IDENTIFICAÇÃO E CONTACTOS DA ENTIDADE ADJUDICANTE\nDesignação da entidade adjudicante: Parques de Sintra - Monte da Lua, SA\nNIPC: 505174839\nEndereço: ESTRADA MONSERRATE, PARQUE DE MONSERRATE\nCódigo postal: 2710-405\nLocalidade: Sintra\nPaís: Portugal\nNUT III: PT170\nDistrito: Lisboa\nConcelho: Sintra\nFreguesia: Todas\nTelefone: 219237300\nFax: 219237350\nEndereço da Entidade (URL): www.parquesdesintra.pt/pt/\nEndereço Eletrónico: viviane.crouzier@parquesdesintra.pt\neDelivery Gateway (URL): https://community.vortal.biz/public/\nFunção da Organização: Adquirente\nNorma jurídica da Entidade Adjudicante: Autoridade da administração central\nÁrea de atividade da Autoridade Adjudicante: Serviços públicos das administrações públicas\n\n2 - JORNAL OFICIAL DA UNIÃO EUROPEIA\nO procedimento a que este anúncio diz respeito também é publicitado no Jornal Oficial da União Europeia? Não\n\n3 - AVISO\nModelo de Anúncio: Concurso público\nData de Envio do Anúncio: 29-12-2025\n\n5 - PROCESSO\nTipo de Procedimento: Concurso público\nPreço base do procedimento: Sim\nValor do preço base do procedimento: 200.000,00 EUR\nProcedimento com lotes? Não\n\n6 - OBJETO DO CONTRATO\nNúmero de referência interna: 01912.2025\nDesignação do contrato: Manutenção de espaços verdes na Matinha de Queluz\nDescrição: Manutenção de espaços verdes na Matinha de Queluz\nTipo de Contrato Principal: Aquisição de Serviços\nTipo de Contrato: Aquisição de Serviços\nClassificação CPV (Vocabulário Comum para os Contratos Públicos)\nObjeto principal\nVocabulário Principal: 77313000\nPreço base s/IVA: 200.000,00 EUR\n\n7 - INDICAÇÕES ADICIONAIS\nO contrato envolve aquisição conjunta (satisfação de várias entidades)? Não\nO contrato é adjudicado por uma central de compras? Não\n\n8 - TÉCNICAS\nO concurso destina-se à celebração de um acordo-quadro? Inexistência de acordo-quadro\nÉ utilizado um leilão eletrónico? Não\nÉ adotada uma fase de negociação? Não\nSistema de Aquisição Dinâmico: Inexistência de sistema de aquisição dinâmico\n\n9 - LOCAL DA EXECUÇÃO DO CONTRATO\nLOCAL DA EXECUÇÃO DO CONTRATO (PROCEDIMENTO)\nPaís: Portugal\nNUT III: PT170\nLocalidade: Lisboa\nDistrito: Lisboa\nConcelho: Sintra\nFreguesia: Todas\n\n10 - PRAZO DE EXECUÇÃO DO CONTRATO\nPrazo de execução do contrato: 12 MESES\nPrevisão de renovações: Não\n\n11 - FUNDOS EU\nTêm fundos EU? Não\n\n12 - DOCUMENTOS DE HABILITAÇÃO\nHabilitação para o exercício da atividade profissional: Não\n\n13 - CONDIÇÕES DE APRESENTAÇÃO\nPlataforma eletrónica utilizada pela entidade adjudicante: VORTAL\nURL para Apresentação: https://community.vortal.biz/public/\nAdmissibilidade da apresentação de propostas variantes: Não autorizado\nPrazo para apresentação das propostas: 13-01-2026 23:59\nPrazo durante o qual os concorrentes são obrigados a manter as respetivas propostas: 90 dias a contar do termo do prazo para a apresentação das propostas\nIndicação de Subcontratação na Proposta: Inexistência de indicação de subcontratação\n\n14 - PRESTAÇÃO DE CAUÇÃO\nPrestação de caução: Não\n\n15 - FORNECIMENTO DAS PEÇAS DO CONCURSO, APRESENTAÇÃO DE PEDIDOS DE PARTICIPAÇÃO E APRESENTAÇÃO DAS PROPOSTAS\nLink para acesso às peças do concurso (URL): https://community.vortal.biz/Public/public-tender-documents/OFp6aEcxbTRyY1BMVGdHMVZjbThhVFZqTUNoa2NQQnFyTUhUeFE3VExZK1FLa2U0cEVSMjhOZnkvZmFER3lzL3JIR2xQb05GRkE3TUhGb1NRczBJVXc9PWcxbGht\n\n20 - OUTROS REQUISITOS\nInformação sobre contratos reservados. Aplica-se a contratos reservados (54º-A)? Não\n\n21 - CRITÉRIO DE ADJUDICAÇÃO\nMultifator: Não\nMonofator:\nNome: Outros\nOutro nome: Preço\n\n24 - CONDIÇÕES DO CONTRATO\nFaturação Eletrónica: Permitido\nObrigação de Subcontratação:\nCódigo da Obrigação de Subcontratação: Não é aplicável nenhuma obrigação de subcontratação.\n\n25 - COMPRA PÚBLICA ESTRATÉGICA\nCompra Pública Estratégica: Inexistência de contratação pública estratégica\n\n26 - INFORMAÇÕES ADICIONAIS\nContrato adequado para PME: Sim\nCobertura ACP (Acordo dos Contratos Públicos da Organização Mundial do Comércio): Não\n\n27 - IDENTIFICAÇÃO E CONTACTOS DO ÓRGÃO DE RECURSOS ADMINISTRATIVOS\nDesignação: Conselho de Administração\nEndereço: Estrada de Monserrate\nCódigo postal: 2710-405\nLocalidade: Sintra\nTelefone: +351 219237300\nFax: +351 219237300\nEndereço eletrónico: info@parquesdesintra.pt\n\n28 - IDENTIFICAÇÃO DO(S) AUTOR(ES) DE ANÚNCIO\nNome: Viviane Crouzier \nCargo: Departamento Jurídico\n419935635",
    "nipc": "505174839",
    "distrito": "Lisboa",
    "concelho": "Sintra",
    "freguesia": "Todas",
    "site": "www.parquesdesintra.pt/pt/",
    "email": "viviane.crouzier@parquesdesintra.pt",
    "designacao_contrato": "Manutenção de espaços verdes na Matinha de Queluz",
    "descricao": "Manutenção de espaços verdes na Matinha de Queluz",
    "preco_base": "200.000,00 EUR",
    "prazo_execucao": "12 MESES",
    "prazo_apresentacao_propostas": "13-01-2026 23:59",
    "fundos_eu": "Não",
    "plataforma_eletronica": "VORTAL",
    "url_procedimento": "https://community.vortal.biz/public/",
    "autor_nome": "Viviane Crouzier",
    "autor_cargo": "Departamento Jurídico"
  },
  {
    "numero_procedimento": "N/A",
    "entidade": "Parques de Sintra - Monte da Lua, SA",
    "link": "https://diariodarepublica.pt/dr/detalhe/contrato-publico/33498-992908344",
    "detalhes_completos": "1 - IDENTIFICAÇÃO E CONTACTOS DA ENTIDADE ADJUDICANTE\nDesignação da entidade adjudicante: Parques de Sintra - Monte da Lua, SA\nNIPC: 505174839\nEndereço: ESTRADA MONSERRATE, PARQUE DE MONSERRATE\nCódigo postal: 2710-405\nLocalidade: Sintra\nPaís: Portugal\nNUT III: PT170\nDistrito: Lisboa\nConcelho: Sintra\nFreguesia: Todas\nTelefone: 219237300\nFax: 219237350\nEndereço da Entidade (URL): www.parquesdesintra.pt/pt/\nEndereço Eletrónico: viviane.crouzier@parquesdesintra.pt\neDelivery Gateway (URL): https://community.vortal.biz/public/\nFunção da Organização: Adquirente\nNorma jurídica da Entidade Adjudicante: Autoridade da administração central\nÁrea de atividade da Autoridade Adjudicante: Serviços públicos das administrações públicas\n\n2 - JORNAL OFICIAL DA UNIÃO EUROPEIA\nO procedimento a que este anúncio diz respeito também é publicitado no Jornal Oficial da União Europeia? Não\n\n3 - AVISO\nModelo de Anúncio: Concurso público\nData de Envio do Anúncio: 29-12-2025\n\n5 - PROCESSO\nTipo de Procedimento: Concurso público\nPreço base do procedimento: Sim\nValor do preço base do procedimento: 25.000,00 EUR\nProcedimento com lotes? Não\n\n6 - OBJETO DO CONTRATO\nNúmero de referência interna: 01898.2025\nDesignação do contrato: Poda de sebes de buxo nos jardins do palácio nacional de Queluz\nDescrição: Poda de sebes de buxo nos jardins do palácio nacional de Queluz\nTipo de Contrato Principal: Aquisição de Serviços\nTipo de Contrato: Aquisição de Serviços\nClassificação CPV (Vocabulário Comum para os Contratos Públicos)\nObjeto principal\nVocabulário Principal: 77340000\nPreço base s/IVA: 25.000,00 EUR\n\n7 - INDICAÇÕES ADICIONAIS\nO contrato envolve aquisição conjunta (satisfação de várias entidades)? Não\nO contrato é adjudicado por uma central de compras? Não\n\n8 - TÉCNICAS\nO concurso destina-se à celebração de um acordo-quadro? Inexistência de acordo-quadro\nÉ utilizado um leilão eletrónico? Não\nÉ adotada uma fase de negociação? Não\nSistema de Aquisição Dinâmico: Inexistência de sistema de aquisição dinâmico\n\n9 - LOCAL DA EXECUÇÃO DO CONTRATO\nLOCAL DA EXECUÇÃO DO CONTRATO (PROCEDIMENTO)\nPaís: Portugal\nNUT III: PT170\nLocalidade: Lisboa\nDistrito: Lisboa\nConcelho: Sintra\nFreguesia: Todas\n\n10 - PRAZO DE EXECUÇÃO DO CONTRATO\nPrazo de execução do contrato: 4 MESES\nPrevisão de renovações: Não\n\n11 - FUNDOS EU\nTêm fundos EU? Não\n\n12 - DOCUMENTOS DE HABILITAÇÃO\nHabilitação para o exercício da atividade profissional: Não\n\n13 - CONDIÇÕES DE APRESENTAÇÃO\nPlataforma eletrónica utilizada pela entidade adjudicante: VORTAL\nURL para Apresentação: https://community.vortal.biz/public/\nAdmissibilidade da apresentação de propostas variantes: Não autorizado\nPrazo para apresentação das propostas: 13-01-2026 23:59\nPrazo durante o qual os concorrentes são obrigados a manter as respetivas propostas: 90 dias a contar do termo do prazo para a apresentação das propostas\nIndicação de Subcontratação na Proposta: Inexistência de indicação de subcontratação\n\n14 - PRESTAÇÃO DE CAUÇÃO\nPrestação de caução: Não\n\n15 - FORNECIMENTO DAS PEÇAS DO CONCURSO, APRESENTAÇÃO DE PEDIDOS DE PARTICIPAÇÃO E APRESENTAÇÃO DAS PROPOSTAS\nLink para acesso às peças do concurso (URL): https://community.vortal.biz/Public/public-tender-documents/MXlCeGt0a1ZQNjNUV2RTd3hLSjFUZitmeVNUYnFPNkdpelE0Rmx1N1F3OEV4NzRpSVAyMm1Fbnkrc3pvUXZPc21ZbnRhbXNZRDVEWm1RcGUvay9yMFE9PWZjKF5y\n\n20 - OUTROS REQUISITOS\nInformação sobre contratos reservados. Aplica-se a contratos reservados (54º-A)? Não\n\n21 - CRITÉRIO DE ADJUDICAÇÃO\nMultifator: Não\nMonofator:\nNome: Outros\nOutro nome: Preço\n\n24 - CONDIÇÕES DO CONTRATO\nFaturação Eletrónica: Permitido\nObrigação de Subcontratação:\nCódigo da Obrigação de Subcontratação: Não é aplicável nenhuma obrigação de subcontratação.\n\n25 - COMPRA PÚBLICA ESTRATÉGICA\nCompra Pública Estratégica: Inexistência de contratação pública estratégica\n\n26 - INFORMAÇÕES ADICIONAIS\nContrato adequado para PME: Sim\nCobertura ACP (Acordo dos Contratos Públicos da Organização Mundial do Comércio): Não\n\n27 - IDENTIFICAÇÃO E CONTACTOS DO ÓRGÃO DE RECURSOS ADMINISTRATIVOS\nDesignação: Conselho de Administração\nEndereço: Estrada de Monserrate\nCódigo postal: 2710-405\nLocalidade: Sintra\nTelefone: +351 219237300\nFax: +351 219237300\nEndereço eletrónico: info@parquesdesintra.pt\n\n28 - IDENTIFICAÇÃO DO(S) AUTOR(ES) DE ANÚNCIO\nNome: Viviane Crouzier\nCargo: Departamento Jurídico\n419935124",
    "nipc": "505174839",
    "distrito": "Lisboa",
    "concelho": "Sintra",
    "freguesia": "Todas",
    "site": "www.parquesdesintra.pt/pt/",
    "email": "viviane.crouzier@parquesdesintra.pt",
    "designacao_contrato": "Poda de sebes de buxo nos jardins do palácio nacional de Queluz",
    "descricao": "Poda de sebes de buxo nos jardins do palácio nacional de Queluz",
    "preco_base": "25.000,00 EUR",
    "prazo_execucao": "4 MESES",
    "prazo_apresentacao_propostas": "13-01-2026 23:59",
    "fundos_eu": "Não",
    "plataforma_eletronica": "VORTAL",
    "url_procedimento": "https://community.vortal.biz/public/",
    "autor_nome": "Viviane Crouzier",
    "autor_cargo": "Departamento Jurídico"
  },
  {
    "numero_procedimento": "N/A",
    "entidade": "Instituto Português de Oncologia de Lisboa Francisco Gentil, EPE",
    "link": "https://diariodarepublica.pt/dr/detalhe/contrato-publico/33472-992908345",
    "detalhes_completos": "1 - IDENTIFICAÇÃO E CONTACTOS DA ENTIDADE ADJUDICANTE\nDesignação da entidade adjudicante: Instituto Português de Oncologia de Lisboa Francisco Gentil, EPE\nNIPC: 506361616\nEndereço: Rua Profº Lima Basto\nCódigo postal: 1099-023\nLocalidade: Lisboa\nPaís: Portugal\nNUT III: PT170\nDistrito: Lisboa\nConcelho: Lisboa\nFreguesia: Todas\nTelefone: 217229800\nFax: 217229880\nEndereço da Entidade (URL): www.ipolisboa.min-saude.pt/\nEndereço Eletrónico: ipofg@ipolisboa.min-saude.pt\neDelivery Gateway (URL): https://community.vortal.biz/public/\nFunção da Organização: Adquirente\nNorma jurídica da Entidade Adjudicante: Organismo de direito público\nÁrea de atividade da Autoridade Adjudicante: Saúde\n\n2 - JORNAL OFICIAL DA UNIÃO EUROPEIA\nO procedimento a que este anúncio diz respeito também é publicitado no Jornal Oficial da União Europeia? Não\n\n3 - AVISO\nModelo de Anúncio: Concurso público urgente\nData de Envio do Anúncio: 29-12-2025 13:13:00\n\n5 - PROCESSO\nTipo de Procedimento: Concurso público\nPreço base do procedimento: Sim\nValor do preço base do procedimento: 42.980,10 EUR\nProcedimento com lotes? Não\n\n6 - OBJETO DO CONTRATO\nNúmero de referência interna: PU/300/2026\nDesignação do contrato: Serviços Postais\nDescrição: Serviços Postais\nTipo de Contrato Principal: Aquisição de Serviços\nTipo de Contrato: Aquisição de Serviços\nClassificação CPV (Vocabulário Comum para os Contratos Públicos)\nObjeto principal\nVocabulário Principal: 64110000\nPreço base s/IVA: 42.980,10 EUR\n\n7 - INDICAÇÕES ADICIONAIS\nO contrato envolve aquisição conjunta (satisfação de várias entidades)? Não\nO contrato é adjudicado por uma central de compras? Não\n\n8 - TÉCNICAS\nO concurso destina-se à celebração de um acordo-quadro? Inexistência de acordo-quadro\nÉ utilizado um leilão eletrónico? Não\nÉ adotada uma fase de negociação? Não\nSistema de Aquisição Dinâmico: Inexistência de sistema de aquisição dinâmico\n\n9 - LOCAL DA EXECUÇÃO DO CONTRATO\nLOCAL DA EXECUÇÃO DO CONTRATO (PROCEDIMENTO)\nPaís: Portugal\nNUT III: PT170\nLocalidade: Lisboa\nDistrito: Lisboa\nConcelho: Lisboa\nFreguesia: Freguesia de São Domingos de Benfica\n\n10 - PRAZO DE EXECUÇÃO DO CONTRATO\nPrazo de execução do contrato: 12 MESES\nPrevisão de renovações: Não\n\n11 - FUNDOS EU\nTêm fundos EU? Não\n\n12 - DOCUMENTOS DE HABILITAÇÃO\nHabilitação para o exercício da atividade profissional: Não\n\n13 - CONDIÇÕES DE APRESENTAÇÃO\nPlataforma eletrónica utilizada pela entidade adjudicante: VORTAL\nURL para Apresentação: https://community.vortal.biz/public/\nAdmissibilidade da apresentação de propostas variantes: Não autorizado\nPrazo para apresentação das propostas: 30-12-2025 13:00\nPrazo durante o qual os concorrentes são obrigados a manter as respetivas propostas: 10 dias a contar do termo do prazo para a apresentação das propostas\nIndicação de Subcontratação na Proposta: Inexistência de indicação de subcontratação\n\n14 - PRESTAÇÃO DE CAUÇÃO\nPrestação de caução: Não\n\n15 - FORNECIMENTO DAS PEÇAS DO CONCURSO, APRESENTAÇÃO DE PEDIDOS DE PARTICIPAÇÃO E APRESENTAÇÃO DAS PROPOSTAS\nLink para acesso às peças do concurso (URL): https://community.vortal.biz/Public/public-tender-documents/UDhaUjJaK2lUMlZBRkJqTGE5dlpYNUtoZnpYS3E4VEpZU3Q2VmZDNENkUUpqQ2RpZUp5a1lWRzlZSnhjMy93UTl1V0g2WEtFSzB2RnYyenBiLzRmYlE9PUBGQGEj\n\n20 - OUTROS REQUISITOS\nInformação sobre contratos reservados. Aplica-se a contratos reservados (54º-A)? Não\n\n21 - CRITÉRIO DE ADJUDICAÇÃO\nMultifator: Não\nMonofator:\nNome: Preço\n\n24 - CONDIÇÕES DO CONTRATO\nFaturação Eletrónica: Permitido\nObrigação de Subcontratação:\nCódigo da Obrigação de Subcontratação: Não é aplicável nenhuma obrigação de subcontratação.\n\n25 - COMPRA PÚBLICA ESTRATÉGICA\nCompra Pública Estratégica: Inexistência de contratação pública estratégica\n\n26 - INFORMAÇÕES ADICIONAIS\nContrato adequado para PME: Sim\nCobertura ACP (Acordo dos Contratos Públicos da Organização Mundial do Comércio): Não\n\n27 - IDENTIFICAÇÃO E CONTACTOS DO ÓRGÃO DE RECURSOS ADMINISTRATIVOS\nDesignação: Conselho de Administração\nEndereço: Rua Prof. Lima Basto\nCódigo postal: 1099-023\nLocalidade: Lisboa\nTelefone: +351 217229800\nFax: +351 217229833\nEndereço eletrónico: ipofg@ipolisboa.min-saude.pt\n\n28 - IDENTIFICAÇÃO DO(S) AUTOR(ES) DE ANÚNCIO\nNome: Bela Paulo\nCargo: Técnica Superior\n419935481",
    "nipc": "506361616",
    "distrito": "Lisboa",
    "concelho": "Lisboa",
    "freguesia": "Todas",
    "site": "www.ipolisboa.min-saude.pt/",
    "email": "ipofg@ipolisboa.min-saude.pt",
    "designacao_contrato": "Serviços Postais",
    "descricao": "Serviços Postais",
    "preco_base": "42.980,10 EUR",
    "prazo_execucao": "12 MESES",
    "prazo_apresentacao_propostas": "30-12-2025 13:00",
    "fundos_eu": "Não",
    "plataforma_eletronica": "VORTAL",
    "url_procedimento": "https://community.vortal.biz/public/",
    "autor_nome": "Bela Paulo",
    "autor_cargo": "Técnica Superior"
  },
  {
    "numero_procedimento": "N/A",
    "entidade": "Unidade Local de Saúde do Alentejo Central, EPE",
    "link": "https://diariodarepublica.pt/dr/detalhe/contrato-publico/33502-992908346",
    "detalhes_completos": "1 - IDENTIFICAÇÃO E CONTACTOS DA ENTIDADE ADJUDICANTE\nDesignação da entidade adjudicante: Unidade Local de Saúde do Alentejo Central, EPE\nNIPC: 508085888\nEndereço: Largo Sr. da Pobreza\nCódigo postal: 7000-811\nLocalidade: Évora\nPaís: Portugal\nNUT III: PT187\nDistrito: Évora\nConcelho: Évora\nFreguesia: Todas\nTelefone: 266740111\nFax: 266744212\nEndereço da Entidade (URL): www.hevora.min-saude.pt\nEndereço Eletrónico: concursos.aprov@ulsac.min-saude.pt\neDelivery Gateway (URL): https://community.vortal.biz/public/\nFunção da Organização: Adquirente\nNorma jurídica da Entidade Adjudicante: Organismo de direito público\nÁrea de atividade da Autoridade Adjudicante: Saúde\n\n2 - JORNAL OFICIAL DA UNIÃO EUROPEIA\nO procedimento a que este anúncio diz respeito também é publicitado no Jornal Oficial da União Europeia? Não\n\n3 - AVISO\nModelo de Anúncio: Concurso público\nData de Envio do Anúncio: 29-12-2025\n\n5 - PROCESSO\nTipo de Procedimento: Concurso público\nPreço base do procedimento: Sim\nValor do preço base do procedimento: 84.000,00 EUR\nProcedimento com lotes? Não\n\n6 - OBJETO DO CONTRATO\nNúmero de referência interna: 190153/25\nDesignação do contrato: Prestação de Serviços de Enfermagem para Centro de Patologia da Aorta\nDescrição: Prestação de Serviços de Enfermagem para Centro de Patol\nTipo de Contrato Principal: Aquisição de Serviços\nTipo de Contrato: Aquisição de Serviços\nClassificação CPV (Vocabulário Comum para os Contratos Públicos)\nObjeto principal\nVocabulário Principal: 85121300\nPreço base s/IVA: 84.000,00 EUR\n\n7 - INDICAÇÕES ADICIONAIS\nO contrato envolve aquisição conjunta (satisfação de várias entidades)? Não\nO contrato é adjudicado por uma central de compras? Não\n\n8 - TÉCNICAS\nO concurso destina-se à celebração de um acordo-quadro? Inexistência de acordo-quadro\nÉ utilizado um leilão eletrónico? Não\nÉ adotada uma fase de negociação? Não\nSistema de Aquisição Dinâmico: Inexistência de sistema de aquisição dinâmico\n\n9 - LOCAL DA EXECUÇÃO DO CONTRATO\nLOCAL DA EXECUÇÃO DO CONTRATO (PROCEDIMENTO)\nPaís: Portugal\nNUT III: PT187\nLocalidade: Évora\nDistrito: Évora\nConcelho: Évora\nFreguesia: União das Freguesias de Évora (São Mamede, Sé, São Pedro e Santo Antão)\n\n10 - PRAZO DE EXECUÇÃO DO CONTRATO\nPrazo de execução do contrato: 426 DIAS\nPrevisão de renovações: Não\n\n11 - FUNDOS EU\nTêm fundos EU? Não\n\n12 - DOCUMENTOS DE HABILITAÇÃO\nHabilitação para o exercício da atividade profissional: Não\n\n13 - CONDIÇÕES DE APRESENTAÇÃO\nPlataforma eletrónica utilizada pela entidade adjudicante: VORTAL\nURL para Apresentação: https://community.vortal.biz/public/\nAdmissibilidade da apresentação de propostas variantes: Não autorizado\nPrazo para apresentação das propostas: 12-01-2026 18:00\nPrazo durante o qual os concorrentes são obrigados a manter as respetivas propostas: 120 dias a contar do termo do prazo para a apresentação das propostas\nIndicação de Subcontratação na Proposta: Inexistência de indicação de subcontratação\n\n14 - PRESTAÇÃO DE CAUÇÃO\nPrestação de caução: Não\n\n15 - FORNECIMENTO DAS PEÇAS DO CONCURSO, APRESENTAÇÃO DE PEDIDOS DE PARTICIPAÇÃO E APRESENTAÇÃO DAS PROPOSTAS\nLink para acesso às peças do concurso (URL): https://community.vortal.biz/Public/public-tender-documents/TkZhOTMyTmVMRCtneDNyV0RzMmZzUStZQ0VpR3gyMUdTZEIwazVHNFEzaTBhendteDNadzI4SmxBM2JjK2xYUUp3T0x6TkxYTitRL01TMkNVRnJOOXc9PXpicnkm\n\n20 - OUTROS REQUISITOS\nInformação sobre contratos reservados. Aplica-se a contratos reservados (54º-A)? Não\n\n21 - CRITÉRIO DE ADJUDICAÇÃO\nMultifator: Não\nMonofator:\nNome: Preço\n\n24 - CONDIÇÕES DO CONTRATO\nFaturação Eletrónica: Permitido\nObrigação de Subcontratação:\nCódigo da Obrigação de Subcontratação: Não é aplicável nenhuma obrigação de subcontratação.\n\n25 - COMPRA PÚBLICA ESTRATÉGICA\nCompra Pública Estratégica: Inexistência de contratação pública estratégica\n\n26 - INFORMAÇÕES ADICIONAIS\nContrato adequado para PME: Sim\nCobertura ACP (Acordo dos Contratos Públicos da Organização Mundial do Comércio): Não\n\n27 - IDENTIFICAÇÃO E CONTACTOS DO ÓRGÃO DE RECURSOS ADMINISTRATIVOS\nDesignação: Conselho de Administração\nEndereço: Largo Sr. de Pobreza\nCódigo postal: 7000-811\nLocalidade: Évora\nTelefone: +351 266740100\nFax: +351 266740100\nEndereço eletrónico: concursos.aprov@ulsac.min-saude.pt\n\n28 - IDENTIFICAÇÃO DO(S) AUTOR(ES) DE ANÚNCIO\nNome: Carlos Antonio Mateus Gomes\nCargo: Presidente do Conselho de Administração\n419933334",
    "nipc": "508085888",
    "distrito": "Évora",
    "concelho": "Évora",
    "freguesia": "Todas",
    "site": "www.hevora.min-saude.pt",
    "email": "concursos.aprov@ulsac.min-saude.pt",
    "designacao_contrato": "Prestação de Serviços de Enfermagem para Centro de Patologia da Aorta",
    "descricao": "Prestação de Serviços de Enfermagem para Centro de Patol",
    "preco_base": "84.000,00 EUR",
    "prazo_execucao": "426 DIAS",
    "prazo_apresentacao_propostas": "12-01-2026 18:00",
    "fundos_eu": "Não",
    "plataforma_eletronica": "VORTAL",
    "url_procedimento": "https://community.vortal.biz/public/",
    "autor_nome": "Carlos Antonio Mateus Gomes",
    "autor_cargo": "Presidente do Conselho de Administração"
  },
  {
    "numero_procedimento": "N/A",
    "entidade": "ViniPortugal - Associação Interprofissional do Vinho",
    "link": "https://diariodarepublica.pt/dr/detalhe/contrato-publico/33503-992908347",
    "detalhes_completos": "1 - IDENTIFICAÇÃO E CONTACTOS DA ENTIDADE ADJUDICANTE\nDesignação da entidade adjudicante: ViniPortugal - Associação Interprofissional do Vinho\nNIPC: 503736864\nEndereço: Rua Mouzinho da Silveira, 5 \nCódigo postal: 2560-312\nLocalidade: Lisboa\nPaís: Portugal\nNUT III: PT16B\nDistrito: Lisboa\nConcelho: Torres Vedras\nFreguesia: Todas\nTelefone: 213569890\nFax: 213569895\nEndereço da Entidade (URL): https://viniportugal.pt/pt/\nEndereço Eletrónico: geral@viniportugal.pt\neDelivery Gateway (URL): https://community.vortal.biz/public/\nFunção da Organização: Adquirente\nNorma jurídica da Entidade Adjudicante: Organismo de direito público\nÁrea de atividade da Autoridade Adjudicante: Educação\n\n2 - JORNAL OFICIAL DA UNIÃO EUROPEIA\nO procedimento a que este anúncio diz respeito também é publicitado no Jornal Oficial da União Europeia? Não\n\n3 - AVISO\nModelo de Anúncio: Concurso público\nData de Envio do Anúncio: 29-12-2025\n\n5 - PROCESSO\nTipo de Procedimento: Concurso público\nPreço base do procedimento: Sim\nValor do preço base do procedimento: 190.000,00 EUR\nProcedimento com lotes? Não\n\n6 - OBJETO DO CONTRATO\nNúmero de referência interna: 2025.52\nDesignação do contrato: Prestação de serviços de Embaixador EUA da marca Wines of Portugal, no período de 2026-2027 (24 meses após assinatura de contrato)\nDescrição: Prestação de serviços de Embaixador EUA da marca Wines of Portugal, no período de 2026-2027 (24 meses após assinatura de contrato)\nTipo de Contrato Principal: Aquisição de Serviços\nTipo de Contrato: Aquisição de Serviços\nClassificação CPV (Vocabulário Comum para os Contratos Públicos)\nObjeto principal\nVocabulário Principal: 79342200\nPreço base s/IVA: 190.000,00 EUR\n\n7 - INDICAÇÕES ADICIONAIS\nO contrato envolve aquisição conjunta (satisfação de várias entidades)? Não\nO contrato é adjudicado por uma central de compras? Não\n\n8 - TÉCNICAS\nO concurso destina-se à celebração de um acordo-quadro? Inexistência de acordo-quadro\nÉ utilizado um leilão eletrónico? Não\nÉ adotada uma fase de negociação? Não\nSistema de Aquisição Dinâmico: Inexistência de sistema de aquisição dinâmico\n\n9 - LOCAL DA EXECUÇÃO DO CONTRATO\nLOCAL DA EXECUÇÃO DO CONTRATO (PROCEDIMENTO)\nPaís: Portugal\nNUT III: PT170\nLocalidade: Lisboa\nDistrito: Lisboa\nConcelho: Lisboa\nFreguesia: Todas\n\n10 - PRAZO DE EXECUÇÃO DO CONTRATO\nPrazo de execução do contrato: 24 MESES\nPrevisão de renovações: Não\n\n11 - FUNDOS EU\nTêm fundos EU? Não\n\n12 - DOCUMENTOS DE HABILITAÇÃO\nHabilitação para o exercício da atividade profissional: Não\n\n13 - CONDIÇÕES DE APRESENTAÇÃO\nPlataforma eletrónica utilizada pela entidade adjudicante: VORTAL\nURL para Apresentação: https://community.vortal.biz/public/\nAdmissibilidade da apresentação de propostas variantes: Não autorizado\nPrazo para apresentação das propostas: 05-01-2026 17:00\nPrazo durante o qual os concorrentes são obrigados a manter as respetivas propostas: 180 dias a contar do termo do prazo para a apresentação das propostas\nIndicação de Subcontratação na Proposta: Inexistência de indicação de subcontratação\n\n14 - PRESTAÇÃO DE CAUÇÃO\nPrestação de caução: Não\n\n15 - FORNECIMENTO DAS PEÇAS DO CONCURSO, APRESENTAÇÃO DE PEDIDOS DE PARTICIPAÇÃO E APRESENTAÇÃO DAS PROPOSTAS\nLink para acesso às peças do concurso (URL): https://community.vortal.biz/Public/public-tender-documents/WFUybTNtaGl5WWVnNEpFQ2lIRm54ZE1nQUc4dXAvU2FlVlpMdUFmNzRmZWtrTUxGWXQrYXhOTCt6bCtyZ0gxT0ZtcDBoek5VYmJpbTJ6V1p4MjBvbVE9PTAqSnYz\n\n20 - OUTROS REQUISITOS\nInformação sobre contratos reservados. Aplica-se a contratos reservados (54º-A)? Não\n\n21 - CRITÉRIO DE ADJUDICAÇÃO\nMultifator: Sim\nFator: \nNome: Preço\nPonderação: 30%\nSubfatores: Não\nFator: \nNome: Qualidade\nPonderação: 70%\nSubfatores: Não\n\n24 - CONDIÇÕES DO CONTRATO\nFaturação Eletrónica: Permitido\nObrigação de Subcontratação:\nCódigo da Obrigação de Subcontratação: Não é aplicável nenhuma obrigação de subcontratação.\n\n25 - COMPRA PÚBLICA ESTRATÉGICA\nCompra Pública Estratégica: Inexistência de contratação pública estratégica\n\n26 - INFORMAÇÕES ADICIONAIS\nContrato adequado para PME: Sim\nCobertura ACP (Acordo dos Contratos Públicos da Organização Mundial do Comércio): Não\n\n27 - IDENTIFICAÇÃO E CONTACTOS DO ÓRGÃO DE RECURSOS ADMINISTRATIVOS\nDesignação: Pedro Fernandes\nEndereço: Rua Mouzinho da Silveira, n.º5\nCódigo postal: 1250-165\nLocalidade: Lisboa\nTelefone: +351 213569890\nFax: +351 213569890\nEndereço eletrónico: processo-concursal@viniportugal.pt\n\n28 - IDENTIFICAÇÃO DO(S) AUTOR(ES) DE ANÚNCIO\nNome: Pedro Fernandes\nCargo: Director Financeiro\n419936007",
    "nipc": "503736864",
    "distrito": "Lisboa",
    "concelho": "Torres Vedras",
    "freguesia": "Todas",
    "site": "https://viniportugal.pt/pt/",
    "email": "geral@viniportugal.pt",
    "designacao_contrato": "Prestação de serviços de Embaixador EUA da marca Wines of Portugal, no período de 2026-2027 (24 meses após assinatura de contrato)",
    "descricao": "Prestação de serviços de Embaixador EUA da marca Wines of Portugal, no período de 2026-2027 (24 meses após assinatura de contrato)",
    "preco_base": "190.000,00 EUR",
    "prazo_execucao": "24 MESES",
    "prazo_apresentacao_propostas": "05-01-2026 17:00",
    "fundos_eu": "Não",
    "plataforma_eletronica": "VORTAL",
    "url_procedimento": "https://community.vortal.biz/public/",
    "autor_nome": "Pedro Fernandes",
    "autor_cargo": "Director Financeiro"
  },
  {
    "numero_procedimento": "N/A",
    "entidade": "Unidade Local de Saúde de Santa Maria, EPE",
    "link": "https://diariodarepublica.pt/dr/detalhe/contrato-publico/33504-992908348",
    "detalhes_completos": "1 - IDENTIFICAÇÃO E CONTACTOS DA ENTIDADE ADJUDICANTE\nDesignação da entidade adjudicante: Unidade Local de Saúde de Santa Maria, EPE\nNIPC: 508481287\nEndereço: Avenida Prof. Egas Moniz\nCódigo postal: 1649-035\nLocalidade: Lisboa\nPaís: Portugal\nNUT III: PT170\nDistrito: Lisboa\nConcelho: Lisboa\nFreguesia: Freguesia de Alvalade - Lisboa\nTelefone: 217805330\nFax: 217805605\nEndereço da Entidade (URL): www.ulssm.min-saude.pt\nEndereço Eletrónico: compras@ulssm.min-saude.pt\neDelivery Gateway (URL): https://community.vortal.biz/public/\nFunção da Organização: Adquirente\nNorma jurídica da Entidade Adjudicante: Empresa pública\nÁrea de atividade da Autoridade Adjudicante: Saúde\n\n2 - JORNAL OFICIAL DA UNIÃO EUROPEIA\nO procedimento a que este anúncio diz respeito também é publicitado no Jornal Oficial da União Europeia? Não\n\n3 - AVISO\nModelo de Anúncio: Concurso público\nData de Envio do Anúncio: 29-12-2025\n\n5 - PROCESSO\nTipo de Procedimento: Concurso público\nPreço base do procedimento: Sim\nValor do preço base do procedimento: 58.616,26 EUR\nProcedimento com lotes? Sim\nNº Máx. de Lotes Autorizado: 21\nNúmero máximo de lotes que podem ser adjudicados a um concorrente: 21\n\n6 - OBJETO DO CONTRATO\nNúmero de referência interna: 262A000073.\nDesignação do contrato: 262A000073 - Aquisição de Dispositivos de drenagem para 2026\nDescrição: 262A000073 - Aquisição de Dispositivos de drenagem para 2026\nTipo de Contrato Principal: Aquisição de Bens Móveis\nTipo de Contrato: Aquisição de Bens Móveis\nClassificação CPV (Vocabulário Comum para os Contratos Públicos)\nObjeto principal\nVocabulário Principal: 33140000\nPreço base s/IVA: 58.616,26 EUR\nLotes: \nNº: LOT-0001\nDescrição do Lote: Lote 1\nPreço base s/IVA: 4.667,00 EUR\nClassificação CPV (Vocabulário Comum para os Contratos Públicos)\nObjeto principal\nVocabulário Principal: 33140000\nNº: LOT-0002\nDescrição do Lote: Lote 2\nPreço base s/IVA: 4.328,00 EUR\nClassificação CPV (Vocabulário Comum para os Contratos Públicos)\nObjeto principal\nVocabulário Principal: 33140000\nNº: LOT-0003\nDescrição do Lote: Lote 3\nPreço base s/IVA: 2.846,80 EUR\nClassificação CPV (Vocabulário Comum para os Contratos Públicos)\nObjeto principal\nVocabulário Principal: 33140000\nNº: LOT-0004\nDescrição do Lote: Lote 4\nPreço base s/IVA: 4.848,00 EUR\nClassificação CPV (Vocabulário Comum para os Contratos Públicos)\nObjeto principal\nVocabulário Principal: 33140000\nNº: LOT-0005\nDescrição do Lote: Lote 5\nPreço base s/IVA: 2.090,00 EUR\nClassificação CPV (Vocabulário Comum para os Contratos Públicos)\nObjeto principal\nVocabulário Principal: 33140000\nNº: LOT-0006\nDescrição do Lote: Lote 6\nPreço base s/IVA: 1.736,00 EUR\nClassificação CPV (Vocabulário Comum para os Contratos Públicos)\nObjeto principal\nVocabulário Principal: 33140000\nNº: LOT-0007\nDescrição do Lote: Lote 7\nPreço base s/IVA: 1.164,00 EUR\nClassificação CPV (Vocabulário Comum para os Contratos Públicos)\nObjeto principal\nVocabulário Principal: 33140000\nNº: LOT-0008\nDescrição do Lote: Lote 8\nPreço base s/IVA: 2.160,00 EUR\nClassificação CPV (Vocabulário Comum para os Contratos Públicos)\nObjeto principal\nVocabulário Principal: 33140000\nNº: LOT-0009\nDescrição do Lote: Lote 9\nPreço base s/IVA: 2.200,00 EUR\nClassificação CPV (Vocabulário Comum para os Contratos Públicos)\nObjeto principal\nVocabulário Principal: 33140000\nNº: LOT-0010\nDescrição do Lote: Lote 10\nPreço base s/IVA: 3.600,00 EUR\nClassificação CPV (Vocabulário Comum para os Contratos Públicos)\nObjeto principal\nVocabulário Principal: 33140000\nNº: LOT-0011\nDescrição do Lote: Lote 11\nPreço base s/IVA: 7.590,00 EUR\nClassificação CPV (Vocabulário Comum para os Contratos Públicos)\nObjeto principal\nVocabulário Principal: 33140000\nNº: LOT-0012\nDescrição do Lote: Lote 12\nPreço base s/IVA: 974,16 EUR\nClassificação CPV (Vocabulário Comum para os Contratos Públicos)\nObjeto principal\nVocabulário Principal: 33140000\nNº: LOT-0013\nDescrição do Lote: Lote 13\nPreço base s/IVA: 99,11 EUR\nClassificação CPV (Vocabulário Comum para os Contratos Públicos)\nObjeto principal\nVocabulário Principal: 33140000\nNº: LOT-0014\nDescrição do Lote: Lote 14\nPreço base s/IVA: 1.450,00 EUR\nClassificação CPV (Vocabulário Comum para os Contratos Públicos)\nObjeto principal\nVocabulário Principal: 33140000\nNº: LOT-0015\nDescrição do Lote: Lote 15\nPreço base s/IVA: 190,00 EUR\nClassificação CPV (Vocabulário Comum para os Contratos Públicos)\nObjeto principal\nVocabulário Principal: 33140000\nNº: LOT-0016\nDescrição do Lote: Lote 16\nPreço base s/IVA: 3.262,50 EUR\nClassificação CPV (Vocabulário Comum para os Contratos Públicos)\nObjeto principal\nVocabulário Principal: 33140000\nNº: LOT-0017\nDescrição do Lote: Lote 17\nPreço base s/IVA: 8.700,00 EUR\nClassificação CPV (Vocabulário Comum para os Contratos Públicos)\nObjeto principal\nVocabulário Principal: 33140000\nNº: LOT-0018\nDescrição do Lote: Lote 18\nPreço base s/IVA: 60,69 EUR\nClassificação CPV (Vocabulário Comum para os Contratos Públicos)\nObjeto principal\nVocabulário Principal: 33140000\nNº: LOT-0019\nDescrição do Lote: Lote 19\nPreço base s/IVA: 70,00 EUR\nClassificação CPV (Vocabulário Comum para os Contratos Públicos)\nObjeto principal\nVocabulário Principal: 33140000\nNº: LOT-0020\nDescrição do Lote: Lote 20\nPreço base s/IVA: 5.720,00 EUR\nClassificação CPV (Vocabulário Comum para os Contratos Públicos)\nObjeto principal\nVocabulário Principal: 33140000\nNº: LOT-0021\nDescrição do Lote: Lote 21\nPreço base s/IVA: 860,00 EUR\nClassificação CPV (Vocabulário Comum para os Contratos Públicos)\nObjeto principal\nVocabulário Principal: 33140000\n\n7 - INDICAÇÕES ADICIONAIS\nO contrato envolve aquisição conjunta (satisfação de várias entidades)? Não\nO contrato é adjudicado por uma central de compras? Não\n\n8 - TÉCNICAS\nO concurso destina-se à celebração de um acordo-quadro? Inexistência de acordo-quadro\nÉ utilizado um leilão eletrónico? Não\nÉ adotada uma fase de negociação? Não\nSistema de Aquisição Dinâmico: Inexistência de sistema de aquisição dinâmico\n\n9 - LOCAL DA EXECUÇÃO DO CONTRATO\nLOCAL DA EXECUÇÃO DO CONTRATO (PROCEDIMENTO)\nPaís: Portugal\nNUT III: PT170\nLocalidade: Lisboa\nDistrito: Lisboa\nConcelho: Lisboa\nFreguesia: Freguesia de Alvalade - Lisboa\nLOCAL DA EXECUÇÃO DO CONTRATO (LOTE)\nIdentificador do Lote: LOT-0001; LOT-0002; LOT-0003; LOT-0004; LOT-0005; LOT-0006; LOT-0007; LOT-0008; LOT-0009; LOT-0010; LOT-0011; LOT-0012; LOT-0013; LOT-0014; LOT-0015; LOT-0016; LOT-0017; LOT-0018; LOT-0019; LOT-0020; LOT-0021\nPaís: Portugal\nNUT III: PT170\nLocalidade: Lisboa\nDistrito: Lisboa\nConcelho: Lisboa\nFreguesia: Freguesia de Alvalade - Lisboa\n\n10 - PRAZO DE EXECUÇÃO DO CONTRATO\nIdentificador do Lote: LOT-0001; LOT-0002; LOT-0003; LOT-0004; LOT-0005; LOT-0006; LOT-0007; LOT-0008; LOT-0009; LOT-0010; LOT-0011; LOT-0012; LOT-0013; LOT-0014; LOT-0015; LOT-0016; LOT-0017; LOT-0018; LOT-0019; LOT-0020; LOT-0021\nPrazo de execução do contrato: 12 MESES\nPrevisão de renovações: Não\n\n11 - FUNDOS EU\nIdentificador do Lote: LOT-0001; LOT-0002; LOT-0003; LOT-0004; LOT-0005; LOT-0006; LOT-0007; LOT-0008; LOT-0009; LOT-0010; LOT-0011; LOT-0012; LOT-0013; LOT-0014; LOT-0015; LOT-0016; LOT-0017; LOT-0018; LOT-0019; LOT-0020; LOT-0021\nTêm fundos EU? Não\n\n12 - DOCUMENTOS DE HABILITAÇÃO\nHabilitação para o exercício da atividade profissional: Não\n\n13 - CONDIÇÕES DE APRESENTAÇÃO\nPlataforma eletrónica utilizada pela entidade adjudicante: VORTAL\nURL para Apresentação: https://community.vortal.biz/public/\nAdmissibilidade da apresentação de propostas variantes: Não autorizado\nPrazo para apresentação das propostas: 07-01-2026 17:00\nPrazo durante o qual os concorrentes são obrigados a manter as respetivas propostas: 180 dias a contar do termo do prazo para a apresentação das propostas\nIndicação de Subcontratação na Proposta: Inexistência de indicação de subcontratação\n\n14 - PRESTAÇÃO DE CAUÇÃO\nPrestação de caução: Não\n\n15 - FORNECIMENTO DAS PEÇAS DO CONCURSO, APRESENTAÇÃO DE PEDIDOS DE PARTICIPAÇÃO E APRESENTAÇÃO DAS PROPOSTAS\nLink para acesso às peças do concurso (URL): https://community.vortal.biz/Public/public-tender-documents/RVpSVG52OVprQ2lJRXNrbVYwZWliMU9iSkdmRjBIaHFrVk1WNFo2ZWI0VFBXUktlaWlKOUk0UDZ6NzRIU3J6NWZYNXZGcXE3RWtpNktKY1VqRUpyaWc9PWtrb15A\n\n20 - OUTROS REQUISITOS\nIdentificador do Lote: LOT-0001; LOT-0002; LOT-0003; LOT-0004; LOT-0005; LOT-0006; LOT-0007; LOT-0008; LOT-0009; LOT-0010; LOT-0011; LOT-0012; LOT-0013; LOT-0014; LOT-0015; LOT-0016; LOT-0017; LOT-0018; LOT-0019; LOT-0020; LOT-0021\nInformação sobre contratos reservados. Aplica-se a contratos reservados (54º-A)? Não\n\n21 - CRITÉRIO DE ADJUDICAÇÃO\nO Critério de adjudicação é diferenciado por lote? Não\nMultifator: Não\nMonofator:\nNome: Preço\n\n24 - CONDIÇÕES DO CONTRATO\nIdentificador do Lote: LOT-0001; LOT-0002; LOT-0003; LOT-0004; LOT-0005; LOT-0006; LOT-0007; LOT-0008; LOT-0009; LOT-0010; LOT-0011; LOT-0012; LOT-0013; LOT-0014; LOT-0015; LOT-0016; LOT-0017; LOT-0018; LOT-0019; LOT-0020; LOT-0021\nFaturação Eletrónica: Permitido\nObrigação de Subcontratação:\nCódigo da Obrigação de Subcontratação: Não é aplicável nenhuma obrigação de subcontratação.\n\n25 - COMPRA PÚBLICA ESTRATÉGICA\nCompra Pública Estratégica: Inexistência de contratação pública estratégica\n\n26 - INFORMAÇÕES ADICIONAIS\nIdentificador do Lote: LOT-0001; LOT-0002; LOT-0003; LOT-0004; LOT-0005; LOT-0006; LOT-0007; LOT-0008; LOT-0009; LOT-0010; LOT-0011; LOT-0012; LOT-0013; LOT-0014; LOT-0015; LOT-0016; LOT-0017; LOT-0018; LOT-0019; LOT-0020; LOT-0021\nContrato adequado para PME: Sim\nCobertura ACP (Acordo dos Contratos Públicos da Organização Mundial do Comércio): Não\n\n27 - IDENTIFICAÇÃO E CONTACTOS DO ÓRGÃO DE RECURSOS ADMINISTRATIVOS\nDesignação: Conselho de Administração\nEndereço: Av Professor Egas Moniz\nCódigo postal: 1649-035\nLocalidade: Lisboa\nTelefone: +351 217805330\nFax: +351 217805605\nEndereço eletrónico: secretariado.ca@ulssm.min-saude.pt\n\n28 - IDENTIFICAÇÃO DO(S) AUTOR(ES) DE ANÚNCIO\nNome: Mariana Figueira\nCargo: Assistente técnica\n419935002",
    "nipc": "508481287",
    "distrito": "Lisboa",
    "concelho": "Lisboa",
    "freguesia": "Freguesia de Alvalade - Lisboa",
    "site": "www.ulssm.min-saude.pt",
    "email": "compras@ulssm.min-saude.pt",
    "designacao_contrato": "262A000073 - Aquisição de Dispositivos de drenagem para 2026",
    "descricao": "262A000073 - Aquisição de Dispositivos de drenagem para 2026",
    "preco_base": "58.616,26 EUR",
    "prazo_execucao": "12 MESES",
    "prazo_apresentacao_propostas": "07-01-2026 17:00",
    "fundos_eu": "Não",
    "plataforma_eletronica": "VORTAL",
    "url_procedimento": "https://community.vortal.biz/public/",
    "autor_nome": "Mariana Figueira",
    "autor_cargo": "Assistente técnica"
  },
  {
    "numero_procedimento": "N/A",
    "entidade": "Município de Torre de Moncorvo",
    "link": "https://diariodarepublica.pt/dr/detalhe/contrato-publico/33510-992908349",
    "detalhes_completos": "1 - IDENTIFICAÇÃO E CONTACTOS DA ENTIDADE ADJUDICANTE\nDesignação da entidade adjudicante: Município de Torre de Moncorvo\nNIPC: 501121536\nServiço/Órgão/Pessoa de contacto: Presidente da Câmara Municipal de Torre de Moncorvo\nEndereço: Largo Dr. Campos Monteiro\nCódigo postal: 5160-303\nLocalidade: Torre de Moncorvo\nPaís: Portugal\nNUT III: PT11D\nDistrito: Braganca\nConcelho: Torre de Moncorvo\nFreguesia: Freguesia de Torre de Moncorvo\nTelefone: 279200220\nFax: 279200240\nEndereço da Entidade (URL): http://www.cm-moncorvo.pt/\nEndereço Eletrónico: gab.presidente@torredemoncorvo.pt\neDelivery Gateway (URL): https://www.acingov.pt\nFunção da Organização: Adquirente\nNorma jurídica da Entidade Adjudicante: Organismo de direito público\nÁrea de atividade da Autoridade Adjudicante: Serviços públicos das administrações públicas\n\n2 - JORNAL OFICIAL DA UNIÃO EUROPEIA\nO procedimento a que este anúncio diz respeito também é publicitado no Jornal Oficial da União Europeia? Não\n\n3 - AVISO\nModelo de Anúncio: Concurso público\nData de Envio do Anúncio: 29-12-2025\n\n5 - PROCESSO\nTipo de Procedimento: Concurso público\nPreço base do procedimento: Sim\nValor do preço base do procedimento: 63.700,00 EUR\nProcedimento com lotes? Sim\nNº Máx. de Lotes Autorizado: 4\nNúmero máximo de lotes que podem ser adjudicados a um concorrente: 4\n\n6 - OBJETO DO CONTRATO\nNúmero de referência interna: CP.01.2025.DAS\nDesignação do contrato: Aquisição de Produtos Alimentares para a Cantina do Centro Escolar e Atividades do Município - 2026\nDescrição: Aquisição de Produtos Alimentares para a Cantina do Centro Escolar e Atividades do Município - 2026\nTipo de Contrato Principal: Aquisição de Bens Móveis\nTipo de Contrato: Aquisição de Bens Móveis\nClassificação CPV (Vocabulário Comum para os Contratos Públicos)\nObjeto principal\nVocabulário Principal: 15800000\nPreço base s/IVA: 63.700,00 EUR\nLotes: \nNº: LOT-0001\nDescrição do Lote: Lote 1 - Carne Fresca - Outros\nPreço base s/IVA: 12.500,00 EUR\nClassificação CPV (Vocabulário Comum para os Contratos Públicos)\nObjeto principal\nVocabulário Principal: 15800000\nNº: LOT-0002\nDescrição do Lote: Lote 2 - Frutas e Legumes\nPreço base s/IVA: 11.000,00 EUR\nClassificação CPV (Vocabulário Comum para os Contratos Públicos)\nObjeto principal\nVocabulário Principal: 15800000\nNº: LOT-0003\nDescrição do Lote: Lote 3 - Géneros Alimentícios\nPreço base s/IVA: 21.500,00 EUR\nClassificação CPV (Vocabulário Comum para os Contratos Públicos)\nObjeto principal\nVocabulário Principal: 15800000\nNº: LOT-0004\nDescrição do Lote: Lote 4 - Peixe Congelado e Outros Congelados\nPreço base s/IVA: 18.700,00 EUR\nClassificação CPV (Vocabulário Comum para os Contratos Públicos)\nObjeto principal\nVocabulário Principal: 15800000\n\n7 - INDICAÇÕES ADICIONAIS\nO contrato envolve aquisição conjunta (satisfação de várias entidades)? Não\nO contrato é adjudicado por uma central de compras? Não\n\n8 - TÉCNICAS\nO concurso destina-se à celebração de um acordo-quadro? Inexistência de acordo-quadro\nÉ utilizado um leilão eletrónico? Não\nÉ adotada uma fase de negociação? Não\nSistema de Aquisição Dinâmico: Inexistência de sistema de aquisição dinâmico\n\n9 - LOCAL DA EXECUÇÃO DO CONTRATO\nLOCAL DA EXECUÇÃO DO CONTRATO (PROCEDIMENTO)\nPaís: Portugal\nNUT III: PT11D\nLocalidade: Freguesia de Torre de Moncorvo\nDistrito: Braganca\nConcelho: Torre de Moncorvo\nFreguesia: Freguesia de Torre de Moncorvo\nLOCAL DA EXECUÇÃO DO CONTRATO (LOTE)\nIdentificador do Lote: LOT-0001; LOT-0002; LOT-0003; LOT-0004\nPaís: Portugal\nNUT III: PT11D\nLocalidade: Freguesia de Torre de Moncorvo\nDistrito: Braganca\nConcelho: Torre de Moncorvo\nFreguesia: Freguesia de Torre de Moncorvo\n\n10 - PRAZO DE EXECUÇÃO DO CONTRATO\nIdentificador do Lote: LOT-0001; LOT-0002; LOT-0003; LOT-0004\nPrazo de execução do contrato: 365 DIAS\nPrevisão de renovações: Não\n\n11 - FUNDOS EU\nIdentificador do Lote: LOT-0001; LOT-0002; LOT-0003; LOT-0004\nTêm fundos EU? Não\n\n12 - DOCUMENTOS DE HABILITAÇÃO\nHabilitação para o exercício da atividade profissional: Não\n\n13 - CONDIÇÕES DE APRESENTAÇÃO\nPlataforma eletrónica utilizada pela entidade adjudicante: ACIN\nURL para Apresentação: https://www.acingov.pt\nAdmissibilidade da apresentação de propostas variantes: Não autorizado\nPrazo para apresentação das propostas: 04-01-2026 23:59\nPrazo durante o qual os concorrentes são obrigados a manter as respetivas propostas: 66 dias a contar do termo do prazo para a apresentação das propostas\nIndicação de Subcontratação na Proposta: Inexistência de indicação de subcontratação\n\n14 - PRESTAÇÃO DE CAUÇÃO\nPrestação de caução: Não\n\n15 - FORNECIMENTO DAS PEÇAS DO CONCURSO, APRESENTAÇÃO DE PEDIDOS DE PARTICIPAÇÃO E APRESENTAÇÃO DAS PROPOSTAS\nLink para acesso às peças do concurso (URL): https://www.acingov.pt/acingovprod/2/zonaPublica/zona_publica_c/donwloadProcedurePiece/MTAxMDUxNA==\n\n20 - OUTROS REQUISITOS\nIdentificador do Lote: LOT-0001; LOT-0002; LOT-0003; LOT-0004\nInformação sobre contratos reservados. Aplica-se a contratos reservados (54º-A)? Não\n\n21 - CRITÉRIO DE ADJUDICAÇÃO\nO Critério de adjudicação é diferenciado por lote? Não\nMultifator: Não\nMonofator:\nNome: Preço\n\n24 - CONDIÇÕES DO CONTRATO\nIdentificador do Lote: LOT-0001; LOT-0002; LOT-0003; LOT-0004\nFaturação Eletrónica: Permitido\nObrigação de Subcontratação:\nCódigo da Obrigação de Subcontratação: Não é aplicável nenhuma obrigação de subcontratação.\n\n25 - COMPRA PÚBLICA ESTRATÉGICA\nCompra Pública Estratégica: Inexistência de contratação pública estratégica\n\n26 - INFORMAÇÕES ADICIONAIS\nIdentificador do Lote: LOT-0001; LOT-0002; LOT-0003; LOT-0004\nContrato adequado para PME: Não\nCobertura ACP (Acordo dos Contratos Públicos da Organização Mundial do Comércio): Não\n\n27 - IDENTIFICAÇÃO E CONTACTOS DO ÓRGÃO DE RECURSOS ADMINISTRATIVOS\nDesignação: Presidente da Câmara Municipal de Torre de Moncorvo\nEndereço: Largo Dr. Campos Monteiro\nCódigo postal: 5160-303\nLocalidade: Torre de Moncorvo\nTelefone: 279200220\nFax: 279200240\nEndereço eletrónico: gab.presidente@torredemoncorvo.pt\n\n28 - IDENTIFICAÇÃO DO(S) AUTOR(ES) DE ANÚNCIO\nNome: Marina de Jesus Cavalheiro Amaral\nCargo: Técnica Superior\n419934396",
    "nipc": "501121536",
    "distrito": "Braganca",
    "concelho": "Torre de Moncorvo",
    "freguesia": "Freguesia de Torre de Moncorvo",
    "site": "http://www.cm-moncorvo.pt/",
    "email": "gab.presidente@torredemoncorvo.pt",
    "designacao_contrato": "Aquisição de Produtos Alimentares para a Cantina do Centro Escolar e Atividades do Município - 2026",
    "descricao": "Aquisição de Produtos Alimentares para a Cantina do Centro Escolar e Atividades do Município - 2026",
    "preco_base": "63.700,00 EUR",
    "prazo_execucao": "365 DIAS",
    "prazo_apresentacao_propostas": "04-01-2026 23:59",
    "fundos_eu": "Não",
    "plataforma_eletronica": "ACIN",
    "url_procedimento": "https://www.acingov.pt",
    "autor_nome": "Marina de Jesus Cavalheiro Amaral",
    "autor_cargo": "Técnica Superior"
  },
  {
    "numero_procedimento": "N/A",
    "entidade": "Unidade Local de Saúde do Algarve, EPE",
    "link": "https://diariodarepublica.pt/dr/detalhe/contrato-publico/33473-992908350",
    "detalhes_completos": "1 - IDENTIFICAÇÃO E CONTACTOS DA ENTIDADE ADJUDICANTE\nDesignação da entidade adjudicante: Unidade Local de Saúde do Algarve, EPE\nNIPC: 510745997\nEndereço: Rua Leão Penedo\nCódigo postal: 8000-386\nLocalidade: Faro\nPaís: Portugal\nNUT III: PT150\nDistrito: Faro\nConcelho: Faro\nFreguesia: União das Freguesias de Faro (Sé e São Pedro)\nTelefone: 289891100\nFax: 289891159\nEndereço da Entidade (URL): https://www.chualgarve.min-saude.pt\nEndereço Eletrónico: concursos@ulsalg.min-saude.pt\neDelivery Gateway (URL): https://community.vortal.biz/public/\nFunção da Organização: Adquirente\nNorma jurídica da Entidade Adjudicante: Organismo de direito público\nÁrea de atividade da Autoridade Adjudicante: Saúde\n\n2 - JORNAL OFICIAL DA UNIÃO EUROPEIA\nO procedimento a que este anúncio diz respeito também é publicitado no Jornal Oficial da União Europeia? Não\n\n3 - AVISO\nModelo de Anúncio: Concurso público urgente\nData de Envio do Anúncio: 29-12-2025 14:37:00\n\n5 - PROCESSO\nTipo de Procedimento: Concurso público\nPreço base do procedimento: Sim\nValor do preço base do procedimento: 101.539,20 EUR\nProcedimento com lotes? Não\n\n6 - OBJETO DO CONTRATO\nNúmero de referência interna: 27-5540-2025\nDesignação do contrato: Aquisição de Doppleres\nDescrição: Aquisição de Doppleres\nTipo de Contrato Principal: Aquisição de Bens Móveis\nTipo de Contrato: Aquisição de Bens Móveis\nClassificação CPV (Vocabulário Comum para os Contratos Públicos)\nObjeto principal\nVocabulário Principal: 33100000\nPreço base s/IVA: 101.539,20 EUR\n\n7 - INDICAÇÕES ADICIONAIS\nO contrato envolve aquisição conjunta (satisfação de várias entidades)? Não\nO contrato é adjudicado por uma central de compras? Não\n\n8 - TÉCNICAS\nO concurso destina-se à celebração de um acordo-quadro? Inexistência de acordo-quadro\nÉ utilizado um leilão eletrónico? Não\nÉ adotada uma fase de negociação? Não\nSistema de Aquisição Dinâmico: Inexistência de sistema de aquisição dinâmico\n\n9 - LOCAL DA EXECUÇÃO DO CONTRATO\nLOCAL DA EXECUÇÃO DO CONTRATO (PROCEDIMENTO)\nPaís: Portugal\nNUT III: PT150\nLocalidade: Faro\nDistrito: Faro\nConcelho: Portimão\nFreguesia: Freguesia de Portimão\n\n10 - PRAZO DE EXECUÇÃO DO CONTRATO\nPrazo de execução do contrato: 6 MESES\nPrevisão de renovações: Não\n\n11 - FUNDOS EU\nTêm fundos EU? Sim\n\n12 - DOCUMENTOS DE HABILITAÇÃO\nHabilitação para o exercício da atividade profissional: Não\n\n13 - CONDIÇÕES DE APRESENTAÇÃO\nPlataforma eletrónica utilizada pela entidade adjudicante: VORTAL\nURL para Apresentação: https://community.vortal.biz/public/\nAdmissibilidade da apresentação de propostas variantes: Não autorizado\nPrazo para apresentação das propostas: 31-12-2025 17:00\nPrazo durante o qual os concorrentes são obrigados a manter as respetivas propostas: 10 dias a contar do termo do prazo para a apresentação das propostas\nIndicação de Subcontratação na Proposta: Inexistência de indicação de subcontratação\n\n14 - PRESTAÇÃO DE CAUÇÃO\nPrestação de caução: Não\n\n15 - FORNECIMENTO DAS PEÇAS DO CONCURSO, APRESENTAÇÃO DE PEDIDOS DE PARTICIPAÇÃO E APRESENTAÇÃO DAS PROPOSTAS\nLink para acesso às peças do concurso (URL): https://community.vortal.biz/Public/public-tender-documents/UTQ1eVVYTGNOSUU2U096TnJkK1hIc0tCM1IzOWVDdk5BTzJGVlhOTmtoNXNOMGFWbmJleDNCZms3Q0g0Zlg3OW1PSStvemdpeGZWTVNGUENNK1F5K2c9PW9hK3Mp\n\n20 - OUTROS REQUISITOS\nInformação sobre contratos reservados. Aplica-se a contratos reservados (54º-A)? Não\n\n21 - CRITÉRIO DE ADJUDICAÇÃO\nMultifator: Não\nMonofator:\nNome: Outros\nOutro nome: Preço\n\n24 - CONDIÇÕES DO CONTRATO\nFaturação Eletrónica: Permitido\nObrigação de Subcontratação:\nCódigo da Obrigação de Subcontratação: Não é aplicável nenhuma obrigação de subcontratação.\n\n25 - COMPRA PÚBLICA ESTRATÉGICA\nCompra Pública Estratégica: Inexistência de contratação pública estratégica\n\n26 - INFORMAÇÕES ADICIONAIS\nContrato adequado para PME: Sim\nCobertura ACP (Acordo dos Contratos Públicos da Organização Mundial do Comércio): Não\n\n27 - IDENTIFICAÇÃO E CONTACTOS DO ÓRGÃO DE RECURSOS ADMINISTRATIVOS\nDesignação: ULSALG, EPE\nEndereço: Rua Leão Penedo\nCódigo postal: 8000-386\nLocalidade: Faro\nTelefone: +351 282450311\nFax: +351 282450311\nEndereço eletrónico: concursos@ulsalg.min-saude.pt\n\n28 - IDENTIFICAÇÃO DO(S) AUTOR(ES) DE ANÚNCIO\nNome: Dr. Gonçalves Júnior\nCargo: Vogal do Conselho de Administração\n419935579",
    "nipc": "510745997",
    "distrito": "Faro",
    "concelho": "Faro",
    "freguesia": "União das Freguesias de Faro (Sé e São Pedro)",
    "site": "https://www.chualgarve.min-saude.pt",
    "email": "concursos@ulsalg.min-saude.pt",
    "designacao_contrato": "Aquisição de Doppleres",
    "descricao": "Aquisição de Doppleres",
    "preco_base": "101.539,20 EUR",
    "prazo_execucao": "6 MESES",
    "prazo_apresentacao_propostas": "31-12-2025 17:00",
    "fundos_eu": "Sim",
    "plataforma_eletronica": "VORTAL",
    "url_procedimento": "https://community.vortal.biz/public/",
    "autor_nome": "Dr. Gonçalves Júnior",
    "autor_cargo": "Vogal do Conselho de Administração"
  },
  {
    "numero_procedimento": "N/A",
    "entidade": "Serviço de Saúde da Região Autónoma da Madeira, EPE-RAM",
    "link": "https://diariodarepublica.pt/dr/detalhe/contrato-publico/33514-992908354",
    "detalhes_completos": "Alteração do Anúncio de procedimento n.º 32702/2025, de 2025-12-17, com o ID 419895046\n\n1 - IDENTIFICAÇÃO E CONTACTOS DA ENTIDADE ADJUDICANTE\nDesignação da entidade adjudicante: Serviço de Saúde da Região Autónoma da Madeira, EPE-RAM\nNIPC: 511228848\nServiço/Órgão/Pessoa de contacto: Núcleo de Aprovisionamento\nEndereço: Avenida Luís de Camões, nº 57\nCódigo postal: 9004-514\nLocalidade: FUNCHAL\nPaís: Portugal\nNUT III: PT300\nDistrito: Região Autónoma da Madeira\nConcelho: Funchal\nFreguesia: Freguesia de São Pedro (Funchal)\nTelefone: 291705610\nFax: 291742545\nEndereço da Entidade (URL): www.sesaram.pt\nEndereço Eletrónico: aprovisionamento@sesaram.pt\neDelivery Gateway (URL): https://www.acingov.pt\nFunção da Organização: Adquirente\nNorma jurídica da Entidade Adjudicante: Organismo de direito público\nÁrea de atividade da Autoridade Adjudicante: Serviços públicos das administrações públicas\n\n2 - JORNAL OFICIAL DA UNIÃO EUROPEIA\nO procedimento a que este anúncio diz respeito também é publicitado no Jornal Oficial da União Europeia? Não\n\n3 - AVISO\nModelo de Anúncio: Concurso público\nData de Envio do Anúncio: 29-12-2025\n\n5 - PROCESSO\nTipo de Procedimento: Concurso público\nPreço base do procedimento: Sim\nValor do preço base do procedimento: 148.949,50 EUR\nProcedimento com lotes? Sim\nNº Máx. de Lotes Autorizado: 81\nNúmero máximo de lotes que podem ser adjudicados a um concorrente: 81\n\n6 - OBJETO DO CONTRATO\nNúmero de referência interna: NCP20260015\nDesignação do contrato: NCP20260015 - FIOS SUTURA DE SEDA OU SINTETICOS\nDescrição: NCP20260015 - FIOS SUTURA DE SEDA OU SINTETICOS\nTipo de Contrato Principal: Aquisição de Bens Móveis\nTipo de Contrato: Aquisição de Bens Móveis\nClassificação CPV (Vocabulário Comum para os Contratos Públicos)\nObjeto principal\nVocabulário Principal: 33190000\nPreço base s/IVA: 148.949,50 EUR\nLotes: \nNº: LOT-0001\nDescrição do Lote: FIO SEDA 1 S/AGULHA 75CM\nPreço base s/IVA: 327,60 EUR\nClassificação CPV (Vocabulário Comum para os Contratos Públicos)\nObjeto principal\nVocabulário Principal: 33190000\nNº: LOT-0002\nDescrição do Lote: FIO SEDA 0 S/AGULHA (PRE-CORTADO)\nPreço base s/IVA: 271,44 EUR\nClassificação CPV (Vocabulário Comum para os Contratos Públicos)\nObjeto principal\nVocabulário Principal: 33190000\nNº: LOT-0003\nDescrição do Lote: FIO SEDA 0 S/AGULHA (FIO-LONGO)\nPreço base s/IVA: 182,52 EUR\nClassificação CPV (Vocabulário Comum para os Contratos Públicos)\nObjeto principal\nVocabulário Principal: 33190000\nNº: LOT-0004\nDescrição do Lote: FIO SEDA 1 C/AG.LANC.3/8 50-60MM\nPreço base s/IVA: 346,68 EUR\nClassificação CPV (Vocabulário Comum para os Contratos Públicos)\nObjeto principal\nVocabulário Principal: 33190000\nNº: LOT-0005\nDescrição do Lote: FIO SEDA 1 C/AG.LANC.3/8 37-45MM\nPreço base s/IVA: 887,04 EUR\nClassificação CPV (Vocabulário Comum para os Contratos Públicos)\nObjeto principal\nVocabulário Principal: 33190000\nNº: LOT-0006\nDescrição do Lote: FIO SEDA 0 C/AG.LANC.3/8 30-35MM\nPreço base s/IVA: 3.146,40 EUR\nClassificação CPV (Vocabulário Comum para os Contratos Públicos)\nObjeto principal\nVocabulário Principal: 33190000\nNº: LOT-0007\nDescrição do Lote: FIO SEDA 2/0 C/AG.LANC.3/8 35-39MM\nPreço base s/IVA: 2.968,20 EUR\nClassificação CPV (Vocabulário Comum para os Contratos Públicos)\nObjeto principal\nVocabulário Principal: 33190000\nNº: LOT-0008\nDescrição do Lote: FIO SEDA 3/0 C/AG.LANC.3/8 25-30MM\nPreço base s/IVA: 1.635,48 EUR\nClassificação CPV (Vocabulário Comum para os Contratos Públicos)\nObjeto principal\nVocabulário Principal: 33190000\nNº: LOT-0009\nDescrição do Lote: FIO SEDA 1 C/AG.CIL.1/2 35MM\nPreço base s/IVA: 76,68 EUR\nClassificação CPV (Vocabulário Comum para os Contratos Públicos)\nObjeto principal\nVocabulário Principal: 33190000\nNº: LOT-0010\nDescrição do Lote: FIO SEDA 0 C/AG.CIL.1/2 30MM\nPreço base s/IVA: 192,96 EUR\nClassificação CPV (Vocabulário Comum para os Contratos Públicos)\nObjeto principal\nVocabulário Principal: 33190000\nNº: LOT-0011\nDescrição do Lote: FIO SEDA 2/0 C/AG.CIL.1/2 25-26MM\nPreço base s/IVA: 794,88 EUR\nClassificação CPV (Vocabulário Comum para os Contratos Públicos)\nObjeto principal\nVocabulário Principal: 33190000\nNº: LOT-0012\nDescrição do Lote: FIO SEDA 3/0 C/AG.CIL.1/2 25MM\nPreço base s/IVA: 138,24 EUR\nClassificação CPV (Vocabulário Comum para os Contratos Públicos)\nObjeto principal\nVocabulário Principal: 33190000\nNº: LOT-0013\nDescrição do Lote: FIO SEDA 3/0 C/AG.CIL.1/2 16MM\nPreço base s/IVA: 75,60 EUR\nClassificação CPV (Vocabulário Comum para os Contratos Públicos)\nObjeto principal\nVocabulário Principal: 33190000\nNº: LOT-0014\nDescrição do Lote: FIO SEDA 4/0 C/AG.CIL.1/2 17-20MM\nPreço base s/IVA: 58,32 EUR\nClassificação CPV (Vocabulário Comum para os Contratos Públicos)\nObjeto principal\nVocabulário Principal: 33190000\nNº: LOT-0015\nDescrição do Lote: FIO SEDA 5/0 C/AG.CIL.1/2 16MM\nPreço base s/IVA: 355,68 EUR\nClassificação CPV (Vocabulário Comum para os Contratos Públicos)\nObjeto principal\nVocabulário Principal: 33190000\nNº: LOT-0016\nDescrição do Lote: FIO SEDA 4 S/AGULHA\nPreço base s/IVA: 133,92 EUR\nClassificação CPV (Vocabulário Comum para os Contratos Públicos)\nObjeto principal\nVocabulário Principal: 33190000\nNº: LOT-0017\nDescrição do Lote: FIO SEDA 4/0 C/AG.LANC.3/8 15-20MM\nPreço base s/IVA: 1.840,32 EUR\nClassificação CPV (Vocabulário Comum para os Contratos Públicos)\nObjeto principal\nVocabulário Principal: 33190000\nNº: LOT-0018\nDescrição do Lote: FIO MONOF.POLIPROPIL.5/0 C/2AGULHAS DE 17MM\nPreço base s/IVA: 590,40 EUR\nClassificação CPV (Vocabulário Comum para os Contratos Públicos)\nObjeto principal\nVocabulário Principal: 33190000\nNº: LOT-0019\nDescrição do Lote: FIO MONOF.POLIAMIDA 1 C/AG.TPCUT LOOP 45MM\nPreço base s/IVA: 742,56 EUR\nClassificação CPV (Vocabulário Comum para os Contratos Públicos)\nObjeto principal\nVocabulário Principal: 33190000\nNº: LOT-0020\nDescrição do Lote: FIO MONOF.POLIAMIDA 0 C/AG.CIL.LOOP 40MM\nPreço base s/IVA: 203,52 EUR\nClassificação CPV (Vocabulário Comum para os Contratos Públicos)\nObjeto principal\nVocabulário Principal: 33190000\nNº: LOT-0021\nDescrição do Lote: FIO MONOF.POLIAMIDA 2/0 C/AG.LANC.3/8 40MM\nPreço base s/IVA: 1.904,04 EUR\nClassificação CPV (Vocabulário Comum para os Contratos Públicos)\nObjeto principal\nVocabulário Principal: 33190000\nNº: LOT-0022\nDescrição do Lote: FIO MONOF.POLIAMIDA 3/0 C/AG.LANC.3/8 26-30MM\nPreço base s/IVA: 2.527,20 EUR\nClassificação CPV (Vocabulário Comum para os Contratos Públicos)\nObjeto principal\nVocabulário Principal: 33190000\nNº: LOT-0023\nDescrição do Lote: FIO MONOF.POLIAMIDA 4/0 C/AG.LANC.3/8 19-20MM\nPreço base s/IVA: 1.485,00 EUR\nClassificação CPV (Vocabulário Comum para os Contratos Públicos)\nObjeto principal\nVocabulário Principal: 33190000\nNº: LOT-0024\nDescrição do Lote: FIO MONOF.POLIAMIDA 5/0 C/AG.LANC.3/8 16MM\nPreço base s/IVA: 1.259,28 EUR\nClassificação CPV (Vocabulário Comum para os Contratos Públicos)\nObjeto principal\nVocabulário Principal: 33190000\nNº: LOT-0025\nDescrição do Lote: FIO MONOF.POLIPROPIL.2/0 C/2AG.1/2 TPCT17MM\nPreço base s/IVA: 684,00 EUR\nClassificação CPV (Vocabulário Comum para os Contratos Públicos)\nObjeto principal\nVocabulário Principal: 33190000\nNº: LOT-0026\nDescrição do Lote: FIO MONOF.POLIPROPIL.2/0 C/2AG.1/2 TPCT 26MM\nPreço base s/IVA: 1.378,08 EUR\nClassificação CPV (Vocabulário Comum para os Contratos Públicos)\nObjeto principal\nVocabulário Principal: 33190000\nNº: LOT-0027\nDescrição do Lote: FIO MONOF.POLIPROPIL.2/0 C/2AG.RECTA 70MM\nPreço base s/IVA: 496,20 EUR\nClassificação CPV (Vocabulário Comum para os Contratos Públicos)\nObjeto principal\nVocabulário Principal: 33190000\nNº: LOT-0028\nDescrição do Lote: FIO MONOF.POLIPROPIL.3/0 C/2AG.CIL.1/2 25MM\nPreço base s/IVA: 1.817,64 EUR\nClassificação CPV (Vocabulário Comum para os Contratos Públicos)\nObjeto principal\nVocabulário Principal: 33190000\nNº: LOT-0029\nDescrição do Lote: FIO SINTETICO ABSOV. MONOF. POLIDIOXANONA 5/0 AG.1/2 CILIND. 13MM DE 45CM\nPreço base s/IVA: 414,72 EUR\nClassificação CPV (Vocabulário Comum para os Contratos Públicos)\nObjeto principal\nVocabulário Principal: 33190000\nNº: LOT-0030\nDescrição do Lote: FIO MONOF.POLIPROPIL.5/0 C/2AG.CIL. 3/8 13MM\nPreço base s/IVA: 1.476,00 EUR\nClassificação CPV (Vocabulário Comum para os Contratos Públicos)\nObjeto principal\nVocabulário Principal: 33190000\nNº: LOT-0031\nDescrição do Lote: FIO MONOF.POLIPROPIL.8/0 C/2AG. 3/8 60CM\nPreço base s/IVA: 264,00 EUR\nClassificação CPV (Vocabulário Comum para os Contratos Públicos)\nObjeto principal\nVocabulário Principal: 33190000\nNº: LOT-0032\nDescrição do Lote: FIO MONOF.POLIPROPIL.4/0 C/2 AG.CIL.3/8 13MM\nPreço base s/IVA: 580,32 EUR\nClassificação CPV (Vocabulário Comum para os Contratos Públicos)\nObjeto principal\nVocabulário Principal: 33190000\nNº: LOT-0033\nDescrição do Lote: FIO SUTURA ABSORVIVEL 2/0 C/AUTO-ANCORAGEM 30CM\nPreço base s/IVA: 624,00 EUR\nClassificação CPV (Vocabulário Comum para os Contratos Públicos)\nObjeto principal\nVocabulário Principal: 33190000\nNº: LOT-0034\nDescrição do Lote: FIO MONOF. ABSORVIVEL 6/0 C/1 AGULHA CILINDRICA 1/2 DE 13MM\nPreço base s/IVA: 707,40 EUR\nClassificação CPV (Vocabulário Comum para os Contratos Públicos)\nObjeto principal\nVocabulário Principal: 33190000\nNº: LOT-0035\nDescrição do Lote: FIO MONOF.POLIPROPIL. N. 4/0 C/2AG. 1/2 CIRCULO CC 25MM FIO AZUL 90CM\nPreço base s/IVA: 446,40 EUR\nClassificação CPV (Vocabulário Comum para os Contratos Públicos)\nObjeto principal\nVocabulário Principal: 33190000\nNº: LOT-0036\nDescrição do Lote: FIO MULTIFIL.REABSORV. 0 C/AG.1/2 CIL.30MM\nPreço base s/IVA: 794,88 EUR\nClassificação CPV (Vocabulário Comum para os Contratos Públicos)\nObjeto principal\nVocabulário Principal: 33190000\nNº: LOT-0037\nDescrição do Lote: FIO MULTIFIL.REABSORV. 0 C/AG.1/2 CIL. C/REV. ANTIBACTERIANO 30MM\nPreço base s/IVA: 1.108,80 EUR\nClassificação CPV (Vocabulário Comum para os Contratos Públicos)\nObjeto principal\nVocabulário Principal: 33190000\nNº: LOT-0038\nDescrição do Lote: FIO MULTIFIL.REABSORV.1 C/AG. TAPERCUT1/2 CIL. 30MM\nPreço base s/IVA: 1.277,64 EUR\nClassificação CPV (Vocabulário Comum para os Contratos Públicos)\nObjeto principal\nVocabulário Principal: 33190000\nNº: LOT-0039\nDescrição do Lote: FIO POLIESTER 2/0 C/2AG.TPCUT 1/2 25MM VERDE\nPreço base s/IVA: 1.361,10 EUR\nClassificação CPV (Vocabulário Comum para os Contratos Públicos)\nObjeto principal\nVocabulário Principal: 33190000\nNº: LOT-0040\nDescrição do Lote: FIO POLIESTER 0 C/2AG.1/2 TPCUT 25MM VERDE\nPreço base s/IVA: 552,60 EUR\nClassificação CPV (Vocabulário Comum para os Contratos Públicos)\nObjeto principal\nVocabulário Principal: 33190000\nNº: LOT-0041\nDescrição do Lote: FIO MONOF. REABSORV. RAPIDA 2/0 C/AGULHA TPCUT 1/2 CIRCULO C/35MM\nPreço base s/IVA: 73,92 EUR\nClassificação CPV (Vocabulário Comum para os Contratos Públicos)\nObjeto principal\nVocabulário Principal: 33190000\nNº: LOT-0042\nDescrição do Lote: FIO DE SUTURA NAO ABSORVIVEL 2/0 C/AG.CIL.1/2CIR.26MM C/AUTO-ANCORAGEM\nPreço base s/IVA: 1.800,00 EUR\nClassificação CPV (Vocabulário Comum para os Contratos Públicos)\nObjeto principal\nVocabulário Principal: 33190000\nNº: LOT-0043\nDescrição do Lote: FIO DE SUTURA NAO ABSORVIVEL 2/0 C/AG.CIL.1/2CIR.22MM C/AUTO-ANCORAGEM\nPreço base s/IVA: 600,00 EUR\nClassificação CPV (Vocabulário Comum para os Contratos Públicos)\nObjeto principal\nVocabulário Principal: 33190000\nNº: LOT-0044\nDescrição do Lote: FIO MONOF.POLIPROPIL.7/0 C/2AG.3/8 CIL.8MM\nPreço base s/IVA: 375,84 EUR\nClassificação CPV (Vocabulário Comum para os Contratos Públicos)\nObjeto principal\nVocabulário Principal: 33190000\nNº: LOT-0045\nDescrição do Lote: FIO MONOF.POLIPROPIL.6/0 C/2AG.CIL.3/8 8MM 60CM\nPreço base s/IVA: 371,52 EUR\nClassificação CPV (Vocabulário Comum para os Contratos Públicos)\nObjeto principal\nVocabulário Principal: 33190000\nNº: LOT-0046\nDescrição do Lote: FIO MONOF.POLIPROPIL.6/0 C/2AG.CIL. 3/8 13MM 60CM\nPreço base s/IVA: 751,68 EUR\nClassificação CPV (Vocabulário Comum para os Contratos Públicos)\nObjeto principal\nVocabulário Principal: 33190000\nNº: LOT-0047\nDescrição do Lote: FIO S.PTFE 5/0 C/2AG.1/2 CIL.13MM-75CM\nPreço base s/IVA: 2.112,00 EUR\nClassificação CPV (Vocabulário Comum para os Contratos Públicos)\nObjeto principal\nVocabulário Principal: 33190000\nNº: LOT-0048\nDescrição do Lote: FIO S.PTFE 6/0 C/2AG.3/8 CIL.9MM-60CM\nPreço base s/IVA: 1.056,00 EUR\nClassificação CPV (Vocabulário Comum para os Contratos Públicos)\nObjeto principal\nVocabulário Principal: 33190000\nNº: LOT-0049\nDescrição do Lote: FIO SUTURA MONOF. REABSORV. VIOLETA 7/0 C/AG.CIL. 3/8 8MM\nPreço base s/IVA: 257,04 EUR\nClassificação CPV (Vocabulário Comum para os Contratos Públicos)\nObjeto principal\nVocabulário Principal: 33190000\nNº: LOT-0050\nDescrição do Lote: FIO MONOF. REABSORV. RAPIDA 3/0 C/AG.CIL.1/2 26MM\nPreço base s/IVA: 1.784,16 EUR\nClassificação CPV (Vocabulário Comum para os Contratos Públicos)\nObjeto principal\nVocabulário Principal: 33190000\nNº: LOT-0051\nDescrição do Lote: FIO MONOF. REABSORV. RAPIDA 4/0 C/AG.LANC.19MM\nPreço base s/IVA: 6.545,56 EUR\nClassificação CPV (Vocabulário Comum para os Contratos Públicos)\nObjeto principal\nVocabulário Principal: 33190000\nNº: LOT-0052\nDescrição do Lote: FIO S.PTFE 5/0 C/2AG. 3/8 CILINDRICA 13MM-75CM\nPreço base s/IVA: 528,00 EUR\nClassificação CPV (Vocabulário Comum para os Contratos Públicos)\nObjeto principal\nVocabulário Principal: 33190000\nNº: LOT-0053\nDescrição do Lote: FIO MULTIFIL. REABSORV. RAPIDA 4/0 C/AG.LANC.19MM\nPreço base s/IVA: 6.552,00 EUR\nClassificação CPV (Vocabulário Comum para os Contratos Públicos)\nObjeto principal\nVocabulário Principal: 33190000\nNº: LOT-0054\nDescrição do Lote: FIO MONOF.REABSORV.RETARD.1 C/AG.CIL.LOOP 50MM\nPreço base s/IVA: 7.131,84 EUR\nClassificação CPV (Vocabulário Comum para os Contratos Públicos)\nObjeto principal\nVocabulário Principal: 33190000\nNº: LOT-0055\nDescrição do Lote: FIO MONOF.REABSORV.RETARD.0 C/AG.CIL.LOOP 40MM\nPreço base s/IVA: 2.615,28 EUR\nClassificação CPV (Vocabulário Comum para os Contratos Públicos)\nObjeto principal\nVocabulário Principal: 33190000\nNº: LOT-0056\nDescrição do Lote: FIO MONOF.REABSORV.RETARD.3/0 C/AG.CIL.1/2 25MM\nPreço base s/IVA: 1.069,20 EUR\nClassificação CPV (Vocabulário Comum para os Contratos Públicos)\nObjeto principal\nVocabulário Principal: 33190000\nNº: LOT-0057\nDescrição do Lote: FIO MONOF.REABSORV.RETARD.4/0 C/AG.CIL.1/2 20MM\nPreço base s/IVA: 193,68 EUR\nClassificação CPV (Vocabulário Comum para os Contratos Públicos)\nObjeto principal\nVocabulário Principal: 33190000\nNº: LOT-0058\nDescrição do Lote: FIO MONOF.REABSORV.RETARD.2/0 C/AG.CIL.1/2 26MM\nPreço base s/IVA: 846,72 EUR\nClassificação CPV (Vocabulário Comum para os Contratos Públicos)\nObjeto principal\nVocabulário Principal: 33190000\nNº: LOT-0059\nDescrição do Lote: FIO MULTIFIL.REABSORV.2/0 DE 35 A 36MM\nPreço base s/IVA: 671,76 EUR\nClassificação CPV (Vocabulário Comum para os Contratos Públicos)\nObjeto principal\nVocabulário Principal: 33190000\nNº: LOT-0060\nDescrição do Lote: FIO MULTIFIL.REABSORV.3/0 C/AG.LANC.26-30MM\nPreço base s/IVA: 1.944,00 EUR\nClassificação CPV (Vocabulário Comum para os Contratos Públicos)\nObjeto principal\nVocabulário Principal: 33190000\nNº: LOT-0061\nDescrição do Lote: FIO MULTIFIL.REABSORV.0 C/AG.1/2 CIL.36 A 37MM\nPreço base s/IVA: 5.680,80 EUR\nClassificação CPV (Vocabulário Comum para os Contratos Públicos)\nObjeto principal\nVocabulário Principal: 33190000\nNº: LOT-0062\nDescrição do Lote: FIO MULTIFIL.REABSORV.1 C/AG.1/2 CIL. 37-40MM\nPreço base s/IVA: 11.448,00 EUR\nClassificação CPV (Vocabulário Comum para os Contratos Públicos)\nObjeto principal\nVocabulário Principal: 33190000\nNº: LOT-0063\nDescrição do Lote: FIO MULTIFIL. REABSORV. RAPIDA 0 C/AG.CIL.1/2 37MM\nPreço base s/IVA: 1.309,68 EUR\nClassificação CPV (Vocabulário Comum para os Contratos Públicos)\nObjeto principal\nVocabulário Principal: 33190000\nNº: LOT-0064\nDescrição do Lote: FIO MULTIFIL. REABSORV. RAPIDA 2/0 C/AG.CIL. 30MM\nPreço base s/IVA: 3.729,60 EUR\nClassificação CPV (Vocabulário Comum para os Contratos Públicos)\nObjeto principal\nVocabulário Principal: 33190000\nNº: LOT-0065\nDescrição do Lote: FIO MULTIFIL. REABSORV. RAPIDA 3/0 C/AG.CIL. 26MM\nPreço base s/IVA: 1.833,12 EUR\nClassificação CPV (Vocabulário Comum para os Contratos Públicos)\nObjeto principal\nVocabulário Principal: 33190000\nNº: LOT-0066\nDescrição do Lote: FIO MULTIFIL. REABSORV. RAPIDA 5/0 C/AG.LANC.12MM\nPreço base s/IVA: 1.089,00 EUR\nClassificação CPV (Vocabulário Comum para os Contratos Públicos)\nObjeto principal\nVocabulário Principal: 33190000\nNº: LOT-0067\nDescrição do Lote: FIO MULTIFIL. REABSORV. 2/0 C/2AG. CIL.1/2 CIRC. 30MM\nPreço base s/IVA: 5.049,00 EUR\nClassificação CPV (Vocabulário Comum para os Contratos Públicos)\nObjeto principal\nVocabulário Principal: 33190000\nNº: LOT-0068\nDescrição do Lote: FIO MULTIFIL.REABSORV.2/0 C/AG.CIL.1/2 31MM\nPreço base s/IVA: 8.963,28 EUR\nClassificação CPV (Vocabulário Comum para os Contratos Públicos)\nObjeto principal\nVocabulário Principal: 33190000\nNº: LOT-0069\nDescrição do Lote: FIO MULTIFIL.REABSORV.3/0 C/AG.CIL.1/2 30 A 31MM\nPreço base s/IVA: 1.425,60 EUR\nClassificação CPV (Vocabulário Comum para os Contratos Públicos)\nObjeto principal\nVocabulário Principal: 33190000\nNº: LOT-0070\nDescrição do Lote: FIO MULTIFIL.REABSORV.3/0 C/AG.CIL.1/2 25MM\nPreço base s/IVA: 3.519,36 EUR\nClassificação CPV (Vocabulário Comum para os Contratos Públicos)\nObjeto principal\nVocabulário Principal: 33190000\nNº: LOT-0071\nDescrição do Lote: FIO MULTIFIL.REABSORV.4/0 C/AG.CIL.1/2 20-22M\nPreço base s/IVA: 1.755,00 EUR\nClassificação CPV (Vocabulário Comum para os Contratos Públicos)\nObjeto principal\nVocabulário Principal: 33190000\nNº: LOT-0072\nDescrição do Lote: FIO MULTIFIL.REABSORV.5/0 C/AG.CIL.1/2 12-17MM\nPreço base s/IVA: 343,44 EUR\nClassificação CPV (Vocabulário Comum para os Contratos Públicos)\nObjeto principal\nVocabulário Principal: 33190000\nNº: LOT-0073\nDescrição do Lote: FIO MULTIFIL.REABSORV.4/0 C/AG.LANC.19MM\nPreço base s/IVA: 936,00 EUR\nClassificação CPV (Vocabulário Comum para os Contratos Públicos)\nObjeto principal\nVocabulário Principal: 33190000\nNº: LOT-0074\nDescrição do Lote: FIO MULTIFIL.REABSORV.5/0 C/AG.LANC.3/8 16MM\nPreço base s/IVA: 1.108,80 EUR\nClassificação CPV (Vocabulário Comum para os Contratos Públicos)\nObjeto principal\nVocabulário Principal: 33190000\nNº: LOT-0075\nDescrição do Lote: FIO MULTIFIL.REABSORV.1 C/AG.1/2 LANC.37-40MM\nPreço base s/IVA: 4.222,80 EUR\nClassificação CPV (Vocabulário Comum para os Contratos Públicos)\nObjeto principal\nVocabulário Principal: 33190000\nNº: LOT-0076\nDescrição do Lote: FIO MULTIFIL.REABSORV.2/0 C/AG.LANC.1/2 30 CM APROX\nPreço base s/IVA: 3.296,16 EUR\nClassificação CPV (Vocabulário Comum para os Contratos Públicos)\nObjeto principal\nVocabulário Principal: 33190000\nNº: LOT-0077\nDescrição do Lote: FIO MULTIFIL.REABSORV.0 C/AG.1/2 LANC.40MM\nPreço base s/IVA: 2.143,44 EUR\nClassificação CPV (Vocabulário Comum para os Contratos Públicos)\nObjeto principal\nVocabulário Principal: 33190000\nNº: LOT-0078\nDescrição do Lote: FIO MULTIFIL.REABSORV.2/0 C/AG.LANC.1/2 34-37MM\nPreço base s/IVA: 4.524,12 EUR\nClassificação CPV (Vocabulário Comum para os Contratos Públicos)\nObjeto principal\nVocabulário Principal: 33190000\nNº: LOT-0079\nDescrição do Lote: FIO MULTIFIL.REABSORV.3/0 C/AG.CIL.1/2 20MM\nPreço base s/IVA: 3.970,44 EUR\nClassificação CPV (Vocabulário Comum para os Contratos Públicos)\nObjeto principal\nVocabulário Principal: 33190000\nNº: LOT-0080\nDescrição do Lote: FIO MULTIFIL.REABSORV.2 C/AG.1/2 LANC 22 A 23MM\nPreço base s/IVA: 6.853,68 EUR\nClassificação CPV (Vocabulário Comum para os Contratos Públicos)\nObjeto principal\nVocabulário Principal: 33190000\nNº: LOT-0081\nDescrição do Lote: FIO MULTIFIL.REABSORV.2/0 S/AG.\nPreço base s/IVA: 2.340,24 EUR\nClassificação CPV (Vocabulário Comum para os Contratos Públicos)\nObjeto principal\nVocabulário Principal: 33190000\n\n7 - INDICAÇÕES ADICIONAIS\nO contrato envolve aquisição conjunta (satisfação de várias entidades)? Não\nO contrato é adjudicado por uma central de compras? Não\n\n8 - TÉCNICAS\nO concurso destina-se à celebração de um acordo-quadro? Inexistência de acordo-quadro\nÉ utilizado um leilão eletrónico? Não\nÉ adotada uma fase de negociação? Não\nSistema de Aquisição Dinâmico: Inexistência de sistema de aquisição dinâmico\n\n9 - LOCAL DA EXECUÇÃO DO CONTRATO\nLOCAL DA EXECUÇÃO DO CONTRATO (PROCEDIMENTO)\nPaís: Portugal\nNUT III: PT300\nLocalidade: Freguesia de São Pedro (Funchal)\nDistrito: Região Autónoma da Madeira\nConcelho: Funchal\nFreguesia: Freguesia de São Pedro (Funchal)\nLOCAL DA EXECUÇÃO DO CONTRATO (LOTE)\nIdentificador do Lote: LOT-0001; LOT-0002; LOT-0003; LOT-0004; LOT-0005; LOT-0006; LOT-0007; LOT-0008; LOT-0009; LOT-0010; LOT-0011; LOT-0012; LOT-0013; LOT-0014; LOT-0015; LOT-0016; LOT-0017; LOT-0018; LOT-0019; LOT-0020; LOT-0021; LOT-0022; LOT-0023; LOT-0024; LOT-0025; LOT-0026; LOT-0027; LOT-0028; LOT-0029; LOT-0030; LOT-0031; LOT-0032; LOT-0033; LOT-0034; LOT-0035; LOT-0036; LOT-0037; LOT-0038; LOT-0039; LOT-0040; LOT-0041; LOT-0042; LOT-0043; LOT-0044; LOT-0045; LOT-0046; LOT-0047; LOT-0048; LOT-0049; LOT-0050; LOT-0051; LOT-0052; LOT-0053; LOT-0054; LOT-0055; LOT-0056; LOT-0057; LOT-0058; LOT-0059; LOT-0060; LOT-0061; LOT-0062; LOT-0063; LOT-0064; LOT-0065; LOT-0066; LOT-0067; LOT-0068; LOT-0069; LOT-0070; LOT-0071; LOT-0072; LOT-0073; LOT-0074; LOT-0075; LOT-0076; LOT-0077; LOT-0078; LOT-0079; LOT-0080; LOT-0081\nPaís: Portugal\nNUT III: PT300\nLocalidade: Funchal\nDistrito: Região Autónoma da Madeira\nConcelho: Funchal\nFreguesia: Freguesia de São Pedro (Funchal)\n\n10 - PRAZO DE EXECUÇÃO DO CONTRATO\nIdentificador do Lote: LOT-0001; LOT-0002; LOT-0003; LOT-0004; LOT-0005; LOT-0006; LOT-0007; LOT-0008; LOT-0009; LOT-0010; LOT-0011; LOT-0012; LOT-0013; LOT-0014; LOT-0015; LOT-0016; LOT-0017; LOT-0018; LOT-0019; LOT-0020; LOT-0021; LOT-0022; LOT-0023; LOT-0024; LOT-0025; LOT-0026; LOT-0027; LOT-0028; LOT-0029; LOT-0030; LOT-0031; LOT-0032; LOT-0033; LOT-0034; LOT-0035; LOT-0036; LOT-0037; LOT-0038; LOT-0039; LOT-0040; LOT-0041; LOT-0042; LOT-0043; LOT-0044; LOT-0045; LOT-0046; LOT-0047; LOT-0048; LOT-0049; LOT-0050; LOT-0051; LOT-0052; LOT-0053; LOT-0054; LOT-0055; LOT-0056; LOT-0057; LOT-0058; LOT-0059; LOT-0060; LOT-0061; LOT-0062; LOT-0063; LOT-0064; LOT-0065; LOT-0066; LOT-0067; LOT-0068; LOT-0069; LOT-0070; LOT-0071; LOT-0072; LOT-0073; LOT-0074; LOT-0075; LOT-0076; LOT-0077; LOT-0078; LOT-0079; LOT-0080; LOT-0081\nPrazo de execução do contrato: 12 MESES\nPrevisão de renovações: Não\n\n11 - FUNDOS EU\nIdentificador do Lote: LOT-0001; LOT-0002; LOT-0003; LOT-0004; LOT-0005; LOT-0006; LOT-0007; LOT-0008; LOT-0009; LOT-0010; LOT-0011; LOT-0012; LOT-0013; LOT-0014; LOT-0015; LOT-0016; LOT-0017; LOT-0018; LOT-0019; LOT-0020; LOT-0021; LOT-0022; LOT-0023; LOT-0024; LOT-0025; LOT-0026; LOT-0027; LOT-0028; LOT-0029; LOT-0030; LOT-0031; LOT-0032; LOT-0033; LOT-0034; LOT-0035; LOT-0036; LOT-0037; LOT-0038; LOT-0039; LOT-0040; LOT-0041; LOT-0042; LOT-0043; LOT-0044; LOT-0045; LOT-0046; LOT-0047; LOT-0048; LOT-0049; LOT-0050; LOT-0051; LOT-0052; LOT-0053; LOT-0054; LOT-0055; LOT-0056; LOT-0057; LOT-0058; LOT-0059; LOT-0060; LOT-0061; LOT-0062; LOT-0063; LOT-0064; LOT-0065; LOT-0066; LOT-0067; LOT-0068; LOT-0069; LOT-0070; LOT-0071; LOT-0072; LOT-0073; LOT-0074; LOT-0075; LOT-0076; LOT-0077; LOT-0078; LOT-0079; LOT-0080; LOT-0081\nTêm fundos EU? Não\n\n12 - DOCUMENTOS DE HABILITAÇÃO\nHabilitação para o exercício da atividade profissional: Não\n\n13 - CONDIÇÕES DE APRESENTAÇÃO\nPlataforma eletrónica utilizada pela entidade adjudicante: ACIN\nURL para Apresentação: https://www.acingov.pt\nAdmissibilidade da apresentação de propostas variantes: Não autorizado\nPrazo para apresentação das propostas: 10-01-2026 17:00\nPrazo durante o qual os concorrentes são obrigados a manter as respetivas propostas: 66 dias a contar do termo do prazo para a apresentação das propostas\nIndicação de Subcontratação na Proposta: Inexistência de indicação de subcontratação\n\n14 - PRESTAÇÃO DE CAUÇÃO\nPrestação de caução: Não\n\n15 - FORNECIMENTO DAS PEÇAS DO CONCURSO, APRESENTAÇÃO DE PEDIDOS DE PARTICIPAÇÃO E APRESENTAÇÃO DAS PROPOSTAS\nLink para acesso às peças do concurso (URL): https://www.acingov.pt/acingovprod/2/zonaPublica/zona_publica_c/donwloadProcedurePiece/MTAwMDg4OA==\n\n20 - OUTROS REQUISITOS\nIdentificador do Lote: LOT-0001; LOT-0002; LOT-0003; LOT-0004; LOT-0005; LOT-0006; LOT-0007; LOT-0008; LOT-0009; LOT-0010; LOT-0011; LOT-0012; LOT-0013; LOT-0014; LOT-0015; LOT-0016; LOT-0017; LOT-0018; LOT-0019; LOT-0020; LOT-0021; LOT-0022; LOT-0023; LOT-0024; LOT-0025; LOT-0026; LOT-0027; LOT-0028; LOT-0029; LOT-0030; LOT-0031; LOT-0032; LOT-0033; LOT-0034; LOT-0035; LOT-0036; LOT-0037; LOT-0038; LOT-0039; LOT-0040; LOT-0041; LOT-0042; LOT-0043; LOT-0044; LOT-0045; LOT-0046; LOT-0047; LOT-0048; LOT-0049; LOT-0050; LOT-0051; LOT-0052; LOT-0053; LOT-0054; LOT-0055; LOT-0056; LOT-0057; LOT-0058; LOT-0059; LOT-0060; LOT-0061; LOT-0062; LOT-0063; LOT-0064; LOT-0065; LOT-0066; LOT-0067; LOT-0068; LOT-0069; LOT-0070; LOT-0071; LOT-0072; LOT-0073; LOT-0074; LOT-0075; LOT-0076; LOT-0077; LOT-0078; LOT-0079; LOT-0080; LOT-0081\nInformação sobre contratos reservados. Aplica-se a contratos reservados (54º-A)? Não\n\n21 - CRITÉRIO DE ADJUDICAÇÃO\nO Critério de adjudicação é diferenciado por lote? Não\nMultifator: Não\nMonofator:\nNome: Preço\n\n24 - CONDIÇÕES DO CONTRATO\nIdentificador do Lote: LOT-0001; LOT-0002; LOT-0003; LOT-0004; LOT-0005; LOT-0006; LOT-0007; LOT-0008; LOT-0009; LOT-0010; LOT-0011; LOT-0012; LOT-0013; LOT-0014; LOT-0015; LOT-0016; LOT-0017; LOT-0018; LOT-0019; LOT-0020; LOT-0021; LOT-0022; LOT-0023; LOT-0024; LOT-0025; LOT-0026; LOT-0027; LOT-0028; LOT-0029; LOT-0030; LOT-0031; LOT-0032; LOT-0033; LOT-0034; LOT-0035; LOT-0036; LOT-0037; LOT-0038; LOT-0039; LOT-0040; LOT-0041; LOT-0042; LOT-0043; LOT-0044; LOT-0045; LOT-0046; LOT-0047; LOT-0048; LOT-0049; LOT-0050; LOT-0051; LOT-0052; LOT-0053; LOT-0054; LOT-0055; LOT-0056; LOT-0057; LOT-0058; LOT-0059; LOT-0060; LOT-0061; LOT-0062; LOT-0063; LOT-0064; LOT-0065; LOT-0066; LOT-0067; LOT-0068; LOT-0069; LOT-0070; LOT-0071; LOT-0072; LOT-0073; LOT-0074; LOT-0075; LOT-0076; LOT-0077; LOT-0078; LOT-0079; LOT-0080; LOT-0081\nFaturação Eletrónica: Permitido\nObrigação de Subcontratação:\nCódigo da Obrigação de Subcontratação: Não é aplicável nenhuma obrigação de subcontratação.\n\n25 - COMPRA PÚBLICA ESTRATÉGICA\nCompra Pública Estratégica: Inexistência de contratação pública estratégica\n\n26 - INFORMAÇÕES ADICIONAIS\nIdentificador do Lote: LOT-0001; LOT-0002; LOT-0003; LOT-0004; LOT-0005; LOT-0006; LOT-0007; LOT-0008; LOT-0009; LOT-0010; LOT-0011; LOT-0012; LOT-0013; LOT-0014; LOT-0015; LOT-0016; LOT-0017; LOT-0018; LOT-0019; LOT-0020; LOT-0021; LOT-0022; LOT-0023; LOT-0024; LOT-0025; LOT-0026; LOT-0027; LOT-0028; LOT-0029; LOT-0030; LOT-0031; LOT-0032; LOT-0033; LOT-0034; LOT-0035; LOT-0036; LOT-0037; LOT-0038; LOT-0039; LOT-0040; LOT-0041; LOT-0042; LOT-0043; LOT-0044; LOT-0045; LOT-0046; LOT-0047; LOT-0048; LOT-0049; LOT-0050; LOT-0051; LOT-0052; LOT-0053; LOT-0054; LOT-0055; LOT-0056; LOT-0057; LOT-0058; LOT-0059; LOT-0060; LOT-0061; LOT-0062; LOT-0063; LOT-0064; LOT-0065; LOT-0066; LOT-0067; LOT-0068; LOT-0069; LOT-0070; LOT-0071; LOT-0072; LOT-0073; LOT-0074; LOT-0075; LOT-0076; LOT-0077; LOT-0078; LOT-0079; LOT-0080; LOT-0081\nContrato adequado para PME: Não\nCobertura ACP (Acordo dos Contratos Públicos da Organização Mundial do Comércio): Não\n\n27 - IDENTIFICAÇÃO E CONTACTOS DO ÓRGÃO DE RECURSOS ADMINISTRATIVOS\nDesignação: Conselho de Administração\nEndereço: Avenida Luís de Camões, nº 57\nCódigo postal: 9004-514\nLocalidade: FUNCHAL\nTelefone: 291705610\nFax: \nEndereço eletrónico: aprovisionamento@sesaram.pt\n\n28 - IDENTIFICAÇÃO DO(S) AUTOR(ES) DE ANÚNCIO\nNome: DEBORA EULALIA PEREIRA SANTOS\nCargo: Assistente Técnica\n\n29 - ALTERAÇÃO\nMotivo da Alteração: Informações atualizadas\nIdentificador da Versão do Anúncio a Alterar: b1f9dab8-455c-4a58-b712-cacd04a5897f-01\nIdentificador das Secções Alteradas do Anúncio Anterior: Condições de Apresentação\nDescrição das Alterações: Prorrogação do prazo de entrega das propostas \nAlteração dos Documentos do Concurso: Não\n419934477",
    "nipc": "511228848",
    "distrito": "Região Autónoma da Madeira",
    "concelho": "Funchal",
    "freguesia": "Freguesia de São Pedro (Funchal)",
    "site": "www.sesaram.pt",
    "email": "aprovisionamento@sesaram.pt",
    "designacao_contrato": "NCP20260015 - FIOS SUTURA DE SEDA OU SINTETICOS",
    "descricao": "NCP20260015 - FIOS SUTURA DE SEDA OU SINTETICOS",
    "preco_base": "148.949,50 EUR",
    "prazo_execucao": "12 MESES",
    "prazo_apresentacao_propostas": "10-01-2026 17:00",
    "fundos_eu": "Não",
    "plataforma_eletronica": "ACIN",
    "url_procedimento": "https://www.acingov.pt",
    "autor_nome": "DEBORA EULALIA PEREIRA SANTOS",
    "autor_cargo": "Assistente Técnica"
  },
  {
    "numero_procedimento": "N/A",
    "entidade": "Município de Alcochete",
    "link": "https://diariodarepublica.pt/dr/detalhe/contrato-publico/33517-992908355",
    "detalhes_completos": "Alteração do Anúncio de procedimento n.º 33341/2025, de 2025-12-23, com o ID 419927819\n\n1 - IDENTIFICAÇÃO E CONTACTOS DA ENTIDADE ADJUDICANTE\nDesignação da entidade adjudicante: Município de Alcochete\nNIPC: 506788490\nEndereço: Largo São João. Edifício Paços Concelho\nCódigo postal: 2894-001\nLocalidade: Setúbal\nPaís: Portugal\nNUT III: PT170\nDistrito: Setúbal\nConcelho: Alcochete\nFreguesia: Freguesia de Alcochete\nTelefone: 212348600\nFax: 212348690\nEndereço da Entidade (URL): www.cm-alcochete.pt\nEndereço Eletrónico: geral@cm-alcochete.pt\neDelivery Gateway (URL): https://community.vortal.biz/public/\nFunção da Organização: Adquirente\nNorma jurídica da Entidade Adjudicante: Autoridade local\nÁrea de atividade da Autoridade Adjudicante: Serviços públicos das administrações públicas\n\n2 - JORNAL OFICIAL DA UNIÃO EUROPEIA\nO procedimento a que este anúncio diz respeito também é publicitado no Jornal Oficial da União Europeia? Não\n\n3 - AVISO\nModelo de Anúncio: Concurso público\nData de Envio do Anúncio: 29-12-2025\n\n5 - PROCESSO\nTipo de Procedimento: Concurso público\nPreço base do procedimento: Sim\nValor do preço base do procedimento: 56.319,32 EUR\nProcedimento com lotes? Não\n\n6 - OBJETO DO CONTRATO\nNúmero de referência interna: Proc.º 536/25/CP\nDesignação do contrato: Serviços Combinados de Vigilância e Segurança Humana e de Ligação á Central de Alarmes para Intrusão e Incêndio\nDescrição: Serviços Combinados de Vigilância e Segurança Humana e de Ligação à Central de Alarmes para Intrusão e Incêndio\nTipo de Contrato Principal: Aquisição de Serviços\nTipo de Contrato: Aquisição de Serviços\nClassificação CPV (Vocabulário Comum para os Contratos Públicos)\nObjeto principal\nVocabulário Principal: 79710000\nPreço base s/IVA: 56.319,32 EUR\n\n7 - INDICAÇÕES ADICIONAIS\nO contrato envolve aquisição conjunta (satisfação de várias entidades)? Não\nO contrato é adjudicado por uma central de compras? Não\n\n8 - TÉCNICAS\nO concurso destina-se à celebração de um acordo-quadro? Inexistência de acordo-quadro\nÉ utilizado um leilão eletrónico? Não\nÉ adotada uma fase de negociação? Não\nSistema de Aquisição Dinâmico: Inexistência de sistema de aquisição dinâmico\n\n9 - LOCAL DA EXECUÇÃO DO CONTRATO\nLOCAL DA EXECUÇÃO DO CONTRATO (PROCEDIMENTO)\nPaís: Portugal\nNUT III: PT170\nLocalidade: Setúbal\nDistrito: Setúbal\nConcelho: Alcochete\nFreguesia: Freguesia de Alcochete\n\n10 - PRAZO DE EXECUÇÃO DO CONTRATO\nPrazo de execução do contrato: 11 MESES\nPrevisão de renovações: Não\n\n11 - FUNDOS EU\nTêm fundos EU? Não\n\n12 - DOCUMENTOS DE HABILITAÇÃO\nHabilitação para o exercício da atividade profissional: Não\n\n13 - CONDIÇÕES DE APRESENTAÇÃO\nPlataforma eletrónica utilizada pela entidade adjudicante: VORTAL\nURL para Apresentação: https://community.vortal.biz/public/\nAdmissibilidade da apresentação de propostas variantes: Não autorizado\nPrazo para apresentação das propostas: 05-01-2026 17:00\nPrazo durante o qual os concorrentes são obrigados a manter as respetivas propostas: 90 dias a contar do termo do prazo para a apresentação das propostas\nApresentação de Catálogo Eletrónico: Permitido\nIndicação de Subcontratação na Proposta: Inexistência de indicação de subcontratação\n\n14 - PRESTAÇÃO DE CAUÇÃO\nPrestação de caução: Não\n\n15 - FORNECIMENTO DAS PEÇAS DO CONCURSO, APRESENTAÇÃO DE PEDIDOS DE PARTICIPAÇÃO E APRESENTAÇÃO DAS PROPOSTAS\nLink para acesso às peças do concurso (URL): https://community.vortal.biz/Public/public-tender-documents/bzkvc3RKckVWOFNTYjVrNUkvdWdranUrWVBvM0JycWZxZmJWaDM2RXZsN0t1SEloQUE1ZXZWeDRZRUlIQnhOZzN0TzdKMjc0QUhsZkFQR0U1L21LdHc9PVZXQyZh\n\n20 - OUTROS REQUISITOS\nInformação sobre contratos reservados. Aplica-se a contratos reservados (54º-A)? Não\n\n21 - CRITÉRIO DE ADJUDICAÇÃO\nMultifator: Não\nMonofator:\nNome: Outros\nOutro nome: Preço\n\n24 - CONDIÇÕES DO CONTRATO\nFaturação Eletrónica: Permitido\nObrigação de Subcontratação:\nCódigo da Obrigação de Subcontratação: Não é aplicável nenhuma obrigação de subcontratação.\n\n25 - COMPRA PÚBLICA ESTRATÉGICA\nCompra Pública Estratégica: Inexistência de contratação pública estratégica\n\n26 - INFORMAÇÕES ADICIONAIS\nContrato adequado para PME: Sim\nCobertura ACP (Acordo dos Contratos Públicos da Organização Mundial do Comércio): Não\n\n27 - IDENTIFICAÇÃO E CONTACTOS DO ÓRGÃO DE RECURSOS ADMINISTRATIVOS\nDesignação: Fernando Manuel Gonçalves Pina Pinto\nEndereço: Largo S. João\nCódigo postal: 2894-001\nLocalidade: Alcochete\nTelefone: +351 212348600\nFax: +351 212348691\nEndereço eletrónico: gp@cm-alcochete.pt\n\n28 - IDENTIFICAÇÃO DO(S) AUTOR(ES) DE ANÚNCIO\nNome: Fernando Manuel Gonçalves Pina Pinto\nCargo: Presidente de Câmra\n\n29 - ALTERAÇÃO\nMotivo da Alteração: Correção pelo editor\nIdentificador da Versão do Anúncio a Alterar: 7494319b-8ccc-4735-a828-ccc7384b2436-01\nIdentificador das Secções Alteradas do Anúncio Anterior: Alteração\nAlteração dos Documentos do Concurso: Sim\nData de alteração dos documentos do concurso: 29-12-2025\n419936031",
    "nipc": "506788490",
    "distrito": "Setúbal",
    "concelho": "Alcochete",
    "freguesia": "Freguesia de Alcochete",
    "site": "www.cm-alcochete.pt",
    "email": "geral@cm-alcochete.pt",
    "designacao_contrato": "Serviços Combinados de Vigilância e Segurança Humana e de Ligação á Central de Alarmes para Intrusão e Incêndio",
    "descricao": "Serviços Combinados de Vigilância e Segurança Humana e de Ligação à Central de Alarmes para Intrusão e Incêndio",
    "preco_base": "56.319,32 EUR",
    "prazo_execucao": "11 MESES",
    "prazo_apresentacao_propostas": "05-01-2026 17:00",
    "fundos_eu": "Não",
    "plataforma_eletronica": "VORTAL",
    "url_procedimento": "https://community.vortal.biz/public/",
    "autor_nome": "Fernando Manuel Gonçalves Pina Pinto",
    "autor_cargo": "Presidente de Câmra"
  },
  {
    "numero_procedimento": "N/A",
    "entidade": "Instituto Português de Oncologia do Porto Francisco Gentil, EPE",
    "link": "https://diariodarepublica.pt/dr/detalhe/contrato-publico/33518-992908356",
    "detalhes_completos": "1 - IDENTIFICAÇÃO E CONTACTOS DA ENTIDADE ADJUDICANTE\nDesignação da entidade adjudicante: Instituto Português de Oncologia do Porto Francisco Gentil, EPE\nNIPC: 506362299\nEndereço: Rua Drº António Bernardino De Almeida S/N, Porto\nCódigo postal: 4200-072\nLocalidade: Área Metropolitana do Porto\nPaís: Portugal\nNUT III: PT11A\nDistrito: Porto\nConcelho: Porto\nFreguesia: Todas\nTelefone: 225084000\nFax: 225084001\nEndereço da Entidade (URL): http://www.ipoporto.pt/\nEndereço Eletrónico: compras@ipoporto.min-saude.pt\neDelivery Gateway (URL): https://community.vortal.biz/public/\nFunção da Organização: Adquirente\nNorma jurídica da Entidade Adjudicante: Organismo de direito público\nÁrea de atividade da Autoridade Adjudicante: Saúde\n\n2 - JORNAL OFICIAL DA UNIÃO EUROPEIA\nO procedimento a que este anúncio diz respeito também é publicitado no Jornal Oficial da União Europeia? Não\n\n3 - AVISO\nModelo de Anúncio: Concurso público\nData de Envio do Anúncio: 29-12-2025\n\n5 - PROCESSO\nTipo de Procedimento: Concurso público\nPreço base do procedimento: Sim\nValor do preço base do procedimento: 8.500,00 EUR\nProcedimento com lotes? Não\n\n6 - OBJETO DO CONTRATO\nNúmero de referência interna: CP 4261/25\nDesignação do contrato: CP 4261/25 - Licenciamento de Software Geral e IBM SPSS\nDescrição: CP 4261/25 - Licenciamento de Software Geral e IBM SPSS\nTipo de Contrato Principal: Aquisição de Bens Móveis\nTipo de Contrato: Aquisição de Bens Móveis\nClassificação CPV (Vocabulário Comum para os Contratos Públicos)\nObjeto principal\nVocabulário Principal: 48700000\nPreço base s/IVA: 8.500,00 EUR\n\n7 - INDICAÇÕES ADICIONAIS\nO contrato envolve aquisição conjunta (satisfação de várias entidades)? Não\nO contrato é adjudicado por uma central de compras? Não\n\n8 - TÉCNICAS\nO concurso destina-se à celebração de um acordo-quadro? Inexistência de acordo-quadro\nÉ utilizado um leilão eletrónico? Não\nÉ adotada uma fase de negociação? Não\nSistema de Aquisição Dinâmico: Inexistência de sistema de aquisição dinâmico\n\n9 - LOCAL DA EXECUÇÃO DO CONTRATO\nLOCAL DA EXECUÇÃO DO CONTRATO (PROCEDIMENTO)\nPaís: Portugal\nNUT III: PT11A\nLocalidade: Área Metropolitana do Porto\nDistrito: Porto\nConcelho: Porto\nFreguesia: Freguesia de Paranhos - Porto\n\n10 - PRAZO DE EXECUÇÃO DO CONTRATO\nPrazo de execução do contrato: 120 DIAS\nPrevisão de renovações: Não\n\n11 - FUNDOS EU\nTêm fundos EU? Não\n\n12 - DOCUMENTOS DE HABILITAÇÃO\nHabilitação para o exercício da atividade profissional: Não\n\n13 - CONDIÇÕES DE APRESENTAÇÃO\nPlataforma eletrónica utilizada pela entidade adjudicante: VORTAL\nURL para Apresentação: https://community.vortal.biz/public/\nAdmissibilidade da apresentação de propostas variantes: Não autorizado\nPrazo para apresentação das propostas: 12-01-2026 17:00\nPrazo durante o qual os concorrentes são obrigados a manter as respetivas propostas: 120 dias a contar do termo do prazo para a apresentação das propostas\nIndicação de Subcontratação na Proposta: Inexistência de indicação de subcontratação\n\n14 - PRESTAÇÃO DE CAUÇÃO\nPrestação de caução: Não\n\n15 - FORNECIMENTO DAS PEÇAS DO CONCURSO, APRESENTAÇÃO DE PEDIDOS DE PARTICIPAÇÃO E APRESENTAÇÃO DAS PROPOSTAS\nLink para acesso às peças do concurso (URL): https://community.vortal.biz/Public/public-tender-documents/Z3ZMc2NqZUJaNlJvbnRnV1lZaUtiSzh5aXBKU3ljRnk4UmJPMXJ4TE5TVXk2NzlKYzVrVDh2SEk2SFZzOEYxUGxsZDA2RUZ0NGhLVk5BNHIzVTVpWUE9PTM3U0Zs\n\n20 - OUTROS REQUISITOS\nInformação sobre contratos reservados. Aplica-se a contratos reservados (54º-A)? Não\n\n21 - CRITÉRIO DE ADJUDICAÇÃO\nMultifator: Não\nMonofator:\nNome: Preço\n\n24 - CONDIÇÕES DO CONTRATO\nFaturação Eletrónica: Permitido\nObrigação de Subcontratação:\nCódigo da Obrigação de Subcontratação: Não é aplicável nenhuma obrigação de subcontratação.\n\n25 - COMPRA PÚBLICA ESTRATÉGICA\nCompra Pública Estratégica: Inexistência de contratação pública estratégica\n\n26 - INFORMAÇÕES ADICIONAIS\nContrato adequado para PME: Sim\nCobertura ACP (Acordo dos Contratos Públicos da Organização Mundial do Comércio): Não\n\n27 - IDENTIFICAÇÃO E CONTACTOS DO ÓRGÃO DE RECURSOS ADMINISTRATIVOS\nDesignação: Conselho de Administração\nEndereço: Rua Dr. António Bernardino de Almeida\nCódigo postal: 4200-072\nLocalidade: Porto\nTelefone: +351 225084000\nFax: +351 225084001\nEndereço eletrónico: compras@ipoporto.min-saude.pt\n\n28 - IDENTIFICAÇÃO DO(S) AUTOR(ES) DE ANÚNCIO\nNome: Sandra Luís\nCargo: Diretora do Serviço de Aprovisionamento e Logística\n419930864",
    "nipc": "506362299",
    "distrito": "Porto",
    "concelho": "Porto",
    "freguesia": "Todas",
    "site": "http://www.ipoporto.pt/",
    "email": "compras@ipoporto.min-saude.pt",
    "designacao_contrato": "CP 4261/25 - Licenciamento de Software Geral e IBM SPSS",
    "descricao": "CP 4261/25 - Licenciamento de Software Geral e IBM SPSS",
    "preco_base": "8.500,00 EUR",
    "prazo_execucao": "120 DIAS",
    "prazo_apresentacao_propostas": "12-01-2026 17:00",
    "fundos_eu": "Não",
    "plataforma_eletronica": "VORTAL",
    "url_procedimento": "https://community.vortal.biz/public/",
    "autor_nome": "Sandra Luís",
    "autor_cargo": "Diretora do Serviço de Aprovisionamento e Logística"
  },
  {
    "numero_procedimento": "N/A",
    "entidade": "Santa Casa da Misericórdia de Lisboa",
    "link": "https://diariodarepublica.pt/dr/detalhe/contrato-publico/33521-993031392",
    "detalhes_completos": "1 - IDENTIFICAÇÃO E CONTACTOS DA ENTIDADE ADJUDICANTE\nDesignação da entidade adjudicante: Santa Casa da Misericórdia de Lisboa\nNIPC: 500745471\nServiço/Órgão/Pessoa de contacto: Exma. Mesa\nEndereço: Largo Trindade Coelho\nCódigo postal: 1200-470\nLocalidade: Lisboa\nPaís: Portugal\nNUT III: PT170\nDistrito: Lisboa\nConcelho: Todos\nFreguesia: Todas\nTelefone: 213235000\nFax: 213235013\nEndereço da Entidade (URL): http://www.scml.pt/\nEndereço Eletrónico: compras@scml.pt\neDelivery Gateway (URL): https://www.acingov.pt\nFunção da Organização: Adquirente\nSubfunção da Organização: Organização cujo orçamento é utilizado para pagar o contrato; Organização que executa o pagamento; Organização que fornece informações adicionais sobre o processo de adjudicação; Organização que fornece mais informações sobre os prazos dos procedimentos de recurso; Organização que fornece acesso fora de linha aos documentos do concurso; Organização responsável pelo tratamento das propostas; Organização que recebe as propostas; Organização que trata os pedidos de participação; Organização que recebe pedidos de participação; Organização que fornece mais informações sobre os procedimentos de recurso; Organização que assina o contrato\nNorma jurídica da Entidade Adjudicante: Organismo de direito público, controlado por uma autoridade da administração central\nÁrea de atividade da Autoridade Adjudicante: Proteção social\n\n2 - JORNAL OFICIAL DA UNIÃO EUROPEIA\nO procedimento a que este anúncio diz respeito também é publicitado no Jornal Oficial da União Europeia? Não\n\n3 - AVISO\nModelo de Anúncio: Concurso público\nData de Envio do Anúncio: 29-12-2025\n\n5 - PROCESSO\nTipo de Procedimento: Concurso público\nPreço base do procedimento: Sim\nValor do preço base do procedimento: 31.585,00 EUR\nProcedimento com lotes? Sim\nNº Máx. de Lotes Autorizado: 13\nNúmero máximo de lotes que podem ser adjudicados a um concorrente: 13\n\n6 - OBJETO DO CONTRATO\nNúmero de referência interna: 25DC05CP008\nDesignação do contrato: Aquisição de Detergentes e Desinfetantes de Esterilização\nDescrição: Aquisição de Detergentes e Desinfetantes de Esterilização\nTipo de Contrato Principal: Aquisição de Bens Móveis\nTipo de Contrato: Aquisição de Bens Móveis\nClassificação CPV (Vocabulário Comum para os Contratos Públicos)\nObjeto principal\nVocabulário Principal: 39831200\nPreço base s/IVA: 31.585,00 EUR\nLotes: \nNº: LOT-0001\nDescrição do Lote: Agente de enxaguamento\nPreço base s/IVA: 1.845,00 EUR\nClassificação CPV (Vocabulário Comum para os Contratos Públicos)\nObjeto principal\nVocabulário Principal: 39831200\nNº: LOT-0002\nDescrição do Lote: Desinfetante a frio glutaraldeido a 2%\nPreço base s/IVA: 2.200,00 EUR\nClassificação CPV (Vocabulário Comum para os Contratos Públicos)\nObjeto principal\nVocabulário Principal: 39831200\nNº: LOT-0003\nDescrição do Lote: Desinfetante de superfícies\nPreço base s/IVA: 9.450,00 EUR\nClassificação CPV (Vocabulário Comum para os Contratos Públicos)\nObjeto principal\nVocabulário Principal: 39831200\nNº: LOT-0004\nDescrição do Lote: Detergente ácido e neutralizador\nPreço base s/IVA: 1.210,00 EUR\nClassificação CPV (Vocabulário Comum para os Contratos Públicos)\nObjeto principal\nVocabulário Principal: 39831200\nNº: LOT-0005\nDescrição do Lote: Detergente alcalino (10L)\nPreço base s/IVA: 2.000,00 EUR\nClassificação CPV (Vocabulário Comum para os Contratos Públicos)\nObjeto principal\nVocabulário Principal: 39831200\nNº: LOT-0006\nDescrição do Lote: Detergente alcalino (5L)\nPreço base s/IVA: 8.130,00 EUR\nClassificação CPV (Vocabulário Comum para os Contratos Públicos)\nObjeto principal\nVocabulário Principal: 39831200\nNº: LOT-0007\nDescrição do Lote: Detergente concentrado para remoção de ferrugem\nPreço base s/IVA: 180,00 EUR\nClassificação CPV (Vocabulário Comum para os Contratos Públicos)\nObjeto principal\nVocabulário Principal: 39831200\nNº: LOT-0008\nDescrição do Lote: Detergente de limpeza com ph neutro para ultrassons\nPreço base s/IVA: 1.235,00 EUR\nClassificação CPV (Vocabulário Comum para os Contratos Públicos)\nObjeto principal\nVocabulário Principal: 39831200\nNº: LOT-0009\nDescrição do Lote: Detergente desinfetante manual de instrumentos cirúrgicos termoestáveis e termoláveis\nPreço base s/IVA: 65,00 EUR\nClassificação CPV (Vocabulário Comum para os Contratos Públicos)\nObjeto principal\nVocabulário Principal: 39831200\nNº: LOT-0010\nDescrição do Lote: Detergente manual para instrumentos termoestáveis termoláveis\nPreço base s/IVA: 2.110,00 EUR\nClassificação CPV (Vocabulário Comum para os Contratos Públicos)\nObjeto principal\nVocabulário Principal: 39831200\nNº: LOT-0011\nDescrição do Lote: Detergente para lavagem profunda\nPreço base s/IVA: 185,00 EUR\nClassificação CPV (Vocabulário Comum para os Contratos Públicos)\nObjeto principal\nVocabulário Principal: 39831200\nNº: LOT-0012\nDescrição do Lote: Espuma pré-tratamento de materiais\nPreço base s/IVA: 2.780,00 EUR\nClassificação CPV (Vocabulário Comum para os Contratos Públicos)\nObjeto principal\nVocabulário Principal: 39831200\nNº: LOT-0013\nDescrição do Lote: Lubrificante em spray para instrumentos cirúrgicos e dispositivos médicos\nPreço base s/IVA: 195,00 EUR\nClassificação CPV (Vocabulário Comum para os Contratos Públicos)\nObjeto principal\nVocabulário Principal: 39831200\n\n7 - INDICAÇÕES ADICIONAIS\nO contrato envolve aquisição conjunta (satisfação de várias entidades)? Não\nO contrato é adjudicado por uma central de compras? Não\n\n8 - TÉCNICAS\nO concurso destina-se à celebração de um acordo-quadro? Inexistência de acordo-quadro\nÉ utilizado um leilão eletrónico? Não\nÉ adotada uma fase de negociação? Não\nSistema de Aquisição Dinâmico: Inexistência de sistema de aquisição dinâmico\n\n9 - LOCAL DA EXECUÇÃO DO CONTRATO\nLOCAL DA EXECUÇÃO DO CONTRATO (PROCEDIMENTO)\nPaís: Portugal\nNUT III: PTZZZ\nLocalidade: União das Freguesias de Carcavelos e Parede\nDistrito: Lisboa\nConcelho: Cascais\nFreguesia: União das Freguesias de Carcavelos e Parede\nLOCAL DA EXECUÇÃO DO CONTRATO (LOTE)\nIdentificador do Lote: LOT-0001; LOT-0002; LOT-0003; LOT-0004; LOT-0005; LOT-0006; LOT-0007; LOT-0008; LOT-0009; LOT-0010; LOT-0011; LOT-0012; LOT-0013\nPaís: Portugal\nNUT III: PTZZZ\nLocalidade: União das Freguesias de Carcavelos e Parede\nDistrito: Lisboa\nConcelho: Cascais\nFreguesia: União das Freguesias de Carcavelos e Parede\n\n10 - PRAZO DE EXECUÇÃO DO CONTRATO\nIdentificador do Lote: LOT-0001; LOT-0002; LOT-0003; LOT-0004; LOT-0005; LOT-0006; LOT-0007; LOT-0008; LOT-0009; LOT-0010; LOT-0011; LOT-0012; LOT-0013\nPrazo de execução do contrato: 18 MESES\nPrevisão de renovações: Não\n\n11 - FUNDOS EU\nIdentificador do Lote: LOT-0001; LOT-0002; LOT-0003; LOT-0004; LOT-0005; LOT-0006; LOT-0007; LOT-0008; LOT-0009; LOT-0010; LOT-0011; LOT-0012; LOT-0013\nTêm fundos EU? Não\n\n12 - DOCUMENTOS DE HABILITAÇÃO\nHabilitação para o exercício da atividade profissional: Não\n\n13 - CONDIÇÕES DE APRESENTAÇÃO\nPlataforma eletrónica utilizada pela entidade adjudicante: ACIN\nURL para Apresentação: https://www.acingov.pt\nAdmissibilidade da apresentação de propostas variantes: Não autorizado\nPrazo para apresentação das propostas: 13-01-2026 17:00\nPrazo durante o qual os concorrentes são obrigados a manter as respetivas propostas: 120 dias a contar do termo do prazo para a apresentação das propostas\nIndicação de Subcontratação na Proposta: Inexistência de indicação de subcontratação\n\n14 - PRESTAÇÃO DE CAUÇÃO\nPrestação de caução: Não\n\n15 - FORNECIMENTO DAS PEÇAS DO CONCURSO, APRESENTAÇÃO DE PEDIDOS DE PARTICIPAÇÃO E APRESENTAÇÃO DAS PROPOSTAS\nLink para acesso às peças do concurso (URL): https://www.acingov.pt/acingovprod/2/zonaPublica/zona_publica_c/donwloadProcedurePiece/MTAxMDg1Ng==\n\n20 - OUTROS REQUISITOS\nIdentificador do Lote: LOT-0001; LOT-0002; LOT-0003; LOT-0004; LOT-0005; LOT-0006; LOT-0007; LOT-0008; LOT-0009; LOT-0010; LOT-0011; LOT-0012; LOT-0013\nInformação sobre contratos reservados. Aplica-se a contratos reservados (54º-A)? Não\n\n21 - CRITÉRIO DE ADJUDICAÇÃO\nO Critério de adjudicação é diferenciado por lote? Não\nMultifator: Não\nMonofator:\nNome: Preço\n\n24 - CONDIÇÕES DO CONTRATO\nIdentificador do Lote: LOT-0001; LOT-0002; LOT-0003; LOT-0004; LOT-0005; LOT-0006; LOT-0007; LOT-0008; LOT-0009; LOT-0010; LOT-0011; LOT-0012; LOT-0013\nFaturação Eletrónica: Necessário\nObrigação de Subcontratação:\nCódigo da Obrigação de Subcontratação: Não é aplicável nenhuma obrigação de subcontratação.\n\n25 - COMPRA PÚBLICA ESTRATÉGICA\nCompra Pública Estratégica: Inexistência de contratação pública estratégica\n\n26 - INFORMAÇÕES ADICIONAIS\nIdentificador do Lote: LOT-0001; LOT-0002; LOT-0003; LOT-0004; LOT-0005; LOT-0006; LOT-0007; LOT-0008; LOT-0009; LOT-0010; LOT-0011; LOT-0012; LOT-0013\nContrato adequado para PME: Sim\nCobertura ACP (Acordo dos Contratos Públicos da Organização Mundial do Comércio): Não\n\n27 - IDENTIFICAÇÃO E CONTACTOS DO ÓRGÃO DE RECURSOS ADMINISTRATIVOS\nDesignação: Exma. Mesa da SCML\nEndereço: Largo Trindade Coelho\nCódigo postal: 1200-470\nLocalidade: Lisboa\nTelefone: 213235000\nFax: 213235013\nEndereço eletrónico: dicom.nas@scml.pt\n\n28 - IDENTIFICAÇÃO DO(S) AUTOR(ES) DE ANÚNCIO\nNome: Vanda Simão\nCargo: Diretora da Direção de Compras\n419935813",
    "nipc": "500745471",
    "distrito": "Lisboa",
    "concelho": "Todos",
    "freguesia": "Todas",
    "site": "http://www.scml.pt/",
    "email": "compras@scml.pt",
    "designacao_contrato": "Aquisição de Detergentes e Desinfetantes de Esterilização",
    "descricao": "Aquisição de Detergentes e Desinfetantes de Esterilização",
    "preco_base": "31.585,00 EUR",
    "prazo_execucao": "18 MESES",
    "prazo_apresentacao_propostas": "13-01-2026 17:00",
    "fundos_eu": "Não",
    "plataforma_eletronica": "ACIN",
    "url_procedimento": "https://www.acingov.pt",
    "autor_nome": "Vanda Simão",
    "autor_cargo": "Diretora da Direção de Compras"
  },
  {
    "numero_procedimento": "N/A",
    "entidade": "EMEL - Empresa Municipal de Mobilidade e Estacionamento de Lisboa, EM, SA",
    "link": "https://diariodarepublica.pt/dr/detalhe/contrato-publico/33522-993031393",
    "detalhes_completos": "1 - IDENTIFICAÇÃO E CONTACTOS DA ENTIDADE ADJUDICANTE\nDesignação da entidade adjudicante: EMEL - Empresa Municipal de Mobilidade e Estacionamento de Lisboa, EM, SA\nNIPC: 503311332\nServiço/Órgão/Pessoa de contacto: Contratação Pública\nEndereço: Alameda das Linhas de Torres, nº 198/200\nCódigo postal: 1750-150\nLocalidade: Lisboa\nPaís: Portugal\nNUT III: PT170\nDistrito: Lisboa\nConcelho: Lisboa\nFreguesia: Freguesia de Lumiar\nTelefone: 211163060\nFax: 217813699\nEndereço da Entidade (URL): www.emel.pt\nEndereço Eletrónico: contratacaopublica@emel.pt\neDelivery Gateway (URL): https://www.acingov.pt\nFunção da Organização: Adquirente\nSubfunção da Organização: Organização cujo orçamento é utilizado para pagar o contrato; Organização que executa o pagamento; Organização que fornece informações adicionais sobre o processo de adjudicação; Organização que fornece mais informações sobre os prazos dos procedimentos de recurso; Organização que fornece acesso fora de linha aos documentos do concurso; Organização responsável pelo tratamento das propostas; Organização que recebe as propostas; Organização que trata os pedidos de participação; Organização que recebe pedidos de participação; Organização que fornece mais informações sobre os procedimentos de recurso; Organização que assina o contrato\nNorma jurídica da Entidade Adjudicante: Organismo de direito público\nÁrea de atividade da Autoridade Adjudicante: Serviços públicos das administrações públicas\n\n2 - JORNAL OFICIAL DA UNIÃO EUROPEIA\nO procedimento a que este anúncio diz respeito também é publicitado no Jornal Oficial da União Europeia? Não\n\n3 - AVISO\nModelo de Anúncio: Concurso público\nData de Envio do Anúncio: 29-12-2025\n\n5 - PROCESSO\nTipo de Procedimento: Concurso público\nPreço base do procedimento: Sim\nValor do preço base do procedimento: 74.783,85 EUR\nProcedimento com lotes? Não\n\n6 - OBJETO DO CONTRATO\nNúmero de referência interna: CP 45/2025\nDesignação do contrato: CP 45/2025 - Aquisição de peças para a manutenção e reparação de bloqueadores da EMEL, sob a forma de bolsa\nDescrição: CP 45/2025 - Aquisição de peças para a manutenção e reparação de bloqueadores da EMEL, sob a forma de bolsa\nTipo de Contrato Principal: Aquisição de Bens Móveis\nTipo de Contrato: Aquisição de Bens Móveis\nClassificação CPV (Vocabulário Comum para os Contratos Públicos)\nObjeto principal\nVocabulário Principal: 34324000\nPreço base s/IVA: 74.783,85 EUR\n\n7 - INDICAÇÕES ADICIONAIS\nO contrato envolve aquisição conjunta (satisfação de várias entidades)? Não\nO contrato é adjudicado por uma central de compras? Não\n\n8 - TÉCNICAS\nO concurso destina-se à celebração de um acordo-quadro? Inexistência de acordo-quadro\nÉ utilizado um leilão eletrónico? Não\nÉ adotada uma fase de negociação? Não\nSistema de Aquisição Dinâmico: Inexistência de sistema de aquisição dinâmico\n\n9 - LOCAL DA EXECUÇÃO DO CONTRATO\nLOCAL DA EXECUÇÃO DO CONTRATO (PROCEDIMENTO)\nPaís: Portugal\nNUT III: PT170\nLocalidade: Freguesia de Lumiar\nDistrito: Lisboa\nConcelho: Lisboa\nFreguesia: Freguesia de Lumiar\n\n10 - PRAZO DE EXECUÇÃO DO CONTRATO\nPrazo de execução do contrato: 180 DIAS\nPrevisão de renovações: Não\n\n11 - FUNDOS EU\nTêm fundos EU? Não\n\n12 - DOCUMENTOS DE HABILITAÇÃO\nHabilitação para o exercício da atividade profissional: Não\n\n13 - CONDIÇÕES DE APRESENTAÇÃO\nPlataforma eletrónica utilizada pela entidade adjudicante: ACIN\nURL para Apresentação: https://www.acingov.pt\nAdmissibilidade da apresentação de propostas variantes: Não autorizado\nPrazo para apresentação das propostas: 13-01-2026 23:59\nPrazo durante o qual os concorrentes são obrigados a manter as respetivas propostas: 66 dias a contar do termo do prazo para a apresentação das propostas\nIndicação de Subcontratação na Proposta: A parte do contrato que o proponente tenciona subcontratar\n\n14 - PRESTAÇÃO DE CAUÇÃO\nPrestação de caução: Não\n\n15 - FORNECIMENTO DAS PEÇAS DO CONCURSO, APRESENTAÇÃO DE PEDIDOS DE PARTICIPAÇÃO E APRESENTAÇÃO DAS PROPOSTAS\nLink para acesso às peças do concurso (URL): https://www.acingov.pt/acingovprod/2/zonaPublica/zona_publica_c/donwloadProcedurePiece/MTAxMDkxMw==\n\n20 - OUTROS REQUISITOS\nInformação sobre contratos reservados. Aplica-se a contratos reservados (54º-A)? Não\n\n21 - CRITÉRIO DE ADJUDICAÇÃO\nMultifator: Não\nMonofator:\nNome: Preço\n\n24 - CONDIÇÕES DO CONTRATO\nFaturação Eletrónica: Permitido\nObrigação de Subcontratação:\nCódigo da Obrigação de Subcontratação: O contratante tem de indicar qualquer mudança de subcontratantes durante a execução do contrato.\n\n25 - COMPRA PÚBLICA ESTRATÉGICA\nCompra Pública Estratégica: Inexistência de contratação pública estratégica\n\n26 - INFORMAÇÕES ADICIONAIS\nContrato adequado para PME: Sim\nCobertura ACP (Acordo dos Contratos Públicos da Organização Mundial do Comércio): Não\n\n27 - IDENTIFICAÇÃO E CONTACTOS DO ÓRGÃO DE RECURSOS ADMINISTRATIVOS\nDesignação: Conselho de Administração\nEndereço: Alameda das Linhas de Torres, nº 198/200\nCódigo postal: 1750-150\nLocalidade: Lisboa\nTelefone: 211163060\nFax: 217813699\nEndereço eletrónico: contratacaopublica@emel.pt\nPrazo de interposição do recurso: 5 dias\n\n28 - IDENTIFICAÇÃO DO(S) AUTOR(ES) DE ANÚNCIO\nNome: Jorge Gonçalves\nCargo: Técnico Superior de Contratação Pública\n419936931",
    "nipc": "503311332",
    "distrito": "Lisboa",
    "concelho": "Lisboa",
    "freguesia": "Freguesia de Lumiar",
    "site": "www.emel.pt",
    "email": "contratacaopublica@emel.pt",
    "designacao_contrato": "CP 45/2025 - Aquisição de peças para a manutenção e reparação de bloqueadores da EMEL, sob a forma de bolsa",
    "descricao": "CP 45/2025 - Aquisição de peças para a manutenção e reparação de bloqueadores da EMEL, sob a forma de bolsa",
    "preco_base": "74.783,85 EUR",
    "prazo_execucao": "180 DIAS",
    "prazo_apresentacao_propostas": "13-01-2026 23:59",
    "fundos_eu": "Não",
    "plataforma_eletronica": "ACIN",
    "url_procedimento": "https://www.acingov.pt",
    "autor_nome": "Jorge Gonçalves",
    "autor_cargo": "Técnico Superior de Contratação Pública"
  },
  {
    "numero_procedimento": "N/A",
    "entidade": "Banco de Portugal",
    "link": "https://diariodarepublica.pt/dr/detalhe/contrato-publico/33524-993031421",
    "detalhes_completos": "1 - IDENTIFICAÇÃO E CONTACTOS DA ENTIDADE ADJUDICANTE\nDesignação da entidade adjudicante: Banco de Portugal\nNIPC: 500792771\nEndereço: Rua Francisco Ribeiro, 2\nCódigo postal: 1150-165\nLocalidade: Lisboa\nPaís: Portugal\nNUT III: PT170\nDistrito: Lisboa\nConcelho: Lisboa\nFreguesia: Todas\nTelefone: 213130000\nFax: 213128124\nEndereço da Entidade (URL): www.bportugal.pt\nEndereço Eletrónico: bdp.compras@bportugal.pt\neDelivery Gateway (URL): https://community.vortal.biz/public/\nFunção da Organização: Adquirente\nNorma jurídica da Entidade Adjudicante: Organismo de direito público\nÁrea de atividade da Autoridade Adjudicante: Assuntos económicos\n\n2 - JORNAL OFICIAL DA UNIÃO EUROPEIA\nO procedimento a que este anúncio diz respeito também é publicitado no Jornal Oficial da União Europeia? Não\n\n3 - AVISO\nModelo de Anúncio: Concurso público\nData de Envio do Anúncio: 29-12-2025\n\n5 - PROCESSO\nTipo de Procedimento: Concurso público\nPreço base do procedimento: Sim\nValor do preço base do procedimento: 150.000,00 EUR\nProcedimento com lotes? Não\n\n6 - OBJETO DO CONTRATO\nNúmero de referência interna: OA039525\nDesignação do contrato: Aquisição de serviços de auditoria externa\nDescrição: Aquisição de serviços de auditoria externa\nTipo de Contrato Principal: Aquisição de Serviços\nTipo de Contrato: Aquisição de Serviços\nClassificação CPV (Vocabulário Comum para os Contratos Públicos)\nObjeto principal\nVocabulário Principal: 79212000\nPreço base s/IVA: 150.000,00 EUR\n\n7 - INDICAÇÕES ADICIONAIS\nO contrato envolve aquisição conjunta (satisfação de várias entidades)? Não\nO contrato é adjudicado por uma central de compras? Não\n\n8 - TÉCNICAS\nO concurso destina-se à celebração de um acordo-quadro? Inexistência de acordo-quadro\nÉ utilizado um leilão eletrónico? Não\nÉ adotada uma fase de negociação? Não\nSistema de Aquisição Dinâmico: Inexistência de sistema de aquisição dinâmico\n\n9 - LOCAL DA EXECUÇÃO DO CONTRATO\nLOCAL DA EXECUÇÃO DO CONTRATO (PROCEDIMENTO)\nPaís: Portugal\nNUT III: PT170\nLocalidade: Lisboa\nDistrito: Lisboa\nConcelho: Lisboa\nFreguesia: Todas\n\n10 - PRAZO DE EXECUÇÃO DO CONTRATO\nPrazo de execução do contrato: 3 MESES\nPrevisão de renovações: Não\n\n11 - FUNDOS EU\nTêm fundos EU? Não\n\n12 - DOCUMENTOS DE HABILITAÇÃO\nHabilitação para o exercício da atividade profissional: Não\n\n13 - CONDIÇÕES DE APRESENTAÇÃO\nPlataforma eletrónica utilizada pela entidade adjudicante: VORTAL\nURL para Apresentação: https://community.vortal.biz/public/\nAdmissibilidade da apresentação de propostas variantes: Não autorizado\nPrazo para apresentação das propostas: 13-01-2026 17:00\nPrazo durante o qual os concorrentes são obrigados a manter as respetivas propostas: 120 dias a contar do termo do prazo para a apresentação das propostas\nIndicação de Subcontratação na Proposta: Inexistência de indicação de subcontratação\n\n14 - PRESTAÇÃO DE CAUÇÃO\nPrestação de caução: Não\n\n15 - FORNECIMENTO DAS PEÇAS DO CONCURSO, APRESENTAÇÃO DE PEDIDOS DE PARTICIPAÇÃO E APRESENTAÇÃO DAS PROPOSTAS\nLink para acesso às peças do concurso (URL): https://community.vortal.biz/Public/public-tender-documents/WGdaSFFhY0d6V0pFMTdIL3Z6TnM5RXVCVlRUeUxuMHQwSFVTbHFINC91ZVdhbDVUTzVKQko5UlhkODdvTlM4NmFjVVZBQ3VUWmRXTmpFOVlnUGtmdVE9PXpEbl5e\n\n20 - OUTROS REQUISITOS\nInformação sobre contratos reservados. Aplica-se a contratos reservados (54º-A)? Não\n\n21 - CRITÉRIO DE ADJUDICAÇÃO\nMultifator: Sim\nFator: \nNome: Preço\nPonderação: 30%\nSubfatores: Não\nFator: \nNome: Qualidade\nPonderação: 70%\nSubfatores: Não\n\n24 - CONDIÇÕES DO CONTRATO\nFaturação Eletrónica: Permitido\nObrigação de Subcontratação:\nCódigo da Obrigação de Subcontratação: Não é aplicável nenhuma obrigação de subcontratação.\n\n25 - COMPRA PÚBLICA ESTRATÉGICA\nCompra Pública Estratégica: Inexistência de contratação pública estratégica\n\n26 - INFORMAÇÕES ADICIONAIS\nContrato adequado para PME: Sim\nCobertura ACP (Acordo dos Contratos Públicos da Organização Mundial do Comércio): Não\n\n27 - IDENTIFICAÇÃO E CONTACTOS DO ÓRGÃO DE RECURSOS ADMINISTRATIVOS\nDesignação: Conselho de Administração do Banco de Portugal\nEndereço: Avenida Álvaro Pais, 2\nCódigo postal: 1600-007\nLocalidade: Lisboa\nTelefone: +351 213130000\nFax: +351 213128124\nEndereço eletrónico: bdp.compras@bportugal.pt\n\n28 - IDENTIFICAÇÃO DO(S) AUTOR(ES) DE ANÚNCIO\nNome: DLIAC-FC\nCargo: DLIAC-FC\n419935627",
    "nipc": "500792771",
    "distrito": "Lisboa",
    "concelho": "Lisboa",
    "freguesia": "Todas",
    "site": "www.bportugal.pt",
    "email": "bdp.compras@bportugal.pt",
    "designacao_contrato": "Aquisição de serviços de auditoria externa",
    "descricao": "Aquisição de serviços de auditoria externa",
    "preco_base": "150.000,00 EUR",
    "prazo_execucao": "3 MESES",
    "prazo_apresentacao_propostas": "13-01-2026 17:00",
    "fundos_eu": "Não",
    "plataforma_eletronica": "VORTAL",
    "url_procedimento": "https://community.vortal.biz/public/",
    "autor_nome": "DLIAC-FC",
    "autor_cargo": "DLIAC-FC"
  },
  {
    "numero_procedimento": "N/A",
    "entidade": "Unidade Local de Saúde da Cova da Beira, EPE",
    "link": "https://diariodarepublica.pt/dr/detalhe/contrato-publico/33525-993031457",
    "detalhes_completos": "1 - IDENTIFICAÇÃO E CONTACTOS DA ENTIDADE ADJUDICANTE\nDesignação da entidade adjudicante: Unidade Local de Saúde da Cova da Beira, EPE\nNIPC: 506361659\nEndereço: Quinta do Alvito\nCódigo postal: 6200-251\nLocalidade: Castelo Branco\nPaís: Portugal\nNUT III: PT16J\nDistrito: Castelo Branco\nConcelho: Covilhã\nFreguesia: União das Freguesias de Covilhã e Canhoso\nTelefone: 275330030\nFax: 275330023\nEndereço da Entidade (URL): https://www.chcbeira.min-saude.pt\nEndereço Eletrónico: aprovisionamento@chcbeira.min-saude.pt\neDelivery Gateway (URL): https://community.vortal.biz/public/\nFunção da Organização: Adquirente\nNorma jurídica da Entidade Adjudicante: Organismo de direito público\nÁrea de atividade da Autoridade Adjudicante: Saúde\n\n2 - JORNAL OFICIAL DA UNIÃO EUROPEIA\nO procedimento a que este anúncio diz respeito também é publicitado no Jornal Oficial da União Europeia? Não\n\n3 - AVISO\nModelo de Anúncio: Concurso público urgente\nData de Envio do Anúncio: 29-12-2025 17:51:00\n\n5 - PROCESSO\nTipo de Procedimento: Concurso público\nPreço base do procedimento: Sim\nValor do preço base do procedimento: 72.828,92 EUR\nProcedimento com lotes? Não\n\n6 - OBJETO DO CONTRATO\nNúmero de referência interna: CP 08/2026\nDesignação do contrato: Exames de diagnóstico da Medicina Nuclear\nDescrição: Exames de diagnóstico da Medicina Nuclear\nTipo de Contrato Principal: Aquisição de Serviços\nTipo de Contrato: Aquisição de Serviços\nClassificação CPV (Vocabulário Comum para os Contratos Públicos)\nObjeto principal\nVocabulário Principal: 85100000\nPreço base s/IVA: 72.828,92 EUR\n\n7 - INDICAÇÕES ADICIONAIS\nO contrato envolve aquisição conjunta (satisfação de várias entidades)? Não\nO contrato é adjudicado por uma central de compras? Não\n\n8 - TÉCNICAS\nO concurso destina-se à celebração de um acordo-quadro? Inexistência de acordo-quadro\nÉ utilizado um leilão eletrónico? Não\nÉ adotada uma fase de negociação? Não\nSistema de Aquisição Dinâmico: Inexistência de sistema de aquisição dinâmico\n\n9 - LOCAL DA EXECUÇÃO DO CONTRATO\nLOCAL DA EXECUÇÃO DO CONTRATO (PROCEDIMENTO)\nPaís: Portugal\nNUT III: PT16J\nLocalidade: Castelo Branco\nDistrito: Castelo Branco\nConcelho: Covilhã\nFreguesia: Todas\n\n10 - PRAZO DE EXECUÇÃO DO CONTRATO\nPrazo de execução do contrato: 3 MESES\nPrevisão de renovações: Não\n\n11 - FUNDOS EU\nTêm fundos EU? Não\n\n12 - DOCUMENTOS DE HABILITAÇÃO\nHabilitação para o exercício da atividade profissional: Não\n\n13 - CONDIÇÕES DE APRESENTAÇÃO\nPlataforma eletrónica utilizada pela entidade adjudicante: VORTAL\nURL para Apresentação: https://community.vortal.biz/public/\nAdmissibilidade da apresentação de propostas variantes: Não autorizado\nPrazo para apresentação das propostas: 30-12-2025 17:00\nPrazo durante o qual os concorrentes são obrigados a manter as respetivas propostas: 10 dias a contar do termo do prazo para a apresentação das propostas\nIndicação de Subcontratação na Proposta: Inexistência de indicação de subcontratação\n\n14 - PRESTAÇÃO DE CAUÇÃO\nPrestação de caução: Não\n\n15 - FORNECIMENTO DAS PEÇAS DO CONCURSO, APRESENTAÇÃO DE PEDIDOS DE PARTICIPAÇÃO E APRESENTAÇÃO DAS PROPOSTAS\nLink para acesso às peças do concurso (URL): https://community.vortal.biz/Public/public-tender-documents/Uk5sYStoTjgweisxUVQ1WEdLZFlacHNRc3EveVNrSFlLMWIxOE56elpOVzRETW5ZdXM0QUxkeWNIRHU5QnExODFLL3VQVlQrU3pFVkd1cjFGNzl2SlE9PUZLOXJX\n\n20 - OUTROS REQUISITOS\nInformação sobre contratos reservados. Aplica-se a contratos reservados (54º-A)? Não\n\n21 - CRITÉRIO DE ADJUDICAÇÃO\nMultifator: Não\nMonofator:\nNome: Preço\n\n24 - CONDIÇÕES DO CONTRATO\nFaturação Eletrónica: Permitido\nObrigação de Subcontratação:\nCódigo da Obrigação de Subcontratação: Não é aplicável nenhuma obrigação de subcontratação.\n\n25 - COMPRA PÚBLICA ESTRATÉGICA\nCompra Pública Estratégica: Inexistência de contratação pública estratégica\n\n26 - INFORMAÇÕES ADICIONAIS\nContrato adequado para PME: Sim\nCobertura ACP (Acordo dos Contratos Públicos da Organização Mundial do Comércio): Não\n\n27 - IDENTIFICAÇÃO E CONTACTOS DO ÓRGÃO DE RECURSOS ADMINISTRATIVOS\nDesignação: ULSCBEIRA,EPE\nEndereço: Quinta do Alvito\nCódigo postal: 6200-251\nLocalidade: Covilhã\nTelefone: +351 275330000\nFax: +351 275330001\nEndereço eletrónico: aprovisionamento@ulscbeira.min-saude.pt\n\n28 - IDENTIFICAÇÃO DO(S) AUTOR(ES) DE ANÚNCIO\nNome: Dr. João Pedro Marques Costa\nCargo: Presidente do Conselho de Administração\n419938357",
    "nipc": "506361659",
    "distrito": "Castelo Branco",
    "concelho": "Covilhã",
    "freguesia": "União das Freguesias de Covilhã e Canhoso",
    "site": "https://www.chcbeira.min-saude.pt",
    "email": "aprovisionamento@chcbeira.min-saude.pt",
    "designacao_contrato": "Exames de diagnóstico da Medicina Nuclear",
    "descricao": "Exames de diagnóstico da Medicina Nuclear",
    "preco_base": "72.828,92 EUR",
    "prazo_execucao": "3 MESES",
    "prazo_apresentacao_propostas": "30-12-2025 17:00",
    "fundos_eu": "Não",
    "plataforma_eletronica": "VORTAL",
    "url_procedimento": "https://community.vortal.biz/public/",
    "autor_nome": "Dr. João Pedro Marques Costa",
    "autor_cargo": "Presidente do Conselho de Administração"
  },
  {
    "numero_procedimento": "N/A",
    "entidade": "Município das Caldas da Rainha",
    "link": "https://diariodarepublica.pt/dr/detalhe/contrato-publico/33513-993032323",
    "detalhes_completos": "1 - IDENTIFICAÇÃO E CONTACTOS DA ENTIDADE ADJUDICANTE\nDesignação da entidade adjudicante: Município das Caldas da Rainha\nNIPC: 501222634\nServiço/Órgão/Pessoa de contacto: Município de Caldas da Rainha\nEndereço: PRAÇA 25 DE ABRIL\nCódigo postal: 2500-110\nLocalidade: Leiria\nPaís: Portugal\nNUT III: PT16B\nDistrito: Leiria\nConcelho: Caldas da Rainha\nFreguesia: União das Freguesias de Caldas da Rainha - Nossa Senhora do Pópulo, Coto e São Gregório\nTelefone: 262240000\nFax: 262839729\nEndereço da Entidade (URL): www.mcr.pt\nEndereço Eletrónico: contratacao.publica@mcr.pt\neDelivery Gateway (URL): https://community.vortal.biz/public/\nFunção da Organização: Adquirente\nNorma jurídica da Entidade Adjudicante: Organismo de direito público\nÁrea de atividade da Autoridade Adjudicante: Serviços públicos das administrações públicas\n\n2 - JORNAL OFICIAL DA UNIÃO EUROPEIA\nO procedimento a que este anúncio diz respeito também é publicitado no Jornal Oficial da União Europeia? Não\n\n3 - AVISO\nModelo de Anúncio: Concurso público\nData de Envio do Anúncio: 29-12-2025\n\n5 - PROCESSO\nTipo de Procedimento: Concurso público\nPreço base do procedimento: Sim\nValor do preço base do procedimento: 100.000,00 EUR\nProcedimento com lotes? Não\n\n6 - OBJETO DO CONTRATO\nNúmero de referência interna: CPúblico_16/2025\nDesignação do contrato: Aquisição de Retroescavadora\nDescrição: Aquisição de Retroescavadora\nTipo de Contrato Principal: Aquisição de Bens Móveis\nTipo de Contrato: Aquisição de Bens Móveis\nClassificação CPV (Vocabulário Comum para os Contratos Públicos)\nObjeto principal\nVocabulário Principal: 43251000\nPreço base s/IVA: 100.000,00 EUR\n\n7 - INDICAÇÕES ADICIONAIS\nO contrato envolve aquisição conjunta (satisfação de várias entidades)? Não\nO contrato é adjudicado por uma central de compras? Não\n\n8 - TÉCNICAS\nO concurso destina-se à celebração de um acordo-quadro? Inexistência de acordo-quadro\nÉ utilizado um leilão eletrónico? Não\nÉ adotada uma fase de negociação? Não\nSistema de Aquisição Dinâmico: Inexistência de sistema de aquisição dinâmico\n\n9 - LOCAL DA EXECUÇÃO DO CONTRATO\nLOCAL DA EXECUÇÃO DO CONTRATO (PROCEDIMENTO)\nPaís: Portugal\nNUT III: PT16B\nLocalidade: Leiria\nDistrito: Leiria\nConcelho: Caldas da Rainha\nFreguesia: União das Freguesias de Caldas da Rainha - Nossa Senhora do Pópulo, Coto e São Gregório\n\n10 - PRAZO DE EXECUÇÃO DO CONTRATO\nPrazo de execução do contrato: 180 DIAS\nPrevisão de renovações: Não\n\n11 - FUNDOS EU\nTêm fundos EU? Não\n\n12 - DOCUMENTOS DE HABILITAÇÃO\nHabilitação para o exercício da atividade profissional: Sim\nTipo: Outros\nDescrição - Outros: Conforme art.º 31.º do programa de procedimento\nDescrição: não aplicável\n\n13 - CONDIÇÕES DE APRESENTAÇÃO\nPlataforma eletrónica utilizada pela entidade adjudicante: VORTAL\nURL para Apresentação: https://community.vortal.biz/public/\nAdmissibilidade da apresentação de propostas variantes: Não autorizado\nPrazo para apresentação das propostas: 19-01-2026 23:59\nPrazo durante o qual os concorrentes são obrigados a manter as respetivas propostas: 66 dias a contar do termo do prazo para a apresentação das propostas\nIndicação de Subcontratação na Proposta: Inexistência de indicação de subcontratação\n\n14 - PRESTAÇÃO DE CAUÇÃO\nPrestação de caução: Não\n\n15 - FORNECIMENTO DAS PEÇAS DO CONCURSO, APRESENTAÇÃO DE PEDIDOS DE PARTICIPAÇÃO E APRESENTAÇÃO DAS PROPOSTAS\nLink para acesso às peças do concurso (URL): https://community.vortal.biz/Public/public-tender-documents/czhlNEQwVG5uOUlTT2JiK2phaGdFZjhrckdCb093a1dMNmNXc2NhY0J5d3FyancxMVl5cUNFdmxxS1dRbndlODNsbThGbzNNT0xhRTZNL2FjT2toVGc9PSRhQHZ5\n\n20 - OUTROS REQUISITOS\nInformação sobre contratos reservados. Aplica-se a contratos reservados (54º-A)? Não\n\n21 - CRITÉRIO DE ADJUDICAÇÃO\nMultifator: Não\nMonofator:\nNome: Preço\n\n24 - CONDIÇÕES DO CONTRATO\nFaturação Eletrónica: Permitido\nObrigação de Subcontratação:\nCódigo da Obrigação de Subcontratação: Não é aplicável nenhuma obrigação de subcontratação.\n\n25 - COMPRA PÚBLICA ESTRATÉGICA\nCompra Pública Estratégica: Inexistência de contratação pública estratégica\n\n26 - INFORMAÇÕES ADICIONAIS\nContrato adequado para PME: Sim\nCobertura ACP (Acordo dos Contratos Públicos da Organização Mundial do Comércio): Não\n\n27 - IDENTIFICAÇÃO E CONTACTOS DO ÓRGÃO DE RECURSOS ADMINISTRATIVOS\nDesignação: Município das Caldas da Rainha\nEndereço: Praça 25 de Abril\nCódigo postal: 2500-110\nLocalidade: Caldas da Rainha\nTelefone: +351 262240000\nFax: +351 262839729\nEndereço eletrónico: juridico@mcr.pt\nPrazo de interposição do recurso: 10 dias\n\n28 - IDENTIFICAÇÃO DO(S) AUTOR(ES) DE ANÚNCIO\nNome: Vítor Manuel Calisto Marques\nCargo: Presidente da Câmara Municipal\n419935692",
    "nipc": "501222634",
    "distrito": "Leiria",
    "concelho": "Caldas da Rainha",
    "freguesia": "União das Freguesias de Caldas da Rainha - Nossa Senhora do Pópulo, Coto e São Gregório",
    "site": "www.mcr.pt",
    "email": "contratacao.publica@mcr.pt",
    "designacao_contrato": "Aquisição de Retroescavadora",
    "descricao": "Aquisição de Retroescavadora",
    "preco_base": "100.000,00 EUR",
    "prazo_execucao": "180 DIAS",
    "prazo_apresentacao_propostas": "19-01-2026 23:59",
    "fundos_eu": "Não",
    "plataforma_eletronica": "VORTAL",
    "url_procedimento": "https://community.vortal.biz/public/",
    "autor_nome": "Vítor Manuel Calisto Marques",
    "autor_cargo": "Presidente da Câmara Municipal"
  },
  {
    "numero_procedimento": "N/A",
    "entidade": "Município de Vagos",
    "link": "https://diariodarepublica.pt/dr/detalhe/contrato-publico/33515-993032325",
    "detalhes_completos": "Alteração do Anúncio de procedimento n.º 33085/2025, de 2025-12-22, com o ID 419912752\n\n1 - IDENTIFICAÇÃO E CONTACTOS DA ENTIDADE ADJUDICANTE\nDesignação da entidade adjudicante: Município de Vagos\nNIPC: 506912833\nEndereço: Rua Da Saudade, nº 90\nCódigo postal: 3840-420\nLocalidade: Aveiro\nPaís: Portugal\nNUT III: PT16D\nDistrito: Aveiro\nConcelho: Vagos\nFreguesia: União das Freguesias de Vagos e Santo António\nTelefone: 234799600\nFax: 234799610\nEndereço da Entidade (URL): www.cm-vagos.pt\nEndereço Eletrónico: aprovisionamento@cm-vagos.pt\neDelivery Gateway (URL): https://community.vortal.biz/public/\nFunção da Organização: Adquirente\nNorma jurídica da Entidade Adjudicante: Autoridade local\nÁrea de atividade da Autoridade Adjudicante: Serviços públicos das administrações públicas\n\n2 - JORNAL OFICIAL DA UNIÃO EUROPEIA\nO procedimento a que este anúncio diz respeito também é publicitado no Jornal Oficial da União Europeia? Não\n\n3 - AVISO\nModelo de Anúncio: Concurso público\nData de Envio do Anúncio: 29-12-2025\n\n5 - PROCESSO\nTipo de Procedimento: Concurso público\nPreço base do procedimento: Sim\nValor do preço base do procedimento: 95.760,00 EUR\nProcedimento com lotes? Sim\nNº Máx. de Lotes Autorizado: 2\nNúmero máximo de lotes que podem ser adjudicados a um concorrente: 2\n\n6 - OBJETO DO CONTRATO\nNúmero de referência interna: NAP 04CPN-2025\nDesignação do contrato: Aquisição de serviço de aluguer operacional de viaturas ligeiras, por lotes, na modalidade de Renting.\nDescrição: Aquisição de serviço de aluguer operacional de viaturas ligeiras, por lotes, na modalidade de Renting.\nTipo de Contrato Principal: Locação de Bens Móveis\nTipo de Contrato: Locação de Bens Móveis\nClassificação CPV (Vocabulário Comum para os Contratos Públicos)\nObjeto principal\nVocabulário Principal: 34100000\nPreço base s/IVA: 95.760,00 EUR\nLotes: \nNº: LOT-0001\nDescrição do Lote: Lote 1 – 1 (Uma) Viatura ligeira Tipo SUV Híbrido Plug In (gasolina e elétrico) \nPreço base s/IVA: 28.440,00 EUR\nClassificação CPV (Vocabulário Comum para os Contratos Públicos)\nObjeto principal\nVocabulário Principal: 34100000\nNº: LOT-0002\nDescrição do Lote: Lote 2 – 2 (Duas) Viaturas ligeiras de 9 lugares para transporte de crianças \nPreço base s/IVA: 67.320,00 EUR\nClassificação CPV (Vocabulário Comum para os Contratos Públicos)\nObjeto principal\nVocabulário Principal: 34100000\n\n7 - INDICAÇÕES ADICIONAIS\nO contrato envolve aquisição conjunta (satisfação de várias entidades)? Não\nO contrato é adjudicado por uma central de compras? Não\n\n8 - TÉCNICAS\nO concurso destina-se à celebração de um acordo-quadro? Inexistência de acordo-quadro\nÉ utilizado um leilão eletrónico? Não\nÉ adotada uma fase de negociação? Não\nSistema de Aquisição Dinâmico: Inexistência de sistema de aquisição dinâmico\n\n9 - LOCAL DA EXECUÇÃO DO CONTRATO\nLOCAL DA EXECUÇÃO DO CONTRATO (PROCEDIMENTO)\nPaís: Portugal\nNUT III: PT16D\nLocalidade: Aveiro\nDistrito: Aveiro\nConcelho: Vagos\nFreguesia: União das Freguesias de Vagos e Santo António\nLOCAL DA EXECUÇÃO DO CONTRATO (LOTE)\nIdentificador do Lote: LOT-0001; LOT-0002\nPaís: Portugal\nNUT III: PT16D\nLocalidade: Aveiro\nDistrito: Aveiro\nConcelho: Vagos\nFreguesia: União das Freguesias de Vagos e Santo António\n\n10 - PRAZO DE EXECUÇÃO DO CONTRATO\nIdentificador do Lote: LOT-0001; LOT-0002\nPrazo de execução do contrato: 36 MESES\nPrevisão de renovações: Não\n\n11 - FUNDOS EU\nIdentificador do Lote: LOT-0001; LOT-0002\nTêm fundos EU? Não\n\n12 - DOCUMENTOS DE HABILITAÇÃO\nHabilitação para o exercício da atividade profissional: Não\n\n13 - CONDIÇÕES DE APRESENTAÇÃO\nPlataforma eletrónica utilizada pela entidade adjudicante: VORTAL\nURL para Apresentação: https://community.vortal.biz/public/\nAdmissibilidade da apresentação de propostas variantes: Não autorizado\nPrazo para apresentação das propostas: 12-01-2026 18:00\nPrazo durante o qual os concorrentes são obrigados a manter as respetivas propostas: 66 dias a contar do termo do prazo para a apresentação das propostas\nApresentação de Catálogo Eletrónico: Permitido\nIndicação de Subcontratação na Proposta: Inexistência de indicação de subcontratação\n\n14 - PRESTAÇÃO DE CAUÇÃO\nPrestação de caução: Não\n\n15 - FORNECIMENTO DAS PEÇAS DO CONCURSO, APRESENTAÇÃO DE PEDIDOS DE PARTICIPAÇÃO E APRESENTAÇÃO DAS PROPOSTAS\nLink para acesso às peças do concurso (URL): https://community.vortal.biz/Public/public-tender-documents/WE9pbDhaNHA5aDY3ZStEb29HMytORXJuVHZTSnFnK084M0hWb095TkpEOU8vdFJsU3pwQlVLOG9XcmZlMFllS3dyUEV2bUU3bkhvcktKeDRnYU1rZkE9PUVZSTd1\n\n20 - OUTROS REQUISITOS\nIdentificador do Lote: LOT-0001; LOT-0002\nInformação sobre contratos reservados. Aplica-se a contratos reservados (54º-A)? Não\n\n21 - CRITÉRIO DE ADJUDICAÇÃO\nO Critério de adjudicação é diferenciado por lote? Não\nMultifator: Não\nMonofator:\nNome: Preço\n\n24 - CONDIÇÕES DO CONTRATO\nIdentificador do Lote: LOT-0001; LOT-0002\nFaturação Eletrónica: Permitido\nObrigação de Subcontratação:\nCódigo da Obrigação de Subcontratação: Não é aplicável nenhuma obrigação de subcontratação.\n\n25 - COMPRA PÚBLICA ESTRATÉGICA\nCompra Pública Estratégica: Inexistência de contratação pública estratégica\n\n26 - INFORMAÇÕES ADICIONAIS\nIdentificador do Lote: LOT-0001; LOT-0002\nContrato adequado para PME: Sim\nCobertura ACP (Acordo dos Contratos Públicos da Organização Mundial do Comércio): Não\n\n27 - IDENTIFICAÇÃO E CONTACTOS DO ÓRGÃO DE RECURSOS ADMINISTRATIVOS\nDesignação: Município de Vagos\nEndereço: Rua da Saudade, nº 90\nCódigo postal: 3840-420\nLocalidade: Vagos\nTelefone: +351 234799600\nFax: +351 234799610\nEndereço eletrónico: geral@cm-vagos.pt\n\n28 - IDENTIFICAÇÃO DO(S) AUTOR(ES) DE ANÚNCIO\nNome: Rui Miguel Rocha da Cruz\nCargo: Presidente da Câmara Municipal de Vagos\n\n29 - ALTERAÇÃO\nMotivo da Alteração: Correção pelo adquirente\nIdentificador da Versão do Anúncio a Alterar: fe37a7c1-dc01-4782-a960-1648178f3277-01\nIdentificador das Secções Alteradas do Anúncio Anterior: Alteração\nDescrição das Alterações: Prorrogação do prazo para entrega das propostas.\nAlteração dos Documentos do Concurso: Não\n419935716",
    "nipc": "506912833",
    "distrito": "Aveiro",
    "concelho": "Vagos",
    "freguesia": "União das Freguesias de Vagos e Santo António",
    "site": "www.cm-vagos.pt",
    "email": "aprovisionamento@cm-vagos.pt",
    "designacao_contrato": "Aquisição de serviço de aluguer operacional de viaturas ligeiras, por lotes, na modalidade de Renting.",
    "descricao": "Aquisição de serviço de aluguer operacional de viaturas ligeiras, por lotes, na modalidade de Renting.",
    "preco_base": "95.760,00 EUR",
    "prazo_execucao": "36 MESES",
    "prazo_apresentacao_propostas": "12-01-2026 18:00",
    "fundos_eu": "Não",
    "plataforma_eletronica": "VORTAL",
    "url_procedimento": "https://community.vortal.biz/public/",
    "autor_nome": "Rui Miguel Rocha da Cruz",
    "autor_cargo": "Presidente da Câmara Municipal de Vagos"
  },
  {
    "numero_procedimento": "N/A",
    "entidade": "Instituto Português de Oncologia do Porto Francisco Gentil, EPE",
    "link": "https://diariodarepublica.pt/dr/detalhe/contrato-publico/33516-993032326",
    "detalhes_completos": "1 - IDENTIFICAÇÃO E CONTACTOS DA ENTIDADE ADJUDICANTE\nDesignação da entidade adjudicante: Instituto Português de Oncologia do Porto Francisco Gentil, EPE\nNIPC: 506362299\nEndereço: Rua Drº António Bernardino De Almeida S/N, Porto\nCódigo postal: 4200-072\nLocalidade: Área Metropolitana do Porto\nPaís: Portugal\nNUT III: PT11A\nDistrito: Porto\nConcelho: Porto\nFreguesia: Todas\nTelefone: 225084000\nFax: 225084001\nEndereço da Entidade (URL): http://www.ipoporto.pt/\nEndereço Eletrónico: compras@ipoporto.min-saude.pt\neDelivery Gateway (URL): https://community.vortal.biz/public/\nFunção da Organização: Adquirente\nNorma jurídica da Entidade Adjudicante: Organismo de direito público\nÁrea de atividade da Autoridade Adjudicante: Saúde\n\n2 - JORNAL OFICIAL DA UNIÃO EUROPEIA\nO procedimento a que este anúncio diz respeito também é publicitado no Jornal Oficial da União Europeia? Não\n\n3 - AVISO\nModelo de Anúncio: Concurso público\nData de Envio do Anúncio: 29-12-2025\n\n5 - PROCESSO\nTipo de Procedimento: Concurso público\nPreço base do procedimento: Sim\nValor do preço base do procedimento: 41.500,00 EUR\nProcedimento com lotes? Não\n\n6 - OBJETO DO CONTRATO\nNúmero de referência interna: CP 4449/25\nDesignação do contrato: CP 4449/25 - Assistência Técnica e Subscrição de Balanceadores F5\nDescrição: CP 4449/25 - Assistência Técnica e Subscrição de Balanceadores F5\nTipo de Contrato Principal: Aquisição de Serviços\nTipo de Contrato: Aquisição de Serviços\nClassificação CPV (Vocabulário Comum para os Contratos Públicos)\nObjeto principal\nVocabulário Principal: 72261000\nPreço base s/IVA: 41.500,00 EUR\n\n7 - INDICAÇÕES ADICIONAIS\nO contrato envolve aquisição conjunta (satisfação de várias entidades)? Não\nO contrato é adjudicado por uma central de compras? Não\n\n8 - TÉCNICAS\nO concurso destina-se à celebração de um acordo-quadro? Inexistência de acordo-quadro\nÉ utilizado um leilão eletrónico? Não\nÉ adotada uma fase de negociação? Não\nSistema de Aquisição Dinâmico: Inexistência de sistema de aquisição dinâmico\n\n9 - LOCAL DA EXECUÇÃO DO CONTRATO\nLOCAL DA EXECUÇÃO DO CONTRATO (PROCEDIMENTO)\nPaís: Portugal\nNUT III: PT11A\nLocalidade: Área Metropolitana do Porto\nDistrito: Porto\nConcelho: Porto\nFreguesia: Freguesia de Paranhos - Porto\n\n10 - PRAZO DE EXECUÇÃO DO CONTRATO\nPrazo de execução do contrato: 12 MESES\nPrevisão de renovações: Não\n\n11 - FUNDOS EU\nTêm fundos EU? Não\n\n12 - DOCUMENTOS DE HABILITAÇÃO\nHabilitação para o exercício da atividade profissional: Não\n\n13 - CONDIÇÕES DE APRESENTAÇÃO\nPlataforma eletrónica utilizada pela entidade adjudicante: VORTAL\nURL para Apresentação: https://community.vortal.biz/public/\nAdmissibilidade da apresentação de propostas variantes: Não autorizado\nPrazo para apresentação das propostas: 12-01-2026 17:00\nPrazo durante o qual os concorrentes são obrigados a manter as respetivas propostas: 120 dias a contar do termo do prazo para a apresentação das propostas\nIndicação de Subcontratação na Proposta: Inexistência de indicação de subcontratação\n\n14 - PRESTAÇÃO DE CAUÇÃO\nPrestação de caução: Não\n\n15 - FORNECIMENTO DAS PEÇAS DO CONCURSO, APRESENTAÇÃO DE PEDIDOS DE PARTICIPAÇÃO E APRESENTAÇÃO DAS PROPOSTAS\nLink para acesso às peças do concurso (URL): https://community.vortal.biz/Public/public-tender-documents/aVdQWStBUlBVdSt4ekVaV29pZWhOM1ZmR0llaVE2V0FUbnpKR3hFYk1XcW9mODF4TkVqL1llUDczMEgrQ0lPWERmQ3NLYVl1Q0dQMjBoemZPOHJoaEE9PVhjJTVa\n\n20 - OUTROS REQUISITOS\nInformação sobre contratos reservados. Aplica-se a contratos reservados (54º-A)? Não\n\n21 - CRITÉRIO DE ADJUDICAÇÃO\nMultifator: Não\nMonofator:\nNome: Preço\n\n24 - CONDIÇÕES DO CONTRATO\nFaturação Eletrónica: Permitido\nObrigação de Subcontratação:\nCódigo da Obrigação de Subcontratação: Não é aplicável nenhuma obrigação de subcontratação.\n\n25 - COMPRA PÚBLICA ESTRATÉGICA\nCompra Pública Estratégica: Inexistência de contratação pública estratégica\n\n26 - INFORMAÇÕES ADICIONAIS\nContrato adequado para PME: Sim\nCobertura ACP (Acordo dos Contratos Públicos da Organização Mundial do Comércio): Não\n\n27 - IDENTIFICAÇÃO E CONTACTOS DO ÓRGÃO DE RECURSOS ADMINISTRATIVOS\nDesignação: Conselho de Administração\nEndereço: Rua Dr. António Bernardino de Almeida\nCódigo postal: 4200-072\nLocalidade: Porto\nTelefone: +351 225084000\nFax: +351 225084001\nEndereço eletrónico: compras@ipoporto.min-saude.pt\n\n28 - IDENTIFICAÇÃO DO(S) AUTOR(ES) DE ANÚNCIO\nNome: Sandra Luís\nCargo: Diretora do Serviço de Aprovisionamento e Logística\n419931155",
    "nipc": "506362299",
    "distrito": "Porto",
    "concelho": "Porto",
    "freguesia": "Todas",
    "site": "http://www.ipoporto.pt/",
    "email": "compras@ipoporto.min-saude.pt",
    "designacao_contrato": "CP 4449/25 - Assistência Técnica e Subscrição de Balanceadores F5",
    "descricao": "CP 4449/25 - Assistência Técnica e Subscrição de Balanceadores F5",
    "preco_base": "41.500,00 EUR",
    "prazo_execucao": "12 MESES",
    "prazo_apresentacao_propostas": "12-01-2026 17:00",
    "fundos_eu": "Não",
    "plataforma_eletronica": "VORTAL",
    "url_procedimento": "https://community.vortal.biz/public/",
    "autor_nome": "Sandra Luís",
    "autor_cargo": "Diretora do Serviço de Aprovisionamento e Logística"
  },
  {
    "numero_procedimento": "N/A",
    "entidade": "Município da Figueira da Foz",
    "link": "https://diariodarepublica.pt/dr/detalhe/contrato-publico/33519-993032327",
    "detalhes_completos": "1 - IDENTIFICAÇÃO E CONTACTOS DA ENTIDADE ADJUDICANTE\nDesignação da entidade adjudicante: Município da Figueira da Foz\nNIPC: 501305580\nEndereço: Av. Saraiva De Carvalho\nCódigo postal: 3080-055\nLocalidade: Coimbra\nPaís: Portugal\nNUT III: PT16E\nDistrito: Coimbra\nConcelho: Figueira da Foz\nFreguesia: Freguesia de Buarcos e São Julião\nTelefone: 233403300\nFax: 233403315\nEndereço da Entidade (URL): www.figueiradigital.com\nEndereço Eletrónico: concursos.aprovisionamento@cm-figfoz.pt\neDelivery Gateway (URL): https://community.vortal.biz/public/\nFunção da Organização: Adquirente\nNorma jurídica da Entidade Adjudicante: Autoridade local\nÁrea de atividade da Autoridade Adjudicante: Serviços públicos das administrações públicas\n\n2 - JORNAL OFICIAL DA UNIÃO EUROPEIA\nO procedimento a que este anúncio diz respeito também é publicitado no Jornal Oficial da União Europeia? Não\n\n3 - AVISO\nModelo de Anúncio: Concurso público\nData de Envio do Anúncio: 29-12-2025\n\n5 - PROCESSO\nTipo de Procedimento: Concurso público\nPreço base do procedimento: Sim\nValor do preço base do procedimento: 190.000,00 EUR\nProcedimento com lotes? Não\n\n6 - OBJETO DO CONTRATO\nNúmero de referência interna: CP_42/2025\nDesignação do contrato: Aquisição de serviços de conceção, construção, montagem e desmontagem de dois stands para promoção do território na Feira de Turismo – BTL 2026\nDescrição: Aquisição de serviços de conceção, construção, montagem e desmontagem de dois stands para promoção do território na Feira de Turismo – BTL 2026\nTipo de Contrato Principal: Aquisição de Serviços\nTipo de Contrato: Aquisição de Serviços\nClassificação CPV (Vocabulário Comum para os Contratos Públicos)\nObjeto principal\nVocabulário Principal: 71320000\nPreço base s/IVA: 190.000,00 EUR\n\n7 - INDICAÇÕES ADICIONAIS\nO contrato envolve aquisição conjunta (satisfação de várias entidades)? Não\nO contrato é adjudicado por uma central de compras? Não\n\n8 - TÉCNICAS\nO concurso destina-se à celebração de um acordo-quadro? Inexistência de acordo-quadro\nÉ utilizado um leilão eletrónico? Não\nÉ adotada uma fase de negociação? Não\nSistema de Aquisição Dinâmico: Inexistência de sistema de aquisição dinâmico\n\n9 - LOCAL DA EXECUÇÃO DO CONTRATO\nLOCAL DA EXECUÇÃO DO CONTRATO (PROCEDIMENTO)\nPaís: Portugal\nNUT III: PT16E\nLocalidade: Coimbra\nDistrito: Coimbra\nConcelho: Figueira da Foz\nFreguesia: Freguesia de Buarcos e São Julião\n\n10 - PRAZO DE EXECUÇÃO DO CONTRATO\nPrazo de execução do contrato: 5 DIAS\nPrevisão de renovações: Não\n\n11 - FUNDOS EU\nTêm fundos EU? Não\n\n12 - DOCUMENTOS DE HABILITAÇÃO\nHabilitação para o exercício da atividade profissional: Não\n\n13 - CONDIÇÕES DE APRESENTAÇÃO\nPlataforma eletrónica utilizada pela entidade adjudicante: VORTAL\nURL para Apresentação: https://community.vortal.biz/public/\nAdmissibilidade da apresentação de propostas variantes: Não autorizado\nPrazo para apresentação das propostas: 08-01-2026 23:59\nPrazo durante o qual os concorrentes são obrigados a manter as respetivas propostas: 120 dias a contar do termo do prazo para a apresentação das propostas\nIndicação de Subcontratação na Proposta: Inexistência de indicação de subcontratação\n\n14 - PRESTAÇÃO DE CAUÇÃO\nPrestação de caução: Não\n\n15 - FORNECIMENTO DAS PEÇAS DO CONCURSO, APRESENTAÇÃO DE PEDIDOS DE PARTICIPAÇÃO E APRESENTAÇÃO DAS PROPOSTAS\nLink para acesso às peças do concurso (URL): https://community.vortal.biz/Public/public-tender-documents/M2g3RkpkTWwyN0RoWkIzMTNldUUrSXl6Wm9wOEsvSDJEeEpwZDVuSmxEVFd1TjRZSVNoNUZoQWVzNE9oMkFXRnU3cFVsYU1RYVRhQ0ExMmdiTncxL3c9PU11TWJt\n\n20 - OUTROS REQUISITOS\nInformação sobre contratos reservados. Aplica-se a contratos reservados (54º-A)? Não\n\n21 - CRITÉRIO DE ADJUDICAÇÃO\nMultifator: Sim\nFator: \nNome: Qualidade\nPonderação: 65%\nSubfatores: Não\nFator: \nNome: Preço\nPonderação: 35%\nSubfatores: Não\n\n24 - CONDIÇÕES DO CONTRATO\nFaturação Eletrónica: Permitido\nObrigação de Subcontratação:\nCódigo da Obrigação de Subcontratação: Não é aplicável nenhuma obrigação de subcontratação.\n\n25 - COMPRA PÚBLICA ESTRATÉGICA\nCompra Pública Estratégica: Inexistência de contratação pública estratégica\n\n26 - INFORMAÇÕES ADICIONAIS\nContrato adequado para PME: Sim\nCobertura ACP (Acordo dos Contratos Públicos da Organização Mundial do Comércio): Não\n\n27 - IDENTIFICAÇÃO E CONTACTOS DO ÓRGÃO DE RECURSOS ADMINISTRATIVOS\nDesignação: Município da Figueira da Foz\nEndereço: Av. Saraiva de Carvalho\nCódigo postal: 3080-501\nLocalidade: Figueira da Foz\nTelefone: +351 233403300\nFax: +351 233403300\nEndereço eletrónico: concursos.aprovisonamento@cm-figfoz.pt\n\n28 - IDENTIFICAÇÃO DO(S) AUTOR(ES) DE ANÚNCIO\nNome: Pedro Miguel de Santana Lopes\nCargo: Presidente da Câmara Municipal\n419936891",
    "nipc": "501305580",
    "distrito": "Coimbra",
    "concelho": "Figueira da Foz",
    "freguesia": "Freguesia de Buarcos e São Julião",
    "site": "www.figueiradigital.com",
    "email": "concursos.aprovisionamento@cm-figfoz.pt",
    "designacao_contrato": "Aquisição de serviços de conceção, construção, montagem e desmontagem de dois stands para promoção do território na Feira de Turismo – BTL 2026",
    "descricao": "Aquisição de serviços de conceção, construção, montagem e desmontagem de dois stands para promoção do território na Feira de Turismo – BTL 2026",
    "preco_base": "190.000,00 EUR",
    "prazo_execucao": "5 DIAS",
    "prazo_apresentacao_propostas": "08-01-2026 23:59",
    "fundos_eu": "Não",
    "plataforma_eletronica": "VORTAL",
    "url_procedimento": "https://community.vortal.biz/public/",
    "autor_nome": "Pedro Miguel de Santana Lopes",
    "autor_cargo": "Presidente da Câmara Municipal"
  },
  {
    "numero_procedimento": "N/A",
    "entidade": "Comissão de Coordenação e Desenvolvimento Regional de Lisboa e Vale do Tejo, IP",
    "link": "https://diariodarepublica.pt/dr/detalhe/contrato-publico/33520-993032355",
    "detalhes_completos": "1 - IDENTIFICAÇÃO E CONTACTOS DA ENTIDADE ADJUDICANTE\nDesignação da entidade adjudicante: Comissão de Coordenação e Desenvolvimento Regional de Lisboa e Vale do Tejo, IP\nNIPC: 517622610\nEndereço: Rua Alexandre Herculano, 37\nCódigo postal: 1250-009\nLocalidade: Lisboa\nPaís: Portugal\nNUT III: PTZZZ\nDistrito: Lisboa\nConcelho: Lisboa\nFreguesia: Freguesia de Santo António - Lisboa\nTelefone: 213837100\nFax: 213837192\nEndereço da Entidade (URL): http://www.ccdr-lvt.pt/\nEndereço Eletrónico: geral@ccdr-lvt.pt\nFunção da Organização: Adquirente\nNorma jurídica da Entidade Adjudicante: Organismo de direito público\nÁrea de atividade da Autoridade Adjudicante: Serviços públicos das administrações públicas\n\n2 - JORNAL OFICIAL DA UNIÃO EUROPEIA\nO procedimento a que este anúncio diz respeito também é publicitado no Jornal Oficial da União Europeia? Não\n\n3 - AVISO\nModelo de Anúncio: Concurso público\nData de Envio do Anúncio: 29-12-2025\n\n5 - PROCESSO\nTipo de Procedimento: Concurso público\nPreço base do procedimento: Sim\nValor do preço base do procedimento: 475.279,39 EUR\nProcedimento com lotes? Não\n\n6 - OBJETO DO CONTRATO\nNúmero de referência interna: 29/2025\nDesignação do contrato: Empreitada Reabilitação e Requalificação dos Edifícios e Infraestruturas do Polo de Inovação para a Conservação e Valorização da Diversidade da Videira (Pegões)\nDescrição: Emp. Reabilitação e Requalificação dos Edifícios e Infraestruturas do Polo de Inovação para a Conservação e Valorização da Diversidade da Videira\nTipo de Contrato Principal: Empreitada de Obras Públicas\nTipo de Contrato: Empreitada de Obras Públicas\nClassificação CPV (Vocabulário Comum para os Contratos Públicos)\nObjeto principal\nVocabulário Principal: 45453000\nPreço base s/IVA: 475.279,39 EUR\n\n7 - INDICAÇÕES ADICIONAIS\nO contrato envolve aquisição conjunta (satisfação de várias entidades)? Não\nO contrato é adjudicado por uma central de compras? Não\n\n8 - TÉCNICAS\nO concurso destina-se à celebração de um acordo-quadro? Inexistência de acordo-quadro\nÉ utilizado um leilão eletrónico? Não\nÉ adotada uma fase de negociação? Não\nSistema de Aquisição Dinâmico: Inexistência de sistema de aquisição dinâmico\n\n9 - LOCAL DA EXECUÇÃO DO CONTRATO\nLOCAL DA EXECUÇÃO DO CONTRATO (PROCEDIMENTO)\nPaís: Portugal\nNUT III: PT170\nLocalidade: Pegões\nDistrito: Setúbal\nConcelho: Montijo\nFreguesia: União das Freguesias de Pegões\n\n10 - PRAZO DE EXECUÇÃO DO CONTRATO\nPrazo de execução do contrato: 210 DIAS\nPrevisão de renovações: Não\n\n11 - FUNDOS EU\nTêm fundos EU? Não\n\n12 - DOCUMENTOS DE HABILITAÇÃO\nHabilitação para o exercício da atividade profissional: Sim\nTipo: Alvará\nDescrição: Alvará de empreiteiro de obras públicas ou certificado de empreiteiro de obras públicas emitido pelo Instituto dos Mercados Públicos, do Imobiliário e da Construção, I.P. (IMPIC, I.P.), contendo as seguintes habilitações: 5.ª subcategoria da 1.ª categoria a qual tem de ser de classe que cubra o valor global da proposta e integra-se na categoria em que o tipo de obra se enquadra, de acordo com o estabelecido no artigo 8.º da Lei n.º 41/2015, de 3 de junho e 8.ª subcategoria da 1.ª categoria, em classe correspondente ao valor dos trabalhos especializados a que respeitem. \n\n13 - CONDIÇÕES DE APRESENTAÇÃO\nPlataforma eletrónica utilizada pela entidade adjudicante: ANOGOV\nURL para Apresentação: https://www.anogov.com/op-ccdrlvt/faces/\nAdmissibilidade da apresentação de propostas variantes: Não autorizado\nPrazo para apresentação das propostas: 22-01-2026 23:59\nPrazo durante o qual os concorrentes são obrigados a manter as respetivas propostas: 90 dias a contar do termo do prazo para a apresentação das propostas\nApresentação de Catálogo Eletrónico: Permitido\nIndicação de Subcontratação na Proposta: O(s) subcontratante(s) proposto(s) necessário(s) para cumprir a obrigação de subcontratar uma percentagem mínima do contrato\n\n14 - PRESTAÇÃO DE CAUÇÃO\nPrestação de caução: Não\n\n15 - FORNECIMENTO DAS PEÇAS DO CONCURSO, APRESENTAÇÃO DE PEDIDOS DE PARTICIPAÇÃO E APRESENTAÇÃO DAS PROPOSTAS\nLink para acesso às peças do concurso (URL): https://www.anogov.com/op-ccdrlvt/faces/app/acessoDocs.jsp?codigoAcesso=yLEBBFpvwmxsdrg8694SLE27jaia2MoVooWRF4rB6BS0dC9Vw9\n\n20 - OUTROS REQUISITOS\nInformação sobre contratos reservados. Aplica-se a contratos reservados (54º-A)? Não\n\n21 - CRITÉRIO DE ADJUDICAÇÃO\nMultifator: Não\nMonofator:\nNome: Preço\n\n24 - CONDIÇÕES DO CONTRATO\nFaturação Eletrónica: Permitido\nObrigação de Subcontratação:\nCódigo da Obrigação de Subcontratação: Não é aplicável nenhuma obrigação de subcontratação.\n\n25 - COMPRA PÚBLICA ESTRATÉGICA\nCompra Pública Estratégica: Inexistência de contratação pública estratégica\n\n26 - INFORMAÇÕES ADICIONAIS\nContrato adequado para PME: Não\nCobertura ACP (Acordo dos Contratos Públicos da Organização Mundial do Comércio): Não\n\n27 - IDENTIFICAÇÃO E CONTACTOS DO ÓRGÃO DE RECURSOS ADMINISTRATIVOS\nDesignação: Secretário de Estado do Planeamento e Coesão Territorial\nEndereço: Campus XXI - Av. João XXI, 63\nCódigo postal: 1000-300\nLocalidade: Lisboa\nEndereço eletrónico: gabinete-sepdr@mect.gov.pt\nPrazo de interposição do recurso: 5 dias\n\n28 - IDENTIFICAÇÃO DO(S) AUTOR(ES) DE ANÚNCIO\nNome: Joaquim Francisco Sardinha\nCargo: Vice-Presidente da Comissão de Coordenação e Desenvolvimento Regional de Lisboa e Vale do Tejo, I.P.\n419935805",
    "nipc": "517622610",
    "distrito": "Lisboa",
    "concelho": "Lisboa",
    "freguesia": "Freguesia de Santo António - Lisboa",
    "site": "http://www.ccdr-lvt.pt/",
    "email": "geral@ccdr-lvt.pt",
    "designacao_contrato": "Empreitada Reabilitação e Requalificação dos Edifícios e Infraestruturas do Polo de Inovação para a Conservação e Valorização da Diversidade da Videira (Pegões)",
    "descricao": "Emp. Reabilitação e Requalificação dos Edifícios e Infraestruturas do Polo de Inovação para a Conservação e Valorização da Diversidade da Videira",
    "preco_base": "475.279,39 EUR",
    "prazo_execucao": "210 DIAS",
    "prazo_apresentacao_propostas": "22-01-2026 23:59",
    "fundos_eu": "Não",
    "plataforma_eletronica": "ANOGOV",
    "url_procedimento": "https://www.anogov.com/op-ccdrlvt/faces/",
    "autor_nome": "Joaquim Francisco Sardinha",
    "autor_cargo": "Vice-Presidente da Comissão de Coordenação e Desenvolvimento Regional de Lisboa e Vale do Tejo, I.P."
  },
  {
    "numero_procedimento": "N/A",
    "entidade": "Instituto Português de Oncologia de Lisboa Francisco Gentil, EPE",
    "link": "https://diariodarepublica.pt/dr/detalhe/contrato-publico/33523-993032357",
    "detalhes_completos": "1 - IDENTIFICAÇÃO E CONTACTOS DA ENTIDADE ADJUDICANTE\nDesignação da entidade adjudicante: Instituto Português de Oncologia de Lisboa Francisco Gentil, EPE\nNIPC: 506361616\nEndereço: Rua Profº Lima Basto\nCódigo postal: 1099-023\nLocalidade: Lisboa\nPaís: Portugal\nNUT III: PT170\nDistrito: Lisboa\nConcelho: Lisboa\nFreguesia: Todas\nTelefone: 217229800\nFax: 217229880\nEndereço da Entidade (URL): www.ipolisboa.min-saude.pt/\nEndereço Eletrónico: ipofg@ipolisboa.min-saude.pt\neDelivery Gateway (URL): https://community.vortal.biz/public/\nFunção da Organização: Adquirente\nNorma jurídica da Entidade Adjudicante: Organismo de direito público\nÁrea de atividade da Autoridade Adjudicante: Saúde\n\n2 - JORNAL OFICIAL DA UNIÃO EUROPEIA\nO procedimento a que este anúncio diz respeito também é publicitado no Jornal Oficial da União Europeia? Não\n\n3 - AVISO\nModelo de Anúncio: Concurso público\nData de Envio do Anúncio: 29-12-2025\n\n5 - PROCESSO\nTipo de Procedimento: Concurso público\nPreço base do procedimento: Sim\nValor do preço base do procedimento: 73.500,00 EUR\nProcedimento com lotes? Não\n\n6 - OBJETO DO CONTRATO\nNúmero de referência interna: PN/230/2026\nDesignação do contrato: Aquisição de Serviços de Manutenção e Assistência Técnica à Plataforma da Intranet do IPO Lisboa\nDescrição: Aquisição de Serviços de Manutenção e Assistência Técnica à Plataforma da Intranet do IPO Lisboa\nTipo de Contrato Principal: Aquisição de Serviços\nTipo de Contrato: Aquisição de Serviços\nClassificação CPV (Vocabulário Comum para os Contratos Públicos)\nObjeto principal\nVocabulário Principal: 72611000\nPreço base s/IVA: 73.500,00 EUR\n\n7 - INDICAÇÕES ADICIONAIS\nO contrato envolve aquisição conjunta (satisfação de várias entidades)? Não\nO contrato é adjudicado por uma central de compras? Não\n\n8 - TÉCNICAS\nO concurso destina-se à celebração de um acordo-quadro? Inexistência de acordo-quadro\nÉ utilizado um leilão eletrónico? Não\nÉ adotada uma fase de negociação? Não\nSistema de Aquisição Dinâmico: Inexistência de sistema de aquisição dinâmico\n\n9 - LOCAL DA EXECUÇÃO DO CONTRATO\nLOCAL DA EXECUÇÃO DO CONTRATO (PROCEDIMENTO)\nPaís: Portugal\nNUT III: PT170\nLocalidade: Lisboa\nDistrito: Lisboa\nConcelho: Lisboa\nFreguesia: Freguesia de São Domingos de Benfica\n\n10 - PRAZO DE EXECUÇÃO DO CONTRATO\nPrazo de execução do contrato: 36 MESES\nPrevisão de renovações: Não\n\n11 - FUNDOS EU\nTêm fundos EU? Não\n\n12 - DOCUMENTOS DE HABILITAÇÃO\nHabilitação para o exercício da atividade profissional: Não\n\n13 - CONDIÇÕES DE APRESENTAÇÃO\nPlataforma eletrónica utilizada pela entidade adjudicante: VORTAL\nURL para Apresentação: https://community.vortal.biz/public/\nAdmissibilidade da apresentação de propostas variantes: Não autorizado\nPrazo para apresentação das propostas: 07-01-2026 17:59\nPrazo durante o qual os concorrentes são obrigados a manter as respetivas propostas: 90 dias a contar do termo do prazo para a apresentação das propostas\nIndicação de Subcontratação na Proposta: Inexistência de indicação de subcontratação\n\n14 - PRESTAÇÃO DE CAUÇÃO\nPrestação de caução: Não\n\n15 - FORNECIMENTO DAS PEÇAS DO CONCURSO, APRESENTAÇÃO DE PEDIDOS DE PARTICIPAÇÃO E APRESENTAÇÃO DAS PROPOSTAS\nLink para acesso às peças do concurso (URL): https://community.vortal.biz/Public/public-tender-documents/ODgyT2ZLSk9uWVZZVXF2TnVSUXJyVWxxQ2Y5ZjZ5L09JbzJZT2dIWGFYVDg5ekE1RTdYM2ZwM1JocU5wQXhDYVFFemhEL1FnQ0NpcHVDK2tRVmdQYUE9PWdYT3Rr\n\n20 - OUTROS REQUISITOS\nInformação sobre contratos reservados. Aplica-se a contratos reservados (54º-A)? Não\n\n21 - CRITÉRIO DE ADJUDICAÇÃO\nMultifator: Não\nMonofator:\nNome: Preço\n\n24 - CONDIÇÕES DO CONTRATO\nFaturação Eletrónica: Permitido\nObrigação de Subcontratação:\nCódigo da Obrigação de Subcontratação: Não é aplicável nenhuma obrigação de subcontratação.\n\n25 - COMPRA PÚBLICA ESTRATÉGICA\nCompra Pública Estratégica: Inexistência de contratação pública estratégica\n\n26 - INFORMAÇÕES ADICIONAIS\nContrato adequado para PME: Sim\nCobertura ACP (Acordo dos Contratos Públicos da Organização Mundial do Comércio): Não\n\n27 - IDENTIFICAÇÃO E CONTACTOS DO ÓRGÃO DE RECURSOS ADMINISTRATIVOS\nDesignação: Conselho de Administração\nEndereço: Rua Prof. Lima Basto\nCódigo postal: 1099-023\nLocalidade: Lisboa\nTelefone: +351 217229800\nFax: +351 217229880\nEndereço eletrónico: ipofg@ipolisboa.min-saude.pt\n\n28 - IDENTIFICAÇÃO DO(S) AUTOR(ES) DE ANÚNCIO\nNome: Ricardo Costa \nCargo: Técnico Superior\n419935854",
    "nipc": "506361616",
    "distrito": "Lisboa",
    "concelho": "Lisboa",
    "freguesia": "Todas",
    "site": "www.ipolisboa.min-saude.pt/",
    "email": "ipofg@ipolisboa.min-saude.pt",
    "designacao_contrato": "Aquisição de Serviços de Manutenção e Assistência Técnica à Plataforma da Intranet do IPO Lisboa",
    "descricao": "Aquisição de Serviços de Manutenção e Assistência Técnica à Plataforma da Intranet do IPO Lisboa",
    "preco_base": "73.500,00 EUR",
    "prazo_execucao": "36 MESES",
    "prazo_apresentacao_propostas": "07-01-2026 17:59",
    "fundos_eu": "Não",
    "plataforma_eletronica": "VORTAL",
    "url_procedimento": "https://community.vortal.biz/public/",
    "autor_nome": "Ricardo Costa",
    "autor_cargo": "Técnico Superior"
  }
]