[
  {
    "numero_procedimento": "N/A",
    "entidade": "AnÃºncio de procedimento  n.Âº 380/2026  -  DiÃ¡rio da RepÃºblica n.Âº 6/2026, SÃ©rie II de 2026-01-09",
    "link": "https://diariodarepublica.pt/dr/detalhe/contrato-publico/380-1002139957"
  },
  {
    "numero_procedimento": "N/A",
    "entidade": "AnÃºncio de procedimento  n.Âº 381/2026  -  DiÃ¡rio da RepÃºblica n.Âº 6/2026, SÃ©rie II de 2026-01-09",
    "link": "https://diariodarepublica.pt/dr/detalhe/contrato-publico/381-1002139960"
  },
  {
    "numero_procedimento": "N/A",
    "entidade": "AnÃºncio de procedimento  n.Âº 382/2026  -  DiÃ¡rio da RepÃºblica n.Âº 6/2026, SÃ©rie II de 2026-01-09",
    "link": "https://diariodarepublica.pt/dr/detalhe/contrato-publico/382-1002139963"
  },
  {
    "numero_procedimento": "N/A",
    "entidade": "Infraestruturas de Portugal, SA",
    "link": "https://diariodarepublica.pt/dr/detalhe/contrato-publico/389-1002139968",
    "detalhes_completos": "1 - IDENTIFICAÇÃO E CONTACTOS DA ENTIDADE ADJUDICANTE\nDesignação da entidade adjudicante: Infraestruturas de Portugal, SA\nNIPC: 503933813\nServiço/Órgão/Pessoa de contacto: Direção de Compras e Logística - Departamento de Compras - Edifício 2\nEndereço: Praça da Portagem\nCódigo postal: 2809-013\nLocalidade: Almada\nPaís: Portugal\nNUT III: PT170\nDistrito: Setúbal\nConcelho: Almada\nFreguesia: União das Freguesias de Almada, Cova da Piedade, Pragal e Cacilhas\nTelefone:  212 879 300 \nFax: 21 287 90 00\nEndereço da Entidade (URL): www.infraestruturasdeportugal.pt\nEndereço Eletrónico: dcl@infraestruturasdeportugal.pt\nFunção da Organização: Adquirente\nNorma jurídica da Entidade Adjudicante: Organismo de direito público\nÁrea de atividade da Entidade Adjudicante: Serviços ferroviários\n2 - JORNAL OFICIAL DA UNIÃO EUROPEIA\nO procedimento a que este anúncio diz respeito também é publicitado no Jornal Oficial da União Europeia? Não\n3 - AVISO\nModelo de Anúncio: Concurso público\nData de Envio do Anúncio: 08-01-2026\n5 - PROCESSO\nTipo de Procedimento: Concurso público\nPreço base do procedimento: Sim\nValor do preço base do procedimento: 39.940,00 EUR\nProcedimento com lotes? Não\n6 - OBJETO DO CONTRATO\nNúmero de referência interna: 10021854\nDesignação do contrato: Aquisição de comando manual \nDescrição: Aquisição de comando manual \nTipo de Contrato Principal: Aquisição de Bens Móveis\nTipo de Contrato: Aquisição de Bens Móveis\nClassificação CPV (Vocabulário Comum para os Contratos Públicos)\nObjeto principal\nVocabulário Principal: 34946120\nPreço base s/IVA: 39.940,00 EUR\n7 - INDICAÇÕES ADICIONAIS\nO contrato envolve aquisição conjunta (satisfação de várias entidades)? Não\nO contrato é adjudicado por uma central de compras? Não\n8 - TÉCNICAS\nO concurso destina-se à celebração de um acordo-quadro? Inexistência de acordo-quadro\nÉ utilizado um leilão eletrónico? Não\nÉ adotada uma fase de negociação? Não\nSistema de Aquisição Dinâmico: Inexistência de sistema de aquisição dinâmico\n9 - LOCAL DA EXECUÇÃO DO CONTRATO\nLOCAL DA EXECUÇÃO DO CONTRATO (PROCEDIMENTO)\nPaís: Portugal\nNUT III: PT16I\nLocalidade: Entroncamento\nDistrito: Santarém\nConcelho: Entroncamento\nFreguesia: Freguesia de Nossa Senhora de Fátima - Entroncamento\n10 - PRAZO DE EXECUÇÃO DO CONTRATO\nPrazo de execução do contrato: 150 DIAS\nPrevisão de renovações: Não\n11 - FUNDOS EU\nTêm fundos EU? Não\n12 - DOCUMENTOS DE HABILITAÇÃO\nHabilitação para o exercício da atividade profissional: Não\n13 - CONDIÇÕES DE APRESENTAÇÃO\nPlataforma eletrónica utilizada pela entidade adjudicante: ANOGOV\nURL para Apresentação: https://www.anogov.com/infraestruturasdeportugal-ip/faces/\nAdmissibilidade da apresentação de propostas variantes: Não autorizado\nPrazo para apresentação das propostas: 12-02-2026 17:00\nPrazo durante o qual os concorrentes são obrigados a manter as respetivas propostas: 120 dias a contar do termo do prazo para a apresentação das propostas\nApresentação de Catálogo Eletrónico: Não autorizado\nIndicação de Subcontratação na Proposta: Inexistência de indicação de subcontratação\n14 - PRESTAÇÃO DE CAUÇÃO\nPrestação de caução: Não\n15 - FORNECIMENTO DAS PEÇAS DO CONCURSO, APRESENTAÇÃO DE PEDIDOS DE PARTICIPAÇÃO E APRESENTAÇÃO DAS PROPOSTAS\nLink para acesso às peças do concurso (URL): https://www.anogov.com/infraestruturasdeportugal-ip/faces/app/acessoDocs.jsp?codigoAcesso=zRttRGYPskoajpzNu3Y24n6P3IulM5V6yJz3dyvEWO2fxrJ7Bn\n20 - OUTROS REQUISITOS\nInformação sobre contratos reservados. Aplica-se a contratos reservados (54º-A)? Não\n21 - CRITÉRIO DE ADJUDICAÇÃO\nMultifator: Não\nMonofator:\nNome: Preço\n24 - CONDIÇÕES DO CONTRATO\nFaturação Eletrónica: Permitido\nObrigação de Subcontratação:\nCódigo da Obrigação de Subcontratação: Não é aplicável nenhuma obrigação de subcontratação.\n25 - COMPRA PÚBLICA ESTRATÉGICA\nCompra Pública Estratégica: Inexistência de contratação pública estratégica\n26 - INFORMAÇÕES ADICIONAIS\nContrato adequado para PME: Sim\nCobertura ACP (Acordo dos Contratos Públicos da Organização Mundial do Comércio): Não\n27 - IDENTIFICAÇÃO E CONTACTOS DO ÓRGÃO DE RECURSOS ADMINISTRATIVOS\nDesignação: Conselho de Administração Executivo da Infraestruturas de Portugal, S.A.\nEndereço: Praça da Portagem\nCódigo postal: 2809-013\nLocalidade: Almada\nTelefone: 212879000\nFax: \nEndereço eletrónico: contratos@infraestruturasdeportugal.pt\n28 - IDENTIFICAÇÃO DO(S) AUTOR(ES) DE ANÚNCIO\nNome: Margarida Veloso\nCargo: Diretora Adjunta da Direção de Compras e Logística\n419947488",
    "nipc": "503933813",
    "distrito": "Setúbal",
    "concelho": "Almada",
    "freguesia": "União das Freguesias de Almada, Cova da Piedade, Pragal e Cacilhas",
    "site": "www.infraestruturasdeportugal.pt",
    "email": "dcl@infraestruturasdeportugal.pt",
    "designacao_contrato": "Aquisição de comando manual",
    "descricao": "Aquisição de comando manual",
    "preco_base": "39.940,00 EUR",
    "prazo_execucao": "150 DIAS",
    "prazo_apresentacao_propostas": "12-02-2026 17:00",
    "fundos_eu": "Não",
    "plataforma_eletronica": "ANOGOV",
    "url_procedimento": "https://www.anogov.com/infraestruturasdeportugal-ip/faces/",
    "autor_nome": "Margarida Veloso",
    "autor_cargo": "Diretora Adjunta da Direção de Compras e Logística"
  },
  {
    "numero_procedimento": "N/A",
    "entidade": "Centro Formação Profissional Indústria de Cortiça",
    "link": "https://diariodarepublica.pt/dr/detalhe/contrato-publico/393-1002139970",
    "detalhes_completos": "1 - IDENTIFICAÇÃO E CONTACTOS DA ENTIDADE ADJUDICANTE\nDesignação da entidade adjudicante: Centro Formação Profissional Indústria de Cortiça\nNIPC: 900220538\nEndereço: Rua Alto do Picão n.º 415\nCódigo postal: 4535-393\nLocalidade: Santa Maria de Lamas\nPaís: Portugal\nNUT III: PT11A\nDistrito: Aveiro\nConcelho: Santa Maria da Feira\nFreguesia: Freguesia de Santa Maria de Lamas\nTelefone: 227471200\nFax: 227471209\nEndereço da Entidade (URL): http://www.cincork.com\nEndereço Eletrónico: geral@cincork.com\nFunção da Organização: Adquirente\nNorma jurídica da Entidade Adjudicante: Organismo de direito público\nÁrea de atividade da Autoridade Adjudicante: Educação\n2 - JORNAL OFICIAL DA UNIÃO EUROPEIA\nO procedimento a que este anúncio diz respeito também é publicitado no Jornal Oficial da União Europeia? Não\n3 - AVISO\nModelo de Anúncio: Concurso público\nData de Envio do Anúncio: 08-01-2026\n5 - PROCESSO\nTipo de Procedimento: Concurso público\nPreço base do procedimento: Sim\nValor do preço base do procedimento: 275.090,00 EUR\nProcedimento com lotes? Sim\nNº Máx. de Lotes Autorizado: 4\nNúmero máximo de lotes que podem ser adjudicados a um concorrente: 4\n6 - OBJETO DO CONTRATO\nNúmero de referência interna: CPBL2601\nDesignação do contrato: CPBL2601 - SISTEMA DE PRODUÇÃO DE BLOCOS E ROLHAS AGLOMERADAS DE CORTIÇA\nDescrição: CPBL2601 - SISTEMA DE PRODUÇÃO DE BLOCOS E ROLHAS AGLOMERADAS DE CORTIÇA\nTipo de Contrato Principal: Aquisição de Bens Móveis\nTipo de Contrato: Aquisição de Bens Móveis\nClassificação CPV (Vocabulário Comum para os Contratos Públicos)\nObjeto principal\nVocabulário Principal: 42642300\nPreço base s/IVA: 275.090,00 EUR\nLotes: \nNº: LOT-0001\nDescrição do Lote: Lote 1- Conjunto de aglomeração para rolhas e peças de cortiça e materiais aglomerados incluindo respetivos equipamentos de suporte\nPreço base s/IVA: 184.590,00 EUR\nClassificação CPV (Vocabulário Comum para os Contratos Públicos)\nObjeto principal\nVocabulário Principal: 42642300\nNº: LOT-0002\nDescrição do Lote: Lote 2 - Máquina Serra de Fita \nPreço base s/IVA: 11.000,00 EUR\nClassificação CPV (Vocabulário Comum para os Contratos Públicos)\nObjeto principal\nVocabulário Principal: 42642300\nNº: LOT-0003\nDescrição do Lote: Lote 3 - Máquina Laminadora de Cortiça \nPreço base s/IVA: 21.500,00 EUR\nClassificação CPV (Vocabulário Comum para os Contratos Públicos)\nObjeto principal\nVocabulário Principal: 42642300\nNº: LOT-0004\nDescrição do Lote: Lote 4 - Máquina Lixadora para Cortiça \nPreço base s/IVA: 58.000,00 EUR\nClassificação CPV (Vocabulário Comum para os Contratos Públicos)\nObjeto principal\nVocabulário Principal: 42642300\n7 - INDICAÇÕES ADICIONAIS\nO contrato envolve aquisição conjunta (satisfação de várias entidades)? Não\nO contrato é adjudicado por uma central de compras? Não\n8 - TÉCNICAS\nO concurso destina-se à celebração de um acordo-quadro? Inexistência de acordo-quadro\nÉ utilizado um leilão eletrónico? Não\nÉ adotada uma fase de negociação? Não\nSistema de Aquisição Dinâmico: Inexistência de sistema de aquisição dinâmico\n9 - LOCAL DA EXECUÇÃO DO CONTRATO\nLOCAL DA EXECUÇÃO DO CONTRATO (PROCEDIMENTO)\nLOCAL DA EXECUÇÃO DO CONTRATO (LOTE)\nIdentificador do Lote: LOT-0001\nPaís: Portugal\nNUT III: PT11A\nLocalidade: Santa Maria de Lamas\nDistrito: Aveiro\nConcelho: Santa Maria da Feira\nFreguesia: Freguesia de Santa Maria de Lamas\nIdentificador do Lote: LOT-0002\nPaís: Portugal\nNUT III: PT11A\nLocalidade: Santa Maria de Lamas\nDistrito: Aveiro\nConcelho: Santa Maria da Feira\nFreguesia: Freguesia de Santa Maria de Lamas\nIdentificador do Lote: LOT-0003\nPaís: Portugal\nNUT III: PT11A\nLocalidade: Santa Maria de Lamas\nDistrito: Aveiro\nConcelho: Santa Maria da Feira\nFreguesia: Freguesia de Santa Maria de Lamas\nIdentificador do Lote: LOT-0004\nPaís: Portugal\nNUT III: PT11A\nLocalidade: Santa Maria de Lamas\nDistrito: Aveiro\nConcelho: Santa Maria da Feira\nFreguesia: Freguesia de Santa Maria de Lamas\n10 - PRAZO DE EXECUÇÃO DO CONTRATO\nIdentificador do Lote: LOT-0001\nPrazo de execução do contrato: 50 DIAS\nPrevisão de renovações: Não\nIdentificador do Lote: LOT-0002\nPrazo de execução do contrato: 50 DIAS\nPrevisão de renovações: Não\nIdentificador do Lote: LOT-0003\nPrazo de execução do contrato: 50 DIAS\nPrevisão de renovações: Não\nIdentificador do Lote: LOT-0004\nPrazo de execução do contrato: 50 DIAS\nPrevisão de renovações: Não\n11 - FUNDOS EU\nIdentificador do Lote: LOT-0001; LOT-0002; LOT-0003; LOT-0004\nTêm fundos EU? Não\n12 - DOCUMENTOS DE HABILITAÇÃO\nHabilitação para o exercício da atividade profissional: Não\n13 - CONDIÇÕES DE APRESENTAÇÃO\nPlataforma eletrónica utilizada pela entidade adjudicante: COMPRASPT\nURL para Apresentação: https://www.compraspt.com/cpt-cincork/faces/\nAdmissibilidade da apresentação de propostas variantes: Não autorizado\nPrazo para apresentação das propostas: 20-01-2026 23:30\nPrazo durante o qual os concorrentes são obrigados a manter as respetivas propostas: 66 dias a contar do termo do prazo para a apresentação das propostas\nApresentação de Catálogo Eletrónico: Permitido\nIndicação de Subcontratação na Proposta: A parte do contrato que o proponente tenciona subcontratar\n14 - PRESTAÇÃO DE CAUÇÃO\nPrestação de caução: Não\n15 - FORNECIMENTO DAS PEÇAS DO CONCURSO, APRESENTAÇÃO DE PEDIDOS DE PARTICIPAÇÃO E APRESENTAÇÃO DAS PROPOSTAS\nLink para acesso às peças do concurso (URL): https://www.compraspt.com/cpt-cincork/faces/app/acessoDocs.jsp?codigoAcesso=6GzEhBi9JX1UvydDJ6itkdAs7Ld2lynTYSQAv95uG2mz6zEMDK\n20 - OUTROS REQUISITOS\nIdentificador do Lote: LOT-0001; LOT-0002; LOT-0003; LOT-0004\nInformação sobre contratos reservados. Aplica-se a contratos reservados (54º-A)? Não\n21 - CRITÉRIO DE ADJUDICAÇÃO\nO Critério de adjudicação é diferenciado por lote? Não\nMultifator: Sim\nFator: \nNome: Preço\nPonderação: 80%\nSubfatores: Não\nFator: \nNome: Outros\nOutro Nome: Prazo de entrega e instalação\nPonderação: 20%\nSubfatores: Não\n24 - CONDIÇÕES DO CONTRATO\nIdentificador do Lote: LOT-0001; LOT-0002; LOT-0003; LOT-0004\nFaturação Eletrónica: Permitido\nObrigação de Subcontratação:\nCódigo da Obrigação de Subcontratação: Não é aplicável nenhuma obrigação de subcontratação.\n25 - COMPRA PÚBLICA ESTRATÉGICA\nCompra Pública Estratégica: Inexistência de contratação pública estratégica\n26 - INFORMAÇÕES ADICIONAIS\nIdentificador do Lote: LOT-0001\nContrato adequado para PME: Sim\nCobertura ACP (Acordo dos Contratos Públicos da Organização Mundial do Comércio): Não\nIdentificador do Lote: LOT-0002\nContrato adequado para PME: Sim\nCobertura ACP (Acordo dos Contratos Públicos da Organização Mundial do Comércio): Não\nIdentificador do Lote: LOT-0003\nContrato adequado para PME: Sim\nCobertura ACP (Acordo dos Contratos Públicos da Organização Mundial do Comércio): Não\nIdentificador do Lote: LOT-0004\nContrato adequado para PME: Sim\nCobertura ACP (Acordo dos Contratos Públicos da Organização Mundial do Comércio): Não\n27 - IDENTIFICAÇÃO E CONTACTOS DO ÓRGÃO DE RECURSOS ADMINISTRATIVOS\nDesignação: Conselho de Administração\nEndereço: Rua Alto do Picão n.º 415\nCódigo postal: 4535-393\nLocalidade: Santa Maria de Lamas\nTelefone: 227471200\nFax: \nEndereço eletrónico: ca@cincork.com\nPrazo de interposição do recurso: 5 dias\n28 - IDENTIFICAÇÃO DO(S) AUTOR(ES) DE ANÚNCIO\nNome: Cristina Rodrigues\nCargo: Presidente do Conselho de Administração\n419947526",
    "nipc": "900220538",
    "distrito": "Aveiro",
    "concelho": "Santa Maria da Feira",
    "freguesia": "Freguesia de Santa Maria de Lamas",
    "site": "http://www.cincork.com",
    "email": "geral@cincork.com",
    "designacao_contrato": "CPBL2601 - SISTEMA DE PRODUÇÃO DE BLOCOS E ROLHAS AGLOMERADAS DE CORTIÇA",
    "descricao": "CPBL2601 - SISTEMA DE PRODUÇÃO DE BLOCOS E ROLHAS AGLOMERADAS DE CORTIÇA",
    "preco_base": "275.090,00 EUR",
    "prazo_execucao": "50 DIAS",
    "prazo_apresentacao_propostas": "20-01-2026 23:30",
    "fundos_eu": "Não",
    "plataforma_eletronica": "COMPRASPT",
    "url_procedimento": "https://www.compraspt.com/cpt-cincork/faces/",
    "autor_nome": "Cristina Rodrigues",
    "autor_cargo": "Presidente do Conselho de Administração"
  },
  {
    "numero_procedimento": "N/A",
    "entidade": "Cooptécnica - Gustave Eiffel, Cooperativa de Ensino e Formação Técnico Profissional, CRL",
    "link": "https://diariodarepublica.pt/dr/detalhe/contrato-publico/395-1002139971",
    "detalhes_completos": "1 - IDENTIFICAÇÃO E CONTACTOS DA ENTIDADE ADJUDICANTE\nDesignação da entidade adjudicante: Cooptécnica - Gustave Eiffel, Cooperativa de Ensino e Formação Técnico Profissional, CRL\nNIPC: 502327669\nEndereço: Rua Elias Garcia, nº 29, Amadora\nCódigo postal: 2700-312\nLocalidade: Lisboa\nPaís: Portugal\nNUT III: PT170\nDistrito: Lisboa\nConcelho: Amadora\nFreguesia: Freguesia de Falagueira-Venda Nova\nTelefone: 214996440\nFax: 214966449\nEndereço da Entidade (URL): www.cooptecnica.pt\nEndereço Eletrónico: contratacao.publica@gustaveeiffel.pt\neDelivery Gateway (URL): https://community.vortal.biz/public/\nFunção da Organização: Adquirente\nNorma jurídica da Entidade Adjudicante: Organismo de direito público\nÁrea de atividade da Autoridade Adjudicante: Educação\n2 - JORNAL OFICIAL DA UNIÃO EUROPEIA\nO procedimento a que este anúncio diz respeito também é publicitado no Jornal Oficial da União Europeia? Sim\n3 - AVISO\nModelo de Anúncio: Concurso público\nData de Envio do Anúncio: 07-01-2026\n5 - PROCESSO\nTipo de Procedimento: Concurso público\nPreço base do procedimento: Sim\nValor do preço base do procedimento: 219.884,59 EUR\nProcedimento com lotes? Sim\nNº Máx. de Lotes Autorizado: 8\nNúmero máximo de lotes que podem ser adjudicados a um concorrente: 8\n6 - OBJETO DO CONTRATO\nNúmero de referência interna: CPI 001 CCP 2026\nDesignação do contrato: Aquisição de Serviço de Implementação de Infraestrutura de Cablagem de Fibra Ótica e Cobre\nDescrição: Aquisição de Serviço de Implementação de Infraestrutura de Cablagem de Fibra Ótica e Cobre\nOpções: Não\nTipo de Contrato Principal: Aquisição de Bens Móveis\nTipo de Contrato: Aquisição de Bens Móveis; Locação de Bens Móveis\nClassificação CPV (Vocabulário Comum para os Contratos Públicos)\nObjeto principal\nVocabulário Principal: 32424000\nPreço base s/IVA: 219.884,59 EUR\nLotes: \nNº: LOT-0001\nDescrição do Lote: Lote 1 – Escola da Amadora Centro – Informática\nPreço base s/IVA: 28.747,74 EUR\nClassificação CPV (Vocabulário Comum para os Contratos Públicos)\nObjeto principal\nVocabulário Principal: 32424000\nNº: LOT-0002\nDescrição do Lote: Lote 2 – Escola da Amadora Sede – Digital\nPreço base s/IVA: 40.226,93 EUR\nClassificação CPV (Vocabulário Comum para os Contratos Públicos)\nObjeto principal\nVocabulário Principal: 32424000\nNº: LOT-0003\nDescrição do Lote: Lote 3 - Escola da Amadora Sede – Industrial\nPreço base s/IVA: 39.504,81 EUR\nClassificação CPV (Vocabulário Comum para os Contratos Públicos)\nObjeto principal\nVocabulário Principal: 32424000\nNº: LOT-0004\nDescrição do Lote: Lote 4 - Escola da Amadora Sede – Informática\nPreço base s/IVA: 17.066,18 EUR\nClassificação CPV (Vocabulário Comum para os Contratos Públicos)\nObjeto principal\nVocabulário Principal: 32424000\nNº: LOT-0005\nDescrição do Lote: Lote 5 - Escola do Entroncamento – Industrial\nPreço base s/IVA: 31.509,15 EUR\nClassificação CPV (Vocabulário Comum para os Contratos Públicos)\nObjeto principal\nVocabulário Principal: 32424000\nNº: LOT-0006\nDescrição do Lote: Lote 6 - Escola do Entroncamento – Energias Renováveis\nPreço base s/IVA: 17.328,48 EUR\nClassificação CPV (Vocabulário Comum para os Contratos Públicos)\nObjeto principal\nVocabulário Principal: 32424000\nNº: LOT-0007\nDescrição do Lote: Lote 7 - Escola do Lumiar – Industrial\nPreço base s/IVA: 26.173,38 EUR\nClassificação CPV (Vocabulário Comum para os Contratos Públicos)\nObjeto principal\nVocabulário Principal: 32424000\nNº: LOT-0008\nDescrição do Lote: Lote 8 - Escola do Lumiar – Energias Renováveis\nPreço base s/IVA: 19.327,92 EUR\nClassificação CPV (Vocabulário Comum para os Contratos Públicos)\nObjeto principal\nVocabulário Principal: 32424000\n7 - INDICAÇÕES ADICIONAIS\nO contrato envolve aquisição conjunta (satisfação de várias entidades)? Não\nO contrato é adjudicado por uma central de compras? Não\n8 - TÉCNICAS\nO concurso destina-se à celebração de um acordo-quadro? Inexistência de acordo-quadro\nÉ utilizado um leilão eletrónico? Não\nÉ adotada uma fase de negociação? Não\nSistema de Aquisição Dinâmico: Inexistência de sistema de aquisição dinâmico\n9 - LOCAL DA EXECUÇÃO DO CONTRATO\nLOCAL DA EXECUÇÃO DO CONTRATO (PROCEDIMENTO)\nPaís: Portugal\nNUT III: PT170\nLocalidade: Lisboa\nDistrito: Lisboa\nConcelho: Amadora\nFreguesia: Todas\nLOCAL DA EXECUÇÃO DO CONTRATO (LOTE)\nIdentificador do Lote: LOT-0001; LOT-0002; LOT-0003; LOT-0004; LOT-0005; LOT-0006; LOT-0007; LOT-0008\nPaís: Portugal\nNUT III: PT170\nLocalidade: Lisboa\nDistrito: Lisboa\nConcelho: Amadora\nFreguesia: Todas\nIdentificador do Lote: LOT-0001; LOT-0002; LOT-0003; LOT-0004; LOT-0005; LOT-0006; LOT-0007; LOT-0008\nPaís: Portugal\nNUT III: PT170\nLocalidade: Lisboa\nDistrito: Lisboa\nConcelho: Lisboa\nFreguesia: Freguesia de Lumiar\nIdentificador do Lote: LOT-0001; LOT-0002; LOT-0003; LOT-0004; LOT-0005; LOT-0006; LOT-0007; LOT-0008\nPaís: Portugal\nNUT III: PT16I\nLocalidade: Santarém\nDistrito: Santarém\nConcelho: Entroncamento\nFreguesia: Todas\nIdentificador do Lote: LOT-0001; LOT-0002; LOT-0003; LOT-0004; LOT-0005; LOT-0006; LOT-0007; LOT-0008\nPaís: Portugal\nNUT III: PT170\nLocalidade: Lisboa\nDistrito: Lisboa\nConcelho: Amadora\nFreguesia: Todas\n10 - PRAZO DE EXECUÇÃO DO CONTRATO\nIdentificador do Lote: LOT-0001; LOT-0002; LOT-0003; LOT-0004; LOT-0005; LOT-0006; LOT-0007; LOT-0008\nPrazo de execução do contrato: 15 DIAS\nPrevisão de renovações: Não\n11 - FUNDOS EU\nIdentificador do Lote: LOT-0001; LOT-0002; LOT-0003; LOT-0004; LOT-0005; LOT-0006; LOT-0007; LOT-0008\nTêm fundos EU? Sim\n12 - DOCUMENTOS DE HABILITAÇÃO\nHabilitação para o exercício da atividade profissional: Não\n13 - CONDIÇÕES DE APRESENTAÇÃO\nPlataforma eletrónica utilizada pela entidade adjudicante: VORTAL\nURL para Apresentação: https://community.vortal.biz/public/\nAdmissibilidade da apresentação de propostas variantes: Não autorizado\nPrazo para apresentação das propostas: 20-01-2026 23:59\nPrazo durante o qual os concorrentes são obrigados a manter as respetivas propostas: 10 dias a contar do termo do prazo para a apresentação das propostas\nApresentação de Catálogo Eletrónico: Não autorizado\nIndicação de Subcontratação na Proposta: Inexistência de indicação de subcontratação\n14 - PRESTAÇÃO DE CAUÇÃO\nPrestação de caução: Sim\nPercentagem: 5%\nDescrição da Garantia Exigida: O adjudicatário deve prestar a caução devida no prazo de 10 (dez) dias úteis a contar da notificação da decisão de adjudicação, no valor de 5% do preço contratual, em benefício da Cooptécnica Gustave Eiffel, devendo comprovar essa prestação no dia imediatamente subsequente.\n15 - FORNECIMENTO DAS PEÇAS DO CONCURSO, APRESENTAÇÃO DE PEDIDOS DE PARTICIPAÇÃO E APRESENTAÇÃO DAS PROPOSTAS\nLink para acesso às peças do concurso (URL): https://community.vortal.biz/Public/public-tender-documents/U2xyRTNnM01SdkNsaGlFWHRPVXhXTnJNZWNLUGVhK0FpR0J5WDlvMlRTdkJmS2VJOTNmVlVhOU5wd1JXRGpmZTg3eGZybHdxUWw0OGYxM2hEUlc1dHc9PXZLTlpz\n20 - OUTROS REQUISITOS\nIdentificador do Lote: LOT-0001; LOT-0002; LOT-0003; LOT-0004; LOT-0005; LOT-0006; LOT-0007; LOT-0008\nInformação sobre contratos reservados. Aplica-se a contratos reservados (54º-A)? Não\n21 - CRITÉRIO DE ADJUDICAÇÃO\nO Critério de adjudicação é diferenciado por lote? Não\nMultifator: Não\nMonofator:\nNome: Outros\nOutro nome: Preço\n24 - CONDIÇÕES DO CONTRATO\nIdentificador do Lote: LOT-0001; LOT-0002; LOT-0003; LOT-0004; LOT-0005; LOT-0006; LOT-0007; LOT-0008\nFaturação Eletrónica: Permitido\nObrigação de Subcontratação:\nCódigo da Obrigação de Subcontratação: Não é aplicável nenhuma obrigação de subcontratação.\n25 - COMPRA PÚBLICA ESTRATÉGICA\nCompra Pública Estratégica: Inexistência de contratação pública estratégica\n26 - INFORMAÇÕES ADICIONAIS\nIdentificador do Lote: LOT-0001; LOT-0002; LOT-0003; LOT-0004; LOT-0005; LOT-0006; LOT-0007; LOT-0008\nContrato adequado para PME: Sim\nCobertura ACP (Acordo dos Contratos Públicos da Organização Mundial do Comércio): Não\n27 - IDENTIFICAÇÃO E CONTACTOS DO ÓRGÃO DE RECURSOS ADMINISTRATIVOS\nDesignação: Susana Fernandes\nEndereço: RUA ELIAS GARCIA Nº 29 - VENDA NOVA\nCódigo postal: 2700-312\nLocalidade: Amadora\nTelefone: +351 912355271\nFax: +351 214996449\nEndereço eletrónico: contratacaopublica@gustaveeiffel.pt\n28 - IDENTIFICAÇÃO DO(S) AUTOR(ES) DE ANÚNCIO\nNome: Susana Fernandes\nCargo: Técnico \n419947073",
    "nipc": "502327669",
    "distrito": "Lisboa",
    "concelho": "Amadora",
    "freguesia": "Freguesia de Falagueira-Venda Nova",
    "site": "www.cooptecnica.pt",
    "email": "contratacao.publica@gustaveeiffel.pt",
    "designacao_contrato": "Aquisição de Serviço de Implementação de Infraestrutura de Cablagem de Fibra Ótica e Cobre",
    "descricao": "Aquisição de Serviço de Implementação de Infraestrutura de Cablagem de Fibra Ótica e Cobre",
    "preco_base": "219.884,59 EUR",
    "prazo_execucao": "15 DIAS",
    "prazo_apresentacao_propostas": "20-01-2026 23:59",
    "fundos_eu": "Sim",
    "plataforma_eletronica": "VORTAL",
    "url_procedimento": "https://community.vortal.biz/public/",
    "autor_nome": "Susana Fernandes",
    "autor_cargo": "Técnico"
  },
  {
    "numero_procedimento": "N/A",
    "entidade": "AnÃºncio de procedimento  n.Âº 397/2026  -  DiÃ¡rio da RepÃºblica n.Âº 6/2026, SÃ©rie II de 2026-01-09",
    "link": "https://diariodarepublica.pt/dr/detalhe/contrato-publico/397-1002139972"
  },
  {
    "numero_procedimento": "N/A",
    "entidade": "AnÃºncio de procedimento  n.Âº 399/2026  -  DiÃ¡rio da RepÃºblica n.Âº 6/2026, SÃ©rie II de 2026-01-09",
    "link": "https://diariodarepublica.pt/dr/detalhe/contrato-publico/399-1002139973"
  },
  {
    "numero_procedimento": "N/A",
    "entidade": "Município de Évora",
    "link": "https://diariodarepublica.pt/dr/detalhe/contrato-publico/401-1002139974",
    "detalhes_completos": "1 - IDENTIFICAÇÃO E CONTACTOS DA ENTIDADE ADJUDICANTE\nDesignação da entidade adjudicante: Município de Évora\nNIPC: 504828576\nEndereço: Pç.  Sertório, Nr. 1\nCódigo postal: 7004-506\nLocalidade: Évora\nPaís: Portugal\nNUT III: PT187\nDistrito: Évora\nConcelho: Évora\nFreguesia: Todas\nTelefone: 266777000\nFax: 266702950\nEndereço da Entidade (URL): https://www.cm-evora.pt/\nEndereço Eletrónico: cmevora@cm-evora.pt\neDelivery Gateway (URL): https://community.vortal.biz/public/\nFunção da Organização: Adquirente\nNorma jurídica da Entidade Adjudicante: Organismo de direito público\nÁrea de atividade da Autoridade Adjudicante: Serviços públicos das administrações públicas\n2 - JORNAL OFICIAL DA UNIÃO EUROPEIA\nO procedimento a que este anúncio diz respeito também é publicitado no Jornal Oficial da União Europeia? Sim\n3 - AVISO\nModelo de Anúncio: Concurso público\nData de Envio do Anúncio: 07-01-2026\n5 - PROCESSO\nTipo de Procedimento: Concurso público\nPreço base do procedimento: Sim\nValor do preço base do procedimento: 303.135,00 EUR\nProcedimento com lotes? Não\n6 - OBJETO DO CONTRATO\nNúmero de referência interna: 218/2025_CPI_BAIRRO_COMERCIAL_DIGITAL_PRR_PRO_5375\nDesignação do contrato: CONTRATAÇÃO DE SERVIÇOS E FORNECIMENTO DA COMPONENTE DE COMUNICAÇÃO DO \"BAIRRO COMERCIAL DIGITAL DE ÉVORA\" PRR – PROJETO BAIRROS COMERCIAIS DIGITAIS - PROJETO Nº 5375.\nDescrição: CONCURSO PÚBLICO INTERNACIONAL NOS TERMOS DA ALÍNEA A) DO N°1 DO ART'.20º DO CCP PARA CONTRATAÇÃO DE SERVIÇOS E FORNECIMENTO DA COMPONENTE DE COMUNICAÇÃO DO \"BAIRRO COMERCIAL DIGITAL DE ÉVORA\" PRR – PROJETO BAIRROS COMERCIAIS DIGITAIS - PROJETO Nº 5375.\nOpções: Não\nTipo de Contrato Principal: Aquisição de Serviços\nTipo de Contrato: Aquisição de Serviços\nClassificação CPV (Vocabulário Comum para os Contratos Públicos)\nObjeto principal\nVocabulário Principal: 72400000\nPreço base s/IVA: 303.135,00 EUR\n7 - INDICAÇÕES ADICIONAIS\nO contrato envolve aquisição conjunta (satisfação de várias entidades)? Não\nO contrato é adjudicado por uma central de compras? Não\n8 - TÉCNICAS\nO concurso destina-se à celebração de um acordo-quadro? Inexistência de acordo-quadro\nÉ utilizado um leilão eletrónico? Não\nÉ adotada uma fase de negociação? Não\nSistema de Aquisição Dinâmico: Inexistência de sistema de aquisição dinâmico\n9 - LOCAL DA EXECUÇÃO DO CONTRATO\nLOCAL DA EXECUÇÃO DO CONTRATO (PROCEDIMENTO)\nPaís: Portugal\nNUT III: PT187\nLocalidade: Évora\nDistrito: Évora\nConcelho: Évora\nFreguesia: União das Freguesias de Évora (São Mamede, Sé, São Pedro e Santo Antão)\n10 - PRAZO DE EXECUÇÃO DO CONTRATO\nPrazo de execução do contrato: 80 DIAS\nPrevisão de renovações: Não\n11 - FUNDOS EU\nTêm fundos EU? Sim\n12 - DOCUMENTOS DE HABILITAÇÃO\nHabilitação para o exercício da atividade profissional: Não\n13 - CONDIÇÕES DE APRESENTAÇÃO\nPlataforma eletrónica utilizada pela entidade adjudicante: VORTAL\nURL para Apresentação: https://community.vortal.biz/public/\nAdmissibilidade da apresentação de propostas variantes: Não autorizado\nPrazo para apresentação das propostas: 22-01-2026 23:59\nPrazo durante o qual os concorrentes são obrigados a manter as respetivas propostas: 66 dias a contar do termo do prazo para a apresentação das propostas\nApresentação de Catálogo Eletrónico: Permitido\nIndicação de Subcontratação na Proposta: Inexistência de indicação de subcontratação\n14 - PRESTAÇÃO DE CAUÇÃO\nPrestação de caução: Não\n15 - FORNECIMENTO DAS PEÇAS DO CONCURSO, APRESENTAÇÃO DE PEDIDOS DE PARTICIPAÇÃO E APRESENTAÇÃO DAS PROPOSTAS\nLink para acesso às peças do concurso (URL): https://community.vortal.biz/Public/public-tender-documents/N0tsWmZBbmhOaTk4YkpLeGlYSW5Yc3VrWTQrL204SFVHaXZEK2paNTc5dkFKNzNmYWY0dllqME05VG1vNy9zbVhpY1BvTDJpcThQSDZ1Ulc1MDJuK2c9PWlZJnd0\n20 - OUTROS REQUISITOS\nInformação sobre contratos reservados. Aplica-se a contratos reservados (54º-A)? Não\n21 - CRITÉRIO DE ADJUDICAÇÃO\nMultifator: Sim\nFator: \nNome: Preço\nPonderação: 30%\nSubfatores: Não\nFator: \nNome: Qualidade\nPonderação: 70%\nSubfatores: Não\n24 - CONDIÇÕES DO CONTRATO\nFaturação Eletrónica: Permitido\nObrigação de Subcontratação:\nCódigo da Obrigação de Subcontratação: Não é aplicável nenhuma obrigação de subcontratação.\n25 - COMPRA PÚBLICA ESTRATÉGICA\nCompra Pública Estratégica: Redução dos impactos ambientais\nDescrição do Processo de Adjudicação Estratégico: Conforme as peças do procedimento\nCritérios de contratos Públicos Ecológicos: Critérios de contratação pública ecológica nacional\nCategorias da estratégia nacional: Centros de dados, salas de servidores e serviços em nuvem\nContratos Públicos Ecológicos: Outros\nDiretiva Veículos Não Poluentes: Não\nCritério de Acessibilidade: Os critérios de acessibilidade para as pessoas com deficiência não estão incluídos porque o contrato não se destina a pessoas singulares\n26 - INFORMAÇÕES ADICIONAIS\nContrato adequado para PME: Sim\nCobertura ACP (Acordo dos Contratos Públicos da Organização Mundial do Comércio): Não\n27 - IDENTIFICAÇÃO E CONTACTOS DO ÓRGÃO DE RECURSOS ADMINISTRATIVOS\nDesignação: CÂMARA MUNICIPAL DE ÉVORA\nEndereço: Praça Sertório, nº1\nCódigo postal: 7004-506\nLocalidade: Évora\nTelefone: +351 266777000\nFax: +351 266777161\nEndereço eletrónico: cme.dagf.aprovisionamento@cm-evora.pt\n28 - IDENTIFICAÇÃO DO(S) AUTOR(ES) DE ANÚNCIO\nNome: Carlos Zorrinho\nCargo: Presidente da Câmara\n419947265",
    "nipc": "504828576",
    "distrito": "Évora",
    "concelho": "Évora",
    "freguesia": "Todas",
    "site": "https://www.cm-evora.pt/",
    "email": "cmevora@cm-evora.pt",
    "designacao_contrato": "CONTRATAÇÃO DE SERVIÇOS E FORNECIMENTO DA COMPONENTE DE COMUNICAÇÃO DO \"BAIRRO COMERCIAL DIGITAL DE ÉVORA\" PRR – PROJETO BAIRROS COMERCIAIS DIGITAIS - PROJETO Nº 5375.",
    "descricao": "CONCURSO PÚBLICO INTERNACIONAL NOS TERMOS DA ALÍNEA A) DO N°1 DO ART'.20º DO CCP PARA CONTRATAÇÃO DE SERVIÇOS E FORNECIMENTO DA COMPONENTE DE COMUNICAÇÃO DO \"BAIRRO COMERCIAL DIGITAL DE ÉVORA\" PRR – PROJETO BAIRROS COMERCIAIS DIGITAIS - PROJETO Nº 5375.",
    "preco_base": "303.135,00 EUR",
    "prazo_execucao": "80 DIAS",
    "prazo_apresentacao_propostas": "22-01-2026 23:59",
    "fundos_eu": "Sim",
    "plataforma_eletronica": "VORTAL",
    "url_procedimento": "https://community.vortal.biz/public/",
    "autor_nome": "Carlos Zorrinho",
    "autor_cargo": "Presidente da Câmara"
  },
  {
    "numero_procedimento": "N/A",
    "entidade": "AnÃºncio de procedimento  n.Âº 383/2026  -  DiÃ¡rio da RepÃºblica n.Âº 6/2026, SÃ©rie II de 2026-01-09",
    "link": "https://diariodarepublica.pt/dr/detalhe/contrato-publico/383-1003170655"
  },
  {
    "numero_procedimento": "N/A",
    "entidade": "AnÃºncio de procedimento  n.Âº 384/2026  -  DiÃ¡rio da RepÃºblica n.Âº 6/2026, SÃ©rie II de 2026-01-09",
    "link": "https://diariodarepublica.pt/dr/detalhe/contrato-publico/384-1003170656"
  },
  {
    "numero_procedimento": "N/A",
    "entidade": "Município de Serpa",
    "link": "https://diariodarepublica.pt/dr/detalhe/contrato-publico/385-1003170658",
    "detalhes_completos": "1 - IDENTIFICAÇÃO E CONTACTOS DA ENTIDADE ADJUDICANTE\nDesignação da entidade adjudicante: Município de Serpa\nNIPC: 501112049\nServiço/Órgão/Pessoa de contacto: Divisão Financeira\nEndereço: Praça da República\nCódigo postal: 7830-389\nLocalidade: Serpa\nPaís: Portugal\nNUT III: PT184\nDistrito: Beja\nConcelho: Serpa\nFreguesia: União das Freguesias de Serpa (Salvador e Santa Maria)\nTelefone: 284540100\nEndereço Eletrónico: geral@cm-serpa.pt\nFunção da Organização: Adquirente\nNorma jurídica da Entidade Adjudicante: Autoridade local\nÁrea de atividade da Autoridade Adjudicante: Serviços públicos das administrações públicas\n2 - JORNAL OFICIAL DA UNIÃO EUROPEIA\nO procedimento a que este anúncio diz respeito também é publicitado no Jornal Oficial da União Europeia? Não\n3 - AVISO\nModelo de Anúncio: Concurso público\nData de Envio do Anúncio: 08-01-2026\n5 - PROCESSO\nTipo de Procedimento: Concurso público\nPreço base do procedimento: Sim\nValor do preço base do procedimento: 149.450,00 EUR\nProcedimento com lotes? Não\n6 - OBJETO DO CONTRATO\nNúmero de referência interna: 201/2025\nDesignação do contrato: Aluguer de Stands e Mobiliário para a Feira do Queijo de 2026\nDescrição: Aluguer de Stands e Mobiliário para a Feira do Queijo de 2026\nTipo de Contrato Principal: Locação de Bens Móveis\nTipo de Contrato: Aquisição de Serviços; Locação de Bens Móveis\nClassificação CPV (Vocabulário Comum para os Contratos Públicos)\nObjeto principal\nVocabulário Principal: 39154000\nPreço base s/IVA: 149.450,00 EUR\n7 - INDICAÇÕES ADICIONAIS\nO contrato envolve aquisição conjunta (satisfação de várias entidades)? Não\nO contrato é adjudicado por uma central de compras? Não\n8 - TÉCNICAS\nO concurso destina-se à celebração de um acordo-quadro? Inexistência de acordo-quadro\nÉ utilizado um leilão eletrónico? Não\nÉ adotada uma fase de negociação? Não\nSistema de Aquisição Dinâmico: Inexistência de sistema de aquisição dinâmico\n9 - LOCAL DA EXECUÇÃO DO CONTRATO\nLOCAL DA EXECUÇÃO DO CONTRATO (PROCEDIMENTO)\nPaís: Portugal\nNUT III: PT184\nLocalidade: serpa\nDistrito: Beja\nConcelho: Serpa\nFreguesia: União das Freguesias de Serpa (Salvador e Santa Maria)\n10 - PRAZO DE EXECUÇÃO DO CONTRATO\nPrazo de execução do contrato: 3 DIAS\nPrevisão de renovações: Não\n11 - FUNDOS EU\nTêm fundos EU? Não\n12 - DOCUMENTOS DE HABILITAÇÃO\nHabilitação para o exercício da atividade profissional: Não\n13 - CONDIÇÕES DE APRESENTAÇÃO\nPlataforma eletrónica utilizada pela entidade adjudicante: VORTAL\nURL para Apresentação: https://community.vortal.biz/\nAdmissibilidade da apresentação de propostas variantes: Não autorizado\nPrazo para apresentação das propostas: 15-01-2026 17:00\nPrazo durante o qual os concorrentes são obrigados a manter as respetivas propostas: 66 dias a contar do termo do prazo para a apresentação das propostas\nApresentação de Catálogo Eletrónico: Não autorizado\nIndicação de Subcontratação na Proposta: Inexistência de indicação de subcontratação\n14 - PRESTAÇÃO DE CAUÇÃO\nPrestação de caução: Não\n15 - FORNECIMENTO DAS PEÇAS DO CONCURSO, APRESENTAÇÃO DE PEDIDOS DE PARTICIPAÇÃO E APRESENTAÇÃO DAS PROPOSTAS\nLink para acesso às peças do concurso (URL): https://community.vortal.biz/\n20 - OUTROS REQUISITOS\nInformação sobre contratos reservados. Aplica-se a contratos reservados (54º-A)? Não\n21 - CRITÉRIO DE ADJUDICAÇÃO\nMultifator: Não\nMonofator:\nNome: Preço\n24 - CONDIÇÕES DO CONTRATO\nFaturação Eletrónica: Permitido\nObrigação de Subcontratação:\nCódigo da Obrigação de Subcontratação: Não é aplicável nenhuma obrigação de subcontratação.\n25 - COMPRA PÚBLICA ESTRATÉGICA\nCompra Pública Estratégica: Inexistência de contratação pública estratégica\n26 - INFORMAÇÕES ADICIONAIS\nContrato adequado para PME: Sim\nCobertura ACP (Acordo dos Contratos Públicos da Organização Mundial do Comércio): Não\n27 - IDENTIFICAÇÃO E CONTACTOS DO ÓRGÃO DE RECURSOS ADMINISTRATIVOS\nDesignação: Municipio de Serpa\nEndereço: Praça da República\nCódigo postal: 7830-389\nLocalidade: Serpa\nEndereço eletrónico: geral@cm-serpa.pt\n28 - IDENTIFICAÇÃO DO(S) AUTOR(ES) DE ANÚNCIO\nNome: Francisco Picareta\nCargo: Presidente de Câmara\n419947404",
    "nipc": "501112049",
    "distrito": "Beja",
    "concelho": "Serpa",
    "freguesia": "União das Freguesias de Serpa (Salvador e Santa Maria)",
    "site": null,
    "email": "geral@cm-serpa.pt",
    "designacao_contrato": "Aluguer de Stands e Mobiliário para a Feira do Queijo de 2026",
    "descricao": "Aluguer de Stands e Mobiliário para a Feira do Queijo de 2026",
    "preco_base": "149.450,00 EUR",
    "prazo_execucao": "3 DIAS",
    "prazo_apresentacao_propostas": "15-01-2026 17:00",
    "fundos_eu": "Não",
    "plataforma_eletronica": "VORTAL",
    "url_procedimento": "https://community.vortal.biz/",
    "autor_nome": "Francisco Picareta",
    "autor_cargo": "Presidente de Câmara"
  },
  {
    "numero_procedimento": "N/A",
    "entidade": "AnÃºncio de procedimento  n.Âº 386/2026  -  DiÃ¡rio da RepÃºblica n.Âº 6/2026, SÃ©rie II de 2026-01-09",
    "link": "https://diariodarepublica.pt/dr/detalhe/contrato-publico/386-1003170659"
  },
  {
    "numero_procedimento": "N/A",
    "entidade": "Município das Lajes do Pico",
    "link": "https://diariodarepublica.pt/dr/detalhe/contrato-publico/387-1003170660",
    "detalhes_completos": "1 - IDENTIFICAÇÃO E CONTACTOS DA ENTIDADE ADJUDICANTE\nDesignação da entidade adjudicante: Município das Lajes do Pico\nNIPC: 512074143\nServiço/Órgão/Pessoa de contacto: Serviço de Aprovisionamento\nEndereço: Rua de São Francisco\nCódigo postal: 9930-135\nLocalidade: Lajes do Pico\nPaís: Portugal\nNUT III: PT200\nDistrito: Região Autónoma dos Açores\nConcelho: Lajes do Pico\nFreguesia: Freguesia de Lajes do Pico\nTelefone: 292679700\nEndereço da Entidade (URL): http://cm-lajesdopico.pt/\nEndereço Eletrónico: aprovisionamento.cmlp@gmail.com\neDelivery Gateway (URL): https://www.acingov.pt\nFunção da Organização: Adquirente\nNorma jurídica da Entidade Adjudicante: Organismo de direito público\nÁrea de atividade da Autoridade Adjudicante: Serviços públicos das administrações públicas\n2 - JORNAL OFICIAL DA UNIÃO EUROPEIA\nO procedimento a que este anúncio diz respeito também é publicitado no Jornal Oficial da União Europeia? Não\n3 - AVISO\nModelo de Anúncio: Concurso público\nData de Envio do Anúncio: 08-01-2026\n5 - PROCESSO\nTipo de Procedimento: Concurso público\nPreço base do procedimento: Sim\nValor do preço base do procedimento: 99.100,00 EUR\nProcedimento com lotes? Não\n6 - OBJETO DO CONTRATO\nNúmero de referência interna: CP/2/CMLP/2026\nDesignação do contrato: Empreitada de Reabilitação de Moradia  Fetais n.º 57, Piedade  Lajes (U554), no âmbito do Plano de Recuperação e Resiliência, Investimento RE-C02-I01  Programa de Apoio ao Acesso à Habitação\nDescrição: Empreitada de Reabilitação de Moradia  Fetais n.º 57, Piedade  Lajes (U554), no âmbito do Plano de Recuperação e Resiliência, Investimento RE-C02-I01  Programa de Apoio ao Acesso à Habitação\nTipo de Contrato Principal: Empreitada de Obras Públicas\nTipo de Contrato: Empreitada de Obras Públicas\nClassificação CPV (Vocabulário Comum para os Contratos Públicos)\nObjeto principal\nVocabulário Principal: 45453100\nPreço base s/IVA: 99.100,00 EUR\n7 - INDICAÇÕES ADICIONAIS\nO contrato envolve aquisição conjunta (satisfação de várias entidades)? Não\nO contrato é adjudicado por uma central de compras? Não\n8 - TÉCNICAS\nO concurso destina-se à celebração de um acordo-quadro? Inexistência de acordo-quadro\nÉ utilizado um leilão eletrónico? Não\nÉ adotada uma fase de negociação? Não\nSistema de Aquisição Dinâmico: Inexistência de sistema de aquisição dinâmico\n9 - LOCAL DA EXECUÇÃO DO CONTRATO\nLOCAL DA EXECUÇÃO DO CONTRATO (PROCEDIMENTO)\nPaís: Portugal\nNUT III: PT200\nLocalidade: Freguesia de Piedade\nDistrito: Região Autónoma dos Açores\nConcelho: Lajes do Pico\nFreguesia: Freguesia de Piedade\n10 - PRAZO DE EXECUÇÃO DO CONTRATO\nPrazo de execução do contrato: 150 DIAS\nPrevisão de renovações: Não\n11 - FUNDOS EU\nTêm fundos EU? Não\n12 - DOCUMENTOS DE HABILITAÇÃO\nHabilitação para o exercício da atividade profissional: Não\n13 - CONDIÇÕES DE APRESENTAÇÃO\nPlataforma eletrónica utilizada pela entidade adjudicante: ACIN\nURL para Apresentação: https://www.acingov.pt\nAdmissibilidade da apresentação de propostas variantes: Não autorizado\nPrazo para apresentação das propostas: 23-01-2026 23:59\nPrazo durante o qual os concorrentes são obrigados a manter as respetivas propostas: 66 dias a contar do termo do prazo para a apresentação das propostas\nIndicação de Subcontratação na Proposta: Inexistência de indicação de subcontratação\n14 - PRESTAÇÃO DE CAUÇÃO\nPrestação de caução: Não\n15 - FORNECIMENTO DAS PEÇAS DO CONCURSO, APRESENTAÇÃO DE PEDIDOS DE PARTICIPAÇÃO E APRESENTAÇÃO DAS PROPOSTAS\nLink para acesso às peças do concurso (URL): https://www.acingov.pt/acingovprod/2/zonaPublica/zona_publica_c/donwloadProcedurePiece/MTA0MTMwNg==\n20 - OUTROS REQUISITOS\nInformação sobre contratos reservados. Aplica-se a contratos reservados (54º-A)? Não\n21 - CRITÉRIO DE ADJUDICAÇÃO\nMultifator: Não\nMonofator:\nNome: Preço\n24 - CONDIÇÕES DO CONTRATO\nFaturação Eletrónica: Permitido\nObrigação de Subcontratação:\nCódigo da Obrigação de Subcontratação: Não é aplicável nenhuma obrigação de subcontratação.\n25 - COMPRA PÚBLICA ESTRATÉGICA\nCompra Pública Estratégica: Inexistência de contratação pública estratégica\n26 - INFORMAÇÕES ADICIONAIS\nContrato adequado para PME: Sim\nCobertura ACP (Acordo dos Contratos Públicos da Organização Mundial do Comércio): Não\n27 - IDENTIFICAÇÃO E CONTACTOS DO ÓRGÃO DE RECURSOS ADMINISTRATIVOS\nDesignação: Câmara Municipal das Lajes do Pico\nEndereço: Rua de São Francisco Convento de São Francisco\nCódigo postal: 9930-135\nLocalidade: Lajes do Pico\nTelefone: 292679700\nFax: \nEndereço eletrónico: geral@cm-lajesdopico.pt\n28 - IDENTIFICAÇÃO DO(S) AUTOR(ES) DE ANÚNCIO\nNome: Manuel dos Santos Pimentel\nCargo: Vice-Presidente da Câmara Municipal das Lajes do Pico\n419947490",
    "nipc": "512074143",
    "distrito": "Região Autónoma dos Açores",
    "concelho": "Lajes do Pico",
    "freguesia": "Freguesia de Lajes do Pico",
    "site": "http://cm-lajesdopico.pt/",
    "email": "aprovisionamento.cmlp@gmail.com",
    "designacao_contrato": "Empreitada de Reabilitação de Moradia  Fetais n.º 57, Piedade  Lajes (U554), no âmbito do Plano de Recuperação e Resiliência, Investimento RE-C02-I01  Programa de Apoio ao Acesso à Habitação",
    "descricao": "Empreitada de Reabilitação de Moradia  Fetais n.º 57, Piedade  Lajes (U554), no âmbito do Plano de Recuperação e Resiliência, Investimento RE-C02-I01  Programa de Apoio ao Acesso à Habitação",
    "preco_base": "99.100,00 EUR",
    "prazo_execucao": "150 DIAS",
    "prazo_apresentacao_propostas": "23-01-2026 23:59",
    "fundos_eu": "Não",
    "plataforma_eletronica": "ACIN",
    "url_procedimento": "https://www.acingov.pt",
    "autor_nome": "Manuel dos Santos Pimentel",
    "autor_cargo": "Vice-Presidente da Câmara Municipal das Lajes do Pico"
  },
  {
    "numero_procedimento": "N/A",
    "entidade": "AnÃºncio de procedimento  n.Âº 388/2026  -  DiÃ¡rio da RepÃºblica n.Âº 6/2026, SÃ©rie II de 2026-01-09",
    "link": "https://diariodarepublica.pt/dr/detalhe/contrato-publico/388-1003170665"
  },
  {
    "numero_procedimento": "N/A",
    "entidade": "Município de Santo Tirso",
    "link": "https://diariodarepublica.pt/dr/detalhe/contrato-publico/390-1003371829",
    "detalhes_completos": "1 - IDENTIFICAÇÃO E CONTACTOS DA ENTIDADE ADJUDICANTE\nDesignação da entidade adjudicante: Município de Santo Tirso\nNIPC: 501306870\nEndereço: Praça 25 de Abril\nCódigo postal: 4780-373\nLocalidade: Área Metropolitana do Porto\nPaís: Portugal\nNUT III: PT11A\nDistrito: Porto\nConcelho: Santo Tirso\nFreguesia: União das Freguesias de Santo Tirso, Couto (Santa Cristina e São Miguel) e Burgães\nTelefone: 252830400\nFax: 252856534\nEndereço da Entidade (URL): www.cm-stirso.pt\nEndereço Eletrónico: santotirso@cm-stirso.pt\neDelivery Gateway (URL): https://community.vortal.biz/public/\nFunção da Organização: Adquirente\nNorma jurídica da Entidade Adjudicante: Autoridade local\nÁrea de atividade da Autoridade Adjudicante: Serviços públicos das administrações públicas\n2 - JORNAL OFICIAL DA UNIÃO EUROPEIA\nO procedimento a que este anúncio diz respeito também é publicitado no Jornal Oficial da União Europeia? Não\n3 - AVISO\nModelo de Anúncio: Concurso público\nData de Envio do Anúncio: 08-01-2026\n5 - PROCESSO\nTipo de Procedimento: Concurso público\nPreço base do procedimento: Sim\nValor do preço base do procedimento: 83.000,00 EUR\nProcedimento com lotes? Não\n6 - OBJETO DO CONTRATO\nNúmero de referência interna: 1003/CPN/S/2025\nDesignação do contrato: CONTRATO DE AQUISIÇÃO DE SERVIÇOS PARA A ORGANIZAÇÃO E IMPLEMENTAÇÃO DE UM PROGRAMA DE APOIO À PROMOÇÃO DAS APRENDIZAGENS DOS ALUNOS DO 2.º E DO 3.º CICLO DO ENSINO BÁSICO\nDescrição: CONTRATO DE AQUISIÇÃO DE SERVIÇOS PARA A ORGANIZAÇÃO E IMPLEMENTAÇÃO DE UM PROGRAMA DE APOIO À PROMOÇÃO DAS APRENDIZAGENS DOS ALUNOS DO 2.º E DO 3.º CICLO\nDO ENSINO BÁSICO\nTipo de Contrato Principal: Aquisição de Serviços\nTipo de Contrato: Aquisição de Serviços\nClassificação CPV (Vocabulário Comum para os Contratos Públicos)\nObjeto principal\nVocabulário Principal: 98133000\nPreço base s/IVA: 83.000,00 EUR\n7 - INDICAÇÕES ADICIONAIS\nO contrato envolve aquisição conjunta (satisfação de várias entidades)? Não\nO contrato é adjudicado por uma central de compras? Não\n8 - TÉCNICAS\nO concurso destina-se à celebração de um acordo-quadro? Inexistência de acordo-quadro\nÉ utilizado um leilão eletrónico? Não\nÉ adotada uma fase de negociação? Não\nSistema de Aquisição Dinâmico: Inexistência de sistema de aquisição dinâmico\n9 - LOCAL DA EXECUÇÃO DO CONTRATO\nLOCAL DA EXECUÇÃO DO CONTRATO (PROCEDIMENTO)\nPaís: Portugal\nNUT III: PT11A\nLocalidade: Área Metropolitana do Porto\nDistrito: Porto\nConcelho: Santo Tirso\nFreguesia: União das Freguesias de Santo Tirso, Couto (Santa Cristina e São Miguel) e Burgães\n10 - PRAZO DE EXECUÇÃO DO CONTRATO\nPrazo de execução do contrato: 24 MESES\nPrevisão de renovações: Não\n11 - FUNDOS EU\nTêm fundos EU? Não\n12 - DOCUMENTOS DE HABILITAÇÃO\nHabilitação para o exercício da atividade profissional: Não\n13 - CONDIÇÕES DE APRESENTAÇÃO\nPlataforma eletrónica utilizada pela entidade adjudicante: VORTAL\nURL para Apresentação: https://community.vortal.biz/public/\nAdmissibilidade da apresentação de propostas variantes: Não autorizado\nPrazo para apresentação das propostas: 26-01-2026 17:30\nPrazo durante o qual os concorrentes são obrigados a manter as respetivas propostas: 66 dias a contar do termo do prazo para a apresentação das propostas\nIndicação de Subcontratação na Proposta: Inexistência de indicação de subcontratação\n14 - PRESTAÇÃO DE CAUÇÃO\nPrestação de caução: Não\n15 - FORNECIMENTO DAS PEÇAS DO CONCURSO, APRESENTAÇÃO DE PEDIDOS DE PARTICIPAÇÃO E APRESENTAÇÃO DAS PROPOSTAS\nLink para acesso às peças do concurso (URL): https://community.vortal.biz/Public/public-tender-documents/UHkxZy9MbVRLR1Y5S3RFUXJnMHdDTCt4WmowVDdlbllFT2Z1WWp3M1U0VzlmKzFQUVd6MmQyYzY2TlBpZ0VzYXduTEZSNjB3V0kvUWZBM01jdkk4SUE9PXAkeUpt\n20 - OUTROS REQUISITOS\nInformação sobre contratos reservados. Aplica-se a contratos reservados (54º-A)? Não\n21 - CRITÉRIO DE ADJUDICAÇÃO\nMultifator: Sim\nFator: \nNome: Preço\nPonderação: 50%\nSubfatores: Não\nFator: \nNome: Qualidade\nPonderação: 50%\nSubfatores: Não\n24 - CONDIÇÕES DO CONTRATO\nFaturação Eletrónica: Permitido\nObrigação de Subcontratação:\nCódigo da Obrigação de Subcontratação: Não é aplicável nenhuma obrigação de subcontratação.\n25 - COMPRA PÚBLICA ESTRATÉGICA\nCompra Pública Estratégica: Inexistência de contratação pública estratégica\n26 - INFORMAÇÕES ADICIONAIS\nContrato adequado para PME: Sim\nCobertura ACP (Acordo dos Contratos Públicos da Organização Mundial do Comércio): Não\n27 - IDENTIFICAÇÃO E CONTACTOS DO ÓRGÃO DE RECURSOS ADMINISTRATIVOS\nDesignação: Município de Santo Tirso\nEndereço: Praça 25 de Abril\nCódigo postal: 4780-373\nLocalidade: Santo Tirso\nTelefone: +351 252830400\nFax: +351 252856534\nEndereço eletrónico: santotirso@cm-stirso.pt\n28 - IDENTIFICAÇÃO DO(S) AUTOR(ES) DE ANÚNCIO\nNome: Alberto Costa\nCargo: Presidente da Câmara Municipal\n419947506",
    "nipc": "501306870",
    "distrito": "Porto",
    "concelho": "Santo Tirso",
    "freguesia": "União das Freguesias de Santo Tirso, Couto (Santa Cristina e São Miguel) e Burgães",
    "site": "www.cm-stirso.pt",
    "email": "santotirso@cm-stirso.pt",
    "designacao_contrato": "CONTRATO DE AQUISIÇÃO DE SERVIÇOS PARA A ORGANIZAÇÃO E IMPLEMENTAÇÃO DE UM PROGRAMA DE APOIO À PROMOÇÃO DAS APRENDIZAGENS DOS ALUNOS DO 2.º E DO 3.º CICLO DO ENSINO BÁSICO",
    "descricao": "CONTRATO DE AQUISIÇÃO DE SERVIÇOS PARA A ORGANIZAÇÃO E IMPLEMENTAÇÃO DE UM PROGRAMA DE APOIO À PROMOÇÃO DAS APRENDIZAGENS DOS ALUNOS DO 2.º E DO 3.º CICLO",
    "preco_base": "83.000,00 EUR",
    "prazo_execucao": "24 MESES",
    "prazo_apresentacao_propostas": "26-01-2026 17:30",
    "fundos_eu": "Não",
    "plataforma_eletronica": "VORTAL",
    "url_procedimento": "https://community.vortal.biz/public/",
    "autor_nome": "Alberto Costa",
    "autor_cargo": "Presidente da Câmara Municipal"
  },
  {
    "numero_procedimento": "N/A",
    "entidade": "AnÃºncio de procedimento  n.Âº 391/2026  -  DiÃ¡rio da RepÃºblica n.Âº 6/2026, SÃ©rie II de 2026-01-09",
    "link": "https://diariodarepublica.pt/dr/detalhe/contrato-publico/391-1003371830"
  },
  {
    "numero_procedimento": "N/A",
    "entidade": "Teatro Nacional de São João, EPE",
    "link": "https://diariodarepublica.pt/dr/detalhe/contrato-publico/392-1003371831",
    "detalhes_completos": "1 - IDENTIFICAÇÃO E CONTACTOS DA ENTIDADE ADJUDICANTE\nDesignação da entidade adjudicante: Teatro Nacional de São João, EPE\nNIPC: 503966908\nServiço/Órgão/Pessoa de contacto: Departamento de Contratação Pública\nEndereço: Praça da Batalha\nCódigo postal: 4000-102\nLocalidade: Porto\nPaís: Portugal\nNUT III: PT11A\nDistrito: Porto\nConcelho: Porto\nFreguesia: União das Freguesias de Cedofeita, Santo Ildefonso, Sé, Miragaia, São Nicolau e Vitória\nTelefone: 223401900\nFax: 222003449\nEndereço da Entidade (URL): https://www.acingov.pt\nEndereço Eletrónico: geral@tnsj.pt\neDelivery Gateway (URL): https://www.acingov.pt\nFunção da Organização: Adquirente\nNorma jurídica da Entidade Adjudicante: Empresa pública, controlada por uma autoridade da administração central\nÁrea de atividade da Autoridade Adjudicante: Atividades recreativas, culturais e religiosas\n2 - JORNAL OFICIAL DA UNIÃO EUROPEIA\nO procedimento a que este anúncio diz respeito também é publicitado no Jornal Oficial da União Europeia? Não\n3 - AVISO\nModelo de Anúncio: Concurso público\nData de Envio do Anúncio: 08-01-2026\n5 - PROCESSO\nTipo de Procedimento: Concurso público\nPreço base do procedimento: Sim\nValor do preço base do procedimento: 61.955,00 EUR\nProcedimento com lotes? Não\n6 - OBJETO DO CONTRATO\nNúmero de referência interna: 02/CPN/2026\nDesignação do contrato: Prestação de Serviços de Impressão dos Cadernos de Programação e Brochuras de Programação (Versão em Inglês)\nDescrição: Prestação de Serviços de Impressão dos Cadernos de Programação e Brochuras de Programação (Versão em Inglês)\nTipo de Contrato Principal: Aquisição de Serviços\nTipo de Contrato: Aquisição de Serviços\nClassificação CPV (Vocabulário Comum para os Contratos Públicos)\nObjeto principal\nVocabulário Principal: 79810000\nPreço base s/IVA: 61.955,00 EUR\n7 - INDICAÇÕES ADICIONAIS\nO contrato envolve aquisição conjunta (satisfação de várias entidades)? Não\nO contrato é adjudicado por uma central de compras? Não\n8 - TÉCNICAS\nO concurso destina-se à celebração de um acordo-quadro? Inexistência de acordo-quadro\nÉ utilizado um leilão eletrónico? Não\nÉ adotada uma fase de negociação? Não\nSistema de Aquisição Dinâmico: Inexistência de sistema de aquisição dinâmico\n9 - LOCAL DA EXECUÇÃO DO CONTRATO\nLOCAL DA EXECUÇÃO DO CONTRATO (PROCEDIMENTO)\nPaís: Portugal\nNUT III: PT111\nLocalidade: União das Freguesias de Cedofeita, Santo Ildefonso, Sé, Miragaia, São Nicolau e Vitória\nDistrito: Porto\nConcelho: Porto\nFreguesia: União das Freguesias de Cedofeita, Santo Ildefonso, Sé, Miragaia, São Nicolau e Vitória\n10 - PRAZO DE EXECUÇÃO DO CONTRATO\nPrazo de execução do contrato: 240 DIAS\nPrevisão de renovações: Não\n11 - FUNDOS EU\nTêm fundos EU? Não\n12 - DOCUMENTOS DE HABILITAÇÃO\nHabilitação para o exercício da atividade profissional: Não\n13 - CONDIÇÕES DE APRESENTAÇÃO\nPlataforma eletrónica utilizada pela entidade adjudicante: ACIN\nURL para Apresentação: https://www.acingov.pt\nAdmissibilidade da apresentação de propostas variantes: Não autorizado\nPrazo para apresentação das propostas: 14-01-2026 23:59\nPrazo durante o qual os concorrentes são obrigados a manter as respetivas propostas: 66 dias a contar do termo do prazo para a apresentação das propostas\nIndicação de Subcontratação na Proposta: A parte do contrato que o proponente tenciona subcontratar\n14 - PRESTAÇÃO DE CAUÇÃO\nPrestação de caução: Não\n15 - FORNECIMENTO DAS PEÇAS DO CONCURSO, APRESENTAÇÃO DE PEDIDOS DE PARTICIPAÇÃO E APRESENTAÇÃO DAS PROPOSTAS\nLink para acesso às peças do concurso (URL): https://www.acingov.pt/acingovprod/2/zonaPublica/zona_publica_c/donwloadProcedurePiece/MTA0MTM1OQ==\n20 - OUTROS REQUISITOS\nInformação sobre contratos reservados. Aplica-se a contratos reservados (54º-A)? Não\n21 - CRITÉRIO DE ADJUDICAÇÃO\nMultifator: Não\nMonofator:\nNome: Preço\n24 - CONDIÇÕES DO CONTRATO\nFaturação Eletrónica: Permitido\nObrigação de Subcontratação:\nCódigo da Obrigação de Subcontratação: Não é aplicável nenhuma obrigação de subcontratação.\n25 - COMPRA PÚBLICA ESTRATÉGICA\nCompra Pública Estratégica: Inexistência de contratação pública estratégica\n26 - INFORMAÇÕES ADICIONAIS\nContrato adequado para PME: Sim\nCobertura ACP (Acordo dos Contratos Públicos da Organização Mundial do Comércio): Não\n27 - IDENTIFICAÇÃO E CONTACTOS DO ÓRGÃO DE RECURSOS ADMINISTRATIVOS\nDesignação: Conselho de Administração do TNSJ\nEndereço: Praça da Batalha\nCódigo postal: 4000-102\nLocalidade: Porto\nTelefone: 223401966\nFax: 222003449\nEndereço eletrónico: contratacaopublica@tnsj.pt\n28 - IDENTIFICAÇÃO DO(S) AUTOR(ES) DE ANÚNCIO\nNome: Cláudia Leite\nCargo: Vogal do Conselho de Administração do TNSJ\n419947527",
    "nipc": "503966908",
    "distrito": "Porto",
    "concelho": "Porto",
    "freguesia": "União das Freguesias de Cedofeita, Santo Ildefonso, Sé, Miragaia, São Nicolau e Vitória",
    "site": "https://www.acingov.pt",
    "email": "geral@tnsj.pt",
    "designacao_contrato": "Prestação de Serviços de Impressão dos Cadernos de Programação e Brochuras de Programação (Versão em Inglês)",
    "descricao": "Prestação de Serviços de Impressão dos Cadernos de Programação e Brochuras de Programação (Versão em Inglês)",
    "preco_base": "61.955,00 EUR",
    "prazo_execucao": "240 DIAS",
    "prazo_apresentacao_propostas": "14-01-2026 23:59",
    "fundos_eu": "Não",
    "plataforma_eletronica": "ACIN",
    "url_procedimento": "https://www.acingov.pt",
    "autor_nome": "Cláudia Leite",
    "autor_cargo": "Vogal do Conselho de Administração do TNSJ"
  },
  {
    "numero_procedimento": "N/A",
    "entidade": "AnÃºncio de procedimento  n.Âº 394/2026  -  DiÃ¡rio da RepÃºblica n.Âº 6/2026, SÃ©rie II de 2026-01-09",
    "link": "https://diariodarepublica.pt/dr/detalhe/contrato-publico/394-1003372800"
  },
  {
    "numero_procedimento": "N/A",
    "entidade": "AnÃºncio de procedimento  n.Âº 396/2026  -  DiÃ¡rio da RepÃºblica n.Âº 6/2026, SÃ©rie II de 2026-01-09",
    "link": "https://diariodarepublica.pt/dr/detalhe/contrato-publico/396-1003372801"
  },
  {
    "numero_procedimento": "N/A",
    "entidade": "Unidade Local de Saúde de Lisboa Ocidental, EPE",
    "link": "https://diariodarepublica.pt/dr/detalhe/contrato-publico/398-1003372802",
    "detalhes_completos": "1 - IDENTIFICAÇÃO E CONTACTOS DA ENTIDADE ADJUDICANTE\nDesignação da entidade adjudicante: Unidade Local de Saúde de Lisboa Ocidental, EPE\nNIPC: 507618319\nEndereço: Santa Maria de Belém  Estrada do Forte do Alto do Duque\nCódigo postal: 1449-005\nLocalidade: Lisboa\nPaís: Portugal\nNUT III: PT170\nDistrito: Lisboa\nConcelho: Lisboa\nFreguesia: Todas\nTelefone: 210431000\nFax: 210431642\nEndereço da Entidade (URL): www.chlo.min-saude.pt/\nEndereço Eletrónico: comprasgeral@ulslo.min-saude.pt\neDelivery Gateway (URL): https://community.vortal.biz/public/\nFunção da Organização: Adquirente\nNorma jurídica da Entidade Adjudicante: Organismo de direito público\nÁrea de atividade da Autoridade Adjudicante: Saúde\n2 - JORNAL OFICIAL DA UNIÃO EUROPEIA\nO procedimento a que este anúncio diz respeito também é publicitado no Jornal Oficial da União Europeia? Sim\n3 - AVISO\nModelo de Anúncio: Concurso público\nData de Envio do Anúncio: 07-01-2026\n5 - PROCESSO\nTipo de Procedimento: Concurso público\nPreço base do procedimento: Sim\nValor do preço base do procedimento: 248.166,00 EUR\nProcedimento com lotes? Não\n6 - OBJETO DO CONTRATO\nNúmero de referência interna: 147001026\nDesignação do contrato: Prestação de serviços de interrupção voluntária da gravidez na ULSLO, E.P.E. em 2026\nDescrição: Prestação de serviços de interrupção voluntária da gravidez na ULSLO, E.P.E. em 2026\nOpções: Não\nTipo de Contrato Principal: Aquisição de Serviços\nTipo de Contrato: Aquisição de Serviços\nClassificação CPV (Vocabulário Comum para os Contratos Públicos)\nObjeto principal\nVocabulário Principal: 85111320\nPreço base s/IVA: 248.166,00 EUR\n7 - INDICAÇÕES ADICIONAIS\nO contrato envolve aquisição conjunta (satisfação de várias entidades)? Não\nO contrato é adjudicado por uma central de compras? Não\n8 - TÉCNICAS\nO concurso destina-se à celebração de um acordo-quadro? Inexistência de acordo-quadro\nÉ utilizado um leilão eletrónico? Não\nÉ adotada uma fase de negociação? Não\nSistema de Aquisição Dinâmico: Inexistência de sistema de aquisição dinâmico\n9 - LOCAL DA EXECUÇÃO DO CONTRATO\nLOCAL DA EXECUÇÃO DO CONTRATO (PROCEDIMENTO)\nPaís: Portugal\nNUT III: PT170\nLocalidade: Lisboa\nDistrito: Lisboa\nConcelho: Lisboa\nFreguesia: Todas\n10 - PRAZO DE EXECUÇÃO DO CONTRATO\nPrazo de execução do contrato: 12 MESES\nPrevisão de renovações: Não\n11 - FUNDOS EU\nTêm fundos EU? Não\n12 - DOCUMENTOS DE HABILITAÇÃO\nHabilitação para o exercício da atividade profissional: Não\n13 - CONDIÇÕES DE APRESENTAÇÃO\nPlataforma eletrónica utilizada pela entidade adjudicante: VORTAL\nURL para Apresentação: https://community.vortal.biz/public/\nAdmissibilidade da apresentação de propostas variantes: Não autorizado\nPrazo para apresentação das propostas: 12-02-2026 17:00\nPrazo durante o qual os concorrentes são obrigados a manter as respetivas propostas: 66 dias a contar do termo do prazo para a apresentação das propostas\nApresentação de Catálogo Eletrónico: Não autorizado\nIndicação de Subcontratação na Proposta: Inexistência de indicação de subcontratação\n14 - PRESTAÇÃO DE CAUÇÃO\nPrestação de caução: Não\n15 - FORNECIMENTO DAS PEÇAS DO CONCURSO, APRESENTAÇÃO DE PEDIDOS DE PARTICIPAÇÃO E APRESENTAÇÃO DAS PROPOSTAS\nLink para acesso às peças do concurso (URL): https://community.vortal.biz/Public/public-tender-documents/Rnp2MGNtZzVKbXdjVDdvdmFWY3Y5Y1JuTlVHbi9WQXE2NVppTkZzdStWY1ZqL0ZwVlRjbjRhbGk4S1QybFVRamNhV0R5S3JpTEJNNFc5SGJQMm9zblE9PXF0RWFQ\n20 - OUTROS REQUISITOS\nInformação sobre contratos reservados. Aplica-se a contratos reservados (54º-A)? Não\n21 - CRITÉRIO DE ADJUDICAÇÃO\nMultifator: Não\nMonofator:\nNome: Preço\n24 - CONDIÇÕES DO CONTRATO\nFaturação Eletrónica: Permitido\nObrigação de Subcontratação:\nCódigo da Obrigação de Subcontratação: Não é aplicável nenhuma obrigação de subcontratação.\n25 - COMPRA PÚBLICA ESTRATÉGICA\nCompra Pública Estratégica: Inexistência de contratação pública estratégica\n26 - INFORMAÇÕES ADICIONAIS\nContrato adequado para PME: Sim\nCobertura ACP (Acordo dos Contratos Públicos da Organização Mundial do Comércio): Não\n27 - IDENTIFICAÇÃO E CONTACTOS DO ÓRGÃO DE RECURSOS ADMINISTRATIVOS\nDesignação: Serviço de Gestão de Compras\nEndereço: Estrada do Forte do Alto  do Duque\nCódigo postal: 1449-005\nLocalidade: Lisboa\nTelefone: +351 210431000\nFax: +351 210431639\nEndereço eletrónico: compras.adm.hot.ps.inv@ulslo.min-saude.pt\n28 - IDENTIFICAÇÃO DO(S) AUTOR(ES) DE ANÚNCIO\nNome: Salomé Pedro\nCargo: Técnica Superior\n419947178",
    "nipc": "507618319",
    "distrito": "Lisboa",
    "concelho": "Lisboa",
    "freguesia": "Todas",
    "site": "www.chlo.min-saude.pt/",
    "email": "comprasgeral@ulslo.min-saude.pt",
    "designacao_contrato": "Prestação de serviços de interrupção voluntária da gravidez na ULSLO, E.P.E. em 2026",
    "descricao": "Prestação de serviços de interrupção voluntária da gravidez na ULSLO, E.P.E. em 2026",
    "preco_base": "248.166,00 EUR",
    "prazo_execucao": "12 MESES",
    "prazo_apresentacao_propostas": "12-02-2026 17:00",
    "fundos_eu": "Não",
    "plataforma_eletronica": "VORTAL",
    "url_procedimento": "https://community.vortal.biz/public/",
    "autor_nome": "Salomé Pedro",
    "autor_cargo": "Técnica Superior"
  },
  {
    "numero_procedimento": "N/A",
    "entidade": "Unidade Local de Saúde da Lezíria, EPE",
    "link": "https://diariodarepublica.pt/dr/detalhe/contrato-publico/400-1003372803",
    "detalhes_completos": "1 - IDENTIFICAÇÃO E CONTACTOS DA ENTIDADE ADJUDICANTE\nDesignação da entidade adjudicante: Unidade Local de Saúde da Lezíria, EPE\nNIPC: 506361462\nEndereço: Av. Bernardo Santareno S/N\nCódigo postal: 2005-177\nLocalidade: Santarém\nPaís: Portugal\nNUT III: PT185\nDistrito: Santarém\nConcelho: Santarém\nFreguesia: União de Freguesias da Cidade de Santarém\nTelefone: 243300200\nFax: 243370220\nEndereço da Entidade (URL): www.hds.min-saude.pt\nEndereço Eletrónico: hdsca@hds.min-saude.pt\neDelivery Gateway (URL): https://community.vortal.biz/public/\nFunção da Organização: Adquirente\nNorma jurídica da Entidade Adjudicante: Organismo de direito público\nÁrea de atividade da Autoridade Adjudicante: Saúde\n2 - JORNAL OFICIAL DA UNIÃO EUROPEIA\nO procedimento a que este anúncio diz respeito também é publicitado no Jornal Oficial da União Europeia? Sim\n3 - AVISO\nModelo de Anúncio: Concurso público\nData de Envio do Anúncio: 07-01-2026\n5 - PROCESSO\nTipo de Procedimento: Concurso público\nPreço base do procedimento: Sim\nValor do preço base do procedimento: 499.908,00 EUR\nProcedimento com lotes? Sim\nNº Máx. de Lotes Autorizado: 6\nNúmero máximo de lotes que podem ser adjudicados a um concorrente: 6\n6 - OBJETO DO CONTRATO\nNúmero de referência interna: 140001/2026 Cópia\nDesignação do contrato: AQUISIÇÃO DE ARTIGOS EM PAPEL PARA HIGIENE E LIMPEZA\nDescrição: AQUISIÇÃO DE ARTIGOS EM PAPEL PARA HIGIENE E LIMPEZA \nOpções: Não\nTipo de Contrato Principal: Aquisição de Bens Móveis\nTipo de Contrato: Aquisição de Bens Móveis\nClassificação CPV (Vocabulário Comum para os Contratos Públicos)\nObjeto principal\nVocabulário Principal: 33140000\nPreço base s/IVA: 499.908,00 EUR\nLotes: \nNº: LOT-0001\nDescrição do Lote: Lote 1\nPreço base s/IVA: 141.180,00 EUR\nClassificação CPV (Vocabulário Comum para os Contratos Públicos)\nObjeto principal\nVocabulário Principal: 33140000\nNº: LOT-0002\nDescrição do Lote: Lote 2\nPreço base s/IVA: 28.044,00 EUR\nClassificação CPV (Vocabulário Comum para os Contratos Públicos)\nObjeto principal\nVocabulário Principal: 33140000\nNº: LOT-0003\nDescrição do Lote: Lote 3\nPreço base s/IVA: 60.000,00 EUR\nClassificação CPV (Vocabulário Comum para os Contratos Públicos)\nObjeto principal\nVocabulário Principal: 33140000\nNº: LOT-0004\nDescrição do Lote: Lote 4\nPreço base s/IVA: 48.960,00 EUR\nClassificação CPV (Vocabulário Comum para os Contratos Públicos)\nObjeto principal\nVocabulário Principal: 33140000\nNº: LOT-0005\nDescrição do Lote: Lote 5\nPreço base s/IVA: 215.604,00 EUR\nClassificação CPV (Vocabulário Comum para os Contratos Públicos)\nObjeto principal\nVocabulário Principal: 33140000\nNº: LOT-0006\nDescrição do Lote: Lote 6\nPreço base s/IVA: 6.120,00 EUR\nClassificação CPV (Vocabulário Comum para os Contratos Públicos)\nObjeto principal\nVocabulário Principal: 33140000\n7 - INDICAÇÕES ADICIONAIS\nO contrato envolve aquisição conjunta (satisfação de várias entidades)? Não\nO contrato é adjudicado por uma central de compras? Não\n8 - TÉCNICAS\nO concurso destina-se à celebração de um acordo-quadro? Inexistência de acordo-quadro\nÉ utilizado um leilão eletrónico? Não\nÉ adotada uma fase de negociação? Não\nSistema de Aquisição Dinâmico: Inexistência de sistema de aquisição dinâmico\n9 - LOCAL DA EXECUÇÃO DO CONTRATO\nLOCAL DA EXECUÇÃO DO CONTRATO (PROCEDIMENTO)\nPaís: Portugal\nNUT III: PTZZZ\nLocalidade: PORTUGAL\nDistrito: Todos\nConcelho: Todos\nFreguesia: Todas\nLOCAL DA EXECUÇÃO DO CONTRATO (LOTE)\nIdentificador do Lote: LOT-0001; LOT-0002; LOT-0003; LOT-0004; LOT-0005; LOT-0006\nPaís: Portugal\nNUT III: PTZZZ\nLocalidade: PORTUGAL\nDistrito: Todos\nConcelho: Todos\nFreguesia: Todas\n10 - PRAZO DE EXECUÇÃO DO CONTRATO\nIdentificador do Lote: LOT-0001; LOT-0002; LOT-0003; LOT-0004; LOT-0005; LOT-0006\nPrazo de execução do contrato: 3 ANOS\nPrevisão de renovações: Não\n11 - FUNDOS EU\nIdentificador do Lote: LOT-0001; LOT-0002; LOT-0003; LOT-0004; LOT-0005; LOT-0006\nTêm fundos EU? Não\n12 - DOCUMENTOS DE HABILITAÇÃO\nHabilitação para o exercício da atividade profissional: Não\n13 - CONDIÇÕES DE APRESENTAÇÃO\nPlataforma eletrónica utilizada pela entidade adjudicante: VORTAL\nURL para Apresentação: https://community.vortal.biz/public/\nAdmissibilidade da apresentação de propostas variantes: Não autorizado\nPrazo para apresentação das propostas: 05-02-2026 23:59\nPrazo durante o qual os concorrentes são obrigados a manter as respetivas propostas: 66 dias a contar do termo do prazo para a apresentação das propostas\nApresentação de Catálogo Eletrónico: Permitido\nIndicação de Subcontratação na Proposta: Inexistência de indicação de subcontratação\n14 - PRESTAÇÃO DE CAUÇÃO\nPrestação de caução: Não\n15 - FORNECIMENTO DAS PEÇAS DO CONCURSO, APRESENTAÇÃO DE PEDIDOS DE PARTICIPAÇÃO E APRESENTAÇÃO DAS PROPOSTAS\nLink para acesso às peças do concurso (URL): https://community.vortal.biz/Public/public-tender-documents/dS9kczFUQURHdVJoMkhlbjlRSjFYdHkvTkkvcVlYTzFWQUxRSUFLbFhhWWFKK01DS2ZvUUNkTk5SbFBZMDMwOUZENXpBZGh6MzBka29WQVYrSklWMWc9PVRxaGh1\n20 - OUTROS REQUISITOS\nIdentificador do Lote: LOT-0001; LOT-0002; LOT-0003; LOT-0004; LOT-0005; LOT-0006\nInformação sobre contratos reservados. Aplica-se a contratos reservados (54º-A)? Não\n21 - CRITÉRIO DE ADJUDICAÇÃO\nO Critério de adjudicação é diferenciado por lote? Não\nMultifator: Não\nMonofator:\nNome: Preço\n24 - CONDIÇÕES DO CONTRATO\nIdentificador do Lote: LOT-0001; LOT-0002; LOT-0003; LOT-0004; LOT-0005; LOT-0006\nFaturação Eletrónica: Permitido\nObrigação de Subcontratação:\nCódigo da Obrigação de Subcontratação: Não é aplicável nenhuma obrigação de subcontratação.\n25 - COMPRA PÚBLICA ESTRATÉGICA\nCompra Pública Estratégica: Inexistência de contratação pública estratégica\n26 - INFORMAÇÕES ADICIONAIS\nIdentificador do Lote: LOT-0001; LOT-0002; LOT-0003; LOT-0004; LOT-0005; LOT-0006\nContrato adequado para PME: Sim\nCobertura ACP (Acordo dos Contratos Públicos da Organização Mundial do Comércio): Não\n27 - IDENTIFICAÇÃO E CONTACTOS DO ÓRGÃO DE RECURSOS ADMINISTRATIVOS\nDesignação: Conselho de Administração da Unidade Local de Saúde da Lezíria\nEndereço: Av. Bernardo Santareno\nCódigo postal: 2005-177\nLocalidade: Santarém\nTelefone: +351 243300200\nFax: +351 243370220\nEndereço eletrónico: ca@ulsleziria.min-saude.pt\n28 - IDENTIFICAÇÃO DO(S) AUTOR(ES) DE ANÚNCIO\nNome: Pedro Manuel Dias de Figueiredo Pereira Marques\nCargo: Presidente do Conselho de Administração\n419947263",
    "nipc": "506361462",
    "distrito": "Santarém",
    "concelho": "Santarém",
    "freguesia": "União de Freguesias da Cidade de Santarém",
    "site": "www.hds.min-saude.pt",
    "email": "hdsca@hds.min-saude.pt",
    "designacao_contrato": "AQUISIÇÃO DE ARTIGOS EM PAPEL PARA HIGIENE E LIMPEZA",
    "descricao": "AQUISIÇÃO DE ARTIGOS EM PAPEL PARA HIGIENE E LIMPEZA",
    "preco_base": "499.908,00 EUR",
    "prazo_execucao": "3 ANOS",
    "prazo_apresentacao_propostas": "05-02-2026 23:59",
    "fundos_eu": "Não",
    "plataforma_eletronica": "VORTAL",
    "url_procedimento": "https://community.vortal.biz/public/",
    "autor_nome": "Pedro Manuel Dias de Figueiredo Pereira Marques",
    "autor_cargo": "Presidente do Conselho de Administração"
  },
  {
    "numero_procedimento": "N/A",
    "entidade": "Unidade Local de Saúde da Lezíria, EPE",
    "link": "https://diariodarepublica.pt/dr/detalhe/contrato-publico/402-1003372804",
    "detalhes_completos": "1 - IDENTIFICAÇÃO E CONTACTOS DA ENTIDADE ADJUDICANTE\nDesignação da entidade adjudicante: Unidade Local de Saúde da Lezíria, EPE\nNIPC: 506361462\nEndereço: Av. Bernardo Santareno S/N\nCódigo postal: 2005-177\nLocalidade: Santarém\nPaís: Portugal\nNUT III: PT185\nDistrito: Santarém\nConcelho: Santarém\nFreguesia: União de Freguesias da Cidade de Santarém\nTelefone: 243300200\nFax: 243370220\nEndereço da Entidade (URL): www.hds.min-saude.pt\nEndereço Eletrónico: hdsca@hds.min-saude.pt\neDelivery Gateway (URL): https://community.vortal.biz/public/\nFunção da Organização: Adquirente\nNorma jurídica da Entidade Adjudicante: Organismo de direito público\nÁrea de atividade da Autoridade Adjudicante: Saúde\n2 - JORNAL OFICIAL DA UNIÃO EUROPEIA\nO procedimento a que este anúncio diz respeito também é publicitado no Jornal Oficial da União Europeia? Sim\n3 - AVISO\nModelo de Anúncio: Concurso público\nData de Envio do Anúncio: 07-01-2026\n5 - PROCESSO\nTipo de Procedimento: Concurso público\nPreço base do procedimento: Sim\nValor do preço base do procedimento: 400.000,00 EUR\nProcedimento com lotes? Não\n6 - OBJETO DO CONTRATO\nNúmero de referência interna: 170024/2025\nDesignação do contrato: Aquisição e Instalação de Sistema de Mamografia Digital\nDescrição: 170024/2025 - Aquisição e Instalação de Sistema de Mamografia Digital\nOpções: Não\nTipo de Contrato Principal: Aquisição de Bens Móveis\nTipo de Contrato: Aquisição de Bens Móveis\nClassificação CPV (Vocabulário Comum para os Contratos Públicos)\nObjeto principal\nVocabulário Principal: 33111650\nPreço base s/IVA: 400.000,00 EUR\n7 - INDICAÇÕES ADICIONAIS\nO contrato envolve aquisição conjunta (satisfação de várias entidades)? Não\nO contrato é adjudicado por uma central de compras? Não\n8 - TÉCNICAS\nO concurso destina-se à celebração de um acordo-quadro? Inexistência de acordo-quadro\nÉ utilizado um leilão eletrónico? Não\nÉ adotada uma fase de negociação? Não\nSistema de Aquisição Dinâmico: Inexistência de sistema de aquisição dinâmico\n9 - LOCAL DA EXECUÇÃO DO CONTRATO\nLOCAL DA EXECUÇÃO DO CONTRATO (PROCEDIMENTO)\nPaís: Portugal\nNUT III: PT185\nLocalidade: Santarém\nDistrito: Santarém\nConcelho: Santarém\nFreguesia: União de Freguesias da Cidade de Santarém\n10 - PRAZO DE EXECUÇÃO DO CONTRATO\nPrazo de execução do contrato: 12 MESES\nPrevisão de renovações: Não\n11 - FUNDOS EU\nTêm fundos EU? Não\n12 - DOCUMENTOS DE HABILITAÇÃO\nHabilitação para o exercício da atividade profissional: Não\n13 - CONDIÇÕES DE APRESENTAÇÃO\nPlataforma eletrónica utilizada pela entidade adjudicante: VORTAL\nURL para Apresentação: https://community.vortal.biz/public/\nAdmissibilidade da apresentação de propostas variantes: Não autorizado\nPrazo para apresentação das propostas: 07-02-2026 23:59\nPrazo durante o qual os concorrentes são obrigados a manter as respetivas propostas: 66 dias a contar do termo do prazo para a apresentação das propostas\nApresentação de Catálogo Eletrónico: Permitido\nIndicação de Subcontratação na Proposta: Inexistência de indicação de subcontratação\n14 - PRESTAÇÃO DE CAUÇÃO\nPrestação de caução: Não\n15 - FORNECIMENTO DAS PEÇAS DO CONCURSO, APRESENTAÇÃO DE PEDIDOS DE PARTICIPAÇÃO E APRESENTAÇÃO DAS PROPOSTAS\nLink para acesso às peças do concurso (URL): https://community.vortal.biz/Public/public-tender-documents/RWlwc211MytsS2FxOG5JbHR0b3h1c0lEWVJNaTQxODZMUlZnSVhvbFlQTGdaamlwZTJrNVppQm5meUordUp1ZkJkVjdCR0hQa0dJVXhrZEpMRW96M0E9PXNIVSZs\n20 - OUTROS REQUISITOS\nInformação sobre contratos reservados. Aplica-se a contratos reservados (54º-A)? Não\n21 - CRITÉRIO DE ADJUDICAÇÃO\nMultifator: Sim\nFator: \nNome: Preço\nPonderação: 50%\nSubfatores: Não\nFator: \nNome: Qualidade\nPonderação: 45%\nSubfatores: Não\nFator: \nNome: Qualidade\nPonderação: 5%\nSubfatores: Não\n24 - CONDIÇÕES DO CONTRATO\nFaturação Eletrónica: Permitido\nObrigação de Subcontratação:\nCódigo da Obrigação de Subcontratação: Não é aplicável nenhuma obrigação de subcontratação.\n25 - COMPRA PÚBLICA ESTRATÉGICA\nCompra Pública Estratégica: Inexistência de contratação pública estratégica\n26 - INFORMAÇÕES ADICIONAIS\nContrato adequado para PME: Sim\nCobertura ACP (Acordo dos Contratos Públicos da Organização Mundial do Comércio): Não\n27 - IDENTIFICAÇÃO E CONTACTOS DO ÓRGÃO DE RECURSOS ADMINISTRATIVOS\nDesignação: Conselho de Administração da ULSL\nEndereço: Avenida Bernardo santareno S/N\nCódigo postal: 2005-177\nLocalidade: Santarém\nTelefone: +351 243300200\nFax: +351 243300224\nEndereço eletrónico: ca@ulsleziria.min-saide.pt\n28 - IDENTIFICAÇÃO DO(S) AUTOR(ES) DE ANÚNCIO\nNome: Pedro Manuel Dias de Figueiredo Pereira Marques\nCargo: Presidente do Conselho de Administração da  ULSL\n419947291",
    "nipc": "506361462",
    "distrito": "Santarém",
    "concelho": "Santarém",
    "freguesia": "União de Freguesias da Cidade de Santarém",
    "site": "www.hds.min-saude.pt",
    "email": "hdsca@hds.min-saude.pt",
    "designacao_contrato": "Aquisição e Instalação de Sistema de Mamografia Digital",
    "descricao": "170024/2025 - Aquisição e Instalação de Sistema de Mamografia Digital",
    "preco_base": "400.000,00 EUR",
    "prazo_execucao": "12 MESES",
    "prazo_apresentacao_propostas": "07-02-2026 23:59",
    "fundos_eu": "Não",
    "plataforma_eletronica": "VORTAL",
    "url_procedimento": "https://community.vortal.biz/public/",
    "autor_nome": "Pedro Manuel Dias de Figueiredo Pereira Marques",
    "autor_cargo": "Presidente do Conselho de Administração da ULSL"
  },
  {
    "numero_procedimento": "N/A",
    "entidade": "Município de Espinho",
    "link": "https://diariodarepublica.pt/dr/detalhe/contrato-publico/404-1003372805",
    "detalhes_completos": "1 - IDENTIFICAÇÃO E CONTACTOS DA ENTIDADE ADJUDICANTE\nDesignação da entidade adjudicante: Município de Espinho\nNIPC: 501158740\nServiço/Órgão/Pessoa de contacto: Presidente da Câmara Municipal\nEndereço: Praça Dr. José de Oliveira Salvador - Apartado 700\nCódigo postal: 4501-901\nLocalidade: Espinho\nPaís: Portugal\nNUT III: PT11A\nDistrito: Aveiro\nConcelho: Espinho\nFreguesia: Todas\nTelefone: 227335800\nFax: 227335852\nEndereço da Entidade (URL): www.cm-espinho.pt\nEndereço Eletrónico: contratacao.publica@cm-espinho.pt\neDelivery Gateway (URL): https://www.acingov.pt\nFunção da Organização: Adquirente\nNorma jurídica da Entidade Adjudicante: Autoridade local\nÁrea de atividade da Autoridade Adjudicante: Serviços públicos das administrações públicas\n2 - JORNAL OFICIAL DA UNIÃO EUROPEIA\nO procedimento a que este anúncio diz respeito também é publicitado no Jornal Oficial da União Europeia? Sim\n3 - AVISO\nModelo de Anúncio: Concurso público\nData de Envio do Anúncio: 07-01-2026\n5 - PROCESSO\nTipo de Procedimento: Concurso público\nPreço base do procedimento: Sim\nValor do preço base do procedimento: 345.000,00 EUR\nProcedimento com lotes? Não\n6 - OBJETO DO CONTRATO\nNúmero de referência interna: 2025CPI14622S\nDesignação do contrato: Aquisição de Seguros - 2026\nDescrição: Aquisição de Seguros - 2026\nOpções: Não\nTipo de Contrato Principal: Aquisição de Serviços\nTipo de Contrato: Aquisição de Serviços\nClassificação CPV (Vocabulário Comum para os Contratos Públicos)\nObjeto principal\nVocabulário Principal: 66512000\nPreço base s/IVA: 345.000,00 EUR\n7 - INDICAÇÕES ADICIONAIS\nO contrato envolve aquisição conjunta (satisfação de várias entidades)? Não\nO contrato é adjudicado por uma central de compras? Não\n8 - TÉCNICAS\nO concurso destina-se à celebração de um acordo-quadro? Inexistência de acordo-quadro\nÉ utilizado um leilão eletrónico? Não\nÉ adotada uma fase de negociação? Não\nSistema de Aquisição Dinâmico: Inexistência de sistema de aquisição dinâmico\n9 - LOCAL DA EXECUÇÃO DO CONTRATO\nLOCAL DA EXECUÇÃO DO CONTRATO (PROCEDIMENTO)\nPaís: Portugal\nNUT III: PT11A\nLocalidade: Espinho\nDistrito: Aveiro\nConcelho: Espinho\nFreguesia: Todas\n10 - PRAZO DE EXECUÇÃO DO CONTRATO\nData de Início: 01-03-2026\nData de Fim: 28-02-2027\nPrevisão de renovações: Não\n11 - FUNDOS EU\nTêm fundos EU? Não\n12 - DOCUMENTOS DE HABILITAÇÃO\nHabilitação para o exercício da atividade profissional: Sim\nTipo: Outros\nDescrição - Outros: Documento comprovativo da titularidade das habilitações legalmente exigidas para a prestação dos serviços, nomeadamente, declaração da Autoridade de Supervisão de Seguros e Fundos de Pensões para o exercício da atividade de seguros\nDescrição: Documento comprovativo da titularidade das habilitações legalmente exigidas para a prestação dos serviços, nomeadamente, declaração da Autoridade de Supervisão de Seguros e Fundos de Pensões para o exercício da atividade de seguros\n13 - CONDIÇÕES DE APRESENTAÇÃO\nPlataforma eletrónica utilizada pela entidade adjudicante: ACIN\nURL para Apresentação: https://www.acingov.pt\nAdmissibilidade da apresentação de propostas variantes: Não autorizado\nPrazo para apresentação das propostas: 13-02-2026 23:59\nPrazo durante o qual os concorrentes são obrigados a manter as respetivas propostas: 66 dias a contar do termo do prazo para a apresentação das propostas\nApresentação de Catálogo Eletrónico: Permitido\nIndicação de Subcontratação na Proposta: Inexistência de indicação de subcontratação\n14 - PRESTAÇÃO DE CAUÇÃO\nPrestação de caução: Não\n15 - FORNECIMENTO DAS PEÇAS DO CONCURSO, APRESENTAÇÃO DE PEDIDOS DE PARTICIPAÇÃO E APRESENTAÇÃO DAS PROPOSTAS\nLink para acesso às peças do concurso (URL): https://www.acingov.pt/acingovprod/2/zonaPublica/zona_publica_c/donwloadProcedurePiece/MTAzNjI5OA==\n20 - OUTROS REQUISITOS\nInformação sobre contratos reservados. Aplica-se a contratos reservados (54º-A)? Não\n21 - CRITÉRIO DE ADJUDICAÇÃO\nMultifator: Não\nMonofator:\nNome: Preço\n24 - CONDIÇÕES DO CONTRATO\nFaturação Eletrónica: Permitido\nObrigação de Subcontratação:\nCódigo da Obrigação de Subcontratação: Não é aplicável nenhuma obrigação de subcontratação.\n25 - COMPRA PÚBLICA ESTRATÉGICA\nCompra Pública Estratégica: Inexistência de contratação pública estratégica\n26 - INFORMAÇÕES ADICIONAIS\nContrato adequado para PME: Sim\nCobertura ACP (Acordo dos Contratos Públicos da Organização Mundial do Comércio): Não\n27 - IDENTIFICAÇÃO E CONTACTOS DO ÓRGÃO DE RECURSOS ADMINISTRATIVOS\nDesignação: Presidente da Câmara Municipal de Espinho\nEndereço: Praça Dr. José de Oliveira Salvador - Apartado 700\nCódigo postal: 4501-901\nLocalidade: Espinho\nTelefone: 227335800\nFax: \nEndereço eletrónico: contratacao.publica@cm-espinho.pt\n28 - IDENTIFICAÇÃO DO(S) AUTOR(ES) DE ANÚNCIO\nNome: Jorge Manuel Mengo Ratola\nCargo: Presidente da Câmara Municipal\n419947304",
    "nipc": "501158740",
    "distrito": "Aveiro",
    "concelho": "Espinho",
    "freguesia": "Todas",
    "site": "www.cm-espinho.pt",
    "email": "contratacao.publica@cm-espinho.pt",
    "designacao_contrato": "Aquisição de Seguros - 2026",
    "descricao": "Aquisição de Seguros - 2026",
    "preco_base": "345.000,00 EUR",
    "prazo_execucao": null,
    "prazo_apresentacao_propostas": "13-02-2026 23:59",
    "fundos_eu": "Não",
    "plataforma_eletronica": "ACIN",
    "url_procedimento": "https://www.acingov.pt",
    "autor_nome": "Jorge Manuel Mengo Ratola",
    "autor_cargo": "Presidente da Câmara Municipal"
  },
  {
    "numero_procedimento": "N/A",
    "entidade": "AnÃºncio de procedimento  n.Âº 406/2026  -  DiÃ¡rio da RepÃºblica n.Âº 6/2026, SÃ©rie II de 2026-01-09",
    "link": "https://diariodarepublica.pt/dr/detalhe/contrato-publico/406-1003372806"
  },
  {
    "numero_procedimento": "N/A",
    "entidade": "AnÃºncio de procedimento  n.Âº 408/2026  -  DiÃ¡rio da RepÃºblica n.Âº 6/2026, SÃ©rie II de 2026-01-09",
    "link": "https://diariodarepublica.pt/dr/detalhe/contrato-publico/408-1003372807"
  },
  {
    "numero_procedimento": "N/A",
    "entidade": "AnÃºncio de procedimento  n.Âº 410/2026  -  DiÃ¡rio da RepÃºblica n.Âº 6/2026, SÃ©rie II de 2026-01-09",
    "link": "https://diariodarepublica.pt/dr/detalhe/contrato-publico/410-1003372808"
  },
  {
    "numero_procedimento": "N/A",
    "entidade": "AnÃºncio de procedimento  n.Âº 412/2026  -  DiÃ¡rio da RepÃºblica n.Âº 6/2026, SÃ©rie II de 2026-01-09",
    "link": "https://diariodarepublica.pt/dr/detalhe/contrato-publico/412-1003372809"
  },
  {
    "numero_procedimento": "N/A",
    "entidade": "Secretaria-Geral do Ministério da Administração Interna",
    "link": "https://diariodarepublica.pt/dr/detalhe/contrato-publico/414-1003372810",
    "detalhes_completos": "Alteração do Anúncio de procedimento n.º 31784/2025, de 2025-12-09, com o ID 419847312\n1 - IDENTIFICAÇÃO E CONTACTOS DA ENTIDADE ADJUDICANTE\nDesignação da entidade adjudicante: Secretaria-Geral do Ministério da Administração Interna\nNIPC: 600014665\nEndereço: Rua São Mamede, 23\nCódigo postal: 1100-523\nLocalidade: Lisboa\nPaís: Portugal\nNUT III: PT170\nDistrito: Lisboa\nConcelho: Lisboa\nFreguesia: Freguesia de Santa Maria Maior - Lisboa\nTelefone: 213409000\nFax: 213409010\nEndereço da Entidade (URL): www.sg.mai.gov.pt/\nEndereço Eletrónico: gab.sec.geral@sg.mai.gov.pt\neDelivery Gateway (URL): https://community.vortal.biz/public/\nFunção da Organização: Adquirente\nNorma jurídica da Entidade Adjudicante: Autoridade da administração central\nÁrea de atividade da Autoridade Adjudicante: Serviços públicos das administrações públicas\n2 - JORNAL OFICIAL DA UNIÃO EUROPEIA\nO procedimento a que este anúncio diz respeito também é publicitado no Jornal Oficial da União Europeia? Sim\n3 - AVISO\nModelo de Anúncio: Concurso público\nData de Envio do Anúncio: 07-01-2026\n5 - PROCESSO\nTipo de Procedimento: Concurso público\nPreço base do procedimento: Sim\nValor do preço base do procedimento: 7.759.250,00 EUR\nProcedimento com lotes? Sim\nNº Máx. de Lotes Autorizado: 9\nNúmero máximo de lotes que podem ser adjudicados a um concorrente: 9\n6 - OBJETO DO CONTRATO\nNúmero de referência interna: Proc.12/DPIE/2025\nDesignação do contrato: Aquisição de computadores de secretária, computadores de elevado desempenho, portáteis e periféricos, para a GNR e PSP, para os anos de 2025 e 2026, no âmbito do DLPIEFSS\nDescrição: Aquisição de computadores de secretária, computadores de elevado desempenho, portáteis e periféricos, para a GNR e PSP, para os anos de 2025 e 2026, no âmbito do DLPIEFSS\nOpções: Não\nTipo de Contrato Principal: Aquisição de Bens Móveis\nTipo de Contrato: Aquisição de Bens Móveis\nClassificação CPV (Vocabulário Comum para os Contratos Públicos)\nObjeto principal\nVocabulário Principal: 30200000\nPreço base s/IVA: 7.759.250,00 EUR\nLotes: \nNº: LOT-0001\nDescrição do Lote: Lote 1 - Computadores de Secretária (completos) para a GNR e para a PSP\nPreço base s/IVA: 4.267.500,00 EUR\nClassificação CPV (Vocabulário Comum para os Contratos Públicos)\nObjeto principal\nVocabulário Principal: 30200000\nNº: LOT-0002\nDescrição do Lote: Lote 2 - Computadores de elevado desempenho c/ 2 monitores de 24” para a GNR e para a PSP\nPreço base s/IVA: 507.500,00 EUR\nClassificação CPV (Vocabulário Comum para os Contratos Públicos)\nObjeto principal\nVocabulário Principal: 30200000\nNº: LOT-0003\nDescrição do Lote: Lote 3 - Computadores Portáteis leves com monitor Hub/Dock e mala de transporte, para a GNR e para a PSP e Computadores Portáteis leves com rato ótico USB e mala de transporte, para a PSP;\nPreço base s/IVA: 2.020.000,00 EUR\nClassificação CPV (Vocabulário Comum para os Contratos Públicos)\nObjeto principal\nVocabulário Principal: 30200000\nNº: LOT-0004\nDescrição do Lote: Lote 4 - Diversos Monitores para a GNR e para a PSP\nPreço base s/IVA: 514.100,00 EUR\nClassificação CPV (Vocabulário Comum para os Contratos Públicos)\nObjeto principal\nVocabulário Principal: 30200000\nNº: LOT-0005\nDescrição do Lote: Lote 5 - Aquisição de Periféricos de Armazenamento para a PSP\nPreço base s/IVA: 55.700,00 EUR\nClassificação CPV (Vocabulário Comum para os Contratos Públicos)\nObjeto principal\nVocabulário Principal: 30200000\nNº: LOT-0006\nDescrição do Lote: Lote 6 - Aquisição de Periféricos diversos para a GNR e para a PSP\nPreço base s/IVA: 144.350,00 EUR\nClassificação CPV (Vocabulário Comum para os Contratos Públicos)\nObjeto principal\nVocabulário Principal: 30200000\nNº: LOT-0007\nDescrição do Lote: Lote 7 - Aquisição de Digitalizadores de mesa para a PSP\nPreço base s/IVA: 48.100,00 EUR\nClassificação CPV (Vocabulário Comum para os Contratos Públicos)\nObjeto principal\nVocabulário Principal: 30200000\nNº: LOT-0008\nDescrição do Lote: Lote 8 - Aquisição de Digitalizadores de alto desempenho para a PSP\nPreço base s/IVA: 56.000,00 EUR\nClassificação CPV (Vocabulário Comum para os Contratos Públicos)\nObjeto principal\nVocabulário Principal: 30200000\nNº: LOT-0009\nDescrição do Lote: Lote 9 - Aquisição de Impressoras portáteis para a PSP\nPreço base s/IVA: 146.000,00 EUR\nClassificação CPV (Vocabulário Comum para os Contratos Públicos)\nObjeto principal\nVocabulário Principal: 30200000\n7 - INDICAÇÕES ADICIONAIS\nO contrato envolve aquisição conjunta (satisfação de várias entidades)? Não\nO contrato é adjudicado por uma central de compras? Não\n8 - TÉCNICAS\nO concurso destina-se à celebração de um acordo-quadro? Inexistência de acordo-quadro\nÉ utilizado um leilão eletrónico? Não\nÉ adotada uma fase de negociação? Não\nSistema de Aquisição Dinâmico: Inexistência de sistema de aquisição dinâmico\n9 - LOCAL DA EXECUÇÃO DO CONTRATO\nLOCAL DA EXECUÇÃO DO CONTRATO (PROCEDIMENTO)\nPaís: Portugal\nNUT III: PT170\nLocalidade: Lisboa\nDistrito: Lisboa\nConcelho: Lisboa\nFreguesia: Todas\nLOCAL DA EXECUÇÃO DO CONTRATO (LOTE)\nIdentificador do Lote: LOT-0001; LOT-0002; LOT-0003; LOT-0004; LOT-0005; LOT-0006; LOT-0007; LOT-0008; LOT-0009\nPaís: Portugal\nNUT III: PT170\nLocalidade: Lisboa\nDistrito: Lisboa\nConcelho: Lisboa\nFreguesia: Todas\n10 - PRAZO DE EXECUÇÃO DO CONTRATO\nIdentificador do Lote: LOT-0001; LOT-0002; LOT-0003; LOT-0004; LOT-0005; LOT-0006; LOT-0007; LOT-0008; LOT-0009\nPrazo de execução do contrato: 95 DIAS\nPrevisão de renovações: Não\n11 - FUNDOS EU\nIdentificador do Lote: LOT-0001; LOT-0002; LOT-0003; LOT-0004; LOT-0005; LOT-0006; LOT-0007; LOT-0008; LOT-0009\nTêm fundos EU? Não\n12 - DOCUMENTOS DE HABILITAÇÃO\nHabilitação para o exercício da atividade profissional: Não\n13 - CONDIÇÕES DE APRESENTAÇÃO\nPlataforma eletrónica utilizada pela entidade adjudicante: VORTAL\nURL para Apresentação: https://community.vortal.biz/public/\nAdmissibilidade da apresentação de propostas variantes: Não autorizado\nPrazo para apresentação das propostas: 23-02-2026 23:59\nPrazo durante o qual os concorrentes são obrigados a manter as respetivas propostas: 66 dias a contar do termo do prazo para a apresentação das propostas\nApresentação de Catálogo Eletrónico: Não autorizado\nIndicação de Subcontratação na Proposta: Inexistência de indicação de subcontratação\n14 - PRESTAÇÃO DE CAUÇÃO\nPrestação de caução: Sim\nPercentagem: 5%\nDescrição da Garantia Exigida: Prestação de caução para os Lotes 1, 2, 3 e 4\n15 - FORNECIMENTO DAS PEÇAS DO CONCURSO, APRESENTAÇÃO DE PEDIDOS DE PARTICIPAÇÃO E APRESENTAÇÃO DAS PROPOSTAS\nLink para acesso às peças do concurso (URL): https://community.vortal.biz/Public/public-tender-documents/M0hzNTMxaVVpK25BMVBZV1RMSXFXM2d1ODREd3o2QmExK3Q5SlAxbkdTTWhacUR3eWFNZnM1dGROVVRTbHBsaGhRTlZnOWZTNENteWFIdmhCT1E5MXc9PUM2U2ha\n20 - OUTROS REQUISITOS\nIdentificador do Lote: LOT-0001; LOT-0002; LOT-0003; LOT-0004; LOT-0005; LOT-0006; LOT-0007; LOT-0008; LOT-0009\nInformação sobre contratos reservados. Aplica-se a contratos reservados (54º-A)? Não\n21 - CRITÉRIO DE ADJUDICAÇÃO\nO Critério de adjudicação é diferenciado por lote? Sim\nIdentificador do lote: LOT-0001\nMultifator: Sim\nFator: \nNome: Qualidade\nPonderação: 70%\nSubfatores: Não\nFator: \nNome: Preço\nPonderação: 5%\nSubfatores: Não\nFator: \nNome: Qualidade\nPonderação: 25%\nSubfatores: Não\nO Critério de adjudicação é diferenciado por lote? Sim\nIdentificador do lote: LOT-0002\nMultifator: Sim\nFator: \nNome: Qualidade\nPonderação: 70%\nSubfatores: Não\nFator: \nNome: Preço\nPonderação: 5%\nSubfatores: Não\nFator: \nNome: Qualidade\nPonderação: 25%\nSubfatores: Não\nO Critério de adjudicação é diferenciado por lote? Sim\nIdentificador do lote: LOT-0003\nMultifator: Sim\nFator: \nNome: Qualidade\nPonderação: 70%\nSubfatores: Não\nFator: \nNome: Preço\nPonderação: 5%\nSubfatores: Não\nFator: \nNome: Qualidade\nPonderação: 25%\nSubfatores: Não\nO Critério de adjudicação é diferenciado por lote? Sim\nIdentificador do lote: LOT-0004\nMultifator: Sim\nFator: \nNome: Qualidade\nPonderação: 70%\nSubfatores: Não\nFator: \nNome: Preço\nPonderação: 5%\nSubfatores: Não\nFator: \nNome: Qualidade\nPonderação: 25%\nSubfatores: Não\nO Critério de adjudicação é diferenciado por lote? Sim\nIdentificador do lote: LOT-0005\nMultifator: Sim\nFator: \nNome: Qualidade\nPonderação: 70%\nSubfatores: Não\nFator: \nNome: Preço\nPonderação: 30%\nSubfatores: Não\nO Critério de adjudicação é diferenciado por lote? Sim\nIdentificador do lote: LOT-0006\nMultifator: Sim\nFator: \nNome: Qualidade\nPonderação: 70%\nSubfatores: Não\nFator: \nNome: Preço\nPonderação: 30%\nSubfatores: Não\nO Critério de adjudicação é diferenciado por lote? Sim\nIdentificador do lote: LOT-0007\nMultifator: Sim\nFator: \nNome: Qualidade\nPonderação: 70%\nSubfatores: Não\nFator: \nNome: Preço\nPonderação: 30%\nSubfatores: Não\nO Critério de adjudicação é diferenciado por lote? Sim\nIdentificador do lote: LOT-0008\nMultifator: Sim\nFator: \nNome: Qualidade\nPonderação: 70%\nSubfatores: Não\nFator: \nNome: Preço\nPonderação: 30%\nSubfatores: Não\nO Critério de adjudicação é diferenciado por lote? Sim\nIdentificador do lote: LOT-0009\nMultifator: Sim\nFator: \nNome: Qualidade\nPonderação: 70%\nSubfatores: Não\nFator: \nNome: Preço\nPonderação: 30%\nSubfatores: Não\n24 - CONDIÇÕES DO CONTRATO\nIdentificador do Lote: LOT-0001; LOT-0002; LOT-0003; LOT-0004; LOT-0005; LOT-0006; LOT-0007; LOT-0008; LOT-0009\nFaturação Eletrónica: Permitido\nObrigação de Subcontratação:\nCódigo da Obrigação de Subcontratação: Não é aplicável nenhuma obrigação de subcontratação.\n25 - COMPRA PÚBLICA ESTRATÉGICA\nCompra Pública Estratégica: Inexistência de contratação pública estratégica\n26 - INFORMAÇÕES ADICIONAIS\nIdentificador do Lote: LOT-0001; LOT-0002; LOT-0003; LOT-0004; LOT-0005; LOT-0006; LOT-0007; LOT-0008; LOT-0009\nContrato adequado para PME: Sim\nCobertura ACP (Acordo dos Contratos Públicos da Organização Mundial do Comércio): Não\n27 - IDENTIFICAÇÃO E CONTACTOS DO ÓRGÃO DE RECURSOS ADMINISTRATIVOS\nDesignação: Ministério da Administração Interna\nEndereço: Praça do Comércio - Ala Oriental\nCódigo postal: 1149-015\nLocalidade: Lisboa\nTelefone: +351 213409000\nFax: +351 213409000\nEndereço eletrónico: dpie@sg.mai.gov.pt\nPrazo de interposição do recurso: 10 dias\n28 - IDENTIFICAÇÃO DO(S) AUTOR(ES) DE ANÚNCIO\nNome: Ricardo Alberto Carrilho\nCargo: Secretário-Geral do Ministério da Administração Interna\n29 - ALTERAÇÃO\nMotivo da Alteração: Correção pelo adquirente\nIdentificador da Versão do Anúncio a Alterar: bac74588-65a9-4155-8090-6ff29a1a0c7f-01\nIdentificador das Secções Alteradas do Anúncio Anterior: Critério de adjudicação\nDescrição das Alterações: No Lote de 1 ao Lote 4:\nFator quantidade - 70%, Fator Preço - 5%, Fator Ecológico - 25%.\nAlteração dos Documentos do Concurso: Sim\nData de alteração dos documentos do concurso: 07-01-2026\n419947373",
    "nipc": "600014665",
    "distrito": "Lisboa",
    "concelho": "Lisboa",
    "freguesia": "Freguesia de Santa Maria Maior - Lisboa",
    "site": "www.sg.mai.gov.pt/",
    "email": "gab.sec.geral@sg.mai.gov.pt",
    "designacao_contrato": "Aquisição de computadores de secretária, computadores de elevado desempenho, portáteis e periféricos, para a GNR e PSP, para os anos de 2025 e 2026, no âmbito do DLPIEFSS",
    "descricao": "Aquisição de computadores de secretária, computadores de elevado desempenho, portáteis e periféricos, para a GNR e PSP, para os anos de 2025 e 2026, no âmbito do DLPIEFSS",
    "preco_base": "7.759.250,00 EUR",
    "prazo_execucao": "95 DIAS",
    "prazo_apresentacao_propostas": "23-02-2026 23:59",
    "fundos_eu": "Não",
    "plataforma_eletronica": "VORTAL",
    "url_procedimento": "https://community.vortal.biz/public/",
    "autor_nome": "Ricardo Alberto Carrilho",
    "autor_cargo": "Secretário-Geral do Ministério da Administração Interna"
  },
  {
    "numero_procedimento": "N/A",
    "entidade": "APS - Administração dos Portos de Sines e do Algarve, SA",
    "link": "https://diariodarepublica.pt/dr/detalhe/contrato-publico/416-1003372811",
    "detalhes_completos": "1 - IDENTIFICAÇÃO E CONTACTOS DA ENTIDADE ADJUDICANTE\nDesignação da entidade adjudicante: APS - Administração dos Portos de Sines e do Algarve, SA\nNIPC: 501208950\nServiço/Órgão/Pessoa de contacto: ISI - Inovação e Sistemas de Informação\nEndereço: Rua do Porto Industrial, Apartado 16, EC Sines\nCódigo postal: 7521-953\nLocalidade: Setúbal\nPaís: Portugal\nNUT III: PT181\nDistrito: Setúbal\nConcelho: Sines\nFreguesia: Freguesia de Sines\nTelefone: 269860600\nFax: 269860690\nEndereço da Entidade (URL): www.portodesines.pt\nEndereço Eletrónico: geral@apsinesalgarve.pt\neDelivery Gateway (URL): https://community.vortal.biz/public/\nFunção da Organização: Adquirente\nNorma jurídica da Entidade Adjudicante: Empresa pública\nÁrea de atividade da Entidade Adjudicante: Atividades portuárias\n2 - JORNAL OFICIAL DA UNIÃO EUROPEIA\nO procedimento a que este anúncio diz respeito também é publicitado no Jornal Oficial da União Europeia? Sim\n3 - AVISO\nModelo de Anúncio: Concurso público\nData de Envio do Anúncio: 07-01-2026\n5 - PROCESSO\nTipo de Procedimento: Concurso público\nPreço base do procedimento: Sim\nValor do preço base do procedimento: 850.000,00 EUR\nProcedimento com lotes? Não\n6 - OBJETO DO CONTRATO\nNúmero de referência interna: ISI.PR.25.020\nDesignação do contrato: ISI.PR.25.020 – NEXUS - Fornecimento e instalação de Storages\nDescrição: ISI.PR.25.020 – NEXUS - Fornecimento de duas unidades de armazenamento (Storages) com capacidade adequada para alocar todos os sistemas de ficheiros e dados da infraestrutura da empresa, de forma a dar resposta às diversas necessidades da APS, recorrendo a tecnologia atualizada que permita acompanhar a evolução dos serviços e sistemas disponibilizados pela APS.\nOpções: Não\nTipo de Contrato Principal: Aquisição de Bens Móveis\nTipo de Contrato: Aquisição de Bens Móveis\nClassificação CPV (Vocabulário Comum para os Contratos Públicos)\nObjeto principal\nVocabulário Principal: 30233100\nPreço base s/IVA: 850.000,00 EUR\n7 - INDICAÇÕES ADICIONAIS\nO contrato envolve aquisição conjunta (satisfação de várias entidades)? Não\nO contrato é adjudicado por uma central de compras? Não\n8 - TÉCNICAS\nO concurso destina-se à celebração de um acordo-quadro? Inexistência de acordo-quadro\nÉ utilizado um leilão eletrónico? Não\nÉ adotada uma fase de negociação? Não\nSistema de Aquisição Dinâmico: Inexistência de sistema de aquisição dinâmico\n9 - LOCAL DA EXECUÇÃO DO CONTRATO\nLOCAL DA EXECUÇÃO DO CONTRATO (PROCEDIMENTO)\nPaís: Portugal\nNUT III: PT181\nLocalidade: Setúbal\nDistrito: Setúbal\nConcelho: Sines\nFreguesia: Freguesia de Sines\n10 - PRAZO DE EXECUÇÃO DO CONTRATO\nPrazo de execução do contrato: 60 DIAS\nPrevisão de renovações: Não\n11 - FUNDOS EU\nTêm fundos EU? Sim\n12 - DOCUMENTOS DE HABILITAÇÃO\nHabilitação para o exercício da atividade profissional: Sim\nTipo: Outros\nDescrição - Outros: Nos termos da legislação aplicável.\nDescrição: Nos termos das peças do procedimento\n13 - CONDIÇÕES DE APRESENTAÇÃO\nPlataforma eletrónica utilizada pela entidade adjudicante: VORTAL\nURL para Apresentação: https://community.vortal.biz/public/\nAdmissibilidade da apresentação de propostas variantes: Não autorizado\nPrazo para apresentação das propostas: 05-02-2026 23:59\nPrazo durante o qual os concorrentes são obrigados a manter as respetivas propostas: 66 dias a contar do termo do prazo para a apresentação das propostas\nApresentação de Catálogo Eletrónico: Permitido\nIndicação de Subcontratação na Proposta: Inexistência de indicação de subcontratação\n14 - PRESTAÇÃO DE CAUÇÃO\nPrestação de caução: Sim\nPercentagem: 5%\nDescrição da Garantia Exigida: Nos termos das peças do procedimento\n15 - FORNECIMENTO DAS PEÇAS DO CONCURSO, APRESENTAÇÃO DE PEDIDOS DE PARTICIPAÇÃO E APRESENTAÇÃO DAS PROPOSTAS\nLink para acesso às peças do concurso (URL): https://community.vortal.biz/Public/public-tender-documents/b3RsMXc1WlBUNVVNVDArQno2Q0RYUnM2V2dhRis0Ly9QNjlBTWx2dUZOT09IakhkQnBKMTF2OWVMaEp3V2tnaVVoQ0hNQ2h3VVhrMWZRZVhrWCs4dXc9PXhHbk83\n20 - OUTROS REQUISITOS\nInformação sobre contratos reservados. Aplica-se a contratos reservados (54º-A)? Não\n21 - CRITÉRIO DE ADJUDICAÇÃO\nMultifator: Não\nMonofator:\nNome: Outros\nOutro nome: Preço\n24 - CONDIÇÕES DO CONTRATO\nFaturação Eletrónica: Permitido\nObrigação de Subcontratação:\nCódigo da Obrigação de Subcontratação: Não é aplicável nenhuma obrigação de subcontratação.\n25 - COMPRA PÚBLICA ESTRATÉGICA\nCompra Pública Estratégica: Inexistência de contratação pública estratégica\n26 - INFORMAÇÕES ADICIONAIS\nContrato adequado para PME: Sim\nCobertura ACP (Acordo dos Contratos Públicos da Organização Mundial do Comércio): Não\n27 - IDENTIFICAÇÃO E CONTACTOS DO ÓRGÃO DE RECURSOS ADMINISTRATIVOS\nDesignação: APS - Administração dos Portos de Sines e do Algarve, SA\nEndereço: Rua do Porto Industrial - Apartado 16 E.C. Sines\nCódigo postal: 7520-953\nLocalidade: Sines\nTelefone: +351 269860600\nFax: +351 269860690\nEndereço eletrónico: geral@apsinesalgarve.pt\n28 - IDENTIFICAÇÃO DO(S) AUTOR(ES) DE ANÚNCIO\nNome: Pedro do Ó Barradas de Oliveira Ramos\nCargo: Presidente do Conselho de Administração da APS\n419947394",
    "nipc": "501208950",
    "distrito": "Setúbal",
    "concelho": "Sines",
    "freguesia": "Freguesia de Sines",
    "site": "www.portodesines.pt",
    "email": "geral@apsinesalgarve.pt",
    "designacao_contrato": "ISI.PR.25.020 – NEXUS - Fornecimento e instalação de Storages",
    "descricao": "ISI.PR.25.020 – NEXUS - Fornecimento de duas unidades de armazenamento (Storages) com capacidade adequada para alocar todos os sistemas de ficheiros e dados da infraestrutura da empresa, de forma a dar resposta às diversas necessidades da APS, recorrendo a tecnologia atualizada que permita acompanhar a evolução dos serviços e sistemas disponibilizados pela APS.",
    "preco_base": "850.000,00 EUR",
    "prazo_execucao": "60 DIAS",
    "prazo_apresentacao_propostas": "05-02-2026 23:59",
    "fundos_eu": "Sim",
    "plataforma_eletronica": "VORTAL",
    "url_procedimento": "https://community.vortal.biz/public/",
    "autor_nome": "Pedro do Ó Barradas de Oliveira Ramos",
    "autor_cargo": "Presidente do Conselho de Administração da APS"
  },
  {
    "numero_procedimento": "N/A",
    "entidade": "Autoridade Tributária e Aduaneira",
    "link": "https://diariodarepublica.pt/dr/detalhe/contrato-publico/418-1003372812",
    "detalhes_completos": "1 - IDENTIFICAÇÃO E CONTACTOS DA ENTIDADE ADJUDICANTE\nDesignação da entidade adjudicante: Autoridade Tributária e Aduaneira\nNIPC: 600084779\nServiço/Órgão/Pessoa de contacto: Direção de Serviços de Contratação Pública e Logística\nEndereço: Rua da Prata, n.ºs 20-22\nCódigo postal: 1149-027\nLocalidade: Lisboa\nPaís: Portugal\nNUT III: PT170\nDistrito: Lisboa\nConcelho: Lisboa\nFreguesia: Freguesia de Santa Maria Maior - Lisboa\nTelefone: 218812600\nFax: 218812935\nEndereço da Entidade (URL): https://www.portaldasfinancas.gov.pt/\nEndereço Eletrónico: at@at.gov.pt\neDelivery Gateway (URL): https://www.acingov.pt\nFunção da Organização: Adquirente\nSubfunção da Organização: Organização cujo orçamento é utilizado para pagar o contrato; Organização que executa o pagamento; Organização que fornece informações adicionais sobre o processo de adjudicação; Organização que fornece mais informações sobre os prazos dos procedimentos de recurso; Organização que fornece acesso fora de linha aos documentos do concurso; Organização responsável pelo tratamento das propostas; Organização que recebe as propostas; Organização que trata os pedidos de participação; Organização que recebe pedidos de participação; Organização que fornece mais informações sobre os procedimentos de recurso; Organização que assina o contrato\nNorma jurídica da Entidade Adjudicante: Organismo de direito público\nÁrea de atividade da Autoridade Adjudicante: Serviços públicos das administrações públicas\n2 - JORNAL OFICIAL DA UNIÃO EUROPEIA\nO procedimento a que este anúncio diz respeito também é publicitado no Jornal Oficial da União Europeia? Sim\n3 - AVISO\nModelo de Anúncio: Concurso público\nData de Envio do Anúncio: 07-01-2026\n5 - PROCESSO\nTipo de Procedimento: Concurso público\nPreço base do procedimento: Sim\nValor do preço base do procedimento: 498.420,00 EUR\nProcedimento com lotes? Não\n6 - OBJETO DO CONTRATO\nNúmero de referência interna: 107/CP/AT/2025\nDesignação do contrato: Renovação do licenciamento do software PowerCenter e PowerExchange\nDescrição: Renovação do licenciamento do software PowerCenter e PowerExchange\nOpções: Não\nTipo de Contrato Principal: Locação de Bens Móveis\nTipo de Contrato: Locação de Bens Móveis\nClassificação CPV (Vocabulário Comum para os Contratos Públicos)\nObjeto principal\nVocabulário Principal: 48000000\nPreço base s/IVA: 498.420,00 EUR\n7 - INDICAÇÕES ADICIONAIS\nO contrato envolve aquisição conjunta (satisfação de várias entidades)? Não\nO contrato é adjudicado por uma central de compras? Não\n8 - TÉCNICAS\nO concurso destina-se à celebração de um acordo-quadro? Inexistência de acordo-quadro\nÉ utilizado um leilão eletrónico? Não\nÉ adotada uma fase de negociação? Não\nSistema de Aquisição Dinâmico: Inexistência de sistema de aquisição dinâmico\n9 - LOCAL DA EXECUÇÃO DO CONTRATO\nLOCAL DA EXECUÇÃO DO CONTRATO (PROCEDIMENTO)\nPaís: Portugal\nNUT III: PT170\nLocalidade: Freguesia de Campolide\nDistrito: Lisboa\nConcelho: Lisboa\nFreguesia: Freguesia de Campolide\n10 - PRAZO DE EXECUÇÃO DO CONTRATO\nPrazo de execução do contrato: 333 DIAS\nPrevisão de renovações: Não\n11 - FUNDOS EU\nTêm fundos EU? Não\n12 - DOCUMENTOS DE HABILITAÇÃO\nHabilitação para o exercício da atividade profissional: Não\n13 - CONDIÇÕES DE APRESENTAÇÃO\nPlataforma eletrónica utilizada pela entidade adjudicante: ACIN\nURL para Apresentação: https://www.acingov.pt\nAdmissibilidade da apresentação de propostas variantes: Não autorizado\nPrazo para apresentação das propostas: 22-01-2026 23:59\nPrazo durante o qual os concorrentes são obrigados a manter as respetivas propostas: 66 dias a contar do termo do prazo para a apresentação das propostas\nApresentação de Catálogo Eletrónico: Permitido\nIndicação de Subcontratação na Proposta: Inexistência de indicação de subcontratação\n14 - PRESTAÇÃO DE CAUÇÃO\nPrestação de caução: Não\n15 - FORNECIMENTO DAS PEÇAS DO CONCURSO, APRESENTAÇÃO DE PEDIDOS DE PARTICIPAÇÃO E APRESENTAÇÃO DAS PROPOSTAS\nLink para acesso às peças do concurso (URL): https://www.acingov.pt/acingovprod/2/zonaPublica/zona_publica_c/donwloadProcedurePiece/MTAzNjA2OQ==\n20 - OUTROS REQUISITOS\nInformação sobre contratos reservados. Aplica-se a contratos reservados (54º-A)? Não\n21 - CRITÉRIO DE ADJUDICAÇÃO\nMultifator: Não\nMonofator:\nNome: Preço\n24 - CONDIÇÕES DO CONTRATO\nFaturação Eletrónica: Permitido\nObrigação de Subcontratação:\nCódigo da Obrigação de Subcontratação: Não é aplicável nenhuma obrigação de subcontratação.\n25 - COMPRA PÚBLICA ESTRATÉGICA\nCompra Pública Estratégica: Inexistência de contratação pública estratégica\n26 - INFORMAÇÕES ADICIONAIS\nContrato adequado para PME: Sim\nCobertura ACP (Acordo dos Contratos Públicos da Organização Mundial do Comércio): Não\n27 - IDENTIFICAÇÃO E CONTACTOS DO ÓRGÃO DE RECURSOS ADMINISTRATIVOS\nDesignação: Secretária de Estado dos Assuntos Fiscais\nEndereço: Avenida do Infante D Henrique 1\nCódigo postal: 1149-009\nLocalidade: Lisboa\nTelefone: 218816800\nFax: \nEndereço eletrónico: seaf@mf.gov.pt\nPrazo de interposição do recurso: 5 dias\n28 - IDENTIFICAÇÃO DO(S) AUTOR(ES) DE ANÚNCIO\nNome: Helena Alves Borges\nCargo: Diretora Geral da AT\n419947401",
    "nipc": "600084779",
    "distrito": "Lisboa",
    "concelho": "Lisboa",
    "freguesia": "Freguesia de Santa Maria Maior - Lisboa",
    "site": "https://www.portaldasfinancas.gov.pt/",
    "email": "at@at.gov.pt",
    "designacao_contrato": "Renovação do licenciamento do software PowerCenter e PowerExchange",
    "descricao": "Renovação do licenciamento do software PowerCenter e PowerExchange",
    "preco_base": "498.420,00 EUR",
    "prazo_execucao": "333 DIAS",
    "prazo_apresentacao_propostas": "22-01-2026 23:59",
    "fundos_eu": "Não",
    "plataforma_eletronica": "ACIN",
    "url_procedimento": "https://www.acingov.pt",
    "autor_nome": "Helena Alves Borges",
    "autor_cargo": "Diretora Geral da AT"
  },
  {
    "numero_procedimento": "N/A",
    "entidade": "AnÃºncio de procedimento  n.Âº 420/2026  -  DiÃ¡rio da RepÃºblica n.Âº 6/2026, SÃ©rie II de 2026-01-09",
    "link": "https://diariodarepublica.pt/dr/detalhe/contrato-publico/420-1003372813"
  },
  {
    "numero_procedimento": "N/A",
    "entidade": "AnÃºncio de procedimento  n.Âº 422/2026  -  DiÃ¡rio da RepÃºblica n.Âº 6/2026, SÃ©rie II de 2026-01-09",
    "link": "https://diariodarepublica.pt/dr/detalhe/contrato-publico/422-1003372814"
  },
  {
    "numero_procedimento": "N/A",
    "entidade": "AnÃºncio de procedimento  n.Âº 423/2026  -  DiÃ¡rio da RepÃºblica n.Âº 6/2026, SÃ©rie II de 2026-01-09",
    "link": "https://diariodarepublica.pt/dr/detalhe/contrato-publico/423-1003372815"
  },
  {
    "numero_procedimento": "N/A",
    "entidade": "Serviços Municipalizados de Castelo Branco",
    "link": "https://diariodarepublica.pt/dr/detalhe/contrato-publico/424-1003372816",
    "detalhes_completos": "1 - IDENTIFICAÇÃO E CONTACTOS DA ENTIDADE ADJUDICANTE\nDesignação da entidade adjudicante: Serviços Municipalizados de Castelo Branco\nNIPC: 680017640\nServiço/Órgão/Pessoa de contacto: Conselho de Administração\nEndereço: Av. Nuno Álvares Nº 32 r/c\nCódigo postal: 6000-083\nLocalidade: Castelo Branco\nPaís: Portugal\nNUT III: PT16H\nDistrito: Castelo Branco\nConcelho: Castelo Branco\nFreguesia: Freguesia de Castelo Branco - Castelo Branco\nTelefone: 272340500\nFax: 272340501\nEndereço da Entidade (URL): www.sm-castelobranco.pt\nEndereço Eletrónico: geral@sm-castelobranco.pt\neDelivery Gateway (URL): https://www.acingov.pt\nFunção da Organização: Adquirente\nNorma jurídica da Entidade Adjudicante: Organismo de direito público\nÁrea de atividade da Autoridade Adjudicante: Serviços públicos das administrações públicas\n2 - JORNAL OFICIAL DA UNIÃO EUROPEIA\nO procedimento a que este anúncio diz respeito também é publicitado no Jornal Oficial da União Europeia? Não\n3 - AVISO\nModelo de Anúncio: Concurso público\nData de Envio do Anúncio: 09-01-2026\n5 - PROCESSO\nTipo de Procedimento: Concurso público\nPreço base do procedimento: Sim\nValor do preço base do procedimento: 19.600,00 EUR\nProcedimento com lotes? Não\n6 - OBJETO DO CONTRATO\nNúmero de referência interna: 19/2025/CP\nDesignação do contrato: Fornecimento continuado de Sacos CãoPeão com logotipo personalizado\nDescrição: Fornecimento continuado de Sacos CãoPeão com logotipo personalizado\nTipo de Contrato Principal: Aquisição de Bens Móveis\nTipo de Contrato: Aquisição de Bens Móveis\nClassificação CPV (Vocabulário Comum para os Contratos Públicos)\nObjeto principal\nVocabulário Principal: 19640000\nPreço base s/IVA: 19.600,00 EUR\n7 - INDICAÇÕES ADICIONAIS\nO contrato envolve aquisição conjunta (satisfação de várias entidades)? Não\nO contrato é adjudicado por uma central de compras? Não\n8 - TÉCNICAS\nO concurso destina-se à celebração de um acordo-quadro? Inexistência de acordo-quadro\nÉ utilizado um leilão eletrónico? Não\nÉ adotada uma fase de negociação? Não\nSistema de Aquisição Dinâmico: Inexistência de sistema de aquisição dinâmico\n9 - LOCAL DA EXECUÇÃO DO CONTRATO\nLOCAL DA EXECUÇÃO DO CONTRATO (PROCEDIMENTO)\nPaís: Portugal\nNUT III: PT16H\nLocalidade: Freguesia de Castelo Branco - Castelo Branco\nDistrito: Castelo Branco\nConcelho: Castelo Branco\nFreguesia: Freguesia de Castelo Branco - Castelo Branco\n10 - PRAZO DE EXECUÇÃO DO CONTRATO\nPrazo de execução do contrato: 24 MESES\nPrevisão de renovações: Não\n11 - FUNDOS EU\nTêm fundos EU? Não\n12 - DOCUMENTOS DE HABILITAÇÃO\nHabilitação para o exercício da atividade profissional: Não\n13 - CONDIÇÕES DE APRESENTAÇÃO\nPlataforma eletrónica utilizada pela entidade adjudicante: ACIN\nURL para Apresentação: https://www.acingov.pt\nAdmissibilidade da apresentação de propostas variantes: Não autorizado\nPrazo para apresentação das propostas: 11-01-2026 23:59\nPrazo durante o qual os concorrentes são obrigados a manter as respetivas propostas: 66 dias a contar do termo do prazo para a apresentação das propostas\nIndicação de Subcontratação na Proposta: Inexistência de indicação de subcontratação\n14 - PRESTAÇÃO DE CAUÇÃO\nPrestação de caução: Não\n15 - FORNECIMENTO DAS PEÇAS DO CONCURSO, APRESENTAÇÃO DE PEDIDOS DE PARTICIPAÇÃO E APRESENTAÇÃO DAS PROPOSTAS\nLink para acesso às peças do concurso (URL): https://www.acingov.pt/acingovprod/2/zonaPublica/zona_publica_c/donwloadProcedurePiece/MTAxMDk4NQ==\n20 - OUTROS REQUISITOS\nInformação sobre contratos reservados. Aplica-se a contratos reservados (54º-A)? Não\n21 - CRITÉRIO DE ADJUDICAÇÃO\nMultifator: Não\nMonofator:\nNome: Preço\n24 - CONDIÇÕES DO CONTRATO\nFaturação Eletrónica: Permitido\nObrigação de Subcontratação:\nCódigo da Obrigação de Subcontratação: Não é aplicável nenhuma obrigação de subcontratação.\n25 - COMPRA PÚBLICA ESTRATÉGICA\nCompra Pública Estratégica: Inexistência de contratação pública estratégica\n26 - INFORMAÇÕES ADICIONAIS\nContrato adequado para PME: Não\nCobertura ACP (Acordo dos Contratos Públicos da Organização Mundial do Comércio): Não\n27 - IDENTIFICAÇÃO E CONTACTOS DO ÓRGÃO DE RECURSOS ADMINISTRATIVOS\nDesignação: Conselho de Administração\nEndereço: Av. Nuno Álvares Nº 32 r/c\nCódigo postal: 6000-083\nLocalidade: Castelo Branco\nTelefone: 272340500\nFax: 272340501\nEndereço eletrónico: geral@sm-castelobranco.pt\nPrazo de interposição do recurso: 5 dias\n28 - IDENTIFICAÇÃO DO(S) AUTOR(ES) DE ANÚNCIO\nNome: Engª. Sónia Cristina Cristóvão Mexia\nCargo: Administradora\n419947113",
    "nipc": "680017640",
    "distrito": "Castelo Branco",
    "concelho": "Castelo Branco",
    "freguesia": "Freguesia de Castelo Branco - Castelo Branco",
    "site": "www.sm-castelobranco.pt",
    "email": "geral@sm-castelobranco.pt",
    "designacao_contrato": "Fornecimento continuado de Sacos CãoPeão com logotipo personalizado",
    "descricao": "Fornecimento continuado de Sacos CãoPeão com logotipo personalizado",
    "preco_base": "19.600,00 EUR",
    "prazo_execucao": "24 MESES",
    "prazo_apresentacao_propostas": "11-01-2026 23:59",
    "fundos_eu": "Não",
    "plataforma_eletronica": "ACIN",
    "url_procedimento": "https://www.acingov.pt",
    "autor_nome": "Engª. Sónia Cristina Cristóvão Mexia",
    "autor_cargo": "Administradora"
  },
  {
    "numero_procedimento": "N/A",
    "entidade": "AnÃºncio de procedimento  n.Âº 425/2026  -  DiÃ¡rio da RepÃºblica n.Âº 6/2026, SÃ©rie II de 2026-01-09",
    "link": "https://diariodarepublica.pt/dr/detalhe/contrato-publico/425-1003372817"
  },
  {
    "numero_procedimento": "N/A",
    "entidade": "AnÃºncio de procedimento  n.Âº 426/2026  -  DiÃ¡rio da RepÃºblica n.Âº 6/2026, SÃ©rie II de 2026-01-09",
    "link": "https://diariodarepublica.pt/dr/detalhe/contrato-publico/426-1003372818"
  },
  {
    "numero_procedimento": "N/A",
    "entidade": "Águas do Tejo Atlântico, SA",
    "link": "https://diariodarepublica.pt/dr/detalhe/contrato-publico/428-1003372819",
    "detalhes_completos": "Alteração do Anúncio de procedimento n.º 30618/2025, de 2025-11-25, com o ID 419814604\n1 - IDENTIFICAÇÃO E CONTACTOS DA ENTIDADE ADJUDICANTE\nDesignação da entidade adjudicante: Águas do Tejo Atlântico, SA\nNIPC: 514387130\nServiço/Órgão/Pessoa de contacto: Direção de Engenharia\nEndereço: ETAR de Alcântara, Av. de Ceuta\nCódigo postal: 1300-254\nLocalidade: Lisboa\nPaís: Portugal\nNUT III: PT170\nDistrito: Lisboa\nConcelho: Lisboa\nFreguesia: Freguesia de Campo de Ourique\nTelefone: 213107900\nFax: 351213107901\nEndereço da Entidade (URL): www.aguasdotejoatlantico.adp.pt\nEndereço Eletrónico: compras_contratacao.adta@adp.pt\neDelivery Gateway (URL): https://www.acingov.pt\nFunção da Organização: Adquirente\nSubfunção da Organização: Organização cujo orçamento é utilizado para pagar o contrato; Organização que executa o pagamento; Organização que fornece informações adicionais sobre o processo de adjudicação; Organização que fornece mais informações sobre os prazos dos procedimentos de recurso; Organização que fornece acesso fora de linha aos documentos do concurso; Organização responsável pelo tratamento das propostas; Organização que recebe as propostas; Organização que trata os pedidos de participação; Organização que recebe pedidos de participação; Organização que fornece mais informações sobre os procedimentos de recurso; Organização que assina o contrato\nNorma jurídica da Entidade Adjudicante: Organismo de direito público\nÁrea de atividade da Entidade Adjudicante: Atividades relacionadas com a água\n2 - JORNAL OFICIAL DA UNIÃO EUROPEIA\nO procedimento a que este anúncio diz respeito também é publicitado no Jornal Oficial da União Europeia? Não\n3 - AVISO\nModelo de Anúncio: Concurso público\nData de Envio do Anúncio: 09-01-2026\n5 - PROCESSO\nTipo de Procedimento: Concurso público\nPreço base do procedimento: Sim\nValor do preço base do procedimento: 2.300.000,00 EUR\nProcedimento com lotes? Não\n6 - OBJETO DO CONTRATO\nNúmero de referência interna: TA_25_131_CP_O_016_DEN\nDesignação do contrato: Empreitada de Reabilitação do Emissário do Jamor - Fase I\nDescrição: Empreitada de Reabilitação do Emissário do Jamor - Fase I\nTipo de Contrato Principal: Empreitada de Obras Públicas\nTipo de Contrato: Empreitada de Obras Públicas\nClassificação CPV (Vocabulário Comum para os Contratos Públicos)\nObjeto principal\nVocabulário Principal: 45232460\nPreço base s/IVA: 2.300.000,00 EUR\n7 - INDICAÇÕES ADICIONAIS\nO contrato envolve aquisição conjunta (satisfação de várias entidades)? Não\nO contrato é adjudicado por uma central de compras? Não\n8 - TÉCNICAS\nO concurso destina-se à celebração de um acordo-quadro? Inexistência de acordo-quadro\nÉ utilizado um leilão eletrónico? Não\nÉ adotada uma fase de negociação? Não\nSistema de Aquisição Dinâmico: Inexistência de sistema de aquisição dinâmico\n9 - LOCAL DA EXECUÇÃO DO CONTRATO\nLOCAL DA EXECUÇÃO DO CONTRATO (PROCEDIMENTO)\nPaís: Portugal\nNUT III: PT170\nLocalidade: União das Freguesias de Algés, Linda-a-Velha e Cruz Quebrada-Dafundo\nDistrito: Lisboa\nConcelho: Oeiras\nFreguesia: União das Freguesias de Algés, Linda-a-Velha e Cruz Quebrada-Dafundo\n10 - PRAZO DE EXECUÇÃO DO CONTRATO\nPrazo de execução do contrato: 365 DIAS\nPrevisão de renovações: Não\n11 - FUNDOS EU\nTêm fundos EU? Não\n12 - DOCUMENTOS DE HABILITAÇÃO\nHabilitação para o exercício da atividade profissional: Sim\nTipo: Alvará\nDescrição: Alvará ou certificado de empreiteiro de obras públicas, contendo as seguintes habilitações:\ni) 6.ª subcategoria (Saneamento básico) da 2.ª categoria (Vias de comunicação, obras de urbanização e outras infraestruturas) da classe correspondente ao valor global da proposta;\nii) 2.ª subcategoria (Movimentação de terras) da 5.ª categoria (Outros trabalhos), da classe correspondente ao valor dos trabalhos especializados que lhe respeite, consoante a parte que a esses trabalhos cabe na proposta.\n13 - CONDIÇÕES DE APRESENTAÇÃO\nPlataforma eletrónica utilizada pela entidade adjudicante: ACIN\nURL para Apresentação: https://www.acingov.pt\nAdmissibilidade da apresentação de propostas variantes: Não autorizado\nPrazo para apresentação das propostas: 28-01-2026 23:59\nPrazo durante o qual os concorrentes são obrigados a manter as respetivas propostas: 120 dias a contar do termo do prazo para a apresentação das propostas\nIndicação de Subcontratação na Proposta: Inexistência de indicação de subcontratação\n14 - PRESTAÇÃO DE CAUÇÃO\nPrestação de caução: Sim\nPercentagem: 5%\nDescrição da Garantia Exigida: O valor da caução é de 5.00% do preço contratual.\n15 - FORNECIMENTO DAS PEÇAS DO CONCURSO, APRESENTAÇÃO DE PEDIDOS DE PARTICIPAÇÃO E APRESENTAÇÃO DAS PROPOSTAS\nLink para acesso às peças do concurso (URL): https://www.acingov.pt/acingovprod/2/zonaPublica/zona_publica_c/donwloadProcedurePiece/OTk4MTY2\n20 - OUTROS REQUISITOS\nInformação sobre contratos reservados. Aplica-se a contratos reservados (54º-A)? Não\n21 - CRITÉRIO DE ADJUDICAÇÃO\nMultifator: Sim\nFator: \nNome: Preço\nPonderação: 50%\nSubfatores: Não\nFator: \nNome: Outros\nOutro Nome: Valia Técnica\nPonderação: 50%\nSubfatores: Sim\nSubfatores: \nNome: Detalhe e consistência do Plano de Trabalhos\nPonderação : 50%; \nNome: Metodologia de execução da obra\nPonderação : 50%; \n24 - CONDIÇÕES DO CONTRATO\nFaturação Eletrónica: Necessário\nObrigação de Subcontratação:\nCódigo da Obrigação de Subcontratação: Não é aplicável nenhuma obrigação de subcontratação.\n25 - COMPRA PÚBLICA ESTRATÉGICA\nCompra Pública Estratégica: Redução dos impactos ambientais\nDescrição do Processo de Adjudicação Estratégico: Cumprimento das disposições legais e regulamentares em vigor sobre ambiente. Em particular, o que respeita à Resolução do Conselho de Ministros n.º 132/2023, de 25 de outubro (Critérios das Compras Públicas Ecológicas). No que respeita ao Regime Geral da Gestão de Resíduos, prevê-se a utilização de, pelo menos, 10% de materiais reciclados ou que incorporem materiais reciclados relativamente à quantidade total de matérias-primas usadas na obra.\nCritérios de contratos Públicos Ecológicos: Critérios de contratação pública ecológica da UE; Critérios de contratação pública ecológica nacional\nCategorias da estratégia nacional: Infraestruturas de tratamento de águas residuais\nContratos Públicos Ecológicos: A transição para uma economia circular\nDiretiva Veículos Não Poluentes: Não\nCritério de Acessibilidade: Os critérios de acessibilidade para as pessoas com deficiência estão incluídos\n26 - INFORMAÇÕES ADICIONAIS\nContrato adequado para PME: Sim\nCobertura ACP (Acordo dos Contratos Públicos da Organização Mundial do Comércio): Não\n27 - IDENTIFICAÇÃO E CONTACTOS DO ÓRGÃO DE RECURSOS ADMINISTRATIVOS\nDesignação: Conselho de Administração\nEndereço: ETAR de Alcântara, Av. de Ceuta\nCódigo postal: 1300-254\nLocalidade: Lisboa\nTelefone: 213107900\nFax: \nEndereço eletrónico: compras_contratacao.adta@adp.pt\nPrazo de interposição do recurso: 5 dias\n28 - IDENTIFICAÇÃO DO(S) AUTOR(ES) DE ANÚNCIO\nNome: Nuno Brôco\nCargo: Presidente do Conselho de Administração\n29 - ALTERAÇÃO\nMotivo da Alteração: Informações atualizadas\nIdentificador da Versão do Anúncio a Alterar: 80c49da6-5b73-4125-847f-a20d96e0c431-01\nIdentificador das Secções Alteradas do Anúncio Anterior: Condições de Apresentação\nDescrição das Alterações: Modificação do prazo para a apresentação de propostas\nAlteração dos Documentos do Concurso: Não\n419947539",
    "nipc": "514387130",
    "distrito": "Lisboa",
    "concelho": "Lisboa",
    "freguesia": "Freguesia de Campo de Ourique",
    "site": "www.aguasdotejoatlantico.adp.pt",
    "email": "compras_contratacao.adta@adp.pt",
    "designacao_contrato": "Empreitada de Reabilitação do Emissário do Jamor - Fase I",
    "descricao": "Empreitada de Reabilitação do Emissário do Jamor - Fase I",
    "preco_base": "2.300.000,00 EUR",
    "prazo_execucao": "365 DIAS",
    "prazo_apresentacao_propostas": "28-01-2026 23:59",
    "fundos_eu": "Não",
    "plataforma_eletronica": "ACIN",
    "url_procedimento": "https://www.acingov.pt",
    "autor_nome": "Nuno Brôco",
    "autor_cargo": "Presidente do Conselho de Administração"
  },
  {
    "numero_procedimento": "N/A",
    "entidade": "AnÃºncio de procedimento  n.Âº 429/2026  -  DiÃ¡rio da RepÃºblica n.Âº 6/2026, SÃ©rie II de 2026-01-09",
    "link": "https://diariodarepublica.pt/dr/detalhe/contrato-publico/429-1003372820"
  },
  {
    "numero_procedimento": "N/A",
    "entidade": "AnÃºncio de procedimento  n.Âº 430/2026  -  DiÃ¡rio da RepÃºblica n.Âº 6/2026, SÃ©rie II de 2026-01-09",
    "link": "https://diariodarepublica.pt/dr/detalhe/contrato-publico/430-1003372821"
  },
  {
    "numero_procedimento": "N/A",
    "entidade": "Freguesia de Rio Maior",
    "link": "https://diariodarepublica.pt/dr/detalhe/contrato-publico/431-1003372822",
    "detalhes_completos": "1 - IDENTIFICAÇÃO E CONTACTOS DA ENTIDADE ADJUDICANTE\nDesignação da entidade adjudicante: Freguesia de Rio Maior\nNIPC: 506806677\nEndereço: Rua Prof Manuel José Ferreira, n.º 70 - R/C\nCódigo postal: 2040-270\nLocalidade: Rio Maior\nPaís: Portugal\nNUT III: PT185\nDistrito: Santarém\nConcelho: Rio Maior\nFreguesia: Todas\nTelefone: +351 243995114\nEndereço Eletrónico: geral@jf-riomaior.pt\neDelivery Gateway (URL): https://community.vortal.biz/public/\nFunção da Organização: Adquirente\nNorma jurídica da Entidade Adjudicante: Organismo de direito público\nÁrea de atividade da Autoridade Adjudicante: Serviços públicos das administrações públicas\n2 - JORNAL OFICIAL DA UNIÃO EUROPEIA\nO procedimento a que este anúncio diz respeito também é publicitado no Jornal Oficial da União Europeia? Não\n3 - AVISO\nModelo de Anúncio: Concurso público\nData de Envio do Anúncio: 09-01-2026\n5 - PROCESSO\nTipo de Procedimento: Concurso público\nPreço base do procedimento: Sim\nValor do preço base do procedimento: 147.000,00 EUR\nProcedimento com lotes? Não\n6 - OBJETO DO CONTRATO\nNúmero de referência interna: 1/2026/FRM\nDesignação do contrato: Aquisição de Serviços de Deservagem em Meio Rural na Freguesia de Rio Maior \nDescrição: Aquisição de Serviços de Deservagem em Meio Rural na Freguesia de Rio Maior \nTipo de Contrato Principal: Aquisição de Serviços\nTipo de Contrato: Aquisição de Serviços\nClassificação CPV (Vocabulário Comum para os Contratos Públicos)\nObjeto principal\nVocabulário Principal: 90610000\nPreço base s/IVA: 147.000,00 EUR\n7 - INDICAÇÕES ADICIONAIS\nO contrato envolve aquisição conjunta (satisfação de várias entidades)? Não\nO contrato é adjudicado por uma central de compras? Não\n8 - TÉCNICAS\nO concurso destina-se à celebração de um acordo-quadro? Inexistência de acordo-quadro\nÉ utilizado um leilão eletrónico? Não\nÉ adotada uma fase de negociação? Não\nSistema de Aquisição Dinâmico: Inexistência de sistema de aquisição dinâmico\n9 - LOCAL DA EXECUÇÃO DO CONTRATO\nLOCAL DA EXECUÇÃO DO CONTRATO (PROCEDIMENTO)\nPaís: Portugal\nNUT III: PT185\nLocalidade: Santarém\nDistrito: Santarém\nConcelho: Rio Maior\nFreguesia: Freguesia de Rio Maior\n10 - PRAZO DE EXECUÇÃO DO CONTRATO\nPrazo de execução do contrato: 730 DIAS\nPrevisão de renovações: Não\n11 - FUNDOS EU\nTêm fundos EU? Não\n12 - DOCUMENTOS DE HABILITAÇÃO\nHabilitação para o exercício da atividade profissional: Não\n13 - CONDIÇÕES DE APRESENTAÇÃO\nPlataforma eletrónica utilizada pela entidade adjudicante: VORTAL\nURL para Apresentação: https://community.vortal.biz/public/\nAdmissibilidade da apresentação de propostas variantes: Não autorizado\nPrazo para apresentação das propostas: 18-01-2026 23:59\nPrazo durante o qual os concorrentes são obrigados a manter as respetivas propostas: 120 dias a contar do termo do prazo para a apresentação das propostas\nIndicação de Subcontratação na Proposta: Inexistência de indicação de subcontratação\n14 - PRESTAÇÃO DE CAUÇÃO\nPrestação de caução: Sim\nPercentagem: 5%\nDescrição da Garantia Exigida: Nos termos do Art. 90.º do CCP\n15 - FORNECIMENTO DAS PEÇAS DO CONCURSO, APRESENTAÇÃO DE PEDIDOS DE PARTICIPAÇÃO E APRESENTAÇÃO DAS PROPOSTAS\nLink para acesso às peças do concurso (URL): https://community.vortal.biz/Public/public-tender-documents/Mml1U1V1WjRnMEdwU3FieWM0cUk5Wmd4cmdyTDlCT1ROejk4L2hZTVRhelB1WDduK3dVN0UydXVmTGx5TytwQTJpcEFGb281UkpoZFNrR1BDMStncXc9PThrNDBh\n20 - OUTROS REQUISITOS\nInformação sobre contratos reservados. Aplica-se a contratos reservados (54º-A)? Não\n21 - CRITÉRIO DE ADJUDICAÇÃO\nMultifator: Não\nMonofator:\nNome: Preço\n24 - CONDIÇÕES DO CONTRATO\nFaturação Eletrónica: Permitido\nObrigação de Subcontratação:\nCódigo da Obrigação de Subcontratação: Não é aplicável nenhuma obrigação de subcontratação.\n25 - COMPRA PÚBLICA ESTRATÉGICA\nCompra Pública Estratégica: Inexistência de contratação pública estratégica\n26 - INFORMAÇÕES ADICIONAIS\nContrato adequado para PME: Sim\nCobertura ACP (Acordo dos Contratos Públicos da Organização Mundial do Comércio): Não\n27 - IDENTIFICAÇÃO E CONTACTOS DO ÓRGÃO DE RECURSOS ADMINISTRATIVOS\nDesignação: Freguesia de Rio Maior\nEndereço: Rua Prof Manuel José Ferreira, n.º 70 - R/C\nCódigo postal: 2040-270\nLocalidade: Rio Maior\nTelefone: +351 243995114\nFax: +351 243992186\nEndereço eletrónico: geral@jf-riomaior.pt\n28 - IDENTIFICAÇÃO DO(S) AUTOR(ES) DE ANÚNCIO\nNome: João Carlos Branco dos Santos Rebocho  \nCargo: Presidente da Junta de Freguesia de Rio Maior\n419947548",
    "nipc": "506806677",
    "distrito": "Santarém",
    "concelho": "Rio Maior",
    "freguesia": "Todas",
    "site": null,
    "email": "geral@jf-riomaior.pt",
    "designacao_contrato": "Aquisição de Serviços de Deservagem em Meio Rural na Freguesia de Rio Maior",
    "descricao": "Aquisição de Serviços de Deservagem em Meio Rural na Freguesia de Rio Maior",
    "preco_base": "147.000,00 EUR",
    "prazo_execucao": "730 DIAS",
    "prazo_apresentacao_propostas": "18-01-2026 23:59",
    "fundos_eu": "Não",
    "plataforma_eletronica": "VORTAL",
    "url_procedimento": "https://community.vortal.biz/public/",
    "autor_nome": "João Carlos Branco dos Santos Rebocho",
    "autor_cargo": "Presidente da Junta de Freguesia de Rio Maior"
  },
  {
    "numero_procedimento": "N/A",
    "entidade": "APSS - Administração dos Portos de Setúbal e Sesimbra, SA",
    "link": "https://diariodarepublica.pt/dr/detalhe/contrato-publico/432-1003372823",
    "detalhes_completos": "1 - IDENTIFICAÇÃO E CONTACTOS DA ENTIDADE ADJUDICANTE\nDesignação da entidade adjudicante: APSS - Administração dos Portos de Setúbal e Sesimbra, SA\nNIPC: 502256869\nServiço/Órgão/Pessoa de contacto: Divisão de Contratação Pública\nEndereço: Praça da República\nCódigo postal: 2904-508\nLocalidade: Setúbal\nPaís: Portugal\nNUT III: PT170\nDistrito: Setúbal\nConcelho: Setúbal\nFreguesia: União das Freguesias de Setúbal (São Julião, Nossa Senhora da Anunciada e Santa Maria da Graça)\nTelefone: 265542000\nEndereço da Entidade (URL): www.portodesetubal.pt\nEndereço Eletrónico: apss-plataforma@portodesetubal.pt\neDelivery Gateway (URL): https://www.acingov.pt\nFunção da Organização: Adquirente\nSubfunção da Organização: Organização cujo orçamento é utilizado para pagar o contrato; Organização que executa o pagamento; Organização que fornece informações adicionais sobre o processo de adjudicação; Organização que fornece mais informações sobre os prazos dos procedimentos de recurso; Organização que fornece acesso fora de linha aos documentos do concurso; Organização responsável pelo tratamento das propostas; Organização que recebe as propostas; Organização que fornece mais informações sobre os procedimentos de recurso; Organização que assina o contrato\nNorma jurídica da Entidade Adjudicante: Empresa pública\nÁrea de atividade da Entidade Adjudicante: Atividades portuárias\n2 - JORNAL OFICIAL DA UNIÃO EUROPEIA\nO procedimento a que este anúncio diz respeito também é publicitado no Jornal Oficial da União Europeia? Não\n3 - AVISO\nModelo de Anúncio: Concurso público\nData de Envio do Anúncio: 09-01-2026\n5 - PROCESSO\nTipo de Procedimento: Concurso público\nPreço base do procedimento: Sim\nValor do preço base do procedimento: 450.000,00 EUR\nProcedimento com lotes? Não\n6 - OBJETO DO CONTRATO\nNúmero de referência interna: P01/2026  S 907/2025\nDesignação do contrato: Substituição de passadiços flutuantes no interior da Doca dos Pescadores  linha 3 e longitudinais de apoio, em Setúbal\nDescrição: Substituição de passadiços flutuantes no interior da Doca dos Pescadores  linha 3 e longitudinais de apoio, em Setúbal\nTipo de Contrato Principal: Empreitada de Obras Públicas\nTipo de Contrato: Empreitada de Obras Públicas\nClassificação CPV (Vocabulário Comum para os Contratos Públicos)\nObjeto principal\nVocabulário Principal: 45246510\nPreço base s/IVA: 450.000,00 EUR\n7 - INDICAÇÕES ADICIONAIS\nO contrato envolve aquisição conjunta (satisfação de várias entidades)? Não\nO contrato é adjudicado por uma central de compras? Não\n8 - TÉCNICAS\nO concurso destina-se à celebração de um acordo-quadro? Inexistência de acordo-quadro\nÉ utilizado um leilão eletrónico? Não\nÉ adotada uma fase de negociação? Não\nSistema de Aquisição Dinâmico: Inexistência de sistema de aquisição dinâmico\n9 - LOCAL DA EXECUÇÃO DO CONTRATO\nLOCAL DA EXECUÇÃO DO CONTRATO (PROCEDIMENTO)\nPaís: Portugal\nNUT III: PT170\nLocalidade: União das Freguesias de Setúbal (São Julião, Nossa Senhora da Anunciada e Santa Maria da Graça)\nDistrito: Setúbal\nConcelho: Setúbal\nFreguesia: União das Freguesias de Setúbal (São Julião, Nossa Senhora da Anunciada e Santa Maria da Graça)\n10 - PRAZO DE EXECUÇÃO DO CONTRATO\nPrazo de execução do contrato: 120 DIAS\nPrevisão de renovações: Não\n11 - FUNDOS EU\nTêm fundos EU? Não\n12 - DOCUMENTOS DE HABILITAÇÃO\nHabilitação para o exercício da atividade profissional: Sim\nTipo: Alvará\nDescrição: Documento comprovativo da titularidade de alvará ou certificado de empreiteiro de obras públicas ou declaração emitida pelo Instituto dos Mercados Públicos, do Imobiliário e da Construção, I. P., (IMPIC, I. P.) nos termos da Portaria n.º 372/2017, de 14 de dezembro, contendo as habilitações adequadas e necessárias à execução da obra a realizar.\n13 - CONDIÇÕES DE APRESENTAÇÃO\nPlataforma eletrónica utilizada pela entidade adjudicante: ACIN\nURL para Apresentação: https://www.acingov.pt\nAdmissibilidade da apresentação de propostas variantes: Não autorizado\nPrazo para apresentação das propostas: 09-02-2026 23:59\nPrazo durante o qual os concorrentes são obrigados a manter as respetivas propostas: 66 dias a contar do termo do prazo para a apresentação das propostas\nIndicação de Subcontratação na Proposta: Inexistência de indicação de subcontratação\n14 - PRESTAÇÃO DE CAUÇÃO\nPrestação de caução: Sim\nPercentagem: 5%\nDescrição da Garantia Exigida: O valor da caução é de 5.00% do preço contratual.\n15 - FORNECIMENTO DAS PEÇAS DO CONCURSO, APRESENTAÇÃO DE PEDIDOS DE PARTICIPAÇÃO E APRESENTAÇÃO DAS PROPOSTAS\nLink para acesso às peças do concurso (URL): https://www.acingov.pt/acingovprod/2/zonaPublica/zona_publica_c/donwloadProcedurePiece/MTAzNjExNA==\n20 - OUTROS REQUISITOS\nInformação sobre contratos reservados. Aplica-se a contratos reservados (54º-A)? Não\n21 - CRITÉRIO DE ADJUDICAÇÃO\nMultifator: Sim\nFator: \nNome: Outros\nOutro Nome: Fator 1 (F1)  Preço de Execução da Empreitada\nPonderação: 70%\nSubfatores: Não\nFator: \nNome: Outros\nOutro Nome: Fator 2 (F2)  Valia Técnica\nPonderação: 20%\nSubfatores: Sim\nSubfatores: \nNome: Subfactor 1 (SF1) - Programa de Trabalhos, Plano de Mão de Obra e Plano de Equipamentos\nPonderação : 50%; \nNome: Subfactor 2 (SF2) - Memória Descritiva apresentada pelo Concorrente\nPonderação : 50%; \nFator: \nNome: Outros\nOutro Nome: Fator 3 (F3) - Prazo de Execução da Empreitada\nPonderação: 5%\nSubfatores: Não\nFator: \nNome: Outros\nOutro Nome: Fator 4 (F4) - Utilização de materiais reutilizados ou reciclados\nPonderação: 5%\nSubfatores: Não\n24 - CONDIÇÕES DO CONTRATO\nFaturação Eletrónica: Necessário\nObrigação de Subcontratação:\nCódigo da Obrigação de Subcontratação: Não é aplicável nenhuma obrigação de subcontratação.\n25 - COMPRA PÚBLICA ESTRATÉGICA\nCompra Pública Estratégica: Inexistência de contratação pública estratégica\n26 - INFORMAÇÕES ADICIONAIS\nContrato adequado para PME: Sim\nCobertura ACP (Acordo dos Contratos Públicos da Organização Mundial do Comércio): Não\n27 - IDENTIFICAÇÃO E CONTACTOS DO ÓRGÃO DE RECURSOS ADMINISTRATIVOS\nDesignação: Conselho de Administração da APSS - Administração dos Portos de Setúbal e Sesimbra, S.A.\nEndereço: Praça da República\nCódigo postal: 2904-508\nLocalidade: Setúbal\nTelefone: 265542000\nFax: 000000000\nEndereço eletrónico: apss-plataforma@portodesetubal.pt\nPrazo de interposição do recurso: 5 dias\n28 - IDENTIFICAÇÃO DO(S) AUTOR(ES) DE ANÚNCIO\nNome: Sérgio Bento\nCargo: Divisão de contratação pública\n419947544",
    "nipc": "502256869",
    "distrito": "Setúbal",
    "concelho": "Setúbal",
    "freguesia": "União das Freguesias de Setúbal (São Julião, Nossa Senhora da Anunciada e Santa Maria da Graça)",
    "site": "www.portodesetubal.pt",
    "email": "apss-plataforma@portodesetubal.pt",
    "designacao_contrato": "Substituição de passadiços flutuantes no interior da Doca dos Pescadores  linha 3 e longitudinais de apoio, em Setúbal",
    "descricao": "Substituição de passadiços flutuantes no interior da Doca dos Pescadores  linha 3 e longitudinais de apoio, em Setúbal",
    "preco_base": "450.000,00 EUR",
    "prazo_execucao": "120 DIAS",
    "prazo_apresentacao_propostas": "09-02-2026 23:59",
    "fundos_eu": "Não",
    "plataforma_eletronica": "ACIN",
    "url_procedimento": "https://www.acingov.pt",
    "autor_nome": "Sérgio Bento",
    "autor_cargo": "Divisão de contratação pública"
  },
  {
    "numero_procedimento": "N/A",
    "entidade": "AnÃºncio de procedimento  n.Âº 433/2026  -  DiÃ¡rio da RepÃºblica n.Âº 6/2026, SÃ©rie II de 2026-01-09",
    "link": "https://diariodarepublica.pt/dr/detalhe/contrato-publico/433-1003372824"
  },
  {
    "numero_procedimento": "N/A",
    "entidade": "AnÃºncio de procedimento  n.Âº 403/2026  -  DiÃ¡rio da RepÃºblica n.Âº 6/2026, SÃ©rie II de 2026-01-09",
    "link": "https://diariodarepublica.pt/dr/detalhe/contrato-publico/403-1003400075"
  },
  {
    "numero_procedimento": "N/A",
    "entidade": "IAPMEI - Agência para a Competitividade e Inovação, IP",
    "link": "https://diariodarepublica.pt/dr/detalhe/contrato-publico/405-1003400076",
    "detalhes_completos": "1 - IDENTIFICAÇÃO E CONTACTOS DA ENTIDADE ADJUDICANTE\nDesignação da entidade adjudicante: IAPMEI - Agência para a Competitividade e Inovação, IP\nNIPC: 501373357\nServiço/Órgão/Pessoa de contacto: CD IAPMEI\nEndereço: Estrada do Paço do Lumiar, Campus do Lumiar, Edificio A\nCódigo postal: 1649-038\nLocalidade: Lisboa\nPaís: Portugal\nNUT III: PT170\nDistrito: Lisboa\nConcelho: Lisboa\nFreguesia: Freguesia de Lumiar\nTelefone: 213836000\nEndereço da Entidade (URL): www.iapmei.pt/\nEndereço Eletrónico: info@iapmei.pt\neDelivery Gateway (URL): https://www.acingov.pt\nFunção da Organização: Adquirente\nNorma jurídica da Entidade Adjudicante: Organismo de direito público\nÁrea de atividade da Autoridade Adjudicante: Serviços públicos das administrações públicas\n2 - JORNAL OFICIAL DA UNIÃO EUROPEIA\nO procedimento a que este anúncio diz respeito também é publicitado no Jornal Oficial da União Europeia? Sim\n3 - AVISO\nModelo de Anúncio: Concurso público\nData de Envio do Anúncio: 07-01-2026\n5 - PROCESSO\nTipo de Procedimento: Concurso público\nPreço base do procedimento: Sim\nValor do preço base do procedimento: 254.460,00 EUR\nProcedimento com lotes? Não\n6 - OBJETO DO CONTRATO\nNúmero de referência interna: DPCP2025CP57\nDesignação do contrato: Aquisição de serviços de higiene e limpeza para a Agência para a Competitividade e Inovação, I.P. (IAPMEI), para 2026\nDescrição: Aquisição de serviços de higiene e limpeza para a Agência para a Competitividade e Inovação, I.P. (IAPMEI), para 2026\nOpções: Não\nTipo de Contrato Principal: Aquisição de Serviços\nTipo de Contrato: Aquisição de Serviços\nClassificação CPV (Vocabulário Comum para os Contratos Públicos)\nObjeto principal\nVocabulário Principal: 90900000\nPreço base s/IVA: 254.460,00 EUR\n7 - INDICAÇÕES ADICIONAIS\nO contrato envolve aquisição conjunta (satisfação de várias entidades)? Não\nO contrato é adjudicado por uma central de compras? Não\n8 - TÉCNICAS\nO concurso destina-se à celebração de um acordo-quadro? Inexistência de acordo-quadro\nÉ utilizado um leilão eletrónico? Não\nÉ adotada uma fase de negociação? Não\nSistema de Aquisição Dinâmico: Inexistência de sistema de aquisição dinâmico\n9 - LOCAL DA EXECUÇÃO DO CONTRATO\nLOCAL DA EXECUÇÃO DO CONTRATO (PROCEDIMENTO)\nPaís: Portugal\nNUT III: PTZZZ\nLocalidade: Todas\nDistrito: Portugal Continental\nConcelho: Todos\nFreguesia: Todas\n10 - PRAZO DE EXECUÇÃO DO CONTRATO\nPrazo de execução do contrato: 11 MESES\nPrevisão de renovações: Não\n11 - FUNDOS EU\nTêm fundos EU? Não\n12 - DOCUMENTOS DE HABILITAÇÃO\nHabilitação para o exercício da atividade profissional: Não\n13 - CONDIÇÕES DE APRESENTAÇÃO\nPlataforma eletrónica utilizada pela entidade adjudicante: ACIN\nURL para Apresentação: https://www.acingov.pt\nAdmissibilidade da apresentação de propostas variantes: Não autorizado\nPrazo para apresentação das propostas: 06-02-2026 17:00\nPrazo durante o qual os concorrentes são obrigados a manter as respetivas propostas: 66 dias a contar do termo do prazo para a apresentação das propostas\nApresentação de Catálogo Eletrónico: Permitido\nIndicação de Subcontratação na Proposta: Inexistência de indicação de subcontratação\n14 - PRESTAÇÃO DE CAUÇÃO\nPrestação de caução: Não\n15 - FORNECIMENTO DAS PEÇAS DO CONCURSO, APRESENTAÇÃO DE PEDIDOS DE PARTICIPAÇÃO E APRESENTAÇÃO DAS PROPOSTAS\nLink para acesso às peças do concurso (URL): https://www.acingov.pt/acingovprod/2/zonaPublica/zona_publica_c/donwloadProcedurePiece/MTAzNjU1NQ==\n20 - OUTROS REQUISITOS\nInformação sobre contratos reservados. Aplica-se a contratos reservados (54º-A)? Não\n21 - CRITÉRIO DE ADJUDICAÇÃO\nMultifator: Não\nMonofator:\nNome: Preço\n24 - CONDIÇÕES DO CONTRATO\nFaturação Eletrónica: Permitido\nObrigação de Subcontratação:\nCódigo da Obrigação de Subcontratação: Não é aplicável nenhuma obrigação de subcontratação.\n25 - COMPRA PÚBLICA ESTRATÉGICA\nCompra Pública Estratégica: Redução dos impactos ambientais\nDescrição do Processo de Adjudicação Estratégico: Aquisição de serviços de higiene e limpeza\nCritérios de contratos Públicos Ecológicos: Critérios de contratação pública ecológica nacional\nCategorias da estratégia nacional: Serviços de limpeza de interiores\nContratos Públicos Ecológicos: A mitigação das alterações climáticas; A prevenção e o controlo da poluição\nDiretiva Veículos Não Poluentes: Não\nCritério de Acessibilidade: Os critérios de acessibilidade para as pessoas com deficiência não estão incluídos porque o contrato não se destina a pessoas singulares\n26 - INFORMAÇÕES ADICIONAIS\nContrato adequado para PME: Sim\nCobertura ACP (Acordo dos Contratos Públicos da Organização Mundial do Comércio): Não\n27 - IDENTIFICAÇÃO E CONTACTOS DO ÓRGÃO DE RECURSOS ADMINISTRATIVOS\nDesignação: CD IAPMEI\nEndereço: https://www.iapmei.pt/\nCódigo postal: 1649-038\nLocalidade: Lisboa\nTelefone: 213836009\nFax: \nEndereço eletrónico: info@iapmei.pt\n28 - IDENTIFICAÇÃO DO(S) AUTOR(ES) DE ANÚNCIO\nNome: Emanuela Alexandra Pires Monteiro\nCargo: Tecnica Superior\n419947322",
    "nipc": "501373357",
    "distrito": "Lisboa",
    "concelho": "Lisboa",
    "freguesia": "Freguesia de Lumiar",
    "site": "www.iapmei.pt/",
    "email": "info@iapmei.pt",
    "designacao_contrato": "Aquisição de serviços de higiene e limpeza para a Agência para a Competitividade e Inovação, I.P. (IAPMEI), para 2026",
    "descricao": "Aquisição de serviços de higiene e limpeza para a Agência para a Competitividade e Inovação, I.P. (IAPMEI), para 2026",
    "preco_base": "254.460,00 EUR",
    "prazo_execucao": "11 MESES",
    "prazo_apresentacao_propostas": "06-02-2026 17:00",
    "fundos_eu": "Não",
    "plataforma_eletronica": "ACIN",
    "url_procedimento": "https://www.acingov.pt",
    "autor_nome": "Emanuela Alexandra Pires Monteiro",
    "autor_cargo": "Tecnica Superior"
  },
  {
    "numero_procedimento": "N/A",
    "entidade": "Unidade Local de Saúde de Lisboa Ocidental, EPE",
    "link": "https://diariodarepublica.pt/dr/detalhe/contrato-publico/407-1003400077",
    "detalhes_completos": "1 - IDENTIFICAÇÃO E CONTACTOS DA ENTIDADE ADJUDICANTE\nDesignação da entidade adjudicante: Unidade Local de Saúde de Lisboa Ocidental, EPE\nNIPC: 507618319\nServiço/Órgão/Pessoa de contacto: Conselho de Administração\nEndereço: Santa Maria de Belém  Estrada do Forte do Alto do Duque\nCódigo postal: 1449-005\nLocalidade: Lisboa\nPaís: Portugal\nNUT III: PT170\nDistrito: Lisboa\nConcelho: Lisboa\nFreguesia: Todas\nTelefone: 210431000\nFax: 210431642\nEndereço da Entidade (URL): www.chlo.min-saude.pt/\nEndereço Eletrónico: comprasgeral@ulslo.min-saude.pt\neDelivery Gateway (URL): https://community.vortal.biz/public/\nFunção da Organização: Adquirente\nNorma jurídica da Entidade Adjudicante: Organismo de direito público\nÁrea de atividade da Autoridade Adjudicante: Saúde\n2 - JORNAL OFICIAL DA UNIÃO EUROPEIA\nO procedimento a que este anúncio diz respeito também é publicitado no Jornal Oficial da União Europeia? Sim\n3 - AVISO\nModelo de Anúncio: Concurso público\nData de Envio do Anúncio: 07-01-2026\n5 - PROCESSO\nTipo de Procedimento: Concurso público\nPreço base do procedimento: Sim\nValor do preço base do procedimento: 1.430.396,60 EUR\nProcedimento com lotes? Sim\nNº Máx. de Lotes Autorizado: 5\nNúmero máximo de lotes que podem ser adjudicados a um concorrente: 5\n6 - OBJETO DO CONTRATO\nNúmero de referência interna: 147000226\nDesignação do contrato: Prestação de serviços de realização de meios complementares de diagnóstico e terapêutica, em RM, a utentes da Unidade Local de Saúde de Lisboa Ocidental, E.P.E. no ano de 2026\nDescrição: Prestação de serviços de realização de meios complementares de diagnóstico e terapêutica, em RM, a utentes da Unidade Local de Saúde de Lisboa Ocidental, E.P.E. no ano de 2026\nOpções: Não\nTipo de Contrato Principal: Aquisição de Serviços\nTipo de Contrato: Aquisição de Serviços\nClassificação CPV (Vocabulário Comum para os Contratos Públicos)\nObjeto principal\nVocabulário Principal: 85150000\nPreço base s/IVA: 1.430.396,60 EUR\nLotes: \nNº: LOT-0005\nDescrição do Lote: Lote 5\nPreço base s/IVA: 7.229,40 EUR\nClassificação CPV (Vocabulário Comum para os Contratos Públicos)\nObjeto principal\nVocabulário Principal: 85150000\nNº: LOT-0004\nDescrição do Lote: Lote 4\nPreço base s/IVA: 6.589,50 EUR\nClassificação CPV (Vocabulário Comum para os Contratos Públicos)\nObjeto principal\nVocabulário Principal: 85150000\nNº: LOT-0003\nDescrição do Lote: Lote 3\nPreço base s/IVA: 55.815,50 EUR\nClassificação CPV (Vocabulário Comum para os Contratos Públicos)\nObjeto principal\nVocabulário Principal: 85150000\nNº: LOT-0002\nDescrição do Lote: Lote 2\nPreço base s/IVA: 1.310.442,80 EUR\nClassificação CPV (Vocabulário Comum para os Contratos Públicos)\nObjeto principal\nVocabulário Principal: 85150000\nNº: LOT-0001\nDescrição do Lote: Lote 1\nPreço base s/IVA: 50.319,40 EUR\nClassificação CPV (Vocabulário Comum para os Contratos Públicos)\nObjeto principal\nVocabulário Principal: 85150000\n7 - INDICAÇÕES ADICIONAIS\nO contrato envolve aquisição conjunta (satisfação de várias entidades)? Não\nO contrato é adjudicado por uma central de compras? Não\n8 - TÉCNICAS\nO concurso destina-se à celebração de um acordo-quadro? Inexistência de acordo-quadro\nÉ utilizado um leilão eletrónico? Não\nÉ adotada uma fase de negociação? Não\nSistema de Aquisição Dinâmico: Inexistência de sistema de aquisição dinâmico\n9 - LOCAL DA EXECUÇÃO DO CONTRATO\nLOCAL DA EXECUÇÃO DO CONTRATO (PROCEDIMENTO)\nPaís: Portugal\nNUT III: PT170\nLocalidade: Lisboa\nDistrito: Lisboa\nConcelho: Lisboa\nFreguesia: Todas\nLOCAL DA EXECUÇÃO DO CONTRATO (LOTE)\nIdentificador do Lote: LOT-0001; LOT-0002; LOT-0003; LOT-0004; LOT-0005\nPaís: Portugal\nNUT III: PT170\nLocalidade: Lisboa\nDistrito: Lisboa\nConcelho: Lisboa\nFreguesia: Todas\n10 - PRAZO DE EXECUÇÃO DO CONTRATO\nIdentificador do Lote: LOT-0001; LOT-0002; LOT-0003; LOT-0004; LOT-0005\nPrazo de execução do contrato: 10 MESES\nPrevisão de renovações: Não\n11 - FUNDOS EU\nIdentificador do Lote: LOT-0001; LOT-0002; LOT-0003; LOT-0004; LOT-0005\nTêm fundos EU? Não\n12 - DOCUMENTOS DE HABILITAÇÃO\nHabilitação para o exercício da atividade profissional: Não\n13 - CONDIÇÕES DE APRESENTAÇÃO\nPlataforma eletrónica utilizada pela entidade adjudicante: VORTAL\nURL para Apresentação: https://community.vortal.biz/public/\nAdmissibilidade da apresentação de propostas variantes: Não autorizado\nPrazo para apresentação das propostas: 12-02-2026 17:00\nPrazo durante o qual os concorrentes são obrigados a manter as respetivas propostas: 120 dias a contar do termo do prazo para a apresentação das propostas\nApresentação de Catálogo Eletrónico: Não autorizado\nIndicação de Subcontratação na Proposta: Inexistência de indicação de subcontratação\n14 - PRESTAÇÃO DE CAUÇÃO\nPrestação de caução: Sim\nPercentagem: 5%\nDescrição da Garantia Exigida: Conforme indicado nas peças do procedimento\n15 - FORNECIMENTO DAS PEÇAS DO CONCURSO, APRESENTAÇÃO DE PEDIDOS DE PARTICIPAÇÃO E APRESENTAÇÃO DAS PROPOSTAS\nLink para acesso às peças do concurso (URL): https://community.vortal.biz/Public/public-tender-documents/Sk9zeDc5UURPSjB0TWw1SEZ4VXc2RHdjeUd2OU1pNXFQZGRaM2hiMCtVRHNKaTFKZG1hQUh4RDQzNjZwVnNGZng3dlRHQ25YMjdmbG1HTTNIZ3lpemc9PXk3Tlc5\n20 - OUTROS REQUISITOS\nIdentificador do Lote: LOT-0001; LOT-0002; LOT-0003; LOT-0004; LOT-0005\nInformação sobre contratos reservados. Aplica-se a contratos reservados (54º-A)? Não\n21 - CRITÉRIO DE ADJUDICAÇÃO\nO Critério de adjudicação é diferenciado por lote? Não\nMultifator: Não\nMonofator:\nNome: Preço\n24 - CONDIÇÕES DO CONTRATO\nIdentificador do Lote: LOT-0001; LOT-0002; LOT-0003; LOT-0004; LOT-0005\nFaturação Eletrónica: Permitido\nObrigação de Subcontratação:\nCódigo da Obrigação de Subcontratação: Não é aplicável nenhuma obrigação de subcontratação.\n25 - COMPRA PÚBLICA ESTRATÉGICA\nCompra Pública Estratégica: Inexistência de contratação pública estratégica\n26 - INFORMAÇÕES ADICIONAIS\nIdentificador do Lote: LOT-0001; LOT-0002; LOT-0003; LOT-0004; LOT-0005\nContrato adequado para PME: Sim\nCobertura ACP (Acordo dos Contratos Públicos da Organização Mundial do Comércio): Não\n27 - IDENTIFICAÇÃO E CONTACTOS DO ÓRGÃO DE RECURSOS ADMINISTRATIVOS\nDesignação: Conselho de Administração\nEndereço: Estrada do alto do forte do duque\nCódigo postal: 1449-005\nLocalidade: Lisboa\nTelefone: +351 210431000\nFax: +351 210431639\nEndereço eletrónico: compras.adm.hot.ps.inv@ulslo.min-saude.pt\n28 - IDENTIFICAÇÃO DO(S) AUTOR(ES) DE ANÚNCIO\nNome: Eduardo Neves\nCargo: Assistente Técnico\n419947338",
    "nipc": "507618319",
    "distrito": "Lisboa",
    "concelho": "Lisboa",
    "freguesia": "Todas",
    "site": "www.chlo.min-saude.pt/",
    "email": "comprasgeral@ulslo.min-saude.pt",
    "designacao_contrato": "Prestação de serviços de realização de meios complementares de diagnóstico e terapêutica, em RM, a utentes da Unidade Local de Saúde de Lisboa Ocidental, E.P.E. no ano de 2026",
    "descricao": "Prestação de serviços de realização de meios complementares de diagnóstico e terapêutica, em RM, a utentes da Unidade Local de Saúde de Lisboa Ocidental, E.P.E. no ano de 2026",
    "preco_base": "1.430.396,60 EUR",
    "prazo_execucao": "10 MESES",
    "prazo_apresentacao_propostas": "12-02-2026 17:00",
    "fundos_eu": "Não",
    "plataforma_eletronica": "VORTAL",
    "url_procedimento": "https://community.vortal.biz/public/",
    "autor_nome": "Eduardo Neves",
    "autor_cargo": "Assistente Técnico"
  },
  {
    "numero_procedimento": "N/A",
    "entidade": "AnÃºncio de procedimento  n.Âº 409/2026  -  DiÃ¡rio da RepÃºblica n.Âº 6/2026, SÃ©rie II de 2026-01-09",
    "link": "https://diariodarepublica.pt/dr/detalhe/contrato-publico/409-1003400078"
  },
  {
    "numero_procedimento": "N/A",
    "entidade": "AnÃºncio de procedimento  n.Âº 411/2026  -  DiÃ¡rio da RepÃºblica n.Âº 6/2026, SÃ©rie II de 2026-01-09",
    "link": "https://diariodarepublica.pt/dr/detalhe/contrato-publico/411-1003400079"
  },
  {
    "numero_procedimento": "N/A",
    "entidade": "Comunidade Intermunicipal do Alto Alentejo",
    "link": "https://diariodarepublica.pt/dr/detalhe/contrato-publico/413-1003400080",
    "detalhes_completos": "Alteração do Anúncio de procedimento n.º 32397/2025, de 2025-12-15, com o ID 419876902\n1 - IDENTIFICAÇÃO E CONTACTOS DA ENTIDADE ADJUDICANTE\nDesignação da entidade adjudicante: Comunidade Intermunicipal do Alto Alentejo\nNIPC: 509020690\nServiço/Órgão/Pessoa de contacto: Central de Compras do Conselho Intermunicipal do Alto Alentejo\nEndereço: Rua 19 de Junho, nº26\nCódigo postal: 7300-155\nLocalidade: Portalegre\nPaís: Portugal\nNUT III: PT186\nDistrito: Portalegre\nConcelho: Portalegre\nFreguesia: União das Freguesias da Sé e São Lourenço\nTelefone: 245301440\nFax: 245301449\nEndereço da Entidade (URL): www.cimaa.pt\nEndereço Eletrónico: geral@cimaa.pt\neDelivery Gateway (URL): https://community.vortal.biz/public/\nFunção da Organização: Adquirente\nNorma jurídica da Entidade Adjudicante: Autoridade da administração central\nÁrea de atividade da Autoridade Adjudicante: Serviços públicos das administrações públicas\n2 - JORNAL OFICIAL DA UNIÃO EUROPEIA\nO procedimento a que este anúncio diz respeito também é publicitado no Jornal Oficial da União Europeia? Sim\n3 - AVISO\nModelo de Anúncio: Concurso público\nData de Envio do Anúncio: 07-01-2026\n5 - PROCESSO\nTipo de Procedimento: Concurso público\nPreço base do procedimento: Sim\nValor do preço base do procedimento: 1.800.000,00 EUR\nProcedimento com lotes? Não\n6 - OBJETO DO CONTRATO\nNúmero de referência interna: 2025/300.10.005/311\nDesignação do contrato: Fornecimento de PGU e Verticais de Smart Cities\nDescrição: A aquisição de uma Plataforma de Gestão Urbana – PGU, e dez verticais de Smart Cities para a Comunidade Intermunicipal do Alto Alentejo. O projeto tem enquadramento no Aviso N.º 01/C19-i08/2024 — Aquisição e Desenvolvimento de Plataformas de Gestão Urbana, no âmbito do investimento C19-i08 Territórios Inteligentes – AMA | Estratégia Nacional dos Territórios Inteligentes, datado de 16 de setembro de 2024.\nOpções: Não\nTipo de Contrato Principal: Aquisição de Serviços\nTipo de Contrato: Aquisição de Serviços\nClassificação CPV (Vocabulário Comum para os Contratos Públicos)\nObjeto principal\nVocabulário Principal: 72230000\nPreço base s/IVA: 1.800.000,00 EUR\n7 - INDICAÇÕES ADICIONAIS\nO contrato envolve aquisição conjunta (satisfação de várias entidades)? Não\nO contrato é adjudicado por uma central de compras? Sim\n8 - TÉCNICAS\nO concurso destina-se à celebração de um acordo-quadro? Inexistência de acordo-quadro\nÉ utilizado um leilão eletrónico? Não\nÉ adotada uma fase de negociação? Não\nSistema de Aquisição Dinâmico: Inexistência de sistema de aquisição dinâmico\n9 - LOCAL DA EXECUÇÃO DO CONTRATO\nLOCAL DA EXECUÇÃO DO CONTRATO (PROCEDIMENTO)\nPaís: Portugal\nNUT III: PT186\nLocalidade: Portalegre\nDistrito: Portalegre\nConcelho: Portalegre\nFreguesia: União das Freguesias da Sé e São Lourenço\n10 - PRAZO DE EXECUÇÃO DO CONTRATO\nPrazo de execução do contrato: 30 DIAS\nPrevisão de renovações: Não\n11 - FUNDOS EU\nTêm fundos EU? Sim\n12 - DOCUMENTOS DE HABILITAÇÃO\nHabilitação para o exercício da atividade profissional: Não\n13 - CONDIÇÕES DE APRESENTAÇÃO\nPlataforma eletrónica utilizada pela entidade adjudicante: VORTAL\nURL para Apresentação: https://community.vortal.biz/public/\nAdmissibilidade da apresentação de propostas variantes: Não autorizado\nPrazo para apresentação das propostas: 17-01-2026 23:59\nPrazo durante o qual os concorrentes são obrigados a manter as respetivas propostas: 120 dias a contar do termo do prazo para a apresentação das propostas\nApresentação de Catálogo Eletrónico: Permitido\nIndicação de Subcontratação na Proposta: Inexistência de indicação de subcontratação\n14 - PRESTAÇÃO DE CAUÇÃO\nPrestação de caução: Sim\nPercentagem: 5%\nDescrição da Garantia Exigida: De acordo com o Caderno de Encargos\n15 - FORNECIMENTO DAS PEÇAS DO CONCURSO, APRESENTAÇÃO DE PEDIDOS DE PARTICIPAÇÃO E APRESENTAÇÃO DAS PROPOSTAS\nLink para acesso às peças do concurso (URL): https://community.vortal.biz/Public/public-tender-documents/MkI2WkpTV0ZKVXZzS2V5NFRmQnJUN1lRQUVPZG43WThTVC81R0hBNHBEeWFKcGQ0aXhLTmNiWWpwdlgrK0pLMGZQbldvTXlLYThETkFFUTNKUFY1bXc9PWxYRGow\n20 - OUTROS REQUISITOS\nInformação sobre contratos reservados. Aplica-se a contratos reservados (54º-A)? Não\n21 - CRITÉRIO DE ADJUDICAÇÃO\nMultifator: Sim\nFator: \nNome: Preço\nPonderação: 60%\nSubfatores: Não\nFator: \nNome: Qualidade\nPonderação: 40%\nSubfatores: Sim\nSubfatores: \nNome: Capacitação da Equipa de Gestão de Projeto \nPonderação : 30%; \nNome: Certificação de Qualidade do Concorrente \nPonderação : 30%; \nNome: Experiência do Concorrente na Implementação de Projetos Similares\nPonderação : 25%; \nNome: Metodologia e Qualidade Técnica da Proposta \nPonderação : 15%; \n24 - CONDIÇÕES DO CONTRATO\nFaturação Eletrónica: Permitido\nObrigação de Subcontratação:\nCódigo da Obrigação de Subcontratação: Não é aplicável nenhuma obrigação de subcontratação.\n25 - COMPRA PÚBLICA ESTRATÉGICA\nCompra Pública Estratégica: Inexistência de contratação pública estratégica\n26 - INFORMAÇÕES ADICIONAIS\nContrato adequado para PME: Sim\nCobertura ACP (Acordo dos Contratos Públicos da Organização Mundial do Comércio): Não\n27 - IDENTIFICAÇÃO E CONTACTOS DO ÓRGÃO DE RECURSOS ADMINISTRATIVOS\nDesignação: Conselho Intermunicipal do Alto Alentejo\nEndereço: Rua 19 de Junho, nº26\nCódigo postal: 7300-155\nLocalidade: Portalegre\nTelefone: +351 245301440\nFax: +351 245301440\nEndereço eletrónico: cc@cimaa.pt\n28 - IDENTIFICAÇÃO DO(S) AUTOR(ES) DE ANÚNCIO\nNome: Nuno Samelo\nCargo: Jurista - Técnico Superior\n29 - ALTERAÇÃO\nMotivo da Alteração: Informações atualizadas\nIdentificador da Versão do Anúncio a Alterar: c1ba0200-72a5-44eb-98ba-827668470cae-01\nIdentificador das Secções Alteradas do Anúncio Anterior: Aviso\nDescrição das Alterações: Prazo alterado ao abrigo do artigo 64.º do CCP\nAlteração dos Documentos do Concurso: Sim\nData de alteração dos documentos do concurso: 07-01-2026\n419947368",
    "nipc": "509020690",
    "distrito": "Portalegre",
    "concelho": "Portalegre",
    "freguesia": "União das Freguesias da Sé e São Lourenço",
    "site": "www.cimaa.pt",
    "email": "geral@cimaa.pt",
    "designacao_contrato": "Fornecimento de PGU e Verticais de Smart Cities",
    "descricao": "A aquisição de uma Plataforma de Gestão Urbana – PGU, e dez verticais de Smart Cities para a Comunidade Intermunicipal do Alto Alentejo. O projeto tem enquadramento no Aviso N.º 01/C19-i08/2024 — Aquisição e Desenvolvimento de Plataformas de Gestão Urbana, no âmbito do investimento C19-i08 Territórios Inteligentes – AMA | Estratégia Nacional dos Territórios Inteligentes, datado de 16 de setembro de 2024.",
    "preco_base": "1.800.000,00 EUR",
    "prazo_execucao": "30 DIAS",
    "prazo_apresentacao_propostas": "17-01-2026 23:59",
    "fundos_eu": "Sim",
    "plataforma_eletronica": "VORTAL",
    "url_procedimento": "https://community.vortal.biz/public/",
    "autor_nome": "Nuno Samelo",
    "autor_cargo": "Jurista - Técnico Superior"
  },
  {
    "numero_procedimento": "N/A",
    "entidade": "Unidade Local de Saúde do Alto Ave, EPE",
    "link": "https://diariodarepublica.pt/dr/detalhe/contrato-publico/415-1003400081",
    "detalhes_completos": "1 - IDENTIFICAÇÃO E CONTACTOS DA ENTIDADE ADJUDICANTE\nDesignação da entidade adjudicante: Unidade Local de Saúde do Alto Ave, EPE\nNIPC: 508080827\nEndereço: Rua dos Cutileiros, Creixomil\nCódigo postal: 4835-044\nLocalidade: Guimarães\nPaís: Portugal\nNUT III: PT119\nDistrito: Braga\nConcelho: Guimarães\nFreguesia: Todas\nTelefone: 253540330\nFax: 253513592\nEndereço da Entidade (URL): http://www.hospitaldeguimaraes.min-saude.pt/\nEndereço Eletrónico: aprovisionamento@hospitaldeguimaraes.min-saude.pt\neDelivery Gateway (URL): https://community.vortal.biz/public/\nFunção da Organização: Adquirente\nNorma jurídica da Entidade Adjudicante: Organismo de direito público\nÁrea de atividade da Autoridade Adjudicante: Saúde\n2 - JORNAL OFICIAL DA UNIÃO EUROPEIA\nO procedimento a que este anúncio diz respeito também é publicitado no Jornal Oficial da União Europeia? Sim\n3 - AVISO\nModelo de Anúncio: Concurso público\nData de Envio do Anúncio: 07-01-2026\n5 - PROCESSO\nTipo de Procedimento: Concurso público\nPreço base do procedimento: Sim\nValor do preço base do procedimento: 338.915,00 EUR\nProcedimento com lotes? Sim\nNº Máx. de Lotes Autorizado: 3\nNúmero máximo de lotes que podem ser adjudicados a um concorrente: 3\n6 - OBJETO DO CONTRATO\nNúmero de referência interna:  CP/0016/2026\nDesignação do contrato: Próteses Totais da Anca \nDescrição:  CP/0016/2026-Próteses Totais da Anca \nOpções: Não\nTipo de Contrato Principal: Aquisição de Bens Móveis\nTipo de Contrato: Aquisição de Bens Móveis\nClassificação CPV (Vocabulário Comum para os Contratos Públicos)\nObjeto principal\nVocabulário Principal: 33100000\nPreço base s/IVA: 338.915,00 EUR\nLotes: \nNº: LOT-0001\nDescrição do Lote: Lote 1\nPreço base s/IVA: 255.035,00 EUR\nClassificação CPV (Vocabulário Comum para os Contratos Públicos)\nObjeto principal\nVocabulário Principal: 33100000\nNº: LOT-0002\nDescrição do Lote: Lote 2\nPreço base s/IVA: 34.020,00 EUR\nClassificação CPV (Vocabulário Comum para os Contratos Públicos)\nObjeto principal\nVocabulário Principal: 33100000\nNº: LOT-0003\nDescrição do Lote: Lote 3\nPreço base s/IVA: 49.860,00 EUR\nClassificação CPV (Vocabulário Comum para os Contratos Públicos)\nObjeto principal\nVocabulário Principal: 33100000\n7 - INDICAÇÕES ADICIONAIS\nO contrato envolve aquisição conjunta (satisfação de várias entidades)? Não\nO contrato é adjudicado por uma central de compras? Não\n8 - TÉCNICAS\nO concurso destina-se à celebração de um acordo-quadro? Inexistência de acordo-quadro\nÉ utilizado um leilão eletrónico? Não\nÉ adotada uma fase de negociação? Não\nSistema de Aquisição Dinâmico: Inexistência de sistema de aquisição dinâmico\n9 - LOCAL DA EXECUÇÃO DO CONTRATO\nLOCAL DA EXECUÇÃO DO CONTRATO (PROCEDIMENTO)\nPaís: Portugal\nNUT III: PT119\nLocalidade: Braga\nDistrito: Braga\nConcelho: Guimarães\nFreguesia: Freguesia de Creixomil - Guimarães\nLOCAL DA EXECUÇÃO DO CONTRATO (LOTE)\nIdentificador do Lote: LOT-0001; LOT-0002; LOT-0003\nPaís: Portugal\nNUT III: PT119\nLocalidade: Braga\nDistrito: Braga\nConcelho: Guimarães\nFreguesia: Freguesia de Creixomil - Guimarães\n10 - PRAZO DE EXECUÇÃO DO CONTRATO\nIdentificador do Lote: LOT-0001; LOT-0002; LOT-0003\nPrazo de execução do contrato: 12 MESES\nPrevisão de renovações: Não\n11 - FUNDOS EU\nIdentificador do Lote: LOT-0001; LOT-0002; LOT-0003\nTêm fundos EU? Não\n12 - DOCUMENTOS DE HABILITAÇÃO\nHabilitação para o exercício da atividade profissional: Não\n13 - CONDIÇÕES DE APRESENTAÇÃO\nPlataforma eletrónica utilizada pela entidade adjudicante: VORTAL\nURL para Apresentação: https://community.vortal.biz/public/\nAdmissibilidade da apresentação de propostas variantes: Não autorizado\nPrazo para apresentação das propostas: 09-02-2026 17:00\nPrazo durante o qual os concorrentes são obrigados a manter as respetivas propostas: 180 dias a contar do termo do prazo para a apresentação das propostas\nApresentação de Catálogo Eletrónico: Permitido\nIndicação de Subcontratação na Proposta: Inexistência de indicação de subcontratação\n14 - PRESTAÇÃO DE CAUÇÃO\nPrestação de caução: Não\n15 - FORNECIMENTO DAS PEÇAS DO CONCURSO, APRESENTAÇÃO DE PEDIDOS DE PARTICIPAÇÃO E APRESENTAÇÃO DAS PROPOSTAS\nLink para acesso às peças do concurso (URL): https://community.vortal.biz/Public/public-tender-documents/RGdBUWtOdXllWXRDNjEvampaS05GY3VuSHZ0Yy9OZUlNN1ZUQUVJWEUvY285bW8xa0t5R1JJSHFzOE8vN3BXUXBjdXY4aS84K0lDM2RCdkVWalRNSFE9PVBOSnFr\n20 - OUTROS REQUISITOS\nIdentificador do Lote: LOT-0001; LOT-0002; LOT-0003\nInformação sobre contratos reservados. Aplica-se a contratos reservados (54º-A)? Não\n21 - CRITÉRIO DE ADJUDICAÇÃO\nO Critério de adjudicação é diferenciado por lote? Não\nMultifator: Sim\nFator: \nNome: Preço\nPonderação: 40%\nSubfatores: Não\nFator: \nNome: Qualidade\nPonderação: 40%\nSubfatores: Não\nFator: \nNome: Qualidade\nPonderação: 20%\nSubfatores: Não\n24 - CONDIÇÕES DO CONTRATO\nIdentificador do Lote: LOT-0001; LOT-0002; LOT-0003\nFaturação Eletrónica: Permitido\nObrigação de Subcontratação:\nCódigo da Obrigação de Subcontratação: Não é aplicável nenhuma obrigação de subcontratação.\n25 - COMPRA PÚBLICA ESTRATÉGICA\nCompra Pública Estratégica: Inexistência de contratação pública estratégica\n26 - INFORMAÇÕES ADICIONAIS\nIdentificador do Lote: LOT-0001; LOT-0002; LOT-0003\nContrato adequado para PME: Sim\nCobertura ACP (Acordo dos Contratos Públicos da Organização Mundial do Comércio): Não\n27 - IDENTIFICAÇÃO E CONTACTOS DO ÓRGÃO DE RECURSOS ADMINISTRATIVOS\nDesignação: UNIDADE LOCAL DE SAUDE DO ALTO AVE\nEndereço: Rua dos Cuileiros\nCódigo postal: 4835-044\nLocalidade: Guimarães\nTelefone: +351 253540330\nFax: +351 253540330\nEndereço eletrónico: compras@ulsaave.min-saude.pt\n28 - IDENTIFICAÇÃO DO(S) AUTOR(ES) DE ANÚNCIO\nNome: Eng. Arlindo Soares\nCargo: Diretor do Serviço Compras e Logística\n419947384",
    "nipc": "508080827",
    "distrito": "Braga",
    "concelho": "Guimarães",
    "freguesia": "Todas",
    "site": "http://www.hospitaldeguimaraes.min-saude.pt/",
    "email": "aprovisionamento@hospitaldeguimaraes.min-saude.pt",
    "designacao_contrato": "Próteses Totais da Anca",
    "descricao": "CP/0016/2026-Próteses Totais da Anca",
    "preco_base": "338.915,00 EUR",
    "prazo_execucao": "12 MESES",
    "prazo_apresentacao_propostas": "09-02-2026 17:00",
    "fundos_eu": "Não",
    "plataforma_eletronica": "VORTAL",
    "url_procedimento": "https://community.vortal.biz/public/",
    "autor_nome": "Eng. Arlindo Soares",
    "autor_cargo": "Diretor do Serviço Compras e Logística"
  },
  {
    "numero_procedimento": "N/A",
    "entidade": "AnÃºncio de procedimento  n.Âº 417/2026  -  DiÃ¡rio da RepÃºblica n.Âº 6/2026, SÃ©rie II de 2026-01-09",
    "link": "https://diariodarepublica.pt/dr/detalhe/contrato-publico/417-1003400082"
  },
  {
    "numero_procedimento": "N/A",
    "entidade": "AnÃºncio de procedimento  n.Âº 419/2026  -  DiÃ¡rio da RepÃºblica n.Âº 6/2026, SÃ©rie II de 2026-01-09",
    "link": "https://diariodarepublica.pt/dr/detalhe/contrato-publico/419-1003400083"
  },
  {
    "numero_procedimento": "N/A",
    "entidade": "Sociedade de Desenvolvimento do Porto Santo, SA",
    "link": "https://diariodarepublica.pt/dr/detalhe/contrato-publico/421-1003400084",
    "detalhes_completos": "Alteração do Anúncio de procedimento n.º 32382/2025, de 2025-12-15, com o ID 419874545\n1 - IDENTIFICAÇÃO E CONTACTOS DA ENTIDADE ADJUDICANTE\nDesignação da entidade adjudicante: Sociedade de Desenvolvimento do Porto Santo, SA\nNIPC: 511131879\nServiço/Órgão/Pessoa de contacto: Unidade de Assessoria Jurídica, Contratação e Contencioso\nEndereço: Sede no edifício do Governo Regional, 3.º andar e escritórios na Rua Nova de São Pedro n.º 50\nCódigo postal: 9000-048\nLocalidade: Funchal\nPaís: Portugal\nNUT III: PT300\nDistrito: Região Autónoma da Madeira\nConcelho: Funchal\nFreguesia: Freguesia de São Pedro (Funchal)\nTelefone: 291215740\nFax: 291215759\nEndereço da Entidade (URL): https://sociedadesdesenvolvimento.com/\nEndereço Eletrónico: contratacaopublica@sociedadesdesenvolvimento.com\neDelivery Gateway (URL): https://www.acingov.pt\nFunção da Organização: Adquirente\nNorma jurídica da Entidade Adjudicante: Organismo de direito público\nÁrea de atividade da Autoridade Adjudicante: Serviços públicos das administrações públicas\n2 - JORNAL OFICIAL DA UNIÃO EUROPEIA\nO procedimento a que este anúncio diz respeito também é publicitado no Jornal Oficial da União Europeia? Sim\n3 - AVISO\nModelo de Anúncio: Concurso público\nData de Envio do Anúncio: 07-01-2026\n5 - PROCESSO\nTipo de Procedimento: Concurso público\nPreço base do procedimento: Sim\nValor do preço base do procedimento: 6.155.811,90 EUR\nProcedimento com lotes? Não\n6 - OBJETO DO CONTRATO\nNúmero de referência interna: CP 02/2025\nDesignação do contrato: Empreitada de Construção do Segundo Campo de Golfe do Porto Santo- Primeira Fase\nDescrição: Empreitada de Construção do Segundo Campo de Golfe do Porto Santo- Primeira Fase\nOpções: Não\nTipo de Contrato Principal: Empreitada de Obras Públicas\nTipo de Contrato: Empreitada de Obras Públicas\nClassificação CPV (Vocabulário Comum para os Contratos Públicos)\nObjeto principal\nVocabulário Principal: 45200000\nPreço base s/IVA: 6.155.811,90 EUR\n7 - INDICAÇÕES ADICIONAIS\nO contrato envolve aquisição conjunta (satisfação de várias entidades)? Não\nO contrato é adjudicado por uma central de compras? Não\n8 - TÉCNICAS\nO concurso destina-se à celebração de um acordo-quadro? Inexistência de acordo-quadro\nÉ utilizado um leilão eletrónico? Não\nÉ adotada uma fase de negociação? Não\nSistema de Aquisição Dinâmico: Inexistência de sistema de aquisição dinâmico\n9 - LOCAL DA EXECUÇÃO DO CONTRATO\nLOCAL DA EXECUÇÃO DO CONTRATO (PROCEDIMENTO)\nPaís: Portugal\nNUT III: PT300\nLocalidade: todas\nDistrito: Região Autónoma da Madeira\nConcelho: Porto Santo\nFreguesia: Todas\n10 - PRAZO DE EXECUÇÃO DO CONTRATO\nPrazo de execução do contrato: 13 MESES\nPrevisão de renovações: Não\n11 - FUNDOS EU\nTêm fundos EU? Não\n12 - DOCUMENTOS DE HABILITAÇÃO\nHabilitação para o exercício da atividade profissional: Sim\nTipo: Alvará\nDescrição:  Alvará de classificação de Empreiteiro de Obras públicas, emitido pelo Instituto dos Mercados Públicos do Imobiliário e da Construção (IMPIC, I. P.), contendo subcategoria em classe que cubra o valor global da proposta, respeitante aos trabalhos mais expressivos da mesma, sem prejuízo da exigência de habilitação noutras classes e subcategorias relativas às restantes obras e trabalhos a executar nos termos da Lei n.º 41/2015, de 3 de junho, alterada pela Lei n.º 25/2018, de 14 de junho, com as seguintes autorizações:\nA classificação como empreiteiro geral da 2.ª categoria - vias de comunicação, obras de urbanização e outras infraestruturas, a qual tem de ser de classe que cubra o valor total da proposta;\nAs seguintes classificações na classe correspondente à parte dos trabalhos a que respeitam: \n 1ª subcategoria - vias de circulação rodoviária e aeródromos, 6ª subcategoria - saneamento básico e 9ª subcategoria - ajardinamentos da 2.ª Categoria - vias de comunicação, obras de urbanização e outras infraestruturas;\n 1ª Subcategoria - Instalações elétricas de utilização de baixa tensão, 2ª Subcategoria - Redes elétricas de baixa tensão e postos de transformação, 18ª Subcategoria - Gestão técnica centralizada e 19ª Subcategoria - Outras instalações mecânicas e eletromecânicas da 4.ª Categoria  Instalações Elétricas e Mecânicas;\n 2ª Subcategoria - Movimentação de terras, 7ª Subcategoria - Drenagens e tratamento de taludes, 11ª Subcategoria - Impermeabilizações e isolamentos e 13ª Subcategoria - Caminhos agrícolas e florestais da 5.ª Categoria  Outros trabalhos.\n13 - CONDIÇÕES DE APRESENTAÇÃO\nPlataforma eletrónica utilizada pela entidade adjudicante: ACIN\nURL para Apresentação: https://www.acingov.pt\nAdmissibilidade da apresentação de propostas variantes: Não autorizado\nPrazo para apresentação das propostas: 23-01-2026 23:59\nPrazo durante o qual os concorrentes são obrigados a manter as respetivas propostas: 180 dias a contar do termo do prazo para a apresentação das propostas\nApresentação de Catálogo Eletrónico: Permitido\nIndicação de Subcontratação na Proposta: Inexistência de indicação de subcontratação\n14 - PRESTAÇÃO DE CAUÇÃO\nPrestação de caução: Sim\nPercentagem: 2%\nDescrição da Garantia Exigida: O valor da caução é de 2.00% do preço contratual.\n15 - FORNECIMENTO DAS PEÇAS DO CONCURSO, APRESENTAÇÃO DE PEDIDOS DE PARTICIPAÇÃO E APRESENTAÇÃO DAS PROPOSTAS\nLink para acesso às peças do concurso (URL): https://www.acingov.pt/acingovprod/2/zonaPublica/zona_publica_c/donwloadProcedurePiece/OTkyODA3\n20 - OUTROS REQUISITOS\nInformação sobre contratos reservados. Aplica-se a contratos reservados (54º-A)? Não\n21 - CRITÉRIO DE ADJUDICAÇÃO\nMultifator: Não\nMonofator:\nNome: Preço\n24 - CONDIÇÕES DO CONTRATO\nFaturação Eletrónica: Permitido\nObrigação de Subcontratação:\nCódigo da Obrigação de Subcontratação: Não é aplicável nenhuma obrigação de subcontratação.\n25 - COMPRA PÚBLICA ESTRATÉGICA\nCompra Pública Estratégica: Inexistência de contratação pública estratégica\n26 - INFORMAÇÕES ADICIONAIS\nContrato adequado para PME: Sim\nCobertura ACP (Acordo dos Contratos Públicos da Organização Mundial do Comércio): Não\n27 - IDENTIFICAÇÃO E CONTACTOS DO ÓRGÃO DE RECURSOS ADMINISTRATIVOS\nDesignação: Presidente do Conselho de Administração\nEndereço: Sede no Edifício do Governo Regional, 3.º andar e escritórios na Rua Nova de São Pedro n.º 50\nCódigo postal: 9000-048\nLocalidade: Funchal\nTelefone: 291215740\nFax: \nEndereço eletrónico: geral@sociedadesdesenvolvimento.com\nPrazo de interposição do recurso: 5 dias\n28 - IDENTIFICAÇÃO DO(S) AUTOR(ES) DE ANÚNCIO\nNome: Élia Fátima da Silva Rodrigues Ribeiro\nCargo: Presidente do Conselho de Administração\n29 - ALTERAÇÃO\nMotivo da Alteração: Correção pelo adquirente\nIdentificador da Versão do Anúncio a Alterar: bfa339b1-6b33-42c7-8e61-e93b6d0f61db-03\nIdentificador das Secções Alteradas do Anúncio Anterior: Condições de Apresentação; Alteração\nDescrição das Alterações: Modificação do prazo para a apresentação de propostas\nAlteração dos Documentos do Concurso: Não\n419947411",
    "nipc": "511131879",
    "distrito": "Região Autónoma da Madeira",
    "concelho": "Funchal",
    "freguesia": "Freguesia de São Pedro (Funchal)",
    "site": "https://sociedadesdesenvolvimento.com/",
    "email": "contratacaopublica@sociedadesdesenvolvimento.com",
    "designacao_contrato": "Empreitada de Construção do Segundo Campo de Golfe do Porto Santo- Primeira Fase",
    "descricao": "Empreitada de Construção do Segundo Campo de Golfe do Porto Santo- Primeira Fase",
    "preco_base": "6.155.811,90 EUR",
    "prazo_execucao": "13 MESES",
    "prazo_apresentacao_propostas": "23-01-2026 23:59",
    "fundos_eu": "Não",
    "plataforma_eletronica": "ACIN",
    "url_procedimento": "https://www.acingov.pt",
    "autor_nome": "Élia Fátima da Silva Rodrigues Ribeiro",
    "autor_cargo": "Presidente do Conselho de Administração"
  },
  {
    "numero_procedimento": "N/A",
    "entidade": "Águas de Santo André, SA",
    "link": "https://diariodarepublica.pt/dr/detalhe/contrato-publico/427-1003400086",
    "detalhes_completos": "Alteração do Anúncio de procedimento n.º 33275/2025, de 2025-12-23, com o ID 419922131\n1 - IDENTIFICAÇÃO E CONTACTOS DA ENTIDADE ADJUDICANTE\nDesignação da entidade adjudicante: Águas de Santo André, SA\nNIPC: 505600005\nServiço/Órgão/Pessoa de contacto: Direção de Operação\nEndereço: Cerca da Água - Rua dos Cravos\nCódigo postal: 7500-130\nLocalidade: Vila Nova de Santo André\nPaís: Portugal\nNUT III: PT181\nDistrito: Setúbal\nConcelho: Santiago do Cacém\nFreguesia: Freguesia de Santo André - Santiago do Cacém\nTelefone: 269708240\nFax: 351269708269\nEndereço da Entidade (URL): www.adsa.pt\nEndereço Eletrónico: geral.adsa@adp.pt\neDelivery Gateway (URL): https://www.acingov.pt\nFunção da Organização: Adquirente\nNorma jurídica da Entidade Adjudicante: Organismo de direito público\nÁrea de atividade da Entidade Adjudicante: Atividades relacionadas com a água\n2 - JORNAL OFICIAL DA UNIÃO EUROPEIA\nO procedimento a que este anúncio diz respeito também é publicitado no Jornal Oficial da União Europeia? Não\n3 - AVISO\nModelo de Anúncio: Concurso público\nData de Envio do Anúncio: 09-01-2026\n5 - PROCESSO\nTipo de Procedimento: Concurso público\nPreço base do procedimento: Sim\nValor do preço base do procedimento: 150.000,00 EUR\nProcedimento com lotes? Não\n6 - OBJETO DO CONTRATO\nNúmero de referência interna: CP 18/DOP/25\nDesignação do contrato: Execução do Programa de Monitorização do Ambiente Marinho (PMAM)\nDescrição: Execução do Programa de Monitorização do Ambiente Marinho (PMAM)\nTipo de Contrato Principal: Aquisição de Serviços\nTipo de Contrato: Aquisição de Serviços\nClassificação CPV (Vocabulário Comum para os Contratos Públicos)\nObjeto principal\nVocabulário Principal: 90733100\nPreço base s/IVA: 150.000,00 EUR\n7 - INDICAÇÕES ADICIONAIS\nO contrato envolve aquisição conjunta (satisfação de várias entidades)? Não\nO contrato é adjudicado por uma central de compras? Não\n8 - TÉCNICAS\nO concurso destina-se à celebração de um acordo-quadro? Inexistência de acordo-quadro\nÉ utilizado um leilão eletrónico? Não\nÉ adotada uma fase de negociação? Não\nSistema de Aquisição Dinâmico: Inexistência de sistema de aquisição dinâmico\n9 - LOCAL DA EXECUÇÃO DO CONTRATO\nLOCAL DA EXECUÇÃO DO CONTRATO (PROCEDIMENTO)\nPaís: Portugal\nNUT III: PT181\nLocalidade: Sines\nDistrito: Setúbal\nConcelho: Sines\nFreguesia: Freguesia de Sines\n10 - PRAZO DE EXECUÇÃO DO CONTRATO\nPrazo de execução do contrato: 3 ANOS\nPrevisão de renovações: Não\n11 - FUNDOS EU\nTêm fundos EU? Não\n12 - DOCUMENTOS DE HABILITAÇÃO\nHabilitação para o exercício da atividade profissional: Não\n13 - CONDIÇÕES DE APRESENTAÇÃO\nPlataforma eletrónica utilizada pela entidade adjudicante: ACIN\nURL para Apresentação: https://www.acingov.pt\nAdmissibilidade da apresentação de propostas variantes: Não autorizado\nPrazo para apresentação das propostas: 30-01-2026 18:00\nPrazo durante o qual os concorrentes são obrigados a manter as respetivas propostas: 120 dias a contar do termo do prazo para a apresentação das propostas\nIndicação de Subcontratação na Proposta: A parte do contrato que o proponente tenciona subcontratar\n14 - PRESTAÇÃO DE CAUÇÃO\nPrestação de caução: Sim\nPercentagem: 5%\nDescrição da Garantia Exigida: O valor da caução é de 5.00% do preço contratual.\n15 - FORNECIMENTO DAS PEÇAS DO CONCURSO, APRESENTAÇÃO DE PEDIDOS DE PARTICIPAÇÃO E APRESENTAÇÃO DAS PROPOSTAS\nLink para acesso às peças do concurso (URL): https://www.acingov.pt/acingovprod/2/zonaPublica/zona_publica_c/donwloadProcedurePiece/OTI2OTY5\n20 - OUTROS REQUISITOS\nInformação sobre contratos reservados. Aplica-se a contratos reservados (54º-A)? Não\n21 - CRITÉRIO DE ADJUDICAÇÃO\nMultifator: Não\nMonofator:\nNome: Preço\n24 - CONDIÇÕES DO CONTRATO\nFaturação Eletrónica: Necessário\nObrigação de Subcontratação:\nCódigo da Obrigação de Subcontratação: Não é aplicável nenhuma obrigação de subcontratação.\n25 - COMPRA PÚBLICA ESTRATÉGICA\nCompra Pública Estratégica: Inexistência de contratação pública estratégica\n26 - INFORMAÇÕES ADICIONAIS\nContrato adequado para PME: Sim\nCobertura ACP (Acordo dos Contratos Públicos da Organização Mundial do Comércio): Não\n27 - IDENTIFICAÇÃO E CONTACTOS DO ÓRGÃO DE RECURSOS ADMINISTRATIVOS\nDesignação: Águas de Santo André, S.A.\nEndereço: Cerca da Água - Rua dos Cravos\nCódigo postal: 7500-130\nLocalidade: Vila Nova de Santo André\nTelefone: 269708240\nFax: \nEndereço eletrónico: contratacao.adsa@adp.pt\n28 - IDENTIFICAÇÃO DO(S) AUTOR(ES) DE ANÚNCIO\nNome: Tânia Raquel Leocádio Viegas\nCargo: Gestora do Procedimento\n29 - ALTERAÇÃO\nMotivo da Alteração: Correção pelo adquirente\nIdentificador da Versão do Anúncio a Alterar: 776d5f00-3ce4-4938-b354-56eb304a6adc-01\nIdentificador das Secções Alteradas do Anúncio Anterior: Condições de Apresentação\nDescrição das Alterações: Prorrogação do prazo para entrega de propostas, em cumprimento com o disposto nos n.º 1 e n.º 3 do artigo 64.º do Código dos Contratos Públicos.\nAlteração dos Documentos do Concurso: Sim\nData de alteração dos documentos do concurso: 07-01-2026\n419947413",
    "nipc": "505600005",
    "distrito": "Setúbal",
    "concelho": "Santiago do Cacém",
    "freguesia": "Freguesia de Santo André - Santiago do Cacém",
    "site": "www.adsa.pt",
    "email": "geral.adsa@adp.pt",
    "designacao_contrato": "Execução do Programa de Monitorização do Ambiente Marinho (PMAM)",
    "descricao": "Execução do Programa de Monitorização do Ambiente Marinho (PMAM)",
    "preco_base": "150.000,00 EUR",
    "prazo_execucao": "3 ANOS",
    "prazo_apresentacao_propostas": "30-01-2026 18:00",
    "fundos_eu": "Não",
    "plataforma_eletronica": "ACIN",
    "url_procedimento": "https://www.acingov.pt",
    "autor_nome": "Tânia Raquel Leocádio Viegas",
    "autor_cargo": "Gestora do Procedimento"
  },
  {
    "numero_procedimento": "N/A",
    "entidade": "AnÃºncio de procedimento  n.Âº 436/2026  -  DiÃ¡rio da RepÃºblica n.Âº 6/2026, SÃ©rie II de 2026-01-09",
    "link": "https://diariodarepublica.pt/dr/detalhe/contrato-publico/436-1003478375"
  },
  {
    "numero_procedimento": "N/A",
    "entidade": "Município de Águeda",
    "link": "https://diariodarepublica.pt/dr/detalhe/contrato-publico/438-1003478782",
    "detalhes_completos": "1 - IDENTIFICAÇÃO E CONTACTOS DA ENTIDADE ADJUDICANTE\nDesignação da entidade adjudicante: Município de Águeda\nNIPC: 501090436\nServiço/Órgão/Pessoa de contacto: Serviço de Aprovisionamento e Contratação Pública\nEndereço: Praça do Município\nCódigo postal: 3754-500\nLocalidade: Águeda\nPaís: Portugal\nNUT III: PT16D\nDistrito: Aveiro\nConcelho: Águeda\nFreguesia: Todas\nTelefone: 234610070\nFax: 234610078\nEndereço da Entidade (URL): www.cm-agueda.pt\nEndereço Eletrónico: geral@cm-agueda.pt\neDelivery Gateway (URL): https://www.acingov.pt\nFunção da Organização: Adquirente\nNorma jurídica da Entidade Adjudicante: Organismo de direito público\nÁrea de atividade da Autoridade Adjudicante: Serviços públicos das administrações públicas\n2 - JORNAL OFICIAL DA UNIÃO EUROPEIA\nO procedimento a que este anúncio diz respeito também é publicitado no Jornal Oficial da União Europeia? Não\n3 - AVISO\nModelo de Anúncio: Concurso público\nData de Envio do Anúncio: 09-01-2026\n5 - PROCESSO\nTipo de Procedimento: Concurso público\nPreço base do procedimento: Sim\nValor do preço base do procedimento: 713.000,00 EUR\nProcedimento com lotes? Não\n6 - OBJETO DO CONTRATO\nNúmero de referência interna: CF/DF/EMP - 25/25\nDesignação do contrato: Repavimentação de vias do Concelho - 8ª fase\nDescrição: Repavimentação de vias do Concelho - 8ª fase\nTipo de Contrato Principal: Empreitada de Obras Públicas\nTipo de Contrato: Empreitada de Obras Públicas\nClassificação CPV (Vocabulário Comum para os Contratos Públicos)\nObjeto principal\nVocabulário Principal: 45233252\nPreço base s/IVA: 713.000,00 EUR\n7 - INDICAÇÕES ADICIONAIS\nO contrato envolve aquisição conjunta (satisfação de várias entidades)? Não\nO contrato é adjudicado por uma central de compras? Não\n8 - TÉCNICAS\nO concurso destina-se à celebração de um acordo-quadro? Inexistência de acordo-quadro\nÉ utilizado um leilão eletrónico? Não\nÉ adotada uma fase de negociação? Não\nSistema de Aquisição Dinâmico: Inexistência de sistema de aquisição dinâmico\n9 - LOCAL DA EXECUÇÃO DO CONTRATO\nLOCAL DA EXECUÇÃO DO CONTRATO (PROCEDIMENTO)\nPaís: Portugal\nNUT III: PT16D\nLocalidade: Águeda\nDistrito: Aveiro\nConcelho: Águeda\nFreguesia: União das Freguesias de Águeda e Borralha\nPaís: Portugal\nNUT III: PT16D\nLocalidade: Águeda\nDistrito: Aveiro\nConcelho: Águeda\nFreguesia: Freguesia de Valongo do Vouga\nPaís: Portugal\nNUT III: PT16D\nLocalidade: Águeda\nDistrito: Aveiro\nConcelho: Águeda\nFreguesia: União das Freguesias de Travassô e Óis da Ribeira\nPaís: Portugal\nNUT III: PT16D\nLocalidade: Águeda\nDistrito: Aveiro\nConcelho: Águeda\nFreguesia: União das Freguesias do Préstimo e Macieira de Alcoba\nPaís: Portugal\nNUT III: PT16D\nLocalidade: Águeda\nDistrito: Aveiro\nConcelho: Águeda\nFreguesia: União das Freguesias de Belazaima do Chão, Castanheira do Vouga e Agadão\nPaís: Portugal\nNUT III: PT16D\nLocalidade: Águeda\nDistrito: Aveiro\nConcelho: Águeda\nFreguesia: Freguesia de Aguada de Cima\nPaís: Portugal\nNUT III: PT16D\nLocalidade: Águeda\nDistrito: Aveiro\nConcelho: Águeda\nFreguesia: União das Freguesias de Barrô e Aguada de Baixo\nPaís: Portugal\nNUT III: PT16D\nLocalidade: Águeda\nDistrito: Aveiro\nConcelho: Águeda\nFreguesia: Freguesia de Fermentelos\nPaís: Portugal\nNUT III: PT16D\nLocalidade: Águeda\nDistrito: Aveiro\nConcelho: Águeda\nFreguesia: Freguesia de Macinhata do Vouga\nPaís: Portugal\nNUT III: PT16D\nLocalidade: Águeda\nDistrito: Aveiro\nConcelho: Águeda\nFreguesia: União das Freguesias de Trofa, Segadães e Lamas do Vouga\n10 - PRAZO DE EXECUÇÃO DO CONTRATO\nPrazo de execução do contrato: 120 DIAS\nPrevisão de renovações: Não\n11 - FUNDOS EU\nTêm fundos EU? Não\n12 - DOCUMENTOS DE HABILITAÇÃO\nHabilitação para o exercício da atividade profissional: Sim\nTipo: Alvará\nDescrição: 1ª Subcategoria da 2ª Categoria e da classe correspondente ao valor global da proposta, nos termos do disposto no artigo 8.º da Lei n.º 41/2015 de 3 de Junho, com as alterações introduzidas pela Lei n.º25/2018, de 14 de junho\n13 - CONDIÇÕES DE APRESENTAÇÃO\nPlataforma eletrónica utilizada pela entidade adjudicante: ACIN\nURL para Apresentação: https://www.acingov.pt\nAdmissibilidade da apresentação de propostas variantes: Não autorizado\nPrazo para apresentação das propostas: 09-02-2026 17:00\nPrazo durante o qual os concorrentes são obrigados a manter as respetivas propostas: 66 dias a contar do termo do prazo para a apresentação das propostas\nIndicação de Subcontratação na Proposta: Inexistência de indicação de subcontratação\n14 - PRESTAÇÃO DE CAUÇÃO\nPrestação de caução: Sim\nPercentagem: 5%\nDescrição da Garantia Exigida: O valor da caução é de 5.00% do preço contratual.\n15 - FORNECIMENTO DAS PEÇAS DO CONCURSO, APRESENTAÇÃO DE PEDIDOS DE PARTICIPAÇÃO E APRESENTAÇÃO DAS PROPOSTAS\nLink para acesso às peças do concurso (URL): https://www.acingov.pt/acingovprod/2/zonaPublica/zona_publica_c/donwloadProcedurePiece/MTAwOTMzMQ==\n20 - OUTROS REQUISITOS\nInformação sobre contratos reservados. Aplica-se a contratos reservados (54º-A)? Não\n21 - CRITÉRIO DE ADJUDICAÇÃO\nMultifator: Não\nMonofator:\nNome: Preço\n24 - CONDIÇÕES DO CONTRATO\nFaturação Eletrónica: Permitido\nObrigação de Subcontratação:\nCódigo da Obrigação de Subcontratação: Não é aplicável nenhuma obrigação de subcontratação.\n25 - COMPRA PÚBLICA ESTRATÉGICA\nCompra Pública Estratégica: Inexistência de contratação pública estratégica\n26 - INFORMAÇÕES ADICIONAIS\nContrato adequado para PME: Sim\nCobertura ACP (Acordo dos Contratos Públicos da Organização Mundial do Comércio): Não\n27 - IDENTIFICAÇÃO E CONTACTOS DO ÓRGÃO DE RECURSOS ADMINISTRATIVOS\nDesignação: Câmara Municipal de Águeda\nEndereço: Praça do Município\nCódigo postal: 3754-500\nLocalidade: Águeda\nTelefone: 234610070\nFax: \nEndereço eletrónico: geral@cm-agueda.pt\nPrazo de interposição do recurso: 5 dias\n28 - IDENTIFICAÇÃO DO(S) AUTOR(ES) DE ANÚNCIO\nNome: Jorge Henrique Fernandes de Almeida\nCargo: Presidente da Câmara Municipal de Águeda\n419947359",
    "nipc": "501090436",
    "distrito": "Aveiro",
    "concelho": "Águeda",
    "freguesia": "Todas",
    "site": "www.cm-agueda.pt",
    "email": "geral@cm-agueda.pt",
    "designacao_contrato": "Repavimentação de vias do Concelho - 8ª fase",
    "descricao": "Repavimentação de vias do Concelho - 8ª fase",
    "preco_base": "713.000,00 EUR",
    "prazo_execucao": "120 DIAS",
    "prazo_apresentacao_propostas": "09-02-2026 17:00",
    "fundos_eu": "Não",
    "plataforma_eletronica": "ACIN",
    "url_procedimento": "https://www.acingov.pt",
    "autor_nome": "Jorge Henrique Fernandes de Almeida",
    "autor_cargo": "Presidente da Câmara Municipal de Águeda"
  },
  {
    "numero_procedimento": "N/A",
    "entidade": "AnÃºncio de procedimento  n.Âº 440/2026  -  DiÃ¡rio da RepÃºblica n.Âº 6/2026, SÃ©rie II de 2026-01-09",
    "link": "https://diariodarepublica.pt/dr/detalhe/contrato-publico/440-1003478815"
  },
  {
    "numero_procedimento": "N/A",
    "entidade": "Município de Paredes de Coura",
    "link": "https://diariodarepublica.pt/dr/detalhe/contrato-publico/442-1003478861",
    "detalhes_completos": "1 - IDENTIFICAÇÃO E CONTACTOS DA ENTIDADE ADJUDICANTE\nDesignação da entidade adjudicante: Município de Paredes de Coura\nNIPC: 506632938\nEndereço: Lg. Viscde Moselos Aptd. 6\nCódigo postal: 4940-525\nLocalidade: Paredes de Coura\nPaís: Portugal\nNUT III: PT111\nDistrito: Viana do Castelo\nConcelho: Paredes de Coura\nFreguesia: Todas\nTelefone: 251780100\nFax: 251780118\nEndereço da Entidade (URL): www.paredesdecoura.pt\nEndereço Eletrónico: geral@paredesdecoura.pt\neDelivery Gateway (URL): https://community.vortal.biz/public/\nFunção da Organização: Adquirente\nNorma jurídica da Entidade Adjudicante: Autoridade local\nÁrea de atividade da Autoridade Adjudicante: Serviços públicos das administrações públicas\n2 - JORNAL OFICIAL DA UNIÃO EUROPEIA\nO procedimento a que este anúncio diz respeito também é publicitado no Jornal Oficial da União Europeia? Não\n3 - AVISO\nModelo de Anúncio: Concurso público\nData de Envio do Anúncio: 09-01-2026\n5 - PROCESSO\nTipo de Procedimento: Concurso público\nPreço base do procedimento: Sim\nValor do preço base do procedimento: 61.193,50 EUR\nProcedimento com lotes? Não\n6 - OBJETO DO CONTRATO\nNúmero de referência interna: 03/26_E\nDesignação do contrato: Execução de Muro no Covelo em Rubiães, Saneamento de Raízes e Repavimentação da Travessa de Sabariz em Romarigães, Repavimentação da Rua da Telhada e Rua do Meijal em São Martinho de Coura\nDescrição: Execução de Muro no Covelo em Rubiães, Saneamento de Raízes e Repavimentação da Travessa de Sabariz em Romarigães, Repavimentação da Rua da Telhada e Rua do Meijal em São Martinho de Coura\nTipo de Contrato Principal: Empreitada de Obras Públicas\nTipo de Contrato: Empreitada de Obras Públicas\nClassificação CPV (Vocabulário Comum para os Contratos Públicos)\nObjeto principal\nVocabulário Principal: 45262510\nPreço base s/IVA: 61.193,50 EUR\n7 - INDICAÇÕES ADICIONAIS\nO contrato envolve aquisição conjunta (satisfação de várias entidades)? Não\nO contrato é adjudicado por uma central de compras? Não\n8 - TÉCNICAS\nO concurso destina-se à celebração de um acordo-quadro? Inexistência de acordo-quadro\nÉ utilizado um leilão eletrónico? Não\nÉ adotada uma fase de negociação? Não\nSistema de Aquisição Dinâmico: Inexistência de sistema de aquisição dinâmico\n9 - LOCAL DA EXECUÇÃO DO CONTRATO\nLOCAL DA EXECUÇÃO DO CONTRATO (PROCEDIMENTO)\nPaís: Portugal\nNUT III: PT111\nLocalidade: Viana do Castelo\nDistrito: Viana do Castelo\nConcelho: Paredes de Coura\nFreguesia: Freguesia de Romarigães\n10 - PRAZO DE EXECUÇÃO DO CONTRATO\nPrazo de execução do contrato: 60 DIAS\nPrevisão de renovações: Não\n11 - FUNDOS EU\nTêm fundos EU? Não\n12 - DOCUMENTOS DE HABILITAÇÃO\nHabilitação para o exercício da atividade profissional: Sim\nTipo: Alvará\nDescrição: Alvará na 4ª subcategoria da 1ª categoria\n13 - CONDIÇÕES DE APRESENTAÇÃO\nPlataforma eletrónica utilizada pela entidade adjudicante: VORTAL\nURL para Apresentação: https://community.vortal.biz/public/\nAdmissibilidade da apresentação de propostas variantes: Não autorizado\nPrazo para apresentação das propostas: 19-01-2026 16:00\nPrazo durante o qual os concorrentes são obrigados a manter as respetivas propostas: 120 dias a contar do termo do prazo para a apresentação das propostas\nIndicação de Subcontratação na Proposta: Inexistência de indicação de subcontratação\n14 - PRESTAÇÃO DE CAUÇÃO\nPrestação de caução: Não\n15 - FORNECIMENTO DAS PEÇAS DO CONCURSO, APRESENTAÇÃO DE PEDIDOS DE PARTICIPAÇÃO E APRESENTAÇÃO DAS PROPOSTAS\nLink para acesso às peças do concurso (URL): https://community.vortal.biz/Public/public-tender-documents/bXd4YWNya05MY293bStSa3A2dWxhQWliV3ArZGNMMHVhU3ZQVzZIRWJVRU9DYVdnVlZxaXNjZ093KzF4Unk2WTRZdVBTOVNXWHB3UWZKWkovalYxY2c9PUJNXlF3\n20 - OUTROS REQUISITOS\nInformação sobre contratos reservados. Aplica-se a contratos reservados (54º-A)? Não\n21 - CRITÉRIO DE ADJUDICAÇÃO\nMultifator: Não\nMonofator:\nNome: Preço\n24 - CONDIÇÕES DO CONTRATO\nFaturação Eletrónica: Permitido\nObrigação de Subcontratação:\nCódigo da Obrigação de Subcontratação: Não é aplicável nenhuma obrigação de subcontratação.\n25 - COMPRA PÚBLICA ESTRATÉGICA\nCompra Pública Estratégica: Inexistência de contratação pública estratégica\n26 - INFORMAÇÕES ADICIONAIS\nContrato adequado para PME: Sim\nCobertura ACP (Acordo dos Contratos Públicos da Organização Mundial do Comércio): Não\n27 - IDENTIFICAÇÃO E CONTACTOS DO ÓRGÃO DE RECURSOS ADMINISTRATIVOS\nDesignação: Município de Paredes de Coura\nEndereço: Largo Visconde de Mozelos, Ap.6\nCódigo postal: 4941-909\nLocalidade: Paredes de Coura\nTelefone: +351 251780100\nFax: +351 251780100\nEndereço eletrónico: geral@paredesdecoura.pt\n28 - IDENTIFICAÇÃO DO(S) AUTOR(ES) DE ANÚNCIO\nNome: Tiago Manuel Pereira da Cunha\nCargo: Presidente\n419947535",
    "nipc": "506632938",
    "distrito": "Viana do Castelo",
    "concelho": "Paredes de Coura",
    "freguesia": "Todas",
    "site": "www.paredesdecoura.pt",
    "email": "geral@paredesdecoura.pt",
    "designacao_contrato": "Execução de Muro no Covelo em Rubiães, Saneamento de Raízes e Repavimentação da Travessa de Sabariz em Romarigães, Repavimentação da Rua da Telhada e Rua do Meijal em São Martinho de Coura",
    "descricao": "Execução de Muro no Covelo em Rubiães, Saneamento de Raízes e Repavimentação da Travessa de Sabariz em Romarigães, Repavimentação da Rua da Telhada e Rua do Meijal em São Martinho de Coura",
    "preco_base": "61.193,50 EUR",
    "prazo_execucao": "60 DIAS",
    "prazo_apresentacao_propostas": "19-01-2026 16:00",
    "fundos_eu": "Não",
    "plataforma_eletronica": "VORTAL",
    "url_procedimento": "https://community.vortal.biz/public/",
    "autor_nome": "Tiago Manuel Pereira da Cunha",
    "autor_cargo": "Presidente"
  },
  {
    "numero_procedimento": "N/A",
    "entidade": "AnÃºncio de procedimento  n.Âº 443/2026  -  DiÃ¡rio da RepÃºblica n.Âº 6/2026, SÃ©rie II de 2026-01-09",
    "link": "https://diariodarepublica.pt/dr/detalhe/contrato-publico/443-1003479092"
  },
  {
    "numero_procedimento": "N/A",
    "entidade": "Município da Guarda",
    "link": "https://diariodarepublica.pt/dr/detalhe/contrato-publico/444-1003479134",
    "detalhes_completos": "Alteração do Anúncio de procedimento n.º 32127/2025, de 2025-12-11, com o ID 419869564\n1 - IDENTIFICAÇÃO E CONTACTOS DA ENTIDADE ADJUDICANTE\nDesignação da entidade adjudicante: Município da Guarda\nNIPC: 501131140\nEndereço: Praça do Município, nº 1\nCódigo postal: 6301-854\nLocalidade: Guarda\nPaís: Portugal\nNUT III: PT16J\nDistrito: Guarda\nConcelho: Guarda\nFreguesia: Freguesia de Guarda\nTelefone: 271220200\nFax: 271220280\nEndereço da Entidade (URL): www.mun-guarda.pt\nEndereço Eletrónico: geral@mun-guarda.pt\neDelivery Gateway (URL): https://community.vortal.biz/public/\nFunção da Organização: Adquirente\nNorma jurídica da Entidade Adjudicante: Autoridade local\nÁrea de atividade da Autoridade Adjudicante: Serviços públicos das administrações públicas\n2 - JORNAL OFICIAL DA UNIÃO EUROPEIA\nO procedimento a que este anúncio diz respeito também é publicitado no Jornal Oficial da União Europeia? Não\n3 - AVISO\nModelo de Anúncio: Concurso público\nData de Envio do Anúncio: 09-01-2026\n5 - PROCESSO\nTipo de Procedimento: Concurso público\nPreço base do procedimento: Sim\nValor do preço base do procedimento: 3.047.626,05 EUR\nProcedimento com lotes? Não\n6 - OBJETO DO CONTRATO\nNúmero de referência interna: DOPEI/ED-2025-37\nDesignação do contrato: Museu dos Sabores da Beira Interior\nDescrição: Museu dos Sabores da Beira Interior\nTipo de Contrato Principal: Empreitada de Obras Públicas\nTipo de Contrato: Empreitada de Obras Públicas\nClassificação CPV (Vocabulário Comum para os Contratos Públicos)\nObjeto principal\nVocabulário Principal: 45262690\nPreço base s/IVA: 3.047.626,05 EUR\n7 - INDICAÇÕES ADICIONAIS\nO contrato envolve aquisição conjunta (satisfação de várias entidades)? Não\nO contrato é adjudicado por uma central de compras? Não\n8 - TÉCNICAS\nO concurso destina-se à celebração de um acordo-quadro? Inexistência de acordo-quadro\nÉ utilizado um leilão eletrónico? Não\nÉ adotada uma fase de negociação? Não\nSistema de Aquisição Dinâmico: Inexistência de sistema de aquisição dinâmico\n9 - LOCAL DA EXECUÇÃO DO CONTRATO\nLOCAL DA EXECUÇÃO DO CONTRATO (PROCEDIMENTO)\nPaís: Portugal\nNUT III: PT16J\nLocalidade: Guarda\nDistrito: Guarda\nConcelho: Guarda\nFreguesia: Freguesia de Guarda\n10 - PRAZO DE EXECUÇÃO DO CONTRATO\nPrazo de execução do contrato: 365 DIAS\nPrevisão de renovações: Não\n11 - FUNDOS EU\nTêm fundos EU? Não\n12 - DOCUMENTOS DE HABILITAÇÃO\nHabilitação para o exercício da atividade profissional: Sim\nTipo: Outros\nDescrição - Outros: Constantes das peças procedimentais\nDescrição: Em conformidade com as peças procedimentais\n13 - CONDIÇÕES DE APRESENTAÇÃO\nPlataforma eletrónica utilizada pela entidade adjudicante: VORTAL\nURL para Apresentação: https://community.vortal.biz/public/\nAdmissibilidade da apresentação de propostas variantes: Não autorizado\nPrazo para apresentação das propostas: 30-01-2026 17:00\nPrazo durante o qual os concorrentes são obrigados a manter as respetivas propostas: 66 dias a contar do termo do prazo para a apresentação das propostas\nApresentação de Catálogo Eletrónico: Permitido\nIndicação de Subcontratação na Proposta: Inexistência de indicação de subcontratação\n14 - PRESTAÇÃO DE CAUÇÃO\nPrestação de caução: Sim\nPercentagem: 5%\nDescrição da Garantia Exigida: Em conformidade com o artigo 45º do programa de procedimento\n15 - FORNECIMENTO DAS PEÇAS DO CONCURSO, APRESENTAÇÃO DE PEDIDOS DE PARTICIPAÇÃO E APRESENTAÇÃO DAS PROPOSTAS\nLink para acesso às peças do concurso (URL): https://community.vortal.biz/Public/public-tender-documents/L3BPSW1BQU9XZXl2YlA3NExLbzlWL1RaOHljaWNVWWFjTldZM2Y0amJxaGxuQy95R2oxdzErS0QxcGJIcFBWTnBxWG9DaDBCV3puUGJ2Y29ieEMyVkE9PVJfNWsz\n20 - OUTROS REQUISITOS\nInformação sobre contratos reservados. Aplica-se a contratos reservados (54º-A)? Não\n21 - CRITÉRIO DE ADJUDICAÇÃO\nMultifator: Sim\nFator: \nNome: Qualidade\nPonderação: 60%\nSubfatores: Sim\nSubfatores: \nNome: Plano de trabalhos\nPonderação : 70%; \nNome: Memória descritiva e justificativa do modo execução da obra\nPonderação : 30%; \nFator: \nNome: Preço\nPonderação: 40%\nSubfatores: Não\n24 - CONDIÇÕES DO CONTRATO\nFaturação Eletrónica: Permitido\nObrigação de Subcontratação:\nCódigo da Obrigação de Subcontratação: Não é aplicável nenhuma obrigação de subcontratação.\n25 - COMPRA PÚBLICA ESTRATÉGICA\nCompra Pública Estratégica: Inexistência de contratação pública estratégica\n26 - INFORMAÇÕES ADICIONAIS\nContrato adequado para PME: Sim\nCobertura ACP (Acordo dos Contratos Públicos da Organização Mundial do Comércio): Não\n27 - IDENTIFICAÇÃO E CONTACTOS DO ÓRGÃO DE RECURSOS ADMINISTRATIVOS\nDesignação: Presidente da Câmara Municipal da Guarda\nEndereço: Praça do Municipio.\nCódigo postal: 6301-854\nLocalidade: Guarda\nTelefone: +351 271220200\nFax: +351 271220280\nEndereço eletrónico: contratacaopublica@mun-guarda.pt\n28 - IDENTIFICAÇÃO DO(S) AUTOR(ES) DE ANÚNCIO\nNome: Sérgio Fernando da Silva Costa\nCargo: Presidente da Câmara Municipal da Guarda\n29 - ALTERAÇÃO\nMotivo da Alteração: Correção pelo adquirente\nIdentificador da Versão do Anúncio a Alterar: 19ddcbe9-f1e0-4292-bf2a-fbd247e32ad0-01\nIdentificador das Secções Alteradas do Anúncio Anterior: Condições de Apresentação\nDescrição das Alterações: Prorrogação do prazo para apresentação das propostas\nAlteração dos Documentos do Concurso: Não\n419947561",
    "nipc": "501131140",
    "distrito": "Guarda",
    "concelho": "Guarda",
    "freguesia": "Freguesia de Guarda",
    "site": "www.mun-guarda.pt",
    "email": "geral@mun-guarda.pt",
    "designacao_contrato": "Museu dos Sabores da Beira Interior",
    "descricao": "Museu dos Sabores da Beira Interior",
    "preco_base": "3.047.626,05 EUR",
    "prazo_execucao": "365 DIAS",
    "prazo_apresentacao_propostas": "30-01-2026 17:00",
    "fundos_eu": "Não",
    "plataforma_eletronica": "VORTAL",
    "url_procedimento": "https://community.vortal.biz/public/",
    "autor_nome": "Sérgio Fernando da Silva Costa",
    "autor_cargo": "Presidente da Câmara Municipal da Guarda"
  },
  {
    "numero_procedimento": "N/A",
    "entidade": "AnÃºncio de procedimento  n.Âº 448/2026  -  DiÃ¡rio da RepÃºblica n.Âº 6/2026, SÃ©rie II de 2026-01-09",
    "link": "https://diariodarepublica.pt/dr/detalhe/contrato-publico/448-1003479510"
  },
  {
    "numero_procedimento": "N/A",
    "entidade": "Unidade Local de Saúde do Baixo Alentejo, EPE",
    "link": "https://diariodarepublica.pt/dr/detalhe/contrato-publico/452-1003479512",
    "detalhes_completos": "1 - IDENTIFICAÇÃO E CONTACTOS DA ENTIDADE ADJUDICANTE\nDesignação da entidade adjudicante: Unidade Local de Saúde do Baixo Alentejo, EPE\nNIPC: 508754275\nEndereço: Rua Dr. António Fernando Covas Lima\nCódigo postal: 7801-849\nLocalidade: Beja\nPaís: Portugal\nNUT III: PT184\nDistrito: Beja\nConcelho: Beja\nFreguesia: União das Freguesias de Beja (Santiago Maior e São João Baptista)\nTelefone: 284310201\nFax: 284310201\nEndereço da Entidade (URL): www.ulsba.min-saude.pt\nEndereço Eletrónico: concursos@ulsba.min-saude.pt\neDelivery Gateway (URL): https://community.vortal.biz/public/\nFunção da Organização: Adquirente\nNorma jurídica da Entidade Adjudicante: Organismo de direito público\nÁrea de atividade da Autoridade Adjudicante: Saúde\n2 - JORNAL OFICIAL DA UNIÃO EUROPEIA\nO procedimento a que este anúncio diz respeito também é publicitado no Jornal Oficial da União Europeia? Não\n3 - AVISO\nModelo de Anúncio: Concurso público\nData de Envio do Anúncio: 09-01-2026\n5 - PROCESSO\nTipo de Procedimento: Concurso público\nPreço base do procedimento: Sim\nValor do preço base do procedimento: 95.445,00 EUR\nProcedimento com lotes? Não\n6 - OBJETO DO CONTRATO\nNúmero de referência interna: 98000126\nDesignação do contrato: REAGENTES PARA IMUNOHISTOQUÍMICA\nDescrição: AQUISIÇÃO DE REAGENTES PARA IMUNOHISTOQUÍMICA\nTipo de Contrato Principal: Aquisição de Bens Móveis\nTipo de Contrato: Aquisição de Bens Móveis\nClassificação CPV (Vocabulário Comum para os Contratos Públicos)\nObjeto principal\nVocabulário Principal: 33696500\nPreço base s/IVA: 95.445,00 EUR\n7 - INDICAÇÕES ADICIONAIS\nO contrato envolve aquisição conjunta (satisfação de várias entidades)? Não\nO contrato é adjudicado por uma central de compras? Não\n8 - TÉCNICAS\nO concurso destina-se à celebração de um acordo-quadro? Inexistência de acordo-quadro\nÉ utilizado um leilão eletrónico? Não\nÉ adotada uma fase de negociação? Não\nSistema de Aquisição Dinâmico: Inexistência de sistema de aquisição dinâmico\n9 - LOCAL DA EXECUÇÃO DO CONTRATO\nLOCAL DA EXECUÇÃO DO CONTRATO (PROCEDIMENTO)\nPaís: Portugal\nNUT III: PT184\nLocalidade: Beja\nDistrito: Beja\nConcelho: Beja\nFreguesia: União das Freguesias de Beja (Santiago Maior e São João Baptista)\n10 - PRAZO DE EXECUÇÃO DO CONTRATO\nPrazo de execução do contrato: 3 ANOS\nPrevisão de renovações: Não\n11 - FUNDOS EU\nTêm fundos EU? Não\n12 - DOCUMENTOS DE HABILITAÇÃO\nHabilitação para o exercício da atividade profissional: Não\n13 - CONDIÇÕES DE APRESENTAÇÃO\nPlataforma eletrónica utilizada pela entidade adjudicante: VORTAL\nURL para Apresentação: https://community.vortal.biz/public/\nAdmissibilidade da apresentação de propostas variantes: Não autorizado\nPrazo para apresentação das propostas: 27-01-2026 18:00\nPrazo durante o qual os concorrentes são obrigados a manter as respetivas propostas: 180 dias a contar do termo do prazo para a apresentação das propostas\nIndicação de Subcontratação na Proposta: Inexistência de indicação de subcontratação\n14 - PRESTAÇÃO DE CAUÇÃO\nPrestação de caução: Não\n15 - FORNECIMENTO DAS PEÇAS DO CONCURSO, APRESENTAÇÃO DE PEDIDOS DE PARTICIPAÇÃO E APRESENTAÇÃO DAS PROPOSTAS\nLink para acesso às peças do concurso (URL): https://community.vortal.biz/Public/public-tender-documents/MVRmZmtrNFY1eGVDSHlNVkp1a1oyQzd2S1VrZWx3VGxhc2xybkltU0tCYVhybWM5cUp3c21YU1JNa01uR0hQWUZzak90a1VFSlhIakwyWjR4VFF4ZGc9PU40X0JO\n20 - OUTROS REQUISITOS\nInformação sobre contratos reservados. Aplica-se a contratos reservados (54º-A)? Não\n21 - CRITÉRIO DE ADJUDICAÇÃO\nMultifator: Não\nMonofator:\nNome: Preço\n24 - CONDIÇÕES DO CONTRATO\nFaturação Eletrónica: Permitido\nObrigação de Subcontratação:\nCódigo da Obrigação de Subcontratação: Não é aplicável nenhuma obrigação de subcontratação.\n25 - COMPRA PÚBLICA ESTRATÉGICA\nCompra Pública Estratégica: Inexistência de contratação pública estratégica\n26 - INFORMAÇÕES ADICIONAIS\nContrato adequado para PME: Sim\nCobertura ACP (Acordo dos Contratos Públicos da Organização Mundial do Comércio): Não\n27 - IDENTIFICAÇÃO E CONTACTOS DO ÓRGÃO DE RECURSOS ADMINISTRATIVOS\nDesignação: Unidade Local de Saúde do Baixo Alentejo E.P.E\nEndereço: RUA DR ANTONIO FERNANDO COVAS LIMA\nCódigo postal: 7801-849\nLocalidade: Beja\nTelefone: +351 284310200\nFax: +351 284318311\nEndereço eletrónico: ca@ulsba.min-saude.pt\n28 - IDENTIFICAÇÃO DO(S) AUTOR(ES) DE ANÚNCIO\nNome: Helena Isabel Ricardo da Graça\nCargo: Administradora Hospitalar - Diretora do Serviço de Aprovisionamento e Logística\n419947534",
    "nipc": "508754275",
    "distrito": "Beja",
    "concelho": "Beja",
    "freguesia": "União das Freguesias de Beja (Santiago Maior e São João Baptista)",
    "site": "www.ulsba.min-saude.pt",
    "email": "concursos@ulsba.min-saude.pt",
    "designacao_contrato": "REAGENTES PARA IMUNOHISTOQUÍMICA",
    "descricao": "AQUISIÇÃO DE REAGENTES PARA IMUNOHISTOQUÍMICA",
    "preco_base": "95.445,00 EUR",
    "prazo_execucao": "3 ANOS",
    "prazo_apresentacao_propostas": "27-01-2026 18:00",
    "fundos_eu": "Não",
    "plataforma_eletronica": "VORTAL",
    "url_procedimento": "https://community.vortal.biz/public/",
    "autor_nome": "Helena Isabel Ricardo da Graça",
    "autor_cargo": "Administradora Hospitalar - Diretora do Serviço de Aprovisionamento e Logística"
  },
  {
    "numero_procedimento": "N/A",
    "entidade": "AnÃºncio de procedimento  n.Âº 455/2026  -  DiÃ¡rio da RepÃºblica n.Âº 6/2026, SÃ©rie II de 2026-01-09",
    "link": "https://diariodarepublica.pt/dr/detalhe/contrato-publico/455-1003479514"
  },
  {
    "numero_procedimento": "N/A",
    "entidade": "Unidade Local de Saúde de São João, EPE",
    "link": "https://diariodarepublica.pt/dr/detalhe/contrato-publico/456-1003479515",
    "detalhes_completos": "1 - IDENTIFICAÇÃO E CONTACTOS DA ENTIDADE ADJUDICANTE\nDesignação da entidade adjudicante: Unidade Local de Saúde de São João, EPE\nNIPC: 509821197\nEndereço: Alameda Prof. Hernâni Monteiro\nCódigo postal: 4200-319\nLocalidade: Área Metropolitana do Porto\nPaís: Portugal\nNUT III: PT11A\nDistrito: Porto\nConcelho: Porto\nFreguesia: Freguesia de Paranhos - Porto\nTelefone: 225512100\nFax: 225504463\nEndereço da Entidade (URL): https://portal-chsj.min-saude.pt/\nEndereço Eletrónico: geral@ulssjoao.min-saude.pt\neDelivery Gateway (URL): https://community.vortal.biz/public/\nFunção da Organização: Adquirente\nNorma jurídica da Entidade Adjudicante: Organismo de direito público\nÁrea de atividade da Autoridade Adjudicante: Saúde\n2 - JORNAL OFICIAL DA UNIÃO EUROPEIA\nO procedimento a que este anúncio diz respeito também é publicitado no Jornal Oficial da União Europeia? Não\n3 - AVISO\nModelo de Anúncio: Concurso público\nData de Envio do Anúncio: 09-01-2026\n5 - PROCESSO\nTipo de Procedimento: Concurso público\nPreço base do procedimento: Sim\nValor do preço base do procedimento: 2.450.000,00 EUR\nProcedimento com lotes? Não\n6 - OBJETO DO CONTRATO\nNúmero de referência interna: 31000826\nDesignação do contrato: Empreitada de construção do Bloco Operatório do Serviço de Urgência \nDescrição: Empreitada de construção do bloco operatório do Serviço de Urgência \nTipo de Contrato Principal: Empreitada de Obras Públicas\nTipo de Contrato: Empreitada de Obras Públicas\nClassificação CPV (Vocabulário Comum para os Contratos Públicos)\nObjeto principal\nVocabulário Principal: 45215141\nPreço base s/IVA: 2.450.000,00 EUR\n7 - INDICAÇÕES ADICIONAIS\nO contrato envolve aquisição conjunta (satisfação de várias entidades)? Não\nO contrato é adjudicado por uma central de compras? Não\n8 - TÉCNICAS\nO concurso destina-se à celebração de um acordo-quadro? Inexistência de acordo-quadro\nÉ utilizado um leilão eletrónico? Não\nÉ adotada uma fase de negociação? Não\nSistema de Aquisição Dinâmico: Inexistência de sistema de aquisição dinâmico\n9 - LOCAL DA EXECUÇÃO DO CONTRATO\nLOCAL DA EXECUÇÃO DO CONTRATO (PROCEDIMENTO)\nPaís: Portugal\nNUT III: PT11A\nLocalidade: Área Metropolitana do Porto\nDistrito: Porto\nConcelho: Porto\nFreguesia: Freguesia de Paranhos - Porto\n10 - PRAZO DE EXECUÇÃO DO CONTRATO\nPrazo de execução do contrato: 120 DIAS\nPrevisão de renovações: Não\n11 - FUNDOS EU\nTêm fundos EU? Sim\n12 - DOCUMENTOS DE HABILITAÇÃO\nHabilitação para o exercício da atividade profissional: Não\n13 - CONDIÇÕES DE APRESENTAÇÃO\nPlataforma eletrónica utilizada pela entidade adjudicante: VORTAL\nURL para Apresentação: https://community.vortal.biz/public/\nAdmissibilidade da apresentação de propostas variantes: Não autorizado\nPrazo para apresentação das propostas: 30-01-2026 17:00\nPrazo durante o qual os concorrentes são obrigados a manter as respetivas propostas: 90 dias a contar do termo do prazo para a apresentação das propostas\nIndicação de Subcontratação na Proposta: Inexistência de indicação de subcontratação\n14 - PRESTAÇÃO DE CAUÇÃO\nPrestação de caução: Sim\nPercentagem: 5%\nDescrição da Garantia Exigida: Ver programa\n15 - FORNECIMENTO DAS PEÇAS DO CONCURSO, APRESENTAÇÃO DE PEDIDOS DE PARTICIPAÇÃO E APRESENTAÇÃO DAS PROPOSTAS\nLink para acesso às peças do concurso (URL): https://community.vortal.biz/Public/public-tender-documents/K2dUTVBmZGlPem1jSTJFdXFCQmdlVlduVEp3NFk2WFZHM081czNEVWl5aDhwcktIS0pRamJ3amlKWjFLdTFrVXRtNTZjSExveXN6Rk16aEwvK2gvdUE9PTZOaiVR\n20 - OUTROS REQUISITOS\nInformação sobre contratos reservados. Aplica-se a contratos reservados (54º-A)? Não\n21 - CRITÉRIO DE ADJUDICAÇÃO\nMultifator: Sim\nFator: \nNome: Preço\nPonderação: 55%\nSubfatores: Não\nFator: \nNome: Qualidade\nPonderação: 45%\nSubfatores: Não\n24 - CONDIÇÕES DO CONTRATO\nFaturação Eletrónica: Permitido\nObrigação de Subcontratação:\nCódigo da Obrigação de Subcontratação: Não é aplicável nenhuma obrigação de subcontratação.\n25 - COMPRA PÚBLICA ESTRATÉGICA\nCompra Pública Estratégica: Inexistência de contratação pública estratégica\n26 - INFORMAÇÕES ADICIONAIS\nContrato adequado para PME: Sim\nCobertura ACP (Acordo dos Contratos Públicos da Organização Mundial do Comércio): Não\n27 - IDENTIFICAÇÃO E CONTACTOS DO ÓRGÃO DE RECURSOS ADMINISTRATIVOS\nDesignação: Conselho de Administração\nEndereço: ULSSJ - Alameda Professor Hernani Monteiro\nCódigo postal: 4200-319\nLocalidade: Porto\nTelefone: +351 225512100\nFax: +351 225025766\nEndereço eletrónico: ca@ulssjoao.min-saude.pt\n28 - IDENTIFICAÇÃO DO(S) AUTOR(ES) DE ANÚNCIO\nNome: Tiago Ferreira\nCargo: Diretor do Serviço de Aprovisionamento \n419947578",
    "nipc": "509821197",
    "distrito": "Porto",
    "concelho": "Porto",
    "freguesia": "Freguesia de Paranhos - Porto",
    "site": "https://portal-chsj.min-saude.pt/",
    "email": "geral@ulssjoao.min-saude.pt",
    "designacao_contrato": "Empreitada de construção do Bloco Operatório do Serviço de Urgência",
    "descricao": "Empreitada de construção do bloco operatório do Serviço de Urgência",
    "preco_base": "2.450.000,00 EUR",
    "prazo_execucao": "120 DIAS",
    "prazo_apresentacao_propostas": "30-01-2026 17:00",
    "fundos_eu": "Sim",
    "plataforma_eletronica": "VORTAL",
    "url_procedimento": "https://community.vortal.biz/public/",
    "autor_nome": "Tiago Ferreira",
    "autor_cargo": "Diretor do Serviço de Aprovisionamento"
  },
  {
    "numero_procedimento": "N/A",
    "entidade": "AnÃºncio de procedimento  n.Âº 459/2026  -  DiÃ¡rio da RepÃºblica n.Âº 6/2026, SÃ©rie II de 2026-01-09",
    "link": "https://diariodarepublica.pt/dr/detalhe/contrato-publico/459-1003479516"
  },
  {
    "numero_procedimento": "N/A",
    "entidade": "AnÃºncio de procedimento  n.Âº 460/2026  -  DiÃ¡rio da RepÃºblica n.Âº 6/2026, SÃ©rie II de 2026-01-09",
    "link": "https://diariodarepublica.pt/dr/detalhe/contrato-publico/460-1003479518"
  },
  {
    "numero_procedimento": "N/A",
    "entidade": "Município de Tondela",
    "link": "https://diariodarepublica.pt/dr/detalhe/contrato-publico/461-1003479519",
    "detalhes_completos": "1 - IDENTIFICAÇÃO E CONTACTOS DA ENTIDADE ADJUDICANTE\nDesignação da entidade adjudicante: Município de Tondela\nNIPC: 506822680\nServiço/Órgão/Pessoa de contacto: Presidente\nEndereço: Largo da República nº 16\nCódigo postal: 3464-001\nLocalidade: Tondela\nPaís: Portugal\nNUT III: PT16G\nDistrito: Viseu\nConcelho: Tondela\nFreguesia: União das Freguesias de Tondela e Nandufe\nTelefone: 232811110\nFax: 232811120\nEndereço da Entidade (URL): www.cm-tondela.pt\nEndereço Eletrónico: obras.publicas@cm-tondela.pt\neDelivery Gateway (URL): https://www.acingov.pt\nFunção da Organização: Adquirente\nNorma jurídica da Entidade Adjudicante: Organismo de direito público\nÁrea de atividade da Autoridade Adjudicante: Serviços públicos das administrações públicas\n2 - JORNAL OFICIAL DA UNIÃO EUROPEIA\nO procedimento a que este anúncio diz respeito também é publicitado no Jornal Oficial da União Europeia? Não\n3 - AVISO\nModelo de Anúncio: Concurso público\nData de Envio do Anúncio: 09-01-2026\n5 - PROCESSO\nTipo de Procedimento: Concurso público\nPreço base do procedimento: Sim\nValor do preço base do procedimento: 94.500,00 EUR\nProcedimento com lotes? Não\n6 - OBJETO DO CONTRATO\nNúmero de referência interna: 83/2025 - F/P\nDesignação do contrato: Aquisição de serviços de Segurança e Saúde no Trabalho\nDescrição: Aquisição de serviços de Segurança e Saúde no Trabalho\nTipo de Contrato Principal: Aquisição de Serviços\nTipo de Contrato: Aquisição de Serviços\nClassificação CPV (Vocabulário Comum para os Contratos Públicos)\nObjeto principal\nVocabulário Principal: 85147000\nPreço base s/IVA: 94.500,00 EUR\n7 - INDICAÇÕES ADICIONAIS\nO contrato envolve aquisição conjunta (satisfação de várias entidades)? Não\nO contrato é adjudicado por uma central de compras? Sim\n8 - TÉCNICAS\nO concurso destina-se à celebração de um acordo-quadro? Inexistência de acordo-quadro\nÉ utilizado um leilão eletrónico? Não\nÉ adotada uma fase de negociação? Não\nSistema de Aquisição Dinâmico: Inexistência de sistema de aquisição dinâmico\n9 - LOCAL DA EXECUÇÃO DO CONTRATO\nLOCAL DA EXECUÇÃO DO CONTRATO (PROCEDIMENTO)\nPaís: Portugal\nNUT III: PT16G\nLocalidade: Tondela\nDistrito: Viseu\nConcelho: Tondela\nFreguesia: União das Freguesias de Tondela e Nandufe\n10 - PRAZO DE EXECUÇÃO DO CONTRATO\nPrazo de execução do contrato: 36 MESES\nPrevisão de renovações: Não\n11 - FUNDOS EU\nTêm fundos EU? Não\n12 - DOCUMENTOS DE HABILITAÇÃO\nHabilitação para o exercício da atividade profissional: Não\n13 - CONDIÇÕES DE APRESENTAÇÃO\nPlataforma eletrónica utilizada pela entidade adjudicante: ACIN\nURL para Apresentação: https://www.acingov.pt\nAdmissibilidade da apresentação de propostas variantes: Não autorizado\nPrazo para apresentação das propostas: 13-01-2026 23:59\nPrazo durante o qual os concorrentes são obrigados a manter as respetivas propostas: 66 dias a contar do termo do prazo para a apresentação das propostas\nIndicação de Subcontratação na Proposta: Inexistência de indicação de subcontratação\n14 - PRESTAÇÃO DE CAUÇÃO\nPrestação de caução: Não\n15 - FORNECIMENTO DAS PEÇAS DO CONCURSO, APRESENTAÇÃO DE PEDIDOS DE PARTICIPAÇÃO E APRESENTAÇÃO DAS PROPOSTAS\nLink para acesso às peças do concurso (URL): https://www.acingov.pt/acingovprod/2/zonaPublica/zona_publica_c/donwloadProcedurePiece/MTAwMTM4OQ==\n20 - OUTROS REQUISITOS\nInformação sobre contratos reservados. Aplica-se a contratos reservados (54º-A)? Não\n21 - CRITÉRIO DE ADJUDICAÇÃO\nMultifator: Sim\nFator: \nNome: Preço\nPonderação: 50%\nSubfatores: Não\nFator: \nNome: Outros\nOutro Nome: Recursos técnicos e logísticos\nPonderação: 50%\nSubfatores: Sim\nSubfatores: \nNome: B.1. Proximidade de Clínica própria à Sede do Município Edifício Paços do Concelho\nPonderação : 30%; \nNome: B.2. Possibilidade de realização de consultas em Unidade Móvel de Saúde\nPonderação : 30%; \nNome: B.3. Experiência da Equipa Técnica 40\nPonderação : 40%; \n24 - CONDIÇÕES DO CONTRATO\nFaturação Eletrónica: Permitido\nObrigação de Subcontratação:\nCódigo da Obrigação de Subcontratação: Não é aplicável nenhuma obrigação de subcontratação.\n25 - COMPRA PÚBLICA ESTRATÉGICA\nCompra Pública Estratégica: Inexistência de contratação pública estratégica\n26 - INFORMAÇÕES ADICIONAIS\nContrato adequado para PME: Não\nCobertura ACP (Acordo dos Contratos Públicos da Organização Mundial do Comércio): Não\n27 - IDENTIFICAÇÃO E CONTACTOS DO ÓRGÃO DE RECURSOS ADMINISTRATIVOS\nDesignação: Câmara Municipal de Tondela\nEndereço: Câmara Municipal de Tondela, Largo da Republica, 16\nCódigo postal: 3464-001\nLocalidade: TONDELA\nTelefone: 232811110\nFax: \nEndereço eletrónico: geral@cm-tondela.pt\nPrazo de interposição do recurso: 5 dias\n28 - IDENTIFICAÇÃO DO(S) AUTOR(ES) DE ANÚNCIO\nNome: Fátima Carla Antunes Borges\nCargo: Presidente\n419947376",
    "nipc": "506822680",
    "distrito": "Viseu",
    "concelho": "Tondela",
    "freguesia": "União das Freguesias de Tondela e Nandufe",
    "site": "www.cm-tondela.pt",
    "email": "obras.publicas@cm-tondela.pt",
    "designacao_contrato": "Aquisição de serviços de Segurança e Saúde no Trabalho",
    "descricao": "Aquisição de serviços de Segurança e Saúde no Trabalho",
    "preco_base": "94.500,00 EUR",
    "prazo_execucao": "36 MESES",
    "prazo_apresentacao_propostas": "13-01-2026 23:59",
    "fundos_eu": "Não",
    "plataforma_eletronica": "ACIN",
    "url_procedimento": "https://www.acingov.pt",
    "autor_nome": "Fátima Carla Antunes Borges",
    "autor_cargo": "Presidente"
  },
  {
    "numero_procedimento": "N/A",
    "entidade": "Município de Braga",
    "link": "https://diariodarepublica.pt/dr/detalhe/contrato-publico/462-1003479524",
    "detalhes_completos": "1 - IDENTIFICAÇÃO E CONTACTOS DA ENTIDADE ADJUDICANTE\nDesignação da entidade adjudicante: Município de Braga\nNIPC: 506901173\nEndereço: Praça do Municípal\nCódigo postal: 4700-435\nLocalidade: Braga\nPaís: Portugal\nNUT III: PT112\nDistrito: Braga\nConcelho: Braga\nFreguesia: União das Freguesias de Braga (Maximinos, Sé e Cividade)\nTelefone: 253616060\nFax: 253203151\nEndereço da Entidade (URL): www.cm-braga.pt\nEndereço Eletrónico: contratacao.publica@cm-braga.pt\neDelivery Gateway (URL): https://community.vortal.biz/public/\nFunção da Organização: Adquirente\nNorma jurídica da Entidade Adjudicante: Autoridade local\nÁrea de atividade da Autoridade Adjudicante: Serviços públicos das administrações públicas\n2 - JORNAL OFICIAL DA UNIÃO EUROPEIA\nO procedimento a que este anúncio diz respeito também é publicitado no Jornal Oficial da União Europeia? Não\n3 - AVISO\nModelo de Anúncio: Concurso público\nData de Envio do Anúncio: 09-01-2026\n5 - PROCESSO\nTipo de Procedimento: Concurso público\nPreço base do procedimento: Sim\nValor do preço base do procedimento: 305.051,79 EUR\nProcedimento com lotes? Não\n6 - OBJETO DO CONTRATO\nNúmero de referência interna: CPE.38.25.DMOSM\nDesignação do contrato: MUSEU DOS BISCAÍNHOS – REQUALIFICAÇÃO DE INSTALAÇÕES ELETROTÉCNICAS EXISTENTES\nDescrição: MUSEU DOS BISCAÍNHOS – REQUALIFICAÇÃO DE INSTALAÇÕES ELETROTÉCNICAS EXISTENTES\nTipo de Contrato Principal: Empreitada de Obras Públicas\nTipo de Contrato: Empreitada de Obras Públicas\nClassificação CPV (Vocabulário Comum para os Contratos Públicos)\nObjeto principal\nVocabulário Principal: 45453100\nPreço base s/IVA: 305.051,79 EUR\n7 - INDICAÇÕES ADICIONAIS\nO contrato envolve aquisição conjunta (satisfação de várias entidades)? Não\nO contrato é adjudicado por uma central de compras? Não\n8 - TÉCNICAS\nO concurso destina-se à celebração de um acordo-quadro? Inexistência de acordo-quadro\nÉ utilizado um leilão eletrónico? Não\nÉ adotada uma fase de negociação? Não\nSistema de Aquisição Dinâmico: Inexistência de sistema de aquisição dinâmico\n9 - LOCAL DA EXECUÇÃO DO CONTRATO\nLOCAL DA EXECUÇÃO DO CONTRATO (PROCEDIMENTO)\nPaís: Portugal\nNUT III: PT112\nLocalidade: Braga\nDistrito: Braga\nConcelho: Braga\nFreguesia: Todas\n10 - PRAZO DE EXECUÇÃO DO CONTRATO\nPrazo de execução do contrato: 120 DIAS\nPrevisão de renovações: Não\n11 - FUNDOS EU\nTêm fundos EU? Não\n12 - DOCUMENTOS DE HABILITAÇÃO\nHabilitação para o exercício da atividade profissional: Sim\nTipo: Alvará\nDescrição: De acordo com o artigo 22.º do Programa do Concurso.\n13 - CONDIÇÕES DE APRESENTAÇÃO\nPlataforma eletrónica utilizada pela entidade adjudicante: VORTAL\nURL para Apresentação: https://community.vortal.biz/public/\nAdmissibilidade da apresentação de propostas variantes: Não autorizado\nPrazo para apresentação das propostas: 25-01-2026 18:00\nPrazo durante o qual os concorrentes são obrigados a manter as respetivas propostas: 120 dias a contar do termo do prazo para a apresentação das propostas\nIndicação de Subcontratação na Proposta: Inexistência de indicação de subcontratação\n14 - PRESTAÇÃO DE CAUÇÃO\nPrestação de caução: Não\n15 - FORNECIMENTO DAS PEÇAS DO CONCURSO, APRESENTAÇÃO DE PEDIDOS DE PARTICIPAÇÃO E APRESENTAÇÃO DAS PROPOSTAS\nLink para acesso às peças do concurso (URL): https://community.vortal.biz/Public/public-tender-documents/dys4bmtIazh2bE8ybUpiRTc4TTVweWxuWFJSTVVVL2M1b3BBdW5HWWVGWmNpRHkxSUxHNU1zYWxmdmpXTXNwRWw4MFFSZzhoL3hmN1JkeU45UkNnOVE9PWpacnpF\n20 - OUTROS REQUISITOS\nInformação sobre contratos reservados. Aplica-se a contratos reservados (54º-A)? Não\n21 - CRITÉRIO DE ADJUDICAÇÃO\nMultifator: Sim\nFator: \nNome: Preço\nPonderação: 70%\nSubfatores: Não\nFator: \nNome: Outros\nOutro Nome: Prazo de Execução\nPonderação: 30%\nSubfatores: Não\n24 - CONDIÇÕES DO CONTRATO\nFaturação Eletrónica: Permitido\nObrigação de Subcontratação:\nCódigo da Obrigação de Subcontratação: Não é aplicável nenhuma obrigação de subcontratação.\n25 - COMPRA PÚBLICA ESTRATÉGICA\nCompra Pública Estratégica: Inexistência de contratação pública estratégica\n26 - INFORMAÇÕES ADICIONAIS\nContrato adequado para PME: Sim\nCobertura ACP (Acordo dos Contratos Públicos da Organização Mundial do Comércio): Não\n27 - IDENTIFICAÇÃO E CONTACTOS DO ÓRGÃO DE RECURSOS ADMINISTRATIVOS\nDesignação: Presidente da Câmara Municipal de Braga\nEndereço: Praça do Município\nCódigo postal: 4700-435\nLocalidade: Braga\nTelefone: +351 253616060\nFax: +351 253203151\nEndereço eletrónico: info@cm-braga.pt\n28 - IDENTIFICAÇÃO DO(S) AUTOR(ES) DE ANÚNCIO\nNome: Rita Gonçalves\nCargo: Técnico Superior\n419947197",
    "nipc": "506901173",
    "distrito": "Braga",
    "concelho": "Braga",
    "freguesia": "União das Freguesias de Braga (Maximinos, Sé e Cividade)",
    "site": "www.cm-braga.pt",
    "email": "contratacao.publica@cm-braga.pt",
    "designacao_contrato": "MUSEU DOS BISCAÍNHOS – REQUALIFICAÇÃO DE INSTALAÇÕES ELETROTÉCNICAS EXISTENTES",
    "descricao": "MUSEU DOS BISCAÍNHOS – REQUALIFICAÇÃO DE INSTALAÇÕES ELETROTÉCNICAS EXISTENTES",
    "preco_base": "305.051,79 EUR",
    "prazo_execucao": "120 DIAS",
    "prazo_apresentacao_propostas": "25-01-2026 18:00",
    "fundos_eu": "Não",
    "plataforma_eletronica": "VORTAL",
    "url_procedimento": "https://community.vortal.biz/public/",
    "autor_nome": "Rita Gonçalves",
    "autor_cargo": "Técnico Superior"
  },
  {
    "numero_procedimento": "N/A",
    "entidade": "Município de Palmela",
    "link": "https://diariodarepublica.pt/dr/detalhe/contrato-publico/463-1003479526",
    "detalhes_completos": "1 - IDENTIFICAÇÃO E CONTACTOS DA ENTIDADE ADJUDICANTE\nDesignação da entidade adjudicante: Município de Palmela\nNIPC: 506187543\nServiço/Órgão/Pessoa de contacto: DFA - Aprovisionamento\nEndereço: Largo Município , Palmela\nCódigo postal: 2954-001\nLocalidade: Setúbal\nPaís: Portugal\nNUT III: PT170\nDistrito: Setúbal\nConcelho: Palmela\nFreguesia: Freguesia de Palmela\nTelefone: 212 336 600\nFax: 212 336 619\nEndereço da Entidade (URL): www.cm-palmela.pt\nEndereço Eletrónico: geral@cm-palmela.pt\neDelivery Gateway (URL): https://community.vortal.biz/public/\nFunção da Organização: Adquirente\nNorma jurídica da Entidade Adjudicante: Organismo de direito público\nÁrea de atividade da Autoridade Adjudicante: Serviços públicos das administrações públicas\n2 - JORNAL OFICIAL DA UNIÃO EUROPEIA\nO procedimento a que este anúncio diz respeito também é publicitado no Jornal Oficial da União Europeia? Não\n3 - AVISO\nModelo de Anúncio: Concurso público\nData de Envio do Anúncio: 09-01-2026\n5 - PROCESSO\nTipo de Procedimento: Concurso público\nPreço base do procedimento: Sim\nValor do preço base do procedimento: 150.000,00 EUR\nProcedimento com lotes? Não\n6 - OBJETO DO CONTRATO\nNúmero de referência interna: 0204.4.8.028/2025\nDesignação do contrato: Aquisição de serviços e bens para veículos pesados da marca Volvo\nDescrição: Aquisição de serviços e bens para veículos pesados da marca Volvo\nTipo de Contrato Principal: Aquisição de Serviços\nTipo de Contrato: Aquisição de Serviços\nClassificação CPV (Vocabulário Comum para os Contratos Públicos)\nObjeto principal\nVocabulário Principal: 50114000\nPreço base s/IVA: 150.000,00 EUR\n7 - INDICAÇÕES ADICIONAIS\nO contrato envolve aquisição conjunta (satisfação de várias entidades)? Não\nO contrato é adjudicado por uma central de compras? Não\n8 - TÉCNICAS\nO concurso destina-se à celebração de um acordo-quadro? Inexistência de acordo-quadro\nÉ utilizado um leilão eletrónico? Não\nÉ adotada uma fase de negociação? Não\nSistema de Aquisição Dinâmico: Inexistência de sistema de aquisição dinâmico\n9 - LOCAL DA EXECUÇÃO DO CONTRATO\nLOCAL DA EXECUÇÃO DO CONTRATO (PROCEDIMENTO)\nPaís: Portugal\nNUT III: PT170\nLocalidade: Palmela\nDistrito: Setúbal\nConcelho: Palmela\nFreguesia: Freguesia de Palmela\n10 - PRAZO DE EXECUÇÃO DO CONTRATO\nPrazo de execução do contrato: 36 MESES\nPrevisão de renovações: Não\n11 - FUNDOS EU\nTêm fundos EU? Não\n12 - DOCUMENTOS DE HABILITAÇÃO\nHabilitação para o exercício da atividade profissional: Não\n13 - CONDIÇÕES DE APRESENTAÇÃO\nPlataforma eletrónica utilizada pela entidade adjudicante: VORTAL\nURL para Apresentação: https://community.vortal.biz/public/\nAdmissibilidade da apresentação de propostas variantes: Não autorizado\nPrazo para apresentação das propostas: 18-01-2026 23:59\nPrazo durante o qual os concorrentes são obrigados a manter as respetivas propostas: 90 dias a contar do termo do prazo para a apresentação das propostas\nIndicação de Subcontratação na Proposta: Inexistência de indicação de subcontratação\n14 - PRESTAÇÃO DE CAUÇÃO\nPrestação de caução: Não\n15 - FORNECIMENTO DAS PEÇAS DO CONCURSO, APRESENTAÇÃO DE PEDIDOS DE PARTICIPAÇÃO E APRESENTAÇÃO DAS PROPOSTAS\nLink para acesso às peças do concurso (URL): https://community.vortal.biz/Public/public-tender-documents/SVhaVnVBZ0FYNVYxa2huNUJRN3k5bnR3aUh6WXpKNll3cmJxNnN1QnQrb0ZYK1I1aThqbkttZ3hFVDlwb0VTcjYrbGtwOGdtbkJNYXBwWFFYbWxhamc9PVJJKm0y\n20 - OUTROS REQUISITOS\nInformação sobre contratos reservados. Aplica-se a contratos reservados (54º-A)? Não\n21 - CRITÉRIO DE ADJUDICAÇÃO\nMultifator: Sim\nFator: \nNome: Preço\nPonderação: 30%\nSubfatores: Não\nFator: \nNome: Outros\nOutro Nome: D\nPonderação: 30%\nSubfatores: Não\nFator: \nNome: Qualidade\nPonderação: 30%\nSubfatores: Não\nFator: \nNome: Preço\nPonderação: 10%\nSubfatores: Não\n24 - CONDIÇÕES DO CONTRATO\nFaturação Eletrónica: Permitido\nObrigação de Subcontratação:\nCódigo da Obrigação de Subcontratação: Não é aplicável nenhuma obrigação de subcontratação.\n25 - COMPRA PÚBLICA ESTRATÉGICA\nCompra Pública Estratégica: Inexistência de contratação pública estratégica\n26 - INFORMAÇÕES ADICIONAIS\nContrato adequado para PME: Sim\nCobertura ACP (Acordo dos Contratos Públicos da Organização Mundial do Comércio): Não\n27 - IDENTIFICAÇÃO E CONTACTOS DO ÓRGÃO DE RECURSOS ADMINISTRATIVOS\nDesignação: Ana Teresa Vicente\nEndereço: Largo do Município\nCódigo postal: 2954-001\nLocalidade: Palmela\nTelefone: +351 212336600\nFax: +351 212336619\nEndereço eletrónico: geral@cm-palmela.pt\n28 - IDENTIFICAÇÃO DO(S) AUTOR(ES) DE ANÚNCIO\nNome: Ana Teresa Vicente\nCargo: Presidente da Câmara Municipal\n419947297",
    "nipc": "506187543",
    "distrito": "Setúbal",
    "concelho": "Palmela",
    "freguesia": "Freguesia de Palmela",
    "site": "www.cm-palmela.pt",
    "email": "geral@cm-palmela.pt",
    "designacao_contrato": "Aquisição de serviços e bens para veículos pesados da marca Volvo",
    "descricao": "Aquisição de serviços e bens para veículos pesados da marca Volvo",
    "preco_base": "150.000,00 EUR",
    "prazo_execucao": "36 MESES",
    "prazo_apresentacao_propostas": "18-01-2026 23:59",
    "fundos_eu": "Não",
    "plataforma_eletronica": "VORTAL",
    "url_procedimento": "https://community.vortal.biz/public/",
    "autor_nome": "Ana Teresa Vicente",
    "autor_cargo": "Presidente da Câmara Municipal"
  },
  {
    "numero_procedimento": "N/A",
    "entidade": "AnÃºncio de procedimento  n.Âº 464/2026  -  DiÃ¡rio da RepÃºblica n.Âº 6/2026, SÃ©rie II de 2026-01-09",
    "link": "https://diariodarepublica.pt/dr/detalhe/contrato-publico/464-1003479527"
  },
  {
    "numero_procedimento": "N/A",
    "entidade": "AnÃºncio de procedimento  n.Âº 465/2026  -  DiÃ¡rio da RepÃºblica n.Âº 6/2026, SÃ©rie II de 2026-01-09",
    "link": "https://diariodarepublica.pt/dr/detalhe/contrato-publico/465-1003479528"
  },
  {
    "numero_procedimento": "N/A",
    "entidade": "AnÃºncio de procedimento  n.Âº 466/2026  -  DiÃ¡rio da RepÃºblica n.Âº 6/2026, SÃ©rie II de 2026-01-09",
    "link": "https://diariodarepublica.pt/dr/detalhe/contrato-publico/466-1003479529"
  },
  {
    "numero_procedimento": "N/A",
    "entidade": "Loulé Concelho Global, EM, Unipessoal, SA",
    "link": "https://diariodarepublica.pt/dr/detalhe/contrato-publico/467-1003479542",
    "detalhes_completos": "1 - IDENTIFICAÇÃO E CONTACTOS DA ENTIDADE ADJUDICANTE\nDesignação da entidade adjudicante: Loulé Concelho Global, EM, Unipessoal, SA\nNIPC: 505493870\nServiço/Órgão/Pessoa de contacto: Conselho de Administração\nEndereço: Rua José Afonso, Lote 61 - R/C\nCódigo postal: 8100-592\nLocalidade: Loulé\nPaís: Portugal\nNUT III: PT150\nDistrito: Faro\nConcelho: Loulé\nFreguesia: Todas\nTelefone: 289401080\nFax: 289401089\nEndereço da Entidade (URL): www.lcglobal.pt\nEndereço Eletrónico: contratacao@lcglobal.pt\neDelivery Gateway (URL): https://www.acingov.pt\nFunção da Organização: Adquirente\nNorma jurídica da Entidade Adjudicante: Organismo de direito público\nÁrea de atividade da Autoridade Adjudicante: Serviços públicos das administrações públicas\n2 - JORNAL OFICIAL DA UNIÃO EUROPEIA\nO procedimento a que este anúncio diz respeito também é publicitado no Jornal Oficial da União Europeia? Não\n3 - AVISO\nModelo de Anúncio: Concurso público urgente\nData de Envio do Anúncio: 09-01-2026 16:29:00\n5 - PROCESSO\nTipo de Procedimento: Concurso público\nPreço base do procedimento: Sim\nValor do preço base do procedimento: 168.881,04 EUR\nProcedimento com lotes? Não\n6 - OBJETO DO CONTRATO\nNúmero de referência interna: 01/26\nDesignação do contrato: Aquisição da prestação de serviço público de transporte urbano de passageiros em autocarro no Município de Loulé\nDescrição: Aquisição da prestação de serviço público de transporte urbano de passageiros em autocarro no Município de Loulé\nTipo de Contrato Principal: Aquisição de Serviços\nTipo de Contrato: Aquisição de Serviços\nClassificação CPV (Vocabulário Comum para os Contratos Públicos)\nObjeto principal\nVocabulário Principal: 60112000\nPreço base s/IVA: 168.881,04 EUR\n7 - INDICAÇÕES ADICIONAIS\nO contrato envolve aquisição conjunta (satisfação de várias entidades)? Não\nO contrato é adjudicado por uma central de compras? Não\n8 - TÉCNICAS\nO concurso destina-se à celebração de um acordo-quadro? Inexistência de acordo-quadro\nÉ utilizado um leilão eletrónico? Não\nÉ adotada uma fase de negociação? Não\nSistema de Aquisição Dinâmico: Inexistência de sistema de aquisição dinâmico\n9 - LOCAL DA EXECUÇÃO DO CONTRATO\nLOCAL DA EXECUÇÃO DO CONTRATO (PROCEDIMENTO)\nPaís: Portugal\nNUT III: PT150\nLocalidade: Loulé\nDistrito: Faro\nConcelho: Loulé\nFreguesia: Todas\n10 - PRAZO DE EXECUÇÃO DO CONTRATO\nPrazo de execução do contrato: 60 DIAS\nPrevisão de renovações: Sim\nIndicar número máximo de renovações: 2\nPrazo de renovações diferente do prazo inicial: Sim\nIndicar o prazo de execução da renovação do contrato: 30 DIAS\n11 - FUNDOS EU\nTêm fundos EU? Não\n12 - DOCUMENTOS DE HABILITAÇÃO\nHabilitação para o exercício da atividade profissional: Não\n13 - CONDIÇÕES DE APRESENTAÇÃO\nPlataforma eletrónica utilizada pela entidade adjudicante: ACIN\nURL para Apresentação: https://www.acingov.pt\nAdmissibilidade da apresentação de propostas variantes: Não autorizado\nPrazo para apresentação das propostas: 14-01-2026 23:59\nPrazo durante o qual os concorrentes são obrigados a manter as respetivas propostas: 10 dias a contar do termo do prazo para a apresentação das propostas\nIndicação de Subcontratação na Proposta: Inexistência de indicação de subcontratação\n14 - PRESTAÇÃO DE CAUÇÃO\nPrestação de caução: Não\n15 - FORNECIMENTO DAS PEÇAS DO CONCURSO, APRESENTAÇÃO DE PEDIDOS DE PARTICIPAÇÃO E APRESENTAÇÃO DAS PROPOSTAS\nLink para acesso às peças do concurso (URL): https://www.acingov.pt/acingovprod/2/zonaPublica/zona_publica_c/donwloadProcedurePiece/MTA0MTUxMA==\n20 - OUTROS REQUISITOS\nInformação sobre contratos reservados. Aplica-se a contratos reservados (54º-A)? Não\n21 - CRITÉRIO DE ADJUDICAÇÃO\nMultifator: Não\nMonofator:\nNome: Preço\n24 - CONDIÇÕES DO CONTRATO\nFaturação Eletrónica: Necessário\nObrigação de Subcontratação:\nCódigo da Obrigação de Subcontratação: Não é aplicável nenhuma obrigação de subcontratação.\n25 - COMPRA PÚBLICA ESTRATÉGICA\nCompra Pública Estratégica: Inexistência de contratação pública estratégica\n26 - INFORMAÇÕES ADICIONAIS\nContrato adequado para PME: Sim\nCobertura ACP (Acordo dos Contratos Públicos da Organização Mundial do Comércio): Não\n27 - IDENTIFICAÇÃO E CONTACTOS DO ÓRGÃO DE RECURSOS ADMINISTRATIVOS\nDesignação: Conselho de Administração\nEndereço: Rua José Afonso, Lote 61 - R/C\nCódigo postal: 8100-592\nLocalidade: Loulé\nTelefone: 289401080\nFax: 289401089\nEndereço eletrónico: contratacao@lcglobal.pt\n28 - IDENTIFICAÇÃO DO(S) AUTOR(ES) DE ANÚNCIO\nNome: Rui Augusto Ventura Guerreiro\nCargo: Presidente do Conselho de Administração\n419947610",
    "nipc": "505493870",
    "distrito": "Faro",
    "concelho": "Loulé",
    "freguesia": "Todas",
    "site": "www.lcglobal.pt",
    "email": "contratacao@lcglobal.pt",
    "designacao_contrato": "Aquisição da prestação de serviço público de transporte urbano de passageiros em autocarro no Município de Loulé",
    "descricao": "Aquisição da prestação de serviço público de transporte urbano de passageiros em autocarro no Município de Loulé",
    "preco_base": "168.881,04 EUR",
    "prazo_execucao": "60 DIAS",
    "prazo_apresentacao_propostas": "14-01-2026 23:59",
    "fundos_eu": "Não",
    "plataforma_eletronica": "ACIN",
    "url_procedimento": "https://www.acingov.pt",
    "autor_nome": "Rui Augusto Ventura Guerreiro",
    "autor_cargo": "Presidente do Conselho de Administração"
  },
  {
    "numero_procedimento": "N/A",
    "entidade": "Município da Maia",
    "link": "https://diariodarepublica.pt/dr/detalhe/contrato-publico/434-1003750287",
    "detalhes_completos": "Alteração do Anúncio de procedimento n.º 30900/2025, de 2025-11-27, com o ID 419824268\n1 - IDENTIFICAÇÃO E CONTACTOS DA ENTIDADE ADJUDICANTE\nDesignação da entidade adjudicante: Município da Maia\nNIPC: 505387131\nServiço/Órgão/Pessoa de contacto: Divisão de Contratação Pública e Aprovisionamento\nEndereço: Praça Dr. José Vieira de Carvalho\nCódigo postal: 4470-202\nLocalidade: Maia\nPaís: Portugal\nNUT III: PT11A\nDistrito: Porto\nConcelho: Maia\nFreguesia: Freguesia de Cidade da Maia\nTelefone: 229 408 600\nFax: 229 418 411\nEndereço da Entidade (URL): www.cm-maia.pt\nEndereço Eletrónico: geral@cm-maia.pt\neDelivery Gateway (URL): https://www.acingov.pt\nFunção da Organização: Adquirente\nSubfunção da Organização: Organização que recebe as propostas\nNorma jurídica da Entidade Adjudicante: Autoridade local\nÁrea de atividade da Autoridade Adjudicante: Serviços públicos das administrações públicas\n2 - JORNAL OFICIAL DA UNIÃO EUROPEIA\nO procedimento a que este anúncio diz respeito também é publicitado no Jornal Oficial da União Europeia? Não\n3 - AVISO\nModelo de Anúncio: Concurso público\nData de Envio do Anúncio: 09-01-2026\n5 - PROCESSO\nTipo de Procedimento: Concurso público\nPreço base do procedimento: Sim\nValor do preço base do procedimento: 3.985.350,29 EUR\nProcedimento com lotes? Não\n6 - OBJETO DO CONTRATO\nNúmero de referência interna: 1055.CPN.E.25 - OBM 71/25\nDesignação do contrato: NOVAS INSTALAÇÕES DA POLÍCIA MUNICIPAL\nDescrição: NOVAS INSTALAÇÕES DA POLÍCIA MUNICIPAL\nTipo de Contrato Principal: Empreitada de Obras Públicas\nTipo de Contrato: Empreitada de Obras Públicas\nClassificação CPV (Vocabulário Comum para os Contratos Públicos)\nObjeto principal\nVocabulário Principal: 45216110\nPreço base s/IVA: 3.985.350,29 EUR\n7 - INDICAÇÕES ADICIONAIS\nO contrato envolve aquisição conjunta (satisfação de várias entidades)? Não\nO contrato é adjudicado por uma central de compras? Não\n8 - TÉCNICAS\nO concurso destina-se à celebração de um acordo-quadro? Inexistência de acordo-quadro\nÉ utilizado um leilão eletrónico? Não\nÉ adotada uma fase de negociação? Não\nSistema de Aquisição Dinâmico: Inexistência de sistema de aquisição dinâmico\n9 - LOCAL DA EXECUÇÃO DO CONTRATO\nLOCAL DA EXECUÇÃO DO CONTRATO (PROCEDIMENTO)\nPaís: Portugal\nNUT III: PT11A\nLocalidade: Freguesia de Cidade da Maia\nDistrito: Porto\nConcelho: Maia\nFreguesia: Freguesia de Cidade da Maia\n10 - PRAZO DE EXECUÇÃO DO CONTRATO\nPrazo de execução do contrato: 540 DIAS\nPrevisão de renovações: Não\n11 - FUNDOS EU\nTêm fundos EU? Sim\n12 - DOCUMENTOS DE HABILITAÇÃO\nHabilitação para o exercício da atividade profissional: Sim\nTipo: Alvará\nDescrição: 1.ª Subcategoria da 1.ª Categoria, da classe correspondente ao valor global da proposta, as 2.ª, 3.ª, 4.ª, 5.ª, 6.ª, 7.ª e 8.ª Subcategorias da 1.ª Categoria, as 8.ª e 9.ª Subcategorias da 2.ª Categoria, as 1.ª, 6.ª, 9.ª, 10.ª, 11.ª e 12.ª Subcategorias da 4.ª Categoria e as 2.ª, 6.ª, 8.ª, 10.ª, 11.ª e 12.ª Subcategorias da 5.ª Categoria, as quais têm de ser da classe que cubra o valor dos respetivos trabalhos.\n13 - CONDIÇÕES DE APRESENTAÇÃO\nPlataforma eletrónica utilizada pela entidade adjudicante: ACIN\nURL para Apresentação: https://www.acingov.pt\nAdmissibilidade da apresentação de propostas variantes: Não autorizado\nPrazo para apresentação das propostas: 24-01-2026 23:59\nPrazo durante o qual os concorrentes são obrigados a manter as respetivas propostas: 66 dias a contar do termo do prazo para a apresentação das propostas\nIndicação de Subcontratação na Proposta: Inexistência de indicação de subcontratação\n14 - PRESTAÇÃO DE CAUÇÃO\nPrestação de caução: Sim\nPercentagem: 5%\nDescrição da Garantia Exigida: O valor da caução é de 5.00% do preço contratual.\n15 - FORNECIMENTO DAS PEÇAS DO CONCURSO, APRESENTAÇÃO DE PEDIDOS DE PARTICIPAÇÃO E APRESENTAÇÃO DAS PROPOSTAS\nLink para acesso às peças do concurso (URL): https://www.acingov.pt/acingovprod/2/zonaPublica/zona_publica_c/donwloadProcedurePiece/OTk4MTE0\n20 - OUTROS REQUISITOS\nInformação sobre contratos reservados. Aplica-se a contratos reservados (54º-A)? Não\n21 - CRITÉRIO DE ADJUDICAÇÃO\nMultifator: Não\nMonofator:\nNome: Preço\n24 - CONDIÇÕES DO CONTRATO\nFaturação Eletrónica: Permitido\nObrigação de Subcontratação:\nCódigo da Obrigação de Subcontratação: Não é aplicável nenhuma obrigação de subcontratação.\n25 - COMPRA PÚBLICA ESTRATÉGICA\nCompra Pública Estratégica: Inexistência de contratação pública estratégica\n26 - INFORMAÇÕES ADICIONAIS\nContrato adequado para PME: Sim\nCobertura ACP (Acordo dos Contratos Públicos da Organização Mundial do Comércio): Não\n27 - IDENTIFICAÇÃO E CONTACTOS DO ÓRGÃO DE RECURSOS ADMINISTRATIVOS\nDesignação: Câmara Municipal da Maia\nEndereço: Praça Dr. José Vieira de Carvalho\nCódigo postal: 4470-202\nLocalidade: Maia\nTelefone: 229408600\nFax: 229418411\nEndereço eletrónico: geral@cm-maia.pt\nPrazo de interposição do recurso: 5 dias\n28 - IDENTIFICAÇÃO DO(S) AUTOR(ES) DE ANÚNCIO\nNome: António Domingos da Silva Tiago\nCargo: Presidente da Câmara Municipal da Maia\n29 - ALTERAÇÃO\nMotivo da Alteração: Correção pelo adquirente\nIdentificador da Versão do Anúncio a Alterar: 69d07789-7f77-49a9-a933-359114d7ef78-01\nIdentificador das Secções Alteradas do Anúncio Anterior: Condições de Apresentação\nDescrição das Alterações: Modificação do prazo para a apresentação de propostas\nAlteração dos Documentos do Concurso: Não\n419947428",
    "nipc": "505387131",
    "distrito": "Porto",
    "concelho": "Maia",
    "freguesia": "Freguesia de Cidade da Maia",
    "site": "www.cm-maia.pt",
    "email": "geral@cm-maia.pt",
    "designacao_contrato": "NOVAS INSTALAÇÕES DA POLÍCIA MUNICIPAL",
    "descricao": "NOVAS INSTALAÇÕES DA POLÍCIA MUNICIPAL",
    "preco_base": "3.985.350,29 EUR",
    "prazo_execucao": "540 DIAS",
    "prazo_apresentacao_propostas": "24-01-2026 23:59",
    "fundos_eu": "Sim",
    "plataforma_eletronica": "ACIN",
    "url_procedimento": "https://www.acingov.pt",
    "autor_nome": "António Domingos da Silva Tiago",
    "autor_cargo": "Presidente da Câmara Municipal da Maia"
  },
  {
    "numero_procedimento": "N/A",
    "entidade": "AnÃºncio de procedimento  n.Âº 435/2026  -  DiÃ¡rio da RepÃºblica n.Âº 6/2026, SÃ©rie II de 2026-01-09",
    "link": "https://diariodarepublica.pt/dr/detalhe/contrato-publico/435-1004293681"
  },
  {
    "numero_procedimento": "N/A",
    "entidade": "Município da Amadora",
    "link": "https://diariodarepublica.pt/dr/detalhe/contrato-publico/437-1004573010",
    "detalhes_completos": "1 - IDENTIFICAÇÃO E CONTACTOS DA ENTIDADE ADJUDICANTE\nDesignação da entidade adjudicante: Município da Amadora\nNIPC: 505456010\nServiço/Órgão/Pessoa de contacto: Departamento de Obras Municipais\nEndereço: Av. do Movimento das Forças Armadas\nCódigo postal: 2700-595\nLocalidade: Lisboa\nPaís: Portugal\nNUT III: PT170\nDistrito: Lisboa\nConcelho: Amadora\nFreguesia: Todas\nTelefone: 214369000\nFax: 214369000\nEndereço da Entidade (URL): https://www.cm-amadora.pt/pt/\nEndereço Eletrónico: geral@cm-amadora.pt\neDelivery Gateway (URL): https://community.vortal.biz/public/\nFunção da Organização: Adquirente\nNorma jurídica da Entidade Adjudicante: Autoridade local\nÁrea de atividade da Autoridade Adjudicante: Serviços públicos das administrações públicas\n2 - JORNAL OFICIAL DA UNIÃO EUROPEIA\nO procedimento a que este anúncio diz respeito também é publicitado no Jornal Oficial da União Europeia? Não\n3 - AVISO\nModelo de Anúncio: Concurso público\nData de Envio do Anúncio: 09-01-2026\n5 - PROCESSO\nTipo de Procedimento: Concurso público\nPreço base do procedimento: Sim\nValor do preço base do procedimento: 550.889,54 EUR\nProcedimento com lotes? Não\n6 - OBJETO DO CONTRATO\nNúmero de referência interna: DOM 51/2025/95884\nDesignação do contrato: Eixos Principais - Pavimentação - Execução de Obra\nDescrição: A obra tem como objetivo a reparação e requalificação dos arruamentos e respetivas zonas envolventes. \nTipo de Contrato Principal: Empreitada de Obras Públicas\nTipo de Contrato: Empreitada de Obras Públicas\nClassificação CPV (Vocabulário Comum para os Contratos Públicos)\nObjeto principal\nVocabulário Principal: 45233200\nPreço base s/IVA: 550.889,54 EUR\n7 - INDICAÇÕES ADICIONAIS\nO contrato envolve aquisição conjunta (satisfação de várias entidades)? Não\nO contrato é adjudicado por uma central de compras? Não\n8 - TÉCNICAS\nO concurso destina-se à celebração de um acordo-quadro? Inexistência de acordo-quadro\nÉ utilizado um leilão eletrónico? Não\nÉ adotada uma fase de negociação? Não\nSistema de Aquisição Dinâmico: Inexistência de sistema de aquisição dinâmico\n9 - LOCAL DA EXECUÇÃO DO CONTRATO\nLOCAL DA EXECUÇÃO DO CONTRATO (PROCEDIMENTO)\nPaís: Portugal\nNUT III: PT170\nLocalidade: Lisboa\nDistrito: Lisboa\nConcelho: Amadora\nFreguesia: Todas\n10 - PRAZO DE EXECUÇÃO DO CONTRATO\nPrazo de execução do contrato: 63 DIAS\nPrevisão de renovações: Não\n11 - FUNDOS EU\nTêm fundos EU? Não\n12 - DOCUMENTOS DE HABILITAÇÃO\nHabilitação para o exercício da atividade profissional: Sim\nTipo: Alvará\nDescrição: Ponto 17 do Programa de Concurso.\n13 - CONDIÇÕES DE APRESENTAÇÃO\nPlataforma eletrónica utilizada pela entidade adjudicante: VORTAL\nURL para Apresentação: https://community.vortal.biz/public/\nAdmissibilidade da apresentação de propostas variantes: Não autorizado\nPrazo para apresentação das propostas: 08-02-2026 23:59\nPrazo durante o qual os concorrentes são obrigados a manter as respetivas propostas: 66 dias a contar do termo do prazo para a apresentação das propostas\nIndicação de Subcontratação na Proposta: Inexistência de indicação de subcontratação\n14 - PRESTAÇÃO DE CAUÇÃO\nPrestação de caução: Sim\nPercentagem: 5%\nDescrição da Garantia Exigida: Ponto 1.11 do Caderno de Encargos\n15 - FORNECIMENTO DAS PEÇAS DO CONCURSO, APRESENTAÇÃO DE PEDIDOS DE PARTICIPAÇÃO E APRESENTAÇÃO DAS PROPOSTAS\nLink para acesso às peças do concurso (URL): https://community.vortal.biz/Public/public-tender-documents/OFhzMW8vcXpSNGRkcTZUNEVwb3ZCNE9GK091Tm9zcElGZjdDOFBzZi9GVFNuR0l5ejY1OFM1MXlBUlJvUjNtd3FMMW83aS8yYUZBVUFSMTd0TEY5alE9PVVFalBm\n20 - OUTROS REQUISITOS\nInformação sobre contratos reservados. Aplica-se a contratos reservados (54º-A)? Não\n21 - CRITÉRIO DE ADJUDICAÇÃO\nMultifator: Sim\nFator: \nNome: Outros\nOutro Nome: Preço\nPonderação: 35%\nSubfatores: Não\nFator: \nNome: Qualidade\nPonderação: 65%\nSubfatores: Sim\nSubfatores: \nNome: Qualidade e Adequabilidade da Memória Descritiva\nPonderação : 70%; \nNome: Plano de Trabalhos\nPonderação : 30%; \n24 - CONDIÇÕES DO CONTRATO\nFaturação Eletrónica: Permitido\nObrigação de Subcontratação:\nCódigo da Obrigação de Subcontratação: Não é aplicável nenhuma obrigação de subcontratação.\n25 - COMPRA PÚBLICA ESTRATÉGICA\nCompra Pública Estratégica: Inexistência de contratação pública estratégica\n26 - INFORMAÇÕES ADICIONAIS\nContrato adequado para PME: Sim\nCobertura ACP (Acordo dos Contratos Públicos da Organização Mundial do Comércio): Não\n27 - IDENTIFICAÇÃO E CONTACTOS DO ÓRGÃO DE RECURSOS ADMINISTRATIVOS\nDesignação: Município da Amadora\nEndereço: Avenida Movimento das Forças Armadas, n.º 1\nCódigo postal: 2700-595\nLocalidade: Amadora\nTelefone: +351 214369000\nFax: +351 000000000\nEndereço eletrónico: geral@cm-amadora.pt\nPrazo de interposição do recurso: 5 dias\n28 - IDENTIFICAÇÃO DO(S) AUTOR(ES) DE ANÚNCIO\nNome: Vítor Ferreira\nCargo: Presidente\n419947514",
    "nipc": "505456010",
    "distrito": "Lisboa",
    "concelho": "Amadora",
    "freguesia": "Todas",
    "site": "https://www.cm-amadora.pt/pt/",
    "email": "geral@cm-amadora.pt",
    "designacao_contrato": "Eixos Principais - Pavimentação - Execução de Obra",
    "descricao": "A obra tem como objetivo a reparação e requalificação dos arruamentos e respetivas zonas envolventes.",
    "preco_base": "550.889,54 EUR",
    "prazo_execucao": "63 DIAS",
    "prazo_apresentacao_propostas": "08-02-2026 23:59",
    "fundos_eu": "Não",
    "plataforma_eletronica": "VORTAL",
    "url_procedimento": "https://community.vortal.biz/public/",
    "autor_nome": "Vítor Ferreira",
    "autor_cargo": "Presidente"
  },
  {
    "numero_procedimento": "N/A",
    "entidade": "Município de Barrancos",
    "link": "https://diariodarepublica.pt/dr/detalhe/contrato-publico/439-1004861201",
    "detalhes_completos": "1 - IDENTIFICAÇÃO E CONTACTOS DA ENTIDADE ADJUDICANTE\nDesignação da entidade adjudicante: Município de Barrancos\nNIPC: 501081216\nServiço/Órgão/Pessoa de contacto: Ana Luísa Delgado Gabinete Jurídico\nEndereço: Praça do Município, n.º 2, r/c\nCódigo postal: 7230-030\nLocalidade: Barrancos\nPaís: Portugal\nNUT III: Baixo Alentejo\nDistrito: Beja\nConcelho: Barrancos\nFreguesia: Freguesia de Barrancos\nTelefone: 285950630\nEndereço da Entidade (URL): https://www.cm-barrancos.pt\nEndereço Eletrónico: geral@cm-barrancos.pt\nFunção da Organização: \nNorma jurídica da Entidade Adjudicante: Autoridade local\nÁrea de atividade da Entidade Adjudicante: Atividades relacionadas com a água\n2 - AVISO\nData de Envio do Anúncio: 09-01-2026\n3 - PROCESSO\nModelo de Anúncio: Hasta pública de alienação de bens móveis\nPreço de licitação base do procedimento: Sim\nValor da licitação base do procedimento: 7.500,00 EUR\nContratação por Lotes? Sim\n4 - OBJETO DO CONTRATO\nNúmero de referência interna: 1/2026\nDesignação do procedimento de alienação de bens móveis: Procedimento de Hasta Pública de dois veículos agrícolas em fim de vida \nTipo de bens: Bens móveis \nLegislação aplicável: Artigo 266.º C do Código dos Contratos Públicos DL n.º 18/2008, de 29 de Janeiro, na sua versão atual\nAvaliação do bem: 7.500,00 EUR\nClassificação CPV (Vocabulário Comum para os Contratos Públicos)\nObjeto: Objeto principal\nVocabulário Principal: Tractores usados\nLotes: \nNº: LOT-0001\nDescrição do Lote: Trator Massey Ferguson  –MF-275, ano 1984 e cilindrada 3860\nPreço base s/IVA: 3.000,00 EUR\nClassificação CPV (Vocabulário Comum para os Contratos Públicos)\nObjeto: Objeto principal\nVocabulário Principal: Tractores usados\nNº: LOT-0002\nDescrição do Lote: Trator Lamborghini - Modelo 880 Plus VDP, Ano 1997, Cilindrada 4000\nPreço base s/IVA: 4.500,00 EUR\nClassificação CPV (Vocabulário Comum para os Contratos Públicos)\nObjeto: Objeto principal\nVocabulário Principal: Tractores usados\n5 - DESTINATÁRIOS\nDestinatários: Todos os interessados, nos termos da Cláusula 3.ª do Programa do Procedimento de Hasta Pública.\n6 - INDICAÇÕES ADICIONAIS\nReferência do Portal dos Contratos Públicos:N/A\nA entidade adjudicante atua como compradora no procedimento? Não\nÉ utilizado um leilão eletrónico?  Não\nÉ adotada uma fase de negociação?  Não\n7 - CONSULTA DAS PEÇAS E OBTENÇÃO DE CÓPIAS\nLink para acesso às peças do concurso (URL):https://www.cm-barrancos.pt\n8 -  PEDIDOS DE ESCLARECIMENTO SOBRE AS PEÇAS DO PROCEDIMENTO\nPedidos de esclarecimento sobre as peças do procedimento: Nos termos no previsto na Cláusula do 9.ª do Procedimento de Hasta Pública.\n9 -  DOCUMENTOS DE HABILITAÇÃO\nDocumentos de habilitação: Conforme previsto na Cláusula 10.ª do Programa do Procedimento da Hasta Pública: documentos comprovativos de que o concorrente não se encontra abrangido pelos condicionalismos descritos no artigo 55.º do Código dos Contratos Públicos.\n10 -  CONDIÇÕES DE PARTICIPAÇÃO\nCondições de participação: Poderão ser concorrentes quaisquer entidades, pessoas singulares ou coletivas, interessadas e que não se encontrem abrangidas pelos condicionalismos descritos no artigo 55.º do Código dos Contratos Públicos.\n11 - DATA, LOCAL E REGRAS ATO PÚBLICO\nData, Local e Regras do Ato Publico: Até às 16H00 do 10.º dia a contar da data de envio do presente anúncio\n12- CONDIÇÕES DE APRESENTAÇÃO\nModo de apresentação das propostas: Sitio da Internet\nLocal de apresentação das propostas:  https://cm-barrancos.pt/\nPrazo para apresentação das propostas: 23-01-2026\nPrazo durante o qual os concorrentes são obrigados a manter as respetivas propostas: 3 dias a contar do termo do prazo para a apresentação das propostas\n13- CRITÉRIO DE SELEÇÃO\nApenas o valor licitado? Sim\nFator de avaliação: \nPonderação: 0\n14 - PRESTAÇÃO DE CAUÇÃO\nPrestação de caução: Não\n15 - IDENTIFICAÇÃO DO(S) AUTOR(ES) DE ANÚNCIO\nNome: Emílio Domingues\nCargo: Presidente da Câmara Municipal de Barrancos\n419947493",
    "nipc": "501081216",
    "distrito": "Beja",
    "concelho": "Barrancos",
    "freguesia": "Freguesia de Barrancos",
    "site": "https://www.cm-barrancos.pt",
    "email": "geral@cm-barrancos.pt",
    "designacao_contrato": null,
    "descricao": null,
    "preco_base": "3.000,00 EUR",
    "prazo_execucao": null,
    "prazo_apresentacao_propostas": "23-01-2026",
    "fundos_eu": null,
    "plataforma_eletronica": null,
    "url_procedimento": null,
    "autor_nome": null,
    "autor_cargo": "Presidente da Câmara Municipal de Barrancos"
  },
  {
    "numero_procedimento": "N/A",
    "entidade": "Instituto Nacional de Emergência Médica, IP",
    "link": "https://diariodarepublica.pt/dr/detalhe/contrato-publico/441-1004861226",
    "detalhes_completos": "1 - IDENTIFICAÇÃO E CONTACTOS DA ENTIDADE ADJUDICANTE\nDesignação da entidade adjudicante: Instituto Nacional de Emergência Médica, IP\nNIPC: 501356126\nServiço/Órgão/Pessoa de contacto: Gabinete de Gestão de Compras e Contratação Pública do INEM, I.P.\nEndereço: RUA ALMIRANTE BARROSO, 36\nCódigo postal: 1000-013\nLocalidade: Lisboa\nPaís: Portugal\nNUT III: PT170\nDistrito: Lisboa\nConcelho: Lisboa\nFreguesia: Freguesia de Arroios - Lisboa\nTelefone: 213508100\nFax: 213508100\nEndereço da Entidade (URL): https://www.inem.pt/\nEndereço Eletrónico: inem@inem.pt\neDelivery Gateway (URL): https://www.acingov.pt\nFunção da Organização: Adquirente\nSubfunção da Organização: Organização que recebe as propostas\nNorma jurídica da Entidade Adjudicante: Organismo de direito público\nÁrea de atividade da Autoridade Adjudicante: Serviços públicos das administrações públicas\n2 - JORNAL OFICIAL DA UNIÃO EUROPEIA\nO procedimento a que este anúncio diz respeito também é publicitado no Jornal Oficial da União Europeia? Não\n3 - AVISO\nModelo de Anúncio: Concurso público\nData de Envio do Anúncio: 09-01-2026\n5 - PROCESSO\nTipo de Procedimento: Concurso público\nPreço base do procedimento: Sim\nValor do preço base do procedimento: 82.350,00 EUR\nProcedimento com lotes? Não\n6 - OBJETO DO CONTRATO\nNúmero de referência interna: CP-25/0058\nDesignação do contrato: ASSISTÊNCIA TÉCNICA AOS PRODUTOS E EQUIPAMENTOS DE SEGURANÇA CONTRA INCÊNDIO EM EDIFÍCIOS (SCIE) PARA O INEM\nDescrição: ASSISTÊNCIA TÉCNICA AOS PRODUTOS E EQUIPAMENTOS DE SEGURANÇA CONTRA INCÊNDIO EM EDIFÍCIOS (SCIE) PARA O INEM \nTipo de Contrato Principal: Aquisição de Serviços\nTipo de Contrato: Aquisição de Serviços\nClassificação CPV (Vocabulário Comum para os Contratos Públicos)\nObjeto principal\nVocabulário Principal: 50413200\nPreço base s/IVA: 82.350,00 EUR\n7 - INDICAÇÕES ADICIONAIS\nO contrato envolve aquisição conjunta (satisfação de várias entidades)? Não\nO contrato é adjudicado por uma central de compras? Não\n8 - TÉCNICAS\nO concurso destina-se à celebração de um acordo-quadro? Inexistência de acordo-quadro\nÉ utilizado um leilão eletrónico? Não\nÉ adotada uma fase de negociação? Não\nSistema de Aquisição Dinâmico: Inexistência de sistema de aquisição dinâmico\n9 - LOCAL DA EXECUÇÃO DO CONTRATO\nLOCAL DA EXECUÇÃO DO CONTRATO (PROCEDIMENTO)\nPaís: Portugal\nNUT III: PTZZZ\nLocalidade: Portugal continental\nDistrito: Portugal Continental\nConcelho: Todos\nFreguesia: Todas\n10 - PRAZO DE EXECUÇÃO DO CONTRATO\nData de Início: 01-03-2026\nData de Fim: 31-12-2027\nPrevisão de renovações: Não\n11 - FUNDOS EU\nTêm fundos EU? Não\n12 - DOCUMENTOS DE HABILITAÇÃO\nHabilitação para o exercício da atividade profissional: Não\n13 - CONDIÇÕES DE APRESENTAÇÃO\nPlataforma eletrónica utilizada pela entidade adjudicante: ACIN\nURL para Apresentação: https://www.acingov.pt\nAdmissibilidade da apresentação de propostas variantes: Não autorizado\nPrazo para apresentação das propostas: 18-01-2026 23:59\nPrazo durante o qual os concorrentes são obrigados a manter as respetivas propostas: 66 dias a contar do termo do prazo para a apresentação das propostas\nIndicação de Subcontratação na Proposta: Inexistência de indicação de subcontratação\n14 - PRESTAÇÃO DE CAUÇÃO\nPrestação de caução: Não\n15 - FORNECIMENTO DAS PEÇAS DO CONCURSO, APRESENTAÇÃO DE PEDIDOS DE PARTICIPAÇÃO E APRESENTAÇÃO DAS PROPOSTAS\nLink para acesso às peças do concurso (URL): https://www.acingov.pt/acingovprod/2/zonaPublica/zona_publica_c/donwloadProcedurePiece/MTA0MTQ0Nw==\n20 - OUTROS REQUISITOS\nInformação sobre contratos reservados. Aplica-se a contratos reservados (54º-A)? Não\n21 - CRITÉRIO DE ADJUDICAÇÃO\nMultifator: Não\nMonofator:\nNome: Outros\nOutro nome: Mais baixo preço da prestação de serviços de manutenção dos equipamentos\n24 - CONDIÇÕES DO CONTRATO\nFaturação Eletrónica: Permitido\nObrigação de Subcontratação:\nCódigo da Obrigação de Subcontratação: Não é aplicável nenhuma obrigação de subcontratação.\n25 - COMPRA PÚBLICA ESTRATÉGICA\nCompra Pública Estratégica: Inexistência de contratação pública estratégica\n26 - INFORMAÇÕES ADICIONAIS\nContrato adequado para PME: Sim\nCobertura ACP (Acordo dos Contratos Públicos da Organização Mundial do Comércio): Não\n27 - IDENTIFICAÇÃO E CONTACTOS DO ÓRGÃO DE RECURSOS ADMINISTRATIVOS\nDesignação: Conselho Diretivo do INEM, I.P.\nEndereço: RUA ALMIRANTE BARROSO, 36\nCódigo postal: 1000-013\nLocalidade: Lisboa\nTelefone: 213508100\nFax: \nEndereço eletrónico: inem@inem.pt\n28 - IDENTIFICAÇÃO DO(S) AUTOR(ES) DE ANÚNCIO\nNome: Sérgio Miguel Justo de Magalhães\nCargo: Coordenador do Gabinete de Gestão de Compras e Contratação Pública\n419947562",
    "nipc": "501356126",
    "distrito": "Lisboa",
    "concelho": "Lisboa",
    "freguesia": "Freguesia de Arroios - Lisboa",
    "site": "https://www.inem.pt/",
    "email": "inem@inem.pt",
    "designacao_contrato": "ASSISTÊNCIA TÉCNICA AOS PRODUTOS E EQUIPAMENTOS DE SEGURANÇA CONTRA INCÊNDIO EM EDIFÍCIOS (SCIE) PARA O INEM",
    "descricao": "ASSISTÊNCIA TÉCNICA AOS PRODUTOS E EQUIPAMENTOS DE SEGURANÇA CONTRA INCÊNDIO EM EDIFÍCIOS (SCIE) PARA O INEM",
    "preco_base": "82.350,00 EUR",
    "prazo_execucao": null,
    "prazo_apresentacao_propostas": "18-01-2026 23:59",
    "fundos_eu": "Não",
    "plataforma_eletronica": "ACIN",
    "url_procedimento": "https://www.acingov.pt",
    "autor_nome": "Sérgio Miguel Justo de Magalhães",
    "autor_cargo": "Coordenador do Gabinete de Gestão de Compras e Contratação Pública"
  },
  {
    "numero_procedimento": "N/A",
    "entidade": "Unidade Local de Saúde de Santa Maria, EPE",
    "link": "https://diariodarepublica.pt/dr/detalhe/contrato-publico/445-1005484241",
    "detalhes_completos": "Alteração do Anúncio de procedimento n.º 137/2026, de 2026-01-05, com o ID 419947118\n1 - IDENTIFICAÇÃO E CONTACTOS DA ENTIDADE ADJUDICANTE\nDesignação da entidade adjudicante: Unidade Local de Saúde de Santa Maria, EPE\nNIPC: 508481287\nEndereço: Avenida Prof. Egas Moniz\nCódigo postal: 1649-035\nLocalidade: Lisboa\nPaís: Portugal\nNUT III: PT170\nDistrito: Lisboa\nConcelho: Lisboa\nFreguesia: Freguesia de Alvalade - Lisboa\nTelefone: 217805330\nFax: 217805605\nEndereço da Entidade (URL): www.ulssm.min-saude.pt\nEndereço Eletrónico: compras@ulssm.min-saude.pt\neDelivery Gateway (URL): https://community.vortal.biz/public/\nFunção da Organização: Adquirente\nNorma jurídica da Entidade Adjudicante: Empresa pública\nÁrea de atividade da Autoridade Adjudicante: Saúde\n2 - JORNAL OFICIAL DA UNIÃO EUROPEIA\nO procedimento a que este anúncio diz respeito também é publicitado no Jornal Oficial da União Europeia? Não\n3 - AVISO\nModelo de Anúncio: Concurso público\nData de Envio do Anúncio: 09-01-2026\n5 - PROCESSO\nTipo de Procedimento: Concurso público\nPreço base do procedimento: Sim\nValor do preço base do procedimento: 38.500,00 EUR\nProcedimento com lotes? Não\n6 - OBJETO DO CONTRATO\nNúmero de referência interna: 262A000017\nDesignação do contrato: 262A000017 - Aquisição de Rolo Absorvente Pré-Cortado, ano 2026 e 2027\nDescrição: Aquisição de Rolo Absorvente Pré-Cortado, ano 2026 e 2027\nTipo de Contrato Principal: Aquisição de Bens Móveis\nTipo de Contrato: Aquisição de Bens Móveis\nClassificação CPV (Vocabulário Comum para os Contratos Públicos)\nObjeto principal\nVocabulário Principal: 33140000\nPreço base s/IVA: 38.500,00 EUR\n7 - INDICAÇÕES ADICIONAIS\nO contrato envolve aquisição conjunta (satisfação de várias entidades)? Não\nO contrato é adjudicado por uma central de compras? Não\n8 - TÉCNICAS\nO concurso destina-se à celebração de um acordo-quadro? Inexistência de acordo-quadro\nÉ utilizado um leilão eletrónico? Não\nÉ adotada uma fase de negociação? Não\nSistema de Aquisição Dinâmico: Inexistência de sistema de aquisição dinâmico\n9 - LOCAL DA EXECUÇÃO DO CONTRATO\nLOCAL DA EXECUÇÃO DO CONTRATO (PROCEDIMENTO)\nPaís: Portugal\nNUT III: PT170\nLocalidade: Lisboa\nDistrito: Lisboa\nConcelho: Lisboa\nFreguesia: Freguesia de Alvalade - Lisboa\n10 - PRAZO DE EXECUÇÃO DO CONTRATO\nPrazo de execução do contrato: 24 MESES\nPrevisão de renovações: Não\n11 - FUNDOS EU\nTêm fundos EU? Não\n12 - DOCUMENTOS DE HABILITAÇÃO\nHabilitação para o exercício da atividade profissional: Não\n13 - CONDIÇÕES DE APRESENTAÇÃO\nPlataforma eletrónica utilizada pela entidade adjudicante: VORTAL\nURL para Apresentação: https://community.vortal.biz/public/\nAdmissibilidade da apresentação de propostas variantes: Não autorizado\nPrazo para apresentação das propostas: 18-01-2026 17:00\nPrazo durante o qual os concorrentes são obrigados a manter as respetivas propostas: 180 dias a contar do termo do prazo para a apresentação das propostas\nApresentação de Catálogo Eletrónico: Permitido\nIndicação de Subcontratação na Proposta: Inexistência de indicação de subcontratação\n14 - PRESTAÇÃO DE CAUÇÃO\nPrestação de caução: Não\n15 - FORNECIMENTO DAS PEÇAS DO CONCURSO, APRESENTAÇÃO DE PEDIDOS DE PARTICIPAÇÃO E APRESENTAÇÃO DAS PROPOSTAS\nLink para acesso às peças do concurso (URL): https://community.vortal.biz/Public/public-tender-documents/R2owT3ZadWNBYVQ3SVlGN1VXZThqV1FoOU5xTXFGQ0Nlc2Vvdm05eTFmMTQ3ajZjMmM5cXJRa3ZoTXQ5ZkQ0eS80UThTYzQrMzBCeE1XK1FBY2RtclE9PSFWSENF\n20 - OUTROS REQUISITOS\nInformação sobre contratos reservados. Aplica-se a contratos reservados (54º-A)? Não\n21 - CRITÉRIO DE ADJUDICAÇÃO\nMultifator: Não\nMonofator:\nNome: Preço\n24 - CONDIÇÕES DO CONTRATO\nFaturação Eletrónica: Permitido\nObrigação de Subcontratação:\nCódigo da Obrigação de Subcontratação: Não é aplicável nenhuma obrigação de subcontratação.\n25 - COMPRA PÚBLICA ESTRATÉGICA\nCompra Pública Estratégica: Inexistência de contratação pública estratégica\n26 - INFORMAÇÕES ADICIONAIS\nContrato adequado para PME: Sim\nCobertura ACP (Acordo dos Contratos Públicos da Organização Mundial do Comércio): Não\n27 - IDENTIFICAÇÃO E CONTACTOS DO ÓRGÃO DE RECURSOS ADMINISTRATIVOS\nDesignação: Conselho de Administração\nEndereço: Av Professor Egas Moniz\nCódigo postal: 1649-035\nLocalidade: Lisboa\nTelefone: +351 217805330\nFax: +351 217805605\nEndereço eletrónico: secretariado.ca@ulssm.min-saude.pt\n28 - IDENTIFICAÇÃO DO(S) AUTOR(ES) DE ANÚNCIO\nNome: Mariana Figueira\nCargo: Assistente Técnica\n29 - ALTERAÇÃO\nMotivo da Alteração: Correção pelo adquirente\nIdentificador da Versão do Anúncio a Alterar: 81ebc648-9c83-4e35-bb09-fa3d342c6342-01\nIdentificador das Secções Alteradas do Anúncio Anterior: Condições de Apresentação\nDescrição das Alterações: Prorrogação de prazo de apresentação de propostas, por motivo de alteração das peças de procedimento.\nAlteração dos Documentos do Concurso: Sim\nData de alteração dos documentos do concurso: 09-01-2026\n419947529",
    "nipc": "508481287",
    "distrito": "Lisboa",
    "concelho": "Lisboa",
    "freguesia": "Freguesia de Alvalade - Lisboa",
    "site": "www.ulssm.min-saude.pt",
    "email": "compras@ulssm.min-saude.pt",
    "designacao_contrato": "262A000017 - Aquisição de Rolo Absorvente Pré-Cortado, ano 2026 e 2027",
    "descricao": "Aquisição de Rolo Absorvente Pré-Cortado, ano 2026 e 2027",
    "preco_base": "38.500,00 EUR",
    "prazo_execucao": "24 MESES",
    "prazo_apresentacao_propostas": "18-01-2026 17:00",
    "fundos_eu": "Não",
    "plataforma_eletronica": "VORTAL",
    "url_procedimento": "https://community.vortal.biz/public/",
    "autor_nome": "Mariana Figueira",
    "autor_cargo": "Assistente Técnica"
  },
  {
    "numero_procedimento": "N/A",
    "entidade": "AnÃºncio de procedimento  n.Âº 446/2026  -  DiÃ¡rio da RepÃºblica n.Âº 6/2026, SÃ©rie II de 2026-01-09",
    "link": "https://diariodarepublica.pt/dr/detalhe/contrato-publico/446-1005484242"
  },
  {
    "numero_procedimento": "N/A",
    "entidade": "AnÃºncio de procedimento  n.Âº 447/2026  -  DiÃ¡rio da RepÃºblica n.Âº 6/2026, SÃ©rie II de 2026-01-09",
    "link": "https://diariodarepublica.pt/dr/detalhe/contrato-publico/447-1005484245"
  },
  {
    "numero_procedimento": "N/A",
    "entidade": "Pombal Prof - Sociedade de Educação e Ensino Profissional, SA",
    "link": "https://diariodarepublica.pt/dr/detalhe/contrato-publico/449-1005484246",
    "detalhes_completos": "1 - IDENTIFICAÇÃO E CONTACTOS DA ENTIDADE ADJUDICANTE\nDesignação da entidade adjudicante: Pombal Prof - Sociedade de Educação e Ensino Profissional, SA\nNIPC: 504609696\nServiço/Órgão/Pessoa de contacto: Conselho de Administração\nEndereço: Avenida Vasco da Gama, Parque Industrial Manuel da Mota\nCódigo postal: 3100-354\nLocalidade: Pombal\nPaís: Portugal\nNUT III: PT16F\nDistrito: Leiria\nConcelho: Pombal\nFreguesia: Freguesia de Pombal - Pombal\nTelefone: 236200810\nEndereço da Entidade (URL): https://www.etap.edu.pt/\nEndereço Eletrónico: info@etap.edu.pt\neDelivery Gateway (URL): https://www.acingov.pt\nFunção da Organização: Adquirente\nNorma jurídica da Entidade Adjudicante: Organismo de direito público\nÁrea de atividade da Autoridade Adjudicante: Serviços públicos das administrações públicas\n2 - JORNAL OFICIAL DA UNIÃO EUROPEIA\nO procedimento a que este anúncio diz respeito também é publicitado no Jornal Oficial da União Europeia? Não\n3 - AVISO\nModelo de Anúncio: Concurso público\nData de Envio do Anúncio: 09-01-2026\n5 - PROCESSO\nTipo de Procedimento: Concurso público\nPreço base do procedimento: Sim\nValor do preço base do procedimento: 72.535,75 EUR\nProcedimento com lotes? Não\n6 - OBJETO DO CONTRATO\nNúmero de referência interna: 0185-2025_CP\nDesignação do contrato: AQUISIÇÃO DE COMPUTADORES PORTÁTEIS\nDescrição: AQUISIÇÃO DE COMPUTADORES PORTÁTEIS\nTipo de Contrato Principal: Aquisição de Bens Móveis\nTipo de Contrato: Aquisição de Bens Móveis\nClassificação CPV (Vocabulário Comum para os Contratos Públicos)\nObjeto principal\nVocabulário Principal: 30213100\nPreço base s/IVA: 72.535,75 EUR\n7 - INDICAÇÕES ADICIONAIS\nO contrato envolve aquisição conjunta (satisfação de várias entidades)? Não\nO contrato é adjudicado por uma central de compras? Não\n8 - TÉCNICAS\nO concurso destina-se à celebração de um acordo-quadro? Inexistência de acordo-quadro\nÉ utilizado um leilão eletrónico? Não\nÉ adotada uma fase de negociação? Não\nSistema de Aquisição Dinâmico: Inexistência de sistema de aquisição dinâmico\n9 - LOCAL DA EXECUÇÃO DO CONTRATO\nLOCAL DA EXECUÇÃO DO CONTRATO (PROCEDIMENTO)\nPaís: Portugal\nNUT III: PT16F\nLocalidade: Freguesia de Pombal - Pombal\nDistrito: Leiria\nConcelho: Pombal\nFreguesia: Freguesia de Pombal - Pombal\n10 - PRAZO DE EXECUÇÃO DO CONTRATO\nPrazo de execução do contrato: 30 DIAS\nPrevisão de renovações: Não\n11 - FUNDOS EU\nTêm fundos EU? Não\n12 - DOCUMENTOS DE HABILITAÇÃO\nHabilitação para o exercício da atividade profissional: Não\n13 - CONDIÇÕES DE APRESENTAÇÃO\nPlataforma eletrónica utilizada pela entidade adjudicante: ACIN\nURL para Apresentação: https://www.acingov.pt\nAdmissibilidade da apresentação de propostas variantes: Não autorizado\nPrazo para apresentação das propostas: 15-01-2026 17:00\nPrazo durante o qual os concorrentes são obrigados a manter as respetivas propostas: 66 dias a contar do termo do prazo para a apresentação das propostas\nIndicação de Subcontratação na Proposta: Inexistência de indicação de subcontratação\n14 - PRESTAÇÃO DE CAUÇÃO\nPrestação de caução: Não\n15 - FORNECIMENTO DAS PEÇAS DO CONCURSO, APRESENTAÇÃO DE PEDIDOS DE PARTICIPAÇÃO E APRESENTAÇÃO DAS PROPOSTAS\nLink para acesso às peças do concurso (URL): https://www.acingov.pt/acingovprod/2/zonaPublica/zona_publica_c/donwloadProcedurePiece/MTA0MDgyOA==\n20 - OUTROS REQUISITOS\nInformação sobre contratos reservados. Aplica-se a contratos reservados (54º-A)? Não\n21 - CRITÉRIO DE ADJUDICAÇÃO\nMultifator: Sim\nFator: \nNome: Preço\nPonderação: 35%\nSubfatores: Não\nFator: \nNome: Outros\nOutro Nome: MÉRITO TÉCNICO DA PROPOSTA (MTPt)\nPonderação: 50%\nSubfatores: Sim\nSubfatores: \nNome: Pontuação do fator Prazo de Entrega (Pz)\nPonderação : 40%; \nNome: Pontuação do fator Características Técnicas(CT)\nPonderação : 60%; \nFator: \nNome: Outros\nOutro Nome: PERSONALIZAÇÃO DOS COMPUTADORES PORTÁTEIS\nPonderação: 15%\nSubfatores: Não\n24 - CONDIÇÕES DO CONTRATO\nFaturação Eletrónica: Permitido\nObrigação de Subcontratação:\nCódigo da Obrigação de Subcontratação: Não é aplicável nenhuma obrigação de subcontratação.\n25 - COMPRA PÚBLICA ESTRATÉGICA\nCompra Pública Estratégica: Redução dos impactos ambientais\nDescrição do Processo de Adjudicação Estratégico: Enquadramento estratégico: a contratação insere-se na estratégia nacional de compras públicas ecológicas (ECO360), integrando critérios de eficiência energética e conceção ecológica nos equipamentos. Reduz significativamente o consumo de papel, promovendo a desmaterialização pedagógica. Cada aluno recebe um computador, assumindo a sua manutenção e responsabilidade. O concurso exige conformidade com DNSH (Do No Significant Harm) e o respectivo equipamento deve respeitar os requisitos técnicos e ambientais do DL n.º 12/2011, garantindo a redução dos impactos ambientais desde a produção até ao ciclo de vida.\nCritérios de contratos Públicos Ecológicos: Critérios de contratação pública ecológica nacional\nCategorias da estratégia nacional: Computadores, monitores, tabletes e telemóveis inteligentes\nContratos Públicos Ecológicos: A mitigação das alterações climáticas\nDiretiva Veículos Não Poluentes: Não\nCritério de Acessibilidade: Os critérios de acessibilidade para as pessoas com deficiência não estão incluídos porque o contrato não se destina a pessoas singulares\n26 - INFORMAÇÕES ADICIONAIS\nContrato adequado para PME: Não\nCobertura ACP (Acordo dos Contratos Públicos da Organização Mundial do Comércio): Não\n27 - IDENTIFICAÇÃO E CONTACTOS DO ÓRGÃO DE RECURSOS ADMINISTRATIVOS\nDesignação: Conselho de Administração\nEndereço: Avenida Vasco da Gama, Parque Industrial Manuel da Mota\nCódigo postal: 3100-354\nLocalidade: Pombal\nTelefone: 236200810\nFax: \nEndereço eletrónico: Info@etap.edu.pt\nPrazo de interposição do recurso: 10 dias\n28 - IDENTIFICAÇÃO DO(S) AUTOR(ES) DE ANÚNCIO\nNome: Nuno Miguel Branco Ferreira\nCargo: Diretor de Formação e Projetos\n419947587",
    "nipc": "504609696",
    "distrito": "Leiria",
    "concelho": "Pombal",
    "freguesia": "Freguesia de Pombal - Pombal",
    "site": "https://www.etap.edu.pt/",
    "email": "info@etap.edu.pt",
    "designacao_contrato": "AQUISIÇÃO DE COMPUTADORES PORTÁTEIS",
    "descricao": "AQUISIÇÃO DE COMPUTADORES PORTÁTEIS",
    "preco_base": "72.535,75 EUR",
    "prazo_execucao": "30 DIAS",
    "prazo_apresentacao_propostas": "15-01-2026 17:00",
    "fundos_eu": "Não",
    "plataforma_eletronica": "ACIN",
    "url_procedimento": "https://www.acingov.pt",
    "autor_nome": "Nuno Miguel Branco Ferreira",
    "autor_cargo": "Diretor de Formação e Projetos"
  },
  {
    "numero_procedimento": "N/A",
    "entidade": "Centro Formação Profissional Indústria de Cortiça",
    "link": "https://diariodarepublica.pt/dr/detalhe/contrato-publico/450-1005484247",
    "detalhes_completos": "1 - IDENTIFICAÇÃO E CONTACTOS DA ENTIDADE ADJUDICANTE\nDesignação da entidade adjudicante: Centro Formação Profissional Indústria de Cortiça\nNIPC: 900220538\nEndereço: Rua Alto do Picão n.º 415\nCódigo postal: 4535-393\nLocalidade: Santa Maria de Lamas\nPaís: Portugal\nNUT III: PT11A\nDistrito: Aveiro\nConcelho: Santa Maria da Feira\nFreguesia: Freguesia de Santa Maria de Lamas\nTelefone: 227471200\nFax: 227471209\nEndereço da Entidade (URL): http://www.cincork.com\nEndereço Eletrónico: geral@cincork.com\nFunção da Organização: Adquirente\nNorma jurídica da Entidade Adjudicante: Organismo de direito público\nÁrea de atividade da Autoridade Adjudicante: Educação\n2 - JORNAL OFICIAL DA UNIÃO EUROPEIA\nO procedimento a que este anúncio diz respeito também é publicitado no Jornal Oficial da União Europeia? Não\n3 - AVISO\nModelo de Anúncio: Concurso público\nData de Envio do Anúncio: 09-01-2026\n5 - PROCESSO\nTipo de Procedimento: Concurso público\nPreço base do procedimento: Sim\nValor do preço base do procedimento: 215.885,00 EUR\nProcedimento com lotes? Sim\nNº Máx. de Lotes Autorizado: 3\nNúmero máximo de lotes que podem ser adjudicados a um concorrente: 3\n6 - OBJETO DO CONTRATO\nNúmero de referência interna: CPBL2602\nDesignação do contrato: CPBL2602 - SISTEMA DE PRODUÇÃO DE BLOCOS E ROLHAS AGLOMERADAS DE CORTIÇA\nDescrição: CPBL2602 - SISTEMA DE PRODUÇÃO DE BLOCOS E ROLHA AGLOMERADAS DE CORTIÇA\nTipo de Contrato Principal: Aquisição de Bens Móveis\nTipo de Contrato: Aquisição de Bens Móveis\nClassificação CPV (Vocabulário Comum para os Contratos Públicos)\nObjeto principal\nVocabulário Principal: 42642300\nPreço base s/IVA: 215.885,00 EUR\nLotes: \nNº: LOT-0001\nDescrição do Lote: Lote 1 - Conjunto de aglomeração para rolhas e peças de cortiça e materiais aglomerados incluindo respetivos equipamentos de suporte\nPreço base s/IVA: 182.985,00 EUR\nClassificação CPV (Vocabulário Comum para os Contratos Públicos)\nObjeto principal\nVocabulário Principal: 42642300\nNº: LOT-0002\nDescrição do Lote: Lote 2 - Máquina Serra de Fita\nPreço base s/IVA: 10.900,00 EUR\nClassificação CPV (Vocabulário Comum para os Contratos Públicos)\nObjeto principal\nVocabulário Principal: 42642300\nNº: LOT-0003\nDescrição do Lote: Lote 3 - Máquina Laminadora de Cortiça\nPreço base s/IVA: 22.000,00 EUR\nClassificação CPV (Vocabulário Comum para os Contratos Públicos)\nObjeto principal\nVocabulário Principal: 42642300\n7 - INDICAÇÕES ADICIONAIS\nO contrato envolve aquisição conjunta (satisfação de várias entidades)? Não\nO contrato é adjudicado por uma central de compras? Não\n8 - TÉCNICAS\nO concurso destina-se à celebração de um acordo-quadro? Inexistência de acordo-quadro\nÉ utilizado um leilão eletrónico? Não\nÉ adotada uma fase de negociação? Não\nSistema de Aquisição Dinâmico: Inexistência de sistema de aquisição dinâmico\n9 - LOCAL DA EXECUÇÃO DO CONTRATO\nLOCAL DA EXECUÇÃO DO CONTRATO (PROCEDIMENTO)\nLOCAL DA EXECUÇÃO DO CONTRATO (LOTE)\nIdentificador do Lote: LOT-0001\nPaís: Portugal\nNUT III: PT11A\nLocalidade: Santa Maria de Lamas\nDistrito: Aveiro\nConcelho: Santa Maria da Feira\nFreguesia: Freguesia de Santa Maria de Lamas\nIdentificador do Lote: LOT-0002\nPaís: Portugal\nNUT III: PT11A\nLocalidade: Santa Maria de Lamas\nDistrito: Aveiro\nConcelho: Santa Maria da Feira\nFreguesia: Freguesia de Santa Maria de Lamas\nIdentificador do Lote: LOT-0003\nPaís: Portugal\nNUT III: PT11A\nLocalidade: Santa Maria de Lamas\nDistrito: Aveiro\nConcelho: Santa Maria da Feira\nFreguesia: Freguesia de Santa Maria de Lamas\n10 - PRAZO DE EXECUÇÃO DO CONTRATO\nIdentificador do Lote: LOT-0001\nPrazo de execução do contrato: 50 DIAS\nPrevisão de renovações: Não\nIdentificador do Lote: LOT-0002\nPrazo de execução do contrato: 50 DIAS\nPrevisão de renovações: Não\nIdentificador do Lote: LOT-0003\nPrazo de execução do contrato: 50 DIAS\nPrevisão de renovações: Não\n11 - FUNDOS EU\nIdentificador do Lote: LOT-0001; LOT-0002; LOT-0003\nTêm fundos EU? Não\n12 - DOCUMENTOS DE HABILITAÇÃO\nHabilitação para o exercício da atividade profissional: Não\n13 - CONDIÇÕES DE APRESENTAÇÃO\nPlataforma eletrónica utilizada pela entidade adjudicante: COMPRASPT\nURL para Apresentação: https://www.compraspt.com/cpt-cincork/faces/\nAdmissibilidade da apresentação de propostas variantes: Não autorizado\nPrazo para apresentação das propostas: 20-01-2026 23:30\nPrazo durante o qual os concorrentes são obrigados a manter as respetivas propostas: 66 dias a contar do termo do prazo para a apresentação das propostas\nApresentação de Catálogo Eletrónico: Permitido\nIndicação de Subcontratação na Proposta: Inexistência de indicação de subcontratação\n14 - PRESTAÇÃO DE CAUÇÃO\nPrestação de caução: Não\n15 - FORNECIMENTO DAS PEÇAS DO CONCURSO, APRESENTAÇÃO DE PEDIDOS DE PARTICIPAÇÃO E APRESENTAÇÃO DAS PROPOSTAS\nLink para acesso às peças do concurso (URL): https://www.compraspt.com/cpt-cincork/faces/app/acessoDocs.jsp?codigoAcesso=p1rnMF7gUMFz3FzSscukLvs6QANMA0S643GMZRFid3aR8Zpegr\n20 - OUTROS REQUISITOS\nIdentificador do Lote: LOT-0001; LOT-0002; LOT-0003\nInformação sobre contratos reservados. Aplica-se a contratos reservados (54º-A)? Não\n21 - CRITÉRIO DE ADJUDICAÇÃO\nO Critério de adjudicação é diferenciado por lote? Não\nMultifator: Sim\nFator: \nNome: Outros\nOutro Nome: Prazo de entrega e instalação dos equipamentos\nPonderação: 20%\nSubfatores: Não\nFator: \nNome: Preço\nPonderação: 80%\nSubfatores: Não\n24 - CONDIÇÕES DO CONTRATO\nIdentificador do Lote: LOT-0001; LOT-0002; LOT-0003\nFaturação Eletrónica: Permitido\nObrigação de Subcontratação:\nCódigo da Obrigação de Subcontratação: Não é aplicável nenhuma obrigação de subcontratação.\n25 - COMPRA PÚBLICA ESTRATÉGICA\nCompra Pública Estratégica: Inexistência de contratação pública estratégica\n26 - INFORMAÇÕES ADICIONAIS\nIdentificador do Lote: LOT-0001\nContrato adequado para PME: Sim\nCobertura ACP (Acordo dos Contratos Públicos da Organização Mundial do Comércio): Não\nIdentificador do Lote: LOT-0002\nContrato adequado para PME: Sim\nCobertura ACP (Acordo dos Contratos Públicos da Organização Mundial do Comércio): Não\nIdentificador do Lote: LOT-0003\nContrato adequado para PME: Sim\nCobertura ACP (Acordo dos Contratos Públicos da Organização Mundial do Comércio): Não\n27 - IDENTIFICAÇÃO E CONTACTOS DO ÓRGÃO DE RECURSOS ADMINISTRATIVOS\nDesignação: Conselho de Administração\nEndereço: Rua Alto do Picão n.º 415\nCódigo postal: 4535-393\nLocalidade: Santa Maria de Lamas\nTelefone: 227471200\nFax: \nEndereço eletrónico: ca@cincork.com\nPrazo de interposição do recurso: 5 dias\n28 - IDENTIFICAÇÃO DO(S) AUTOR(ES) DE ANÚNCIO\nNome: Cristina Rodrigues\nCargo: Presidente do Conselho de Administração\n419947579",
    "nipc": "900220538",
    "distrito": "Aveiro",
    "concelho": "Santa Maria da Feira",
    "freguesia": "Freguesia de Santa Maria de Lamas",
    "site": "http://www.cincork.com",
    "email": "geral@cincork.com",
    "designacao_contrato": "CPBL2602 - SISTEMA DE PRODUÇÃO DE BLOCOS E ROLHAS AGLOMERADAS DE CORTIÇA",
    "descricao": "CPBL2602 - SISTEMA DE PRODUÇÃO DE BLOCOS E ROLHA AGLOMERADAS DE CORTIÇA",
    "preco_base": "215.885,00 EUR",
    "prazo_execucao": "50 DIAS",
    "prazo_apresentacao_propostas": "20-01-2026 23:30",
    "fundos_eu": "Não",
    "plataforma_eletronica": "COMPRASPT",
    "url_procedimento": "https://www.compraspt.com/cpt-cincork/faces/",
    "autor_nome": "Cristina Rodrigues",
    "autor_cargo": "Presidente do Conselho de Administração"
  },
  {
    "numero_procedimento": "N/A",
    "entidade": "AnÃºncio de procedimento  n.Âº 451/2026  -  DiÃ¡rio da RepÃºblica n.Âº 6/2026, SÃ©rie II de 2026-01-09",
    "link": "https://diariodarepublica.pt/dr/detalhe/contrato-publico/451-1005484249"
  },
  {
    "numero_procedimento": "N/A",
    "entidade": "Santa Casa da Misericórdia de Lisboa",
    "link": "https://diariodarepublica.pt/dr/detalhe/contrato-publico/453-1005484250",
    "detalhes_completos": "1 - IDENTIFICAÇÃO E CONTACTOS DA ENTIDADE ADJUDICANTE\nDesignação da entidade adjudicante: Santa Casa da Misericórdia de Lisboa\nNIPC: 500745471\nServiço/Órgão/Pessoa de contacto: Exma. Mesa\nEndereço: Largo Trindade Coelho\nCódigo postal: 1200-470\nLocalidade: Lisboa\nPaís: Portugal\nNUT III: PT170\nDistrito: Lisboa\nConcelho: Todos\nFreguesia: Todas\nTelefone: 213235000\nFax: 213235013\nEndereço da Entidade (URL): http://www.scml.pt/\nEndereço Eletrónico: compras@scml.pt\neDelivery Gateway (URL): https://www.acingov.pt\nFunção da Organização: Adquirente\nSubfunção da Organização: Organização cujo orçamento é utilizado para pagar o contrato; Organização que executa o pagamento; Organização que fornece informações adicionais sobre o processo de adjudicação; Organização que fornece mais informações sobre os prazos dos procedimentos de recurso; Organização que fornece acesso fora de linha aos documentos do concurso; Organização responsável pelo tratamento das propostas; Organização que recebe as propostas; Organização que trata os pedidos de participação; Organização que recebe pedidos de participação; Organização que fornece mais informações sobre os procedimentos de recurso; Organização que assina o contrato\nNorma jurídica da Entidade Adjudicante: Organismo de direito público, controlado por uma autoridade da administração central\nÁrea de atividade da Autoridade Adjudicante: Proteção social\n2 - JORNAL OFICIAL DA UNIÃO EUROPEIA\nO procedimento a que este anúncio diz respeito também é publicitado no Jornal Oficial da União Europeia? Não\n3 - AVISO\nModelo de Anúncio: Concurso público\nData de Envio do Anúncio: 09-01-2026\n5 - PROCESSO\nTipo de Procedimento: Concurso público\nPreço base do procedimento: Sim\nValor do preço base do procedimento: 28.000,00 EUR\nProcedimento com lotes? Não\n6 - OBJETO DO CONTRATO\nNúmero de referência interna: 25DC39CP027\nDesignação do contrato: Empreitada de Revestimento das paredes de contenção das rampas de acesso ao estacionamento do Edifício sito na Praça José Fontana, 36-39 a Rua Sousa Martins, 24-28 e Rua Sousa Martins, 22\nDescrição: Empreitada de Revestimento das paredes de contenção das rampas de acesso ao estacionamento do Edifício sito na Praça José Fontana, 36-39 a Rua Sousa Martins, 24-28 e Rua Sousa Martins, 22 \nTipo de Contrato Principal: Empreitada de Obras Públicas\nTipo de Contrato: Empreitada de Obras Públicas\nClassificação CPV (Vocabulário Comum para os Contratos Públicos)\nObjeto principal\nVocabulário Principal: 45260000\nPreço base s/IVA: 28.000,00 EUR\n7 - INDICAÇÕES ADICIONAIS\nO contrato envolve aquisição conjunta (satisfação de várias entidades)? Não\nO contrato é adjudicado por uma central de compras? Não\n8 - TÉCNICAS\nO concurso destina-se à celebração de um acordo-quadro? Inexistência de acordo-quadro\nÉ utilizado um leilão eletrónico? Não\nÉ adotada uma fase de negociação? Não\nSistema de Aquisição Dinâmico: Inexistência de sistema de aquisição dinâmico\n9 - LOCAL DA EXECUÇÃO DO CONTRATO\nLOCAL DA EXECUÇÃO DO CONTRATO (PROCEDIMENTO)\nPaís: Portugal\nNUT III: PT170\nLocalidade: Freguesia de Misericórdia\nDistrito: Lisboa\nConcelho: Lisboa\nFreguesia: Freguesia de Misericórdia\n10 - PRAZO DE EXECUÇÃO DO CONTRATO\nPrazo de execução do contrato: 1 MESES\nPrevisão de renovações: Não\n11 - FUNDOS EU\nTêm fundos EU? Não\n12 - DOCUMENTOS DE HABILITAÇÃO\nHabilitação para o exercício da atividade profissional: Sim\nTipo: Alvará\nDescrição: Da 1ª Categoria (Edificios e Património), na classe correspondente à parte dos trabalhos a que respeitem:\nDa 5ª subcategoria \nDa 7ª subcategoria \n13 - CONDIÇÕES DE APRESENTAÇÃO\nPlataforma eletrónica utilizada pela entidade adjudicante: ACIN\nURL para Apresentação: https://www.acingov.pt\nAdmissibilidade da apresentação de propostas variantes: Não autorizado\nPrazo para apresentação das propostas: 30-01-2026 17:00\nPrazo durante o qual os concorrentes são obrigados a manter as respetivas propostas: 120 dias a contar do termo do prazo para a apresentação das propostas\nIndicação de Subcontratação na Proposta: Inexistência de indicação de subcontratação\n14 - PRESTAÇÃO DE CAUÇÃO\nPrestação de caução: Não\n15 - FORNECIMENTO DAS PEÇAS DO CONCURSO, APRESENTAÇÃO DE PEDIDOS DE PARTICIPAÇÃO E APRESENTAÇÃO DAS PROPOSTAS\nLink para acesso às peças do concurso (URL): https://www.acingov.pt/acingovprod/2/zonaPublica/zona_publica_c/donwloadProcedurePiece/MTAxMjA5OA==\n20 - OUTROS REQUISITOS\nInformação sobre contratos reservados. Aplica-se a contratos reservados (54º-A)? Não\n21 - CRITÉRIO DE ADJUDICAÇÃO\nMultifator: Não\nMonofator:\nNome: Outros\nOutro nome: Fator Preço\n24 - CONDIÇÕES DO CONTRATO\nFaturação Eletrónica: Necessário\nObrigação de Subcontratação:\nCódigo da Obrigação de Subcontratação: Não é aplicável nenhuma obrigação de subcontratação.\n25 - COMPRA PÚBLICA ESTRATÉGICA\nCompra Pública Estratégica: Inexistência de contratação pública estratégica\n26 - INFORMAÇÕES ADICIONAIS\nContrato adequado para PME: Sim\nCobertura ACP (Acordo dos Contratos Públicos da Organização Mundial do Comércio): Não\n27 - IDENTIFICAÇÃO E CONTACTOS DO ÓRGÃO DE RECURSOS ADMINISTRATIVOS\nDesignação: Direção de Compras\nEndereço: Largo Trindade Coelho\nCódigo postal: 1200-470\nLocalidade: Lisboa\nTelefone: 213235000\nFax: \nEndereço eletrónico: dicom.neei@scml.pt\nPrazo de interposição do recurso: 10 dias\n28 - IDENTIFICAÇÃO DO(S) AUTOR(ES) DE ANÚNCIO\nNome: Vanda Simão\nCargo: Diretora da Direção de Compras\n419947567",
    "nipc": "500745471",
    "distrito": "Lisboa",
    "concelho": "Todos",
    "freguesia": "Todas",
    "site": "http://www.scml.pt/",
    "email": "compras@scml.pt",
    "designacao_contrato": "Empreitada de Revestimento das paredes de contenção das rampas de acesso ao estacionamento do Edifício sito na Praça José Fontana, 36-39 a Rua Sousa Martins, 24-28 e Rua Sousa Martins, 22",
    "descricao": "Empreitada de Revestimento das paredes de contenção das rampas de acesso ao estacionamento do Edifício sito na Praça José Fontana, 36-39 a Rua Sousa Martins, 24-28 e Rua Sousa Martins, 22",
    "preco_base": "28.000,00 EUR",
    "prazo_execucao": "1 MESES",
    "prazo_apresentacao_propostas": "30-01-2026 17:00",
    "fundos_eu": "Não",
    "plataforma_eletronica": "ACIN",
    "url_procedimento": "https://www.acingov.pt",
    "autor_nome": "Vanda Simão",
    "autor_cargo": "Diretora da Direção de Compras"
  },
  {
    "numero_procedimento": "N/A",
    "entidade": "Santa Casa da Misericórdia de Lisboa",
    "link": "https://diariodarepublica.pt/dr/detalhe/contrato-publico/454-1005484251",
    "detalhes_completos": "1 - IDENTIFICAÇÃO E CONTACTOS DA ENTIDADE ADJUDICANTE\nDesignação da entidade adjudicante: Santa Casa da Misericórdia de Lisboa\nNIPC: 500745471\nServiço/Órgão/Pessoa de contacto: Exma. Mesa\nEndereço: Largo Trindade Coelho\nCódigo postal: 1200-470\nLocalidade: Lisboa\nPaís: Portugal\nNUT III: PT170\nDistrito: Lisboa\nConcelho: Todos\nFreguesia: Todas\nTelefone: 213235000\nFax: 213235013\nEndereço da Entidade (URL): http://www.scml.pt/\nEndereço Eletrónico: compras@scml.pt\neDelivery Gateway (URL): https://www.acingov.pt\nFunção da Organização: Adquirente\nSubfunção da Organização: Organização cujo orçamento é utilizado para pagar o contrato; Organização que executa o pagamento; Organização que fornece informações adicionais sobre o processo de adjudicação; Organização que fornece mais informações sobre os prazos dos procedimentos de recurso; Organização que fornece acesso fora de linha aos documentos do concurso; Organização responsável pelo tratamento das propostas; Organização que recebe as propostas; Organização que trata os pedidos de participação; Organização que recebe pedidos de participação; Organização que fornece mais informações sobre os procedimentos de recurso; Organização que assina o contrato\nNorma jurídica da Entidade Adjudicante: Organismo de direito público, controlado por uma autoridade da administração central\nÁrea de atividade da Autoridade Adjudicante: Proteção social\n2 - JORNAL OFICIAL DA UNIÃO EUROPEIA\nO procedimento a que este anúncio diz respeito também é publicitado no Jornal Oficial da União Europeia? Não\n3 - AVISO\nModelo de Anúncio: Concurso público\nData de Envio do Anúncio: 09-01-2026\n5 - PROCESSO\nTipo de Procedimento: Concurso público\nPreço base do procedimento: Sim\nValor do preço base do procedimento: 15.525,00 EUR\nProcedimento com lotes? Não\n6 - OBJETO DO CONTRATO\nNúmero de referência interna: 25DC39CP035\nDesignação do contrato: Prestação de serviços de manutenção da estufa de pintura automóvel da Aldeia de Santa Isabel\nDescrição: Prestação de serviços de manutenção da estufa de pintura automóvel da Aldeia de Santa Isabel \nTipo de Contrato Principal: Aquisição de Serviços\nTipo de Contrato: Aquisição de Serviços\nClassificação CPV (Vocabulário Comum para os Contratos Públicos)\nObjeto principal\nVocabulário Principal: 50110000\nPreço base s/IVA: 15.525,00 EUR\n7 - INDICAÇÕES ADICIONAIS\nO contrato envolve aquisição conjunta (satisfação de várias entidades)? Não\nO contrato é adjudicado por uma central de compras? Não\n8 - TÉCNICAS\nO concurso destina-se à celebração de um acordo-quadro? Inexistência de acordo-quadro\nÉ utilizado um leilão eletrónico? Não\nÉ adotada uma fase de negociação? Não\nSistema de Aquisição Dinâmico: Inexistência de sistema de aquisição dinâmico\n9 - LOCAL DA EXECUÇÃO DO CONTRATO\nLOCAL DA EXECUÇÃO DO CONTRATO (PROCEDIMENTO)\nPaís: Portugal\nNUT III: PT170\nLocalidade: Freguesia de Misericórdia\nDistrito: Lisboa\nConcelho: Lisboa\nFreguesia: Freguesia de Misericórdia\n10 - PRAZO DE EXECUÇÃO DO CONTRATO\nPrazo de execução do contrato: 36 MESES\nPrevisão de renovações: Não\n11 - FUNDOS EU\nTêm fundos EU? Não\n12 - DOCUMENTOS DE HABILITAÇÃO\nHabilitação para o exercício da atividade profissional: Não\n13 - CONDIÇÕES DE APRESENTAÇÃO\nPlataforma eletrónica utilizada pela entidade adjudicante: ACIN\nURL para Apresentação: https://www.acingov.pt\nAdmissibilidade da apresentação de propostas variantes: Não autorizado\nPrazo para apresentação das propostas: 30-01-2026 17:00\nPrazo durante o qual os concorrentes são obrigados a manter as respetivas propostas: 120 dias a contar do termo do prazo para a apresentação das propostas\nIndicação de Subcontratação na Proposta: Inexistência de indicação de subcontratação\n14 - PRESTAÇÃO DE CAUÇÃO\nPrestação de caução: Não\n15 - FORNECIMENTO DAS PEÇAS DO CONCURSO, APRESENTAÇÃO DE PEDIDOS DE PARTICIPAÇÃO E APRESENTAÇÃO DAS PROPOSTAS\nLink para acesso às peças do concurso (URL): https://www.acingov.pt/acingovprod/2/zonaPublica/zona_publica_c/donwloadProcedurePiece/MTAxMDg5NQ==\n20 - OUTROS REQUISITOS\nInformação sobre contratos reservados. Aplica-se a contratos reservados (54º-A)? Não\n21 - CRITÉRIO DE ADJUDICAÇÃO\nMultifator: Sim\nFator: \nNome: Outros\nOutro Nome: Multifator\nPonderação: 100%\nSubfatores: Não\n24 - CONDIÇÕES DO CONTRATO\nFaturação Eletrónica: Necessário\nObrigação de Subcontratação:\nCódigo da Obrigação de Subcontratação: Não é aplicável nenhuma obrigação de subcontratação.\n25 - COMPRA PÚBLICA ESTRATÉGICA\nCompra Pública Estratégica: Inexistência de contratação pública estratégica\n26 - INFORMAÇÕES ADICIONAIS\nContrato adequado para PME: Sim\nCobertura ACP (Acordo dos Contratos Públicos da Organização Mundial do Comércio): Não\n27 - IDENTIFICAÇÃO E CONTACTOS DO ÓRGÃO DE RECURSOS ADMINISTRATIVOS\nDesignação: Direção de Compras\nEndereço: Largo Trindade Coelho\nCódigo postal: 1200-470\nLocalidade: Lisboa\nTelefone: 213235000\nFax: \nEndereço eletrónico: dicom.neei@scml.pt\nPrazo de interposição do recurso: 10 dias\n28 - IDENTIFICAÇÃO DO(S) AUTOR(ES) DE ANÚNCIO\nNome: Vanda Simão\nCargo: Diretora da Direção de Compras\n419947566",
    "nipc": "500745471",
    "distrito": "Lisboa",
    "concelho": "Todos",
    "freguesia": "Todas",
    "site": "http://www.scml.pt/",
    "email": "compras@scml.pt",
    "designacao_contrato": "Prestação de serviços de manutenção da estufa de pintura automóvel da Aldeia de Santa Isabel",
    "descricao": "Prestação de serviços de manutenção da estufa de pintura automóvel da Aldeia de Santa Isabel",
    "preco_base": "15.525,00 EUR",
    "prazo_execucao": "36 MESES",
    "prazo_apresentacao_propostas": "30-01-2026 17:00",
    "fundos_eu": "Não",
    "plataforma_eletronica": "ACIN",
    "url_procedimento": "https://www.acingov.pt",
    "autor_nome": "Vanda Simão",
    "autor_cargo": "Diretora da Direção de Compras"
  },
  {
    "numero_procedimento": "N/A",
    "entidade": "AnÃºncio de procedimento  n.Âº 457/2026  -  DiÃ¡rio da RepÃºblica n.Âº 6/2026, SÃ©rie II de 2026-01-09",
    "link": "https://diariodarepublica.pt/dr/detalhe/contrato-publico/457-1005484252"
  },
  {
    "numero_procedimento": "N/A",
    "entidade": "AnÃºncio de procedimento  n.Âº 458/2026  -  DiÃ¡rio da RepÃºblica n.Âº 6/2026, SÃ©rie II de 2026-01-09",
    "link": "https://diariodarepublica.pt/dr/detalhe/contrato-publico/458-1005484253"
  }
]